Workbook

Sheet EVENTOS
B3: martes, 22 de Abril del 2025
B5: INFORMACIÓN DE EVENTOS PRINCIPALES EN SUS INSTALACIONES
B6: TIPO DE EVENTO | C6: EMPRESA | D6: UBICACIÓN | E6: TIPO DE EQUIPO | F6: EQUIPO | G6: INICIO | H6: FINAL | I6: DESCRIPCIÓN | J6: MW INDISP. | K6: INTERRUPCIÓN (SI/NO) | L6: TENSIÓN DE FALLA (kV)
B7: FALLA | C7: CONELSUR LT SAC | D7: MOYOPAMPA - SALAMANCA | E7: LINEA DE TRANSMISION | F7: L-6060 | G7: 22/04/2025 07:57:00 | H7: 22/04/2025 13:16:00 | I7: DESCONEXIÓN DE LA LÍNEA L-6060 (MOYOPAMPA - SALAMANCA) DE 60 kV POR FALLA | K7: NO | L7: 60
B8: EVENTO | C8: CONELSUR LT SAC | D8: PORTILLO | E8: SUBESTACION | F8: SS.EE. | G8: 22/04/2025 00:00:00 | H8: 23/04/2025 00:00:00 | I8: DECLARACIÓN DE SITUACIÓN EXCEPCIONAL EN LA S.E. PORTILLO DE 60 kV | K8: NO
B9: FALLA | C9: EGEJUNIN | D9: SANTA CRUZ II | E9: GENERADOR HIDROELÉCTRICO | F9: G1 | G9: 22/04/2025 13:39:00 | H9: 22/04/2025 13:39:00 | I9: DESCONEXIÓN DEL GENERADOR G1 DE LA CH SANTA CRUZ II POR FALLA | K9: NO | L9: 2.3
B10: FALLA | C10: ELECTRO ORIENTE | D10: BELAUNDE TERRY - TARAPOTO | E10: LINEA DE TRANSMISION | F10: L-1018 | G10: 22/04/2025 12:21:00 | H10: 22/04/2025 12:38:00 | I10: DESCONEXIÓN DE LA LÍNEA L-1018 (BELAUNDE TERRY - TARAPOTO) DE 138 kV POR FALLA | K10: SI | L10: 138
B11: P.ENERG | C11: HYDRO GLOBAL PERÚ S.A.C. | D11: SAN GABAN III | E11: GENERADOR HIDROELÉCTRICO | F11: G2 | G11: 22/04/2025 17:40:00 | H11: 22/04/2025 17:40:00 | I11: PRIMERA SINCRONIZACIÓN DEL GENERADOR G2 DE LA C.H. SAN GABAN III POR PRUEBAS | K11: NO
B12: FALLA | C12: ISA PERU | D12: AGUAYTÍA - TINGO MARÍA | E12: LINEA DE TRANSMISION | F12: L-2251 | G12: 22/04/2025 03:23:00 | H12: 22/04/2025 03:23:00 | I12: RECIERRE MONOFASICO EXITOSO DE LA LÍNEA L-2251 (TINGO MARIA - AGUAYTIA) DE 220 kV POR FALLA | K12: NO | L12: 220
B13: FALLA | C13: ORYGEN PERU S.A.A. | D13: HUINCO | E13: GENERADOR HIDROELÉCTRICO | F13: G2 | G13: 22/04/2025 12:21:00 | H13: 22/04/2025 16:35:00 | I13: DESCONEXIÓN DE LA UNIDAD G2 DE LA C.H. HUINCO POR FALLA | K13: NO | L13: 12.5
B14: EVENTO | C14: RED DE ENERGIA DEL PERU S.A. | D14: TINGO MARÍA - AUCAYACU | E14: LINEA DE TRANSMISION | F14: L-1122 | G14: 22/04/2025 09:20:00 | H14: 22/04/2025 12:22:00 | I14: DECLARACIÓN DE SITUACIÓN EXCEPCIONAL EN LA LÍNEA L-1122 (TINGO MARÍA - AUCAYACU) DE 138 kV | K14: NO
B15: EVENTO | C15: RED DE ENERGIA DEL PERU S.A. | D15: TINGO MARÍA - AUCAYACU | E15: LINEA DE TRANSMISION | F15: L-1122 | G15: 22/04/2025 14:06:00 | H15: 22/04/2025 17:11:00 | I15: DECLARACIÓN DE SITUACIÓN EXCEPCIONAL EN LA LÍNEA L-1122 (TINGO MARÍA - AUCAYACU) DE 138 kV | K15: NO
B16: EVENTO | C16: RED DE ENERGIA DEL PERU S.A. | D16: TINGO MARÍA - AUCAYACU | E16: LINEA DE TRANSMISION | F16: L-1122 | G16: 22/04/2025 18:10:00 | H16: 22/04/2025 21:30:00 | I16: DECLARACIÓN DE SITUACIÓN EXCEPCIONAL EN LA LÍNEA L-1122 (TINGO MARÍA - AUCAYACU) DE 138 kV | K16: NO

Sheet RESTRIC_OPE
B3: martes, 22 de Abril del 2025
B5: RESTRICCIONES OPERATIVAS
B6: FECHA | C6: HORA INICIO | D6: HORA FINAL | E6: EMPRESA | F6: UBICACIÓN | G6: T.Eq. | H6: EQUIPO | I6: DESCRIPCIÓN
B7: 22/04/2025 | C7: 00:00 | D7: 24:00 | E7: CELEPSA | F7: C.H. EL PLATANAL | G7: CH | H7: CENTRAL | I7: Debido al incremento del caudal del rio cañete y establecimiento de la temporada de avenida, se declara la C.H. El Platanal como CENTRAL HIDRÁULICA DE PASADA (correo 03/01/2025).
B8: 22/04/2025 | C8: 00:00 | D8: 24:00 | E8: EGASA | F8: C.H. CHARCANI II | G8: GH | H8: G2 | I8: El Grupo N°02 esta operando con una potencia no mayor a 0.07MW en referencia a 0.18MW de su potencia efectiva, con el fin de no generar daños mayores hasta la reparación de su cojinete.
B9: 22/04/2025 | C9: 00:00 | D9: 24:00 | E9: EGASA | F9: S.E. CONVERTIDOR | G9: BARRA | H9: BARRA138KV | I9: EGASA limitó la capacidad del transformador 138 kV/33 kV a 50 MVA por deterioro del aislamiento.
B10: 22/04/2025 | C10: 00:00 | D10: 24:00 | E10: ENEL GENERACION PIURA S.A. | F10: C.T. MALACAS | G10: CT | H10: CENTRAL | I10: De acuerdo con la comunicación vía correo del día 24.10.2024. ENEL GENERACIÓN PIURA informa una restricción de potencia para alcanzar 105 MW en simultaneo (TG6+TGN4).
B11: 22/04/2025 | C11: 00:00 | D11: 24:00 | E11: ENEL GENERACION PIURA S.A. | F11: C.T. MALACAS | G11: CT | H11: CENTRAL | I11: La unidad TGN4 de la CT Malacas está limitada a 35 MW y no puede operar en conjunto con la TG6. Esto debido a que el ducto estará en mantenimiento, así como su compresor de GAS hasta el 05/05/2025.
B12: 22/04/2025 | C12: 00:00 | D12: 24:00 | E12: ENGIE | F12: C.E. PUNTA LOMITAS | G12: CE | H12: CENTRAL | I12: De acuerdo a la carta ENG/737-2024 (Exp:202400007555). Limitación de cables de media tensión a 100 MW de los transformadores PLT1 y PLT2 de la CE Punta Lomitas. Quedan limitados a 200 MW la generación de CE Punta Lomitas y Punta Lomitas Extensión.
B13: 22/04/2025 | C13: 00:00 | D13: 24:00 | E13: ENGIE | F13: C.H. QUITARACSA | G13: CH | H13: CENTRAL | I13: De acuerdo con el correo del 23.04 se considera la operación continua de la CH Quitaracsa debido a que el sistema de refrigeración de la CH Cañón del Pato se alimenta desde la descarga del caudal turbinado por la CH Quitaracsa.
B14: 22/04/2025 | C14: 00:00 | D14: 24:00 | E14: ENGIE | F14: C.H. YUNCÁN | G14: GH | H14: G3 | I14: Según la carta N° ENG/ 198-2024 enviada por su representada, se opera de forma continua el G3 de la CH Yuncán, debido a la ejecución de mantenimientos necesarios para evitar daños en los sellos de seguridad de la válvula esférica del grupo.
B15: 22/04/2025 | C15: 00:00 | D15: 24:00 | E15: ENGIE | F15: C.T. CHILCA 1 | G15: CT | H15: CENTRAL | I15: Con carta ENG/971-2023, indica que no puede cumplir con las IO considerada en el PDO_17122023 dado que vulneran la seguridad de sus activos. Indican que se debe tomar TMO=168h.
B16: 22/04/2025 | C16: 00:00 | D16: 24:00 | E16: ENGIE | F16: C.T. CHILCA 1 | G16: CT | H16: CENTRAL | I16: Restricción de temperatura de la C.T Chilca, ver valor en el modelo de despacho.
B17: 22/04/2025 | C17: 00:00 | D17: 24:00 | E17: ENGIE | F17: C.T. CHILCA 2 | G17: CT | H17: CENTRAL | I17: Restricción de temperatura de la C.T Chilca2, ver valor en el modelo de despacho.
... B50: 22/04/2025 | C50: 00:00 | D50: 24:00 | E50: TRANSMANTARO | F50: S.E. SOCABAYA | G50: SSEE | H50: S.E. | I50: Opera en simple barra en 220 kV por indisponibilidad de la protección diferencial de barras por alarma.

Sheet INGRESO OC
A3: martes, 22 de Abril del 2025
A5: INGRESO A OPERACIÓN COMERCIAL
A6: EMPRESA | B6: TIPO DE EQUIPO | C6: UBICACIÓN | D6: EQUIPO | E6: Fecha y hora de Ingreso a Operación Comercial

Sheet MANTENIMIENTO EJECUTADOS
B3: martes, 22 de Abril del 2025
B5: Mantenimiento Ejecutado
B6: Empresa | C6: Ubicación | D6: Equipo | E6: Inicio | F6: Final | G6: Descripción | H6: MW Indisp. | I6: Prog. | J6: Dispon | K6: Interrupc. | L6: Tipo | M6: CodEq | N6: TipoEq_Osinerg
B7: AGROAURORA S.A.C. | C7: MAPLE ETANOL | D7: CENTRAL | E7: 22/04/2025 00:00 | F7: 23/04/2025 00:00 | G7: MANTENIMIENTO PREVENTIVO PROGRAMADO DE LA CENTRAL TERMOELECTRICA Y EQUIPOS AUXILIARES. | H7: 14 | I7: P | J7: F/S | K7: N | L7: PREV. | M7: 13417 | N7: G
B8: AGROAURORA S.A.C. | C8: MAPLE ETANOL | D8: CENTRAL | E8: 22/04/2025 00:00 | F8: 23/04/2025 00:00 | G8: CENTRAL TERMOELECTRICA FUERA DE SERVICIO POR FALTA DE MATERIA PRIMA PARA LOS REQUERIMIENTOS DE CALOR UTIL EN FABRICA. | H8: 14 | I8: P | J8: F/S | K8: N | L8: OTROS | M8: 13417 | N8: G
B9: AGROINDUSTRIAS SAN JACINTO S.A.A. | C9: SAN JACINTO | D9: CENTRAL | E9: 22/04/2025 00:00 | F9: 23/04/2025 00:00 | G9: Mantenimiento Anual. | H9: 8.15 | I9: P | J9: F/S | K9: N | L9: PREV. | M9: 19865 | N9: G
B10: ATLANTICA TRANSMISION SUR S.A. | C10: CHILCA-CTM | D10: INT-5261 | E10: 22/04/2025 00:00 | F10: 23/04/2025 00:00 | G10: Seccionador SBB-5261 fase S indisponible para maniobras de apertura y cierre por anomalia en tapa de tanque de compresion, el seccionador permanece cerrado y bloqueado. | H10: 0 | I10: P | J10: E/S | K10: N | L10: OTROS | M10: 13854 | N10: T
B11: ATLANTICA TRANSMISION SUR S.A. | C11: MONTALVO | D11: ACOPLE 220 | E11: 22/04/2025 00:00 | F11: 23/04/2025 00:00 | G11: Proyecto Refuerzos: Reemplazo del HMI existente, Pruebas y Configuracion. No se contara con nivel 1 de operacion. | H11: 0 | I11: P | J11: E/S | K11: N | L11: P.ENERG | M11: 14767 | N11: T
B12: ATLANTICA TRANSMISION SUR S.A. | C12: MONTALVO | D12: CL-2057 | E12: 22/04/2025 00:00 | F12: 23/04/2025 00:00 | G12: Proyecto Refuerzos: Reemplazo del HMI existente, Pruebas y Configuracion. No se contara con nivel 1 de operacion. | H12: 0 | I12: P | J12: E/S | K12: N | L12: P.ENERG | M12: 13812 | N12: T
B13: ATLANTICA TRANSMISION SUR S.A. | C13: MONTALVO | D13: CL-AUT-5671_500 | E13: 22/04/2025 00:00 | F13: 23/04/2025 00:00 | G13: Proyecto Refuerzos: Reemplazo del HMI existente, Pruebas y Configuracion. No se contara con nivel 1 de operacion en INT-5671, INT-5652 y SAT-5671. | H13: 0 | I13: P | J13: E/S | K13: N | L13: P.ENERG | M13: 13809 | N13: T
B14: ATLANTICA TRANSMISION SUR S.A. | C14: MONTALVO | D14: INT-5652 | E14: 22/04/2025 00:00 | F14: 23/04/2025 00:00 | G14: Proyecto Refuerzos:Indisponible por Implementacion de conexion de corrientes, disparos, posiciones, enclavamientos hacia los equipos del nuevos Autotransformador. AUT-5671 en servicio solo por Barra A 500kV. | H14: 0 | I14: P | J14: F/S | K14: N | L14: P.ENERG | M14: 13765 | N14: T
B15: ATLANTICA TRANSMISION SUR S.A. | C15: OCONA | D15: INT-5450 | E15: 22/04/2025 00:00 | F15: 23/04/2025 00:00 | G15: Interruptor INT-5450 cerrado con restriccion operativa, REB-5450 en servicio y suministrando los SS.AA. de la S.E. Oco?a. | H15: 0 | I15: P | J15: E/S | K15: N | L15: OTROS | M15: 13761 | N15: T
B16: ATLANTICA TRANSMISION SUR S.A. | C16: OCONA | D16: INT-5462 | E16: 22/04/2025 00:00 | F16: 23/04/2025 00:00 | G16: Seccionador SBA-5462 fase T indisponible por problemas mecanicos, el seccionador permanece cerrado y bloqueado | H16: 0 | I16: P | J16: E/S | K16: N | L16: OTROS | M16: 13758 | N16: T
B17: ATLANTICA TRANSMISION SUR S.A. | C17: OCONA | D17: SE OCOÑA | E17: 22/04/2025 08:42 | F17: 22/04/2025 15:40 | G17: MANTENIMIENTO PREVENTIVO EN SUBESTACION | H17: 0 | I17: P | J17: F/S | K17: N | L17: PREV. | M17: 13741 | N17: T
B18: ATLANTICA TRANSMISION SUR S.A. | C18: OCONA - SAN JOSE | D18: L-5036 | E18: 22/04/2025 07:57 | F18: 22/04/2025 16:03 | G18: INDISPONIBLE POR MANTENIMIENTO EN SUBESTACION OCO?A | H18: 0 | I18: P | J18: F/S | K18: N | L18: OTROS | M18: 14961 | N18: T
... B168: TRANSMANTARO | C168: YARABAMBA | D168: IN-5120 | E168: 22/04/2025 00:00 | F168: 23/04/2025 00:00 | G168: INTERRUPTOR INDISPONIBLE POR FALLA EN LOS MANDOS DE CONTROL DE N1, N2 Y N3. | H168: 0 | I168: P | J168: F/S | K168: N | L168: OTROS | M168: 17437 | N168: T

Sheet DESPACHO_EJECUTADO
B3: martes, 22 de Abril del 2025
A5: POTENCIA ACTIVA EJECUTADA DE LAS UNIDADES DE GENERACIÓN DEL SEIN (MW) | FL5: CENTRALES NO INTEGRANTES COES
A6: FECHA | B6: HORA | C6: 337 | D6: 338 | E6: 65333 | F6: 101 | G6: 102 | H6: 42667 | I6: 42668 | J6: 126 | K6: 127 | L6: 138 | M6: 139 | N6: 197 | O6: 203 | P6: 204 | Q6: 230 | R6: 209 | S6: 56677 | T6: 796 | U6: 2146 | V6: 142 | W6: 143 | X6: 125 | Y6: 187 | Z6: 163 | AA6: 298 | AB6: 299 | AC6: 219 | AD6: 151 | AE6: 152 | AF6: 153 | AG6: 154 | AH6: 756 | AI6: 156 | AJ6: 155 | AK6: 182 | AL6: 212 | AM6: 758 | AN6: 263 | AO6: 265 | AP6: 775 | AQ6: 777 | AR6: 2154 | AS6: 150 | AT6: 149 | AU6: 188 | AV6: 2131 | AW6: 755 | AX6: 252 | AY6: 249 | AZ6: 250 | BA6: 117 | BB6: 267 | BC6: 268 | BD6: 119 | BE6: 120 | BF6: 189 | BG6: 122 | BH6: 266 | BI6: 251 | BJ6: 115 | BK6: 239 | BL6: 288 | BM6: 240 | BN6: 241 | BO6: 242 | BP6: 191 | BQ6: 194 | BR6: 196 | BS6: 207 | BT6: 236 | BU6: 795 | BV6: 285 | BW6: 995 | BX6: 996 | BY6: 997 | BZ6: 766 | CA6: 926 | CB6: 924 | CC6: 121 | CD6: 103 | CE6: 104 | CF6: 106 | CG6: 105 | CH6: 107 | CI6: 110 | CJ6: 109 | CK6: 144 | CL6: 113 | CM6: 114 | CN6: 193 | CO6: 208 | CP6: 786 | CQ6: 787 | CR6: 788 | CS6: 789 | CT6: 248 | CU6: 2159 | CV6: 303 | CW6: 59715 | CX6: 62255 | CY6: 1263 | CZ6: 61800 | DA6: 2194 | DB6: 216 | DC6: 198 | DD6: 49607 | DE6: 214 | DF6: 260 | DG6: 2152 | DH6: 2128 | DI6: 247 | DJ6: 228 | DK6: 2135 | DL6: 261 | DM6: 237 | DN6: 253 | DO6: 770 | DP6: 225 | DQ6: 2201 | DR6: 2171 | DS6: 760 | DT6: 235 | DU6: 238 | DV6: 2184 | DW6: 61855 | DX6: 223 | DY6: 226 | DZ6: 201 | EA6: 258 | EB6: 259 | EC6: 920 | ED6: 257 | EE6: 256 | EF6: 2148 | EG6: 58288 | EH6: 58289 | EI6: 58839 | EJ6: 58840 | EK6: 296 | EL6: 297 | EM6: 211 | EN6: 2175 | EO6: 2178 | EP6: 2181 | EQ6: 1262 | ER6: 63425 | ES6: 233 | ET6: 2150 | EU6: 2165 | EV6: 2161 | EW6: 61197 | EX6: 58851 | EY6: 234 | EZ6: 215 | FA6: 917 | FB6: 289 | FC6: 58333 | FD6: 58336 | FE6: 202 | FF6: 58487 | FG6: 213 | FH6: 232 | FI6: 2190 | FJ6: TOTAL COES | FL6: 221 | FM6: 222 | FN6: 224 | FO6: 2187 | FP6: 227 | FQ6: 49400 | FR6: 199 | FS6: 200 | FT6: TOTAL NO COES
C7: CENTRO | D7: CENTRO | E7: SUR | F7: CENTRO | G7: CENTRO | H7: NORTE | I7: NORTE | J7: NORTE | K7: NORTE | L7: CENTRO | M7: CENTRO | N7: CENTRO | O7: CENTRO | P7: CENTRO | Q7: CENTRO | R7: CENTRO | S7: CENTRO | T7: CENTRO | U7: CENTRO | V7: CENTRO | W7: CENTRO | X7: CENTRO | Y7: CENTRO | Z7: SUR | AA7: SUR | AB7: SUR | AC7: CENTRO | AD7: SUR | AE7: SUR | AF7: SUR | AG7: SUR | AH7: SUR | AI7: SUR | AJ7: SUR | AK7: SUR | AL7: CENTRO | AM7: NORTE | AN7: NORTE | AO7: NORTE | AP7: CENTRO | AQ7: CENTRO | AR7: CENTRO | AS7: CENTRO | AT7: CENTRO | AU7: CENTRO | AV7: CENTRO | AW7: SUR | AX7: CENTRO | AY7: CENTRO | AZ7: CENTRO | BA7: CENTRO | BB7: CENTRO | BC7: CENTRO | BD7: CENTRO | BE7: CENTRO | BF7: SUR | BG7: NORTE | BH7: CENTRO | BI7: CENTRO | BJ7: NORTE | BK7: NORTE | BL7: NORTE | BM7: SUR | BN7: SUR | BO7: SUR | BP7: CENTRO | BQ7: CENTRO | BR7: CENTRO | BS7: CENTRO | BT7: CENTRO | BU7: CENTRO | BV7: CENTRO | BW7: SUR | BX7: SUR | BY7: SUR | BZ7: NORTE | CA7: SUR | CB7: CENTRO | CC7: NORTE | CD7: CENTRO | CE7: CENTRO | CF7: CENTRO | CG7: CENTRO | CH7: CENTRO | CI7: CENTRO | CJ7: CENTRO | CK7: CENTRO | CL7: CENTRO | CM7: CENTRO | CN7: CENTRO | CO7: CENTRO | CP7: SUR | CQ7: SUR | CR7: SUR | CS7: SUR | CT7: CENTRO | CU7: CENTRO | CV7: CENTRO | CW7: CENTRO | CX7: SUR | CY7: NORTE | CZ7: NORTE | DA7: NORTE | DB7: NORTE | DC7: NORTE | DD7: SUR | DE7: CENTRO | DF7: CENTRO | DG7: CENTRO | DH7: NORTE | DI7: NORTE | DJ7: CENTRO | DK7: CENTRO | DL7: SUR | DM7: SUR | DN7: CENTRO | DO7: CENTRO | DP7: CENTRO | DQ7: CENTRO | DR7: CENTRO | DS7: CENTRO | DT7: SUR | DU7: CENTRO | DV7: CENTRO | DW7: NORTE | DX7: CENTRO | DY7: CENTRO | DZ7: NORTE | EA7: CENTRO | EB7: CENTRO | EC7: CENTRO | ED7: NORTE | EE7: NORTE | EF7: SUR | EG7: CENTRO | EH7: CENTRO | EI7: CENTRO | EJ7: CENTRO | EK7: CENTRO | EL7: CENTRO | EM7: SUR | EN7: SUR | EO7: SUR | EP7: SUR | EQ7: NORTE | ER7: SUR | ES7: SUR | ET7: SUR | EU7: CENTRO | EV7: CENTRO | EW7: CENTRO | EX7: SUR | EY7: SUR | EZ7: NORTE | FA7: CENTRO | FB7: NORTE | FC7: NORTE | FD7: NORTE | FE7: CENTRO | FF7: CENTRO | FG7: CENTRO | FH7: NORTE | FI7: NORTE | FL7: NORTE | FM7: CENTRO | FN7: NORTE | FO7: NORTE | FP7: NORTE | FQ7: NORTE | FR7: NORTE | FS7: NORTE
C8: HIDROELÉCTRICA | D8: HIDROELÉCTRICA | E8: HIDROELÉCTRICA | F8: HIDROELÉCTRICA | G8: HIDROELÉCTRICA | H8: TERMOELÉCTRICA | I8: TERMOELÉCTRICA | J8: HIDROELÉCTRICA | K8: HIDROELÉCTRICA | L8: TERMOELÉCTRICA | M8: TERMOELÉCTRICA | N8: TERMOELÉCTRICA | O8: TERMOELÉCTRICA | P8: TERMOELÉCTRICA | Q8: TERMOELÉCTRICA | R8: TERMOELÉCTRICA | S8: TERMOELÉCTRICA | T8: HIDROELÉCTRICA | U8: HIDROELÉCTRICA | V8: TERMOELÉCTRICA | W8: TERMOELÉCTRICA | X8: TERMOELÉCTRICA | Y8: TERMOELÉCTRICA | Z8: HIDROELÉCTRICA | AA8: HIDROELÉCTRICA | AB8: HIDROELÉCTRICA | AC8: TERMOELÉCTRICA | AD8: HIDROELÉCTRICA | AE8: HIDROELÉCTRICA | AF8: HIDROELÉCTRICA | AG8: HIDROELÉCTRICA | AH8: TERMOELÉCTRICA | AI8: TERMOELÉCTRICA | AJ8: TERMOELÉCTRICA | AK8: HIDROELÉCTRICA | AL8: HIDROELÉCTRICA | AM8: TERMOELÉCTRICA | AN8: TERMOELÉCTRICA | AO8: TERMOELÉCTRICA | AP8: HIDROELÉCTRICA | AQ8: HIDROELÉCTRICA | AR8: HIDROELÉCTRICA | AS8: HIDROELÉCTRICA | AT8: HIDROELÉCTRICA | AU8: HIDROELÉCTRICA | AV8: HIDROELÉCTRICA | AW8: HIDROELÉCTRICA | AX8: TERMOELÉCTRICA | AY8: TERMOELÉCTRICA | AZ8: TERMOELÉCTRICA | BA8: HIDROELÉCTRICA | BB8: HIDROELÉCTRICA | BC8: HIDROELÉCTRICA | BD8: HIDROELÉCTRICA | BE8: HIDROELÉCTRICA | BF8: HIDROELÉCTRICA | BG8: HIDROELÉCTRICA | BH8: HIDROELÉCTRICA | BI8: HIDROELÉCTRICA | BJ8: TERMOELÉCTRICA | BK8: TERMOELÉCTRICA | BL8: TERMOELÉCTRICA | BM8: TERMOELÉCTRICA | BN8: TERMOELÉCTRICA | BO8: TERMOELÉCTRICA | BP8: HIDROELÉCTRICA | BQ8: TERMOELÉCTRICA | BR8: TERMOELÉCTRICA | BS8: TERMOELÉCTRICA | BT8: TERMOELÉCTRICA | BU8: TERMOELÉCTRICA | BV8: TERMOELÉCTRICA | BW8: TERMOELÉCTRICA | BX8: TERMOELÉCTRICA | BY8: TERMOELÉCTRICA | BZ8: HIDROELÉCTRICA | CA8: TERMOELÉCTRICA | CB8: TERMOELÉCTRICA | CC8: HIDROELÉCTRICA | CD8: HIDROELÉCTRICA | CE8: HIDROELÉCTRICA | CF8: HIDROELÉCTRICA | CG8: HIDROELÉCTRICA | CH8: HIDROELÉCTRICA | CI8: TERMOELÉCTRICA | CJ8: TERMOELÉCTRICA | CK8: TERMOELÉCTRICA | CL8: TERMOELÉCTRICA | CM8: TERMOELÉCTRICA | CN8: TERMOELÉCTRICA | CO8: TERMOELÉCTRICA | CP8: TERMOELÉCTRICA | CQ8: TERMOELÉCTRICA | CR8: TERMOELÉCTRICA | CS8: TERMOELÉCTRICA | CT8: TERMOELÉCTRICA | CU8: TERMOELÉCTRICA | CV8: SOLAR | CW8: EÓLICA | CX8: SOLAR | CY8: EÓLICA | CZ8: SOLAR | DA8: HIDROELÉCTRICA | DB8: HIDROELÉCTRICA | DC8: HIDROELÉCTRICA | DD8: HIDROELÉCTRICA | DE8: HIDROELÉCTRICA | DF8: HIDROELÉCTRICA | DG8: HIDROELÉCTRICA | DH8: HIDROELÉCTRICA | DI8: HIDROELÉCTRICA | DJ8: HIDROELÉCTRICA | DK8: HIDROELÉCTRICA | DL8: SOLAR | DM8: SOLAR | DN8: EÓLICA | DO8: EÓLICA | DP8: TERMOELÉCTRICA | DQ8: TERMOELÉCTRICA | DR8: TERMOELÉCTRICA | DS8: TERMOELÉCTRICA | DT8: SOLAR | DU8: HIDROELÉCTRICA | DV8: HIDROELÉCTRICA | DW8: HIDROELÉCTRICA | DX8: HIDROELÉCTRICA | DY8: HIDROELÉCTRICA | DZ8: HIDROELÉCTRICA | EA8: HIDROELÉCTRICA | EB8: HIDROELÉCTRICA | EC8: HIDROELÉCTRICA | ED8: EÓLICA | EE8: EÓLICA | EF8: SOLAR | EG8: EÓLICA | EH8: EÓLICA | EI8: EÓLICA | EJ8: EÓLICA | EK8: HIDROELÉCTRICA | EL8: HIDROELÉCTRICA | EM8: HIDROELÉCTRICA | EN8: HIDROELÉCTRICA | EO8: HIDROELÉCTRICA | EP8: HIDROELÉCTRICA | EQ8: EÓLICA | ER8: SOLAR | ES8: SOLAR | ET8: SOLAR | EU8: HIDROELÉCTRICA | EV8: EÓLICA | EW8: EÓLICA | EX8: SOLAR | EY8: SOLAR | EZ8: HIDROELÉCTRICA | FA8: HIDROELÉCTRICA | FB8: TERMOELÉCTRICA | FC8: TERMOELÉCTRICA | FD8: TERMOELÉCTRICA | FE8: TERMOELÉCTRICA | FF8: TERMOELÉCTRICA | FG8: TERMOELÉCTRICA | FH8: TERMOELÉCTRICA | FI8: TERMOELÉCTRICA | FL8: HIDROELÉCTRICA | FM8: HIDROELÉCTRICA | FN8: HIDROELÉCTRICA | FO8: HIDROELÉCTRICA | FP8: TERMOELÉCTRICA | FQ8: TERMOELÉCTRICA | FR8: HIDROELÉCTRICA | FS8: HIDROELÉCTRICA
C9: CENTRALES SANTA ROSA S.A.C. | D9: CENTRALES SANTA ROSA S.A.C. | E9: HYDRO GLOBAL PERÚ S.A.C. | F9: ELECTROPERU | G9: ELECTROPERU | H9: ELECTROPERU | I9: ELECTROPERU | J9: ORAZUL ENERGY PERÚ | K9: ORAZUL ENERGY PERÚ | L9: TERMOSELVA | M9: TERMOSELVA | N9: KALLPA GENERACION S.A. | O9: KALLPA GENERACION S.A. | P9: KALLPA GENERACION S.A. | Q9: KALLPA GENERACION S.A. | R9: KALLPA GENERACION S.A. | S9: KALLPA GENERACION S.A. | T9: KALLPA GENERACION S.A. | U9: KALLPA GENERACION S.A. | V9: SHOUGESA | W9: SHOUGESA | X9: SHOUGESA | Y9: SHOUGESA | Z9: EGEMSA | AA9: EGESUR | AB9: EGESUR | AC9: EGESUR | AD9: EGASA | AE9: EGASA | AF9: EGASA | AG9: EGASA | AH9: EGASA | AI9: EGASA | AJ9: EGASA | AK9: SAN GABAN | AL9: CELEPSA | AM9: MINERA CERRO VERDE | AN9: PLANTA DE RESERVA FRIA DE GENERACION DE ETEN S.A. | AO9: PLANTA DE RESERVA FRIA DE GENERACION DE ETEN S.A. | AP9: EMPRESA DE GENERACION HUALLAGA | AQ9: EMPRESA DE GENERACION HUALLAGA | AR9: LA VIRGEN | AS9: CHINANGO S.A.C. | AT9: CHINANGO S.A.C. | AU9: HIDROELECTRICA HUANCHOR S.A.C. | AV9: CELEPSA RENOVABLES S.R.L. | AW9: INLAND ENERGY SAC | AX9: FENIX POWER PERÚ | AY9: FENIX POWER PERÚ | AZ9: FENIX POWER PERÚ | BA9: STATKRAFT S.A | BB9: STATKRAFT S.A | BC9: STATKRAFT S.A | BD9: STATKRAFT S.A | BE9: STATKRAFT S.A | BF9: STATKRAFT S.A | BG9: STATKRAFT S.A | BH9: STATKRAFT S.A | BI9: EMPRESA DE GENERACION HUANZA | BJ9: ENEL GENERACION PIURA S.A. | BK9: ENEL GENERACION PIURA S.A. | BL9: ENEL GENERACION PIURA S.A. | BM9: ENGIE | BN9: ENGIE | BO9: ENGIE | BP9: ENGIE | BQ9: ENGIE | BR9: ENGIE | BS9: ENGIE | BT9: ENGIE | BU9: ENGIE | BV9: ENGIE | BW9: ENGIE | BX9: ENGIE | BY9: ENGIE | BZ9: ENGIE | CA9: INFRAESTRUCTURAS Y ENERGIAS DEL PERU S.A.C. | CB9: INFRAESTRUCTURAS Y ENERGIAS DEL PERU S.A.C. | CC9: INVERSIONES SHAQSHA S.A.C. | CD9: ORYGEN PERU S.A.A. | CE9: ORYGEN PERU S.A.A. | CF9: ORYGEN PERU S.A.A. | CG9: ORYGEN PERU S.A.A. | CH9: ORYGEN PERU S.A.A. | CI9: ORYGEN PERU S.A.A. | CJ9: ORYGEN PERU S.A.A. | CK9: ORYGEN PERU S.A.A. | CL9: ORYGEN PERU S.A.A. | CM9: ORYGEN PERU S.A.A. | CN9: ORYGEN PERU S.A.A. | CO9: ORYGEN PERU S.A.A. | CP9: SAMAY I S.A.C | CQ9: SAMAY I S.A.C | CR9: SAMAY I S.A.C | CS9: SAMAY I S.A.C | CT9: TERMOCHILCA S.A.C. | CU9: TERMOCHILCA S.A.C. | CV9: COLCA SOLAR S.A.C. | CW9: ENERGIA RENOVABLE DEL SUR S.A. | CX9: GR CORTARRAMA SOCIEDAD ANONIMA CERRADA | CY9: GR TARUCA SOCIEDAD ANONIMA CERRADA | CZ9: KONDU SAC | DA9: PERUANA DE INVERSIONES EN ENERGIAS RENOVABLES S.A. | DB9: ORAZUL ENERGY PERÚ | DC9: ORAZUL ENERGY PERÚ | DD9: SAN GABAN | DE9: MAJA ENERGIA S.A.C. | DF9: EMPRESA DE GENERACION ELECTRICA CANCHAYLLO SAC | DG9: EMPRESA DE GENERACION ELECTRICA SANTA ANA S.A.C. | DH9: EMPRESA ELECTRICA AGUA AZUL | DI9: EMPRESA ELECTRICA RIO DOBLE | DJ9: HIDROCAÑETE S.A. | DK9: HUAURA POWER GROUP S.A. | DL9: MOQUEGUA FV S.A.C. | DM9: PANAMERICANA SOLAR SAC. | DN9: PARQUE EOLICO MARCONA S.A.C. | DO9: PARQUE EOLICO TRES HERMANAS S.A.C. | DP9: PETRAMAS | DQ9: PETRAMAS | DR9: PETRAMAS | DS9: PETRAMAS | DT9: TACNA SOLAR SAC. | DU9: ELECTRICA YANAPAMPA SAC | DV9: ANDEAN POWER S.A.C. | DW9: ASOCIACIÓN SANTA LUCIA DE CHACAS | DX9: ATRIA ENERGIA S.A.C. | DY9: EGEJUNIN | DZ9: EGEJUNIN | EA9: EGEJUNIN | EB9: EGEJUNIN | EC9: EMPRESA DE GENERACION ELECTRICA RIO BAÑOS S.A.C. | ED9: ENERGÍA EÓLICA S.A. | EE9: ENERGÍA EÓLICA S.A. | EF9: ENGIE | EG9: ENGIE | EH9: ENGIE | EI9: ENGIE | EJ9: ENGIE | EK9: GENERACIÓN ANDINA S.A.C. | EL9: GENERACIÓN ANDINA S.A.C. | EM9: GENERADORA DE ENERGÍA DEL PERÚ | EN9: GENERADORA DE ENERGÍA DEL PERÚ | EO9: GENERADORA DE ENERGÍA DEL PERÚ | EP9: GENERADORA DE ENERGÍA DEL PERÚ | EQ9: GR PAINO SOCIEDAD ANONIMA CERRADA | ER9: JOYA SOLAR S.A.C. | ES9: MAJES ARCUS S.A.C. | ET9: ORYGEN PERU S.A.A. | EU9: ORYGEN PERU S.A.A. | EV9: ORYGEN PERU S.A.A. | EW9: ORYGEN PERU S.A.A. | EX9: ORYGEN PERU S.A.A. | EY9: REPARTICIÓN ARCUS S.A.C. | EZ9: SINERSA | FA9: SINERSA | FB9: BIOENERGIA DEL CHIRA S.A. | FC9: GM OPERACIONES S.A.C. | FD9: GM OPERACIONES S.A.C. | FE9: SDF ENERGIA SAC | FF9: SDF ENERGIA SAC | FG9: AGRO INDUSTRIAL PARAMONGA S.A. | FH9: AGROAURORA S.A.C. | FI9: AGROINDUSTRIAS SAN JACINTO S.A.A. | FL9: UNACEM PERU S.A. | FM9: ELECTRO ORIENTE | FN9: AGUAS Y ENERGIA PERU | FO9: ELECTRO ZAÑA S.A.C. | FP9: ELECTRONOROESTE S.A. | FQ9: SDE PIURA | FR9: SINERSA | FS9: SINERSA
C10: SANTA ROSA 1 | D10: SANTA ROSA 2 | E10: SAN GABAN III | F10: MANTARO | G10: RESTITUCION | H10: TUMBES MAK 1 | I10: TUMBES MAK 2 | J10: CARHUAQUERO | K10: CAÑON DEL PATO | L10: AGUAYTIA TG1 | M10: AGUAYTIA TG2 | N10: KALLPA TG1 | O10: KALLPA TG2 | P10: KALLPA TG3 | Q10: KALLPA TV | R10: LFLORES TG1 | S10: LFLORES TV | T10: CERRO DEL AGUILA | U10: CERRODELAGUILAG4 | V10: SHOUGESA TV1 | W10: SHOUGESA TV2 | X10: SHOUGESA TV3 | Y10: SHOUGESA CUMMINS | Z10: MACHUPICCHU | AA10: ARICOTA 1 | AB10: ARICOTA 2 | AC10: INDEPENDENCIA | AD10: CHARCANI I,II,III | AE10: CHARCANI IV | AF10: CHARCANI V | AG10: CHARCANI VI | AH10: CHILINA TG | AI10: MOLLENDO 1, 2, 3 | AJ10: CHILINA (SULZ 1,2) | AK10: SAN GABAN II | AL10: PLATANAL | AM10: RECKA | AN10: RF ETEN TG1 | AO10: RF ETEN TG2 | AP10: CHAGLLA GP1 | AQ10: CHAGLLA | AR10: LA VIRGEN | AS10: CHIMAY | AT10: YANANGO | AU10: HUANCHOR | AV10: MARAÑON | AW10: STA TERESA | AX10: FENIX GT11 | AY10: FENIX GT12 | AZ10: FENIX TV10 | BA10: YAUPI | BB10: OROYA | BC10: PACHACHACA | BD10: MALPASO | BE10: CAHUA | BF10: ARCATA | BG10: GALLITO CIEGO | BH10: CHEVES | BI10: HUANZA | BJ10: MALACAS2 TG4 | BK10: MALACAS3 TG 5 | BL10: MALACAS1 TG6 | BM10: RF ILO2 TG1 | BN10: RF ILO2 TG2 | BO10: RF ILO2 TG3 | BP10: YUNCAN | BQ10: CHILCA1 TG1 | BR10: CHILCA1 TG2 | BS10: CHILCA1 TG3 | BT10: CHILCA-TV | BU10: CHILCA2 TG41 | BV10: CHILCA2-TV | BW10: CTNEPI_TG41 | BX10: CTNEPI_TG42 | BY10: CTNEPI_TG43 | BZ10: QUITARACSA | CA10: RF PTO MALDONADO | CB10: RF PUCALLPA | CC10: PARIAC | CD10: HUINCO | CE10: MATUCANA | CF10: MOYOPAMPA | CG10: CALLAHUANCA | CH10: HUAMPANI | CI10: STA ROSA WEST TG7 | CJ10: UTI_5 | CK10: UTI_6 | CL10: VENTANILLA 3 | CM10: VENTANILLA 4 | CN10: VENTANILLA TV | CO10: STAROSA TG8 | CP10: PTO_BRVO TG1 | CQ10: PTO_BRVO TG2 | CR10: PTO_BRVO TG3 | CS10: PTO_BRVO TG4 | CT10: OLLEROS TG1 | CU10: OLLEROS TV | CV10: CS YARUCAYA | CW10: SAN JUAN | CX10: MATARANI | CY10: DUNA | CZ10: CARHUAQUERO (CS) | DA10: MANTA I | DB10: CARHUAQUERO4 | DC10: CAÑA BRAVA | DD10: TUPURI | DE10: RONCADOR | DF10: CANCHAYLLO | DG10: RENOVANDESH1 | DH10: POTRERO | DI10: PIZARRAS | DJ10: NIMPERIAL | DK10: YARUCAYA | DL10: MOQUEGUA-SOLAR | DM10: PANAMERICANA-SOLAR | DN10: PQE-EOLICO-MARCONA | DO10: PQE-EOLICO-3-HERMANAS | DP10: HUAYCOLORO | DQ10: CALLAO | DR10: DONA_CATALINA | DS10: LAGRINGAV | DT10: TACNA-SOLAR | DU10: YANAPAMPA | DV10: CARHUAC | DW10: HUALLIN | DX10: PURMACANA | DY10: HUASAHUASI | DZ10: STACRUZ_1_2 | EA10: RUNATULLO_II | EB10: RUNATULLO_III | EC10: RUCUY | ED10: PQE-EOLICO-TALARA | EE10: PQE-EOLICO-CUPISNIQUE | EF10: INTIPAMPA | EG10: PUNTA LOMITAS-BL1 | EH10: PUNTA LOMITAS-BL2 | EI10: PUN LOMITAS_EXP-BL1 | EJ10: PUN LOMITAS_EXP-BL2 | EK10: 8AGOSTO | EL10: EL CARMEN | EM10: LA JOYA | EN10: ANGEL_I | EO10: ANGEL_II | EP10: ANGEL_III | EQ10: HUAMBOS | ER10: SAN MARTIN SOLAR | ES10: MAJES | ET10: RUBI | EU10: CH_HER1 | EV10: WAYRA-I | EW10: WAYRA EXTENSION | EX10: CLEMESI | EY10: REPARTICION | EZ10: POECHOS2 | FA10: CHANCAY | FB10: CANA BRAVA | FC10: REFINERIA TALARA TV1 | FD10: REFINERÍA TALARA TV2 | FE10: OQUENDO TG1 | FF10: OQUENDO TV1 | FG10: PARAMONGA | FH10: MAPLE | FI10: SAN_JACINTO | FJ10: MW | FL10: CARPAPATA | FM10: CENTRALES ELOR | FN10: PIAS1 | FO10: ZANA | FP10: TABLAZO | FQ10: TALLANCA | FR10: CURUMUY | FS10: POECHOS1 | FT10: MW
A11: 22/04/2025 | B11: 00:30 | E11: 0 | F11: 587.1 | G11: 195.3 | J11: 59.5 | K11: 228.2 | N11: 105.8 | O11: 105.8 | P11: 105.7 | Q11: 207.7 | R11: 108.8 | S11: 66.7 | T11: 533.4 | U11: 10.2 | Z11: 163.5 | AA11: 7.2 | AB11: 3.1 | AD11: 6.8 | AE11: 10.2 | AF11: 86.6 | AG11: 6.2 | AK11: 109.4 | AL11: 219.6 | AP11: 6.4 | AQ11: 298.4 | AR11: 81.6 | AS11: 123.6 | AT11: 42 | AU11: 18.5 | AV11: 19.7 | AW11: 87.7 | AX11: 0 | AY11: 92.8 | BA11: 107.5 | BB11: 7.3 | BC11: 6.7 | BD11: 45.9 | BE11: 22.1 | BF11: 0 | BG11: 37.2 | BH11: 170.2 | BI11: 0 | BL11: 47.8 | BP11: 85.4 | BQ11: 110 | BS11: 115.1 | BT11: 137.9 | CC11: 4.6 | CD11: 79.2 | CE11: 131.3 | CF11: 62.1 | CG11: 79 | CH11: 29.5 | CL11: 104.1 | CM11: 103.9 | CN11: 120.9 | CQ11: 0 | CV11: 0 | CW11: 108.2 | CX11: 0 | CY11: 0 | CZ11: 0 | DA11: 20 | DB11: 9.9 | DC11: 4.8 | DD11: 1.2 | DE11: 3.3 | DF11: 4.9 | DG11: 19.9 | DH11: 20 | DI11: 19.1 | DJ11: 3.6 | DK11: 9.3 | DL11: 0 | DM11: 0 | DN11: 25.6 | DO11: 64.3 | DP11: 4.6 | DQ11: 2.4 | DR11: 2.4 | DT11: 0 | DU11: 3.3 | DV11: 9.3 | DW11: 3.1 | DY11: 19.8 | DZ11: 9.7 | EA11: 18.5 | EB11: 20.2 | EC11: 19.8 | ED11: 18.8 | EE11: 35.4 | EF11: 0 | EG11: 67.6 | EH11: 85.7 | EI11: 8.2 | EJ11: 0.7 | EK11: 21 | EL11: 6.9 | EM11: 5.2 | EN11: 20.4 | EO11: 20.4 | EP11: 20.2 | EQ11: 0 | ER11: 0 | ES11: 0 | ET11: 0 | EU11: 0.6 | EV11: 87.2 | EW11: 68.3 | EX11: 0 | EY11: 0 | EZ11: 8.6 | FA11: 19.8 | FC11: 43.1 | FD11: 31.8 | FE11: 29.1 | FF11: 3.4 | FG11: 16 | FJ11: 6350.8 | FL11: 23.14369 | FM11: 0 | FO11: 13.2 | FQ11: 9.43433 | FR11: 10.2 | FS11: 15.4 | FT11: 71.37802
A12: 22/04/2025 | B12: 01:00 | E12: 0 | F12: 599.2 | G12: 201.5 | J12: 60.2 | K12: 231.5 | N12: 105.3 | O12: 105.2 | P12: 105.4 | Q12: 208.1 | R12: 107.6 | S12: 66 | T12: 561.1 | U12: 10.4 | Z12: 165.8 | AA12: 7.8 | AB12: 3.4 | AD12: 6.8 | AE12: 10.2 | AF12: 89.8 | AG12: 6 | AK12: 110.8 | AL12: 223.2 | AP12: 6.5 | AQ12: 464.4 | AR12: 81.8 | AS12: 148.7 | AT12: 42.2 | AU12: 18.7 | AV12: 19.7 | AW12: 85.4 | AX12: 0 | AY12: 35.1 | BA12: 108.7 | BB12: 7.3 | BC12: 6.6 | BD12: 47 | BE12: 22 | BF12: 0 | BG12: 38.1 | BH12: 174.8 | BI12: 0 | BL12: 24.9 | BP12: 86.4 | BQ12: 83.9 | BS12: 83.7 | BT12: 107.3 | CC12: 4.6 | CD12: 32.4 | CE12: 134.4 | CF12: 63.4 | CG12: 79.5 | CH12: 30.1 | CL12: 104 | CM12: 103.9 | CN12: 120.2 | CQ12: 0 | CV12: 0 | CW12: 108.1 | CX12: 0 | CY12: 0 | CZ12: 0 | DA12: 20 | DB12: 9.9 | DC12: 4.7 | DD12: 1.2 | DE12: 3.4 | DF12: 5 | DG12: 20.4 | DH12: 20 | DI12: 19.1 | DJ12: 3.6 | DK12: 9.3 | DL12: 0 | DM12: 0 | DN12: 27.3 | DO12: 69.8 | DP12: 4.6 | DQ12: 2.4 | DR12: 2.4 | DT12: 0 | DU12: 3.3 | DV12: 5.9 | DW12: 3.1 | DY12: 19.8 | DZ12: 9.6 | EA12: 18.7 | EB12: 20.3 | EC12: 19.8 | ED12: 23.6 | EE12: 46 | EF12: 0 | EG12: 101.8 | EH12: 90.8 | EI12: 9.2 | EJ12: 3.1 | EK12: 21 | EL12: 6.9 | EM12: 5.5 | EN12: 20.4 | EO12: 20.4 | EP12: 20.2 | EQ12: 0 | ER12: 0 | ES12: 0 | ET12: 0 | EU12: 0.6 | EV12: 96 | EW12: 85.5 | EX12: 0 | EY12: 0 | EZ12: 8.5 | FA12: 19.9 | FC12: 41.5 | FD12: 31.8 | FE12: 29.1 | FF12: 3.2 | FG12: 16 | FJ12: 6483.7 | FL12: 23.14725 | FM12: 0 | FO12: 13.2 | FQ12: 9.43416 | FR12: 10.2 | FS12: 15.4 | FT12: 71.38141
A13: 22/04/2025 | B13: 01:30 | E13: 0 | F13: 599.2 | G13: 199.7 | J13: 60 | K13: 231.5 | N13: 106.2 | O13: 106.5 | P13: 107.1 | Q13: 208.1 | R13: 107.9 | S13: 65.6 | T13: 565.6 | U13: 10.5 | Z13: 166.2 | AA13: 7.6 | AB13: 3.5 | AD13: 6.8 | AE13: 10.2 | AF13: 89.8 | AG13: 5.8 | AK13: 110.9 | AL13: 224.1 | AP13: 6.5 | AQ13: 467 | AR13: 81.8 | AS13: 148.9 | AT13: 42.2 | AU13: 18.7 | AV13: 19.7 | AW13: 92.2 | AX13: 0 | AY13: 35.1 | BA13: 108.7 | BB13: 7.3 | BC13: 6.5 | BD13: 47.1 | BE13: 22 | BF13: 0 | BG13: 37.9 | BH13: 174.2 | BI13: 0 | BL13: 24.7 | BP13: 86.4 | BQ13: 83.8 | BS13: 83.5 | BT13: 109.4 | CC13: 4.6 | CD13: 27.2 | CE13: 132 | CF13: 63.5 | CG13: 79.4 | CH13: 30.1 | CL13: 104.1 | CM13: 103.9 | CN13: 120.4 | CQ13: 0 | CV13: 0 | CW13: 102.2 | CX13: 0 | CY13: 0 | CZ13: 0 | DA13: 20 | DB13: 9.9 | DC13: 4.7 | DD13: 1.2 | DE13: 3.4 | DF13: 5 | DG13: 20.2 | DH13: 20 | DI13: 19.1 | DJ13: 3.6 | DK13: 9.3 | DL13: 0 | DM13: 0 | DN13: 25.2 | DO13: 71 | DP13: 4.6 | DQ13: 2.4 | DR13: 2.4 | DT13: 0 | DU13: 3.3 | DV13: 6 | DW13: 3.1 | DY13: 19.8 | DZ13: 9.6 | EA13: 18.6 | EB13: 20.3 | EC13: 20 | ED13: 16.9 | EE13: 39.4 | EF13: 0 | EG13: 88.8 | EH13: 91.9 | EI13: 8.4 | EJ13: 5 | EK13: 21 | EL13: 6.9 | EM13: 5.5 | EN13: 20.4 | EO13: 20.4 | EP13: 20.2 | EQ13: 0 | ER13: 0 | ES13: 0 | ET13: 0 | EU13: 0.6 | EV13: 100.7 | EW13: 88.1 | EX13: 0 | EY13: 0 | EZ13: 8.6 | FA13: 20 | FC13: 41.5 | FD13: 31.4 | FE13: 29.2 | FF13: 3.2 | FG13: 16 | FJ13: 6470.6 | FL13: 23.14646 | FM13: 0 | FO13: 13.2 | FQ13: 9.43426 | FR13: 10.2 | FS13: 15.4 | FT13: 71.38072
A14: 22/04/2025 | B14: 02:00 | E14: 0 | F14: 592.2 | G14: 197.5 | J14: 59.1 | K14: 237.2 | N14: 105.1 | O14: 103.7 | P14: 104.5 | Q14: 213.8 | R14: 108.6 | S14: 67.4 | T14: 550.5 | U14: 10.3 | Z14: 159.6 | AA14: 6.8 | AB14: 3.2 | AD14: 6.8 | AE14: 10.2 | AF14: 90.2 | AG14: 5.8 | AK14: 108.9 | AL14: 223.4 | AP14: 6.4 | AQ14: 427.2 | AR14: 81.8 | AS14: 140.3 | AT14: 42.1 | AU14: 18.7 | AV14: 19.7 | AW14: 88.8 | AX14: 0 | AY14: 30.5 | BA14: 105.8 | BB14: 7.4 | BC14: 6.6 | BD14: 44.2 | BE14: 22.1 | BF14: 0 | BG14: 36.3 | BH14: 171.2 | BI14: 0 | BL14: 24.5 | BP14: 85.6 | BQ14: 84.1 | BS14: 83.1 | BT14: 108 | CC14: 4.6 | CD14: 20.1 | CE14: 126.2 | CF14: 61.7 | CG14: 78.5 | CH14: 29 | CL14: 103.7 | CM14: 104.7 | CN14: 119.9 | CQ14: 0 | CV14: 0 | CW14: 96.9 | CX14: 0 | CY14: 0.6 | CZ14: 0 | DA14: 20 | DB14: 9.9 | DC14: 4.7 | DD14: 1.2 | DE14: 3.4 | DF14: 5 | DG14: 19.8 | DH14: 20 | DI14: 19.1 | DJ14: 3.6 | DK14: 9.3 | DL14: 0 | DM14: 0 | DN14: 27 | DO14: 69.2 | DP14: 4.6 | DQ14: 2.4 | DR14: 2.4 | DT14: 0 | DU14: 3.3 | DV14: 5.9 | DW14: 3.1 | DY14: 19.8 | DZ14: 9.6 | EA14: 18.5 | EB14: 20.2 | EC14: 20 | ED14: 11.3 | EE14: 22.5 | EF14: 0 | EG14: 86.2 | EH14: 92.2 | EI14: 7.9 | EJ14: 1.7 | EK14: 21 | EL14: 6.9 | EM14: 5.5 | EN14: 20.4 | EO14: 20.4 | EP14: 20.2 | EQ14: 0 | ER14: 0 | ES14: 0 | ET14: 0 | EU14: 0.6 | EV14: 81.4 | EW14: 70.5 | EX14: 0 | EY14: 0 | EZ14: 8.7 | FA14: 20 | FC14: 42.7 | FD14: 31.4 | FE14: 29.2 | FF14: 3.1 | FG14: 17 | FJ14: 6287.9 | FL14: 23.14213 | FM14: 0 | FO14: 13.2 | FQ14: 9.43451 | FR14: 10.2 | FS14: 15.5 | FT14: 71.47664
A15: 22/04/2025 | B15: 02:30 | E15: 0 | F15: 599.8 | G15: 201.8 | J15: 57.7 | K15: 230.9 | N15: 121.5 | O15: 122.1 | P15: 121.8 | Q15: 216.8 | R15: 109.3 | S15: 67.8 | T15: 564.3 | U15: 10 | Z15: 163.1 | AA15: 7.1 | AB15: 3.6 | AD15: 6.8 | AE15: 10.2 | AF15: 89.8 | AG15: 5.8 | AK15: 110.3 | AL15: 224 | AP15: 6.5 | AQ15: 465.3 | AR15: 81.9 | AS15: 143.5 | AT15: 42.2 | AU15: 18.7 | AV15: 19.7 | AW15: 89.3 | AX15: 0 | AY15: 33 | BA15: 108.2 | BB15: 7.4 | BC15: 6.7 | BD15: 46.6 | BE15: 22.2 | BF15: 0 | BG15: 36.5 | BH15: 174.4 | BI15: 0 | BL15: 24.8 | BP15: 85 | BQ15: 86.2 | BS15: 84.7 | BT15: 108.8 | CC15: 4.6 | CD15: 20.2 | CE15: 129.6 | CF15: 62.6 | CG15: 78.8 | CH15: 29.6 | CL15: 106.1 | CM15: 105.8 | CN15: 123 | CQ15: 0 | CV15: 0 | CW15: 88.6 | CX15: 0 | CY15: 0.3 | CZ15: 0 | DA15: 20 | DB15: 9.8 | DC15: 4.8 | DD15: 1.2 | DE15: 3.4 | DF15: 5 | DG15: 20.4 | DH15: 20 | DI15: 19.1 | DJ15: 3.6 | DK15: 9.3 | DL15: 0 | DM15: 0 | DN15: 24.7 | DO15: 66.7 | DP15: 4.6 | DQ15: 2.4 | DR15: 2.4 | DT15: 0 | DU15: 3.3 | DV15: 5.7 | DW15: 3.1 | DY15: 19.8 | DZ15: 9.6 | EA15: 18.5 | EB15: 20.3 | EC15: 20 | ED15: 11.4 | EE15: 19.9 | EF15: 0 | EG15: 90.3 | EH15: 88 | EI15: 8.1 | EJ15: 3.3 | EK15: 21 | EL15: 6.9 | EM15: 5.5 | EN15: 20.4 | EO15: 20.4 | EP15: 20.2 | EQ15: 0 | ER15: 0 | ES15: 0 | ET15: 0 | EU15: 0.6 | EV15: 61.1 | EW15: 55.5 | EX15: 0 | EY15: 0 | EZ15: 8.6 | FA15: 20 | FC15: 42.6 | FD15: 31.4 | FE15: 29.1 | FF15: 3.2 | FG15: 17 | FJ15: 6387.5 | FL15: 23.14456 | FM15: 0 | FO15: 13.2 | FQ15: 9.43441 | FR15: 10.4 | FS15: 15.5 | FT15: 71.67897
A16: 22/04/2025 | B16: 03:00 | E16: 0 | F16: 597.7 | G16: 200.4 | J16: 59.4 | K16: 231.3 | N16: 114 | O16: 113.1 | P16: 113.1 | Q16: 213.6 | R16: 108.6 | S16: 66.5 | T16: 559 | U16: 10.3 | Z16: 161.4 | AA16: 6.9 | AB16: 3.6 | AD16: 6.8 | AE16: 10.2 | AF16: 90.2 | AG16: 5.8 | AK16: 110.2 | AL16: 223.8 | AP16: 6.5 | AQ16: 429.1 | AR16: 81.8 | AS16: 147.7 | AT16: 42.2 | AU16: 18.7 | AV16: 19.7 | AW16: 90 | AX16: 0 | AY16: 32.7 | BA16: 108.2 | BB16: 7.4 | BC16: 6.5 | BD16: 46.5 | BE16: 22 | BF16: 0 | BG16: 37.3 | BH16: 173.3 | BI16: 0 | BL16: 24.5 | BP16: 85.7 | BQ16: 84 | BS16: 83.8 | BT16: 107.4 | CC16: 4.6 | CD16: 19.6 | CE16: 130.5 | CF16: 62.8 | CG16: 79.2 | CH16: 29.7 | CL16: 104.2 | CM16: 104.3 | CN16: 120.4 | CQ16: 0 | CV16: 0 | CW16: 89.4 | CX16: 0 | CY16: 0 | CZ16: 0 | DA16: 20 | DB16: 9.9 | DC16: 4.8 | DD16: 1.2 | DE16: 3.4 | DF16: 4.9 | DG16: 20 | DH16: 20 | DI16: 19.1 | DJ16: 3.6 | DK16: 9.3 | DL16: 0 | DM16: 0 | DN16: 21.6 | DO16: 60 | DP16: 4.6 | DQ16: 2.4 | DR16: 2.4 | DT16: 0 | DU16: 3.3 | DV16: 5.7 | DW16: 3.1 | DY16: 19.8 | DZ16: 9.6 | EA16: 18.4 | EB16: 20.2 | EC16: 20 | ED16: 16 | EE16: 25.1 | EF16: 0 | EG16: 100.4 | EH16: 89.4 | EI16: 11.8 | EJ16: 3.5 | EK16: 21 | EL16: 6.9 | EM16: 5.5 | EN16: 20.4 | EO16: 20.4 | EP16: 20.2 | EQ16: 0 | ER16: 0 | ES16: 0 | ET16: 0 | EU16: 0.6 | EV16: 57.3 | EW16: 67.7 | EX16: 0 | EY16: 0 | EZ16: 8.7 | FA16: 20 | FC16: 43.2 | FD16: 31.4 | FE16: 29.2 | FF16: 3.3 | FG16: 16.7 | FJ16: 6331.6 | FL16: 23.1421 | FM16: 0 | FO16: 13.2 | FQ16: 9.43434 | FR16: 10.4 | FS16: 15.4 | FT16: 71.57644
A17: 22/04/2025 | B17: 03:30 | E17: 0 | F17: 597.7 | G17: 199.9 | J17: 59.8 | K17: 231.4 | N17: 106.4 | O17: 105.8 | P17: 106.2 | Q17: 207.3 | R17: 108.4 | S17: 67 | T17: 561.5 | U17: 10.3 | Z17: 161.4 | AA17: 7.1 | AB17: 3.7 | AD17: 6.8 | AE17: 10.2 | AF17: 89.4 | AG17: 5.8 | AK17: 110.5 | AL17: 223.7 | AP17: 6.5 | AQ17: 423.7 | AR17: 81.9 | AS17: 140.9 | AT17: 42.2 | AU17: 18.7 | AV17: 19.7 | AW17: 90.2 | AX17: 32 | AY17: 33.7 | BA17: 106.4 | BB17: 7.4 | BC17: 6.6 | BD17: 45.8 | BE17: 22.1 | BF17: 0 | BG17: 36.8 | BH17: 173.5 | BI17: 0 | BL17: 24.8 | BP17: 86.1 | BQ17: 83.4 | BS17: 83.1 | BT17: 108.7 | CC17: 4.6 | CD17: 21.8 | CE17: 126.2 | CF17: 63 | CG17: 76.2 | CH17: 29.6 | CL17: 103.8 | CM17: 104.3 | CN17: 120.5 | CQ17: 0 | CV17: 0 | CW17: 95.5 | CX17: 0 | CY17: 0 | CZ17: 0 | DA17: 20 | DB17: 9.9 | DC17: 4.6 | DD17: 1.2 | DE17: 3.4 | DF17: 4.9 | DG17: 20.2 | DH17: 20 | DI17: 19.1 | DJ17: 3.6 | DK17: 9.3 | DL17: 0 | DM17: 0 | DN17: 20.7 | DO17: 59.8 | DP17: 4.6 | DQ17: 2.4 | DR17: 2.4 | DT17: 0 | DU17: 3.3 | DV17: 5.7 | DW17: 3.1 | DY17: 19.8 | DZ17: 9.6 | EA17: 18.3 | EB17: 20.3 | EC17: 20 | ED17: 27.5 | EE17: 26.7 | EF17: 0 | EG17: 94.1 | EH17: 88.5 | EI17: 14.9 | EJ17: 3 | EK17: 21 | EL17: 6.9 | EM17: 5 | EN17: 20.4 | EO17: 20.4 | EP17: 20.2 | EQ17: 0 | ER17: 0 | ES17: 0 | ET17: 0 | EU17: 0.6 | EV17: 63 | EW17: 57.2 | EX17: 0 | EY17: 0 | EZ17: 8.6 | FA17: 20 | FC17: 42.5 | FD17: 32.1 | FE17: 29.2 | FF17: 3.2 | FG17: 16.9 | FJ17: 6328.1 | FL17: 23.13819 | FM17: 0 | FO17: 13.2 | FQ17: 9.43435 | FR17: 10.2 | FS17: 15.4 | FT17: 71.37254
A18: 22/04/2025 | B18: 04:00 | E18: 0 | F18: 601.5 | G18: 199.3 | J18: 60.2 | K18: 233.6 | N18: 107.4 | O18: 106 | P18: 106.1 | Q18: 208 | R18: 109.7 | S18: 67.4 | T18: 563.8 | U18: 10.5 | Z18: 167.5 | AA18: 7.3 | AB18: 3.6 | AD18: 6.8 | AE18: 10.2 | AF18: 90 | AG18: 5.8 | AK18: 111.1 | AL18: 223.3 | AP18: 6.5 | AQ18: 436.8 | AR18: 81.8 | AS18: 144.1 | AT18: 42.1 | AU18: 18.7 | AV18: 19.7 | AW18: 90.4 | AX18: 35.4 | AY18: 36.8 | BA18: 108.8 | BB18: 7.6 | BC18: 6.6 | BD18: 46.8 | BE18: 22.1 | BF18: 0 | BG18: 37.9 | BH18: 174.7 | BI18: 0 | BL18: 25.3 | BP18: 86.6 | BQ18: 84.1 | BS18: 83.8 | BT18: 107 | CC18: 4.6 | CD18: 22.4 | CE18: 128.7 | CF18: 63.6 | CG18: 76.5 | CH18: 30.1 | CL18: 104.2 | CM18: 104.2 | CN18: 121 | CQ18: 0 | CV18: 0 | CW18: 92.8 | CX18: 0 | CY18: 0 | CZ18: 0 | DA18: 20 | DB18: 9.9 | DC18: 4.8 | DD18: 1.2 | DE18: 3.4 | DF18: 4.9 | DG18: 20.3 | DH18: 20 | DI18: 19.1 | DJ18: 3.6 | DK18: 9.3 | DL18: 0 | DM18: 0 | DN18: 23.2 | DO18: 57.4 | DP18: 4.6 | DQ18: 2.4 | DR18: 2.4 | DT18: 0 | DU18: 3.3 | DV18: 5.8 | DW18: 3.1 | DY18: 19.8 | DZ18: 9.6 | EA18: 18.4 | EB18: 20.3 | EC18: 19.9 | ED18: 23.2 | EE18: 36.3 | EF18: 0 | EG18: 93.1 | EH18: 88.5 | EI18: 12.2 | EJ18: 2.8 | EK18: 21 | EL18: 6.8 | EM18: 5.1 | EN18: 20.4 | EO18: 20.4 | EP18: 20.2 | EQ18: 0 | ER18: 0 | ES18: 0 | ET18: 0 | EU18: 0.6 | EV18: 58.7 | EW18: 49.8 | EX18: 0 | EY18: 0 | EZ18: 8.7 | FA18: 20 | FC18: 42.9 | FD18: 31.1 | FE18: 29.2 | FF18: 3.2 | FG18: 17 | FJ18: 6368.7 | FL18: 23.14311 | FM18: 0 | FO18: 13.2 | FQ18: 9.43464 | FR18: 10.4 | FS18: 15.4 | FT18: 71.57775
A19: 22/04/2025 | B19: 04:30 | E19: 0 | F19: 595.6 | G19: 198.5 | J19: 60 | K19: 231.3 | N19: 107 | O19: 107.5 | P19: 107 | Q19: 223.6 | R19: 109.5 | S19: 66.6 | T19: 555.7 | U19: 10.4 | Z19: 164.6 | AA19: 6.9 | AB19: 3.2 | AD19: 6.8 | AE19: 10.2 | AF19: 90.9 | AG19: 5.6 | AK19: 110.6 | AL19: 223.5 | AP19: 6.4 | AQ19: 463.1 | AR19: 81.9 | AS19: 148.7 | AT19: 42.2 | AU19: 18.7 | AV19: 19.7 | AW19: 88.9 | AX19: 34.8 | AY19: 0 | BA19: 108.4 | BB19: 7.7 | BC19: 6.5 | BD19: 46.4 | BE19: 22.1 | BF19: 0 | BG19: 37.5 | BH19: 172.7 | BI19: 0 | BL19: 25 | BP19: 86.2 | BQ19: 83.5 | BS19: 83.5 | BT19: 108.1 | CC19: 4.6 | CD19: 19.5 | CE19: 131.6 | CF19: 63.2 | CG19: 76.5 | CH19: 29.9 | CL19: 104 | CM19: 104 | CN19: 120.7 | CQ19: 0 | CV19: 0 | CW19: 96.5 | CX19: 0 | CY19: 0 | CZ19: 0 | DA19: 20 | DB19: 9.9 | DC19: 4.8 | DD19: 1.2 | DE19: 3.4 | DF19: 4.9 | DG19: 20.1 | DH19: 20 | DI19: 19.1 | DJ19: 3.6 | DK19: 9.3 | DL19: 0 | DM19: 0 | DN19: 23.2 | DO19: 52.4 | DP19: 4.6 | DQ19: 2.4 | DR19: 2.4 | DT19: 0 | DU19: 2.8 | DV19: 5.8 | DW19: 3.1 | DY19: 19.8 | DZ19: 9.7 | EA19: 18.2 | EB19: 20.2 | EC19: 20 | ED19: 28.2 | EE19: 34.6 | EF19: 0 | EG19: 62.4 | EH19: 79.7 | EI19: 6.5 | EJ19: 2 | EK19: 21 | EL19: 6.8 | EM19: 5 | EN19: 20.4 | EO19: 20.4 | EP19: 20.2 | EQ19: 0 | ER19: 0 | ES19: 0 | ET19: 0 | EU19: 0.6 | EV19: 37.1 | EW19: 35.9 | EX19: 0 | EY19: 0 | EZ19: 8.6 | FA19: 20 | FC19: 43 | FD19: 31.4 | FE19: 29.2 | FF19: 3.3 | FG19: 16 | FJ19: 6270.7 | FL19: 23.14071 | FM19: 0 | FO19: 13.2 | FQ19: 9.4349 | FR19: 10.3 | FS19: 15.4 | FT19: 71.47561
A20: 22/04/2025 | B20: 05:00 | E20: 0 | F20: 601.2 | G20: 202.2 | J20: 60.2 | K20: 231.6 | N20: 131.3 | O20: 131.6 | P20: 131.5 | Q20: 221.7 | R20: 106.9 | S20: 66.2 | T20: 566.3 | U20: 10.5 | Z20: 166.8 | AA20: 7.3 | AB20: 3.4 | AD20: 6.8 | AE20: 10.2 | AF20: 90.1 | AG20: 5.8 | AK20: 111 | AL20: 223.2 | AP20: 6.5 | AQ20: 465.4 | AR20: 81.9 | AS20: 148.4 | AT20: 42.2 | AU20: 18.7 | AV20: 19.7 | AW20: 90.8 | AX20: 32.4 | AY20: 0 | BA20: 108.6 | BB20: 8.3 | BC20: 6.6 | BD20: 46.4 | BE20: 22.1 | BF20: 0 | BG20: 38.1 | BH20: 174.1 | BI20: 0 | BL20: 47 | BP20: 86.5 | BQ20: 144 | BS20: 127.6 | BT20: 139.6 | CC20: 4.6 | CD20: 43.5 | CE20: 132.4 | CF20: 63.5 | CG20: 76.6 | CH20: 30.1 | CL20: 103.8 | CM20: 103.9 | CN20: 120 | CQ20: 0 | CV20: 0 | CW20: 100.8 | CX20: 0 | CY20: 0 | CZ20: 0 | DA20: 20 | DB20: 9.9 | DC20: 4.7 | DD20: 1.2 | DE20: 3.4 | DF20: 5.1 | DG20: 20.4 | DH20: 20 | DI20: 19.1 | DJ20: 3.7 | DK20: 9.3 | DL20: 0 | DM20: 0 | DN20: 22.1 | DO20: 53.6 | DP20: 4.6 | DQ20: 2.4 | DR20: 2.4 | DT20: 0 | DU20: 3.2 | DV20: 5.8 | DW20: 3.1 | DY20: 19.8 | DZ20: 9.7 | EA20: 18 | EB20: 20.3 | EC20: 20 | ED20: 30.2 | EE20: 42.3 | EF20: 0 | EG20: 54.7 | EH20: 81.4 | EI20: 6.7 | EJ20: 1.9 | EK20: 21 | EL20: 6.8 | EM20: 4.9 | EN20: 20.4 | EO20: 20.4 | EP20: 20.2 | EQ20: 0 | ER20: 0 | ES20: 0 | ET20: 0 | EU20: 0.6 | EV20: 17.8 | EW20: 16.2 | EX20: 0 | EY20: 0 | EZ20: 8.6 | FA20: 20 | FC20: 42.8 | FD20: 31.3 | FE20: 29.3 | FF20: 3.3 | FG20: 16 | FJ20: 6518.5 | FL20: 23.14089 | FM20: 0 | FO20: 13.2 | FQ20: 9.4348 | FR20: 10.2 | FS20: 15.5 | FT20: 71.47569
A21: 22/04/2025 | B21: 05:30 | E21: 0 | F21: 599.2 | G21: 201.9 | J21: 91.5 | K21: 233.9 | N21: 111.9 | O21: 111.6 | P21: 111.3 | Q21: 213.1 | R21: 108 | S21: 66.5 | T21: 553.3 | U21: 10.7 | Z21: 166 | AA21: 7.5 | AB21: 3.3 | AD21: 6.7 | AE21: 10.2 | AF21: 90 | AG21: 5.9 | AK21: 111.2 | AL21: 224 | AP21: 6.5 | AQ21: 465.5 | AR21: 81.8 | AS21: 149.6 | AT21: 42.1 | AU21: 18.7 | AV21: 19.7 | AW21: 91 | AX21: 31.9 | AY21: 0 | BA21: 108.9 | BB21: 0 | BC21: 6.5 | BD21: 46 | BE21: 20.5 | BF21: 0 | BG21: 38 | BH21: 174.8 | BI21: 0 | BL21: 47 | BP21: 87.2 | BQ21: 171.8 | BS21: 200 | BT21: 181.9 | CC21: 4.6 | CD21: 34.7 | CE21: 133.7 | CF21: 61.2 | CG21: 76.7 | CH21: 30.3 | CL21: 102.7 | CM21: 102.5 | CN21: 119 | CQ21: 0 | CV21: 0 | CW21: 95.4 | CX21: 0 | CY21: 0 | CZ21: 0 | DA21: 20 | DB21: 9.9 | DC21: 5.4 | DD21: 1.2 | DE21: 3.3 | DF21: 5 | DG21: 20.3 | DH21: 20 | DI21: 19.1 | DJ21: 3.6 | DK21: 9.3 | DL21: 0 | DM21: 0 | DN21: 21.1 | DO21: 50.2 | DP21: 4.6 | DQ21: 2.4 | DR21: 2.4 | DT21: 0 | DU21: 3.2 | DV21: 5.7 | DW21: 3 | DY21: 19.8 | DZ21: 9.7 | EA21: 18.2 | EB21: 20.3 | EC21: 19.9 | ED21: 30.2 | EE21: 39.1 | EF21: 0 | EG21: 39.8 | EH21: 68.6 | EI21: 3.6 | EJ21: 1.9 | EK21: 21 | EL21: 6.8 | EM21: 4.9 | EN21: 20.4 | EO21: 20.4 | EP21: 20.2 | EQ21: 0 | ER21: 0 | ES21: 0 | ET21: 0 | EU21: 0.6 | EV21: 10 | EW21: 12 | EX21: 0 | EY21: 0 | EZ21: 8.6 | FA21: 20 | FC21: 42.1 | FD21: 31.4 | FE21: 29.3 | FF21: 3.3 | FG21: 16 | FJ21: 6535.7 | FL21: 23.1428 | FM21: 0 | FO21: 13.2 | FQ21: 9.43483 | FR21: 10.2 | FS21: 15.5 | FT21: 71.47763
A22: 22/04/2025 | B22: 06:00 | E22: 0 | F22: 601.1 | G22: 201.4 | J22: 90.1 | K22: 232.4 | N22: 139.5 | O22: 139.2 | P22: 138.8 | Q22: 235.4 | R22: 113.5 | S22: 66.5 | T22: 562.1 | U22: 10.5 | Z22: 164.6 | AA22: 7.5 | AB22: 3.3 | AD22: 6.6 | AE22: 10.1 | AF22: 88.3 | AG22: 5.9 | AK22: 111 | AL22: 223.9 | AP22: 6.4 | AQ22: 466.4 | AR22: 81.9 | AS22: 148.7 | AT22: 42.2 | AU22: 18.7 | AV22: 19.7 | AW22: 90.7 | AX22: 32.3 | AY22: 0 | BA22: 108.9 | BB22: 0 | BC22: 6.6 | BD22: 46 | BE22: 20.1 | BF22: 0 | BG22: 38 | BH22: 175.4 | BI22: 0 | BL22: 46.9 | BP22: 86.6 | BQ22: 173.7 | BS22: 200 | BT22: 183.2 | CC22: 4.6 | CD22: 85.5 | CE22: 132.6 | CF22: 57.1 | CG22: 76.6 | CH22: 30.2 | CL22: 103.5 | CM22: 104.1 | CN22: 119.6 | CQ22: 0 | CV22: 0 | CW22: 107 | CX22: 0 | CY22: 0 | CZ22: 0 | DA22: 20 | DB22: 9.9 | DC22: 5.3 | DD22: 1.2 | DE22: 3.3 | DF22: 5 | DG22: 20.4 | DH22: 20 | DI22: 19.1 | DJ22: 3.6 | DK22: 9.3 | DL22: 0.4 | DM22: 0.3 | DN22: 20.4 | DO22: 51.9 | DP22: 4.6 | DQ22: 2.4 | DR22: 2.4 | DT22: 0 | DU22: 3.3 | DV22: 5.8 | DW22: 3.1 | DY22: 19.8 | DZ22: 9.7 | EA22: 18.2 | EB22: 20.3 | EC22: 20 | ED22: 30.2 | EE22: 35.1 | EF22: 0 | EG22: 24.7 | EH22: 45.8 | EI22: 4 | EJ22: 0.5 | EK22: 21 | EL22: 6.8 | EM22: 4.9 | EN22: 20.4 | EO22: 20.4 | EP22: 20.2 | EQ22: 0 | ER22: 0 | ES22: 0 | ET22: 0.8 | EU22: 0.6 | EV22: 5.9 | EW22: 13.4 | EX22: 0.6 | EY22: 0 | EZ22: 8.7 | FA22: 20 | FC22: 42.1 | FD22: 31.4 | FE22: 29.3 | FF22: 3.3 | FG22: 16.5 | FJ22: 6671.2 | FL22: 23.1413 | FM22: 0 | FO22: 13.2 | FQ22: 9.43471 | FR22: 10.2 | FS22: 15.4 | FT22: 71.37601
... A58: 23/04/2025 | B58: 00:00 | E58: 62.02 | F58: 640 | G58: 214.7 | J58: 89.8 | K58: 231.1 | N58: 106.4 | O58: 105.3 | P58: 106.6 | Q58: 208.9 | R58: 108.5 | S58: 67.5 | T58: 542.1 | U58: 10.4 | Z58: 166.8 | AA58: 7.1 | AB58: 3.3 | AD58: 6.7 | AE58: 10.1 | AF58: 75.9 | AG58: 4.4 | AK58: 110.4 | AL58: 221.3 | AP58: 6.4 | AQ58: 383 | AR58: 81.8 | AS58: 123.2 | AT58: 42.1 | AU58: 18.5 | AV58: 19.7 | AW58: 86.3 | AX58: 0 | AY58: 0 | BA58: 108.4 | BB58: 7.7 | BC58: 5.9 | BD58: 46.6 | BE58: 11.6 | BF58: 3.8 | BG58: 38.2 | BH58: 172.4 | BI58: 93.2 | BL58: 0 | BP58: 86 | BQ58: 120.2 | BS58: 122.4 | BT58: 143.5 | CC58: 4.6 | CD58: 187.2 | CE58: 111.1 | CF58: 65.5 | CG58: 79.3 | CH58: 30.8 | CL58: 103 | CM58: 103 | CN58: 119.9 | CQ58: 0 | CV58: 0 | CW58: 101.4 | CX58: 0 | CY58: 0 | CZ58: 0 | DA58: 19.8 | DB58: 9.8 | DC58: 5.3 | DD58: 1.2 | DE58: 3.4 | DF58: 4.9 | DG58: 20.3 | DH58: 20 | DI58: 19.1 | DJ58: 3.6 | DK58: 9.3 | DL58: 0 | DM58: 0 | DN58: 28.7 | DO58: 68.3 | DP58: 4.5 | DQ58: 2.4 | DR58: 2.4 | DT58: 0 | DU58: 3.3 | DV58: 20.3 | DW58: 3.1 | DY58: 19.8 | DZ58: 9.6 | EA58: 17.9 | EB58: 20.2 | EC58: 19.9 | ED58: 28.3 | EE58: 40.3 | EF58: 0 | EG58: 80.2 | EH58: 104.5 | EI58: 8.6 | EJ58: 6.4 | EK58: 21 | EL58: 7.9 | EM58: 7.8 | EN58: 20.4 | EO58: 20.4 | EP58: 20.2 | EQ58: 0 | ER58: 0 | ES58: 0 | ET58: 0 | EU58: 0.6 | EV58: 40.6 | EW58: 48.7 | EX58: 0 | EY58: 0 | EZ58: 8.8 | FA58: 19.9 | FC58: 43 | FD58: 32 | FE58: 29 | FF58: 3.2 | FG58: 16.2 | FJ58: 6671.12 | FL58: 23.31108 | FM58: 0 | FO58: 13.2 | FQ58: 9.43556 | FR58: 10.3 | FS58: 15.8 | FT58: 72.04664
A59: EJEC | C59: 0 | D59: 0 | E59: 679.245 | F59: 15029.5 | G59: 5001.4 | H59: 0 | I59: 0 | J59: 2014 | K59: 5564.05 | L59: 0 | M59: 0 | N59: 2795.45 | O59: 2789.75 | P59: 2792.45 | Q59: 5172.1 | R59: 3933.35 | S59: 2188.3 | T59: 13420.95 | U59: 250.45 | V59: 0 | W59: 0 | X59: 0 | Y59: 0 | Z59: 3955.4 | AA59: 177.6 | AB59: 83.4 | AC59: 0 | AD59: 160.6 | AE59: 244.35 | AF59: 2156.8 | AG59: 141.6 | AH59: 0 | AI59: 0 | AJ59: 0 | AK59: 2656.3 | AL59: 4993.45 | AM59: 0 | AN59: 0 | AO59: 0 | AP59: 155.3 | AQ59: 10824.75 | AR59: 1963.7 | AS59: 3392 | AT59: 1011.55 | AU59: 448.05 | AV59: 472.8 | AW59: 2169.55 | AX59: 1681.25 | AY59: 164.85 | AZ59: 0 | BA59: 2603.6 | BB59: 110.3 | BC59: 150.55 | BD59: 1114.45 | BE59: 314.45 | BF59: 49.4 | BG59: 905.9 | BH59: 4176.85 | BI59: 822.85 | BJ59: 0 | BK59: 0 | BL59: 968.4 | BM59: 0 | BN59: 0 | BO59: 0 | BP59: 2071.25 | BQ59: 3586.1 | BR59: 0 | BS59: 4035 | BT59: 3889.4 | BU59: 0 | BV59: 0 | BW59: 0 | BX59: 0 | BY59: 0 | BZ59: 0 | CA59: 0 | CB59: 0 | CC59: 110.4 | CD59: 2947.4 | CE59: 3114.95 | CF59: 1514.35 | CG59: 1900.7 | CH59: 725.65 | CI59: 0 | CJ59: 0 | CK59: 0 | CL59: 2647 | CM59: 2655 | CN59: 2995.7 | CO59: 0 | CP59: 0 | CQ59: 372.85 | CR59: 0 | CS59: 0 | CT59: 0 | CU59: 0 | CV59: 9.05 | CW59: 2367.55 | CX59: 575.8 | CY59: 22.8 | CZ59: 2.1 | DA59: 479.65 | DB59: 237.35 | DC59: 126.65 | DD59: 28.8 | DE59: 79.05 | DF59: 118 | DG59: 486.85 | DH59: 480 | DI59: 458.25 | DJ59: 85.95 | DK59: 222.75 | DL59: 87.25 | DM59: 103.1 | DN59: 552.4 | DO59: 1535.9 | DP59: 108.55 | DQ59: 57.6 | DR59: 50.5 | DS59: 0 | DT59: 133.6 | DU59: 75.5 | DV59: 283.4 | DW59: 74 | DX59: 0 | DY59: 475.3 | DZ59: 225.25 | EA59: 437 | EB59: 486.5 | EC59: 478.45 | ED59: 562.45 | EE59: 1254.4 | EF59: 303.9 | EG59: 1747.4 | EH59: 1985.75 | EI59: 244.55 | EJ59: 136.55 | EK59: 504 | EL59: 187.35 | EM59: 171.5 | EN59: 489.6 | EO59: 489.6 | EP59: 484.8 | EQ59: 20.25 | ER59: 1783.075 | ES59: 105.6 | ET59: 903.15 | EU59: 14.4 | EV59: 1819.45 | EW59: 1981.1 | EX59: 670.5 | EY59: 123.65 | EZ59: 209.1 | FA59: 478.8 | FB59: 0 | FC59: 1020.2 | FD59: 758.7 | FE59: 694.3 | FF59: 77.5 | FG59: 359.3 | FH59: 0 | FI59: 0 | FJ59: 172792.62 | FL59: 559.07709 | FM59: 58.275 | FN59: 0 | FO59: 316.8 | FP59: 0 | FQ59: 205.25288 | FR59: 239.7 | FS59: 376.8 | FT59: 1755.905

Sheet REACTIVA
B3: martes, 22 de Abril del 2025
A5: POTENCIA REACTIVA EJECUTADA DE LAS UNIDADES DE GENERACIÓN DEL COES (MVAR) | FK5: CENTRALES NO INTEGRANTES COES
A6: FECHA | B6: HORA | C6: 337 | D6: 338 | E6: 65333 | F6: 101 | G6: 102 | H6: 42667 | I6: 42668 | J6: 126 | K6: 127 | L6: 138 | M6: 139 | N6: 197 | O6: 203 | P6: 204 | Q6: 230 | R6: 209 | S6: 56677 | T6: 796 | U6: 2146 | V6: 142 | W6: 143 | X6: 125 | Y6: 187 | Z6: 163 | AA6: 298 | AB6: 219 | AC6: 151 | AD6: 152 | AE6: 153 | AF6: 154 | AG6: 756 | AH6: 156 | AI6: 155 | AJ6: 182 | AK6: 212 | AL6: 758 | AM6: 263 | AN6: 265 | AO6: 775 | AP6: 777 | AQ6: 2154 | AR6: 150 | AS6: 149 | AT6: 188 | AU6: 2131 | AV6: 755 | AW6: 252 | AX6: 249 | AY6: 250 | AZ6: 117 | BA6: 267 | BB6: 268 | BC6: 119 | BD6: 120 | BE6: 189 | BF6: 122 | BG6: 266 | BH6: 251 | BI6: 115 | BJ6: 239 | BK6: 288 | BL6: 240 | BM6: 241 | BN6: 242 | BO6: 191 | BP6: 194 | BQ6: 196 | BR6: 207 | BS6: 236 | BT6: 795 | BU6: 285 | BV6: 995 | BW6: 996 | BX6: 997 | BY6: 766 | BZ6: 926 | CA6: 924 | CB6: 121 | CC6: 103 | CD6: 104 | CE6: 106 | CF6: 105 | CG6: 107 | CH6: 110 | CI6: 109 | CJ6: 144 | CK6: 113 | CL6: 114 | CM6: 193 | CN6: 208 | CO6: 786 | CP6: 787 | CQ6: 788 | CR6: 789 | CS6: 248 | CT6: 2159 | CU6: 303 | CV6: 59715 | CW6: 62255 | CX6: 1263 | CY6: 61800 | CZ6: 2194 | DA6: 216 | DB6: 198 | DC6: 49607 | DD6: 214 | DE6: 260 | DF6: 2152 | DG6: 2128 | DH6: 247 | DI6: 228 | DJ6: 2135 | DK6: 261 | DL6: 237 | DM6: 253 | DN6: 770 | DO6: 225 | DP6: 2201 | DQ6: 2171 | DR6: 760 | DS6: 235 | DT6: 238 | DU6: 2184 | DV6: 61855 | DW6: 223 | DX6: 226 | DY6: 201 | DZ6: 258 | EA6: 259 | EB6: 920 | EC6: 257 | ED6: 256 | EE6: 2148 | EF6: 58288 | EG6: 58289 | EH6: 58839 | EI6: 58840 | EJ6: 296 | EK6: 297 | EL6: 211 | EM6: 2175 | EN6: 2178 | EO6: 2181 | EP6: 1262 | EQ6: 63425 | ER6: 233 | ES6: 2150 | ET6: 2165 | EU6: 2161 | EV6: 61197 | EW6: 58851 | EX6: 234 | EY6: 215 | EZ6: 917 | FA6: 289 | FB6: 58333 | FC6: 58336 | FD6: 202 | FE6: 58487 | FF6: 213 | FG6: 232 | FH6: 2190 | FI6: TOTAL COES | FK6: 221 | FL6: 222 | FM6: 224 | FN6: 2187 | FO6: 227 | FP6: 49400 | FQ6: 199 | FR6: 200 | FS6: TOTAL NO COES
C7: CENTRO | D7: CENTRO | E7: SUR | F7: CENTRO | G7: CENTRO | H7: NORTE | I7: NORTE | J7: NORTE | K7: NORTE | L7: CENTRO | M7: CENTRO | N7: CENTRO | O7: CENTRO | P7: CENTRO | Q7: CENTRO | R7: CENTRO | S7: CENTRO | T7: CENTRO | U7: CENTRO | V7: CENTRO | W7: CENTRO | X7: CENTRO | Y7: CENTRO | Z7: SUR | AA7: SUR | AB7: CENTRO | AC7: SUR | AD7: SUR | AE7: SUR | AF7: SUR | AG7: SUR | AH7: SUR | AI7: SUR | AJ7: SUR | AK7: CENTRO | AL7: NORTE | AM7: NORTE | AN7: NORTE | AO7: CENTRO | AP7: CENTRO | AQ7: CENTRO | AR7: CENTRO | AS7: CENTRO | AT7: CENTRO | AU7: CENTRO | AV7: SUR | AW7: CENTRO | AX7: CENTRO | AY7: CENTRO | AZ7: CENTRO | BA7: CENTRO | BB7: CENTRO | BC7: CENTRO | BD7: CENTRO | BE7: SUR | BF7: NORTE | BG7: CENTRO | BH7: CENTRO | BI7: NORTE | BJ7: NORTE | BK7: NORTE | BL7: SUR | BM7: SUR | BN7: SUR | BO7: CENTRO | BP7: CENTRO | BQ7: CENTRO | BR7: CENTRO | BS7: CENTRO | BT7: CENTRO | BU7: CENTRO | BV7: SUR | BW7: SUR | BX7: SUR | BY7: NORTE | BZ7: SUR | CA7: CENTRO | CB7: NORTE | CC7: CENTRO | CD7: CENTRO | CE7: CENTRO | CF7: CENTRO | CG7: CENTRO | CH7: CENTRO | CI7: CENTRO | CJ7: CENTRO | CK7: CENTRO | CL7: CENTRO | CM7: CENTRO | CN7: CENTRO | CO7: SUR | CP7: SUR | CQ7: SUR | CR7: SUR | CS7: CENTRO | CT7: CENTRO | CU7: CENTRO | CV7: CENTRO | CW7: SUR | CX7: NORTE | CY7: NORTE | CZ7: NORTE | DA7: NORTE | DB7: NORTE | DC7: SUR | DD7: CENTRO | DE7: CENTRO | DF7: CENTRO | DG7: NORTE | DH7: NORTE | DI7: CENTRO | DJ7: CENTRO | DK7: SUR | DL7: SUR | DM7: CENTRO | DN7: CENTRO | DO7: CENTRO | DP7: CENTRO | DQ7: CENTRO | DR7: CENTRO | DS7: SUR | DT7: CENTRO | DU7: CENTRO | DV7: NORTE | DW7: CENTRO | DX7: CENTRO | DY7: NORTE | DZ7: CENTRO | EA7: CENTRO | EB7: CENTRO | EC7: NORTE | ED7: NORTE | EE7: SUR | EF7: CENTRO | EG7: CENTRO | EH7: CENTRO | EI7: CENTRO | EJ7: CENTRO | EK7: CENTRO | EL7: SUR | EM7: SUR | EN7: SUR | EO7: SUR | EP7: NORTE | EQ7: SUR | ER7: SUR | ES7: SUR | ET7: CENTRO | EU7: CENTRO | EV7: CENTRO | EW7: SUR | EX7: SUR | EY7: NORTE | EZ7: CENTRO | FA7: NORTE | FB7: NORTE | FC7: NORTE | FD7: CENTRO | FE7: CENTRO | FF7: CENTRO | FG7: NORTE | FH7: NORTE | FK7: NORTE | FL7: CENTRO | FM7: NORTE | FN7: NORTE | FO7: NORTE | FP7: NORTE | FQ7: NORTE | FR7: NORTE
C8: HIDROELÉCTRICA | D8: HIDROELÉCTRICA | E8: HIDROELÉCTRICA | F8: HIDROELÉCTRICA | G8: HIDROELÉCTRICA | H8: TERMOELÉCTRICA | I8: TERMOELÉCTRICA | J8: HIDROELÉCTRICA | K8: HIDROELÉCTRICA | L8: TERMOELÉCTRICA | M8: TERMOELÉCTRICA | N8: TERMOELÉCTRICA | O8: TERMOELÉCTRICA | P8: TERMOELÉCTRICA | Q8: TERMOELÉCTRICA | R8: TERMOELÉCTRICA | S8: TERMOELÉCTRICA | T8: HIDROELÉCTRICA | U8: HIDROELÉCTRICA | V8: TERMOELÉCTRICA | W8: TERMOELÉCTRICA | X8: TERMOELÉCTRICA | Y8: TERMOELÉCTRICA | Z8: HIDROELÉCTRICA | AA8: HIDROELÉCTRICA | AB8: TERMOELÉCTRICA | AC8: HIDROELÉCTRICA | AD8: HIDROELÉCTRICA | AE8: HIDROELÉCTRICA | AF8: HIDROELÉCTRICA | AG8: TERMOELÉCTRICA | AH8: TERMOELÉCTRICA | AI8: TERMOELÉCTRICA | AJ8: HIDROELÉCTRICA | AK8: HIDROELÉCTRICA | AL8: TERMOELÉCTRICA | AM8: TERMOELÉCTRICA | AN8: TERMOELÉCTRICA | AO8: HIDROELÉCTRICA | AP8: HIDROELÉCTRICA | AQ8: HIDROELÉCTRICA | AR8: HIDROELÉCTRICA | AS8: HIDROELÉCTRICA | AT8: HIDROELÉCTRICA | AU8: HIDROELÉCTRICA | AV8: HIDROELÉCTRICA | AW8: TERMOELÉCTRICA | AX8: TERMOELÉCTRICA | AY8: TERMOELÉCTRICA | AZ8: HIDROELÉCTRICA | BA8: HIDROELÉCTRICA | BB8: HIDROELÉCTRICA | BC8: HIDROELÉCTRICA | BD8: HIDROELÉCTRICA | BE8: HIDROELÉCTRICA | BF8: HIDROELÉCTRICA | BG8: HIDROELÉCTRICA | BH8: HIDROELÉCTRICA | BI8: TERMOELÉCTRICA | BJ8: TERMOELÉCTRICA | BK8: TERMOELÉCTRICA | BL8: TERMOELÉCTRICA | BM8: TERMOELÉCTRICA | BN8: TERMOELÉCTRICA | BO8: HIDROELÉCTRICA | BP8: TERMOELÉCTRICA | BQ8: TERMOELÉCTRICA | BR8: TERMOELÉCTRICA | BS8: TERMOELÉCTRICA | BT8: TERMOELÉCTRICA | BU8: TERMOELÉCTRICA | BV8: TERMOELÉCTRICA | BW8: TERMOELÉCTRICA | BX8: TERMOELÉCTRICA | BY8: HIDROELÉCTRICA | BZ8: TERMOELÉCTRICA | CA8: TERMOELÉCTRICA | CB8: HIDROELÉCTRICA | CC8: HIDROELÉCTRICA | CD8: HIDROELÉCTRICA | CE8: HIDROELÉCTRICA | CF8: HIDROELÉCTRICA | CG8: HIDROELÉCTRICA | CH8: TERMOELÉCTRICA | CI8: TERMOELÉCTRICA | CJ8: TERMOELÉCTRICA | CK8: TERMOELÉCTRICA | CL8: TERMOELÉCTRICA | CM8: TERMOELÉCTRICA | CN8: TERMOELÉCTRICA | CO8: TERMOELÉCTRICA | CP8: TERMOELÉCTRICA | CQ8: TERMOELÉCTRICA | CR8: TERMOELÉCTRICA | CS8: TERMOELÉCTRICA | CT8: TERMOELÉCTRICA | CU8: SOLAR | CV8: EÓLICA | CW8: SOLAR | CX8: EÓLICA | CY8: SOLAR | CZ8: HIDROELÉCTRICA | DA8: HIDROELÉCTRICA | DB8: HIDROELÉCTRICA | DC8: HIDROELÉCTRICA | DD8: HIDROELÉCTRICA | DE8: HIDROELÉCTRICA | DF8: HIDROELÉCTRICA | DG8: HIDROELÉCTRICA | DH8: HIDROELÉCTRICA | DI8: HIDROELÉCTRICA | DJ8: HIDROELÉCTRICA | DK8: SOLAR | DL8: SOLAR | DM8: EÓLICA | DN8: EÓLICA | DO8: TERMOELÉCTRICA | DP8: TERMOELÉCTRICA | DQ8: TERMOELÉCTRICA | DR8: TERMOELÉCTRICA | DS8: SOLAR | DT8: HIDROELÉCTRICA | DU8: HIDROELÉCTRICA | DV8: HIDROELÉCTRICA | DW8: HIDROELÉCTRICA | DX8: HIDROELÉCTRICA | DY8: HIDROELÉCTRICA | DZ8: HIDROELÉCTRICA | EA8: HIDROELÉCTRICA | EB8: HIDROELÉCTRICA | EC8: EÓLICA | ED8: EÓLICA | EE8: SOLAR | EF8: EÓLICA | EG8: EÓLICA | EH8: EÓLICA | EI8: EÓLICA | EJ8: HIDROELÉCTRICA | EK8: HIDROELÉCTRICA | EL8: HIDROELÉCTRICA | EM8: HIDROELÉCTRICA | EN8: HIDROELÉCTRICA | EO8: HIDROELÉCTRICA | EP8: EÓLICA | EQ8: SOLAR | ER8: SOLAR | ES8: SOLAR | ET8: HIDROELÉCTRICA | EU8: EÓLICA | EV8: EÓLICA | EW8: SOLAR | EX8: SOLAR | EY8: HIDROELÉCTRICA | EZ8: HIDROELÉCTRICA | FA8: TERMOELÉCTRICA | FB8: TERMOELÉCTRICA | FC8: TERMOELÉCTRICA | FD8: TERMOELÉCTRICA | FE8: TERMOELÉCTRICA | FF8: TERMOELÉCTRICA | FG8: TERMOELÉCTRICA | FH8: TERMOELÉCTRICA | FK8: HIDROELÉCTRICA | FL8: HIDROELÉCTRICA | FM8: HIDROELÉCTRICA | FN8: HIDROELÉCTRICA | FO8: TERMOELÉCTRICA | FP8: TERMOELÉCTRICA | FQ8: HIDROELÉCTRICA | FR8: HIDROELÉCTRICA
C9: CENTRALES SANTA ROSA S.A.C. | D9: CENTRALES SANTA ROSA S.A.C. | E9: HYDRO GLOBAL PERÚ S.A.C. | F9: ELECTROPERU | G9: ELECTROPERU | H9: ELECTROPERU | I9: ELECTROPERU | J9: ORAZUL ENERGY PERÚ | K9: ORAZUL ENERGY PERÚ | L9: TERMOSELVA | M9: TERMOSELVA | N9: KALLPA GENERACION S.A. | O9: KALLPA GENERACION S.A. | P9: KALLPA GENERACION S.A. | Q9: KALLPA GENERACION S.A. | R9: KALLPA GENERACION S.A. | S9: KALLPA GENERACION S.A. | T9: KALLPA GENERACION S.A. | U9: KALLPA GENERACION S.A. | V9: SHOUGESA | W9: SHOUGESA | X9: SHOUGESA | Y9: SHOUGESA | Z9: EGEMSA | AA9: EGESUR | AB9: EGESUR | AC9: EGASA | AD9: EGASA | AE9: EGASA | AF9: EGASA | AG9: EGASA | AH9: EGASA | AI9: EGASA | AJ9: SAN GABAN | AK9: CELEPSA | AL9: MINERA CERRO VERDE | AM9: PLANTA DE RESERVA FRIA DE GENERACION DE ETEN S.A. | AN9: PLANTA DE RESERVA FRIA DE GENERACION DE ETEN S.A. | AO9: EMPRESA DE GENERACION HUALLAGA | AP9: EMPRESA DE GENERACION HUALLAGA | AQ9: LA VIRGEN | AR9: CHINANGO S.A.C. | AS9: CHINANGO S.A.C. | AT9: HIDROELECTRICA HUANCHOR S.A.C. | AU9: CELEPSA RENOVABLES S.R.L. | AV9: INLAND ENERGY SAC | AW9: FENIX POWER PERÚ | AX9: FENIX POWER PERÚ | AY9: FENIX POWER PERÚ | AZ9: STATKRAFT S.A | BA9: STATKRAFT S.A | BB9: STATKRAFT S.A | BC9: STATKRAFT S.A | BD9: STATKRAFT S.A | BE9: STATKRAFT S.A | BF9: STATKRAFT S.A | BG9: STATKRAFT S.A | BH9: EMPRESA DE GENERACION HUANZA | BI9: ENEL GENERACION PIURA S.A. | BJ9: ENEL GENERACION PIURA S.A. | BK9: ENEL GENERACION PIURA S.A. | BL9: ENGIE | BM9: ENGIE | BN9: ENGIE | BO9: ENGIE | BP9: ENGIE | BQ9: ENGIE | BR9: ENGIE | BS9: ENGIE | BT9: ENGIE | BU9: ENGIE | BV9: ENGIE | BW9: ENGIE | BX9: ENGIE | BY9: ENGIE | BZ9: INFRAESTRUCTURAS Y ENERGIAS DEL PERU S.A.C. | CA9: INFRAESTRUCTURAS Y ENERGIAS DEL PERU S.A.C. | CB9: INVERSIONES SHAQSHA S.A.C. | CC9: ORYGEN PERU S.A.A. | CD9: ORYGEN PERU S.A.A. | CE9: ORYGEN PERU S.A.A. | CF9: ORYGEN PERU S.A.A. | CG9: ORYGEN PERU S.A.A. | CH9: ORYGEN PERU S.A.A. | CI9: ORYGEN PERU S.A.A. | CJ9: ORYGEN PERU S.A.A. | CK9: ORYGEN PERU S.A.A. | CL9: ORYGEN PERU S.A.A. | CM9: ORYGEN PERU S.A.A. | CN9: ORYGEN PERU S.A.A. | CO9: SAMAY I S.A.C | CP9: SAMAY I S.A.C | CQ9: SAMAY I S.A.C | CR9: SAMAY I S.A.C | CS9: TERMOCHILCA S.A.C. | CT9: TERMOCHILCA S.A.C. | CU9: COLCA SOLAR S.A.C. | CV9: ENERGIA RENOVABLE DEL SUR S.A. | CW9: GR CORTARRAMA SOCIEDAD ANONIMA CERRADA | CX9: GR TARUCA SOCIEDAD ANONIMA CERRADA | CY9: KONDU SAC | CZ9: PERUANA DE INVERSIONES EN ENERGIAS RENOVABLES S.A. | DA9: ORAZUL ENERGY PERÚ | DB9: ORAZUL ENERGY PERÚ | DC9: SAN GABAN | DD9: MAJA ENERGIA S.A.C. | DE9: EMPRESA DE GENERACION ELECTRICA CANCHAYLLO SAC | DF9: EMPRESA DE GENERACION ELECTRICA SANTA ANA S.A.C. | DG9: EMPRESA ELECTRICA AGUA AZUL | DH9: EMPRESA ELECTRICA RIO DOBLE | DI9: HIDROCAÑETE S.A. | DJ9: HUAURA POWER GROUP S.A. | DK9: MOQUEGUA FV S.A.C. | DL9: PANAMERICANA SOLAR SAC. | DM9: PARQUE EOLICO MARCONA S.A.C. | DN9: PARQUE EOLICO TRES HERMANAS S.A.C. | DO9: PETRAMAS | DP9: PETRAMAS | DQ9: PETRAMAS | DR9: PETRAMAS | DS9: TACNA SOLAR SAC. | DT9: ELECTRICA YANAPAMPA SAC | DU9: ANDEAN POWER S.A.C. | DV9: ASOCIACIÓN SANTA LUCIA DE CHACAS | DW9: ATRIA ENERGIA S.A.C. | DX9: EGEJUNIN | DY9: EGEJUNIN | DZ9: EGEJUNIN | EA9: EGEJUNIN | EB9: EMPRESA DE GENERACION ELECTRICA RIO BAÑOS S.A.C. | EC9: ENERGÍA EÓLICA S.A. | ED9: ENERGÍA EÓLICA S.A. | EE9: ENGIE | EF9: ENGIE | EG9: ENGIE | EH9: ENGIE | EI9: ENGIE | EJ9: GENERACIÓN ANDINA S.A.C. | EK9: GENERACIÓN ANDINA S.A.C. | EL9: GENERADORA DE ENERGÍA DEL PERÚ | EM9: GENERADORA DE ENERGÍA DEL PERÚ | EN9: GENERADORA DE ENERGÍA DEL PERÚ | EO9: GENERADORA DE ENERGÍA DEL PERÚ | EP9: GR PAINO SOCIEDAD ANONIMA CERRADA | EQ9: JOYA SOLAR S.A.C. | ER9: MAJES ARCUS S.A.C. | ES9: ORYGEN PERU S.A.A. | ET9: ORYGEN PERU S.A.A. | EU9: ORYGEN PERU S.A.A. | EV9: ORYGEN PERU S.A.A. | EW9: ORYGEN PERU S.A.A. | EX9: REPARTICIÓN ARCUS S.A.C. | EY9: SINERSA | EZ9: SINERSA | FA9: BIOENERGIA DEL CHIRA S.A. | FB9: GM OPERACIONES S.A.C. | FC9: GM OPERACIONES S.A.C. | FD9: SDF ENERGIA SAC | FE9: SDF ENERGIA SAC | FF9: AGRO INDUSTRIAL PARAMONGA S.A. | FG9: AGROAURORA S.A.C. | FH9: AGROINDUSTRIAS SAN JACINTO S.A.A. | FK9: UNACEM PERU S.A. | FL9: ELECTRO ORIENTE | FM9: AGUAS Y ENERGIA PERU | FN9: ELECTRO ZAÑA S.A.C. | FO9: ELECTRONOROESTE S.A. | FP9: SDE PIURA | FQ9: SINERSA | FR9: SINERSA
C10: SANTA ROSA 1 | D10: SANTA ROSA 2 | E10: SAN GABAN III | F10: MANTARO | G10: RESTITUCION | H10: TUMBES MAK 1 | I10: TUMBES MAK 2 | J10: CARHUAQUERO | K10: CAÑON DEL PATO | L10: AGUAYTIA TG1 | M10: AGUAYTIA TG2 | N10: KALLPA TG1 | O10: KALLPA TG2 | P10: KALLPA TG3 | Q10: KALLPA TV | R10: LFLORES TG1 | S10: LFLORES TV | T10: CERRO DEL AGUILA | U10: CERRODELAGUILAG4 | V10: SHOUGESA TV1 | W10: SHOUGESA TV2 | X10: SHOUGESA TV3 | Y10: SHOUGESA CUMMINS | Z10: MACHUPICCHU | AA10: ARICOTA 1 | AB10: INDEPENDENCIA | AC10: CHARCANI I,II,III | AD10: CHARCANI IV | AE10: CHARCANI V | AF10: CHARCANI VI | AG10: CHILINA TG | AH10: MOLLENDO 1, 2, 3 | AI10: CHILINA (SULZ 1,2) | AJ10: SAN GABAN II | AK10: PLATANAL | AL10: RECKA | AM10: RF ETEN TG1 | AN10: RF ETEN TG2 | AO10: CHAGLLA GP1 | AP10: CHAGLLA | AQ10: LA VIRGEN | AR10: CHIMAY | AS10: YANANGO | AT10: HUANCHOR | AU10: MARAÑON | AV10: STA TERESA | AW10: FENIX GT11 | AX10: FENIX GT12 | AY10: FENIX TV10 | AZ10: YAUPI | BA10: OROYA | BB10: PACHACHACA | BC10: MALPASO | BD10: CAHUA | BE10: ARCATA | BF10: GALLITO CIEGO | BG10: CHEVES | BH10: HUANZA | BI10: MALACAS2 TG4 | BJ10: MALACAS3 TG 5 | BK10: MALACAS1 TG6 | BL10: RF ILO2 TG1 | BM10: RF ILO2 TG2 | BN10: RF ILO2 TG3 | BO10: YUNCAN | BP10: CHILCA1 TG1 | BQ10: CHILCA1 TG2 | BR10: CHILCA1 TG3 | BS10: CHILCA-TV | BT10: CHILCA2 TG41 | BU10: CHILCA2-TV | BV10: CTNEPI_TG41 | BW10: CTNEPI_TG42 | BX10: CTNEPI_TG43 | BY10: QUITARACSA | BZ10: RF PTO MALDONADO | CA10: RF PUCALLPA | CB10: PARIAC | CC10: HUINCO | CD10: MATUCANA | CE10: MOYOPAMPA | CF10: CALLAHUANCA | CG10: HUAMPANI | CH10: STA ROSA WEST TG7 | CI10: UTI_5 | CJ10: UTI_6 | CK10: VENTANILLA 3 | CL10: VENTANILLA 4 | CM10: VENTANILLA TV | CN10: STAROSA TG8 | CO10: PTO_BRVO TG1 | CP10: PTO_BRVO TG2 | CQ10: PTO_BRVO TG3 | CR10: PTO_BRVO TG4 | CS10: OLLEROS TG1 | CT10: OLLEROS TV | CU10: CS YARUCAYA | CV10: SAN JUAN | CW10: MATARANI | CX10: DUNA | CY10: CARHUAQUERO (CS) | CZ10: MANTA I | DA10: CARHUAQUERO4 | DB10: CAÑA BRAVA | DC10: TUPURI | DD10: RONCADOR | DE10: CANCHAYLLO | DF10: RENOVANDESH1 | DG10: POTRERO | DH10: PIZARRAS | DI10: NIMPERIAL | DJ10: YARUCAYA | DK10: MOQUEGUA-SOLAR | DL10: PANAMERICANA-SOLAR | DM10: PQE-EOLICO-MARCONA | DN10: PQE-EOLICO-3-HERMANAS | DO10: HUAYCOLORO | DP10: CALLAO | DQ10: DONA_CATALINA | DR10: LAGRINGAV | DS10: TACNA-SOLAR | DT10: YANAPAMPA | DU10: CARHUAC | DV10: HUALLIN | DW10: PURMACANA | DX10: HUASAHUASI | DY10: STACRUZ_1_2 | DZ10: RUNATULLO_II | EA10: RUNATULLO_III | EB10: RUCUY | EC10: PQE-EOLICO-TALARA | ED10: PQE-EOLICO-CUPISNIQUE | EE10: INTIPAMPA | EF10: PUNTA LOMITAS-BL1 | EG10: PUNTA LOMITAS-BL2 | EH10: PUN LOMITAS_EXP-BL1 | EI10: PUN LOMITAS_EXP-BL2 | EJ10: 8AGOSTO | EK10: EL CARMEN | EL10: LA JOYA | EM10: ANGEL_I | EN10: ANGEL_II | EO10: ANGEL_III | EP10: HUAMBOS | EQ10: SAN MARTIN SOLAR | ER10: MAJES | ES10: RUBI | ET10: CH_HER1 | EU10: WAYRA-I | EV10: WAYRA EXTENSION | EW10: CLEMESI | EX10: REPARTICION | EY10: POECHOS2 | EZ10: CHANCAY | FA10: CANA BRAVA | FB10: REFINERIA TALARA TV1 | FC10: REFINERÍA TALARA TV2 | FD10: OQUENDO TG1 | FE10: OQUENDO TV1 | FF10: PARAMONGA | FG10: MAPLE | FH10: SAN_JACINTO | FI10: MVAR | FK10: CARPAPATA | FL10: CENTRALES ELOR | FM10: PIAS1 | FN10: ZANA | FO10: TABLAZO | FP10: TALLANCA | FQ10: CURUMUY | FR10: POECHOS1 | FS10: MVAR
A11: 22/04/2025 | B11: 00:30 | E11: 0 | F11: -2.3 | G11: 14.7 | J11: -11.1 | K11: 19.8 | N11: -31.7 | O11: -28.7 | P11: -18.9 | Q11: 1.1 | R11: -13.2 | S11: 0.7 | T11: 36.4 | U11: 0.2 | Z11: -10.4 | AA11: 0.5 | AC11: -3.3 | AD11: 3.2 | AE11: 2 | AF11: 0.8 | AJ11: 6.9 | AK11: 11.1 | AO11: -1.4 | AP11: 5.2 | AQ11: 10.3 | AR11: 1.8 | AS11: -1.1 | AT11: 0.9 | AU11: 2.7 | AV11: 0.9 | AW11: 0 | AX11: -43.3 | AZ11: 5.5 | BA11: -2.1 | BB11: 0.2 | BC11: -4.4 | BD11: 1.8 | BE11: 0 | BF11: -0.1 | BG11: -4.4 | BK11: -3.7 | BO11: -1.1 | BP11: -25.8 | BR11: -31.9 | BS11: -20.2 | CB11: -0.5 | CC11: 17.8 | CD11: 21.1 | CE11: -1.8 | CF11: 0.8 | CG11: -8.1 | CK11: 7 | CL11: 10.1 | CM11: -23.9 | CP11: 0 | CV11: -2.8 | CW11: 0 | CX11: 0 | CZ11: 1.4 | DA11: 0 | DB11: -0.4 | DD11: 0 | DE11: 1.3 | DF11: 2.1 | DG11: -1.4 | DH11: 1.3 | DI11: 0.6 | DJ11: 0 | DK11: 0 | DL11: 0 | DM11: -0.3 | DN11: 3.8 | DO11: 1.8 | DP11: 0.5 | DQ11: 0.8 | DS11: 0 | DT11: -0.2 | DU11: 0.2 | DV11: 0.1 | DX11: -4.5 | DY11: 0.7 | DZ11: 2.6 | EA11: 2.2 | EB11: 1.3 | EC11: 0.8 | ED11: 4 | EE11: 0 | EF11: -10.9 | EG11: -11.4 | EH11: 0 | EI11: 0 | EJ11: 2.6 | EK11: 0 | EL11: 1.2 | EM11: 0.2 | EN11: 0.2 | EO11: 0.2 | EP11: 0 | ER11: 0 | ES11: 0 | ET11: 0 | EU11: 0.5 | EV11: 2.1 | EW11: 0 | EX11: 0 | EY11: 0.2 | EZ11: 1.6 | FB11: 9.2 | FC11: 5.4 | FD11: 1.7 | FE11: 2 | FF11: 4 | FI11: -85.2 | FL11: 0 | FN11: 1.7 | FP11: 1.92638 | FQ11: 1 | FR11: 1.9 | FS11: 6.52638
A12: 22/04/2025 | B12: 01:00 | E12: 0 | F12: 27 | G12: 21.1 | J12: -10.8 | K12: 10.6 | N12: -28.3 | O12: -23.7 | P12: -13.7 | Q12: 6.4 | R12: -12.3 | S12: 1.1 | T12: 56.3 | U12: 0.1 | Z12: -7.8 | AA12: 0.9 | AC12: -3.3 | AD12: 3.4 | AE12: 4.5 | AF12: 0.8 | AJ12: 7.9 | AK12: 14 | AO12: -1.2 | AP12: 55.7 | AQ12: 12.4 | AR12: 0.8 | AS12: -1.3 | AT12: 1.2 | AU12: 2.7 | AV12: 2 | AW12: 0 | AX12: -41.3 | AZ12: 9.1 | BA12: -1.9 | BB12: 0.4 | BC12: -1.6 | BD12: 1.9 | BE12: 0 | BF12: -0.1 | BG12: -4.1 | BK12: -3.2 | BO12: 9.7 | BP12: -25.8 | BR12: -32.1 | BS12: -20.3 | CB12: -0.4 | CC12: 9.9 | CD12: 21.6 | CE12: -0.5 | CF12: 0.8 | CG12: -8 | CK12: 9.1 | CL12: 12.4 | CM12: -20.5 | CP12: 0 | CV12: -2.8 | CW12: 0 | CX12: 0 | CZ12: 1.4 | DA12: 0 | DB12: -0.3 | DD12: 0.2 | DE12: 1.5 | DF12: 2.2 | DG12: -1.2 | DH12: 1.3 | DI12: 0.5 | DJ12: 0.1 | DK12: 0 | DL12: 0 | DM12: 1.2 | DN12: 7.5 | DO12: 1.8 | DP12: 0.5 | DQ12: 0.8 | DS12: 0 | DT12: -0.1 | DU12: 0.3 | DV12: 0.1 | DX12: -4.6 | DY12: 0.9 | DZ12: 2.4 | EA12: 2.2 | EB12: 1.7 | EC12: 0.8 | ED12: 4 | EE12: 0 | EF12: -2.6 | EG12: -2.8 | EH12: 0.7 | EI12: 0.5 | EJ12: 2.6 | EK12: 0 | EL12: 1.2 | EM12: 0.2 | EN12: 0.2 | EO12: 0.2 | EP12: 0 | ER12: 0 | ES12: 0 | ET12: 0 | EU12: -0.4 | EV12: 1.5 | EW12: 0 | EX12: 0 | EY12: 0.2 | EZ12: 2 | FB12: 9.4 | FC12: 5.7 | FD12: 1.7 | FE12: 2.1 | FF12: 3.9 | FI12: 90.3 | FL12: 0 | FN12: 1.7 | FP12: 1.91963 | FQ12: 1.2 | FR12: 1.9 | FS12: 6.71963
A13: 22/04/2025 | B13: 01:30 | E13: 0 | F13: 25.9 | G13: 20.3 | J13: -9.5 | K13: 23.3 | N13: -28.7 | O13: -26.3 | P13: -16.9 | Q13: 4.7 | R13: -11.8 | S13: 1.7 | T13: 57.1 | U13: 0.1 | Z13: -5.2 | AA13: 0.8 | AC13: -3.3 | AD13: 3.3 | AE13: 4.7 | AF13: 0.9 | AJ13: 8.3 | AK13: 13.6 | AO13: -1.3 | AP13: 31.3 | AQ13: 12.1 | AR13: 1.5 | AS13: -1.2 | AT13: 0.9 | AU13: 2.7 | AV13: 1.2 | AW13: 0 | AX13: -40.9 | AZ13: 9.8 | BA13: -1.9 | BB13: 0.3 | BC13: -2.3 | BD13: 2.4 | BE13: 0 | BF13: -0.2 | BG13: -4.6 | BK13: -1.2 | BO13: 9.7 | BP13: -25.6 | BR13: -31.8 | BS13: -19.1 | CB13: -0.4 | CC13: 9.9 | CD13: 23.1 | CE13: 0.1 | CF13: 0.8 | CG13: -7.9 | CK13: 8.8 | CL13: 11.8 | CM13: -21.2 | CP13: 0 | CV13: -3.2 | CW13: 0 | CX13: 0 | CZ13: 1.4 | DA13: -0.1 | DB13: -0.3 | DD13: 0.1 | DE13: 1.5 | DF13: 2.2 | DG13: -1.8 | DH13: 1.3 | DI13: 0.5 | DJ13: 0 | DK13: 0 | DL13: 0 | DM13: 1.2 | DN13: 7.4 | DO13: 1.8 | DP13: 0.5 | DQ13: 0.8 | DS13: 0 | DT13: -0.2 | DU13: 0.3 | DV13: 0.1 | DX13: -4.6 | DY13: 0.6 | DZ13: 2.3 | EA13: 2.2 | EB13: 1.7 | EC13: 0.8 | ED13: 4 | EE13: 0 | EF13: -4.6 | EG13: -5.5 | EH13: 0.1 | EI13: 0.1 | EJ13: 2.6 | EK13: 0 | EL13: 1.1 | EM13: 0.2 | EN13: 0.2 | EO13: 0.2 | EP13: 0 | ER13: 0 | ES13: 0 | ET13: -0.2 | EU13: -0.9 | EV13: 1.3 | EW13: 0 | EX13: 0 | EY13: 0.2 | EZ13: 2 | FB13: 9.9 | FC13: 6.2 | FD13: 1.8 | FE13: 1.9 | FF13: 3.6 | FI13: 70.5 | FL13: 0 | FN13: 1.6 | FP13: 1.91822 | FQ13: 1.5 | FR13: 2 | FS13: 7.01822
A14: 22/04/2025 | B14: 02:00 | E14: 0 | F14: 1.6 | G14: 15.2 | J14: -10.3 | K14: 11.3 | N14: -27.9 | O14: -42.4 | P14: -34.1 | Q14: 8 | R14: -12.9 | S14: 1.6 | T14: 57.1 | U14: -0.6 | Z14: -10.6 | AA14: 0.6 | AC14: -3.3 | AD14: 3.3 | AE14: 4.8 | AF14: 0.9 | AJ14: 5.9 | AK14: 13.7 | AO14: -1.2 | AP14: 59.7 | AQ14: 12.7 | AR14: 2.7 | AS14: -0.2 | AT14: 1.4 | AU14: 2.7 | AV14: -0.8 | AW14: 0 | AX14: -41.7 | AZ14: 8.1 | BA14: -1.8 | BB14: 0.4 | BC14: -8.3 | BD14: -0.9 | BE14: 0 | BF14: -0.1 | BG14: -15.5 | BK14: -4.2 | BO14: 10.2 | BP14: -25.7 | BR14: -32.8 | BS14: -22.8 | CB14: -0.4 | CC14: 10.3 | CD14: 23.3 | CE14: 1.1 | CF14: 0.6 | CG14: -8 | CK14: 8 | CL14: 11.7 | CM14: -23 | CP14: 0 | CV14: -3.6 | CW14: 0 | CX14: 0 | CZ14: 1.4 | DA14: -0.1 | DB14: -0.3 | DD14: 0.2 | DE14: 1.5 | DF14: 2.2 | DG14: -1.6 | DH14: 1.3 | DI14: 0.6 | DJ14: 0.1 | DK14: 0 | DL14: 0 | DM14: 0.8 | DN14: 6.6 | DO14: 1.8 | DP14: 0.5 | DQ14: 0.8 | DS14: 0 | DT14: 0 | DU14: 0.3 | DV14: 0.1 | DX14: -4.6 | DY14: 0.7 | DZ14: 2.1 | EA14: 2.2 | EB14: 1.5 | EC14: 0.8 | ED14: 4 | EE14: 0 | EF14: -7.7 | EG14: -9.1 | EH14: 0 | EI14: 0 | EJ14: 2.6 | EK14: 0 | EL14: 1.1 | EM14: 0.2 | EN14: 0.2 | EO14: 0.2 | EP14: 0 | ER14: 0 | ES14: 0 | ET14: -0.1 | EU14: 1.1 | EV14: 1.6 | EW14: 0 | EX14: 0 | EY14: 0.2 | EZ14: 1.9 | FB14: 10 | FC14: 6.1 | FD14: 1.8 | FE14: 1.9 | FF14: 3.9 | FI14: -17.4 | FL14: 0 | FN14: 1.8 | FP14: 1.91811 | FQ14: 1.6 | FR14: 2.3 | FS14: 7.61811
A15: 22/04/2025 | B15: 02:30 | E15: 0 | F15: 18 | G15: 20.4 | J15: -12.7 | K15: 6.8 | N15: -31.1 | O15: -30 | P15: -20.2 | Q15: 4.2 | R15: -14.7 | S15: -0.3 | T15: 63.1 | U15: -0.2 | Z15: -8.4 | AA15: 0.3 | AC15: -3.3 | AD15: 3.3 | AE15: 4.8 | AF15: 0.9 | AJ15: 8 | AK15: 13.7 | AO15: -1.3 | AP15: 59.1 | AQ15: 12.7 | AR15: -2.1 | AS15: -0.6 | AT15: 1.4 | AU15: 2.7 | AV15: 0.4 | AW15: 0 | AX15: -42.5 | AZ15: 8.9 | BA15: -1.7 | BB15: 0.5 | BC15: -3.7 | BD15: 0.8 | BE15: 0 | BF15: -0.1 | BG15: -4.8 | BK15: -4.1 | BO15: 10.6 | BP15: -25.7 | BR15: -33 | BS15: -21.7 | CB15: -0.5 | CC15: 11.4 | CD15: 19.6 | CE15: -1.5 | CF15: 0.9 | CG15: -7.8 | CK15: 7.7 | CL15: 10.1 | CM15: -21.6 | CP15: 0 | CV15: -4 | CW15: 0 | CX15: 0 | CZ15: 1.4 | DA15: 0 | DB15: -0.3 | DD15: 0 | DE15: 1.5 | DF15: 2.3 | DG15: -1.6 | DH15: 1.3 | DI15: 0.6 | DJ15: 0.1 | DK15: 0 | DL15: 0 | DM15: 0.2 | DN15: 5 | DO15: 1.8 | DP15: 0.5 | DQ15: 0.8 | DS15: 0 | DT15: -0.2 | DU15: 0.3 | DV15: 0.1 | DX15: -4.7 | DY15: 0.6 | DZ15: 2.3 | EA15: 2.2 | EB15: 1.6 | EC15: 0.8 | ED15: 4 | EE15: 0 | EF15: -6.8 | EG15: -7.4 | EH15: 0 | EI15: 0 | EJ15: 2.6 | EK15: 0 | EL15: 1.2 | EM15: 0.2 | EN15: 0.2 | EO15: 0.2 | EP15: 0 | ER15: 0 | ES15: 0 | ET15: -0.1 | EU15: 2.5 | EV15: 2.5 | EW15: 0 | EX15: 0 | EY15: 0.2 | EZ15: 1.9 | FB15: 9.9 | FC15: 6 | FD15: 1.8 | FE15: 1.9 | FF15: 3.3 | FI15: 33.4 | FL15: 0 | FN15: 1.7 | FP15: 1.92077 | FQ15: 1.3 | FR15: 2 | FS15: 6.92077
A16: 22/04/2025 | B16: 03:00 | E16: 0 | F16: 16.8 | G16: 18.8 | J16: -12.3 | K16: 7 | N16: -31.3 | O16: -29.9 | P16: -20.4 | Q16: 1.7 | R16: -15.7 | S16: -0.5 | T16: 54.6 | U16: 0 | Z16: -6.9 | AA16: 0.7 | AC16: -3.3 | AD16: 3.3 | AE16: 4.8 | AF16: 0.9 | AJ16: 7 | AK16: 13.1 | AO16: -1.4 | AP16: 41.5 | AQ16: 12.1 | AR16: 0.6 | AS16: -0.7 | AT16: 1.7 | AU16: 2.7 | AV16: 0.3 | AW16: 0 | AX16: -45.4 | AZ16: 9.2 | BA16: -1.9 | BB16: 0.5 | BC16: -3.5 | BD16: 1.5 | BE16: 0 | BF16: -0.1 | BG16: -5.9 | BK16: -7.7 | BO16: 6 | BP16: -28.4 | BR16: -35.1 | BS16: -24.6 | CB16: -0.4 | CC16: 9.7 | CD16: 22.3 | CE16: -0.3 | CF16: 0.8 | CG16: -8 | CK16: 4.1 | CL16: 7.2 | CM16: -27.7 | CP16: 0 | CV16: -4 | CW16: 0 | CX16: 0.2 | CZ16: 1.4 | DA16: 0 | DB16: -0.3 | DD16: 0 | DE16: 1.5 | DF16: 2.2 | DG16: -1.6 | DH16: 1.3 | DI16: 0.5 | DJ16: 0.1 | DK16: 0 | DL16: 0 | DM16: 0.4 | DN16: 5.6 | DO16: 1.8 | DP16: 0.5 | DQ16: 0.8 | DS16: 0 | DT16: -0.1 | DU16: 0.3 | DV16: 0.1 | DX16: -4.7 | DY16: 0.6 | DZ16: 2.3 | EA16: 2.2 | EB16: 1.5 | EC16: 0.8 | ED16: 4 | EE16: 0 | EF16: -6.1 | EG16: -6.6 | EH16: 0 | EI16: 0.1 | EJ16: 2.6 | EK16: 0 | EL16: 1.2 | EM16: 0.2 | EN16: 0.2 | EO16: 0.2 | EP16: 0 | ER16: 0 | ES16: 0 | ET16: -0.2 | EU16: 2.7 | EV16: 2.1 | EW16: 0 | EX16: 0 | EY16: 0.2 | EZ16: 1.8 | FB16: 8.2 | FC16: 4.3 | FD16: 1.8 | FE16: 1.7 | FF16: 3.1 | FI16: -27.6 | FL16: 0 | FN16: 1.7 | FP16: 1.92607 | FQ16: 0.3 | FR16: 1.9 | FS16: 5.82607
A17: 22/04/2025 | B17: 03:30 | E17: 0 | F17: 15.9 | G17: 18 | J17: -11.1 | K17: -0.8 | N17: -30.9 | O17: -33 | P17: -22.8 | Q17: 3 | R17: -15.7 | S17: -1.1 | T17: 54.8 | U17: -0.3 | Z17: -6.1 | AA17: 0.5 | AC17: -3.3 | AD17: 3.3 | AE17: 4.8 | AF17: 0.9 | AJ17: 5.2 | AK17: 12.5 | AO17: -1.5 | AP17: 29.9 | AQ17: 12.1 | AR17: 1.4 | AS17: -0.7 | AT17: -0.1 | AU17: 2.7 | AV17: 0.1 | AW17: 8 | AX17: -47.5 | AZ17: 8.6 | BA17: -1.8 | BB17: 0.5 | BC17: -5.7 | BD17: 0.9 | BE17: 0 | BF17: -0.1 | BG17: -11.3 | BK17: -2.2 | BO17: 7.1 | BP17: -28.7 | BR17: -35.5 | BS17: -24 | CB17: -0.5 | CC17: 10 | CD17: 22.7 | CE17: 0.7 | CF17: 0.7 | CG17: -8 | CK17: 4.1 | CL17: 7.3 | CM17: -28.2 | CP17: 0 | CV17: -3.6 | CW17: 0 | CX17: 0 | CZ17: 1.4 | DA17: 0 | DB17: -0.3 | DD17: 0 | DE17: 1.5 | DF17: 2.3 | DG17: -1.4 | DH17: 1.3 | DI17: 0.6 | DJ17: 0 | DK17: 0 | DL17: 0 | DM17: 0.5 | DN17: 5 | DO17: 1.8 | DP17: 0.5 | DQ17: 0.8 | DS17: 0 | DT17: -0.2 | DU17: 0.2 | DV17: 0.1 | DX17: -4.6 | DY17: 0.9 | DZ17: 1.7 | EA17: 2.2 | EB17: 1.5 | EC17: 0.8 | ED17: 4 | EE17: 0 | EF17: -4.1 | EG17: -5.6 | EH17: 0 | EI17: 0.2 | EJ17: 2.6 | EK17: 0 | EL17: 1.1 | EM17: 0.2 | EN17: 0.2 | EO17: 0.2 | EP17: 0 | ER17: 0 | ES17: 0 | ET17: -0.2 | EU17: 2.4 | EV17: 2.3 | EW17: 0 | EX17: 0 | EY17: 0.2 | EZ17: 1.8 | FB17: 10.4 | FC17: 6.6 | FD17: 1.8 | FE17: 1.7 | FF17: 3.5 | FI17: -42.9 | FL17: 0 | FN17: 1.8 | FP17: 1.92748 | FQ17: 1.5 | FR17: 2 | FS17: 7.22748
A18: 22/04/2025 | B18: 04:00 | E18: 0 | F18: 24.6 | G18: 20.2 | J18: -10.4 | K18: 10.7 | N18: -28.2 | O18: -29.6 | P18: -20.8 | Q18: 6.6 | R18: -14.1 | S18: 0.2 | T18: 56.7 | U18: -0.1 | Z18: -4.6 | AA18: 0.6 | AC18: -3.3 | AD18: 3.3 | AE18: 5.8 | AF18: 0.9 | AJ18: 7 | AK18: 12.5 | AO18: -1.3 | AP18: 35.1 | AQ18: 11.8 | AR18: 1 | AS18: -1.4 | AT18: -0.4 | AU18: 2.7 | AV18: 0.3 | AW18: 9.4 | AX18: -45.2 | AZ18: 8.2 | BA18: -2 | BB18: 0.2 | BC18: -3.5 | BD18: 1.9 | BE18: 0 | BF18: -0.2 | BG18: -6.2 | BK18: -1.1 | BO18: 8.3 | BP18: -27.3 | BR18: -34.1 | BS18: -25.4 | CB18: -0.4 | CC18: 10.1 | CD18: 22 | CE18: -0.1 | CF18: 0.8 | CG18: -7.8 | CK18: 5.7 | CL18: 8.7 | CM18: -25.5 | CP18: 0 | CV18: -3.8 | CW18: 0 | CX18: 0 | CZ18: 1.4 | DA18: -0.1 | DB18: -0.3 | DD18: 0.2 | DE18: 1.5 | DF18: 2.2 | DG18: -1.5 | DH18: 1.3 | DI18: 0.6 | DJ18: 0 | DK18: 0 | DL18: 0 | DM18: 0.6 | DN18: 5.4 | DO18: 1.8 | DP18: 0.5 | DQ18: 0.8 | DS18: 0 | DT18: -0.2 | DU18: 0.3 | DV18: 0.1 | DX18: -4.6 | DY18: 0.8 | DZ18: 1.8 | EA18: 2.1 | EB18: 1.5 | EC18: 0.8 | ED18: 4 | EE18: 0 | EF18: -2.8 | EG18: -4.5 | EH18: 0.2 | EI18: 0.3 | EJ18: 2.6 | EK18: 0 | EL18: 1.1 | EM18: 0.2 | EN18: 0.2 | EO18: 0.2 | EP18: 0 | ER18: 0 | ES18: 0 | ET18: -0.2 | EU18: 2.8 | EV18: 2.8 | EW18: 0 | EX18: 0 | EY18: 0.2 | EZ18: 1.8 | FB18: 10.6 | FC18: 6.6 | FD18: 1.8 | FE18: 1.7 | FF18: 2.3 | FI18: 27.4 | FL18: 0 | FN18: 1.9 | FP18: 1.93025 | FQ18: 1.6 | FR18: 2 | FS18: 7.43025
A19: 22/04/2025 | B19: 04:30 | E19: 0 | F19: 10.6 | G19: 17.1 | J19: -10.6 | K19: 1.3 | N19: -32.3 | O19: -34.5 | P19: -25 | Q19: 2.7 | R19: -17.9 | S19: -2.3 | T19: 53.5 | U19: -0.1 | Z19: -6.3 | AA19: 0.8 | AC19: -3.3 | AD19: 3.3 | AE19: 6.5 | AF19: 0.9 | AJ19: 6.9 | AK19: 12.7 | AO19: -1.2 | AP19: 59.2 | AQ19: 12.4 | AR19: 1.6 | AS19: -1.3 | AT19: -0.6 | AU19: 2.7 | AV19: 1.4 | AW19: 2.4 | AX19: 0 | AZ19: 6.6 | BA19: -2.1 | BB19: 0.2 | BC19: -4.5 | BD19: 1.4 | BE19: 0 | BF19: -0.2 | BG19: -7.1 | BK19: -1.3 | BO19: 9.3 | BP19: -30.9 | BR19: -37.9 | BS19: -26.6 | CB19: -0.4 | CC19: 10.2 | CD19: 23 | CE19: 0.3 | CF19: 0.8 | CG19: -7.8 | CK19: 3.3 | CL19: 6.3 | CM19: -29.4 | CP19: 0 | CV19: -3.6 | CW19: 0 | CX19: 0 | CZ19: 1.4 | DA19: 0 | DB19: -0.3 | DD19: 0.2 | DE19: 1.7 | DF19: 2.2 | DG19: -1.4 | DH19: 1.3 | DI19: 0.6 | DJ19: 0.1 | DK19: 0 | DL19: 0 | DM19: -0.3 | DN19: 4.4 | DO19: 1.8 | DP19: 0.5 | DQ19: 0.8 | DS19: 0 | DT19: -0.2 | DU19: 0.3 | DV19: 0.1 | DX19: -4.6 | DY19: 0.6 | DZ19: 1.8 | EA19: 2.3 | EB19: 1.5 | EC19: 0.8 | ED19: 4 | EE19: 0 | EF19: -11 | EG19: -11.9 | EH19: 0 | EI19: 0 | EJ19: 2.6 | EK19: 0 | EL19: 1.2 | EM19: 0.2 | EN19: 0.2 | EO19: 0.2 | EP19: 0 | ER19: 0 | ES19: 0 | ET19: -0.2 | EU19: 4 | EV19: 3.3 | EW19: 0 | EX19: 0 | EY19: 0.2 | EZ19: 1.8 | FB19: 10.5 | FC19: 6.6 | FD19: 1.8 | FE19: 1.8 | FF19: 3 | FI19: 4.1 | FL19: 0 | FN19: 1.8 | FP19: 1.92376 | FQ19: 1.7 | FR19: 2 | FS19: 7.42376
A20: 22/04/2025 | B20: 05:00 | E20: 0 | F20: 28.6 | G20: 20.9 | J20: -10.4 | K20: 11.1 | N20: -25.9 | O20: -26.3 | P20: -16.5 | Q20: 7.8 | R20: -13.1 | S20: 0.8 | T20: 60.5 | U20: 0 | Z20: -4.1 | AA20: 0.9 | AC20: -3.3 | AD20: 3.5 | AE20: 6.5 | AF20: 1.1 | AJ20: 7.7 | AK20: 12.9 | AO20: -1.2 | AP20: 58.4 | AQ20: 12.6 | AR20: 1.3 | AS20: -1 | AT20: -1.1 | AU20: 2.7 | AV20: 1.2 | AW20: 7.3 | AX20: 0 | AZ20: 8.9 | BA20: -2.1 | BB20: 0.2 | BC20: -3.2 | BD20: 1.7 | BE20: 0 | BF20: -0.3 | BG20: -6.9 | BK20: -2.3 | BO20: 9.3 | BP20: -23.4 | BR20: -31.4 | BS20: -21.3 | CB20: -0.4 | CC20: 10 | CD20: 22.7 | CE20: -0.2 | CF20: 1 | CG20: -8 | CK20: 6.2 | CL20: 9.4 | CM20: -25.2 | CP20: 0 | CV20: -3.4 | CW20: 0 | CX20: 0 | CZ20: 1.4 | DA20: -0.1 | DB20: -0.3 | DD20: 0 | DE20: 1.5 | DF20: 2.2 | DG20: -1.6 | DH20: 1.3 | DI20: 0.6 | DJ20: 0.1 | DK20: 0 | DL20: 0 | DM20: 0 | DN20: 4.7 | DO20: 1.8 | DP20: 0.5 | DQ20: 0.8 | DS20: 0.2 | DT20: -0.1 | DU20: 0.3 | DV20: 0.1 | DX20: -4.6 | DY20: 0.7 | DZ20: 1.4 | EA20: 2.3 | EB20: 1.4 | EC20: 0.8 | ED20: 4 | EE20: 0.4 | EF20: -6.3 | EG20: -6 | EH20: 0 | EI20: 0.1 | EJ20: 2.6 | EK20: 0 | EL20: 1.1 | EM20: 0.2 | EN20: 0.2 | EO20: 0.2 | EP20: 0 | ER20: 0 | ES20: 0 | ET20: -0.2 | EU20: 4.6 | EV20: 3.5 | EW20: 0 | EX20: 0 | EY20: 0.2 | EZ20: 1.8 | FB20: 10 | FC20: 6.2 | FD20: 1.7 | FE20: 1.9 | FF20: 2.9 | FI20: 128.7 | FL20: 0 | FN20: 1.8 | FP20: 1.92347 | FQ20: 1.5 | FR20: 2 | FS20: 7.22347
A21: 22/04/2025 | B21: 05:30 | E21: 0 | F21: 22.5 | G21: 18.9 | J21: -5.3 | K21: 4.8 | N21: -26.8 | O21: -29.4 | P21: -19.6 | Q21: 8.3 | R21: -10.6 | S21: 3.9 | T21: 55.3 | U21: 0 | Z21: -4.9 | AA21: 1.1 | AC21: -3.3 | AD21: 3.6 | AE21: 6.9 | AF21: 1.2 | AJ21: 7.4 | AK21: 13.9 | AO21: -1.2 | AP21: 56.3 | AQ21: 11.8 | AR21: 3.1 | AS21: -1.3 | AT21: -0.1 | AU21: 2.7 | AV21: 0.2 | AW21: 12 | AX21: 0 | AZ21: 10 | BA21: 0 | BB21: -0.1 | BC21: -4.5 | BD21: 2.2 | BE21: 0 | BF21: -0.3 | BG21: -10.4 | BK21: -0.2 | BO21: 9 | BP21: -18.8 | BR21: -19.5 | BS21: -14.5 | CB21: -0.4 | CC21: 9.8 | CD21: 24.7 | CE21: 1.2 | CF21: 0.4 | CG21: -8.1 | CK21: 7.7 | CL21: 11.6 | CM21: -24 | CP21: 0 | CV21: -3.8 | CW21: 0 | CX21: 0 | CZ21: 1.4 | DA21: -0.1 | DB21: -0.8 | DD21: 0.2 | DE21: 1.5 | DF21: 2.2 | DG21: -1 | DH21: 1.3 | DI21: 0.6 | DJ21: 0.1 | DK21: 0 | DL21: 0 | DM21: -0.1 | DN21: 4.7 | DO21: 1.8 | DP21: 0.5 | DQ21: 0.8 | DS21: 0.3 | DT21: 0 | DU21: 0.3 | DV21: 0.1 | DX21: -4.6 | DY21: 0.5 | DZ21: 1.7 | EA21: 2.4 | EB21: 1.5 | EC21: 0.8 | ED21: 4 | EE21: 0.4 | EF21: -8.5 | EG21: -10.4 | EH21: 0 | EI21: 0 | EJ21: 2.6 | EK21: 0 | EL21: 1 | EM21: 0.2 | EN21: 0.2 | EO21: 0.2 | EP21: 0 | ER21: 0 | ES21: 0 | ET21: -0.1 | EU21: 4.8 | EV21: 3.5 | EW21: 0 | EX21: 0 | EY21: 0.2 | EZ21: 1.8 | FB21: 10.5 | FC21: 6.8 | FD21: 1.7 | FE21: 1.9 | FF21: 2.2 | FI21: 142.5 | FL21: 0 | FN21: 1.7 | FP21: 1.92034 | FQ21: 1.5 | FR21: 2.1 | FS21: 7.22034
A22: 22/04/2025 | B22: 06:00 | E22: 0 | F22: 26.8 | G22: 20.4 | J22: -3.2 | K22: 13.3 | N22: -23.7 | O22: -24.4 | P22: -14.6 | Q22: 12.4 | R22: -8.3 | S22: 4.6 | T22: 59.5 | U22: 0 | Z22: -3.9 | AA22: 0.9 | AC22: -3.3 | AD22: 3.6 | AE22: 7 | AF22: 1 | AJ22: 6.4 | AK22: 14.7 | AO22: -1.2 | AP22: 57.6 | AQ22: 12.1 | AR22: 1.1 | AS22: -1.3 | AT22: -0.5 | AU22: 2.7 | AV22: -0.2 | AW22: 13.3 | AX22: 0 | AZ22: 8.3 | BA22: 0 | BB22: 0.4 | BC22: -2.8 | BD22: 3.6 | BE22: 0 | BF22: -0.1 | BG22: -4.6 | BK22: 3 | BO22: 8.5 | BP22: -16.1 | BR22: -18.2 | BS22: -10.2 | CB22: -0.4 | CC22: 18.7 | CD22: 22.3 | CE22: 5.9 | CF22: 0.8 | CG22: -8 | CK22: 10.2 | CL22: 13.8 | CM22: -19.5 | CP22: 0 | CV22: -2.9 | CW22: 0 | CX22: 0 | CZ22: 1.4 | DA22: -0.1 | DB22: -0.8 | DD22: 0 | DE22: 1.5 | DF22: 2.2 | DG22: -1 | DH22: 1.3 | DI22: 0.6 | DJ22: 0.1 | DK22: 0 | DL22: 0 | DM22: -0.4 | DN22: 3.5 | DO22: 1.8 | DP22: 0.5 | DQ22: 0.8 | DS22: 0.4 | DT22: -0.1 | DU22: 0.2 | DV22: 0.1 | DX22: -4.7 | DY22: 0.5 | DZ22: 1.8 | EA22: 2.4 | EB22: 1.6 | EC22: 0.8 | ED22: 4 | EE22: 0.3 | EF22: -8.4 | EG22: -9.8 | EH22: 0 | EI22: 0 | EJ22: 2.6 | EK22: 0 | EL22: 1 | EM22: 0.2 | EN22: 0.2 | EO22: 0.2 | EP22: 0 | ER22: 0 | ES22: 2.2 | ET22: -0.1 | EU22: 4.9 | EV22: 3.5 | EW22: 0.1 | EX22: 0 | EY22: 0.2 | EZ22: 2 | FB22: 11.9 | FC22: 8.1 | FD22: 1.7 | FE22: 2.1 | FF22: 4 | FI22: 230.8 | FL22: 0 | FN22: 1.8 | FP22: 1.92856 | FQ22: 2.4 | FR22: 2.1 | FS22: 8.22856
... A58: 23/04/2025 | B58: 00:00 | E58: 3.72 | F58: 25.2 | G58: 17.6 | J58: -18.8 | K58: 5.7 | N58: -28.5 | O58: -23.7 | P58: -19.1 | Q58: 6.6 | R58: -12.4 | S58: -6.9 | T58: 47.4 | U58: 0.2 | Z58: 0 | AA58: 1.9 | AC58: -3.3 | AD58: 3.1 | AE58: 3.7 | AF58: 0.9 | AJ58: 2.7 | AK58: 13.7 | AO58: -0.7 | AP58: 32.2 | AQ58: 11.8 | AR58: 10.2 | AS58: 0.9 | AT58: 0.3 | AU58: 2.7 | AV58: 1.2 | AW58: 0 | AX58: 0 | AZ58: 6 | BA58: -2.2 | BB58: 0.5 | BC58: -2.4 | BD58: 1.9 | BE58: 1 | BF58: -0.1 | BG58: -1.7 | BK58: 0 | BO58: 3.6 | BP58: -53.3 | BR58: -2 | BS58: -32.5 | CB58: -0.4 | CC58: 32.5 | CD58: 20 | CE58: 5.1 | CF58: 2 | CG58: 3.9 | CK58: -4.6 | CL58: -1.3 | CM58: -42.3 | CP58: 0 | CV58: 4.1 | CW58: 0 | CX58: 0 | CZ58: 1.4 | DA58: -0.1 | DB58: -0.9 | DD58: 0 | DE58: 1.1 | DF58: 2.3 | DG58: -1.4 | DH58: 0.1 | DI58: 0.6 | DJ58: 0.1 | DK58: 0 | DL58: 0 | DM58: -1.5 | DN58: 3.6 | DO58: 1.5 | DP58: 0.5 | DQ58: 0.8 | DS58: 0 | DT58: 0.1 | DU58: 0.5 | DV58: 0.1 | DX58: -4.8 | DY58: 0 | DZ58: 2.4 | EA58: 2.1 | EB58: 1.7 | EC58: 0.8 | ED58: 4 | EE58: 0 | EF58: -6.7 | EG58: -6.8 | EH58: 0 | EI58: 0 | EJ58: 2.6 | EK58: -0.1 | EL58: 1.5 | EM58: 0.2 | EN58: 0.2 | EO58: 0.2 | EP58: 0 | ER58: 0 | ES58: 0 | ET58: -0.2 | EU58: 1.4 | EV58: 2.1 | EW58: 0 | EX58: 0 | EY58: 0.4 | EZ58: 2 | FB58: 8.2 | FC58: 4.4 | FD58: 1.8 | FE58: 2.1 | FF58: 2.3 | FI58: 46.72 | FL58: 0 | FN58: 1.7 | FP58: 1.8865 | FQ58: -1.5 | FR58: 0.9 | FS58: 2.9865
A59: EJEC | C59: 0 | D59: 0 | E59: 76.585 | F59: 1885.6 | G59: 650.4 | H59: 0 | I59: 0 | J59: -137.15 | K59: 417.75 | L59: 0 | M59: 0 | N59: 288.4 | O59: 164.3 | P59: 212.8 | Q59: 711.55 | R59: 16.45 | S59: 43.75 | T59: 930.7 | U59: -0.5 | V59: 0 | W59: 0 | X59: 0 | Y59: 0 | Z59: -66.15 | AA59: 26.95 | AB59: 0 | AC59: -79.35 | AD59: 78.85 | AE59: 217.1 | AF59: 29.15 | AG59: 0 | AH59: 0 | AI59: 0 | AJ59: 184.45 | AK59: 271 | AL59: 0 | AM59: 0 | AN59: 0 | AO59: -28.55 | AP59: 1239.45 | AQ59: 291.95 | AR59: 216.55 | AS59: 15.8 | AT59: 4.35 | AU59: 64.8 | AV59: 18.45 | AW59: 450.4 | AX59: -173.9 | AY59: 0 | AZ59: 224.35 | BA59: -30.1 | BB59: 5.4 | BC59: -84.9 | BD59: 51 | BE59: 12.95 | BF59: -1.1 | BG59: -152.15 | BH59: 0 | BI59: 0 | BJ59: 0 | BK59: 67.5 | BL59: 0 | BM59: 0 | BN59: 0 | BO59: 197.6 | BP59: -240.4 | BQ59: 0 | BR59: -194.2 | BS59: 18.05 | BT59: 0 | BU59: 0 | BV59: 0 | BW59: 0 | BX59: 0 | BY59: 0 | BZ59: 0 | CA59: 0 | CB59: -9 | CC59: 794.75 | CD59: 697.75 | CE59: 195.95 | CF59: 197.65 | CG59: 5.3 | CH59: 0 | CI59: 0 | CJ59: 0 | CK59: 573 | CL59: 640.8 | CM59: -386.25 | CN59: 0 | CO59: 0 | CP59: -11.85 | CQ59: 0 | CR59: 0 | CS59: 0 | CT59: 0 | CU59: 0 | CV59: -30.85 | CW59: 60.9 | CX59: 0.1 | CY59: 0 | CZ59: 33.6 | DA59: -0.85 | DB59: -18.7 | DC59: 0 | DD59: 0.25 | DE59: 32.8 | DF59: 45.8 | DG59: -7.25 | DH59: 29.95 | DI59: 14.25 | DJ59: 0.8 | DK59: -4.85 | DL59: -8.3 | DM59: -23.4 | DN59: 106.9 | DO59: 40.65 | DP59: 12.1 | DQ59: 16.85 | DR59: 0 | DS59: -21.9 | DT59: 0.2 | DU59: 8.9 | DV59: 2.8 | DW59: 0 | DX59: -112.15 | DY59: 15.1 | DZ59: 50.55 | EA59: 65.15 | EB59: 38.15 | EC59: 19.2 | ED59: 95.55 | EE59: 22.45 | EF59: -166.3 | EG59: -180.65 | EH59: 0.5 | EI59: 0.65 | EJ59: 62.4 | EK59: -1.55 | EL59: 37.35 | EM59: 4.8 | EN59: 4.8 | EO59: 4.8 | EP59: 0.45 | EQ59: 0 | ER59: 13.45 | ES59: 95.75 | ET59: -4.2 | EU59: 171.7 | EV59: 110.45 | EW59: 60.65 | EX59: 13.15 | EY59: 17.45 | EZ59: 46.2 | FA59: 0 | FB59: 248.15 | FC59: 155 | FD59: 42 | FE59: 45.75 | FF59: 77.55 | FG59: 0 | FH59: 0 | FI59: 11939.085 | FK59: 0 | FL59: -5.828 | FM59: 0 | FN59: 41.95 | FO59: 0 | FP59: 49.94322 | FQ59: 19.85 | FR59: 58.25 | FS59: 164.16522

Sheet DEMANDA_AREAS
B3: martes, 22 de Abril del 2025
B5: REPORTE DE LA DEMANDA POR ÁREAS Y SUBAREAS OPERATIVAS (MW)
B6: FECHA HORA | C6: DEMANDA | E6: AREA | H6: SUBAREAS
C7: INTERCAMBIOS INTERNACIONALES | D7: SEIN | E7: NORTE | F7: CENTRO | G7: SUR | H7: ELECTROANDES
B8: 00:30 | C8: 0 | D8: 6350.8 | E8: 938.4749 | F8: 3791.672 | G8: 1620.6531 | H8: 230.9182
B9: 01:00 | C9: 0 | D9: 6483.7 | E9: 892.9244 | F9: 3858.6956 | G9: 1732.08 | H9: 237.1431
B10: 01:30 | C10: 0 | D10: 6470.6 | E10: 940.3342 | F10: 3743.2619 | G10: 1787.0039 | H10: 231.7944
B11: 02:00 | C11: 0 | D11: 6287.9 | E11: 881.5991 | F11: 3626.3847 | G11: 1779.9162 | H11: 231.7386
B12: 02:30 | C12: 0 | D12: 6387.5 | E12: 872.9529 | F12: 3737.4669 | G12: 1777.0802 | H12: 232.9123
B13: 03:00 | C13: 0 | D13: 6331.6 | E13: 850.5281 | F13: 3691.8209 | G13: 1789.251 | H13: 234.1496
B14: 03:30 | C14: 0 | D14: 6328.1 | E14: 854.5186 | F14: 3707.7062 | G14: 1765.8752 | H14: 235.3661
B15: 04:00 | C15: 0 | D15: 6368.7 | E15: 906.9268 | F15: 3699.772 | G15: 1762.0012 | H15: 237.743
B16: 04:30 | C16: 0 | D16: 6270.7 | E16: 868.6515 | F16: 3609.4692 | G16: 1792.5793 | H16: 236.986
B17: 05:00 | C17: 0 | D17: 6518.5 | E17: 929.1681 | F17: 3779.0423 | G17: 1810.2896 | H17: 230.5943
B18: 05:30 | C18: 0 | D18: 6535.7 | E18: 930.4559 | F18: 3796.629 | G18: 1808.6151 | H18: 218.6838
B19: 06:00 | C19: 0 | D19: 6671.2 | E19: 1007.0299 | F19: 3857.1548 | G19: 1807.0153 | H19: 213.8507
... B59: ENERGÍA | C59: 0 | D59: 172792.62 | E59: 26113.478 | F59: 103005.57 | G59: 43673.571 | H59: 5110.2797
B61: LEYENDA:
D63: Potencia recibida del Ecuador
D64: Potencia entregada al Ecuador

Sheet DEMANDA_UL
B3: martes, 22 de Abril del 2025
B5: POTENCIA DE LOS GRANDES USUARIOS LIBRES (MW)
B6: FECHA HORA | C6: GRANDES USUARIOS LIBRES DEL ÁREA NORTE | X6: GRANDES USUARIOS LIBRES DEL ÁREA CENTRO | BP6: GRANDES USUARIOS LIBRES DEL ÁREA SUR
C7: ARCA CONTINENTAL LINDLEY S.A. | D7: AUSTRAL GROUP S.A.A | E7: CEMENTOS PACASMAYO | F7: CORPORACIÓN PESQUERA INCA S.A.C. | G7: CREDITEX: CIA IND.TEXTIL CREDISA | H7: HIPERMERCADOS TOTTUS S.A | I7: INDUSTRIA TEXTIL PIURA | J7: MINERA BOROO MISQUICHILCA S.A. | K7: MINERA GOLD FIELDS | L7: MINERA HORIZONTE | M7: MINERA MARSA | N7: MINERA MISKY MAYO | O7: MINERA YANACOCHA | P7: OPEN PLAZA | Q7: PESQUERA DIAMANTE | R7: PETROPERU | S7: REAL PLAZA S.R.L. | T7: SIDER PERU | U7: SUPERMERCADOS PERUANOS S.A. | V7: TRUPAL S.A. | W7: UNIÓN DE CERVECERÍAS PERUANAS BACKUS Y JOHNSTON S. | X7: ACEROS AREQUIPA | Y7: ADMINISTRADORA JOCKEY PLAZA SHOPPING CENTER S.A. | Z7: ALICORP | AA7: ARCA CONTINENTAL LINDLEY S.A. | AB7: AUSTRAL GROUP S.A.A | AC7: COMPAÑIA MINERA CONDESTABLE | AD7: CORPORACIÓN PESQUERA INCA S.A.C. | AE7: CREDITEX: CIA IND.TEXTIL CREDISA | AF7: FUNDICION CHILCA S.A. | AG7: HIPERMERCADOS TOTTUS S.A | AH7: INMOBILIARIA KANPU S.A. | AI7: INMUEBLES PANAMERICANA S.A. | AJ7: KIMBERLY-CLARK PERU | AK7: LECHE GLORIA S.A. | AL7: MALL AVENTURA S.A. | AM7: MARCOBRE S.A.C. | AN7: MINERA ANTAMINA | AO7: MINERA ARES | AP7: MINERA BUENAVENTURA | AQ7: MINERA CHINALCO PERÚ S.A. | AR7: MINERA SHOUXIN PERU S.A. | AS7: MINERA VOLCAN | AT7: MINSUR | AU7: MOLYCOP-ADESUR | AV7: NEXA RESOURCES CAJAMARQUILLA S.A. | AW7: NEXA RESOURCES PERÚ S.A.A. | AX7: OPEN PLAZA | AY7: OPP FILM | AZ7: OWENS-ILLINOIS PERÚ S.A. | BA7: PAPELERA NACIONAL S.A. | BB7: PESQUERA DIAMANTE | BC7: QUIMPAC S.A. | BD7: REAL PLAZA S.R.L. | BE7: REFINERIA LA PAMPILLA S.A.A | BF7: SAGA FALABELLA | BG7: SAN MIGUEL INDUSTRIAS PET S.A. | BH7: SHOUGANG HIERRO PERU | BI7: SOFTYS PERU S.A.C. | BJ7: SUPERMERCADOS PERUANOS S.A. | BK7: TEJIDOS SAN JACINTO | BL7: TREN URBANO DE LIMA S.A. | BM7: TRUPAL S.A. | BN7: UNACEM PERU S.A. | BO7: UNIÓN DE CERVECERÍAS PERUANAS BACKUS Y JOHNSTON S. | BP7: ANGLO AMERICAN QUELLAVECO S.A. | BQ7: ARCA CONTINENTAL LINDLEY S.A. | BR7: CAL & CEMENTO SUR S.A. | BS7: COMPAÑIA MINERA ANTAPACCAY S.A. | BT7: COMPAÑÍA MINERA CHUNGAR SAC | BU7: COMPAÑIA MINERA SAN IGNACIO DE MOROCOCHA S.A.A. | BV7: EL BROCAL .S.A. | BW7: EMPRESA ADMINISTRADORA CERRO S.A.C. | BX7: EMPRESA MINERA LOS QUENUALES S.A.C. | BY7: HIPERMERCADOS TOTTUS S.A | BZ7: HUDBAY PERU S.A.C. | CA7: INDUSTRIA CACHIMAYO | CB7: MALL AVENTURA S.A. | CC7: MINERA ARES | CD7: MINERA BUENAVENTURA | CE7: MINERA CERRO VERDE | CF7: MINERA CORONA | CG7: MINERA LAS BAMBAS S.A. | CH7: MINERA VOLCAN | CI7: MINSUR | CJ7: MOLYCOP-ADESUR | CK7: NEXA RESOURCES PERÚ S.A.A. | CL7: OXIDOS DE PASCO S.A.C. | CM7: PESQUERA DIAMANTE | CN7: REAL PLAZA S.R.L. | CO7: SOBREANDES S.A.C. | CP7: SOUTHERN PERU CC | CQ7: SUPERMERCADOS PERUANOS S.A. | CR7: UNACEM PERU S.A. | CS7: UNIÓN DE CERVECERÍAS PERUANAS BACKUS Y JOHNSTON S. | CT7: YURA
B8: 00:30 | E8: 17.12249 | J8: 19.9286 | K8: 27.6324 | L8: 12.206 | M8: 13.686 | N8: 13.18 | O8: 33.41 | R8: 54.952 | T8: 40.932 | V8: 9.5 | X8: 126.79344 | Z8: 4.20202 | AF8: 1.7 | AH8: 0.6534 | AJ8: 5.33786 | AK8: 0 | AL8: 1.4135 | AM8: 46.6056 | AN8: 135.73707 | AO8: 28.66676 | AP8: 0.81 | AQ8: 157.84605 | AS8: 38.22579 | AT8: 26.91 | AV8: 192.11087 | AW8: 39.1381 | AY8: 6.51692 | BA8: 2.4 | BC8: 64.13195 | BE8: 19.2 | BK8: 5.53978 | BM8: 6.984 | BN8: 49.71 | BO8: 2.18 | BP8: 150.02065 | BR8: 4.72367 | BS8: 120.54 | BT8: 14.8342 | BV8: 33.7873 | BW8: 3.85819 | BZ8: 93.1941 | CA8: 22.82317 | CB8: 0.3187 | CC8: 0.654 | CD8: 26.1111 | CE8: 292.58152 | CF8: 11.8309 | CG8: 155.13 | CH8: 17.41148 | CK8: 14.6831 | CL8: 4.97991 | CP8: 299.13 | CR8: 37.233 | CT8: 23.74028
B9: 01:00 | E9: 18.63592 | J9: 19.7449 | K9: 27.9263 | L9: 12.399 | M9: 13.457 | N9: 13.76 | O9: 33.934 | R9: 54.394 | T9: 16.9734 | V9: 9.5 | X9: 129.76033 | Z9: 4.32312 | AF9: 1.7 | AH9: 0.6083 | AJ9: 5.33431 | AK9: 0 | AL9: 1.2925 | AM9: 46.8588 | AN9: 136.28063 | AO9: 28.95332 | AP9: 0.7 | AQ9: 159.55045 | AS9: 37.81815 | AT9: 26.48 | AV9: 194.37075 | AW9: 38.2997 | AY9: 7.45953 | BA9: 2.6 | BC9: 65.46421 | BE9: 19.2 | BK9: 5.82917 | BM9: 6.549 | BN9: 50.32 | BO9: 2.04 | BP9: 154.73853 | BR9: 4.6191 | BS9: 120 | BT9: 13.91263 | BV9: 33.9139 | BW9: 3.96348 | BZ9: 93.0165 | CA9: 22.51243 | CB9: 0.3014 | CC9: 0.696 | CD9: 26.55295 | CE9: 379.84173 | CF9: 11.6365 | CG9: 149.629 | CH9: 17.93214 | CK9: 14.5392 | CL9: 4.96923 | CP9: 293.9 | CR9: 37.138 | CT9: 23.90076
B10: 01:30 | E10: 21.89772 | J10: 19.8971 | K10: 27.9277 | L10: 13.025 | M10: 13.631 | N10: 13.22 | O10: 33.714 | R10: 54.515 | T10: 42.6488 | V10: 9.5 | X10: 68.35908 | Z10: 4.21693 | AF10: 1.7 | AH10: 0.6352 | AJ10: 5.31128 | AK10: 0 | AL10: 1.22 | AM10: 48.7929 | AN10: 135.87939 | AO10: 29.07363 | AP10: 0.64 | AQ10: 159.37208 | AS10: 37.33629 | AT10: 26.56 | AV10: 194.41027 | AW10: 38.3935 | AY10: 7.82041 | BA10: 2.6 | BC10: 65.40943 | BE10: 19.2 | BK10: 5.80902 | BM10: 6.789 | BN10: 50.48 | BO10: 1.86 | BP10: 150.25657 | BR10: 4.7154 | BS10: 121.12 | BT10: 13.63261 | BV10: 31.7126 | BW10: 4.0073 | BZ10: 93.7659 | CA10: 22.38177 | CB10: 0.2899 | CC10: 0.639 | CD10: 27.19493 | CE10: 457.479 | CF10: 11.6385 | CG10: 154.533 | CH10: 18.26302 | CK10: 15.2955 | CL10: 4.7974 | CP10: 296.13 | CR10: 37.078 | CT10: 24.07488
B11: 02:00 | E11: 24.55665 | J11: 19.7656 | K11: 27.7667 | L11: 12.783 | M11: 13.664 | N11: 13.26 | O11: 32.984 | R11: 54.801 | T11: 37.7634 | V11: 9.6 | X11: 152.54902 | Z11: 4.00005 | AF11: 1.5 | AH11: 0.6114 | AJ11: 5.27359 | AK11: 0 | AL11: 1.1931 | AM11: 49.0985 | AN11: 134.4559 | AO11: 28.53519 | AP11: 0.44 | AQ11: 158.9107 | AS11: 38.47973 | AT11: 26.87 | AV11: 194.05336 | AW11: 38.0904 | AY11: 7.48998 | BA11: 2.5 | BC11: 67.06751 | BE11: 19.2 | BK11: 5.72474 | BM11: 6.985 | BN11: 50.86 | BO11: 1.92 | BP11: 150.8563 | BR11: 4.6547 | BS11: 120.45 | BT11: 13.821 | BV11: 32.4234 | BW11: 3.7307 | BZ11: 94.0489 | CA11: 22.50032 | CB11: 0.2881 | CC11: 0.677 | CD11: 27.82548 | CE11: 462.43266 | CF11: 11.4345 | CG11: 152.08 | CH11: 17.97393 | CK11: 15.1068 | CL11: 4.89567 | CP11: 290.09 | CR11: 37.278 | CT11: 23.54666
B12: 02:30 | E12: 24.53874 | J12: 19.5151 | K12: 27.5444 | L12: 12.993 | M12: 14.573 | N12: 13.57 | O12: 32.598 | R12: 55.096 | T12: 44.8937 | V12: 9 | X12: 146.87597 | Z12: 4.11339 | AF12: 1.5 | AH12: 0.5216 | AJ12: 5.22184 | AK12: 0 | AL12: 1.1736 | AM12: 48.7776 | AN12: 133.00363 | AO12: 28.40793 | AP12: 0.41 | AQ12: 156.96279 | AS12: 37.33572 | AT12: 27.11 | AV12: 193.94166 | AW12: 38.7507 | AY12: 6.91716 | BA12: 2.5 | BC12: 68.42123 | BE12: 19.2 | BK12: 5.7569 | BM12: 6.6978 | BN12: 50.95 | BO12: 1.82 | BP12: 150.4056 | BR12: 4.61351 | BS12: 122.03 | BT12: 14.66691 | BV12: 31.9332 | BW12: 3.87202 | BZ12: 92.9729 | CA12: 22.41524 | CB12: 0.2829 | CC12: 0.625 | CD12: 27.14755 | CE12: 468.62028 | CF12: 11.8931 | CG12: 155.156 | CH12: 17.73431 | CK12: 14.6973 | CL12: 4.65978 | CP12: 285.8 | CR12: 36.997 | CT12: 23.4688
B13: 03:00 | E13: 24.79596 | J13: 20.0355 | K13: 27.2093 | L13: 13.343 | M13: 14.578 | N13: 13.92 | O13: 32.462 | R13: 55.351 | T13: 40.1064 | V13: 8.5 | X13: 136.98733 | Z13: 4.30127 | AF13: 1.7 | AH13: 0.5562 | AJ13: 4.81592 | AK13: 0 | AL13: 1.1527 | AM13: 49.3023 | AN13: 134.45064 | AO13: 28.20651 | AP13: 0.67 | AQ13: 154.8783 | AS13: 38.11987 | AT13: 26.76 | AV13: 193.48781 | AW13: 39.0283 | AY13: 6.97158 | BA13: 2.5 | BC13: 69.32539 | BE13: 19.2 | BK13: 5.82449 | BM13: 6.984 | BN13: 50.59 | BO13: 1.86 | BP13: 144.29068 | BR13: 4.73099 | BS13: 121.64 | BT13: 15.71735 | BV13: 32.605 | BW13: 3.96593 | BZ13: 91.5852 | CA13: 22.45059 | CB13: 0.2802 | CC13: 0.681 | CD13: 26.8442 | CE13: 468.69935 | CF13: 11.759 | CG13: 155.274 | CH13: 18.14552 | CK13: 15.3122 | CL13: 4.70416 | CP13: 294.23 | CR13: 36.83 | CT13: 23.4307
B14: 03:30 | E14: 24.3818 | J14: 19.8942 | K14: 27.0615 | L14: 13.291 | M14: 14.464 | N14: 13.94 | O14: 32.554 | R14: 54.744 | T14: 34.0319 | V14: 8.5 | X14: 112.91513 | Z14: 4.39146 | AF14: 2 | AH14: 0.5789 | AJ14: 5.05719 | AK14: 0 | AL14: 1.1529 | AM14: 48.9637 | AN14: 133.78375 | AO14: 26.9721 | AP14: 0.48 | AQ14: 154.08801 | AS14: 37.81875 | AT14: 24.64 | AV14: 194.30652 | AW14: 39.0458 | AY14: 7.41307 | BA14: 2.6 | BC14: 69.84078 | BE14: 19.2 | BK14: 5.82997 | BM14: 6.789 | BN14: 57.28 | BO14: 1.97 | BP14: 143.66253 | BR14: 4.68636 | BS14: 120.89 | BT14: 15.61745 | BV14: 33.13 | BW14: 4.02736 | BZ14: 90.3901 | CA14: 22.46306 | CB14: 0.2803 | CC14: 0.663 | CD14: 26.20391 | CE14: 464.67117 | CF14: 12.0986 | CG14: 156.61 | CH14: 18.01129 | CK14: 14.6555 | CL14: 4.63886 | CP14: 288.58 | CR14: 36.322 | CT14: 24.4199
B15: 04:00 | E15: 24.46213 | J15: 19.5557 | K15: 27.1007 | L15: 13.673 | M15: 14.843 | N15: 13.81 | O15: 32.676 | R15: 55.034 | T15: 42.2105 | V15: 8.5 | X15: 117.40851 | Z15: 4.40325 | AF15: 1.7 | AH15: 0.6334 | AJ15: 5.19055 | AK15: 0 | AL15: 1.1571 | AM15: 48.7296 | AN15: 133.35909 | AO15: 28.13789 | AP15: 0.18 | AQ15: 153.45585 | AS15: 37.28776 | AT15: 24.62 | AV15: 194.70528 | AW15: 39.2207 | AY15: 7.73725 | BA15: 2.6 | BC15: 70.20481 | BE15: 19.2 | BK15: 5.85527 | BM15: 6.984 | BN15: 59.81 | BO15: 2.08 | BP15: 146.61886 | BR15: 4.57673 | BS15: 123.08 | BT15: 15.64426 | BV15: 33.2004 | BW15: 3.88656 | BZ15: 92.3333 | CA15: 22.4309 | CB15: 0.2659 | CC15: 0.684 | CD15: 26.90933 | CE15: 459.87042 | CF15: 12.3563 | CG15: 153.954 | CH15: 17.87591 | CK15: 15.0656 | CL15: 4.64444 | CP15: 291.05 | CR15: 36.269 | CT15: 25.25426
B16: 04:30 | E16: 24.46938 | J16: 19.5086 | K16: 26.9953 | L16: 13.389 | M16: 15.682 | N16: 13.02 | O16: 33.048 | R16: 55.149 | T16: 45.6656 | V16: 8.6 | X16: 128.80088 | Z16: 4.39562 | AF16: 1.6 | AH16: 0.5847 | AJ16: 5.28152 | AK16: 0 | AL16: 1.1421 | AM16: 49.5204 | AN16: 132.88676 | AO16: 27.83334 | AP16: 1.65 | AQ16: 154.97768 | AS16: 36.8984 | AT16: 24.78 | AV16: 193.76543 | AW16: 38.4046 | AY16: 7.68375 | BA16: 2.59 | BC16: 70.19068 | BE16: 19.2 | BK16: 5.86275 | BM16: 6.549 | BN16: 58.17 | BO16: 2.19 | BP16: 147.78334 | BR16: 4.63218 | BS16: 120.54 | BT16: 15.45903 | BV16: 33.7104 | BW16: 3.90366 | BZ16: 93.8655 | CA16: 22.43961 | CB16: 0.2598 | CC16: 0.658 | CD16: 26.38062 | CE16: 463.59565 | CF16: 12.2845 | CG16: 150.819 | CH16: 17.76781 | CK16: 14.9928 | CL16: 4.89503 | CP16: 294.83 | CR16: 36.343 | CT16: 25.28458
B17: 05:00 | E17: 24.35167 | J17: 19.6742 | K17: 26.8476 | L17: 12.678 | M17: 15.858 | N17: 13.38 | O17: 32.442 | R17: 54.937 | T17: 44.6324 | V17: 8.6 | X17: 121.38166 | Z17: 4.50637 | AF17: 1.4 | AH17: 0.5834 | AJ17: 5.03627 | AK17: 0 | AL17: 1.1393 | AM17: 49.6871 | AN17: 134.10848 | AO17: 28.10492 | AP17: 2.1 | AQ17: 159.12171 | AS17: 35.66831 | AT17: 24.74 | AV17: 192.97066 | AW17: 37.9038 | AY17: 6.8172 | BA17: 2.4 | BC17: 69.82111 | BE17: 19.2 | BK17: 5.69245 | BM17: 6.789 | BN17: 58.44 | BO17: 2.24 | BP17: 147.36043 | BR17: 4.68232 | BS17: 120.66 | BT17: 14.73174 | BV17: 32.6433 | BW17: 4.37541 | BZ17: 93.5407 | CA17: 22.40881 | CB17: 0.2517 | CC17: 0.665 | CD17: 26.09726 | CE17: 459.98149 | CF17: 12.1788 | CG17: 152.612 | CH17: 18.30766 | CK17: 14.1699 | CL17: 4.87579 | CP17: 299.59 | CR17: 36.53 | CT17: 25.47914
B18: 05:30 | E18: 24.271 | J18: 17.8462 | K18: 26.8821 | L18: 12.298 | M18: 15.511 | N18: 13.89 | O18: 32.892 | R18: 55.197 | T18: 40.4259 | V18: 8.8 | X18: 134.86716 | Z18: 4.36765 | AF18: 1.3 | AH18: 0.5739 | AJ18: 5.08865 | AK18: 0 | AL18: 1.1435 | AM18: 49.9963 | AN18: 134.41918 | AO18: 26.6038 | AP18: 1.93 | AQ18: 159.12482 | AS18: 34.47469 | AT18: 24.8 | AV18: 193.24245 | AW18: 35.823 | AY18: 7.06899 | BA18: 2.3 | BC18: 53.42068 | BE18: 19.2 | BK18: 5.59479 | BM18: 6.985 | BN18: 58.41 | BO18: 1.88 | BP18: 146.39415 | BR18: 4.68129 | BS18: 118.72 | BT18: 14.23561 | BV18: 30.869 | BW18: 3.85894 | BZ18: 92.2181 | CA18: 22.38289 | CB18: 0.2478 | CC18: 0.636 | CD18: 25.92093 | CE18: 459.21772 | CF18: 11.5879 | CG18: 142.661 | CH18: 17.79985 | CK18: 13.9015 | CL18: 5.02105 | CP18: 298.3 | CR18: 37.018 | CT18: 25.25552
B19: 06:00 | E19: 25.01922 | J19: 19.6611 | K19: 27.0401 | L19: 9.97 | M19: 15.205 | N19: 13.63 | O19: 33.25 | R19: 55.499 | T19: 41.0466 | V19: 9.1 | X19: 111.32617 | Z19: 4.49807 | AF19: 1.4 | AH19: 0.593 | AJ19: 5.10208 | AK19: 0 | AL19: 1.1691 | AM19: 50.2914 | AN19: 128.88497 | AO19: 25.87997 | AP19: 1.54 | AQ19: 158.63627 | AS19: 34.45566 | AT19: 24.02 | AV19: 193.43601 | AW19: 35.496 | AY19: 7.44605 | BA19: 2.2 | BC19: 42.55087 | BE19: 19.2 | BK19: 5.61413 | BM19: 6.6978 | BN19: 52.9 | BO19: 2.25 | BP19: 149.41158 | BR19: 4.68522 | BS19: 117 | BT19: 13.90837 | BV19: 31.4788 | BW19: 3.65085 | BZ19: 90.9344 | CA19: 22.51929 | CB19: 0.253 | CC19: 0.708 | CD19: 24.28623 | CE19: 455.37054 | CF19: 10.9933 | CG19: 149.101 | CH19: 18.51002 | CK19: 13.4274 | CL19: 4.65345 | CP19: 297.27 | CR19: 37.161 | CT19: 25.15251
... B55: 00:00 | E55: 24.49191 | J55: 18.1315 | K55: 25.6129 | L55: 12.973 | M55: 13.583 | N55: 10.48 | O55: 32.792 | R55: 54.593 | T55: 42.0056 | V55: 8.5 | X55: 108.83955 | Z55: 6.55875 | AF55: 2.5 | AH55: 0.6995 | AJ55: 5.27586 | AK55: 0 | AL55: 1.3819 | AM55: 49.4553 | AN55: 33.86305 | AO55: 29.10528 | AP55: 0.83 | AQ55: 160.8873 | AS55: 39.23939 | AT55: 26.33 | AV55: 192.45345 | AW55: 38.5257 | AY55: 4.50525 | BA55: 5.1 | BC55: 49.96871 | BE55: 19.9 | BK55: 5.6513 | BM55: 6.984 | BN55: 51.93 | BO55: 2.02 | BP55: 142.71319 | BR55: 4.64119 | BS55: 121.53 | BT55: 14.84144 | BV55: 33.082 | BW55: 3.83695 | BZ55: 91.0404 | CA55: 22.47055 | CB55: 0.3579 | CC55: 0.673 | CD55: 26.60958 | CE55: 466.01353 | CF55: 11.6344 | CG55: 153.826 | CH55: 17.98202 | CK55: 17.2176 | CL55: 5.29603 | CP55: 266.88 | CR55: 36.536 | CT55: 23.32789
B56: MWh | C56: 0 | D56: 0 | E56: 562.37705 | F56: 0 | G56: 0 | H56: 0 | I56: 0 | J56: 468.01355 | K56: 651.74655 | L56: 298.552 | M56: 318.443 | N56: 314.89 | O56: 767.851 | P56: 0 | Q56: 0 | R56: 1299.497 | S56: 0 | T56: 802.70235 | U56: 0 | V56: 179.85 | W56: 0 | X56: 2432.4037 | Y56: 0 | Z56: 144.79459 | AA56: 0 | AB56: 0 | AC56: 0 | AD56: 0 | AE56: 0 | AF56: 53.4 | AG56: 0 | AH56: 14.75645 | AI56: 0 | AJ56: 118.96792 | AK56: 0 | AL56: 81.85145 | AM56: 1070.0998 | AN56: 2391.5023 | AO56: 668.85284 | AP56: 18.01 | AQ56: 3764.1299 | AR56: 0 | AS56: 867.44115 | AT56: 639.92 | AU56: 0 | AV56: 4140.1642 | AW56: 886.1429 | AX56: 0 | AY56: 158.0363 | AZ56: 0 | BA56: 56.045 | BB56: 0 | BC56: 961.97632 | BD56: 0 | BE56: 469.85 | BF56: 0 | BG56: 0 | BH56: 0 | BI56: 0 | BJ56: 0 | BK56: 138.02362 | BL56: 0 | BM56: 163.8278 | BN56: 924.695 | BO56: 51.355 | BP56: 3492.3736 | BQ56: 0 | BR56: 112.7399 | BS56: 2843.085 | BT56: 325.01407 | BU56: 0 | BV56: 759.99095 | BW56: 93.35209 | BX56: 0 | BY56: 0 | BZ56: 2185.3544 | CA56: 473.10971 | CB56: 19.87245 | CC56: 16.147 | CD56: 616.41345 | CE56: 10597.244 | CF56: 273.31945 | CG56: 3615.763 | CH56: 417.02456 | CI56: 0 | CJ56: 0 | CK56: 357.9223 | CL56: 114.52315 | CM56: 0 | CN56: 0 | CO56: 0 | CP56: 6476.06 | CQ56: 0 | CR56: 831.8805 | CS56: 0 | CT56: 346.56635
B59: Nota :
B60: Información proporcionada por la empresas
C62: DATOS ESTIMADOS
C64: SIN DATOS

Sheet TIPO_RECURSO
B3: martes, 22 de Abril del 2025
B5: REPORTE POTENCIA GENERADA POR TIPO DE RECURSO
B6: HORA | C6: H. PASADA | D6: H. REGULACION | E6: GAS DE CAMISEA | F6: GAS DE MALACAS | G6: GAS DE AGUAYTIA | H6: DIESEL | I6: RESIDUAL | J6: NAFTA+GAS DE REFINERIA | K6: FLEXIGAS+GAS DE REFINERIA | L6: DIESEL | M6: BAGAZO | N6: BIOGAS | O6: SOLAR | P6: EÓLICA | Q6: TOTAL | V6: EMPRESA | W6: CENTRAL | X6: HIDROELECTRICA DE PASADA | Y6: HIDROELECTRICA DE REGULACION
B7: 00:30 | C7: 1132.7 | D7: 2982.3 | E7: 1517.7 | F7: 47.8 | J7: =+DESPACHO_EJECUTADO!FC11+DESPACHO_EJECUTADO!FD11 -> 74.9 | L7: 0 | M7: 16 | N7: 9.4 | O7: 0 | P7: 570 | Q7: =+SUM(C7:P7) -> 6350.8 | V7: ANDEAN POWER S.A.C. | W7: C.H.CARHUAC | X7: 283.4
B8: 01:00 | C8: 1140.2 | D8: 3190.7 | E8: 1368 | F8: 24.9 | J8: =+DESPACHO_EJECUTADO!FC12+DESPACHO_EJECUTADO!FD12 -> 73.3 | L8: 0 | M8: 16 | N8: 9.4 | O8: 0 | P8: 661.2 | Q8: =+SUM(C8:P8) -> 6483.7 | V8: ASOCIACIÓN SANTA LUCIA DE CHACAS | W8: C.H. HUALLIN | X8: 74
B9: 01:30 | C9: 1145.9 | D9: 3190.1 | E9: 1374 | F9: 24.7 | J9: =+DESPACHO_EJECUTADO!FC13+DESPACHO_EJECUTADO!FD13 -> 72.9 | L9: 0 | M9: 16 | N9: 9.4 | O9: 0 | P9: 637.6 | Q9: =+SUM(C9:P9) -> 6470.6 | V9: CELEPSA | W9: C.H. EL PLATANAL | Y9: 4993.45
B10: 02:00 | C10: 1127.2 | D10: 3098.9 | E10: 1369.4 | F10: 24.5 | J10: =+DESPACHO_EJECUTADO!FC14+DESPACHO_EJECUTADO!FD14 -> 74.1 | L10: 0 | M10: 17 | N10: 9.4 | O10: 0 | P10: 567.4 | Q10: =+SUM(C10:P10) -> 6287.9 | V10: CELEPSA RENOVABLES S.R.L. | W10: C.H. MARAÑON | X10: 472.8
B11: 02:30 | C11: 1139.9 | D11: 3165.3 | E11: 1439.2 | F11: 24.8 | J11: =+DESPACHO_EJECUTADO!FC15+DESPACHO_EJECUTADO!FD15 -> 74 | L11: 0 | M11: 17 | N11: 9.4 | O11: 0 | P11: 517.9 | Q11: =+SUM(C11:P11) -> 6387.5 | V11: CHINANGO S.A.C. | W11: C.H. CHIMAY | Y11: 3392
B12: 03:00 | C12: 1137.2 | D12: 3128.8 | E12: 1398.2 | F12: 24.5 | J12: =+DESPACHO_EJECUTADO!FC16+DESPACHO_EJECUTADO!FD16 -> 74.6 | L12: 0 | M12: 16.7 | N12: 9.4 | O12: 0 | P12: 542.2 | Q12: =+SUM(C12:P12) -> 6331.6 | W12: C.H. YANANGO | X12: 1011.55
B13: 03:30 | C13: 1134.8 | D13: 3113.7 | E13: 1403 | F13: 24.8 | J13: =+DESPACHO_EJECUTADO!FC17+DESPACHO_EJECUTADO!FD17 -> 74.6 | L13: 0 | M13: 16.9 | N13: 9.4 | O13: 0 | P13: 550.9 | Q13: =+SUM(C13:P13) -> 6328.1 | V13: EGASA | W13: C.H. CHARCANI III | X13: 160.6
B14: 04:00 | C14: 1144.8 | D14: 3146.7 | E14: 1413.5 | F14: 25.3 | J14: =+DESPACHO_EJECUTADO!FC18+DESPACHO_EJECUTADO!FD18 -> 74 | L14: 0 | M14: 17 | N14: 9.4 | O14: 0 | P14: 538 | Q14: =+SUM(C14:P14) -> 6368.7 | W14: C.H. CHARCANI IV | Y14: 244.35
B15: 04:30 | C15: 1137.5 | D15: 3157.6 | E15: 1392.3 | F15: 25 | J15: =+DESPACHO_EJECUTADO!FC19+DESPACHO_EJECUTADO!FD19 -> 74.4 | L15: 0 | M15: 16 | N15: 9.4 | O15: 0 | P15: 458.5 | Q15: =+SUM(C15:P15) -> 6270.7 | W15: C.H. CHARCANI V | Y15: 2156.8
B16: 05:00 | C16: 1147.6 | D16: 3203.6 | E16: 1593.1 | F16: 47 | J16: =+DESPACHO_EJECUTADO!FC20+DESPACHO_EJECUTADO!FD20 -> 74.1 | L16: 0 | M16: 16 | N16: 9.4 | O16: 0 | P16: 427.7 | Q16: =+SUM(C16:P16) -> 6518.5 | W16: C.H. CHARCANI VI | Y16: 141.6
B17: 05:30 | C17: 1135.1 | D17: 3218 | E17: 1664.8 | F17: 47 | J17: =+DESPACHO_EJECUTADO!FC21+DESPACHO_EJECUTADO!FD21 -> 73.5 | L17: 0 | M17: 16 | N17: 9.4 | O17: 0 | P17: 371.9 | Q17: =+SUM(C17:P17) -> 6535.7 | V17: EGEJUNIN | W17: C.H. HUASAHUASI I | X17: 475.3
B18: 06:00 | C18: 1128.6 | D18: 3273.4 | E18: 1781.9 | F18: 46.9 | J18: =+DESPACHO_EJECUTADO!FC22+DESPACHO_EJECUTADO!FD22 -> 73.5 | L18: 0 | M18: 16.5 | N18: 9.4 | O18: 2.1 | P18: 338.9 | Q18: =+SUM(C18:P18) -> 6671.2 | W18: C.H. RUNATULLO II | X18: 437
B19: 06:30 | C19: 1129.3 | D19: 3297.8 | E19: 1851.3 | F19: 47.1 | J19: =+DESPACHO_EJECUTADO!FC23+DESPACHO_EJECUTADO!FD23 -> 73.9 | L19: 0 | M19: 16 | N19: 9.4 | O19: 31.96 | P19: 341.5 | Q19: =+SUM(C19:P19) -> 6798.26 | W19: C.H. RUNATULLO III | X19: 486.5
B20: 07:00 | C20: 1131.3 | D20: 3245.6 | E20: 1794 | F20: 47.2 | J20: =+DESPACHO_EJECUTADO!FC24+DESPACHO_EJECUTADO!FD24 -> 73.8 | L20: 0 | M20: 7.2 | N20: 9.4 | O20: 76.3 | P20: 424 | Q20: =+SUM(C20:P20) -> 6808.8 | W20: C.H. SANTA CRUZ I | X20: 225.25
B21: 07:30 | C21: 1115 | D21: 3300.5 | E21: 1804.9 | F21: 47.5 | J21: =+DESPACHO_EJECUTADO!FC25+DESPACHO_EJECUTADO!FD25 -> 73.5 | L21: 0 | M21: 7.3 | N21: 9.4 | O21: 96.75 | P21: 467.9 | Q21: =+SUM(C21:P21) -> 6922.75 | V21: EGEMSA | W21: C.H. MACHUPICCHU | X21: 3955.4
B22: 08:00 | C22: 1120.3 | D22: 3359.5 | E22: 1834.8 | F22: 47.3 | J22: =+DESPACHO_EJECUTADO!FC26+DESPACHO_EJECUTADO!FD26 -> 73.8 | L22: 0 | M22: 4.7 | N22: 9.4 | O22: 124.03 | P22: 483.5 | Q22: =+SUM(C22:P22) -> 7057.33 | V22: EGESUR | W22: C.H. ARICOTA I | Y22: 177.6
B23: 08:30 | C23: 1116.4 | D23: 3311.7 | E23: 1980.7 | F23: 47 | J23: =+DESPACHO_EJECUTADO!FC27+DESPACHO_EJECUTADO!FD27 -> 74.8 | L23: 0 | M23: 4.3 | N23: 8.3 | O23: 208.28 | P23: 503.9 | Q23: =+SUM(C23:P23) -> 7255.38 | W23: C.H. ARICOTA II | Y23: 83.4
B24: 09:00 | C24: 1135.1 | D24: 3262.6 | E24: 1979.8 | F24: 46.7 | J24: =+DESPACHO_EJECUTADO!FC28+DESPACHO_EJECUTADO!FD28 -> 73.8 | L24: 0 | M24: 4.2 | N24: 8.3 | O24: 364.64 | P24: 529.1 | Q24: =+SUM(C24:P24) -> 7404.24 | V24: ELECTRICA YANAPAMPA SAC | W24: C.H. YANAPAMPA | X24: 75.5
B25: 09:30 | C25: 1116.2 | D25: 3251.6 | E25: 1930.8 | F25: 47.3 | J25: =+DESPACHO_EJECUTADO!FC29+DESPACHO_EJECUTADO!FD29 -> 74.8 | L25: 0 | M25: 10 | N25: 8.3 | O25: 425 | P25: 570.6 | Q25: =+SUM(C25:P25) -> 7434.6 | V25: ELECTROPERU | W25: C.H. MANTARO | Y25: 15029.5
B26: 10:00 | C26: 1125.1 | D26: 3252.8 | E26: 1913.1 | F26: 46 | J26: =+DESPACHO_EJECUTADO!FC30+DESPACHO_EJECUTADO!FD30 -> 74.4 | L26: 0 | M26: 16.3 | N26: 8.3 | O26: 540.46 | P26: 543.7 | Q26: =+SUM(C26:P26) -> 7520.16 | W26: C.H. RESTITUCION | X26: 5001.4
B27: 10:30 | C27: 1149.2 | D27: 3271.7 | E27: 1912.8 | F27: 45.6 | J27: =+DESPACHO_EJECUTADO!FC31+DESPACHO_EJECUTADO!FD31 -> 74.7 | L27: 0 | M27: 16.2 | N27: 8.2 | O27: 615.39 | P27: 494 | Q27: =+SUM(C27:P27) -> 7587.79 | V27: EMPRESA DE GENERACION ELECTRICA CANCHAYLLO SAC | W27: C.H. CANCHAYLLO | X27: 118
B28: 11:00 | C28: 1155.4 | D28: 3368.28 | E28: 1927.4 | F28: 46.3 | J28: =+DESPACHO_EJECUTADO!FC32+DESPACHO_EJECUTADO!FD32 -> 74.3 | L28: 0 | M28: 16.2 | N28: 8.1 | O28: 592.82 | P28: 513.7 | Q28: =+SUM(C28:P28) -> 7702.5 | V28: EMPRESA DE GENERACION ELECTRICA RIO BAÑOS S.A.C. | W28: C.H. RUCUY | X28: 478.45
B29: 11:30 | C29: 1165.6 | D29: 3466.06 | E29: 1962 | F29: 45.9 | J29: =+DESPACHO_EJECUTADO!FC33+DESPACHO_EJECUTADO!FD33 -> 74.6 | L29: 0 | M29: 16 | N29: 8.1 | O29: 566.93 | P29: 550.5 | Q29: =+SUM(C29:P29) -> 7855.69 | V29: EMPRESA DE GENERACION ELECTRICA SANTA ANA S.A.C. | W29: C.H. RENOVANDES H1 | X29: 486.85
B30: 12:00 | C30: 1158.3 | D30: 3396.65 | E30: 1912.8 | F30: 46.2 | J30: =+DESPACHO_EJECUTADO!FC34+DESPACHO_EJECUTADO!FD34 -> 74.6 | L30: 0 | M30: 16 | N30: 8.1 | O30: 532.32 | P30: 548.1 | Q30: =+SUM(C30:P30) -> 7693.07 | V30: EMPRESA DE GENERACION HUALLAGA | W30: C.H. CHAGLLA | Y30: 10824.75
B31: 12:30 | C31: 1158.1 | D31: 3264.49 | E31: 1897.1 | F31: 45.9 | J31: =+DESPACHO_EJECUTADO!FC35+DESPACHO_EJECUTADO!FD35 -> 74.6 | L31: 0 | M31: 15.5 | N31: 8.1 | O31: 655.43 | P31: 560.2 | Q31: =+SUM(C31:P31) -> 7679.42 | W31: P.C.H. CHAGLLA | X31: 155.3
B32: 13:00 | C32: 1161.6 | D32: 3287.16 | E32: 1735.9 | F32: 45.5 | J32: =+DESPACHO_EJECUTADO!FC36+DESPACHO_EJECUTADO!FD36 -> 74.7 | L32: 0 | M32: 14.5 | N32: 8.1 | O32: 659.51 | P32: 579.3 | Q32: =+SUM(C32:P32) -> 7566.27 | V32: EMPRESA DE GENERACION HUANZA | W32: C.H. HUANZA | Y32: 822.85
B33: 13:30 | C33: 1147.8 | D33: 3314.67 | E33: 1590.8 | F33: 45.6 | J33: =+DESPACHO_EJECUTADO!FC37+DESPACHO_EJECUTADO!FD37 -> 74.3 | L33: 0 | M33: 15.2 | N33: 8.1 | O33: 637.44 | P33: 616.3 | Q33: =+SUM(C33:P33) -> 7450.21 | V33: EMPRESA ELECTRICA AGUA AZUL | W33: C.H. POTRERO | X33: 480
B34: 14:00 | C34: 1150.9 | D34: 3419.21 | E34: 1604.4 | F34: 45.6 | J34: =+DESPACHO_EJECUTADO!FC38+DESPACHO_EJECUTADO!FD38 -> 74.4 | L34: 0 | M34: 14.9 | N34: 8.1 | O34: 638.31 | P34: 655.8 | Q34: =+SUM(C34:P34) -> 7611.62 | V34: EMPRESA ELECTRICA RIO DOBLE | W34: C.H. LAS PIZARRAS | X34: 458.25
B35: 14:30 | C35: 1151.8 | D35: 3408.25 | E35: 1648.8 | F35: 45.7 | J35: =+DESPACHO_EJECUTADO!FC39+DESPACHO_EJECUTADO!FD39 -> 73.8 | L35: 0 | M35: 15 | N35: 8.5 | O35: 632.92 | P35: 677.8 | Q35: =+SUM(C35:P35) -> 7662.57 | V35: ENGIE | W35: C.H. YUNCAN | Y35: 2071.25
B36: 15:00 | C36: 1154.8 | D36: 3377.69 | E36: 1813.2 | F36: 46.2 | J36: =+DESPACHO_EJECUTADO!FC40+DESPACHO_EJECUTADO!FD40 -> 74.1 | L36: 0 | M36: 15 | N36: 9.2 | O36: 639.94 | P36: 657.5 | Q36: =+SUM(C36:P36) -> 7787.63 | V36: GENERACIÓN ANDINA S.A.C. | W36: C.H. 8 DE AGOSTO | X36: 504
B37: 15:30 | C37: 1168.7 | D37: 3429.34 | E37: 1851 | F37: 45.8 | J37: =+DESPACHO_EJECUTADO!FC41+DESPACHO_EJECUTADO!FD41 -> 73.8 | L37: 0 | M37: 16.8 | N37: 9.2 | O37: 583.86 | P37: 664.7 | Q37: =+SUM(C37:P37) -> 7843.2 | W37: C.H. EL CARMEN | X37: 187.35
B38: 16:00 | C38: 1165.5 | D38: 3410.06 | E38: 1901 | F38: 46.2 | J38: =+DESPACHO_EJECUTADO!FC42+DESPACHO_EJECUTADO!FD42 -> 73.3 | L38: 0 | M38: 17.6 | N38: 9.3 | O38: 512.46 | P38: 690.7 | Q38: =+SUM(C38:P38) -> 7826.12 | V38: GENERADORA DE ENERGÍA DEL PERÚ | W38: C.H. ÁNGEL I | X38: 489.6
B39: 16:30 | C39: 1161.2 | D39: 3440.98 | E39: 1996.9 | F39: 46.1 | J39: =+DESPACHO_EJECUTADO!FC43+DESPACHO_EJECUTADO!FD43 -> 74 | L39: 0 | M39: 16.5 | N39: 9.3 | O39: 316.55 | P39: 716.8 | Q39: =+SUM(C39:P39) -> 7778.33 | W39: C.H. ÁNGEL II | X39: 489.6
B40: 17:00 | C40: 1151.1 | D40: 3286.49 | E40: 2132.8 | F40: 46.7 | J40: =+DESPACHO_EJECUTADO!FC44+DESPACHO_EJECUTADO!FD44 -> 73.5 | L40: 0 | M40: 16.2 | N40: 9.1 | O40: 71.92 | P40: 800 | Q40: =+SUM(C40:P40) -> 7587.81 | W40: C.H. ÁNGEL III | X40: 484.8
B41: 17:30 | C41: 1165.1 | D41: 3381.26 | E41: 2008.3 | F41: 46.1 | J41: =+DESPACHO_EJECUTADO!FC45+DESPACHO_EJECUTADO!FD45 -> 73.8 | L41: 0 | M41: 15.5 | N41: 9.3 | O41: 76.23 | P41: 817.1 | Q41: =+SUM(C41:P41) -> 7592.69 | W41: C.H. LA JOYA | X41: 171.5
B42: 18:00 | C42: 1168 | D42: 3383.77 | E42: 1988.1 | F42: 48.3 | J42: =+DESPACHO_EJECUTADO!FC46+DESPACHO_EJECUTADO!FD46 -> 74.2 | L42: 0 | M42: 16 | N42: 9.3 | O42: 0 | P42: 798 | Q42: =+SUM(C42:P42) -> 7485.67 | V42: HIDROCAÑETE S.A. | W42: C.H. IMPERIAL | X42: 85.95
B43: 18:30 | C43: 1166.2 | D43: 3474.05 | E43: 2056.3 | F43: 48.3 | J43: =+DESPACHO_EJECUTADO!FC47+DESPACHO_EJECUTADO!FD47 -> 73.9 | L43: 47 | M43: 16.2 | N43: 9.3 | O43: 0 | P43: 782 | Q43: =+SUM(C43:P43) -> 7673.25 | V43: HIDROELECTRICA HUANCHOR S.A.C. | W43: C.H. HUANCHOR | X43: 448.05
B44: 19:00 | C44: 1170.3 | D44: 3455.9 | E44: 1923.9 | F44: 48 | J44: =+DESPACHO_EJECUTADO!FC48+DESPACHO_EJECUTADO!FD48 -> 73.1 | L44: 175.9 | M44: 16.4 | N44: 9.3 | O44: 0 | P44: 764.1 | Q44: =+SUM(C44:P44) -> 7636.9 | V44: HUAURA POWER GROUP S.A. | W44: C.H. YARUCAYA | X44: 222.75
B45: 19:30 | C45: 1164.4 | D45: 3427.89 | E45: 1920.5 | F45: 48.8 | J45: =+DESPACHO_EJECUTADO!FC49+DESPACHO_EJECUTADO!FD49 -> 73.6 | L45: 172.2 | M45: 17 | N45: 9.3 | O45: 0 | P45: 802.8 | Q45: =+SUM(C45:P45) -> 7636.49 | V45: HYDRO GLOBAL PERÚ S.A.C. | W45: CH SAN GABAN III | Y45: 679.245
B46: 20:00 | C46: 1158.3 | D46: 3572.43 | E46: 1832.7 | F46: 48.4 | J46: =+DESPACHO_EJECUTADO!FC50+DESPACHO_EJECUTADO!FD50 -> 73.5 | L46: 175.9 | M46: 17.8 | N46: 9.3 | O46: 0 | P46: 711.1 | Q46: =+SUM(C46:P46) -> 7599.43 | V46: INLAND ENERGY SAC | W46: C.H. SANTA TERESA | X46: 2169.55
B47: 20:30 | C47: 1162.7 | D47: 3649.96 | E47: 1757.4 | F47: 48.4 | J47: =+DESPACHO_EJECUTADO!FC51+DESPACHO_EJECUTADO!FD51 -> 74.5 | L47: 174.7 | M47: 17 | N47: 9.3 | O47: 0 | P47: 688 | Q47: =+SUM(C47:P47) -> 7581.96 | V47: INVERSIONES SHAQSHA S.A.C. | W47: C.H. PARIAC | X47: 110.4
B48: 21:00 | C48: 1161.7 | D48: 3683.6 | E48: 1905.5 | F48: 48.5 | J48: =+DESPACHO_EJECUTADO!FC52+DESPACHO_EJECUTADO!FD52 -> 74 | L48: 0 | M48: 17 | N48: 9.3 | O48: 0 | P48: 679.7 | Q48: =+SUM(C48:P48) -> 7579.3 | V48: KALLPA GENERACION S.A. | W48: C.H. CERRO DEL AGUILA | Y48: 13420.95
B49: 21:30 | C49: 1165.2 | D49: 3683.91 | E49: 1815.4 | F49: 48.5 | J49: =+DESPACHO_EJECUTADO!FC53+DESPACHO_EJECUTADO!FD53 -> 74.5 | L49: 0 | M49: 16.1 | N49: 9.3 | O49: 0 | P49: 667.7 | Q49: =+SUM(C49:P49) -> 7480.61 | W49: M.C.H. CERRO DEL AGUILA | X49: 250.45
B50: 22:00 | C50: 1156.6 | D50: 3671.25 | E50: 1821 | F50: 48.4 | J50: =+DESPACHO_EJECUTADO!FC54+DESPACHO_EJECUTADO!FD54 -> 74.1 | L50: 0 | M50: 16.8 | N50: 9.3 | O50: 0 | P50: 671.9 | Q50: =+SUM(C50:P50) -> 7469.35 | V50: LA VIRGEN | W50: C.H. LA VIRGEN | Y50: 1963.7
B51: 22:30 | C51: 1166.3 | D51: 3607.52 | E51: 1758.4 | F51: 48.5 | J51: =+DESPACHO_EJECUTADO!FC55+DESPACHO_EJECUTADO!FD55 -> 74.5 | L51: 0 | M51: 16.5 | N51: 9.3 | O51: 0 | P51: 615.1 | Q51: =+SUM(C51:P51) -> 7296.12 | V51: MAJA ENERGIA S.A.C. | W51: C.H. RONCADOR | X51: 79.05
B52: 23:00 | C52: 1163 | D52: 3605 | E52: 1681.4 | F52: 0 | J52: =+DESPACHO_EJECUTADO!FC56+DESPACHO_EJECUTADO!FD56 -> 74.5 | L52: 0 | M52: 15.5 | N52: 9.3 | O52: 0 | P52: 575.1 | Q52: =+SUM(C52:P52) -> 7123.8 | V52: ORAZUL ENERGY PERÚ | W52: C.H. CAÑA BRAVA | X52: 126.65
B53: 23:30 | C53: 1167.6 | D53: 3503.8 | E53: 1587.3 | F53: 0 | J53: =+DESPACHO_EJECUTADO!FC57+DESPACHO_EJECUTADO!FD57 -> 75.2 | L53: 0 | M53: 15.9 | N53: 9.3 | O53: 0 | P53: 560.7 | Q53: =+SUM(C53:P53) -> 6919.8 | W53: C.H. CAÑON DEL PATO | Y53: 5564.05
B54: 00:00 | C54: 1167.7 | D54: 3399.52 | E54: 1447.4 | F54: 0 | J54: =+DESPACHO_EJECUTADO!FC58+DESPACHO_EJECUTADO!FD58 -> 75 | L54: 0 | M54: 16.2 | N54: 9.3 | O54: 0 | P54: 556 | Q54: =+SUM(C54:P54) -> 6671.12 | W54: C.H. CARHUAQUERO | Y54: 2014
B55: TOTAL MWh | C55: =SUM(C7:C54)/2 -> 27571.65 | D55: =SUM(D7:D54)/2 -> 80396.045 | E55: =SUM(E7:E54)/2 -> 42097.5 | F55: =SUM(F7:F54)/2 -> 968.4 | G55: =SUM(G7:G54)/2 -> 0 | H55: =SUM(H7:H54)/2 -> 0 | I55: =SUM(I7:I54)/2 -> 0 | J55: =SUM(J7:J54)/2 -> 1778.9 | ... Q55: =SUM(Q7:Q54)/2 -> 172792.62 | W55: C.H. CARHUAQUERO IV | X55: 237.35
B56: % | C56: 16.122478 | D56: 47.011459 | E56: 24.616446 | F56: 0.56627036 | L56: 0.21802344 | M56: 0.2101001 | N56: 0.12668574 | O56: 2.8072455 | P56: 8.3212914 | Q56: 100.00 | V56: ORYGEN PERU S.A.A. | W56: C.H. CALLAHUANCA | Y56: 1900.7
W57: C.H. HER 1 | X57: 14.4
W58: C.H. HUAMPANI | X58: 725.65
W59: C.H. HUINCO | Y59: 2947.4
W60: C.H. MATUCANA | Y60: 3114.95
W61: C.H. MOYOPAMPA | X61: 1514.35
V62: PERUANA DE INVERSIONES EN ENERGIAS RENOVABLES S.A. | W62: C.H. MANTA I | X62: 479.65
V63: SAN GABAN | W63: C.H. SAN GABAN II | Y63: 2656.3
W64: MCH TUPURI | X64: 28.8
V65: SINERSA | W65: C.H. CHANCAY | X65: 478.8
W66: C.H. POECHOS II | X66: 209.1
V67: STATKRAFT S.A | W67: C.H. ARCATA | X67: 49.4
W68: C.H. CAHUA | X68: 314.45
W69: C.H. CHEVES | Y69: 4176.85
W70: C.H. GALLITO CIEGO | Y70: 905.9
W71: C.H. MALPASO | Y71: 1114.45
W72: C.H. OROYA | X72: 110.3
W73: C.H. PACHACHACA | X73: 150.55
W74: C.H. YAUPI | X74: 2603.6
V75: TOTAL MWh | X75: 27571.65 | Y75: 80396.045

Sheet GENERACION RER
B3: martes, 22 de Abril del 2025
B5: GENERACIÓN ELÉCTRICA DE LAS CENTRALES RER (MW)
B6: HORA | C6: AGRO INDUSTRIAL PARAMONGA S.A. | D6: AGROAURORA S.A.C. | E6: AGROINDUSTRIAS SAN JACINTO S.A.A. | F6: ANDEAN POWER S.A.C. | G6: ASOCIACIÓN SANTA LUCIA DE CHACAS | H6: ATRIA ENERGIA S.A.C. | I6: BIOENERGIA DEL CHIRA S.A. | J6: COLCA SOLAR S.A.C. | K6: EGEJUNIN | P6: ELECTRICA YANAPAMPA SAC | Q6: EMPRESA DE GENERACION ELECTRICA CANCHAYLLO SAC | R6: EMPRESA DE GENERACION ELECTRICA RIO BAÑOS S.A.C. | S6: EMPRESA DE GENERACION ELECTRICA SANTA ANA S.A.C. | T6: EMPRESA ELECTRICA AGUA AZUL | U6: EMPRESA ELECTRICA RIO DOBLE | V6: ENERGÍA EÓLICA S.A. | X6: ENERGIA RENOVABLE DEL SUR S.A. | Y6: ENGIE | AD6: GENERACIÓN ANDINA S.A.C. | AF6: GENERADORA DE ENERGÍA DEL PERÚ | AJ6: GR CORTARRAMA SOCIEDAD ANONIMA CERRADA | AK6: GR PAINO SOCIEDAD ANONIMA CERRADA | AL6: GR TARUCA SOCIEDAD ANONIMA CERRADA | AM6: HIDROCAÑETE S.A. | AN6: HUAURA POWER GROUP S.A. | AO6: HYDRO PATAPO S.A.C. | AP6: JOYA SOLAR S.A.C. | AQ6: KONDU SAC | AR6: MAJA ENERGIA S.A.C. | AS6: MAJES ARCUS S.A.C. | AT6: MOQUEGUA FV S.A.C. | AU6: ORAZUL ENERGY PERÚ | AW6: ORYGEN PERU S.A.A. | BB6: PANAMERICANA SOLAR SAC. | BC6: PARQUE EOLICO MARCONA S.A.C. | BD6: PARQUE EOLICO TRES HERMANAS S.A.C. | BE6: PERUANA DE INVERSIONES EN ENERGIAS RENOVABLES S.A. | BF6: PETRAMAS | BJ6: REPARTICIÓN ARCUS S.A.C. | BK6: SAN GABAN | BL6: SDF ENERGIA SAC | BM6: SINERSA | BO6: TACNA SOLAR SAC. | BP6: TOTAL RER
C7: C.T. PARAMONGA | D7: C.T. MAPLE | E7: C.T SAN JACINTO | F7: C.H. CARHUAC | G7: C.H. HUALLIN | H7: C.H. PURMACANA | I7: C.T. CAÑA BRAVA | K7: C.H. HUASAHUASI I | L7: C.H. HUASAHUASI II | M7: C.H. RUNATULLO II | N7: C.H. RUNATULLO III | O7: C.H. STA CRUZ I y II | P7: C.H. YANAPAMPA | Q7: C.H. CANCHAYLLO | R7: C.H. RUCUY | S7: C.H. RENOVANDES H1 | T7: C.H. POTRERO | U7: C.H. LAS PIZARRAS | AD7: C.H. 8 DE AGOSTO | AE7: C.H. EL CARMEN | AF7: C.H. ANGEL I | AG7: C.H. ANGEL II | AH7: C.H. ANGEL III | AI7: C.H. LA JOYA | AM7: C.H. NUEVAIMPERIAL | AN7: C.H. YARUCAYA | AO7: MCH PATAPO | AR7: C.H. RONCADOR | AU7: C.H. CANA BRAVA | AV7: C.H. CARHUAQUERO4 | BA7: C.H. HER 1 | BE7: C.H. MANTA | BF7: C.T. HUAYCOLORO | BG7: C.T. LA GRINGA V | BH7: CTB CALLAO | BI7: CTB. DONA CATALINA | BK7: C.H. TUPURI | BL7: C.T. OQUENDO | BM7: C.H. CHANCAY | BN7: C.H. POECHOS2 | BP7: MW
B8: 0:30 | C8: 16 | F8: 9.3 | G8: 3.1 | K8: 19.8 | M8: 18.5 | N8: 20.2 | O8: 9.7 | P8: 3.3 | Q8: 4.9 | R8: 19.8 | S8: 19.9 | T8: 20 | U8: 19.1 | V8: 18.8 | W8: 35.4 | X8: 108.2 | Y8: 67.6 | Z8: 85.7 | AB8: 8.2 | AC8: 0.7 | AD8: 21 | AE8: 6.9 | AF8: 20.4 | AG8: 20.4 | AH8: 20.2 | AI8: 5.2 | AM8: 3.6 | AN8: 9.3 | AR8: 3.3 | AU8: 4.8 | AV8: 9.9 | AW8: 68.3 | AY8: 87.2 | BA8: 0.6 | BC8: 25.6 | BD8: 64.3 | BE8: 20 | BF8: 4.6 | BH8: 2.4 | BI8: 2.4 | BK8: 1.2 | BM8: 19.8 | BN8: 8.6 | BP8: 938.2
B9: 1:00 | C9: 16 | F9: 5.9 | G9: 3.1 | K9: 19.8 | M9: 18.7 | N9: 20.3 | O9: 9.6 | P9: 3.3 | Q9: 5 | R9: 19.8 | S9: 20.4 | T9: 20 | U9: 19.1 | V9: 23.6 | W9: 46 | X9: 108.1 | Y9: 101.8 | Z9: 90.8 | AB9: 9.2 | AC9: 3.1 | AD9: 21 | AE9: 6.9 | AF9: 20.4 | AG9: 20.4 | AH9: 20.2 | AI9: 5.5 | AM9: 3.6 | AN9: 9.3 | AR9: 3.4 | AU9: 4.7 | AV9: 9.9 | AW9: 85.5 | AY9: 96 | BA9: 0.6 | BC9: 27.3 | BD9: 69.8 | BE9: 20 | BF9: 4.6 | BH9: 2.4 | BI9: 2.4 | BK9: 1.2 | BM9: 19.9 | BN9: 8.5 | BP9: 1027.1
B10: 1:30 | C10: 16 | F10: 6 | G10: 3.1 | K10: 19.8 | M10: 18.6 | N10: 20.3 | O10: 9.6 | P10: 3.3 | Q10: 5 | R10: 20 | S10: 20.2 | T10: 20 | U10: 19.1 | V10: 16.9 | W10: 39.4 | X10: 102.2 | Y10: 88.8 | Z10: 91.9 | AB10: 8.4 | AC10: 5 | AD10: 21 | AE10: 6.9 | AF10: 20.4 | AG10: 20.4 | AH10: 20.2 | AI10: 5.5 | AM10: 3.6 | AN10: 9.3 | AR10: 3.4 | AU10: 4.7 | AV10: 9.9 | AW10: 88.1 | AY10: 100.7 | BA10: 0.6 | BC10: 25.2 | BD10: 71 | BE10: 20 | BF10: 4.6 | BH10: 2.4 | BI10: 2.4 | BK10: 1.2 | BM10: 20 | BN10: 8.6 | BP10: 1003.7
B11: 2:00 | C11: 17 | F11: 5.9 | G11: 3.1 | K11: 19.8 | M11: 18.5 | N11: 20.2 | O11: 9.6 | P11: 3.3 | Q11: 5 | R11: 20 | S11: 19.8 | T11: 20 | U11: 19.1 | V11: 11.3 | W11: 22.5 | X11: 96.9 | Y11: 86.2 | Z11: 92.2 | AB11: 7.9 | AC11: 1.7 | AD11: 21 | AE11: 6.9 | AF11: 20.4 | AG11: 20.4 | AH11: 20.2 | AI11: 5.5 | AL11: 0.6 | AM11: 3.6 | AN11: 9.3 | AR11: 3.4 | AU11: 4.7 | AV11: 9.9 | AW11: 70.5 | AY11: 81.4 | BA11: 0.6 | BC11: 27 | BD11: 69.2 | BE11: 20 | BF11: 4.6 | BH11: 2.4 | BI11: 2.4 | BK11: 1.2 | BM11: 20 | BN11: 8.7 | BP11: 933.9
B12: 2:30 | C12: 17 | F12: 5.7 | G12: 3.1 | K12: 19.8 | M12: 18.5 | N12: 20.3 | O12: 9.6 | P12: 3.3 | Q12: 5 | R12: 20 | S12: 20.4 | T12: 20 | U12: 19.1 | V12: 11.4 | W12: 19.9 | X12: 88.6 | Y12: 90.3 | Z12: 88 | AB12: 8.1 | AC12: 3.3 | AD12: 21 | AE12: 6.9 | AF12: 20.4 | AG12: 20.4 | AH12: 20.2 | AI12: 5.5 | AL12: 0.3 | AM12: 3.6 | AN12: 9.3 | AR12: 3.4 | AU12: 4.8 | AV12: 9.8 | AW12: 55.5 | AY12: 61.1 | BA12: 0.6 | BC12: 24.7 | BD12: 66.7 | BE12: 20 | BF12: 4.6 | BH12: 2.4 | BI12: 2.4 | BK12: 1.2 | BM12: 20 | BN12: 8.6 | BP12: 884.8
B13: 3:00 | C13: 16.7 | F13: 5.7 | G13: 3.1 | K13: 19.8 | M13: 18.4 | N13: 20.2 | O13: 9.6 | P13: 3.3 | Q13: 4.9 | R13: 20 | S13: 20 | T13: 20 | U13: 19.1 | V13: 16 | W13: 25.1 | X13: 89.4 | Y13: 100.4 | Z13: 89.4 | AB13: 11.8 | AC13: 3.5 | AD13: 21 | AE13: 6.9 | AF13: 20.4 | AG13: 20.4 | AH13: 20.2 | AI13: 5.5 | AM13: 3.6 | AN13: 9.3 | AR13: 3.4 | AU13: 4.8 | AV13: 9.9 | AW13: 67.7 | AY13: 57.3 | BA13: 0.6 | BC13: 21.6 | BD13: 60 | BE13: 20 | BF13: 4.6 | BH13: 2.4 | BI13: 2.4 | BK13: 1.2 | BM13: 20 | BN13: 8.7 | BP13: 908.3
B14: 3:30 | C14: 16.9 | F14: 5.7 | G14: 3.1 | K14: 19.8 | M14: 18.3 | N14: 20.3 | O14: 9.6 | P14: 3.3 | Q14: 4.9 | R14: 20 | S14: 20.2 | T14: 20 | U14: 19.1 | V14: 27.5 | W14: 26.7 | X14: 95.5 | Y14: 94.1 | Z14: 88.5 | AB14: 14.9 | AC14: 3 | AD14: 21 | AE14: 6.9 | AF14: 20.4 | AG14: 20.4 | AH14: 20.2 | AI14: 5 | AM14: 3.6 | AN14: 9.3 | AR14: 3.4 | AU14: 4.6 | AV14: 9.9 | AW14: 57.2 | AY14: 63 | BA14: 0.6 | BC14: 20.7 | BD14: 59.8 | BE14: 20 | BF14: 4.6 | BH14: 2.4 | BI14: 2.4 | BK14: 1.2 | BM14: 20 | BN14: 8.6 | BP14: 916.6
B15: 4:00 | C15: 17 | F15: 5.8 | G15: 3.1 | K15: 19.8 | M15: 18.4 | N15: 20.3 | O15: 9.6 | P15: 3.3 | Q15: 4.9 | R15: 19.9 | S15: 20.3 | T15: 20 | U15: 19.1 | V15: 23.2 | W15: 36.3 | X15: 92.8 | Y15: 93.1 | Z15: 88.5 | AB15: 12.2 | AC15: 2.8 | AD15: 21 | AE15: 6.8 | AF15: 20.4 | AG15: 20.4 | AH15: 20.2 | AI15: 5.1 | AM15: 3.6 | AN15: 9.3 | AR15: 3.4 | AU15: 4.8 | AV15: 9.9 | AW15: 49.8 | AY15: 58.7 | BA15: 0.6 | BC15: 23.2 | BD15: 57.4 | BE15: 20 | BF15: 4.6 | BH15: 2.4 | BI15: 2.4 | BK15: 1.2 | BM15: 20 | BN15: 8.7 | BP15: 904.3
B16: 4:30 | C16: 16 | F16: 5.8 | G16: 3.1 | K16: 19.8 | M16: 18.2 | N16: 20.2 | O16: 9.7 | P16: 2.8 | Q16: 4.9 | R16: 20 | S16: 20.1 | T16: 20 | U16: 19.1 | V16: 28.2 | W16: 34.6 | X16: 96.5 | Y16: 62.4 | Z16: 79.7 | AB16: 6.5 | AC16: 2 | AD16: 21 | AE16: 6.8 | AF16: 20.4 | AG16: 20.4 | AH16: 20.2 | AI16: 5 | AM16: 3.6 | AN16: 9.3 | AR16: 3.4 | AU16: 4.8 | AV16: 9.9 | AW16: 35.9 | AY16: 37.1 | BA16: 0.6 | BC16: 23.2 | BD16: 52.4 | BE16: 20 | BF16: 4.6 | BH16: 2.4 | BI16: 2.4 | BK16: 1.2 | BM16: 20 | BN16: 8.6 | BP16: 822.8
B17: 5:00 | C17: 16 | F17: 5.8 | G17: 3.1 | K17: 19.8 | M17: 18 | N17: 20.3 | O17: 9.7 | P17: 3.2 | Q17: 5.1 | R17: 20 | S17: 20.4 | T17: 20 | U17: 19.1 | V17: 30.2 | W17: 42.3 | X17: 100.8 | Y17: 54.7 | Z17: 81.4 | AB17: 6.7 | AC17: 1.9 | AD17: 21 | AE17: 6.8 | AF17: 20.4 | AG17: 20.4 | AH17: 20.2 | AI17: 4.9 | AM17: 3.7 | AN17: 9.3 | AR17: 3.4 | AU17: 4.7 | AV17: 9.9 | AW17: 16.2 | AY17: 17.8 | BA17: 0.6 | BC17: 22.1 | BD17: 53.6 | BE17: 20 | BF17: 4.6 | BH17: 2.4 | BI17: 2.4 | BK17: 1.2 | BM17: 20 | BN17: 8.6 | BP17: 792.7
B18: 5:30 | C18: 16 | F18: 5.7 | G18: 3 | K18: 19.8 | M18: 18.2 | N18: 20.3 | O18: 9.7 | P18: 3.2 | Q18: 5 | R18: 19.9 | S18: 20.3 | T18: 20 | U18: 19.1 | V18: 30.2 | W18: 39.1 | X18: 95.4 | Y18: 39.8 | Z18: 68.6 | AB18: 3.6 | AC18: 1.9 | AD18: 21 | AE18: 6.8 | AF18: 20.4 | AG18: 20.4 | AH18: 20.2 | AI18: 4.9 | AM18: 3.6 | AN18: 9.3 | AR18: 3.3 | AU18: 5.4 | AV18: 9.9 | AW18: 12 | AY18: 10 | BA18: 0.6 | BC18: 21.1 | BD18: 50.2 | BE18: 20 | BF18: 4.6 | BH18: 2.4 | BI18: 2.4 | BK18: 1.2 | BM18: 20 | BN18: 8.6 | BP18: 737.1
B19: 6:00 | C19: 16.5 | F19: 5.8 | G19: 3.1 | K19: 19.8 | M19: 18.2 | N19: 20.3 | O19: 9.7 | P19: 3.3 | Q19: 5 | R19: 20 | S19: 20.4 | T19: 20 | U19: 19.1 | V19: 30.2 | W19: 35.1 | X19: 107 | Y19: 24.7 | Z19: 45.8 | AB19: 4 | AC19: 0.5 | AD19: 21 | AE19: 6.8 | AF19: 20.4 | AG19: 20.4 | AH19: 20.2 | AI19: 4.9 | AM19: 3.6 | AN19: 9.3 | AR19: 3.3 | AT19: 0.4 | AU19: 5.3 | AV19: 9.9 | AW19: 13.4 | AX19: 0.8 | AY19: 5.9 | AZ19: 0.6 | BA19: 0.6 | BB19: 0.3 | BC19: 20.4 | BD19: 51.9 | BE19: 20 | BF19: 4.6 | BH19: 2.4 | BI19: 2.4 | BK19: 1.2 | BM19: 20 | BN19: 8.7 | BP19: 707.2
B20: 6:30 | C20: 16 | F20: 5.8 | G20: 3.1 | K20: 19.8 | M20: 18.2 | N20: 20.3 | O20: 9.6 | P20: 3.3 | Q20: 5 | R20: 19.8 | S20: 20.3 | T20: 20 | U20: 19.1 | V20: 30.1 | W20: 23.4 | X20: 120.1 | Y20: 22.7 | Z20: 38.7 | AA20: 3.9 | AB20: 2.3 | AC20: 0.6 | AD20: 21 | AE20: 7.6 | AF20: 20.4 | AG20: 20.4 | AH20: 20.2 | AI20: 4.8 | AJ20: 1.9 | AK20: 0.2 | AM20: 3.6 | AN20: 9.3 | AP20: 8.96 | AR20: 3.3 | AT20: 0.9 | AU20: 5.2 | AV20: 9.8 | AW20: 17.9 | AX20: 5.4 | AY20: 9.2 | AZ20: 3.7 | BA20: 0.6 | BB20: 0.9 | BC20: 22.7 | BD20: 53.6 | BE20: 20 | BF20: 4.6 | BH20: 2.4 | BI20: 2.4 | BJ20: 0.3 | BK20: 1.2 | BM20: 19.9 | BN20: 8.6 | BO20: 6 | BP20: 739.06
B21: 7:00 | C21: 7.2 | F21: 9.3 | G21: 3 | K21: 19.8 | M21: 18.2 | N21: 20.3 | O21: 9.6 | P21: 3.3 | Q21: 5 | R21: 19.9 | S21: 20.1 | T21: 20 | U21: 19.1 | V21: 30.1 | W21: 19.1 | X21: 116.8 | Y21: 30.3 | Z21: 52.6 | AA21: 14 | AB21: 4.8 | AC21: 0.7 | AD21: 21 | AE21: 8.1 | AF21: 20.4 | AG21: 20.4 | AH21: 20.2 | AI21: 5.6 | AJ21: 11 | AK21: 0.1 | AM21: 3.6 | AN21: 9.3 | AP21: 17.2 | AR21: 3.2 | AS21: 0.8 | AT21: 1.4 | AU21: 5.4 | AV21: 10 | AW21: 56.4 | AX21: 7.8 | AY21: 34.7 | AZ21: 5.6 | BA21: 0.6 | BB21: 1.2 | BC21: 23.2 | BD21: 55.2 | BE21: 20 | BF21: 4.6 | BH21: 2.4 | BI21: 2.4 | BJ21: 3 | BK21: 1.2 | BM21: 20 | BN21: 8.7 | BO21: 14.3 | BP21: 862.2
B22: 7:30 | C22: 7.3 | F22: 10.5 | G22: 3.1 | J22: 0.1 | K22: 19.8 | M22: 18.2 | N22: 20.3 | O22: 9.6 | P22: 3.3 | Q22: 4.9 | R22: 20 | S22: 20.4 | T22: 20 | U22: 19.1 | V22: 29.6 | W22: 24.5 | X22: 108.8 | Y22: 27.4 | Z22: 48.8 | AA22: 19.5 | AB22: 2.6 | AC22: 1.5 | AD22: 21 | AE22: 8.2 | AF22: 20.4 | AG22: 20.4 | AH22: 20.2 | AI22: 6.8 | AJ22: 11.8 | AM22: 3.6 | AN22: 9.3 | AP22: 21.55 | AR22: 3.3 | AS22: 1.3 | AT22: 1.7 | AU22: 5.4 | AV22: 10 | AW22: 71.9 | AX22: 10.9 | AY22: 72.5 | AZ22: 7.9 | BA22: 0.6 | BB22: 1.3 | BC22: 22.8 | BD22: 57.5 | BE22: 20 | BF22: 4.6 | BH22: 2.4 | BI22: 2.4 | BJ22: 5.9 | BK22: 1.2 | BM22: 20 | BN22: 8.6 | BO22: 14.8 | BP22: 929.55
B23: 8:00 | C23: 4.7 | F23: 10.5 | G23: 3 | J23: 0.2 | K23: 19.8 | M23: 18.2 | N23: 20.3 | O23: 9.6 | P23: 3.2 | Q23: 5.1 | R23: 20 | S23: 20.6 | T23: 20 | U23: 19 | V23: 29.2 | W23: 35.5 | X23: 109.4 | Y23: 30.7 | Z23: 67.7 | AA23: 31.9 | AB23: 4.9 | AC23: 1.4 | AD23: 21 | AE23: 8.1 | AF23: 20.4 | AG23: 20.4 | AH23: 20.2 | AI23: 7.7 | AJ23: 12.3 | AL23: 0.2 | AM23: 3.6 | AN23: 9.3 | AP23: 38.53 | AR23: 3.1 | AS23: 2.1 | AT23: 2.3 | AU23: 5.4 | AV23: 10 | AW23: 58.6 | AX23: 9.1 | AY23: 56.6 | AZ23: 8.5 | BA23: 0.6 | BB23: 1.9 | BC23: 22.4 | BD23: 66.9 | BE23: 20 | BF23: 4.6 | BH23: 2.4 | BI23: 2.4 | BJ23: 6.5 | BK23: 1.2 | BM23: 20 | BN23: 8.7 | BO23: 10.7 | BP23: 970.63
B24: 8:30 | C24: 4.3 | F24: 10.5 | G24: 3.1 | J24: 0.7 | K24: 19.8 | M24: 18.2 | N24: 20.2 | O24: 9.6 | P24: 3.3 | Q24: 5.1 | R24: 20 | S24: 20.1 | T24: 20 | U24: 19.1 | V24: 28.2 | W24: 33.6 | X24: 113.1 | Y24: 32.1 | Z24: 70.4 | AA24: 33.1 | AB24: 5.3 | AC24: 2.9 | AD24: 21 | AE24: 8 | AF24: 20.4 | AG24: 20.4 | AH24: 20.2 | AI24: 7.3 | AJ24: 13 | AK24: 0.4 | AL24: 1.6 | AM24: 3.5 | AN24: 9.3 | AP24: 106.28 | AQ24: 0.1 | AR24: 3.2 | AS24: 1.9 | AT24: 2.7 | AU24: 5.4 | AV24: 9.9 | AW24: 71 | AX24: 12.6 | AY24: 54.9 | AZ24: 11.5 | BA24: 0.6 | BB24: 2.5 | BC24: 23.1 | BD24: 67.3 | BE24: 20 | BF24: 4.7 | BH24: 2.4 | BI24: 1.2 | BJ24: 9.8 | BK24: 1.2 | BM24: 20 | BN24: 8.7 | BO24: 14.1 | BP24: 1072.88
B25: 9:00 | C25: 4.2 | F25: 10.4 | G25: 3 | J25: 0.9 | K25: 19.8 | M25: 18.5 | N25: 20.3 | O25: 9.6 | P25: 3.3 | Q25: 5.1 | R25: 19.8 | S25: 20.6 | T25: 20 | U25: 19.1 | V25: 25.5 | W25: 31.7 | X25: 107.3 | Y25: 29.5 | Z25: 72 | AA25: 34.6 | AB25: 6 | AC25: 1.7 | AD25: 21 | AE25: 8 | AF25: 20.4 | AG25: 20.4 | AH25: 20.2 | AI25: 6.8 | AJ25: 35.3 | AK25: 1.8 | AL25: 1.9 | AM25: 3.5 | AN25: 9.3 | AP25: 209.24 | AQ25: 0.2 | AR25: 3.2 | AS25: 2.2 | AT25: 3.8 | AU25: 5.4 | AV25: 10 | AW25: 80.4 | AX25: 25.3 | AY25: 72.6 | AZ25: 21.1 | BA25: 0.6 | BB25: 4 | BC25: 22.3 | BD25: 76.4 | BE25: 20 | BF25: 4.7 | BH25: 2.4 | BI25: 1.2 | BJ25: 12.3 | BK25: 1.2 | BM25: 19.9 | BN25: 8.5 | BO25: 15.7 | BP25: 1254.14
B26: 9:30 | C26: 10 | F26: 10.4 | G26: 3.1 | J26: 1 | K26: 19.8 | M26: 18.4 | N26: 20.2 | O26: 9.6 | P26: 2.7 | Q26: 5 | R26: 20 | S26: 20.3 | T26: 20 | U26: 19.1 | V26: 21.8 | W26: 26 | X26: 90.4 | Y26: 66.2 | Z26: 84.4 | AA26: 33.2 | AB26: 3.8 | AC26: 1.4 | AD26: 21 | AE26: 8.1 | AF26: 20.4 | AG26: 20.4 | AH26: 20.2 | AI26: 3.1 | AJ26: 71.8 | AK26: 0.8 | AL26: 1.3 | AM26: 3.5 | AN26: 9.3 | AP26: 214.2 | AQ26: 0.2 | AR26: 3.2 | AS26: 3.6 | AT26: 5.1 | AU26: 5.5 | AV26: 9.8 | AW26: 93.1 | AX26: 34.2 | AY26: 87 | AZ26: 25.8 | BA26: 0.6 | BB26: 5.4 | BC26: 21.4 | BD26: 73 | BE26: 20 | BF26: 4.7 | BH26: 2.4 | BI26: 1.2 | BJ26: 12.5 | BK26: 1.2 | BM26: 20 | BN26: 8.7 | BO26: 18 | BP26: 1357.5
B27: 10:00 | C27: 16.3 | F27: 10.4 | G27: 3.1 | J27: 1.1 | K27: 19.8 | M27: 18.7 | N27: 20.3 | O27: 9.6 | P27: 2.3 | Q27: 5 | R27: 20 | S27: 20.4 | T27: 20 | U27: 19.1 | V27: 21.1 | W27: 26.5 | X27: 76.2 | Y27: 70.7 | Z27: 84.6 | AA27: 33.1 | AB27: 11.2 | AC27: 6.4 | AD27: 21 | AE27: 8.1 | AF27: 20.4 | AG27: 20.4 | AH27: 20.2 | AI27: 7.2 | AJ27: 72.1 | AK27: 0.7 | AL27: 1.3 | AM27: 3.5 | AN27: 9.3 | AP27: 220.96 | AQ27: 0.3 | AR27: 3.2 | AS27: 9.3 | AT27: 5.3 | AU27: 5.5 | AV27: 10 | AW27: 78.2 | AX27: 90.8 | AY27: 71.8 | AZ27: 71.8 | BA27: 0.6 | BB27: 6.2 | BC27: 23.1 | BD27: 71.9 | BE27: 20 | BF27: 4.7 | BH27: 2.4 | BI27: 1.2 | BJ27: 14.7 | BK27: 1.2 | BM27: 20 | BN27: 8.7 | BO27: 14.8 | BP27: 1456.76
B28: 10:30 | C28: 16.2 | F28: 10.4 | G28: 3.1 | J28: 1.2 | K28: 19.8 | M28: 18.7 | N28: 20.3 | O28: 9.6 | P28: 2.9 | Q28: 5 | R28: 20 | S28: 20.5 | T28: 20 | U28: 19.1 | V28: 18.9 | W28: 26.4 | X28: 81.7 | Y28: 61.8 | Z28: 68.6 | AA28: 32.7 | AB28: 13.6 | AC28: 6.8 | AD28: 21 | AE28: 8.1 | AF28: 20.4 | AG28: 20.4 | AH28: 20.2 | AI28: 7.1 | AJ28: 72.8 | AK28: 1.7 | AL28: 2.4 | AM28: 3.5 | AN28: 9.3 | AP28: 226.09 | AQ28: 0.3 | AR28: 3.1 | AS28: 16.6 | AT28: 6 | AU28: 5.4 | AV28: 9.9 | AW28: 63.1 | AX28: 130.1 | AY28: 62.4 | AZ28: 94.6 | BA28: 0.6 | BB28: 7.2 | BC28: 16.1 | BD28: 70.5 | BE28: 19.9 | BF28: 4.6 | BH28: 2.4 | BI28: 1.2 | BJ28: 15.7 | BK28: 1.2 | BM28: 20 | BN28: 8.6 | BO28: 12.1 | BP28: 1481.89
B29: 11:00 | C29: 16.2 | F29: 10.4 | G29: 3.1 | J29: 1.3 | K29: 19.8 | M29: 18.5 | N29: 20.3 | O29: 9.6 | P29: 3 | Q29: 5.1 | R29: 20 | S29: 20.4 | T29: 20 | U29: 19.1 | V29: 17.8 | W29: 55.7 | X29: 83.3 | Y29: 66.3 | Z29: 72.4 | AA29: 32.6 | AB29: 14.1 | AC29: 7.9 | AD29: 21 | AE29: 8.1 | AF29: 20.4 | AG29: 20.4 | AH29: 20.2 | AI29: 9 | AJ29: 75.4 | AK29: 2.5 | AL29: 3.4 | AM29: 3.4 | AN29: 9.3 | AP29: 193.12 | AQ29: 0.3 | AR29: 2.9 | AS29: 17.6 | AT29: 6.9 | AU29: 5.5 | AV29: 9.9 | AW29: 60.3 | AX29: 132.6 | AY29: 54.7 | AZ29: 96 | BA29: 0.6 | BB29: 8.3 | BC29: 15 | BD29: 60.3 | BE29: 20 | BF29: 4.5 | BH29: 2.4 | BI29: 1.2 | BJ29: 16.8 | BK29: 1.2 | BM29: 20 | BN29: 8.8 | BO29: 11.9 | BP29: 1480.82
B30: 11:30 | C30: 16 | F30: 10.4 | G30: 3.1 | J30: 1.3 | K30: 19.8 | M30: 18.6 | N30: 20.3 | O30: 9.6 | P30: 3.2 | Q30: 5.1 | R30: 20 | S30: 20.5 | T30: 20 | U30: 19.1 | V30: 18.1 | W30: 71.5 | X30: 89.6 | Y30: 75.9 | Z30: 82.1 | AA30: 32.9 | AB30: 14.6 | AC30: 7.9 | AD30: 21 | AE30: 8.2 | AF30: 20.4 | AG30: 20.4 | AH30: 20.2 | AI30: 9.1 | AJ30: 75.4 | AK30: 2.9 | AL30: 3.3 | AM30: 3.6 | AN30: 9.3 | AP30: 150.23 | AQ30: 0.4 | AR30: 3.1 | AS30: 17.8 | AT30: 11.3 | AU30: 5.4 | AV30: 9.8 | AW30: 62.8 | AX30: 134 | AY30: 50.2 | AZ30: 97.5 | BA30: 0.6 | BB30: 13.2 | BC30: 13.8 | BD30: 57.8 | BE30: 20 | BF30: 4.5 | BH30: 2.4 | BI30: 1.2 | BJ30: 17.4 | BK30: 1.2 | BM30: 20 | BN30: 8.6 | BO30: 15.5 | BP30: 1492.13
B31: 12:00 | C31: 16 | F31: 10.4 | G31: 3.1 | J31: 1.3 | K31: 19.8 | M31: 18.5 | N31: 20.2 | O31: 9.6 | P31: 3.3 | Q31: 5 | R31: 20 | S31: 20.1 | T31: 20 | U31: 19.1 | V31: 16.6 | W31: 72 | X31: 85.9 | Y31: 74.4 | Z31: 83.1 | AA31: 32.7 | AB31: 16 | AC31: 7.5 | AD31: 21 | AE31: 8.2 | AF31: 20.4 | AG31: 20.4 | AH31: 20.2 | AI31: 9.3 | AJ31: 74.5 | AK31: 3.7 | AL31: 5.8 | AM31: 3.7 | AN31: 9.3 | AP31: 111.12 | AQ31: 0.4 | AR31: 3.2 | AS31: 17.8 | AT31: 13.6 | AU31: 5.3 | AV31: 9.9 | AW31: 60.3 | AX31: 132.3 | AY31: 43.6 | AZ31: 96.9 | BA31: 0.6 | BB31: 16.6 | BC31: 16.8 | BD31: 62.4 | BE31: 20 | BF31: 4.5 | BH31: 2.4 | BI31: 1.2 | BJ31: 17.7 | BK31: 1.2 | BM31: 20 | BN31: 8.6 | BO31: 17.4 | BP31: 1454.92
B32: 12:30 | C32: 15.5 | F32: 10.4 | G32: 3.1 | J32: 1.3 | K32: 19.8 | M32: 18.3 | N32: 20.3 | O32: 9.7 | P32: 3.3 | Q32: 4.9 | R32: 19.9 | S32: 20.1 | T32: 20 | U32: 19.1 | V32: 20.5 | W32: 67.5 | X32: 85 | Y32: 74.1 | Z32: 83.1 | AA32: 32.9 | AB32: 16.3 | AC32: 7.7 | AD32: 21 | AE32: 8.2 | AF32: 20.4 | AG32: 20.4 | AH32: 20.2 | AI32: 8.9 | AJ32: 76.9 | AK32: 1.5 | AL32: 2.6 | AM32: 3.7 | AN32: 9.3 | AP32: 232.33 | AQ32: 0.4 | AR32: 3.2 | AS32: 17.5 | AT32: 13.7 | AU32: 5.4 | AV32: 10 | AW32: 59 | AX32: 133 | AY32: 51.8 | AZ32: 96.2 | BA32: 0.6 | BB32: 16.6 | BC32: 19.7 | BD32: 71.4 | BE32: 19.8 | BF32: 4.5 | BH32: 2.4 | BI32: 1.2 | BJ32: 17.6 | BK32: 1.2 | BM32: 20 | BN32: 8.7 | BO32: 17 | BP32: 1589.13
B33: 13:00 | C33: 14.5 | F33: 10.4 | G33: 3.1 | J33: 1.3 | K33: 19.9 | M33: 18.3 | N33: 20.3 | O33: 9.6 | P33: 3.3 | Q33: 5 | R33: 19.6 | S33: 20.5 | T33: 20 | U33: 19.1 | V33: 18 | W33: 72.4 | X33: 87.2 | Y33: 67.5 | Z33: 73.6 | AA33: 32.9 | AB33: 12.9 | AC33: 6.4 | AD33: 21 | AE33: 8.2 | AF33: 20.4 | AG33: 20.4 | AH33: 20.2 | AI33: 8.4 | AJ33: 75.2 | AK33: 1.6 | AL33: 2 | AM33: 3.7 | AN33: 9.3 | AP33: 242.41 | AQ33: 0.4 | AR33: 3.2 | AS33: 17 | AT33: 13.6 | AU33: 5.3 | AV33: 9.9 | AW33: 76.7 | AX33: 131.4 | AY33: 71.9 | AZ33: 95 | BA33: 0.6 | BB33: 16.5 | BC33: 22.8 | BD33: 66.3 | BE33: 20 | BF33: 4.5 | BH33: 2.4 | BI33: 1.2 | BJ33: 16.9 | BK33: 1.2 | BM33: 19.7 | BN33: 8.7 | BO33: 16.9 | BP33: 1610.71
B34: 13:30 | C34: 15.2 | F34: 10.4 | G34: 3 | J34: 1.3 | K34: 19.8 | M34: 18.1 | N34: 20.2 | O34: 9.4 | P34: 3.3 | Q34: 5 | R34: 20 | S34: 20 | T34: 20 | U34: 19.1 | V34: 19.1 | W34: 73.2 | X34: 95.6 | Y34: 59 | Z34: 64.1 | AA34: 33.1 | AB34: 11.3 | AC34: 5.8 | AD34: 21 | AE34: 8.2 | AF34: 20.4 | AG34: 20.4 | AH34: 20.2 | AI34: 8.8 | AJ34: 72 | AK34: 1 | AL34: 1.4 | AM34: 3.7 | AN34: 9.3 | AP34: 229.34 | AQ34: 0.3 | AR34: 3.1 | AS34: 17.1 | AT34: 13.5 | AU34: 5.4 | AV34: 9.9 | AW34: 99.5 | AX34: 128.8 | AY34: 91.8 | AZ34: 92.5 | BA34: 0.6 | BB34: 16.7 | BC34: 23.2 | BD34: 71.3 | BE34: 20 | BF34: 4.5 | BH34: 2.4 | BI34: 1.2 | BJ34: 15.8 | BK34: 1.2 | BM34: 20 | BN34: 8.6 | BO34: 17 | BP34: 1626.14
B35: 14:00 | C35: 14.9 | F35: 10.4 | G35: 3.1 | J35: 1.2 | K35: 19.8 | M35: 18.3 | N35: 20.3 | O35: 6 | P35: 2.6 | Q35: 4.9 | R35: 20 | S35: 20.4 | T35: 20 | U35: 19.1 | V35: 24.7 | W35: 74 | X35: 92.2 | Y35: 58.7 | Z35: 64.9 | AA35: 32.7 | AB35: 11.4 | AC35: 5.5 | AD35: 21 | AE35: 8.2 | AF35: 20.4 | AG35: 20.4 | AH35: 20.2 | AI35: 8.5 | AJ35: 77.2 | AM35: 3.6 | AN35: 9.3 | AP35: 222.11 | AQ35: 0.2 | AR35: 3.2 | AS35: 15.5 | AT35: 13.8 | AU35: 5.4 | AV35: 9.9 | AW35: 123 | AX35: 131.3 | AY35: 108 | AZ35: 95.2 | BA35: 0.6 | BB35: 16.8 | BC35: 23.8 | BD35: 69.6 | BE35: 20 | BF35: 4.3 | BH35: 2.4 | BI35: 1.4 | BJ35: 15.3 | BK35: 1.2 | BM35: 20 | BN35: 8.8 | BO35: 17 | BP35: 1662.71
B36: 14:30 | C36: 15 | F36: 10.4 | G36: 3 | J36: 1.1 | K36: 19.8 | M36: 18.1 | N36: 20.3 | O36: 6 | P36: 2.6 | Q36: 5 | R36: 20 | S36: 20.3 | T36: 20 | U36: 19.1 | V36: 28.5 | W36: 70.9 | X36: 90.7 | Y36: 59 | Z36: 64.7 | AA36: 31.8 | AB36: 11.2 | AC36: 5.6 | AD36: 21 | AE36: 8.2 | AF36: 20.4 | AG36: 20.4 | AH36: 20.2 | AI36: 8.4 | AJ36: 76.5 | AK36: 1.4 | AL36: 0.7 | AM36: 3.6 | AN36: 9.3 | AP36: 225.02 | AQ36: 0.2 | AR36: 3.2 | AS36: 14.4 | AT36: 13.8 | AU36: 5.5 | AV36: 9.9 | AW36: 137.1 | AX36: 130.3 | AY36: 111.8 | AZ36: 93.1 | BA36: 0.6 | BB36: 16.8 | BC36: 22.7 | BD36: 73.5 | BE36: 20 | BF36: 3.7 | BH36: 2.4 | BI36: 2.4 | BJ36: 13 | BK36: 1.2 | BM36: 20 | BN36: 8.8 | BO36: 16.9 | BP36: 1679.52
B37: 15:00 | C37: 15 | F37: 10.4 | G37: 3.1 | J37: 0.9 | K37: 19.8 | M37: 18 | N37: 20.2 | O37: 6.1 | P37: 3.3 | Q37: 5.1 | R37: 20 | S37: 20.2 | T37: 20 | U37: 19 | V37: 29.9 | W37: 72.4 | X37: 77.3 | Y37: 58.3 | Z37: 64.1 | AA37: 31.7 | AB37: 11.8 | AC37: 5.9 | AD37: 21 | AE37: 8.2 | AF37: 20.4 | AG37: 20.4 | AH37: 20.2 | AI37: 8.4 | AJ37: 74.6 | AM37: 3.6 | AN37: 9.3 | AP37: 235.74 | AQ37: 0.1 | AR37: 3.2 | AS37: 12.5 | AT37: 13.6 | AU37: 5.5 | AV37: 9.9 | AW37: 134 | AX37: 130.8 | AY37: 111.8 | AZ37: 94.4 | BA37: 0.6 | BB37: 16.4 | BC37: 21.6 | BD37: 70.4 | BE37: 20 | BF37: 4.4 | BH37: 2.4 | BI37: 2.4 | BJ37: 12.1 | BK37: 1.2 | BM37: 20 | BN37: 8.8 | BO37: 17.1 | BP37: 1667.54
B38: 15:30 | C38: 16.8 | F38: 10.4 | G38: 3.1 | J38: 0.8 | K38: 19.8 | M38: 18.2 | N38: 20.3 | O38: 9.6 | P38: 3.3 | Q38: 5 | R38: 20 | S38: 20.4 | T38: 20 | U38: 19.1 | V38: 30.1 | W38: 72.3 | X38: 75.1 | Y38: 60.2 | Z38: 64.4 | AA38: 32.3 | AB38: 10.4 | AC38: 5.8 | AD38: 21 | AE38: 8.2 | AF38: 20.4 | AG38: 20.4 | AH38: 20.2 | AI38: 8.3 | AJ38: 71.2 | AL38: 0.6 | AM38: 3.6 | AN38: 9.3 | AP38: 222.06 | AQ38: 0.1 | AR38: 3.2 | AS38: 10.4 | AT38: 12.8 | AU38: 5.5 | AV38: 9.8 | AW38: 146.9 | AX38: 122.4 | AY38: 113.5 | AZ38: 86.5 | BA38: 0.6 | BB38: 15.6 | BC38: 21.5 | BD38: 63.9 | BE38: 20 | BF38: 4.4 | BH38: 2.4 | BI38: 2.4 | BJ38: 9.7 | BK38: 1.2 | BM38: 20 | BN38: 8.7 | BP38: 1624.16
B39: 16:00 | C39: 17.6 | F39: 10.4 | G39: 3 | J39: 0.6 | K39: 19.8 | M39: 18.1 | N39: 20.3 | O39: 9.6 | P39: 3.3 | Q39: 5 | R39: 20 | S39: 20.5 | T39: 20 | U39: 19.1 | V39: 29.8 | W39: 73.2 | X39: 82.1 | Y39: 59.7 | Z39: 62.2 | AA39: 26 | AB39: 10.6 | AC39: 7.8 | AD39: 21 | AE39: 8.2 | AF39: 20.4 | AG39: 20.4 | AH39: 20.2 | AI39: 8.3 | AJ39: 60.2 | AK39: 1 | AL39: 1.8 | AM39: 3.6 | AN39: 9.3 | AP39: 200.86 | AQ39: 0.1 | AR39: 3.2 | AS39: 7.9 | AT39: 11.3 | AU39: 5.4 | AV39: 9.9 | AW39: 153.7 | AX39: 102.3 | AY39: 119.4 | AZ39: 82.2 | BA39: 0.6 | BB39: 13.7 | BC39: 20.9 | BD39: 68.5 | BE39: 20 | BF39: 4.5 | BH39: 2.4 | BI39: 2.4 | BJ39: 7.3 | BK39: 1.2 | BM39: 20 | BN39: 8.7 | BP39: 1579.56
B40: 16:30 | C40: 16.5 | F40: 10.4 | G40: 3.1 | J40: 0.4 | K40: 19.8 | M40: 18.3 | N40: 20.3 | O40: 9.6 | P40: 3.3 | Q40: 5 | R40: 20 | S40: 20.7 | T40: 20 | U40: 19.1 | V40: 29.8 | W40: 77.8 | X40: 92.5 | Y40: 61.6 | Z40: 62.7 | AA40: 15.2 | AB40: 9 | AC40: 7.6 | AD40: 21 | AE40: 8.2 | AF40: 20.4 | AG40: 20.4 | AH40: 20.2 | AI40: 8.1 | AJ40: 31 | AM40: 3.6 | AN40: 9.3 | AP40: 132.75 | AQ40: 0.1 | AR40: 3.2 | AS40: 5.2 | AT40: 6 | AU40: 5.4 | AV40: 9.9 | AW40: 162.1 | AX40: 59.8 | AY40: 125.8 | AZ40: 54.3 | BA40: 0.6 | BB40: 7.1 | BC40: 22 | BD40: 65.9 | BE40: 20 | BF40: 4.5 | BH40: 2.4 | BI40: 2.4 | BJ40: 4.7 | BK40: 1.2 | BM40: 20 | BN40: 8.8 | BP40: 1409.05
B41: 17:00 | C41: 16.2 | F41: 10.4 | G41: 3.1 | J41: 0.1 | K41: 19.8 | M41: 18.1 | N41: 20.3 | O41: 9.6 | P41: 3.3 | Q41: 4.9 | R41: 20 | S41: 20.1 | T41: 20 | U41: 19.1 | V41: 29.7 | W41: 78.5 | X41: 105.5 | Y41: 94.7 | Z41: 88.1 | AA41: 5 | AB41: 10.4 | AC41: 7.4 | AD41: 21 | AE41: 8.2 | AF41: 20.4 | AG41: 20.4 | AH41: 20.2 | AI41: 8.5 | AJ41: 9.5 | AK41: 2.2 | AL41: 1.2 | AM41: 3.6 | AN41: 9.3 | AP41: 31.22 | AQ41: 0.1 | AR41: 3.4 | AS41: 2.4 | AT41: 1 | AU41: 5.3 | AV41: 9.9 | AW41: 159.2 | AX41: 9.9 | AY41: 126 | AZ41: 9.6 | BA41: 0.6 | BB41: 1 | BC41: 27.4 | BD41: 69.7 | BE41: 20 | BF41: 4.3 | BH41: 2.4 | BI41: 2.4 | BJ41: 2.1 | BK41: 1.2 | BM41: 20 | BN41: 8.8 | BP41: 1246.72
B42: 17:30 | C42: 15.5 | F42: 10.3 | G42: 3.1 | K42: 19.8 | M42: 18.2 | N42: 20.3 | O42: 9.5 | P42: 3.3 | Q42: 4.9 | R42: 19.9 | S42: 20.5 | T42: 20 | U42: 19.1 | V42: 28.9 | W42: 80.9 | X42: 105.5 | Y42: 88.7 | Z42: 98.3 | AB42: 12.1 | AC42: 9.7 | AD42: 21 | AE42: 8.2 | AF42: 20.4 | AG42: 20.4 | AH42: 20.2 | AI42: 8.3 | AK42: 4 | AL42: 3 | AM42: 3.6 | AN42: 8.4 | AP42: 74.83 | AR42: 3.4 | AS42: 0.3 | AU42: 5.5 | AV42: 9.9 | AW42: 160.1 | AX42: 0.4 | AY42: 126 | AZ42: 0.5 | BA42: 0.6 | BC42: 29 | BD42: 70.9 | BE42: 20 | BF42: 4.5 | BH42: 2.4 | BI42: 2.4 | BJ42: 0.2 | BK42: 1.2 | BM42: 20 | BN42: 8.8 | BP42: 1266.93
B43: 18:00 | C43: 16 | F43: 15.8 | G43: 3.1 | K43: 19.8 | M43: 18 | N43: 20.3 | O43: 9.6 | P43: 1.9 | Q43: 5 | R43: 20 | S43: 20.3 | T43: 20 | U43: 19.1 | V43: 24.9 | W43: 81 | X43: 106.6 | Y43: 86.5 | Z43: 101.7 | AB43: 10.9 | AC43: 3.6 | AD43: 21 | AE43: 8.2 | AF43: 20.4 | AG43: 20.4 | AH43: 20.2 | AI43: 8.1 | AK43: 1.3 | AL43: 1.2 | AM43: 3.5 | AN43: 9.3 | AR43: 3.4 | AU43: 5.6 | AV43: 9.8 | AW43: 156.3 | AY43: 126.5 | BA43: 0.6 | BC43: 26.5 | BD43: 71 | BE43: 20 | BF43: 4.5 | BH43: 2.4 | BI43: 2.4 | BK43: 1.2 | BM43: 20 | BN43: 8.9 | BP43: 1176.8
B44: 18:30 | C44: 16.2 | F44: 20.4 | G44: 3.1 | K44: 19.8 | M44: 17.8 | N44: 20.3 | O44: 9.6 | P44: 2.4 | Q44: 5 | R44: 20 | S44: 20.5 | T44: 20 | U44: 19.1 | V44: 20.7 | W44: 75.3 | X44: 106.6 | Y44: 93.8 | Z44: 105.4 | AB44: 12.8 | AC44: 3.3 | AD44: 21 | AE44: 8.2 | AF44: 20.4 | AG44: 20.4 | AH44: 20.2 | AI44: 8.1 | AK44: 0.5 | AL44: 0.6 | AM44: 3.5 | AN44: 9.3 | AR44: 3.4 | AU44: 5.5 | AV44: 9.9 | AW44: 145.5 | AY44: 124.4 | BA44: 0.6 | BC44: 25.4 | BD44: 67.7 | BE44: 20 | BF44: 4.5 | BH44: 2.4 | BI44: 2.4 | BK44: 1.2 | BM44: 20 | BN44: 8.8 | BP44: 1166
B45: 19:00 | C45: 16.4 | F45: 20.4 | G45: 3.1 | K45: 19.8 | M45: 17.9 | N45: 20.2 | O45: 9.6 | P45: 3.3 | Q45: 5 | R45: 20 | S45: 20.3 | T45: 20 | U45: 19.1 | V45: 16.3 | W45: 70.2 | X45: 108.6 | Y45: 97.2 | Z45: 104.1 | AB45: 10.6 | AC45: 7.2 | AD45: 21 | AE45: 8.2 | AF45: 20.4 | AG45: 20.4 | AH45: 20.2 | AI45: 8.1 | AK45: 1.6 | AL45: 1.7 | AM45: 3.5 | AN45: 9.3 | AR45: 3.4 | AU45: 5.5 | AV45: 9.9 | AW45: 132.8 | AY45: 123.6 | BA45: 0.6 | BC45: 22.5 | BD45: 67.7 | BE45: 19.8 | BF45: 4.5 | BH45: 2.4 | BI45: 2.4 | BK45: 1.2 | BM45: 20 | BN45: 8.8 | BP45: 1148.8
B46: 19:30 | C46: 17 | F46: 20.3 | G46: 3.1 | K46: 19.8 | M46: 17.9 | N46: 20.2 | O46: 9.6 | P46: 3.3 | Q46: 4.9 | R46: 19.4 | S46: 19.9 | T46: 20 | U46: 19.2 | V46: 18.7 | W46: 73.7 | X46: 108.6 | Y46: 107 | Z46: 105.7 | AB46: 14 | AC46: 11 | AD46: 21 | AE46: 8.2 | AF46: 20.4 | AG46: 20.4 | AH46: 20.2 | AI46: 8.3 | AK46: 2.7 | AL46: 2.1 | AM46: 3.5 | AN46: 9.3 | AR46: 3.4 | AU46: 5.4 | AV46: 9.8 | AW46: 135 | AY46: 128.2 | BA46: 0.6 | BC46: 26.1 | BD46: 70 | BE46: 20 | BF46: 4.5 | BH46: 2.4 | BI46: 2.4 | BK46: 1.2 | BM46: 19.1 | BN46: 8.9 | BP46: 1186.4
B47: 20:00 | C47: 17.8 | F47: 20.3 | G47: 3.1 | K47: 19.8 | M47: 18.1 | N47: 20.3 | O47: 9.6 | P47: 3.3 | Q47: 4.9 | R47: 19.6 | S47: 20.3 | T47: 20 | U47: 19.1 | V47: 16.9 | W47: 74.1 | X47: 108.2 | Y47: 101.6 | Z47: 105.5 | AB47: 11.8 | AC47: 10.9 | AD47: 21 | AE47: 8.2 | AF47: 20.4 | AG47: 20.4 | AH47: 20.2 | AI47: 8.3 | AK47: 2.3 | AL47: 1.6 | AM47: 3.5 | AN47: 9.3 | AR47: 3.4 | AU47: 5.4 | AV47: 9.9 | AW47: 95.4 | AY47: 102 | BA47: 0.6 | BC47: 20.8 | BD47: 60 | BE47: 20 | BF47: 4.5 | BH47: 2.4 | BI47: 2.4 | BK47: 1.2 | BM47: 19.5 | BN47: 8.8 | BP47: 1096.7
B48: 20:30 | C48: 17 | F48: 20.4 | G48: 3.1 | K48: 19.8 | M48: 17.9 | N48: 20.2 | O48: 9.6 | P48: 3.1 | Q48: 4.8 | R48: 20 | S48: 20.1 | T48: 20 | U48: 19.1 | V48: 16.4 | W48: 71.3 | X48: 108.2 | Y48: 100.1 | Z48: 106.1 | AB48: 14.2 | AC48: 11.5 | AD48: 21 | AE48: 8.2 | AF48: 20.4 | AG48: 20.4 | AH48: 20.2 | AI48: 8 | AK48: 1.6 | AL48: 1.8 | AM48: 3.5 | AN48: 9.3 | AR48: 3.4 | AU48: 5.6 | AV48: 9.9 | AW48: 83 | AY48: 90.3 | BA48: 0.6 | BC48: 23.3 | BD48: 60.2 | BE48: 20 | BF48: 4.5 | BH48: 2.4 | BI48: 2.4 | BK48: 1.2 | BM48: 20 | BN48: 8.8 | BP48: 1072.9
B49: 21:00 | C49: 17 | F49: 20.4 | G49: 3.1 | K49: 19.8 | M49: 17.9 | N49: 20.3 | O49: 9.6 | P49: 3 | Q49: 4.8 | R49: 20 | S49: 20.4 | T49: 20 | U49: 19 | V49: 15.6 | W49: 69 | X49: 106.4 | Y49: 102.9 | Z49: 105.4 | AB49: 13.7 | AC49: 11.6 | AD49: 21 | AE49: 8.2 | AF49: 20.4 | AG49: 20.4 | AH49: 20.2 | AI49: 8 | AK49: 1.2 | AL49: 0.8 | AM49: 3.5 | AN49: 9.3 | AR49: 3.3 | AU49: 5.6 | AV49: 9.8 | AW49: 72.7 | AY49: 96.1 | BA49: 0.6 | BC49: 22.6 | BD49: 61.7 | BE49: 20 | BF49: 4.5 | BH49: 2.4 | BI49: 2.4 | BK49: 1.2 | BM49: 20 | BN49: 8.8 | BP49: 1064.6
B50: 21:30 | C50: 16.1 | F50: 20.3 | G50: 3 | K50: 19.8 | M50: 17.7 | N50: 20.3 | O50: 9.6 | P50: 3.3 | Q50: 4.9 | R50: 19.9 | S50: 20.4 | T50: 20 | U50: 19.1 | V50: 21 | W50: 73.7 | X50: 106.4 | Y50: 103.5 | Z50: 105.5 | AB50: 14.8 | AC50: 11.9 | AD50: 21 | AE50: 8.2 | AF50: 20.4 | AG50: 20.4 | AH50: 20.2 | AI50: 7.6 | AL50: 0.1 | AM50: 3.6 | AN50: 9.3 | AR50: 3.4 | AU50: 5.4 | AV50: 9.9 | AW50: 75.2 | AY50: 81.5 | BA50: 0.6 | BC50: 19.6 | BD50: 54.5 | BE50: 20 | BF50: 4.5 | BH50: 2.4 | BI50: 2.4 | BK50: 1.2 | BM50: 20 | BN50: 8.9 | BP50: 1051.5
B51: 22:00 | C51: 16.8 | F51: 20.4 | G51: 3.1 | K51: 19.8 | M51: 17.8 | N51: 20.2 | O51: 9.6 | P51: 3.3 | Q51: 4.8 | R51: 20 | S51: 19.9 | T51: 20 | U51: 19 | V51: 26.4 | W51: 72.5 | X51: 106.3 | Y51: 104.7 | Z51: 105.8 | AB51: 16.1 | AC51: 10 | AD51: 21 | AE51: 8 | AF51: 20.4 | AG51: 20.4 | AH51: 20.2 | AI51: 8 | AK51: 0.9 | AL51: 0.2 | AM51: 3.6 | AN51: 9.3 | AR51: 3.4 | AU51: 5.5 | AV51: 9.9 | AW51: 67.9 | AY51: 74.8 | BA51: 0.6 | BC51: 25.5 | BD51: 60.8 | BE51: 20 | BF51: 4.5 | BH51: 2.4 | BI51: 2.4 | BK51: 1.2 | BM51: 20 | BN51: 8.8 | BP51: 1056.2
B52: 22:30 | C52: 16.5 | F52: 20.4 | G52: 3.1 | K52: 19.9 | M52: 17.9 | N52: 20.3 | O52: 9.7 | P52: 3.3 | Q52: 4.8 | R52: 20 | S52: 20.4 | T52: 20 | U52: 19.1 | V52: 22.3 | W52: 56.2 | X52: 106.3 | Y52: 94.8 | Z52: 105.4 | AB52: 13.2 | AC52: 11 | AD52: 21 | AE52: 8 | AF52: 20.4 | AG52: 20.4 | AH52: 20.2 | AI52: 7.9 | AK52: 0.6 | AL52: 0.1 | AM52: 3.6 | AN52: 9.3 | AR52: 3.4 | AU52: 5.4 | AV52: 9.8 | AW52: 58.6 | AY52: 65.7 | BA52: 0.6 | BC52: 25.6 | BD52: 55.3 | BE52: 20 | BF52: 4.5 | BH52: 2.4 | BI52: 2.4 | BK52: 1.2 | BM52: 20 | BN52: 8.8 | BP52: 999.8
B53: 23:00 | C53: 15.5 | F53: 20.3 | G53: 3.1 | K53: 19.8 | M53: 17.9 | N53: 20.3 | O53: 9.6 | P53: 3.3 | Q53: 4.7 | R53: 20 | S53: 20.5 | T53: 20 | U53: 19.1 | V53: 26 | W53: 47 | X53: 104.4 | Y53: 98.4 | Z53: 105.6 | AB53: 12.7 | AC53: 12 | AD53: 21 | AE53: 8 | AF53: 20.4 | AG53: 20.4 | AH53: 20.2 | AI53: 7.8 | AK53: 0.3 | AM53: 3.6 | AN53: 9.3 | AR53: 3.4 | AU53: 5.2 | AV53: 9.8 | AW53: 46.3 | AY53: 44.3 | BA53: 0.6 | BC53: 28.5 | BD53: 49.6 | BE53: 20 | BF53: 4.5 | BH53: 2.4 | BI53: 2.4 | BK53: 1.2 | BM53: 20 | BN53: 8.8 | BP53: 958.2
B54: 23:30 | C54: 15.9 | F54: 20.3 | G54: 3.1 | K54: 19.8 | M54: 17.9 | N54: 20.3 | O54: 9.6 | P54: 3.3 | Q54: 2.8 | R54: 19.8 | S54: 20 | T54: 20 | U54: 19.1 | V54: 27.9 | W54: 43.1 | X54: 104.4 | Y54: 90.7 | Z54: 104.7 | AB54: 7.6 | AC54: 11.4 | AD54: 21 | AE54: 7.9 | AF54: 20.4 | AG54: 20.4 | AH54: 20.2 | AI54: 7.8 | AM54: 3.6 | AN54: 9.3 | AR54: 3.4 | AU54: 5.4 | AV54: 9.9 | AW54: 39.4 | AY54: 36.7 | BA54: 0.6 | BC54: 30.3 | BD54: 64.5 | BE54: 20 | BF54: 4.5 | BH54: 2.4 | BI54: 2.4 | BK54: 1.2 | BM54: 19.9 | BN54: 8.8 | BP54: 941.7
B55: 0:00 | C55: 16.2 | F55: 20.3 | G55: 3.1 | K55: 19.8 | M55: 17.9 | N55: 20.2 | O55: 9.6 | P55: 3.3 | Q55: 4.9 | R55: 19.9 | S55: 20.3 | T55: 20 | U55: 19.1 | V55: 28.3 | W55: 40.3 | X55: 101.4 | Y55: 80.2 | Z55: 104.5 | AB55: 8.6 | AC55: 6.4 | AD55: 21 | AE55: 7.9 | AF55: 20.4 | AG55: 20.4 | AH55: 20.2 | AI55: 7.8 | AM55: 3.6 | AN55: 9.3 | AR55: 3.4 | AU55: 5.3 | AV55: 9.8 | AW55: 48.7 | AY55: 40.6 | BA55: 0.6 | BC55: 28.7 | BD55: 68.3 | BE55: 19.8 | BF55: 4.5 | BH55: 2.4 | BI55: 2.4 | BK55: 1.2 | BM55: 19.9 | BN55: 8.8 | BP55: 939.3
B56: EJEC MWh | C56: 359.3 | D56: 0 | E56: 0 | F56: 283.4 | G56: 74 | H56: 0 | I56: 0 | J56: 9.05 | K56: 475.3 | L56: 0 | M56: 437 | N56: 486.5 | O56: 225.25 | P56: 75.5 | Q56: 118 | R56: 478.45 | S56: 486.85 | T56: 480 | U56: 458.25 | V56: 562.45 | W56: 1254.4 | X56: 2367.55 | Y56: 1747.4 | Z56: 1985.75 | AA56: 303.9 | AB56: 244.55 | AC56: 136.55 | AD56: 504 | AE56: 187.35 | AF56: 489.6 | AG56: 489.6 | AH56: 484.8 | AI56: 171.5 | AJ56: 575.8 | AK56: 20.25 | AL56: 22.8 | AM56: 85.95 | AN56: 222.75 | AO56: 0 | AP56: 1783.075 | AQ56: 2.1 | AR56: 79.05 | AS56: 105.6 | AT56: 87.25 | AU56: 126.65 | AV56: 237.35 | AW56: 1981.1 | AX56: 903.15 | AY56: 1819.45 | AZ56: 670.5 | BA56: 14.4 | BB56: 103.1 | BC56: 552.4 | BD56: 1535.9 | BE56: 479.65 | BF56: 108.55 | BG56: 0 | BH56: 57.6 | BI56: 50.5 | BJ56: 123.65 | BK56: 28.8 | BL56: 0 | BM56: 478.8 | BN56: 209.1 | BO56: 133.6 | BP56: 27975.125
L70: TERMOELÉCTRICA | M70: 575.95 | N70: 2.0587933 | O70: #FF0000
L71: SOLAR | M71: 4800.775 | N71: 17.160871 | O71: #FBFB00
L72: HIDROELÉCTRICA | M72: 8367.85 | N72: 29.911752 | O72: #00B0F0
L73: EÓLICA | M73: 14230.55 | N73: 50.868584 | O73: #FBBD00

Sheet COGENERACIÓN
B3: martes, 22 de Abril del 2025
B5: CENTRALES DE COGENERACIÓN DEL SEIN
B6: HORA | C6: AGRO INDUSTRIAL PARAMONGA S.A. | D6: AGROAURORA S.A.C. | E6: AGROINDUSTRIAS SAN JACINTO S.A.A. | F6: BIOENERGIA DEL CHIRA S.A. | G6: GM OPERACIONES S.A.C. | H6: SDF ENERGIA SAC | I6: TOTAL COGENERACION
C7: C.T. PARAMONGA | D7: C.T. MAPLE | E7: C.T SAN JACINTO | F7: C.T. CAÑA BRAVA | G7: C.T. REFINERÍA TALARA | H7: C.T. OQUENDO | I7: MW
B8: 0:30 | C8: 16 | G8: 74.9 | H8: 32.5 | I8: 123.4
B9: 1:00 | C9: 16 | G9: 73.3 | H9: 32.3 | I9: 121.6
B10: 1:30 | C10: 16 | G10: 72.9 | H10: 32.4 | I10: 121.3
B11: 2:00 | C11: 17 | G11: 74.1 | H11: 32.3 | I11: 123.4
B12: 2:30 | C12: 17 | G12: 74 | H12: 32.3 | I12: 123.3
B13: 3:00 | C13: 16.7 | G13: 74.6 | H13: 32.5 | I13: 123.8
B14: 3:30 | C14: 16.9 | G14: 74.6 | H14: 32.4 | I14: 123.9
B15: 4:00 | C15: 17 | G15: 74 | H15: 32.4 | I15: 123.4
B16: 4:30 | C16: 16 | G16: 74.4 | H16: 32.5 | I16: 122.9
B17: 5:00 | C17: 16 | G17: 74.1 | H17: 32.6 | I17: 122.7
B18: 5:30 | C18: 16 | G18: 73.5 | H18: 32.6 | I18: 122.1
B19: 6:00 | C19: 16.5 | G19: 73.5 | H19: 32.6 | I19: 122.6
... B55: 0:00 | C55: 16.2 | G55: 75 | H55: 32.2 | I55: 123.4
B56: EJEC MWh | C56: 359.3 | D56: 0 | E56: 0 | F56: 0 | G56: 1778.9 | H56: 771.8 | I56: 2910

Sheet EVO_PRO_ENE
B3: martes, 1 de Abril del 2025 - martes, 22 de Abril del 2025
B5: EVOLUCIÓN DE LA PRODUCCIÓN DE LA ENERGÍA DIARIA DE LOS INTEGRANTES DEL COES (MWh)
B6: EMPRESA | C6: CENTRAL | D6: UNIDAD | E6: TIPO | F6: Abril
F7: 1 | G7: 2 | H7: 3 | I7: 4 | J7: 5 | K7: 6 | L7: 7 | M7: 8 | N7: 9 | O7: 10 | P7: 11 | Q7: 12 | R7: 13 | S7: 14 | T7: 15 | U7: 16 | V7: 17 | W7: 18 | X7: 19 | Y7: 20 | Z7: 21 | AA7: 22 | AB7: TOTAL
B8: AGRO INDUSTRIAL PARAMONGA S.A. | C8: C.T. PARAMONGA | D8: TV-01 | E8: TERMOELÉCTRICA | F8: 169.5 | G8: 245.7 | H8: 400.2 | I8: 407.05 | J8: 368.75 | K8: 335.9 | L8: 386.5 | M8: 390.9 | N8: 397 | O8: 404.2 | P8: 409.9 | Q8: 377.85 | R8: 212.4 | S8: 293.4 | T8: 323.2 | U8: 347.1 | V8: 360.45 | W8: 338.55 | X8: 267 | Y8: 390.9 | Z8: 398.15 | AA8: 359.3 | AB8: 7583.9
B9: AGROAURORA S.A.C. | C9: C.T. MAPLE ETANOL | D9: TV | E9: TERMOELÉCTRICA | AB9: 0
B10: AGROINDUSTRIAS SAN JACINTO S.A.A. | C10: C.T. SAN JACINTO | D10: CENTRAL | E10: TERMOELÉCTRICA | F10: 120.97 | G10: 109.3 | H10: 25.6 | AB10: 255.87
B11: ANDEAN POWER S.A.C. | C11: C.H.CARHUAC | D11: CENTRAL | E11: HIDROELÉCTRICA | F11: 488.5 | G11: 480.45 | H11: 486.9 | I11: 484.9 | J11: 483.9 | K11: 480.35 | L11: 485.6 | M11: 486.15 | N11: 486.95 | O11: 483.35 | P11: 485.85 | Q11: 485.7 | R11: 457.1 | S11: 475.5 | T11: 487.15 | U11: 483.65 | V11: 470.35 | W11: 485.5 | X11: 483.55 | Y11: 458.1 | Z11: 402.6 | AA11: 283.4 | AB11: 10305.5
B12: ASOCIACIÓN SANTA LUCIA DE CHACAS | C12: C.H. HUALLIN | D12: CENTRAL | E12: HIDROELÉCTRICA | F12: 71.9 | G12: 70.3 | H12: 71.4 | I12: 71.5 | J12: 72 | K12: 72 | L12: 72 | M12: 71.95 | N12: 71.35 | O12: 71.35 | P12: 70.45 | Q12: 71.95 | R12: 72 | S12: 71.2 | T12: 71.5 | U12: 63.8 | V12: 72 | W12: 71.5 | X12: 72 | Y12: 72 | Z12: 72 | AA12: 74 | AB12: 1570.15
B13: ATRIA ENERGIA S.A.C. | C13: C.H. PURMACANA | D13: CENTRAL | E13: HIDROELÉCTRICA | F13: 1.95 | G13: 1.2 | H13: 1.9 | I13: 2.5 | J13: 1.7 | Y13: 4.1 | Z13: 1.75 | AB13: 15.1
B14: BIOENERGIA DEL CHIRA S.A. | C14: C.T. CAÑA BRAVA | D14: CENTRAL | E14: TERMOELÉCTRICA | AB14: 0
B15: CELEPSA | C15: C.H. EL PLATANAL | D15: CENTRAL | E15: HIDROELÉCTRICA | F15: 5347.15 | G15: 5339.95 | H15: 1378.3 | I15: 5218.2 | J15: 5088.55 | K15: 4928.1 | L15: 4820.1 | M15: 4611.65 | N15: 4963.3 | O15: 5002.8 | P15: 5166.75 | Q15: 5150.4 | R15: 4786.25 | S15: 4891.35 | T15: 4742.75 | U15: 4977.4 | V15: 5033 | W15: 4936.15 | X15: 5341.55 | Y15: 5423.95 | Z15: 4666.15 | AA15: 4993.45 | AB15: 106807.25
B16: CELEPSA RENOVABLES S.R.L. | C16: C.H. MARAÑON | D16: CENTRAL | E16: HIDROELÉCTRICA | F16: 473.53848 | G16: 472.8 | H16: 470.1 | I16: 472.4 | J16: 472.8 | K16: 472.8 | L16: 472.8 | M16: 472.8 | N16: 472.8 | O16: 472.8 | P16: 465.3 | Q16: 466.9 | R16: 472.8 | S16: 472.8 | T16: 472.8 | U16: 472.8 | V16: 472.8 | W16: 472.8 | X16: 472.8 | Y16: 472.8 | Z16: 472.8 | AA16: 472.8 | AB16: 10385.838
B17: CENTRALES SANTA ROSA S.A.C. | C17: C.H. SANTA ROSA I | D17: CENTRAL | E17: HIDROELÉCTRICA | AB17: 0
B18: CENTRALES SANTA ROSA S.A.C. | C18: C.H. SANTA ROSA II | D18: CENTRAL | E18: HIDROELÉCTRICA | AB18: 0
B19: CHINANGO S.A.C. | C19: C.H. CHIMAY | D19: CENTRAL | E19: HIDROELÉCTRICA | F19: 3355.35 | G19: 3375.8 | H19: 3482.65 | I19: 3415.15 | J19: 3427.9 | K19: 3416.3 | L19: 3380.6 | M19: 3331.3 | N19: 3419.15 | O19: 3435.35 | P19: 3466.6 | Q19: 3463.25 | R19: 3144.9 | S19: 3401.05 | T19: 3363.95 | U19: 3386.15 | V19: 3547.25 | W19: 3479.4 | X19: 3473.7 | Y19: 3416.8 | Z19: 3490.05 | AA19: 3392 | AB19: 75064.65
B20: CHINANGO S.A.C. | C20: C.H. YANANGO | D20: CENTRAL | E20: HIDROELÉCTRICA | F20: 1016.7 | G20: 1013.95 | H20: 1013.6 | I20: 1009.2 | J20: 186.5 | K20: 678.65 | L20: 1017.15 | M20: 1016.6 | N20: 1016.6 | O20: 1016.3 | P20: 1016.3 | Q20: 1011.55 | R20: 1015.5 | S20: 1014.75 | T20: 1013.45 | U20: 1014 | V20: 1013.9 | W20: 1013.6 | X20: 1012.25 | Y20: 1012.1 | Z20: 1011.95 | AA20: 1011.55 | AB20: 21146.15
B21: COLCA SOLAR S.A.C. | C21: C.S. YARUCAYA | D21: CENTRAL | E21: SOLAR | F21: 5.2 | G21: 4.6 | H21: 5.55 | I21: 7.85 | J21: 5.6 | K21: 6.8 | L21: 8.05 | M21: 6.95 | N21: 7.3 | O21: 8.2 | P21: 9.05 | Q21: 9.2 | R21: 8.8 | S21: 8.7 | T21: 8.75 | U21: 9.05 | V21: 6.15 | W21: 8.4 | X21: 7.05 | Y21: 5.3 | Z21: 7 | AA21: 9.05 | AB21: 162.6
B22: EGASA | C22: C.H. CHARCANI III | D22: CENTRAL | E22: HIDROELÉCTRICA | F22: 156 | G22: 157.75 | H22: 158.4 | I22: 158.6 | J22: 157.05 | K22: 159.75 | L22: 158.4 | M22: 156.4 | N22: 154.5 | O22: 108.7 | P22: 154.85 | Q22: 151.3 | R22: 99.8 | S22: 143.55 | T22: 145.25 | U22: 158.9 | V22: 160.15 | W22: 158.7 | X22: 159.15 | Y22: 161.4 | Z22: 158.35 | AA22: 160.6 | AB22: 3337.55
B23: EGASA | C23: C.H. CHARCANI IV | D23: CENTRAL | E23: HIDROELÉCTRICA | F23: 242.5 | G23: 242.5 | H23: 242.45 | I23: 242.85 | J23: 242.9 | K23: 243.1 | L23: 242.5 | M23: 242.9 | N23: 242.45 | O23: 242.85 | P23: 242.485 | Q23: 243.15 | R23: 161.45 | S23: 170.2 | T23: 240.2 | U23: 243.6 | V23: 244.75 | W23: 244.75 | X23: 244.7 | Y23: 244.6 | Z23: 244.55 | AA23: 244.35 | AB23: 5195.785
B24: EGASA | C24: C.H. CHARCANI V | D24: CENTRAL | E24: HIDROELÉCTRICA | F24: 3149.6 | G24: 3430.2 | H24: 3438.15 | I24: 3168.35 | J24: 3422.5 | K24: 3434.9 | L24: 3434.9 | M24: 3050 | N24: 3197.05 | O24: 3439.3 | P24: 3441.475 | Q24: 3439.2 | R24: 3433.8 | S24: 3439 | T24: 3435.2 | U24: 3435.1 | V24: 3434.5 | W24: 3430.95 | X24: 3441.1 | Y24: 3436.45 | Z24: 2856.75 | AA24: 2156.8 | AB24: 72545.275
B25: EGASA | C25: C.H. CHARCANI VI | D25: CENTRAL | E25: HIDROELÉCTRICA | F25: 210.05 | G25: 214.55 | H25: 215.4 | I25: 211.45 | J25: 214.7 | K25: 214.85 | L25: 215.25 | M25: 215.6 | N25: 215.15 | O25: 215.8 | P25: 209.39 | Q25: 208 | R25: 199.45 | S25: 196.1 | T25: 139.45 | U25: 180.9 | V25: 181.9 | W25: 182.45 | X25: 182.8 | Y25: 182.95 | Z25: 166.6 | AA25: 141.6 | AB25: 4314.39
B26: EGASA | C26: C.T. CHILINA DIESEL | D26: CENTRAL | E26: TERMOELÉCTRICA | F26: 9 | P26: 10.8 | AB26: 19.8
B27: EGASA | C27: C.T. CHILINA DIESEL | D27: TG | E27: TERMOELÉCTRICA | AB27: 0
B28: EGASA | C28: C.T. MOLLENDO DIESEL | D28: CENTRAL | E28: TERMOELÉCTRICA | AB28: 0
B29: EGEJUNIN | C29: C.H. HUASAHUASI I | D29: CENTRAL | E29: HIDROELÉCTRICA | F29: 475.4 | G29: 476.1 | H29: 475.8 | I29: 474.55 | J29: 471.75 | K29: 475.3 | L29: 474.1 | M29: 449.65 | N29: 407.15 | O29: 380.25 | P29: 370.65 | Q29: 360.15 | R29: 413.7 | S29: 437.15 | T29: 424.8 | U29: 475.3 | V29: 475.2 | W29: 475.45 | X29: 475.2 | Y29: 475.25 | Z29: 475.35 | AA29: 475.3 | AB29: 9893.55
B30: EGEJUNIN | C30: C.H. RUNATULLO II | D30: CENTRAL | E30: HIDROELÉCTRICA | F30: 483.85 | G30: 481.95 | H30: 482.9 | I30: 482.15 | J30: 473.65 | K30: 479.9 | L30: 480.75 | M30: 482.15 | N30: 484.4 | O30: 484.55 | P30: 484.7 | Q30: 483.5 | R30: 483.15 | S30: 483.95 | T30: 482.5 | U30: 483.5 | V30: 482.9 | W30: 478.55 | X30: 464.55 | Y30: 458.35 | Z30: 471.75 | AA30: 437 | AB30: 10510.65
B31: EGEJUNIN | C31: C.H. RUNATULLO III | D31: CENTRAL | E31: HIDROELÉCTRICA | F31: 486.55 | G31: 486.55 | H31: 486.6 | I31: 486.45 | J31: 486.4 | K31: 486.85 | L31: 486.85 | M31: 486.6 | N31: 486.6 | O31: 486.45 | P31: 486.6 | Q31: 486.45 | R31: 486.45 | S31: 486.5 | T31: 486.2 | U31: 486.45 | V31: 486.2 | W31: 485.65 | X31: 486.15 | Y31: 485.8 | Z31: 485.8 | AA31: 486.5 | AB31: 10700.65
B32: EGEJUNIN | C32: C.H. SANTA CRUZ I | D32: CENTRAL | E32: HIDROELÉCTRICA | F32: 235.65 | G32: 235.2 | H32: 237.35 | I32: 229.55 | J32: 235.75 | K32: 235.05 | L32: 234.25 | M32: 234.05 | N32: 234.05 | O32: 233.55 | P32: 233.15 | Q32: 232.7 | R32: 232.45 | S32: 232.4 | T32: 231.15 | U32: 229.3 | V32: 232.85 | W32: 223.4 | X32: 230.2 | Y32: 216.65 | Z32: 231.5 | AA32: 225.25 | AB32: 5095.45
B33: EGEMSA | C33: C.H. MACHUPICCHU | D33: CENTRAL | E33: HIDROELÉCTRICA | F33: 3962.35 | G33: 3952.55 | H33: 3937.9 | I33: 3946.1 | J33: 3906.6 | K33: 3890.85 | L33: 3968.85 | M33: 3960.7 | N33: 3928.15 | O33: 3971.1 | P33: 3962.75 | Q33: 3932.8 | R33: 3167.45 | S33: 3998.25 | T33: 3972.2 | U33: 3950.05 | V33: 3954.3 | W33: 3959.45 | X33: 3959.1 | Y33: 3952.9 | Z33: 3970.25 | AA33: 3955.4 | AB33: 86160.05
B34: EGESUR | C34: C.H. ARICOTA I | D34: CENTRAL | E34: HIDROELÉCTRICA | F34: 178.75 | G34: 179.35 | H34: 180.65 | I34: 180.3 | J34: 177.6 | K34: 180.65 | L34: 180.45 | M34: 178.55 | N34: 181.05 | O34: 179.25 | P34: 180.5 | Q34: 181 | R34: 180.2 | S34: 181.6 | T34: 178.5 | U34: 180 | V34: 179.5 | W34: 181 | X34: 178.1 | Y34: 174.75 | Z34: 176.5 | AA34: 177.6 | AB34: 3945.85
B35: EGESUR | C35: C.H. ARICOTA II | D35: CENTRAL | E35: HIDROELÉCTRICA | F35: 78.25 | G35: 79.15 | H35: 78.25 | I35: 80.4 | J35: 79.6 | K35: 79.7 | L35: 79.65 | M35: 78.5 | N35: 78.7 | O35: 78.9 | P35: 81.05 | Q35: 80.8 | R35: 81.6 | S35: 84.9 | T35: 82.25 | U35: 82.7 | V35: 80.6 | W35: 80 | X35: 82.4 | Y35: 81 | Z35: 81.45 | AA35: 83.4 | AB35: 1773.25
B36: EGESUR | C36: C.T. INDEPENDENCIA | D36: CENTRAL | E36: TERMOELÉCTRICA | F36: 6.95 | G36: 31.25 | H36: 237 | I36: 126.85 | J36: 55.15 | K36: 46.35 | N36: 131.95 | O36: 74.3 | P36: 183.15 | Q36: 37.6 | R36: 80.55 | S36: 40.85 | U36: 55.2 | V36: 110.6 | W36: 101.4 | X36: 99.3 | Y36: 333.45 | Z36: 118.45 | AB36: 1870.35
B37: ELECTRICA YANAPAMPA SAC | C37: C.H. YANAPAMPA | D37: CENTRAL | E37: HIDROELÉCTRICA | F37: 74.5 | G37: 69.1 | H37: 73.75 | I37: 67.1 | J37: 72.45 | K37: 70.3 | L37: 73.4 | M37: 73.4 | N37: 65.8 | O37: 66.2 | P37: 60.3 | Q37: 17.65 | R37: 37.85 | S37: 71.7 | T37: 71.3 | U37: 74.8 | V37: 73.55 | W37: 77.2 | X37: 77 | Y37: 76.3 | Z37: 76.3 | AA37: 75.5 | AB37: 1495.45
B38: ELECTROPERU | C38: C.H. MANTARO | D38: CENTRAL | E38: HIDROELÉCTRICA | F38: 15574.5 | G38: 15381 | H38: 15127.05 | I38: 14878.9 | J38: 15509.65 | K38: 14698.4 | L38: 14679.5 | M38: 14286.7 | N38: 14716.15 | O38: 15539.05 | P38: 15554.9 | Q38: 15541 | R38: 14942.7 | S38: 15295.05 | T38: 13798.95 | U38: 15072.05 | V38: 15261.5 | W38: 15388.05 | X38: 15556.25 | Y38: 15524.85 | Z38: 15534.35 | AA38: 15029.5 | AB38: 332890.05
B39: ELECTROPERU | C39: C.H. RESTITUCION | D39: CENTRAL | E39: HIDROELÉCTRICA | F39: 4479.45 | G39: 4692.25 | H39: 4788.4 | I39: 4812.75 | J39: 3560 | K39: 3195.95 | L39: 3320.5 | M39: 3487.05 | N39: 4891.8 | O39: 5178 | P39: 5187.05 | Q39: 5179.9 | R39: 4364.85 | S39: 5083.05 | T39: 4574.55 | U39: 5038 | V39: 5100.15 | W39: 5134.15 | X39: 5157.7 | Y39: 4473.9 | Z39: 5156.8 | AA39: 5001.4 | AB39: 101857.65
B40: ELECTROPERU | C40: C.T. TUMBES | D40: MAK1 | E40: TERMOELÉCTRICA | Y40: 41.95 | AB40: 41.95
B41: ELECTROPERU | C41: C.T. TUMBES | D41: MAK2 | E41: TERMOELÉCTRICA | Y41: 43.95 | AB41: 43.95
B42: EMPRESA DE GENERACION ELECTRICA CANCHAYLLO SAC | C42: C.H. CANCHAYLLO | D42: CENTRAL | E42: HIDROELÉCTRICA | F42: 120.25 | G42: 96.8 | H42: 112.6 | I42: 117.35 | J42: 121 | K42: 120.05 | L42: 117.95 | M42: 116.65 | N42: 114.2 | O42: 110.8 | P42: 100.55 | Q42: 97.5 | R42: 98.3 | S42: 100.6 | T42: 95.6 | U42: 98.95 | V42: 120.2 | W42: 118.95 | X42: 113.45 | Y42: 115.75 | Z42: 119.25 | AA42: 118 | AB42: 2444.75
B43: EMPRESA DE GENERACION ELECTRICA RIO BAÑOS S.A.C. | C43: C.H. RUCUY | D43: CENTRAL | E43: HIDROELÉCTRICA | F43: 478.8 | G43: 360.9 | H43: 393 | I43: 246.75 | J43: 478.65 | K43: 478.7 | L43: 478 | M43: 478.8 | N43: 478.95 | O43: 479.65 | P43: 479.55 | Q43: 479.65 | R43: 479.55 | S43: 479.15 | T43: 478.85 | U43: 479.1 | V43: 479.1 | W43: 479.15 | X43: 479.7 | Y43: 479.8 | Z43: 478.85 | AA43: 478.45 | AB43: 10103.1
B44: EMPRESA DE GENERACION ELECTRICA SANTA ANA S.A.C. | C44: C.H. RENOVANDES H1 | D44: CENTRAL | E44: HIDROELÉCTRICA | F44: 487.75 | G44: 487.05 | H44: 487.75 | I44: 486.95 | J44: 417.7 | K44: 487.15 | L44: 486.95 | M44: 485.1 | N44: 485.4 | O44: 484.95 | P44: 485.6 | Q44: 485.5 | R44: 484.8 | S44: 485.85 | T44: 482.55 | U44: 484.35 | V44: 484.45 | W44: 484.15 | X44: 486.45 | Y44: 447.15 | Z44: 487 | AA44: 486.85 | AB44: 10581.45
B45: EMPRESA DE GENERACION HUALLAGA | C45: C.H. CHAGLLA | D45: CENTRAL | E45: HIDROELÉCTRICA | F45: 10661.95 | G45: 10629.55 | H45: 10754.5 | I45: 10970.9 | J45: 10660.45 | K45: 9385.5 | L45: 9964.75 | M45: 9993.5 | N45: 9951.85 | O45: 10263.55 | P45: 10272.3 | Q45: 10718.05 | R45: 8555.1 | S45: 9969.1 | T45: 9530.35 | U45: 10263.4 | V45: 9810.65 | W45: 9204.95 | X45: 10209 | Y45: 9341.75 | Z45: 10752.3 | AA45: 10824.75 | AB45: 222688.2
B46: EMPRESA DE GENERACION HUALLAGA | C46: P.C.H. CHAGLLA | D46: CENTRAL | E46: HIDROELÉCTRICA | F46: 154.85 | G46: 154.95 | H46: 154.55 | I46: 155.55 | J46: 155.3 | K46: 155.05 | L46: 154.75 | M46: 154.35 | N46: 154.7 | O46: 154.95 | P46: 155.65 | Q46: 155.65 | R46: 155.55 | S46: 155.5 | T46: 155.45 | U46: 155.5 | V46: 154.85 | W46: 155.3 | X46: 155.45 | Y46: 155.6 | Z46: 155.55 | AA46: 155.3 | AB46: 3414.35
B47: EMPRESA DE GENERACION HUANZA | C47: C.H. HUANZA | D47: CENTRAL | E47: HIDROELÉCTRICA | F47: 2125.9 | G47: 2037.7 | H47: 2140 | I47: 2192.2 | J47: 2288.2 | K47: 2285.95 | L47: 2192.55 | M47: 2215.3 | N47: 2165.15 | O47: 2118.6 | P47: 2233.4 | Q47: 2191.25 | R47: 1916.75 | S47: 1846.35 | T47: 2141.6 | U47: 1950.45 | V47: 1828.45 | W47: 1992.4 | X47: 2084.85 | Y47: 1988.65 | Z47: 1351.75 | AA47: 822.85 | AB47: 44110.3
B48: EMPRESA ELECTRICA AGUA AZUL | C48: C.H. POTRERO | D48: CENTRAL | E48: HIDROELÉCTRICA | F48: 410.7 | G48: 458.1 | H48: 469.4 | I48: 431.05 | J48: 479.7 | K48: 474.6 | L48: 480 | M48: 480 | N48: 476.75 | O48: 468.45 | P48: 475.1 | Q48: 462.75 | R48: 479.15 | S48: 480 | T48: 439.65 | U48: 419.1 | V48: 479.9 | W48: 479.85 | X48: 479.8 | Y48: 479.95 | Z48: 480 | AA48: 480 | AB48: 10264
B49: EMPRESA ELECTRICA RIO DOBLE | C49: C.H. LAS PIZARRAS | D49: CENTRAL | E49: HIDROELÉCTRICA | G49: 198.25 | H49: 391.95 | I49: 457.5 | J49: 456.1 | K49: 455.35 | L49: 454.5 | M49: 453.9 | N49: 423.35 | O49: 424.3 | P49: 453 | Q49: 453.5 | R49: 451.1 | S49: 452 | T49: 441.55 | U49: 455.4 | V49: 455.75 | W49: 455.65 | X49: 455.55 | Y49: 431.15 | Z49: 458.35 | AA49: 458.25 | AB49: 9136.45
B50: ENEL GENERACION PIURA S.A. | C50: C.T. MALACAS 1 | D50: TG6 | E50: TERMOELÉCTRICA | F50: 1019 | G50: 814.1 | H50: 813.8 | I50: 823.7 | J50: 747.2 | K50: 34.7 | L50: 649.9 | M50: 669.5 | N50: 694.8 | O50: 767.6 | P50: 807.35 | Q50: 810.15 | R50: 570.2 | S50: 659.65 | U50: 737.4 | V50: 376.65 | W50: 682.05 | X50: 682.7 | Y50: 1106.2 | Z50: 1107.45 | AA50: 968.4 | AB50: 15542.5
B51: ENEL GENERACION PIURA S.A. | C51: C.T. MALACAS 2 | D51: TG4 | E51: TERMOELÉCTRICA | AB51: 0
B52: ENEL GENERACION PIURA S.A. | C52: C.T. RF DE GENERACION TALARA | D52: TG5 | E52: TERMOELÉCTRICA | AB52: 0
B53: ENERGÍA EÓLICA S.A. | C53: C.E. CUPISNIQUE | D53: CENTRAL | E53: EÓLICA | F53: 1063.95 | G53: 1005.35 | H53: 861.2 | I53: 769 | J53: 801.95 | K53: 1122.55 | L53: 1183.5 | M53: 976.95 | N53: 796.15 | O53: 976.8 | P53: 851.5 | Q53: 957.4 | R53: 1196.5 | S53: 1444.65 | T53: 1784.75 | U53: 1304.25 | V53: 1235.05 | W53: 1101.05 | X53: 957 | Y53: 843.9 | Z53: 1077.45 | AA53: 1254.4 | AB53: 23565.3
B54: ENERGÍA EÓLICA S.A. | C54: C.E. TALARA | D54: CENTRAL | E54: EÓLICA | F54: 108.95 | G54: 206.5 | H54: 105.4 | I54: 241.5 | J54: 166.2 | K54: 297.3 | L54: 419.35 | M54: 198.75 | N54: 317.55 | O54: 370.55 | P54: 133.7 | Q54: 286.65 | R54: 507.5 | S54: 504.2 | T54: 700.3 | U54: 654.4 | V54: 314.05 | W54: 424.05 | X54: 398 | Y54: 381.45 | Z54: 437.5 | AA54: 562.45 | AB54: 7736.3
B55: ENERGIA RENOVABLE DEL SUR S.A. | C55: C.E. SAN JUAN | D55: CENTRAL | E55: EÓLICA | F55: 2690.05 | G55: 2781.75 | H55: 2483.9 | I55: 1829.25 | J55: 1028.15 | K55: 2249 | L55: 2083.9 | M55: 2008.95 | N55: 1750.95 | O55: 1563.5 | P55: 1767.4 | Q55: 2368.65 | R55: 2339.75 | S55: 2693.7 | T55: 2380.05 | U55: 2190.95 | V55: 2040.8 | W55: 2440.75 | X55: 2477.5 | Y55: 1356.8 | Z55: 1699.75 | AA55: 2367.55 | AB55: 46593.05
B56: ENGIE | C56: C.E. PUNTA LOMITAS | D56: PL-BL1 | E56: EÓLICA | F56: 1634.25 | G56: 1352.8 | H56: 1500.95 | I56: 1406.8 | J56: 1156 | K56: 1529.45 | L56: 1744.1 | M56: 1646.8 | N56: 1026.85 | O56: 1293.6 | P56: 1009.05 | Q56: 1090.65 | R56: 1872.95 | S56: 1819.65 | T56: 1991.35 | U56: 1751.1 | V56: 1249.05 | W56: 732.25 | X56: 955.65 | Y56: 642.05 | Z56: 654.95 | AA56: 1747.4 | AB56: 29807.7
B57: ENGIE | C57: C.E. PUNTA LOMITAS | D57: PL-BL2 | E57: EÓLICA | F57: 2042.2 | G57: 1773.95 | H57: 1973.35 | I57: 1691.25 | J57: 1734.7 | K57: 1740.05 | L57: 1825.15 | M57: 2006.15 | N57: 1441.65 | O57: 1662.3 | P57: 1504.35 | Q57: 1551 | R57: 2156.05 | S57: 1975.45 | T57: 2121.1 | U57: 1929 | V57: 1631.65 | W57: 1132.15 | X57: 1313.95 | Y57: 1048.35 | Z57: 957.25 | AA57: 1985.75 | AB57: 37196.8
B58: ENGIE | C58: C.E. PUNTA LOMITAS_EXP | D58: PUN LOM_EXP-BL1 | E58: EÓLICA | F58: 274.2 | G58: 191.35 | H58: 214.25 | I58: 233.5 | J58: 115.7 | K58: 171.2 | L58: 249.45 | M58: 277.2 | N58: 138.35 | O58: 196.45 | P58: 106.75 | Q58: 116.05 | R58: 259.8 | S58: 276.85 | T58: 340.9 | U58: 274.45 | V58: 193.8 | W58: 91.4 | X58: 137.75 | Y58: 84.1 | Z58: 87.6 | AA58: 244.55 | AB58: 4275.65
B59: ENGIE | C59: C.E. PUNTA LOMITAS_EXP | D59: PUN LOM_EXP-BL2 | E59: EÓLICA | F59: 142.75 | G59: 106.7 | H59: 127.9 | I59: 155 | J59: 130.95 | K59: 165.8 | L59: 211.9 | M59: 164.1 | N59: 92.7 | O59: 140.3 | P59: 76.7 | Q59: 79.15 | R59: 169.9 | S59: 198.15 | T59: 253.75 | U59: 212.25 | V59: 111.1 | W59: 36.1 | X59: 40.9 | Y59: 40.2 | Z59: 25.2 | AA59: 136.55 | AB59: 2818.05
B60: ENGIE | C60: C.H. QUITARACSA | D60: CENTRAL | E60: HIDROELÉCTRICA | AB60: 0
B61: ENGIE | C61: C.H. YUNCAN | D61: CENTRAL | E61: HIDROELÉCTRICA | F61: 2071.75 | G61: 2068.6 | H61: 2071.6 | I61: 2070.9 | J61: 2071.95 | K61: 2071.7 | L61: 2073.7 | M61: 2070.35 | N61: 2074.6 | O61: 1983.2 | P61: 2074 | Q61: 2072.15 | R61: 2067.9 | S61: 1979.45 | T61: 2052.2 | U61: 2080.5 | V61: 2077.1 | W61: 2070.45 | X61: 2074.85 | Y61: 2066.75 | Z61: 2071.9 | AA61: 2071.25 | AB61: 45386.85
B62: ENGIE | C62: C.S. INTIPAMPA | D62: CENTRAL | E62: SOLAR | F62: 277.95 | G62: 208.65 | H62: 294.3 | I62: 307.75 | J62: 328.15 | K62: 296.25 | L62: 328 | M62: 325.65 | N62: 328.5 | O62: 320.9 | P62: 317.25 | Q62: 327.45 | R62: 325.95 | S62: 326.2 | T62: 320.3 | U62: 322.8 | V62: 321.4 | W62: 312.75 | X62: 248.95 | Y62: 259.05 | Z62: 81.05 | AA62: 303.9 | AB62: 6483.15
B63: ENGIE | C63: C.T. CHILCA 1 | D63: TG1 | E63: TERMOELÉCTRICA | F63: 3436.15 | G63: 3474.7 | H63: 3658.45 | I63: 3920.3 | J63: 3531.45 | K63: 2517.7 | L63: 3192.3 | M63: 3117.85 | N63: 230 | O63: 2589.95 | P63: 3535.7 | Q63: 3838.55 | R63: 3855.9 | S63: 3834.55 | T63: 3864.55 | U63: 3856.45 | V63: 2060.5 | W63: 662.35 | X63: 1030.5 | Y63: 2102.65 | Z63: 3981.4 | AA63: 3586.1 | AB63: 65878.05
B64: ENGIE | C64: C.T. CHILCA 1 | D64: TG2 | E64: TERMOELÉCTRICA | AB64: 0
B65: ENGIE | C65: C.T. CHILCA 1 | D65: TG3 | E65: TERMOELÉCTRICA | F65: 3042.95 | G65: 3618.95 | H65: 4172 | I65: 4513.65 | J65: 3512.8 | K65: 2669.6 | L65: 3571.05 | M65: 3665.75 | N65: 4027.9 | O65: 4129.05 | P65: 4037.75 | Q65: 249.65 | R65: 760.45 | S65: 159.55 | U65: 493.5 | V65: 399.15 | Z65: 3554.8 | AA65: 4035 | AB65: 50613.55
B66: ENGIE | C66: C.T. CHILCA 1 | D66: TV | E66: TERMOELÉCTRICA | F66: 3048.95 | G66: 3682.95 | H66: 3961.4 | I66: 4167.25 | J66: 3614.7 | K66: 3011.9 | L66: 3559.1 | M66: 3503.35 | N66: 1841.3 | O66: 3226.15 | P66: 3748.15 | Q66: 1652.25 | R66: 1659.95 | S66: 1642.55 | T66: 1656.85 | U66: 1654.5 | V66: 639.45 | Y66: 722.95 | Z66: 3570.5 | AA66: 3889.4 | AB66: 54453.6
B67: ENGIE | C67: C.T. CHILCA 2 | D67: TG41 | E67: TERMOELÉCTRICA | I67: 273.8 | N67: 168.7 | P67: 457.9 | Q67: 482.85 | U67: 181.25 | V67: 236.2 | W67: 235.55 | X67: 238.25 | Y67: 352.95 | Z67: 421.5 | AB67: 3048.95
B68: ENGIE | C68: C.T. CHILCA 2 | D68: TV42 | E68: TERMOELÉCTRICA | AB68: 0
B69: ENGIE | C69: C.T. NEPI | D69: TG41 | E69: TERMOELÉCTRICA | AB69: 0
B70: ENGIE | C70: C.T. NEPI | D70: TG42 | E70: TERMOELÉCTRICA | AB70: 0
B71: ENGIE | C71: C.T. NEPI | D71: TG43 | E71: TERMOELÉCTRICA | AB71: 0
B72: ENGIE | C72: C.T. RF PLANTA ILO | D72: TG1 | E72: TERMOELÉCTRICA | J72: 216.2 | V72: 1208.35 | W72: 442.6 | AB72: 1867.15
B73: ENGIE | C73: C.T. RF PLANTA ILO | D73: TG2 | E73: TERMOELÉCTRICA | V73: 1109.7 | X73: 496.8 | AB73: 1606.5
B74: ENGIE | C74: C.T. RF PLANTA ILO | D74: TG3 | E74: TERMOELÉCTRICA | V74: 1037.15 | X74: 515 | AB74: 1552.15
B75: FENIX POWER PERÚ | C75: C.T. FENIX | D75: GT11 | E75: TERMOELÉCTRICA | F75: 3186.75 | G75: 3118.65 | AA75: 1681.25 | AB75: 7986.65
B76: FENIX POWER PERÚ | C76: C.T. FENIX | D76: GT12 | E76: TERMOELÉCTRICA | F76: 3191.9 | G76: 3310.45 | H76: 3701 | Z76: 2807.25 | AA76: 164.85 | AB76: 13175.45
B77: FENIX POWER PERÚ | C77: C.T. FENIX | D77: TV10 | E77: TERMOELÉCTRICA | F77: 3798.4 | G77: 3735.75 | H77: 1934.9 | AB77: 9469.05
B78: GENERACIÓN ANDINA S.A.C. | C78: C.H. 8 DE AGOSTO | D78: CENTRAL | E78: HIDROELÉCTRICA | F78: 503.5 | G78: 502.5 | H78: 503.8 | I78: 465.4 | J78: 504 | K78: 504 | L78: 504 | M78: 504 | N78: 504 | O78: 503.25 | P78: 471.5 | Q78: 501.65 | R78: 501.7 | S78: 453.5 | T78: 497.25 | U78: 482.3 | V78: 499.3 | W78: 502.4 | X78: 502.1 | Y78: 475.95 | Z78: 293.1 | AA78: 504 | AB78: 10683.2
B79: GENERACIÓN ANDINA S.A.C. | C79: C.H. EL CARMEN | D79: CENTRAL | E79: HIDROELÉCTRICA | F79: 200.85 | G79: 201.6 | H79: 201.45 | I79: 194.05 | J79: 201.35 | K79: 193.85 | L79: 182.4 | M79: 170.5 | N79: 166.9 | O79: 164.8 | P79: 179.6 | Q79: 176.6 | R79: 198 | S79: 189.65 | T79: 184.95 | U79: 172.9 | V79: 180.4 | W79: 171 | X79: 168.3 | Y79: 195.4 | Z79: 179.15 | AA79: 187.35 | AB79: 4061.05
B80: GENERADORA DE ENERGÍA DEL PERÚ | C80: C.H. ÁNGEL I | D80: CENTRAL | E80: HIDROELÉCTRICA | F80: 489.6 | G80: 489.6 | H80: 489.6 | I80: 489.6 | J80: 489.6 | K80: 489.6 | L80: 489.6 | M80: 489.6 | N80: 489.6 | O80: 489.6 | P80: 489.6 | Q80: 450.55 | R80: 489.6 | S80: 489.6 | T80: 489.6 | U80: 489.6 | V80: 489.6 | W80: 489.6 | X80: 489.6 | Y80: 489.6 | Z80: 489.6 | AA80: 489.6 | AB80: 10732.15
B81: GENERADORA DE ENERGÍA DEL PERÚ | C81: C.H. ÁNGEL II | D81: CENTRAL | E81: HIDROELÉCTRICA | F81: 489.6 | G81: 489.6 | H81: 489.6 | I81: 489.6 | J81: 489.6 | K81: 489.6 | L81: 489.6 | M81: 489.6 | N81: 489.6 | O81: 489.6 | P81: 489.6 | Q81: 446.6 | R81: 489.6 | S81: 489.6 | T81: 489.6 | U81: 489.6 | V81: 489.6 | W81: 489.6 | X81: 489.6 | Y81: 489.6 | Z81: 489.6 | AA81: 489.6 | AB81: 10728.2
B82: GENERADORA DE ENERGÍA DEL PERÚ | C82: C.H. ÁNGEL III | D82: CENTRAL | E82: HIDROELÉCTRICA | F82: 484.8 | G82: 484.8 | H82: 484.8 | I82: 484.8 | J82: 484.8 | K82: 484.8 | L82: 484.8 | M82: 484.8 | N82: 484.8 | O82: 484.8 | P82: 484.8 | Q82: 433.5 | R82: 480 | S82: 480 | T82: 480 | U82: 483 | V82: 484.8 | W82: 484.8 | X82: 484.8 | Y82: 484.8 | Z82: 484.8 | AA82: 484.8 | AB82: 10598.1
B83: GENERADORA DE ENERGÍA DEL PERÚ | C83: C.H. LA JOYA | D83: CENTRAL | E83: HIDROELÉCTRICA | F83: 184.05 | G83: 162.95 | H83: 194.25 | I83: 201.35 | J83: 218.05 | K83: 126.45 | L83: 225.25 | M83: 205.5 | N83: 185.35 | O83: 198.15 | P83: 187.4 | Q83: 201.45 | R83: 205.9 | S83: 198.85 | T83: 209.5 | U83: 209.15 | V83: 210.25 | W83: 208.05 | X83: 208.95 | Y83: 209.05 | Z83: 199.7 | AA83: 171.5 | AB83: 4321.1
B84: GM OPERACIONES S.A.C. | C84: CT REFINERIA TALARA | D84: TV1 REF TALARA | E84: TERMOELÉCTRICA | F84: 114.1 | G84: 432.7 | H84: 590.8 | I84: 789.4 | J84: 936.7 | K84: 1033.1 | L84: 1058.9 | M84: 1053.25 | N84: 1042.8 | O84: 1045.35 | P84: 1048.2 | Q84: 1048.875 | R84: 1021.57 | S84: 1013.9 | T84: 971.415 | U84: 1044.35 | V84: 1037.2 | W84: 1006.05 | X84: 1016.05 | Y84: 903.2 | Z84: 1004.6 | AA84: 1020.2 | AB84: 20232.71
B85: GM OPERACIONES S.A.C. | C85: CT REFINERIA TALARA | D85: TV2 REF TALARA | E85: TERMOELÉCTRICA | N85: 115.2 | O85: 448.3 | P85: 485.8 | Q85: 592.58 | R85: 745.865 | S85: 582.3 | T85: 619.79 | U85: 711.25 | V85: 720.45 | W85: 412.75 | X85: 22.75 | Y85: 632.25 | Z85: 740.05 | AA85: 758.7 | AB85: 7588.035
B86: GR CORTARRAMA SOCIEDAD ANONIMA CERRADA | C86: C.S. MATARANI | D86: C.S. MATARANI | E86: SOLAR | F86: 618.9 | G86: 610.2 | H86: 579.2 | I86: 677.1 | J86: 676.1 | K86: 10.9 | L86: 671.2 | M86: 679.3 | N86: 692.7 | O86: 701.9 | P86: 607.05 | Q86: 696.05 | R86: 697.4 | S86: 634 | T86: 688.2 | U86: 692.3 | V86: 700.95 | W86: 675.75 | X86: 484.05 | Y86: 508 | Z86: 258.85 | AA86: 575.8 | AB86: 13135.9
B87: GR PAINO SOCIEDAD ANONIMA CERRADA | C87: C.E. HUAMBOS | D87: CENTRAL | E87: EÓLICA | F87: 33.05 | G87: 79.4 | H87: 72.7 | I87: 186.65 | J87: 242.8 | K87: 230.25 | L87: 201.1 | M87: 146 | N87: 192.65 | O87: 36.75 | P87: 17.9 | Q87: 23.05 | R87: 185.15 | S87: 265.2 | T87: 238.15 | U87: 159.75 | V87: 263.6 | W87: 285.3 | X87: 243.7 | Y87: 136.35 | Z87: 79.75 | AA87: 20.25 | AB87: 3339.5
B88: GR TARUCA SOCIEDAD ANONIMA CERRADA | C88: C.E. DUNA | D88: CENTRAL | E88: EÓLICA | F88: 53.2 | G88: 103.5 | H88: 102 | I88: 241.35 | J88: 307.25 | K88: 285.6 | L88: 264.25 | M88: 198.1 | N88: 201.25 | O88: 40.4 | P88: 23.6 | Q88: 28.5 | R88: 248.5 | S88: 318.95 | T88: 297.6 | U88: 194.65 | V88: 334.7 | W88: 352.4 | X88: 333 | Y88: 204.3 | Z88: 92.4 | AA88: 22.8 | AB88: 4248.3
B89: HIDROCAÑETE S.A. | C89: C.H. IMPERIAL | D89: CENTRAL | E89: HIDROELÉCTRICA | F89: 84.85 | G89: 85.55 | H89: 86 | I89: 85.1 | J89: 87.1 | K89: 88.45 | L89: 87.1 | M89: 85.75 | N89: 75.9 | O89: 87.45 | P89: 88 | Q89: 86 | R89: 87.75 | S89: 89.35 | T89: 88.7 | U89: 87.2 | V89: 85.3 | W89: 87.1 | X89: 85.55 | Y89: 85.7 | Z89: 84.45 | AA89: 85.95 | AB89: 1894.3
B90: HIDROELECTRICA HUANCHOR S.A.C. | C90: C.H. HUANCHOR | D90: CENTRAL | E90: HIDROELÉCTRICA | F90: 444.3032 | G90: 440.55 | H90: 442.15 | I90: 398.3 | J90: 437.4 | K90: 445.05 | L90: 443.95 | M90: 444.6 | N90: 444.6 | O90: 445.2 | P90: 444.35 | Q90: 444 | R90: 445.1 | S90: 443.4 | T90: 443.5 | U90: 444.65 | V90: 444 | W90: 444.2 | X90: 446.05 | Y90: 445.78156 | Z90: 445.75 | AA90: 448.05 | AB90: 9724.9348
B91: HUAURA POWER GROUP S.A. | C91: C.H. YARUCAYA | D91: CENTRAL | E91: HIDROELÉCTRICA | F91: 444.35 | G91: 228.25 | H91: 94.55 | I91: 119.7 | J91: 221.3 | K91: 223.2 | L91: 223.2 | M91: 223.2 | N91: 223.2 | O91: 222.6 | P91: 223.2 | Q91: 223.15 | R91: 223.2 | S91: 223.2 | T91: 222.95 | U91: 223.2 | V91: 223.2 | W91: 223.2 | X91: 223.2 | Y91: 223.2 | Z91: 223.2 | AA91: 222.75 | AB91: 4901.2
B92: HYDRO GLOBAL PERÚ S.A.C. | C92: CH SAN GABAN III | D92: CHSAN GABAN III | E92: HIDROELÉCTRICA | V92: 185.935 | W92: 223.256 | X92: 421.894 | Y92: 125.155 | AA92: 679.245 | AB92: 1635.485
B93: INFRAESTRUCTURAS Y ENERGIAS DEL PERU S.A.C. | C93: C.T. RF PTO MALDONADO | D93: CENTRAL | E93: TERMOELÉCTRICA | K93: 86.8 | L93: 32.15 | AB93: 118.95
B94: INFRAESTRUCTURAS Y ENERGIAS DEL PERU S.A.C. | C94: C.T. RF PUCALLPA | D94: CENTRAL | E94: TERMOELÉCTRICA | K94: 131.5 | O94: 17.65 | AB94: 149.15
B95: INLAND ENERGY SAC | C95: C.H. SANTA TERESA | D95: CENTRAL | E95: HIDROELÉCTRICA | F95: 2165.05 | G95: 2166.25 | H95: 2155.3 | I95: 2162.95 | J95: 2125.4 | K95: 2133.9 | L95: 2177.15 | M95: 2161.6 | N95: 2137.5 | O95: 2157.5 | P95: 2156.65 | Q95: 2138.15 | R95: 1601.725 | S95: 2177.1 | T95: 2172.35 | U95: 2155.15 | V95: 2151.15 | W95: 2172.35 | X95: 2174.15 | Y95: 2158.4 | Z95: 2163.75 | AA95: 2169.55 | AB95: 46933.075
B96: INVERSIONES SHAQSHA S.A.C. | C96: C.H. PARIAC | D96: CENTRAL | E96: HIDROELÉCTRICA | F96: 104.7 | G96: 103.2 | H96: 98.15 | I96: 105.6 | J96: 107.85 | K96: 108.45 | L96: 108.85 | M96: 110.4 | N96: 110.4 | O96: 110.1 | P96: 111.6 | Q96: 110.8 | R96: 106.89 | S96: 111.5 | T96: 111.3 | U96: 112.15 | V96: 111.7 | W96: 112.8 | X96: 111.7 | Y96: 112.65 | Z96: 111.55 | AA96: 110.4 | AB96: 2402.74
B97: JOYA SOLAR S.A.C. | C97: C.S. SAN MARTIN SOLAR | D97: CENTRAL | E97: SOLAR | O97: 27.405 | P97: 447.54 | Q97: 1100.3 | R97: 1063.415 | S97: 1293.545 | T97: 708.18 | U97: 1532.245 | V97: 1946.61 | W97: 1974.185 | X97: 1540.6515 | Y97: 1578.02 | Z97: 903.515 | AA97: 1783.075 | AB97: 15898.686
B98: KALLPA GENERACION S.A. | C98: C.H. CERRO DEL AGUILA | D98: CENTRAL | E98: HIDROELÉCTRICA | F98: 13408.8 | G98: 13394.55 | H98: 11308.8 | I98: 12224.1 | J98: 13304.26 | K98: 13006.1 | L98: 13406.05 | M98: 13384.85 | N98: 13430.55 | O98: 13418.25 | P98: 10633.3 | Q98: 11389.05 | R98: 13350.95 | S98: 13423.9 | T98: 13399.8 | U98: 12845.75 | V98: 12932 | W98: 13361.2 | X98: 13448.8 | Y98: 13449.9 | Z98: 13410.15 | AA98: 13420.95 | AB98: 285352.06
B99: KALLPA GENERACION S.A. | C99: C.T. KALLPA | D99: TG1 | E99: TERMOELÉCTRICA | F99: 2961.8 | G99: 3023.25 | H99: 3288.05 | I99: 3169.85 | J99: 2972.61 | K99: 2797.85 | L99: 2792.7 | M99: 2742 | N99: 3021.95 | O99: 2936.8 | P99: 3082.85 | Q99: 2978.55 | R99: 2863 | S99: 2815.15 | T99: 2838.15 | U99: 2953.55 | V99: 2996.2 | W99: 2910 | X99: 3235.75 | Y99: 3178.5 | Z99: 3394.8 | AA99: 2795.45 | AB99: 65748.81
B100: KALLPA GENERACION S.A. | C100: C.T. KALLPA | D100: TG2 | E100: TERMOELÉCTRICA | F100: 2959.1 | G100: 3018.55 | H100: 3285.95 | I100: 3170.8 | J100: 2968.27 | K100: 2795.35 | L100: 2779.1 | M100: 2737.2 | N100: 3023.4 | O100: 2931.85 | P100: 3085.45 | Q100: 2977.3 | R100: 2859.75 | S100: 2809.2 | T100: 2832.85 | U100: 2948.9 | V100: 3009.85 | W100: 2900.7 | X100: 3266.45 | Y100: 3204.9 | Z100: 3399.45 | AA100: 2789.75 | AB100: 65754.12
B101: KALLPA GENERACION S.A. | C101: C.T. KALLPA | D101: TG3 | E101: TERMOELÉCTRICA | F101: 2957.85 | G101: 3016.15 | H101: 3287.2 | I101: 3171.45 | J101: 2968.445 | K101: 2793.95 | L101: 2779.95 | M101: 2740.55 | N101: 3023.5 | O101: 2933.4 | P101: 3087.65 | Q101: 2972.5 | R101: 1856.6 | S101: 2811.95 | T101: 2833.95 | U101: 2950.95 | V101: 3011.8 | W101: 2906 | X101: 3265.25 | Y101: 3209.8 | Z101: 3402.4 | AA101: 2792.45 | AB101: 64773.745
B102: KALLPA GENERACION S.A. | C102: C.T. KALLPA | D102: TV | E102: TERMOELÉCTRICA | F102: 5369.05 | G102: 5402.15 | H102: 5621.85 | I102: 5538.9 | J102: 5386.72 | K102: 5219.1 | L102: 5197.2 | M102: 5143.1 | N102: 5411.45 | O102: 5344.05 | P102: 5471.15 | Q102: 5370.1 | R102: 4509.55 | S102: 5230 | T102: 5245.4 | U102: 5349.65 | V102: 5375.75 | W102: 5298.6 | X102: 5602.55 | Y102: 5549.4 | Z102: 5761.25 | AA102: 5172.1 | AB102: 117569.07
B103: KALLPA GENERACION S.A. | C103: C.T. LAS FLORES | D103: TG1 | E103: TERMOELÉCTRICA | F103: 3812.95 | G103: 3553.5 | H103: 4147.65 | I103: 3984.75 | J103: 3519.735 | K103: 2961.75 | L103: 3331.55 | M103: 3351.35 | N103: 3776.4 | O103: 4115.4 | P103: 4148.8 | Q103: 4721.1 | R103: 3475.15 | S103: 3665.15 | T103: 3772.1 | U103: 4052.2 | V103: 54.95 | Z103: 3795 | AA103: 3933.35 | AB103: 68172.835
...

Sheet G_AREAS
B3: martes, 22 de Abril del 2025
B5: HORA | C5: RESUMEN DE GENERACIÓN POR ÁREAS DEL SEIN | D5: RESUMEN DE GENERACIÓN POR ÁREAS DEL SEIN | E5: RESUMEN DE GENERACIÓN POR ÁREAS DEL SEIN | F5: RESUMEN DE GENERACIÓN POR ÁREAS DEL SEIN | G5: RESUMEN DE GENERACIÓN POR ÁREAS DEL SEIN | H5: RESUMEN DE GENERACIÓN POR ÁREAS DEL SEIN | I5: RESUMEN DE GENERACIÓN POR ÁREAS DEL SEIN | J5: RESUMEN DE GENERACIÓN POR ÁREAS DEL SEIN | K5: RESUMEN DE GENERACIÓN POR ÁREAS DEL SEIN | L5: RESUMEN DE GENERACIÓN POR ÁREAS DEL SEIN | M5: RESUMEN DE GENERACIÓN POR ÁREAS DEL SEIN | N5: RESUMEN DE GENERACIÓN POR ÁREAS DEL SEIN | O5: RESUMEN DE GENERACIÓN POR ÁREAS DEL SEIN | P5: RESUMEN DE GENERACIÓN POR ÁREAS DEL SEIN | Q5: RESUMEN DE GENERACIÓN POR ÁREAS DEL SEIN | R5: RESUMEN DE GENERACIÓN POR ÁREAS DEL SEIN | S5: HORA | T5: GENERACIÓN POR TIPO DE GENERACIÓN | U5: GENERACIÓN POR TIPO DE GENERACIÓN | V5: GENERACIÓN POR TIPO DE GENERACIÓN | W5: GENERACIÓN POR TIPO DE GENERACIÓN | X5: GENERACIÓN POR TIPO DE GENERACIÓN | Y5: HORA | Z5: GENERACIÓN POR TIPO DE GENERACIÓN | AA5: GENERACIÓN POR TIPO DE GENERACIÓN | AB5: GENERACIÓN POR TIPO DE GENERACIÓN | AC5: GENERACIÓN POR TIPO DE GENERACIÓN | AD5: GENERACIÓN POR TIPO DE GENERACIÓN
C6: NORTE | D6: NORTE | E6: NORTE | F6: NORTE | G6: CENTRO | H6: CENTRO | I6: CENTRO | J6: CENTRO | K6: SUR | L6: SUR | M6: SUR | N6: SUR | O6: GENERACIÓN INTEGRANTES COES | P6: GENERACIÓN INTEGRANTES COES | Q6: GENERACIÓN INTEGRANTES COES | R6: GENERACIÓN INTEGRANTES COES | T6: INTEGRANTES COES | U6: INTEGRANTES COES | V6: INTEGRANTES COES | W6: INTEGRANTES COES | X6: INTEGRANTES COES | Z6: INTEGRANTES COES RER | AA6: INTEGRANTES COES RER | AB6: INTEGRANTES COES RER | AC6: INTEGRANTES COES RER | AD6: INTEGRANTES COES RER
C7: GENERACIÓN HIDROELÉCTRICA NORTE | D7: GENERACIÓN TERMOELÉCTRICA NORTE | E7: GENERACIÓN SOLAR NORTE | F7: GENERACIÓN EÓLICA NORTE | G7: GENERACIÓN HIDROELÉCTRICA CENTRO | H7: GENERACIÓN TERMOELÉCTRICA CENTRO | I7: GENERACIÓN SOLAR CENTRO | J7: GENERACIÓN EÓLICA CENTRO | K7: GENERACIÓN HIDROELÉCTRICA SUR | L7: GENERACIÓN TERMOELÉCTRICA SUR | M7: GENERACIÓN SOLAR SUR | N7: GENERACIÓN EÓLICA SUR | O7: GENERACIÓN COES NORTE | P7: GENERACIÓN COES CENTRO | Q7: GENERACIÓN COES SUR | R7: TOTAL GENERACION | T7: HIDROELÉCTRICA | U7: TERMOELÉCTRICA | V7: SOLAR | W7: EÓLICA | X7: TOTAL GENERACION | Z7: HIDROELÉCTRICA RER | AA7: TERMOELÉCTRICA RER | AB7: SOLAR RER | AC7: EÓLICA RER | AD7: TOTAL RER
B8: 00:30 | C8: 424.7 | D8: 122.7 | E8: 0 | F8: 54.2 | G8: 3142.2 | H8: 1543.1 | I8: 0 | J8: 515.8 | K8: 548.1 | L8: 0 | M8: 0 | N8: 0 | O8: 601.6 | P8: 5201.1 | Q8: 548.1 | R8: 6350.8 | S8: 00:30 | T8: 4115 | U8: 1665.8 | V8: 0 | W8: 570 | X8: 6350.8 | Y8: 00:30 | Z8: 342.8 | AA8: 25.4 | AB8: 0 | AC8: 570 | AD8: 938.2
B9: 01:00 | C9: 429.3 | D9: 98.2 | E9: 0 | F9: 69.6 | G9: 3347.9 | H9: 1393.4 | I9: 0 | J9: 591.6 | K9: 553.7 | L9: 0 | M9: 0 | N9: 0 | O9: 597.1 | P9: 5332.9 | Q9: 553.7 | R9: 6483.7 | S9: 01:00 | T9: 4330.9 | U9: 1491.6 | V9: 0 | W9: 661.2 | X9: 6483.7 | Y9: 01:00 | Z9: 340.5 | AA9: 25.4 | AB9: 0 | AC9: 661.2 | AD9: 1027.1
B10: 01:30 | C10: 429 | D10: 97.6 | E10: 0 | F10: 56.3 | G10: 3346.3 | H10: 1399.4 | I10: 0 | J10: 581.3 | K10: 560.7 | L10: 0 | M10: 0 | N10: 0 | O10: 582.9 | P10: 5327 | Q10: 560.7 | R10: 6470.6 | S10: 01:30 | T10: 4336 | U10: 1497 | V10: 0 | W10: 637.6 | X10: 6470.6 | Y10: 01:30 | Z10: 340.7 | AA10: 25.4 | AB10: 0 | AC10: 637.6 | AD10: 1003.7
B11: 02:00 | C11: 432.3 | D11: 98.6 | E11: 0 | F11: 34.4 | G11: 3245.8 | H11: 1395.8 | I11: 0 | J11: 533 | K11: 548 | L11: 0 | M11: 0 | N11: 0 | O11: 565.3 | P11: 5174.6 | Q11: 548 | R11: 6287.9 | S11: 02:00 | T11: 4226.1 | U11: 1494.4 | V11: 0 | W11: 567.4 | X11: 6287.9 | Y11: 02:00 | Z11: 340.1 | AA11: 26.4 | AB11: 0 | AC11: 567.4 | AD11: 933.9
B12: 02:30 | C12: 424.7 | D12: 98.8 | E12: 0 | F12: 31.6 | G12: 3326.8 | H12: 1465.6 | I12: 0 | J12: 486.3 | K12: 553.7 | L12: 0 | M12: 0 | N12: 0 | O12: 555.1 | P12: 5278.7 | Q12: 553.7 | R12: 6387.5 | S12: 02:30 | T12: 4305.2 | U12: 1564.4 | V12: 0 | W12: 517.9 | X12: 6387.5 | Y12: 02:30 | Z12: 340.5 | AA12: 26.4 | AB12: 0 | AC12: 517.9 | AD12: 884.8
B13: 03:00 | C13: 427.8 | D13: 99.1 | E13: 0 | F13: 41.1 | G13: 3285.4 | H13: 1424.3 | I13: 0 | J13: 501.1 | K13: 552.8 | L13: 0 | M13: 0 | N13: 0 | O13: 568 | P13: 5210.8 | Q13: 552.8 | R13: 6331.6 | S13: 03:00 | T13: 4266 | U13: 1523.4 | V13: 0 | W13: 542.2 | X13: 6331.6 | Y13: 03:00 | Z13: 340 | AA13: 26.1 | AB13: 0 | AC13: 542.2 | AD13: 908.3
B14: 03:30 | C14: 427.5 | D14: 99.4 | E14: 0 | F14: 54.2 | G14: 3268.7 | H14: 1429.3 | I14: 0 | J14: 496.7 | K14: 552.3 | L14: 0 | M14: 0 | N14: 0 | O14: 581.1 | P14: 5194.7 | Q14: 552.3 | R14: 6328.1 | S14: 03:30 | T14: 4248.5 | U14: 1528.7 | V14: 0 | W14: 550.9 | X14: 6328.1 | Y14: 03:30 | Z14: 339.4 | AA14: 26.3 | AB14: 0 | AC14: 550.9 | AD14: 916.6
B15: 04:00 | C15: 431.5 | D15: 99.3 | E15: 0 | F15: 59.5 | G15: 3300 | H15: 1439.9 | I15: 0 | J15: 478.5 | K15: 560 | L15: 0 | M15: 0 | N15: 0 | O15: 590.3 | P15: 5218.4 | Q15: 560 | R15: 6368.7 | S15: 04:00 | T15: 4291.5 | U15: 1539.2 | V15: 0 | W15: 538 | X15: 6368.7 | Y15: 04:00 | Z15: 339.9 | AA15: 26.4 | AB15: 0 | AC15: 538 | AD15: 904.3
B16: 04:30 | C16: 428.6 | D16: 99.4 | E16: 0 | F16: 62.8 | G16: 3311.6 | H16: 1417.7 | I16: 0 | J16: 395.7 | K16: 554.9 | L16: 0 | M16: 0 | N16: 0 | O16: 590.8 | P16: 5125 | Q16: 554.9 | R16: 6270.7 | S16: 04:30 | T16: 4295.1 | U16: 1517.1 | V16: 0 | W16: 458.5 | X16: 6270.7 | Y16: 04:30 | Z16: 338.9 | AA16: 25.4 | AB16: 0 | AC16: 458.5 | AD16: 822.8
B17: 05:00 | C17: 429.6 | D17: 121.1 | E17: 0 | F17: 72.5 | G17: 3362.3 | H17: 1618.5 | I17: 0 | J17: 355.2 | K17: 559.3 | L17: 0 | M17: 0 | N17: 0 | O17: 623.2 | P17: 5336 | Q17: 559.3 | R17: 6518.5 | S17: 05:00 | T17: 4351.2 | U17: 1739.6 | V17: 0 | W17: 427.7 | X17: 6518.5 | Y17: 05:00 | Z17: 339.6 | AA17: 25.4 | AB17: 0 | AC17: 427.7 | AD17: 792.7
B18: 05:30 | C18: 463.7 | D18: 120.5 | E18: 0 | F18: 69.3 | G18: 3330.5 | H18: 1690.2 | I18: 0 | J18: 302.6 | K18: 558.9 | L18: 0 | M18: 0 | N18: 0 | O18: 653.5 | P18: 5323.3 | Q18: 558.9 | R18: 6535.7 | S18: 05:30 | T18: 4353.1 | U18: 1810.7 | V18: 0 | W18: 371.9 | X18: 6535.7 | Y18: 05:30 | Z18: 339.8 | AA18: 25.4 | AB18: 0 | AC18: 371.9 | AD18: 737.1
B19: 06:00 | C19: 460.9 | D19: 120.4 | E19: 0 | F19: 65.3 | G19: 3386 | H19: 1807.8 | I19: 0 | J19: 273.6 | K19: 555.1 | L19: 0 | M19: 2.1 | N19: 0 | O19: 646.6 | P19: 5467.4 | Q19: 557.2 | R19: 6671.2 | S19: 06:00 | T19: 4402 | U19: 1928.2 | V19: 2.1 | W19: 338.9 | X19: 6671.2 | Y19: 06:00 | Z19: 340.3 | AA19: 25.9 | AB19: 2.1 | AC19: 338.9 | AD19: 707.2
... B56: TOTAL MWh | C56: 10884.6 | D56: 2747.3 | E56: 2.1 | F56: 1859.9 | G56: 82944.55 | H56: 42673.45 | I56: 9.05 | J56: 12370.65 | K56: 14138.545 | L56: 372.85 | M56: 4789.625 | N56: 0 | O56: 15493.9 | P56: 137997.7 | Q56: 19301.02 | R56: 172792.62 | S56: TOTAL MWh | T56: 107967.7 | U56: 45793.6 | V56: 4800.775 | W56: 14230.55 | X56: 172792.62 | Y56: TOTAL MWh | Z56: 8367.85 | AA56: 575.95 | AB56: 4800.775 | AC56: 14230.55 | AD56: 27975.125

Sheet HOP
B3: martes, 22 de Abril del 2025
B5: Reporte de Horas de Operación
B6: Empresa | C6: Central | D6: Grupo | E6: Modo de Operación | F6: Inicio | G6: Final | H6: O. Arranque | I6: O. Parada | J6: Tipo Operación | K6: Ensayo de Potencia Efectiva | L6: Ensayo de Potencia Mínima | M6: Sistema | N6: Lim. Transm. | O6: Causa | P6: Observación
B7: AGRO INDUSTRIAL PARAMONGA S.A. | C7: C.T. PARAMONGA | D7: CENTRAL | E7: PARAMONGA - BAGAZO | F7: 22/04/2025 00:00:00 | G7: 23/04/2025 00:00:00 | J7: POR COGENERACION | O7: ...
B8: ENEL GENERACION PIURA S.A. | C8: C.T. MALACAS 1 | D8: CENTRAL | E8: MALACAS1 TG6 - GAS | F8: 22/04/2025 00:00:00 | G8: 22/04/2025 00:29:00 | J8: POR POTENCIA O ENERGIA | O8: ...
B9: ENEL GENERACION PIURA S.A. | C9: C.T. MALACAS 1 | D9: CENTRAL | E9: MALACAS1 TG6 - GAS | F9: 22/04/2025 00:29:00 | G9: 22/04/2025 04:38:00 | J9: A MINIMA CARGA | O9: ...
B10: ENEL GENERACION PIURA S.A. | C10: C.T. MALACAS 1 | D10: CENTRAL | E10: MALACAS1 TG6 - GAS | F10: 22/04/2025 04:38:00 | G10: 22/04/2025 22:47:00 | J10: POR POTENCIA O ENERGIA | O10: ...
B11: ENGIE | C11: C.T. CHILCA 1 | D11: CENTRAL | E11: CHILCA1 CCOMB TG1 & TG3 - GAS | F11: 22/04/2025 00:00:00 | G11: 22/04/2025 00:24:00 | J11: POR POTENCIA O ENERGIA | O11: ...
B12: ENGIE | C12: C.T. CHILCA 1 | D12: CENTRAL | E12: CHILCA1 CCOMB TG1 & TG3 - GAS | F12: 22/04/2025 00:24:00 | G12: 22/04/2025 04:44:00 | J12: A MINIMA CARGA | O12: ...
B13: ENGIE | C13: C.T. CHILCA 1 | D13: CENTRAL | E13: CHILCA1 CCOMB TG1 & TG3 - GAS | F13: 22/04/2025 04:44:00 | G13: 22/04/2025 23:57:00 | J13: POR POTENCIA O ENERGIA | O13: ... | P13: A las 12:42 h, S/C generar a 400 MW. A las 15:34 h, S/C generar a máxima. A las 23:17 h, S/C generar a 400 MW.
B14: ENGIE | C14: C.T. CHILCA 1 | D14: CENTRAL | E14: CHILCA1 CCOMB TG1 & TG3 - GAS | F14: 22/04/2025 23:57:00 | G14: 23/04/2025 00:00:00 | J14: A MINIMA CARGA | O14: ...
B15: FENIX POWER PERÚ | C15: C.T. FENIX | D15: GT12 | E15: FENIX GT12 - GAS | F15: 22/04/2025 00:00:00 | G15: 22/04/2025 04:14:00 | J15: POR PRUEBAS | O15: REQ. PROPIO
B16: FENIX POWER PERÚ | C16: C.T. FENIX | D16: GT11 | E16: FENIX GT11 - GAS | F16: 22/04/2025 03:22:00 | G16: 22/04/2025 19:31:00 | J16: POR PRUEBAS | O16: REQ. PROPIO | P16: A las 09:01 h, S/C generar a 170 MW por prueba.
B17: GM OPERACIONES S.A.C. | C17: CT REFINERIA TALARA | D17: TV1 REF TALARA | E17: REF_TALARA TV1 - NLH_RFG | F17: 22/04/2025 00:00:00 | G17: 23/04/2025 00:00:00 | J17: POR COGENERACION | O17: ...
B18: GM OPERACIONES S.A.C. | C18: CT REFINERIA TALARA | D18: TV2 REF TALARA | E18: REF_TALARA TV2 - NLH_RFG | F18: 22/04/2025 00:00:00 | G18: 23/04/2025 00:00:00 | J18: POR COGENERACION | O18: ...
B19: KALLPA GENERACION S.A. | C19: C.T. KALLPA | D19: CENTRAL | E19: KALLPA CCOMB TG1 & TG2 & TG3 - GAS | F19: 22/04/2025 00:00:00 | G19: 22/04/2025 16:34:00 | J19: POR RSF | O19: ...
B20: KALLPA GENERACION S.A. | C20: C.T. KALLPA | D20: CENTRAL | E20: KALLPA CCOMB TG1 & TG2 & TG3 - GAS | F20: 22/04/2025 16:34:00 | G20: 22/04/2025 19:41:00 | J20: POR POTENCIA O ENERGIA | O20: ...
B21: KALLPA GENERACION S.A. | C21: C.T. KALLPA | D21: CENTRAL | E21: KALLPA CCOMB TG1 & TG2 & TG3 - GAS | F21: 22/04/2025 19:41:00 | G21: 23/04/2025 00:00:00 | J21: POR RSF | O21: ...
B22: KALLPA GENERACION S.A. | C22: C.T. LAS FLORES | D22: CENTRAL | E22: LAS FLORES CCOMB TG1 - GAS | F22: 22/04/2025 00:00:00 | G22: 22/04/2025 05:55:00 | J22: A MINIMA CARGA | O22: ...
B23: KALLPA GENERACION S.A. | C23: C.T. LAS FLORES | D23: CENTRAL | E23: LAS FLORES CCOMB TG1 - GAS | F23: 22/04/2025 05:55:00 | G23: 22/04/2025 12:40:00 | J23: POR POTENCIA O ENERGIA | O23: ...
B24: KALLPA GENERACION S.A. | C24: C.T. LAS FLORES | D24: CENTRAL | E24: LAS FLORES CCOMB TG1 - GAS | F24: 22/04/2025 12:40:00 | G24: 22/04/2025 15:37:00 | J24: A MINIMA CARGA | O24: ...
B25: KALLPA GENERACION S.A. | C25: C.T. LAS FLORES | D25: CENTRAL | E25: LAS FLORES CCOMB TG1 - GAS | F25: 22/04/2025 15:37:00 | G25: 22/04/2025 22:43:00 | J25: POR POTENCIA O ENERGIA | O25: ...
B26: KALLPA GENERACION S.A. | C26: C.T. LAS FLORES | D26: CENTRAL | E26: LAS FLORES CCOMB TG1 - GAS | F26: 22/04/2025 22:43:00 | G26: 23/04/2025 00:00:00 | J26: A MINIMA CARGA | O26: ...
B27: ORYGEN PERU S.A.A. | C27: C.T. VENTANILLA | D27: CENTRAL | E27: VENTANILLA CCOMB TG3 & TG4 - GAS | F27: 22/04/2025 00:00:00 | G27: 22/04/2025 08:08:00 | J27: A MINIMA CARGA | O27: ...
B28: ORYGEN PERU S.A.A. | C28: C.T. VENTANILLA | D28: CENTRAL | E28: VENTANILLA CCOMB TG3 & TG4 - GAS | F28: 22/04/2025 08:08:00 | G28: 22/04/2025 09:02:00 | J28: POR POTENCIA O ENERGIA | O28: ...
... B32: PETRAMAS | C32: C.T. HUAYCOLORO | D32: CENTRAL | E32: HUAYCOLORO - BIOGAS | F32: 22/04/2025 00:00:00 | G32: 23/04/2025 00:00:00 | J32: POR POTENCIA O ENERGIA | O32: ...
B33: PETRAMAS | C33: C.T.B DOÑA CATALINA | D33: CENTRAL | E33: DONA CATALINA - BIOGAS | F33: 22/04/2025 00:00:00 | G33: 23/04/2025 00:00:00 | H33: 22/04/2025 13:55:00 | I33: 22/04/2025 08:02:00 | J33: POR POTENCIA O ENERGIA | O33: ...
B34: PETRAMAS | C34: C.T.B. CALLAO | D34: CENTRAL | E34: CALLAO - BIOGAS | F34: 22/04/2025 00:00:00 | G34: 23/04/2025 00:00:00 | J34: POR POTENCIA O ENERGIA | O34: ...
B35: SAMAY I S.A.C | C35: C.T. PUERTO BRAVO | D35: TG2 | E35: PTO BRAVO TG2 - D2 | F35: 22/04/2025 18:25:00 | G35: 22/04/2025 20:53:00 | H35: 22/04/2025 18:01:00 | I35: 22/04/2025 20:41:00 | J35: POR PRUEBAS ALEATORIAS PR-25 | O35: ... | P35: A las 18:41 h, alcanzó su máxima generación
B36: SDF ENERGIA SAC | C36: C.T. OQUENDO | D36: CENTRAL | E36: OQUENDO CCOMB TG1 - GAS | F36: 22/04/2025 00:00:00 | G36: 23/04/2025 00:00:00 | J36: POR COGENERACION | O36: ...

Sheet INDISP
B3: martes, 22 de Abril del 2025
B5: Hora Inicio y Fin de Indisponibilidades de las Unidades de Generación SEIN
B6: Empresa | C6: Ubicación | D6: Equipo | E6: Inicio | F6: Final | G6: Descripción | H6: MW Indisp. | I6: Prog. | J6: Dispon | K6: Interrupc. | L6: Tipo | M6: CodEq | N6: TipoEq_Osinerg
B7: AGROAURORA S.A.C. | C7: MAPLE ETANOL | D7: CENTRAL | E7: 22/04/2025 00:00 | F7: 23/04/2025 00:00 | G7: MANTENIMIENTO PREVENTIVO PROGRAMADO DE LA CENTRAL TERMOELECTRICA Y EQUIPOS AUXILIARES. | H7: 14 | I7: P | J7: F/S | K7: N | L7: PREV. | M7: 13417 | N7: G
B8: AGROAURORA S.A.C. | C8: MAPLE ETANOL | D8: CENTRAL | E8: 22/04/2025 00:00 | F8: 23/04/2025 00:00 | G8: CENTRAL TERMOELECTRICA FUERA DE SERVICIO POR FALTA DE MATERIA PRIMA PARA LOS REQUERIMIENTOS DE CALOR ÚTIL EN FÁBRICA. | H8: 14 | I8: P | J8: F/S | K8: N | L8: OTROS | M8: 13417 | N8: G
B9: AGROINDUSTRIAS SAN JACINTO S.A.A. | C9: SAN JACINTO | D9: CENTRAL | E9: 22/04/2025 00:00 | F9: 23/04/2025 00:00 | G9: Mantenimiento Anual. | H9: 8.15 | I9: P | J9: F/S | K9: N | L9: PREV. | M9: 19865 | N9: G
B10: BIOENERGIA DEL CHIRA S.A. | C10: CAÑA BRAVA | D10: CENTRAL | E10: 22/04/2025 00:00 | F10: 23/04/2025 00:00 | G10: Para Central Caña Brava debido a mantenimiento anual preventivo | H10: 12 | I10: P | J10: F/S | K10: N | L10: PREV. | M10: 20510 | N10: G
B11: EGASA | C11: CHARCANI IV | D11: G3 | E11: 22/04/2025 00:00 | F11: 23/04/2025 00:00 | G11: Mantenimiento Generador | H11: 5.1 | I11: P | J11: F/S | K11: N | L11: PREV. | M11: 120 | N11: G
B12: EGEJUNIN | C12: SANTA CRUZ II | D12: G2 | E12: 22/04/2025 00:00 | F12: 23/04/2025 00:00 | G12: Mantenimiento correctivo mayor de turbina del G2. | H12: 3.15 | I12: P | J12: F/S | K12: N | L12: CORR. | M12: 12651 | N12: G
B13: ELECTROPERU | C13: MANTARO | D13: G6 | E13: 22/04/2025 00:03 | F13: 22/04/2025 10:48 | G13: MANTENIMIENTO PREVENTIVO Y CONTROLES SISTEMÁTICOS | H13: 100 | I13: P | J13: F/S | K13: N | L13: PREV. | M13: 6 | N13: G
B14: ENGIE | C14: CHILCA 1 | D14: TG2 | E14: 22/04/2025 00:00 | F14: 23/04/2025 00:00 | G14: INSPECCION DE 33000 EOH (HOT GAS PATH) | H14: 170 | I14: P | J14: F/S | K14: N | L14: PREV. | M14: 198 | N14: G
B15: ENGIE | C15: ILO 4 | D15: TG42 | E15: 22/04/2025 07:00 | F15: 22/04/2025 15:50 | G15: TG42 -Medición resistencia de los tiristores del sistema SFC | H15: 200 | I15: P | J15: F/S | K15: N | L15: CORR. | M15: 16329 | N15: G
B16: ENGIE | C16: QUITARACSA | D16: CENTRAL | E16: 22/04/2025 00:00 | F16: 23/04/2025 00:00 | G16: FUERA DE SERVICIO DEBIDO A INDISPONIBILIDAD BOCATOMA QUITARACSA Y SAN MATEO POR CAIDA DE ROCAS EN LA ZONA. NO SE PUEDE CAPTAR AGUA EN LA CONDICION PRESENTADA | H16: 110 | I16: P | J16: F/S | K16: N | L16: CORR. | M16: 14448 | N16: G
B17: ENGIE | C17: QUITARACSA | D17: G2 | E17: 22/04/2025 00:00 | F17: 23/04/2025 00:00 | G17: TERMOVACIO TRANSFORMADOR U2 | H17: 55 | I17: P | J17: F/S | K17: N | L17: PREV. | M17: 14450 | N17: G
B18: ENGIE | C18: YUNCÁN | D18: G2 | E18: 22/04/2025 00:00 | F18: 23/04/2025 00:00 | G18: MANTENIMIENTO CORRECTIVO DEL GENERADOR | H18: 45.5 | I18: P | J18: F/S | K18: N | L18: CORR. | M18: 200 | N18: G
... B37: TERMOCHILCA S.A.C. | C37: SANTO DOMINGO DE LOS OLLEROS | D37: TG1 | E37: 22/04/2025 00:00 | F37: 23/04/2025 00:00 | G37: Inspección mayor de la unidad TG1 (55000 horas)**************************** | H37: 296.3 | I37: P | J37: F/S | K37: N | L37: PREV. | M37: 13657 | N37: G

Sheet RESERVA_FRÍA
B3: 22/04/2025 | E3: EJECUTADO | L3: Martes 22 de Abril del 2025 / SEM N° 16 | V3: EJECUTADO | AC3: Martes 22 de Abril del 2025 / SEM N° 16 | EE3: ENERGIA RENOVABLES | GP3: COGENERACION | GY3: NO INTEGRANTES
B4: Martes | C4: STARO | E4: HYDROG | F4: ELECTROPERU | J4: ORAZU | L4: TER | N4: KALLPA GENERACION S.A. | V4: SHOUGESA | Z4: EGM | AA4: EGESUR | AD4: EGASA | AK4: SGB | AL4: CELEP | AM4: MINCVE | AN4: ETEN | AP4: HUALLA | AR4: LAVI | AS4: CHIN | AU4: HUANCH | AV4: CELER | AW4: INLD | AX4: FENIX POWER PERÚ | BA4: STATKRAFT S.A | BI4: HUANZA | BJ4: ENEL GENERACION PIURA S.A. | BM4: ENGIE | CA4: IYEP | CC4: SHAQSH | CD4: ORYGEN PERU S.A.A. | CP4: SAMAY I S.A.C | CT4: TCHILC | CV4: GENERACION | CY4: SALIDAS YUPANA | DC4: FLUJO EN LINEAS | DO4: COSTOS MARGINALES | DS4: RESERVA | DX4: DEMANDA POR AREAS | EE4: ACHI | EF4: COLCA | EG4: ERSUR | EH4: GRCOR | EI4: TARU | EJ4: KONDU | EK4: PIEREN | EL4: ORAZU | EN4: SGB | EO4: AIPSA | EP4: MAJA | EQ4: EGECSA | ER4: STANA | ES4: AGUAA | ET4: RDOBLE | EU4: HIDRO | EV4: HUARA | EW4: MOQUE | EX4: PANAM | EY4: PARQU | EZ4: PE3HER | FA4: PETRAMAS | FE4: TACNA | FF4: EYSAC | FG4: AURORA | FH4: AGROIN | FI4: ANDEA | FJ4: ASLC | FK4: ATRIA | FL4: EGEJUNIN | FP4: EGERBA | FQ4: EOL | FS4: ENGIE | FX4: GENE | FZ4: GENERADORA DE ENERGÍA DEL PERÚ | GD4: PAINO | GE4: JOYAS | GF4: SARCUS | GG4: ORYGEN PERU S.A.A. | GL4: RARCUS | GM4: SINERS | GP4: ACHI | GQ4: GM OP | GS4: SDF | GU4: AIPSA | GV4: AURORA | GW4: AGROIN | GY4: UNACEM | GZ4: EOR | HA4: AYEP | HB4: ELZANA | HC4: ENOSA | HD4: SDE | HE4: SINERS
