Workbook

Sheet EVENTOS
B3: miércoles, 15 de Enero del 2025
B5: INFORMACIÓN DE EVENTOS PRINCIPALES EN SUS INSTALACIONES
B6: TIPO DE EVENTO | C6: EMPRESA | D6: UBICACIÓN | E6: TIPO DE EQUIPO | F6: EQUIPO | G6: INICIO | H6: FINAL | I6: DESCRIPCIÓN | J6: MW INDISP. | K6: INTERRUPCIÓN (SI/NO) | L6: TENSIÓN DE FALLA (kV)
B7: FALLA | C7: CONCESIONARIA LINEA DE TRANSMISION CCNCM S.A.C. | D7: CAJAMARCA NORTE - CACLIC | E7: LINEA DE TRANSMISION | F7: L-2192 | G7: 15/01/2025 13:57:00 | H7: 15/01/2025 13:57:00 | I7: RECIERRE EXITOSO EN LA LÍNEA L-2192 (CAJAMARCA NORTE - CÁCLIC) DE 220 kV | K7: NO | L7: 220
B8: EVENTO | C8: CONELSUR LT SAC | D8: PORTILLO | E8: SUBESTACION | F8: SS.EE. | G8: 15/01/2025 00:00:00 | H8: 16/01/2025 00:00:00 | I8: DECLARACIÓN DE SITUACIÓN EXCEPCIONAL EN LA S.E. PORTILLO DE 60 kV | K8: NO
B9: FALLA | C9: EMPRESA DE GENERACION ELECTRICA SANTA ANA S.A.C. | D9: Derv. PUNTAYACU - LA VIRGEN | E9: LINEA DE TRANSMISION | F9: L-6089 | G9: 15/01/2025 12:54:00 | H9: 15/01/2025 13:02:00 | I9: DESCONEXIÓN DE LA LÍNEA L-6089 (CHANCHAMAYO -PUNTAYACU- LA VIRGEN) DE 60 kV | J9: 5.81 | K9: SI | L9: 138
B10: FALLA | C10: LUZ DEL SUR | D10: PORTILLO-ÑAÑA | E10: LINEA DE TRANSMISION | F10: L-6577 | G10: 15/01/2025 17:13:09 | H10: 15/01/2025 20:47:09 | I10: DESCONEXIÓN DE LA LÍNEA L-6577 (PORTILLO - NAÑA) 60KV | K10: NO | L10: 60
B11: FALLA | C11: RED DE ENERGIA DEL PERU S.A. | D11: AMARILIS - PARAGSHA II | E11: LINEA DE TRANSMISION | F11: L-1120 | G11: 15/01/2025 18:42:25 | H11: 15/01/2025 18:42:25 | I11: RECIERRE EXITOSO EN LA LÍNEA L-1120 ( AMARILIS - PARAGSHA II) 138 KV | K11: NO | L11: 138
B12: EVENTO | C12: RED DE ENERGIA DEL PERU S.A. | D12: TINGO MARÍA - AUCAYACU | E12: LINEA DE TRANSMISION | F12: L-1122 | G12: 15/01/2025 19:03:00 | H12: 15/01/2025 20:08:00 | I12: DECLARACIÓN DE SITUACIÓN EXCEPCIONAL EN LA LÍNEA L-1122 (TINGO MARÍA - AUCAYACU) DE 138 KV | K12: NO
B13: FALLA | C13: RED DE ENERGIA DEL PERU S.A. | D13: CHICLAYO OESTE | E13: SVC | F13: SVC-2 | G13: 15/01/2025 04:09:08 | H13: 15/01/2025 06:21:00 | I13: DESCONEXIÓN DEL SVC-2 DE LA S.E. CHICLAYO OESTE | K13: NO | L13: 0
B14: FALLA | C14: STATKRAFT S.A | D14: HUARÓN - EXCELSIOR | E14: LINEA DE TRANSMISION | F14: L-6516 | G14: 15/01/2025 09:29:12 | H14: 15/01/2025 15:30:00 | I14: DESCONEXIÓN DE LA LÍNEA L-6516 (CARHUAMAYO - EXCELSIOR) DE 50 kV | K14: NO | L14: 50

Sheet RESTRIC_OPE
B3: miércoles, 15 de Enero del 2025
B5: RESTRICCIONES OPERATIVAS
B6: FECHA | C6: HORA INICIO | D6: HORA FINAL | E6: EMPRESA | F6: UBICACIÓN | G6: T.Eq. | H6: EQUIPO | I6: DESCRIPCIÓN
B7: 15/01/2025 | C7: 00:00 | D7: 24:00 | E7: CELEPSA | F7: C.H. EL PLATANAL | G7: CH | H7: CENTRAL | I7: Debido al incremento del caudal del rio cañete y establecimiento de la temporada de avenida, se declara la C.H. El Platanal como CENTRAL HIDRÁULICA DE PASADA (correo 03/01/2025).
B8: 15/01/2025 | C8: 00:00 | D8: 24:00 | E8: CHINANGO S.A.C. | F8: C.H. CHIMAY | G8: GH | H8: G2 | I8: De acuerdo con el correo enviado el 27/12/2024 el grupo G2 de CH Chimay está habilitada con un límite de oferta de 72 MW.
B9: 15/01/2025 | C9: 00:00 | D9: 24:00 | E9: EGASA | F9: S.E. CONVERTIDOR | G9: BARRA | H9: BARRA138KV | I9: EGASA limitó la capacidad del transformador 138 kV/33 kV a 50 MVA por deterioro del aislamiento.
B10: 15/01/2025 | C10: 00:00 | D10: 24:00 | E10: ENEL GENERACION PIURA S.A. | F10: C.T. MALACAS | G10: CT | H10: CENTRAL | I10: De acuerdo con la comunicación vía correo del día 24.10.2024. ENEL GENERACIÓN PIURA informa una restricción de potencia para alcanzar 105 MW en simultaneo (TG6+TGN4).
B11: 15/01/2025 | C11: 00:00 | D11: 24:00 | E11: ENGIE | F11: C.E. PUNTA LOMITAS | G11: CE | H11: CENTRAL | I11: De acuerdo a la carta ENG/737-2024 (Exp:202400007555). Limitación de cables de media tensión a 100 MW de los transformadores PLT1 y PLT2 de la CE Punta Lomitas. Quedan limitados a 200 MW la generación de CE Punta Lomitas y Punta Lomitas Extensión.
B12: 15/01/2025 | C12: 00:00 | D12: 24:00 | E12: ENGIE | F12: C.H. QUITARACSA | G12: CH | H12: CENTRAL | I12: De acuerdo con el correo del 23.04 se considera la operación continua de la CH Quitaracsa debido a que el sistema de refrigeración de la CH Cañón del Pato se alimenta desde la descarga del caudal turbinado por la CH Quitaracsa.
B13: 15/01/2025 | C13: 00:00 | D13: 24:00 | E13: ENGIE | F13: C.H. YUNCÁN | G13: GH | H13: G3 | I13: Según la carta N° ENG/ 198-2024 enviada por su representada, se opera de forma continua el G3 de la CH Yuncán, debido a la ejecución de mantenimientos necesarios para evitar daños en los sellos de seguridad de la válvula esférica del grupo.
B14: 15/01/2025 | C14: 00:00 | D14: 24:00 | E14: ENGIE | F14: C.T. CHILCA 1 | G14: CT | H14: CENTRAL | I14: Restricción de temperatura de la C.T Chilca, ver valor en el modelo de despacho.
B15: 15/01/2025 | C15: 00:00 | D15: 24:00 | E15: ENGIE | F15: C.T. CHILCA 1 | G15: CT | H15: CENTRAL | I15: De acuerdo con el correo del 05/03 la CT Chilca 1 se encuentra indisponible para dar RSF.
B16: 15/01/2025 | C16: 00:00 | D16: 24:00 | E16: ENGIE | F16: C.T. CHILCA 1 | G16: CT | H16: CENTRAL | I16: Con carta ENG/971-2023, indica que no puede cumplir con las IO considerada en el PDO_17122023 dado que vulneran la seguridad de sus activos. Indican que se debe tomar TMO=168h.
B17: 15/01/2025 | C17: 00:00 | D17: 24:00 | E17: ENGIE | F17: C.T. CHILCA 2 | G17: CT | H17: CENTRAL | I17: Restricción de temperatura de la C.T Chilca2, ver valor en el modelo de despacho.
... B38: 15/01/2025 | C38: 00:00 | D38: 24:00 | E38: TRANSMANTARO | F38: S.E. SOCABAYA | G38: SSEE | H38: S.E. | I38: Opera en simple barra en 220 kV por indisponibilidad de la protección diferencial de barras por alarma.

Sheet MANTENIMIENTO EJECUTADOS
B3: miércoles, 15 de Enero del 2025
B5: Mantenimiento Ejecutado
B6: Empresa | C6: Ubicación | D6: Equipo | E6: Inicio | F6: Final | G6: Descripción | H6: MW Indisp. | I6: Prog. | J6: Dispon | K6: Interrupc. | L6: Tipo | M6: CodEq | N6: TipoEq_Osinerg
B7: ATLANTICA TRANSMISION SUR S.A. | C7: CHILCA-CTM | D7: INT-5261 | E7: 15/01/2025 00:00 | F7: 16/01/2025 00:00 | G7: Seccionador SBB-5261 fase S indisponible para maniobras de apertura y cierre por anomalia en tapa de tanque de compresion, el seccionador permanece cerrado y bloqueado. | H7: 0 | I7: P | J7: E/S | K7: N | L7: OTROS | M7: 13854 | N7: T
B8: ATLANTICA TRANSMISION SUR S.A. | C8: OCONA | D8: INT-5450 | E8: 15/01/2025 00:00 | F8: 16/01/2025 00:00 | G8: RESTRICCION OPERATIVA EN INTERRUPTOR INT-5450, POSICION CERRADA, REB-5450 EN SERVICIO SUMINISTRANDO LOS SS.AA. DE S.E. OCO?A | H8: 0 | I8: P | J8: E/S | K8: N | L8: OTROS | M8: 13761 | N8: T
B9: ATLANTICA TRANSMISION SUR S.A. | C9: OCONA | D9: INT-5462 | E9: 15/01/2025 00:00 | F9: 16/01/2025 00:00 | G9: Seccionador SBA-5462 fase T indisponible por problemas mecanicos, el seccionador permanece cerrado y bloqueado | H9: 0 | I9: P | J9: E/S | K9: N | L9: OTROS | M9: 13758 | N9: T
B10: ATLANTICA TRANSMISION SUR S.A. | C10: POROMA | D10: INT-5361 | E10: 15/01/2025 00:00 | F10: 16/01/2025 00:00 | G10: Seccionador SBA-5361 fase R indisponible por problemas mecanicos, el seccionador permanece cerrado y bloqueado | H10: 0 | I10: P | J10: E/S | K10: N | L10: OTROS | M10: 13746 | N10: T
B11: ATLANTICA TRANSMISION SUR S.A. | C11: POROMA | D11: REB-5350 | E11: 15/01/2025 00:00 | F11: 16/01/2025 00:00 | G11: FUERA DE SERVICIO POR FALLA EN EL EQUIPO. | H11: 0 | I11: P | J11: F/S | K11: N | L11: OTROS | M11: 13771 | N11: T
B12: ATRIA ENERGIA S.A.C. | C12: PURMACANA | D12: G1 | E12: 15/01/2025 00:00 | F12: 16/01/2025 00:00 | G12: OVERHAUL DE TURBINA | H12: 0.7 | I12: P | J12: F/S | K12: N | L12: PREV. | M12: 13133 | N12: G
B13: CONELSUR LT SAC | C13: CAJAMARQUILLA | D13: BARRA B 220kV | E13: 15/01/2025 00:00 | F13: 16/01/2025 00:00 | G13: CIERRE DE ACOPLE PARA ENERGIZAR LA BARRA B POR SEGURIDAD POR MANTENIMIENTO ANTICORROSIVO DE PORTICOS Y ESTRUCTURAS EN CL-2014, CL-2015 Y CL-TR1 | H13: 0 | I13: P | J13: E/S | K13: N | L13: SEG.PER | M13: 1104 | N13: T
B14: CONELSUR LT SAC | C14: CAJAMARQUILLA | D14: CL-2015 | E14: 15/01/2025 00:00 | F14: 15/01/2025 07:30 | G14: POR SEGURIDAD POR MANTENIMIENTO ANTICORROSIVO DE PORTICOS Y ESTRUCTURAS. SE REQUIERE AMBOS SECCIONADORES DE BARRA CERRADOS POR SEGURIDAD. | H14: 0 | I14: P | J14: E/S | K14: N | L14: SEG.PER | M14: 1535 | N14: T
B15: CONELSUR LT SAC | C15: CAJAMARQUILLA | D15: BARRA B 220kV | E15: 15/01/2025 05:07 | F15: 15/01/2025 07:35 | G15: CORONOGRAFIA DE EQUIPOS DE CONELSUR. SE REQUIERE LA BARRA B ENERGIZADO | H15: 0 | I15: P | J15: E/S | K15: N | L15: PREV. | M15: 1104 | N15: T
B16: CONELSUR LT SAC | C16: CAJAMARQUILLA | D16: CL-TRAFO | E16: 15/01/2025 07:35 | F16: 16/01/2025 00:00 | G16: POR SEGURIDAD POR MANTENIMIENTO ANTICORROSIVO DE PORTICOS Y ESTRUCTURAS. SE REQUIERE AMBOS SECCIONADORES DE BARRA CERRADOS POR SEGURIDAD. | H16: 0 | I16: P | J16: E/S | K16: N | L16: SEG.PER | M16: 1906 | N16: T
B17: CONELSUR LT SAC | C17: CALLALLI | D17: CL-1040 | E17: 15/01/2025 09:48 | F17: 15/01/2025 13:11 | G17: LEVANTAMIENTO DE INFORMACION, REVISION Y RETIRO DEL REGISTRADOR DE FALLAS DE LA CELDA CL-1040 DE LA S.E. CALLALLI. | H17: 0 | I17: P | J17: E/S | K17: N | L17: CORR. | M17: 12786 | N17: T
B18: CONELSUR LT SAC | C18: LOMERA | D18: BARRA A 220 kV | E18: 15/01/2025 00:00 | F18: 16/01/2025 00:00 | G18: POR REEMPLAZO DE COMPONENTES Y GAS SF6 EN CL2117. LOMERA OPERA EN BARRA SIMPLE | H18: 0 | I18: P | J18: F/S | K18: N | L18: OTROS | M18: 16951 | N18: T
... B91: TRANSMANTARO | C91: YARABAMBA | D91: IN-5120 | E91: 15/01/2025 00:00 | F91: 16/01/2025 00:00 | G91: INSTALACION DE CAPACITORES EN INTERRUPTOR IN-5120, ACTIVIDAD CON CORTE CONTINUO. (EL REACTOR R-31 DISPONIBLE PARA LA OPERACION CON MANDO SINCRONIZADO MEDIANTE EL INTERRUPTOR IN-5116). (R0097959) | H91: 0 | I91: P | J91: F/S | K91: N | L91: PREV. | M91: 17437 | N91: T

Sheet INGRESO OC
A3: miércoles, 15 de Enero del 2025
A5: INGRESO A OPERACIÓN COMERCIAL
A6: EMPRESA | B6: TIPO DE EQUIPO | C6: UBICACIÓN | D6: EQUIPO | E6: Fecha y hora de Ingreso a Operación Comercial

Sheet DESPACHO_EJECUTADO
B3: miércoles, 15 de Enero del 2025
A5: POTENCIA ACTIVA EJECUTADA DE LAS UNIDADES DE GENERACIÓN DEL SEIN (MW) | FH5: CENTRALES NO INTEGRANTES COES
A6: FECHA | B6: HORA | C6: 337 | D6: 338 | E6: 121 | F6: 101 | G6: 102 | H6: 42667 | I6: 42668 | J6: 126 | K6: 127 | L6: 138 | M6: 139 | N6: 197 | O6: 203 | P6: 204 | Q6: 230 | R6: 209 | S6: 56677 | T6: 796 | U6: 2146 | V6: 142 | W6: 143 | X6: 125 | Y6: 187 | Z6: 163 | AA6: 298 | AB6: 219 | AC6: 151 | AD6: 152 | AE6: 153 | AF6: 154 | AG6: 756 | AH6: 156 | AI6: 155 | AJ6: 182 | AK6: 212 | AL6: 758 | AM6: 263 | AN6: 265 | AO6: 775 | AP6: 777 | AQ6: 2154 | AR6: 150 | AS6: 149 | AT6: 188 | AU6: 2131 | AV6: 755 | AW6: 252 | AX6: 249 | AY6: 250 | AZ6: 117 | BA6: 267 | BB6: 268 | BC6: 119 | BD6: 120 | BE6: 189 | BF6: 122 | BG6: 266 | BH6: 251 | BI6: 115 | BJ6: 239 | BK6: 288 | BL6: 240 | BM6: 241 | BN6: 242 | BO6: 191 | BP6: 194 | BQ6: 196 | BR6: 207 | BS6: 236 | BT6: 795 | BU6: 285 | BV6: 995 | BW6: 996 | BX6: 997 | BY6: 766 | BZ6: 926 | CA6: 924 | CB6: 103 | CC6: 104 | CD6: 106 | CE6: 105 | CF6: 107 | CG6: 110 | CH6: 109 | CI6: 144 | CJ6: 113 | CK6: 114 | CL6: 193 | CM6: 208 | CN6: 786 | CO6: 787 | CP6: 788 | CQ6: 789 | CR6: 248 | CS6: 2159 | CT6: 303 | CU6: 59715 | CV6: 62255 | CW6: 1263 | CX6: 61800 | CY6: 2194 | CZ6: 216 | DA6: 198 | DB6: 214 | DC6: 260 | DD6: 2152 | DE6: 2128 | DF6: 247 | DG6: 228 | DH6: 2135 | DI6: 261 | DJ6: 237 | DK6: 253 | DL6: 770 | DM6: 225 | DN6: 2201 | DO6: 2171 | DP6: 760 | DQ6: 235 | DR6: 238 | DS6: 2184 | DT6: 61855 | DU6: 223 | DV6: 226 | DW6: 201 | DX6: 258 | DY6: 259 | DZ6: 920 | EA6: 257 | EB6: 256 | EC6: 2148 | ED6: 58288 | EE6: 58289 | EF6: 58839 | EG6: 58840 | EH6: 296 | EI6: 297 | EJ6: 211 | EK6: 2175 | EL6: 2178 | EM6: 2181 | EN6: 1262 | EO6: 233 | EP6: 2150 | EQ6: 2165 | ER6: 2161 | ES6: 61197 | ET6: 58851 | EU6: 234 | EV6: 215 | EW6: 917 | EX6: 289 | EY6: 58333 | EZ6: 58336 | FA6: 202 | FB6: 58487 | FC6: 213 | FD6: 232 | FE6: 2190 | FF6: TOTAL COES | FH6: 221 | FI6: 49607 | FJ6: 222 | FK6: 224 | FL6: 2187 | FM6: 227 | FN6: 49400 | FO6: 199 | FP6: 200 | FQ6: TOTAL NO COES
C7: CENTRO | D7: CENTRO | E7: NORTE | F7: CENTRO | G7: CENTRO | H7: NORTE | I7: NORTE | J7: NORTE | K7: NORTE | L7: CENTRO | M7: CENTRO | N7: CENTRO | O7: CENTRO | P7: CENTRO | Q7: CENTRO | R7: CENTRO | S7: CENTRO | T7: CENTRO | U7: CENTRO | V7: CENTRO | W7: CENTRO | X7: CENTRO | Y7: CENTRO | Z7: SUR | AA7: SUR | AB7: CENTRO | AC7: SUR | AD7: SUR | AE7: SUR | AF7: SUR | AG7: SUR | AH7: SUR | AI7: SUR | AJ7: SUR | AK7: CENTRO | AL7: NORTE | AM7: NORTE | AN7: NORTE | AO7: CENTRO | AP7: CENTRO | AQ7: CENTRO | AR7: CENTRO | AS7: CENTRO | AT7: CENTRO | AU7: CENTRO | AV7: SUR | AW7: CENTRO | AX7: CENTRO | AY7: CENTRO | AZ7: CENTRO | BA7: CENTRO | BB7: CENTRO | BC7: CENTRO | BD7: CENTRO | BE7: SUR | BF7: NORTE | BG7: CENTRO | BH7: CENTRO | BI7: NORTE | BJ7: NORTE | BK7: NORTE | BL7: SUR | BM7: SUR | BN7: SUR | BO7: CENTRO | BP7: CENTRO | BQ7: CENTRO | BR7: CENTRO | BS7: CENTRO | BT7: CENTRO | BU7: CENTRO | BV7: SUR | BW7: SUR | BX7: SUR | BY7: NORTE | BZ7: SUR | CA7: CENTRO | CB7: CENTRO | CC7: CENTRO | CD7: CENTRO | CE7: CENTRO | CF7: CENTRO | CG7: CENTRO | CH7: CENTRO | CI7: CENTRO | CJ7: CENTRO | CK7: CENTRO | CL7: CENTRO | CM7: CENTRO | CN7: SUR | CO7: SUR | CP7: SUR | CQ7: SUR | CR7: CENTRO | CS7: CENTRO | CT7: CENTRO | CU7: CENTRO | CV7: SUR | CW7: NORTE | CX7: NORTE | CY7: NORTE | CZ7: NORTE | DA7: NORTE | DB7: CENTRO | DC7: CENTRO | DD7: CENTRO | DE7: NORTE | DF7: NORTE | DG7: CENTRO | DH7: CENTRO | DI7: SUR | DJ7: SUR | DK7: CENTRO | DL7: CENTRO | DM7: CENTRO | DN7: CENTRO | DO7: CENTRO | DP7: CENTRO | DQ7: SUR | DR7: CENTRO | DS7: CENTRO | DT7: NORTE | DU7: CENTRO | DV7: CENTRO | DW7: NORTE | DX7: CENTRO | DY7: CENTRO | DZ7: CENTRO | EA7: NORTE | EB7: NORTE | EC7: SUR | ED7: CENTRO | EE7: CENTRO | EF7: CENTRO | EG7: CENTRO | EH7: CENTRO | EI7: CENTRO | EJ7: SUR | EK7: SUR | EL7: SUR | EM7: SUR | EN7: NORTE | EO7: SUR | EP7: SUR | EQ7: CENTRO | ER7: CENTRO | ES7: CENTRO | ET7: SUR | EU7: SUR | EV7: NORTE | EW7: CENTRO | EX7: NORTE | EY7: NORTE | EZ7: NORTE | FA7: CENTRO | FB7: CENTRO | FC7: CENTRO | FD7: NORTE | FE7: NORTE | FH7: NORTE | FI7: SUR | FJ7: CENTRO | FK7: NORTE | FL7: NORTE | FM7: NORTE | FN7: NORTE | FO7: NORTE | FP7: NORTE
C8: HIDROELÉCTRICA | D8: HIDROELÉCTRICA | E8: HIDROELÉCTRICA | F8: HIDROELÉCTRICA | G8: HIDROELÉCTRICA | H8: TERMOELÉCTRICA | I8: TERMOELÉCTRICA | J8: HIDROELÉCTRICA | K8: HIDROELÉCTRICA | L8: TERMOELÉCTRICA | M8: TERMOELÉCTRICA | N8: TERMOELÉCTRICA | O8: TERMOELÉCTRICA | P8: TERMOELÉCTRICA | Q8: TERMOELÉCTRICA | R8: TERMOELÉCTRICA | S8: TERMOELÉCTRICA | T8: HIDROELÉCTRICA | U8: HIDROELÉCTRICA | V8: TERMOELÉCTRICA | W8: TERMOELÉCTRICA | X8: TERMOELÉCTRICA | Y8: TERMOELÉCTRICA | Z8: HIDROELÉCTRICA | AA8: HIDROELÉCTRICA | AB8: TERMOELÉCTRICA | AC8: HIDROELÉCTRICA | AD8: HIDROELÉCTRICA | AE8: HIDROELÉCTRICA | AF8: HIDROELÉCTRICA | AG8: TERMOELÉCTRICA | AH8: TERMOELÉCTRICA | AI8: TERMOELÉCTRICA | AJ8: HIDROELÉCTRICA | AK8: HIDROELÉCTRICA | AL8: TERMOELÉCTRICA | AM8: TERMOELÉCTRICA | AN8: TERMOELÉCTRICA | AO8: HIDROELÉCTRICA | AP8: HIDROELÉCTRICA | AQ8: HIDROELÉCTRICA | AR8: HIDROELÉCTRICA | AS8: HIDROELÉCTRICA | AT8: HIDROELÉCTRICA | AU8: HIDROELÉCTRICA | AV8: HIDROELÉCTRICA | AW8: TERMOELÉCTRICA | AX8: TERMOELÉCTRICA | AY8: TERMOELÉCTRICA | AZ8: HIDROELÉCTRICA | BA8: HIDROELÉCTRICA | BB8: HIDROELÉCTRICA | BC8: HIDROELÉCTRICA | BD8: HIDROELÉCTRICA | BE8: HIDROELÉCTRICA | BF8: HIDROELÉCTRICA | BG8: HIDROELÉCTRICA | BH8: HIDROELÉCTRICA | BI8: TERMOELÉCTRICA | BJ8: TERMOELÉCTRICA | BK8: TERMOELÉCTRICA | BL8: TERMOELÉCTRICA | BM8: TERMOELÉCTRICA | BN8: TERMOELÉCTRICA | BO8: HIDROELÉCTRICA | BP8: TERMOELÉCTRICA | BQ8: TERMOELÉCTRICA | BR8: TERMOELÉCTRICA | BS8: TERMOELÉCTRICA | BT8: TERMOELÉCTRICA | BU8: TERMOELÉCTRICA | BV8: TERMOELÉCTRICA | BW8: TERMOELÉCTRICA | BX8: TERMOELÉCTRICA | BY8: HIDROELÉCTRICA | BZ8: TERMOELÉCTRICA | CA8: TERMOELÉCTRICA | CB8: HIDROELÉCTRICA | CC8: HIDROELÉCTRICA | CD8: HIDROELÉCTRICA | CE8: HIDROELÉCTRICA | CF8: HIDROELÉCTRICA | CG8: TERMOELÉCTRICA | CH8: TERMOELÉCTRICA | CI8: TERMOELÉCTRICA | CJ8: TERMOELÉCTRICA | CK8: TERMOELÉCTRICA | CL8: TERMOELÉCTRICA | CM8: TERMOELÉCTRICA | CN8: TERMOELÉCTRICA | CO8: TERMOELÉCTRICA | CP8: TERMOELÉCTRICA | CQ8: TERMOELÉCTRICA | CR8: TERMOELÉCTRICA | CS8: TERMOELÉCTRICA | CT8: SOLAR | CU8: EÓLICA | CV8: SOLAR | CW8: EÓLICA | CX8: SOLAR | CY8: HIDROELÉCTRICA | CZ8: HIDROELÉCTRICA | DA8: HIDROELÉCTRICA | DB8: HIDROELÉCTRICA | DC8: HIDROELÉCTRICA | DD8: HIDROELÉCTRICA | DE8: HIDROELÉCTRICA | DF8: HIDROELÉCTRICA | DG8: HIDROELÉCTRICA | DH8: HIDROELÉCTRICA | DI8: SOLAR | DJ8: SOLAR | DK8: EÓLICA | DL8: EÓLICA | DM8: TERMOELÉCTRICA | DN8: TERMOELÉCTRICA | DO8: TERMOELÉCTRICA | DP8: TERMOELÉCTRICA | DQ8: SOLAR | DR8: HIDROELÉCTRICA | DS8: HIDROELÉCTRICA | DT8: HIDROELÉCTRICA | DU8: HIDROELÉCTRICA | DV8: HIDROELÉCTRICA | DW8: HIDROELÉCTRICA | DX8: HIDROELÉCTRICA | DY8: HIDROELÉCTRICA | DZ8: HIDROELÉCTRICA | EA8: EÓLICA | EB8: EÓLICA | EC8: SOLAR | ED8: EÓLICA | EE8: EÓLICA | EF8: EÓLICA | EG8: EÓLICA | EH8: HIDROELÉCTRICA | EI8: HIDROELÉCTRICA | EJ8: HIDROELÉCTRICA | EK8: HIDROELÉCTRICA | EL8: HIDROELÉCTRICA | EM8: HIDROELÉCTRICA | EN8: EÓLICA | EO8: SOLAR | EP8: SOLAR | EQ8: HIDROELÉCTRICA | ER8: EÓLICA | ES8: EÓLICA | ET8: SOLAR | EU8: SOLAR | EV8: HIDROELÉCTRICA | EW8: HIDROELÉCTRICA | EX8: TERMOELÉCTRICA | EY8: TERMOELÉCTRICA | EZ8: TERMOELÉCTRICA | FA8: TERMOELÉCTRICA | FB8: TERMOELÉCTRICA | FC8: TERMOELÉCTRICA | FD8: TERMOELÉCTRICA | FE8: TERMOELÉCTRICA | FH8: HIDROELÉCTRICA | FI8: HIDROELÉCTRICA | FJ8: HIDROELÉCTRICA | FK8: HIDROELÉCTRICA | FL8: HIDROELÉCTRICA | FM8: TERMOELÉCTRICA | FN8: TERMOELÉCTRICA | FO8: HIDROELÉCTRICA | FP8: HIDROELÉCTRICA
C9: CENTRALES SANTA ROSA S.A.C. | D9: CENTRALES SANTA ROSA S.A.C. | E9: INVERSIONES SHAQSHA S.A.C. | F9: ELECTROPERU | G9: ELECTROPERU | H9: ELECTROPERU | I9: ELECTROPERU | J9: ORAZUL ENERGY PERÚ | K9: ORAZUL ENERGY PERÚ | L9: TERMOSELVA | M9: TERMOSELVA | N9: KALLPA GENERACION S.A. | O9: KALLPA GENERACION S.A. | P9: KALLPA GENERACION S.A. | Q9: KALLPA GENERACION S.A. | R9: KALLPA GENERACION S.A. | S9: KALLPA GENERACION S.A. | T9: KALLPA GENERACION S.A. | U9: KALLPA GENERACION S.A. | V9: SHOUGESA | W9: SHOUGESA | X9: SHOUGESA | Y9: SHOUGESA | Z9: EGEMSA | AA9: EGESUR | AB9: EGESUR | AC9: EGASA | AD9: EGASA | AE9: EGASA | AF9: EGASA | AG9: EGASA | AH9: EGASA | AI9: EGASA | AJ9: SAN GABAN | AK9: CELEPSA | AL9: MINERA CERRO VERDE | AM9: PLANTA DE RESERVA FRIA DE GENERACION DE ETEN S.A. | AN9: PLANTA DE RESERVA FRIA DE GENERACION DE ETEN S.A. | AO9: EMPRESA DE GENERACION HUALLAGA | AP9: EMPRESA DE GENERACION HUALLAGA | AQ9: LA VIRGEN | AR9: CHINANGO S.A.C. | AS9: CHINANGO S.A.C. | AT9: HIDROELECTRICA HUANCHOR S.A.C. | AU9: CELEPSA RENOVABLES S.R.L. | AV9: INLAND ENERGY SAC | AW9: FENIX POWER PERÚ | AX9: FENIX POWER PERÚ | AY9: FENIX POWER PERÚ | AZ9: STATKRAFT S.A | BA9: STATKRAFT S.A | BB9: STATKRAFT S.A | BC9: STATKRAFT S.A | BD9: STATKRAFT S.A | BE9: STATKRAFT S.A | BF9: STATKRAFT S.A | BG9: STATKRAFT S.A | BH9: EMPRESA DE GENERACION HUANZA | BI9: ENEL GENERACION PIURA S.A. | BJ9: ENEL GENERACION PIURA S.A. | BK9: ENEL GENERACION PIURA S.A. | BL9: ENGIE | BM9: ENGIE | BN9: ENGIE | BO9: ENGIE | BP9: ENGIE | BQ9: ENGIE | BR9: ENGIE | BS9: ENGIE | BT9: ENGIE | BU9: ENGIE | BV9: ENGIE | BW9: ENGIE | BX9: ENGIE | BY9: ENGIE | BZ9: INFRAESTRUCTURAS Y ENERGIAS DEL PERU S.A.C. | CA9: INFRAESTRUCTURAS Y ENERGIAS DEL PERU S.A.C. | CB9: ORYGEN PERU S.A.A. | CC9: ORYGEN PERU S.A.A. | CD9: ORYGEN PERU S.A.A. | CE9: ORYGEN PERU S.A.A. | CF9: ORYGEN PERU S.A.A. | CG9: ORYGEN PERU S.A.A. | CH9: ORYGEN PERU S.A.A. | CI9: ORYGEN PERU S.A.A. | CJ9: ORYGEN PERU S.A.A. | CK9: ORYGEN PERU S.A.A. | CL9: ORYGEN PERU S.A.A. | CM9: ORYGEN PERU S.A.A. | CN9: SAMAY I S.A.C | CO9: SAMAY I S.A.C | CP9: SAMAY I S.A.C | CQ9: SAMAY I S.A.C | CR9: TERMOCHILCA S.A.C. | CS9: TERMOCHILCA S.A.C. | CT9: COLCA SOLAR S.A.C. | CU9: ENERGIA RENOVABLE DEL SUR S.A. | CV9: GR CORTARRAMA SOCIEDAD ANONIMA CERRADA | CW9: GR TARUCA SOCIEDAD ANONIMA CERRADA | CX9: KONDU SAC | CY9: PERUANA DE INVERSIONES EN ENERGIAS RENOVABLES S.A. | CZ9: ORAZUL ENERGY PERÚ | DA9: ORAZUL ENERGY PERÚ | DB9: MAJA ENERGIA S.A.C. | DC9: EMPRESA DE GENERACION ELECTRICA CANCHAYLLO SAC | DD9: EMPRESA DE GENERACION ELECTRICA SANTA ANA S.A.C. | DE9: EMPRESA ELECTRICA AGUA AZUL | DF9: EMPRESA ELECTRICA RIO DOBLE | DG9: HIDROCAÑETE S.A. | DH9: HUAURA POWER GROUP S.A. | DI9: MOQUEGUA FV S.A.C. | DJ9: PANAMERICANA SOLAR SAC. | DK9: PARQUE EOLICO MARCONA S.A.C. | DL9: PARQUE EOLICO TRES HERMANAS S.A.C. | DM9: PETRAMAS | DN9: PETRAMAS | DO9: PETRAMAS | DP9: PETRAMAS | DQ9: TACNA SOLAR SAC. | DR9: ELECTRICA YANAPAMPA SAC | DS9: ANDEAN POWER S.A.C. | DT9: ASOCIACIÓN SANTA LUCIA DE CHACAS | DU9: ATRIA ENERGIA S.A.C. | DV9: EGEJUNIN | DW9: EGEJUNIN | DX9: EGEJUNIN | DY9: EGEJUNIN | DZ9: EMPRESA DE GENERACION ELECTRICA RIO BAÑOS S.A.C. | EA9: ENERGÍA EÓLICA S.A. | EB9: ENERGÍA EÓLICA S.A. | EC9: ENGIE | ED9: ENGIE | EE9: ENGIE | EF9: ENGIE | EG9: ENGIE | EH9: GENERACIÓN ANDINA S.A.C. | EI9: GENERACIÓN ANDINA S.A.C. | EJ9: GENERADORA DE ENERGÍA DEL PERÚ | EK9: GENERADORA DE ENERGÍA DEL PERÚ | EL9: GENERADORA DE ENERGÍA DEL PERÚ | EM9: GENERADORA DE ENERGÍA DEL PERÚ | EN9: GR PAINO SOCIEDAD ANONIMA CERRADA | EO9: MAJES ARCUS S.A.C. | EP9: ORYGEN PERU S.A.A. | EQ9: ORYGEN PERU S.A.A. | ER9: ORYGEN PERU S.A.A. | ES9: ORYGEN PERU S.A.A. | ET9: ORYGEN PERU S.A.A. | EU9: REPARTICIÓN ARCUS S.A.C. | EV9: SINERSA | EW9: SINERSA | EX9: BIOENERGIA DEL CHIRA S.A. | EY9: GM OPERACIONES S.A.C. | EZ9: GM OPERACIONES S.A.C. | FA9: SDF ENERGIA SAC | FB9: SDF ENERGIA SAC | FC9: AGRO INDUSTRIAL PARAMONGA S.A. | FD9: AGROAURORA S.A.C. | FE9: AGROINDUSTRIAS SAN JACINTO S.A.A. | FH9: UNACEM PERU S.A. | FI9: SAN GABAN | FJ9: ELECTRO ORIENTE | FK9: AGUAS Y ENERGIA PERU | FL9: ELECTRO ZAÑA S.A.C. | FM9: ELECTRONOROESTE S.A. | FN9: SDE PIURA | FO9: SINERSA | FP9: SINERSA
C10: SANTA ROSA 1 | D10: SANTA ROSA 2 | E10: PARIAC | F10: MANTARO | G10: RESTITUCION | H10: TUMBES MAK 1 | I10: TUMBES MAK 2 | J10: CARHUAQUERO | K10: CAÑON DEL PATO | L10: AGUAYTIA TG1 | M10: AGUAYTIA TG2 | N10: KALLPA TG1 | O10: KALLPA TG2 | P10: KALLPA TG3 | Q10: KALLPA TV | R10: LFLORES TG1 | S10: LFLORES TV | T10: CERRO DEL AGUILA | U10: CERRODELAGUILAG4 | V10: SHOUGESA TV1 | W10: SHOUGESA TV2 | X10: SHOUGESA TV3 | Y10: SHOUGESA CUMMINS | Z10: MACHUPICCHU | AA10: ARICOTA 1 | AB10: INDEPENDENCIA | AC10: CHARCANI I,II,III | AD10: CHARCANI IV | AE10: CHARCANI V | AF10: CHARCANI VI | AG10: CHILINA TG | AH10: MOLLENDO 1, 2, 3 | AI10: CHILINA (SULZ 1,2) | AJ10: SAN GABAN II | AK10: PLATANAL | AL10: RECKA | AM10: RF ETEN TG1 | AN10: RF ETEN TG2 | AO10: CHAGLLA GP1 | AP10: CHAGLLA | AQ10: LA VIRGEN | AR10: CHIMAY | AS10: YANANGO | AT10: HUANCHOR | AU10: MARAÑON | AV10: STA TERESA | AW10: FENIX GT11 | AX10: FENIX GT12 | AY10: FENIX TV10 | AZ10: YAUPI | BA10: OROYA | BB10: PACHACHACA | BC10: MALPASO | BD10: CAHUA | BE10: ARCATA | BF10: GALLITO CIEGO | BG10: CHEVES | BH10: HUANZA | BI10: MALACAS2 TG4 | BJ10: MALACAS3 TG 5 | BK10: MALACAS1 TG6 | BL10: RF ILO2 TG1 | BM10: RF ILO2 TG2 | BN10: RF ILO2 TG3 | BO10: YUNCAN | BP10: CHILCA1 TG1 | BQ10: CHILCA1 TG2 | BR10: CHILCA1 TG3 | BS10: CHILCA-TV | BT10: CHILCA2 TG41 | BU10: CHILCA2-TV | BV10: CTNEPI_TG41 | BW10: CTNEPI_TG42 | BX10: CTNEPI_TG43 | BY10: QUITARACSA | BZ10: RF PTO MALDONADO | CA10: RF PUCALLPA | CB10: HUINCO | CC10: MATUCANA | CD10: MOYOPAMPA | CE10: CALLAHUANCA | CF10: HUAMPANI | CG10: STA ROSA WEST TG7 | CH10: UTI_5 | CI10: UTI_6 | CJ10: VENTANILLA 3 | CK10: VENTANILLA 4 | CL10: VENTANILLA TV | CM10: STAROSA TG8 | CN10: PTO_BRVO TG1 | CO10: PTO_BRVO TG2 | CP10: PTO_BRVO TG3 | CQ10: PTO_BRVO TG4 | CR10: OLLEROS TG1 | CS10: OLLEROS TV | CT10: CS YARUCAYA | CU10: SAN JUAN | CV10: MATARANI | CW10: DUNA | CX10: CARHUAQUERO (CS) | CY10: MANTA I | CZ10: CARHUAQUERO4 | DA10: CAÑA BRAVA | DB10: RONCADOR | DC10: CANCHAYLLO | DD10: RENOVANDESH1 | DE10: POTRERO | DF10: PIZARRAS | DG10: NIMPERIAL | DH10: YARUCAYA | DI10: MOQUEGUA-SOLAR | DJ10: PANAMERICANA-SOLAR | DK10: PQE-EOLICO-MARCONA | DL10: PQE-EOLICO-3-HERMANAS | DM10: HUAYCOLORO | DN10: CALLAO | DO10: DONA_CATALINA | DP10: LAGRINGAV | DQ10: TACNA-SOLAR | DR10: YANAPAMPA | DS10: CARHUAC | DT10: HUALLIN | DU10: PURMACANA | DV10: HUASAHUASI | DW10: STACRUZ_1_2 | DX10: RUNATULLO_II | DY10: RUNATULLO_III | DZ10: RUCUY | EA10: PQE-EOLICO-TALARA | EB10: PQE-EOLICO-CUPISNIQUE | EC10: INTIPAMPA | ED10: PUNTA LOMITAS-BL1 | EE10: PUNTA LOMITAS-BL2 | EF10: PUN LOMITAS_EXP-BL1 | EG10: PUN LOMITAS_EXP-BL2 | EH10: 8AGOSTO | EI10: EL CARMEN | EJ10: LA JOYA | EK10: ANGEL_I | EL10: ANGEL_II | EM10: ANGEL_III | EN10: HUAMBOS | EO10: MAJES | EP10: RUBI | EQ10: CH_HER1 | ER10: WAYRA-I | ES10: WAYRA EXTENSION | ET10: CLEMESI | EU10: REPARTICION | EV10: POECHOS2 | EW10: CHANCAY | EX10: CANA BRAVA | EY10: REFINERIA TALARA TV1 | EZ10: REFINERÍA TALARA TV2 | FA10: OQUENDO TG1 | FB10: OQUENDO TV1 | FC10: PARAMONGA | FD10: MAPLE | FE10: SAN_JACINTO | FF10: MW | FH10: CARPAPATA | FI10: TUPURI | FJ10: CENTRALES ELOR | FK10: PIAS1 | FL10: ZANA | FM10: TABLAZO | FN10: TALLANCA | FO10: CURUMUY | FP10: POECHOS1 | FQ10: MW
A11: 15/01/2025 | B11: 00:30 | C11: 1 | D11: 1.7 | E11: 4.2 | F11: 647.8 | G11: 219.3 | J11: 90.6 | K11: 238.6 | L11: 0 | M11: 0 | N11: 108.1 | O11: 108.4 | P11: 109 | Q11: 211.1 | R11: 205.8 | S11: 109.3 | T11: 560.7 | U11: 10.5 | Z11: 162.7 | AA11: 8.1 | AB11: 0 | AC11: 6.5 | AD11: 10 | AE11: 40.7 | AF11: 6 | AJ11: 110.9 | AK11: 222.2 | AL11: 0 | AO11: 6.5 | AP11: 467.9 | AQ11: 54 | AR11: 148.7 | AS11: 36.6 | AT11: 18.3 | AU11: 19.7 | AV11: 93.4 | AW11: 170.1 | AX11: 170.4 | AY11: 177.1 | AZ11: 108.5 | BA11: 7.8 | BB11: 6.2 | BC11: 36 | BD11: 46.9 | BE11: 3.1 | BF11: 30.9 | BG11: 173.8 | BH11: 57.5 | BK11: 47.6 | BO11: 131.2 | BQ11: 0 | BY11: 112.5 | CB11: 93.5 | CC11: 132.3 | CD11: 64.3 | CE11: 77.2 | CF11: 30 | CJ11: 114.3 | CL11: 56.1 | CN11: 0 | CT11: 0 | CU11: 72.9 | CV11: 0 | CW11: 3.2 | CX11: 0 | CY11: 20 | CZ11: 9.9 | DA11: 5.5 | DB11: 3.6 | DC11: 4.8 | DD11: 20.2 | DE11: 20 | DF11: 18.8 | DG11: 3.5 | DH11: 18.7 | DI11: 0 | DJ11: 0 | DK11: 14.8 | DL11: 26.5 | DM11: 4.8 | DN11: 2.4 | DO11: 2.4 | DP11: 2.8 | DQ11: 0 | DR11: 3.6 | DS11: 17.3 | DT11: 2 | DV11: 14.7 | DW11: 12 | DX11: 20 | DY11: 20.4 | DZ11: 19.8 | EA11: 7.1 | EB11: 21.2 | EC11: 0 | ED11: 35.4 | EE11: 56.9 | EF11: 2.6 | EG11: 1.6 | EH11: 20.1 | EI11: 5.7 | EJ11: 5.6 | EK11: 20.4 | EL11: 20.4 | EM11: 0 | EN11: 3.6 | EO11: 0 | EP11: 0 | EQ11: 0.6 | ER11: 13.8 | ES11: 8 | ET11: 0 | EU11: 0 | EV11: 4.7 | EW11: 19.8 | EX11: 11.1 | EY11: 25.6 | EZ11: 34.3 | FA11: 29.2 | FB11: 3.5 | FC11: 15 | FD11: 14.6 | FE11: 7.7 | FF11: 6638.7 | FH11: 24.19245 | FI11: 1.3 | FJ11: 8.1 | FK11: 11.6265 | FL11: 12.2 | FN11: 18.91303 | FO11: 2.4 | FP11: 3.8 | FQ11: 82.53198
A12: 15/01/2025 | B12: 01:00 | C12: 1.1 | D12: 1.7 | E12: 4.2 | F12: 642.5 | G12: 217.8 | J12: 89.7 | K12: 237.8 | L12: 0 | M12: 0 | N12: 107.6 | O12: 108 | P12: 108.1 | Q12: 210.8 | R12: 206.2 | S12: 109.4 | T12: 551.3 | U12: 10.5 | Z12: 165.8 | AA12: 7.7 | AB12: 0 | AC12: 6.5 | AD12: 9.8 | AE12: 39.4 | AF12: 6 | AJ12: 109.8 | AK12: 221.2 | AL12: 0 | AO12: 6.5 | AP12: 338.3 | AQ12: 53.7 | AR12: 130.2 | AS12: 36.6 | AT12: 18.3 | AU12: 19.7 | AV12: 90.3 | AW12: 166.2 | AX12: 166.4 | AY12: 170.7 | AZ12: 107.5 | BA12: 7.8 | BB12: 6.2 | BC12: 35.1 | BD12: 46.6 | BE12: 3.1 | BF12: 31 | BG12: 172.7 | BH12: 56.5 | BK12: 47.7 | BO12: 130.5 | BQ12: 0 | BY12: 110.8 | CB12: 140.6 | CC12: 118 | CD12: 63.9 | CE12: 75.8 | CF12: 29.8 | CJ12: 115 | CL12: 55.3 | CN12: 0 | CT12: 0 | CU12: 74.4 | CV12: 0 | CW12: 1.9 | CX12: 0 | CY12: 20 | CZ12: 9.9 | DA12: 5.5 | DB12: 3.6 | DC12: 4.8 | DD12: 19.9 | DE12: 20 | DF12: 18.8 | DG12: 3.5 | DH12: 18.7 | DI12: 0 | DJ12: 0 | DK12: 11 | DL12: 20.9 | DM12: 4.8 | DN12: 2.4 | DO12: 2.4 | DP12: 2.8 | DQ12: 0 | DR12: 3.6 | DS12: 17.1 | DT12: 2 | DV12: 14.7 | DW12: 12 | DX12: 19.8 | DY12: 20.4 | DZ12: 19.8 | EA12: 9.2 | EB12: 26.8 | EC12: 0 | ED12: 19 | EE12: 38.8 | EF12: 1.1 | EG12: 0 | EH12: 20.2 | EI12: 5.7 | EJ12: 5.9 | EK12: 20.4 | EL12: 20.4 | EM12: 0 | EN12: 2.4 | EO12: 0 | EP12: 0 | EQ12: 0.6 | ER12: 9.1 | ES12: 5.2 | ET12: 0 | EU12: 0 | EV12: 4.7 | EW12: 19.8 | EX12: 10.2 | EY12: 25.2 | EZ12: 34.2 | FA12: 29.2 | FB12: 3.4 | FC12: 15.2 | FD12: 14.6 | FE12: 7.3 | FF12: 6427 | FH12: 24.18951 | FI12: 1.3 | FJ12: 8.1 | FK12: 11.32581 | FL12: 12.2 | FN12: 18.91209 | FO12: 2.8 | FP12: 3.8 | FQ12: 82.62741
A13: 15/01/2025 | B13: 01:30 | C13: 1.1 | D13: 1.6 | E13: 4.2 | F13: 647 | G13: 218.9 | J13: 90.2 | K13: 238.3 | L13: 0 | M13: 0 | N13: 109.9 | O13: 110.2 | P13: 110.6 | Q13: 210.6 | R13: 205.6 | S13: 109.3 | T13: 561.1 | U13: 10.5 | Z13: 168.8 | AA13: 8 | AB13: 0 | AC13: 6.5 | AD13: 9.8 | AE13: 40.4 | AF13: 6 | AJ13: 110.9 | AK13: 222.1 | AL13: 0 | AO13: 6.5 | AP13: 466.2 | AQ13: 53.7 | AR13: 149 | AS13: 35.8 | AT13: 18.3 | AU13: 19.7 | AV13: 89.5 | AW13: 126.1 | AX13: 126.2 | AY13: 152.8 | AZ13: 107.4 | BA13: 7.8 | BB13: 6.2 | BC13: 36.1 | BD13: 47 | BE13: 3.1 | BF13: 29.9 | BG13: 173.8 | BH13: 57.4 | BK13: 47.7 | BO13: 131.1 | BQ13: 0 | BY13: 112.5 | CB13: 87.1 | CC13: 132.1 | CD13: 64.4 | CE13: 76 | CF13: 30 | CJ13: 115 | CL13: 54.6 | CN13: 0 | CT13: 0 | CU13: 78.3 | CV13: 0 | CW13: 0.5 | CX13: 0 | CY13: 20 | CZ13: 9.9 | DA13: 5.4 | DB13: 3.6 | DC13: 4.8 | DD13: 20.3 | DE13: 20 | DF13: 18.9 | DG13: 3.5 | DH13: 18.7 | DI13: 0 | DJ13: 0 | DK13: 10.1 | DL13: 25.6 | DM13: 4.8 | DN13: 2.4 | DO13: 2.4 | DP13: 2.8 | DQ13: 0 | DR13: 3.6 | DS13: 17.1 | DT13: 2 | DV13: 14.6 | DW13: 12 | DX13: 19.7 | DY13: 20.4 | DZ13: 19.8 | EA13: 11.1 | EB13: 30.9 | EC13: 0 | ED13: 12.7 | EE13: 28 | EF13: 0.4 | EG13: 0.1 | EH13: 20.2 | EI13: 5.7 | EJ13: 5.9 | EK13: 20.4 | EL13: 20.4 | EM13: 0 | EN13: 0.7 | EO13: 0 | EP13: 0 | EQ13: 0.6 | ER13: 2.5 | ES13: 0.5 | ET13: 0 | EU13: 0 | EV13: 4.7 | EW13: 19.8 | EX13: 9.9 | EY13: 25 | EZ13: 33.8 | FA13: 29.2 | FB13: 3.4 | FC13: 15 | FD13: 14.6 | FE13: 8.7 | FF13: 6450 | FH13: 24.15002 | FI13: 1.3 | FJ13: 8.1 | FK13: 11.73875 | FL13: 12.2 | FN13: 18.91143 | FO13: 2.8 | FP13: 3.8 | FQ13: 83.0002
A14: 15/01/2025 | B14: 02:00 | C14: 1.1 | D14: 1.7 | E14: 4.2 | F14: 646.7 | G14: 219.5 | J14: 90.1 | K14: 237.7 | L14: 0 | M14: 0 | N14: 107.5 | O14: 108.2 | P14: 107.2 | Q14: 209.4 | R14: 206.1 | S14: 109.5 | T14: 557.7 | U14: 10.5 | Z14: 165.3 | AA14: 7.8 | AB14: 0 | AC14: 6.5 | AD14: 9.8 | AE14: 40.2 | AF14: 5.8 | AJ14: 110.9 | AK14: 222.1 | AL14: 0 | AO14: 6.5 | AP14: 441 | AQ14: 53.1 | AR14: 145.4 | AS14: 36.3 | AT14: 18.3 | AU14: 19.7 | AV14: 89.7 | AW14: 123.5 | AX14: 123.7 | AY14: 152.6 | AZ14: 108.8 | BA14: 7.8 | BB14: 6.2 | BC14: 35.8 | BD14: 46.9 | BE14: 3.1 | BF14: 31.5 | BG14: 173.7 | BH14: 57.5 | BK14: 0 | BO14: 131.1 | BQ14: 0 | BY14: 112.4 | CB14: 94.4 | CC14: 129 | CD14: 63.9 | CE14: 73.9 | CF14: 30.1 | CJ14: 117.4 | CL14: 53.8 | CN14: 0 | CT14: 0 | CU14: 68.1 | CV14: 0 | CW14: 0.8 | CX14: 0 | CY14: 20 | CZ14: 9.9 | DA14: 5.3 | DB14: 3.6 | DC14: 4.7 | DD14: 20.2 | DE14: 19.3 | DF14: 19 | DG14: 3.5 | DH14: 18.7 | DI14: 0 | DJ14: 0 | DK14: 9 | DL14: 20.4 | DM14: 4.8 | DN14: 2.4 | DO14: 2.4 | DP14: 2.8 | DQ14: 0 | DR14: 3.6 | DS14: 17.2 | DT14: 2 | DV14: 14.6 | DW14: 12 | DX14: 19.4 | DY14: 20.4 | DZ14: 19.8 | EA14: 11.7 | EB14: 25.4 | EC14: 0 | ED14: 9.1 | EE14: 24 | EF14: 0.6 | EG14: 0.1 | EH14: 20.2 | EI14: 5.7 | EJ14: 6.1 | EK14: 20.4 | EL14: 20.4 | EM14: 0 | EN14: 1 | EO14: 0 | EP14: 0 | EQ14: 0.6 | ER14: 0 | ES14: 0 | ET14: 0 | EU14: 0 | EV14: 4.7 | EW14: 19.8 | EX14: 9.2 | EY14: 24.4 | EZ14: 34.9 | FA14: 29.3 | FB14: 3.4 | FC14: 15 | FD14: 14.6 | FE14: 9 | FF14: 6326.1 | FH14: 24.10385 | FI14: 1.3 | FJ14: 8.1 | FK14: 11.84559 | FL14: 12.2 | FN14: 18.91074 | FO14: 2.7 | FP14: 3.9 | FQ14: 83.06018
A15: 15/01/2025 | B15: 02:30 | C15: 1.1 | D15: 1.7 | E15: 4.2 | F15: 649.8 | G15: 220.2 | J15: 90.4 | K15: 239.8 | L15: 0 | M15: 0 | N15: 107.2 | O15: 107.8 | P15: 107.4 | Q15: 209.8 | R15: 207.9 | S15: 109.5 | T15: 555.7 | U15: 10.5 | Z15: 167.9 | AA15: 7.9 | AB15: 0 | AC15: 6.4 | AD15: 9.8 | AE15: 40.1 | AF15: 5.9 | AJ15: 111.2 | AK15: 213.7 | AL15: 0 | AO15: 6.5 | AP15: 434.9 | AQ15: 52.1 | AR15: 149.7 | AS15: 37.9 | AT15: 18.3 | AU15: 19.7 | AV15: 88.9 | AW15: 124.5 | AX15: 125 | AY15: 152.5 | AZ15: 109.5 | BA15: 7.7 | BB15: 6.2 | BC15: 35.8 | BD15: 47.3 | BE15: 3.1 | BF15: 30.8 | BG15: 174.5 | BH15: 57.7 | BK15: 0 | BO15: 131.7 | BQ15: 0 | BY15: 113.2 | CB15: 88.9 | CC15: 132.8 | CD15: 64.2 | CE15: 77 | CF15: 30.3 | CJ15: 115.2 | CL15: 53.3 | CN15: 0 | CT15: 0 | CU15: 54 | CV15: 0 | CW15: 1.5 | CX15: 0 | CY15: 20 | CZ15: 9.9 | DA15: 5.5 | DB15: 3.6 | DC15: 4.8 | DD15: 20.5 | DE15: 20 | DF15: 18.9 | DG15: 3.5 | DH15: 18.7 | DI15: 0 | DJ15: 0 | DK15: 8.5 | DL15: 16.6 | DM15: 4.8 | DN15: 2.4 | DO15: 2.4 | DP15: 2.8 | DQ15: 0 | DR15: 3.6 | DS15: 17.2 | DT15: 2 | DV15: 14.6 | DW15: 12 | DX15: 19.6 | DY15: 20.4 | DZ15: 19.8 | EA15: 11 | EB15: 16.7 | EC15: 0 | ED15: 12.1 | EE15: 23.3 | EF15: 0.4 | EG15: 0 | EH15: 20.2 | EI15: 5.7 | EJ15: 6 | EK15: 20.4 | EL15: 20.4 | EM15: 0 | EN15: 1.7 | EO15: 0 | EP15: 0 | EQ15: 0.6 | ER15: 0 | ES15: 0 | ET15: 0 | EU15: 0 | EV15: 4.7 | EW15: 19.8 | EX15: 9.8 | EY15: 24.5 | EZ15: 35.4 | FA15: 29.3 | FB15: 3.4 | FC15: 15 | FD15: 14.6 | FE15: 8.5 | FF15: 6306.2 | FH15: 24.10269 | FI15: 1.3 | FJ15: 8.1 | FK15: 11.53931 | FL15: 12.2 | FN15: 18.91054 | FO15: 2.6 | FP15: 3.8 | FQ15: 82.55254
A16: 15/01/2025 | B16: 03:00 | C16: 1.1 | D16: 1.7 | E16: 4.2 | F16: 648.4 | G16: 219.7 | J16: 89.8 | K16: 238.2 | L16: 0 | M16: 0 | N16: 107.8 | O16: 108.8 | P16: 108.8 | Q16: 211.9 | R16: 208.1 | S16: 109.3 | T16: 560.4 | U16: 10.5 | Z16: 164.7 | AA16: 7.7 | AB16: 0 | AC16: 6.5 | AD16: 9.8 | AE16: 40.3 | AF16: 5.8 | AJ16: 110.9 | AK16: 169.2 | AL16: 0 | AO16: 6.5 | AP16: 465 | AQ16: 53.6 | AR16: 149.7 | AS16: 36.1 | AT16: 18.3 | AU16: 19.7 | AV16: 91.2 | AW16: 156.5 | AX16: 157 | AY16: 165.3 | AZ16: 109.1 | BA16: 7.8 | BB16: 6.5 | BC16: 28.5 | BD16: 47 | BE16: 3.1 | BF16: 30.3 | BG16: 152.3 | BH16: 57.9 | BK16: 0 | BO16: 119.3 | BQ16: 0 | BY16: 112.7 | CB16: 66.6 | CC16: 132.4 | CD16: 63.9 | CE16: 75 | CF16: 30.2 | CJ16: 115.4 | CL16: 55.3 | CN16: 0 | CT16: 0 | CU16: 34.9 | CV16: 0 | CW16: 3 | CX16: 0 | CY16: 20 | CZ16: 9.9 | DA16: 5.4 | DB16: 3.6 | DC16: 4.8 | DD16: 20.4 | DE16: 20 | DF16: 18.9 | DG16: 3.5 | DH16: 18.7 | DI16: 0 | DJ16: 0 | DK16: 3.6 | DL16: 5.8 | DM16: 4.8 | DN16: 2.4 | DO16: 2.4 | DP16: 2.8 | DQ16: 0 | DR16: 3.6 | DS16: 17.2 | DT16: 2 | DV16: 14.6 | DW16: 12 | DX16: 19.4 | DY16: 20.4 | DZ16: 19.8 | EA16: 16.9 | EB16: 22.8 | EC16: 0 | ED16: 10.2 | EE16: 22.7 | EF16: 0.3 | EG16: 0 | EH16: 20 | EI16: 5.7 | EJ16: 5.7 | EK16: 20.4 | EL16: 20.4 | EM16: 0 | EN16: 3.5 | EO16: 0 | EP16: 0 | EQ16: 0.6 | ER16: 0 | ES16: 0 | ET16: 0 | EU16: 0 | EV16: 4.7 | EW16: 19.9 | EX16: 9.3 | EY16: 24.6 | EZ16: 35.4 | FA16: 29.4 | FB16: 3.5 | FC16: 15.1 | FD16: 14.1 | FE16: 8.2 | FF16: 6283.1 | FH16: 24.10117 | FI16: 1.3 | FJ16: 8.1 | FK16: 11.48931 | FL16: 12.2 | FN16: 18.91011 | FO16: 2.5 | FP16: 3.8 | FQ16: 82.40059
A17: 15/01/2025 | B17: 03:30 | C17: 1.1 | D17: 1.7 | E17: 4.2 | F17: 644.9 | G17: 218.7 | J17: 90.1 | K17: 237.9 | L17: 0 | M17: 0 | N17: 108.5 | O17: 107.7 | P17: 108.3 | Q17: 214.9 | R17: 205.7 | S17: 108.8 | T17: 557.3 | U17: 10.6 | Z17: 164.4 | AA17: 7.5 | AB17: 0 | AC17: 6.5 | AD17: 9.8 | AE17: 40 | AF17: 5.8 | AJ17: 110.7 | AK17: 222 | AL17: 0 | AO17: 6.5 | AP17: 467.2 | AQ17: 54 | AR17: 147.7 | AS17: 36.7 | AT17: 18.3 | AU17: 19.7 | AV17: 93.2 | AW17: 139.8 | AX17: 141.3 | AY17: 162.9 | AZ17: 108.5 | BA17: 7.7 | BB17: 6.3 | BC17: 25.5 | BD17: 46.9 | BE17: 3.1 | BF17: 30.8 | BG17: 153.6 | BH17: 57.1 | BK17: 0 | BO17: 101.6 | BQ17: 0 | BY17: 111.9 | CB17: 67.2 | CC17: 130.8 | CD17: 63.7 | CE17: 74.9 | CF17: 30.1 | CJ17: 115.4 | CL17: 52.7 | CN17: 0 | CT17: 0 | CU17: 31.3 | CV17: 0 | CW17: 3.9 | CX17: 0 | CY17: 20 | CZ17: 9.9 | DA17: 5.4 | DB17: 3.6 | DC17: 4.8 | DD17: 20 | DE17: 20 | DF17: 18.9 | DG17: 3.5 | DH17: 18.7 | DI17: 0 | DJ17: 0 | DK17: 1.7 | DL17: 1.3 | DM17: 4.8 | DN17: 2.4 | DO17: 2.4 | DP17: 2.8 | DQ17: 0 | DR17: 3.6 | DS17: 17.2 | DT17: 2 | DV17: 14.6 | DW17: 12.2 | DX17: 19.3 | DY17: 20.3 | DZ17: 19.8 | EA17: 17 | EB17: 27.6 | EC17: 0 | ED17: 4.3 | EE17: 12.5 | EF17: 0 | EG17: 0 | EH17: 20 | EI17: 5.7 | EJ17: 5.7 | EK17: 20.4 | EL17: 20.4 | EM17: 0 | EN17: 5.5 | EO17: 0 | EP17: 0 | EQ17: 0.6 | ER17: 0 | ES17: 0 | ET17: 0 | EU17: 0 | EV17: 4.7 | EW17: 19.9 | EX17: 9.8 | EY17: 25.1 | EZ17: 35.3 | FA17: 29.4 | FB17: 3.4 | FC17: 15.2 | FD17: 14.6 | FE17: 7.7 | FF17: 6251.4 | FH17: 24.10307 | FI17: 1.3 | FJ17: 8.1 | FK17: 11.92919 | FL17: 11.8 | FN17: 18.90966 | FO17: 2.5 | FP17: 3.8 | FQ17: 82.44192
A18: 15/01/2025 | B18: 04:00 | C18: 1.1 | D18: 1.7 | E18: 4.2 | F18: 642 | G18: 217.4 | J18: 89.7 | K18: 237.5 | L18: 0 | M18: 0 | N18: 108.2 | O18: 108.5 | P18: 108.3 | Q18: 210 | R18: 210.5 | S18: 109.3 | T18: 551.7 | U18: 10.4 | Z18: 164.9 | AA18: 7.1 | AB18: 0 | AC18: 6.5 | AD18: 9.8 | AE18: 39.6 | AF18: 6 | AJ18: 110 | AK18: 221.9 | AL18: 0 | AO18: 6.5 | AP18: 364.7 | AQ18: 54 | AR18: 147.4 | AS18: 37.3 | AT18: 18.3 | AU18: 19.7 | AV18: 92.4 | AW18: 161.7 | AX18: 161.9 | AY18: 172.6 | AZ18: 107.5 | BA18: 7.8 | BB18: 6.3 | BC18: 24.7 | BD18: 46.5 | BE18: 3.1 | BF18: 30.8 | BG18: 153.1 | BH18: 56.5 | BK18: 0 | BO18: 101.3 | BQ18: 0 | BY18: 111 | CB18: 72.4 | CC18: 121.6 | CD18: 63.4 | CE18: 74.9 | CF18: 29.9 | CJ18: 116.8 | CL18: 55.4 | CN18: 0 | CT18: 0 | CU18: 40.6 | CV18: 0 | CW18: 2.7 | CX18: 0 | CY18: 20 | CZ18: 9.9 | DA18: 5.4 | DB18: 3.6 | DC18: 4.8 | DD18: 20 | DE18: 20 | DF18: 18.9 | DG18: 3.5 | DH18: 18.7 | DI18: 0 | DJ18: 0 | DK18: 4.9 | DL18: 2 | DM18: 4.8 | DN18: 2.4 | DO18: 2.4 | DP18: 2.8 | DQ18: 0 | DR18: 3.6 | DS18: 17.3 | DT18: 2 | DV18: 14.6 | DW18: 12.2 | DX18: 19.2 | DY18: 20.3 | DZ18: 19.9 | EA18: 18.4 | EB18: 26.1 | EC18: 0 | ED18: 3.6 | EE18: 10.3 | EF18: 0 | EG18: 0 | EH18: 20 | EI18: 5.7 | EJ18: 5.8 | EK18: 20.4 | EL18: 20.4 | EM18: 0 | EN18: 2.7 | EO18: 0 | EP18: 0 | EQ18: 0.6 | ER18: 0 | ES18: 0 | ET18: 0 | EU18: 0 | EV18: 4.7 | EW18: 19.9 | EX18: 9.6 | EY18: 25 | EZ18: 34.8 | FA18: 29.4 | FB18: 3.3 | FC18: 15.4 | FD18: 14.7 | FE18: 7.8 | FF18: 6190.9 | FH18: 24.1 | FI18: 1.3 | FJ18: 8.1 | FK18: 11.3565 | FL18: 11.4 | FN18: 18.90903 | FO18: 2.5 | FP18: 3.8 | FQ18: 81.46553
A19: 15/01/2025 | B19: 04:30 | C19: 1.1 | D19: 1.6 | E19: 4.2 | F19: 645.9 | G19: 218.7 | J19: 91.6 | K19: 238.8 | L19: 0 | M19: 0 | N19: 119.6 | O19: 119.8 | P19: 119.8 | Q19: 221.8 | R19: 207.3 | S19: 109.2 | T19: 557.9 | U19: 10.5 | Z19: 167.7 | AA19: 7.9 | AB19: 0 | AC19: 6.5 | AD19: 9.8 | AE19: 40.5 | AF19: 5.9 | AJ19: 111 | AK19: 222.3 | AL19: 0 | AO19: 6.5 | AP19: 465.9 | AQ19: 54.3 | AR19: 148.7 | AS19: 37.8 | AT19: 18.3 | AU19: 19.7 | AV19: 87.5 | AW19: 128.1 | AX19: 128.7 | AY19: 153.5 | AZ19: 108.5 | BA19: 7.7 | BB19: 6.6 | BC19: 26.3 | BD19: 47.2 | BE19: 3.1 | BF19: 30.4 | BG19: 156 | BH19: 57.4 | BK19: 0 | BO19: 102 | BQ19: 0 | BY19: 112.2 | CB19: 103.2 | CC19: 132.3 | CD19: 63.8 | CE19: 72 | CF19: 30.1 | CJ19: 114.2 | CL19: 55.2 | CN19: 0 | CT19: 0 | CU19: 47.7 | CV19: 0 | CW19: 1.4 | CX19: 0 | CY19: 20 | CZ19: 9.9 | DA19: 5.5 | DB19: 3.6 | DC19: 4.8 | DD19: 20.1 | DE19: 19.4 | DF19: 19 | DG19: 3.5 | DH19: 18.7 | DI19: 0 | DJ19: 0 | DK19: 6.8 | DL19: 4.9 | DM19: 4.8 | DN19: 2.4 | DO19: 2.4 | DP19: 2.8 | DQ19: 0 | DR19: 3.6 | DS19: 17.3 | DT19: 2 | DV19: 14.6 | DW19: 12.2 | DX19: 19.4 | DY19: 20.4 | DZ19: 19.8 | EA19: 14.4 | EB19: 17.9 | EC19: 0 | ED19: 3.2 | EE19: 10 | EF19: 0 | EG19: 0 | EH19: 20 | EI19: 5.7 | EJ19: 6 | EK19: 20.4 | EL19: 20.4 | EM19: 0 | EN19: 1.1 | EO19: 0 | EP19: 0 | EQ19: 0.6 | ER19: 0 | ES19: 0 | ET19: 0 | EU19: 0 | EV19: 4.7 | EW19: 19.8 | EX19: 9.5 | EY19: 24.9 | EZ19: 35 | FA19: 29.4 | FB19: 3.4 | FC19: 15.1 | FD19: 14.6 | FE19: 7.8 | FF19: 6307.5 | FH19: 24.10246 | FI19: 1.3 | FJ19: 8.1 | FK19: 11.07825 | FL19: 11.4 | FN19: 18.90872 | FO19: 2.5 | FP19: 3.8 | FQ19: 81.18943
A20: 15/01/2025 | B20: 05:00 | C20: 1.1 | D20: 1.7 | E20: 4.2 | F20: 649.6 | G20: 219.5 | J20: 91.2 | K20: 238.6 | L20: 0 | M20: 0 | N20: 129.9 | O20: 128.9 | P20: 129.4 | Q20: 229 | R20: 206.8 | S20: 109 | T20: 564.9 | U20: 10.6 | Z20: 168.3 | AA20: 8.2 | AB20: 0 | AC20: 6.5 | AD20: 9.8 | AE20: 40.5 | AF20: 5.9 | AJ20: 111.1 | AK20: 222.2 | AL20: 0 | AO20: 6.5 | AP20: 465.8 | AQ20: 55 | AR20: 148.9 | AS20: 38.3 | AT20: 18.3 | AU20: 19.7 | AV20: 86.1 | AW20: 124.6 | AX20: 124.9 | AY20: 152.9 | AZ20: 109.9 | BA20: 7.7 | BB20: 6.4 | BC20: 25.8 | BD20: 47.1 | BE20: 3.1 | BF20: 32.1 | BG20: 155.9 | BH20: 57.9 | BK20: 0 | BO20: 102 | BQ20: 0 | BY20: 112.9 | CB20: 66.9 | CC20: 132.8 | CD20: 64.1 | CE20: 69 | CF20: 30.4 | CJ20: 115.4 | CL20: 54.7 | CN20: 0 | CT20: 0 | CU20: 57.4 | CV20: 0 | CW20: 0.7 | CX20: 0 | CY20: 20 | CZ20: 9.9 | DA20: 5.4 | DB20: 3.6 | DC20: 4.7 | DD20: 20.4 | DE20: 20 | DF20: 19 | DG20: 3.5 | DH20: 18.7 | DI20: 0 | DJ20: 0 | DK20: 7.7 | DL20: 7.7 | DM20: 4.8 | DN20: 2.4 | DO20: 2.4 | DP20: 2.8 | DQ20: 0 | DR20: 3.6 | DS20: 17.2 | DT20: 2 | DV20: 14.6 | DW20: 12.2 | DX20: 19.5 | DY20: 20.4 | DZ20: 19.8 | EA20: 10.6 | EB20: 8.3 | EC20: 0 | ED20: 4.3 | EE20: 13.3 | EF20: 0 | EG20: 0 | EH20: 20 | EI20: 5.7 | EJ20: 6 | EK20: 20.4 | EL20: 20.4 | EM20: 0 | EN20: 1.9 | EO20: 0 | EP20: 0 | EQ20: 0.6 | ER20: 0 | ES20: 0 | ET20: 0 | EU20: 0 | EV20: 4.7 | EW20: 20 | EX20: 9.4 | EY20: 24.9 | EZ20: 35 | FA20: 29.5 | FB20: 3.3 | FC20: 15 | FD20: 14.7 | FE20: 6.6 | FF20: 6317 | FH20: 24.09817 | FI20: 1.3 | FJ20: 8.1 | FK20: 10.84091 | FL20: 11.4 | FN20: 18.9083 | FO20: 2.5 | FP20: 3.8 | FQ20: 80.94738
A21: 15/01/2025 | B21: 05:30 | C21: 1.1 | D21: 1.7 | E21: 4.2 | F21: 635.4 | G21: 215.7 | J21: 88.7 | K21: 233.6 | L21: 0 | M21: 0 | N21: 114.6 | O21: 115.2 | P21: 115.3 | Q21: 215.4 | R21: 207.2 | S21: 109.6 | T21: 540.7 | U21: 10.3 | Z21: 155.2 | AA21: 7 | AB21: 0 | AC21: 6.5 | AD21: 9.8 | AE21: 38.8 | AF21: 5.8 | AJ21: 108.5 | AK21: 222.1 | AL21: 0 | AO21: 6.5 | AP21: 445.7 | AQ21: 55 | AR21: 140.8 | AS21: 35.8 | AT21: 18.3 | AU21: 19.7 | AV21: 90.1 | AW21: 160.6 | AX21: 160.9 | AY21: 173.6 | AZ21: 108.1 | BA21: 7.7 | BB21: 6.6 | BC21: 23.2 | BD21: 46 | BE21: 3.1 | BF21: 30.6 | BG21: 153.1 | BH21: 54.2 | BK21: 0 | BO21: 99.8 | BQ21: 0 | BY21: 109.5 | CB21: 56.7 | CC21: 126.3 | CD21: 61.7 | CE21: 68.3 | CF21: 29.2 | CJ21: 114.2 | CL21: 54.2 | CN21: 0 | CT21: 0 | CU21: 60 | CV21: 0 | CW21: 0.7 | CX21: 0 | CY21: 20 | CZ21: 9.9 | DA21: 5.3 | DB21: 3.6 | DC21: 4.7 | DD21: 19.7 | DE21: 20 | DF21: 18.9 | DG21: 3.5 | DH21: 18.7 | DI21: 0.9 | DJ21: 1.1 | DK21: 9 | DL21: 11.3 | DM21: 4.8 | DN21: 2.4 | DO21: 2.4 | DP21: 2.9 | DQ21: 1.7 | DR21: 3.6 | DS21: 17.2 | DT21: 2 | DV21: 14.6 | DW21: 12.2 | DX21: 19.1 | DY21: 20.3 | DZ21: 19.8 | EA21: 10.8 | EB21: 7.9 | EC21: 0.1 | ED21: 6.6 | EE21: 19.4 | EF21: 0 | EG21: 0 | EH21: 20 | EI21: 5.7 | EJ21: 5.7 | EK21: 20.4 | EL21: 20.4 | EM21: 0 | EN21: 1.6 | EO21: 0 | EP21: 1 | EQ21: 0.6 | ER21: 0 | ES21: 0 | ET21: 0.9 | EU21: 0 | EV21: 4.8 | EW21: 19.8 | EX21: 9.7 | EY21: 24.9 | EZ21: 34.4 | FA21: 29.5 | FB21: 3.3 | FC21: 15 | FD21: 14.7 | FE21: 6.7 | FF21: 6236.1 | FH21: 24.09891 | FI21: 1.3 | FJ21: 8.1 | FK21: 9.92553 | FL21: 11.4 | FN21: 18.90792 | FO21: 2.4 | FP21: 3.8 | FQ21: 79.93236
A22: 15/01/2025 | B22: 06:00 | C22: 1.1 | D22: 1.7 | E22: 4.2 | F22: 646.6 | G22: 218.6 | J22: 90 | K22: 238.9 | L22: 0 | M22: 0 | N22: 108.4 | O22: 108.9 | P22: 108.7 | Q22: 212.1 | R22: 206 | S22: 109.6 | T22: 557.6 | U22: 10.5 | Z22: 166.9 | AA22: 7.6 | AB22: 0 | AC22: 6.5 | AD22: 9.7 | AE22: 40 | AF22: 5.8 | AJ22: 110.5 | AK22: 221.8 | AL22: 0 | AO22: 6.5 | AP22: 390.6 | AQ22: 55 | AR22: 137.6 | AS22: 38 | AT22: 18.3 | AU22: 19.7 | AV22: 93.7 | AW22: 169.3 | AX22: 169.6 | AY22: 175.9 | AZ22: 108.7 | BA22: 7.8 | BB22: 6.6 | BC22: 25.3 | BD22: 44.2 | BE22: 3.1 | BF22: 31.6 | BG22: 155.3 | BH22: 57.1 | BK22: 0 | BO22: 101.6 | BQ22: 0 | BY22: 111.8 | CB22: 64.8 | CC22: 124.1 | CD22: 63.6 | CE22: 69 | CF22: 29.9 | CJ22: 115.2 | CL22: 55.3 | CN22: 0 | CT22: 0 | CU22: 56.9 | CV22: 7.6 | CW22: 2.1 | CX22: 0 | CY22: 19.9 | CZ22: 9.9 | DA22: 5.4 | DB22: 3.6 | DC22: 4.7 | DD22: 20 | DE22: 19.4 | DF22: 18.9 | DG22: 3.5 | DH22: 18.7 | DI22: 6.3 | DJ22: 6.9 | DK22: 9.2 | DL22: 12.7 | DM22: 4.8 | DN22: 2.4 | DO22: 2.4 | DP22: 2.9 | DQ22: 8.1 | DR22: 3.6 | DS22: 17.2 | DT22: 2 | DV22: 14.6 | DW22: 12.2 | DX22: 19.4 | DY22: 20.3 | DZ22: 19.8 | EA22: 12.8 | EB22: 16.2 | EC22: 4.1 | ED22: 3.7 | EE22: 11.8 | EF22: 0 | EG22: 0 | EH22: 20 | EI22: 5.7 | EJ22: 5.5 | EK22: 20.4 | EL22: 20.4 | EM22: 0 | EN22: 2.4 | EO22: 0 | EP22: 17 | EQ22: 0.6 | ER22: 0 | ES22: 0 | ET22: 14.4 | EU22: 0.2 | EV22: 4.8 | EW22: 19.9 | EX22: 9.5 | EY22: 25 | EZ22: 34.9 | FA22: 29.5 | FB22: 3.2 | FC22: 15 | FD22: 14.7 | FE22: 6.5 | FF22: 6314.5 | FH22: 24.0989 | FI22: 1.3 | FJ22: 8.1 | FK22: 10.01938 | FL22: 11.4 | FN22: 18.90716 | FO22: 2.5 | FP22: 3.8 | FQ22: 80.12544
... A58: 16/01/2025 | B58: 00:00 | C58: 1 | D58: 1.6 | E58: 4.2 | F58: 645 | G58: 218.7 | J58: 87.1 | K58: 237.5 | L58: 27.2 | M58: 59.4 | N58: 110.7 | O58: 110.1 | P58: 110.1 | Q58: 213.7 | R58: 110.8 | S58: 70.1 | T58: 558.3 | U58: 10.3 | Z58: 162.7 | AA58: 7.7 | AB58: 0 | AC58: 6.5 | AD58: 9.6 | AE58: 71.8 | AF58: 6 | AJ58: 109.8 | AK58: 204.9 | AL58: 58.8 | AO58: 6.5 | AP58: 457 | AQ58: 47 | AR58: 146.2 | AS58: 32.1 | AT58: 18.4 | AU58: 19.7 | AV58: 91.2 | AW58: 15 | AX58: 120.6 | AY58: 94.1 | AZ58: 108.4 | BA58: 7.6 | BB58: 6.5 | BC58: 43 | BD58: 46.5 | BE58: 3 | BF58: 31.2 | BG58: 148 | BH58: 90.5 | BK58: 47.7 | BO58: 128.9 | BQ58: 0 | BY58: 111.1 | CB58: 172.9 | CC58: 129.4 | CD58: 63.3 | CE58: 80.3 | CF58: 29.7 | CJ58: 116.2 | CL58: 55.8 | CN58: 29.4 | CT58: 0 | CU58: 57.6 | CV58: 0 | CW58: 5.2 | CX58: 0 | CY58: 20 | CZ58: 9.9 | DA58: 5.4 | DB58: 3.5 | DC58: 4.6 | DD58: 19.9 | DE58: 20 | DF58: 18.9 | DG58: 3.6 | DH58: 18.7 | DI58: 0 | DJ58: 0 | DK58: 12.8 | DL58: 46.9 | DM58: 4.8 | DN58: 2.4 | DO58: 2.4 | DP58: 2.9 | DQ58: 0 | DR58: 3.5 | DS58: 20.2 | DT58: 2 | DV58: 12.3 | DW58: 12.2 | DX58: 20.2 | DY58: 20.4 | DZ58: 19.8 | EA58: 6.3 | EB58: 17.4 | EC58: 0 | ED58: 43.5 | EE58: 74.3 | EF58: 0.9 | EG58: 1.8 | EH58: 19.7 | EI58: 7.6 | EJ58: 5.8 | EK58: 20.4 | EL58: 20.4 | EM58: 10.2 | EN58: 6 | EO58: 0 | EP58: 0 | EQ58: 0.6 | ER58: 46.7 | ES58: 48.3 | ET58: 0 | EU58: 0 | EV58: 4.9 | EW58: 19.9 | EX58: 9.8 | EY58: 25.6 | EZ58: 34.2 | FA58: 29.3 | FB58: 3.3 | FC58: 14.9 | FD58: 15.5 | FE58: 7.8 | FF58: 6576 | FH58: 24.00606 | FI58: 1.3 | FJ58: 8.1 | FK58: 11.59662 | FL58: 10.4 | FN58: 18.91033 | FO58: 2.4 | FP58: 7 | FQ58: 83.71301
A59: EJEC | C59: 14.65 | D59: 22.3 | E59: 101.2 | F59: 15518.25 | G59: 5260.2 | H59: 0 | I59: 0 | J59: 2159.3 | K59: 5714.1 | L59: 69.6 | M59: 107.15 | N59: 3131.8 | O59: 3135.95 | P59: 3138 | Q59: 5514.1 | R59: 4816.85 | S59: 2567.7 | T59: 13388.45 | U59: 251.7 | V59: 0 | W59: 0 | X59: 0 | Y59: 0 | Z59: 3981.75 | AA59: 187.3 | AB59: 123.85 | AC59: 154.45 | AD59: 229.7 | AE59: 1515.85 | AF59: 137.25 | AG59: 0 | AH59: 0 | AI59: 0 | AJ59: 2656.15 | AK59: 5167.65 | AL59: 29.4 | AM59: 0 | AN59: 0 | AO59: 156 | AP59: 10715.3 | AQ59: 1235.7 | AR59: 3447 | AS59: 853.8 | AT59: 439.25 | AU59: 472.8 | AV59: 2069 | AW59: 3804.9 | AX59: 3866.3 | AY59: 4122.1 | AZ59: 2605.05 | BA59: 184.7 | BB59: 156.55 | BC59: 661.15 | BD59: 1118.4 | BE59: 73.6 | BF59: 740.25 | BG59: 3746.85 | BH59: 1343.3 | BI59: 0 | BJ59: 0 | BK59: 816.45 | BL59: 0 | BM59: 0 | BN59: 0 | BO59: 2892.7 | BP59: 0 | BQ59: 525.55 | BR59: 0 | BS59: 0 | BT59: 0 | BU59: 0 | BV59: 0 | BW59: 0 | BX59: 0 | BY59: 2690.35 | BZ59: 0 | CA59: 0 | CB59: 3037 | CC59: 3095.55 | CD59: 1522.75 | CE59: 1855.6 | CF59: 721.35 | CG59: 0 | CH59: 0 | CI59: 0 | CJ59: 2953 | CK59: 0 | CL59: 1386.7 | CM59: 0 | CN59: 14.7 | CO59: 0 | CP59: 0 | CQ59: 0 | CR59: 0 | CS59: 0 | CT59: 8.85 | CU59: 1889.8 | CV59: 802.55 | CW59: 141.35 | CX59: 2.45 | CY59: 479.8 | CZ59: 238.1 | DA59: 129.8 | DB59: 86 | DC59: 114.7 | DD59: 464.4 | DE59: 477.65 | DF59: 453.3 | DG59: 85.3 | DH59: 448.8 | DI59: 156.75 | DJ59: 197.7 | DK59: 422.25 | DL59: 1146.1 | DM59: 113.3 | DN59: 56.2 | DO59: 57.6 | DP59: 66.25 | DQ59: 188.25 | DR59: 85.9 | DS59: 360.5 | DT59: 48 | DU59: 0 | DV59: 325.1 | DW59: 289.7 | DX59: 478.8 | DY59: 489.05 | DZ59: 477.7 | EA59: 349.75 | EB59: 845.9 | EC59: 363.05 | ED59: 1134.95 | EE59: 1469.25 | EF59: 110.1 | EG59: 90.25 | EH59: 467.65 | EI59: 136.05 | EJ59: 140.45 | EK59: 489.6 | EL59: 489.6 | EM59: 122.4 | EN59: 160.25 | EO59: 38.85 | EP59: 1121.55 | EQ59: 14.4 | ER59: 1090.45 | ES59: 1105.4 | ET59: 909.3 | EU59: 133.25 | EV59: 114.7 | EW59: 478.2 | EX59: 240.05 | EY59: 606.3 | EZ59: 830.8 | FA59: 696.1 | FB59: 79.7 | FC59: 354.05 | FD59: 325.2 | FE59: 187.3 | FF59: 167895.2 | FH59: 573.5579 | FI59: 31.2 | FJ59: 194.2 | FK59: 260.37379 | FL59: 269.7 | FM59: 0 | FN59: 453.85152 | FO59: 39.65 | FP59: 152.4 | FQ59: 1974.9332

Sheet REACTIVA
B3: miércoles, 15 de Enero del 2025
A5: POTENCIA REACTIVA EJECUTADA DE LAS UNIDADES DE GENERACIÓN DEL COES (MVAR) | FH5: CENTRALES NO INTEGRANTES COES
A6: FECHA | B6: HORA | C6: 337 | D6: 338 | E6: 121 | F6: 101 | G6: 102 | H6: 42667 | I6: 42668 | J6: 126 | K6: 127 | L6: 138 | M6: 139 | N6: 197 | O6: 203 | P6: 204 | Q6: 230 | R6: 209 | S6: 56677 | T6: 796 | U6: 2146 | V6: 142 | W6: 143 | X6: 125 | Y6: 187 | Z6: 163 | AA6: 298 | AB6: 219 | AC6: 151 | AD6: 152 | AE6: 153 | AF6: 154 | AG6: 756 | AH6: 156 | AI6: 155 | AJ6: 182 | AK6: 212 | AL6: 758 | AM6: 263 | AN6: 265 | AO6: 775 | AP6: 777 | AQ6: 2154 | AR6: 150 | AS6: 149 | AT6: 188 | AU6: 2131 | AV6: 755 | AW6: 252 | AX6: 249 | AY6: 250 | AZ6: 117 | BA6: 267 | BB6: 268 | BC6: 119 | BD6: 120 | BE6: 189 | BF6: 122 | BG6: 266 | BH6: 251 | BI6: 115 | BJ6: 239 | BK6: 288 | BL6: 240 | BM6: 241 | BN6: 242 | BO6: 191 | BP6: 194 | BQ6: 196 | BR6: 207 | BS6: 236 | BT6: 795 | BU6: 285 | BV6: 995 | BW6: 996 | BX6: 997 | BY6: 766 | BZ6: 926 | CA6: 924 | CB6: 103 | CC6: 104 | CD6: 106 | CE6: 105 | CF6: 107 | CG6: 110 | CH6: 109 | CI6: 144 | CJ6: 113 | CK6: 114 | CL6: 193 | CM6: 208 | CN6: 786 | CO6: 787 | CP6: 788 | CQ6: 789 | CR6: 248 | CS6: 2159 | CT6: 303 | CU6: 59715 | CV6: 62255 | CW6: 1263 | CX6: 61800 | CY6: 2194 | CZ6: 216 | DA6: 198 | DB6: 214 | DC6: 260 | DD6: 2152 | DE6: 2128 | DF6: 247 | DG6: 228 | DH6: 2135 | DI6: 261 | DJ6: 237 | DK6: 253 | DL6: 770 | DM6: 225 | DN6: 2201 | DO6: 2171 | DP6: 760 | DQ6: 235 | DR6: 238 | DS6: 2184 | DT6: 61855 | DU6: 223 | DV6: 226 | DW6: 201 | DX6: 258 | DY6: 259 | DZ6: 920 | EA6: 257 | EB6: 256 | EC6: 2148 | ED6: 58288 | EE6: 58289 | EF6: 58839 | EG6: 58840 | EH6: 296 | EI6: 297 | EJ6: 211 | EK6: 2175 | EL6: 2178 | EM6: 2181 | EN6: 1262 | EO6: 233 | EP6: 2150 | EQ6: 2165 | ER6: 2161 | ES6: 61197 | ET6: 58851 | EU6: 234 | EV6: 215 | EW6: 917 | EX6: 289 | EY6: 58333 | EZ6: 58336 | FA6: 202 | FB6: 58487 | FC6: 213 | FD6: 232 | FE6: 2190 | FF6: TOTAL COES | FH6: 221 | FI6: 49607 | FJ6: 222 | FK6: 224 | FL6: 2187 | FM6: 227 | FN6: 49400 | FO6: 199 | FP6: 200 | FQ6: TOTAL NO COES
C7: CENTRO | D7: CENTRO | E7: NORTE | F7: CENTRO | G7: CENTRO | H7: NORTE | I7: NORTE | J7: NORTE | K7: NORTE | L7: CENTRO | M7: CENTRO | N7: CENTRO | O7: CENTRO | P7: CENTRO | Q7: CENTRO | R7: CENTRO | S7: CENTRO | T7: CENTRO | U7: CENTRO | V7: CENTRO | W7: CENTRO | X7: CENTRO | Y7: CENTRO | Z7: SUR | AA7: SUR | AB7: CENTRO | AC7: SUR | AD7: SUR | AE7: SUR | AF7: SUR | AG7: SUR | AH7: SUR | AI7: SUR | AJ7: SUR | AK7: CENTRO | AL7: NORTE | AM7: NORTE | AN7: NORTE | AO7: CENTRO | AP7: CENTRO | AQ7: CENTRO | AR7: CENTRO | AS7: CENTRO | AT7: CENTRO | AU7: CENTRO | AV7: SUR | AW7: CENTRO | AX7: CENTRO | AY7: CENTRO | AZ7: CENTRO | BA7: CENTRO | BB7: CENTRO | BC7: CENTRO | BD7: CENTRO | BE7: SUR | BF7: NORTE | BG7: CENTRO | BH7: CENTRO | BI7: NORTE | BJ7: NORTE | BK7: NORTE | BL7: SUR | BM7: SUR | BN7: SUR | BO7: CENTRO | BP7: CENTRO | BQ7: CENTRO | BR7: CENTRO | BS7: CENTRO | BT7: CENTRO | BU7: CENTRO | BV7: SUR | BW7: SUR | BX7: SUR | BY7: NORTE | BZ7: SUR | CA7: CENTRO | CB7: CENTRO | CC7: CENTRO | CD7: CENTRO | CE7: CENTRO | CF7: CENTRO | CG7: CENTRO | CH7: CENTRO | CI7: CENTRO | CJ7: CENTRO | CK7: CENTRO | CL7: CENTRO | CM7: CENTRO | CN7: SUR | CO7: SUR | CP7: SUR | CQ7: SUR | CR7: CENTRO | CS7: CENTRO | CT7: CENTRO | CU7: CENTRO | CV7: SUR | CW7: NORTE | CX7: NORTE | CY7: NORTE | CZ7: NORTE | DA7: NORTE | DB7: CENTRO | DC7: CENTRO | DD7: CENTRO | DE7: NORTE | DF7: NORTE | DG7: CENTRO | DH7: CENTRO | DI7: SUR | DJ7: SUR | DK7: CENTRO | DL7: CENTRO | DM7: CENTRO | DN7: CENTRO | DO7: CENTRO | DP7: CENTRO | DQ7: SUR | DR7: CENTRO | DS7: CENTRO | DT7: NORTE | DU7: CENTRO | DV7: CENTRO | DW7: NORTE | DX7: CENTRO | DY7: CENTRO | DZ7: CENTRO | EA7: NORTE | EB7: NORTE | EC7: SUR | ED7: CENTRO | EE7: CENTRO | EF7: CENTRO | EG7: CENTRO | EH7: CENTRO | EI7: CENTRO | EJ7: SUR | EK7: SUR | EL7: SUR | EM7: SUR | EN7: NORTE | EO7: SUR | EP7: SUR | EQ7: CENTRO | ER7: CENTRO | ES7: CENTRO | ET7: SUR | EU7: SUR | EV7: NORTE | EW7: CENTRO | EX7: NORTE | EY7: NORTE | EZ7: NORTE | FA7: CENTRO | FB7: CENTRO | FC7: CENTRO | FD7: NORTE | FE7: NORTE | FH7: NORTE | FI7: SUR | FJ7: CENTRO | FK7: NORTE | FL7: NORTE | FM7: NORTE | FN7: NORTE | FO7: NORTE | FP7: NORTE
C8: HIDROELÉCTRICA | D8: HIDROELÉCTRICA | E8: HIDROELÉCTRICA | F8: HIDROELÉCTRICA | G8: HIDROELÉCTRICA | H8: TERMOELÉCTRICA | I8: TERMOELÉCTRICA | J8: HIDROELÉCTRICA | K8: HIDROELÉCTRICA | L8: TERMOELÉCTRICA | M8: TERMOELÉCTRICA | N8: TERMOELÉCTRICA | O8: TERMOELÉCTRICA | P8: TERMOELÉCTRICA | Q8: TERMOELÉCTRICA | R8: TERMOELÉCTRICA | S8: TERMOELÉCTRICA | T8: HIDROELÉCTRICA | U8: HIDROELÉCTRICA | V8: TERMOELÉCTRICA | W8: TERMOELÉCTRICA | X8: TERMOELÉCTRICA | Y8: TERMOELÉCTRICA | Z8: HIDROELÉCTRICA | AA8: HIDROELÉCTRICA | AB8: TERMOELÉCTRICA | AC8: HIDROELÉCTRICA | AD8: HIDROELÉCTRICA | AE8: HIDROELÉCTRICA | AF8: HIDROELÉCTRICA | AG8: TERMOELÉCTRICA | AH8: TERMOELÉCTRICA | AI8: TERMOELÉCTRICA | AJ8: HIDROELÉCTRICA | AK8: HIDROELÉCTRICA | AL8: TERMOELÉCTRICA | AM8: TERMOELÉCTRICA | AN8: TERMOELÉCTRICA | AO8: HIDROELÉCTRICA | AP8: HIDROELÉCTRICA | AQ8: HIDROELÉCTRICA | AR8: HIDROELÉCTRICA | AS8: HIDROELÉCTRICA | AT8: HIDROELÉCTRICA | AU8: HIDROELÉCTRICA | AV8: HIDROELÉCTRICA | AW8: TERMOELÉCTRICA | AX8: TERMOELÉCTRICA | AY8: TERMOELÉCTRICA | AZ8: HIDROELÉCTRICA | BA8: HIDROELÉCTRICA | BB8: HIDROELÉCTRICA | BC8: HIDROELÉCTRICA | BD8: HIDROELÉCTRICA | BE8: HIDROELÉCTRICA | BF8: HIDROELÉCTRICA | BG8: HIDROELÉCTRICA | BH8: HIDROELÉCTRICA | BI8: TERMOELÉCTRICA | BJ8: TERMOELÉCTRICA | BK8: TERMOELÉCTRICA | BL8: TERMOELÉCTRICA | BM8: TERMOELÉCTRICA | BN8: TERMOELÉCTRICA | BO8: HIDROELÉCTRICA | BP8: TERMOELÉCTRICA | BQ8: TERMOELÉCTRICA | BR8: TERMOELÉCTRICA | BS8: TERMOELÉCTRICA | BT8: TERMOELÉCTRICA | BU8: TERMOELÉCTRICA | BV8: TERMOELÉCTRICA | BW8: TERMOELÉCTRICA | BX8: TERMOELÉCTRICA | BY8: HIDROELÉCTRICA | BZ8: TERMOELÉCTRICA | CA8: TERMOELÉCTRICA | CB8: HIDROELÉCTRICA | CC8: HIDROELÉCTRICA | CD8: HIDROELÉCTRICA | CE8: HIDROELÉCTRICA | CF8: HIDROELÉCTRICA | CG8: TERMOELÉCTRICA | CH8: TERMOELÉCTRICA | CI8: TERMOELÉCTRICA | CJ8: TERMOELÉCTRICA | CK8: TERMOELÉCTRICA | CL8: TERMOELÉCTRICA | CM8: TERMOELÉCTRICA | CN8: TERMOELÉCTRICA | CO8: TERMOELÉCTRICA | CP8: TERMOELÉCTRICA | CQ8: TERMOELÉCTRICA | CR8: TERMOELÉCTRICA | CS8: TERMOELÉCTRICA | CT8: SOLAR | CU8: EÓLICA | CV8: SOLAR | CW8: EÓLICA | CX8: SOLAR | CY8: HIDROELÉCTRICA | CZ8: HIDROELÉCTRICA | DA8: HIDROELÉCTRICA | DB8: HIDROELÉCTRICA | DC8: HIDROELÉCTRICA | DD8: HIDROELÉCTRICA | DE8: HIDROELÉCTRICA | DF8: HIDROELÉCTRICA | DG8: HIDROELÉCTRICA | DH8: HIDROELÉCTRICA | DI8: SOLAR | DJ8: SOLAR | DK8: EÓLICA | DL8: EÓLICA | DM8: TERMOELÉCTRICA | DN8: TERMOELÉCTRICA | DO8: TERMOELÉCTRICA | DP8: TERMOELÉCTRICA | DQ8: SOLAR | DR8: HIDROELÉCTRICA | DS8: HIDROELÉCTRICA | DT8: HIDROELÉCTRICA | DU8: HIDROELÉCTRICA | DV8: HIDROELÉCTRICA | DW8: HIDROELÉCTRICA | DX8: HIDROELÉCTRICA | DY8: HIDROELÉCTRICA | DZ8: HIDROELÉCTRICA | EA8: EÓLICA | EB8: EÓLICA | EC8: SOLAR | ED8: EÓLICA | EE8: EÓLICA | EF8: EÓLICA | EG8: EÓLICA | EH8: HIDROELÉCTRICA | EI8: HIDROELÉCTRICA | EJ8: HIDROELÉCTRICA | EK8: HIDROELÉCTRICA | EL8: HIDROELÉCTRICA | EM8: HIDROELÉCTRICA | EN8: EÓLICA | EO8: SOLAR | EP8: SOLAR | EQ8: HIDROELÉCTRICA | ER8: EÓLICA | ES8: EÓLICA | ET8: SOLAR | EU8: SOLAR | EV8: HIDROELÉCTRICA | EW8: HIDROELÉCTRICA | EX8: TERMOELÉCTRICA | EY8: TERMOELÉCTRICA | EZ8: TERMOELÉCTRICA | FA8: TERMOELÉCTRICA | FB8: TERMOELÉCTRICA | FC8: TERMOELÉCTRICA | FD8: TERMOELÉCTRICA | FE8: TERMOELÉCTRICA | FH8: HIDROELÉCTRICA | FI8: HIDROELÉCTRICA | FJ8: HIDROELÉCTRICA | FK8: HIDROELÉCTRICA | FL8: HIDROELÉCTRICA | FM8: TERMOELÉCTRICA | FN8: TERMOELÉCTRICA | FO8: HIDROELÉCTRICA | FP8: HIDROELÉCTRICA
C9: CENTRALES SANTA ROSA S.A.C. | D9: CENTRALES SANTA ROSA S.A.C. | E9: INVERSIONES SHAQSHA S.A.C. | F9: ELECTROPERU | G9: ELECTROPERU | H9: ELECTROPERU | I9: ELECTROPERU | J9: ORAZUL ENERGY PERÚ | K9: ORAZUL ENERGY PERÚ | L9: TERMOSELVA | M9: TERMOSELVA | N9: KALLPA GENERACION S.A. | O9: KALLPA GENERACION S.A. | P9: KALLPA GENERACION S.A. | Q9: KALLPA GENERACION S.A. | R9: KALLPA GENERACION S.A. | S9: KALLPA GENERACION S.A. | T9: KALLPA GENERACION S.A. | U9: KALLPA GENERACION S.A. | V9: SHOUGESA | W9: SHOUGESA | X9: SHOUGESA | Y9: SHOUGESA | Z9: EGEMSA | AA9: EGESUR | AB9: EGESUR | AC9: EGASA | AD9: EGASA | AE9: EGASA | AF9: EGASA | AG9: EGASA | AH9: EGASA | AI9: EGASA | AJ9: SAN GABAN | AK9: CELEPSA | AL9: MINERA CERRO VERDE | AM9: PLANTA DE RESERVA FRIA DE GENERACION DE ETEN S.A. | AN9: PLANTA DE RESERVA FRIA DE GENERACION DE ETEN S.A. | AO9: EMPRESA DE GENERACION HUALLAGA | AP9: EMPRESA DE GENERACION HUALLAGA | AQ9: LA VIRGEN | AR9: CHINANGO S.A.C. | AS9: CHINANGO S.A.C. | AT9: HIDROELECTRICA HUANCHOR S.A.C. | AU9: CELEPSA RENOVABLES S.R.L. | AV9: INLAND ENERGY SAC | AW9: FENIX POWER PERÚ | AX9: FENIX POWER PERÚ | AY9: FENIX POWER PERÚ | AZ9: STATKRAFT S.A | BA9: STATKRAFT S.A | BB9: STATKRAFT S.A | BC9: STATKRAFT S.A | BD9: STATKRAFT S.A | BE9: STATKRAFT S.A | BF9: STATKRAFT S.A | BG9: STATKRAFT S.A | BH9: EMPRESA DE GENERACION HUANZA | BI9: ENEL GENERACION PIURA S.A. | BJ9: ENEL GENERACION PIURA S.A. | BK9: ENEL GENERACION PIURA S.A. | BL9: ENGIE | BM9: ENGIE | BN9: ENGIE | BO9: ENGIE | BP9: ENGIE | BQ9: ENGIE | BR9: ENGIE | BS9: ENGIE | BT9: ENGIE | BU9: ENGIE | BV9: ENGIE | BW9: ENGIE | BX9: ENGIE | BY9: ENGIE | BZ9: INFRAESTRUCTURAS Y ENERGIAS DEL PERU S.A.C. | CA9: INFRAESTRUCTURAS Y ENERGIAS DEL PERU S.A.C. | CB9: ORYGEN PERU S.A.A. | CC9: ORYGEN PERU S.A.A. | CD9: ORYGEN PERU S.A.A. | CE9: ORYGEN PERU S.A.A. | CF9: ORYGEN PERU S.A.A. | CG9: ORYGEN PERU S.A.A. | CH9: ORYGEN PERU S.A.A. | CI9: ORYGEN PERU S.A.A. | CJ9: ORYGEN PERU S.A.A. | CK9: ORYGEN PERU S.A.A. | CL9: ORYGEN PERU S.A.A. | CM9: ORYGEN PERU S.A.A. | CN9: SAMAY I S.A.C | CO9: SAMAY I S.A.C | CP9: SAMAY I S.A.C | CQ9: SAMAY I S.A.C | CR9: TERMOCHILCA S.A.C. | CS9: TERMOCHILCA S.A.C. | CT9: COLCA SOLAR S.A.C. | CU9: ENERGIA RENOVABLE DEL SUR S.A. | CV9: GR CORTARRAMA SOCIEDAD ANONIMA CERRADA | CW9: GR TARUCA SOCIEDAD ANONIMA CERRADA | CX9: KONDU SAC | CY9: PERUANA DE INVERSIONES EN ENERGIAS RENOVABLES S.A. | CZ9: ORAZUL ENERGY PERÚ | DA9: ORAZUL ENERGY PERÚ | DB9: MAJA ENERGIA S.A.C. | DC9: EMPRESA DE GENERACION ELECTRICA CANCHAYLLO SAC | DD9: EMPRESA DE GENERACION ELECTRICA SANTA ANA S.A.C. | DE9: EMPRESA ELECTRICA AGUA AZUL | DF9: EMPRESA ELECTRICA RIO DOBLE | DG9: HIDROCAÑETE S.A. | DH9: HUAURA POWER GROUP S.A. | DI9: MOQUEGUA FV S.A.C. | DJ9: PANAMERICANA SOLAR SAC. | DK9: PARQUE EOLICO MARCONA S.A.C. | DL9: PARQUE EOLICO TRES HERMANAS S.A.C. | DM9: PETRAMAS | DN9: PETRAMAS | DO9: PETRAMAS | DP9: PETRAMAS | DQ9: TACNA SOLAR SAC. | DR9: ELECTRICA YANAPAMPA SAC | DS9: ANDEAN POWER S.A.C. | DT9: ASOCIACIÓN SANTA LUCIA DE CHACAS | DU9: ATRIA ENERGIA S.A.C. | DV9: EGEJUNIN | DW9: EGEJUNIN | DX9: EGEJUNIN | DY9: EGEJUNIN | DZ9: EMPRESA DE GENERACION ELECTRICA RIO BAÑOS S.A.C. | EA9: ENERGÍA EÓLICA S.A. | EB9: ENERGÍA EÓLICA S.A. | EC9: ENGIE | ED9: ENGIE | EE9: ENGIE | EF9: ENGIE | EG9: ENGIE | EH9: GENERACIÓN ANDINA S.A.C. | EI9: GENERACIÓN ANDINA S.A.C. | EJ9: GENERADORA DE ENERGÍA DEL PERÚ | EK9: GENERADORA DE ENERGÍA DEL PERÚ | EL9: GENERADORA DE ENERGÍA DEL PERÚ | EM9: GENERADORA DE ENERGÍA DEL PERÚ | EN9: GR PAINO SOCIEDAD ANONIMA CERRADA | EO9: MAJES ARCUS S.A.C. | EP9: ORYGEN PERU S.A.A. | EQ9: ORYGEN PERU S.A.A. | ER9: ORYGEN PERU S.A.A. | ES9: ORYGEN PERU S.A.A. | ET9: ORYGEN PERU S.A.A. | EU9: REPARTICIÓN ARCUS S.A.C. | EV9: SINERSA | EW9: SINERSA | EX9: BIOENERGIA DEL CHIRA S.A. | EY9: GM OPERACIONES S.A.C. | EZ9: GM OPERACIONES S.A.C. | FA9: SDF ENERGIA SAC | FB9: SDF ENERGIA SAC | FC9: AGRO INDUSTRIAL PARAMONGA S.A. | FD9: AGROAURORA S.A.C. | FE9: AGROINDUSTRIAS SAN JACINTO S.A.A. | FH9: UNACEM PERU S.A. | FI9: SAN GABAN | FJ9: ELECTRO ORIENTE | FK9: AGUAS Y ENERGIA PERU | FL9: ELECTRO ZAÑA S.A.C. | FM9: ELECTRONOROESTE S.A. | FN9: SDE PIURA | FO9: SINERSA | FP9: SINERSA
C10: SANTA ROSA 1 | D10: SANTA ROSA 2 | E10: PARIAC | F10: MANTARO | G10: RESTITUCION | H10: TUMBES MAK 1 | I10: TUMBES MAK 2 | J10: CARHUAQUERO | K10: CAÑON DEL PATO | L10: AGUAYTIA TG1 | M10: AGUAYTIA TG2 | N10: KALLPA TG1 | O10: KALLPA TG2 | P10: KALLPA TG3 | Q10: KALLPA TV | R10: LFLORES TG1 | S10: LFLORES TV | T10: CERRO DEL AGUILA | U10: CERRODELAGUILAG4 | V10: SHOUGESA TV1 | W10: SHOUGESA TV2 | X10: SHOUGESA TV3 | Y10: SHOUGESA CUMMINS | Z10: MACHUPICCHU | AA10: ARICOTA 1 | AB10: INDEPENDENCIA | AC10: CHARCANI I,II,III | AD10: CHARCANI IV | AE10: CHARCANI V | AF10: CHARCANI VI | AG10: CHILINA TG | AH10: MOLLENDO 1, 2, 3 | AI10: CHILINA (SULZ 1,2) | AJ10: SAN GABAN II | AK10: PLATANAL | AL10: RECKA | AM10: RF ETEN TG1 | AN10: RF ETEN TG2 | AO10: CHAGLLA GP1 | AP10: CHAGLLA | AQ10: LA VIRGEN | AR10: CHIMAY | AS10: YANANGO | AT10: HUANCHOR | AU10: MARAÑON | AV10: STA TERESA | AW10: FENIX GT11 | AX10: FENIX GT12 | AY10: FENIX TV10 | AZ10: YAUPI | BA10: OROYA | BB10: PACHACHACA | BC10: MALPASO | BD10: CAHUA | BE10: ARCATA | BF10: GALLITO CIEGO | BG10: CHEVES | BH10: HUANZA | BI10: MALACAS2 TG4 | BJ10: MALACAS3 TG 5 | BK10: MALACAS1 TG6 | BL10: RF ILO2 TG1 | BM10: RF ILO2 TG2 | BN10: RF ILO2 TG3 | BO10: YUNCAN | BP10: CHILCA1 TG1 | BQ10: CHILCA1 TG2 | BR10: CHILCA1 TG3 | BS10: CHILCA-TV | BT10: CHILCA2 TG41 | BU10: CHILCA2-TV | BV10: CTNEPI_TG41 | BW10: CTNEPI_TG42 | BX10: CTNEPI_TG43 | BY10: QUITARACSA | BZ10: RF PTO MALDONADO | CA10: RF PUCALLPA | CB10: HUINCO | CC10: MATUCANA | CD10: MOYOPAMPA | CE10: CALLAHUANCA | CF10: HUAMPANI | CG10: STA ROSA WEST TG7 | CH10: UTI_5 | CI10: UTI_6 | CJ10: VENTANILLA 3 | CK10: VENTANILLA 4 | CL10: VENTANILLA TV | CM10: STAROSA TG8 | CN10: PTO_BRVO TG1 | CO10: PTO_BRVO TG2 | CP10: PTO_BRVO TG3 | CQ10: PTO_BRVO TG4 | CR10: OLLEROS TG1 | CS10: OLLEROS TV | CT10: CS YARUCAYA | CU10: SAN JUAN | CV10: MATARANI | CW10: DUNA | CX10: CARHUAQUERO (CS) | CY10: MANTA I | CZ10: CARHUAQUERO4 | DA10: CAÑA BRAVA | DB10: RONCADOR | DC10: CANCHAYLLO | DD10: RENOVANDESH1 | DE10: POTRERO | DF10: PIZARRAS | DG10: NIMPERIAL | DH10: YARUCAYA | DI10: MOQUEGUA-SOLAR | DJ10: PANAMERICANA-SOLAR | DK10: PQE-EOLICO-MARCONA | DL10: PQE-EOLICO-3-HERMANAS | DM10: HUAYCOLORO | DN10: CALLAO | DO10: DONA_CATALINA | DP10: LAGRINGAV | DQ10: TACNA-SOLAR | DR10: YANAPAMPA | DS10: CARHUAC | DT10: HUALLIN | DU10: PURMACANA | DV10: HUASAHUASI | DW10: STACRUZ_1_2 | DX10: RUNATULLO_II | DY10: RUNATULLO_III | DZ10: RUCUY | EA10: PQE-EOLICO-TALARA | EB10: PQE-EOLICO-CUPISNIQUE | EC10: INTIPAMPA | ED10: PUNTA LOMITAS-BL1 | EE10: PUNTA LOMITAS-BL2 | EF10: PUN LOMITAS_EXP-BL1 | EG10: PUN LOMITAS_EXP-BL2 | EH10: 8AGOSTO | EI10: EL CARMEN | EJ10: LA JOYA | EK10: ANGEL_I | EL10: ANGEL_II | EM10: ANGEL_III | EN10: HUAMBOS | EO10: MAJES | EP10: RUBI | EQ10: CH_HER1 | ER10: WAYRA-I | ES10: WAYRA EXTENSION | ET10: CLEMESI | EU10: REPARTICION | EV10: POECHOS2 | EW10: CHANCAY | EX10: CANA BRAVA | EY10: REFINERIA TALARA TV1 | EZ10: REFINERÍA TALARA TV2 | FA10: OQUENDO TG1 | FB10: OQUENDO TV1 | FC10: PARAMONGA | FD10: MAPLE | FE10: SAN_JACINTO | FF10: MVAR | FH10: CARPAPATA | FI10: TUPURI | FJ10: CENTRALES ELOR | FK10: PIAS1 | FL10: ZANA | FM10: TABLAZO | FN10: TALLANCA | FO10: CURUMUY | FP10: POECHOS1 | FQ10: MVAR
A11: 15/01/2025 | B11: 00:30 | C11: 0.2 | D11: 0 | F11: 34.3 | G11: 21.6 | J11: -12.1 | K11: 28.9 | L11: 0 | M11: 0 | N11: -25.6 | O11: -38.3 | P11: -21.6 | Q11: 42.4 | R11: -11.2 | S11: -0.6 | T11: 77.5 | U11: 0 | Z11: 0.6 | AA11: 0.5 | AB11: 0 | AC11: -3.2 | AD11: 2 | AE11: 8.4 | AF11: 1.3 | AJ11: 11.9 | AK11: 18.7 | AL11: 0 | AO11: -1.5 | AP11: 26.7 | AQ11: 4.6 | AR11: 15.3 | AS11: 1.1 | AT11: 0.1 | AU11: 2.7 | AV11: 1.1 | AW11: 12.3 | AX11: -18.2 | AY11: -45.4 | AZ11: 8.5 | BA11: -0.9 | BB11: 0.7 | BC11: -2.7 | BD11: 8.2 | BE11: 0.9 | BF11: -0.1 | BG11: 8.8 | BH11: 1.8 | BK11: -6 | BO11: 16.2 | BQ11: 0 | BY11: -12.7 | CB11: 40.1 | CC11: 27.9 | CD11: 3.2 | CE11: 7.6 | CF11: 0.1 | CJ11: 24.5 | CL11: -41.3 | CN11: 0 | CU11: -4.3 | CV11: 0 | CY11: 1.4 | CZ11: 0 | DA11: -0.9 | DB11: 0.3 | DC11: 1.8 | DD11: 2.1 | DE11: 0 | DF11: 1.8 | DG11: 0.5 | DI11: 0 | DJ11: 0 | DK11: -3.6 | DL11: -7.5 | DM11: 1.5 | DN11: 0.5 | DO11: 0.6 | DP11: 1 | DQ11: 0 | DR11: -0.1 | DS11: 0.5 | DT11: 0 | DV11: -3.6 | DW11: 0.2 | DX11: 2.5 | DY11: 2.2 | DZ11: 1.1 | EA11: 0.8 | EB11: 4 | EC11: 0 | ED11: -2.8 | EE11: -3 | EF11: 7.8 | EG11: 7.7 | EH11: 2.5 | EI11: 0 | EJ11: 1.1 | EK11: 0.2 | EL11: 0.2 | EM11: 0 | EO11: 0 | EP11: 0 | EQ11: -0.2 | ER11: -5.3 | ES11: 3.6 | ET11: 0 | EU11: 0 | EV11: 1.6 | EW11: 1.4 | EX11: 2.8 | EY11: 7.8 | EZ11: 7.7 | FA11: 0.7 | FB11: 1.4 | FC11: 4 | FD11: 0.4 | FE11: 4 | FF11: 265.7 | FH11: 2.34237 | FK11: 3.516 | FL11: 1.7 | FN11: 0.10975 | FO11: 0.1 | FP11: 2 | FQ11: 9.76812
A12: 15/01/2025 | B12: 01:00 | C12: 0.2 | D12: 0 | F12: 11 | G12: 17.3 | J12: -14.3 | K12: 21.3 | L12: 0 | M12: 0 | N12: -30.3 | O12: -43.8 | P12: -28.2 | Q12: 37.1 | R12: -15.2 | S12: -3.5 | T12: 67.2 | U12: 0 | Z12: -1.8 | AA12: 0.6 | AB12: 0 | AC12: -3.3 | AD12: 2 | AE12: 8.9 | AF12: 1.3 | AJ12: 10.4 | AK12: 18.4 | AL12: 0 | AO12: -1.5 | AP12: 37.9 | AQ12: 4.8 | AR12: 16.1 | AS12: 0.8 | AT12: 0 | AU12: 2.7 | AV12: 1.5 | AW12: 6.1 | AX12: -24.2 | AY12: -51.6 | AZ12: 7.8 | BA12: -1 | BB12: 0.4 | BC12: -6 | BD12: 7.1 | BE12: 1 | BF12: -0.1 | BG12: 7.2 | BH12: -0.1 | BK12: -5.5 | BO12: 2.7 | BQ12: 0 | BY12: -16.8 | CB12: 41.1 | CC12: 29.7 | CD12: 3 | CE12: 10 | CF12: 0 | CJ12: 18 | CL12: -51.3 | CN12: 0 | CU12: -4.2 | CV12: 0 | CY12: 1.4 | CZ12: 0 | DA12: -0.9 | DB12: 0.2 | DC12: 1.9 | DD12: 2.1 | DE12: 0 | DF12: 1.8 | DG12: 0.5 | DI12: 0 | DJ12: 0 | DK12: -3.7 | DL12: -8.5 | DM12: 1.5 | DN12: 0.5 | DO12: 0.6 | DP12: 1 | DQ12: 0 | DR12: -0.1 | DS12: 0.5 | DT12: 0 | DV12: -3.5 | DW12: 0.2 | DX12: 2.5 | DY12: 2.1 | DZ12: 1.1 | EA12: 0.8 | EB12: 4 | EC12: 0 | ED12: -3.6 | EE12: -4.9 | EF12: 7.8 | EG12: 6.1 | EH12: 2.4 | EI12: -0.1 | EJ12: 1.2 | EK12: 0.2 | EL12: 0.2 | EM12: 0 | EO12: 0 | EP12: 0 | EQ12: -0.2 | ER12: -6.5 | ES12: 3.6 | ET12: 0 | EU12: 0 | EV12: 1.6 | EW12: 1.4 | EX12: 2.6 | EY12: 7.8 | EZ12: 6.1 | FA12: 0.7 | FB12: 1.4 | FC12: 3.1 | FD12: 0 | FE12: 3.7 | FF12: 131.5 | FH12: 2.48263 | FK12: 3.312 | FL12: 1.7 | FN12: 0.1665 | FO12: -0.4 | FP12: 1.9 | FQ12: 9.16113
A13: 15/01/2025 | B13: 01:30 | C13: 0.2 | D13: 0 | F13: 41.9 | G13: 23.2 | J13: -14.9 | K13: 24.7 | L13: 0 | M13: 0 | N13: -26.7 | O13: -37.5 | P13: -21.8 | Q13: 41.2 | R13: -12.3 | S13: -1.9 | T13: 77.2 | U13: 0 | Z13: 0.3 | AA13: 0.6 | AB13: 0 | AC13: -3.3 | AD13: 2 | AE13: 9.1 | AF13: 1.3 | AJ13: 11.7 | AK13: 18 | AL13: 0 | AO13: -1.7 | AP13: 21.7 | AQ13: 3.4 | AR13: 4.4 | AS13: -1.5 | AT13: 0 | AU13: 2.7 | AV13: 0.9 | AW13: 5.7 | AX13: -24.8 | AY13: -51 | AZ13: 7.7 | BA13: -1.8 | BB13: 0.7 | BC13: -1.8 | BD13: 7.9 | BE13: 1 | BF13: -0.1 | BG13: 9 | BH13: 0.7 | BK13: -3.1 | BO13: 15 | BQ13: 0 | BY13: -13 | CB13: 39.6 | CC13: 24.4 | CD13: -3 | CE13: 7.3 | CF13: -0.1 | CJ13: 20.2 | CL13: -47.9 | CN13: 0 | CU13: -4.1 | CV13: 0 | CY13: 1.4 | CZ13: 0.1 | DA13: -0.9 | DB13: 0.2 | DC13: 1.7 | DD13: 2.1 | DE13: -0.1 | DF13: 1.3 | DG13: 0.5 | DI13: 0 | DJ13: 0 | DK13: -3.2 | DL13: -7.8 | DM13: 1.5 | DN13: 0.5 | DO13: 0.6 | DP13: 1 | DQ13: 0 | DR13: 0 | DS13: 0.5 | DT13: 0 | DV13: -3.6 | DW13: 0.2 | DX13: 2.5 | DY13: 2.1 | DZ13: 1.1 | EA13: 0.8 | EB13: 4 | EC13: 0 | ED13: 0.7 | EE13: 0.1 | EF13: 7.7 | EG13: 8.4 | EH13: 2.6 | EI13: -0.1 | EJ13: 1.1 | EK13: 0.2 | EL13: 0.2 | EM13: 0 | EO13: 0 | EP13: 0 | EQ13: -0.2 | ER13: -5.6 | ES13: 3.6 | ET13: 0 | EU13: 0 | EV13: 1.6 | EW13: 1.4 | EX13: 2.5 | EY13: 7.7 | EZ13: 8.4 | FA13: 0.7 | FB13: 1.7 | FC13: 4 | FD13: 0.9 | FE13: 3 | FF13: 208.5 | FH13: 2.21533 | FK13: 3.484 | FL13: 1.6 | FN13: 0.19749 | FO13: 0 | FP13: 1.9 | FQ13: 9.39682
A14: 15/01/2025 | B14: 02:00 | C14: 0.2 | D14: 0 | F14: 32.1 | G14: 21.5 | J14: -14.3 | K14: 14.6 | L14: 0 | M14: 0 | N14: -30 | O14: -40.7 | P14: -25.6 | Q14: 37.1 | R14: -15 | S14: -3.7 | T14: 73.1 | U14: 0.1 | Z14: -0.9 | AA14: 0.3 | AB14: 0 | AC14: -3.3 | AD14: 2.1 | AE14: 8.2 | AF14: 1.5 | AJ14: 10.7 | AK14: 17.5 | AL14: 0 | AO14: -1.6 | AP14: 34.7 | AQ14: 3.6 | AR14: 8.4 | AS14: -1.4 | AT14: 0.2 | AU14: 2.7 | AV14: 1.4 | AW14: 2.6 | AX14: -27.9 | AY14: -54 | AZ14: 8.6 | BA14: -1.8 | BB14: 0.7 | BC14: -2.9 | BD14: 7.3 | BE14: 0.9 | BF14: -0.1 | BG14: 8.8 | BH14: 1.4 | BK14: 0 | BO14: 12.5 | BQ14: 0 | BY14: -14.4 | CB14: 39.8 | CC14: 23.1 | CD14: -3.1 | CE14: 4.6 | CF14: -0.1 | CJ14: 16.7 | CL14: -53.3 | CN14: 0 | CU14: -4.5 | CV14: 0 | CY14: 1.4 | CZ14: 0 | DA14: -0.8 | DB14: 0.4 | DC14: 1.7 | DD14: 2.1 | DE14: -0.1 | DF14: 1.8 | DG14: 0.6 | DI14: 0 | DJ14: 0 | DK14: -3.4 | DL14: -7.9 | DM14: 1.5 | DN14: 0.5 | DO14: 0.6 | DP14: 1 | DQ14: 0 | DR14: 0 | DS14: 0.5 | DT14: 0 | DV14: -3.5 | DW14: 0.2 | DX14: 2.5 | DY14: 2.1 | DZ14: 1.1 | EA14: 0.8 | EB14: 4 | EC14: 0 | ED14: -0.5 | EE14: -1.4 | EF14: 7.6 | EG14: 9.3 | EH14: 2.6 | EI14: -0.1 | EJ14: 1.2 | EK14: 0.2 | EL14: 0.2 | EM14: 0 | EO14: 0 | EP14: 0 | EQ14: -0.2 | ER14: 0 | ES14: 3.6 | ET14: 0 | EU14: 0 | EV14: 1.6 | EW14: 1.4 | EX14: 2.3 | EY14: 7.6 | EZ14: 9.3 | FA14: 0.8 | FB14: 1.7 | FC14: 2.9 | FD14: 1.2 | FE14: 3.2 | FF14: 160 | FH14: 2.31465 | FK14: 3.292 | FL14: 1.6 | FN14: 0.1443 | FO14: 0.2 | FP14: 1.9 | FQ14: 9.45095
A15: 15/01/2025 | B15: 02:30 | C15: 0.2 | D15: 0 | F15: 34.8 | G15: 22.4 | J15: -13.1 | K15: 23.1 | L15: 0 | M15: 0 | N15: -31.4 | O15: -40.2 | P15: -24.1 | Q15: 37.9 | R15: -14.9 | S15: -3.5 | T15: 75.1 | U15: 0.1 | Z15: 0.1 | AA15: 0.3 | AB15: 0 | AC15: -3.2 | AD15: 2.1 | AE15: 8.5 | AF15: 1.5 | AJ15: 11.7 | AK15: 15 | AL15: 0 | AO15: -1.5 | AP15: 40 | AQ15: 3.5 | AR15: 8 | AS15: -1.2 | AT15: -0.1 | AU15: 2.7 | AV15: 1.5 | AW15: 3.4 | AX15: -27 | AY15: -53.2 | AZ15: 8.3 | BA15: -1.5 | BB15: 0.7 | BC15: -2 | BD15: 7.7 | BE15: 1 | BF15: -0.1 | BG15: 9.8 | BH15: 0.5 | BK15: 0 | BO15: 10.5 | BQ15: 0 | BY15: -11.5 | CB15: 40.3 | CC15: 22.6 | CD15: -3.4 | CE15: 4.7 | CF15: 0 | CJ15: 16.5 | CL15: -53.4 | CN15: 0 | CU15: -5 | CV15: 0 | CY15: 1.4 | CZ15: 0 | DA15: -1 | DB15: 0.4 | DC15: 1.8 | DD15: 2.1 | DE15: -0.1 | DF15: 1.8 | DG15: 0.5 | DI15: 0 | DJ15: 0 | DK15: -2.9 | DL15: -6.3 | DM15: 1.5 | DN15: 0.5 | DO15: 0.6 | DP15: 1 | DQ15: 0 | DR15: 0.1 | DS15: 0.5 | DT15: 0 | DV15: -3.6 | DW15: 0.2 | DX15: 2.5 | DY15: 2.1 | DZ15: 1.1 | EA15: 0.8 | EB15: 4 | EC15: 0 | ED15: -1.8 | EE15: -2.8 | EF15: 7.6 | EG15: 9.6 | EH15: 2.6 | EI15: -0.1 | EJ15: 1.3 | EK15: 0.2 | EL15: 0.2 | EM15: 0 | EO15: 0 | EP15: 0 | EQ15: -0.2 | ER15: 0 | ES15: 3.6 | ET15: 0 | EU15: 0 | EV15: 1.6 | EW15: 1.4 | EX15: 2.5 | EY15: 7.6 | EZ15: 9.6 | FA15: 0.7 | FB15: 1.6 | FC15: 2.9 | FD15: 1.7 | FE15: 3.5 | FF15: 186.5 | FH15: 2.36135 | FK15: 3.1 | FL15: 1.7 | FN15: 0.10213 | FO15: 0.3 | FP15: 1.9 | FQ15: 9.46348
A16: 15/01/2025 | B16: 03:00 | C16: 0.2 | D16: 0 | F16: 33 | G16: 22.6 | J16: -14 | K16: 21.3 | L16: 0 | M16: 0 | N16: -32.3 | O16: -41.4 | P16: -25.1 | Q16: 36.2 | R16: -15 | S16: -4.1 | T16: 78.8 | U16: 0.1 | Z16: -0.2 | AA16: 0.7 | AB16: 0 | AC16: -3.2 | AD16: 2.2 | AE16: 8.7 | AF16: 1.5 | AJ16: 11.4 | AK16: 5 | AL16: 0 | AO16: -1.6 | AP16: 48.3 | AQ16: 4 | AR16: 7.7 | AS16: -1 | AT16: 0.5 | AU16: 2.7 | AV16: 1.6 | AW16: 6.5 | AX16: -23.8 | AY16: -51.1 | AZ16: 7.9 | BA16: -0.9 | BB16: 0.6 | BC16: -3.7 | BD16: 6.9 | BE16: 1 | BF16: -0.1 | BG16: 9 | BH16: 0.5 | BK16: 0 | BO16: 11.6 | BQ16: 0 | BY16: -12 | CB16: 31.2 | CC16: 23.1 | CD16: -3.8 | CE16: 6.8 | CF16: 0.1 | CJ16: 16.5 | CL16: -53.1 | CN16: 0 | CU16: -5.5 | CV16: 0 | CY16: 1.4 | CZ16: 0.1 | DA16: -0.8 | DB16: 0.4 | DC16: 1.8 | DD16: 2.1 | DE16: 0 | DF16: 1.8 | DG16: 0.5 | DI16: 0 | DJ16: 0 | DK16: -2.5 | DL16: -5 | DM16: 1.5 | DN16: 0.5 | DO16: 0.6 | DP16: 1 | DQ16: 0 | DR16: -0.1 | DS16: 0.5 | DT16: 0 | DV16: -3.7 | DW16: 0.2 | DX16: 2.4 | DY16: 2.1 | DZ16: 1.1 | EA16: 0.8 | EB16: 4 | EC16: 0 | ED16: -1.4 | EE16: -3.7 | EF16: 7.6 | EG16: 9.3 | EH16: 2.4 | EI16: -0.1 | EJ16: 1.2 | EK16: 0.2 | EL16: 0.2 | EM16: 0 | EO16: 0 | EP16: 0 | EQ16: -0.2 | ER16: 0 | ES16: 3.6 | ET16: 0 | EU16: 0 | EV16: 1.6 | EW16: 1.4 | EX16: 2.3 | EY16: 7.6 | EZ16: 9.3 | FA16: 0.7 | FB16: 1.5 | FC16: 2.1 | FD16: 1.1 | FE16: 2.9 | FF16: 176.6 | FH16: 2.27738 | FK16: 3.116 | FL16: 1.7 | FN16: 0.13069 | FO16: 0.2 | FP16: 1.9 | FQ16: 9.32407
A17: 15/01/2025 | B17: 03:30 | C17: 0.2 | D17: 0 | F17: 32.5 | G17: 21.1 | J17: -13 | K17: 13.5 | L17: 0 | M17: 0 | N17: -30.6 | O17: -44.2 | P17: -27.9 | Q17: 38.7 | R17: -14 | S17: -3 | T17: 76 | U17: 0.1 | Z17: -0.2 | AA17: 0.5 | AB17: 0 | AC17: -3.2 | AD17: 2.2 | AE17: 9.3 | AF17: 1.6 | AJ17: 11.2 | AK17: 17.7 | AL17: 0 | AO17: -1.7 | AP17: 35.8 | AQ17: 3.3 | AR17: 8.8 | AS17: -1.1 | AT17: 0.3 | AU17: 2.7 | AV17: 2.1 | AW17: -3.7 | AX17: -25.4 | AY17: -51.7 | AZ17: 7.6 | BA17: -1 | BB17: 0.6 | BC17: -3.9 | BD17: 7 | BE17: 1 | BF17: -0.1 | BG17: 9.3 | BH17: -0.9 | BK17: 0 | BO17: 8.7 | BQ17: 0 | BY17: -16.2 | CB17: 30.6 | CC17: 23.4 | CD17: -2.9 | CE17: 5.7 | CF17: 0 | CJ17: 15.5 | CL17: -54.5 | CN17: 0 | CU17: -5.6 | CV17: 0 | CY17: 1.5 | CZ17: 0 | DA17: -0.8 | DB17: 0.4 | DC17: 1.7 | DD17: 2.1 | DE17: -0.1 | DF17: 1.8 | DG17: 0.6 | DI17: 0 | DJ17: 0 | DK17: -3.1 | DL17: 3.5 | DM17: 1.5 | DN17: 0.5 | DO17: 0.6 | DP17: 1 | DQ17: 0 | DR17: -0.1 | DS17: 0.3 | DT17: 0 | DV17: -3.7 | DW17: 0.2 | DX17: 2.4 | DY17: 2.1 | DZ17: 1.1 | EA17: 0.8 | EB17: 4 | EC17: 0 | ED17: -0.3 | EE17: -1.6 | EF17: 7.8 | EG17: 8.8 | EH17: 2.4 | EI17: -0.1 | EJ17: 1.2 | EK17: 0.2 | EL17: 0.2 | EM17: 0 | EO17: 0 | EP17: 0 | EQ17: -0.2 | ER17: 0 | ES17: 3.6 | ET17: 0 | EU17: 0 | EV17: 1.6 | EW17: 1.4 | EX17: 2.5 | EY17: 7.8 | EZ17: 8.8 | FA17: 0.7 | FB17: 1.4 | FC17: 2 | FD17: 1.3 | FE17: 3.1 | FF17: 153.1 | FH17: 2.06087 | FK17: 2.766 | FL17: 1.6 | FN17: 0.08248 | FO17: 0.1 | FP17: 1.9 | FQ17: 8.50935
A18: 15/01/2025 | B18: 04:00 | C18: 0.2 | D18: 0 | F18: 19.8 | G18: 19.3 | J18: -13.4 | K18: 19.9 | L18: 0 | M18: 0 | N18: -32.4 | O18: -45.6 | P18: -30.4 | Q18: 36.2 | R18: -14.7 | S18: -3.3 | T18: 73.2 | U18: 0 | Z18: 0.3 | AA18: 1 | AB18: 0 | AC18: -3.1 | AD18: 2.2 | AE18: 9.7 | AF18: 1.6 | AJ18: 11.2 | AK18: 17.5 | AL18: 0 | AO18: -1.7 | AP18: 31.6 | AQ18: 2.9 | AR18: 8.2 | AS18: -1.1 | AT18: 0.1 | AU18: 2.7 | AV18: 1.6 | AW18: -2 | AX18: -23.8 | AY18: -50.6 | AZ18: 6.8 | BA18: -1.1 | BB18: 0.4 | BC18: -6.5 | BD18: 5.9 | BE18: 1 | BF18: -0.1 | BG18: 5.2 | BH18: -0.2 | BK18: 0 | BO18: -0.1 | BQ18: 0 | BY18: -18.5 | CB18: 30.6 | CC18: 22.7 | CD18: -3.1 | CE18: 4.6 | CF18: 0 | CJ18: 15.2 | CL18: -55.3 | CN18: 0 | CU18: -5.4 | CV18: 0 | CY18: 1.4 | CZ18: 0.1 | DA18: -0.9 | DB18: 0.2 | DC18: 1.7 | DD18: 2.1 | DE18: -1 | DF18: 1.8 | DG18: 0.6 | DI18: 0 | DJ18: 0 | DK18: -3.3 | DL18: 3.5 | DM18: 1.5 | DN18: 0.5 | DO18: 0.6 | DP18: 1 | DQ18: 0 | DR18: -0.1 | DS18: 0.5 | DT18: 0 | DV18: -3.6 | DW18: 0.2 | DX18: 2.4 | DY18: 2.1 | DZ18: 1 | EA18: 0.8 | EB18: 4 | EC18: 0 | ED18: -0.5 | EE18: -4 | EF18: 7.8 | EG18: 9 | EH18: 2.4 | EI18: -0.1 | EJ18: 1.2 | EK18: 0.2 | EL18: 0.2 | EM18: 0 | EO18: 0 | EP18: 0 | EQ18: -0.2 | ER18: 0 | ES18: 3.7 | ET18: 0 | EU18: 0 | EV18: 1.6 | EW18: 1.2 | EX18: 2.4 | EY18: 7.8 | EZ18: 9 | FA18: 0.7 | FB18: 1.5 | FC18: 2.3 | FD18: 1.3 | FE18: 2.9 | FF18: 106.7 | FH18: 2.04579 | FK18: 2.664 | FL18: 1.5 | FN18: 0.11249 | FO18: 0.2 | FP18: 1.6 | FQ18: 8.12228
A19: 15/01/2025 | B19: 04:30 | C19: 0.2 | D19: 0 | F19: 40.2 | G19: 22.2 | J19: -12.7 | K19: 29.4 | L19: 0 | M19: 0 | N19: -26.5 | O19: -38.9 | P19: -23.3 | Q19: 40.8 | R19: -12.2 | S19: -2.2 | T19: 77.3 | U19: 0.1 | Z19: 3.1 | AA19: 1 | AB19: 0 | AC19: -3.2 | AD19: 2.3 | AE19: 10 | AF19: 1.6 | AJ19: 11.2 | AK19: 18.1 | AL19: 0 | AO19: -1.6 | AP19: 44.9 | AQ19: 3.2 | AR19: 9.3 | AS19: -1 | AT19: 0 | AU19: 2.7 | AV19: 1.9 | AW19: -3.2 | AX19: -24.9 | AY19: -51.3 | AZ19: 8.5 | BA19: -1 | BB19: 0.3 | BC19: -3.8 | BD19: 8 | BE19: 0.9 | BF19: -0.1 | BG19: 8.9 | BH19: -0.1 | BK19: 0 | BO19: 7.8 | BQ19: 0 | BY19: -12.6 | CB19: 30.5 | CC19: 24 | CD19: -2.4 | CE19: 4.7 | CF19: 0 | CJ19: 17.1 | CL19: -52.3 | CN19: 0 | CU19: -5.2 | CV19: 0 | CY19: 1.5 | CZ19: 0 | DA19: -0.9 | DB19: 0 | DC19: 1.7 | DD19: 2 | DE19: -0.5 | DF19: 1.8 | DG19: 0.6 | DI19: 0 | DJ19: 0 | DK19: -3.3 | DL19: 3.7 | DM19: 1.5 | DN19: 0.5 | DO19: 0.6 | DP19: 1 | DQ19: 0 | DR19: 0 | DS19: 0.5 | DT19: 0 | DV19: -3.7 | DW19: 0.2 | DX19: 2.4 | DY19: 2.1 | DZ19: 1.1 | EA19: 0.8 | EB19: 4 | EC19: 0 | ED19: 0.3 | EE19: 0.2 | EF19: 7.7 | EG19: 9.6 | EH19: 2.4 | EI19: -0.1 | EJ19: 1.3 | EK19: 0.2 | EL19: 0.2 | EM19: 0 | EO19: 0 | EP19: 0 | EQ19: -0.2 | ER19: 0 | ES19: 3.6 | ET19: 0 | EU19: 0 | EV19: 1.6 | EW19: 1.3 | EX19: 2.4 | EY19: 7.7 | EZ19: 9.6 | FA19: 0.7 | FB19: 1.6 | FC19: 3.5 | FD19: 1.3 | FE19: 3.3 | FF19: 227.5 | FH19: 2.21438 | FK19: 2.692 | FL19: 1.6 | FN19: 0.08442 | FO19: 0.2 | FP19: 1.5 | FQ19: 8.2908
A20: 15/01/2025 | B20: 05:00 | C20: 0.2 | D20: 0 | F20: 38.2 | G20: 22.2 | J20: -13 | K20: 24.4 | L20: 0 | M20: 0 | N20: -27.5 | O20: -35.8 | P20: -19.9 | Q20: 41 | R20: -12.6 | S20: -1.5 | T20: 80.2 | U20: 0.1 | Z20: 2.6 | AA20: 1.2 | AB20: 0 | AC20: -3.2 | AD20: 2.4 | AE20: 10.4 | AF20: 1.7 | AJ20: 11.7 | AK20: 18.2 | AL20: 0 | AO20: -1.6 | AP20: 45.7 | AQ20: 3.9 | AR20: 8.7 | AS20: -1.3 | AT20: 0.2 | AU20: 2.7 | AV20: 1.2 | AW20: -2.6 | AX20: -24.4 | AY20: -50.7 | AZ20: 10 | BA20: -1 | BB20: 0.4 | BC20: -2.3 | BD20: 8.1 | BE20: 1 | BF20: -0.1 | BG20: 11.1 | BH20: 0.4 | BK20: 0 | BO20: 7.4 | BQ20: 0 | BY20: -10.9 | CB20: 30.5 | CC20: 23.8 | CD20: -2.9 | CE20: 4.7 | CF20: 0.1 | CJ20: 18.1 | CL20: -50.6 | CN20: 0 | CU20: -4.9 | CV20: 0 | CY20: 1.5 | CZ20: 0 | DA20: -0.9 | DB20: 0 | DC20: 1.6 | DD20: 2.1 | DE20: -0.9 | DF20: 1.8 | DG20: 0.6 | DI20: 0 | DJ20: 0 | DK20: -3.5 | DL20: 2.9 | DM20: 1.5 | DN20: 0.5 | DO20: 0.6 | DP20: 1 | DQ20: 0.4 | DR20: 0.1 | DS20: 0.5 | DT20: 0 | DV20: -3.8 | DW20: 0.2 | DX20: 2.5 | DY20: 2.1 | DZ20: 1.1 | EA20: 0.8 | EB20: 4 | EC20: 0.4 | ED20: 0 | EE20: -1.7 | EF20: 7.8 | EG20: 10.3 | EH20: 2.5 | EI20: -0.1 | EJ20: 1.3 | EK20: 0.2 | EL20: 0.2 | EM20: 0 | EO20: 0 | EP20: 0 | EQ20: -0.2 | ER20: 0 | ES20: 3.6 | ET20: 0 | EU20: 0 | EV20: 1.6 | EW20: 1.4 | EX20: 2.4 | EY20: 7.8 | EZ20: 10.3 | FA20: 0.8 | FB20: 1.6 | FC20: 3.4 | FD20: 1.6 | FE20: 3.3 | FF20: 240.9 | FH20: 2.19709 | FK20: 2.418 | FL20: 1.5 | FN20: 0.074 | FO20: 0.3 | FP20: 1.4 | FQ20: 7.88909
A21: 15/01/2025 | B21: 05:30 | C21: 0.2 | D21: 0 | F21: 13.9 | G21: 18.4 | J21: -13.1 | K21: 13.2 | L21: 0 | M21: 0 | N21: -29.5 | O21: -44 | P21: -28.9 | Q21: 38.2 | R21: -13.7 | S21: -2.6 | T21: 70.7 | U21: 0 | Z21: -0.5 | AA21: 1.3 | AB21: 0 | AC21: -3.3 | AD21: 2 | AE21: 8.6 | AF21: 1.3 | AJ21: 9.9 | AK21: 18.3 | AL21: 0 | AO21: -1.6 | AP21: 35.3 | AQ21: 3.3 | AR21: 8.6 | AS21: -1 | AT21: 0 | AU21: 2.7 | AV21: 1.1 | AW21: -1 | AX21: -22.6 | AY21: -49.2 | AZ21: 8.9 | BA21: -0.8 | BB21: 0.3 | BC21: -4.9 | BD21: 6.1 | BE21: 1 | BF21: -0.1 | BG21: 4.2 | BH21: -0.2 | BK21: 0 | BO21: 3.9 | BQ21: 0 | BY21: -16 | CB21: 30.5 | CC21: 25 | CD21: -2.9 | CE21: 4.5 | CF21: -0.1 | CJ21: 17.7 | CL21: -51.5 | CN21: 0 | CU21: -4.8 | CV21: 0 | CY21: 1.4 | CZ21: -0.1 | DA21: -0.8 | DB21: 0 | DC21: 1.5 | DD21: 2.1 | DE21: -0.4 | DF21: 1.8 | DG21: 0.6 | DI21: 0 | DJ21: 0 | DK21: -3.9 | DL21: 1.9 | DM21: 1.5 | DN21: 0.5 | DO21: 0.6 | DP21: 1 | DQ21: 0.3 | DR21: -0.1 | DS21: 0.5 | DT21: 0 | DV21: -3.9 | DW21: 0.2 | DX21: 2.4 | DY21: 2.1 | DZ21: 1.1 | EA21: 0.8 | EB21: 4 | EC21: 0.3 | ED21: -2.9 | EE21: -6 | EF21: 7.8 | EG21: 11.3 | EH21: 2.5 | EI21: -0.1 | EJ21: 1.1 | EK21: 0.2 | EL21: 0.2 | EM21: 0 | EO21: 0 | EP21: -0.1 | EQ21: -0.2 | ER21: 0 | ES21: 3.7 | ET21: 1.2 | EU21: 0 | EV21: 1.6 | EW21: 1.4 | EX21: 2.4 | EY21: 7.8 | EZ21: 11.3 | FA21: 0.7 | FB21: 1.7 | FC21: 3.6 | FD21: 2.3 | FE21: 3.3 | FF21: 127 | FH21: 2.11966 | FK21: 2.158 | FL21: 1.7 | FN21: 0.06711 | FO21: 0.4 | FP21: 1.5 | FQ21: 7.94477
A22: 15/01/2025 | B22: 06:00 | C22: 0.2 | D22: 0 | F22: 18.7 | G22: 19.1 | J22: -12.8 | K22: 18.1 | L22: 0 | M22: 0 | N22: -29.2 | O22: -43.6 | P22: -28.2 | Q22: 39.7 | R22: -14.3 | S22: -2.4 | T22: 72.8 | U22: 0 | Z22: 0.5 | AA22: 0.9 | AB22: 0 | AC22: -3.3 | AD22: 2 | AE22: 7.4 | AF22: 1.3 | AJ22: 10.1 | AK22: 17.6 | AL22: 0 | AO22: -1.7 | AP22: 19.3 | AQ22: 4 | AR22: 8.4 | AS22: -0.5 | AT22: 0.3 | AU22: 2.7 | AV22: 1.2 | AW22: -0.3 | AX22: -22 | AY22: -49.1 | AZ22: 7.6 | BA22: -0.9 | BB22: 0.5 | BC22: -4.2 | BD22: 6.4 | BE22: 1 | BF22: -0.1 | BG22: 7.8 | BH22: 0.5 | BK22: 0 | BO22: 0.3 | BQ22: 0 | BY22: -16.8 | CB22: 31 | CC22: 24.1 | CD22: -3.3 | CE22: 4.8 | CF22: 0.1 | CJ22: 16.6 | CL22: -52.9 | CN22: 0 | CU22: -5 | CV22: 2.6 | CY22: 1.4 | CZ22: 0 | DA22: -0.8 | DB22: 0 | DC22: 1.6 | DD22: 2.1 | DE22: 0.4 | DF22: 1.8 | DG22: 0.6 | DI22: -0.3 | DJ22: -0.3 | DK22: -3.9 | DL22: 2 | DM22: 1.5 | DN22: 0.5 | DO22: 0.6 | DP22: 1 | DQ22: -0.7 | DR22: -0.1 | DS22: 0.3 | DT22: 0 | DV22: -3.8 | DW22: 0.2 | DX22: 2.4 | DY22: 2.1 | DZ22: 1.1 | EA22: 0.8 | EB22: 4 | EC22: -0.1 | ED22: -1.2 | EE22: -2.5 | EF22: 7.8 | EG22: 11.4 | EH22: 2.4 | EI22: -0.1 | EJ22: 1.1 | EK22: 0.2 | EL22: 0.2 | EM22: 0 | EO22: 0 | EP22: 0.4 | EQ22: -0.2 | ER22: 0 | ES22: 3.7 | ET22: 1.1 | EU22: 0 | EV22: 1.6 | EW22: 1.4 | EX22: 2.4 | EY22: 7.8 | EZ22: 11.4 | FA22: 0.8 | FB22: 1.3 | FC22: 0.6 | FD22: 2 | FE22: 3.6 | FF22: 128.6 | FH22: 2.10271 | FK22: 2.164 | FL22: 1.7 | FN22: 0.11351 | FO22: 0.6 | FP22: 1.7 | FQ22: 8.38022
... A58: 16/01/2025 | B58: 00:00 | C58: 0.2 | D58: 0.1 | F58: 26.8 | G58: 18.9 | J58: -12.5 | K58: 16.7 | L58: -0.2 | M58: 2.6 | N58: -36.4 | O58: -38.1 | P58: -2.9 | Q58: 17.2 | R58: -34.6 | S58: -29 | T58: 71.1 | U58: 0.1 | Z58: -2.1 | AA58: 0.9 | AB58: 0 | AC58: -3.5 | AD58: 2.8 | AE58: 9.1 | AF58: 2 | AJ58: 11.5 | AK58: 12.6 | AL58: -2.6 | AO58: -1.5 | AP58: 44.5 | AQ58: 2.4 | AR58: 14 | AS58: 2 | AT58: 0.2 | AU58: 2.7 | AV58: 1.4 | AW58: 7.3 | AX58: -18.2 | AY58: -56.7 | AZ58: 7.9 | BA58: -1.1 | BB58: 0.7 | BC58: -1.5 | BD58: 6.2 | BE58: 0.9 | BF58: -0.1 | BG58: 11.2 | BH58: 4.3 | BK58: -4 | BO58: 9.4 | BQ58: 0 | BY58: -10.3 | CB58: 41 | CC58: 27.5 | CD58: 3 | CE58: 5.5 | CF58: -2 | CJ58: 51 | CL58: -15.9 | CN58: 14.4 | CU58: 0 | CV58: 0 | CY58: 1.4 | CZ58: 0 | DA58: -0.8 | DB58: -0.2 | DC58: 1.7 | DD58: 1.8 | DE58: -1.2 | DF58: 0.1 | DG58: 0.5 | DI58: 0 | DJ58: 0 | DK58: -6.2 | DL58: -28.5 | DM58: 1.5 | DN58: 0.5 | DO58: 0.6 | DP58: 1 | DQ58: 0 | DR58: -0.2 | DS58: 0.3 | DT58: 0.2 | DV58: -2.9 | DW58: 0.2 | DX58: 2.6 | DY58: 2.4 | DZ58: 1.1 | EA58: 0.8 | EB58: 4 | EC58: 0 | ED58: -5.4 | EE58: -5.6 | EF58: 9.7 | EG58: 11.4 | EH58: 2.4 | EI58: -0.1 | EJ58: 1.1 | EK58: 0.2 | EL58: 0.2 | EM58: 0.1 | EO58: 0 | EP58: 0 | EQ58: -0.2 | ER58: -6.6 | ES58: 2.9 | ET58: 0 | EU58: 0 | EV58: 0.8 | EW58: 1.4 | EX58: 2.6 | EY58: 9.7 | EZ58: 11.4 | FA58: 0.7 | FB58: 1.2 | FC58: 1 | FD58: 0.6 | FE58: 3.5 | FF58: 200.6 | FH58: 1.99927 | FK58: 2.674 | FL58: 1.4 | FN58: 0.23048 | FO58: 0.3 | FP58: 0.8 | FQ58: 7.40375
A59: EJEC | C59: 2.75 | D59: 0.1 | E59: 0 | F59: 1476.1 | G59: 669 | H59: 0 | I59: 0 | J59: -203.5 | K59: 538.45 | L59: -6.75 | M59: 7.1 | N59: 132.8 | O59: 62.6 | P59: 220.65 | Q59: 937.55 | R59: -330.6 | S59: -155.65 | T59: 1472.05 | U59: 0.9 | V59: 0 | W59: 0 | X59: 0 | Y59: 0 | Z59: 9.95 | AA59: 19.2 | AB59: 15.45 | AC59: -79.1 | AD59: 69.3 | AE59: 334.95 | AF59: 51.75 | AG59: 0 | AH59: 0 | AI59: 0 | AJ59: 360.75 | AK59: 468.6 | AL59: -1.3 | AM59: 0 | AN59: 0 | AO59: -32.1 | AP59: 958.9 | AQ59: 78.35 | AR59: 294.8 | AS59: 0.3 | AT59: 4.2 | AU59: 64.8 | AV59: 30.7 | AW59: 463.05 | AX59: -56.5 | AY59: -850.9 | AZ59: 217.3 | BA59: -27.6 | BB59: 8.9 | BC59: -51.2 | BD59: 167.55 | BE59: 22.75 | BF59: 0.15 | BG59: 201.4 | BH59: 81.15 | BI59: 0 | BJ59: 0 | BK59: -23.1 | BL59: 0 | BM59: 0 | BN59: 0 | BO59: 181 | BP59: 0 | BQ59: -21.35 | BR59: 0 | BS59: 0 | BT59: 0 | BU59: 0 | BV59: 0 | BW59: 0 | BX59: 0 | BY59: -243.25 | BZ59: 0 | CA59: 0 | CB59: 1279.8 | CC59: 936.9 | CD59: 124.95 | CE59: 275.35 | CF59: 36.4 | CG59: 0 | CH59: 0 | CI59: 0 | CJ59: 1158.55 | CK59: 0 | CL59: -404 | CM59: 0 | CN59: 7.2 | CO59: 0 | CP59: 0 | CQ59: 0 | CR59: 0 | CS59: 0 | CT59: 0 | CU59: -81.55 | CV59: 85.55 | CW59: 0 | CX59: 0 | CY59: 33.95 | CZ59: -0.5 | DA59: -20.85 | DB59: -1.9 | DC59: 32.5 | DD59: 54.25 | DE59: 6.75 | DF59: 39.7 | DG59: 14 | DH59: 0 | DI59: -8.2 | DJ59: -22.25 | DK59: -111.2 | DL59: -109.15 | DM59: 36.35 | DN59: 12.15 | DO59: 13.55 | DP59: 22.95 | DQ59: -34.5 | DR59: -0.15 | DS59: 9.75 | DT59: 0.5 | DU59: 0 | DV59: -79.25 | DW59: 4.8 | DX59: 59.65 | DY59: 61.7 | DZ59: 33.9 | EA59: 19.2 | EB59: 95.9 | EC59: 29.2 | ED59: -119 | EE59: -138.05 | EF59: 190.9 | EG59: 233.1 | EH59: 58.1 | EI59: -1.55 | EJ59: 30.05 | EK59: 4.8 | EL59: 4.8 | EM59: 1.2 | EN59: 0 | EO59: 8.65 | EP59: 112.4 | EQ59: -4.7 | ER59: 4.8 | ES59: 57.95 | ET59: -42.3 | EU59: 14.95 | EV59: 33.1 | EW59: 41.65 | EX59: 60.85 | EY59: 190.9 | EZ59: 233.1 | FA59: 18.3 | FB59: 36.85 | FC59: 68.85 | FD59: 24.85 | FE59: 83.15 | FF59: 12362.05 | FH59: 50.455465 | FI59: 0 | FJ59: 0 | FK59: 62.384 | FL59: 36.65 | FM59: 0 | FN59: 30.88808 | FO59: 5.8 | FP59: 42.85 | FQ59: 229.02755

Sheet DEMANDA_AREAS
B3: miércoles, 15 de Enero del 2025
B5: REPORTE DE LA DEMANDA POR ÁREAS Y SUBAREAS OPERATIVAS (MW)
B6: FECHA HORA | C6: DEMANDA | E6: AREA | H6: SUBAREAS
C7: INTERCAMBIOS INTERNACIONALES | D7: SEIN | E7: NORTE | F7: CENTRO | G7: SUR | H7: ELECTROANDES
B8: 00:30 | C8: 0 | D8: 6638.7 | E8: 993.861 | F8: 3994.219 | G8: 1650.62 | H8: 210.81
B9: 01:00 | C9: 0 | D9: 6427 | E9: 997.71 | F9: 3797.6 | G9: 1631.69 | H9: 212.854
B10: 01:30 | C10: 0 | D10: 6450 | E10: 973.312 | F10: 3860.838 | G10: 1615.85 | H10: 216.739
B11: 02:00 | C11: 0 | D11: 6326.1 | E11: 929.575 | F11: 3779.165 | G11: 1617.36 | H11: 220.805
B12: 02:30 | C12: 0 | D12: 6306.2 | E12: 952.735 | F12: 3730.345 | G12: 1623.12 | H12: 212.464
B13: 03:00 | C13: 0 | D13: 6283.1 | E13: 957.114 | F13: 3698.566 | G13: 1627.42 | H13: 212.683
B14: 03:30 | C14: 0 | D14: 6251.4 | E14: 924.854 | F14: 3701.696 | G14: 1624.85 | H14: 208.873
B15: 04:00 | C15: 0 | D15: 6190.9 | E15: 964.622 | F15: 3583.148 | G15: 1643.13 | H15: 215.332
B16: 04:30 | C16: 0 | D16: 6307.5 | E16: 961.89 | F16: 3703.88 | G16: 1641.73 | H16: 208.118
B17: 05:00 | C17: 0 | D17: 6317 | E17: 964.687 | F17: 3700.543 | G17: 1651.77 | H17: 208.045
B18: 05:30 | C18: 0 | D18: 6236.1 | E18: 949.463 | F18: 3639.157 | G18: 1647.48 | H18: 204.586
B19: 06:00 | C19: 0 | D19: 6314.5 | E19: 977.998 | F19: 3706.162 | G19: 1630.34 | H19: 202.731
... B59: ENERGÍA | C59: 0 | D59: 167895.2 | E59: 26793.019 | F59: 101128.7 | G59: 39973.485 | H59: 4675.296
B61: LEYENDA:
D63: Potencia recibida del Ecuador
D64: Potencia entregada al Ecuador

Sheet DEMANDA_UL
B3: miércoles, 15 de Enero del 2025
B5: POTENCIA DE LOS GRANDES USUARIOS LIBRES (MW)
B6: FECHA HORA | C6: GRANDES USUARIOS LIBRES DEL ÁREA NORTE | X6: GRANDES USUARIOS LIBRES DEL ÁREA CENTRO | BP6: GRANDES USUARIOS LIBRES DEL ÁREA SUR
C7: ARCA CONTINENTAL LINDLEY S.A. | D7: AUSTRAL GROUP S.A.A | E7: CEMENTOS PACASMAYO | F7: CORPORACIÓN PESQUERA INCA S.A.C. | G7: CREDITEX: CIA IND.TEXTIL CREDISA | H7: HIPERMERCADOS TOTTUS S.A | I7: INDUSTRIA TEXTIL PIURA | J7: MINERA BOROO MISQUICHILCA S.A. | K7: MINERA GOLD FIELDS | L7: MINERA HORIZONTE | M7: MINERA MARSA | N7: MINERA MISKY MAYO | O7: MINERA YANACOCHA | P7: OPEN PLAZA | Q7: PESQUERA DIAMANTE | R7: PETROPERU | S7: REAL PLAZA S.R.L. | T7: SIDER PERU | U7: SUPERMERCADOS PERUANOS S.A. | V7: TRUPAL S.A. | W7: UNIÓN DE CERVECERÍAS PERUANAS BACKUS Y JOHNSTON S. | X7: ACEROS AREQUIPA | Y7: ADMINISTRADORA JOCKEY PLAZA SHOPPING CENTER S.A. | Z7: ALICORP | AA7: ARCA CONTINENTAL LINDLEY S.A. | AB7: AUSTRAL GROUP S.A.A | AC7: COMPAÑIA MINERA CONDESTABLE | AD7: CORPORACIÓN PESQUERA INCA S.A.C. | AE7: CREDITEX: CIA IND.TEXTIL CREDISA | AF7: FUNDICION CHILCA S.A. | AG7: HIPERMERCADOS TOTTUS S.A | AH7: INMOBILIARIA KANPU S.A. | AI7: INMUEBLES PANAMERICANA S.A. | AJ7: KIMBERLY-CLARK PERU | AK7: LECHE GLORIA S.A. | AL7: MALL AVENTURA S.A. | AM7: MARCOBRE S.A.C. | AN7: MINERA ANTAMINA | AO7: MINERA ARES | AP7: MINERA BUENAVENTURA | AQ7: MINERA CHINALCO PERÚ S.A. | AR7: MINERA SHOUXIN PERU S.A. | AS7: MINERA VOLCAN | AT7: MINSUR | AU7: MOLYCOP-ADESUR | AV7: NEXA RESOURCES CAJAMARQUILLA S.A. | AW7: NEXA RESOURCES PERÚ S.A.A. | AX7: OPEN PLAZA | AY7: OPP FILM | AZ7: OWENS-ILLINOIS PERÚ S.A. | BA7: PAPELERA NACIONAL S.A. | BB7: PESQUERA DIAMANTE | BC7: QUIMPAC S.A. | BD7: REAL PLAZA S.R.L. | BE7: REFINERIA LA PAMPILLA S.A.A | BF7: SAGA FALABELLA | BG7: SAN MIGUEL INDUSTRIAS PET S.A. | BH7: SHOUGANG HIERRO PERU | BI7: SOFTYS PERU S.A.C. | BJ7: SUPERMERCADOS PERUANOS S.A. | BK7: TEJIDOS SAN JACINTO | BL7: TREN URBANO DE LIMA S.A. | BM7: TRUPAL S.A. | BN7: UNACEM PERU S.A. | BO7: UNIÓN DE CERVECERÍAS PERUANAS BACKUS Y JOHNSTON S. | BP7: ANGLO AMERICAN QUELLAVECO S.A. | BQ7: ARCA CONTINENTAL LINDLEY S.A. | BR7: CAL & CEMENTO SUR S.A. | BS7: COMPAÑIA MINERA ANTAPACCAY S.A. | BT7: COMPAÑÍA MINERA CHUNGAR SAC | BU7: COMPAÑIA MINERA SAN IGNACIO DE MOROCOCHA S.A.A. | BV7: EL BROCAL .S.A. | BW7: EMPRESA ADMINISTRADORA CERRO S.A.C. | BX7: EMPRESA MINERA LOS QUENUALES S.A.C. | BY7: HIPERMERCADOS TOTTUS S.A | BZ7: HUDBAY PERU S.A.C. | CA7: INDUSTRIA CACHIMAYO | CB7: MALL AVENTURA S.A. | CC7: MINERA ARES | CD7: MINERA BUENAVENTURA | CE7: MINERA CERRO VERDE | CF7: MINERA CORONA | CG7: MINERA LAS BAMBAS S.A. | CH7: MINERA VOLCAN | CI7: MINSUR | CJ7: MOLYCOP-ADESUR | CK7: NEXA RESOURCES PERÚ S.A.A. | CL7: OXIDOS DE PASCO S.A.C. | CM7: PESQUERA DIAMANTE | CN7: REAL PLAZA S.R.L. | CO7: SOBREANDES S.A.C. | CP7: SOUTHERN PERU CC | CQ7: SUPERMERCADOS PERUANOS S.A. | CR7: UNACEM PERU S.A. | CS7: UNIÓN DE CERVECERÍAS PERUANAS BACKUS Y JOHNSTON S. | CT7: YURA
B8: 00:30 | E8: 32.51386 | J8: 20.6124 | K8: 26.3458 | L8: 11.708 | M8: 12.8552 | N8: 13.6 | O8: 34.182 | R8: 51.907 | T8: 25.73552 | V8: 9 | X8: 96.33927 | Z8: 10.00626 | AC8: 14.17 | AF8: 2 | AH8: 7.1126 | AJ8: 5.33786 | AK8: 0 | AL8: 1.3454 | AM8: 42.6977 | AN8: 103.0827 | AO8: 25.9824 | AP8: 0.81 | AQ8: 151.9929 | AS8: 35.38077 | AT8: 29.48529 | AV8: 188.06669 | AW8: 28.7534 | AY8: 3.18033 | BA8: 5.3 | BC8: 46.67606 | BE8: 19.3 | BK8: 5.46216 | BM8: 7.218 | BN8: 42.63 | BP8: 140.58885 | BR8: 4.03639 | BS8: 126.75335 | BT8: 11.43438 | BW8: 3.85819 | BZ8: 85.25309 | CA8: 22.358 | CB8: 0.4467 | CC8: 0.86318 | CD8: 27.3711 | CE8: 355.1128 | CF8: 11.7608 | CG8: 158.106 | CH8: 17.76901 | CK8: 13.9928 | CL8: 4.80962 | CO8: 15.33264 | CP8: 273.57 | CR8: 36.839 | CT8: 11.61168
B9: 01:00 | E9: 32.75879 | J9: 20.2238 | K9: 26.2242 | L9: 11.222 | M9: 13.0935 | N9: 13.75 | O9: 34.818 | R9: 51.669 | T9: 44.54068 | V9: 9.1 | X9: 129.79677 | Z9: 9.55928 | AC9: 15.36 | AF9: 4.5 | AH9: 7.8533 | AJ9: 5.33431 | AK9: 0 | AL9: 1.237 | AM9: 42.8717 | AN9: 102.76023 | AO9: 26.3353 | AP9: 0.7 | AQ9: 157.4104 | AS9: 34.9574 | AT9: 29.24118 | AV9: 190.68558 | AW9: 29.1694 | AY9: 3.19735 | BA9: 5.4 | BC9: 46.75995 | BE9: 19.3 | BK9: 5.35935 | BM9: 7.393 | BN9: 41.91 | BP9: 139.83658 | BR9: 4.47181 | BS9: 127.55465 | BT9: 11.50728 | BW9: 3.96348 | BZ9: 85.35052 | CA9: 22.258 | CB9: 0.4011 | CC9: 0.8462 | CD9: 27.98295 | CE9: 354.40757 | CF9: 11.8014 | CG9: 144.794 | CH9: 17.96587 | CK9: 14.7223 | CL9: 4.74342 | CO9: 16.23573 | CP9: 274.41 | CR9: 36.809 | CT9: 12.27225
B10: 01:30 | E10: 33.2337 | J10: 20.5102 | K10: 25.3177 | L10: 11.67 | M10: 14.0808 | N10: 13.79 | O10: 34.512 | R10: 51.778 | T10: 32.85866 | V10: 8.8 | X10: 136.75764 | Z10: 9.59677 | AC10: 15.53 | AF10: 2.8 | AH10: 6.4412 | AJ10: 5.31128 | AK10: 0 | AL10: 1.1495 | AM10: 45.7495 | AN10: 102.80167 | AO10: 26.5752 | AP10: 0.64 | AQ10: 155.7942 | AS10: 35.90215 | AT10: 29.42164 | AV10: 193.76601 | AW10: 30.029 | AY10: 3.1765 | BA10: 5.2 | BC10: 46.58891 | BE10: 19.3 | BK10: 5.48073 | BM10: 7.513 | BN10: 41.4 | BP10: 139.50966 | BR10: 4.44934 | BS10: 125.66166 | BT10: 11.33194 | BW10: 4.0073 | BZ10: 86.91909 | CA10: 22.30628 | CB10: 0.3824 | CC10: 0.82735 | CD10: 28.85493 | CE10: 341.97557 | CF10: 11.5269 | CG10: 152.583 | CH10: 18.27414 | CK10: 14.8029 | CL10: 5.0023 | CO10: 15.35184 | CP10: 276.16 | CR10: 36.129 | CT10: 15.50846
B11: 02:00 | E11: 33.59933 | J11: 19.5996 | K11: 24.6342 | L11: 11.634 | M11: 14.0608 | N11: 13.75 | O11: 34.944 | R11: 51.744 | T11: 37.96295 | V11: 8.7 | X11: 136.13131 | Z11: 9.52842 | AC11: 15.33 | AF11: 1.7 | AH11: 6.2958 | AJ11: 5.27359 | AK11: 0 | AL11: 1.0664 | AM11: 44.976 | AN11: 101.59607 | AO11: 27.2315 | AP11: 0.44 | AQ11: 152.1622 | AS11: 35.17277 | AT11: 29.08708 | AV11: 193.30984 | AW11: 30.6761 | AY11: 3.16191 | BA11: 5.1 | BC11: 46.45962 | BE11: 19.3 | BK11: 5.37785 | BM11: 7.404 | BN11: 41.64 | BP11: 138.82608 | BR11: 4.28467 | BS11: 125.57002 | BT11: 11.29149 | BW11: 3.7307 | BZ11: 88.65559 | CA11: 22.358 | CB11: 0.3638 | CC11: 0.86054 | CD11: 29.88548 | CE11: 326.12671 | CF11: 11.5424 | CG11: 156.283 | CH11: 17.98924 | CK11: 14.9934 | CL11: 4.92817 | CO11: 15.82818 | CP11: 272.41 | CR11: 36.283 | CT11: 17.26916
B12: 02:30 | E12: 34.5545 | J12: 19.6342 | K12: 25.0588 | L12: 12.075 | M12: 14.4456 | N12: 13.57 | O12: 34.9 | R12: 52.094 | T12: 40.83983 | V12: 8.6 | X12: 130.02801 | Z12: 9.74284 | AC12: 15.3 | AF12: 2.4 | AH12: 6.0667 | AJ12: 5.22184 | AK12: 0 | AL12: 1.0611 | AM12: 45.5909 | AN12: 109.39203 | AO12: 27.09 | AP12: 0.41 | AQ12: 153.9251 | AS12: 36.27226 | AT12: 29.39431 | AV12: 190.76485 | AW12: 32.8878 | AY12: 3.17184 | BA12: 5.1 | BC12: 46.58046 | BE12: 19.3 | BK12: 5.27836 | BM12: 7.496 | BN12: 42.77 | BP12: 136.99972 | BR12: 4.35426 | BS12: 125.76637 | BT12: 8.95407 | BW12: 3.87202 | BZ12: 88.46673 | CA12: 22.36981 | CB12: 0.3549 | CC12: 0.82476 | CD12: 29.61755 | CE12: 349.02637 | CF12: 11.8424 | CG12: 152.495 | CH12: 18.30588 | CK12: 14.2975 | CL12: 4.88672 | CO12: 16.31069 | CP12: 273.84 | CR12: 36.264 | CT12: 15.09252
B13: 03:00 | E13: 38.59807 | J13: 19.407 | K13: 26.1051 | L13: 11.892 | M13: 14.2251 | N13: 13.1 | O13: 35.07 | R13: 52.179 | T13: 38.5181 | V13: 8.6 | X13: 107.01105 | Z13: 9.57253 | AC13: 15.42 | AF13: 4.8 | AH13: 3.5625 | AJ13: 4.81592 | AK13: 0 | AL13: 1.0353 | AM13: 45.4726 | AN13: 115.50889 | AO13: 26.9166 | AP13: 0.67 | AQ13: 151.3883 | AS13: 35.23838 | AT13: 29.18765 | AV13: 192.9308 | AW13: 33.6395 | AY13: 3.17074 | BA13: 4.8 | BC13: 46.54243 | BE13: 19.3 | BK13: 5.42971 | BM13: 7.56 | BN13: 42.67 | BP13: 139.22319 | BR13: 4.28328 | BS13: 125.65994 | BT13: 11.46 | BW13: 3.96593 | BZ13: 89.63578 | CA13: 22.384 | CB13: 0.3285 | CC13: 0.83782 | CD13: 29.2342 | CE13: 350.65195 | CF13: 11.7299 | CG13: 154.136 | CH13: 18.33496 | CK13: 13.9386 | CL13: 4.63075 | CO13: 15.9426 | CP13: 284.31 | CR13: 36.311 | CT13: 13.26572
B14: 03:30 | E14: 38.54392 | J14: 18.2723 | K14: 26.2389 | L14: 11.997 | M14: 13.8694 | N14: 13.18 | O14: 34.662 | R14: 51.744 | T14: 29.80148 | V14: 8.5 | X14: 121.84191 | Z14: 9.50471 | AC14: 15.22 | AF14: 4.9 | AH14: 3.3836 | AJ14: 5.05719 | AK14: 0 | AL14: 1.014 | AM14: 45.4198 | AN14: 115.28629 | AO14: 25.9167 | AP14: 0.48 | AQ14: 152.0319 | AS14: 36.24363 | AT14: 29.47982 | AV14: 193.4073 | AW14: 32.3388 | AY14: 3.1742 | BA14: 4.5 | BC14: 46.569 | BE14: 19.3 | BK14: 5.34687 | BM14: 7.607 | BN14: 42.33 | BP14: 134.19614 | BR14: 4.4149 | BS14: 127.22945 | BT14: 11.73373 | BW14: 4.02736 | BZ14: 89.12445 | CA14: 22.3918 | CB14: 0.3112 | CC14: 0.87292 | CD14: 28.47391 | CE14: 349.04461 | CF14: 11.7448 | CG14: 155.308 | CH14: 17.44434 | CK14: 14.5054 | CL14: 4.6157 | CO14: 16.2403 | CP14: 271.89 | CR14: 35.726 | CT14: 16.91718
B15: 04:00 | E15: 38.18482 | J15: 18.7819 | K15: 26.8965 | L15: 10.072 | M15: 14.4252 | N15: 13.34 | O15: 34.02 | R15: 51.869 | T15: 39.93362 | V15: 8.4 | X15: 154.96445 | Z15: 9.76151 | AC15: 15.03 | AF15: 3.2 | AH15: 8.1992 | AJ15: 5.19055 | AK15: 0 | AL15: 1.0016 | AM15: 43.6718 | AN15: 106.82963 | AO15: 26.2295 | AP15: 0.18 | AQ15: 152.1376 | AS15: 36.62595 | AT15: 28.32601 | AV15: 192.71065 | AW15: 32.616 | AY15: 3.13777 | BA15: 5 | BC15: 46.6343 | BE15: 19.3 | BK15: 5.35135 | BM15: 7.489 | BN15: 43.17 | BP15: 138.08546 | BR15: 4.32259 | BS15: 130.12893 | BT15: 11.60185 | BW15: 3.88656 | BZ15: 87.1871 | CA15: 22.4102 | CB15: 0.2942 | CC15: 0.91129 | CD15: 28.34933 | CE15: 353.37055 | CF15: 11.878 | CG15: 152.963 | CH15: 17.81678 | CK15: 14.6322 | CL15: 4.66955 | CO15: 17.04712 | CP15: 276.75 | CR15: 35.671 | CT15: 17.33997
B16: 04:30 | E16: 37.64161 | J16: 19.2923 | K16: 26.5931 | L16: 11.112 | M16: 14.6656 | N16: 13.25 | O16: 33.88 | R16: 51.766 | T16: 44.12249 | V16: 8.2 | X16: 144.85803 | Z16: 9.86471 | AC16: 14.69 | AF16: 2.3 | AH16: 5.1954 | AJ16: 5.28152 | AK16: 0 | AL16: 0.9999 | AM16: 44.369 | AN16: 103.86494 | AO16: 26.3501 | AP16: 1.65 | AQ16: 117.5285 | AS16: 35.70046 | AT16: 27.76746 | AV16: 192.14023 | AW16: 32.2343 | AY16: 3.13586 | BA16: 5.6 | BC16: 46.53148 | BE16: 19.3 | BK16: 5.42608 | BM16: 7.555 | BN16: 45.78 | BP16: 142.38682 | BR16: 4.28525 | BS16: 129.00165 | BT16: 11.155 | BW16: 3.90366 | BZ16: 87.53338 | CA16: 22.37523 | CB16: 0.2908 | CC16: 0.87649 | CD16: 27.84062 | CE16: 353.00821 | CF16: 11.9245 | CG16: 149.366 | CH16: 17.89139 | CK16: 14.1373 | CL16: 4.61793 | CO16: 16.87215 | CP16: 282.66 | CR16: 36.169 | CT16: 17.62525
B17: 05:00 | E17: 37.54175 | J17: 20.6888 | K17: 26.7495 | L17: 10.446 | M17: 14.377 | N17: 13.62 | O17: 34.15 | R17: 51.921 | T17: 22.94188 | V17: 8.1 | X17: 140.54645 | Z17: 9.99026 | AC17: 14.76 | AF17: 1.6 | AH17: 6.9258 | AJ17: 5.03627 | AK17: 0 | AL17: 0.9941 | AM17: 44.6616 | AN17: 103.54589 | AO17: 25.7602 | AP17: 2.1 | AQ17: 105.1246 | AS17: 34.74729 | AT17: 27.86136 | AV17: 192.81696 | AW17: 31.6186 | AY17: 3.106 | BA17: 5.4 | BC17: 46.40072 | BE17: 19.3 | BK17: 5.23109 | BM17: 7.464 | BN17: 46.26 | BP17: 140.18082 | BR17: 4.34155 | BS17: 129.39979 | BT17: 11.29859 | BW17: 4.37541 | BZ17: 87.5568 | CA17: 22.358 | CB17: 0.2865 | CC17: 0.82065 | CD17: 27.65726 | CE17: 353.91115 | CF17: 11.627 | CG17: 144.499 | CH17: 17.25753 | CK17: 14.1344 | CL17: 4.56239 | CO17: 16.01844 | CP17: 283 | CR17: 36.304 | CT17: 17.59689
B18: 05:30 | E18: 37.53384 | J18: 21.1218 | K18: 26.7436 | L18: 9.975 | M18: 14.5618 | N18: 13.77 | O18: 34.198 | R18: 52.206 | T18: 39.22454 | V18: 8.3 | X18: 124.8617 | Z18: 9.75989 | AC18: 14.82 | AF18: 2 | AH18: 7.756 | AJ18: 5.08865 | AK18: 0 | AL18: 0.9983 | AM18: 44.4848 | AN18: 103.2723 | AO18: 25.3824 | AP18: 1.93 | AQ18: 98.9091 | AS18: 33.51449 | AT18: 27.94258 | AV18: 192.06561 | AW18: 31.2485 | AY18: 3.1061 | BA18: 5.4 | BC18: 46.55071 | BE18: 19.3 | BK18: 5.21748 | BM18: 7.535 | BN18: 46.62 | BP18: 140.12155 | BR18: 4.1717 | BS18: 128.11173 | BT18: 11.10191 | BW18: 3.85894 | BZ18: 88.49262 | CA18: 22.36808 | CB18: 0.305 | CC18: 0.92077 | CD18: 26.26093 | CE18: 349.14801 | CF18: 11.0993 | CG18: 153.076 | CH18: 18.25067 | CK18: 14.5824 | CL18: 4.59216 | CO18: 14.81672 | CP18: 285.33 | CR18: 36.21 | CT18: 17.77443
B19: 06:00 | E19: 38.17929 | J19: 21.3445 | K19: 26.3899 | L19: 9.845 | M19: 14.9827 | N19: 13.87 | O19: 34.856 | R19: 51.836 | T19: 43.86957 | V19: 8.5 | X19: 107.6459 | Z19: 9.80614 | AC19: 15.2 | AF19: 2.4 | AH19: 6.293 | AJ19: 5.10208 | AK19: 0 | AL19: 1.1274 | AM19: 45.0189 | AN19: 102.95894 | AO19: 25.343 | AP19: 1.54 | AQ19: 96.0771 | AS19: 32.36415 | AT19: 27.97834 | AV19: 191.62245 | AW19: 29.5775 | AY19: 3.10358 | BA19: 5.3 | BC19: 46.61157 | BE19: 19.3 | BK19: 5.37229 | BM19: 7.464 | BN19: 45.82 | BP19: 143.38315 | BR19: 4.21427 | BS19: 127.33381 | BT19: 11.13271 | BW19: 3.65085 | BZ19: 87.93306 | CA19: 33.362 | CB19: 0.2996 | CC19: 0.83366 | CD19: 26.55623 | CE19: 348.19252 | CF19: 10.6477 | CG19: 152.008 | CH19: 18.25006 | CK19: 13.8889 | CL19: 4.65491 | CO19: 13.0122 | CP19: 285.44 | CR19: 35.243 | CT19: 14.97033
... B55: 00:00 | E55: 21.65864 | J55: 19.7173 | K55: 26.2652 | L55: 11.855 | M55: 13.7355 | N55: 13.67 | O55: 32.136 | R55: 50.816 | T55: 44.19581 | V55: 9.2 | X55: 101.92403 | Z55: 9.24277 | AC55: 14.21 | AF55: 2 | AH55: 3.182 | AJ55: 5.27586 | AK55: 0 | AL55: 1.5866 | AM55: 25.1213 | AN55: 101.15763 | AO55: 26.5305 | AP55: 0.83 | AQ55: 98.3377 | AS55: 34.66096 | AT55: 28.65872 | AV55: 191.8685 | AW55: 27.9384 | AY55: 3.15514 | BA55: 5.4 | BC55: 46.3986 | BE55: 19.9 | BK55: 5.40851 | BM55: 6.711 | BN55: 42.63 | BP55: 121.61224 | BR55: 4.34707 | BS55: 130.92603 | BT55: 11.01368 | BW55: 3.83695 | BZ55: 88.85307 | CA55: 22.38 | CB55: 0.4927 | CC55: 0.83289 | CD55: 27.10958 | CE55: 348.08171 | CF55: 11.6683 | CG55: 154.016 | CH55: 18.24822 | CK55: 13.9984 | CL55: 4.83629 | CO55: 16.27353 | CP55: 224.47 | CR55: 29.936 | CT55: 18.51752
B56: MWh | C56: 0 | D56: 0 | E56: 744.93174 | F56: 0 | G56: 0 | H56: 0 | I56: 0 | J56: 470.7161 | K56: 639.60985 | L56: 259.663 | M56: 314.5916 | N56: 325.285 | O56: 792.108 | P56: 0 | Q56: 0 | R56: 1235.399 | S56: 0 | T56: 744.3933 | U56: 0 | V56: 218 | W56: 0 | X56: 2510.8893 | Y56: 0 | Z56: 240.15236 | AA56: 0 | AB56: 0 | AC56: 365.355 | AD56: 0 | AE56: 0 | AF56: 65.85 | AG56: 0 | AH56: 92.25855 | AI56: 0 | AJ56: 118.96792 | AK56: 0 | AL56: 73.502 | AM56: 729.2129 | AN56: 2465.9106 | AO56: 623.48375 | AP56: 18.01 | AQ56: 2212.7087 | AR56: 0 | AS56: 809.72082 | AT56: 712.2627 | AU56: 0 | AV56: 2903.7046 | AW56: 691.3277 | AX56: 0 | AY56: 72.80007 | AZ56: 0 | BA56: 124.15 | BB56: 0 | BC56: 991.70515 | BD56: 0 | BE56: 473.7 | BF56: 0 | BG56: 0 | BH56: 0 | BI56: 0 | BJ56: 0 | BK56: 128.93135 | BL56: 0 | BM56: 166.989 | BN56: 780.8 | BO56: 0 | BP56: 3317.128 | BQ56: 0 | BR56: 102.49992 | BS56: 3082.3256 | BT56: 244.43999 | BU56: 0 | BV56: 0 | BW56: 93.491925 | BX56: 0 | BY56: 0 | BZ56: 2111.5309 | CA56: 459.78199 | CB56: 21.72425 | CC56: 20.2545 | CD56: 659.90846 | CE56: 8392.4019 | CF56: 267.3994 | CG56: 3680.5735 | CH56: 421.64945 | CI56: 0 | CJ56: 0 | CK56: 335.2364 | CL56: 111.21426 | CM56: 0 | CN56: 0 | CO56: 356.76321 | CP56: 5749.79 | CQ56: 0 | CR56: 827.1705 | CS56: 0 | CT56: 310.24677
B59: Nota :
B60: Información proporcionada por la empresas
C62: DATOS ESTIMADOS
C64: SIN DATOS

Sheet TIPO_RECURSO
B3: miércoles, 15 de Enero del 2025
B5: REPORTE POTENCIA GENERADA POR TIPO DE RECURSO
B6: HORA | C6: H. PASADA | D6: H. REGULACION | E6: GAS DE CAMISEA | F6: GAS DE MALACAS | G6: GAS DE AGUAYTIA | H6: DIESEL | I6: NAFTA+GAS DE REFINERIA | J6: FLEXIGAS+GAS DE REFINERIA | K6: BAGAZO | L6: BIOGAS | M6: SOLAR | N6: EOLICA | O6: TOTAL | T6: EMPRESA | U6: CENTRAL | V6: HIDROELECTRICA DE PASADA | W6: HIDROELECTRICA DE REGULACION
B7: 00:30 | C7: 1179.3 | D7: 3451.1 | E7: 1572.4 | F7: 47.6 | G7: 0 | H7: 0 | I7: =+DESPACHO_EJECUTADO!EY11+DESPACHO_EJECUTADO!EZ11 -> 59.9 | K7: 48.4 | L7: 12.4 | M7: 0 | N7: 267.6 | O7: 6638.7 | T7: ANDEAN POWER S.A.C. | U7: C.H. CARHUAC | V7: 360.5
B8: 01:00 | C8: 1175.7 | D8: 3308.4 | E8: 1556.3 | F8: 47.7 | G8: 0 | H8: 0 | I8: =+DESPACHO_EJECUTADO!EY12+DESPACHO_EJECUTADO!EZ12 -> 59.4 | K8: 47.3 | L8: 12.4 | M8: 0 | N8: 219.8 | O8: 6427 | T8: ASOCIACIÓN SANTA LUCIA DE CHACAS | U8: C.H. HUALLIN | V8: 48
B9: 01:30 | C9: 1179.3 | D9: 3438.7 | E9: 1463.5 | F9: 47.7 | G9: 0 | H9: 0 | I9: =+DESPACHO_EJECUTADO!EY13+DESPACHO_EJECUTADO!EZ13 -> 58.8 | K9: 48.2 | L9: 12.4 | M9: 0 | N9: 201.4 | O9: 6450 | T9: CELEPSA | U9: C.H. EL PLATANAL | W9: 5167.65
B10: 02:00 | C10: 1177.2 | D10: 3407.6 | E10: 1451.6 | F10: 0 | G10: 0 | H10: 0 | I10: =+DESPACHO_EJECUTADO!EY14+DESPACHO_EJECUTADO!EZ14 -> 59.3 | K10: 47.8 | L10: 12.4 | M10: 0 | N10: 170.2 | O10: 6326.1 | T10: CELEPSA RENOVABLES S.R.L. | U10: C.H. MARAÑON | V10: 472.8
B11: 02:30 | C11: 1184 | D11: 3403.4 | E11: 1452.8 | F11: 0 | G11: 0 | H11: 0 | I11: =+DESPACHO_EJECUTADO!EY15+DESPACHO_EJECUTADO!EZ15 -> 59.9 | K11: 47.9 | L11: 12.4 | M11: 0 | N11: 145.8 | O11: 6306.2 | T11: CENTRALES SANTA ROSA S.A.C. | U11: C.H. SANTA ROSA I | V11: 14.65
B12: 03:00 | C12: 1179.4 | D12: 3323.8 | E12: 1537.1 | F12: 0 | G12: 0 | H12: 0 | I12: =+DESPACHO_EJECUTADO!EY16+DESPACHO_EJECUTADO!EZ16 -> 60 | K12: 46.7 | L12: 12.4 | M12: 0 | N12: 123.7 | O12: 6283.1 | U12: C.H. SANTA ROSA II | V12: 22.3
B13: 03:30 | C13: 1179.1 | D13: 3348.3 | E13: 1498.8 | F13: 0 | G13: 0 | H13: 0 | I13: =+DESPACHO_EJECUTADO!EY17+DESPACHO_EJECUTADO!EZ17 -> 60.4 | K13: 47.3 | L13: 12.4 | M13: 0 | N13: 105.1 | O13: 6251.4 | T13: CHINANGO S.A.C. | U13: C.H. CHIMAY | W13: 3447
B14: 04:00 | C14: 1176.3 | D14: 3227.7 | E14: 1555.9 | F14: 0 | G14: 0 | H14: 0 | I14: =+DESPACHO_EJECUTADO!EY18+DESPACHO_EJECUTADO!EZ18 -> 59.8 | K14: 47.5 | L14: 12.4 | M14: 0 | N14: 111.3 | O14: 6190.9 | U14: C.H. YANANGO | V14: 853.8
B15: 04:30 | C15: 1178.5 | D15: 3392.3 | E15: 1510 | F15: 0 | G15: 0 | H15: 0 | I15: =+DESPACHO_EJECUTADO!EY19+DESPACHO_EJECUTADO!EZ19 -> 59.9 | K15: 47 | L15: 12.4 | M15: 0 | N15: 107.4 | O15: 6307.5 | T15: EGASA | U15: C.H. CHARCANI III | V15: 154.45
B16: 05:00 | C16: 1181.8 | D16: 3367 | E16: 1538.3 | F16: 0 | G16: 0 | H16: 0 | I16: =+DESPACHO_EJECUTADO!EY20+DESPACHO_EJECUTADO!EZ20 -> 59.9 | K16: 45.7 | L16: 12.4 | M16: 0 | N16: 111.9 | O16: 6317 | U16: C.H. CHARCANI IV | W16: 229.7
B17: 05:30 | C17: 1158 | D17: 3253.6 | E17: 1573.6 | F17: 0 | G17: 0 | H17: 0 | I17: =+DESPACHO_EJECUTADO!EY21+DESPACHO_EJECUTADO!EZ21 -> 59.3 | K17: 46.1 | L17: 12.5 | M17: 5.7 | N17: 127.3 | O17: 6236.1 | U17: C.H. CHARCANI V | W17: 1515.85
B18: 06:00 | C18: 1180 | D18: 3252.3 | E18: 1571.7 | F18: 0 | G18: 0 | H18: 0 | I18: =+DESPACHO_EJECUTADO!EY22+DESPACHO_EJECUTADO!EZ22 -> 59.9 | K18: 45.7 | L18: 12.5 | M18: 64.6 | N18: 127.8 | O18: 6314.5 | U18: C.H. CHARCANI VI | W18: 137.25
B19: 06:30 | C19: 1160.1 | D19: 3108.4 | E19: 1578.9 | F19: 0 | G19: 0 | H19: 0 | I19: =+DESPACHO_EJECUTADO!EY23+DESPACHO_EJECUTADO!EZ23 -> 60.5 | K19: 46.6 | L19: 12.5 | M19: 186.1 | N19: 159.5 | O19: 6312.6 | T19: EGEJUNIN | U19: C.H. HUASAHUASI I | V19: 325.1
B20: 07:00 | C20: 1180.1 | D20: 3096.8 | E20: 1598.5 | F20: 0 | G20: 0 | H20: 0 | I20: =+DESPACHO_EJECUTADO!EY24+DESPACHO_EJECUTADO!EZ24 -> 60.3 | K20: 47.1 | L20: 12.5 | M20: 298.4 | N20: 160.4 | O20: 6454.1 | U20: C.H. RUNATULLO II | V20: 478.8
B21: 07:30 | C21: 1158.9 | D21: 3320.5 | E21: 1500.7 | F21: 0 | G21: 0 | H21: 0 | I21: =+DESPACHO_EJECUTADO!EY25+DESPACHO_EJECUTADO!EZ25 -> 60.7 | K21: 46.6 | L21: 12.5 | M21: 369.5 | N21: 168.2 | O21: 6637.6 | U21: C.H. RUNATULLO III | V21: 489.05
B22: 08:00 | C22: 1169.1 | D22: 3386.9 | E22: 1562.6 | F22: 0 | G22: 0 | H22: 0 | I22: =+DESPACHO_EJECUTADO!EY26+DESPACHO_EJECUTADO!EZ26 -> 60.4 | K22: 47.7 | L22: 12.5 | M22: 394.9 | N22: 182.1 | O22: 6816.2 | U22: C.H. SANTA CRUZ I | V22: 289.7
B23: 08:30 | C23: 1176.3 | D23: 3365.6 | E23: 1835.9 | F23: 45.2 | G23: 0 | H23: 0 | I23: =+DESPACHO_EJECUTADO!EY27+DESPACHO_EJECUTADO!EZ27 -> 59.8 | K23: 45.7 | L23: 12.4 | M23: 410.7 | N23: 206.7 | O23: 7158.3 | T23: EGEMSA | U23: C.H. MACHUPICCHU | V23: 3981.75
B24: 09:00 | C24: 1174.3 | D24: 3382.3 | E24: 1838.7 | F24: 45.7 | G24: 0 | H24: 0 | I24: =+DESPACHO_EJECUTADO!EY28+DESPACHO_EJECUTADO!EZ28 -> 61 | K24: 48.8 | L24: 12.4 | M24: 423.8 | N24: 209.9 | O24: 7196.9 | T24: EGESUR | U24: C.H. ARICOTA I | W24: 187.3
B25: 09:30 | C25: 1163.2 | D25: 3336.9 | E25: 1926.1 | F25: 46.3 | G25: 0 | H25: 0 | I25: =+DESPACHO_EJECUTADO!EY29+DESPACHO_EJECUTADO!EZ29 -> 59.8 | K25: 47.6 | L25: 12.4 | M25: 435.3 | N25: 235.6 | O25: 7263.2 | T25: ELECTRICA YANAPAMPA SAC | U25: C.H. YANAPAMPA | V25: 85.9
B26: 10:00 | C26: 1172.3 | D26: 3348.8 | E26: 1825.1 | F26: 45.5 | G26: 0 | H26: 0 | I26: =+DESPACHO_EJECUTADO!EY30+DESPACHO_EJECUTADO!EZ30 -> 60.2 | K26: 43.4 | L26: 12.4 | M26: 441.9 | N26: 329.1 | O26: 7278.7 | T26: ELECTROPERU | U26: C.H. MANTARO | W26: 15518.25
B27: 10:30 | C27: 1169.7 | D27: 3380.7 | E27: 1912.2 | F27: 45.8 | G27: 0 | H27: 0 | I27: =+DESPACHO_EJECUTADO!EY31+DESPACHO_EJECUTADO!EZ31 -> 60.5 | K27: 44.3 | L27: 12.1 | M27: 443.9 | N27: 402.9 | O27: 7472.1 | U27: C.H. RESTITUCION | V27: 5260.2
B28: 11:00 | C28: 1150.4 | D28: 3336.5 | E28: 2043.1 | F28: 45.4 | G28: 0 | H28: 0 | I28: =+DESPACHO_EJECUTADO!EY32+DESPACHO_EJECUTADO!EZ32 -> 59.9 | K28: 44.6 | L28: 12.1 | M28: 370.8 | N28: 409.3 | O28: 7472.1 | T28: EMPRESA DE GENERACION ELECTRICA CANCHAYLLO SAC | U28: C.H. CANCHAYLLO | V28: 114.7
B29: 11:30 | C29: 1161.3 | D29: 3401.8 | E29: 2008.2 | F29: 45.6 | G29: 0 | H29: 0 | I29: =+DESPACHO_EJECUTADO!EY33+DESPACHO_EJECUTADO!EZ33 -> 59.4 | K29: 41.7 | L29: 12 | M29: 394.7 | N29: 463.7 | O29: 7588.4 | T29: EMPRESA DE GENERACION ELECTRICA RIO BAÑOS S.A.C. | U29: C.H. RUCUY | V29: 477.7
B30: 12:00 | C30: 1159.4 | D30: 3362.1 | E30: 1864.3 | F30: 45.3 | G30: 0 | H30: 0 | I30: =+DESPACHO_EJECUTADO!EY34+DESPACHO_EJECUTADO!EZ34 -> 60.3 | K30: 37.5 | L30: 11.9 | M30: 435.3 | N30: 522.4 | O30: 7498.5 | T30: EMPRESA DE GENERACION ELECTRICA SANTA ANA S.A.C. | U30: C.H. RENOVANDES H1 | V30: 464.4
B31: 12:30 | C31: 1176.2 | D31: 3373.3 | E31: 1880.4 | F31: 45.4 | G31: 0 | H31: 0 | I31: =+DESPACHO_EJECUTADO!EY35+DESPACHO_EJECUTADO!EZ35 -> 59.4 | K31: 38 | L31: 11.8 | M31: 460.6 | N31: 546.4 | O31: 7591.5 | T31: EMPRESA DE GENERACION HUALLAGA | U31: C.H. CHAGLLA | W31: 10715.3
B32: 13:00 | C32: 1153.2 | D32: 3337.2 | E32: 1795.5 | F32: 46.6 | G32: 0 | H32: 0 | I32: =+DESPACHO_EJECUTADO!EY36+DESPACHO_EJECUTADO!EZ36 -> 59.6 | K32: 38.5 | L32: 11.8 | M32: 452.7 | N32: 612 | O32: 7507.1 | U32: P.C.H. CHAGLLA | V32: 156
B33: 13:30 | C33: 1157.3 | D33: 3321.8 | E33: 1685.1 | F33: 46.1 | G33: 0 | H33: 0 | I33: =+DESPACHO_EJECUTADO!EY37+DESPACHO_EJECUTADO!EZ37 -> 59.8 | K33: 43.2 | L33: 11.8 | M33: 413.7 | N33: 664.8 | O33: 7403.6 | T33: EMPRESA DE GENERACION HUANZA | U33: C.H. HUANZA | W33: 1343.3
B34: 14:00 | C34: 1186.3 | D34: 3402.1 | E34: 1627.8 | F34: 46.2 | G34: 0 | H34: 0 | I34: =+DESPACHO_EJECUTADO!EY38+DESPACHO_EJECUTADO!EZ38 -> 60.2 | K34: 41.7 | L34: 11.7 | M34: 405.4 | N34: 685.4 | O34: 7466.8 | T34: EMPRESA ELECTRICA AGUA AZUL | U34: C.H. POTRERO | V34: 477.65
B35: 14:30 | C35: 1172.3 | D35: 3504 | E35: 1673.6 | F35: 46.5 | G35: 0 | H35: 0 | I35: =+DESPACHO_EJECUTADO!EY39+DESPACHO_EJECUTADO!EZ39 -> 59.8 | K35: 42.8 | L35: 11.7 | M35: 333.6 | N35: 753.1 | O35: 7597.4 | T35: EMPRESA ELECTRICA RIO DOBLE | U35: C.H. LAS PIZARRAS | V35: 453.3
B36: 15:00 | C36: 1181.8 | D36: 3492.9 | E36: 1733.1 | F36: 46.6 | G36: 0 | H36: 0 | I36: =+DESPACHO_EJECUTADO!EY40+DESPACHO_EJECUTADO!EZ40 -> 60 | K36: 41.3 | L36: 11.7 | M36: 289.9 | N36: 757.2 | O36: 7614.5 | T36: ENGIE | U36: C.H. QUITARACSA | W36: 2690.35
B37: 15:30 | C37: 1194.6 | D37: 3570 | E37: 1682.7 | F37: 46.8 | G37: 0 | H37: 0 | I37: =+DESPACHO_EJECUTADO!EY41+DESPACHO_EJECUTADO!EZ41 -> 59.9 | K37: 41.6 | L37: 11.7 | M37: 217 | N37: 766.9 | O37: 7591.2 | U37: C.H. YUNCAN | W37: 2892.7
B38: 16:00 | C38: 1156.3 | D38: 3558.3 | E38: 1722.1 | F38: 46.4 | G38: 0 | H38: 0 | I38: =+DESPACHO_EJECUTADO!EY42+DESPACHO_EJECUTADO!EZ42 -> 60.6 | K38: 47.6 | L38: 11.7 | M38: 188.7 | N38: 734.8 | O38: 7526.5 | T38: GENERACIÓN ANDINA S.A.C. | U38: C.H. 8 DE AGOSTO | V38: 467.65
B39: 16:30 | C39: 1143.7 | D39: 3494.1 | E39: 1678.1 | F39: 46.4 | G39: 0 | H39: 0 | I39: =+DESPACHO_EJECUTADO!EY43+DESPACHO_EJECUTADO!EZ43 -> 60.4 | K39: 47.5 | L39: 11.7 | M39: 178.1 | N39: 758.2 | O39: 7418.2 | U39: C.H. EL CARMEN | V39: 136.05
B40: 17:00 | C40: 1155.9 | D40: 3473.5 | E40: 1577.2 | F40: 46.5 | G40: 0 | H40: 0 | I40: =+DESPACHO_EJECUTADO!EY44+DESPACHO_EJECUTADO!EZ44 -> 60.3 | K40: 47.2 | L40: 11.8 | M40: 125.3 | N40: 745.7 | O40: 7243.4 | T40: GENERADORA DE ENERGÍA DEL PERÚ | U40: C.H. ÁNGEL I | V40: 489.6
B41: 17:30 | C41: 1150.3 | D41: 3422.1 | E41: 1518.3 | F41: 46.3 | G41: 0 | H41: 0 | I41: =+DESPACHO_EJECUTADO!EY45+DESPACHO_EJECUTADO!EZ45 -> 60 | K41: 47.7 | L41: 11.9 | M41: 80.5 | N41: 764.8 | O41: 7101.9 | U41: C.H. ÁNGEL II | V41: 489.6
B42: 18:00 | C42: 1146.6 | D42: 3389.8 | E42: 1426.2 | F42: 46.3 | G42: 0 | H42: 0 | I42: =+DESPACHO_EJECUTADO!EY46+DESPACHO_EJECUTADO!EZ46 -> 59.9 | K42: 46.6 | L42: 11.9 | M42: 24 | N42: 771.4 | O42: 6922.7 | U42: C.H. ÁNGEL III | V42: 122.4
B43: 18:30 | C43: 1155.6 | D43: 3442.3 | E43: 1451.2 | F43: 47 | G43: 0 | H43: 0 | I43: =+DESPACHO_EJECUTADO!EY47+DESPACHO_EJECUTADO!EZ47 -> 60.1 | K43: 48.8 | L43: 12.1 | M43: 0 | N43: 770.6 | O43: 6987.7 | U43: C.H. LA JOYA | V43: 140.45
B44: 19:00 | C44: 1180.1 | D44: 3480.3 | E44: 1766.3 | F44: 46.8 | G44: 0 | H44: 0 | I44: =+DESPACHO_EJECUTADO!EY48+DESPACHO_EJECUTADO!EZ48 -> 59.8 | K44: 49.1 | L44: 12.2 | M44: 0 | N44: 724.4 | O44: 7319 | T44: HIDROCAÑETE S.A. | U44: C.H. IMPERIAL | V44: 85.3
B45: 19:30 | C45: 1194.1 | D45: 3592.5 | E45: 1778.7 | F45: 47.3 | G45: 0 | H45: 0 | I45: =+DESPACHO_EJECUTADO!EY49+DESPACHO_EJECUTADO!EZ49 -> 59.8 | K45: 49.2 | L45: 12.2 | M45: 0 | N45: 697 | O45: 7430.8 | T45: HIDROELECTRICA HUANCHOR S.A.C. | U45: C.H. HUANCHOR | V45: 439.25
B46: 20:00 | C46: 1180.8 | D46: 3611.9 | E46: 1824.7 | F46: 47.1 | G46: 0 | H46: 0 | I46: =+DESPACHO_EJECUTADO!EY50+DESPACHO_EJECUTADO!EZ50 -> 59.9 | K46: 48.9 | L46: 12.4 | M46: 0 | N46: 645.5 | O46: 7431.2 | T46: HUAURA POWER GROUP S.A. | U46: C.H. YARUCAYA | V46: 448.8
B47: 20:30 | C47: 1190.4 | D47: 3621.4 | E47: 1826.6 | F47: 47.4 | G47: 0 | H47: 0 | I47: =+DESPACHO_EJECUTADO!EY51+DESPACHO_EJECUTADO!EZ51 -> 60.1 | K47: 48.3 | L47: 12.4 | M47: 0 | N47: 561.4 | O47: 7368 | T47: INLAND ENERGY SAC | U47: C.H. SANTA TERESA | V47: 2069
B48: 21:00 | C48: 1181.7 | D48: 3629.7 | E48: 1828.8 | F48: 47.5 | G48: 0 | H48: 0 | I48: =+DESPACHO_EJECUTADO!EY52+DESPACHO_EJECUTADO!EZ52 -> 59.6 | K48: 48.4 | L48: 12.5 | M48: 0 | N48: 517.6 | O48: 7325.8 | T48: INVERSIONES SHAQSHA S.A.C. | U48: C.H. PARIAC | V48: 101.2
B49: 21:30 | C49: 1183.4 | D49: 3688.4 | E49: 1799.2 | F49: 47.5 | G49: 0 | H49: 0 | I49: =+DESPACHO_EJECUTADO!EY53+DESPACHO_EJECUTADO!EZ53 -> 58.7 | K49: 49.4 | L49: 12.5 | M49: 0 | N49: 451.5 | O49: 7290.6 | T49: KALLPA GENERACION S.A. | U49: C.H. CERRO DEL AGUILA | W49: 13388.45
B50: 22:00 | C50: 1180.5 | D50: 3632.8 | E50: 1778.6 | F50: 47.3 | G50: 28.4 | H50: 0 | I50: =+DESPACHO_EJECUTADO!EY54+DESPACHO_EJECUTADO!EZ54 -> 59.8 | K50: 49.1 | L50: 12.5 | M50: 0 | N50: 360.5 | O50: 7149.5 | U50: M.C.H. CERRO DEL AGUILA | V50: 251.7
B51: 22:30 | C51: 1187.4 | D51: 3646.3 | E51: 1665.4 | F51: 47.9 | G51: 55.4 | H51: 0 | I51: =+DESPACHO_EJECUTADO!EY55+DESPACHO_EJECUTADO!EZ55 -> 59.2 | K51: 47.9 | L51: 12.5 | M51: 0 | N51: 338.6 | O51: 7060.6 | T51: LA VIRGEN | U51: C.H. LA VIRGEN | W51: 1235.7
B52: 23:00 | C52: 1183 | D52: 3487.6 | E52: 1602.2 | F52: 47.8 | G52: 91.3 | H52: 0 | I52: =+DESPACHO_EJECUTADO!EY56+DESPACHO_EJECUTADO!EZ56 -> 58.9 | K52: 47.6 | L52: 12.5 | M52: 0 | N52: 301.2 | O52: 6832.1 | T52: MAJA ENERGIA S.A.C. | U52: C.H. RONCADOR | V52: 86
B53: 23:30 | C53: 1192.6 | D53: 3572.5 | E53: 1467.3 | F53: 47.7 | G53: 91.8 | H53: 0 | I53: =+DESPACHO_EJECUTADO!EY57+DESPACHO_EJECUTADO!EZ57 -> 59.3 | K53: 47.6 | L53: 12.5 | M53: 0 | N53: 345.8 | O53: 6837.1 | T53: ORAZUL ENERGY PERÚ | U53: C.H. CAÑA BRAVA | V53: 129.8
B54: 00:00 | C54: 1182.5 | D54: 3523.2 | E54: 1159.8 | F54: 47.7 | G54: 86.6 | H54: 88.2 | I54: =+DESPACHO_EJECUTADO!EY58+DESPACHO_EJECUTADO!EZ58 -> 59.8 | K54: 48 | L54: 12.5 | M54: 0 | N54: 367.7 | O54: 6576 | U54: C.H. CAÑON DEL PATO | W54: 5714.1
B55: TOTAL MWh | C55: =+SUM(C7:C54)/2 -> 28145.15 | D55: =+SUM(D7:D54)/2 -> 82134.75 | E55: =+SUM(E7:E54)/2 -> 39862.6 | F55: =+SUM(F7:F54)/2 -> 816.45 | G55: =+SUM(G7:G54)/2 -> 176.75 | H55: =+SUM(H7:H54)/2 -> 44.1 | I55: =+SUM(I7:I54)/2 -> 1437.1 | J55: =+SUM(J7:J54)/2 -> 0 | ... O55: =+SUM(O7:O54)/2 -> 167895.2 | U55: C.H. CARHUAQUERO | W55: 2159.3
B56: % | C56: =+C55/$O$55*100 -> 16.763523 | D56: =+D55/$O$55*100 -> 48.920249 | E56: =+E55/$O$55*100 -> 23.742549 | F56: =+F55/$O$55*100 -> 0.48628549 | G56: =+G55/$O$55*100 -> 0.105274 | H56: =+H55/$O$55*100 -> 0.026266385 | I56: =+I55/$O$55*100 -> 0.85595062 | J56: =+J55/$O$55*100 -> 0 | ... N56: =+N55/$O$55*100 -> 5.9297705 | O56: 100.00 | U56: C.H. CARHUAQUERO IV | V56: 238.1
T57: ORYGEN PERU S.A.A. | U57: C.H. CALLAHUANCA | W57: 1855.6
U58: C.H. HER 1 | V58: 14.4
U59: C.H. HUAMPANI | V59: 721.35
U60: C.H. HUINCO | W60: 3037
U61: C.H. MATUCANA | W61: 3095.55
U62: C.H. MOYOPAMPA | V62: 1522.75
T63: PERUANA DE INVERSIONES EN ENERGIAS RENOVABLES S.A. | U63: C.H. MANTA I | V63: 479.8
T64: SAN GABAN | U64: C.H. SAN GABAN II | W64: 2656.15
T65: SINERSA | U65: C.H. CHANCAY | V65: 478.2
U66: C.H. POECHOS II | V66: 114.7
T67: STATKRAFT S.A | U67: C.H. ARCATA | V67: 73.6
U68: C.H. CAHUA | V68: 1118.4
U69: C.H. CHEVES | W69: 3746.85
U70: C.H. GALLITO CIEGO | W70: 740.25
U71: C.H. MALPASO | W71: 661.15
U72: C.H. OROYA | V72: 184.7
U73: C.H. PACHACHACA | V73: 156.55
U74: C.H. YAUPI | V74: 2605.05
T75: TOTAL MWh | V75: 28145.15 | W75: 82134.75

Sheet GENERACION RER
B3: miércoles, 15 de Enero del 2025
B5: GENERACIÓN ELÉCTRICA DE LAS CENTRALES RER (MW)
B6: HORA | C6: AGRO INDUSTRIAL PARAMONGA S.A. | D6: AGROAURORA S.A.C. | E6: AGROINDUSTRIAS SAN JACINTO S.A.A. | F6: ANDEAN POWER S.A.C. | G6: ASOCIACIÓN SANTA LUCIA DE CHACAS | H6: ATRIA ENERGIA S.A.C. | I6: BIOENERGIA DEL CHIRA S.A. | J6: COLCA SOLAR S.A.C. | K6: EGEJUNIN | P6: ELECTRICA YANAPAMPA SAC | Q6: EMPRESA DE GENERACION ELECTRICA CANCHAYLLO SAC | R6: EMPRESA DE GENERACION ELECTRICA RIO BAÑOS S.A.C. | S6: EMPRESA DE GENERACION ELECTRICA SANTA ANA S.A.C. | T6: EMPRESA ELECTRICA AGUA AZUL | U6: EMPRESA ELECTRICA RIO DOBLE | V6: ENERGÍA EÓLICA S.A. | X6: ENERGIA RENOVABLE DEL SUR S.A. | Y6: ENGIE | AD6: GENERACIÓN ANDINA S.A.C. | AF6: GENERADORA DE ENERGÍA DEL PERÚ | AJ6: GR CORTARRAMA SOCIEDAD ANONIMA CERRADA | AK6: GR PAINO SOCIEDAD ANONIMA CERRADA | AL6: GR TARUCA SOCIEDAD ANONIMA CERRADA | AM6: HIDROCAÑETE S.A. | AN6: HUAURA POWER GROUP S.A. | AO6: HYDRO PATAPO S.A.C. | AP6: KONDU SAC | AQ6: MAJA ENERGIA S.A.C. | AR6: MAJES ARCUS S.A.C. | AS6: MOQUEGUA FV S.A.C. | AT6: ORAZUL ENERGY PERÚ | AV6: ORYGEN PERU S.A.A. | BA6: PANAMERICANA SOLAR SAC. | BB6: PARQUE EOLICO MARCONA S.A.C. | BC6: PARQUE EOLICO TRES HERMANAS S.A.C. | BD6: PERUANA DE INVERSIONES EN ENERGIAS RENOVABLES S.A. | BE6: PETRAMAS | BI6: REPARTICIÓN ARCUS S.A.C. | BJ6: SDF ENERGIA SAC | BK6: SINERSA | BM6: TACNA SOLAR SAC. | BN6: TOTAL RER
C7: C.T. PARAMONGA | D7: C.T. MAPLE | E7: C.T SAN JACINTO | F7: C.H. CARHUAC | G7: C.H. HUALLIN | H7: C.H. PURMACANA | I7: C.T. CAÑA BRAVA | K7: C.H. HUASAHUASI I | L7: C.H. HUASAHUASI II | M7: C.H. RUNATULLO II | N7: C.H. RUNATULLO III | O7: C.H. STA CRUZ I y II | P7: C.H. YANAPAMPA | Q7: C.H. CANCHAYLLO | R7: C.H. RUCUY | S7: C.H. RENOVANDES H1 | T7: C.H. POTRERO | U7: C.H. LAS PIZARRAS | AD7: C.H. 8 DE AGOSTO | AE7: C.H. EL CARMEN | AF7: C.H. ANGEL I | AG7: C.H. ANGEL II | AH7: C.H. ANGEL III | AI7: C.H. LA JOYA | AM7: C.H. NUEVAIMPERIAL | AN7: C.H. YARUCAYA | AO7: MCH PATAPO | AQ7: C.H. RONCADOR | AT7: C.H. CANA BRAVA | AU7: C.H. CARHUAQUERO4 | AZ7: C.H. HER 1 | BD7: C.H. MANTA | BE7: C.T. HUAYCOLORO | BF7: C.T. LA GRINGA V | BG7: CTB CALLAO | BH7: CTB. DONA CATALINA | BJ7: C.T. OQUENDO | BK7: C.H. CHANCAY | BL7: C.H. POECHOS2 | BN7: MW
B8: 0:30 | C8: 15 | D8: 14.6 | E8: 7.7 | F8: 17.3 | G8: 2 | I8: 11.1 | K8: 14.7 | M8: 20 | N8: 20.4 | O8: 12 | P8: 3.6 | Q8: 4.8 | R8: 19.8 | S8: 20.2 | T8: 20 | U8: 18.8 | V8: 7.1 | W8: 21.2 | X8: 72.9 | Y8: 35.4 | Z8: 56.9 | AB8: 2.6 | AC8: 1.6 | AD8: 20.1 | AE8: 5.7 | AF8: 20.4 | AG8: 20.4 | AI8: 5.6 | AK8: 3.6 | AL8: 3.2 | AM8: 3.5 | AN8: 18.7 | AQ8: 3.6 | AT8: 5.5 | AU8: 9.9 | AV8: 8 | AX8: 13.8 | AZ8: 0.6 | BB8: 14.8 | BC8: 26.5 | BD8: 20 | BE8: 4.8 | BF8: 2.8 | BG8: 2.4 | BH8: 2.4 | BK8: 19.8 | BL8: 4.7 | BN8: 660.5
B9: 1:00 | C9: 15.2 | D9: 14.6 | E9: 7.3 | F9: 17.1 | G9: 2 | I9: 10.2 | K9: 14.7 | M9: 19.8 | N9: 20.4 | O9: 12 | P9: 3.6 | Q9: 4.8 | R9: 19.8 | S9: 19.9 | T9: 20 | U9: 18.8 | V9: 9.2 | W9: 26.8 | X9: 74.4 | Y9: 19 | Z9: 38.8 | AB9: 1.1 | AD9: 20.2 | AE9: 5.7 | AF9: 20.4 | AG9: 20.4 | AI9: 5.9 | AK9: 2.4 | AL9: 1.9 | AM9: 3.5 | AN9: 18.7 | AQ9: 3.6 | AT9: 5.5 | AU9: 9.9 | AV9: 5.2 | AX9: 9.1 | AZ9: 0.6 | BB9: 11 | BC9: 20.9 | BD9: 20 | BE9: 4.8 | BF9: 2.8 | BG9: 2.4 | BH9: 2.4 | BK9: 19.8 | BL9: 4.7 | BN9: 611.3
B10: 1:30 | C10: 15 | D10: 14.6 | E10: 8.7 | F10: 17.1 | G10: 2 | I10: 9.9 | K10: 14.6 | M10: 19.7 | N10: 20.4 | O10: 12 | P10: 3.6 | Q10: 4.8 | R10: 19.8 | S10: 20.3 | T10: 20 | U10: 18.9 | V10: 11.1 | W10: 30.9 | X10: 78.3 | Y10: 12.7 | Z10: 28 | AB10: 0.4 | AC10: 0.1 | AD10: 20.2 | AE10: 5.7 | AF10: 20.4 | AG10: 20.4 | AI10: 5.9 | AK10: 0.7 | AL10: 0.5 | AM10: 3.5 | AN10: 18.7 | AQ10: 3.6 | AT10: 5.4 | AU10: 9.9 | AV10: 0.5 | AX10: 2.5 | AZ10: 0.6 | BB10: 10.1 | BC10: 25.6 | BD10: 20 | BE10: 4.8 | BF10: 2.8 | BG10: 2.4 | BH10: 2.4 | BK10: 19.8 | BL10: 4.7 | BN10: 594
B11: 2:00 | C11: 15 | D11: 14.6 | E11: 9 | F11: 17.2 | G11: 2 | I11: 9.2 | K11: 14.6 | M11: 19.4 | N11: 20.4 | O11: 12 | P11: 3.6 | Q11: 4.7 | R11: 19.8 | S11: 20.2 | T11: 19.3 | U11: 19 | V11: 11.7 | W11: 25.4 | X11: 68.1 | Y11: 9.1 | Z11: 24 | AB11: 0.6 | AC11: 0.1 | AD11: 20.2 | AE11: 5.7 | AF11: 20.4 | AG11: 20.4 | AI11: 6.1 | AK11: 1 | AL11: 0.8 | AM11: 3.5 | AN11: 18.7 | AQ11: 3.6 | AT11: 5.3 | AU11: 9.9 | AZ11: 0.6 | BB11: 9 | BC11: 20.4 | BD11: 20 | BE11: 4.8 | BF11: 2.8 | BG11: 2.4 | BH11: 2.4 | BK11: 19.8 | BL11: 4.7 | BN11: 561.5
B12: 2:30 | C12: 15 | D12: 14.6 | E12: 8.5 | F12: 17.2 | G12: 2 | I12: 9.8 | K12: 14.6 | M12: 19.6 | N12: 20.4 | O12: 12 | P12: 3.6 | Q12: 4.8 | R12: 19.8 | S12: 20.5 | T12: 20 | U12: 18.9 | V12: 11 | W12: 16.7 | X12: 54 | Y12: 12.1 | Z12: 23.3 | AB12: 0.4 | AD12: 20.2 | AE12: 5.7 | AF12: 20.4 | AG12: 20.4 | AI12: 6 | AK12: 1.7 | AL12: 1.5 | AM12: 3.5 | AN12: 18.7 | AQ12: 3.6 | AT12: 5.5 | AU12: 9.9 | AZ12: 0.6 | BB12: 8.5 | BC12: 16.6 | BD12: 20 | BE12: 4.8 | BF12: 2.8 | BG12: 2.4 | BH12: 2.4 | BK12: 19.8 | BL12: 4.7 | BN12: 538.5
B13: 3:00 | C13: 15.1 | D13: 14.1 | E13: 8.2 | F13: 17.2 | G13: 2 | I13: 9.3 | K13: 14.6 | M13: 19.4 | N13: 20.4 | O13: 12 | P13: 3.6 | Q13: 4.8 | R13: 19.8 | S13: 20.4 | T13: 20 | U13: 18.9 | V13: 16.9 | W13: 22.8 | X13: 34.9 | Y13: 10.2 | Z13: 22.7 | AB13: 0.3 | AD13: 20 | AE13: 5.7 | AF13: 20.4 | AG13: 20.4 | AI13: 5.7 | AK13: 3.5 | AL13: 3 | AM13: 3.5 | AN13: 18.7 | AQ13: 3.6 | AT13: 5.4 | AU13: 9.9 | AZ13: 0.6 | BB13: 3.6 | BC13: 5.8 | BD13: 20 | BE13: 4.8 | BF13: 2.8 | BG13: 2.4 | BH13: 2.4 | BK13: 19.9 | BL13: 4.7 | BN13: 514.4
B14: 3:30 | C14: 15.2 | D14: 14.6 | E14: 7.7 | F14: 17.2 | G14: 2 | I14: 9.8 | K14: 14.6 | M14: 19.3 | N14: 20.3 | O14: 12.2 | P14: 3.6 | Q14: 4.8 | R14: 19.8 | S14: 20 | T14: 20 | U14: 18.9 | V14: 17 | W14: 27.6 | X14: 31.3 | Y14: 4.3 | Z14: 12.5 | AD14: 20 | AE14: 5.7 | AF14: 20.4 | AG14: 20.4 | AI14: 5.7 | AK14: 5.5 | AL14: 3.9 | AM14: 3.5 | AN14: 18.7 | AQ14: 3.6 | AT14: 5.4 | AU14: 9.9 | AZ14: 0.6 | BB14: 1.7 | BC14: 1.3 | BD14: 20 | BE14: 4.8 | BF14: 2.8 | BG14: 2.4 | BH14: 2.4 | BK14: 19.9 | BL14: 4.7 | BN14: 496
B15: 4:00 | C15: 15.4 | D15: 14.7 | E15: 7.8 | F15: 17.3 | G15: 2 | I15: 9.6 | K15: 14.6 | M15: 19.2 | N15: 20.3 | O15: 12.2 | P15: 3.6 | Q15: 4.8 | R15: 19.9 | S15: 20 | T15: 20 | U15: 18.9 | V15: 18.4 | W15: 26.1 | X15: 40.6 | Y15: 3.6 | Z15: 10.3 | AD15: 20 | AE15: 5.7 | AF15: 20.4 | AG15: 20.4 | AI15: 5.8 | AK15: 2.7 | AL15: 2.7 | AM15: 3.5 | AN15: 18.7 | AQ15: 3.6 | AT15: 5.4 | AU15: 9.9 | AZ15: 0.6 | BB15: 4.9 | BC15: 2 | BD15: 20 | BE15: 4.8 | BF15: 2.8 | BG15: 2.4 | BH15: 2.4 | BK15: 19.9 | BL15: 4.7 | BN15: 502.6
B16: 4:30 | C16: 15.1 | D16: 14.6 | E16: 7.8 | F16: 17.3 | G16: 2 | I16: 9.5 | K16: 14.6 | M16: 19.4 | N16: 20.4 | O16: 12.2 | P16: 3.6 | Q16: 4.8 | R16: 19.8 | S16: 20.1 | T16: 19.4 | U16: 19 | V16: 14.4 | W16: 17.9 | X16: 47.7 | Y16: 3.2 | Z16: 10 | AD16: 20 | AE16: 5.7 | AF16: 20.4 | AG16: 20.4 | AI16: 6 | AK16: 1.1 | AL16: 1.4 | AM16: 3.5 | AN16: 18.7 | AQ16: 3.6 | AT16: 5.5 | AU16: 9.9 | AZ16: 0.6 | BB16: 6.8 | BC16: 4.9 | BD16: 20 | BE16: 4.8 | BF16: 2.8 | BG16: 2.4 | BH16: 2.4 | BK16: 19.8 | BL16: 4.7 | BN16: 498.2
B17: 5:00 | C17: 15 | D17: 14.7 | E17: 6.6 | F17: 17.2 | G17: 2 | I17: 9.4 | K17: 14.6 | M17: 19.5 | N17: 20.4 | O17: 12.2 | P17: 3.6 | Q17: 4.7 | R17: 19.8 | S17: 20.4 | T17: 20 | U17: 19 | V17: 10.6 | W17: 8.3 | X17: 57.4 | Y17: 4.3 | Z17: 13.3 | AD17: 20 | AE17: 5.7 | AF17: 20.4 | AG17: 20.4 | AI17: 6 | AK17: 1.9 | AL17: 0.7 | AM17: 3.5 | AN17: 18.7 | AQ17: 3.6 | AT17: 5.4 | AU17: 9.9 | AZ17: 0.6 | BB17: 7.7 | BC17: 7.7 | BD17: 20 | BE17: 4.8 | BF17: 2.8 | BG17: 2.4 | BH17: 2.4 | BK17: 20 | BL17: 4.7 | BN17: 502.3
B18: 5:30 | C18: 15 | D18: 14.7 | E18: 6.7 | F18: 17.2 | G18: 2 | I18: 9.7 | K18: 14.6 | M18: 19.1 | N18: 20.3 | O18: 12.2 | P18: 3.6 | Q18: 4.7 | R18: 19.8 | S18: 19.7 | T18: 20 | U18: 18.9 | V18: 10.8 | W18: 7.9 | X18: 60 | Y18: 6.6 | Z18: 19.4 | AA18: 0.1 | AD18: 20 | AE18: 5.7 | AF18: 20.4 | AG18: 20.4 | AI18: 5.7 | AK18: 1.6 | AL18: 0.7 | AM18: 3.5 | AN18: 18.7 | AQ18: 3.6 | AS18: 0.9 | AT18: 5.3 | AU18: 9.9 | AW18: 1 | AY18: 0.9 | AZ18: 0.6 | BA18: 1.1 | BB18: 9 | BC18: 11.3 | BD18: 20 | BE18: 4.8 | BF18: 2.9 | BG18: 2.4 | BH18: 2.4 | BK18: 19.8 | BL18: 4.8 | BM18: 1.7 | BN18: 522.1
B19: 6:00 | C19: 15 | D19: 14.7 | E19: 6.5 | F19: 17.2 | G19: 2 | I19: 9.5 | K19: 14.6 | M19: 19.4 | N19: 20.3 | O19: 12.2 | P19: 3.6 | Q19: 4.7 | R19: 19.8 | S19: 20 | T19: 19.4 | U19: 18.9 | V19: 12.8 | W19: 16.2 | X19: 56.9 | Y19: 3.7 | Z19: 11.8 | AA19: 4.1 | AD19: 20 | AE19: 5.7 | AF19: 20.4 | AG19: 20.4 | AI19: 5.5 | AJ19: 7.6 | AK19: 2.4 | AL19: 2.1 | AM19: 3.5 | AN19: 18.7 | AQ19: 3.6 | AS19: 6.3 | AT19: 5.4 | AU19: 9.9 | AW19: 17 | AY19: 14.4 | AZ19: 0.6 | BA19: 6.9 | BB19: 9.2 | BC19: 12.7 | BD19: 19.9 | BE19: 4.8 | BF19: 2.9 | BG19: 2.4 | BH19: 2.4 | BI19: 0.2 | BK19: 19.9 | BL19: 4.8 | BM19: 8.1 | BN19: 581
B20: 6:30 | C20: 15 | D20: 14.7 | E20: 6.1 | F20: 17 | G20: 2 | I20: 10.8 | J20: 0.1 | K20: 14.4 | M20: 19.5 | N20: 20.2 | O20: 12.2 | P20: 3.7 | Q20: 4.7 | R20: 19.6 | S20: 19.8 | T20: 20 | U20: 18.9 | V20: 20.7 | W20: 19.4 | X20: 69.7 | Y20: 1.1 | Z20: 9.6 | AA20: 13.7 | AD20: 20 | AE20: 5.7 | AF20: 20.4 | AG20: 20.4 | AI20: 5.8 | AJ20: 27.2 | AK20: 3.4 | AL20: 2.9 | AM20: 3.5 | AN20: 18.7 | AQ20: 3.6 | AS20: 11.3 | AT20: 5.4 | AU20: 10 | AW20: 55.6 | AY20: 48.9 | AZ20: 0.6 | BA20: 13.5 | BB20: 10.9 | BC20: 21.8 | BD20: 19.8 | BE20: 4.8 | BF20: 2.9 | BG20: 2.4 | BH20: 2.4 | BI20: 1.1 | BK20: 19.6 | BL20: 4.8 | BM20: 14.7 | BN20: 735
B21: 7:00 | C21: 15 | D21: 14.7 | E21: 7.2 | F21: 16.9 | G21: 2 | I21: 10.2 | J21: 0.1 | K21: 14.4 | M21: 19.9 | N21: 20.2 | O21: 12.2 | P21: 3.6 | Q21: 5 | R21: 19.6 | S21: 20 | T21: 20 | U21: 18.9 | V21: 24.2 | W21: 19.8 | X21: 70.5 | Y21: 0.4 | Z21: 3.7 | AA21: 21.8 | AD21: 20 | AE21: 5.6 | AF21: 20.4 | AG21: 20.4 | AI21: 6.2 | AJ21: 48 | AK21: 4 | AL21: 3.2 | AM21: 3.5 | AN21: 18.7 | AQ21: 3.6 | AS21: 13 | AT21: 5.3 | AU21: 10 | AW21: 95.9 | AY21: 83.9 | AZ21: 0.6 | BA21: 15.9 | BB21: 11.3 | BC21: 23.3 | BD21: 19.9 | BE21: 4.8 | BF21: 2.9 | BG21: 2.4 | BH21: 2.4 | BI21: 3 | BK21: 19.6 | BL21: 4.7 | BM21: 16.8 | BN21: 849.6
B22: 7:30 | C22: 15 | D22: 14.2 | E22: 7.1 | F22: 11.4 | G22: 2 | I22: 10.3 | J22: 0.1 | K22: 13.5 | M22: 20 | N22: 20.4 | O22: 12.2 | P22: 3.6 | Q22: 4.9 | R22: 19.8 | S22: 20 | T22: 20 | U22: 18.9 | V22: 23.5 | W22: 11.3 | X22: 69.9 | Y22: 1.7 | Z22: 8.5 | AA22: 31.6 | AD22: 20 | AE22: 5.6 | AF22: 20.4 | AG22: 20.4 | AI22: 6.2 | AJ22: 63.7 | AK22: 6.6 | AL22: 5.8 | AM22: 3.6 | AN22: 18.7 | AQ22: 3.6 | AS22: 13.8 | AT22: 5.3 | AU22: 10 | AV22: 0.7 | AW22: 123.6 | AY22: 96.1 | AZ22: 0.6 | BA22: 16.9 | BB22: 16.8 | BC22: 23.4 | BD22: 20 | BE22: 4.8 | BF22: 2.9 | BG22: 2.4 | BH22: 2.4 | BI22: 5.5 | BK22: 19.8 | BL22: 4.8 | BM22: 18.2 | BN22: 922.5
B23: 8:00 | C23: 14.6 | D23: 14.2 | E23: 8.3 | F23: 5.8 | G23: 2 | I23: 10.6 | J23: 0.1 | K23: 13.5 | M23: 19.8 | N23: 20.4 | O23: 12.2 | P23: 3.5 | Q23: 4.9 | R23: 20 | S23: 20.3 | T23: 18.6 | U23: 18.9 | V23: 19.6 | W23: 7.7 | X23: 71.4 | Y23: 7.9 | Z23: 16.1 | AA23: 33.3 | AD23: 20 | AE23: 5.6 | AF23: 20.4 | AG23: 20.4 | AI23: 6.1 | AJ23: 69.1 | AK23: 3.1 | AL23: 3.1 | AM23: 3.5 | AN23: 18.7 | AP23: 0.1 | AQ23: 3.6 | AS23: 14.3 | AT23: 5.3 | AU23: 9.9 | AV23: 5.6 | AW23: 131 | AX23: 1.1 | AY23: 102.4 | AZ23: 0.6 | BA23: 17.6 | BB23: 15.3 | BC23: 31.2 | BD23: 20 | BE23: 4.8 | BF23: 2.9 | BG23: 2.4 | BH23: 2.4 | BI23: 8 | BK23: 20 | BL23: 4.8 | BM23: 19 | BN23: 956
B24: 8:30 | C24: 14.1 | D24: 14.2 | E24: 7 | F24: 6 | G24: 2 | I24: 10.4 | J24: 0.7 | K24: 13.3 | M24: 20 | N24: 20.4 | O24: 12.2 | P24: 3.6 | Q24: 4.9 | R24: 20.1 | S24: 20.1 | T24: 20 | U24: 18.8 | V24: 19.8 | W24: 9.8 | X24: 64 | Y24: 15.5 | Z24: 32.2 | AA24: 32.6 | AB24: 0.1 | AD24: 20 | AE24: 5.6 | AF24: 20.4 | AG24: 20.4 | AI24: 5.7 | AJ24: 72 | AK24: 3 | AL24: 2.3 | AM24: 3.5 | AN24: 18.7 | AP24: 0.2 | AQ24: 3.6 | AR24: 1.2 | AS24: 14.7 | AT24: 5.5 | AU24: 10 | AV24: 8.4 | AW24: 135.4 | AX24: 0.7 | AY24: 106.1 | AZ24: 0.6 | BA24: 18 | BB24: 19 | BC24: 31.9 | BD24: 20 | BE24: 4.7 | BF24: 2.9 | BG24: 2.4 | BH24: 2.4 | BI24: 10.4 | BK24: 20.2 | BL24: 4.8 | BM24: 19.4 | BN24: 995.9
B25: 9:00 | C25: 14.4 | D25: 14.2 | E25: 9 | F25: 5.7 | G25: 2 | I25: 11.2 | J25: 0.8 | K25: 13.4 | M25: 20 | N25: 20.4 | O25: 12.2 | P25: 3.6 | Q25: 4.9 | R25: 20 | S25: 20.4 | T25: 20 | U25: 18.8 | V25: 18.1 | W25: 11.5 | X25: 60.8 | Y25: 18.3 | Z25: 32.3 | AA25: 33.4 | AB25: 0.3 | AC25: 0.5 | AD25: 19.9 | AE25: 5.6 | AF25: 20.4 | AG25: 20.4 | AI25: 5.7 | AJ25: 74.2 | AK25: 2.8 | AL25: 1.2 | AM25: 3.5 | AN25: 18.7 | AP25: 0.2 | AQ25: 3.6 | AR25: 2.6 | AS25: 15 | AT25: 5.3 | AU25: 10 | AV25: 8.7 | AW25: 138.5 | AX25: 0.3 | AY25: 108.6 | AZ25: 0.6 | BA25: 18.4 | BB25: 16.2 | BC25: 38.9 | BD25: 20 | BE25: 4.8 | BF25: 2.8 | BG25: 2.4 | BH25: 2.4 | BI25: 12.4 | BK25: 20 | BL25: 4.8 | BM25: 19.7 | BN25: 1014.8
B26: 9:30 | C26: 14 | D26: 14.6 | E26: 9.2 | F26: 5.6 | G26: 2 | I26: 9.8 | J26: 1 | K26: 14 | M26: 20.1 | N26: 20.4 | O26: 12.2 | P26: 3.6 | Q26: 4.9 | R26: 20 | S26: 20.1 | T26: 20 | U26: 18.8 | V26: 16.3 | W26: 27.4 | X26: 68.3 | Y26: 21.1 | Z26: 34.4 | AA26: 33.9 | AB26: 1.3 | AC26: 0.6 | AD26: 19.8 | AE26: 5.6 | AF26: 20.4 | AG26: 20.4 | AI26: 5.8 | AJ26: 75.9 | AK26: 3.7 | AL26: 2.4 | AM26: 3.6 | AN26: 18.7 | AP26: 0.3 | AQ26: 3.6 | AR26: 4.1 | AS26: 15.3 | AT26: 5.5 | AU26: 9.9 | AV26: 4 | AW26: 141.1 | AY26: 111 | AZ26: 0.6 | BA26: 18.7 | BB26: 19.9 | BC26: 36.2 | BD26: 20 | BE26: 4.8 | BF26: 2.8 | BG26: 2.4 | BH26: 2.4 | BI26: 14.2 | BK26: 20 | BL26: 4.8 | BM26: 19.8 | BN26: 1051.3
B27: 10:00 | C27: 12.1 | D27: 14.5 | E27: 7.4 | F27: 5.6 | G27: 2 | I27: 9.4 | J27: 1.1 | K27: 14.2 | M27: 20.1 | N27: 20.4 | O27: 12.2 | P27: 3.6 | Q27: 4.9 | R27: 20 | S27: 20.3 | T27: 20 | U27: 18.8 | V27: 13.9 | W27: 47.8 | X27: 89.6 | Y27: 45.1 | Z27: 56.6 | AA27: 34.8 | AB27: 3.9 | AC27: 1.5 | AD27: 19.6 | AE27: 5.6 | AF27: 20.4 | AG27: 20.4 | AI27: 5.6 | AJ27: 79.1 | AK27: 2.1 | AL27: 2 | AM27: 3.6 | AN27: 18.7 | AP27: 0.3 | AQ27: 3.6 | AR27: 5.8 | AS27: 15.3 | AT27: 5.5 | AU27: 9.9 | AV27: 2.9 | AW27: 142.5 | AY27: 108.2 | AZ27: 0.6 | BA27: 19.1 | BB27: 21 | BC27: 42.7 | BD27: 20 | BE27: 4.8 | BF27: 2.8 | BG27: 2.4 | BH27: 2.4 | BI27: 15.8 | BK27: 20 | BL27: 4.8 | BM27: 19.9 | BN27: 1147.2
B28: 10:30 | C28: 12 | D28: 14.2 | E28: 8.4 | F28: 5.6 | G28: 2 | I28: 9.7 | J28: 1.2 | K28: 14.2 | M28: 20.2 | N28: 20.4 | O28: 12.2 | P28: 3.6 | Q28: 4.9 | R28: 20 | S28: 20.3 | T28: 20 | U28: 18.9 | V28: 15.6 | W28: 57.5 | X28: 98.4 | Y28: 58.3 | Z28: 72.2 | AA28: 39.5 | AB28: 5.9 | AC28: 3.4 | AD28: 19.7 | AE28: 5.6 | AF28: 20.4 | AG28: 20.4 | AI28: 5.6 | AJ28: 74.6 | AK28: 3.2 | AL28: 2.3 | AM28: 3.6 | AN28: 18.7 | AP28: 0.4 | AQ28: 3.5 | AR28: 6.6 | AS28: 15.6 | AT28: 5.4 | AU28: 9.9 | AV28: 2 | AW28: 146 | AY28: 104 | AZ28: 0.6 | BA28: 19.6 | BB28: 22.7 | BC28: 61.4 | BD28: 20 | BE28: 4.8 | BF28: 2.6 | BG28: 2.3 | BH28: 2.4 | BI28: 16.5 | BK28: 20 | BL28: 4.8 | BM28: 19.9 | BN28: 1223.7
B29: 11:00 | C29: 12.1 | D29: 14.6 | E29: 7.9 | F29: 5.7 | G29: 2 | I29: 10 | J29: 1.3 | K29: 14.2 | M29: 20.2 | N29: 20.4 | O29: 12.2 | P29: 3.6 | Q29: 4.9 | R29: 20 | S29: 19.5 | T29: 20 | U29: 18.9 | V29: 14 | W29: 57.7 | X29: 94.6 | Y29: 55.9 | Z29: 76.4 | AA29: 39.6 | AB29: 6.9 | AC29: 2.6 | AD29: 19.7 | AE29: 5.5 | AF29: 20.4 | AG29: 20.4 | AI29: 5.6 | AJ29: 80.5 | AK29: 4.9 | AL29: 4.5 | AM29: 3.6 | AN29: 18.7 | AP29: 0.4 | AQ29: 3.5 | AR29: 7.4 | AS29: 15.6 | AT29: 5.4 | AU29: 10 | AV29: 11.2 | AW29: 101 | AX29: 2.7 | AY29: 69.6 | AZ29: 0.6 | BA29: 19.7 | BB29: 19.8 | BC29: 58.1 | BD29: 20 | BE29: 4.8 | BF29: 2.6 | BG29: 2.3 | BH29: 2.4 | BI29: 15.8 | BK29: 20 | BL29: 4.8 | BM29: 19.9 | BN29: 1156.6
B30: 11:30 | C30: 11.5 | D30: 12.5 | E30: 8.3 | F30: 5.7 | G30: 2 | I30: 9.4 | J30: 1.2 | K30: 13.9 | M30: 20.1 | N30: 20.4 | O30: 12.2 | P30: 3.6 | Q30: 4.9 | R30: 20 | S30: 20 | T30: 20 | U30: 18.8 | V30: 16.1 | W30: 61.5 | X30: 91.6 | Y30: 69.8 | Z30: 79 | AA30: 41.1 | AB30: 8.5 | AC30: 5.7 | AD30: 19.5 | AE30: 5.5 | AF30: 20.4 | AG30: 20.4 | AI30: 5.6 | AJ30: 80.5 | AK30: 4.6 | AL30: 4.7 | AM30: 3.6 | AN30: 18.7 | AP30: 0.4 | AQ30: 3.6 | AR30: 7.9 | AS30: 15.5 | AT30: 5.3 | AU30: 9.9 | AV30: 24.1 | AW30: 106.6 | AX30: 17.3 | AY30: 83.9 | AZ30: 0.6 | BA30: 19.6 | BB30: 21.9 | BC30: 58.9 | BD30: 20 | BE30: 4.8 | BF30: 2.6 | BG30: 2.2 | BH30: 2.4 | BI30: 18.1 | BK30: 20 | BL30: 4.8 | BM30: 19.9 | BN30: 1231.6
B31: 12:00 | C31: 14.8 | D31: 5.1 | E31: 8.1 | F31: 5.7 | G31: 2 | I31: 9.5 | J31: 1 | K31: 13.5 | M31: 20 | N31: 20.4 | O31: 12.2 | P31: 3.6 | Q31: 4.9 | R31: 20 | S31: 20.1 | T31: 20 | U31: 18.8 | V31: 19.6 | W31: 65.5 | X31: 87.8 | Y31: 73.2 | Z31: 86.3 | AA31: 40.5 | AB31: 9.7 | AC31: 6.5 | AD31: 19.2 | AE31: 5.6 | AF31: 20.4 | AG31: 20.4 | AI31: 5.7 | AJ31: 80.5 | AK31: 5.4 | AL31: 6.7 | AM31: 3.6 | AN31: 18.7 | AP31: 0.5 | AQ31: 3.6 | AR31: 8.5 | AS31: 15.1 | AT31: 5.5 | AU31: 10 | AV31: 36 | AW31: 129.3 | AX31: 38.4 | AY31: 105 | AZ31: 0.6 | BA31: 19.5 | BB31: 21.5 | BC31: 65.8 | BD31: 20 | BE31: 4.7 | BF31: 2.6 | BG31: 2.2 | BH31: 2.4 | BI31: 15.5 | BK31: 20 | BL31: 4.8 | BM31: 19.9 | BN31: 1326.4
B32: 12:30 | C32: 15.6 | D32: 5.1 | E32: 7.4 | F32: 5.7 | G32: 2 | I32: 9.9 | J32: 1.3 | K32: 13.5 | M32: 20.2 | N32: 20.4 | O32: 12.2 | P32: 3.6 | Q32: 4.9 | R32: 20 | S32: 20.3 | T32: 20 | U32: 18.9 | V32: 20.8 | W32: 62.9 | X32: 87.3 | Y32: 76.5 | Z32: 85 | AA32: 40.5 | AB32: 11.1 | AC32: 5.7 | AD32: 19.1 | AE32: 5.6 | AF32: 20.4 | AG32: 20.4 | AH32: 10.2 | AI32: 6.1 | AJ32: 80.5 | AK32: 9.2 | AL32: 8.8 | AM32: 3.6 | AN32: 18.7 | AP32: 0.5 | AQ32: 3.6 | AR32: 8.7 | AS32: 14.7 | AT32: 5.4 | AU32: 10 | AV32: 48.8 | AW32: 145.6 | AX32: 38 | AY32: 114.5 | AZ32: 0.6 | BA32: 19.2 | BB32: 23.8 | BC32: 68.5 | BD32: 20 | BE32: 4.6 | BF32: 2.6 | BG32: 2.2 | BH32: 2.4 | BI32: 15.2 | BK32: 20 | BL32: 4.8 | BM32: 19.9 | BN32: 1387
B33: 13:00 | C33: 15.5 | D33: 5.5 | E33: 8.1 | F33: 5.7 | G33: 2 | I33: 9.4 | J33: 1.3 | K33: 13.5 | M33: 20.1 | N33: 20.3 | O33: 12 | P33: 3.6 | Q33: 4.9 | R33: 19.9 | T33: 19.8 | U33: 18.9 | V33: 20.2 | W33: 60 | X33: 90.7 | Y33: 82.9 | Z33: 90.8 | AA33: 40.5 | AB33: 9.5 | AC33: 10 | AD33: 18.8 | AE33: 5.6 | AF33: 20.4 | AG33: 20.4 | AH33: 10.2 | AI33: 6.1 | AJ33: 80.4 | AK33: 10.5 | AL33: 9.5 | AM33: 3.6 | AN33: 18.7 | AP33: 0.2 | AQ33: 3.6 | AR33: 8 | AS33: 14.4 | AT33: 5.3 | AU33: 9.9 | AV33: 74.7 | AW33: 140.9 | AX33: 59.4 | AY33: 112.6 | AZ33: 0.6 | BA33: 19.2 | BB33: 24.2 | BC33: 69.6 | BD33: 20 | BE33: 4.6 | BF33: 2.6 | BG33: 2.2 | BH33: 2.4 | BI33: 15.3 | BK33: 20 | BL33: 4.8 | BM33: 19.9 | BN33: 1423.7
B34: 13:30 | C34: 15.6 | D34: 9.9 | E34: 8 | F34: 5.7 | G34: 2 | I34: 9.7 | J34: 1.2 | K34: 13.5 | M34: 20.1 | N34: 20.4 | O34: 12 | P34: 3.6 | Q34: 4.9 | R34: 20 | T34: 20 | U34: 18.8 | V34: 17.2 | W34: 67.4 | X34: 94.7 | Y34: 84.3 | Z34: 89.6 | AA34: 25 | AB34: 10.1 | AC34: 11.3 | AD34: 18.9 | AE34: 5.6 | AF34: 20.4 | AG34: 20.4 | AH34: 10.2 | AI34: 6.1 | AJ34: 80.4 | AK34: 9.4 | AL34: 11 | AM34: 3.6 | AN34: 18.7 | AP34: 0.2 | AQ34: 3.6 | AR34: 6.5 | AS34: 15.3 | AT34: 5.4 | AU34: 9.9 | AV34: 77.8 | AW34: 116.9 | AX34: 96.9 | AY34: 112.5 | AZ34: 0.6 | BA34: 19 | BB34: 22.3 | BC34: 72.8 | BD34: 20 | BE34: 4.6 | BF34: 2.6 | BG34: 2.2 | BH34: 2.4 | BI34: 16.8 | BK34: 20 | BL34: 4.8 | BM34: 19.9 | BN34: 1442.7
B35: 14:00 | C35: 15 | D35: 9.9 | E35: 7.2 | F35: 5.7 | G35: 2 | I35: 9.6 | J35: 1.2 | K35: 13.6 | M35: 20.1 | N35: 20.4 | O35: 12 | P35: 3.6 | Q35: 4.9 | R35: 20 | S35: 20.9 | T35: 20 | U35: 18.9 | V35: 19 | W35: 69.9 | X35: 74.5 | Y35: 87.3 | Z35: 90.9 | AA35: 34.5 | AB35: 10.3 | AC35: 8.6 | AD35: 19.1 | AE35: 5.5 | AF35: 20.4 | AG35: 20.4 | AH35: 10.2 | AI35: 6.1 | AJ35: 80.4 | AK35: 13.9 | AL35: 12.4 | AM35: 3.6 | AN35: 18.7 | AP35: 0.2 | AQ35: 3.6 | AR35: 5.2 | AS35: 15.3 | AT35: 5.4 | AU35: 9.9 | AV35: 92.6 | AW35: 106.7 | AX35: 110.6 | AY35: 106.9 | AZ35: 0.6 | BA35: 18.7 | BB35: 24.9 | BC35: 70.5 | BD35: 20 | BE35: 4.5 | BF35: 2.6 | BG35: 2.2 | BH35: 2.4 | BI35: 16.8 | BK35: 20 | BL35: 4.8 | BM35: 19.5 | BN35: 1474.6
B36: 14:30 | C36: 14.5 | D36: 9.9 | E36: 8 | F36: 9.7 | G36: 2 | I36: 10.4 | J36: 0.9 | K36: 13.6 | M36: 20.2 | N36: 20.4 | O36: 12 | P36: 3.6 | Q36: 4.9 | R36: 20 | S36: 20.2 | T36: 20 | U36: 18.9 | V36: 18.4 | W36: 70.2 | X36: 93.7 | Y36: 89.1 | Z36: 90.6 | AA36: 39.6 | AB36: 10.8 | AC36: 10 | AD36: 19.1 | AE36: 5.4 | AF36: 20.4 | AG36: 20.4 | AH36: 10.2 | AI36: 6.1 | AJ36: 80.4 | AK36: 16.5 | AL36: 11.8 | AM36: 3.6 | AN36: 18.7 | AP36: 0.2 | AQ36: 3.6 | AR36: 3.5 | AS36: 14.9 | AT36: 5.4 | AU36: 9.9 | AV36: 133 | AW36: 78.7 | AX36: 113.6 | AY36: 63.2 | AZ36: 0.6 | BA36: 18.3 | BB36: 22.8 | BC36: 72.6 | BD36: 20 | BE36: 4.5 | BF36: 2.6 | BG36: 2.2 | BH36: 2.4 | BI36: 15.5 | BK36: 20 | BL36: 4.8 | BM36: 18.4 | BN36: 1474.9
B37: 15:00 | C37: 15 | D37: 10 | E37: 6.8 | F37: 20.2 | G37: 2 | I37: 9.5 | J37: 0.9 | K37: 13.6 | M37: 20.2 | N37: 20.4 | O37: 12 | P37: 3.6 | Q37: 4.9 | R37: 20 | S37: 20.1 | T37: 20 | U37: 18.9 | V37: 20.7 | W37: 69.2 | X37: 101.3 | Y37: 90.6 | Z37: 90.1 | AA37: 39.6 | AB37: 10.6 | AC37: 10.1 | AD37: 19.1 | AE37: 5.4 | AF37: 20.4 | AG37: 20.4 | AH37: 10.2 | AI37: 6 | AJ37: 78.5 | AK37: 16.8 | AL37: 12.6 | AM37: 3.6 | AN37: 18.7 | AP37: 0.2 | AQ37: 3.6 | AR37: 1.7 | AS37: 10.4 | AT37: 5.3 | AU37: 10 | AV37: 123.2 | AW37: 54.5 | AX37: 117.2 | AY37: 54 | AZ37: 0.6 | BA37: 18.3 | BB37: 22.7 | BC37: 72.1 | BD37: 20 | BE37: 4.5 | BF37: 2.6 | BG37: 2.2 | BH37: 2.4 | BI37: 13.7 | BK37: 20 | BL37: 4.8 | BM37: 18.1 | BN37: 1444.1
B38: 15:30 | C38: 15 | D38: 10.5 | E38: 5.5 | F38: 20.2 | G38: 2 | I38: 10.6 | J38: 0.8 | K38: 13.6 | M38: 20.2 | N38: 20.4 | O38: 12 | P38: 3.6 | Q38: 4.9 | R38: 20 | S38: 20.5 | T38: 20 | U38: 18.9 | V38: 19.4 | W38: 68.4 | X38: 105.9 | Y38: 89 | Z38: 93.3 | AA38: 23.9 | AB38: 9.9 | AC38: 8 | AD38: 19.1 | AE38: 5.5 | AF38: 20.4 | AG38: 20.4 | AH38: 10.2 | AI38: 5.8 | AJ38: 76.2 | AK38: 14.3 | AL38: 13.6 | AM38: 3.6 | AN38: 18.7 | AP38: 0.2 | AQ38: 3.6 | AS38: 10.2 | AT38: 5.4 | AU38: 9.9 | AV38: 123.2 | AW38: 35.3 | AX38: 115.9 | AY38: 30.2 | AZ38: 0.6 | BA38: 17.9 | BB38: 24.5 | BC38: 81.5 | BD38: 20 | BE38: 4.5 | BF38: 2.6 | BG38: 2.2 | BH38: 2.4 | BI38: 11.8 | BK38: 20 | BL38: 4.8 | BM38: 10.5 | BN38: 1381.5
B39: 16:00 | C39: 15.2 | D39: 13.6 | E39: 8.7 | F39: 20.2 | G39: 2 | I39: 10.1 | J39: 0.6 | K39: 13.6 | M39: 20.2 | N39: 20.4 | O39: 12 | P39: 3.6 | Q39: 4.9 | R39: 20 | S39: 20.4 | T39: 20 | U39: 18.9 | V39: 15.3 | W39: 54.9 | X39: 104.3 | Y39: 87.5 | Z39: 90.4 | AA39: 19 | AB39: 10.8 | AC39: 8.9 | AD39: 19.1 | AE39: 5.5 | AF39: 20.4 | AG39: 20.4 | AH39: 10.2 | AI39: 5.9 | AJ39: 71.8 | AK39: 16.8 | AL39: 15.6 | AM39: 3.6 | AN39: 18.7 | AP39: 0.1 | AQ39: 3.6 | AS39: 10.4 | AT39: 5.4 | AU39: 9.9 | AV39: 113.3 | AW39: 31 | AX39: 109.9 | AY39: 24.4 | AZ39: 0.6 | BA39: 15.9 | BB39: 24.6 | BC39: 82.5 | BD39: 20 | BE39: 4.5 | BF39: 2.6 | BG39: 2.2 | BH39: 2.4 | BI39: 9.7 | BK39: 20 | BL39: 4.8 | BM39: 5.8 | BN39: 1327.1
B40: 16:30 | C40: 15.3 | D40: 13.6 | E40: 9 | F40: 20.2 | G40: 2 | I40: 9.6 | J40: 0.4 | K40: 13.3 | M40: 20 | N40: 20.3 | O40: 12 | P40: 3.6 | Q40: 4.9 | R40: 19.9 | S40: 19.9 | T40: 20 | U40: 18.9 | V40: 14.4 | W40: 46.3 | X40: 110 | Y40: 83.3 | Z40: 89.1 | AA40: 25.2 | AB40: 7.2 | AC40: 8.1 | AD40: 19.1 | AE40: 5.4 | AF40: 20.4 | AG40: 20.4 | AH40: 10.2 | AI40: 5.8 | AJ40: 65.3 | AK40: 14.7 | AL40: 15.1 | AM40: 3.6 | AN40: 18.7 | AP40: 0.1 | AQ40: 3.6 | AS40: 11.8 | AT40: 5.4 | AU40: 10 | AV40: 133.9 | AW40: 26.4 | AX40: 123.5 | AY40: 28.2 | AZ40: 0.6 | BA40: 10.2 | BB40: 26.4 | BC40: 86.2 | BD40: 20 | BE40: 4.5 | BF40: 2.6 | BG40: 2.2 | BH40: 2.4 | BI40: 7.3 | BK40: 20 | BL40: 4.8 | BM40: 3.2 | BN40: 1338.5
B41: 17:00 | C41: 14.7 | D41: 14 | E41: 8.6 | F41: 20.2 | G41: 2 | I41: 9.9 | J41: 0.3 | K41: 13 | M41: 20.2 | N41: 20.4 | O41: 12 | P41: 3.5 | Q41: 4.9 | R41: 20 | S41: 20.3 | T41: 20 | U41: 18.9 | V41: 12.8 | W41: 36.9 | X41: 110.4 | Y41: 70.8 | Z41: 84.1 | AA41: 24.9 | AB41: 7.1 | AC41: 8.1 | AD41: 19.2 | AE41: 5.4 | AF41: 20.4 | AG41: 20.4 | AH41: 10.2 | AI41: 5.5 | AJ41: 47.3 | AK41: 14.2 | AL41: 13.8 | AM41: 3.6 | AN41: 18.7 | AP41: 0.1 | AQ41: 3.6 | AS41: 9.6 | AT41: 5.5 | AU41: 9.9 | AV41: 138 | AW41: 15.1 | AX41: 132.1 | AY41: 11.8 | AZ41: 0.6 | BA41: 8.9 | BB41: 31.2 | BC41: 86.2 | BD41: 20 | BE41: 4.5 | BF41: 2.6 | BG41: 2.3 | BH41: 2.4 | BI41: 4.7 | BK41: 20 | BL41: 4.8 | BM41: 2.6 | BN41: 1273.2
B42: 17:30 | C42: 15.2 | D42: 14.5 | E42: 7.7 | F42: 20.3 | G42: 2 | I42: 10.3 | J42: 0.1 | K42: 13 | M42: 20.1 | N42: 20.4 | O42: 12 | P42: 3.6 | Q42: 4.8 | R42: 19.8 | S42: 20.2 | T42: 20 | U42: 18.9 | V42: 16.6 | W42: 41.6 | X42: 110.2 | Y42: 74.2 | Z42: 89.6 | AA42: 10.9 | AB42: 7.3 | AC42: 9.1 | AD42: 19.2 | AE42: 5.4 | AF42: 20.4 | AG42: 20.4 | AH42: 10.2 | AI42: 5.5 | AJ42: 23.2 | AK42: 14.4 | AL42: 12.4 | AM42: 3.6 | AN42: 18.7 | AP42: 0.1 | AQ42: 3.6 | AS42: 4.3 | AT42: 5.3 | AU42: 9.9 | AV42: 142.2 | AW42: 21.4 | AX42: 130.3 | AY42: 11.6 | AZ42: 0.6 | BA42: 4.9 | BB42: 30.2 | BC42: 86.7 | BD42: 20 | BE42: 4.6 | BF42: 2.6 | BG42: 2.3 | BH42: 2.4 | BI42: 2.4 | BK42: 19.9 | BL42: 4.8 | BM42: 1.6 | BN42: 1247.5
B43: 18:00 | C43: 15 | D43: 14.6 | E43: 7.1 | F43: 20.3 | G43: 2 | I43: 9.9 | K43: 13 | M43: 20 | N43: 20.3 | O43: 12 | P43: 3.6 | Q43: 4.6 | R43: 19.8 | S43: 19.9 | T43: 20 | U43: 18.9 | V43: 15.4 | W43: 46.9 | X43: 109.1 | Y43: 85.7 | Z43: 88.4 | AA43: 2.5 | AB43: 8.9 | AC43: 10.6 | AD43: 19.2 | AE43: 5.4 | AF43: 20.4 | AG43: 20.4 | AH43: 10.2 | AI43: 6.1 | AJ43: 7.8 | AK43: 11.2 | AL43: 8.8 | AM43: 3.6 | AN43: 18.7 | AQ43: 3.6 | AS43: 0.5 | AT43: 5.5 | AU43: 9.9 | AV43: 142.3 | AW43: 6.1 | AX43: 129 | AY43: 5.7 | AZ43: 0.6 | BA43: 0.4 | BB43: 27.5 | BC43: 87.6 | BD43: 20 | BE43: 4.6 | BF43: 2.6 | BG43: 2.3 | BH43: 2.4 | BI43: 0.8 | BK43: 19.8 | BL43: 4.8 | BM43: 0.2 | BN43: 1196.5
B44: 18:30 | C44: 15.3 | D44: 14.6 | E44: 8.5 | F44: 20.4 | G44: 2 | I44: 10.4 | K44: 12.9 | M44: 20.2 | N44: 20.4 | O44: 12 | P44: 3.6 | Q44: 4.5 | R44: 19.8 | S44: 20.2 | T44: 20 | U44: 18.9 | V44: 13.9 | W44: 48.8 | X44: 107.1 | Y44: 86.8 | Z44: 92 | AB44: 9.2 | AC44: 8.2 | AD44: 18.9 | AE44: 5.4 | AF44: 20.4 | AG44: 20.4 | AH44: 10.2 | AI44: 6.1 | AK44: 12.5 | AL44: 8.9 | AM44: 3.6 | AN44: 18.7 | AQ44: 3.6 | AT44: 5.5 | AU44: 9.9 | AV44: 144.8 | AX44: 128.1 | AZ44: 0.6 | BB44: 26.2 | BC44: 84.1 | BD44: 20 | BE44: 4.7 | BF44: 2.7 | BG44: 2.3 | BH44: 2.4 | BK44: 19.9 | BL44: 4.8 | BN44: 1174.4
B45: 19:00 | C45: 15.5 | D45: 14.6 | E45: 8.8 | F45: 20.3 | G45: 2 | I45: 10.2 | K45: 12.3 | M45: 20.2 | N45: 20.4 | O45: 12 | P45: 3.5 | Q45: 4.6 | R45: 20 | S45: 20.5 | T45: 19.5 | U45: 18.9 | V45: 17.2 | W45: 41.1 | X45: 99.5 | Y45: 84.6 | Z45: 93.5 | AB45: 9 | AC45: 7 | AD45: 18.9 | AE45: 5.4 | AF45: 20.4 | AG45: 20.4 | AH45: 10.2 | AI45: 6.1 | AK45: 7.5 | AL45: 6.7 | AM45: 3.6 | AN45: 18.7 | AQ45: 3.6 | AT45: 5.5 | AU45: 9.9 | AV45: 122.2 | AX45: 122.5 | AZ45: 0.6 | BB45: 26.9 | BC45: 86.7 | BD45: 20 | BE45: 4.7 | BF45: 2.7 | BG45: 2.4 | BH45: 2.4 | BK45: 20 | BL45: 4.8 | BN45: 1128
B46: 19:30 | C46: 15.2 | D46: 14.7 | E46: 8.6 | F46: 20.3 | G46: 2 | I46: 10.7 | K46: 12.3 | M46: 20.2 | N46: 20.4 | O46: 12 | P46: 3.6 | Q46: 4.6 | R46: 20 | S46: 20.5 | T46: 20 | U46: 18.9 | V46: 15.7 | W46: 37.4 | X46: 97.3 | Y46: 89.9 | Z46: 91.9 | AB46: 11.5 | AC46: 8.5 | AD46: 18.9 | AE46: 5.4 | AF46: 20.4 | AG46: 20.4 | AH46: 10.2 | AI46: 6.1 | AK46: 8.1 | AL46: 6.2 | AM46: 3.6 | AN46: 18.7 | AQ46: 3.6 | AT46: 5.5 | AU46: 9.9 | AV46: 112.4 | AX46: 115.9 | AZ46: 0.6 | BB46: 26.5 | BC46: 75.7 | BD46: 20 | BE46: 4.7 | BF46: 2.7 | BG46: 2.4 | BH46: 2.4 | BK46: 20 | BL46: 4.8 | BN46: 1101.3
B47: 20:00 | C47: 15 | D47: 14.7 | E47: 8.8 | F47: 20.4 | G47: 2 | I47: 10.4 | K47: 12.2 | M47: 20.2 | N47: 20.4 | O47: 12 | P47: 3.5 | Q47: 4.6 | R47: 20 | S47: 20.5 | T47: 20 | U47: 18.9 | V47: 13.3 | W47: 33 | X47: 94.2 | Y47: 88.6 | Z47: 96.4 | AB47: 6.9 | AC47: 4.7 | AD47: 18.9 | AE47: 5.4 | AF47: 20.4 | AG47: 20.4 | AH47: 10.2 | AI47: 6.1 | AK47: 9.4 | AL47: 6.7 | AM47: 3.5 | AN47: 18.7 | AQ47: 3.6 | AT47: 5.3 | AU47: 9.9 | AV47: 100.1 | AX47: 107.9 | AZ47: 0.6 | BB47: 19.7 | BC47: 64.6 | BD47: 20 | BE47: 4.7 | BF47: 2.9 | BG47: 2.4 | BH47: 2.4 | BK47: 20 | BL47: 4.8 | BN47: 1049.3
B48: 20:30 | C48: 15 | D48: 15 | E48: 7.7 | F48: 20.4 | G48: 2 | I48: 10.6 | K48: 12.2 | M48: 20.2 | N48: 20.4 | O48: 12 | P48: 3.5 | Q48: 4.5 | R48: 20 | S48: 20.4 | T48: 20 | U48: 18.9 | V48: 7.9 | W48: 30.1 | X48: 85.3 | Y48: 74.3 | Z48: 93.7 | AB48: 10.5 | AC48: 6.9 | AD48: 18.9 | AE48: 5.4 | AF48: 20.4 | AG48: 20.4 | AH48: 10.2 | AI48: 6.1 | AK48: 7.3 | AL48: 10.2 | AM48: 3.5 | AN48: 18.7 | AQ48: 3.6 | AT48: 5.5 | AU48: 9.9 | AV48: 60.9 | AX48: 96.2 | AZ48: 0.6 | BB48: 18.4 | BC48: 59.7 | BD48: 20 | BE48: 4.7 | BF48: 2.9 | BG48: 2.4 | BH48: 2.4 | BK48: 20 | BL48: 4.8 | BN48: 964.6
B49: 21:00 | C49: 15 | D49: 15.3 | E49: 7.7 | F49: 20.4 | G49: 2 | I49: 10.4 | K49: 12.2 | M49: 20.2 | N49: 20.4 | O49: 11.8 | P49: 3.5 | Q49: 4.5 | R49: 20 | S49: 20.4 | T49: 20 | U49: 18.9 | V49: 5.9 | W49: 34.1 | X49: 78.4 | Y49: 76.4 | Z49: 99 | AB49: 5.5 | AC49: 2.1 | AD49: 18.9 | AE49: 5.4 | AF49: 20.4 | AG49: 20.4 | AH49: 10.2 | AI49: 6.1 | AK49: 5.6 | AL49: 5.3 | AM49: 3.6 | AN49: 18.7 | AQ49: 3.5 | AT49: 5.5 | AU49: 9.9 | AV49: 57.9 | AX49: 74.5 | AZ49: 0.6 | BB49: 14.8 | BC49: 58.1 | BD49: 20 | BE49: 4.8 | BF49: 2.9 | BG49: 2.4 | BH49: 2.4 | BK49: 20 | BL49: 4.8 | BN49: 920.8
B50: 21:30 | C50: 15.5 | D50: 15.8 | E50: 8.2 | F50: 20.4 | G50: 2 | I50: 9.9 | K50: 12.2 | M50: 20.2 | N50: 20.4 | O50: 11.8 | P50: 3.5 | Q50: 4.5 | R50: 20 | S50: 20 | T50: 20 | U50: 18.9 | V50: 6.9 | W50: 35 | X50: 79 | Y50: 61.4 | Z50: 95 | AB50: 4.1 | AC50: 2.5 | AD50: 18.9 | AE50: 5.4 | AF50: 20.4 | AG50: 20.4 | AH50: 10.2 | AI50: 6 | AK50: 5.4 | AL50: 4.9 | AM50: 3.6 | AN50: 18.7 | AQ50: 3.5 | AT50: 5.4 | AU50: 9.9 | AV50: 42.3 | AX50: 46.9 | AZ50: 0.6 | BB50: 16.1 | BC50: 52 | BD50: 20 | BE50: 4.8 | BF50: 2.9 | BG50: 2.4 | BH50: 2.4 | BK50: 20 | BL50: 4.8 | BN50: 855.1
B51: 22:00 | C51: 15.5 | D51: 15.9 | E51: 7.3 | F51: 20.3 | G51: 2 | I51: 10.4 | K51: 12.3 | M51: 20.2 | N51: 20.4 | O51: 11.8 | P51: 3.5 | Q51: 4.7 | R51: 20 | S51: 20.3 | T51: 20 | U51: 18.9 | V51: 7.2 | W51: 25.9 | X51: 74.2 | Y51: 43.5 | Z51: 84.3 | AB51: 2.3 | AC51: 1.7 | AD51: 18.9 | AE51: 5.4 | AF51: 20.4 | AG51: 20.4 | AH51: 10.2 | AI51: 5.4 | AK51: 6 | AL51: 5.3 | AM51: 3.5 | AN51: 18.7 | AQ51: 3.6 | AT51: 5.5 | AU51: 9.9 | AV51: 20.7 | AX51: 26.9 | AZ51: 0.6 | BB51: 15.2 | BC51: 47.3 | BD51: 20 | BE51: 4.8 | BF51: 2.9 | BG51: 2.4 | BH51: 2.4 | BK51: 20 | BL51: 4.8 | BN51: 763.8
B52: 22:30 | C52: 15 | D52: 15.9 | E52: 6.7 | F52: 20.2 | G52: 2 | I52: 10.3 | K52: 12.2 | M52: 20.2 | N52: 20.4 | O52: 11.8 | P52: 3.5 | Q52: 4.7 | R52: 20 | S52: 20.2 | T52: 19.4 | U52: 18.9 | V52: 5.7 | W52: 18.1 | X52: 74.2 | Y52: 53.9 | Z52: 89.1 | AB52: 2.6 | AC52: 2.1 | AD52: 19.1 | AE52: 5.4 | AF52: 20.4 | AG52: 20.4 | AH52: 10.2 | AI52: 5.5 | AK52: 5.6 | AL52: 4.8 | AM52: 3.5 | AN52: 18.7 | AQ52: 3.5 | AT52: 5.4 | AU52: 9.8 | AV52: 8.5 | AX52: 15 | AZ52: 0.6 | BB52: 15.9 | BC52: 43.1 | BD52: 20 | BE52: 4.8 | BF52: 2.9 | BG52: 2.4 | BH52: 2.4 | BK52: 19.9 | BL52: 4.8 | BN52: 739.7
B53: 23:00 | C53: 14.5 | D53: 15.1 | E53: 7.9 | F53: 20.2 | G53: 2 | I53: 10.1 | K53: 12.2 | M53: 20.1 | N53: 20.4 | O53: 12 | P53: 3.5 | Q53: 4.7 | R53: 19.8 | S53: 20.1 | T53: 19.9 | U53: 18.9 | V53: 7.3 | W53: 15.5 | X53: 63.8 | Y53: 35.4 | Z53: 86.1 | AB53: 1.1 | AC53: 2.1 | AD53: 19 | AE53: 6.9 | AF53: 20.4 | AG53: 20.4 | AH53: 10.2 | AI53: 5.5 | AK53: 4.3 | AL53: 5 | AM53: 3.5 | AN53: 18.7 | AQ53: 3.5 | AT53: 5.2 | AU53: 10 | AV53: 7.8 | AX53: 10.7 | AZ53: 0.6 | BB53: 19 | BC53: 43.1 | BD53: 20 | BE53: 4.8 | BF53: 2.9 | BG53: 2.4 | BH53: 2.4 | BK53: 19.8 | BL53: 4.8 | BN53: 703.6
B54: 23:30 | C54: 14.5 | D54: 15.4 | E54: 8 | F54: 20.2 | G54: 2 | I54: 9.7 | K54: 12.2 | M54: 20.2 | N54: 20.4 | O54: 12.2 | P54: 3.6 | Q54: 4.6 | R54: 19.8 | S54: 20.5 | T54: 20 | U54: 18.9 | V54: 9.6 | W54: 16.1 | X54: 63.8 | Y54: 37.9 | Z54: 93 | AB54: 1 | AC54: 1.8 | AD54: 19 | AE54: 7.8 | AF54: 20.4 | AG54: 20.4 | AH54: 10.2 | AI54: 5.5 | AK54: 6 | AL54: 4.6 | AM54: 3.6 | AN54: 18.7 | AQ54: 3.5 | AT54: 5.5 | AU54: 9.9 | AV54: 24.6 | AX54: 27.3 | AZ54: 0.6 | BB54: 15.3 | BC54: 44.8 | BD54: 20 | BE54: 4.8 | BF54: 2.9 | BG54: 2.4 | BH54: 2.4 | BK54: 19.8 | BL54: 4.8 | BN54: 750.2
B55: 0:00 | C55: 14.9 | D55: 15.5 | E55: 7.8 | F55: 20.2 | G55: 2 | I55: 9.8 | K55: 12.3 | M55: 20.2 | N55: 20.4 | O55: 12.2 | P55: 3.5 | Q55: 4.6 | R55: 19.8 | S55: 19.9 | T55: 20 | U55: 18.9 | V55: 6.3 | W55: 17.4 | X55: 57.6 | Y55: 43.5 | Z55: 74.3 | AB55: 0.9 | AC55: 1.8 | AD55: 19.7 | AE55: 7.6 | AF55: 20.4 | AG55: 20.4 | AH55: 10.2 | AI55: 5.8 | AK55: 6 | AL55: 5.2 | AM55: 3.6 | AN55: 18.7 | AQ55: 3.5 | AT55: 5.4 | AU55: 9.9 | AV55: 48.3 | AX55: 46.7 | AZ55: 0.6 | BB55: 12.8 | BC55: 46.9 | BD55: 20 | BE55: 4.8 | BF55: 2.9 | BG55: 2.4 | BH55: 2.4 | BK55: 19.9 | BL55: 4.9 | BN55: 772.8
B56: EJEC MWh | C56: 354.05 | D56: 325.2 | E56: 187.3 | F56: 360.5 | G56: 48 | H56: 0 | I56: 240.05 | J56: 8.85 | K56: 325.1 | L56: 0 | M56: 478.8 | N56: 489.05 | O56: 289.7 | P56: 85.9 | Q56: 114.7 | R56: 477.7 | S56: 464.4 | T56: 477.65 | U56: 453.3 | V56: 349.75 | W56: 845.9 | X56: 1889.8 | Y56: 1134.95 | Z56: 1469.25 | AA56: 363.05 | AB56: 110.1 | AC56: 90.25 | AD56: 467.65 | AE56: 136.05 | AF56: 489.6 | AG56: 489.6 | AH56: 122.4 | AI56: 140.45 | AJ56: 802.55 | AK56: 160.25 | AL56: 141.35 | AM56: 85.3 | AN56: 448.8 | AO56: 0 | AP56: 2.45 | AQ56: 86 | AR56: 38.85 | AS56: 156.75 | AT56: 129.8 | AU56: 238.1 | AV56: 1105.4 | AW56: 1121.55 | AX56: 1090.45 | AY56: 909.3 | AZ56: 14.4 | BA56: 197.7 | BB56: 422.25 | BC56: 1146.1 | BD56: 479.8 | BE56: 113.3 | BF56: 66.25 | BG56: 56.2 | BH56: 57.6 | BI56: 133.25 | BJ56: 0 | BK56: 478.2 | BL56: 114.7 | BM56: 188.25 | BN56: 23263.95
L70: TERMOELÉCTRICA | M70: 1399.95 | N70: 6.0176797 | O70: #FF0000
L71: SOLAR | M71: 3922.55 | N71: 16.861066 | O71: #FBFB00
L72: HIDROELÉCTRICA | M72: 7985.65 | N72: 34.326286 | O72: #00B0F0
L73: EÓLICA | M73: 9955.8 | N73: 42.794968 | O73: #FBBD00

Sheet COGENERACIÓN
B3: miércoles, 15 de Enero del 2025
B5: CENTRALES DE COGENERACIÓN DEL SEIN
B6: HORA | C6: AGRO INDUSTRIAL PARAMONGA S.A. | D6: AGROAURORA S.A.C. | E6: AGROINDUSTRIAS SAN JACINTO S.A.A. | F6: BIOENERGIA DEL CHIRA S.A. | G6: GM OPERACIONES S.A.C. | H6: SDF ENERGIA SAC | I6: TOTAL COGENERACION
C7: C.T. PARAMONGA | D7: C.T. MAPLE | E7: C.T SAN JACINTO | F7: C.T. CAÑA BRAVA | G7: C.T. REFINERÍA TALARA | H7: C.T. OQUENDO | I7: MW
B8: 0:30 | C8: 15 | D8: 14.6 | E8: 7.7 | F8: 11.1 | G8: 59.9 | H8: 32.7 | I8: 141
B9: 1:00 | C9: 15.2 | D9: 14.6 | E9: 7.3 | F9: 10.2 | G9: 59.4 | H9: 32.6 | I9: 139.3
B10: 1:30 | C10: 15 | D10: 14.6 | E10: 8.7 | F10: 9.9 | G10: 58.8 | H10: 32.6 | I10: 139.6
B11: 2:00 | C11: 15 | D11: 14.6 | E11: 9 | F11: 9.2 | G11: 59.3 | H11: 32.7 | I11: 139.8
B12: 2:30 | C12: 15 | D12: 14.6 | E12: 8.5 | F12: 9.8 | G12: 59.9 | H12: 32.7 | I12: 140.5
B13: 3:00 | C13: 15.1 | D13: 14.1 | E13: 8.2 | F13: 9.3 | G13: 60 | H13: 32.9 | I13: 139.6
B14: 3:30 | C14: 15.2 | D14: 14.6 | E14: 7.7 | F14: 9.8 | G14: 60.4 | H14: 32.8 | I14: 140.5
B15: 4:00 | C15: 15.4 | D15: 14.7 | E15: 7.8 | F15: 9.6 | G15: 59.8 | H15: 32.7 | I15: 140
B16: 4:30 | C16: 15.1 | D16: 14.6 | E16: 7.8 | F16: 9.5 | G16: 59.9 | H16: 32.8 | I16: 139.7
B17: 5:00 | C17: 15 | D17: 14.7 | E17: 6.6 | F17: 9.4 | G17: 59.9 | H17: 32.8 | I17: 138.4
B18: 5:30 | C18: 15 | D18: 14.7 | E18: 6.7 | F18: 9.7 | G18: 59.3 | H18: 32.8 | I18: 138.2
B19: 6:00 | C19: 15 | D19: 14.7 | E19: 6.5 | F19: 9.5 | G19: 59.9 | H19: 32.7 | I19: 138.3
... B56: EJEC MWh | C56: 354.05 | D56: 325.2 | E56: 187.3 | F56: 240.05 | G56: 1437.1 | H56: 775.8 | I56: 3319.5

Sheet EVO_PRO_ENE
B3: miércoles, 1 de Enero del 2025 - miércoles, 15 de Enero del 2025
B5: EVOLUCIÓN DE LA PRODUCCIÓN DE LA ENERGÍA DIARIA DE LOS INTEGRANTES DEL COES (MWh)
B6: EMPRESA | C6: CENTRAL | D6: UNIDAD | E6: TIPO | F6: Enero
F7: 1 | G7: 2 | H7: 3 | I7: 4 | J7: 5 | K7: 6 | L7: 7 | M7: 8 | N7: 9 | O7: 10 | P7: 11 | Q7: 12 | R7: 13 | S7: 14 | T7: 15 | U7: TOTAL
B8: AGRO INDUSTRIAL PARAMONGA S.A. | C8: C.T. PARAMONGA | D8: TV-01 | E8: TERMOELÉCTRICA | L8: 224.55 | M8: 388.3 | N8: 387.45 | O8: 389.1 | P8: 389.05 | Q8: 381.85 | R8: 353.1 | S8: 355.3 | T8: 354.05 | U8: 3222.75
B9: AGROAURORA S.A.C. | C9: C.T. MAPLE ETANOL | D9: TV | E9: TERMOELÉCTRICA | F9: 360 | H9: 179.75 | I9: 379.5 | J9: 393.65 | K9: 392.45 | L9: 383.75 | M9: 362.8 | N9: 358.2 | O9: 362.8 | P9: 359.2 | Q9: 375.75 | R9: 354.95 | S9: 349.4 | T9: 325.2 | U9: 4937.4
B10: AGROINDUSTRIAS SAN JACINTO S.A.A. | C10: C.T. SAN JACINTO | D10: CENTRAL | E10: TERMOELÉCTRICA | K10: 58.45 | L10: 96.65 | M10: 161.7 | N10: 175.7 | O10: 179.9 | P10: 182.405 | Q10: 177.25 | R10: 172.8 | S10: 188.05 | T10: 187.3 | U10: 1580.205
B11: ANDEAN POWER S.A.C. | C11: C.H. CARHUAC | D11: CENTRAL | E11: HIDROELÉCTRICA | F11: 436.45 | G11: 447.15 | H11: 484.25 | I11: 484.6 | J11: 483.35 | K11: 484 | L11: 450.25 | M11: 439.95 | N11: 429.3 | O11: 414.6 | P11: 437.75 | Q11: 418.5 | R11: 384.05 | S11: 410.75 | T11: 360.5 | U11: 6565.45
B12: ASOCIACIÓN SANTA LUCIA DE CHACAS | C12: C.H. HUALLIN | D12: CENTRAL | E12: HIDROELÉCTRICA | F12: 48 | G12: 45.85 | H12: 48 | I12: 48 | J12: 48 | K12: 48 | L12: 48 | M12: 48 | N12: 48 | O12: 48 | P12: 29.55 | Q12: 48 | R12: 46.9 | S12: 48 | T12: 48 | U12: 698.3
B13: ATRIA ENERGIA S.A.C. | C13: C.H. PURMACANA | D13: CENTRAL | E13: HIDROELÉCTRICA | U13: 0
B14: BIOENERGIA DEL CHIRA S.A. | C14: C.T. CAÑA BRAVA | D14: CENTRAL | E14: TERMOELÉCTRICA | F14: 230.05 | G14: 4.15 | H14: 207.1 | I14: 231.25 | J14: 226.25 | K14: 229.1 | L14: 220.25 | M14: 242.55 | N14: 215 | O14: 246.75 | P14: 247.3 | Q14: 230.9 | R14: 230.2 | S14: 243 | T14: 240.05 | U14: 3243.9
B15: CELEPSA | C15: C.H. EL PLATANAL | D15: CENTRAL | E15: HIDROELÉCTRICA | F15: 4523.65 | G15: 4474.1 | H15: 4762.5 | I15: 5166.1 | J15: 5163.45 | K15: 5266.75 | L15: 5280.35 | M15: 5023.05 | N15: 5010.85 | O15: 5120.1 | P15: 5245 | Q15: 5145.95 | R15: 5180.55 | S15: 5298.45 | T15: 5167.65 | U15: 75828.5
B16: CELEPSA RENOVABLES S.R.L. | C16: C.H. MARAÑON | D16: CENTRAL | E16: HIDROELÉCTRICA | F16: 473.65 | G16: 473.1 | H16: 415.2 | I16: 360.25 | J16: 431.7 | K16: 469.85 | L16: 472.8 | M16: 472.8 | N16: 473.1415 | O16: 472.8 | P16: 472.8 | Q16: 472.8 | R16: 472.8 | S16: 472.8 | T16: 472.8 | U16: 6879.2915
B17: CENTRALES SANTA ROSA S.A.C. | C17: C.H. SANTA ROSA I | D17: CENTRAL | E17: HIDROELÉCTRICA | F17: 25.45 | G17: 25.95 | H17: 19.75 | I17: 13.4 | J17: 18.1 | K17: 20.2 | L17: 22.1 | M17: 23.3 | N17: 24.3 | O17: 24.45 | P17: 25.2 | Q17: 25.2 | R17: 25.35 | S17: 23.95 | T17: 14.65 | U17: 331.35
B18: CENTRALES SANTA ROSA S.A.C. | C18: C.H. SANTA ROSA II | D18: CENTRAL | E18: HIDROELÉCTRICA | F18: 37.7 | G18: 37.1 | H18: 31.9 | I18: 24.55 | J18: 31.45 | K18: 35.3 | L18: 35.95 | M18: 36.35 | N18: 37.05 | O18: 37.2 | P18: 38.45 | Q18: 38.2 | R18: 37.9 | S18: 36.25 | T18: 22.3 | U18: 517.65
B19: CHINANGO S.A.C. | C19: C.H. CHIMAY | D19: CENTRAL | E19: HIDROELÉCTRICA | F19: 3094.35 | G19: 3340.85 | H19: 3399.5 | I19: 3452.55 | J19: 3481.7 | K19: 3446.85 | L19: 2227.35 | M19: 3331.064 | N19: 2748.9 | O19: 3452.7 | P19: 2273.8 | Q19: 3314.15 | R19: 3434.2 | S19: 3445.75 | T19: 3447 | U19: 47890.714
B20: CHINANGO S.A.C. | C20: C.H. YANANGO | D20: CENTRAL | E20: HIDROELÉCTRICA | F20: 816.75 | G20: 970.5 | H20: 1005.45 | I20: 1002.9 | J20: 1005 | K20: 1004.55 | L20: 1004.4 | M20: 1004.0105 | N20: 1004.4 | O20: 993.6 | P20: 999.4 | Q20: 1004.85 | R20: 993.1 | S20: 929.1 | T20: 853.8 | U20: 14591.81
B21: COLCA SOLAR S.A.C. | C21: C.S. YARUCAYA | D21: CENTRAL | E21: SOLAR | F21: 4.85 | G21: 4.35 | H21: 6.75 | I21: 6.6 | J21: 7.6 | K21: 4.8 | L21: 5.35 | M21: 7.05 | N21: 7.3 | O21: 4.7 | P21: 6.9 | Q21: 7.95 | R21: 6.7 | S21: 6.95 | T21: 8.85 | U21: 96.7
B22: EGASA | C22: C.H. CHARCANI III | D22: CENTRAL | E22: HIDROELÉCTRICA | F22: 144.4 | G22: 148.8 | H22: 151.3 | I22: 151.2 | J22: 154.25 | K22: 151.25 | L22: 151.15 | M22: 151.2 | N22: 151.2 | O22: 153.1 | P22: 156.51 | Q22: 156.7 | R22: 156.15 | S22: 155.05 | T22: 154.45 | U22: 2286.71
B23: EGASA | C23: C.H. CHARCANI IV | D23: CENTRAL | E23: HIDROELÉCTRICA | F23: 239.55 | G23: 234.3 | H23: 245.4 | I23: 241.3 | J23: 241.65 | K23: 239.15 | L23: 234.75 | M23: 231.05 | N23: 231.35 | O23: 235.64 | P23: 230.91 | Q23: 236.25 | R23: 236.1 | S23: 231.15 | T23: 229.7 | U23: 3538.25
B24: EGASA | C24: C.H. CHARCANI V | D24: CENTRAL | E24: HIDROELÉCTRICA | F24: 1540.9 | G24: 1524 | H24: 1529.2 | I24: 1526.8 | J24: 1554.35 | K24: 1503.95 | L24: 1515 | M24: 1511.6 | N24: 1504.7 | O24: 1496.02 | P24: 1512.455 | Q24: 1528 | R24: 1503.7 | S24: 1525.2 | T24: 1515.85 | U24: 22791.725
B25: EGASA | C25: C.H. CHARCANI VI | D25: CENTRAL | E25: HIDROELÉCTRICA | F25: 134.95 | G25: 136.9 | H25: 144.1 | I25: 126 | J25: 140.8 | K25: 138.75 | L25: 141.85 | M25: 137.65 | N25: 139.9 | O25: 138.645 | P25: 139.425 | Q25: 141.25 | R25: 140.55 | S25: 137.7 | T25: 137.25 | U25: 2075.72
B26: EGASA | C26: C.T. CHILINA DIESEL | D26: CENTRAL | E26: TERMOELÉCTRICA | G26: 4.25 | U26: 4.25
B27: EGASA | C27: C.T. CHILINA DIESEL | D27: TG | E27: TERMOELÉCTRICA | U27: 0
B28: EGASA | C28: C.T. MOLLENDO DIESEL | D28: CENTRAL | E28: TERMOELÉCTRICA | U28: 0
B29: EGEJUNIN | C29: C.H. HUASAHUASI I | D29: CENTRAL | E29: HIDROELÉCTRICA | F29: 247.6 | G29: 430.95 | H29: 474.25 | I29: 475.2 | J29: 473.2 | K29: 475.2 | L29: 470.1 | M29: 472.65 | N29: 445.9 | O29: 414.8 | P29: 412.6 | Q29: 475.2 | R29: 464.3 | S29: 382.85 | T29: 325.1 | U29: 6439.9
B30: EGEJUNIN | C30: C.H. RUNATULLO II | D30: CENTRAL | E30: HIDROELÉCTRICA | F30: 349.2 | G30: 426.2 | H30: 478.5 | I30: 478.35 | J30: 477.55 | K30: 477 | L30: 477.65 | M30: 478.6 | N30: 481.25 | O30: 481.2 | P30: 480 | Q30: 473.45 | R30: 475.35 | S30: 476.6 | T30: 478.8 | U30: 6989.7
B31: EGEJUNIN | C31: C.H. RUNATULLO III | D31: CENTRAL | E31: HIDROELÉCTRICA | F31: 450.65 | G31: 490.95 | H31: 491.2 | I31: 490.75 | J31: 489.65 | K31: 490.05 | L31: 489.75 | M31: 489.8 | N31: 490.05 | O31: 490.15 | P31: 490.1 | Q31: 489.25 | R31: 489.35 | S31: 489.4 | T31: 489.05 | U31: 7310.15
B32: EGEJUNIN | C32: C.H. SANTA CRUZ I | D32: CENTRAL | E32: HIDROELÉCTRICA | F32: 279.3 | G32: 256 | H32: 177.35 | I32: 234.2 | J32: 290.3 | K32: 280.9 | L32: 289.2 | M32: 288 | N32: 289.8 | O32: 276.3 | P32: 279.6 | Q32: 288.5 | R32: 287.6 | S32: 289.3 | T32: 289.7 | U32: 4096.05
B33: EGEMSA | C33: C.H. MACHUPICCHU | D33: CENTRAL | E33: HIDROELÉCTRICA | F33: 4014.15 | G33: 3890.05 | H33: 4014.9 | I33: 3957.7 | J33: 3526.95 | K33: 4017.5 | L33: 4007.85 | M33: 3997.65 | N33: 3976.3 | O33: 4001.35 | P33: 3995.1 | Q33: 3227.3 | R33: 4003.9 | S33: 3993.295 | T33: 3981.75 | U33: 58605.745
B34: EGESUR | C34: C.H. ARICOTA I | D34: CENTRAL | E34: HIDROELÉCTRICA | F34: 172.05 | G34: 172.05 | H34: 172.25 | I34: 171 | J34: 171.45 | K34: 170.85 | L34: 169.05 | M34: 169.55 | N34: 172.1 | O34: 179.4 | P34: 176.65 | Q34: 179.65 | R34: 200.4 | S34: 186.25 | T34: 187.3 | U34: 2650
B35: EGESUR | C35: C.T. INDEPENDENCIA | D35: CENTRAL | E35: TERMOELÉCTRICA | G35: 48.3 | H35: 166.35 | I35: 140.45 | J35: 64.7 | K35: 212.35 | L35: 95 | M35: 108.5 | N35: 162.35 | O35: 129.65 | P35: 74.3 | Q35: 24.3 | R35: 122.15 | S35: 125.5 | T35: 123.85 | U35: 1597.75
B36: ELECTRICA YANAPAMPA SAC | C36: C.H. YANAPAMPA | D36: CENTRAL | E36: HIDROELÉCTRICA | F36: 76.35 | G36: 78.35 | H36: 67.15 | I36: 71.6 | J36: 75.8 | K36: 79.4 | L36: 74.05 | M36: 82.95 | N36: 81.65 | O36: 83.5 | P36: 84 | Q36: 83.9 | R36: 85.8 | S36: 81.9 | T36: 85.9 | U36: 1192.3
B37: ELECTROPERU | C37: C.H. MANTARO | D37: CENTRAL | E37: HIDROELÉCTRICA | F37: 15545.15 | G37: 15118.55 | H37: 15559.05 | I37: 14563.895 | J37: 15542.75 | K37: 15304.6 | L37: 15533.6 | M37: 15528.8 | N37: 14996.7 | O37: 15556.6 | P37: 15559.7 | Q37: 15542 | R37: 15555.85 | S37: 15532.55 | T37: 15518.25 | U37: 230958.05
B38: ELECTROPERU | C38: C.H. RESTITUCION | D38: CENTRAL | E38: HIDROELÉCTRICA | F38: 5257.75 | G38: 5067.3 | H38: 5237.45 | I38: 4858.585 | J38: 5248.6 | K38: 5140.55 | L38: 5236.45 | M38: 5237.55 | N38: 5048.15 | O38: 5256.95 | P38: 3516.65 | Q38: 3595.4 | R38: 5258.55 | S38: 5249.2 | T38: 5260.2 | U38: 74469.335
B39: ELECTROPERU | C39: C.T. TUMBES | D39: MAK1 | E39: TERMOELÉCTRICA | H39: 31.13 | I39: 14.71 | U39: 45.84
B40: ELECTROPERU | C40: C.T. TUMBES | D40: MAK2 | E40: TERMOELÉCTRICA | H40: 29.09 | I40: 14.83 | U40: 43.92
B41: EMPRESA DE GENERACION ELECTRICA CANCHAYLLO SAC | C41: C.H. CANCHAYLLO | D41: CENTRAL | E41: HIDROELÉCTRICA | F41: 114.5 | G41: 103.6 | H41: 121.4 | I41: 119.45 | J41: 115.45 | K41: 97.35 | L41: 122.9 | M41: 123.75 | N41: 123.75 | O41: 123 | P41: 123.65 | Q41: 123.35 | R41: 123.35 | S41: 121.85 | T41: 114.7 | U41: 1772.05
B42: EMPRESA DE GENERACION ELECTRICA RIO BAÑOS S.A.C. | C42: C.H. RUCUY | D42: CENTRAL | E42: HIDROELÉCTRICA | F42: 479.95 | G42: 479.15 | H42: 479.65 | I42: 474 | J42: 479.15 | K42: 479.3 | L42: 479.45 | M42: 479.25 | N42: 479 | O42: 478.95 | P42: 479.25 | Q42: 479 | R42: 479.45 | S42: 478.9 | T42: 477.7 | U42: 7182.15
B43: EMPRESA DE GENERACION ELECTRICA SANTA ANA S.A.C. | C43: C.H. RENOVANDES H1 | D43: CENTRAL | E43: HIDROELÉCTRICA | F43: 485 | G43: 423.7 | H43: 485.75 | I43: 484.65 | J43: 485.9 | K43: 465 | L43: 483.85 | M43: 484.4 | N43: 484.8 | O43: 486 | P43: 385.15 | Q43: 485.4 | R43: 486.5 | S43: 484.965 | T43: 464.4 | U43: 7075.465
B44: EMPRESA DE GENERACION HUALLAGA | C44: C.H. CHAGLLA | D44: CENTRAL | E44: HIDROELÉCTRICA | F44: 3199.75 | G44: 7586.7 | H44: 10939.2 | I44: 8710.6 | J44: 10473.2 | K44: 10518.25 | L44: 10829.2 | M44: 10647.45 | N44: 10225.1 | O44: 10768.1 | P44: 10912.65 | Q44: 10121 | R44: 10631.6 | S44: 10732 | T44: 10715.3 | U44: 147010.1
B45: EMPRESA DE GENERACION HUALLAGA | C45: P.C.H. CHAGLLA | D45: CENTRAL | E45: HIDROELÉCTRICA | F45: 156 | G45: 156 | H45: 156 | I45: 155.3 | J45: 156 | K45: 156 | L45: 156 | M45: 156 | N45: 156 | O45: 155.95 | P45: 156 | Q45: 156 | R45: 155.95 | S45: 156 | T45: 156 | U45: 2339.2
B46: EMPRESA DE GENERACION HUANZA | C46: C.H. HUANZA | D46: CENTRAL | E46: HIDROELÉCTRICA | F46: 1305.9 | G46: 1930.85 | H46: 2249.7 | I46: 2277.7 | J46: 2270.7 | K46: 2002.5 | L46: 1713.8 | M46: 1676.2 | N46: 1549.45 | O46: 1463.3 | P46: 1644.65 | Q46: 1485.8 | R46: 1510.35 | S46: 1604.5 | T46: 1343.3 | U46: 26028.7
B47: EMPRESA ELECTRICA AGUA AZUL | C47: C.H. POTRERO | D47: CENTRAL | E47: HIDROELÉCTRICA | F47: 476.9 | G47: 478.3 | H47: 471.8 | I47: 476.45 | J47: 475.2 | K47: 477.75 | L47: 474.7 | M47: 399.25 | N47: 425.5 | O47: 479.95 | P47: 478.8 | Q47: 477.1 | R47: 479.25 | S47: 469.8 | T47: 477.65 | U47: 7018.4
B48: EMPRESA ELECTRICA RIO DOBLE | C48: C.H. LAS PIZARRAS | D48: CENTRAL | E48: HIDROELÉCTRICA | F48: 450.2 | G48: 451.5 | H48: 442.55 | I48: 428.7 | J48: 452.7 | K48: 454.2 | L48: 455.15 | M48: 454.15 | N48: 453.645 | O48: 453.2 | P48: 453.92 | Q48: 453.85 | R48: 453.5 | S48: 453.95 | T48: 453.3 | U48: 6764.515
B49: ENEL GENERACION PIURA S.A. | C49: C.T. MALACAS 1 | D49: TG6 | E49: TERMOELÉCTRICA | F49: 355.85 | G49: 457.5 | H49: 359.15 | J49: 727.05 | L49: 441.55 | M49: 752.4 | N49: 738.3 | O49: 816.85 | P49: 771.75 | Q49: 766.15 | R49: 1105.15 | S49: 805.45 | T49: 816.45 | U49: 8913.6
B50: ENEL GENERACION PIURA S.A. | C50: C.T. MALACAS 2 | D50: TG4 | E50: TERMOELÉCTRICA | H50: 663.05 | I50: 894.45 | J50: 44.65 | K50: 914.15 | L50: 74.85 | U50: 2591.15
B51: ENEL GENERACION PIURA S.A. | C51: C.T. RF DE GENERACION TALARA | D51: TG5 | E51: TERMOELÉCTRICA | H51: 407 | U51: 407
B52: ENERGÍA EÓLICA S.A. | C52: C.E. CUPISNIQUE | D52: CENTRAL | E52: EÓLICA | F52: 826 | G52: 637.1 | H52: 565.05 | I52: 483.8 | J52: 446.9 | K52: 946.35 | L52: 1252.6 | M52: 1412.8 | N52: 1299.5 | O52: 1060.15 | P52: 721.65 | Q52: 1086.1 | R52: 1006 | S52: 1036.9 | T52: 845.9 | U52: 13626.8
B53: ENERGÍA EÓLICA S.A. | C53: C.E. TALARA | D53: CENTRAL | E53: EÓLICA | F53: 344.35 | G53: 395.75 | H53: 384.4 | I53: 141.95 | J53: 94.85 | K53: 161.95 | L53: 465.35 | M53: 531.8 | N53: 530.7 | O53: 329.8 | P53: 230.45 | Q53: 302.4 | R53: 354.85 | S53: 305.55 | T53: 349.75 | U53: 4923.9
B54: ENERGIA RENOVABLE DEL SUR S.A. | C54: C.E. SAN JUAN | D54: CENTRAL | E54: EÓLICA | F54: 2667.35 | G54: 1888.4 | H54: 1031.8 | I54: 1510.75 | J54: 862.7 | K54: 715 | L54: 1712.65 | M54: 1729.05 | N54: 1633.15 | O54: 1758.3 | P54: 2050.7 | Q54: 1899.4 | R54: 1355.45 | S54: 1224.5 | T54: 1889.8 | U54: 23929
B55: ENGIE | C55: C.E. PUNTA LOMITAS | D55: PL-BL1 | E55: EÓLICA | F55: 1416 | G55: 1294.2 | H55: 490.05 | I55: 910.85 | J55: 885.7 | K55: 777.2 | L55: 1793.85 | M55: 1777.65 | N55: 1646.2 | O55: 1640.35 | P55: 1225.1 | Q55: 1266.85 | R55: 1046.65 | S55: 1040.35 | T55: 1134.95 | U55: 18345.95
B56: ENGIE | C56: C.E. PUNTA LOMITAS | D56: PL-BL2 | E56: EÓLICA | F56: 1675.05 | G56: 1567.65 | H56: 664.2 | I56: 1146.85 | J56: 995.45 | K56: 964.6 | L56: 1911.45 | M56: 1824.7 | N56: 1813.75 | O56: 1862.9 | P56: 1474.45 | Q56: 1526 | R56: 1347.1 | S56: 1347.25 | T56: 1469.25 | U56: 21590.65
B57: ENGIE | C57: C.E. PUNTA LOMITAS_EXP | D57: PUN LOM_EXP-BL1 | E57: EÓLICA | F57: 74.35 | G57: 61.95 | H57: 36.6 | I57: 85.7 | J57: 74.9 | K57: 54.35 | L57: 161.2 | M57: 173 | N57: 163.95 | O57: 163.25 | P57: 110.5 | Q57: 103.95 | R57: 99.75 | S57: 102.05 | T57: 110.1 | U57: 1575.6
B58: ENGIE | C58: C.E. PUNTA LOMITAS_EXP | D58: PUN LOM_EXP-BL2 | E58: EÓLICA | F58: 98.4 | G58: 84.15 | H58: 33.8 | I58: 60.6 | J58: 70.6 | K58: 58.2 | L58: 158.1 | M58: 184.75 | N58: 174.55 | O58: 149.95 | P58: 94.75 | Q58: 89.05 | R58: 92.45 | S58: 89.7 | T58: 90.25 | U58: 1529.3
B59: ENGIE | C59: C.H. QUITARACSA | D59: CENTRAL | E59: HIDROELÉCTRICA | F59: 1800.35 | G59: 2646.35 | H59: 2696.9 | I59: 2692.95 | J59: 2048.55 | K59: 2695.4 | L59: 2693 | M59: 2690.65 | N59: 2689.7 | O59: 2696.7 | P59: 2277.3 | Q59: 2005.8 | R59: 2068.5 | S59: 2671.3 | T59: 2690.35 | U59: 37063.8
B60: ENGIE | C60: C.H. YUNCAN | D60: CENTRAL | E60: HIDROELÉCTRICA | F60: 2668.75 | G60: 3146.2 | H60: 3160.15 | I60: 3169.95 | J60: 3162.05 | K60: 3086.9 | L60: 2896.45 | M60: 3154.05 | N60: 3147.05 | O60: 3136.45 | P60: 2823.6 | Q60: 2843.2 | R60: 3128.7 | S60: 3147.75 | T60: 2892.7 | U60: 45563.95
B61: ENGIE | C61: C.S. INTIPAMPA | D61: CENTRAL | E61: SOLAR | F61: 276.8 | G61: 239.4 | H61: 187.95 | I61: 218.3 | J61: 239.15 | K61: 174.4 | L61: 248.2 | M61: 341 | N61: 337.4 | O61: 395.5 | P61: 384.95 | Q61: 390.7 | R61: 385.5 | S61: 375.45 | T61: 363.05 | U61: 4557.75
B62: ENGIE | C62: C.T. CHILCA 1 | D62: TG1 | E62: TERMOELÉCTRICA | F62: 2419.9 | G62: 3695.6 | N62: 354.9 | O62: 277.95 | R62: 475.3 | S62: 483.45 | U62: 7707.1
B63: ENGIE | C63: C.T. CHILCA 1 | D63: TG2 | E63: TERMOELÉCTRICA | F63: 2390.45 | G63: 82.1 | H63: 1769.5 | I63: 568.3 | J63: 704.45 | K63: 1146.55 | L63: 312.65 | N63: 504.15 | O63: 282.05 | R63: 1185.6 | S63: 1266.75 | T63: 525.55 | U63: 10738.1
B64: ENGIE | C64: C.T. CHILCA 1 | D64: TG3 | E64: TERMOELÉCTRICA | H64: 1835.4 | I64: 574.55 | J64: 598.85 | K64: 808.7 | O64: 1047 | R64: 1313.45 | U64: 6177.95
B65: ENGIE | C65: C.T. CHILCA 1 | D65: TV | E65: TERMOELÉCTRICA | F65: 2850.4 | G65: 1646 | U65: 4496.4
B66: ENGIE | C66: C.T. CHILCA 2 | D66: TG41 | E66: TERMOELÉCTRICA | J66: 182.9 | P66: 145.15 | Q66: 214.1 | U66: 542.15
B67: ENGIE | C67: C.T. CHILCA 2 | D67: TV42 | E67: TERMOELÉCTRICA | U67: 0
B68: ENGIE | C68: C.T. NEPI | D68: TG41 | E68: TERMOELÉCTRICA | U68: 0
B69: ENGIE | C69: C.T. NEPI | D69: TG42 | E69: TERMOELÉCTRICA | U69: 0
B70: ENGIE | C70: C.T. NEPI | D70: TG43 | E70: TERMOELÉCTRICA | U70: 0
B71: ENGIE | C71: C.T. RF PLANTA ILO | D71: TG1 | E71: TERMOELÉCTRICA | H71: 367.5 | U71: 367.5
B72: ENGIE | C72: C.T. RF PLANTA ILO | D72: TG2 | E72: TERMOELÉCTRICA | U72: 0
B73: ENGIE | C73: C.T. RF PLANTA ILO | D73: TG3 | E73: TERMOELÉCTRICA | J73: 403.7 | U73: 403.7
B74: FENIX POWER PERÚ | C74: C.T. FENIX | D74: GT11 | E74: TERMOELÉCTRICA | F74: 3326.015 | G74: 3251.75 | H74: 3326.1 | I74: 3474.85 | J74: 646.2 | K74: 3160.05 | L74: 3562.15 | O74: 252 | P74: 2747.3 | Q74: 1428.6 | R74: 3722.45 | S74: 3961.8 | T74: 3804.9 | U74: 36664.165
B75: FENIX POWER PERÚ | C75: C.T. FENIX | D75: GT12 | E75: TERMOELÉCTRICA | F75: 3332.585 | G75: 3258.15 | H75: 3332.05 | I75: 3542.65 | J75: 1382.55 | K75: 3910.85 | L75: 3686.2 | M75: 3731.8985 | N75: 3661.85 | O75: 3940.25 | P75: 3722.85 | Q75: 1294.4 | R75: 3728.8 | S75: 3970.45 | T75: 3866.3 | U75: 50361.834
B76: FENIX POWER PERÚ | C76: C.T. FENIX | D76: TV10 | E76: TERMOELÉCTRICA | F76: 3823.35 | G76: 3823.75 | H76: 3872 | I76: 3959.9 | J76: 596.15 | K76: 3672.25 | L76: 4004 | M76: 1994.0565 | N76: 1966.1 | O76: 2035.45 | P76: 3442.95 | Q76: 1211.8 | R76: 4080.15 | S76: 4224.3 | T76: 4122.1 | U76: 46828.307
B77: GENERACIÓN ANDINA S.A.C. | C77: C.H. 8 DE AGOSTO | D77: CENTRAL | E77: HIDROELÉCTRICA | F77: 485.75 | G77: 428.15 | H77: 474.45 | I77: 501.2 | J77: 499.85 | K77: 501.3 | L77: 502.2 | M77: 502.8 | N77: 501.6 | O77: 502.65 | P77: 499.6 | Q77: 497.8 | R77: 497.9 | S77: 497.45 | T77: 467.65 | U77: 7360.35
B78: GENERACIÓN ANDINA S.A.C. | C78: C.H. EL CARMEN | D78: CENTRAL | E78: HIDROELÉCTRICA | F78: 177.2 | G78: 190.15 | H78: 200.05 | I78: 180.2 | J78: 195.1 | K78: 184.55 | L78: 193.8 | M78: 192.85 | N78: 191.5 | O78: 145.6 | P78: 45.75 | Q78: 200 | R78: 173.45 | S78: 149.35 | T78: 136.05 | U78: 2555.6
B79: GENERADORA DE ENERGÍA DEL PERÚ | C79: C.H. ÁNGEL I | D79: CENTRAL | E79: HIDROELÉCTRICA | F79: 329.25 | G79: 489.6 | H79: 489.6 | I79: 489.6 | J79: 489.6 | K79: 489.6 | L79: 489.6 | M79: 489.6 | N79: 489.6 | O79: 469.2 | P79: 489.6 | Q79: 489.6 | R79: 489.6 | S79: 489.6 | T79: 489.6 | U79: 7163.25
B80: GENERADORA DE ENERGÍA DEL PERÚ | C80: C.H. ÁNGEL II | D80: CENTRAL | E80: HIDROELÉCTRICA | F80: 331.75 | G80: 489.6 | H80: 489.6 | I80: 489.6 | J80: 489.6 | K80: 489.6 | L80: 489.6 | M80: 489.6 | N80: 478.3 | O80: 462.5 | P80: 489.6 | Q80: 489.6 | R80: 484.5 | S80: 489.6 | T80: 489.6 | U80: 7142.65
B81: GENERADORA DE ENERGÍA DEL PERÚ | C81: C.H. ÁNGEL III | D81: CENTRAL | E81: HIDROELÉCTRICA | F81: 229.4 | G81: 244.8 | H81: 244.8 | I81: 244.8 | J81: 244.8 | K81: 244.8 | L81: 244.8 | M81: 244.8 | N81: 241.1 | O81: 142.8 | T81: 122.4 | U81: 2449.3
B82: GENERADORA DE ENERGÍA DEL PERÚ | C82: C.H. LA JOYA | D82: CENTRAL | E82: HIDROELÉCTRICA | F82: 144.45 | G82: 141.75 | H82: 176.25 | I82: 174.1 | J82: 167.05 | K82: 181.15 | L82: 183.2 | M82: 157.05 | N82: 148.3 | O82: 149.1 | P82: 152.85 | Q82: 145.5 | R82: 142.95 | S82: 142.05 | T82: 140.45 | U82: 2346.2
B83: GM OPERACIONES S.A.C. | C83: CT REFINERIA TALARA | D83: TV1 REF TALARA | E83: TERMOELÉCTRICA | K83: 65.7 | L83: 465.35 | M83: 328.55 | N83: 364.25 | O83: 471.9 | P83: 514.3 | Q83: 564.54 | R83: 595.2 | S83: 609.25 | T83: 606.3 | U83: 4585.34
B84: GM OPERACIONES S.A.C. | C84: CT REFINERIA TALARA | D84: TV2 REF TALARA | E84: TERMOELÉCTRICA | F84: 796.2 | G84: 802.5 | H84: 837.05 | I84: 909.62 | J84: 904.05 | K84: 862.1 | L84: 722.75 | M84: 925.4 | N84: 926.5 | O84: 917.35 | P84: 887.2 | Q84: 871.88 | R84: 852.3 | S84: 835.1 | T84: 830.8 | U84: 12880.8
B85: GR CORTARRAMA SOCIEDAD ANONIMA CERRADA | C85: C.S. MATARANI | D85: C.S. MATARANI | E85: SOLAR | F85: 538.8 | G85: 418.65 | H85: 457.4 | I85: 457.85 | J85: 742.5 | K85: 640.35 | L85: 688.7 | M85: 789.4 | N85: 775.45 | O85: 774.2 | P85: 806.2 | Q85: 783.65 | R85: 757.65 | S85: 799.4 | T85: 802.55 | U85: 10232.75
B86: GR PAINO SOCIEDAD ANONIMA CERRADA | C86: C.E. HUAMBOS | D86: CENTRAL | E86: EÓLICA | F86: 61.9 | G86: 35.15 | H86: 23.85 | I86: 54.9 | J86: 127 | K86: 84.3 | L86: 43.3 | M86: 38.6 | N86: 74.3 | O86: 47.65 | P86: 163.55 | Q86: 161.9 | R86: 31.85 | S86: 93.25 | T86: 160.25 | U86: 1201.75
B87: GR TARUCA SOCIEDAD ANONIMA CERRADA | C87: C.E. DUNA | D87: CENTRAL | E87: EÓLICA | F87: 56.9 | G87: 33.1 | H87: 39.4 | I87: 111.35 | J87: 188.4 | K87: 139.65 | L87: 63.4 | M87: 38.45 | N87: 49.65 | O87: 41.5 | P87: 225.7 | Q87: 205.2 | R87: 34.65 | S87: 70.05 | T87: 141.35 | U87: 1438.75
B88: HIDROCAÑETE S.A. | C88: C.H. IMPERIAL | D88: CENTRAL | E88: HIDROELÉCTRICA | F88: 73.65 | G88: 81.05 | H88: 78.8 | I88: 79.95 | J88: 75.95 | K88: 80.5 | L88: 83.35 | M88: 83.4 | N88: 84.35 | O88: 84.25 | P88: 84.6 | Q88: 83.85 | R88: 84.45 | S88: 83.65 | T88: 85.3 | U88: 1227.1
B89: HIDROELECTRICA HUANCHOR S.A.C. | C89: C.H. HUANCHOR | D89: CENTRAL | E89: HIDROELÉCTRICA | F89: 437 | G89: 438.4 | H89: 431.6 | I89: 432.55 | J89: 435.15 | K89: 439.7 | L89: 440.1 | M89: 440.4 | N89: 439.6 | O89: 440.45 | P89: 440.4 | Q89: 439.15 | R89: 440.5 | S89: 441 | T89: 439.25 | U89: 6575.25
B90: HUAURA POWER GROUP S.A. | C90: C.H. YARUCAYA | D90: CENTRAL | E90: HIDROELÉCTRICA | F90: 451.15 | G90: 450.5 | H90: 425.05 | I90: 127.2 | J90: 250.7 | K90: 451.2 | L90: 451.1 | M90: 450.45 | N90: 451.2 | O90: 451.05 | P90: 449.74 | Q90: 450.85 | R90: 450.9 | S90: 408.735 | T90: 448.8 | U90: 6168.625
B91: INFRAESTRUCTURAS Y ENERGIAS DEL PERU S.A.C. | C91: C.T. RF PTO MALDONADO | D91: CENTRAL | E91: TERMOELÉCTRICA | U91: 0
B92: INFRAESTRUCTURAS Y ENERGIAS DEL PERU S.A.C. | C92: C.T. RF PUCALLPA | D92: CENTRAL | E92: TERMOELÉCTRICA | U92: 0
B93: INLAND ENERGY SAC | C93: C.H. SANTA TERESA | D93: CENTRAL | E93: HIDROELÉCTRICA | F93: 2173 | G93: 1849.5 | H93: 2179.65 | I93: 1920.05 | J93: 1893.3 | K93: 2162.5 | L93: 2164.2 | M93: 2169.3 | N93: 2173.3 | O93: 2164.15 | P93: 2172.75 | Q93: 1768.4 | R93: 2162.75 | S93: 2173.095 | T93: 2069 | U93: 31194.945
B94: INVERSIONES SHAQSHA S.A.C. | C94: C.H. PARIAC | D94: CENTRAL | E94: HIDROELÉCTRICA | N94: 17.55 | O94: 83.6 | P94: 98.75 | Q94: 99.25 | R94: 102 | S94: 100.75 | T94: 101.2 | U94: 603.1
B95: KALLPA GENERACION S.A. | C95: C.H. CERRO DEL AGUILA | D95: CENTRAL | E95: HIDROELÉCTRICA | F95: 10008.95 | G95: 13509.65 | H95: 13475.45 | I95: 13406.25 | J95: 13426.15 | K95: 13440.05 | L95: 13427.6 | M95: 13408.95 | N95: 13425.7 | O95: 13273.25 | P95: 13413.7 | Q95: 13404.15 | R95: 12851.8 | S95: 13407.95 | T95: 13388.45 | U95: 197268.05
B96: KALLPA GENERACION S.A. | C96: C.T. KALLPA | D96: TG1 | E96: TERMOELÉCTRICA | I96: 2346.15 | J96: 3078.3 | K96: 3219.7 | L96: 3035.85 | M96: 2982.7 | N96: 3067.85 | O96: 3322.05 | P96: 3056.95 | Q96: 3063.4 | R96: 3222.65 | S96: 3400.75 | T96: 3131.8 | U96: 36928.15
B97: KALLPA GENERACION S.A. | C97: C.T. KALLPA | D97: TG2 | E97: TERMOELÉCTRICA | G97: 1165.5 | H97: 4076 | I97: 3216.25 | J97: 3091.45 | K97: 3217.3 | L97: 3026.8 | M97: 2977.8 | N97: 3073 | O97: 3370.8 | P97: 3064.1 | Q97: 3067.15 | R97: 3236.6 | S97: 3454 | T97: 3135.95 | U97: 43172.7
B98: KALLPA GENERACION S.A. | C98: C.T. KALLPA | D98: TG3 | E98: TERMOELÉCTRICA | G98: 3573.15 | H98: 4104.95 | I98: 3226.3 | J98: 3094.85 | K98: 3219.05 | L98: 3029.6 | M98: 2974.85 | N98: 3071.7 | O98: 2956.1 | P98: 3066.1 | Q98: 3067.1 | R98: 3238.95 | S98: 3453.1 | T98: 3138 | U98: 45213.8
B99: KALLPA GENERACION S.A. | C99: C.T. KALLPA | D99: TV | E99: TERMOELÉCTRICA | G99: 2135.75 | H99: 4227.75 | I99: 5016.8 | J99: 5432.85 | K99: 5552.2 | L99: 5405.7 | M99: 5333.9 | N99: 5439.7 | O99: 5450.95 | P99: 5405.4 | Q99: 5429.3 | R99: 5614.6 | S99: 5780.95 | T99: 5514.1 | U99: 71739.95
B100: KALLPA GENERACION S.A. | C100: C.T. LAS FLORES | D100: TG1 | E100: TERMOELÉCTRICA | F100: 454.1 | G100: 3712.5 | H100: 4774.05 | I100: 4599.6 | J100: 4401.6 | K100: 3835.95 | L100: 4318.35 | M100: 4046.45 | N100: 4041.85 | O100: 4524.3 | P100: 4427.85 | Q100: 4195.75 | R100: 4222.4 | S100: 4905.55 | T100: 4816.85 | U100: 61277.15
B101: KALLPA GENERACION S.A. | C101: C.T. LAS FLORES | D101: TV | E101: TERMOELÉCTRICA | F101: 262.75 | G101: 1823.75 | H101: 2503.5 | I101: 2442.5 | J101: 2377.45 | K101: 1992.5 | L101: 2337.85 | M101: 2234.95 | N101: 2213.8 | O101: 2422.8 | P101: 2387.8 | Q101: 2292.2 | R101: 2298.6 | S101: 2588 | T101: 2567.7 | U101: 32746.15
B102: KALLPA GENERACION S.A. | C102: M.C.H. CERRO DEL AGUILA | D102: CENTRAL | E102: HIDROELÉCTRICA | F102: 246.85 | G102: 251.7 | H102: 251.3 | I102: 252 | J102: 251.45 | K102: 245.85 | L102: 250.65 | M102: 251.6 | N102: 251.2 | O102: 252 | P102: 251.1 | Q102: 250.85 | R102: 221.05 | S102: 252.45 | T102: 251.7 | U102: 3731.75
B103: KONDU SAC | C103: C.S. CARHUAQUERO | D103: CENTRAL | E103: SOLAR | F103: 2.1 | G103: 1.5 | H103: 2.1 | I103: 1.9 | J103: 2.1 | K103: 1.6 | L103: 2.1 | M103: 2.15 | N103: 2.75 | O103: 2.55 | P103: 1.05 | Q103: 1.95 | R103: 1.5 | S103: 1.85 | T103: 2.45 | U103: 29.65
...

Sheet G_AREAS
B3: miércoles, 15 de Enero del 2025
B5: HORA | C5: RESUMEN DE GENERACIÓN POR ÁREAS DEL SEIN | D5: RESUMEN DE GENERACIÓN POR ÁREAS DEL SEIN | E5: RESUMEN DE GENERACIÓN POR ÁREAS DEL SEIN | F5: RESUMEN DE GENERACIÓN POR ÁREAS DEL SEIN | G5: RESUMEN DE GENERACIÓN POR ÁREAS DEL SEIN | H5: RESUMEN DE GENERACIÓN POR ÁREAS DEL SEIN | I5: RESUMEN DE GENERACIÓN POR ÁREAS DEL SEIN | J5: RESUMEN DE GENERACIÓN POR ÁREAS DEL SEIN | K5: RESUMEN DE GENERACIÓN POR ÁREAS DEL SEIN | L5: RESUMEN DE GENERACIÓN POR ÁREAS DEL SEIN | M5: RESUMEN DE GENERACIÓN POR ÁREAS DEL SEIN | N5: RESUMEN DE GENERACIÓN POR ÁREAS DEL SEIN | O5: RESUMEN DE GENERACIÓN POR ÁREAS DEL SEIN | P5: RESUMEN DE GENERACIÓN POR ÁREAS DEL SEIN | Q5: RESUMEN DE GENERACIÓN POR ÁREAS DEL SEIN | R5: RESUMEN DE GENERACIÓN POR ÁREAS DEL SEIN | S5: HORA | T5: GENERACIÓN POR TIPO DE GENERACIÓN | U5: GENERACIÓN POR TIPO DE GENERACIÓN | V5: GENERACIÓN POR TIPO DE GENERACIÓN | W5: GENERACIÓN POR TIPO DE GENERACIÓN | X5: GENERACIÓN POR TIPO DE GENERACIÓN | Y5: HORA | Z5: GENERACIÓN POR TIPO DE GENERACIÓN | AA5: GENERACIÓN POR TIPO DE GENERACIÓN | AB5: GENERACIÓN POR TIPO DE GENERACIÓN | AC5: GENERACIÓN POR TIPO DE GENERACIÓN | AD5: GENERACIÓN POR TIPO DE GENERACIÓN
C6: NORTE | D6: NORTE | E6: NORTE | F6: NORTE | G6: CENTRO | H6: CENTRO | I6: CENTRO | J6: CENTRO | K6: SUR | L6: SUR | M6: SUR | N6: SUR | O6: GENERACIÓN INTEGRANTES COES | P6: GENERACIÓN INTEGRANTES COES | Q6: GENERACIÓN INTEGRANTES COES | R6: GENERACIÓN INTEGRANTES COES | T6: INTEGRANTES COES | U6: INTEGRANTES COES | V6: INTEGRANTES COES | W6: INTEGRANTES COES | X6: INTEGRANTES COES | Z6: INTEGRANTES COES RER | AA6: INTEGRANTES COES RER | AB6: INTEGRANTES COES RER | AC6: INTEGRANTES COES RER | AD6: INTEGRANTES COES RER
C7: GENERACIÓN HIDROELÉCTRICA NORTE | D7: GENERACIÓN TERMOELÉCTRICA NORTE | E7: GENERACIÓN SOLAR NORTE | F7: GENERACIÓN EÓLICA NORTE | G7: GENERACIÓN HIDROELÉCTRICA CENTRO | H7: GENERACIÓN TERMOELÉCTRICA CENTRO | I7: GENERACIÓN SOLAR CENTRO | J7: GENERACIÓN EÓLICA CENTRO | K7: GENERACIÓN HIDROELÉCTRICA SUR | L7: GENERACIÓN TERMOELÉCTRICA SUR | M7: GENERACIÓN SOLAR SUR | N7: GENERACIÓN EÓLICA SUR | O7: GENERACIÓN COES NORTE | P7: GENERACIÓN COES CENTRO | Q7: GENERACIÓN COES SUR | R7: TOTAL GENERACION | T7: HIDROELÉCTRICA | U7: TERMOELÉCTRICA | V7: SOLAR | W7: EÓLICA | X7: TOTAL GENERACION | Z7: HIDROELÉCTRICA RER | AA7: TERMOELÉCTRICA RER | AB7: SOLAR RER | AC7: EÓLICA RER | AD7: TOTAL RER
B8: 00:30 | C8: 569.7 | D8: 140.9 | E8: 0 | F8: 35.1 | G8: 3572.9 | H8: 1599.8 | I8: 0 | J8: 232.5 | K8: 487.8 | L8: 0 | M8: 0 | N8: 0 | O8: 745.7 | P8: 5405.2 | Q8: 487.8 | R8: 6638.7 | S8: 00:30 | T8: 4630.4 | U8: 1740.7 | V8: 0 | W8: 267.6 | X8: 6638.7 | Y8: 00:30 | Z8: 332.1 | AA8: 60.8 | AB8: 0 | AC8: 267.6 | AD8: 660.5
B9: 01:00 | C9: 566.4 | D9: 139.2 | E9: 0 | F9: 40.3 | G9: 3432.6 | H9: 1583.9 | I9: 0 | J9: 179.5 | K9: 485.1 | L9: 0 | M9: 0 | N9: 0 | O9: 745.9 | P9: 5196 | Q9: 485.1 | R9: 6427 | S9: 01:00 | T9: 4484.1 | U9: 1723.1 | V9: 0 | W9: 219.8 | X9: 6427 | Y9: 01:00 | Z9: 331.8 | AA9: 59.7 | AB9: 0 | AC9: 219.8 | AD9: 611.3
B10: 01:30 | C10: 568 | D10: 139.7 | E10: 0 | F10: 43.2 | G10: 3560.3 | H10: 1490.9 | I10: 0 | J10: 158.2 | K10: 489.7 | L10: 0 | M10: 0 | N10: 0 | O10: 750.9 | P10: 5209.4 | Q10: 489.7 | R10: 6450 | S10: 01:30 | T10: 4618 | U10: 1630.6 | V10: 0 | W10: 201.4 | X10: 6450 | Y10: 01:30 | Z10: 332 | AA10: 60.6 | AB10: 0 | AC10: 201.4 | AD10: 594
B11: 02:00 | C11: 568.1 | D11: 92.1 | E11: 0 | F11: 38.9 | G11: 3530.7 | H11: 1479 | I11: 0 | J11: 131.3 | K11: 486 | L11: 0 | M11: 0 | N11: 0 | O11: 699.1 | P11: 5141 | Q11: 486 | R11: 6326.1 | S11: 02:00 | T11: 4584.8 | U11: 1571.1 | V11: 0 | W11: 170.2 | X11: 6326.1 | Y11: 02:00 | Z11: 331.1 | AA11: 60.2 | AB11: 0 | AC11: 170.2 | AD11: 561.5
B12: 02:30 | C12: 571.4 | D12: 92.8 | E12: 0 | F12: 30.9 | G12: 3528 | H12: 1480.2 | I12: 0 | J12: 114.9 | K12: 488 | L12: 0 | M12: 0 | N12: 0 | O12: 695.1 | P12: 5123.1 | Q12: 488 | R12: 6306.2 | S12: 02:30 | T12: 4587.4 | U12: 1573 | V12: 0 | W12: 145.8 | X12: 6306.2 | Y12: 02:30 | Z12: 332.4 | AA12: 60.3 | AB12: 0 | AC12: 145.8 | AD12: 538.5
B13: 03:00 | C13: 568.1 | D13: 91.6 | E13: 0 | F13: 46.2 | G13: 3448.6 | H13: 1564.6 | I13: 0 | J13: 77.5 | K13: 486.5 | L13: 0 | M13: 0 | N13: 0 | O13: 705.9 | P13: 5090.7 | Q13: 486.5 | R13: 6283.1 | S13: 03:00 | T13: 4503.2 | U13: 1656.2 | V13: 0 | W13: 123.7 | X13: 6283.1 | Y13: 03:00 | Z13: 331.6 | AA13: 59.1 | AB13: 0 | AC13: 123.7 | AD13: 514.4
B14: 03:30 | C14: 568 | D14: 92.5 | E14: 0 | F14: 54 | G14: 3471.9 | H14: 1526.4 | I14: 0 | J14: 51.1 | K14: 487.5 | L14: 0 | M14: 0 | N14: 0 | O14: 714.5 | P14: 5049.4 | Q14: 487.5 | R14: 6251.4 | S14: 03:30 | T14: 4527.4 | U14: 1618.9 | V14: 0 | W14: 105.1 | X14: 6251.4 | Y14: 03:30 | Z14: 331.2 | AA14: 59.7 | AB14: 0 | AC14: 105.1 | AD14: 496
B15: 04:00 | C15: 566.3 | D15: 91.9 | E15: 0 | F15: 49.9 | G15: 3351.7 | H15: 1583.7 | I15: 0 | J15: 61.4 | K15: 486 | L15: 0 | M15: 0 | N15: 0 | O15: 708.1 | P15: 4996.8 | Q15: 486 | R15: 6190.9 | S15: 04:00 | T15: 4404 | U15: 1675.6 | V15: 0 | W15: 111.3 | X15: 6190.9 | Y15: 04:00 | Z15: 331.4 | AA15: 59.9 | AB15: 0 | AC15: 111.3 | AD15: 502.6
B16: 04:30 | C16: 569.9 | D16: 91.8 | E16: 0 | F16: 34.8 | G16: 3514.2 | H16: 1537.5 | I16: 0 | J16: 72.6 | K16: 486.7 | L16: 0 | M16: 0 | N16: 0 | O16: 696.5 | P16: 5124.3 | Q16: 486.7 | R16: 6307.5 | S16: 04:30 | T16: 4570.8 | U16: 1629.3 | V16: 0 | W16: 107.4 | X16: 6307.5 | Y16: 04:30 | Z16: 331.4 | AA16: 59.4 | AB16: 0 | AC16: 107.4 | AD16: 498.2
B17: 05:00 | C17: 572.2 | D17: 90.6 | E17: 0 | F17: 21.5 | G17: 3490.3 | H17: 1565.7 | I17: 0 | J17: 90.4 | K17: 486.3 | L17: 0 | M17: 0 | N17: 0 | O17: 684.3 | P17: 5146.4 | Q17: 486.3 | R17: 6317 | S17: 05:00 | T17: 4548.8 | U17: 1656.3 | V17: 0 | W17: 111.9 | X17: 6317 | Y17: 05:00 | Z17: 332.3 | AA17: 58.1 | AB17: 0 | AC17: 111.9 | AD17: 502.3
B18: 05:30 | C18: 559.7 | D18: 90.4 | E18: 0 | F18: 21 | G18: 3380.6 | H18: 1601.1 | I18: 0 | J18: 106.3 | K18: 471.3 | L18: 0 | M18: 5.7 | N18: 0 | O18: 671.1 | P18: 5088 | Q18: 477 | R18: 6236.1 | S18: 05:30 | T18: 4411.6 | U18: 1691.5 | V18: 5.7 | W18: 127.3 | X18: 6236.1 | Y18: 05:30 | Z18: 330.5 | AA18: 58.6 | AB18: 5.7 | AC18: 127.3 | AD18: 522.1
B19: 06:00 | C19: 569 | D19: 90.6 | E19: 0 | F19: 33.5 | G19: 3373.2 | H19: 1599.2 | I19: 0 | J19: 94.3 | K19: 490.1 | L19: 0 | M19: 64.6 | N19: 0 | O19: 693.1 | P19: 5066.7 | Q19: 554.7 | R19: 6314.5 | S19: 06:00 | T19: 4432.3 | U19: 1689.8 | V19: 64.6 | W19: 127.8 | X19: 6314.5 | Y19: 06:00 | Z19: 330.4 | AA19: 58.2 | AB19: 64.6 | AC19: 127.8 | AD19: 581
... B56: TOTAL MWh | C56: 13636.25 | D56: 3035.5 | E56: 2.45 | F56: 1497.25 | G56: 84396.55 | H56: 40686.75 | I56: 8.85 | J56: 8458.55 | K56: 12247.1 | L56: 14.7 | M56: 3911.25 | N56: 0 | O56: 18171.45 | P56: 133550.7 | Q56: 16173.05 | R56: 167895.2 | S56: TOTAL MWh | T56: 110279.9 | U56: 43736.95 | V56: 3922.55 | W56: 9955.8 | X56: 167895.2 | Y56: TOTAL MWh | Z56: 7985.65 | AA56: 1399.95 | AB56: 3922.55 | AC56: 9955.8 | AD56: 23263.95

Sheet HOP
B3: miércoles, 15 de Enero del 2025
B5: Reporte de Horas de Operación
B6: Empresa | C6: Central | D6: Grupo | E6: Modo de Operación | F6: Inicio | G6: Final | H6: O. Arranque | I6: O. Parada | J6: Tipo Operación | K6: Ensayo de Potencia Efectiva | L6: Ensayo de Potencia Mínima | M6: Sistema | N6: Lim. Transm. | O6: Causa | P6: Observación
B7: AGRO INDUSTRIAL PARAMONGA S.A. | C7: C.T. PARAMONGA | D7: CENTRAL | E7: PARAMONGA - BAGAZO | F7: 15/01/2025 00:00:00 | G7: 16/01/2025 00:00:00 | J7: POR COGENERACION | O7: ...
B8: AGROAURORA S.A.C. | C8: C.T. MAPLE ETANOL | D8: CENTRAL | E8: MAPLE- BAGAZO | F8: 15/01/2025 00:00:00 | G8: 16/01/2025 00:00:00 | J8: POR COGENERACION | O8: ...
B9: AGROINDUSTRIAS SAN JACINTO S.A.A. | C9: C.T. SAN JACINTO | D9: CENTRAL | E9: SAN_JACINTO - BAGAZO | F9: 15/01/2025 00:00:00 | G9: 16/01/2025 00:00:00 | J9: POR COGENERACION | O9: ...
B10: BIOENERGIA DEL CHIRA S.A. | C10: C.T. CAÑA BRAVA | D10: CENTRAL | E10: CANA BRAVA TV1 & TV2 - BAGAZO | F10: 15/01/2025 00:00:00 | G10: 16/01/2025 00:00:00 | J10: POR COGENERACION | O10: ...
B11: EGESUR | C11: C.T. INDEPENDENCIA | D11: CENTRAL | E11: INDEPENDENCIA GAS | F11: 15/01/2025 08:01:00 | G11: 15/01/2025 08:41:00 | H11: 15/01/2025 07:57:00 | J11: POR POTENCIA O ENERGIA | N11: xLT | O11: ...
B12: EGESUR | C12: C.T. INDEPENDENCIA | D12: CENTRAL | E12: INDEPENDENCIA GAS | F12: 15/01/2025 08:41:00 | G12: 15/01/2025 13:21:00 | J12: POR POTENCIA O ENERGIA | O12: ...
B13: EGESUR | C13: C.T. INDEPENDENCIA | D13: CENTRAL | E13: INDEPENDENCIA GAS | F13: 15/01/2025 13:21:00 | G13: 15/01/2025 17:00:00 | I13: 15/01/2025 16:48:00 | J13: POR POTENCIA O ENERGIA | N13: xLT | O13: ...
B14: EGESUR | C14: C.T. INDEPENDENCIA | D14: INDEP_G3 | E14: INDEPENDENCIA GAS | F14: 15/01/2025 17:02:00 | G14: 15/01/2025 17:12:00 | J14: A MINIMA CARGA | O14: ...
B15: ENEL GENERACION PIURA S.A. | C15: C.T. MALACAS 1 | D15: CENTRAL | E15: MALACAS1 TG6 - GAS | F15: 15/01/2025 00:00:00 | G15: 15/01/2025 01:54:00 | I15: 15/01/2025 01:37:00 | J15: POR POTENCIA O ENERGIA | O15: ...
B16: ENEL GENERACION PIURA S.A. | C16: C.T. MALACAS 1 | D16: CENTRAL | E16: MALACAS1 TG6 - GAS | F16: 15/01/2025 08:09:00 | G16: 16/01/2025 00:00:00 | H16: 15/01/2025 07:56:00 | J16: POR POTENCIA O ENERGIA | O16: ...
B17: ENGIE | C17: C.T. CHILCA 1 | D17: TG2 | E17: CHILCA1 TG2 - GAS | F17: 15/01/2025 08:56:00 | G17: 15/01/2025 12:04:00 | H17: 15/01/2025 08:41:00 | J17: POR POTENCIA O ENERGIA | O17: ...
B18: ENGIE | C18: C.T. CHILCA 1 | D18: TG2 | E18: CHILCA1 TG2 - GAS | F18: 15/01/2025 12:04:00 | G18: 15/01/2025 13:04:00 | I18: 15/01/2025 12:50:00 | J18: A MINIMA CARGA | O18: ...
B19: FENIX POWER PERÚ | C19: C.T. FENIX | D19: CENTRAL | E19: FENIX CCOMB GT11 & GT12 - GAS | F19: 15/01/2025 00:00:00 | G19: 15/01/2025 01:00:00 | J19: POR POTENCIA O ENERGIA | O19: ...
B20: FENIX POWER PERÚ | C20: C.T. FENIX | D20: CENTRAL | E20: FENIX CCOMB GT11 & GT12 - GAS | F20: 15/01/2025 01:00:00 | G20: 15/01/2025 05:06:00 | J20: POR RSF | O20: ...
B21: FENIX POWER PERÚ | C21: C.T. FENIX | D21: CENTRAL | E21: FENIX CCOMB GT11 & GT12 - GAS | F21: 15/01/2025 05:06:00 | G21: 15/01/2025 07:00:00 | J21: POR POTENCIA O ENERGIA | O21: ...
B22: FENIX POWER PERÚ | C22: C.T. FENIX | D22: CENTRAL | E22: FENIX CCOMB GT11 & GT12 - GAS | F22: 15/01/2025 07:00:00 | G22: 15/01/2025 07:37:00 | J22: POR RSF | O22: ...
B23: FENIX POWER PERÚ | C23: C.T. FENIX | D23: CENTRAL | E23: FENIX CCOMB GT11 & GT12 - GAS | F23: 15/01/2025 07:37:00 | G23: 15/01/2025 17:30:00 | J23: POR POTENCIA O ENERGIA | O23: ...
B24: FENIX POWER PERÚ | C24: C.T. FENIX | D24: CENTRAL | E24: FENIX CCOMB GT11 & GT12 - GAS | F24: 15/01/2025 17:30:00 | G24: 15/01/2025 18:30:00 | J24: POR RSF | O24: ...
B25: FENIX POWER PERÚ | C25: C.T. FENIX | D25: CENTRAL | E25: FENIX CCOMB GT11 & GT12 - GAS | F25: 15/01/2025 18:30:00 | G25: 15/01/2025 23:01:00 | J25: POR POTENCIA O ENERGIA | O25: ... | P25: S/C generar a 480 MW. A las 18:57 h, S/C generar a máxima.
B26: FENIX POWER PERÚ | C26: C.T. FENIX | D26: CENTRAL | E26: FENIX CCOMB GT11 & GT12 - GAS | F26: 15/01/2025 23:01:00 | G26: 16/01/2025 00:00:00 | J26: A MINIMA CARGA | O26: ... | P26: En proceso de desaciople de la unidad TG11.
B27: GM OPERACIONES S.A.C. | C27: CT REFINERIA TALARA | D27: TV1 REF TALARA | E27: REF_TALARA TV1 - NLH_RFG | F27: 15/01/2025 00:00:00 | G27: 16/01/2025 00:00:00 | J27: POR COGENERACION | O27: ...
B28: GM OPERACIONES S.A.C. | C28: CT REFINERIA TALARA | D28: TV2 REF TALARA | E28: REF_TALARA TV2 - NLH_RFG | F28: 15/01/2025 00:00:00 | G28: 16/01/2025 00:00:00 | J28: POR COGENERACION | O28: ...
B29: KALLPA GENERACION S.A. | C29: C.T. KALLPA | D29: CENTRAL | E29: KALLPA CCOMB TG1 & TG2 & TG3 - GAS | F29: 15/01/2025 00:00:00 | G29: 15/01/2025 00:16:00 | J29: POR POTENCIA O ENERGIA | O29: ...
B30: KALLPA GENERACION S.A. | C30: C.T. KALLPA | D30: CENTRAL | E30: KALLPA CCOMB TG1 & TG2 & TG3 - GAS | F30: 15/01/2025 00:16:00 | G30: 15/01/2025 07:37:00 | J30: POR RSF | O30: ...
B31: KALLPA GENERACION S.A. | C31: C.T. KALLPA | D31: CENTRAL | E31: KALLPA CCOMB TG1 & TG2 & TG3 - GAS | F31: 15/01/2025 07:37:00 | G31: 15/01/2025 13:21:00 | J31: POR POTENCIA O ENERGIA | O31: ...
B32: KALLPA GENERACION S.A. | C32: C.T. KALLPA | D32: CENTRAL | E32: KALLPA CCOMB TG1 & TG2 & TG3 - GAS | F32: 15/01/2025 13:21:00 | G32: 15/01/2025 14:30:00 | J32: POR RSF | O32: ...
B33: KALLPA GENERACION S.A. | C33: C.T. KALLPA | D33: CENTRAL | E33: KALLPA CCOMB TG1 & TG2 & TG3 - GAS | F33: 15/01/2025 14:30:00 | G33: 15/01/2025 17:00:00 | J33: POR POTENCIA O ENERGIA | O33: ...
B34: KALLPA GENERACION S.A. | C34: C.T. KALLPA | D34: CENTRAL | E34: KALLPA CCOMB TG1 & TG2 & TG3 - GAS | F34: 15/01/2025 17:00:00 | G34: 15/01/2025 19:23:00 | J34: POR RSF | O34: ...
B35: KALLPA GENERACION S.A. | C35: C.T. KALLPA | D35: CENTRAL | E35: KALLPA CCOMB TG1 & TG2 & TG3 - GAS | F35: 15/01/2025 19:23:00 | G35: 15/01/2025 23:00:00 | J35: POR POTENCIA O ENERGIA | O35: ...
B36: KALLPA GENERACION S.A. | C36: C.T. KALLPA | D36: CENTRAL | E36: KALLPA CCOMB TG1 & TG2 & TG3 - GAS | F36: 15/01/2025 23:00:00 | G36: 16/01/2025 00:00:00 | J36: POR RSF | O36: ...
B37: KALLPA GENERACION S.A. | C37: C.T. LAS FLORES | D37: CENTRAL | E37: LAS FLORES CCOMB TG1 - GAS | F37: 15/01/2025 00:00:00 | G37: 15/01/2025 23:18:00 | J37: POR POTENCIA O ENERGIA | O37: ... | P37: A las 17:50 h, S/C generar a 220 MW.
B38: KALLPA GENERACION S.A. | C38: C.T. LAS FLORES | D38: CENTRAL | E38: LAS FLORES CCOMB TG1 - GAS | F38: 15/01/2025 23:18:00 | G38: 16/01/2025 00:00:00 | J38: A MINIMA CARGA | O38: ...
B39: MINERA CERRO VERDE | C39: C.T. RECKA | D39: CENTRAL | E39: RECKA TG1 - D2 | F39: 15/01/2025 23:43:00 | G39: 16/01/2025 00:00:00 | H39: 15/01/2025 23:20:00 | J39: A MINIMA CARGA | O39: ...
B40: ORYGEN PERU S.A.A. | C40: C.T. VENTANILLA | D40: CENTRAL | E40: VENTANILLA CCOMB TG3 - GAS | F40: 15/01/2025 00:00:00 | G40: 15/01/2025 00:16:00 | J40: POR POTENCIA O ENERGIA | O40: ...
B41: ORYGEN PERU S.A.A. | C41: C.T. VENTANILLA | D41: CENTRAL | E41: VENTANILLA CCOMB TG3 - GAS | F41: 15/01/2025 00:16:00 | G41: 15/01/2025 08:34:00 | J41: A MINIMA CARGA | O41: ...
B42: ORYGEN PERU S.A.A. | C42: C.T. VENTANILLA | D42: CENTRAL | E42: VENTANILLA CCOMB TG3 - GAS | F42: 15/01/2025 08:34:00 | G42: 15/01/2025 13:21:00 | J42: POR POTENCIA O ENERGIA | O42: ...
B43: ORYGEN PERU S.A.A. | C43: C.T. VENTANILLA | D43: CENTRAL | E43: VENTANILLA CCOMB TG3 - GAS | F43: 15/01/2025 13:21:00 | G43: 15/01/2025 19:23:00 | J43: A MINIMA CARGA | O43: ...
B44: ORYGEN PERU S.A.A. | C44: C.T. VENTANILLA | D44: CENTRAL | E44: VENTANILLA CCOMB TG3 - GAS | F44: 15/01/2025 19:23:00 | G44: 15/01/2025 21:00:00 | J44: POR POTENCIA O ENERGIA | O44: ...
B45: ORYGEN PERU S.A.A. | C45: C.T. VENTANILLA | D45: CENTRAL | E45: VENTANILLA CCOMB TG3 - GAS | F45: 15/01/2025 21:00:00 | G45: 16/01/2025 00:00:00 | J45: A MINIMA CARGA | O45: ...
B46: PETRAMAS | C46: C.T. HUAYCOLORO | D46: CENTRAL | E46: HUAYCOLORO - BIOGAS | F46: 15/01/2025 00:00:00 | G46: 16/01/2025 00:00:00 | J46: POR POTENCIA O ENERGIA | O46: ...
B47: PETRAMAS | C47: C.T. LA GRINGA | D47: CENTRAL | E47: LA GRINGA V - BIOGAS | F47: 15/01/2025 00:00:00 | G47: 16/01/2025 00:00:00 | J47: POR POTENCIA O ENERGIA | O47: ...
B48: PETRAMAS | C48: C.T.B DOÑA CATALINA | D48: CENTRAL | E48: DONA CATALINA - BIOGAS | F48: 15/01/2025 00:00:00 | G48: 16/01/2025 00:00:00 | J48: POR POTENCIA O ENERGIA | O48: ...
B49: PETRAMAS | C49: C.T.B. CALLAO | D49: CENTRAL | E49: CALLAO - BIOGAS | F49: 15/01/2025 00:00:00 | G49: 16/01/2025 00:00:00 | J49: POR POTENCIA O ENERGIA | O49: ...
B50: SAMAY I S.A.C | C50: C.T. PUERTO BRAVO | D50: TG1 | E50: PTO BRAVO TG1 - D2 | F50: 15/01/2025 23:59:00 | G50: 16/01/2025 00:00:00 | H50: 15/01/2025 23:26:00 | J50: A MINIMA CARGA | O50: ...
B51: SDF ENERGIA SAC | C51: C.T. OQUENDO | D51: CENTRAL | E51: OQUENDO CCOMB TG1 - GAS | F51: 15/01/2025 00:00:00 | G51: 16/01/2025 00:00:00 | J51: POR COGENERACION | O51: ...
B52: TERMOSELVA | C52: C.T. AGUAYTIA | D52: TG1 | E52: AGUAYTIA TG1 - GAS | F52: 15/01/2025 21:35:00 | G52: 16/01/2025 00:00:00 | H52: 15/01/2025 21:04:00 | J52: A MINIMA CARGA | O52: ...
B53: TERMOSELVA | C53: C.T. AGUAYTIA | D53: TG2 | E53: AGUAYTIA TG2 - GAS | F53: 15/01/2025 22:24:00 | G53: 16/01/2025 00:00:00 | H53: 15/01/2025 22:11:00 | J53: A MINIMA CARGA | O53: ...

Sheet INDISP
B3: miércoles, 15 de Enero del 2025
B5: Hora Inicio y Fin de Indisponibilidades de las Unidades de Generación SEIN
B6: Empresa | C6: Ubicación | D6: Equipo | E6: Inicio | F6: Final | G6: Descripción | H6: MW Indisp. | I6: Prog. | J6: Dispon | K6: Interrupc. | L6: Tipo | M6: CodEq | N6: TipoEq_Osinerg
B7: ATRIA ENERGIA S.A.C. | C7: PURMACANA | D7: G1 | E7: 15/01/2025 00:00 | F7: 16/01/2025 00:00 | G7: OVERHAUL DE TURBINA | H7: 0.7 | I7: P | J7: F/S | K7: N | L7: PREV. | M7: 13133 | N7: G
B8: EGASA | C8: CHARCANI IV | D8: G2 | E8: 15/01/2025 00:00 | F8: 16/01/2025 00:00 | G8: Mantenimiento de Generador | H8: 5.1 | I8: P | J8: F/S | K8: N | L8: PREV. | M8: 119 | N8: G
B9: EGESUR | C9: INDEPENDENCIA | D9: INDEP_G4 | E9: 15/01/2025 00:00 | F9: 16/01/2025 00:00 | G9: Mantenimiento Correctivo por fatiga en la leva del cilindro A8 - 1ra ampliación | H9: 5.732 | I9: P | J9: F/S | K9: N | L9: CORR. | M9: 12780 | N9: G
B10: ENEL GENERACION PIURA S.A. | C10: MALACAS | D10: TG4 | E10: 15/01/2025 00:00 | F10: 16/01/2025 00:00 | G10: INSPECCION BOROSCOPIA TG4 | H10: 91.59 | I10: P | J10: F/S | K10: N | L10: PREV. | M10: 38 | N10: G
B11: ENGIE | C11: CHILCA 1 | D11: TG3 | E11: 15/01/2025 00:00 | F11: 16/01/2025 00:00 | G11: MANTENIMIENTO MAYOR 109500 EBH + LTE. UPGRADE FDX | H11: 190 | I11: P | J11: F/S | K11: N | L11: PREV. | M11: 12332 | N11: G
B12: INLAND ENERGY SAC | C12: SANTA TERESA | D12: G2 | E12: 15/01/2025 15:49 | F12: 15/01/2025 18:46 | G12: Se presencia fuga de aceite en a unidad U2 CHST. el cual requiere atencion inmediata | H12: 33 | I12: P | J12: F/S | K12: N | L12: CORR. | M12: 14846 | N12: G
B13: MINERA CERRO VERDE | C13: RECKA | D13: RECKA-TG1 | E13: 15/01/2025 08:27 | F13: 15/01/2025 16:51 | G13: PRUEBA DETECTORES DE FLAMA TG1. | H13: 179.37 | I13: P | J13: F/S | K13: N | L13: PREV. | M13: 15108 | N13: G
B14: ORYGEN PERU S.A.A. | C14: WAYRA EXTENSION | D14: CENTRAL | E14: 15/01/2025 00:00 | F14: 16/01/2025 00:00 | G14: 25 aerogeneradores disponibles, que equivale a una potencia nominal de 147.5 MW. Presenta 02 aerogeneradores en falla por alarmas. | H14: 11.8 | I14: P | J14: F/S | K14: N | L14: OTROS | M14: 23253 | N14: G
B15: TERMOCHILCA S.A.C. | C15: SANTO DOMINGO DE LOS OLLEROS | D15: TV | E15: 15/01/2025 00:00 | F15: 16/01/2025 00:00 | G15: Reparación interna del ACC y mantenimiento correctivo de válvula ESV HP | H15: 100 | I15: P | J15: F/S | K15: N | L15: CORR. | M15: 18479 | N15: G

Sheet RESERVA_FRÍA
B3: 15/01/2025 | E3: EJECUTADO | L3: Miércoles 15 de Enero del 2025 / SEM N° 2 | V3: EJECUTADO | AC3: Miércoles 15 de Enero del 2025 / SEM N° 2 | EC3: ENERGIA RENOVABLES | GL3: COGENERACION | GU3: NO INTEGRANTES
B4: Miércoles | C4: STARO | F4: ELECTROPERU | J4: ORAZU | L4: TER | N4: KALLPA GENERACION S.A. | V4: SHOUGESA | Z4: EGM | AA4: EGS | AC4: EGASA | AJ4: SGB | AK4: CELEP | AL4: MINCVE | AM4: ETEN | AO4: HUALLA | AQ4: LAVI | AR4: CHIN | AT4: HUANCH | AU4: CELER | AV4: INLD | AW4: FENIX POWER PERÚ | AZ4: STATKRAFT S.A | BH4: HUANZA | BI4: ENEL GENERACION PIURA S.A. | BL4: ENGIE | BZ4: IYEP | CB4: ORYGEN PERU S.A.A. | CN4: SAMAY I S.A.C | CR4: TCHILC | CT4: GENERACION | CW4: SALIDAS YUPANA | DA4: FLUJO EN LINEAS | DM4: COSTOS MARGINALES | DQ4: RESERVA | DV4: DEMANDA POR AREAS | EC4: ACHI | ED4: COLCA | EE4: ERSUR | EF4: GRCOR | EG4: TARU | EH4: KONDU | EI4: PIEREN | EJ4: ORAZU | EL4: AIPSA | EM4: MAJA | EN4: EGECSA | EO4: STANA | EP4: AGUAA | EQ4: RDOBLE | ER4: HIDRO | ES4: HUARA | ET4: MOQUE | EU4: PANAM | EV4: PARQU | EW4: PE3HER | EX4: PETRAMAS | FB4: TACNA | FC4: EYSAC | FD4: AURORA | FE4: AGROIN | FF4: ANDEA | FG4: ASLC | FH4: ATRIA | FI4: EGEJUNIN | FM4: EGERBA | FN4: EOL | FP4: ENGIE | FU4: GENE | FW4: GENERADORA DE ENERGÍA DEL PERÚ | GA4: PAINO | GB4: SARCUS | GC4: ORYGEN PERU S.A.A. | GH4: RARCUS | GI4: SINERS | GL4: ACHI | GM4: GM OP | GO4: SDF | GQ4: AIPSA | GR4: AURORA | GS4: AGROIN | GU4: UNACEM | GV4: SGB | GW4: EOR | GX4: AYEP | GY4: ELZANA | GZ4: ENOSA | HA4: SDE | HB4: SINERS | HE4: RESERVA
