Workbook

Sheet EVENTOS
B3: jueves, 20 de Marzo del 2025
B5: INFORMACIÓN DE EVENTOS PRINCIPALES EN SUS INSTALACIONES
B6: TIPO DE EVENTO | C6: EMPRESA | D6: UBICACIÓN | E6: TIPO DE EQUIPO | F6: EQUIPO | G6: INICIO | H6: FINAL | I6: DESCRIPCIÓN | J6: MW INDISP. | K6: INTERRUPCIÓN (SI/NO) | L6: TENSIÓN DE FALLA (kV)
B7: FALLA | C7: ATN 2 S.A. | D7: COTARUSE - LAS BAMBAS | E7: LINEA DE TRANSMISION | F7: L-2055 | G7: 20/03/2025 14:51:00 | H7: 20/03/2025 14:51:00 | I7: RECIERRE EXITOSO EN LAS LÍNEAS L-2055 Y L-2056 (COTARUSE - LAS BAMBAS) EN 220 KV | J7: 94.08 | K7: SI | L7: 220
B8: EVENTO | C8: CONELSUR LT SAC | D8: PORTILLO | E8: SUBESTACION | F8: SS.EE. | G8: 20/03/2025 00:00:00 | H8: 21/03/2025 00:00:00 | I8: DECLARACIÓN DE SITUACIÓN EXCEPCIONAL EN LA S.E. PORTILLO DE 60 kV | K8: NO
B9: EVENTO | C9: RED DE ENERGIA DEL PERU S.A. | D9: TINGO MARÍA - AUCAYACU | E9: LINEA DE TRANSMISION | F9: L-1122 | G9: 20/03/2025 10:03:00 | H9: 20/03/2025 13:06:00 | I9: DECLARACIÓN DE SITUACIÓN EXCEPCIONAL EN LA LÍNEA L-1122 (TINGO MARÍA - AUCAYACU) DE 138 kV | K9: NO
B10: EVENTO | C10: RED DE ENERGIA DEL PERU S.A. | D10: TINGO MARÍA - AUCAYACU | E10: LINEA DE TRANSMISION | F10: L-1122 | G10: 20/03/2025 18:29:00 | H10: 20/03/2025 21:42:00 | I10: DECLARACIÓN DE SITUACIÓN EXCEPCIONAL EN LA LÍNEA L-1122 (TINGO MARÍA - AUCAYACU) DE 138 kV | K10: NO
B11: FALLA | C11: RED DE ENERGIA DEL PERU S.A. | D11: SAN JUAN | E11: BANCO DE CONDENSADOR PARALELO | F11: BC-08 | G11: 20/03/2025 15:12:19 | H11: 20/03/2025 15:30:26 | I11: DESCONEXIÓN DEL BANCO BC-08 DE LA S.E. SAN JUAN | K11: NO | L11: 60
B12: FALLA | C12: SAN GABAN | D12: MCH TUPURI | E12: CENTRAL HIDROELÉCTRICA | F12: CENTRAL | G12: 20/03/2025 08:36:00 | H12: 20/03/2025 09:41:00 | I12: DESCONEXIÓN DE LA C.H. TUPURI | K12: NO | L12: 2.4
B13: FALLA | C13: STATKRAFT S.A | D13: MISAPUQUIO | E13: CENTRAL HIDROELÉCTRICA | F13: CENTRAL | G13: 20/03/2025 16:06:12 | H13: 21/03/2025 00:00:00 | I13: DESCONEXIÓN DE LA C.H. MISAPUQUIO | K13: NO | L13: 0
B14: FALLA | C14: TRANSMANTARO | D14: COTARUSE - SOCABAYA | E14: LINEA DE TRANSMISION | F14: L-2054 | G14: 20/03/2025 13:03:16 | H14: 20/03/2025 13:03:16 | I14: RECIERRE EN LA LÍNEA L-2054 (COTARUSE - SOCABAYA) DE 220 kV | K14: NO | L14: 220

Sheet RESTRIC_OPE
B3: jueves, 20 de Marzo del 2025
B5: RESTRICCIONES OPERATIVAS
B6: FECHA | C6: HORA INICIO | D6: HORA FINAL | E6: EMPRESA | F6: UBICACIÓN | G6: T.Eq. | H6: EQUIPO | I6: DESCRIPCIÓN
B7: 20/03/2025 | C7: 00:00 | D7: 24:00 | E7: CELEPSA | F7: C.H. EL PLATANAL | G7: CH | H7: CENTRAL | I7: Debido al incremento del caudal del rio cañete y establecimiento de la temporada de avenida, se declara la C.H. El Platanal como CENTRAL HIDRÁULICA DE PASADA (correo 03/01/2025).
B8: 20/03/2025 | C8: 00:00 | D8: 24:00 | E8: EGASA | F8: C.H. CHARCANI II | G8: GH | H8: G2 | I8: El Grupo N°02 esta operando con una potencia no mayor a 0.07MW en referencia a 0.18MW de su potencia efectiva, con el fin de no generar daños mayores hasta la reparación de su cojinete.
B9: 20/03/2025 | C9: 00:00 | D9: 24:00 | E9: EGASA | F9: S.E. CONVERTIDOR | G9: BARRA | H9: BARRA138KV | I9: EGASA limitó la capacidad del transformador 138 kV/33 kV a 50 MVA por deterioro del aislamiento.
B10: 20/03/2025 | C10: 00:00 | D10: 24:00 | E10: ENEL GENERACION PIURA S.A. | F10: C.T. MALACAS | G10: CT | H10: CENTRAL | I10: De acuerdo con la comunicación vía correo del día 24.10.2024. ENEL GENERACIÓN PIURA informa una restricción de potencia para alcanzar 105 MW en simultaneo (TG6+TGN4).
B11: 20/03/2025 | C11: 00:00 | D11: 24:00 | E11: ENGIE | F11: C.E. PUNTA LOMITAS | G11: CE | H11: CENTRAL | I11: De acuerdo a la carta ENG/737-2024 (Exp:202400007555). Limitación de cables de media tensión a 100 MW de los transformadores PLT1 y PLT2 de la CE Punta Lomitas. Quedan limitados a 200 MW la generación de CE Punta Lomitas y Punta Lomitas Extensión.
B12: 20/03/2025 | C12: 00:00 | D12: 24:00 | E12: ENGIE | F12: C.H. QUITARACSA | G12: CH | H12: CENTRAL | I12: De acuerdo con el correo del 23.04 se considera la operación continua de la CH Quitaracsa debido a que el sistema de refrigeración de la CH Cañón del Pato se alimenta desde la descarga del caudal turbinado por la CH Quitaracsa.
B13: 20/03/2025 | C13: 00:00 | D13: 24:00 | E13: ENGIE | F13: C.H. YUNCÁN | G13: GH | H13: G3 | I13: Según la carta N° ENG/ 198-2024 enviada por su representada, se opera de forma continua el G3 de la CH Yuncán, debido a la ejecución de mantenimientos necesarios para evitar daños en los sellos de seguridad de la válvula esférica del grupo.
B14: 20/03/2025 | C14: 00:00 | D14: 24:00 | E14: ENGIE | F14: C.T. CHILCA 1 | G14: CT | H14: CENTRAL | I14: Restricción de temperatura de la C.T Chilca, ver valor en el modelo de despacho.
B15: 20/03/2025 | C15: 00:00 | D15: 24:00 | E15: ENGIE | F15: C.T. CHILCA 1 | G15: CT | H15: CENTRAL | I15: Con carta ENG/971-2023, indica que no puede cumplir con las IO considerada en el PDO_17122023 dado que vulneran la seguridad de sus activos. Indican que se debe tomar TMO=168h.
B16: 20/03/2025 | C16: 00:00 | D16: 24:00 | E16: ENGIE | F16: C.T. CHILCA 2 | G16: CT | H16: CENTRAL | I16: Restricción de temperatura de la C.T Chilca2, ver valor en el modelo de despacho.
B17: 20/03/2025 | C17: 00:00 | D17: 24:00 | E17: ENGIE | F17: C.T. CHILCA 2 | G17: CT | H17: CENTRAL | I17: Con carta ENG/971-2023, indica que no puede cumplir con las IO considerada en el PDO_17122023 dado que vulneran la seguridad de sus activos. Indican que se debe tomar TMO=168h.
... B50: 20/03/2025 | C50: 00:00 | D50: 24:00 | E50: TRANSMANTARO | F50: S.E. SOCABAYA | G50: SSEE | H50: S.E. | I50: Opera en simple barra en 220 kV por indisponibilidad de la protección diferencial de barras por alarma.

Sheet MANTENIMIENTO EJECUTADOS
B3: jueves, 20 de Marzo del 2025
B5: Mantenimiento Ejecutado
B6: Empresa | C6: Ubicación | D6: Equipo | E6: Inicio | F6: Final | G6: Descripción | H6: MW Indisp. | I6: Prog. | J6: Dispon | K6: Interrupc. | L6: Tipo | M6: CodEq | N6: TipoEq_Osinerg
B7: ASOCIACION SANTA LUCIA DE CHACAS | C7: CH HUALLIN | D7: CENTRAL | E7: 20/03/2025 10:00 | F7: 20/03/2025 14:01 | G7: DESARENADO DE BOCATOMA | H7: 3 | I7: P | J7: F/S | K7: N | L7: PREV. | M7: 23678 | N7: G
B8: ATLANTICA TRANSMISION SUR S.A. | C8: CHILCA-CTM | D8: INT-5261 | E8: 20/03/2025 00:00 | F8: 21/03/2025 00:00 | G8: Seccionador SBB-5261 fase S indisponible para maniobras de apertura y cierre por anomalia en tapa de tanque de compresion, el seccionador permanece cerrado y bloqueado. | H8: 0 | I8: P | J8: E/S | K8: N | L8: OTROS | M8: 13854 | N8: T
B9: ATLANTICA TRANSMISION SUR S.A. | C9: CHILCA-CTM | D9: INT-5251 | E9: 20/03/2025 08:00 | F9: 20/03/2025 16:56 | G9: Reparacion de Fuga de gas SF6 en INT-5251 fase T | H9: 0 | I9: P | J9: F/S | K9: N | L9: CORR. | M9: 13855 | N9: T
B10: ATLANTICA TRANSMISION SUR S.A. | C10: MONTALVO | D10: ACOPLE 220 | E10: 20/03/2025 00:00 | F10: 21/03/2025 00:00 | G10: Proyecto Refuerzos: Reemplazo del HMI existente, Pruebas y Configuracion. No se contara con nivel 1 de operacion. | H10: 0 | I10: P | J10: E/S | K10: N | L10: P.ENERG | M10: 14767 | N10: T
B11: ATLANTICA TRANSMISION SUR S.A. | C11: MONTALVO | D11: CL-2057 | E11: 20/03/2025 00:00 | F11: 21/03/2025 00:00 | G11: Proyecto Refuerzos: Reemplazo del HMI existente, Pruebas y Configuracion. No se contara con nivel 1 de operacion. | H11: 0 | I11: P | J11: E/S | K11: N | L11: P.ENERG | M11: 13812 | N11: T
B12: ATLANTICA TRANSMISION SUR S.A. | C12: MONTALVO | D12: CL-AUT-5671_500 | E12: 20/03/2025 00:00 | F12: 21/03/2025 00:00 | G12: Proyecto Refuerzos: Reemplazo del HMI existente, Pruebas y Configuracion. No se contara con nivel 1 de operacion en INT-5671, INT-5652 y SAT-5671. | H12: 0 | I12: P | J12: E/S | K12: N | L12: P.ENERG | M12: 13809 | N12: T
B13: ATLANTICA TRANSMISION SUR S.A. | C13: MONTALVO | D13: INT-5652 | E13: 20/03/2025 00:00 | F13: 21/03/2025 00:00 | G13: Proyecto Refuerzos:Indisponible por Implementacion de conexion de corrientes, disparos, posiciones, enclavamientos hacia los nuevos equipos del transformador. Pruebas y Puesta en servicio. AUT-5671 en servicio solo por Barra A 500kV. | H13: 0 | I13: P | J13: F/S | K13: N | L13: P.ENERG | M13: 13765 | N13: T
B14: ATLANTICA TRANSMISION SUR S.A. | C14: MONTALVO | D14: AUT-5671 | E14: 20/03/2025 08:34 | F14: 20/03/2025 17:38 | G14: Cambio de rele de mando sincronizado. Prueba de Interruptor INT-5671 | H14: 0 | I14: P | J14: F/S | K14: N | L14: CORR. | M14: 13784 | N14: T
B15: ATLANTICA TRANSMISION SUR S.A. | C15: OCONA | D15: INT-5450 | E15: 20/03/2025 00:00 | F15: 21/03/2025 00:00 | G15: RESTRICCION OPERATIVA EN INTERRUPTOR INT-5450, POSICION CERRADA, REB-5450 EN SERVICIO SUMINISTRANDO LOS SS.AA. DE S.E. OCO?A | H15: 0 | I15: P | J15: E/S | K15: N | L15: OTROS | M15: 13761 | N15: T
B16: ATLANTICA TRANSMISION SUR S.A. | C16: OCONA | D16: INT-5462 | E16: 20/03/2025 00:00 | F16: 21/03/2025 00:00 | G16: Seccionador SBA-5462 fase T indisponible por problemas mecanicos, el seccionador permanece cerrado y bloqueado | H16: 0 | I16: P | J16: E/S | K16: N | L16: OTROS | M16: 13758 | N16: T
B17: ATLANTICA TRANSMISION SUR S.A. | C17: POROMA | D17: ACOPLE 220 | E17: 20/03/2025 00:00 | F17: 21/03/2025 00:00 | G17: Proyecto Refuerzos: Reemplazo del HMI existente, Pruebas y Configuracion. No se contara con nivel 1 de operacion. | H17: 0 | I17: P | J17: E/S | K17: N | L17: P.ENERG | M17: 13797 | N17: T
B18: ATLANTICA TRANSMISION SUR S.A. | C18: POROMA | D18: CL-2292 | E18: 20/03/2025 00:00 | F18: 21/03/2025 00:00 | G18: Proyecto Refuerzos: Reemplazo del HMI existente, Pruebas y Configuracion. No se contara con nivel 1 de operacion. | H18: 0 | I18: P | J18: E/S | K18: N | L18: P.ENERG | M18: 13798 | N18: T
... B127: TRANSMANTARO | C127: YARABAMBA | D127: IN-5120 | E127: 20/03/2025 00:00 | F127: 21/03/2025 00:00 | G127: INTERRUPTOR INDISPONIBLE POR FALLA EN LOS MANDOS DE CONTROL DE N1, N2 Y N3. | H127: 0 | I127: P | J127: F/S | K127: N | L127: OTROS | M127: 17437 | N127: T

Sheet INGRESO OC
A3: jueves, 20 de Marzo del 2025
A5: INGRESO A OPERACIÓN COMERCIAL
A6: EMPRESA | B6: TIPO DE EQUIPO | C6: UBICACIÓN | D6: EQUIPO | E6: Fecha y hora de Ingreso a Operación Comercial

Sheet DESPACHO_EJECUTADO
B3: jueves, 20 de Marzo del 2025
A5: POTENCIA ACTIVA EJECUTADA DE LAS UNIDADES DE GENERACIÓN DEL SEIN (MW) | FJ5: CENTRALES NO INTEGRANTES COES
A6: FECHA | B6: HORA | C6: 337 | D6: 338 | E6: 101 | F6: 102 | G6: 42667 | H6: 42668 | I6: 126 | J6: 127 | K6: 138 | L6: 139 | M6: 197 | N6: 203 | O6: 204 | P6: 230 | Q6: 209 | R6: 56677 | S6: 796 | T6: 2146 | U6: 142 | V6: 143 | W6: 125 | X6: 187 | Y6: 163 | Z6: 298 | AA6: 299 | AB6: 219 | AC6: 151 | AD6: 152 | AE6: 153 | AF6: 154 | AG6: 756 | AH6: 156 | AI6: 155 | AJ6: 182 | AK6: 212 | AL6: 758 | AM6: 263 | AN6: 265 | AO6: 775 | AP6: 777 | AQ6: 2154 | AR6: 150 | AS6: 149 | AT6: 188 | AU6: 2131 | AV6: 755 | AW6: 252 | AX6: 249 | AY6: 250 | AZ6: 117 | BA6: 267 | BB6: 268 | BC6: 119 | BD6: 120 | BE6: 189 | BF6: 122 | BG6: 266 | BH6: 251 | BI6: 115 | BJ6: 239 | BK6: 288 | BL6: 240 | BM6: 241 | BN6: 242 | BO6: 191 | BP6: 194 | BQ6: 196 | BR6: 207 | BS6: 236 | BT6: 795 | BU6: 285 | BV6: 995 | BW6: 996 | BX6: 997 | BY6: 766 | BZ6: 926 | CA6: 924 | CB6: 121 | CC6: 103 | CD6: 104 | CE6: 106 | CF6: 105 | CG6: 107 | CH6: 110 | CI6: 109 | CJ6: 144 | CK6: 113 | CL6: 114 | CM6: 193 | CN6: 208 | CO6: 786 | CP6: 787 | CQ6: 788 | CR6: 789 | CS6: 248 | CT6: 2159 | CU6: 303 | CV6: 59715 | CW6: 62255 | CX6: 1263 | CY6: 61800 | CZ6: 2194 | DA6: 216 | DB6: 198 | DC6: 49607 | DD6: 214 | DE6: 260 | DF6: 2152 | DG6: 2128 | DH6: 247 | DI6: 228 | DJ6: 2135 | DK6: 261 | DL6: 237 | DM6: 253 | DN6: 770 | DO6: 225 | DP6: 2201 | DQ6: 2171 | DR6: 760 | DS6: 235 | DT6: 238 | DU6: 2184 | DV6: 61855 | DW6: 223 | DX6: 226 | DY6: 201 | DZ6: 258 | EA6: 259 | EB6: 920 | EC6: 257 | ED6: 256 | EE6: 2148 | EF6: 58288 | EG6: 58289 | EH6: 58839 | EI6: 58840 | EJ6: 296 | EK6: 297 | EL6: 211 | EM6: 2175 | EN6: 2178 | EO6: 2181 | EP6: 1262 | EQ6: 233 | ER6: 2150 | ES6: 2165 | ET6: 2161 | EU6: 61197 | EV6: 58851 | EW6: 234 | EX6: 215 | EY6: 917 | EZ6: 289 | FA6: 58333 | FB6: 58336 | FC6: 202 | FD6: 58487 | FE6: 213 | FF6: 232 | FG6: 2190 | FH6: TOTAL COES | FJ6: 221 | FK6: 222 | FL6: 224 | FM6: 2187 | FN6: 227 | FO6: 49400 | FP6: 199 | FQ6: 200 | FR6: TOTAL NO COES
C7: CENTRO | D7: CENTRO | E7: CENTRO | F7: CENTRO | G7: NORTE | H7: NORTE | I7: NORTE | J7: NORTE | K7: CENTRO | L7: CENTRO | M7: CENTRO | N7: CENTRO | O7: CENTRO | P7: CENTRO | Q7: CENTRO | R7: CENTRO | S7: CENTRO | T7: CENTRO | U7: CENTRO | V7: CENTRO | W7: CENTRO | X7: CENTRO | Y7: SUR | Z7: SUR | AA7: SUR | AB7: CENTRO | AC7: SUR | AD7: SUR | AE7: SUR | AF7: SUR | AG7: SUR | AH7: SUR | AI7: SUR | AJ7: SUR | AK7: CENTRO | AL7: NORTE | AM7: NORTE | AN7: NORTE | AO7: CENTRO | AP7: CENTRO | AQ7: CENTRO | AR7: CENTRO | AS7: CENTRO | AT7: CENTRO | AU7: CENTRO | AV7: SUR | AW7: CENTRO | AX7: CENTRO | AY7: CENTRO | AZ7: CENTRO | BA7: CENTRO | BB7: CENTRO | BC7: CENTRO | BD7: CENTRO | BE7: SUR | BF7: NORTE | BG7: CENTRO | BH7: CENTRO | BI7: NORTE | BJ7: NORTE | BK7: NORTE | BL7: SUR | BM7: SUR | BN7: SUR | BO7: CENTRO | BP7: CENTRO | BQ7: CENTRO | BR7: CENTRO | BS7: CENTRO | BT7: CENTRO | BU7: CENTRO | BV7: SUR | BW7: SUR | BX7: SUR | BY7: NORTE | BZ7: SUR | CA7: CENTRO | CB7: NORTE | CC7: CENTRO | CD7: CENTRO | CE7: CENTRO | CF7: CENTRO | CG7: CENTRO | CH7: CENTRO | CI7: CENTRO | CJ7: CENTRO | CK7: CENTRO | CL7: CENTRO | CM7: CENTRO | CN7: CENTRO | CO7: SUR | CP7: SUR | CQ7: SUR | CR7: SUR | CS7: CENTRO | CT7: CENTRO | CU7: CENTRO | CV7: CENTRO | CW7: SUR | CX7: NORTE | CY7: NORTE | CZ7: NORTE | DA7: NORTE | DB7: NORTE | DC7: SUR | DD7: CENTRO | DE7: CENTRO | DF7: CENTRO | DG7: NORTE | DH7: NORTE | DI7: CENTRO | DJ7: CENTRO | DK7: SUR | DL7: SUR | DM7: CENTRO | DN7: CENTRO | DO7: CENTRO | DP7: CENTRO | DQ7: CENTRO | DR7: CENTRO | DS7: SUR | DT7: CENTRO | DU7: CENTRO | DV7: NORTE | DW7: CENTRO | DX7: CENTRO | DY7: NORTE | DZ7: CENTRO | EA7: CENTRO | EB7: CENTRO | EC7: NORTE | ED7: NORTE | EE7: SUR | EF7: CENTRO | EG7: CENTRO | EH7: CENTRO | EI7: CENTRO | EJ7: CENTRO | EK7: CENTRO | EL7: SUR | EM7: SUR | EN7: SUR | EO7: SUR | EP7: NORTE | EQ7: SUR | ER7: SUR | ES7: CENTRO | ET7: CENTRO | EU7: CENTRO | EV7: SUR | EW7: SUR | EX7: NORTE | EY7: CENTRO | EZ7: NORTE | FA7: NORTE | FB7: NORTE | FC7: CENTRO | FD7: CENTRO | FE7: CENTRO | FF7: NORTE | FG7: NORTE | FJ7: NORTE | FK7: CENTRO | FL7: NORTE | FM7: NORTE | FN7: NORTE | FO7: NORTE | FP7: NORTE | FQ7: NORTE
C8: HIDROELÉCTRICA | D8: HIDROELÉCTRICA | E8: HIDROELÉCTRICA | F8: HIDROELÉCTRICA | G8: TERMOELÉCTRICA | H8: TERMOELÉCTRICA | I8: HIDROELÉCTRICA | J8: HIDROELÉCTRICA | K8: TERMOELÉCTRICA | L8: TERMOELÉCTRICA | M8: TERMOELÉCTRICA | N8: TERMOELÉCTRICA | O8: TERMOELÉCTRICA | P8: TERMOELÉCTRICA | Q8: TERMOELÉCTRICA | R8: TERMOELÉCTRICA | S8: HIDROELÉCTRICA | T8: HIDROELÉCTRICA | U8: TERMOELÉCTRICA | V8: TERMOELÉCTRICA | W8: TERMOELÉCTRICA | X8: TERMOELÉCTRICA | Y8: HIDROELÉCTRICA | Z8: HIDROELÉCTRICA | AA8: HIDROELÉCTRICA | AB8: TERMOELÉCTRICA | AC8: HIDROELÉCTRICA | AD8: HIDROELÉCTRICA | AE8: HIDROELÉCTRICA | AF8: HIDROELÉCTRICA | AG8: TERMOELÉCTRICA | AH8: TERMOELÉCTRICA | AI8: TERMOELÉCTRICA | AJ8: HIDROELÉCTRICA | AK8: HIDROELÉCTRICA | AL8: TERMOELÉCTRICA | AM8: TERMOELÉCTRICA | AN8: TERMOELÉCTRICA | AO8: HIDROELÉCTRICA | AP8: HIDROELÉCTRICA | AQ8: HIDROELÉCTRICA | AR8: HIDROELÉCTRICA | AS8: HIDROELÉCTRICA | AT8: HIDROELÉCTRICA | AU8: HIDROELÉCTRICA | AV8: HIDROELÉCTRICA | AW8: TERMOELÉCTRICA | AX8: TERMOELÉCTRICA | AY8: TERMOELÉCTRICA | AZ8: HIDROELÉCTRICA | BA8: HIDROELÉCTRICA | BB8: HIDROELÉCTRICA | BC8: HIDROELÉCTRICA | BD8: HIDROELÉCTRICA | BE8: HIDROELÉCTRICA | BF8: HIDROELÉCTRICA | BG8: HIDROELÉCTRICA | BH8: HIDROELÉCTRICA | BI8: TERMOELÉCTRICA | BJ8: TERMOELÉCTRICA | BK8: TERMOELÉCTRICA | BL8: TERMOELÉCTRICA | BM8: TERMOELÉCTRICA | BN8: TERMOELÉCTRICA | BO8: HIDROELÉCTRICA | BP8: TERMOELÉCTRICA | BQ8: TERMOELÉCTRICA | BR8: TERMOELÉCTRICA | BS8: TERMOELÉCTRICA | BT8: TERMOELÉCTRICA | BU8: TERMOELÉCTRICA | BV8: TERMOELÉCTRICA | BW8: TERMOELÉCTRICA | BX8: TERMOELÉCTRICA | BY8: HIDROELÉCTRICA | BZ8: TERMOELÉCTRICA | CA8: TERMOELÉCTRICA | CB8: HIDROELÉCTRICA | CC8: HIDROELÉCTRICA | CD8: HIDROELÉCTRICA | CE8: HIDROELÉCTRICA | CF8: HIDROELÉCTRICA | CG8: HIDROELÉCTRICA | CH8: TERMOELÉCTRICA | CI8: TERMOELÉCTRICA | CJ8: TERMOELÉCTRICA | CK8: TERMOELÉCTRICA | CL8: TERMOELÉCTRICA | CM8: TERMOELÉCTRICA | CN8: TERMOELÉCTRICA | CO8: TERMOELÉCTRICA | CP8: TERMOELÉCTRICA | CQ8: TERMOELÉCTRICA | CR8: TERMOELÉCTRICA | CS8: TERMOELÉCTRICA | CT8: TERMOELÉCTRICA | CU8: SOLAR | CV8: EÓLICA | CW8: SOLAR | CX8: EÓLICA | CY8: SOLAR | CZ8: HIDROELÉCTRICA | DA8: HIDROELÉCTRICA | DB8: HIDROELÉCTRICA | DC8: HIDROELÉCTRICA | DD8: HIDROELÉCTRICA | DE8: HIDROELÉCTRICA | DF8: HIDROELÉCTRICA | DG8: HIDROELÉCTRICA | DH8: HIDROELÉCTRICA | DI8: HIDROELÉCTRICA | DJ8: HIDROELÉCTRICA | DK8: SOLAR | DL8: SOLAR | DM8: EÓLICA | DN8: EÓLICA | DO8: TERMOELÉCTRICA | DP8: TERMOELÉCTRICA | DQ8: TERMOELÉCTRICA | DR8: TERMOELÉCTRICA | DS8: SOLAR | DT8: HIDROELÉCTRICA | DU8: HIDROELÉCTRICA | DV8: HIDROELÉCTRICA | DW8: HIDROELÉCTRICA | DX8: HIDROELÉCTRICA | DY8: HIDROELÉCTRICA | DZ8: HIDROELÉCTRICA | EA8: HIDROELÉCTRICA | EB8: HIDROELÉCTRICA | EC8: EÓLICA | ED8: EÓLICA | EE8: SOLAR | EF8: EÓLICA | EG8: EÓLICA | EH8: EÓLICA | EI8: EÓLICA | EJ8: HIDROELÉCTRICA | EK8: HIDROELÉCTRICA | EL8: HIDROELÉCTRICA | EM8: HIDROELÉCTRICA | EN8: HIDROELÉCTRICA | EO8: HIDROELÉCTRICA | EP8: EÓLICA | EQ8: SOLAR | ER8: SOLAR | ES8: HIDROELÉCTRICA | ET8: EÓLICA | EU8: EÓLICA | EV8: SOLAR | EW8: SOLAR | EX8: HIDROELÉCTRICA | EY8: HIDROELÉCTRICA | EZ8: TERMOELÉCTRICA | FA8: TERMOELÉCTRICA | FB8: TERMOELÉCTRICA | FC8: TERMOELÉCTRICA | FD8: TERMOELÉCTRICA | FE8: TERMOELÉCTRICA | FF8: TERMOELÉCTRICA | FG8: TERMOELÉCTRICA | FJ8: HIDROELÉCTRICA | FK8: HIDROELÉCTRICA | FL8: HIDROELÉCTRICA | FM8: HIDROELÉCTRICA | FN8: TERMOELÉCTRICA | FO8: TERMOELÉCTRICA | FP8: HIDROELÉCTRICA | FQ8: HIDROELÉCTRICA
C9: CENTRALES SANTA ROSA S.A.C. | D9: CENTRALES SANTA ROSA S.A.C. | E9: ELECTROPERU | F9: ELECTROPERU | G9: ELECTROPERU | H9: ELECTROPERU | I9: ORAZUL ENERGY PERÚ | J9: ORAZUL ENERGY PERÚ | K9: TERMOSELVA | L9: TERMOSELVA | M9: KALLPA GENERACION S.A. | N9: KALLPA GENERACION S.A. | O9: KALLPA GENERACION S.A. | P9: KALLPA GENERACION S.A. | Q9: KALLPA GENERACION S.A. | R9: KALLPA GENERACION S.A. | S9: KALLPA GENERACION S.A. | T9: KALLPA GENERACION S.A. | U9: SHOUGESA | V9: SHOUGESA | W9: SHOUGESA | X9: SHOUGESA | Y9: EGEMSA | Z9: EGESUR | AA9: EGESUR | AB9: EGESUR | AC9: EGASA | AD9: EGASA | AE9: EGASA | AF9: EGASA | AG9: EGASA | AH9: EGASA | AI9: EGASA | AJ9: SAN GABAN | AK9: CELEPSA | AL9: MINERA CERRO VERDE | AM9: PLANTA DE RESERVA FRIA DE GENERACION DE ETEN S.A. | AN9: PLANTA DE RESERVA FRIA DE GENERACION DE ETEN S.A. | AO9: EMPRESA DE GENERACION HUALLAGA | AP9: EMPRESA DE GENERACION HUALLAGA | AQ9: LA VIRGEN | AR9: CHINANGO S.A.C. | AS9: CHINANGO S.A.C. | AT9: HIDROELECTRICA HUANCHOR S.A.C. | AU9: CELEPSA RENOVABLES S.R.L. | AV9: INLAND ENERGY SAC | AW9: FENIX POWER PERÚ | AX9: FENIX POWER PERÚ | AY9: FENIX POWER PERÚ | AZ9: STATKRAFT S.A | BA9: STATKRAFT S.A | BB9: STATKRAFT S.A | BC9: STATKRAFT S.A | BD9: STATKRAFT S.A | BE9: STATKRAFT S.A | BF9: STATKRAFT S.A | BG9: STATKRAFT S.A | BH9: EMPRESA DE GENERACION HUANZA | BI9: ENEL GENERACION PIURA S.A. | BJ9: ENEL GENERACION PIURA S.A. | BK9: ENEL GENERACION PIURA S.A. | BL9: ENGIE | BM9: ENGIE | BN9: ENGIE | BO9: ENGIE | BP9: ENGIE | BQ9: ENGIE | BR9: ENGIE | BS9: ENGIE | BT9: ENGIE | BU9: ENGIE | BV9: ENGIE | BW9: ENGIE | BX9: ENGIE | BY9: ENGIE | BZ9: INFRAESTRUCTURAS Y ENERGIAS DEL PERU S.A.C. | CA9: INFRAESTRUCTURAS Y ENERGIAS DEL PERU S.A.C. | CB9: INVERSIONES SHAQSHA S.A.C. | CC9: ORYGEN PERU S.A.A. | CD9: ORYGEN PERU S.A.A. | CE9: ORYGEN PERU S.A.A. | CF9: ORYGEN PERU S.A.A. | CG9: ORYGEN PERU S.A.A. | CH9: ORYGEN PERU S.A.A. | CI9: ORYGEN PERU S.A.A. | CJ9: ORYGEN PERU S.A.A. | CK9: ORYGEN PERU S.A.A. | CL9: ORYGEN PERU S.A.A. | CM9: ORYGEN PERU S.A.A. | CN9: ORYGEN PERU S.A.A. | CO9: SAMAY I S.A.C | CP9: SAMAY I S.A.C | CQ9: SAMAY I S.A.C | CR9: SAMAY I S.A.C | CS9: TERMOCHILCA S.A.C. | CT9: TERMOCHILCA S.A.C. | CU9: COLCA SOLAR S.A.C. | CV9: ENERGIA RENOVABLE DEL SUR S.A. | CW9: GR CORTARRAMA SOCIEDAD ANONIMA CERRADA | CX9: GR TARUCA SOCIEDAD ANONIMA CERRADA | CY9: KONDU SAC | CZ9: PERUANA DE INVERSIONES EN ENERGIAS RENOVABLES S.A. | DA9: ORAZUL ENERGY PERÚ | DB9: ORAZUL ENERGY PERÚ | DC9: SAN GABAN | DD9: MAJA ENERGIA S.A.C. | DE9: EMPRESA DE GENERACION ELECTRICA CANCHAYLLO SAC | DF9: EMPRESA DE GENERACION ELECTRICA SANTA ANA S.A.C. | DG9: EMPRESA ELECTRICA AGUA AZUL | DH9: EMPRESA ELECTRICA RIO DOBLE | DI9: HIDROCAÑETE S.A. | DJ9: HUAURA POWER GROUP S.A. | DK9: MOQUEGUA FV S.A.C. | DL9: PANAMERICANA SOLAR SAC. | DM9: PARQUE EOLICO MARCONA S.A.C. | DN9: PARQUE EOLICO TRES HERMANAS S.A.C. | DO9: PETRAMAS | DP9: PETRAMAS | DQ9: PETRAMAS | DR9: PETRAMAS | DS9: TACNA SOLAR SAC. | DT9: ELECTRICA YANAPAMPA SAC | DU9: ANDEAN POWER S.A.C. | DV9: ASOCIACIÓN SANTA LUCIA DE CHACAS | DW9: ATRIA ENERGIA S.A.C. | DX9: EGEJUNIN | DY9: EGEJUNIN | DZ9: EGEJUNIN | EA9: EGEJUNIN | EB9: EMPRESA DE GENERACION ELECTRICA RIO BAÑOS S.A.C. | EC9: ENERGÍA EÓLICA S.A. | ED9: ENERGÍA EÓLICA S.A. | EE9: ENGIE | EF9: ENGIE | EG9: ENGIE | EH9: ENGIE | EI9: ENGIE | EJ9: GENERACIÓN ANDINA S.A.C. | EK9: GENERACIÓN ANDINA S.A.C. | EL9: GENERADORA DE ENERGÍA DEL PERÚ | EM9: GENERADORA DE ENERGÍA DEL PERÚ | EN9: GENERADORA DE ENERGÍA DEL PERÚ | EO9: GENERADORA DE ENERGÍA DEL PERÚ | EP9: GR PAINO SOCIEDAD ANONIMA CERRADA | EQ9: MAJES ARCUS S.A.C. | ER9: ORYGEN PERU S.A.A. | ES9: ORYGEN PERU S.A.A. | ET9: ORYGEN PERU S.A.A. | EU9: ORYGEN PERU S.A.A. | EV9: ORYGEN PERU S.A.A. | EW9: REPARTICIÓN ARCUS S.A.C. | EX9: SINERSA | EY9: SINERSA | EZ9: BIOENERGIA DEL CHIRA S.A. | FA9: GM OPERACIONES S.A.C. | FB9: GM OPERACIONES S.A.C. | FC9: SDF ENERGIA SAC | FD9: SDF ENERGIA SAC | FE9: AGRO INDUSTRIAL PARAMONGA S.A. | FF9: AGROAURORA S.A.C. | FG9: AGROINDUSTRIAS SAN JACINTO S.A.A. | FJ9: UNACEM PERU S.A. | FK9: ELECTRO ORIENTE | FL9: AGUAS Y ENERGIA PERU | FM9: ELECTRO ZAÑA S.A.C. | FN9: ELECTRONOROESTE S.A. | FO9: SDE PIURA | FP9: SINERSA | FQ9: SINERSA
C10: SANTA ROSA 1 | D10: SANTA ROSA 2 | E10: MANTARO | F10: RESTITUCION | G10: TUMBES MAK 1 | H10: TUMBES MAK 2 | I10: CARHUAQUERO | J10: CAÑON DEL PATO | K10: AGUAYTIA TG1 | L10: AGUAYTIA TG2 | M10: KALLPA TG1 | N10: KALLPA TG2 | O10: KALLPA TG3 | P10: KALLPA TV | Q10: LFLORES TG1 | R10: LFLORES TV | S10: CERRO DEL AGUILA | T10: CERRODELAGUILAG4 | U10: SHOUGESA TV1 | V10: SHOUGESA TV2 | W10: SHOUGESA TV3 | X10: SHOUGESA CUMMINS | Y10: MACHUPICCHU | Z10: ARICOTA 1 | AA10: ARICOTA 2 | AB10: INDEPENDENCIA | AC10: CHARCANI I,II,III | AD10: CHARCANI IV | AE10: CHARCANI V | AF10: CHARCANI VI | AG10: CHILINA TG | AH10: MOLLENDO 1, 2, 3 | AI10: CHILINA (SULZ 1,2) | AJ10: SAN GABAN II | AK10: PLATANAL | AL10: RECKA | AM10: RF ETEN TG1 | AN10: RF ETEN TG2 | AO10: CHAGLLA GP1 | AP10: CHAGLLA | AQ10: LA VIRGEN | AR10: CHIMAY | AS10: YANANGO | AT10: HUANCHOR | AU10: MARAÑON | AV10: STA TERESA | AW10: FENIX GT11 | AX10: FENIX GT12 | AY10: FENIX TV10 | AZ10: YAUPI | BA10: OROYA | BB10: PACHACHACA | BC10: MALPASO | BD10: CAHUA | BE10: ARCATA | BF10: GALLITO CIEGO | BG10: CHEVES | BH10: HUANZA | BI10: MALACAS2 TG4 | BJ10: MALACAS3 TG 5 | BK10: MALACAS1 TG6 | BL10: RF ILO2 TG1 | BM10: RF ILO2 TG2 | BN10: RF ILO2 TG3 | BO10: YUNCAN | BP10: CHILCA1 TG1 | BQ10: CHILCA1 TG2 | BR10: CHILCA1 TG3 | BS10: CHILCA-TV | BT10: CHILCA2 TG41 | BU10: CHILCA2-TV | BV10: CTNEPI_TG41 | BW10: CTNEPI_TG42 | BX10: CTNEPI_TG43 | BY10: QUITARACSA | BZ10: RF PTO MALDONADO | CA10: RF PUCALLPA | CB10: PARIAC | CC10: HUINCO | CD10: MATUCANA | CE10: MOYOPAMPA | CF10: CALLAHUANCA | CG10: HUAMPANI | CH10: STA ROSA WEST TG7 | CI10: UTI_5 | CJ10: UTI_6 | CK10: VENTANILLA 3 | CL10: VENTANILLA 4 | CM10: VENTANILLA TV | CN10: STAROSA TG8 | CO10: PTO_BRVO TG1 | CP10: PTO_BRVO TG2 | CQ10: PTO_BRVO TG3 | CR10: PTO_BRVO TG4 | CS10: OLLEROS TG1 | CT10: OLLEROS TV | CU10: CS YARUCAYA | CV10: SAN JUAN | CW10: MATARANI | CX10: DUNA | CY10: CARHUAQUERO (CS) | CZ10: MANTA I | DA10: CARHUAQUERO4 | DB10: CAÑA BRAVA | DC10: TUPURI | DD10: RONCADOR | DE10: CANCHAYLLO | DF10: RENOVANDESH1 | DG10: POTRERO | DH10: PIZARRAS | DI10: NIMPERIAL | DJ10: YARUCAYA | DK10: MOQUEGUA-SOLAR | DL10: PANAMERICANA-SOLAR | DM10: PQE-EOLICO-MARCONA | DN10: PQE-EOLICO-3-HERMANAS | DO10: HUAYCOLORO | DP10: CALLAO | DQ10: DONA_CATALINA | DR10: LAGRINGAV | DS10: TACNA-SOLAR | DT10: YANAPAMPA | DU10: CARHUAC | DV10: HUALLIN | DW10: PURMACANA | DX10: HUASAHUASI | DY10: STACRUZ_1_2 | DZ10: RUNATULLO_II | EA10: RUNATULLO_III | EB10: RUCUY | EC10: PQE-EOLICO-TALARA | ED10: PQE-EOLICO-CUPISNIQUE | EE10: INTIPAMPA | EF10: PUNTA LOMITAS-BL1 | EG10: PUNTA LOMITAS-BL2 | EH10: PUN LOMITAS_EXP-BL1 | EI10: PUN LOMITAS_EXP-BL2 | EJ10: 8AGOSTO | EK10: EL CARMEN | EL10: LA JOYA | EM10: ANGEL_I | EN10: ANGEL_II | EO10: ANGEL_III | EP10: HUAMBOS | EQ10: MAJES | ER10: RUBI | ES10: CH_HER1 | ET10: WAYRA-I | EU10: WAYRA EXTENSION | EV10: CLEMESI | EW10: REPARTICION | EX10: POECHOS2 | EY10: CHANCAY | EZ10: CANA BRAVA | FA10: REFINERIA TALARA TV1 | FB10: REFINERÍA TALARA TV2 | FC10: OQUENDO TG1 | FD10: OQUENDO TV1 | FE10: PARAMONGA | FF10: MAPLE | FG10: SAN_JACINTO | FH10: MW | FJ10: CARPAPATA | FK10: CENTRALES ELOR | FL10: PIAS1 | FM10: ZANA | FN10: TABLAZO | FO10: TALLANCA | FP10: CURUMUY | FQ10: POECHOS1 | FR10: MW
A11: 20/03/2025 | B11: 00:30 | C11: 0 | D11: 0 | E11: 593 | F11: 181.5 | I11: 90.2 | J11: 226.8 | M11: 116.5 | N11: 116.7 | O11: 116.7 | P11: 214.5 | Q11: 107.7 | R11: 67.7 | S11: 368.9 | T11: 10.5 | Y11: 162.9 | Z11: 7.5 | AA11: 2.9 | AB11: 0 | AC11: 6.2 | AD11: 10 | AE11: 143.4 | AF11: 9 | AJ11: 110.3 | AK11: 223.1 | AO11: 6.5 | AP11: 461.5 | AQ11: 81.9 | AR11: 129.9 | AS11: 42.3 | AT11: 18.5 | AU11: 19.7 | AV11: 89.5 | AW11: 121.6 | AX11: 121.5 | AY11: 151.7 | AZ11: 105.4 | BB11: 0 | BC11: 44.8 | BD11: 46.5 | BE11: 3.8 | BF11: 37.8 | BG11: 172.8 | BH11: 95.2 | BI11: 24.9 | BN11: 0 | BO11: 86.7 | BP11: 84.7 | BQ11: 0 | BR11: 84.7 | BS11: 109.4 | CB11: 1.5 | CC11: 221.7 | CD11: 117.4 | CE11: 64.4 | CF11: 78.5 | CG11: 30.2 | CL11: 120.5 | CM11: 57 | CU11: 0 | CV11: 95.3 | CW11: 0 | CX11: 17 | CY11: 0 | DA11: 10.3 | DB11: 5.5 | DC11: 1.3 | DD11: 1.8 | DE11: 5.1 | DF11: 20 | DG11: 18.2 | DH11: 19 | DI11: 3.4 | DJ11: 18.6 | DK11: 0 | DL11: 0 | DM11: 30.1 | DN11: 71.5 | DO11: 4.8 | DP11: 2.4 | DQ11: 2.4 | DR11: 2.3 | DS11: 0 | DT11: 3.3 | DU11: 20.3 | DV11: 3 | DW11: 0 | DX11: 19.8 | DY11: 13 | DZ11: 20.1 | EA11: 20.2 | EB11: 20 | EC11: 13.9 | ED11: 12.1 | EE11: 0 | EF11: 41.8 | EG11: 67 | EH11: 1.1 | EI11: 1 | EJ11: 21 | EK11: 4 | EL11: 6.7 | EM11: 20.4 | EN11: 20.4 | EO11: 20.2 | EP11: 13.4 | EQ11: 0 | ER11: 0 | ES11: 0.6 | ET11: 22.1 | EU11: 15.9 | EV11: 0 | EW11: 0 | EX11: 9 | EY11: 20 | FA11: 44 | FB11: 24.3 | FC11: 28.9 | FD11: 3.4 | FE11: 15.5 | FF11: 9.6 | FG11: 7.2 | FH11: 6610.7 | FJ11: 24.45276 | FK11: 8.068 | FM11: 13.2 | FO11: 9.47073 | FP11: 10.4 | FQ11: 16.1 | FR11: 81.69149
A12: 20/03/2025 | B12: 01:00 | C12: 0 | D12: 0 | E12: 598.5 | F12: 182.3 | I12: 85.2 | J12: 227.6 | M12: 107 | N12: 106.8 | O12: 106.9 | P12: 207.6 | Q12: 108 | R12: 68 | S12: 367.6 | T12: 10.5 | Y12: 165.3 | Z12: 7.5 | AA12: 3 | AB12: 0 | AC12: 6.1 | AD12: 10.2 | AE12: 143.4 | AF12: 9 | AJ12: 111.4 | AK12: 222.7 | AO12: 6.5 | AP12: 350.6 | AQ12: 81.9 | AR12: 124.9 | AS12: 42.2 | AT12: 18.5 | AU12: 19.7 | AV12: 90.1 | AW12: 122.9 | AX12: 122.8 | AY12: 151.8 | AZ12: 105.4 | BB12: 0 | BC12: 44.7 | BD12: 47.1 | BE12: 3.8 | BF12: 38.1 | BG12: 174.4 | BH12: 95.8 | BI12: 24.9 | BN12: 0 | BO12: 87.3 | BP12: 85.9 | BQ12: 0 | BR12: 85.5 | BS12: 108.5 | CB12: 1.5 | CC12: 207.4 | CD12: 112.8 | CE12: 65 | CF12: 79.6 | CG12: 30.7 | CL12: 120.7 | CM12: 57.5 | CU12: 0 | CV12: 94.5 | CW12: 0 | CX12: 14.6 | CY12: 0 | DA12: 10.3 | DB12: 5.4 | DC12: 1.3 | DD12: 1.8 | DE12: 5.2 | DF12: 20.4 | DG12: 18.4 | DH12: 19 | DI12: 3.5 | DJ12: 18.6 | DK12: 0 | DL12: 0 | DM12: 30.6 | DN12: 73.5 | DO12: 4.8 | DP12: 2.4 | DQ12: 2.4 | DR12: 2.3 | DS12: 0 | DT12: 3.1 | DU12: 20.3 | DV12: 3 | DW12: 0 | DX12: 19.8 | DY12: 13 | DZ12: 19.9 | EA12: 20.3 | EB12: 19.9 | EC12: 12 | ED12: 19.4 | EE12: 0 | EF12: 43.7 | EG12: 61.6 | EH12: 1.7 | EI12: 1.1 | EJ12: 21 | EK12: 4.2 | EL12: 6.7 | EM12: 20.4 | EN12: 20.4 | EO12: 20.2 | EP12: 9.4 | EQ12: 0 | ER12: 0 | ES12: 0.6 | ET12: 25.3 | EU12: 18.6 | EV12: 0 | EW12: 0 | EX12: 9 | EY12: 19.9 | FA12: 44.1 | FB12: 24.4 | FC12: 28.9 | FD12: 3.3 | FE12: 15.4 | FF12: 9.6 | FG12: 6.7 | FH12: 6459 | FJ12: 24.45244 | FK12: 8.067 | FM12: 13.2 | FO12: 9.47059 | FP12: 10.5 | FQ12: 16.2 | FR12: 81.89003
A13: 20/03/2025 | B13: 01:30 | C13: 0 | D13: 0 | E13: 598.5 | F13: 200 | I13: 87.1 | J13: 227.7 | M13: 114.6 | N13: 114 | O13: 114 | P13: 210.8 | Q13: 108.3 | R13: 68 | S13: 374.9 | T13: 10.5 | Y13: 163.1 | Z13: 7 | AA13: 3.2 | AB13: 0 | AC13: 6 | AD13: 10 | AE13: 143.6 | AF13: 8.9 | AJ13: 111 | AK13: 222.7 | AO13: 6.5 | AP13: 297.2 | AQ13: 81.9 | AR13: 133.8 | AS13: 42.2 | AT13: 18.5 | AU13: 19.7 | AV13: 90.2 | AW13: 122.2 | AX13: 122.2 | AY13: 151.7 | AZ13: 105.3 | BB13: 0 | BC13: 44.9 | BD13: 46.8 | BE13: 3.8 | BF13: 37.9 | BG13: 173.8 | BH13: 95.4 | BI13: 24.8 | BN13: 0 | BO13: 87 | BP13: 84.5 | BQ13: 0 | BR13: 84.3 | BS13: 109.1 | CB13: 1.5 | CC13: 230.6 | CD13: 120.4 | CE13: 64.6 | CF13: 79.6 | CG13: 30.8 | CL13: 120.2 | CM13: 56.6 | CU13: 0 | CV13: 94.5 | CW13: 0 | CX13: 12.7 | CY13: 0 | DA13: 10.3 | DB13: 5.4 | DC13: 1.3 | DD13: 1.7 | DE13: 5.2 | DF13: 20.3 | DG13: 18.9 | DH13: 18.9 | DI13: 3.5 | DJ13: 18.6 | DK13: 0 | DL13: 0 | DM13: 31.4 | DN13: 76.3 | DO13: 4.8 | DP13: 2.4 | DQ13: 2.4 | DR13: 2.5 | DS13: 0 | DT13: 3.2 | DU13: 20.3 | DV13: 3 | DW13: 0 | DX13: 19.8 | DY13: 13.1 | DZ13: 19.6 | EA13: 20.3 | EB13: 20 | EC13: 15.1 | ED13: 29.6 | EE13: 0 | EF13: 26.3 | EG13: 48.7 | EH13: 0.7 | EI13: 0 | EJ13: 21 | EK13: 4.3 | EL13: 6.7 | EM13: 20.4 | EN13: 20.4 | EO13: 20.2 | EP13: 8 | EQ13: 0 | ER13: 0 | ES13: 0.6 | ET13: 30 | EU13: 29.3 | EV13: 0 | EW13: 0 | EX13: 9 | EY13: 20 | FA13: 44.4 | FB13: 24.4 | FC13: 29 | FD13: 3.4 | FE13: 15.5 | FF13: 9.5 | FG13: 7 | FH13: 6485.8 | FJ13: 24.45051 | FK13: 8.068 | FM13: 13.2 | FO13: 9.47069 | FP13: 10.5 | FQ13: 16.1 | FR13: 81.7892
A14: 20/03/2025 | B14: 02:00 | C14: 0 | D14: 0 | E14: 598.6 | F14: 199.6 | I14: 87.5 | J14: 227.3 | M14: 113.3 | N14: 113.8 | O14: 115.1 | P14: 213.7 | Q14: 109.4 | R14: 68.4 | S14: 378.2 | T14: 10.5 | Y14: 165.9 | Z14: 7.1 | AA14: 3.8 | AB14: 0 | AC14: 6 | AD14: 10.1 | AE14: 144.3 | AF14: 8.9 | AJ14: 82.6 | AK14: 222.9 | AO14: 6.5 | AP14: 302.5 | AQ14: 47.4 | AR14: 132.4 | AS14: 42.3 | AT14: 18.5 | AU14: 19.7 | AV14: 90.7 | AW14: 123.7 | AX14: 124.8 | AY14: 152.5 | AZ14: 72.6 | BB14: 0 | BC14: 44.7 | BD14: 47.4 | BE14: 3.8 | BF14: 38.4 | BG14: 174.8 | BH14: 95.9 | BI14: 24.8 | BN14: 0 | BO14: 87.3 | BP14: 86.1 | BQ14: 0 | BR14: 86 | BS14: 108.5 | CB14: 1.5 | CC14: 230.7 | CD14: 120.5 | CE14: 65 | CF14: 79.6 | CG14: 30.8 | CL14: 120.9 | CM14: 57.6 | CU14: 0 | CV14: 92.6 | CW14: 0 | CX14: 12.7 | CY14: 0 | DA14: 10.3 | DB14: 5.4 | DC14: 1.2 | DD14: 1.7 | DE14: 5.1 | DF14: 20.4 | DG14: 18 | DH14: 18.9 | DI14: 3.5 | DJ14: 18.6 | DK14: 0 | DL14: 0 | DM14: 30.1 | DN14: 71.7 | DO14: 4.8 | DP14: 2.4 | DQ14: 2.4 | DR14: 2.5 | DS14: 0 | DT14: 3.3 | DU14: 20.3 | DV14: 3 | DW14: 0 | DX14: 19.8 | DY14: 13 | DZ14: 19.5 | EA14: 20.3 | EB14: 19.8 | EC14: 14.6 | ED14: 32.1 | EE14: 0 | EF14: 23.6 | EG14: 49.9 | EH14: 0.6 | EI14: 0.1 | EJ14: 21 | EK14: 4.3 | EL14: 6.6 | EM14: 20.4 | EN14: 20.4 | EO14: 20.2 | EP14: 9.7 | EQ14: 0 | ER14: 0 | ES14: 0.6 | ET14: 40.6 | EU14: 29.1 | EV14: 0 | EW14: 0 | EX14: 9 | EY14: 19.9 | FA14: 43.3 | FB14: 23.8 | FC14: 29 | FD14: 3.4 | FE14: 15.5 | FF14: 9.6 | FG14: 7.3 | FH14: 6420.8 | FJ14: 24.44629 | FK14: 8.066 | FM14: 13.2 | FO14: 9.4709 | FP14: 10.5 | FQ14: 16 | FR14: 81.68319
A15: 20/03/2025 | B15: 02:30 | C15: 0 | D15: 0 | E15: 599.7 | F15: 149 | I15: 91 | J15: 227.8 | M15: 108 | N15: 107.9 | O15: 107.8 | P15: 204.2 | Q15: 109.5 | R15: 67.2 | S15: 378.9 | T15: 10.4 | Y15: 164.9 | Z15: 7.7 | AA15: 3 | AB15: 0 | AC15: 5.9 | AD15: 10.1 | AE15: 144.2 | AF15: 8.9 | AJ15: 82.2 | AK15: 222.6 | AO15: 6.5 | AP15: 340.3 | AQ15: 40 | AR15: 135.1 | AS15: 42.3 | AT15: 18.5 | AU15: 19.7 | AV15: 88.1 | AW15: 121.3 | AX15: 121.6 | AY15: 152.2 | AZ15: 71.9 | BB15: 0 | BC15: 43.9 | BD15: 47 | BE15: 3.8 | BF15: 37.4 | BG15: 173.6 | BH15: 95.4 | BI15: 25.5 | BN15: 0 | BO15: 87.1 | BP15: 86.3 | BQ15: 0 | BR15: 85.6 | BS15: 109.3 | CB15: 1.5 | CC15: 236.7 | CD15: 135.9 | CE15: 64.6 | CF15: 79.6 | CG15: 30.2 | CL15: 122.5 | CM15: 58.4 | CU15: 0 | CV15: 92.6 | CW15: 0 | CX15: 14.4 | CY15: 0 | DA15: 10.3 | DB15: 5.5 | DC15: 1.2 | DD15: 1.7 | DE15: 5.1 | DF15: 20.1 | DG15: 18.4 | DH15: 19 | DI15: 3.5 | DJ15: 18.6 | DK15: 0 | DL15: 0 | DM15: 29.7 | DN15: 65.5 | DO15: 4.8 | DP15: 2.4 | DQ15: 2.4 | DR15: 2.5 | DS15: 0 | DT15: 3.3 | DU15: 20.3 | DV15: 3 | DW15: 0 | DX15: 19.8 | DY15: 13 | DZ15: 19.6 | EA15: 20.3 | EB15: 19.9 | EC15: 13.4 | ED15: 23.9 | EE15: 0 | EF15: 24.8 | EG15: 45.8 | EH15: 0.8 | EI15: 0.1 | EJ15: 21 | EK15: 4.3 | EL15: 6.6 | EM15: 20.4 | EN15: 20.4 | EO15: 20.2 | EP15: 11.8 | EQ15: 0 | ER15: 0 | ES15: 0.6 | ET15: 25.5 | EU15: 12.6 | EV15: 0 | EW15: 0 | EX15: 9.1 | EY15: 19.8 | FA15: 44.5 | FB15: 23.5 | FC15: 29.1 | FD15: 3.4 | FE15: 15.5 | FF15: 9.6 | FG15: 6.3 | FH15: 6342.6 | FJ15: 24.449 | FK15: 8.067 | FM15: 13.2 | FO15: 9.47089 | FP15: 10.5 | FQ15: 16.1 | FR15: 81.78689
A16: 20/03/2025 | B16: 03:00 | C16: 0 | D16: 0 | E16: 590 | F16: 148.4 | I16: 90.1 | J16: 225.1 | M16: 107.4 | N16: 107.3 | O16: 108 | P16: 205 | Q16: 108.5 | R16: 66.1 | S16: 367.6 | T16: 10.3 | Y16: 160.1 | Z16: 7.3 | AA16: 2.8 | AB16: 0 | AC16: 5.9 | AD16: 10.1 | AE16: 141.7 | AF16: 8.9 | AJ16: 81.1 | AK16: 221.6 | AO16: 6.5 | AP16: 296.7 | AQ16: 40 | AR16: 127.9 | AS16: 42.3 | AT16: 18.5 | AU16: 19.7 | AV16: 87.8 | AW16: 117.5 | AX16: 118 | AY16: 151.1 | AZ16: 72 | BB16: 0 | BC16: 44.3 | BD16: 46.5 | BE16: 3.8 | BF16: 37.4 | BG16: 171.3 | BH16: 95 | BI16: 25.4 | BN16: 0 | BO16: 85.8 | BP16: 86.2 | BQ16: 0 | BR16: 86.2 | BS16: 109.1 | CB16: 1.5 | CC16: 256.7 | CD16: 133.7 | CE16: 63.4 | CF16: 79.2 | CG16: 30 | CL16: 120.9 | CM16: 58.7 | CU16: 0 | CV16: 92 | CW16: 0 | CX16: 15 | CY16: 0 | DA16: 10.4 | DB16: 5.5 | DC16: 1.2 | DD16: 1.7 | DE16: 5.2 | DF16: 19.9 | DG16: 18.2 | DH16: 19 | DI16: 3.5 | DJ16: 18.6 | DK16: 0 | DL16: 0 | DM16: 31.6 | DN16: 65 | DO16: 4.8 | DP16: 2.4 | DQ16: 2.4 | DR16: 2.5 | DS16: 0 | DT16: 3.3 | DU16: 20.3 | DV16: 3 | DW16: 0 | DX16: 19.8 | DY16: 12.9 | DZ16: 19.4 | EA16: 20.2 | EB16: 19.8 | EC16: 11 | ED16: 22.4 | EE16: 0 | EF16: 23.4 | EG16: 48.9 | EH16: 0.7 | EI16: 0 | EJ16: 21 | EK16: 4.3 | EL16: 6.6 | EM16: 20.4 | EN16: 20.4 | EO16: 20.2 | EP16: 13.8 | EQ16: 0 | ER16: 0 | ES16: 0.6 | ET16: 24.8 | EU16: 12.1 | EV16: 0 | EW16: 0 | EX16: 9 | EY16: 19.8 | FA16: 44.4 | FB16: 23.6 | FC16: 29.1 | FD16: 3.4 | FE16: 15.5 | FF16: 9.6 | FG16: 6.9 | FH16: 6255.9 | FJ16: 24.44496 | FK16: 8.058 | FM16: 13.2 | FO16: 9.47079 | FP16: 10.5 | FQ16: 16 | FR16: 81.67375
A17: 20/03/2025 | B17: 03:30 | C17: 0 | D17: 0 | E17: 599.3 | F17: 165.2 | I17: 90.7 | J17: 226.6 | M17: 112.4 | N17: 112.6 | O17: 112.9 | P17: 209.3 | Q17: 107 | R17: 67.2 | S17: 398.6 | T17: 10.5 | Y17: 161.6 | Z17: 7.8 | AA17: 2.7 | AB17: 0 | AC17: 5.7 | AD17: 10 | AE17: 143.7 | AF17: 8.9 | AJ17: 82.5 | AK17: 223.2 | AO17: 6.5 | AP17: 394.2 | AQ17: 14.7 | AR17: 148.6 | AS17: 42.3 | AT17: 18.5 | AU17: 19.7 | AV17: 91.5 | AW17: 122.8 | AX17: 122.9 | AY17: 151.5 | AZ17: 30.4 | BB17: 0 | BC17: 44.4 | BD17: 47.1 | BE17: 3.8 | BF17: 37.7 | BG17: 174.3 | BH17: 95.7 | BI17: 25.1 | BN17: 0 | BO17: 61 | BP17: 85.1 | BQ17: 0 | BR17: 85 | BS17: 108.3 | CB17: 1.5 | CC17: 262.5 | CD17: 136.3 | CE17: 65.7 | CF17: 79.6 | CG17: 30.5 | CL17: 120.8 | CM17: 56.8 | CU17: 0 | CV17: 92 | CW17: 0 | CX17: 16 | CY17: 0 | DA17: 10.3 | DB17: 5.5 | DC17: 1.2 | DD17: 1.7 | DE17: 5.2 | DF17: 20.4 | DG17: 19.5 | DH17: 19 | DI17: 3.5 | DJ17: 18.6 | DK17: 0 | DL17: 0 | DM17: 30.5 | DN17: 60.9 | DO17: 4.8 | DP17: 2.4 | DQ17: 2.4 | DR17: 2.5 | DS17: 0 | DT17: 3.3 | DU17: 20.3 | DV17: 3 | DW17: 0 | DX17: 19.8 | DY17: 12.9 | DZ17: 19.4 | EA17: 20.3 | EB17: 20 | EC17: 8.3 | ED17: 16.5 | EE17: 0 | EF17: 15.7 | EG17: 36 | EH17: 0.4 | EI17: 0 | EJ17: 21 | EK17: 4.3 | EL17: 6.6 | EM17: 20.4 | EN17: 20.4 | EO17: 20.2 | EP17: 13.1 | EQ17: 0 | ER17: 0 | ES17: 0.6 | ET17: 12.2 | EU17: 6.1 | EV17: 0 | EW17: 0 | EX17: 9 | EY17: 20 | FA17: 44 | FB17: 23.3 | FC17: 29.1 | FD17: 3.3 | FE17: 15.4 | FF17: 9.6 | FG17: 7.2 | FH17: 6341.3 | FJ17: 24.44565 | FK17: 8.057 | FM17: 13.2 | FO17: 9.47039 | FP17: 10.5 | FQ17: 16 | FR17: 81.67304
A18: 20/03/2025 | B18: 04:00 | C18: 0 | D18: 0 | E18: 595.6 | F18: 202.7 | I18: 91.1 | J18: 225.7 | M18: 106.9 | N18: 106.4 | O18: 106.7 | P18: 207.2 | Q18: 107.3 | R18: 66.2 | S18: 395.2 | T18: 10.5 | Y18: 160.8 | Z18: 7.5 | AA18: 2.7 | AB18: 0 | AC18: 5.8 | AD18: 10.1 | AE18: 143.6 | AF18: 8.9 | AJ18: 81.8 | AK18: 223.2 | AO18: 6.5 | AP18: 354.2 | AQ18: 10 | AR18: 137.6 | AS18: 42.3 | AT18: 18.5 | AU18: 19.7 | AV18: 89.6 | AW18: 121.7 | AX18: 122.2 | AY18: 152.1 | AZ18: 30 | BB18: 0 | BC18: 44.3 | BD18: 46.8 | BE18: 3.8 | BF18: 38.4 | BG18: 172.6 | BH18: 95.1 | BI18: 0 | BN18: 0 | BO18: 60.9 | BP18: 85.6 | BQ18: 0 | BR18: 85.5 | BS18: 109.2 | CB18: 1.5 | CC18: 241.4 | CD18: 131.8 | CE18: 63.4 | CF18: 77.5 | CG18: 29.9 | CL18: 120.3 | CM18: 58.1 | CU18: 0 | CV18: 90.8 | CW18: 0 | CX18: 14 | CY18: 0 | DA18: 10.5 | DB18: 5.6 | DC18: 1.2 | DD18: 1.7 | DE18: 5.2 | DF18: 20 | DG18: 17.3 | DH18: 19 | DI18: 3.5 | DJ18: 18.6 | DK18: 0 | DL18: 0 | DM18: 29.4 | DN18: 64.4 | DO18: 4.8 | DP18: 2.4 | DQ18: 2.4 | DR18: 2.5 | DS18: 0 | DT18: 3.3 | DU18: 20.3 | DV18: 3 | DW18: 0 | DX18: 19.8 | DY18: 13 | DZ18: 19.3 | EA18: 20.3 | EB18: 20 | EC18: 6.9 | ED18: 21.7 | EE18: 0 | EF18: 18.6 | EG18: 37.3 | EH18: 0.2 | EI18: 0 | EJ18: 21 | EK18: 4.3 | EL18: 6.6 | EM18: 20.4 | EN18: 20.4 | EO18: 20.2 | EP18: 9.7 | EQ18: 0 | ER18: 0 | ES18: 0.6 | ET18: 9.4 | EU18: 5 | EV18: 0 | EW18: 0 | EX18: 9 | EY18: 20 | FA18: 44.1 | FB18: 23.3 | FC18: 29.1 | FD18: 3.3 | FE18: 15.5 | FF18: 9.6 | FG18: 6.4 | FH18: 6231.3 | FJ18: 24.44899 | FK18: 8.059 | FM18: 13.2 | FO18: 9.47016 | FP18: 10.6 | FQ18: 16.1 | FR18: 81.87815
A19: 20/03/2025 | B19: 04:30 | C19: 0 | D19: 0 | E19: 599.6 | F19: 195.3 | I19: 91.1 | J19: 227.2 | M19: 110 | N19: 109.3 | O19: 109.6 | P19: 207.3 | Q19: 108.6 | R19: 66.7 | S19: 404.2 | T19: 10.5 | Y19: 163.9 | Z19: 7.8 | AA19: 2.8 | AB19: 0 | AC19: 5.8 | AD19: 10.1 | AE19: 144.2 | AF19: 8.9 | AJ19: 82.1 | AK19: 223.2 | AO19: 6.5 | AP19: 412.4 | AQ19: 10 | AR19: 147.8 | AS19: 42.3 | AT19: 18.5 | AU19: 19.7 | AV19: 90.2 | AW19: 123.1 | AX19: 124 | AY19: 152.8 | AZ19: 30.3 | BB19: 0 | BC19: 44.7 | BD19: 46.7 | BE19: 3.8 | BF19: 37.8 | BG19: 174.3 | BH19: 95.6 | BI19: 0 | BN19: 0 | BO19: 61.2 | BP19: 85.8 | BQ19: 0 | BR19: 85.6 | BS19: 108.7 | CB19: 1.5 | CC19: 268.4 | CD19: 132 | CE19: 63.6 | CF19: 77.7 | CG19: 30.2 | CL19: 121.1 | CM19: 57.6 | CU19: 0 | CV19: 90.8 | CW19: 0 | CX19: 16.5 | CY19: 0 | DA19: 10.4 | DB19: 5.5 | DC19: 1.2 | DD19: 1.8 | DE19: 5.1 | DF19: 20.2 | DG19: 18 | DH19: 19 | DI19: 3.5 | DJ19: 18.6 | DK19: 0 | DL19: 0 | DM19: 30 | DN19: 71.4 | DO19: 4.8 | DP19: 2.4 | DQ19: 2.4 | DR19: 2.5 | DS19: 0 | DT19: 3.3 | DU19: 20.3 | DV19: 3 | DW19: 0 | DX19: 19.8 | DY19: 13 | DZ19: 19.3 | EA19: 20.3 | EB19: 20 | EC19: 6.2 | ED19: 22.1 | EE19: 0 | EF19: 13.8 | EG19: 32.2 | EH19: 0 | EI19: 0 | EJ19: 21 | EK19: 4.3 | EL19: 7.7 | EM19: 20.4 | EN19: 20.4 | EO19: 20.2 | EP19: 11.7 | EQ19: 0 | ER19: 0 | ES19: 0.6 | ET19: 5.4 | EU19: 4.5 | EV19: 0 | EW19: 0 | EX19: 9 | EY19: 20 | FA19: 44 | FB19: 23.5 | FC19: 29.2 | FD19: 3.3 | FE19: 15.5 | FF19: 9.6 | FG19: 6.7 | FH19: 6356.5 | FJ19: 24.44834 | FK19: 8.056 | FM19: 13.2 | FO19: 9.46997 | FP19: 10.5 | FQ19: 16.1 | FR19: 81.77431
A20: 20/03/2025 | B20: 05:00 | C20: 0 | D20: 0 | E20: 602.2 | F20: 148.5 | I20: 91.2 | J20: 228.2 | M20: 106.6 | N20: 107.1 | O20: 106.7 | P20: 203.4 | Q20: 107.8 | R20: 66.1 | S20: 414.5 | T20: 10.5 | Y20: 168.1 | Z20: 7.3 | AA20: 4.1 | AB20: 0 | AC20: 5.8 | AD20: 10.1 | AE20: 144 | AF20: 8.9 | AJ20: 111.2 | AK20: 222.3 | AO20: 6.5 | AP20: 376.8 | AQ20: 22 | AR20: 141.5 | AS20: 42.2 | AT20: 18.5 | AU20: 19.7 | AV20: 92.3 | AW20: 123.5 | AX20: 123.4 | AY20: 151.8 | AZ20: 61.5 | BB20: 0 | BC20: 45.5 | BD20: 47.4 | BE20: 3.8 | BF20: 38.3 | BG20: 174.9 | BH20: 96.2 | BI20: 0 | BN20: 0 | BO20: 87.4 | BP20: 85.5 | BQ20: 0 | BR20: 85.2 | BS20: 108 | CB20: 1.5 | CC20: 250.4 | CD20: 133.6 | CE20: 64.2 | CF20: 77.7 | CG20: 30.5 | CL20: 120.7 | CM20: 57.4 | CU20: 0 | CV20: 93.6 | CW20: 0 | CX20: 13.1 | CY20: 0 | DA20: 10.4 | DB20: 5.5 | DC20: 1.3 | DD20: 1.8 | DE20: 5.1 | DF20: 20.6 | DG20: 18.6 | DH20: 19 | DI20: 3.5 | DJ20: 18.6 | DK20: 0 | DL20: 0 | DM20: 30.7 | DN20: 76 | DO20: 4.8 | DP20: 2.4 | DQ20: 2.4 | DR20: 2.5 | DS20: 0 | DT20: 3.3 | DU20: 20.3 | DV20: 3 | DW20: 0 | DX20: 19.8 | DY20: 13 | DZ20: 19.5 | EA20: 20.3 | EB20: 20 | EC20: 9.3 | ED20: 18.4 | EE20: 0 | EF20: 19.4 | EG20: 42.3 | EH20: 0.3 | EI20: 0 | EJ20: 21 | EK20: 4.3 | EL20: 8 | EM20: 20.4 | EN20: 20.4 | EO20: 20.2 | EP20: 8.5 | EQ20: 0 | ER20: 0 | ES20: 0.6 | ET20: 6.3 | EU20: 4.6 | EV20: 0 | EW20: 0 | EX20: 9 | EY20: 20 | FA20: 43.7 | FB20: 23.3 | FC20: 29.1 | FD20: 3.2 | FE20: 15.6 | FF20: 9.6 | FG20: 6.8 | FH20: 6375.9 | FJ20: 24.4495 | FK20: 8.055 | FM20: 13.2 | FO20: 9.46997 | FP20: 10.3 | FQ20: 16 | FR20: 81.47447
A21: 20/03/2025 | B21: 05:30 | C21: 0.2 | D21: 0.3 | E21: 588.7 | F21: 148.5 | I21: 88.4 | J21: 223.9 | M21: 130.2 | N21: 130.7 | O21: 130.8 | P21: 240.2 | Q21: 107.8 | R21: 66.2 | S21: 389.5 | T21: 10.3 | Y21: 159.7 | Z21: 6.6 | AA21: 3.2 | AB21: 0 | AC21: 5.2 | AD21: 10 | AE21: 142.3 | AF21: 8.6 | AJ21: 109 | AK21: 222.1 | AO21: 6.5 | AP21: 350 | AQ21: 42.9 | AR21: 137.7 | AS21: 42.1 | AT21: 18.5 | AU21: 19.7 | AV21: 87.9 | AW21: 118.4 | AX21: 118.9 | AY21: 150.9 | AZ21: 103.5 | BB21: 0 | BC21: 44 | BD21: 46 | BE21: 3.8 | BF21: 37.1 | BG21: 169.8 | BH21: 94.4 | BI21: 0 | BN21: 0 | BO21: 86.1 | BP21: 85.5 | BQ21: 0 | BR21: 85.3 | BS21: 108.3 | CB21: 1.5 | CC21: 239.9 | CD21: 122.9 | CE21: 62.1 | CF21: 76.9 | CG21: 29.5 | CL21: 120.3 | CM21: 57.2 | CU21: 0 | CV21: 115.7 | CW21: 0 | CX21: 15.7 | CY21: 0 | DA21: 10.4 | DB21: 5.5 | DC21: 1.2 | DD21: 1.7 | DE21: 5.1 | DF21: 19.8 | DG21: 17.6 | DH21: 19 | DI21: 3.5 | DJ21: 18.6 | DK21: 0 | DL21: 0 | DM21: 30 | DN21: 75.5 | DO21: 4.8 | DP21: 2.4 | DQ21: 2.4 | DR21: 2.5 | DS21: 0 | DT21: 3.3 | DU21: 20.3 | DV21: 3 | DW21: 0 | DX21: 19.8 | DY21: 12.9 | DZ21: 19.8 | EA21: 20.2 | EB21: 20 | EC21: 9 | ED21: 15.1 | EE21: 0 | EF21: 17.1 | EG21: 36.8 | EH21: 0.1 | EI21: 0 | EJ21: 21 | EK21: 4.3 | EL21: 8.2 | EM21: 20.4 | EN21: 20.4 | EO21: 20.2 | EP21: 10.9 | EQ21: 0 | ER21: 0 | ES21: 0.6 | ET21: 18.3 | EU21: 17.9 | EV21: 0 | EW21: 0 | EX21: 8.9 | EY21: 20 | FA21: 43.8 | FB21: 23.4 | FC21: 29.2 | FD21: 3.3 | FE21: 15.5 | FF21: 9.6 | FG21: 6.7 | FH21: 6441.4 | FJ21: 24.44664 | FK21: 8.053 | FM21: 13.2 | FO21: 9.46952 | FP21: 10.4 | FQ21: 16 | FR21: 81.56916
A22: 20/03/2025 | B22: 06:00 | C22: 0.3 | D22: 1.1 | E22: 599.8 | F22: 148.3 | I22: 90.2 | J22: 227.9 | M22: 120.3 | N22: 120.6 | O22: 120.6 | P22: 217.5 | Q22: 107.5 | R22: 66.1 | S22: 435.4 | T22: 10.7 | Y22: 166.9 | Z22: 8.1 | AA22: 3.2 | AB22: 0 | AC22: 4.6 | AD22: 10 | AE22: 144.2 | AF22: 8.6 | AJ22: 111.2 | AK22: 223.1 | AO22: 6.5 | AP22: 423.9 | AQ22: 69.2 | AR22: 143.8 | AS22: 42.2 | AT22: 18.3 | AU22: 19.7 | AV22: 92.6 | AW22: 124.3 | AX22: 124.9 | AY22: 152 | AZ22: 106.5 | BB22: 0 | BC22: 45.5 | BD22: 47.1 | BE22: 3.8 | BF22: 38.3 | BG22: 175.1 | BH22: 95.9 | BI22: 0 | BN22: 0 | BO22: 87.8 | BP22: 85.2 | BQ22: 0 | BR22: 85.3 | BS22: 108.3 | CB22: 1.5 | CC22: 254.1 | CD22: 127.7 | CE22: 64.3 | CF22: 77.7 | CG22: 30.5 | CL22: 120.5 | CM22: 56.9 | CU22: 0 | CV22: 118.5 | CW22: 0 | CX22: 16.4 | CY22: 0 | DA22: 10.4 | DB22: 5.4 | DC22: 1.3 | DD22: 1.8 | DE22: 5.1 | DF22: 20.3 | DG22: 18.8 | DH22: 19 | DI22: 3.5 | DJ22: 18.6 | DK22: 1.8 | DL22: 1.9 | DM22: 31.5 | DN22: 74.1 | DO22: 4.8 | DP22: 2.4 | DQ22: 2.4 | DR22: 2.5 | DS22: 0 | DT22: 3.3 | DU22: 20.3 | DV22: 3 | DW22: 0 | DX22: 19.8 | DY22: 12.8 | DZ22: 20.1 | EA22: 20.3 | EB22: 19.8 | EC22: 10.2 | ED22: 17.5 | EE22: 0.2 | EF22: 24.1 | EG22: 50.6 | EH22: 0.4 | EI22: 0.5 | EJ22: 21 | EK22: 4.3 | EL22: 7.8 | EM22: 20.4 | EN22: 20.4 | EO22: 20.2 | EP22: 13.7 | EQ22: 0 | ER22: 1.4 | ES22: 0.6 | ET22: 34.8 | EU22: 28.3 | EV22: 1.3 | EW22: 0 | EX22: 9 | EY22: 19.8 | FA22: 44.2 | FB22: 23.3 | FC22: 29.2 | FD22: 3.2 | FE22: 15.6 | FF22: 9.6 | FG22: 7.1 | FH22: 6694.2 | FJ22: 24.45245 | FK22: 8.054 | FM22: 13.2 | FO22: 9.46928 | FP22: 10.4 | FQ22: 16 | FR22: 81.57573
... A58: 21/03/2025 | B58: 00:00 | C58: 0.3 | D58: 0.5 | E58: 642.5 | F58: 148.1 | I58: 89.8 | J58: 226.2 | M58: 104.9 | N58: 105.2 | O58: 105.1 | P58: 214.3 | Q58: 108.2 | R58: 68.4 | S58: 550.1 | T58: 10.4 | Y58: 166 | Z58: 7.6 | AA58: 2.7 | AB58: 0 | AC58: 6.7 | AD58: 10 | AE58: 142.7 | AF58: 8.8 | AJ58: 110.1 | AK58: 221.9 | AO58: 6.5 | AP58: 456.2 | AQ58: 81.9 | AR58: 121.5 | AS58: 39.9 | AT58: 18.5 | AU58: 19.7 | AV58: 91.2 | AW58: 0 | AX58: 121.1 | AY58: 72.7 | AZ58: 104.4 | BB58: 8.3 | BC58: 44.1 | BD58: 46.5 | BE58: 0 | BF58: 37.5 | BG58: 171.5 | BH58: 94.5 | BI58: 0 | BN58: 0 | BO58: 86.9 | BP58: 147.2 | BQ58: 0 | BR58: 147.1 | BS58: 155 | CB58: 0 | CC58: 198.8 | CD58: 108.8 | CE58: 63.4 | CF58: 77.8 | CG58: 29.8 | CL58: 142.2 | CM58: 65.7 | CU58: 0 | CV58: 90.3 | CW58: 0 | CX58: 13.8 | CY58: 0 | DA58: 10.4 | DB58: 5.5 | DC58: 1.3 | DD58: 1.8 | DE58: 5 | DF58: 20 | DG58: 20 | DH58: 19.1 | DI58: 3.5 | DJ58: 18.6 | DK58: 0 | DL58: 0 | DM58: 18.2 | DN58: 50.3 | DO58: 4.8 | DP58: 2.4 | DQ58: 2.4 | DR58: 2.6 | DS58: 0 | DT58: 3.5 | DU58: 20.3 | DV58: 2 | DW58: 0.3 | DX58: 19.8 | DY58: 13 | DZ58: 20.3 | EA58: 20.3 | EB58: 20 | EC58: 0.6 | ED58: 25.9 | EE58: 0 | EF58: 41.5 | EG58: 72.6 | EH58: 2.1 | EI58: 2.1 | EJ58: 21 | EK58: 8.4 | EL58: 6.6 | EM58: 20.4 | EN58: 20.4 | EO58: 20.2 | EP58: 9.6 | EQ58: 0 | ER58: 0 | ES58: 0.6 | ET58: 42.7 | EU58: 32.2 | EV58: 0 | EW58: 0 | EX58: 8.9 | EY58: 20 | FA58: 44.7 | FB58: 24.9 | FC58: 29 | FD58: 3.1 | FE58: 16 | FF58: 9.3 | FG58: 7 | FH58: 6708.5 | FJ58: 24.4133 | FK58: 8.051 | FM58: 0 | FO58: 9.47466 | FP58: 10.2 | FQ58: 16 | FR58: 68.13896
A59: EJEC | C59: 4.05 | D59: 14.3 | E59: 15035 | F59: 4432.15 | G59: 0 | H59: 0 | I59: 2149.35 | J59: 5443.9 | K59: 0 | L59: 0 | M59: 3024.95 | N59: 3025.1 | O59: 3027.3 | P59: 5302.8 | Q59: 3176.75 | R59: 1858.55 | S59: 12231.45 | T59: 250.55 | U59: 0 | V59: 0 | W59: 0 | X59: 0 | Y59: 3937.45 | Z59: 177.45 | AA59: 72.85 | AB59: 21.1 | AC59: 154.4 | AD59: 241.4 | AE59: 3444.35 | AF59: 211.85 | AG59: 0 | AH59: 0 | AI59: 0 | AJ59: 2568.55 | AK59: 5344 | AL59: 0 | AM59: 0 | AN59: 0 | AO59: 155.9 | AP59: 10351.65 | AQ59: 1323.8 | AR59: 3303.4 | AS59: 632.2 | AT59: 442.7 | AU59: 472.75 | AV59: 2164.25 | AW59: 3182.2 | AX59: 3368.65 | AY59: 3779.85 | AZ59: 2272.15 | BA59: 0 | BB59: 49.8 | BC59: 1067.6 | BD59: 1118.8 | BE59: 60.8 | BF59: 890.3 | BG59: 4159.6 | BH59: 2177.75 | BI59: 87.7 | BJ59: 0 | BK59: 0 | BL59: 0 | BM59: 0 | BN59: 211.805 | BO59: 2046.8 | BP59: 3035.7 | BQ59: 278.5 | BR59: 3334.75 | BS59: 3424.5 | BT59: 0 | BU59: 0 | BV59: 0 | BW59: 0 | BX59: 0 | BY59: 0 | BZ59: 0 | CA59: 0 | CB59: 27.9 | CC59: 5811.2 | CD59: 3048.95 | CE59: 1535.1 | CF59: 1890.05 | CG59: 721.55 | CH59: 0 | CI59: 0 | CJ59: 0 | CK59: 0 | CL59: 3210.3 | CM59: 1500.65 | CN59: 0 | CO59: 0 | CP59: 0 | CQ59: 0 | CR59: 0 | CS59: 0 | CT59: 0 | CU59: 6.5 | CV59: 2515.75 | CW59: 706.85 | CX59: 365.15 | CY59: 2.55 | CZ59: 0 | DA59: 248.85 | DB59: 131.15 | DC59: 28.4 | DD59: 32.7 | DE59: 123.2 | DF59: 484.85 | DG59: 462.45 | DH59: 456.15 | DI59: 84.35 | DJ59: 446.35 | DK59: 149.75 | DL59: 179.7 | DM59: 658.15 | DN59: 1816.05 | DO59: 115.15 | DP59: 57.6 | DQ59: 57.6 | DR59: 58.55 | DS59: 156.3 | DT59: 78.55 | DU59: 487.95 | DV59: 57.65 | DW59: 5.2 | DX59: 475.3 | DY59: 308.6 | DZ59: 482.7 | EA59: 486.7 | EB59: 478.5 | EC59: 81.25 | ED59: 947.85 | EE59: 320.4 | EF59: 1215.4 | EG59: 1579.6 | EH59: 76.25 | EI59: 94.85 | EJ59: 504 | EK59: 148.35 | EL59: 176.75 | EM59: 489.6 | EN59: 489.6 | EO59: 484.8 | EP59: 282 | EQ59: 127.8 | ER59: 1270.55 | ES59: 14.4 | ET59: 1733.45 | EU59: 1588.45 | EV59: 961.9 | EW59: 132.7 | EX59: 215.1 | EY59: 479 | EZ59: 0 | FA59: 1070.5 | FB59: 575.15 | FC59: 688.8 | FD59: 78.6 | FE59: 378.35 | FF59: 228.2 | FG59: 162.35 | FH59: 175090.45 | FJ59: 583.40444 | FK59: 193.2525 | FL59: 0 | FM59: 264 | FN59: 0 | FO59: 219.2935 | FP59: 241.9 | FQ59: 385.5 | FR59: 1887.3504

Sheet REACTIVA
B3: jueves, 20 de Marzo del 2025
A5: POTENCIA REACTIVA EJECUTADA DE LAS UNIDADES DE GENERACIÓN DEL COES (MVAR) | FI5: CENTRALES NO INTEGRANTES COES
A6: FECHA | B6: HORA | C6: 337 | D6: 338 | E6: 101 | F6: 102 | G6: 42667 | H6: 42668 | I6: 126 | J6: 127 | K6: 138 | L6: 139 | M6: 197 | N6: 203 | O6: 204 | P6: 230 | Q6: 209 | R6: 56677 | S6: 796 | T6: 2146 | U6: 142 | V6: 143 | W6: 125 | X6: 187 | Y6: 163 | Z6: 298 | AA6: 219 | AB6: 151 | AC6: 152 | AD6: 153 | AE6: 154 | AF6: 756 | AG6: 156 | AH6: 155 | AI6: 182 | AJ6: 212 | AK6: 758 | AL6: 263 | AM6: 265 | AN6: 775 | AO6: 777 | AP6: 2154 | AQ6: 150 | AR6: 149 | AS6: 188 | AT6: 2131 | AU6: 755 | AV6: 252 | AW6: 249 | AX6: 250 | AY6: 117 | AZ6: 267 | BA6: 268 | BB6: 119 | BC6: 120 | BD6: 189 | BE6: 122 | BF6: 266 | BG6: 251 | BH6: 115 | BI6: 239 | BJ6: 288 | BK6: 240 | BL6: 241 | BM6: 242 | BN6: 191 | BO6: 194 | BP6: 196 | BQ6: 207 | BR6: 236 | BS6: 795 | BT6: 285 | BU6: 995 | BV6: 996 | BW6: 997 | BX6: 766 | BY6: 926 | BZ6: 924 | CA6: 121 | CB6: 103 | CC6: 104 | CD6: 106 | CE6: 105 | CF6: 107 | CG6: 110 | CH6: 109 | CI6: 144 | CJ6: 113 | CK6: 114 | CL6: 193 | CM6: 208 | CN6: 786 | CO6: 787 | CP6: 788 | CQ6: 789 | CR6: 248 | CS6: 2159 | CT6: 303 | CU6: 59715 | CV6: 62255 | CW6: 1263 | CX6: 61800 | CY6: 2194 | CZ6: 216 | DA6: 198 | DB6: 49607 | DC6: 214 | DD6: 260 | DE6: 2152 | DF6: 2128 | DG6: 247 | DH6: 228 | DI6: 2135 | DJ6: 261 | DK6: 237 | DL6: 253 | DM6: 770 | DN6: 225 | DO6: 2201 | DP6: 2171 | DQ6: 760 | DR6: 235 | DS6: 238 | DT6: 2184 | DU6: 61855 | DV6: 223 | DW6: 226 | DX6: 201 | DY6: 258 | DZ6: 259 | EA6: 920 | EB6: 257 | EC6: 256 | ED6: 2148 | EE6: 58288 | EF6: 58289 | EG6: 58839 | EH6: 58840 | EI6: 296 | EJ6: 297 | EK6: 211 | EL6: 2175 | EM6: 2178 | EN6: 2181 | EO6: 1262 | EP6: 233 | EQ6: 2150 | ER6: 2165 | ES6: 2161 | ET6: 61197 | EU6: 58851 | EV6: 234 | EW6: 215 | EX6: 917 | EY6: 289 | EZ6: 58333 | FA6: 58336 | FB6: 202 | FC6: 58487 | FD6: 213 | FE6: 232 | FF6: 2190 | FG6: TOTAL COES | FI6: 221 | FJ6: 222 | FK6: 224 | FL6: 2187 | FM6: 227 | FN6: 49400 | FO6: 199 | FP6: 200 | FQ6: TOTAL NO COES
C7: CENTRO | D7: CENTRO | E7: CENTRO | F7: CENTRO | G7: NORTE | H7: NORTE | I7: NORTE | J7: NORTE | K7: CENTRO | L7: CENTRO | M7: CENTRO | N7: CENTRO | O7: CENTRO | P7: CENTRO | Q7: CENTRO | R7: CENTRO | S7: CENTRO | T7: CENTRO | U7: CENTRO | V7: CENTRO | W7: CENTRO | X7: CENTRO | Y7: SUR | Z7: SUR | AA7: CENTRO | AB7: SUR | AC7: SUR | AD7: SUR | AE7: SUR | AF7: SUR | AG7: SUR | AH7: SUR | AI7: SUR | AJ7: CENTRO | AK7: NORTE | AL7: NORTE | AM7: NORTE | AN7: CENTRO | AO7: CENTRO | AP7: CENTRO | AQ7: CENTRO | AR7: CENTRO | AS7: CENTRO | AT7: CENTRO | AU7: SUR | AV7: CENTRO | AW7: CENTRO | AX7: CENTRO | AY7: CENTRO | AZ7: CENTRO | BA7: CENTRO | BB7: CENTRO | BC7: CENTRO | BD7: SUR | BE7: NORTE | BF7: CENTRO | BG7: CENTRO | BH7: NORTE | BI7: NORTE | BJ7: NORTE | BK7: SUR | BL7: SUR | BM7: SUR | BN7: CENTRO | BO7: CENTRO | BP7: CENTRO | BQ7: CENTRO | BR7: CENTRO | BS7: CENTRO | BT7: CENTRO | BU7: SUR | BV7: SUR | BW7: SUR | BX7: NORTE | BY7: SUR | BZ7: CENTRO | CA7: NORTE | CB7: CENTRO | CC7: CENTRO | CD7: CENTRO | CE7: CENTRO | CF7: CENTRO | CG7: CENTRO | CH7: CENTRO | CI7: CENTRO | CJ7: CENTRO | CK7: CENTRO | CL7: CENTRO | CM7: CENTRO | CN7: SUR | CO7: SUR | CP7: SUR | CQ7: SUR | CR7: CENTRO | CS7: CENTRO | CT7: CENTRO | CU7: CENTRO | CV7: SUR | CW7: NORTE | CX7: NORTE | CY7: NORTE | CZ7: NORTE | DA7: NORTE | DB7: SUR | DC7: CENTRO | DD7: CENTRO | DE7: CENTRO | DF7: NORTE | DG7: NORTE | DH7: CENTRO | DI7: CENTRO | DJ7: SUR | DK7: SUR | DL7: CENTRO | DM7: CENTRO | DN7: CENTRO | DO7: CENTRO | DP7: CENTRO | DQ7: CENTRO | DR7: SUR | DS7: CENTRO | DT7: CENTRO | DU7: NORTE | DV7: CENTRO | DW7: CENTRO | DX7: NORTE | DY7: CENTRO | DZ7: CENTRO | EA7: CENTRO | EB7: NORTE | EC7: NORTE | ED7: SUR | EE7: CENTRO | EF7: CENTRO | EG7: CENTRO | EH7: CENTRO | EI7: CENTRO | EJ7: CENTRO | EK7: SUR | EL7: SUR | EM7: SUR | EN7: SUR | EO7: NORTE | EP7: SUR | EQ7: SUR | ER7: CENTRO | ES7: CENTRO | ET7: CENTRO | EU7: SUR | EV7: SUR | EW7: NORTE | EX7: CENTRO | EY7: NORTE | EZ7: NORTE | FA7: NORTE | FB7: CENTRO | FC7: CENTRO | FD7: CENTRO | FE7: NORTE | FF7: NORTE | FI7: NORTE | FJ7: CENTRO | FK7: NORTE | FL7: NORTE | FM7: NORTE | FN7: NORTE | FO7: NORTE | FP7: NORTE
C8: HIDROELÉCTRICA | D8: HIDROELÉCTRICA | E8: HIDROELÉCTRICA | F8: HIDROELÉCTRICA | G8: TERMOELÉCTRICA | H8: TERMOELÉCTRICA | I8: HIDROELÉCTRICA | J8: HIDROELÉCTRICA | K8: TERMOELÉCTRICA | L8: TERMOELÉCTRICA | M8: TERMOELÉCTRICA | N8: TERMOELÉCTRICA | O8: TERMOELÉCTRICA | P8: TERMOELÉCTRICA | Q8: TERMOELÉCTRICA | R8: TERMOELÉCTRICA | S8: HIDROELÉCTRICA | T8: HIDROELÉCTRICA | U8: TERMOELÉCTRICA | V8: TERMOELÉCTRICA | W8: TERMOELÉCTRICA | X8: TERMOELÉCTRICA | Y8: HIDROELÉCTRICA | Z8: HIDROELÉCTRICA | AA8: TERMOELÉCTRICA | AB8: HIDROELÉCTRICA | AC8: HIDROELÉCTRICA | AD8: HIDROELÉCTRICA | AE8: HIDROELÉCTRICA | AF8: TERMOELÉCTRICA | AG8: TERMOELÉCTRICA | AH8: TERMOELÉCTRICA | AI8: HIDROELÉCTRICA | AJ8: HIDROELÉCTRICA | AK8: TERMOELÉCTRICA | AL8: TERMOELÉCTRICA | AM8: TERMOELÉCTRICA | AN8: HIDROELÉCTRICA | AO8: HIDROELÉCTRICA | AP8: HIDROELÉCTRICA | AQ8: HIDROELÉCTRICA | AR8: HIDROELÉCTRICA | AS8: HIDROELÉCTRICA | AT8: HIDROELÉCTRICA | AU8: HIDROELÉCTRICA | AV8: TERMOELÉCTRICA | AW8: TERMOELÉCTRICA | AX8: TERMOELÉCTRICA | AY8: HIDROELÉCTRICA | AZ8: HIDROELÉCTRICA | BA8: HIDROELÉCTRICA | BB8: HIDROELÉCTRICA | BC8: HIDROELÉCTRICA | BD8: HIDROELÉCTRICA | BE8: HIDROELÉCTRICA | BF8: HIDROELÉCTRICA | BG8: HIDROELÉCTRICA | BH8: TERMOELÉCTRICA | BI8: TERMOELÉCTRICA | BJ8: TERMOELÉCTRICA | BK8: TERMOELÉCTRICA | BL8: TERMOELÉCTRICA | BM8: TERMOELÉCTRICA | BN8: HIDROELÉCTRICA | BO8: TERMOELÉCTRICA | BP8: TERMOELÉCTRICA | BQ8: TERMOELÉCTRICA | BR8: TERMOELÉCTRICA | BS8: TERMOELÉCTRICA | BT8: TERMOELÉCTRICA | BU8: TERMOELÉCTRICA | BV8: TERMOELÉCTRICA | BW8: TERMOELÉCTRICA | BX8: HIDROELÉCTRICA | BY8: TERMOELÉCTRICA | BZ8: TERMOELÉCTRICA | CA8: HIDROELÉCTRICA | CB8: HIDROELÉCTRICA | CC8: HIDROELÉCTRICA | CD8: HIDROELÉCTRICA | CE8: HIDROELÉCTRICA | CF8: HIDROELÉCTRICA | CG8: TERMOELÉCTRICA | CH8: TERMOELÉCTRICA | CI8: TERMOELÉCTRICA | CJ8: TERMOELÉCTRICA | CK8: TERMOELÉCTRICA | CL8: TERMOELÉCTRICA | CM8: TERMOELÉCTRICA | CN8: TERMOELÉCTRICA | CO8: TERMOELÉCTRICA | CP8: TERMOELÉCTRICA | CQ8: TERMOELÉCTRICA | CR8: TERMOELÉCTRICA | CS8: TERMOELÉCTRICA | CT8: SOLAR | CU8: EÓLICA | CV8: SOLAR | CW8: EÓLICA | CX8: SOLAR | CY8: HIDROELÉCTRICA | CZ8: HIDROELÉCTRICA | DA8: HIDROELÉCTRICA | DB8: HIDROELÉCTRICA | DC8: HIDROELÉCTRICA | DD8: HIDROELÉCTRICA | DE8: HIDROELÉCTRICA | DF8: HIDROELÉCTRICA | DG8: HIDROELÉCTRICA | DH8: HIDROELÉCTRICA | DI8: HIDROELÉCTRICA | DJ8: SOLAR | DK8: SOLAR | DL8: EÓLICA | DM8: EÓLICA | DN8: TERMOELÉCTRICA | DO8: TERMOELÉCTRICA | DP8: TERMOELÉCTRICA | DQ8: TERMOELÉCTRICA | DR8: SOLAR | DS8: HIDROELÉCTRICA | DT8: HIDROELÉCTRICA | DU8: HIDROELÉCTRICA | DV8: HIDROELÉCTRICA | DW8: HIDROELÉCTRICA | DX8: HIDROELÉCTRICA | DY8: HIDROELÉCTRICA | DZ8: HIDROELÉCTRICA | EA8: HIDROELÉCTRICA | EB8: EÓLICA | EC8: EÓLICA | ED8: SOLAR | EE8: EÓLICA | EF8: EÓLICA | EG8: EÓLICA | EH8: EÓLICA | EI8: HIDROELÉCTRICA | EJ8: HIDROELÉCTRICA | EK8: HIDROELÉCTRICA | EL8: HIDROELÉCTRICA | EM8: HIDROELÉCTRICA | EN8: HIDROELÉCTRICA | EO8: EÓLICA | EP8: SOLAR | EQ8: SOLAR | ER8: HIDROELÉCTRICA | ES8: EÓLICA | ET8: EÓLICA | EU8: SOLAR | EV8: SOLAR | EW8: HIDROELÉCTRICA | EX8: HIDROELÉCTRICA | EY8: TERMOELÉCTRICA | EZ8: TERMOELÉCTRICA | FA8: TERMOELÉCTRICA | FB8: TERMOELÉCTRICA | FC8: TERMOELÉCTRICA | FD8: TERMOELÉCTRICA | FE8: TERMOELÉCTRICA | FF8: TERMOELÉCTRICA | FI8: HIDROELÉCTRICA | FJ8: HIDROELÉCTRICA | FK8: HIDROELÉCTRICA | FL8: HIDROELÉCTRICA | FM8: TERMOELÉCTRICA | FN8: TERMOELÉCTRICA | FO8: HIDROELÉCTRICA | FP8: HIDROELÉCTRICA
C9: CENTRALES SANTA ROSA S.A.C. | D9: CENTRALES SANTA ROSA S.A.C. | E9: ELECTROPERU | F9: ELECTROPERU | G9: ELECTROPERU | H9: ELECTROPERU | I9: ORAZUL ENERGY PERÚ | J9: ORAZUL ENERGY PERÚ | K9: TERMOSELVA | L9: TERMOSELVA | M9: KALLPA GENERACION S.A. | N9: KALLPA GENERACION S.A. | O9: KALLPA GENERACION S.A. | P9: KALLPA GENERACION S.A. | Q9: KALLPA GENERACION S.A. | R9: KALLPA GENERACION S.A. | S9: KALLPA GENERACION S.A. | T9: KALLPA GENERACION S.A. | U9: SHOUGESA | V9: SHOUGESA | W9: SHOUGESA | X9: SHOUGESA | Y9: EGEMSA | Z9: EGESUR | AA9: EGESUR | AB9: EGASA | AC9: EGASA | AD9: EGASA | AE9: EGASA | AF9: EGASA | AG9: EGASA | AH9: EGASA | AI9: SAN GABAN | AJ9: CELEPSA | AK9: MINERA CERRO VERDE | AL9: PLANTA DE RESERVA FRIA DE GENERACION DE ETEN S.A. | AM9: PLANTA DE RESERVA FRIA DE GENERACION DE ETEN S.A. | AN9: EMPRESA DE GENERACION HUALLAGA | AO9: EMPRESA DE GENERACION HUALLAGA | AP9: LA VIRGEN | AQ9: CHINANGO S.A.C. | AR9: CHINANGO S.A.C. | AS9: HIDROELECTRICA HUANCHOR S.A.C. | AT9: CELEPSA RENOVABLES S.R.L. | AU9: INLAND ENERGY SAC | AV9: FENIX POWER PERÚ | AW9: FENIX POWER PERÚ | AX9: FENIX POWER PERÚ | AY9: STATKRAFT S.A | AZ9: STATKRAFT S.A | BA9: STATKRAFT S.A | BB9: STATKRAFT S.A | BC9: STATKRAFT S.A | BD9: STATKRAFT S.A | BE9: STATKRAFT S.A | BF9: STATKRAFT S.A | BG9: EMPRESA DE GENERACION HUANZA | BH9: ENEL GENERACION PIURA S.A. | BI9: ENEL GENERACION PIURA S.A. | BJ9: ENEL GENERACION PIURA S.A. | BK9: ENGIE | BL9: ENGIE | BM9: ENGIE | BN9: ENGIE | BO9: ENGIE | BP9: ENGIE | BQ9: ENGIE | BR9: ENGIE | BS9: ENGIE | BT9: ENGIE | BU9: ENGIE | BV9: ENGIE | BW9: ENGIE | BX9: ENGIE | BY9: INFRAESTRUCTURAS Y ENERGIAS DEL PERU S.A.C. | BZ9: INFRAESTRUCTURAS Y ENERGIAS DEL PERU S.A.C. | CA9: INVERSIONES SHAQSHA S.A.C. | CB9: ORYGEN PERU S.A.A. | CC9: ORYGEN PERU S.A.A. | CD9: ORYGEN PERU S.A.A. | CE9: ORYGEN PERU S.A.A. | CF9: ORYGEN PERU S.A.A. | CG9: ORYGEN PERU S.A.A. | CH9: ORYGEN PERU S.A.A. | CI9: ORYGEN PERU S.A.A. | CJ9: ORYGEN PERU S.A.A. | CK9: ORYGEN PERU S.A.A. | CL9: ORYGEN PERU S.A.A. | CM9: ORYGEN PERU S.A.A. | CN9: SAMAY I S.A.C | CO9: SAMAY I S.A.C | CP9: SAMAY I S.A.C | CQ9: SAMAY I S.A.C | CR9: TERMOCHILCA S.A.C. | CS9: TERMOCHILCA S.A.C. | CT9: COLCA SOLAR S.A.C. | CU9: ENERGIA RENOVABLE DEL SUR S.A. | CV9: GR CORTARRAMA SOCIEDAD ANONIMA CERRADA | CW9: GR TARUCA SOCIEDAD ANONIMA CERRADA | CX9: KONDU SAC | CY9: PERUANA DE INVERSIONES EN ENERGIAS RENOVABLES S.A. | CZ9: ORAZUL ENERGY PERÚ | DA9: ORAZUL ENERGY PERÚ | DB9: SAN GABAN | DC9: MAJA ENERGIA S.A.C. | DD9: EMPRESA DE GENERACION ELECTRICA CANCHAYLLO SAC | DE9: EMPRESA DE GENERACION ELECTRICA SANTA ANA S.A.C. | DF9: EMPRESA ELECTRICA AGUA AZUL | DG9: EMPRESA ELECTRICA RIO DOBLE | DH9: HIDROCAÑETE S.A. | DI9: HUAURA POWER GROUP S.A. | DJ9: MOQUEGUA FV S.A.C. | DK9: PANAMERICANA SOLAR SAC. | DL9: PARQUE EOLICO MARCONA S.A.C. | DM9: PARQUE EOLICO TRES HERMANAS S.A.C. | DN9: PETRAMAS | DO9: PETRAMAS | DP9: PETRAMAS | DQ9: PETRAMAS | DR9: TACNA SOLAR SAC. | DS9: ELECTRICA YANAPAMPA SAC | DT9: ANDEAN POWER S.A.C. | DU9: ASOCIACIÓN SANTA LUCIA DE CHACAS | DV9: ATRIA ENERGIA S.A.C. | DW9: EGEJUNIN | DX9: EGEJUNIN | DY9: EGEJUNIN | DZ9: EGEJUNIN | EA9: EMPRESA DE GENERACION ELECTRICA RIO BAÑOS S.A.C. | EB9: ENERGÍA EÓLICA S.A. | EC9: ENERGÍA EÓLICA S.A. | ED9: ENGIE | EE9: ENGIE | EF9: ENGIE | EG9: ENGIE | EH9: ENGIE | EI9: GENERACIÓN ANDINA S.A.C. | EJ9: GENERACIÓN ANDINA S.A.C. | EK9: GENERADORA DE ENERGÍA DEL PERÚ | EL9: GENERADORA DE ENERGÍA DEL PERÚ | EM9: GENERADORA DE ENERGÍA DEL PERÚ | EN9: GENERADORA DE ENERGÍA DEL PERÚ | EO9: GR PAINO SOCIEDAD ANONIMA CERRADA | EP9: MAJES ARCUS S.A.C. | EQ9: ORYGEN PERU S.A.A. | ER9: ORYGEN PERU S.A.A. | ES9: ORYGEN PERU S.A.A. | ET9: ORYGEN PERU S.A.A. | EU9: ORYGEN PERU S.A.A. | EV9: REPARTICIÓN ARCUS S.A.C. | EW9: SINERSA | EX9: SINERSA | EY9: BIOENERGIA DEL CHIRA S.A. | EZ9: GM OPERACIONES S.A.C. | FA9: GM OPERACIONES S.A.C. | FB9: SDF ENERGIA SAC | FC9: SDF ENERGIA SAC | FD9: AGRO INDUSTRIAL PARAMONGA S.A. | FE9: AGROAURORA S.A.C. | FF9: AGROINDUSTRIAS SAN JACINTO S.A.A. | FI9: UNACEM PERU S.A. | FJ9: ELECTRO ORIENTE | FK9: AGUAS Y ENERGIA PERU | FL9: ELECTRO ZAÑA S.A.C. | FM9: ELECTRONOROESTE S.A. | FN9: SDE PIURA | FO9: SINERSA | FP9: SINERSA
C10: SANTA ROSA 1 | D10: SANTA ROSA 2 | E10: MANTARO | F10: RESTITUCION | G10: TUMBES MAK 1 | H10: TUMBES MAK 2 | I10: CARHUAQUERO | J10: CAÑON DEL PATO | K10: AGUAYTIA TG1 | L10: AGUAYTIA TG2 | M10: KALLPA TG1 | N10: KALLPA TG2 | O10: KALLPA TG3 | P10: KALLPA TV | Q10: LFLORES TG1 | R10: LFLORES TV | S10: CERRO DEL AGUILA | T10: CERRODELAGUILAG4 | U10: SHOUGESA TV1 | V10: SHOUGESA TV2 | W10: SHOUGESA TV3 | X10: SHOUGESA CUMMINS | Y10: MACHUPICCHU | Z10: ARICOTA 1 | AA10: INDEPENDENCIA | AB10: CHARCANI I,II,III | AC10: CHARCANI IV | AD10: CHARCANI V | AE10: CHARCANI VI | AF10: CHILINA TG | AG10: MOLLENDO 1, 2, 3 | AH10: CHILINA (SULZ 1,2) | AI10: SAN GABAN II | AJ10: PLATANAL | AK10: RECKA | AL10: RF ETEN TG1 | AM10: RF ETEN TG2 | AN10: CHAGLLA GP1 | AO10: CHAGLLA | AP10: LA VIRGEN | AQ10: CHIMAY | AR10: YANANGO | AS10: HUANCHOR | AT10: MARAÑON | AU10: STA TERESA | AV10: FENIX GT11 | AW10: FENIX GT12 | AX10: FENIX TV10 | AY10: YAUPI | AZ10: OROYA | BA10: PACHACHACA | BB10: MALPASO | BC10: CAHUA | BD10: ARCATA | BE10: GALLITO CIEGO | BF10: CHEVES | BG10: HUANZA | BH10: MALACAS2 TG4 | BI10: MALACAS3 TG 5 | BJ10: MALACAS1 TG6 | BK10: RF ILO2 TG1 | BL10: RF ILO2 TG2 | BM10: RF ILO2 TG3 | BN10: YUNCAN | BO10: CHILCA1 TG1 | BP10: CHILCA1 TG2 | BQ10: CHILCA1 TG3 | BR10: CHILCA-TV | BS10: CHILCA2 TG41 | BT10: CHILCA2-TV | BU10: CTNEPI_TG41 | BV10: CTNEPI_TG42 | BW10: CTNEPI_TG43 | BX10: QUITARACSA | BY10: RF PTO MALDONADO | BZ10: RF PUCALLPA | CA10: PARIAC | CB10: HUINCO | CC10: MATUCANA | CD10: MOYOPAMPA | CE10: CALLAHUANCA | CF10: HUAMPANI | CG10: STA ROSA WEST TG7 | CH10: UTI_5 | CI10: UTI_6 | CJ10: VENTANILLA 3 | CK10: VENTANILLA 4 | CL10: VENTANILLA TV | CM10: STAROSA TG8 | CN10: PTO_BRVO TG1 | CO10: PTO_BRVO TG2 | CP10: PTO_BRVO TG3 | CQ10: PTO_BRVO TG4 | CR10: OLLEROS TG1 | CS10: OLLEROS TV | CT10: CS YARUCAYA | CU10: SAN JUAN | CV10: MATARANI | CW10: DUNA | CX10: CARHUAQUERO (CS) | CY10: MANTA I | CZ10: CARHUAQUERO4 | DA10: CAÑA BRAVA | DB10: TUPURI | DC10: RONCADOR | DD10: CANCHAYLLO | DE10: RENOVANDESH1 | DF10: POTRERO | DG10: PIZARRAS | DH10: NIMPERIAL | DI10: YARUCAYA | DJ10: MOQUEGUA-SOLAR | DK10: PANAMERICANA-SOLAR | DL10: PQE-EOLICO-MARCONA | DM10: PQE-EOLICO-3-HERMANAS | DN10: HUAYCOLORO | DO10: CALLAO | DP10: DONA_CATALINA | DQ10: LAGRINGAV | DR10: TACNA-SOLAR | DS10: YANAPAMPA | DT10: CARHUAC | DU10: HUALLIN | DV10: PURMACANA | DW10: HUASAHUASI | DX10: STACRUZ_1_2 | DY10: RUNATULLO_II | DZ10: RUNATULLO_III | EA10: RUCUY | EB10: PQE-EOLICO-TALARA | EC10: PQE-EOLICO-CUPISNIQUE | ED10: INTIPAMPA | EE10: PUNTA LOMITAS-BL1 | EF10: PUNTA LOMITAS-BL2 | EG10: PUN LOMITAS_EXP-BL1 | EH10: PUN LOMITAS_EXP-BL2 | EI10: 8AGOSTO | EJ10: EL CARMEN | EK10: LA JOYA | EL10: ANGEL_I | EM10: ANGEL_II | EN10: ANGEL_III | EO10: HUAMBOS | EP10: MAJES | EQ10: RUBI | ER10: CH_HER1 | ES10: WAYRA-I | ET10: WAYRA EXTENSION | EU10: CLEMESI | EV10: REPARTICION | EW10: POECHOS2 | EX10: CHANCAY | EY10: CANA BRAVA | EZ10: REFINERIA TALARA TV1 | FA10: REFINERÍA TALARA TV2 | FB10: OQUENDO TG1 | FC10: OQUENDO TV1 | FD10: PARAMONGA | FE10: MAPLE | FF10: SAN_JACINTO | FG10: MVAR | FI10: CARPAPATA | FJ10: CENTRALES ELOR | FK10: PIAS1 | FL10: ZANA | FM10: TABLAZO | FN10: TALLANCA | FO10: CURUMUY | FP10: POECHOS1 | FQ10: MVAR
A11: 20/03/2025 | B11: 00:30 | C11: 0 | D11: 0 | E11: 36 | F11: 10.7 | I11: -12.8 | J11: 4.7 | M11: -37.4 | N11: -36.2 | O11: -14.4 | P11: 17.1 | Q11: -21.2 | R11: -17 | S11: 27.5 | T11: 0.1 | Y11: 9.8 | Z11: 0.8 | AA11: 0 | AB11: -3.2 | AC11: 1.9 | AD11: 6.1 | AE11: 1.5 | AI11: 7 | AJ11: 12.8 | AN11: -1.3 | AO11: 49.7 | AP11: 9.9 | AQ11: 8 | AR11: -0.2 | AS11: -0.6 | AT11: 2.7 | AU11: 0.5 | AV11: -24.2 | AW11: -34.1 | AX11: -52.9 | AY11: 9 | BA11: 0 | BB11: 2.3 | BC11: 11 | BD11: 1.1 | BE11: -0.1 | BF11: 1.2 | BG11: -0.2 | BH11: -8.9 | BM11: 0 | BN11: 5.3 | BO11: -1 | BP11: 0 | BR11: 11.1 | CA11: 0 | CB11: 17 | CC11: 17.4 | CD11: -0.4 | CE11: 4.3 | CF11: -0.2 | CK11: 13.4 | CL11: -36.6 | CU11: -2.2 | CV11: 0 | CZ11: 0 | DA11: -0.9 | DC11: 0 | DD11: 1.3 | DE11: 2.7 | DF11: -1.1 | DG11: 0.6 | DH11: 0.6 | DJ11: 0 | DK11: 0 | DL11: -0.8 | DM11: 6.1 | DN11: 1.8 | DO11: 0.5 | DP11: 0.68 | DQ11: 1 | DR11: 0 | DS11: 0 | DT11: 0.4 | DU11: 0.3 | DW11: -4.8 | DX11: 0.6 | DY11: 2 | DZ11: 2.7 | EA11: 1.3 | EB11: 0.8 | EC11: 4 | ED11: 0 | EE11: -5.2 | EF11: -6.2 | EG11: 0 | EH11: 0 | EI11: 2.6 | EJ11: -0.3 | EK11: 1.2 | EL11: 0.2 | EM11: 0.2 | EN11: 0.2 | EP11: 0 | EQ11: 0 | ER11: -0.2 | ES11: 4.5 | ET11: 0 | EU11: 0 | EV11: 0 | EW11: 0.2 | EX11: 1.6 | EZ11: 11.8 | FA11: 7.6 | FB11: 1.2 | FC11: 2 | FD11: 1.5 | FE11: 0 | FF11: 2 | FG11: 39.48 | FI11: 2.62157 | FJ11: -0.656 | FL11: 1.7 | FN11: 2.43515 | FO11: -0.6 | FP11: 2 | FQ11: 7.50072
A12: 20/03/2025 | B12: 01:00 | C12: 0 | D12: 0 | E12: 28.5 | F12: 9.9 | I12: -15.7 | J12: -1.4 | M12: -40.4 | N12: -42.7 | O12: -21.2 | P12: 14.1 | Q12: -22.3 | R12: -17.9 | S12: 38.3 | T12: 0 | Y12: 12 | Z12: 0.9 | AA12: 0 | AB12: -3.3 | AC12: 1.8 | AD12: 5.8 | AE12: 1.5 | AI12: 7 | AJ12: 12 | AN12: -1.2 | AO12: 33 | AP12: 9.4 | AQ12: 0.7 | AR12: 0.1 | AS12: -0.5 | AT12: 2.7 | AU12: 1.1 | AV12: -25.6 | AW12: -35.5 | AX12: -54.2 | AY12: 4.7 | BA12: 0 | BB12: -0.4 | BC12: 9.4 | BD12: 1.1 | BE12: -0.1 | BF12: -1.3 | BG12: -0.9 | BH12: 5.1 | BM12: 0 | BN12: -1.6 | BO12: -1.8 | BP12: 0 | BR12: 10.3 | CA12: 0 | CB12: 18.2 | CC12: 16.8 | CD12: -0.1 | CE12: 3.2 | CF12: -0.1 | CK12: 10.5 | CL12: -40.8 | CU12: -1.9 | CV12: 0 | CZ12: -0.1 | DA12: -0.9 | DC12: 0.1 | DD12: 1.3 | DE12: 2.7 | DF12: -1.2 | DG12: 0.6 | DH12: 0.6 | DJ12: 0 | DK12: 0 | DL12: -0.6 | DM12: 6.5 | DN12: 1.8 | DO12: 0.5 | DP12: 0.68 | DQ12: 1 | DR12: 0 | DS12: 0 | DT12: 0.4 | DU12: 0.3 | DW12: -4.6 | DX12: 0.9 | DY12: 2.1 | DZ12: 2.3 | EA12: 1.1 | EB12: 0.8 | EC12: 4 | ED12: 0 | EE12: -6.9 | EF12: -7 | EG12: 0 | EH12: 0 | EI12: 2.6 | EJ12: -0.3 | EK12: 1.3 | EL12: 0.2 | EM12: 0.2 | EN12: 0.2 | EP12: 0 | EQ12: 0 | ER12: -0.2 | ES12: 4.5 | ET12: 0 | EU12: 0 | EV12: 0 | EW12: 0.2 | EX12: 1.4 | EZ12: 9.8 | FA12: 5.7 | FB12: 1.2 | FC12: 1.9 | FD12: 4 | FE12: 0 | FF12: 2.8 | FG12: -30.92 | FI12: 2.48143 | FJ12: -0.822 | FL12: 1.7 | FN12: 2.43184 | FO12: -0.4 | FP12: 2 | FQ12: 7.39127
A13: 20/03/2025 | B13: 01:30 | C13: 0 | D13: 0 | E13: 36.4 | F13: 12.3 | I13: -16.9 | J13: 5.6 | M13: -38.1 | N13: -37.8 | O13: -15.9 | P13: 16.1 | Q13: -22.7 | R13: -17.4 | S13: 39.6 | T13: 0.1 | Y13: 12 | Z13: 0.7 | AA13: 0 | AB13: -3.2 | AC13: 1.8 | AD13: 6.5 | AE13: 1.5 | AI13: 7.6 | AJ13: 12 | AN13: -1.4 | AO13: -6 | AP13: 8 | AQ13: 0.6 | AR13: -3.5 | AS13: -0.6 | AT13: 2.7 | AU13: -0.2 | AV13: -26.6 | AW13: -36.7 | AX13: -55.3 | AY13: 6.5 | BA13: 0 | BB13: 0.1 | BC13: 10.5 | BD13: 1.1 | BE13: 0.1 | BF13: -0.5 | BG13: 2.5 | BH13: 1.3 | BM13: 0 | BN13: -4.2 | BO13: -2.6 | BP13: 0 | BR13: 9.5 | CA13: 0 | CB13: 18.1 | CC13: 17 | CD13: -0.2 | CE13: 3.1 | CF13: -0.2 | CK13: 16.6 | CL13: -32.6 | CU13: -2.4 | CV13: 0 | CZ13: 0 | DA13: -0.9 | DC13: 0.1 | DD13: 1.2 | DE13: 2.7 | DF13: -0.2 | DG13: 0.6 | DH13: 0.6 | DJ13: 0 | DK13: 0 | DL13: -0.8 | DM13: 6.1 | DN13: 1.8 | DO13: 0.5 | DP13: 0.68 | DQ13: 1.1 | DR13: 0 | DS13: 0 | DT13: 0.4 | DU13: 0.3 | DW13: -4.7 | DX13: 0.9 | DY13: 2.1 | DZ13: 2.3 | EA13: 1.1 | EB13: 0.8 | EC13: 4 | ED13: 0 | EE13: -3.4 | EF13: -4.6 | EG13: 0.1 | EH13: 0 | EI13: 2.6 | EJ13: -0.3 | EK13: 1.3 | EL13: 0.2 | EM13: 0.2 | EN13: 0.2 | EP13: 0 | EQ13: 0 | ER13: -0.2 | ES13: 4.3 | ET13: 0 | EU13: 0 | EV13: 0 | EW13: 0.2 | EX13: 1.4 | EZ13: 9.3 | FA13: 5.1 | FB13: 1.2 | FC13: 2.7 | FD13: 5 | FE13: 0 | FF13: 2.2 | FG13: -26.92 | FI13: 2.13321 | FJ13: -0.145 | FL13: 1.6 | FN13: 2.42764 | FO13: -0.7 | FP13: 1.9 | FQ13: 7.21585
A14: 20/03/2025 | B14: 02:00 | C14: 0 | D14: 0 | E14: 30.8 | F14: 10.1 | I14: -17.1 | J14: 5.9 | M14: -36.8 | N14: -41.1 | O14: -20.2 | P14: 18.2 | Q14: -22.1 | R14: -17.5 | S14: 40.6 | T14: -0.1 | Y14: 11.4 | Z14: 0.3 | AA14: 0 | AB14: -3.3 | AC14: 1.8 | AD14: 6.2 | AE14: 1.5 | AI14: -1.1 | AJ14: 11.5 | AN14: -1.4 | AO14: -9.7 | AP14: 0.5 | AQ14: 1.8 | AR14: -3.1 | AS14: -0.2 | AT14: 2.7 | AU14: 0.2 | AV14: -27.8 | AW14: -37.1 | AX14: -50.9 | AY14: -3.4 | BA14: 0 | BB14: -4.5 | BC14: 10.1 | BD14: 1.1 | BE14: -0.1 | BF14: -0.3 | BG14: 1.8 | BH14: 1.4 | BM14: 0 | BN14: -3.3 | BO14: -1.3 | BP14: 0 | BR14: 7.7 | CA14: 0 | CB14: 20.6 | CC14: 18.8 | CD14: 1 | CE14: 3.8 | CF14: 0 | CK14: 15.1 | CL14: -33.1 | CU14: -2.2 | CV14: 0 | CZ14: 0 | DA14: -0.9 | DC14: -0.1 | DD14: 1 | DE14: 1.8 | DF14: 0 | DG14: 0.6 | DH14: 0.5 | DJ14: 0 | DK14: 0 | DL14: -1 | DM14: 5.8 | DN14: 1.8 | DO14: 0.5 | DP14: 0.68 | DQ14: 1.1 | DR14: 0 | DS14: 0 | DT14: 0.4 | DU14: 0.3 | DW14: -4.7 | DX14: 0.4 | DY14: 2.1 | DZ14: 2.3 | EA14: 1.1 | EB14: 0.8 | EC14: 4 | ED14: 0 | EE14: -3 | EF14: -5.3 | EG14: 0.1 | EH14: 0 | EI14: 2.6 | EJ14: -0.3 | EK14: 1.2 | EL14: 0.2 | EM14: 0.2 | EN14: 0.2 | EP14: 0 | EQ14: 0 | ER14: -0.2 | ES14: 3.9 | ET14: 0 | EU14: 0 | EV14: 0 | EW14: 0.2 | EX14: 1.4 | EZ14: 9.6 | FA14: 5.3 | FB14: 1.2 | FC14: 2.6 | FD14: 5.7 | FE14: 0 | FF14: 2.4 | FG14: -66.32 | FI14: 1.31305 | FJ14: 0.025 | FL14: 1.7 | FN14: 2.4246 | FO14: -0.6 | FP14: 2 | FQ14: 6.86265
A15: 20/03/2025 | B15: 02:30 | C15: 0 | D15: 0 | E15: 22.4 | F15: 8.9 | I15: -17.9 | J15: 5.8 | M15: -42 | N15: -47.4 | O15: -26.9 | P15: 14.4 | Q15: -23.9 | R15: -19.3 | S15: 39.8 | T15: -0.1 | Y15: 10.7 | Z15: 0.6 | AA15: 0 | AB15: -3.1 | AC15: 1.7 | AD15: 5.7 | AE15: 1.4 | AI15: 4 | AJ15: 10.1 | AN15: -1.3 | AO15: -12.2 | AP15: -1 | AQ15: -1.7 | AR15: -2.7 | AS15: -0.3 | AT15: 2.7 | AU15: 0 | AV15: -28.1 | AW15: -37.8 | AX15: -51.6 | AY15: -2.3 | BA15: 0 | BB15: -4.1 | BC15: 9.4 | BD15: 1.2 | BE15: -0.1 | BF15: -3.4 | BG15: 1.3 | BH15: 0.6 | BM15: 0 | BN15: -1.3 | BO15: -2.3 | BP15: 0 | BR15: 9 | CA15: 0 | CB15: 19.7 | CC15: 17 | CD15: -0.2 | CE15: 4.5 | CF15: 0 | CK15: 14.5 | CL15: -34.4 | CU15: -2.4 | CV15: 0 | CZ15: 0 | DA15: -1 | DC15: -0.1 | DD15: 1 | DE15: 1.7 | DF15: 0.3 | DG15: 0.6 | DH15: 0.6 | DJ15: 0 | DK15: 0 | DL15: -1.2 | DM15: 5.3 | DN15: 1.8 | DO15: 0.5 | DP15: 0.7 | DQ15: 1.1 | DR15: 0 | DS15: 0.2 | DT15: 0.4 | DU15: 0.3 | DW15: -4.7 | DX15: 0.3 | DY15: 2 | DZ15: 2.3 | EA15: 1 | EB15: 0.8 | EC15: 4 | ED15: 0 | EE15: -5.5 | EF15: -6.7 | EG15: 0 | EH15: 0 | EI15: 2.6 | EJ15: -0.3 | EK15: 1.3 | EL15: 0.2 | EM15: 0.2 | EN15: 0.2 | EP15: 0 | EQ15: 0 | ER15: -0.2 | ES15: 4.4 | ET15: 0 | EU15: 0 | EV15: 0 | EW15: 0.2 | EX15: 1.3 | EZ15: 9.1 | FA15: 4.9 | FB15: 1.2 | FC15: 2.4 | FD15: 5.6 | FE15: 0 | FF15: 2.1 | FG15: -121.5 | FI15: 1.38972 | FJ15: -0.009 | FL15: 1.6 | FN15: 2.42676 | FO15: -0.7 | FP15: 2 | FQ15: 6.70748
A16: 20/03/2025 | B16: 03:00 | C16: 0 | D16: 0 | E16: 21 | F16: 8.7 | I16: -17.2 | J16: 2.2 | M16: -45.8 | N16: -41.6 | O16: -19.7 | P16: 6.6 | Q16: -25.5 | R16: -20 | S16: 32.4 | T16: 0.4 | Y16: 9.9 | Z16: 1 | AA16: 0 | AB16: -3.1 | AC16: 1.6 | AD16: 5.1 | AE16: 1.3 | AI16: 3.9 | AJ16: 10.4 | AN16: -1.3 | AO16: -10.2 | AP16: -0.8 | AQ16: -1.9 | AR16: -3.1 | AS16: -0.3 | AT16: 2.7 | AU16: 1.2 | AV16: -34.3 | AW16: -43.8 | AX16: -55.5 | AY16: -0.4 | BA16: 0 | BB16: -0.5 | BC16: 12.3 | BD16: 1.1 | BE16: 0.1 | BF16: 4.6 | BG16: 0.7 | BH16: -0.4 | BM16: 0 | BN16: -7.6 | BO16: -5.1 | BP16: 0 | BR16: 6.7 | CA16: 0 | CB16: 17.2 | CC16: 16.6 | CD16: -1.1 | CE16: 3.3 | CF16: 0 | CK16: 10.1 | CL16: -39.8 | CU16: -2.2 | CV16: 0 | CZ16: -0.1 | DA16: -0.9 | DC16: -0.2 | DD16: 1.2 | DE16: 1.6 | DF16: 0.1 | DG16: 0.6 | DH16: 0.6 | DJ16: 0 | DK16: 0 | DL16: -2 | DM16: 8.9 | DN16: 1.8 | DO16: 0.5 | DP16: 0.7 | DQ16: 1.1 | DR16: 0 | DS16: 0 | DT16: 0.4 | DU16: 0.3 | DW16: -4.6 | DX16: 0.3 | DY16: 1.9 | DZ16: 2.3 | EA16: 0.9 | EB16: 0.8 | EC16: 4 | ED16: 0 | EE16: -6 | EF16: -9 | EG16: 0 | EH16: 0 | EI16: 2.6 | EJ16: -0.3 | EK16: 1.3 | EL16: 0.2 | EM16: 0.2 | EN16: 0.2 | EP16: 0 | EQ16: 0 | ER16: -0.2 | ES16: 4.4 | ET16: 0 | EU16: 0 | EV16: 0 | EW16: 0.2 | EX16: 1.2 | EZ16: 9 | FA16: 4.8 | FB16: 1.2 | FC16: 2.3 | FD16: 5.2 | FE16: 0 | FF16: 1.9 | FG16: -160.7 | FI16: 1.452 | FJ16: -0.084 | FL16: 1.6 | FN16: 2.42542 | FO16: -0.9 | FP16: 0.1 | FQ16: 4.59342
A17: 20/03/2025 | B17: 03:30 | C17: 0 | D17: 0 | E17: 33.3 | F17: 12.3 | I17: -15.4 | J17: 16.9 | M17: -40.6 | N17: -41 | O17: -19.2 | P17: 14.6 | Q17: -22.5 | R17: -17.9 | S17: 37.4 | T17: 0 | Y17: 10.4 | Z17: 1.3 | AA17: 0 | AB17: -3.2 | AC17: 1.8 | AD17: 7.7 | AE17: 1.5 | AI17: 4.4 | AJ17: 11.5 | AN17: -1.4 | AO17: 6 | AP17: -3.1 | AQ17: -2.4 | AR17: -3 | AS17: -0.2 | AT17: 2.7 | AU17: 0.7 | AV17: -28.5 | AW17: -38.5 | AX17: -50 | AY17: -5.7 | BA17: 0 | BB17: -4 | BC17: 11.4 | BD17: 1.1 | BE17: -0.1 | BF17: -1.6 | BG17: 1.5 | BH17: 2.3 | BM17: 0 | BN17: -7.2 | BO17: -2.6 | BP17: 0 | BR17: 8.8 | CA17: 0.1 | CB17: 18 | CC17: 16.8 | CD17: -0.6 | CE17: 3.1 | CF17: -0.2 | CK17: 15.5 | CL17: -34.1 | CU17: -2.3 | CV17: 0 | CZ17: 0 | DA17: -0.9 | DC17: -0.2 | DD17: 1 | DE17: 1.7 | DF17: 0 | DG17: 0.6 | DH17: 0.6 | DJ17: 0 | DK17: 0 | DL17: -2.3 | DM17: 8 | DN17: 1.8 | DO17: 0.5 | DP17: 0.7 | DQ17: 1.1 | DR17: 0 | DS17: 0.2 | DT17: 0.3 | DU17: 0.3 | DW17: -4.9 | DX17: 0.8 | DY17: 2 | DZ17: 2.3 | EA17: 1.1 | EB17: 0.8 | EC17: 4 | ED17: 0 | EE17: -2 | EF17: -4.2 | EG17: 0 | EH17: 0 | EI17: 2.6 | EJ17: -0.3 | EK17: 1.4 | EL17: 0.2 | EM17: 0.2 | EN17: 0.2 | EP17: 0 | EQ17: 0 | ER17: -0.2 | ES17: 4.8 | ET17: 0 | EU17: 0 | EV17: 0 | EW17: 0.1 | EX17: 1.4 | EZ17: 9.4 | FA17: 5.2 | FB17: 1.2 | FC17: 2.5 | FD17: 5.6 | FE17: 0 | FF17: 2.1 | FG17: -54.5 | FI17: 1.0288 | FJ17: 0.01 | FL17: 1.6 | FN17: 2.42993 | FO17: -0.5 | FP17: 0.3 | FQ17: 4.86873
A18: 20/03/2025 | B18: 04:00 | C18: 0 | D18: 0 | E18: 23.4 | F18: 10.8 | I18: -14.6 | J18: 17.6 | M18: -40.9 | N18: -47.3 | O18: -26.2 | P18: 13.1 | Q18: -23.1 | R18: -18.2 | S18: 36.6 | T18: 0 | Y18: 11.4 | Z18: 1.7 | AA18: 0 | AB18: -3.2 | AC18: 1.8 | AD18: 8.1 | AE18: 1.5 | AI18: 4.1 | AJ18: 11.1 | AN18: -1.4 | AO18: 1.8 | AP18: -3.5 | AQ18: -1.2 | AR18: -3.6 | AS18: -0.4 | AT18: 2.7 | AU18: 0.5 | AV18: -29.2 | AW18: -39.1 | AX18: -50.5 | AY18: -6.2 | BA18: 0 | BB18: -5.2 | BC18: 11.5 | BD18: 1.1 | BE18: -0.1 | BF18: -2 | BG18: 1.8 | BH18: 0 | BM18: 0 | BN18: -9.1 | BO18: -2.5 | BP18: 0 | BR18: 8.9 | CA18: 0.1 | CB18: 18.4 | CC18: 17.3 | CD18: -0.1 | CE18: 3.2 | CF18: 0.1 | CK18: 14.9 | CL18: -34.4 | CU18: -2.4 | CV18: 0 | CZ18: -0.1 | DA18: -1 | DC18: -0.2 | DD18: 1 | DE18: 1.6 | DF18: 0.5 | DG18: 0.3 | DH18: 0.7 | DJ18: 0 | DK18: 0 | DL18: -2.4 | DM18: 7.4 | DN18: 1.8 | DO18: 0.5 | DP18: 0.7 | DQ18: 1.1 | DR18: 0 | DS18: 0.2 | DT18: 0.4 | DU18: 0.3 | DW18: -4.9 | DX18: 0.5 | DY18: 2 | DZ18: 2.3 | EA18: 1.1 | EB18: 0.8 | EC18: 4 | ED18: 0 | EE18: -4.7 | EF18: -7.3 | EG18: 0 | EH18: 0 | EI18: 2.6 | EJ18: -0.3 | EK18: 1.4 | EL18: 0.2 | EM18: 0.2 | EN18: 0.2 | EP18: 0 | EQ18: 0 | ER18: -0.2 | ES18: 4.8 | ET18: 0 | EU18: 0 | EV18: 0 | EW18: 0.2 | EX18: 1.4 | EZ18: 11.1 | FA18: 6.8 | FB18: 1.2 | FC18: 2.5 | FD18: 5 | FE18: 0 | FF18: 2 | FG18: -95.2 | FI18: 0.90312 | FJ18: -0.037 | FL18: 1.7 | FN18: 2.42327 | FO18: 0 | FP18: 0.3 | FQ18: 5.28939
A19: 20/03/2025 | B19: 04:30 | C19: 0 | D19: 0 | E19: 33.5 | F19: 12.5 | I19: -14.7 | J19: 3.8 | M19: -38 | N19: -44.3 | O19: -23.3 | P19: 18.1 | Q19: -21.9 | R19: -17.3 | S19: 41.2 | T19: 0 | Y19: 12.5 | Z19: 0.8 | AA19: 0 | AB19: -3.2 | AC19: 2 | AD19: 8.4 | AE19: 1.6 | AI19: 4.1 | AJ19: 11.1 | AN19: -1.4 | AO19: 4.7 | AP19: -3.7 | AQ19: -1.9 | AR19: -3.1 | AS19: -1.2 | AT19: 2.7 | AU19: 0.4 | AV19: -27.8 | AW19: -37.6 | AX19: -49 | AY19: -5.2 | BA19: 0 | BB19: -4.4 | BC19: 11.3 | BD19: 1.1 | BE19: -0.1 | BF19: -2.1 | BG19: 1.9 | BH19: 0 | BM19: 0 | BN19: -5.8 | BO19: -1 | BP19: 0 | BR19: 10.5 | CA19: 0 | CB19: 19.5 | CC19: 16.7 | CD19: -0.4 | CE19: 4.6 | CF19: 0 | CK19: 16.5 | CL19: -31.9 | CU19: -2.8 | CV19: 0 | CZ19: -0.1 | DA19: -1 | DC19: -0.3 | DD19: 1 | DE19: 1.6 | DF19: 0.3 | DG19: 0.6 | DH19: 0.6 | DJ19: 0 | DK19: 0 | DL19: -2.1 | DM19: 7.7 | DN19: 1.8 | DO19: 0.5 | DP19: 0.7 | DQ19: 1.1 | DR19: 0 | DS19: 0.2 | DT19: 0.4 | DU19: 0.3 | DW19: -4.9 | DX19: 0.6 | DY19: 2 | DZ19: 2.3 | EA19: 1.3 | EB19: 0.8 | EC19: 4 | ED19: 0 | EE19: -1.7 | EF19: -3.9 | EG19: 0.1 | EH19: 0 | EI19: 2.6 | EJ19: -0.3 | EK19: 1.6 | EL19: 0.2 | EM19: 0.2 | EN19: 0.2 | EP19: 0 | EQ19: 0 | ER19: -0.2 | ES19: 4.8 | ET19: 0 | EU19: 0 | EV19: 0 | EW19: 0.2 | EX19: 1.6 | EZ19: 11.1 | FA19: 6.9 | FB19: 1.2 | FC19: 2.5 | FD19: 5.1 | FE19: 0 | FF19: 2.7 | FG19: -48.3 | FI19: 0.93664 | FJ19: 0.137 | FL19: 1.8 | FN19: 2.41594 | FO19: 0.1 | FP19: 0.4 | FQ19: 5.78958
A20: 20/03/2025 | B20: 05:00 | C20: 0 | D20: 0 | E20: 33.3 | F20: 9.6 | I20: -13.1 | J20: 4.9 | M20: -40.1 | N20: -39.3 | O20: -16.9 | P20: 13.8 | Q20: -22.9 | R20: -17.5 | S20: 37.4 | T20: 0.1 | Y20: 13.1 | Z20: 1 | AA20: 0 | AB20: -3.2 | AC20: 2 | AD20: 8.5 | AE20: 1.6 | AI20: 13.8 | AJ20: 11.2 | AN20: -1.3 | AO20: 3 | AP20: -2.7 | AQ20: -1.4 | AR20: -3.2 | AS20: -1.4 | AT20: 2.7 | AU20: 0.5 | AV20: -29.2 | AW20: -39 | AX20: -50.8 | AY20: -4.2 | BA20: 0 | BB20: -2.1 | BC20: 13 | BD20: 1.1 | BE20: -0.1 | BF20: 0.9 | BG20: 2.3 | BH20: 0 | BM20: 0 | BN20: -3.5 | BO20: -2.5 | BP20: 0 | BR20: 9.9 | CA20: 0 | CB20: 17.2 | CC20: 17.3 | CD20: -0.1 | CE20: 3.2 | CF20: 0.1 | CK20: 15.9 | CL20: -32.8 | CU20: -2.4 | CV20: 0 | CZ20: 0 | DA20: -0.9 | DC20: -0.3 | DD20: 0.9 | DE20: 1.6 | DF20: 0.1 | DG20: 0.6 | DH20: 0.6 | DJ20: 0 | DK20: 0 | DL20: -2.2 | DM20: 7.3 | DN20: 1.8 | DO20: 0.5 | DP20: 0.7 | DQ20: 1.1 | DR20: 0 | DS20: 0.1 | DT20: 0.4 | DU20: 0.3 | DW20: -4.9 | DX20: 0.2 | DY20: 2.1 | DZ20: 2.3 | EA20: 1.3 | EB20: 0.8 | EC20: 4 | ED20: 0.4 | EE20: -3.3 | EF20: -5.5 | EG20: 0 | EH20: 0 | EI20: 2.6 | EJ20: -0.3 | EK20: 1.6 | EL20: 0.2 | EM20: 0.2 | EN20: 0.2 | EP20: 0 | EQ20: 0 | ER20: -0.2 | ES20: 4.8 | ET20: 0 | EU20: 0 | EV20: 0 | EW20: 0.2 | EX20: 1.6 | EZ20: 11.2 | FA20: 7 | FB20: 1.2 | FC20: 2.5 | FD20: 5.2 | FE20: 0 | FF20: 2.3 | FG20: -42 | FI20: 1.24865 | FJ20: 0.213 | FL20: 1.7 | FN20: 2.41838 | FO20: 0.1 | FP20: 0.2 | FQ20: 5.88003
A21: 20/03/2025 | B21: 05:30 | C21: 0.1 | D21: 0 | E21: 24.4 | F21: 8.7 | I21: -11 | J21: 5.7 | M21: -37 | N21: -38.5 | O21: -16.9 | P21: 19.7 | Q21: -21 | R21: -16.6 | S21: 34 | T21: 0.1 | Y21: 12.1 | Z21: 1.2 | AA21: 0 | AB21: -3 | AC21: 2.2 | AD21: 9.4 | AE21: 1.8 | AI21: 13.6 | AJ21: 12.9 | AN21: -1.2 | AO21: -12.9 | AP21: -1 | AQ21: -1 | AR21: -3.3 | AS21: 0.8 | AT21: 2.7 | AU21: 0.3 | AV21: -26.6 | AW21: -36.4 | AX21: -47.8 | AY21: 4.2 | BA21: 0 | BB21: -1.7 | BC21: 12.7 | BD21: 1.1 | BE21: -0.1 | BF21: 0.5 | BG21: 3.3 | BH21: 0 | BM21: 0 | BN21: -0.1 | BO21: -0.8 | BP21: 0 | BR21: 11.3 | CA21: 0 | CB21: 18 | CC21: 17.6 | CD21: 0.5 | CE21: 3.2 | CF21: 0.1 | CK21: 19.1 | CL21: -28.1 | CU21: -2.8 | CV21: 0 | CZ21: 0 | DA21: -0.9 | DC21: -0.2 | DD21: 0.9 | DE21: 1.6 | DF21: 0.8 | DG21: 0.6 | DH21: 0.5 | DJ21: 0 | DK21: 0 | DL21: -2.1 | DM21: 7.4 | DN21: 1.8 | DO21: 0.5 | DP21: 0.7 | DQ21: 1.1 | DR21: 0 | DS21: 0.2 | DT21: 0.4 | DU21: 0.3 | DW21: -5 | DX21: 0.4 | DY21: 2.1 | DZ21: 2.3 | EA21: 1.3 | EB21: 0.8 | EC21: 4 | ED21: 0.4 | EE21: -5 | EF21: -7.7 | EG21: 0 | EH21: 0 | EI21: 2.6 | EJ21: -0.3 | EK21: 1.7 | EL21: 0.2 | EM21: 0.2 | EN21: 0.2 | EP21: 0 | EQ21: 0 | ER21: -0.2 | ES21: 4.7 | ET21: 0 | EU21: 0 | EV21: 0 | EW21: 0.2 | EX21: 1.6 | EZ21: 12.3 | FA21: 8.1 | FB21: 1.2 | FC21: 0.9 | FD21: 5.4 | FE21: 0 | FF21: 2.7 | FG21: -17.8 | FI21: 1.41644 | FJ21: 0.376 | FL21: 1.8 | FN21: 2.41368 | FO21: 0.5 | FP21: 0.2 | FQ21: 6.70612
A22: 20/03/2025 | B22: 06:00 | C22: 0.1 | D22: 0 | E22: 48 | F22: 11.9 | I22: -9.6 | J22: 9.5 | M22: -30.6 | N22: -33.4 | O22: -11.8 | P22: 25.6 | Q22: -17.5 | R22: -14.4 | S22: 45.7 | T22: 0.1 | Y22: 14.3 | Z22: 1.1 | AA22: 0 | AB22: -2.9 | AC22: 2.2 | AD22: 9.2 | AE22: 1.8 | AI22: 14.6 | AJ22: 13.7 | AN22: -0.9 | AO22: 28.3 | AP22: 6.7 | AQ22: -0.6 | AR22: -2.5 | AS22: 0.6 | AT22: 2.7 | AU22: 1 | AV22: -20.9 | AW22: -30.8 | AX22: -42.4 | AY22: 4.9 | BA22: 0 | BB22: 1.3 | BC22: 13.9 | BD22: 1.1 | BE22: -0.1 | BF22: -1 | BG22: 5.1 | BH22: 0 | BM22: 0 | BN22: 8.4 | BO22: 0 | BP22: 0 | BR22: 13.4 | CA22: 0 | CB22: 18.3 | CC22: 17.8 | CD22: 0.2 | CE22: 3.2 | CF22: 0.1 | CK22: 26.2 | CL22: -18.2 | CU22: -2.4 | CV22: 0 | CZ22: -0.1 | DA22: -0.9 | DC22: -0.3 | DD22: 1.1 | DE22: 1.6 | DF22: 0.8 | DG22: 0.6 | DH22: 0.6 | DJ22: -0.1 | DK22: 0 | DL22: -1.8 | DM22: 8.6 | DN22: 1.8 | DO22: 0.5 | DP22: 0.7 | DQ22: 1.1 | DR22: 0 | DS22: 0.1 | DT22: 0.3 | DU22: 0.3 | DW22: -4.9 | DX22: 0.8 | DY22: 2.3 | DZ22: 2.5 | EA22: 1.3 | EB22: 0.8 | EC22: 4 | ED22: 0.3 | EE22: -1.6 | EF22: -3.1 | EG22: 0.3 | EH22: 0.1 | EI22: 2.6 | EJ22: -0.3 | EK22: 1.6 | EL22: 0.2 | EM22: 0.2 | EN22: 0.2 | EP22: 0 | EQ22: -0.5 | ER22: -0.2 | ES22: 4 | ET22: 0 | EU22: -0.1 | EV22: 0 | EW22: 0.2 | EX22: 1.6 | EZ22: 11.4 | FA22: 7.1 | FB22: 1.2 | FC22: 2.7 | FD22: 5 | FE22: 0.1 | FF22: 2.3 | FG22: 168 | FI22: 2.48984 | FJ22: 0.018 | FL22: 1.8 | FN22: 2.412 | FO22: -0.3 | FP22: 0.2 | FQ22: 6.61984
... A58: 21/03/2025 | B58: 00:00 | C58: 0.1 | D58: 0 | E58: 28.5 | F58: 16.1 | I58: -15 | J58: 0.6 | M58: 7.3 | N58: 1.8 | O58: -12.8 | P58: 11.1 | Q58: -4.7 | R58: -8.6 | S58: 80.4 | T58: -0.1 | Y58: 11 | Z58: 1 | AA58: 0 | AB58: -3.3 | AC58: 2.1 | AD58: 15.2 | AE58: 1.8 | AI58: 5.9 | AJ58: 4.5 | AN58: -1.5 | AO58: 50 | AP58: 10.5 | AQ58: 4.7 | AR58: -5.4 | AS58: 0.7 | AT58: 2.7 | AU58: 1.4 | AV58: 0 | AW58: -36 | AX58: -60.2 | AY58: 9.9 | BA58: 0 | BB58: 0.4 | BC58: 6.7 | BD58: 0 | BE58: -0.1 | BF58: 11.4 | BG58: -0.6 | BH58: 0 | BM58: 0 | BN58: 7.3 | BO58: -7.4 | BP58: 0 | BR58: 14 | CA58: 0 | CB58: 45.9 | CC58: 38.2 | CD58: 0.6 | CE58: 7.1 | CF58: -3.7 | CK58: -6.7 | CL58: -53.2 | CU58: -3.6 | CV58: 0 | CZ58: 0 | DA58: -0.9 | DC58: 0.3 | DD58: 1.3 | DE58: 1.6 | DF58: -1.2 | DG58: 0.6 | DH58: 0.6 | DJ58: 0 | DK58: 0 | DL58: -1.4 | DM58: 2.9 | DN58: 1.8 | DO58: 0.5 | DP58: 0.7 | DQ58: 1.1 | DR58: 0 | DS58: 0.1 | DT58: 0 | DU58: 0.2 | DW58: -4.6 | DX58: 0.2 | DY58: 2.2 | DZ58: 3.1 | EA58: 1.1 | EB58: 0.8 | EC58: 4 | ED58: 0 | EE58: -12.4 | EF58: -17 | EG58: 0 | EH58: 0 | EI58: 2.6 | EJ58: -0.1 | EK58: 1.7 | EL58: 0.2 | EM58: 0.2 | EN58: 0.2 | EP58: 0 | EQ58: 0 | ER58: -0.2 | ES58: -7.6 | ET58: 0 | EU58: 0 | EV58: 0 | EW58: 0.8 | EX58: 1.4 | EZ58: 12.6 | FA58: 3.9 | FB58: 1.2 | FC58: 1.4 | FD58: 1.9 | FE58: 0 | FF58: 2.3 | FG58: 184.1 | FI58: 1.71276 | FJ58: 0.179 | FL58: 0 | FN58: 1.98262 | FO58: -1.6 | FP58: 2 | FQ58: 4.27438
A59: EJEC | C59: 1.05 | D59: 0.1 | E59: 2417.85 | F59: 537.1 | G59: 0 | H59: 0 | I59: -180.1 | J59: 351.5 | K59: 0 | L59: 0 | M59: 204.4 | N59: 138.4 | O59: 75.45 | P59: 750.65 | Q59: 144.25 | R59: -27.5 | S59: 1436.6 | T59: 0.2 | U59: 0 | V59: 0 | W59: 0 | X59: 0 | Y59: 277.15 | Z59: 24.3 | AA59: 1.15 | AB59: -78.1 | AC59: 48.75 | AD59: 340.8 | AE59: 36.6 | AF59: 0 | AG59: 0 | AH59: 0 | AI59: 265.6 | AJ59: 365.8 | AK59: 0 | AL59: 0 | AM59: 0 | AN59: -27.65 | AO59: 957 | AP59: 125 | AQ59: 166.65 | AR59: -47.2 | AS59: 1.45 | AT59: 64.8 | AU59: 16.3 | AV59: 177.95 | AW59: -308.15 | AX59: -1031.25 | AY59: 184.7 | AZ59: 0 | BA59: 1.7 | BB59: 13 | BC59: 195.75 | BD59: 17.5 | BE59: 0.75 | BF59: 159 | BG59: 118.1 | BH59: 0.7 | BI59: 0 | BJ59: 0 | BK59: 0 | BL59: 0 | BM59: -4.15776 | BN59: 213.75 | BO59: -16.4 | BP59: -94.55 | BQ59: 0 | BR59: 663 | BS59: 0 | BT59: 0 | BU59: 0 | BV59: 0 | BW59: 0 | BX59: 0 | BY59: 0 | BZ59: 0 | CA59: 0.8 | CB59: 1219.85 | CC59: 888.15 | CD59: 142.05 | CE59: 215.85 | CF59: 49.9 | CG59: 0 | CH59: 0 | CI59: 0 | CJ59: 0 | CK59: 861.35 | CL59: -138.3 | CM59: 0 | CN59: 0 | CO59: 0 | CP59: 0 | CQ59: 0 | CR59: 0 | CS59: 0 | CT59: 0 | CU59: -64.85 | CV59: 73.05 | CW59: 0 | CX59: 0 | CY59: 0 | CZ59: -1.55 | DA59: -22.4 | DB59: 0 | DC59: -0.15 | DD59: 30.75 | DE59: 40.2 | DF59: -12.6 | DG59: 13.05 | DH59: 14.25 | DI59: 0 | DJ59: -7.8 | DK59: -19.3 | DL59: -34.1 | DM59: 235.5 | DN59: 41.7 | DO59: 12 | DP59: 16.675 | DQ59: 25.7 | DR59: -29.3 | DS59: 1.2 | DT59: 13.6 | DU59: 5.45 | DV59: 0 | DW59: -114.2 | DX59: 14.5 | DY59: 63.05 | DZ59: 68.5 | EA59: 36.65 | EB59: 9.4 | EC59: 90.35 | ED59: 23.65 | EE59: -102.2 | EF59: -186.45 | EG59: 4.8 | EH59: 2.1 | EI59: 62.4 | EJ59: -5.1 | EK59: 36.45 | EL59: 4.8 | EM59: 4.8 | EN59: 4.8 | EO59: 0 | EP59: 15.4 | EQ59: 143.25 | ER59: -4.8 | ES59: 161.65 | ET59: 40.2 | EU59: 95.9 | EV59: 16.15 | EW59: 14.05 | EX59: 44.3 | EY59: 0 | EZ59: 291.15 | FA59: 176.5 | FB59: 28.4 | FC59: 43.75 | FD59: 78.1 | FE59: 1.2 | FF59: 52.55 | FG59: 13466.517 | FI59: 41.194025 | FJ59: -15.7325 | FK59: 0 | FL59: 35.05 | FM59: 0 | FN59: 51.906935 | FO59: 0.15 | FP59: 49.5 | FQ59: 162.06846

Sheet DEMANDA_AREAS
B3: jueves, 20 de Marzo del 2025
B5: REPORTE DE LA DEMANDA POR ÁREAS Y SUBAREAS OPERATIVAS (MW)
B6: FECHA HORA | C6: DEMANDA | E6: AREA | H6: SUBAREAS
C7: INTERCAMBIOS INTERNACIONALES | D7: SEIN | E7: NORTE | F7: CENTRO | G7: SUR | H7: ELECTROANDES
B8: 00:30 | C8: 0 | D8: 6610.7 | E8: 1040.553 | F8: 3865.097 | G8: 1705.05 | H8: 217.923
B9: 01:00 | C9: 0 | D9: 6459 | E9: 998.889 | F9: 3760.601 | G9: 1699.51 | H9: 218.566
B10: 01:30 | C10: 0 | D10: 6485.8 | E10: 974.114 | F10: 3813.436 | G10: 1698.25 | H10: 225.354
B11: 02:00 | C11: 0 | D11: 6420.8 | E11: 984.921 | F11: 3759.879 | G11: 1676 | H11: 231.402
B12: 02:30 | C12: 0 | D12: 6342.6 | E12: 990.27 | F12: 3703.41 | G12: 1648.92 | H12: 222.532
B13: 03:00 | C13: 0 | D13: 6255.9 | E13: 978.059 | F13: 3612.101 | G13: 1665.74 | H13: 223.504
B14: 03:30 | C14: 0 | D14: 6341.3 | E14: 970.991 | F14: 3692.849 | G14: 1677.46 | H14: 215.132
B15: 04:00 | C15: 0 | D15: 6231.3 | E15: 974.901 | F15: 3573.519 | G15: 1682.88 | H15: 212.4686
B16: 04:30 | C16: 0 | D16: 6356.5 | E16: 937.731 | F16: 3731.789 | G16: 1686.98 | H16: 212.519
B17: 05:00 | C17: 0 | D17: 6375.9 | E17: 950.954 | F17: 3720.126 | G17: 1704.82 | H17: 195.532
B18: 05:30 | C18: 0 | D18: 6441.4 | E18: 985.374 | F18: 3732.386 | G18: 1723.64 | H18: 197.197
B19: 06:00 | C19: 0 | D19: 6694.2 | E19: 1016.058 | F19: 3958.662 | G19: 1719.48 | H19: 192.608
... B59: ENERGÍA | C59: 0 | D59: 175090.45 | E59: 27372.189 | F59: 104877.68 | G59: 42840.59 | H59: 4937.0268
B61: LEYENDA:
D63: Potencia recibida del Ecuador
D64: Potencia entregada al Ecuador

Sheet DEMANDA_UL
B3: jueves, 20 de Marzo del 2025
B5: POTENCIA DE LOS GRANDES USUARIOS LIBRES (MW)
B6: FECHA HORA | C6: GRANDES USUARIOS LIBRES DEL ÁREA NORTE | X6: GRANDES USUARIOS LIBRES DEL ÁREA CENTRO | BP6: GRANDES USUARIOS LIBRES DEL ÁREA SUR
C7: ARCA CONTINENTAL LINDLEY S.A. | D7: AUSTRAL GROUP S.A.A | E7: CEMENTOS PACASMAYO | F7: CORPORACIÓN PESQUERA INCA S.A.C. | G7: CREDITEX: CIA IND.TEXTIL CREDISA | H7: HIPERMERCADOS TOTTUS S.A | I7: INDUSTRIA TEXTIL PIURA | J7: MINERA BOROO MISQUICHILCA S.A. | K7: MINERA GOLD FIELDS | L7: MINERA HORIZONTE | M7: MINERA MARSA | N7: MINERA MISKY MAYO | O7: MINERA YANACOCHA | P7: OPEN PLAZA | Q7: PESQUERA DIAMANTE | R7: PETROPERU | S7: REAL PLAZA S.R.L. | T7: SIDER PERU | U7: SUPERMERCADOS PERUANOS S.A. | V7: TRUPAL S.A. | W7: UNIÓN DE CERVECERÍAS PERUANAS BACKUS Y JOHNSTON S. | X7: ACEROS AREQUIPA | Y7: ADMINISTRADORA JOCKEY PLAZA SHOPPING CENTER S.A. | Z7: ALICORP | AA7: ARCA CONTINENTAL LINDLEY S.A. | AB7: AUSTRAL GROUP S.A.A | AC7: COMPAÑIA MINERA CONDESTABLE | AD7: CORPORACIÓN PESQUERA INCA S.A.C. | AE7: CREDITEX: CIA IND.TEXTIL CREDISA | AF7: FUNDICION CHILCA S.A. | AG7: HIPERMERCADOS TOTTUS S.A | AH7: INMOBILIARIA KANPU S.A. | AI7: INMUEBLES PANAMERICANA S.A. | AJ7: KIMBERLY-CLARK PERU | AK7: LECHE GLORIA S.A. | AL7: MALL AVENTURA S.A. | AM7: MARCOBRE S.A.C. | AN7: MINERA ANTAMINA | AO7: MINERA ARES | AP7: MINERA BUENAVENTURA | AQ7: MINERA CHINALCO PERÚ S.A. | AR7: MINERA SHOUXIN PERU S.A. | AS7: MINERA VOLCAN | AT7: MINSUR | AU7: MOLYCOP-ADESUR | AV7: NEXA RESOURCES CAJAMARQUILLA S.A. | AW7: NEXA RESOURCES PERÚ S.A.A. | AX7: OPEN PLAZA | AY7: OPP FILM | AZ7: OWENS-ILLINOIS PERÚ S.A. | BA7: PAPELERA NACIONAL S.A. | BB7: PESQUERA DIAMANTE | BC7: QUIMPAC S.A. | BD7: REAL PLAZA S.R.L. | BE7: REFINERIA LA PAMPILLA S.A.A | BF7: SAGA FALABELLA | BG7: SAN MIGUEL INDUSTRIAS PET S.A. | BH7: SHOUGANG HIERRO PERU | BI7: SOFTYS PERU S.A.C. | BJ7: SUPERMERCADOS PERUANOS S.A. | BK7: TEJIDOS SAN JACINTO | BL7: TREN URBANO DE LIMA S.A. | BM7: TRUPAL S.A. | BN7: UNACEM PERU S.A. | BO7: UNIÓN DE CERVECERÍAS PERUANAS BACKUS Y JOHNSTON S. | BP7: ANGLO AMERICAN QUELLAVECO S.A. | BQ7: ARCA CONTINENTAL LINDLEY S.A. | BR7: CAL & CEMENTO SUR S.A. | BS7: COMPAÑIA MINERA ANTAPACCAY S.A. | BT7: COMPAÑÍA MINERA CHUNGAR SAC | BU7: COMPAÑIA MINERA SAN IGNACIO DE MOROCOCHA S.A.A. | BV7: EL BROCAL .S.A. | BW7: EMPRESA ADMINISTRADORA CERRO S.A.C. | BX7: EMPRESA MINERA LOS QUENUALES S.A.C. | BY7: HIPERMERCADOS TOTTUS S.A | BZ7: HUDBAY PERU S.A.C. | CA7: INDUSTRIA CACHIMAYO | CB7: MALL AVENTURA S.A. | CC7: MINERA ARES | CD7: MINERA BUENAVENTURA | CE7: MINERA CERRO VERDE | CF7: MINERA CORONA | CG7: MINERA LAS BAMBAS S.A. | CH7: MINERA VOLCAN | CI7: MINSUR | CJ7: MOLYCOP-ADESUR | CK7: NEXA RESOURCES PERÚ S.A.A. | CL7: OXIDOS DE PASCO S.A.C. | CM7: PESQUERA DIAMANTE | CN7: REAL PLAZA S.R.L. | CO7: SOBREANDES S.A.C. | CP7: SOUTHERN PERU CC | CQ7: SUPERMERCADOS PERUANOS S.A. | CR7: UNACEM PERU S.A. | CS7: UNIÓN DE CERVECERÍAS PERUANAS BACKUS Y JOHNSTON S. | CT7: YURA
B8: 00:30 | E8: 42.57943 | G8: 4.039 | J8: 19.356 | K8: 27.38185 | L8: 11.58 | M8: 14.6511 | N8: 9.99 | O8: 34.92 | R8: 52.386 | T8: 45.4968 | V8: 8.5 | X8: 123.37573 | Z8: 9.98216 | AC8: 14.81 | AE8: 4.382 | AF8: 2.5 | AH8: 4.7553 | AJ8: 5.33786 | AK8: 0.15 | AL8: 1.1039 | AN8: 134.00236 | AO8: 29.2981 | AP8: 0.81 | AQ8: 113.9245 | AS8: 38.28961 | AT8: 34.27295 | AV8: 190.35 | AW8: 33.69048 | AY8: 2.95425 | BA8: 1.1 | BC8: 73.7917 | BE8: 19.6 | BK8: 5.81876 | BM8: 0 | BN8: 53.16 | BO8: 1.78 | BP8: 143.55779 | BR8: 5.609 | BS8: 133.03445 | BT8: 7.46327 | BV8: 31.2989 | BW8: 3.85819 | BX8: 16.71 | BZ8: 91.0566 | CA8: 22.69816 | CB8: 0.3864 | CC8: 0.767 | CD8: 23.3211 | CE8: 459.36532 | CG8: 151.5405 | CH8: 18.82387 | CK8: 14.4671 | CL8: 1.58234 | CO8: 15.84777 | CP8: 217.27 | CR8: 36.991 | CS8: 2.33021 | CT8: 9.0469
B9: 01:00 | E9: 42.44144 | G9: 4.034 | J9: 18.8903 | K9: 27.21551 | L9: 10.993 | M9: 14.6382 | N9: 10.12 | O9: 35.112 | R9: 52.187 | T9: 38.5066 | V9: 8.6 | X9: 142.16433 | Z9: 10.25132 | AC9: 16.31 | AE9: 4.504 | AF9: 2.7 | AH9: 5.1639 | AJ9: 5.33431 | AK9: 0.15 | AL9: 1.014 | AN9: 133.90217 | AO9: 29.4289 | AP9: 0.7 | AQ9: 115.9647 | AS9: 38.39997 | AT9: 34.2591 | AV9: 189.616 | AW9: 34.11756 | AY9: 3.057 | BA9: 1.4 | BC9: 73.88386 | BE9: 19.6 | BK9: 5.70063 | BM9: 3.987 | BN9: 53.31 | BO9: 2.18 | BP9: 143.82695 | BR9: 5.63185 | BS9: 134.50322 | BT9: 7.50413 | BV9: 31.5377 | BW9: 3.96348 | BX9: 16.8 | BZ9: 90.3899 | CA9: 22.56127 | CB9: 0.3561 | CC9: 0.719 | CD9: 22.27295 | CE9: 457.84666 | CG9: 156.2284 | CH9: 19.20465 | CK9: 15.1307 | CL9: 1.64302 | CO9: 15.67105 | CP9: 215.89 | CR9: 34.723 | CS9: 2.23997 | CT9: 9.0911
B10: 01:30 | E10: 42.71503 | G10: 4.018 | J10: 18.9994 | K10: 27.33787 | L10: 11.342 | M10: 14.5906 | N10: 10.55 | O10: 35.002 | R10: 52.452 | T10: 35.7855 | V10: 9 | X10: 150.5582 | Z10: 10.11001 | AC10: 16.05 | AE10: 4.483 | AF10: 4.9 | AH10: 5.3473 | AJ10: 5.31128 | AK10: 0.15 | AL10: 0.9491 | AN10: 133.68421 | AO10: 29.9068 | AP10: 0.64 | AQ10: 116.0354 | AS10: 38.3643 | AT10: 33.6418 | AV10: 189.6544 | AW10: 34.96693 | AY10: 3.10327 | BA10: 1.7 | BC10: 73.81368 | BE10: 19.6 | BK10: 5.82829 | BM10: 3.995 | BN10: 51.68 | BO10: 2.21 | BP10: 142.65633 | BR10: 5.80764 | BS10: 135.73691 | BT10: 7.40754 | BV10: 32.8389 | BW10: 4.0073 | BX10: 16.69 | BZ10: 90.3689 | CA10: 22.56936 | CB10: 0.3464 | CC10: 0.734 | CD10: 27.72493 | CE10: 460.81619 | CG10: 155.1616 | CH10: 19.1882 | CK10: 15.0868 | CL10: 1.6198 | CO10: 14.95984 | CP10: 215.24 | CR10: 34.701 | CS10: 1.90832 | CT10: 9.19397
B11: 02:00 | E11: 41.7821 | G11: 3.999 | J11: 19.035 | K11: 27.21681 | L11: 11.86 | M11: 14.1941 | N11: 10.42 | O11: 34.288 | R11: 52.186 | T11: 40.1584 | V11: 9.3 | X11: 139.59184 | Z11: 9.73734 | AC11: 16.25 | AE11: 4.485 | AF11: 5.7 | AH11: 5.3743 | AJ11: 5.27359 | AK11: 0.15 | AL11: 0.9118 | AN11: 134.93873 | AO11: 29.0591 | AP11: 0.44 | AQ11: 115.6914 | AS11: 38.16087 | AT11: 33.75124 | AV11: 189.5786 | AW11: 34.43343 | AY11: 3.13296 | BA11: 2.5 | BC11: 73.96877 | BE11: 19.6 | BK11: 5.76966 | BM11: 3.989 | BN11: 51.04 | BO11: 2.27 | BP11: 144.16488 | BR11: 5.621 | BS11: 134.50224 | BT11: 7.79575 | BV11: 32.47 | BW11: 3.7307 | BX11: 16.89 | BZ11: 91.3687 | CA11: 22.72099 | CB11: 0.3208 | CC11: 0.737 | CD11: 28.98548 | CE11: 463.18409 | CG11: 154.1931 | CH11: 19.20654 | CK11: 14.8781 | CL11: 1.60029 | CO11: 15.63127 | CP11: 208.74 | CR11: 34.646 | CS11: 2.14213 | CT11: 9.39324
B12: 02:30 | E12: 41.66987 | G12: 4.125 | J12: 20.3247 | K12: 26.27909 | L12: 12.185 | M12: 13.9887 | N12: 10.21 | O12: 34.388 | R12: 52.188 | T12: 41.1404 | V12: 9.5 | X12: 97.08767 | Z12: 9.77911 | AC12: 15.88 | AE12: 4.265 | AF12: 2.8 | AH12: 2.144 | AJ12: 5.22184 | AK12: 0.15 | AL12: 0.9099 | AN12: 137.45932 | AO12: 29.7611 | AP12: 0.41 | AQ12: 115.5838 | AS12: 37.64154 | AT12: 33.67225 | AV12: 184.3942 | AW12: 34.62489 | AY12: 3.14614 | BA12: 2.4 | BC12: 73.99874 | BE12: 19.6 | BK12: 5.76368 | BM12: 3.991 | BN12: 51.7 | BO12: 2.25 | BP12: 146.84743 | BR12: 5.64638 | BS12: 133.28186 | BT12: 7.89353 | BV12: 30.8045 | BW12: 3.87202 | BX12: 17.47 | BZ12: 90.7038 | CA12: 22.73628 | CB12: 0.3187 | CC12: 0.726 | CD12: 29.46755 | CE12: 457.87856 | CG12: 151.6917 | CH12: 19.5574 | CK12: 14.99 | CL12: 1.63571 | CO12: 15.92783 | CP12: 193.6 | CR12: 34.412 | CS12: 2.26231 | CT12: 10.30109
B13: 03:00 | E13: 39.42949 | G13: 4.153 | J13: 19.2995 | K13: 26.3273 | L13: 12.902 | M13: 14.5513 | N13: 10.37 | O13: 34.174 | R13: 51.957 | T13: 40.9877 | V13: 9.7 | X13: 135.06966 | Z13: 9.96764 | AC13: 15.11 | AE13: 4.317 | AF13: 0.9 | AH13: 3.9555 | AJ13: 4.81592 | AK13: 0.15 | AL13: 0.8522 | AN13: 136.11164 | AO13: 30.4963 | AP13: 0.67 | AQ13: 113.8266 | AS13: 37.59506 | AT13: 32.87832 | AV13: 190.699 | AW13: 35.49774 | AY13: 3.14857 | BA13: 2.4 | BC13: 73.89709 | BE13: 19.6 | BK13: 5.75629 | BM13: 3.988 | BN13: 54.55 | BO13: 2.22 | BP13: 145.38957 | BR13: 5.61285 | BS13: 130.36567 | BT13: 7.06901 | BV13: 30.977 | BW13: 3.96593 | BX13: 17.22 | BZ13: 90.5069 | CA13: 22.76702 | CB13: 0.3065 | CC13: 0.728 | CD13: 30.2742 | CE13: 460.15676 | CG13: 154.9173 | CH13: 19.53961 | CK13: 15.0415 | CL13: 1.72615 | CO13: 16.30326 | CP13: 204.31 | CR13: 34.323 | CS13: 2.24445 | CT13: 10.24158
B14: 03:30 | E14: 39.51917 | G14: 4.095 | J14: 19.7502 | K14: 26.96294 | L14: 13.085 | M14: 14.5987 | N14: 9.75 | O14: 34.49 | R14: 52.275 | T14: 43.6907 | V14: 9.8 | X14: 145.14931 | Z14: 9.78496 | AC14: 15.27 | AE14: 4.233 | AF14: 2.3 | AH14: 4.1712 | AJ14: 5.05719 | AK14: 0.15 | AL14: 0.8353 | AN14: 135.36763 | AO14: 29.7264 | AP14: 0.48 | AQ14: 112.9093 | AS14: 38.47093 | AT14: 31.98349 | AV14: 190.8568 | AW14: 35.34704 | AY14: 3.16864 | BA14: 2.4 | BC14: 73.94019 | BE14: 19.6 | BK14: 5.71352 | BM14: 3.989 | BN14: 53.38 | BO14: 2.17 | BP14: 144.69742 | BR14: 5.83807 | BS14: 132.18334 | BT14: 5.21845 | BV14: 31.6888 | BW14: 4.02736 | BX14: 17.33 | BZ14: 89.9607 | CA14: 22.78941 | CB14: 0.294 | CC14: 0.725 | CD14: 29.89391 | CE14: 462.56003 | CG14: 153.6687 | CH14: 19.28471 | CK14: 14.5914 | CL14: 1.65363 | CO14: 16.26914 | CP14: 208.08 | CR14: 32.365 | CS14: 2.316 | CT14: 10.32443
B15: 04:00 | E15: 39.31151 | G15: 3.807 | J15: 20.0614 | K15: 27.22582 | L15: 12.67 | M15: 14.4107 | N15: 9.98 | O15: 34.232 | R15: 52.312 | T15: 35.969 | V15: 9.9 | X15: 128.39323 | Z15: 9.69715 | AC15: 15.02 | AE15: 4.177 | AF15: 1.4 | AH15: 4.1499 | AJ15: 5.19055 | AK15: 0.15 | AL15: 0.8319 | AN15: 136.5341 | AO15: 29.0757 | AP15: 0.18 | AQ15: 113.786 | AS15: 38.53835 | AT15: 31.60801 | AV15: 190.909 | AW15: 35.15616 | AY15: 3.19112 | BA15: 2.5 | BC15: 73.92246 | BE15: 19.6 | BK15: 5.68927 | BM15: 3.989 | BN15: 53.46 | BO15: 2.1 | BP15: 147.55525 | BR15: 5.92155 | BS15: 131.86755 | BT15: 5.01051 | BV15: 31.9245 | BW15: 3.88656 | BX15: 16.93 | BZ15: 89.9893 | CA15: 22.75413 | CB15: 0.2897 | CC15: 0.699 | CD15: 29.17933 | CE15: 456.64787 | CG15: 155.6921 | CH15: 19.18203 | CK15: 14.5481 | CL15: 2.74823 | CO15: 16.25287 | CP15: 213.28 | CR15: 31.036 | CS15: 2.00584 | CT15: 13.6809
B16: 04:30 | E16: 38.65414 | G16: 4.13 | J16: 20.2776 | K16: 27.50254 | L16: 12.174 | M16: 14.7225 | N16: 9.98 | O16: 34.36 | R16: 52.125 | T16: 37.0572 | V16: 9.6 | X16: 118.92566 | Z16: 9.89658 | AC16: 13.92 | AE16: 4.204 | AF16: 1.7 | AH16: 2.0866 | AJ16: 5.28152 | AK16: 0.15 | AL16: 0.8295 | AN16: 138.74762 | AO16: 29.2351 | AP16: 1.65 | AQ16: 111.7964 | AS16: 37.36509 | AT16: 31.27071 | AV16: 190.1494 | AW16: 34.42046 | AY16: 3.22884 | BA16: 2.5 | BC16: 73.6232 | BE16: 19.6 | BK16: 5.78093 | BM16: 3.989 | BN16: 54.75 | BO16: 2.17 | BP16: 148.11925 | BR16: 5.86856 | BS16: 133.49138 | BT16: 4.86686 | BV16: 31.4547 | BW16: 3.90366 | BX16: 16.84 | BZ16: 90.677 | CA16: 22.71854 | CB16: 0.2765 | CC16: 0.709 | CD16: 29.12062 | CE16: 457.6905 | CG16: 151.2257 | CH16: 19.07783 | CK16: 14.2743 | CL16: 3.55855 | CO16: 15.88603 | CP16: 211.34 | CR16: 30.704 | CS16: 2.07233 | CT16: 13.05556
B17: 05:00 | E17: 38.33428 | G17: 4.058 | J17: 20.3336 | K17: 27.63349 | L17: 11.722 | M17: 14.9253 | N17: 9.87 | O17: 35.128 | R17: 52.33 | T17: 24.4677 | V17: 9.4 | X17: 120.80202 | Z17: 10.14543 | AC17: 14.4 | AE17: 4.346 | AF17: 5 | AH17: 2.0699 | AJ17: 5.03627 | AK17: 0.15 | AL17: 0.8083 | AN17: 141.95875 | AO17: 29.3013 | AP17: 2.1 | AQ17: 110.5616 | AS17: 37.21698 | AT17: 31.66199 | AV17: 190.4167 | AW17: 34.54563 | AY17: 3.29311 | BA17: 2.4 | BC17: 73.60492 | BE17: 19.6 | BK17: 5.76429 | BM17: 3.989 | BN17: 55.45 | BO17: 2.33 | BP17: 150.0293 | BR17: 5.77224 | BS17: 132.27259 | BT17: 5.36358 | BV17: 29.7838 | BW17: 4.37541 | BX17: 16.02 | BZ17: 91.1922 | CA17: 22.73322 | CB17: 0.2743 | CC17: 0.71 | CD17: 27.62726 | CE17: 460.37506 | CG17: 152.9344 | CH17: 19.22574 | CK17: 13.6981 | CL17: 3.86608 | CO17: 15.5971 | CP17: 212.41 | CR17: 30.881 | CS17: 2.2018 | CT17: 14.33375
B18: 05:30 | E18: 38.6215 | G18: 4.042 | J18: 19.4769 | K18: 27.84416 | L18: 11.254 | M18: 15.2593 | N18: 10.28 | O18: 35.282 | R18: 52.499 | T18: 15.7744 | V18: 9 | X18: 147.50528 | Z18: 10.03076 | AC18: 14.84 | AE18: 4.421 | AF18: 4.6 | AH18: 3.6572 | AJ18: 5.08865 | AK18: 0.15 | AL18: 0.8057 | AN18: 139.52104 | AO18: 28.14 | AP18: 1.93 | AQ18: 108.453 | AS18: 36.57081 | AT18: 32.28079 | AV18: 190.7546 | AW18: 33.86819 | AY18: 3.21379 | BA18: 2.4 | BC18: 73.6544 | BE18: 19.6 | BK18: 5.65077 | BM18: 3.989 | BN18: 55.06 | BO18: 2.38 | BP18: 148.74236 | BR18: 5.758 | BS18: 134.11029 | BT18: 5.54839 | BV18: 29.4058 | BW18: 3.85894 | BX18: 15.44 | BZ18: 92.4332 | CA18: 22.77024 | CB18: 0.2676 | CC18: 0.648 | CD18: 27.67093 | CE18: 464.5328 | CG18: 149.2132 | CH18: 19.3667 | CK18: 14.3982 | CL18: 4.01372 | CO18: 14.22696 | CP18: 215.21 | CR18: 31.182 | CS18: 2.30869 | CT18: 14.81462
B19: 06:00 | E19: 39.00278 | G19: 4.083 | J19: 19.6223 | K19: 28.1935 | L19: 10.102 | M19: 15.7902 | N19: 10.31 | O19: 35.972 | R19: 52.129 | T19: 11.3201 | V19: 8 | X19: 142.68614 | Z19: 10.20501 | AC19: 15.65 | AE19: 4.323 | AF19: 2.4 | AH19: 1.7369 | AJ19: 5.10208 | AK19: 0.15 | AL19: 0.8503 | AN19: 140.08701 | AO19: 28.3968 | AP19: 1.54 | AQ19: 110.9772 | AS19: 35.42544 | AT19: 31.9313 | AV19: 191.3184 | AW19: 32.19275 | AY19: 3.26716 | BA19: 2.4 | BC19: 73.45971 | BE19: 19.6 | BK19: 5.69738 | BM19: 3.988 | BN19: 55.43 | BO19: 2.33 | BP19: 148.36128 | BR19: 5.38632 | BS19: 134.30048 | BT19: 5.24214 | BV19: 27.9428 | BW19: 3.65085 | BX19: 15.36 | BZ19: 91.3841 | CA19: 22.76685 | CB19: 0.2635 | CC19: 0.732 | CD19: 26.94623 | CE19: 462.59653 | CG19: 142.2701 | CH19: 19.05837 | CK19: 14.2168 | CL19: 3.95688 | CO19: 13.38044 | CP19: 217.97 | CR19: 28.276 | CS19: 2.30018 | CT19: 13.85142
... B55: 00:00 | E55: 24.30978 | G55: 0 | J55: 18.4852 | K55: 25.42907 | L55: 12.645 | M55: 14.3753 | N55: 10.52 | O55: 33.128 | R55: 51.964 | T55: 32.4187 | V55: 8.1 | X55: 157.79936 | Z55: 9.98471 | AC55: 13.68 | AE55: 0 | AF55: 3.7 | AH55: 5.3538 | AJ55: 5.27586 | AK55: 0.15 | AL55: 1.4517 | AN55: 134.77697 | AO55: 29.8595 | AP55: 0.83 | AQ55: 112.9681 | AS55: 36.8908 | AT55: 33.74623 | AV55: 152.7559 | AW55: 34.70795 | AY55: 3.32485 | BA55: 2.5 | BC55: 72.1632 | BE55: 19.1 | BK55: 5.79023 | BM55: 3.988 | BN55: 55.54 | BO55: 2.22 | BP55: 144.38396 | BR55: 5.91365 | BS55: 133.2733 | BT55: 10.39366 | BV55: 25.8704 | BW55: 3.83695 | BX55: 17.14 | BZ55: 90.0708 | CA55: 22.42717 | CB55: 0.4081 | CC55: 0.691 | CD55: 30.52958 | CE55: 453.24875 | CG55: 148.6195 | CH55: 19.09398 | CK55: 17.6575 | CL55: 4.70405 | CO55: 16.39682 | CP55: 246.39 | CR55: 20.875 | CS55: 2.1893 | CT55: 15.03845
B56: MWh | C56: 0 | D56: 0 | E56: 717.99726 | F56: 0 | G56: 93.308 | H56: 0 | I56: 0 | J56: 480.8915 | K56: 651.48412 | L56: 280.2125 | M56: 318.52005 | N56: 242.93 | O56: 803.072 | P56: 0 | Q56: 0 | R56: 1249.1095 | S56: 0 | T56: 711.38635 | U56: 0 | V56: 214.1 | W56: 0 | X56: 2664.1148 | Y56: 0 | Z56: 239.11379 | AA56: 0 | AB56: 0 | AC56: 370.55 | AD56: 0 | AE56: 104.2775 | AF56: 62.15 | AG56: 0 | AH56: 60.71235 | AI56: 0 | AJ56: 118.96792 | AK56: 3.6 | AL56: 71.4269 | AM56: 0 | AN56: 3216.8009 | AO56: 692.9589 | AP56: 18.01 | AQ56: 2310.3663 | AR56: 0 | AS56: 859.50081 | AT56: 759.84038 | AU56: 0 | AV56: 3894.1382 | AW56: 783.22051 | AX56: 0 | AY56: 75.719515 | AZ56: 0 | BA56: 58.7 | BB56: 0 | BC56: 1527.1995 | BD56: 0 | BE56: 458.45 | BF56: 0 | BG56: 0 | BH56: 0 | BI56: 0 | BJ56: 0 | BK56: 136.68998 | BL56: 0 | BM56: 93.712 | BN56: 1026.76 | BO56: 56.22 | BP56: 3501.4594 | BQ56: 0 | BR56: 138.65921 | BS56: 3192.3081 | BT56: 175.01995 | BU56: 0 | BV56: 743.471 | BW56: 93.388145 | BX56: 383.39 | BY56: 0 | BZ56: 2148.7834 | CA56: 464.86735 | CB56: 20.75955 | CC56: 17.4665 | CD56: 706.58345 | CE56: 10863.995 | CF56: 0 | CG56: 3464.6836 | CH56: 448.75293 | CI56: 0 | CJ56: 0 | CK56: 354.76405 | CL56: 93.711355 | CM56: 0 | CN56: 0 | CO56: 350.47683 | CP56: 5358.695 | CQ56: 0 | CR56: 626.2235 | CS56: 49.29486 | CT56: 211.09498
B59: Nota :
B60: Información proporcionada por la empresas
C62: DATOS ESTIMADOS
C64: SIN DATOS

Sheet TIPO_RECURSO
B3: jueves, 20 de Marzo del 2025
B5: REPORTE POTENCIA GENERADA POR TIPO DE RECURSO
B6: HORA | C6: H. PASADA | D6: H. REGULACION | E6: GAS DE CAMISEA | F6: GAS DE MALACAS | G6: GAS AGUAYTÍA | H6: DIESEL | I6: RESIDUAL | J6: NAFTA+GAS DE REFINERIA | K6: FLEXIGAS+GAS DE REFINERIA | L6: BAGAZO | M6: BIOGAS | N6: SOLAR | O6: EOLICA | P6: TOTAL | U6: EMPRESA | V6: CENTRAL | W6: HIDROELECTRICA DE PASADA | X6: HIDROELECTRICA DE REGULACION
B7: 00:30 | C7: 1134.6 | D7: 3313.3 | E7: 1623.2 | F7: 24.9 | H7: 0 | J7: =DESPACHO_EJECUTADO!FA11+DESPACHO_EJECUTADO!FB11 -> 68.3 | L7: 32.3 | M7: 11.9 | N7: 0 | O7: 402.2 | P7: =SUM(C7:O7) -> 6610.7 | U7: ANDEAN POWER S.A.C. | V7: C.H. CARHUAC | W7: 487.95
B8: 01:00 | C8: 1140.3 | D8: 3183.6 | E8: 1592.1 | F8: 24.9 | H8: 0 | J8: =DESPACHO_EJECUTADO!FA12+DESPACHO_EJECUTADO!FB12 -> 68.5 | L8: 31.7 | M8: 11.9 | N8: 0 | O8: 406 | P8: =SUM(C8:O8) -> 6459 | U8: ASOCIACIÓN SANTA LUCIA DE CHACAS | V8: C.H. HUALLIN | W8: 57.65
B9: 01:30 | C9: 1155.5 | D9: 3177.1 | E9: 1612.9 | F9: 24.8 | H9: 0 | J9: =DESPACHO_EJECUTADO!FA13+DESPACHO_EJECUTADO!FB13 -> 68.8 | L9: 32 | M9: 12.1 | N9: 0 | O9: 402.6 | P9: =SUM(C9:O9) -> 6485.8 | U9: ATRIA ENERGIA S.A.C. | V9: C.H. PURMACANA | W9: 5.2
B10: 02:00 | C10: 1125.3 | D10: 3125.5 | E10: 1626.2 | F10: 24.8 | H10: 0 | J10: =DESPACHO_EJECUTADO!FA14+DESPACHO_EJECUTADO!FB14 -> 67.1 | L10: 32.4 | M10: 12.1 | N10: 0 | O10: 407.4 | P10: =SUM(C10:O10) -> 6420.8 | U10: CELEPSA | V10: C.H. EL PLATANAL | X10: 5344
B11: 02:30 | C11: 1069.3 | D11: 3181.1 | E11: 1594.3 | F11: 25.5 | H11: 0 | J11: =DESPACHO_EJECUTADO!FA15+DESPACHO_EJECUTADO!FB15 -> 68 | L11: 31.4 | M11: 12.1 | N11: 0 | O11: 360.9 | P11: =SUM(C11:O11) -> 6342.6 | U11: CELEPSA RENOVABLES S.R.L. | V11: C.H. MARAÑON | W11: 472.75
B12: 03:00 | C12: 1060.9 | D12: 3114.3 | E12: 1582.5 | F12: 25.4 | H12: 0 | J12: =DESPACHO_EJECUTADO!FA16+DESPACHO_EJECUTADO!FB16 -> 68 | L12: 32 | M12: 12.1 | N12: 0 | O12: 360.7 | P12: =SUM(C12:O12) -> 6255.9 | U12: CENTRALES SANTA ROSA S.A.C. | V12: C.H. SANTA ROSA I | W12: 4.05
B13: 03:30 | C13: 1046.9 | D13: 3243 | E13: 1607 | F13: 25.1 | H13: 0 | J13: =DESPACHO_EJECUTADO!FA17+DESPACHO_EJECUTADO!FB17 -> 67.3 | L13: 32.2 | M13: 12.1 | N13: 0 | O13: 307.7 | P13: =SUM(C13:O13) -> 6341.3 | V13: C.H. SANTA ROSA II | W13: 14.3
B14: 04:00 | C14: 1075.9 | D14: 3149.2 | E14: 1587.8 | F14: 0 | H14: 0 | J14: =DESPACHO_EJECUTADO!FA18+DESPACHO_EJECUTADO!FB18 -> 67.4 | L14: 31.5 | M14: 12.1 | N14: 0 | O14: 307.4 | P14: =SUM(C14:O14) -> 6231.3 | U14: CHINANGO S.A.C. | V14: C.H. CHIMAY | X14: 3303.4
B15: 04:30 | C15: 1074.7 | D15: 3263.1 | E15: 1602.7 | F15: 0 | H15: 0 | J15: =DESPACHO_EJECUTADO!FA19+DESPACHO_EJECUTADO!FB19 -> 67.5 | L15: 31.8 | M15: 12.1 | N15: 0 | O15: 304.6 | P15: =SUM(C15:O15) -> 6356.5 | V15: C.H. YANANGO | W15: 632.2
B16: 05:00 | C16: 1068.5 | D16: 3288.3 | E16: 1585.5 | F16: 0 | H16: 0 | J16: =DESPACHO_EJECUTADO!FA20+DESPACHO_EJECUTADO!FB20 -> 67 | L16: 32 | M16: 12.1 | N16: 0 | O16: 322.5 | P16: =SUM(C16:O16) -> 6375.9 | U16: EGASA | V16: C.H. CHARCANI III | W16: 154.4
B17: 05:30 | C17: 1091 | D17: 3194 | E17: 1683.2 | F17: 0 | H17: 0 | J17: =DESPACHO_EJECUTADO!FA21+DESPACHO_EJECUTADO!FB21 -> 67.2 | L17: 31.8 | M17: 12.1 | N17: 0 | O17: 362.1 | P17: =SUM(C17:O17) -> 6441.4 | V17: C.H. CHARCANI IV | X17: 241.4
B18: 06:00 | C18: 1112 | D18: 3400.7 | E18: 1642.4 | F18: 0 | H18: 0 | J18: =DESPACHO_EJECUTADO!FA22+DESPACHO_EJECUTADO!FB22 -> 67.5 | L18: 32.3 | M18: 12.1 | N18: 6.6 | O18: 420.6 | P18: =SUM(C18:O18) -> 6694.2 | V18: C.H. CHARCANI V | X18: 3444.35
B19: 06:30 | C19: 1107.1 | D19: 3444.7 | E19: 1666.6 | F19: 0 | H19: 0 | J19: =DESPACHO_EJECUTADO!FA23+DESPACHO_EJECUTADO!FB23 -> 67.5 | L19: 32 | M19: 12.1 | N19: 61.7 | O19: 427.4 | P19: =SUM(C19:O19) -> 6819.1 | V19: C.H. CHARCANI VI | X19: 211.85
B20: 07:00 | C20: 1057 | D20: 3318.8 | E20: 1693.8 | F20: 0 | H20: 0 | J20: =DESPACHO_EJECUTADO!FA24+DESPACHO_EJECUTADO!FB24 -> 67.6 | L20: 31.9 | M20: 12.2 | N20: 214 | O20: 430.7 | P20: =SUM(C20:O20) -> 6826 | U20: EGEJUNIN | V20: C.H. HUASAHUASI I | W20: 475.3
B21: 07:30 | C21: 1063.3 | D21: 3394.4 | E21: 1738.5 | F21: 0 | H21: 0 | J21: =DESPACHO_EJECUTADO!FA25+DESPACHO_EJECUTADO!FB25 -> 67.8 | L21: 32.2 | M21: 12.2 | N21: 195.6 | O21: 434.1 | P21: =SUM(C21:O21) -> 6938.1 | V21: C.H. RUNATULLO II | W21: 482.7
B22: 08:00 | C22: 1067.9 | D22: 3466.8 | E22: 1620.1 | F22: 0 | H22: 0 | J22: =DESPACHO_EJECUTADO!FA26+DESPACHO_EJECUTADO!FB26 -> 67.8 | L22: 31.9 | M22: 12.2 | N22: 330.6 | O22: 462.9 | P22: =SUM(C22:O22) -> 7060.2 | V22: C.H. RUNATULLO III | W22: 486.7
B23: 08:30 | C23: 1071.8 | D23: 3457.5 | E23: 1712.7 | F23: 0 | H23: 0 | J23: =DESPACHO_EJECUTADO!FA27+DESPACHO_EJECUTADO!FB27 -> 68.5 | L23: 32.1 | M23: 12.2 | N23: 404.8 | O23: 502.4 | P23: =SUM(C23:O23) -> 7262 | V23: C.H. SANTA CRUZ I | W23: 308.6
B24: 09:00 | C24: 1067.4 | D24: 3449.4 | E24: 1912.9 | F24: 0 | H24: 0 | J24: =DESPACHO_EJECUTADO!FA28+DESPACHO_EJECUTADO!FB28 -> 68.8 | L24: 31.7 | M24: 12.2 | N24: 406.4 | O24: 533.8 | P24: =SUM(C24:O24) -> 7482.6 | U24: EGEMSA | V24: C.H. MACHUPICCHU | W24: 3937.45
B25: 09:30 | C25: 1061.2 | D25: 3434.7 | E25: 2058.8 | F25: 0 | H25: 0 | J25: =DESPACHO_EJECUTADO!FA29+DESPACHO_EJECUTADO!FB29 -> 67.7 | L25: 31.5 | M25: 12.2 | N25: 424.7 | O25: 580 | P25: =SUM(C25:O25) -> 7670.8 | U25: EGESUR | V25: C.H. ARICOTA I | X25: 177.45
B26: 10:00 | C26: 1066.7 | D26: 3488.7 | E26: 2085.2 | F26: 0 | H26: 0 | J26: =DESPACHO_EJECUTADO!FA30+DESPACHO_EJECUTADO!FB30 -> 68.1 | L26: 32.1 | M26: 12.1 | N26: 435 | O26: 639.6 | P26: =SUM(C26:O26) -> 7827.5 | V26: C.H. ARICOTA II | X26: 72.85
B27: 10:30 | C27: 1072.7 | D27: 3528.2 | E27: 2119.1 | F27: 0 | H27: 0 | J27: =DESPACHO_EJECUTADO!FA31+DESPACHO_EJECUTADO!FB31 -> 68.3 | L27: 32 | M27: 11.9 | N27: 405.6 | O27: 632.3 | P27: =SUM(C27:O27) -> 7870.1 | U27: ELECTRICA YANAPAMPA SAC | V27: C.H. YANAPAMPA | W27: 78.55
B28: 11:00 | C28: 1061.4 | D28: 3597.2 | E28: 2169.1 | F28: 0 | H28: 0 | J28: =DESPACHO_EJECUTADO!FA32+DESPACHO_EJECUTADO!FB32 -> 69 | L28: 32.7 | M28: 11.9 | N28: 430.5 | O28: 630.9 | P28: =SUM(C28:O28) -> 8002.7 | U28: ELECTROPERU | V28: C.H. MANTARO | X28: 15035
B29: 11:30 | C29: 1055.3 | D29: 3600.2 | E29: 2149.1 | F29: 0 | H29: 0 | J29: =DESPACHO_EJECUTADO!FA33+DESPACHO_EJECUTADO!FB33 -> 68.8 | L29: 32.5 | M29: 11.9 | N29: 466.5 | O29: 650 | P29: =SUM(C29:O29) -> 8034.3 | V29: C.H. RESTITUCION | W29: 4432.15
B30: 12:00 | C30: 1055.5 | D30: 3585.1 | E30: 2158.9 | F30: 0 | H30: 0 | J30: =DESPACHO_EJECUTADO!FA34+DESPACHO_EJECUTADO!FB34 -> 68.5 | L30: 31.1 | M30: 11.7 | N30: 412.7 | O30: 681.7 | P30: =SUM(C30:O30) -> 8005.2 | U30: EMPRESA DE GENERACION ELECTRICA CANCHAYLLO SAC | V30: C.H. CANCHAYLLO | W30: 123.2
B31: 12:30 | C31: 1054 | D31: 3434.3 | E31: 2094.1 | F31: 0 | H31: 0 | J31: =DESPACHO_EJECUTADO!FA35+DESPACHO_EJECUTADO!FB35 -> 68.6 | L31: 30.9 | M31: 11.6 | N31: 415.5 | O31: 731.9 | P31: =SUM(C31:O31) -> 7840.9 | U31: EMPRESA DE GENERACION ELECTRICA RIO BAÑOS S.A.C. | V31: C.H. RUCUY | W31: 478.5
B32: 13:00 | C32: 1128.9 | D32: 3614.8 | E32: 1774.6 | F32: 0 | H32: 0 | J32: =DESPACHO_EJECUTADO!FA36+DESPACHO_EJECUTADO!FB36 -> 68.7 | L32: 31.9 | M32: 11.6 | N32: 456.6 | O32: 729.9 | P32: =SUM(C32:O32) -> 7817 | U32: EMPRESA DE GENERACION ELECTRICA SANTA ANA S.A.C. | V32: C.H. RENOVANDES H1 | W32: 484.85
B33: 13:30 | C33: 1120.9 | D33: 3589.6 | E33: 1847.5 | F33: 0 | H33: 0 | J33: =DESPACHO_EJECUTADO!FA37+DESPACHO_EJECUTADO!FB37 -> 68.6 | L33: 32.7 | M33: 11.6 | N33: 441.9 | O33: 706.9 | P33: =SUM(C33:O33) -> 7819.7 | U33: EMPRESA DE GENERACION HUALLAGA | V33: C.H. CHAGLLA | X33: 10351.65
B34: 14:00 | C34: 1150.5 | D34: 3628.4 | E34: 1845.2 | F34: 0 | H34: 0 | J34: =DESPACHO_EJECUTADO!FA38+DESPACHO_EJECUTADO!FB38 -> 68.9 | L34: 32.8 | M34: 11.6 | N34: 418.1 | O34: 695.5 | P34: =SUM(C34:O34) -> 7851 | V34: P.C.H. CHAGLLA | W34: 155.9
B35: 14:30 | C35: 1134.5 | D35: 3490.8 | E35: 1872.8 | F35: 0 | H35: 0 | J35: =DESPACHO_EJECUTADO!FA39+DESPACHO_EJECUTADO!FB39 -> 68.6 | L35: 32.3 | M35: 11.6 | N35: 440.7 | O35: 742.5 | P35: =SUM(C35:O35) -> 7793.8 | U35: EMPRESA DE GENERACION HUANZA | V35: C.H. HUANZA | X35: 2177.75
B36: 15:00 | C36: 1125.8 | D36: 3575.5 | E36: 1927.2 | F36: 0 | H36: 0 | J36: =DESPACHO_EJECUTADO!FA40+DESPACHO_EJECUTADO!FB40 -> 68.8 | L36: 31.8 | M36: 11.6 | N36: 418.7 | O36: 736.6 | P36: =SUM(C36:O36) -> 7896 | U36: EMPRESA ELECTRICA AGUA AZUL | V36: C.H. POTRERO | W36: 462.45
B37: 15:30 | C37: 1121.3 | D37: 3583.1 | E37: 1986.3 | F37: 0 | H37: 0 | J37: =DESPACHO_EJECUTADO!FA41+DESPACHO_EJECUTADO!FB41 -> 69.3 | L37: 32 | M37: 11.7 | N37: 408.3 | O37: 733.2 | P37: =SUM(C37:O37) -> 7945.2 | U37: EMPRESA ELECTRICA RIO DOBLE | V37: C.H. LAS PIZARRAS | W37: 456.15
B38: 16:00 | C38: 1170.5 | D38: 3470.9 | E38: 2078.9 | F38: 0 | H38: 0 | J38: =DESPACHO_EJECUTADO!FA42+DESPACHO_EJECUTADO!FB42 -> 68 | L38: 32 | M38: 11.7 | N38: 388.4 | O38: 734.3 | P38: =SUM(C38:O38) -> 7954.7 | U38: ENGIE | V38: C.H. YUNCAN | X38: 2046.8
B39: 16:30 | C39: 1106.1 | D39: 3319.8 | E39: 2306.7 | F39: 0 | H39: 0 | J39: =DESPACHO_EJECUTADO!FA43+DESPACHO_EJECUTADO!FB43 -> 69.7 | L39: 32.4 | M39: 12.2 | N39: 252.6 | O39: 767 | P39: =SUM(C39:O39) -> 7866.5 | U39: GENERACIÓN ANDINA S.A.C. | V39: C.H. 8 DE AGOSTO | W39: 504
B40: 17:00 | C40: 1156 | D40: 3448.3 | E40: 1963.6 | F40: 0 | H40: 87.26 | J40: =DESPACHO_EJECUTADO!FA44+DESPACHO_EJECUTADO!FB44 -> 69.4 | L40: 31.9 | M40: 12.2 | N40: 150.5 | O40: 749.3 | P40: =SUM(C40:O40) -> 7668.46 | V40: C.H. EL CARMEN | W40: 148.35
B41: 17:30 | C41: 1158.4 | D41: 3617.9 | E41: 1733.2 | F41: 0 | H41: 105.72 | J41: =DESPACHO_EJECUTADO!FA45+DESPACHO_EJECUTADO!FB45 -> 69.3 | L41: 31.3 | M41: 12.2 | N41: 43.7 | O41: 798.1 | P41: =SUM(C41:O41) -> 7569.82 | U41: GENERADORA DE ENERGÍA DEL PERÚ | V41: C.H. ÁNGEL I | W41: 489.6
B42: 18:00 | C42: 1167.4 | D42: 3587.1 | E42: 1708.4 | F42: 0 | H42: 106.86 | J42: =DESPACHO_EJECUTADO!FA46+DESPACHO_EJECUTADO!FB46 -> 70.1 | L42: 31.7 | M42: 12.2 | N42: 0.3 | O42: 761.3 | P42: =SUM(C42:O42) -> 7445.36 | V42: C.H. ÁNGEL II | W42: 489.6
B43: 18:30 | C43: 1166.8 | D43: 3653.5 | E43: 1970.4 | F43: 0 | H43: 95.63 | J43: =DESPACHO_EJECUTADO!FA47+DESPACHO_EJECUTADO!FB47 -> 70 | L43: 31.3 | M43: 12.2 | N43: 0 | O43: 688.3 | P43: =SUM(C43:O43) -> 7688.13 | V43: C.H. ÁNGEL III | W43: 484.8
B44: 19:00 | C44: 1179.2 | D44: 3635.1 | E44: 2194.8 | F44: 0 | H44: 28.14 | J44: =DESPACHO_EJECUTADO!FA48+DESPACHO_EJECUTADO!FB48 -> 69.9 | L44: 31.9 | M44: 12.2 | N44: 0 | O44: 632.7 | P44: =SUM(C44:O44) -> 7783.94 | V44: C.H. LA JOYA | W44: 176.75
B45: 19:30 | C45: 1183.7 | D45: 3621.4 | E45: 2293.2 | F45: 0 | H45: 0 | J45: =DESPACHO_EJECUTADO!FA49+DESPACHO_EJECUTADO!FB49 -> 69.5 | L45: 32.2 | M45: 12.2 | N45: 0 | O45: 568.6 | P45: =SUM(C45:O45) -> 7780.8 | U45: HIDROCAÑETE S.A. | V45: C.H. IMPERIAL | W45: 84.35
B46: 20:00 | C46: 1188.2 | D46: 3643.6 | E46: 2324 | F46: 0 | H46: 0 | J46: =DESPACHO_EJECUTADO!FA50+DESPACHO_EJECUTADO!FB50 -> 69.5 | L46: 32.6 | M46: 12.2 | N46: 0 | O46: 534.1 | P46: =SUM(C46:O46) -> 7804.2 | U46: HIDROELECTRICA HUANCHOR S.A.C. | V46: C.H. HUANCHOR | W46: 442.7
B47: 20:30 | C47: 1185 | D47: 3633.6 | E47: 2384.3 | F47: 0 | H47: 0 | J47: =DESPACHO_EJECUTADO!FA51+DESPACHO_EJECUTADO!FB51 -> 69.2 | L47: 32.6 | M47: 12.2 | N47: 0 | O47: 413.1 | P47: =SUM(C47:O47) -> 7730 | U47: HUAURA POWER GROUP S.A. | V47: C.H. YARUCAYA | W47: 446.35
B48: 21:00 | C48: 1183.9 | D48: 3593.9 | E48: 2342.8 | F48: 0 | H48: 0 | J48: =DESPACHO_EJECUTADO!FA52+DESPACHO_EJECUTADO!FB52 -> 69.3 | L48: 32.7 | M48: 12.2 | N48: 0 | O48: 439.8 | P48: =SUM(C48:O48) -> 7674.6 | U48: INLAND ENERGY SAC | V48: C.H. SANTA TERESA | W48: 2164.25
B49: 21:30 | C49: 1191.7 | D49: 3619.7 | E49: 2223.7 | F49: 0 | H49: 0 | J49: =DESPACHO_EJECUTADO!FA53+DESPACHO_EJECUTADO!FB53 -> 69.4 | L49: 32.2 | M49: 12.2 | N49: 0 | O49: 515.5 | P49: =SUM(C49:O49) -> 7664.4 | U49: INVERSIONES SHAQSHA S.A.C. | V49: C.H. PARIAC | W49: 27.9
B50: 22:00 | C50: 1184.3 | D50: 3567 | E50: 2198.6 | F50: 0 | H50: 0 | J50: =DESPACHO_EJECUTADO!FA54+DESPACHO_EJECUTADO!FB54 -> 69.1 | L50: 32.2 | M50: 12.2 | N50: 0 | O50: 508 | P50: =SUM(C50:O50) -> 7571.4 | U50: KALLPA GENERACION S.A. | V50: C.H. CERRO DEL AGUILA | X50: 12231.45
B51: 22:30 | C51: 1185.7 | D51: 3603.3 | E51: 2095.2 | F51: 0 | H51: 0 | J51: =DESPACHO_EJECUTADO!FA55+DESPACHO_EJECUTADO!FB55 -> 68.1 | L51: 32.1 | M51: 12.2 | N51: 0 | O51: 443.3 | P51: =SUM(C51:O51) -> 7439.9 | V51: M.C.H.+CERRO+DEL+AGUILA | W51: 250.55
B52: 23:00 | C52: 1174.1 | D52: 3497.4 | E52: 1820.3 | F52: 0 | H52: 0 | J52: =DESPACHO_EJECUTADO!FA56+DESPACHO_EJECUTADO!FB56 -> 69.2 | L52: 32.5 | M52: 12.2 | N52: 0 | O52: 460.8 | P52: =SUM(C52:O52) -> 7066.5 | U52: LA VIRGEN | V52: C.H. LA VIRGEN | X52: 1323.8
B53: 23:30 | C53: 1125.5 | D53: 3662.7 | E53: 1638.5 | F53: 0 | H53: 0 | J53: =DESPACHO_EJECUTADO!FA57+DESPACHO_EJECUTADO!FB57 -> 69.5 | L53: 32.4 | M53: 12.2 | N53: 0 | O53: 445.3 | P53: =SUM(C53:O53) -> 6986.1 | U53: MAJA ENERGIA S.A.C. | V53: C.H. RONCADOR | W53: 32.7
B54: 00:00 | C54: 1111.4 | D54: 3491.9 | E54: 1589.2 | F54: 0 | H54: 0 | J54: =DESPACHO_EJECUTADO!FA58+DESPACHO_EJECUTADO!FB58 -> 69.6 | L54: 32.3 | M54: 12.2 | N54: 0 | O54: 401.9 | P54: =SUM(C54:O54) -> 6708.5 | U54: ORAZUL ENERGY PERÚ | V54: C.H. CAÑA BRAVA | W54: 131.15
B55: TOTAL MWh | C55: =+SUM(C7:C54)/2 -> 26808 | D55: =+SUM(D7:D54)/2 -> 82991.25 | E55: =+SUM(E7:E54)/2 -> 45319.05 | F55: =+SUM(F7:F54)/2 -> 87.7 | G55: =+SUM(G7:G54)/2 -> 0 | H55: =+SUM(H7:H54)/2 -> 211.805 | I55: =+SUM(I7:I54)/2 -> 0 | J55: =+SUM(J7:J54)/2 -> 1645.65 | ... P55: =+SUM(P7:P54)/2 -> 175090.46 | V55: C.H. CAÑON DEL PATO | X55: 5443.9
B56: % | C56: =+C55/$P$55*100 -> 15.310943 | D56: =+D55/$P$55*100 -> 47.399072 | E56: =+E55/$P$55*100 -> 25.883221 | F56: =+F55/$P$55*100 -> 0.050088396 | G56: =+G55/$P$55*100 -> 0 | H56: =+H55/$P$55*100 -> 0.1209689 | I56: =+I55/$P$55*100 -> 0 | J56: =+J55/$P$55*100 -> 0.93988562 | ... P56: =+P55/$P$55*100 -> 100 | V56: C.H. CARHUAQUERO | X56: 2149.35
V57: C.H. CARHUAQUERO IV | W57: 248.85
U58: ORYGEN PERU S.A.A. | V58: C.H. CALLAHUANCA | X58: 1890.05
V59: C.H. HER 1 | W59: 14.4
V60: C.H. HUAMPANI | W60: 721.55
V61: C.H. HUINCO | X61: 5811.2
V62: C.H. MATUCANA | X62: 3048.95
V63: C.H. MOYOPAMPA | W63: 1535.1
U64: SAN GABAN | V64: C.H. SAN GABAN II | X64: 2568.55
V65: MCH TUPURI | W65: 28.4
U66: SINERSA | V66: C.H. CHANCAY | W66: 479
V67: C.H. POECHOS II | W67: 215.1
U68: STATKRAFT S.A | V68: C.H. ARCATA | W68: 60.8
V69: C.H. CAHUA | W69: 1118.8
V70: C.H. CHEVES | X70: 4159.6
V71: C.H. GALLITO CIEGO | X71: 890.3
V72: C.H. MALPASO | X72: 1067.6
V73: C.H. PACHACHACA | W73: 49.8
V74: C.H. YAUPI | W74: 2272.15
U75: TOTAL MWh | W75: 26808 | X75: 82991.25

Sheet GENERACION RER
B3: jueves, 20 de Marzo del 2025
B5: GENERACIÓN ELÉCTRICA DE LAS CENTRALES RER (MW)
B6: HORA | C6: AGRO INDUSTRIAL PARAMONGA S.A. | D6: AGROAURORA S.A.C. | E6: AGROINDUSTRIAS SAN JACINTO S.A.A. | F6: ANDEAN POWER S.A.C. | G6: ASOCIACIÓN SANTA LUCIA DE CHACAS | H6: ATRIA ENERGIA S.A.C. | I6: BIOENERGIA DEL CHIRA S.A. | J6: COLCA SOLAR S.A.C. | K6: EGEJUNIN | P6: ELECTRICA YANAPAMPA SAC | Q6: EMPRESA DE GENERACION ELECTRICA CANCHAYLLO SAC | R6: EMPRESA DE GENERACION ELECTRICA RIO BAÑOS S.A.C. | S6: EMPRESA DE GENERACION ELECTRICA SANTA ANA S.A.C. | T6: EMPRESA ELECTRICA AGUA AZUL | U6: EMPRESA ELECTRICA RIO DOBLE | V6: ENERGÍA EÓLICA S.A. | X6: ENERGIA RENOVABLE DEL SUR S.A. | Y6: ENGIE | AD6: GENERACIÓN ANDINA S.A.C. | AF6: GENERADORA DE ENERGÍA DEL PERÚ | AJ6: GR CORTARRAMA SOCIEDAD ANONIMA CERRADA | AK6: GR PAINO SOCIEDAD ANONIMA CERRADA | AL6: GR TARUCA SOCIEDAD ANONIMA CERRADA | AM6: HIDROCAÑETE S.A. | AN6: HUAURA POWER GROUP S.A. | AO6: HYDRO PATAPO S.A.C. | AP6: KONDU SAC | AQ6: MAJA ENERGIA S.A.C. | AR6: MAJES ARCUS S.A.C. | AS6: MOQUEGUA FV S.A.C. | AT6: ORAZUL ENERGY PERÚ | AV6: ORYGEN PERU S.A.A. | BA6: PANAMERICANA SOLAR SAC. | BB6: PARQUE EOLICO MARCONA S.A.C. | BC6: PARQUE EOLICO TRES HERMANAS S.A.C. | BD6: PERUANA DE INVERSIONES EN ENERGIAS RENOVABLES S.A. | BE6: PETRAMAS | BI6: REPARTICIÓN ARCUS S.A.C. | BJ6: SAN GABAN | BK6: SDF ENERGIA SAC | BL6: SINERSA | BN6: TACNA SOLAR SAC. | BO6: TOTAL RER
C7: C.T. PARAMONGA | D7: C.T. MAPLE | E7: C.T SAN JACINTO | F7: C.H. CARHUAC | G7: C.H. HUALLIN | H7: C.H. PURMACANA | I7: C.T. CAÑA BRAVA | K7: C.H. HUASAHUASI I | L7: C.H. HUASAHUASI II | M7: C.H. RUNATULLO II | N7: C.H. RUNATULLO III | O7: C.H. STA CRUZ I y II | P7: C.H. YANAPAMPA | Q7: C.H. CANCHAYLLO | R7: C.H. RUCUY | S7: C.H. RENOVANDES H1 | T7: C.H. POTRERO | U7: C.H. LAS PIZARRAS | AD7: C.H. 8 DE AGOSTO | AE7: C.H. EL CARMEN | AF7: C.H. ANGEL I | AG7: C.H. ANGEL II | AH7: C.H. ANGEL III | AI7: C.H. LA JOYA | AM7: C.H. NUEVAIMPERIAL | AN7: C.H. YARUCAYA | AO7: MCH PATAPO | AQ7: C.H. RONCADOR | AT7: C.H. CANA BRAVA | AU7: C.H. CARHUAQUERO4 | AZ7: C.H. HER 1 | BD7: C.H. MANTA | BE7: C.T. HUAYCOLORO | BF7: C.T. LA GRINGA V | BG7: CTB CALLAO | BH7: CTB. DONA CATALINA | BJ7: C.H. TUPURI | BK7: C.T. OQUENDO | BL7: C.H. CHANCAY | BM7: C.H. POECHOS2 | BO7: MW
B8: 0:30 | C8: 15.5 | D8: 9.6 | E8: 7.2 | F8: 20.3 | G8: 3 | K8: 19.8 | M8: 20.1 | N8: 20.2 | O8: 13 | P8: 3.3 | Q8: 5.1 | R8: 20 | S8: 20 | T8: 18.2 | U8: 19 | V8: 13.9 | W8: 12.1 | X8: 95.3 | Y8: 41.8 | Z8: 67 | AB8: 1.1 | AC8: 1 | AD8: 21 | AE8: 4 | AF8: 20.4 | AG8: 20.4 | AH8: 20.2 | AI8: 6.7 | AK8: 13.4 | AL8: 17 | AM8: 3.4 | AN8: 18.6 | AQ8: 1.8 | AT8: 5.5 | AU8: 10.3 | AV8: 15.9 | AX8: 22.1 | AZ8: 0.6 | BB8: 30.1 | BC8: 71.5 | BE8: 4.8 | BF8: 2.3 | BG8: 2.4 | BH8: 2.4 | BJ8: 1.3 | BL8: 20 | BM8: 9 | BO8: 791.6
B9: 1:00 | C9: 15.4 | D9: 9.6 | E9: 6.7 | F9: 20.3 | G9: 3 | K9: 19.8 | M9: 19.9 | N9: 20.3 | O9: 13 | P9: 3.1 | Q9: 5.2 | R9: 19.9 | S9: 20.4 | T9: 18.4 | U9: 19 | V9: 12 | W9: 19.4 | X9: 94.5 | Y9: 43.7 | Z9: 61.6 | AB9: 1.7 | AC9: 1.1 | AD9: 21 | AE9: 4.2 | AF9: 20.4 | AG9: 20.4 | AH9: 20.2 | AI9: 6.7 | AK9: 9.4 | AL9: 14.6 | AM9: 3.5 | AN9: 18.6 | AQ9: 1.8 | AT9: 5.4 | AU9: 10.3 | AV9: 18.6 | AX9: 25.3 | AZ9: 0.6 | BB9: 30.6 | BC9: 73.5 | BE9: 4.8 | BF9: 2.3 | BG9: 2.4 | BH9: 2.4 | BJ9: 1.3 | BL9: 19.9 | BM9: 9 | BO9: 795.2
B10: 1:30 | C10: 15.5 | D10: 9.5 | E10: 7 | F10: 20.3 | G10: 3 | K10: 19.8 | M10: 19.6 | N10: 20.3 | O10: 13.1 | P10: 3.2 | Q10: 5.2 | R10: 20 | S10: 20.3 | T10: 18.9 | U10: 18.9 | V10: 15.1 | W10: 29.6 | X10: 94.5 | Y10: 26.3 | Z10: 48.7 | AB10: 0.7 | AD10: 21 | AE10: 4.3 | AF10: 20.4 | AG10: 20.4 | AH10: 20.2 | AI10: 6.7 | AK10: 8 | AL10: 12.7 | AM10: 3.5 | AN10: 18.6 | AQ10: 1.7 | AT10: 5.4 | AU10: 10.3 | AV10: 29.3 | AX10: 30 | AZ10: 0.6 | BB10: 31.4 | BC10: 76.3 | BE10: 4.8 | BF10: 2.5 | BG10: 2.4 | BH10: 2.4 | BJ10: 1.3 | BL10: 20 | BM10: 9 | BO10: 792.7
B11: 2:00 | C11: 15.5 | D11: 9.6 | E11: 7.3 | F11: 20.3 | G11: 3 | K11: 19.8 | M11: 19.5 | N11: 20.3 | O11: 13 | P11: 3.3 | Q11: 5.1 | R11: 19.8 | S11: 20.4 | T11: 18 | U11: 18.9 | V11: 14.6 | W11: 32.1 | X11: 92.6 | Y11: 23.6 | Z11: 49.9 | AB11: 0.6 | AC11: 0.1 | AD11: 21 | AE11: 4.3 | AF11: 20.4 | AG11: 20.4 | AH11: 20.2 | AI11: 6.6 | AK11: 9.7 | AL11: 12.7 | AM11: 3.5 | AN11: 18.6 | AQ11: 1.7 | AT11: 5.4 | AU11: 10.3 | AV11: 29.1 | AX11: 40.6 | AZ11: 0.6 | BB11: 30.1 | BC11: 71.7 | BE11: 4.8 | BF11: 2.5 | BG11: 2.4 | BH11: 2.4 | BJ11: 1.2 | BL11: 19.9 | BM11: 9 | BO11: 796.4
B12: 2:30 | C12: 15.5 | D12: 9.6 | E12: 6.3 | F12: 20.3 | G12: 3 | K12: 19.8 | M12: 19.6 | N12: 20.3 | O12: 13 | P12: 3.3 | Q12: 5.1 | R12: 19.9 | S12: 20.1 | T12: 18.4 | U12: 19 | V12: 13.4 | W12: 23.9 | X12: 92.6 | Y12: 24.8 | Z12: 45.8 | AB12: 0.8 | AC12: 0.1 | AD12: 21 | AE12: 4.3 | AF12: 20.4 | AG12: 20.4 | AH12: 20.2 | AI12: 6.6 | AK12: 11.8 | AL12: 14.4 | AM12: 3.5 | AN12: 18.6 | AQ12: 1.7 | AT12: 5.5 | AU12: 10.3 | AV12: 12.6 | AX12: 25.5 | AZ12: 0.6 | BB12: 29.7 | BC12: 65.5 | BE12: 4.8 | BF12: 2.5 | BG12: 2.4 | BH12: 2.4 | BJ12: 1.2 | BL12: 19.8 | BM12: 9.1 | BO12: 749.4
B13: 3:00 | C13: 15.5 | D13: 9.6 | E13: 6.9 | F13: 20.3 | G13: 3 | K13: 19.8 | M13: 19.4 | N13: 20.2 | O13: 12.9 | P13: 3.3 | Q13: 5.2 | R13: 19.8 | S13: 19.9 | T13: 18.2 | U13: 19 | V13: 11 | W13: 22.4 | X13: 92 | Y13: 23.4 | Z13: 48.9 | AB13: 0.7 | AD13: 21 | AE13: 4.3 | AF13: 20.4 | AG13: 20.4 | AH13: 20.2 | AI13: 6.6 | AK13: 13.8 | AL13: 15 | AM13: 3.5 | AN13: 18.6 | AQ13: 1.7 | AT13: 5.5 | AU13: 10.4 | AV13: 12.1 | AX13: 24.8 | AZ13: 0.6 | BB13: 31.6 | BC13: 65 | BE13: 4.8 | BF13: 2.5 | BG13: 2.4 | BH13: 2.4 | BJ13: 1.2 | BL13: 19.8 | BM13: 9 | BO13: 749
B14: 3:30 | C14: 15.4 | D14: 9.6 | E14: 7.2 | F14: 20.3 | G14: 3 | K14: 19.8 | M14: 19.4 | N14: 20.3 | O14: 12.9 | P14: 3.3 | Q14: 5.2 | R14: 20 | S14: 20.4 | T14: 19.5 | U14: 19 | V14: 8.3 | W14: 16.5 | X14: 92 | Y14: 15.7 | Z14: 36 | AB14: 0.4 | AD14: 21 | AE14: 4.3 | AF14: 20.4 | AG14: 20.4 | AH14: 20.2 | AI14: 6.6 | AK14: 13.1 | AL14: 16 | AM14: 3.5 | AN14: 18.6 | AQ14: 1.7 | AT14: 5.5 | AU14: 10.3 | AV14: 6.1 | AX14: 12.2 | AZ14: 0.6 | BB14: 30.5 | BC14: 60.9 | BE14: 4.8 | BF14: 2.5 | BG14: 2.4 | BH14: 2.4 | BJ14: 1.2 | BL14: 20 | BM14: 9 | BO14: 698.4
B15: 4:00 | C15: 15.5 | D15: 9.6 | E15: 6.4 | F15: 20.3 | G15: 3 | K15: 19.8 | M15: 19.3 | N15: 20.3 | O15: 13 | P15: 3.3 | Q15: 5.2 | R15: 20 | S15: 20 | T15: 17.3 | U15: 19 | V15: 6.9 | W15: 21.7 | X15: 90.8 | Y15: 18.6 | Z15: 37.3 | AB15: 0.2 | AD15: 21 | AE15: 4.3 | AF15: 20.4 | AG15: 20.4 | AH15: 20.2 | AI15: 6.6 | AK15: 9.7 | AL15: 14 | AM15: 3.5 | AN15: 18.6 | AQ15: 1.7 | AT15: 5.6 | AU15: 10.5 | AV15: 5 | AX15: 9.4 | AZ15: 0.6 | BB15: 29.4 | BC15: 64.4 | BE15: 4.8 | BF15: 2.5 | BG15: 2.4 | BH15: 2.4 | BJ15: 1.2 | BL15: 20 | BM15: 9 | BO15: 695.1
B16: 4:30 | C16: 15.5 | D16: 9.6 | E16: 6.7 | F16: 20.3 | G16: 3 | K16: 19.8 | M16: 19.3 | N16: 20.3 | O16: 13 | P16: 3.3 | Q16: 5.1 | R16: 20 | S16: 20.2 | T16: 18 | U16: 19 | V16: 6.2 | W16: 22.1 | X16: 90.8 | Y16: 13.8 | Z16: 32.2 | AD16: 21 | AE16: 4.3 | AF16: 20.4 | AG16: 20.4 | AH16: 20.2 | AI16: 7.7 | AK16: 11.7 | AL16: 16.5 | AM16: 3.5 | AN16: 18.6 | AQ16: 1.8 | AT16: 5.5 | AU16: 10.4 | AV16: 4.5 | AX16: 5.4 | AZ16: 0.6 | BB16: 30 | BC16: 71.4 | BE16: 4.8 | BF16: 2.5 | BG16: 2.4 | BH16: 2.4 | BJ16: 1.2 | BL16: 20 | BM16: 9 | BO16: 694.4
B17: 5:00 | C17: 15.6 | D17: 9.6 | E17: 6.8 | F17: 20.3 | G17: 3 | K17: 19.8 | M17: 19.5 | N17: 20.3 | O17: 13 | P17: 3.3 | Q17: 5.1 | R17: 20 | S17: 20.6 | T17: 18.6 | U17: 19 | V17: 9.3 | W17: 18.4 | X17: 93.6 | Y17: 19.4 | Z17: 42.3 | AB17: 0.3 | AD17: 21 | AE17: 4.3 | AF17: 20.4 | AG17: 20.4 | AH17: 20.2 | AI17: 8 | AK17: 8.5 | AL17: 13.1 | AM17: 3.5 | AN17: 18.6 | AQ17: 1.8 | AT17: 5.5 | AU17: 10.4 | AV17: 4.6 | AX17: 6.3 | AZ17: 0.6 | BB17: 30.7 | BC17: 76 | BE17: 4.8 | BF17: 2.5 | BG17: 2.4 | BH17: 2.4 | BJ17: 1.3 | BL17: 20 | BM17: 9 | BO17: 714.1
B18: 5:30 | C18: 15.5 | D18: 9.6 | E18: 6.7 | F18: 20.3 | G18: 3 | K18: 19.8 | M18: 19.8 | N18: 20.2 | O18: 12.9 | P18: 3.3 | Q18: 5.1 | R18: 20 | S18: 19.8 | T18: 17.6 | U18: 19 | V18: 9 | W18: 15.1 | X18: 115.7 | Y18: 17.1 | Z18: 36.8 | AB18: 0.1 | AD18: 21 | AE18: 4.3 | AF18: 20.4 | AG18: 20.4 | AH18: 20.2 | AI18: 8.2 | AK18: 10.9 | AL18: 15.7 | AM18: 3.5 | AN18: 18.6 | AQ18: 1.7 | AT18: 5.5 | AU18: 10.4 | AV18: 17.9 | AX18: 18.3 | AZ18: 0.6 | BB18: 30 | BC18: 75.5 | BE18: 4.8 | BF18: 2.5 | BG18: 2.4 | BH18: 2.4 | BJ18: 1.2 | BL18: 20 | BM18: 8.9 | BO18: 751.7
B19: 6:00 | C19: 15.6 | D19: 9.6 | E19: 7.1 | F19: 20.3 | G19: 3 | K19: 19.8 | M19: 20.1 | N19: 20.3 | O19: 12.8 | P19: 3.3 | Q19: 5.1 | R19: 19.8 | S19: 20.3 | T19: 18.8 | U19: 19 | V19: 10.2 | W19: 17.5 | X19: 118.5 | Y19: 24.1 | Z19: 50.6 | AA19: 0.2 | AB19: 0.4 | AC19: 0.5 | AD19: 21 | AE19: 4.3 | AF19: 20.4 | AG19: 20.4 | AH19: 20.2 | AI19: 7.8 | AK19: 13.7 | AL19: 16.4 | AM19: 3.5 | AN19: 18.6 | AQ19: 1.8 | AS19: 1.8 | AT19: 5.4 | AU19: 10.4 | AV19: 28.3 | AW19: 1.4 | AX19: 34.8 | AY19: 1.3 | AZ19: 0.6 | BA19: 1.9 | BB19: 31.5 | BC19: 74.1 | BE19: 4.8 | BF19: 2.5 | BG19: 2.4 | BH19: 2.4 | BJ19: 1.3 | BL19: 19.8 | BM19: 9 | BO19: 818.7
B20: 6:30 | C20: 15.4 | D20: 9.6 | E20: 7 | F20: 20.3 | G20: 3 | K20: 19.8 | M20: 20.1 | N20: 20.3 | O20: 12.8 | P20: 3.3 | Q20: 5.1 | R20: 20 | S20: 20.6 | T20: 16.8 | U20: 19 | V20: 9.9 | W20: 15 | X20: 120.6 | Y20: 27.8 | Z20: 58 | AA20: 6.9 | AB20: 0.9 | AC20: 0.4 | AD20: 21 | AE20: 4.3 | AF20: 20.4 | AG20: 20.4 | AH20: 20.2 | AI20: 8.1 | AJ20: 0.7 | AK20: 13.3 | AL20: 16.4 | AM20: 3.4 | AN20: 18.6 | AQ20: 1.8 | AR20: 0.6 | AS20: 7.1 | AT20: 5.4 | AU20: 10.2 | AV20: 28.3 | AW20: 21.9 | AX20: 34.3 | AY20: 16.4 | AZ20: 0.6 | BA20: 7.3 | BB20: 31.2 | BC20: 71.3 | BE20: 4.8 | BF20: 2.5 | BG20: 2.4 | BH20: 2.4 | BI20: 0.8 | BJ20: 1.2 | BL20: 20 | BM20: 9 | BO20: 878.9
B21: 7:00 | C21: 15.5 | D21: 9.6 | E21: 6.8 | F21: 20.3 | G21: 2.9 | J21: 0.1 | K21: 19.8 | M21: 20.2 | N21: 20.3 | O21: 12.9 | P21: 3.3 | Q21: 5.1 | R21: 20 | S21: 20 | T21: 19.1 | U21: 19 | V21: 6.8 | W21: 10.5 | X21: 121 | Y21: 26.2 | Z21: 54.3 | AA21: 15.6 | AB21: 0.9 | AC21: 0.6 | AD21: 21 | AE21: 4.3 | AF21: 20.4 | AG21: 20.4 | AH21: 20.2 | AI21: 8.1 | AJ21: 32.4 | AK21: 12.9 | AL21: 16.1 | AM21: 3.4 | AN21: 18.6 | AQ21: 1.8 | AR21: 2.5 | AS21: 12.2 | AT21: 5.5 | AU21: 10.3 | AV21: 30.6 | AW21: 75.3 | AX21: 39.5 | AY21: 59.1 | AZ21: 0.6 | BA21: 14.4 | BB21: 31.8 | BC21: 79.5 | BE21: 4.8 | BF21: 2.6 | BG21: 2.4 | BH21: 2.4 | BI21: 2.4 | BJ21: 1.3 | BL21: 20 | BM21: 9 | BO21: 1036.6
B22: 7:30 | C22: 15.3 | D22: 9.6 | E22: 7.3 | F22: 20.3 | G22: 3 | J22: 0.1 | K22: 19.8 | M22: 20.2 | N22: 20.3 | O22: 12.8 | P22: 3.3 | Q22: 5.1 | R22: 20 | S22: 20.1 | T22: 19.9 | U22: 19 | W22: 8.3 | X22: 119.4 | Y22: 25.7 | Z22: 57.1 | AA22: 26.1 | AB22: 0.9 | AC22: 0.2 | AD22: 21 | AE22: 4.3 | AF22: 20.4 | AG22: 20.4 | AH22: 20.2 | AI22: 7.9 | AJ22: 47.6 | AK22: 13.8 | AL22: 17.3 | AM22: 3.5 | AN22: 18.6 | AP22: 0.1 | AQ22: 1.8 | AR22: 4.8 | AS22: 13.3 | AT22: 5.5 | AU22: 10.4 | AV22: 34.4 | AW22: 48 | AX22: 38.9 | AY22: 35.2 | AZ22: 0.6 | BA22: 15.9 | BB22: 31.9 | BC22: 86.2 | BE22: 4.8 | BF22: 2.6 | BG22: 2.4 | BH22: 2.4 | BI22: 4.5 | BJ22: 1.3 | BL22: 20 | BM22: 8.9 | BO22: 1022.7
B23: 8:00 | C23: 15.5 | D23: 9.5 | E23: 6.9 | F23: 20.3 | G23: 3 | J23: 0.2 | K23: 19.8 | M23: 20.4 | N23: 20.3 | O23: 12.8 | P23: 3.3 | Q23: 5.1 | R23: 20 | S23: 20.4 | T23: 18.9 | U23: 19 | W23: 10.3 | X23: 115.3 | Y23: 36.4 | Z23: 65.8 | AA23: 31.5 | AB23: 1.1 | AC23: 0.8 | AD23: 21 | AE23: 4.3 | AF23: 20.4 | AG23: 20.4 | AH23: 20.2 | AI23: 7.9 | AJ23: 64.2 | AK23: 14.3 | AL23: 17.4 | AM23: 3.5 | AN23: 18.6 | AP23: 0.1 | AQ23: 1.5 | AR23: 7.6 | AS23: 14.4 | AT23: 5.5 | AU23: 10.5 | AV23: 41.4 | AW23: 111.1 | AX23: 42.2 | AY23: 76.4 | AZ23: 0.6 | BA23: 17.5 | BB23: 32.1 | BC23: 85.8 | BE23: 4.8 | BF23: 2.6 | BG23: 2.4 | BH23: 2.4 | BI23: 7.6 | BJ23: 1.2 | BL23: 20 | BM23: 9 | BO23: 1185.5
B24: 8:30 | C24: 15.4 | D24: 9.6 | E24: 7.1 | F24: 20.3 | G24: 3 | J24: 0.6 | K24: 19.8 | M24: 20.3 | N24: 20.3 | O24: 12.8 | P24: 3.4 | Q24: 5.1 | R24: 20 | S24: 20.3 | T24: 19.9 | U24: 19 | W24: 8.6 | X24: 116.7 | Y24: 48.1 | Z24: 70.9 | AA24: 33.9 | AB24: 2.4 | AC24: 0.7 | AD24: 21 | AE24: 4.3 | AF24: 20.4 | AG24: 20.4 | AH24: 20.2 | AI24: 7.9 | AJ24: 67.8 | AK24: 13 | AL24: 18.1 | AM24: 3.5 | AN24: 18.6 | AP24: 0.2 | AQ24: 1.1 | AR24: 9.9 | AS24: 14.7 | AT24: 5.6 | AU24: 10.5 | AV24: 47.4 | AW24: 134.5 | AX24: 56.1 | AY24: 97.7 | AZ24: 0.6 | BA24: 17.8 | BB24: 31.2 | BC24: 89.2 | BE24: 4.8 | BF24: 2.6 | BG24: 2.4 | BH24: 2.4 | BI24: 10 | BJ24: 1.3 | BL24: 20 | BM24: 9.1 | BN24: 17.7 | BO24: 1300.2
B25: 9:00 | C25: 15.5 | D25: 9.6 | E25: 6.6 | F25: 20.3 | G25: 3 | J25: 0.9 | K25: 19.8 | M25: 20.4 | N25: 20.3 | O25: 12.8 | P25: 3.4 | Q25: 5.2 | R25: 20 | S25: 20.2 | T25: 19.7 | U25: 19 | W25: 3.9 | X25: 116.9 | Y25: 57 | Z25: 77.3 | AA25: 34.8 | AB25: 4.1 | AC25: 2.1 | AD25: 21 | AE25: 4.3 | AF25: 20.4 | AG25: 20.4 | AH25: 20.2 | AI25: 7.9 | AJ25: 72.3 | AK25: 14.1 | AL25: 17.7 | AM25: 3.5 | AN25: 18.6 | AP25: 0.2 | AQ25: 0.9 | AR25: 11.7 | AS25: 14.4 | AT25: 5.5 | AU25: 10.4 | AV25: 54.8 | AW25: 129 | AX25: 64.6 | AY25: 94.4 | AZ25: 0.6 | BA25: 17.9 | BB25: 31.5 | BC25: 89.8 | BE25: 4.8 | BF25: 2.6 | BG25: 2.4 | BH25: 2.4 | BI25: 12.1 | BL25: 20 | BM25: 9 | BN25: 18.7 | BO25: 1330.9
B26: 9:30 | C26: 15.5 | D26: 9.4 | E26: 6.6 | F26: 20.3 | G26: 3 | J26: 1.1 | K26: 19.8 | M26: 20.2 | N26: 20.3 | O26: 12.8 | P26: 3.4 | Q26: 5.2 | R26: 20 | S26: 20 | T26: 18.5 | U26: 19 | W26: 5 | X26: 114.2 | Y26: 66.3 | Z26: 82.5 | AA26: 35 | AB26: 5.6 | AC26: 2.4 | AD26: 21 | AE26: 4.3 | AF26: 20.4 | AG26: 20.4 | AH26: 20.2 | AI26: 8 | AJ26: 73.8 | AK26: 14.9 | AL26: 17.6 | AM26: 3.5 | AN26: 18.6 | AP26: 0.3 | AQ26: 0.8 | AR26: 12.7 | AS26: 14.2 | AT26: 5.6 | AU26: 10.4 | AV26: 68.1 | AW26: 138.3 | AX26: 82.9 | AY26: 98.9 | AZ26: 0.6 | BA26: 17.5 | BB26: 31.2 | BC26: 89.3 | BE26: 4.8 | BF26: 2.6 | BG26: 2.4 | BH26: 2.4 | BI26: 14.1 | BL26: 20 | BM26: 9 | BN26: 18.8 | BO26: 1393.7
B27: 10:00 | C27: 15.5 | D27: 9.6 | E27: 7 | F27: 20.3 | G27: 0.2 | J27: 1.2 | K27: 19.8 | M27: 20.3 | N27: 20.3 | O27: 12.9 | P27: 3.4 | Q27: 5.2 | R27: 20 | S27: 20.1 | T27: 20 | U27: 19 | W27: 11.2 | X27: 116.3 | Y27: 82.5 | Z27: 78 | AA27: 35.2 | AB27: 5.9 | AC27: 4.9 | AD27: 21 | AE27: 4.3 | AF27: 20.4 | AG27: 20.4 | AH27: 20.2 | AI27: 8 | AJ27: 71.3 | AK27: 13.1 | AL27: 16.7 | AM27: 3.5 | AN27: 18.6 | AP27: 0.3 | AQ27: 0.7 | AR27: 15.1 | AS27: 14.3 | AT27: 5.5 | AU27: 10.4 | AV27: 86.8 | AW27: 141.6 | AX27: 104.9 | AY27: 104 | AZ27: 0.6 | BA27: 17.6 | BB27: 31.7 | BC27: 87.6 | BE27: 4.8 | BF27: 2.5 | BG27: 2.4 | BH27: 2.4 | BI27: 15.7 | BJ27: 0.9 | BL27: 20 | BM27: 8.9 | BN27: 18.7 | BO27: 1463.7
B28: 10:30 | C28: 15.5 | D28: 9.6 | E28: 6.9 | F28: 20.3 | H28: 0.1 | J28: 0.8 | K28: 19.8 | M28: 20.4 | N28: 20.3 | O28: 12.9 | P28: 3.4 | Q28: 5.2 | R28: 20 | S28: 20.4 | T28: 19.3 | U28: 19 | W28: 16.7 | X28: 119 | Y28: 81.8 | Z28: 79.4 | AA28: 35.4 | AB28: 5.9 | AC28: 6.6 | AD28: 21 | AE28: 4.3 | AF28: 20.4 | AG28: 20.4 | AH28: 20.2 | AI28: 8 | AJ28: 69.3 | AK28: 13.6 | AL28: 17.9 | AM28: 3.5 | AN28: 18.6 | AP28: 0.4 | AQ28: 0.4 | AR28: 16.3 | AS28: 14.7 | AT28: 5.5 | AU28: 10.4 | AV28: 78.4 | AW28: 122.2 | AX28: 92.4 | AY28: 93.4 | AZ28: 0.6 | BA28: 17.8 | BB28: 31.7 | BC28: 88.9 | BE28: 4.8 | BF28: 2.3 | BG28: 2.4 | BH28: 2.4 | BI28: 16.8 | BJ28: 1.2 | BL28: 20 | BM28: 9 | BN28: 18.5 | BO28: 1426.4
B29: 11:00 | C29: 16 | D29: 9.6 | E29: 7.1 | F29: 20.3 | H29: 0.4 | J29: 0.8 | K29: 19.8 | M29: 20.4 | N29: 20.3 | O29: 12.8 | P29: 3.4 | Q29: 5.2 | R29: 19.9 | S29: 20.2 | T29: 20 | U29: 19 | W29: 22.4 | X29: 122.1 | Y29: 72.2 | Z29: 78.5 | AA29: 35.2 | AB29: 2.9 | AC29: 7.7 | AD29: 21 | AE29: 4.3 | AF29: 20.4 | AG29: 20.4 | AH29: 20.2 | AI29: 8 | AJ29: 68.3 | AK29: 14.8 | AL29: 17.6 | AM29: 3.6 | AN29: 18.6 | AP29: 0.4 | AQ29: 0.7 | AR29: 17.2 | AS29: 14.5 | AT29: 5.5 | AU29: 10.3 | AV29: 85.2 | AW29: 136.7 | AX29: 89.7 | AY29: 102.5 | AZ29: 0.6 | BA29: 18.3 | BB29: 29.7 | BC29: 88.1 | BE29: 4.7 | BF29: 2.4 | BG29: 2.4 | BH29: 2.4 | BI29: 17.8 | BJ29: 1.2 | BL29: 20 | BM29: 9.1 | BN29: 18.8 | BO29: 1451.6
B30: 11:30 | C30: 16 | D30: 9.5 | E30: 7 | F30: 20.3 | H30: 0.4 | J30: 0.8 | K30: 19.8 | M30: 20.4 | N30: 20.3 | O30: 12.8 | P30: 3.4 | Q30: 5.2 | R30: 19.9 | S30: 20.2 | T30: 20 | U30: 19 | W30: 25 | X30: 123 | Y30: 83.6 | Z30: 78.7 | AA30: 36.7 | AB30: 3 | AC30: 7.4 | AD30: 21 | AE30: 4.3 | AF30: 20.4 | AG30: 20.4 | AH30: 20.2 | AI30: 8 | AJ30: 78.2 | AK30: 12.4 | AL30: 17.2 | AM30: 3.5 | AN30: 18.6 | AP30: 0.4 | AQ30: 0.6 | AR30: 17.7 | AS30: 14.7 | AT30: 5.6 | AU30: 10.3 | AV30: 89.5 | AW30: 151.4 | AX30: 90.9 | AY30: 112.4 | AZ30: 0.6 | BA30: 18.2 | BB30: 29.6 | BC30: 89.7 | BE30: 4.8 | BF30: 2.3 | BG30: 2.4 | BH30: 2.4 | BI30: 17.9 | BJ30: 1.2 | BL30: 19.9 | BM30: 8.9 | BN30: 18.1 | BO30: 1506.1
B31: 12:00 | C31: 16.1 | D31: 9.5 | E31: 5.5 | F31: 20.3 | H31: 0.4 | J31: 0.6 | K31: 19.8 | M31: 20.4 | N31: 20.3 | O31: 12.8 | P31: 3.4 | Q31: 5.2 | R31: 19.9 | S31: 20.3 | T31: 19.3 | U31: 19 | W31: 29.3 | X31: 126.6 | Y31: 78.9 | Z31: 73.5 | AA31: 28 | AB31: 2.6 | AC31: 8 | AD31: 21 | AE31: 4.3 | AF31: 20.4 | AG31: 20.4 | AH31: 20.2 | AI31: 8 | AJ31: 76.3 | AK31: 12.6 | AL31: 17.3 | AM31: 3.6 | AN31: 18.6 | AP31: 0.5 | AQ31: 0.6 | AR31: 18.2 | AS31: 15.2 | AT31: 5.1 | AU31: 10.4 | AV31: 101 | AW31: 121.3 | AX31: 113.4 | AY31: 97 | AZ31: 0.6 | BA31: 18.1 | BB31: 29.1 | BC31: 89.4 | BE31: 4.8 | BF31: 2.1 | BG31: 2.4 | BH31: 2.4 | BI31: 18.9 | BJ31: 1.2 | BL31: 20 | BM31: 8.9 | BN31: 18.6 | BO31: 1481.6
B32: 12:30 | C32: 16 | D32: 9.4 | E32: 5.5 | F32: 20.3 | H32: 0.4 | J32: 1.3 | K32: 19.8 | M32: 20.2 | N32: 20.2 | O32: 12.8 | P32: 3.4 | Q32: 5.2 | R32: 19.7 | S32: 19.9 | T32: 20 | U32: 19 | W32: 55.7 | X32: 128.9 | Y32: 75.9 | Z32: 69.1 | AA32: 25.1 | AB32: 2.5 | AC32: 8.8 | AD32: 21 | AE32: 4.3 | AF32: 20.4 | AG32: 20.4 | AH32: 20.2 | AI32: 7.9 | AJ32: 77.7 | AK32: 15.4 | AL32: 17.8 | AM32: 3.6 | AN32: 18.6 | AP32: 0.5 | AQ32: 0.6 | AR32: 18.1 | AS32: 15.2 | AT32: 5.4 | AU32: 10.4 | AV32: 120 | AW32: 127.9 | AX32: 122.1 | AY32: 94.1 | AZ32: 0.6 | BA32: 18 | BB32: 29.5 | BC32: 86.2 | BE32: 4.8 | BF32: 2 | BG32: 2.4 | BH32: 2.4 | BI32: 18.7 | BJ32: 1.3 | BL32: 19.8 | BM32: 9 | BN32: 18.9 | BO32: 1534.3
B33: 13:00 | C33: 16 | D33: 9.3 | E33: 6.6 | F33: 20.3 | H33: 0.4 | J33: 1 | K33: 19.8 | M33: 20.4 | N33: 20.3 | O33: 12.8 | P33: 3.4 | Q33: 5.2 | R33: 19.9 | S33: 20.4 | T33: 18.7 | U33: 19 | W33: 67.9 | X33: 124.1 | Y33: 71.3 | Z33: 67.7 | AA33: 30 | AB33: 6.6 | AC33: 10.2 | AD33: 21 | AE33: 7 | AF33: 20.4 | AG33: 20.4 | AH33: 20.2 | AI33: 7.8 | AJ33: 79.1 | AK33: 14.1 | AL33: 17.3 | AM33: 3.5 | AN33: 18.6 | AP33: 0.5 | AQ33: 0.6 | AR33: 17.1 | AS33: 15.1 | AT33: 5.5 | AU33: 10.4 | AV33: 114.2 | AW33: 149.7 | AX33: 121.5 | AY33: 108.8 | AZ33: 0.6 | BA33: 18 | BB33: 29.2 | BC33: 85.8 | BE33: 4.8 | BF33: 2 | BG33: 2.4 | BH33: 2.4 | BI33: 18.4 | BJ33: 1.3 | BL33: 20 | BM33: 9 | BN33: 18.9 | BO33: 1576.9
B34: 13:30 | C34: 16 | D34: 9.5 | E34: 7.2 | F34: 20.3 | H34: 0.4 | J34: 0.6 | K34: 19.8 | M34: 20.4 | N34: 20.3 | O34: 12.8 | P34: 3.4 | Q34: 5.2 | R34: 20 | S34: 20.1 | T34: 20 | U34: 19 | W34: 67.4 | X34: 128.3 | Y34: 64.1 | Z34: 62.1 | AA34: 33.8 | AB34: 5.7 | AC34: 8.6 | AD34: 21 | AE34: 8.1 | AF34: 20.4 | AG34: 20.4 | AH34: 20.2 | AI34: 7.5 | AJ34: 79 | AK34: 14.7 | AL34: 16.1 | AM34: 3.5 | AN34: 18.6 | AP34: 0.5 | AR34: 11.9 | AS34: 15.1 | AT34: 5.4 | AU34: 10.5 | AV34: 109.5 | AW34: 142.9 | AX34: 115.5 | AY34: 103.6 | AZ34: 0.6 | BA34: 17.8 | BB34: 29.2 | BC34: 85.7 | BE34: 4.8 | BF34: 2 | BG34: 2.4 | BH34: 2.4 | BI34: 17.7 | BJ34: 1.2 | BL34: 20 | BM34: 9 | BN34: 19 | BO34: 1541.2
B35: 14:00 | C35: 15.9 | D35: 9.5 | E35: 7.4 | F35: 20.3 | H35: 0.4 | J35: 0.7 | K35: 19.8 | M35: 20.4 | N35: 20.3 | O35: 12.8 | P35: 3.4 | Q35: 5.1 | R35: 20 | S35: 20.6 | T35: 19.9 | U35: 19 | W35: 75.2 | X35: 125 | Y35: 64.3 | Z35: 61.8 | AA35: 36.2 | AB35: 5.9 | AC35: 8.2 | AD35: 21 | AE35: 8.1 | AF35: 20.4 | AG35: 20.4 | AH35: 20.2 | AI35: 7.5 | AJ35: 76.3 | AK35: 13.8 | AL35: 17.3 | AM35: 3.5 | AN35: 18.6 | AP35: 0.3 | AR35: 14.2 | AS35: 15.1 | AT35: 5.5 | AU35: 10.4 | AV35: 99.3 | AW35: 128.5 | AX35: 106.9 | AY35: 93 | AZ35: 0.6 | BA35: 17.8 | BB35: 29.2 | BC35: 88.6 | BE35: 4.8 | BF35: 2 | BG35: 2.4 | BH35: 2.4 | BI35: 16.9 | BJ35: 1.2 | BL35: 20 | BM35: 8.9 | BN35: 19.1 | BO35: 1506.3
B36: 14:30 | C36: 16 | D36: 9.5 | E36: 6.8 | F36: 20.3 | G36: 3 | H36: 0.4 | J36: 0.5 | K36: 19.9 | M36: 20.2 | N36: 20.2 | O36: 12.8 | P36: 3.4 | Q36: 5.1 | R36: 20 | S36: 20 | T36: 20 | U36: 19 | W36: 79.6 | X36: 121.2 | Y36: 66.4 | Z36: 63.6 | AA36: 34.3 | AB36: 6 | AC36: 9 | AD36: 21 | AE36: 8.1 | AF36: 20.4 | AG36: 20.4 | AH36: 20.2 | AI36: 7.5 | AJ36: 76.3 | AK36: 14.7 | AL36: 17.2 | AM36: 3.6 | AN36: 18.6 | AP36: 0.2 | AR36: 14.9 | AS36: 15 | AT36: 5.5 | AU36: 10.3 | AV36: 129.1 | AW36: 143.4 | AX36: 123.3 | AY36: 104.4 | AZ36: 0.6 | BA36: 17.6 | BB36: 25.3 | BC36: 87.1 | BE36: 4.8 | BF36: 2 | BG36: 2.4 | BH36: 2.4 | BI36: 15.1 | BJ36: 1.2 | BL36: 20 | BM36: 9 | BN36: 19 | BO36: 1577.8
B37: 15:00 | C37: 16 | D37: 9.5 | E37: 6.3 | F37: 20.3 | G37: 3 | H37: 0.4 | J37: 0.6 | K37: 19.8 | M37: 20.3 | N37: 20.3 | O37: 12.8 | P37: 3.4 | Q37: 5.2 | R37: 20 | S37: 20.3 | T37: 18.2 | U37: 19 | W37: 75.7 | X37: 117.4 | Y37: 61.3 | Z37: 60.1 | AA37: 24.4 | AB37: 5.6 | AC37: 8 | AD37: 21 | AE37: 8.1 | AF37: 20.4 | AG37: 20.4 | AH37: 20.2 | AI37: 7.5 | AJ37: 74.6 | AK37: 14.1 | AL37: 18 | AM37: 3.6 | AN37: 18.6 | AP37: 0.1 | AR37: 12.9 | AS37: 14.7 | AT37: 5.5 | AU37: 10.5 | AV37: 136 | AW37: 141.1 | AX37: 125.5 | AY37: 102.8 | AZ37: 0.6 | BA37: 17.6 | BB37: 27.6 | BC37: 87.3 | BE37: 4.8 | BF37: 2 | BG37: 2.4 | BH37: 2.4 | BI37: 11.3 | BJ37: 1.2 | BL37: 20 | BM37: 8.9 | BN37: 18.6 | BO37: 1548.2
B38: 15:30 | C38: 16 | D38: 9.5 | E38: 6.5 | F38: 20.3 | G38: 3 | H38: 0.4 | J38: 0.4 | K38: 19.8 | M38: 20.3 | N38: 20.3 | O38: 12.8 | P38: 1.2 | Q38: 5.2 | R38: 20 | S38: 20.2 | T38: 20 | U38: 19 | W38: 77.5 | X38: 125 | Y38: 57.7 | Z38: 55.8 | AA38: 29 | AB38: 5.4 | AC38: 7.1 | AD38: 21 | AE38: 8.1 | AF38: 20.4 | AG38: 20.4 | AH38: 20.2 | AI38: 8 | AJ38: 71.7 | AK38: 14 | AL38: 16.5 | AM38: 3.6 | AN38: 18.6 | AP38: 0.1 | AR38: 11.3 | AS38: 14.1 | AT38: 5.5 | AU38: 10.3 | AV38: 136.3 | AW38: 136.6 | AX38: 125 | AY38: 99.1 | AZ38: 0.6 | BA38: 17 | BB38: 26.9 | BC38: 86 | BE38: 4.8 | BF38: 2.1 | BG38: 2.4 | BH38: 2.4 | BI38: 11.4 | BJ38: 1.2 | BL38: 20 | BM38: 8.9 | BN38: 17.6 | BO38: 1534.5
B39: 16:00 | C39: 16 | D39: 9.5 | E39: 6.5 | F39: 20.3 | G39: 2.8 | H39: 0.4 | J39: 0.4 | K39: 19.8 | M39: 20.3 | N39: 20.3 | O39: 12.8 | P39: 2.2 | Q39: 5.2 | R39: 19.9 | S39: 20.3 | T39: 17.9 | U39: 19 | W39: 78.1 | X39: 126.2 | Y39: 57.6 | Z39: 55.8 | AA39: 33.7 | AB39: 5.3 | AC39: 7.1 | AD39: 21 | AE39: 8.1 | AF39: 20.4 | AG39: 20.4 | AH39: 20.2 | AI39: 8 | AJ39: 66.4 | AK39: 14 | AL39: 15.4 | AM39: 3.6 | AN39: 18.6 | AQ39: 1.8 | AR39: 9.6 | AS39: 13.2 | AT39: 5.4 | AU39: 10.4 | AV39: 134.2 | AW39: 129.6 | AX39: 125.4 | AY39: 94 | AZ39: 0.6 | BA39: 16 | BB39: 26.6 | BC39: 88.6 | BE39: 4.8 | BF39: 2.1 | BG39: 2.4 | BH39: 2.4 | BI39: 9.4 | BJ39: 1.2 | BL39: 20 | BM39: 9 | BN39: 16.1 | BO39: 1516.3
B40: 16:30 | C40: 16.1 | D40: 9.3 | E40: 7 | F40: 19.8 | G40: 2.8 | H40: 0.4 | J40: 0.2 | K40: 19.9 | M40: 19.7 | N40: 19.9 | O40: 12.8 | P40: 2.7 | Q40: 5.2 | R40: 19.4 | S40: 19 | T40: 20 | U40: 19 | W40: 80.2 | X40: 121.7 | Y40: 66.6 | Z40: 64.7 | AA40: 24.9 | AB40: 6.4 | AC40: 8 | AD40: 21 | AE40: 8.1 | AF40: 20.4 | AG40: 20.4 | AH40: 20.2 | AI40: 8 | AJ40: 51.1 | AK40: 11.7 | AL40: 14.2 | AM40: 3.5 | AN40: 18.6 | AQ40: 1.8 | AR40: 4.9 | AS40: 11 | AT40: 5.4 | AU40: 10.3 | AV40: 147.5 | AW40: 48.5 | AX40: 129.1 | AY40: 82.4 | AZ40: 0.6 | BA40: 13.2 | BB40: 28.8 | BC40: 88.1 | BE40: 4.8 | BF40: 2.6 | BG40: 2.4 | BH40: 2.4 | BI40: 3.8 | BJ40: 1.2 | BL40: 19.6 | BM40: 9 | BN40: 12.6 | BO40: 1412.9
B41: 17:00 | C41: 16 | D41: 9.3 | E41: 6.6 | F41: 20.3 | G41: 2.8 | H41: 0.4 | J41: 0.1 | K41: 19.8 | M41: 20.2 | N41: 20.2 | O41: 12.8 | P41: 2.6 | Q41: 5.2 | R41: 19.6 | S41: 20.1 | T41: 19.7 | U41: 19 | W41: 80.4 | X41: 117.8 | Y41: 67.7 | Z41: 67.3 | AA41: 13.4 | AB41: 5.7 | AC41: 5.1 | AD41: 21 | AE41: 8.3 | AF41: 20.4 | AG41: 20.4 | AH41: 20.2 | AI41: 8 | AJ41: 28.1 | AK41: 11.5 | AL41: 13 | AM41: 3.5 | AN41: 18.6 | AQ41: 1.8 | AR41: 4.3 | AS41: 5 | AT41: 5.5 | AU41: 10.3 | AV41: 139.1 | AW41: 47.6 | AX41: 131 | AY41: 39.4 | AZ41: 0.6 | BA41: 5.8 | BB41: 23 | BC41: 87.7 | BE41: 4.8 | BF41: 2.6 | BG41: 2.4 | BH41: 2.4 | BI41: 2.1 | BJ41: 1.3 | BL41: 19.8 | BM41: 9 | BN41: 4.7 | BO41: 1295.3
B42: 17:30 | C42: 16 | D42: 9.2 | E42: 6.1 | F42: 20.4 | G42: 3 | H42: 0.5 | K42: 19.8 | M42: 20.3 | N42: 20.3 | O42: 12.8 | P42: 3.1 | Q42: 5.2 | R42: 19.8 | S42: 20.2 | T42: 20 | U42: 19 | W42: 75.9 | X42: 114.5 | Y42: 80.7 | Z42: 89.3 | AA42: 1.5 | AB42: 7.4 | AC42: 9.9 | AD42: 21 | AE42: 8.4 | AF42: 20.4 | AG42: 20.4 | AH42: 20.2 | AI42: 8 | AJ42: 11.2 | AK42: 9 | AL42: 11.7 | AM42: 3.6 | AN42: 18.6 | AQ42: 1.8 | AR42: 1.9 | AS42: 0.5 | AT42: 5.5 | AU42: 10.3 | AV42: 153 | AW42: 12.6 | AX42: 132.1 | AY42: 13.5 | AZ42: 0.6 | BA42: 0.4 | BB42: 25.9 | BC42: 88.7 | BE42: 4.8 | BF42: 2.6 | BG42: 2.4 | BH42: 2.4 | BI42: 1.9 | BJ42: 1.2 | BL42: 19.8 | BM42: 8.9 | BN42: 0.2 | BO42: 1238.4
B43: 18:00 | C43: 16 | D43: 9.3 | E43: 6.4 | F43: 20.5 | G43: 3 | H43: 0.5 | K43: 19.8 | M43: 20.2 | N43: 20.3 | O43: 12.8 | P43: 3.4 | Q43: 5.2 | R43: 20 | S43: 20.3 | T43: 20 | U43: 19 | W43: 70.9 | X43: 104.2 | Y43: 83.3 | Z43: 91.4 | AB43: 5.8 | AC43: 7.7 | AD43: 21 | AE43: 8.4 | AF43: 20.4 | AG43: 20.4 | AH43: 20.2 | AI43: 8 | AK43: 8 | AL43: 13.3 | AM43: 3.6 | AN43: 18.6 | AQ43: 1.8 | AR43: 0.2 | AT43: 5.4 | AU43: 10.4 | AV43: 137.2 | AX43: 131.5 | AZ43: 0.6 | BB43: 25.3 | BC43: 82.7 | BE43: 4.8 | BF43: 2.6 | BG43: 2.4 | BH43: 2.4 | BI43: 0.1 | BJ43: 1.3 | BL43: 20 | BM43: 8.9 | BO43: 1159.5
B44: 18:30 | C44: 15.8 | D44: 9.4 | E44: 6.1 | F44: 20.5 | G44: 2.8 | H44: 0.5 | K44: 19.8 | M44: 20.3 | N44: 20.3 | O44: 12.8 | P44: 3.5 | Q44: 5.2 | R44: 20 | S44: 20.4 | T44: 19.6 | U44: 19 | W44: 66 | X44: 87.1 | Y44: 62.7 | Z44: 90 | AB44: 4 | AC44: 7.2 | AD44: 21 | AE44: 8.4 | AF44: 20.4 | AG44: 20.4 | AH44: 20.2 | AI44: 8 | AK44: 6.3 | AL44: 12.6 | AM44: 3.6 | AN44: 18.5 | AQ44: 1.8 | AT44: 5.5 | AU44: 10.3 | AV44: 116.4 | AX44: 129.8 | AZ44: 0.6 | BB44: 26.8 | BC44: 79.4 | BE44: 4.8 | BF44: 2.6 | BG44: 2.4 | BH44: 2.4 | BJ44: 1.3 | BL44: 20 | BM44: 9 | BO44: 1085.5
B45: 19:00 | C45: 15.9 | D45: 9.6 | E45: 6.4 | F45: 20.5 | G45: 3 | H45: 0.5 | K45: 19.8 | M45: 20.2 | N45: 20.3 | O45: 12.8 | P45: 3.5 | Q45: 5.1 | R45: 20 | S45: 20.3 | T45: 20 | U45: 19 | W45: 69.3 | X45: 82.6 | Y45: 55.2 | Z45: 85.9 | AB45: 5.4 | AC45: 5.8 | AD45: 21 | AE45: 8.4 | AF45: 20.4 | AG45: 20.4 | AH45: 20.2 | AI45: 6.3 | AK45: 7.3 | AL45: 13.4 | AM45: 3.5 | AN45: 18.6 | AQ45: 1.8 | AT45: 5.4 | AU45: 10.5 | AV45: 94 | AX45: 125.1 | AZ45: 0.6 | BB45: 20.5 | BC45: 68.2 | BE45: 4.8 | BF45: 2.6 | BG45: 2.4 | BH45: 2.4 | BJ45: 1.3 | BL45: 20 | BM45: 8.8 | BO45: 1029
B46: 19:30 | C46: 16 | D46: 9.6 | E46: 6.6 | F46: 20.5 | G46: 3 | H46: 0.4 | K46: 19.8 | M46: 20.2 | N46: 20.3 | O46: 12.8 | P46: 3.5 | Q46: 5 | R46: 20 | S46: 20.2 | T46: 19.9 | U46: 18.9 | V46: 1.8 | W46: 64.2 | X46: 75.9 | Y46: 65.9 | Z46: 85.7 | AB46: 3.1 | AC46: 3.6 | AD46: 21 | AE46: 8.4 | AF46: 20.4 | AG46: 20.4 | AH46: 20.2 | AI46: 4.4 | AK46: 6.4 | AL46: 11 | AM46: 3.5 | AN46: 18.6 | AQ46: 1.8 | AT46: 5.5 | AU46: 10.4 | AV46: 64.6 | AX46: 98.9 | AZ46: 0.6 | BB46: 24.3 | BC46: 63.2 | BE46: 4.8 | BF46: 2.6 | BG46: 2.4 | BH46: 2.4 | BJ46: 1.2 | BL46: 20 | BM46: 8.9 | BO46: 962.8
B47: 20:00 | C47: 16 | D47: 9.6 | E47: 7 | F47: 20.5 | G47: 3 | H47: 0.3 | K47: 19.8 | M47: 20.3 | N47: 20.3 | O47: 12.8 | P47: 3.5 | Q47: 5 | R47: 20 | S47: 20.2 | T47: 20 | U47: 19 | V47: 3.3 | W47: 63.7 | X47: 58.9 | Y47: 71.5 | Z47: 91.5 | AB47: 6.3 | AC47: 6.1 | AD47: 21 | AE47: 8.4 | AF47: 20.4 | AG47: 20.4 | AH47: 20.2 | AI47: 6.3 | AK47: 7.7 | AL47: 14.5 | AM47: 3.5 | AN47: 18.6 | AQ47: 1.8 | AT47: 5.4 | AU47: 10.3 | AV47: 66.7 | AX47: 77.6 | AZ47: 0.6 | BB47: 17.3 | BC47: 49 | BE47: 4.8 | BF47: 2.6 | BG47: 2.4 | BH47: 2.4 | BJ47: 1.3 | BL47: 20 | BM47: 9 | BO47: 930.8
B48: 20:30 | C48: 16 | D48: 9.5 | E48: 7.1 | F48: 20.5 | G48: 3 | H48: 0.3 | K48: 19.8 | M48: 20.3 | N48: 20.3 | O48: 12.8 | P48: 3.5 | Q48: 5 | R48: 20 | S48: 20.2 | T48: 20 | U48: 19 | V48: 3.6 | W48: 55.6 | X48: 52.7 | Y48: 46.2 | Z48: 70.5 | AB48: 3 | AC48: 3.7 | AD48: 21 | AE48: 8.4 | AF48: 20.4 | AG48: 20.4 | AH48: 20.2 | AI48: 7.8 | AK48: 10 | AL48: 12.6 | AM48: 3.5 | AN48: 18.6 | AQ48: 1.8 | AT48: 5.4 | AU48: 10.4 | AV48: 42.3 | AX48: 56.6 | AZ48: 0.6 | BB48: 10.9 | BC48: 45.4 | BE48: 4.8 | BF48: 2.6 | BG48: 2.4 | BH48: 2.4 | BJ48: 1.2 | BL48: 20 | BM48: 9 | BO48: 811.3
B49: 21:00 | C49: 16 | D49: 9.4 | E49: 7.3 | F49: 20.5 | G49: 3 | H49: 0.3 | K49: 19.8 | M49: 20.4 | N49: 20.3 | O49: 12.9 | P49: 3.5 | Q49: 5.1 | R49: 20 | S49: 20.3 | T49: 20 | U49: 18.9 | V49: 2.9 | W49: 60.8 | X49: 57.6 | Y49: 51 | Z49: 74.2 | AB49: 2.7 | AC49: 3.6 | AD49: 21 | AE49: 8.4 | AF49: 20.4 | AG49: 20.4 | AH49: 20.2 | AI49: 7.2 | AK49: 10.8 | AL49: 13.3 | AM49: 3.5 | AN49: 18.6 | AQ49: 1.8 | AT49: 5.5 | AU49: 10.3 | AV49: 48.7 | AX49: 58 | AZ49: 0.6 | BB49: 12.6 | BC49: 43.6 | BE49: 4.8 | BF49: 2.6 | BG49: 2.4 | BH49: 2.4 | BJ49: 1.3 | BL49: 20 | BM49: 8.9 | BO49: 837.8
B50: 21:30 | C50: 16 | D50: 9.5 | E50: 6.7 | F50: 20.5 | G50: 3 | H50: 0.3 | K50: 19.8 | M50: 20.2 | N50: 20.3 | O50: 12.9 | P50: 3.4 | Q50: 5 | R50: 20 | S50: 20.5 | T50: 20 | U50: 18.9 | V50: 1.8 | W50: 53.2 | X50: 91.3 | Y50: 61.8 | Z50: 85.7 | AB50: 2.8 | AC50: 6 | AD50: 21 | AE50: 8.4 | AF50: 20.4 | AG50: 20.4 | AH50: 20.2 | AI50: 7.2 | AK50: 9.4 | AL50: 11.8 | AM50: 3.5 | AN50: 18.6 | AQ50: 1.8 | AT50: 5.4 | AU50: 10.4 | AV50: 51.6 | AX50: 62.2 | AZ50: 0.6 | BB50: 21.2 | BC50: 56.7 | BE50: 4.8 | BF50: 2.6 | BG50: 2.4 | BH50: 2.4 | BJ50: 1.2 | BL50: 20 | BM50: 8.9 | BO50: 912.7
B51: 22:00 | C51: 15.9 | D51: 9.5 | E51: 6.8 | F51: 20.5 | G51: 3 | H51: 0.3 | K51: 19.8 | M51: 20.4 | N51: 20.3 | O51: 12.8 | P51: 3.4 | Q51: 5 | R51: 20 | S51: 20.2 | T51: 20 | U51: 19.1 | V51: 0.9 | W51: 41.3 | X51: 99.5 | Y51: 45.3 | Z51: 71.7 | AB51: 3.6 | AC51: 3.9 | AD51: 21 | AE51: 8.4 | AF51: 20.4 | AG51: 20.4 | AH51: 20.2 | AI51: 6.3 | AK51: 12.4 | AL51: 12.6 | AM51: 3.5 | AN51: 18.6 | AQ51: 1.8 | AT51: 5.5 | AU51: 10.3 | AV51: 54.2 | AX51: 72.5 | AZ51: 0.6 | BB51: 22.9 | BC51: 67.2 | BE51: 4.8 | BF51: 2.6 | BG51: 2.4 | BH51: 2.4 | BJ51: 1.3 | BL51: 20 | BM51: 8.9 | BO51: 904.4
B52: 22:30 | C52: 16 | D52: 9.6 | E52: 6.5 | F52: 20.4 | G52: 3 | H52: 0.3 | K52: 19.8 | M52: 20.3 | N52: 20.3 | O52: 12.8 | P52: 3.5 | Q52: 5 | R52: 20 | S52: 20.3 | T52: 20 | U52: 19.2 | V52: 0.3 | W52: 31.7 | X52: 99.4 | Y52: 40.8 | Z52: 63.9 | AB52: 2 | AC52: 2.5 | AD52: 21 | AE52: 8.4 | AF52: 20.4 | AG52: 20.4 | AH52: 20.2 | AI52: 6.2 | AK52: 10.3 | AL52: 13.1 | AM52: 3.5 | AN52: 18.6 | AQ52: 1.8 | AT52: 5.5 | AU52: 10.4 | AV52: 39 | AX52: 49.3 | AZ52: 0.6 | BB52: 24 | BC52: 67 | BE52: 4.8 | BF52: 2.6 | BG52: 2.4 | BH52: 2.4 | BJ52: 1.2 | BL52: 20 | BM52: 8.9 | BO52: 839.6
B53: 23:00 | C53: 16 | D53: 9.5 | E53: 7 | F53: 20.3 | G53: 3 | H53: 0.3 | K53: 19.8 | M53: 20.1 | N53: 20.2 | O53: 12.8 | P53: 3.5 | Q53: 5.1 | R53: 19.8 | S53: 19.9 | T53: 20 | U53: 19.2 | V53: 0.5 | W53: 32.2 | X53: 96.4 | Y53: 45.3 | Z53: 74.1 | AB53: 2.7 | AC53: 1.3 | AD53: 21 | AE53: 8.4 | AF53: 20.4 | AG53: 20.4 | AH53: 20.2 | AI53: 6.2 | AK53: 10 | AL53: 12.5 | AM53: 3.5 | AN53: 18.6 | AQ53: 1.8 | AT53: 5.3 | AU53: 10.4 | AV53: 41.6 | AX53: 54.4 | AZ53: 0.6 | BB53: 27.2 | BC53: 62.6 | BE53: 4.8 | BF53: 2.6 | BG53: 2.4 | BH53: 2.4 | BJ53: 1.2 | BL53: 19.9 | BM53: 8.8 | BO53: 856.2
B54: 23:30 | C54: 15.9 | D54: 9.3 | E54: 7.2 | F54: 20.3 | G54: 3 | H54: 0.3 | K54: 19.8 | M54: 20.3 | N54: 20.4 | O54: 12.9 | P54: 3.5 | Q54: 5.1 | R54: 20 | S54: 20.6 | T54: 19.7 | U54: 19.2 | V54: 0.2 | W54: 30.3 | X54: 91.5 | Y54: 47.9 | Z54: 73.6 | AB54: 3.3 | AC54: 1.6 | AD54: 21 | AE54: 8.4 | AF54: 20.4 | AG54: 20.4 | AH54: 20.2 | AI54: 6.7 | AK54: 12.3 | AL54: 15.9 | AM54: 3.5 | AN54: 18.6 | AQ54: 1.8 | AT54: 5.4 | AU54: 10.3 | AV54: 40.3 | AX54: 46.4 | AZ54: 0.6 | BB54: 25.6 | BC54: 56.4 | BE54: 4.8 | BF54: 2.6 | BG54: 2.4 | BH54: 2.4 | BJ54: 1.3 | BL54: 20 | BM54: 8.9 | BO54: 842.5
B55: 0:00 | C55: 16 | D55: 9.3 | E55: 7 | F55: 20.3 | G55: 2 | H55: 0.3 | K55: 19.8 | M55: 20.3 | N55: 20.3 | O55: 13 | P55: 3.5 | Q55: 5 | R55: 20 | S55: 20 | T55: 20 | U55: 19.1 | V55: 0.6 | W55: 25.9 | X55: 90.3 | Y55: 41.5 | Z55: 72.6 | AB55: 2.1 | AC55: 2.1 | AD55: 21 | AE55: 8.4 | AF55: 20.4 | AG55: 20.4 | AH55: 20.2 | AI55: 6.6 | AK55: 9.6 | AL55: 13.8 | AM55: 3.5 | AN55: 18.6 | AQ55: 1.8 | AT55: 5.5 | AU55: 10.4 | AV55: 32.2 | AX55: 42.7 | AZ55: 0.6 | BB55: 18.2 | BC55: 50.3 | BE55: 4.8 | BF55: 2.6 | BG55: 2.4 | BH55: 2.4 | BJ55: 1.3 | BL55: 20 | BM55: 8.9 | BO55: 797.6
B56: EJEC MWh | C56: 378.35 | D56: 228.2 | E56: 162.35 | F56: 487.95 | G56: 57.65 | H56: 5.2 | I56: 0 | J56: 6.5 | K56: 475.3 | L56: 0 | M56: 482.7 | N56: 486.7 | O56: 308.6 | P56: 78.55 | Q56: 123.2 | R56: 478.5 | S56: 484.85 | T56: 462.45 | U56: 456.15 | V56: 81.25 | W56: 947.85 | X56: 2515.75 | Y56: 1215.4 | Z56: 1579.6 | AA56: 320.4 | AB56: 76.25 | AC56: 94.85 | AD56: 504 | AE56: 148.35 | AF56: 489.6 | AG56: 489.6 | AH56: 484.8 | AI56: 176.75 | AJ56: 706.85 | AK56: 282 | AL56: 365.15 | AM56: 84.35 | AN56: 446.35 | AO56: 0 | AP56: 2.55 | AQ56: 32.7 | AR56: 127.8 | AS56: 149.75 | AT56: 131.15 | AU56: 248.85 | AV56: 1588.45 | AW56: 1270.55 | AX56: 1733.45 | AY56: 961.9 | AZ56: 14.4 | BA56: 179.7 | BB56: 658.15 | BC56: 1816.05 | BD56: 0 | BE56: 115.15 | BF56: 58.55 | BG56: 57.6 | BH56: 57.6 | BI56: 132.7 | BJ56: 28.4 | BK56: 0 | BL56: 479 | BM56: 215.1 | BN56: 156.3 | BO56: 26388.2
L70: TERMOELÉCTRICA | M70: 1057.8 | N70: 4.0086099 | O70: #FF0000
L71: SOLAR | M71: 4015 | N71: 15.215134 | O71: #FBFB00
L72: HIDROELÉCTRICA | M72: 8361.2 | N72: 31.685375 | O72: #00B0F0
L73: EÓLICA | M73: 12954.2 | N73: 49.090882 | O73: #FBBD00

Sheet COGENERACIÓN
B3: jueves, 20 de Marzo del 2025
B5: CENTRALES DE COGENERACIÓN DEL SEIN
B6: HORA | C6: AGRO INDUSTRIAL PARAMONGA S.A. | D6: AGROAURORA S.A.C. | E6: AGROINDUSTRIAS SAN JACINTO S.A.A. | F6: BIOENERGIA DEL CHIRA S.A. | G6: GM OPERACIONES S.A.C. | H6: SDF ENERGIA SAC | I6: TOTAL COGENERACION
C7: C.T. PARAMONGA | D7: C.T. MAPLE | E7: C.T SAN JACINTO | F7: C.T. CAÑA BRAVA | G7: C.T. REFINERÍA TALARA | H7: C.T. OQUENDO | I7: MW
B8: 0:30 | C8: 15.5 | D8: 9.6 | E8: 7.2 | G8: 68.3 | H8: 32.3 | I8: 132.9
B9: 1:00 | C9: 15.4 | D9: 9.6 | E9: 6.7 | G9: 68.5 | H9: 32.2 | I9: 132.4
B10: 1:30 | C10: 15.5 | D10: 9.5 | E10: 7 | G10: 68.8 | H10: 32.4 | I10: 133.2
B11: 2:00 | C11: 15.5 | D11: 9.6 | E11: 7.3 | G11: 67.1 | H11: 32.4 | I11: 131.9
B12: 2:30 | C12: 15.5 | D12: 9.6 | E12: 6.3 | G12: 68 | H12: 32.5 | I12: 131.9
B13: 3:00 | C13: 15.5 | D13: 9.6 | E13: 6.9 | G13: 68 | H13: 32.5 | I13: 132.5
B14: 3:30 | C14: 15.4 | D14: 9.6 | E14: 7.2 | G14: 67.3 | H14: 32.4 | I14: 131.9
B15: 4:00 | C15: 15.5 | D15: 9.6 | E15: 6.4 | G15: 67.4 | H15: 32.4 | I15: 131.3
B16: 4:30 | C16: 15.5 | D16: 9.6 | E16: 6.7 | G16: 67.5 | H16: 32.5 | I16: 131.8
B17: 5:00 | C17: 15.6 | D17: 9.6 | E17: 6.8 | G17: 67 | H17: 32.3 | I17: 131.3
B18: 5:30 | C18: 15.5 | D18: 9.6 | E18: 6.7 | G18: 67.2 | H18: 32.5 | I18: 131.5
B19: 6:00 | C19: 15.6 | D19: 9.6 | E19: 7.1 | G19: 67.5 | H19: 32.4 | I19: 132.2
... B55: 0:00 | C55: 16 | D55: 9.3 | E55: 7 | G55: 69.6 | H55: 32.1 | I55: 134
B56: EJEC MWh | C56: 378.35 | D56: 228.2 | E56: 162.35 | F56: 0 | G56: 1645.65 | H56: 767.4 | I56: 3181.95

Sheet EVO_PRO_ENE
B3: sábado, 1 de Marzo del 2025 - jueves, 20 de Marzo del 2025
B5: EVOLUCIÓN DE LA PRODUCCIÓN DE LA ENERGÍA DIARIA DE LOS INTEGRANTES DEL COES (MWh)
B6: EMPRESA | C6: CENTRAL | D6: UNIDAD | E6: TIPO | F6: Marzo
F7: 1 | G7: 2 | H7: 3 | I7: 4 | J7: 5 | K7: 6 | L7: 7 | M7: 8 | N7: 9 | O7: 10 | P7: 11 | Q7: 12 | R7: 13 | S7: 14 | T7: 15 | U7: 16 | V7: 17 | W7: 18 | X7: 19 | Y7: 20 | Z7: TOTAL
B8: AGRO INDUSTRIAL PARAMONGA S.A. | C8: C.T. PARAMONGA | D8: TV-01 | E8: TERMOELÉCTRICA | T8: 82.25 | U8: 328.35 | V8: 359.55 | W8: 364.3 | X8: 368.25 | Y8: 378.35 | Z8: 1881.05
B9: AGROAURORA S.A.C. | C9: C.T. MAPLE ETANOL | D9: TV | E9: TERMOELÉCTRICA | F9: 248 | G9: 283.07 | H9: 247.43 | I9: 287.315 | J9: 291.3 | K9: 307.1 | L9: 294.95 | M9: 188.3 | N9: 194.25 | O9: 229.85 | P9: 227 | Q9: 108.25 | T9: 123.75 | U9: 229.1 | V9: 228.6 | W9: 228.35 | X9: 228.75 | Y9: 228.2 | Z9: 4173.565
B10: AGROINDUSTRIAS SAN JACINTO S.A.A. | C10: C.T. SAN JACINTO | D10: CENTRAL | E10: TERMOELÉCTRICA | F10: 164.55 | G10: 162.075 | H10: 155.435 | I10: 156.885 | J10: 153.6 | K10: 142.2 | L10: 152.8 | M10: 152.8 | N10: 112.85 | O10: 152 | P10: 162.1 | Q10: 170.35 | R10: 173.4 | S10: 168.65 | T10: 167.85 | U10: 103.45 | W10: 6.25 | X10: 133.75 | Y10: 162.35 | Z10: 2753.345
B11: ANDEAN POWER S.A.C. | C11: C.H. CARHUAC | D11: CENTRAL | E11: HIDROELÉCTRICA | F11: 478.15 | G11: 481.675 | H11: 485.209 | I11: 486.023 | J11: 409.85 | K11: 486.85 | L11: 488.3 | M11: 487.7 | N11: 486.15 | O11: 487.5 | P11: 487.3 | Q11: 488.7 | R11: 488 | S11: 487.95 | T11: 487.5 | U11: 487.2 | V11: 488.5 | W11: 488.95 | X11: 488.1 | Y11: 487.95 | Z11: 9657.557
B12: ASOCIACIÓN SANTA LUCIA DE CHACAS | C12: C.H. HUALLIN | D12: CENTRAL | E12: HIDROELÉCTRICA | F12: 34 | G12: 47.44 | H12: 32.698 | I12: 38.556 | J12: 39.65 | K12: 29.25 | L12: 27.55 | M12: 32.35 | N12: 49.4 | O12: 57.15 | P12: 50.35 | Q12: 52.2 | R12: 70.4 | S12: 71.5 | T12: 71.7 | U12: 71.9 | V12: 71.95 | W12: 72 | X12: 71.35 | Y12: 57.65 | Z12: 1049.044
B13: ATRIA ENERGIA S.A.C. | C13: C.H. PURMACANA | D13: CENTRAL | E13: HIDROELÉCTRICA | F13: 7.2 | G13: 3.25 | I13: 1.1045 | J13: 2.3 | L13: 2.05 | M13: 0.1 | O13: 0.85 | S13: 3.3 | T13: 4.35 | W13: 1.15 | Y13: 5.2 | Z13: 30.8545
B14: BIOENERGIA DEL CHIRA S.A. | C14: C.T. CAÑA BRAVA | D14: CENTRAL | E14: TERMOELÉCTRICA | Z14: 0
B15: CELEPSA | C15: C.H. EL PLATANAL | D15: CENTRAL | E15: HIDROELÉCTRICA | F15: 5202.15 | G15: 5150.6494 | H15: 5193.4355 | I15: 4494.7598 | J15: 3066.7 | K15: 5091.6 | L15: 4440.85 | M15: 5339.05 | N15: 5258.85 | O15: 4801.8 | P15: 4972.45 | Q15: 4841.95 | R15: 4786.4 | S15: 4964.05 | T15: 4829.15 | U15: 3646.65 | V15: 5205.85 | W15: 4695.6 | X15: 5147.35 | Y15: 5344 | Z15: 96473.295
B16: CELEPSA RENOVABLES S.R.L. | C16: C.H. MARAÑON | D16: CENTRAL | E16: HIDROELÉCTRICA | F16: 17.65 | G16: 170.67622 | H16: 416.9567 | L16: 62.25 | M16: 472.8 | N16: 472.8 | O16: 472.9 | P16: 470.35 | Q16: 472.8 | R16: 469.65 | S16: 382.35 | T16: 373.4 | U16: 212.25 | V16: 393.8 | W16: 474.95 | X16: 472.1 | Y16: 472.75 | Z16: 6280.4329
B17: CENTRALES SANTA ROSA S.A.C. | C17: C.H. SANTA ROSA I | D17: CENTRAL | E17: HIDROELÉCTRICA | F17: 23.45 | G17: 21.818685 | H17: 24.70173 | I17: 25.127895 | J17: 25.2 | K17: 23.45 | L17: 21.8 | M17: 22 | N17: 22.9 | O17: 23.7 | P17: 24.4 | Q17: 25.05 | R17: 23.2 | S17: 23.4 | T17: 23.65 | U17: 12.05 | V17: 0.866085 | W17: 3.4 | X17: 2.35 | Y17: 4.05 | Z17: 376.56439
B18: CENTRALES SANTA ROSA S.A.C. | C18: C.H. SANTA ROSA II | D18: CENTRAL | E18: HIDROELÉCTRICA | F18: 37 | G18: 38.079535 | H18: 37.97834 | I18: 38.746845 | J18: 38.45 | K18: 35.65 | L18: 34.65 | M18: 34.4 | N18: 33.5 | O18: 36.95 | P18: 36.25 | Q18: 15.9 | R18: 34.35 | S18: 36.8 | T18: 37.25 | U18: 23.75 | V18: 3.28202 | W18: 14.15 | X18: 5.8 | Y18: 14.3 | Z18: 587.23674
B19: CHINANGO S.A.C. | C19: C.H. CHIMAY | D19: CENTRAL | E19: HIDROELÉCTRICA | F19: 3492.5 | G19: 3496.9515 | H19: 3533.8086 | I19: 3514.6025 | J19: 3473.8 | K19: 3549.4 | L19: 3335.25 | M19: 3417.2 | N19: 3420.1 | O19: 1744 | P19: 3447.8 | Q19: 3405.2 | R19: 3368.35 | S19: 1564.35 | T19: 3415.65 | U19: 3372 | V19: 3287.05 | W19: 3315.35 | X19: 3367.2 | Y19: 3303.4 | Z19: 64823.963
B20: CHINANGO S.A.C. | C20: C.H. YANANGO | D20: CENTRAL | E20: HIDROELÉCTRICA | F20: 1014.75 | G20: 1014.6382 | H20: 997.45541 | I20: 1013.5946 | J20: 561.5 | K20: 358.45 | N20: 212.15 | P20: 45.3 | Q20: 339.9 | R20: 994.55 | S20: 524.4 | T20: 1017.35 | U20: 1016.1 | V20: 1015.45 | W20: 1014.8 | X20: 1014.1 | Y20: 632.2 | Z20: 12786.688
B21: COLCA SOLAR S.A.C. | C21: C.S. YARUCAYA | D21: CENTRAL | E21: SOLAR | F21: 5.85 | G21: 4.23 | H21: 4.03 | I21: 5.56 | J21: 4.95 | K21: 4.35 | L21: 7.2 | M21: 4.65 | N21: 6.75 | O21: 7.55 | P21: 6.65 | Q21: 7.45 | R21: 6.2 | S21: 6.5 | T21: 5 | U21: 4.8 | V21: 6.55 | W21: 4.3 | X21: 6.7 | Y21: 6.5 | Z21: 115.77
B22: EGASA | C22: C.H. CHARCANI III | D22: CENTRAL | E22: HIDROELÉCTRICA | F22: 153.4 | G22: 145.4 | H22: 152.59 | I22: 153.095 | J22: 145.05 | K22: 152.6 | L22: 136.15 | M22: 101.85 | N22: 152.845 | O22: 107.35 | P22: 109.7 | Q22: 151.9 | R22: 159.9 | S22: 153.7 | T22: 148.95 | U22: 149.15 | V22: 160.6 | W22: 152.25 | X22: 153.9 | Y22: 154.4 | Z22: 2894.78
B23: EGASA | C23: C.H. CHARCANI IV | D23: CENTRAL | E23: HIDROELÉCTRICA | O23: 30.2 | P23: 160.15 | Q23: 177 | R23: 182.3 | S23: 190.5 | T23: 166.45 | U23: 166.7 | V23: 207.3 | W23: 207.75 | X23: 223.75 | Y23: 241.4 | Z23: 1953.5
B24: EGASA | C24: C.H. CHARCANI V | D24: CENTRAL | E24: HIDROELÉCTRICA | F24: 3441.6 | G24: 3441.145 | H24: 3291.375 | I24: 3290.875 | J24: 3400.15 | K24: 3440.25 | L24: 3441.15 | M24: 2960.8 | N24: 3433.535 | O24: 3430.35 | P24: 3436.45 | Q24: 3437.55 | R24: 3431.9 | S24: 3437.4 | T24: 3434.05 | U24: 3433.6 | V24: 3434.5 | W24: 3441.25 | X24: 3436.8 | Y24: 3444.35 | Z24: 67939.08
B25: EGASA | C25: C.H. CHARCANI VI | D25: CENTRAL | E25: HIDROELÉCTRICA | F25: 164.4 | G25: 161.315 | H25: 166.855 | I25: 122.535 | J25: 171.6 | K25: 189.65 | L25: 121.1 | M25: 41.35 | N25: 99.37 | O25: 99.8 | P25: 114.8 | Q25: 105.5 | R25: 109.55 | S25: 100.8 | T25: 97.55 | U25: 99.85 | V25: 215.5 | W25: 212.05 | X25: 209.4 | Y25: 211.85 | Z25: 2814.825
B26: EGASA | C26: C.T. CHILINA DIESEL | D26: CENTRAL | E26: TERMOELÉCTRICA | Z26: 0
B27: EGASA | C27: C.T. CHILINA DIESEL | D27: TG | E27: TERMOELÉCTRICA | Z27: 0
B28: EGASA | C28: C.T. MOLLENDO DIESEL | D28: CENTRAL | E28: TERMOELÉCTRICA | K28: 18.45 | R28: 21.25 | Z28: 39.7
B29: EGEJUNIN | C29: C.H. HUASAHUASI I | D29: CENTRAL | E29: HIDROELÉCTRICA | F29: 475.45 | G29: 476.6105 | H29: 476.5165 | I29: 476.589 | J29: 476.8 | K29: 386.65 | L29: 451.15 | M29: 475.45 | N29: 475.6 | O29: 475.45 | P29: 475.55 | Q29: 475.5 | R29: 475.6 | S29: 475.95 | T29: 475.6 | U29: 475.35 | V29: 475.5 | W29: 475.4 | X29: 475.25 | Y29: 475.3 | Z29: 9401.266
B30: EGEJUNIN | C30: C.H. RUNATULLO II | D30: CENTRAL | E30: HIDROELÉCTRICA | F30: 478.3 | G30: 478.82 | H30: 479.35 | I30: 480.04 | J30: 480.05 | K30: 432.7 | L30: 479.45 | M30: 479.25 | N30: 371.55 | O30: 479.85 | P30: 480.8 | Q30: 480.05 | R30: 480.4 | S30: 482.35 | T30: 480.25 | U30: 477.55 | V30: 480.2 | W30: 478.2 | X30: 482.05 | Y30: 482.7 | Z30: 9443.91
B31: EGEJUNIN | C31: C.H. RUNATULLO III | D31: CENTRAL | E31: HIDROELÉCTRICA | F31: 487.45 | G31: 487.64 | H31: 487.09 | I31: 487.025 | J31: 486.4 | K31: 441.15 | L31: 487.3 | M31: 487.2 | N31: 412.75 | O31: 486.65 | P31: 486.25 | Q31: 486.85 | R31: 486.6 | S31: 486.25 | T31: 486.5 | U31: 486.95 | V31: 487 | W31: 486.9 | X31: 486.9 | Y31: 486.7 | Z31: 9617.555
B32: EGEJUNIN | C32: C.H. SANTA CRUZ I | D32: CENTRAL | E32: HIDROELÉCTRICA | F32: 295.15 | G32: 232.5675 | L32: 25.6 | M32: 253.8 | N32: 309.2 | O32: 248.85 | P32: 310 | Q32: 311.9 | R32: 287.95 | S32: 260.5 | T32: 308.4 | U32: 309.9 | V32: 301.4 | W32: 306.45 | X32: 310.1 | Y32: 308.6 | Z32: 4380.3675
B33: EGEMSA | C33: C.H. MACHUPICCHU | D33: CENTRAL | E33: HIDROELÉCTRICA | F33: 3964.55 | G33: 3798.3184 | H33: 3756.9495 | I33: 3888.3744 | J33: 3971.4 | K33: 3939.6 | L33: 3968.7 | M33: 4037.7 | N33: 3995.15 | O33: 3976.25 | P33: 3970.5 | Q33: 3961.5 | R33: 3952.05 | S33: 3889.5 | T33: 3952.4 | U33: 3949 | V33: 2949.9 | W33: 3959.35 | X33: 3941.7 | Y33: 3937.45 | Z33: 77760.342
B34: EGESUR | C34: C.H. ARICOTA I | D34: CENTRAL | E34: HIDROELÉCTRICA | F34: 179.35 | G34: 179.6695 | H34: 178.3585 | I34: 180.8635 | J34: 179.4 | K34: 177.95 | L34: 179.55 | M34: 181.5 | N34: 182.4 | O34: 179.45 | P34: 179.7 | Q34: 180.2 | R34: 180.2 | S34: 179.05 | T34: 182.6 | U34: 180.15 | V34: 180.65 | W34: 179.1 | X34: 178.7 | Y34: 177.45 | Z34: 3596.2915
B35: EGESUR | C35: C.H. ARICOTA II | D35: CENTRAL | E35: HIDROELÉCTRICA | F35: 56.2 | G35: 63.505 | H35: 64.4495 | I35: 66.3065 | J35: 67.501 | K35: 67.5 | L35: 68.25 | M35: 70.95 | N35: 72.45 | O35: 72.45 | P35: 71.55 | Q35: 72.9 | R35: 72.85 | S35: 71.9 | T35: 70.7 | U35: 72.85 | V35: 74.2 | W35: 72.6 | X35: 72.9 | Y35: 72.85 | Z35: 1394.862
B36: EGESUR | C36: C.T. INDEPENDENCIA | D36: CENTRAL | E36: TERMOELÉCTRICA | F36: 287.9 | G36: 270.4815 | H36: 295.579 | I36: 228.8855 | J36: 275.7 | K36: 293.4 | L36: 215.35 | M36: 84 | N36: 25.85 | O36: 56.5 | P36: 88 | Q36: 28.4 | R36: 11.95 | S36: 71 | U36: 73.95 | V36: 30.75 | X36: 41.95 | Y36: 21.1 | Z36: 2400.746
B37: ELECTRICA YANAPAMPA SAC | C37: C.H. YANAPAMPA | D37: CENTRAL | E37: HIDROELÉCTRICA | F37: 76.55 | G37: 76.297 | H37: 72.5515 | I37: 57.187 | J37: 55.35 | K37: 62.05 | L37: 69.4 | M37: 64.4 | N37: 67.95 | O37: 62.55 | P37: 30.35 | Q37: 56.75 | R37: 67.35 | S37: 75.05 | T37: 66.85 | U37: 63.9 | V37: 16.15 | W37: 70.45 | X37: 77.7 | Y37: 78.55 | Z37: 1267.3855
B38: ELECTROPERU | C38: C.H. MANTARO | D38: CENTRAL | E38: HIDROELÉCTRICA | F38: 197.4 | G38: 38.2 | I38: 7.24 | K38: 24.6 | L38: 1961.1 | M38: 11064.2 | N38: 15276.45 | O38: 14809.9 | P38: 15171.35 | Q38: 15606.9 | R38: 15371.45 | S38: 15582.3 | T38: 15592.6 | U38: 15562.95 | V38: 15562.85 | W38: 15565.95 | X38: 15551.35 | Y38: 15035 | Z38: 197981.79
B39: ELECTROPERU | C39: C.H. RESTITUCION | D39: CENTRAL | E39: HIDROELÉCTRICA | F39: 72.1 | G39: 12.29 | L39: 287.05 | M39: 3536.3 | N39: 5081.55 | O39: 4931.15 | P39: 4633.95 | Q39: 5104.45 | R39: 5089.7 | S39: 4544.8 | T39: 5227.6 | U39: 5224.15 | V39: 4295.4 | W39: 4593.1 | X39: 4722.835 | Y39: 4432.15 | Z39: 61788.575
B40: ELECTROPERU | C40: C.T. TUMBES | D40: MAK1 | E40: TERMOELÉCTRICA | H40: 17.535 | K40: 18.945 | L40: 36.955 | N40: 10.5 | Z40: 83.935
B41: ELECTROPERU | C41: C.T. TUMBES | D41: MAK2 | E41: TERMOELÉCTRICA | H41: 17.45 | K41: 36.92 | Z41: 54.37
B42: EMPRESA DE GENERACION ELECTRICA CANCHAYLLO SAC | C42: C.H. CANCHAYLLO | D42: CENTRAL | E42: HIDROELÉCTRICA | F42: 122.6 | G42: 118.814 | H42: 107.897 | I42: 104.2105 | J42: 74.55 | K42: 89.8 | L42: 66.75 | M42: 53.1 | N42: 79.15 | O42: 114.35 | P42: 103.25 | Q42: 104.2 | R42: 100.05 | S42: 99.95 | T42: 122.25 | U42: 123.25 | V42: 123.7 | W42: 123.65 | X42: 122.65 | Y42: 123.2 | Z42: 2077.3715
B43: EMPRESA DE GENERACION ELECTRICA RIO BAÑOS S.A.C. | C43: C.H. RUCUY | D43: CENTRAL | E43: HIDROELÉCTRICA | F43: 479.95 | G43: 480.30641 | H43: 479.72303 | I43: 479.53348 | J43: 479.4 | K43: 479.95 | L43: 480.05 | M43: 479.1 | N43: 479.55 | O43: 479.2 | P43: 479.25 | Q43: 479.75 | R43: 479.7 | S43: 479.75 | T43: 479.35 | U43: 479 | V43: 479.6 | W43: 479.2 | X43: 479.45 | Y43: 478.5 | Z43: 9590.3129
B44: EMPRESA DE GENERACION ELECTRICA SANTA ANA S.A.C. | C44: C.H. RENOVANDES H1 | D44: CENTRAL | E44: HIDROELÉCTRICA | F44: 405.15 | G44: 487.25 | H44: 484.16 | I44: 485.585 | J44: 484.35 | K44: 420.4 | L44: 485.1 | M44: 314.25 | N44: 422.45 | O44: 480.8 | P44: 485.95 | Q44: 385.05 | R44: 486.5 | S44: 485.85 | T44: 485.7 | U44: 485.8 | V44: 486 | W44: 486.6 | X44: 485.3 | Y44: 484.85 | Z44: 9227.095
B45: EMPRESA DE GENERACION HUALLAGA | C45: C.H. CHAGLLA | D45: CENTRAL | E45: HIDROELÉCTRICA | F45: 10738.25 | G45: 10686.699 | H45: 11141.905 | I45: 10819.019 | J45: 11035.45 | K45: 11113.25 | L45: 11033.5 | M45: 10867.85 | N45: 11032 | O45: 10887.65 | P45: 11064.7 | Q45: 11044.75 | R45: 10843.15 | S45: 11045.05 | T45: 10924.9 | U45: 10423.75 | V45: 10466.8 | W45: 10494.55 | X45: 10930.4 | Y45: 10351.65 | Z45: 216945.27
B46: EMPRESA DE GENERACION HUALLAGA | C46: P.C.H. CHAGLLA | D46: CENTRAL | E46: HIDROELÉCTRICA | F46: 156 | G46: 156.37672 | H46: 156.33116 | I46: 156.36868 | J46: 156 | K46: 156 | L46: 156 | M46: 53.1 | N46: 41.45 | O46: 158.4 | P46: 158.35 | Q46: 158.4 | R46: 158.4 | S46: 158.4 | T46: 98.3 | U46: 156 | V46: 156 | W46: 156 | X46: 156 | Y46: 155.9 | Z46: 2857.7766
B47: EMPRESA DE GENERACION HUANZA | C47: C.H. HUANZA | D47: CENTRAL | E47: HIDROELÉCTRICA | F47: 1961.4 | G47: 2049.705 | H47: 2281.335 | I47: 2293.63 | J47: 2290.35 | K47: 2284.4 | L47: 2285.8 | M47: 2282.3 | N47: 2275.9 | O47: 2275.65 | P47: 2277.15 | Q47: 2281.115 | R47: 2275.05 | S47: 2271.2 | T47: 2275.7 | U47: 2275.7 | V47: 2287.15 | W47: 2291.65 | X47: 2291.85 | Y47: 2177.75 | Z47: 44984.785
B48: EMPRESA ELECTRICA AGUA AZUL | C48: C.H. POTRERO | D48: CENTRAL | E48: HIDROELÉCTRICA | F48: 415.2 | G48: 255.962 | H48: 172.3435 | I48: 326.1015 | J48: 369.1 | K48: 414.25 | L48: 375.15 | M48: 395.7 | N48: 478.65 | O48: 480 | P48: 479.9 | Q48: 479.6 | R48: 437.05 | S48: 467.25 | T48: 476.05 | U48: 459.2 | V48: 458.55 | W48: 479.3 | X48: 354 | Y48: 462.45 | Z48: 8235.807
B49: EMPRESA ELECTRICA RIO DOBLE | C49: C.H. LAS PIZARRAS | D49: CENTRAL | E49: HIDROELÉCTRICA | F49: 445.45 | G49: 445.745 | H49: 448.68 | I49: 401.74 | J49: 428.6 | K49: 458 | L49: 453.35 | M49: 453.45 | N49: 453.65 | O49: 454.95 | P49: 455.95 | Q49: 456.75 | R49: 453.65 | S49: 443.65 | T49: 447.7 | U49: 452.6 | V49: 399.37 | W49: 448.85 | X49: 449.75 | Y49: 456.15 | Z49: 8908.035
B50: ENEL GENERACION PIURA S.A. | C50: C.T. MALACAS 1 | D50: TG6 | E50: TERMOELÉCTRICA | F50: 757.75 | G50: 589.6265 | H50: 812.884 | I50: 558.9085 | J50: 721.7 | K50: 662.7 | L50: 630.3 | M50: 1095.5 | N50: 777.2 | O50: 744.15 | P50: 782.3 | Q50: 796.5 | R50: 753.9 | Z50: 9683.419
B51: ENEL GENERACION PIURA S.A. | C51: C.T. MALACAS 2 | D51: TG4 | E51: TERMOELÉCTRICA | G51: 700.3035 | H51: 87.8185 | I51: 564.608 | J51: 352.7 | K51: 682.85 | L51: 485 | N51: 458.6 | O51: 330.6 | S51: 629.55 | T51: 49.7 | U51: 919.3 | V51: 484.4 | W51: 74.7 | X51: 524.35 | Y51: 87.7 | Z51: 6432.18
B52: ENEL GENERACION PIURA S.A. | C52: C.T. RF DE GENERACION TALARA | D52: TG5 | E52: TERMOELÉCTRICA | Z52: 0
B53: ENERGÍA EÓLICA S.A. | C53: C.E. CUPISNIQUE | D53: CENTRAL | E53: EÓLICA | F53: 492.4 | G53: 234.21632 | H53: 573.41678 | I53: 829.4876 | J53: 693.1 | K53: 784.65 | L53: 1130.35 | M53: 732.65 | N53: 489.55 | O53: 893.55 | P53: 920.05 | Q53: 978.3 | R53: 674.75 | S53: 673.5 | T53: 990.85 | U53: 1091.6 | V53: 975.95 | W53: 1020.1 | X53: 900.9 | Y53: 947.85 | Z53: 16027.221
B54: ENERGÍA EÓLICA S.A. | C54: C.E. TALARA | D54: CENTRAL | E54: EÓLICA | F54: 126.35 | G54: 72.805165 | H54: 99.786865 | I54: 119.53852 | J54: 97.4 | K54: 28.15 | L54: 104.5 | M54: 118.8 | N54: 43.85 | O54: 130.3 | P54: 113.1 | Q54: 370.8 | R54: 191.9 | S54: 69.55 | T54: 260.15 | U54: 279.8 | V54: 171.35 | W54: 95.55 | X54: 145 | Y54: 81.25 | Z54: 2719.9305
B55: ENERGIA RENOVABLE DEL SUR S.A. | C55: C.E. SAN JUAN | D55: CENTRAL | E55: EÓLICA | F55: 1476.15 | G55: 2410.149 | H55: 2215.8275 | I55: 1834.392 | J55: 1267.4 | K55: 1121.7 | L55: 2566.25 | M55: 2061.45 | N55: 2112.2 | O55: 2161.25 | P55: 876.65 | Q55: 802.45 | R55: 1505.3 | S55: 1240.75 | T55: 2307.8 | U55: 2114.05 | V55: 2385.6 | W55: 1861.45 | X55: 2239.2 | Y55: 2515.75 | Z55: 37075.768
B56: ENGIE | C56: C.E. PUNTA LOMITAS | D56: PL-BL1 | E56: EÓLICA | F56: 674.7 | G56: 1264.1088 | H56: 1969.2187 | I56: 1769.0911 | J56: 813.75 | K56: 487.1 | L56: 1355.4 | M56: 1565.3616 | N56: 1622.25 | O56: 1644.95 | P56: 958.6 | Q56: 541.2 | R56: 894.1 | S56: 635.05 | T56: 1607.2 | U56: 1289.55 | V56: 1739 | W56: 1625.1 | X56: 901 | Y56: 1215.4 | Z56: 24572.13
B57: ENGIE | C57: C.E. PUNTA LOMITAS | D57: PL-BL2 | E57: EÓLICA | F57: 765.7 | G57: 1453.6883 | H57: 1920.3587 | I57: 1827.2767 | J57: 973.65 | K57: 732.8 | L57: 1533.7 | M57: 2060.2078 | N57: 1916.75 | O57: 1998.8 | P57: 1153.8 | Q57: 938.9 | R57: 1223.7 | S57: 1046.5 | T57: 1943.3 | U57: 1647.1 | V57: 1889.3 | W57: 1833.2 | X57: 1190.75 | Y57: 1579.6 | Z57: 29629.082
B58: ENGIE | C58: C.E. PUNTA LOMITAS_EXP | D58: PUN LOM_EXP-BL1 | E58: EÓLICA | F58: 43.1 | G58: 65.92504 | H58: 137.81323 | I58: 122.02934 | J58: 58.05 | K58: 25.6 | L58: 104.95 | M58: 128.15 | N58: 165.3 | O58: 168.3 | P58: 96.4 | Q58: 43.25 | R58: 66.9 | S58: 48.3 | T58: 142.45 | U58: 134.95 | V58: 159.6 | W58: 132.65 | X58: 69.15 | Y58: 76.25 | Z58: 1989.1176
B59: ENGIE | C59: C.E. PUNTA LOMITAS_EXP | D59: PUN LOM_EXP-BL2 | E59: EÓLICA | F59: 12.05 | G59: 93.158995 | H59: 228.80567 | I59: 207.60234 | J59: 67.45 | K59: 27.5 | L59: 139.75 | M59: 121.3 | N59: 134.85 | O59: 150.85 | P59: 104.4 | Q59: 51.45 | R59: 71.1 | S59: 42.8 | T59: 171.5 | U59: 150 | V59: 219.05 | W59: 127.8 | X59: 55.75 | Y59: 94.85 | Z59: 2272.017
B60: ENGIE | C60: C.H. QUITARACSA | D60: CENTRAL | E60: HIDROELÉCTRICA | F60: 2731.65 | G60: 2741.6212 | H60: 2118.2061 | I60: 2367.8402 | J60: 2517.45 | K60: 202.65 | Z60: 12679.417
B61: ENGIE | C61: C.H. YUNCAN | D61: CENTRAL | E61: HIDROELÉCTRICA | F61: 2086.95 | G61: 2082.6452 | H61: 2080.9741 | I61: 2087.1043 | J61: 2084.1 | K61: 2081.6 | L61: 2071.75 | M61: 2073.25 | N61: 2001.45 | O61: 1780.55 | P61: 2086.5 | Q61: 2088.1 | R61: 2084.75 | S61: 2085.7 | T61: 2087.7 | U61: 2083.8 | V61: 2088.15 | W61: 2086.75 | X61: 2087.05 | Y61: 2046.8 | Z61: 41255.674
B62: ENGIE | C62: C.S. INTIPAMPA | D62: CENTRAL | E62: SOLAR | F62: 189.1 | G62: 199.38369 | H62: 162.58559 | I62: 155.53618 | J62: 311.35 | K62: 89.1 | L62: 252.9 | M62: 250.75 | N62: 219.25 | O62: 140.4 | P62: 324.65 | Q62: 343.25 | R62: 337.8 | S62: 294.25 | T62: 328.95 | U62: 289.7 | V62: 250.95 | W62: 343 | X62: 323.4 | Y62: 320.4 | Z62: 5126.7055
B63: ENGIE | C63: C.T. CHILCA 1 | D63: TG1 | E63: TERMOELÉCTRICA | F63: 3993.45 | G63: 3934.7808 | H63: 4015.2463 | I63: 3840.5846 | J63: 3981.15 | K63: 4065.6 | L63: 4060.6 | M63: 3084.3 | N63: 3109.8 | O63: 2889.35 | P63: 2980.2 | Q63: 2960 | R63: 2934.6 | S63: 3019.75 | T63: 3263 | U63: 2661.7 | V63: 2860.05 | W63: 3300.6 | X63: 3798.05 | Y63: 3035.7 | Z63: 67788.512
B64: ENGIE | C64: C.T. CHILCA 1 | D64: TG2 | E64: TERMOELÉCTRICA | F64: 3813.85 | G64: 3757.0858 | H64: 3829.2164 | I64: 3678.231 | J64: 3813.4 | K64: 3873.55 | L64: 3872.4 | M64: 3025.75 | N64: 3065.85 | O64: 2866.55 | P64: 2962.2 | Q64: 2956.6 | R64: 2927.15 | S64: 3015.65 | T64: 3172.85 | U64: 2654.35 | V64: 2856.5 | W64: 2676.2 | X64: 29.1 | Y64: 278.5 | Z64: 59124.983
B65: ENGIE | C65: C.T. CHILCA 1 | D65: TG3 | E65: TERMOELÉCTRICA | F65: 4701.75 | G65: 4625.8253 | H65: 4766.0346 | I65: 4437.1885 | J65: 4653.65 | K65: 4792.4 | L65: 4735.45 | M65: 3296.95 | N65: 3211.05 | O65: 2942.45 | P65: 2993.05 | Q65: 2955.7 | R65: 2949.25 | S65: 3016.85 | T65: 3611.95 | U65: 2681.45 | V65: 2863.7 | W65: 3595.5 | X65: 4337.25 | Y65: 3334.75 | Z65: 74502.198
B66: ENGIE | C66: C.T. CHILCA 1 | D66: TV | E66: TERMOELÉCTRICA | F66: 6174.35 | G66: 6051.7682 | H66: 6167.3929 | I66: 5988.3888 | J66: 6157.7 | K66: 6221.3 | L66: 6206.7 | M66: 5254.8 | N66: 5179.3 | O66: 4960 | P66: 5004.9 | Q66: 5005.4 | R66: 5024.5 | S66: 5038 | T66: 5308.6 | U66: 4647.15 | V66: 4850.15 | W66: 4854.7 | X66: 4114.1 | Y66: 3424.5 | Z66: 105633.7
B67: ENGIE | C67: C.T. CHILCA 2 | D67: TG41 | E67: TERMOELÉCTRICA | F67: 200.55 | G67: 326.31458 | H67: 1225.8121 | I67: 1295.9138 | J67: 1525.2 | K67: 1580.05 | L67: 1477.25 | M67: 1171.9 | N67: 1112.8 | O67: 1074.75 | P67: 594 | Q67: 371.55 | R67: 84.7 | S67: 227.15 | U67: 230.35 | W67: 107.6 | Z67: 12605.891
B68: ENGIE | C68: C.T. CHILCA 2 | D68: TV42 | E68: TERMOELÉCTRICA | H68: 524.739 | I68: 645.85564 | J68: 779.2 | K68: 793.95 | L68: 769.15 | M68: 701.3 | N68: 679.85 | O68: 674.75 | Z68: 5568.7946
B69: ENGIE | C69: C.T. NEPI | D69: TG41 | E69: TERMOELÉCTRICA | H69: 1277.7673 | I69: 241.04592 | K69: 1181.45 | L69: 1058.7 | Z69: 3758.9633
B70: ENGIE | C70: C.T. NEPI | D70: TG42 | E70: TERMOELÉCTRICA | Z70: 0
B71: ENGIE | C71: C.T. NEPI | D71: TG43 | E71: TERMOELÉCTRICA | N71: 471.65 | Z71: 471.65
B72: ENGIE | C72: C.T. RF PLANTA ILO | D72: TG1 | E72: TERMOELÉCTRICA | Z72: 0
B73: ENGIE | C73: C.T. RF PLANTA ILO | D73: TG2 | E73: TERMOELÉCTRICA | Z73: 0
B74: ENGIE | C74: C.T. RF PLANTA ILO | D74: TG3 | E74: TERMOELÉCTRICA | Y74: 211.805 | Z74: 211.805
B75: FENIX POWER PERÚ | C75: C.T. FENIX | D75: GT11 | E75: TERMOELÉCTRICA | F75: 3665.9 | G75: 1305.8552 | H75: 4013.905 | I75: 3902.759 | J75: 3939.1 | K75: 4134.25 | L75: 3659.45 | M75: 3875.25 | N75: 1684.45 | O75: 3558.75 | P75: 3869.65 | Q75: 3980.2 | R75: 3625.45 | S75: 3700.5 | T75: 25.35 | V75: 2762.8691 | W75: 3395.3 | X75: 3514.55 | Y75: 3182.2 | Z75: 61795.738
B76: FENIX POWER PERÚ | C76: C.T. FENIX | D76: GT12 | E76: TERMOELÉCTRICA | F76: 3683.3 | G76: 2328.6156 | H76: 4029.2245 | I76: 3910.078 | J76: 3948.95 | K76: 4144.35 | L76: 3665.9 | M76: 3883.3 | N76: 1677.6 | O76: 3565.35 | P76: 3878.6 | Q76: 3991.05 | R76: 3633.65 | S76: 3706.15 | T76: 3224.7 | U76: 1317.9 | V76: 3594.3645 | W76: 3403.75 | X76: 3522.1 | Y76: 3368.65 | Z76: 68477.583
B77: FENIX POWER PERÚ | C77: C.T. FENIX | D77: TV10 | E77: TERMOELÉCTRICA | F77: 4080.1 | G77: 1775.6855 | H77: 4282.333 | I77: 4202.2535 | J77: 4217.15 | K77: 4345.05 | L77: 4052.75 | M77: 4172 | N77: 1572 | O77: 3975.4 | P77: 4156.45 | Q77: 4242.35 | R77: 4031.05 | S77: 4089.2 | T77: 1834.5 | U77: 633.3 | V77: 3388.7966 | W77: 3908.95 | X77: 3980.15 | Y77: 3779.85 | Z77: 70719.319
B78: GENERACIÓN ANDINA S.A.C. | C78: C.H. 8 DE AGOSTO | D78: CENTRAL | E78: HIDROELÉCTRICA | F78: 504.05 | G78: 399.7495 | H78: 503.8515 | I78: 502.1525 | J78: 395.7 | K78: 0.1 | L78: 18.45 | M78: 250.1 | N78: 252 | O78: 252 | P78: 252 | Q78: 355.1 | R78: 357.65 | S78: 463.85 | T78: 374.25 | U78: 302.9 | V78: 252.75 | W78: 500.25 | X78: 501.9 | Y78: 504 | Z78: 6942.8035
B79: GENERACIÓN ANDINA S.A.C. | C79: C.H. EL CARMEN | D79: CENTRAL | E79: HIDROELÉCTRICA | F79: 170.8 | G79: 174.774 | H79: 201.9495 | I79: 201.6775 | J79: 186.85 | K79: 203.55 | L79: 203.85 | M79: 202.8 | N79: 200.9 | O79: 203.55 | P79: 200.45 | Q79: 201.8 | R79: 201.6 | S79: 200.15 | T79: 201.6 | U79: 201.6 | V79: 192.35 | W79: 194.2 | X79: 144.95 | Y79: 148.35 | Z79: 3837.751
B80: GENERADORA DE ENERGÍA DEL PERÚ | C80: C.H. ÁNGEL I | D80: CENTRAL | E80: HIDROELÉCTRICA | F80: 489.6 | G80: 489.6 | H80: 489.6 | I80: 489.6 | J80: 489.6 | K80: 489.6 | L80: 489.6 | M80: 234.6 | N80: 235.6 | O80: 244.8 | P80: 489.6 | Q80: 489.6 | R80: 489.6 | S80: 227.9 | T80: 234.75 | U80: 489.6 | V80: 489.6 | W80: 489.6 | X80: 489.6 | Y80: 489.6 | Z80: 8521.65
B81: GENERADORA DE ENERGÍA DEL PERÚ | C81: C.H. ÁNGEL II | D81: CENTRAL | E81: HIDROELÉCTRICA | F81: 489.6 | G81: 489.6 | H81: 489.6 | I81: 489.6 | J81: 489.6 | K81: 489.6 | L81: 489.6 | M81: 214.2 | N81: 229.75 | O81: 239.7 | P81: 489.6 | Q81: 489.6 | R81: 489.6 | S81: 227.15 | T81: 214.7 | U81: 489.6 | V81: 489.6 | W81: 489.6 | X81: 489.6 | Y81: 489.6 | Z81: 8469.5
B82: GENERADORA DE ENERGÍA DEL PERÚ | C82: C.H. ÁNGEL III | D82: CENTRAL | E82: HIDROELÉCTRICA | F82: 480 | G82: 480 | H82: 480 | I82: 480 | J82: 480 | K82: 480 | L82: 480 | M82: 186 | N82: 187.5 | O82: 227 | P82: 480 | Q82: 480 | R82: 480 | S82: 222 | T82: 158.7 | U82: 480 | V82: 480 | W82: 480 | X82: 484.7 | Y82: 484.8 | Z82: 8190.7
B83: GENERADORA DE ENERGÍA DEL PERÚ | C83: C.H. LA JOYA | D83: CENTRAL | E83: HIDROELÉCTRICA | L83: 22 | M83: 78.7 | N83: 89.8 | O83: 33.35 | Q83: 33.15 | R83: 107.15 | S83: 115.55 | T83: 141.65 | U83: 169.35 | V83: 179.2 | W83: 178 | X83: 179.2 | Y83: 176.75 | Z83: 1503.85
B84: GM OPERACIONES S.A.C. | C84: CT REFINERIA TALARA | D84: TV1 REF TALARA | E84: TERMOELÉCTRICA | O84: 2.55 | P84: 382.38 | Q84: 444.95 | R84: 196.55 | S84: 414.1 | T84: 737.85 | U84: 746.55 | V84: 933.15 | W84: 1051.65 | X84: 1065.3 | Y84: 1070.5 | Z84: 7045.53
B85: GM OPERACIONES S.A.C. | C85: CT REFINERIA TALARA | D85: TV2 REF TALARA | E85: TERMOELÉCTRICA | F85: 869.55 | G85: 872.48 | H85: 874.555 | I85: 870.815 | J85: 879.35 | K85: 880.565 | L85: 870.95 | M85: 854.65 | N85: 844.55 | O85: 795.9 | P85: 789.205 | Q85: 82.935 | S85: 281.75 | T85: 844.65 | U85: 852.95 | V85: 718.1 | W85: 554.25 | X85: 574.8 | Y85: 575.15 | Z85: 13887.155
B86: GR CORTARRAMA SOCIEDAD ANONIMA CERRADA | C86: C.S. MATARANI | D86: C.S. MATARANI | E86: SOLAR | F86: 732.6 | G86: 610.685 | H86: 729.91 | I86: 482.955 | J86: 607.45 | K86: 522.6 | L86: 733.55 | M86: 656.95 | N86: 538.15 | O86: 544.6 | P86: 718 | Q86: 717.9 | R86: 718.2 | S86: 729 | T86: 730.8 | U86: 696.65 | V86: 564.35 | W86: 572.3 | X86: 704.35 | Y86: 706.85 | Z86: 13017.85
B87: GR PAINO SOCIEDAD ANONIMA CERRADA | C87: C.E. HUAMBOS | D87: CENTRAL | E87: EÓLICA | F87: 51.65 | G87: 32.58597 | H87: 23.62121 | I87: 31.77664 | J87: 41.9 | K87: 70.9 | L87: 41.1 | M87: 47.85 | N87: 22.7 | O87: 78.2 | P87: 76.8 | Q87: 62.7 | R87: 84.95 | S87: 50.25 | T87: 10.5 | U87: 101.5 | V87: 174.55 | W87: 30.3 | X87: 172.8 | Y87: 282 | Z87: 1488.6338
B88: GR TARUCA SOCIEDAD ANONIMA CERRADA | C88: C.E. DUNA | D88: CENTRAL | E88: EÓLICA | F88: 47.25 | G88: 42.391385 | H88: 31.94139 | I88: 25.49812 | J88: 27.3 | K88: 52 | L88: 26.8 | M88: 53.35 | N88: 16.05 | O88: 76.15 | P88: 63.95 | Q88: 109.9 | R88: 119.35 | S88: 55.55 | T88: 14.1 | U88: 128.9 | V88: 232.7 | W88: 30.55 | X88: 234.1 | Y88: 365.15 | Z88: 1752.9809
B89: HIDROCAÑETE S.A. | C89: C.H. IMPERIAL | D89: CENTRAL | E89: HIDROELÉCTRICA | F89: 85.65 | G89: 85.692 | H89: 83.4875 | I89: 84.5665 | J89: 84.55 | K89: 83.2 | L89: 81.95 | M89: 82.95 | N89: 82.5 | O89: 82.15 | P89: 83.85 | Q89: 84.8 | R89: 84.75 | S89: 84.45 | T89: 71.8 | U89: 83.05 | V89: 83.35 | W89: 83.35 | X89: 85.05 | Y89: 84.35 | Z89: 1665.496
B90: HIDROELECTRICA HUANCHOR S.A.C. | C90: C.H. HUANCHOR | D90: CENTRAL | E90: HIDROELÉCTRICA | F90: 441.55 | G90: 441.72442 | H90: 441.4533 | I90: 439.11521 | J90: 440.2 | K90: 440.9 | L90: 439.55 | M90: 441.5 | N90: 441.25 | O90: 440.75 | P90: 442.55 | Q90: 442.15 | R90: 441.9 | S90: 442.85 | T90: 442.65 | U90: 441.95 | V90: 443.4 | W90: 442.65 | X90: 443.75 | Y90: 442.7 | Z90: 8834.5429
B91: HUAURA POWER GROUP S.A. | C91: C.H. YARUCAYA | D91: CENTRAL | E91: HIDROELÉCTRICA | F91: 449.7 | G91: 448.935 | H91: 448.6 | I91: 448.255 | J91: 446.05 | K91: 176.2 | L91: 229.95 | M91: 343.85 | N91: 444.6 | O91: 444.2 | P91: 444.1 | Q91: 444.05 | R91: 444.45 | S91: 444.15 | T91: 444 | U91: 132.35 | V91: 150.8 | W91: 446.1 | X91: 446.4 | Y91: 446.35 | Z91: 7723.09
B92: INFRAESTRUCTURAS Y ENERGIAS DEL PERU S.A.C. | C92: C.T. RF PTO MALDONADO | D92: CENTRAL | E92: TERMOELÉCTRICA | G92: 87.975 | Z92: 87.975
B93: INFRAESTRUCTURAS Y ENERGIAS DEL PERU S.A.C. | C93: C.T. RF PUCALLPA | D93: CENTRAL | E93: TERMOELÉCTRICA | Z93: 0
B94: INLAND ENERGY SAC | C94: C.H. SANTA TERESA | D94: CENTRAL | E94: HIDROELÉCTRICA | F94: 2172.25 | G94: 2066.7676 | H94: 2036.195 | I94: 2111.575 | J94: 2170.7 | K94: 2157.45 | L94: 2160.4 | M94: 2167.15 | N94: 2173 | O94: 2173 | P94: 2170.65 | Q94: 2161.4 | R94: 2160.8 | S94: 2118.85 | T94: 2158.9 | U94: 2160.65 | V94: 1630.95 | W94: 2166.95 | X94: 2171.8 | Y94: 2164.25 | Z94: 42453.688
B95: INVERSIONES SHAQSHA S.A.C. | C95: C.H. PARIAC | D95: CENTRAL | E95: HIDROELÉCTRICA | J95: 32.9 | K95: 54.5 | L95: 82.65 | M95: 73.8 | N95: 59.15 | O95: 48.9 | P95: 50.45 | Q95: 50.25 | R95: 50.4 | S95: 50.35 | T95: 50.3 | U95: 36.235 | V95: 36 | W95: 36 | X95: 36 | Y95: 27.9 | Z95: 775.785
B96: KALLPA GENERACION S.A. | C96: C.H. CERRO DEL AGUILA | D96: CENTRAL | E96: HIDROELÉCTRICA | F96: 13450.75 | G96: 11195.95 | H96: 1672.29 | I96: 13405.74 | J96: 13385.35 | K96: 13395.8 | L96: 5973.9 | M96: 929.5 | O96: 5953.05 | P96: 9064.7 | Q96: 9077.95 | R96: 8976.55 | S96: 9043.1 | T96: 9053.65 | U96: 9017 | V96: 8995.4 | W96: 9044.85 | X96: 9085.15 | Y96: 12231.45 | Z96: 172952.13
B97: KALLPA GENERACION S.A. | C97: C.T. KALLPA | D97: TG1 | E97: TERMOELÉCTRICA | F97: 3231.4 | G97: 3230.39 | H97: 3268.245 | I97: 2988.66 | J97: 3168.65 | K97: 3581.95 | L97: 3771.95 | M97: 3596.7 | N97: 3396.05 | O97: 3100.9 | P97: 3215.75 | Q97: 3584.8 | R97: 3299.8 | S97: 3341.3 | T97: 2961.1 | U97: 3043.9 | V97: 3356.15 | W97: 2847.35 | X97: 3053.65 | Y97: 3024.95 | Z97: 65063.645
B98: KALLPA GENERACION S.A. | C98: C.T. KALLPA | D98: TG2 | E98: TERMOELÉCTRICA | F98: 3255.7 | G98: 3265.37 | H98: 3271.86 | I98: 2990.33 | J98: 3167.35 | K98: 3608.15 | L98: 4018.15 | M98: 3791.75 | N98: 3520.8 | O98: 3205.95 | P98: 2861.75 | T98: 2849.35 | U98: 517.3 | W98: 2222.5 | X98: 3050.8 | Y98: 3025.1 | Z98: 48622.21
B99: KALLPA GENERACION S.A. | C99: C.T. KALLPA | D99: TG3 | E99: TERMOELÉCTRICA | F99: 3251.05 | G99: 3267.43 | H99: 3273.555 | I99: 2994.04 | J99: 3168.8 | K99: 3607.9 | L99: 4022.5 | M99: 3804.25 | N99: 3037.55 | O99: 3211.8 | P99: 3283.4 | Q99: 3858.75 | R99: 3455.7 | S99: 3517.35 | T99: 2972.8 | U99: 3151.55 | V99: 3546.95 | W99: 2849 | X99: 3049.8 | Y99: 3027.3 | Z99: 66351.475
B100: KALLPA GENERACION S.A. | C100: C.T. KALLPA | D100: TV | E100: TERMOELÉCTRICA | F100: 5592.5 | G100: 5571.865 | H100: 5622.475 | I100: 5390.81 | J100: 5538.25 | K100: 5879.15 | L100: 6211.85 | M100: 6053.8 | N100: 5551.1 | O100: 5536.25 | P100: 5372.6 | Q100: 4024.65 | R100: 3783.5 | S100: 3821.95 | T100: 5140 | U100: 3931.3 | V100: 3833.9 | W100: 4736.8 | X100: 5408.85 | Y100: 5302.8 | Z100: 102304.4
B101: KALLPA GENERACION S.A. | C101: C.T. LAS FLORES | D101: TG1 | E101: TERMOELÉCTRICA | F101: 4439.3 | G101: 4629.825 | H101: 4641.86 | I101: 4326.075 | J101: 4577.3 | K101: 4870.95 | L101: 4718 | M101: 4672.85 | N101: 4449.5 | O101: 3917.15 | P101: 4161.05 | Q101: 4568 | R101: 4201.75 | S101: 4558.65 | T101: 3633.05 | U101: 3317.2 | V101: 4178.8 | W101: 3929.45 | X101: 3976.35 | Y101: 3176.75 | Z101: 84943.86
B102: KALLPA GENERACION S.A. | C102: C.T. LAS FLORES | D102: TV | E102: TERMOELÉCTRICA | F102: 2384.2 | G102: 2455.11 | H102: 2476.415 | I102: 2347.8 | J102: 2457.3 | K102: 2561.15 | L102: 2502.95 | M102: 2484.8 | N102: 2396.7 | O102: 2167.3 | P102: 2269.45 | Q102: 2443.25 | R102: 2293.8 | S102: 2441.75 | T102: 2047.15 | U102: 1916.95 | V102: 2278.6 | W102: 2166.7 | X102: 2193 | Y102: 1858.55 | Z102: 46142.925
B103: KALLPA GENERACION S.A. | C103: M.C.H.+CERRO+DEL+AGUILA | D103: CENTRAL | E103: HIDROELÉCTRICA | F103: 251.1 | G103: 229.035 | H103: 46.745 | I103: 252.15 | J103: 251.75 | K103: 253.75 | L103: 115.7 | M103: 57.4 | O103: 173.05 | P103: 252.15 | Q103: 210.1 | S103: 109.45 | T103: 250.9 | U103: 249.95 | V103: 251.3 | W103: 250.85 | X103: 251.15 | Y103: 250.55 | Z103: 3707.08
...

Sheet G_AREAS
B3: jueves, 20 de Marzo del 2025
B5: HORA | C5: RESUMEN DE GENERACIÓN POR ÁREAS DEL SEIN | D5: RESUMEN DE GENERACIÓN POR ÁREAS DEL SEIN | E5: RESUMEN DE GENERACIÓN POR ÁREAS DEL SEIN | F5: RESUMEN DE GENERACIÓN POR ÁREAS DEL SEIN | G5: RESUMEN DE GENERACIÓN POR ÁREAS DEL SEIN | H5: RESUMEN DE GENERACIÓN POR ÁREAS DEL SEIN | I5: RESUMEN DE GENERACIÓN POR ÁREAS DEL SEIN | J5: RESUMEN DE GENERACIÓN POR ÁREAS DEL SEIN | K5: RESUMEN DE GENERACIÓN POR ÁREAS DEL SEIN | L5: RESUMEN DE GENERACIÓN POR ÁREAS DEL SEIN | M5: RESUMEN DE GENERACIÓN POR ÁREAS DEL SEIN | N5: RESUMEN DE GENERACIÓN POR ÁREAS DEL SEIN | O5: RESUMEN DE GENERACIÓN POR ÁREAS DEL SEIN | P5: RESUMEN DE GENERACIÓN POR ÁREAS DEL SEIN | Q5: RESUMEN DE GENERACIÓN POR ÁREAS DEL SEIN | R5: RESUMEN DE GENERACIÓN POR ÁREAS DEL SEIN | S5: HORA | T5: GENERACIÓN POR TIPO DE GENERACIÓN | U5: GENERACIÓN POR TIPO DE GENERACIÓN | V5: GENERACIÓN POR TIPO DE GENERACIÓN | W5: GENERACIÓN POR TIPO DE GENERACIÓN | X5: GENERACIÓN POR TIPO DE GENERACIÓN | Y5: HORA | Z5: GENERACIÓN POR TIPO DE GENERACIÓN | AA5: GENERACIÓN POR TIPO DE GENERACIÓN | AB5: GENERACIÓN POR TIPO DE GENERACIÓN | AC5: GENERACIÓN POR TIPO DE GENERACIÓN | AD5: GENERACIÓN POR TIPO DE GENERACIÓN
C6: NORTE | D6: NORTE | E6: NORTE | F6: NORTE | G6: CENTRO | H6: CENTRO | I6: CENTRO | J6: CENTRO | K6: SUR | L6: SUR | M6: SUR | N6: SUR | O6: GENERACIÓN INTEGRANTES COES | P6: GENERACIÓN INTEGRANTES COES | Q6: GENERACIÓN INTEGRANTES COES | R6: GENERACIÓN INTEGRANTES COES | T6: INTEGRANTES COES | U6: INTEGRANTES COES | V6: INTEGRANTES COES | W6: INTEGRANTES COES | X6: INTEGRANTES COES | Z6: INTEGRANTES COES RER | AA6: INTEGRANTES COES RER | AB6: INTEGRANTES COES RER | AC6: INTEGRANTES COES RER | AD6: INTEGRANTES COES RER
C7: GENERACIÓN HIDROELÉCTRICA NORTE | D7: GENERACIÓN TERMOELÉCTRICA NORTE | E7: GENERACIÓN SOLAR NORTE | F7: GENERACIÓN EÓLICA NORTE | G7: GENERACIÓN HIDROELÉCTRICA CENTRO | H7: GENERACIÓN TERMOELÉCTRICA CENTRO | I7: GENERACIÓN SOLAR CENTRO | J7: GENERACIÓN EÓLICA CENTRO | K7: GENERACIÓN HIDROELÉCTRICA SUR | L7: GENERACIÓN TERMOELÉCTRICA SUR | M7: GENERACIÓN SOLAR SUR | N7: GENERACIÓN EÓLICA SUR | O7: GENERACIÓN COES NORTE | P7: GENERACIÓN COES CENTRO | Q7: GENERACIÓN COES SUR | R7: TOTAL GENERACION | T7: HIDROELÉCTRICA | U7: TERMOELÉCTRICA | V7: SOLAR | W7: EÓLICA | X7: TOTAL GENERACION | Z7: HIDROELÉCTRICA RER | AA7: TERMOELÉCTRICA RER | AB7: SOLAR RER | AC7: EÓLICA RER | AD7: TOTAL RER
B8: 00:30 | C8: 434.3 | D8: 110 | E8: 0 | F8: 56.4 | G8: 3399.1 | H8: 1650.6 | I8: 0 | J8: 345.8 | K8: 614.5 | L8: 0 | M8: 0 | N8: 0 | O8: 600.7 | P8: 5395.5 | Q8: 614.5 | R8: 6610.7 | S8: 00:30 | T8: 4447.9 | U8: 1760.6 | V8: 0 | W8: 402.2 | X8: 6610.7 | Y8: 00:30 | Z8: 345.2 | AA8: 44.2 | AB8: 0 | AC8: 402.2 | AD8: 791.6
B9: 01:00 | C9: 430.5 | D9: 109.7 | E9: 0 | F9: 55.4 | G9: 3274.6 | H9: 1619.4 | I9: 0 | J9: 350.6 | K9: 618.8 | L9: 0 | M9: 0 | N9: 0 | O9: 595.6 | P9: 5244.6 | Q9: 618.8 | R9: 6459 | S9: 01:00 | T9: 4323.9 | U9: 1729.1 | V9: 0 | W9: 406 | X9: 6459 | Y9: 01:00 | Z9: 345.6 | AA9: 43.6 | AB9: 0 | AC9: 406 | AD9: 795.2
B10: 01:30 | C10: 432.8 | D10: 110.1 | E10: 0 | F10: 65.4 | G10: 3284 | H10: 1640.5 | I10: 0 | J10: 337.2 | K10: 615.8 | L10: 0 | M10: 0 | N10: 0 | O10: 608.3 | P10: 5261.7 | Q10: 615.8 | R10: 6485.8 | S10: 01:30 | T10: 4332.6 | U10: 1750.6 | V10: 0 | W10: 402.6 | X10: 6485.8 | Y10: 01:30 | Z10: 346 | AA10: 44.1 | AB10: 0 | AC10: 402.6 | AD10: 792.7
B11: 02:00 | C11: 432.3 | D11: 108.8 | E11: 0 | F11: 69.1 | G11: 3226.5 | H11: 1653.8 | I11: 0 | J11: 338.3 | K11: 592 | L11: 0 | M11: 0 | N11: 0 | O11: 610.2 | P11: 5218.6 | Q11: 592 | R11: 6420.8 | S11: 02:00 | T11: 4250.8 | U11: 1762.6 | V11: 0 | W11: 407.4 | X11: 6420.8 | Y11: 02:00 | Z11: 344.5 | AA11: 44.5 | AB11: 0 | AC11: 407.4 | AD11: 796.4
B12: 02:30 | C12: 436 | D12: 109.4 | E12: 0 | F12: 63.5 | G12: 3226.8 | H12: 1621.9 | I12: 0 | J12: 297.4 | K12: 587.6 | L12: 0 | M12: 0 | N12: 0 | O12: 608.9 | P12: 5146.1 | Q12: 587.6 | R12: 6342.6 | S12: 02:30 | T12: 4250.4 | U12: 1731.3 | V12: 0 | W12: 360.9 | X12: 6342.6 | Y12: 02:30 | Z12: 345 | AA12: 43.5 | AB12: 0 | AC12: 360.9 | AD12: 749.4
B13: 03:00 | C13: 432.1 | D13: 109.9 | E13: 0 | F13: 62.2 | G13: 3164.8 | H13: 1610.1 | I13: 0 | J13: 298.5 | K13: 578.3 | L13: 0 | M13: 0 | N13: 0 | O13: 604.2 | P13: 5073.4 | Q13: 578.3 | R13: 6255.9 | S13: 03:00 | T13: 4175.2 | U13: 1720 | V13: 0 | W13: 360.7 | X13: 6255.9 | Y13: 03:00 | Z13: 344.2 | AA13: 44.1 | AB13: 0 | AC13: 360.7 | AD13: 749
B14: 03:30 | C14: 435.7 | D14: 109.2 | E14: 0 | F14: 53.9 | G14: 3267.2 | H14: 1634.5 | I14: 0 | J14: 253.8 | K14: 587 | L14: 0 | M14: 0 | N14: 0 | O14: 598.8 | P14: 5155.5 | Q14: 587 | R14: 6341.3 | S14: 03:30 | T14: 4289.9 | U14: 1743.7 | V14: 0 | W14: 307.7 | X14: 6341.3 | Y14: 03:30 | Z14: 346.4 | AA14: 44.3 | AB14: 0 | AC14: 307.7 | AD14: 698.4
B15: 04:00 | C15: 434.1 | D15: 83.4 | E15: 0 | F15: 52.3 | G15: 3207.6 | H15: 1615.4 | I15: 0 | J15: 255.1 | K15: 583.4 | L15: 0 | M15: 0 | N15: 0 | O15: 569.8 | P15: 5078.1 | Q15: 583.4 | R15: 6231.3 | S15: 04:00 | T15: 4225.1 | U15: 1698.8 | V15: 0 | W15: 307.4 | X15: 6231.3 | Y15: 04:00 | Z15: 344.1 | AA15: 43.6 | AB15: 0 | AC15: 307.4 | AD15: 695.1
B16: 04:30 | C16: 435.5 | D16: 83.8 | E16: 0 | F16: 56.5 | G16: 3312.8 | H16: 1630.3 | I16: 0 | J16: 248.1 | K16: 589.5 | L16: 0 | M16: 0 | N16: 0 | O16: 575.8 | P16: 5191.2 | Q16: 589.5 | R16: 6356.5 | S16: 04:30 | T16: 4337.8 | U16: 1714.1 | V16: 0 | W16: 304.6 | X16: 6356.5 | Y16: 04:30 | Z16: 345.9 | AA16: 43.9 | AB16: 0 | AC16: 304.6 | AD16: 694.4
B17: 05:00 | C17: 437.7 | D17: 83.4 | E17: 0 | F17: 49.3 | G17: 3293.2 | H17: 1613.2 | I17: 0 | J17: 273.2 | K17: 625.9 | L17: 0 | M17: 0 | N17: 0 | O17: 570.4 | P17: 5179.6 | Q17: 625.9 | R17: 6375.9 | S17: 05:00 | T17: 4356.8 | U17: 1696.6 | V17: 0 | W17: 322.5 | X17: 6375.9 | Y17: 05:00 | Z17: 347.5 | AA17: 44.1 | AB17: 0 | AC17: 322.5 | AD17: 714.1
B18: 05:30 | C18: 428.2 | D18: 83.5 | E18: 0 | F18: 50.7 | G18: 3250.1 | H18: 1710.8 | I18: 0 | J18: 311.4 | K18: 606.7 | L18: 0 | M18: 0 | N18: 0 | O18: 562.4 | P18: 5272.3 | Q18: 606.7 | R18: 6441.4 | S18: 05:30 | T18: 4285 | U18: 1794.3 | V18: 0 | W18: 362.1 | X18: 6441.4 | Y18: 05:30 | Z18: 345.7 | AA18: 43.9 | AB18: 0 | AC18: 362.1 | AD18: 751.7
B19: 06:00 | C19: 436.3 | D19: 84.2 | E19: 0 | F19: 57.8 | G19: 3453.1 | H19: 1670.1 | I19: 0 | J19: 362.8 | K19: 623.3 | L19: 0 | M19: 6.6 | N19: 0 | O19: 578.3 | P19: 5486 | Q19: 629.9 | R19: 6694.2 | S19: 06:00 | T19: 4512.7 | U19: 1754.3 | V19: 6.6 | W19: 420.6 | X19: 6694.2 | Y19: 06:00 | Z19: 347.1 | AA19: 44.4 | AB19: 6.6 | AC19: 420.6 | AD19: 818.7
... B56: TOTAL MWh | C56: 10391.4 | D56: 2123.9 | E56: 2.55 | F56: 1676.25 | G56: 84705.35 | H56: 45986.3 | I56: 6.5 | J56: 11277.95 | K56: 14702.5 | L56: 211.805 | M56: 4005.95 | N56: 0 | O56: 14194.1 | P56: 141976.1 | Q56: 18920.255 | R56: 175090.45 | S56: TOTAL MWh | T56: 109799.25 | U56: 48322.005 | V56: 4015 | W56: 12954.2 | X56: 175090.45 | Y56: TOTAL MWh | Z56: 8361.2 | AA56: 1057.8 | AB56: 4015 | AC56: 12954.2 | AD56: 26388.2

Sheet HOP
B3: jueves, 20 de Marzo del 2025
B5: Reporte de Horas de Operación
B6: Empresa | C6: Central | D6: Grupo | E6: Modo de Operación | F6: Inicio | G6: Final | H6: O. Arranque | I6: O. Parada | J6: Tipo Operación | K6: Ensayo de Potencia Efectiva | L6: Ensayo de Potencia Mínima | M6: Sistema | N6: Lim. Transm. | O6: Causa | P6: Observación
B7: AGRO INDUSTRIAL PARAMONGA S.A. | C7: C.T. PARAMONGA | D7: CENTRAL | E7: PARAMONGA - BAGAZO | F7: 20/03/2025 00:00:00 | G7: 21/03/2025 00:00:00 | J7: POR COGENERACION | O7: ...
B8: AGROAURORA S.A.C. | C8: C.T. MAPLE ETANOL | D8: CENTRAL | E8: MAPLE- BAGAZO | F8: 20/03/2025 00:00:00 | G8: 21/03/2025 00:00:00 | J8: POR COGENERACION | O8: ...
B9: AGROINDUSTRIAS SAN JACINTO S.A.A. | C9: C.T. SAN JACINTO | D9: CENTRAL | E9: SAN_JACINTO - BAGAZO | F9: 20/03/2025 00:00:00 | G9: 21/03/2025 00:00:00 | J9: POR COGENERACION | O9: ...
B10: EGESUR | C10: C.T. INDEPENDENCIA | D10: INDEP_G2 | E10: INDEPENDENCIA GAS | F10: 20/03/2025 10:01:00 | G10: 20/03/2025 14:00:00 | H10: 20/03/2025 09:58:00 | J10: POR PRUEBAS | O10: REQ. PROPIO
B11: ENEL GENERACION PIURA S.A. | C11: C.T. MALACAS 2 | D11: CENTRAL | E11: MALACAS2 TG4 - GAS | F11: 20/03/2025 00:00:00 | G11: 20/03/2025 03:41:00 | I11: 20/03/2025 03:34:00 | J11: A MINIMA CARGA | O11: ...
B12: ENGIE | C12: C.T. CHILCA 1 | D12: CENTRAL | E12: CHILCA1 CCOMB TG1 & TG3 - GAS | F12: 20/03/2025 00:00:00 | G12: 20/03/2025 08:23:00 | J12: A MINIMA CARGA | O12: ...
B13: ENGIE | C13: C.T. CHILCA 1 | D13: CENTRAL | E13: CHILCA1 CCOMB TG1 & TG3 - GAS | F13: 20/03/2025 08:23:00 | G13: 20/03/2025 12:31:00 | J13: POR POTENCIA O ENERGIA | O13: ... | P13: A las 12:26 h, S/C generar a 400 MW.
B14: ENGIE | C14: C.T. CHILCA 1 | D14: CENTRAL | E14: CHILCA1 CCOMB TG1 & TG3 - GAS | F14: 20/03/2025 12:31:00 | G14: 20/03/2025 14:10:00 | J14: A MINIMA CARGA | O14: ...
B15: ENGIE | C15: C.T. CHILCA 1 | D15: CENTRAL | E15: CHILCA1 CCOMB TG1 & TG3 - GAS | F15: 20/03/2025 14:10:00 | G15: 20/03/2025 17:04:00 | J15: POR POTENCIA O ENERGIA | O15: ... | P15: A las 14:10 h, S/C generar a 450 MW. A las 16:44 h, S/C generar a 450 MW.
B16: ENGIE | C16: C.T. CHILCA 1 | D16: TG2 | E16: CHILCA1 TG2 - GAS | F16: 20/03/2025 16:42:00 | G16: 20/03/2025 21:20:00 | H16: 20/03/2025 16:31:00 | I16: 20/03/2025 21:05:00 | J16: A MINIMA CARGA | O16: ...
B17: ENGIE | C17: C.T. CHILCA 1 | D17: CENTRAL | E17: CHILCA1 CCOMB TG1 & TG3 - GAS | F17: 20/03/2025 17:04:00 | G17: 20/03/2025 18:22:00 | J17: A MINIMA CARGA | O17: ...
B18: ENGIE | C18: C.T. CHILCA 1 | D18: CENTRAL | E18: CHILCA1 CCOMB TG1 & TG3 - GAS | F18: 20/03/2025 18:22:00 | G18: 21/03/2025 00:00:00 | J18: POR POTENCIA O ENERGIA | O18: ... | P18: A las 18:22 h, S/C generar a 450 MW. A las 18:28 h, S/C generar a máxima. A las 22:57 h, S/C generar a 450 MW.
B19: ENGIE | C19: C.T. RF PLANTA ILO | D19: TG3 | E19: RF ILO2 TG3 - D2 | F19: 20/03/2025 16:42:00 | G19: 20/03/2025 18:52:00 | H19: 20/03/2025 16:21:00 | I19: 20/03/2025 18:43:00 | J19: POR SEGURIDAD | O19: ... | P19: Para evitar sobrecarga L-2025 y L-2026 por mantenimiento correctivo AUT-5671.
B20: FENIX POWER PERÚ | C20: C.T. FENIX | D20: CENTRAL | E20: FENIX CCOMB GT11 & GT12 - GAS | F20: 20/03/2025 00:00:00 | G20: 20/03/2025 08:58:00 | J20: A MINIMA CARGA | O20: ...
B21: FENIX POWER PERÚ | C21: C.T. FENIX | D21: CENTRAL | E21: FENIX CCOMB GT11 & GT12 - GAS | F21: 20/03/2025 08:58:00 | G21: 20/03/2025 16:47:00 | J21: POR PRUEBAS | O21: REQ. PROPIO
B22: FENIX POWER PERÚ | C22: C.T. FENIX | D22: CENTRAL | E22: FENIX CCOMB GT11 & GT12 - GAS | F22: 20/03/2025 16:47:00 | G22: 20/03/2025 19:08:00 | J22: A MINIMA CARGA | O22: ...
B23: FENIX POWER PERÚ | C23: C.T. FENIX | D23: CENTRAL | E23: FENIX CCOMB GT11 & GT12 - GAS | F23: 20/03/2025 19:08:00 | G23: 20/03/2025 22:01:00 | J23: POR POTENCIA O ENERGIA | O23: ...
B24: FENIX POWER PERÚ | C24: C.T. FENIX | D24: CENTRAL | E24: FENIX CCOMB GT11 & GT12 - GAS | F24: 20/03/2025 22:01:00 | G24: 20/03/2025 23:07:00 | J24: A MINIMA CARGA | O24: ...
B25: FENIX POWER PERÚ | C25: C.T. FENIX | D25: CENTRAL | E25: FENIX CCOMB GT12 - GAS | F25: 20/03/2025 23:07:00 | G25: 21/03/2025 00:00:00 | J25: A MINIMA CARGA | O25: ...
B26: FENIX POWER PERÚ | C26: C.T. FENIX | D26: GT11 | E26: FENIX GT11 - GAS | F26: 20/03/2025 23:07:00 | G26: 20/03/2025 23:11:00 | J26: A MINIMA CARGA | O26: ...
B27: GM OPERACIONES S.A.C. | C27: CT REFINERIA TALARA | D27: TV1 REF TALARA | E27: REF_TALARA TV1 - NLH_RFG | F27: 20/03/2025 00:00:00 | G27: 21/03/2025 00:00:00 | J27: POR COGENERACION | O27: ...
B28: GM OPERACIONES S.A.C. | C28: CT REFINERIA TALARA | D28: TV2 REF TALARA | E28: REF_TALARA TV2 - NLH_RFG | F28: 20/03/2025 00:00:00 | G28: 21/03/2025 00:00:00 | J28: POR COGENERACION | O28: ...
B29: KALLPA GENERACION S.A. | C29: C.T. KALLPA | D29: CENTRAL | E29: KALLPA CCOMB TG1 & TG2 & TG3 - GAS | F29: 20/03/2025 00:00:00 | G29: 20/03/2025 20:23:00 | J29: POR RSF | O29: ...
B30: KALLPA GENERACION S.A. | C30: C.T. KALLPA | D30: CENTRAL | E30: KALLPA CCOMB TG1 & TG2 & TG3 - GAS | F30: 20/03/2025 20:23:00 | G30: 20/03/2025 21:00:00 | J30: POR POTENCIA O ENERGIA | O30: ...
B31: KALLPA GENERACION S.A. | C31: C.T. KALLPA | D31: CENTRAL | E31: KALLPA CCOMB TG1 & TG2 & TG3 - GAS | F31: 20/03/2025 21:00:00 | G31: 21/03/2025 00:00:00 | J31: POR RSF | O31: ...
B32: KALLPA GENERACION S.A. | C32: C.T. LAS FLORES | D32: CENTRAL | E32: LAS FLORES CCOMB TG1 - GAS | F32: 20/03/2025 00:00:00 | G32: 20/03/2025 10:07:00 | J32: A MINIMA CARGA | O32: ...
B33: KALLPA GENERACION S.A. | C33: C.T. LAS FLORES | D33: CENTRAL | E33: LAS FLORES CCOMB TG1 - GAS | F33: 20/03/2025 10:07:00 | G33: 20/03/2025 12:23:00 | J33: POR POTENCIA O ENERGIA | O33: ... | P33: A las 10:07 h, S/C generar a 250 MW.
B34: KALLPA GENERACION S.A. | C34: C.T. LAS FLORES | D34: CENTRAL | E34: LAS FLORES CCOMB TG1 - GAS | F34: 20/03/2025 12:23:00 | G34: 20/03/2025 15:42:00 | J34: A MINIMA CARGA | O34: ...
B35: KALLPA GENERACION S.A. | C35: C.T. LAS FLORES | D35: CENTRAL | E35: LAS FLORES CCOMB TG1 - GAS | F35: 20/03/2025 15:42:00 | G35: 20/03/2025 16:36:00 | J35: POR POTENCIA O ENERGIA | O35: ... | P35: A las 15:49 h, S/C generar a 200 MW.
B36: KALLPA GENERACION S.A. | C36: C.T. LAS FLORES | D36: CENTRAL | E36: LAS FLORES CCOMB TG1 - GAS | F36: 20/03/2025 16:36:00 | G36: 20/03/2025 18:35:00 | J36: A MINIMA CARGA | O36: ...
B37: KALLPA GENERACION S.A. | C37: C.T. LAS FLORES | D37: CENTRAL | E37: LAS FLORES CCOMB TG1 - GAS | F37: 20/03/2025 18:35:00 | G37: 20/03/2025 22:42:00 | J37: POR POTENCIA O ENERGIA | O37: ...
B38: KALLPA GENERACION S.A. | C38: C.T. LAS FLORES | D38: CENTRAL | E38: LAS FLORES CCOMB TG1 - GAS | F38: 20/03/2025 22:42:00 | G38: 21/03/2025 00:00:00 | J38: A MINIMA CARGA | O38: ...
B39: ORYGEN PERU S.A.A. | C39: C.T. VENTANILLA | D39: CENTRAL | E39: VENTANILLA CCOMB TG4 - GAS | F39: 20/03/2025 00:00:00 | G39: 20/03/2025 08:22:00 | J39: A MINIMA CARGA | O39: ...
B40: ORYGEN PERU S.A.A. | C40: C.T. VENTANILLA | D40: CENTRAL | E40: VENTANILLA CCOMB TG4 - GAS | F40: 20/03/2025 08:22:00 | G40: 20/03/2025 17:09:00 | J40: POR POTENCIA O ENERGIA | O40: ...
B41: ORYGEN PERU S.A.A. | C41: C.T. VENTANILLA | D41: CENTRAL | E41: VENTANILLA CCOMB TG4 - GAS | F41: 20/03/2025 17:09:00 | G41: 20/03/2025 18:17:00 | J41: A MINIMA CARGA | O41: ...
B42: ORYGEN PERU S.A.A. | C42: C.T. VENTANILLA | D42: CENTRAL | E42: VENTANILLA CCOMB TG4 - GAS | F42: 20/03/2025 18:17:00 | G42: 21/03/2025 00:00:00 | J42: POR POTENCIA O ENERGIA | O42: ...
B43: PETRAMAS | C43: C.T. HUAYCOLORO | D43: CENTRAL | E43: HUAYCOLORO - BIOGAS | F43: 20/03/2025 00:00:00 | G43: 21/03/2025 00:00:00 | J43: POR POTENCIA O ENERGIA | O43: ...
B44: PETRAMAS | C44: C.T. LA GRINGA | D44: CENTRAL | E44: LA GRINGA V - BIOGAS | F44: 20/03/2025 00:00:00 | G44: 21/03/2025 00:00:00 | J44: POR POTENCIA O ENERGIA | O44: ...
B45: PETRAMAS | C45: C.T.B DOÑA CATALINA | D45: CENTRAL | E45: DONA CATALINA - BIOGAS | F45: 20/03/2025 00:00:00 | G45: 21/03/2025 00:00:00 | J45: POR POTENCIA O ENERGIA | O45: ...
B46: PETRAMAS | C46: C.T.B. CALLAO | D46: CENTRAL | E46: CALLAO - BIOGAS | F46: 20/03/2025 00:00:00 | G46: 21/03/2025 00:00:00 | J46: POR POTENCIA O ENERGIA | O46: ...
B47: SDF ENERGIA SAC | C47: C.T. OQUENDO | D47: CENTRAL | E47: OQUENDO CCOMB TG1 - GAS | F47: 20/03/2025 00:00:00 | G47: 21/03/2025 00:00:00 | J47: POR COGENERACION | O47: ...

Sheet RESERVA_FRÍA
B3: 20/03/2025 | E3: EJECUTADO | L3: Jueves 20 de Marzo del 2025 / SEM N° 11 | V3: EJECUTADO | AC3: Jueves 20 de Marzo del 2025 / SEM N° 11 | ED3: ENERGIA RENOVABLES | GN3: COGENERACION | GW3: NO INTEGRANTES
