Workbook

Sheet EVENTOS
B3: sábado, 26 de Julio del 2025
B5: INFORMACIÓN DE EVENTOS PRINCIPALES EN SUS INSTALACIONES
B6: TIPO DE EVENTO | C6: EMPRESA | D6: UBICACIÓN | E6: TIPO DE EQUIPO | F6: EQUIPO | G6: INICIO | H6: FINAL | I6: DESCRIPCIÓN | J6: MW INDISP. | K6: INTERRUPCIÓN (SI/NO) | L6: TENSIÓN DE FALLA (kV)
B7: EVENTO | C7: CONELSUR LT SAC | D7: PORTILLO | E7: SUBESTACION | F7: SS.EE. | G7: 26/07/2025 00:00:00 | H7: 27/07/2025 00:00:00 | I7: DECLARACIÓN DE SITUACIÓN EXCEPCIONAL EN LA S.E. PORTILLO DE 60 kV | K7: NO
B8: FALLA | C8: LUZ DEL SUR | D8: BALNEARIOS | E8: SVC | F8: SVC-BALNEARIOS | G8: 26/07/2025 19:07:00 | H8: 27/07/2025 00:00:00 | I8: DESCONEXIÓN DEL SVC DE LA S.E. BALNEARIOS | K8: NO | L8: 0
B9: FALLA | C9: RED DE ENERGIA DEL PERU S.A. | D9: TINGO MARÍA | E9: TRANSFORMADOR 3D | F9: AT82-211 | G9: 26/07/2025 15:14:00 | H9: 26/07/2025 15:27:00 | I9: DESCONEXIÓN DEL TRANSFORMADOR AT82-211 DE 220/138 KV DE LA S.E. TINGO MARIA | K9: NO | L9: 220

Sheet RESTRIC_OPE
B3: sábado, 26 de Julio del 2025
B5: RESTRICCIONES OPERATIVAS
B6: FECHA | C6: HORA INICIO | D6: HORA FINAL | E6: EMPRESA | F6: UBICACIÓN | G6: T.Eq. | H6: EQUIPO | I6: DESCRIPCIÓN
B7: 26/07/2025 | C7: 00:00 | D7: 24:00 | E7: EGASA | F7: S.E. CONVERTIDOR | G7: BARRA | H7: BARRA138KV | I7: EGASA limitó la capacidad del transformador 138 kV/33 kV a 50 MVA por deterioro del aislamiento.
B8: 26/07/2025 | C8: 00:00 | D8: 24:00 | E8: ENEL GENERACION PIURA S.A. | F8: C.T. MALACAS | G8: CT | H8: CENTRAL | I8: De acuerdo con la comunicación vía correo del día 24.10.2024. ENEL GENERACIÓN PIURA informa una restricción de potencia para alcanzar 105 MW en simultaneo (TG6+TGN4).
B9: 26/07/2025 | C9: 00:00 | D9: 24:00 | E9: ENEL GENERACION PIURA S.A. | F9: C.T. MALACAS | G9: GT | H9: TG4 | I9: De acuerdo a lo informado mediante correo electronico el día 04.07, la uniadTG4 puede operar a potencia efectiva durante 3 horas o con 80MW durante 4 horas, y el resto de los periodos a mínima generación.
B10: 26/07/2025 | C10: 00:00 | D10: 24:00 | E10: ENGIE | F10: C.E. PUNTA LOMITAS | G10: CE | H10: CENTRAL | I10: De acuerdo a la carta ENG/737-2024 (Exp:202400007555). Limitación de cables de media tensión a 100 MW de los transformadores PLT1 y PLT2 de la CE Punta Lomitas. Quedan limitados a 200 MW la generación de CE Punta Lomitas y Punta Lomitas Extensión.
B11: 26/07/2025 | C11: 00:00 | D11: 24:00 | E11: ENGIE | F11: C.H. YUNCÁN | G11: GH | H11: G3 | I11: Según la carta N° ENG/ 198-2024 enviada por su representada, se opera de forma continua el G3 de la CH Yuncán, debido a la ejecución de mantenimientos necesarios para evitar daños en los sellos de seguridad de la válvula esférica del grupo.
B12: 26/07/2025 | C12: 00:00 | D12: 24:00 | E12: ENGIE | F12: C.T. CHILCA 1 | G12: CT | H12: CENTRAL | I12: Con carta ENG/971-2023, indica que no puede cumplir con las IO considerada en el PDO_17122023 dado que vulneran la seguridad de sus activos. Indican que se debe tomar TMO=168h.
B13: 26/07/2025 | C13: 00:00 | D13: 24:00 | E13: ENGIE | F13: C.T. CHILCA 1 | G13: CT | H13: CENTRAL | I13: Restricción de temperatura de la C.T Chilca, ver valor en el modelo de despacho.
B14: 26/07/2025 | C14: 00:00 | D14: 24:00 | E14: ENGIE | F14: C.T. CHILCA 2 | G14: CT | H14: CENTRAL | I14: Restricción de temperatura de la C.T Chilca2, ver valor en el modelo de despacho.
B15: 26/07/2025 | C15: 00:00 | D15: 24:00 | E15: ENGIE | F15: C.T. CHILCA 2 | G15: CT | H15: CENTRAL | I15: Con carta ENG/971-2023, indica que no puede cumplir con las IO considerada en el PDO_17122023 dado que vulneran la seguridad de sus activos. Indican que se debe tomar TMO=168h.
B16: 26/07/2025 | C16: 00:00 | D16: 24:00 | E16: FENIX POWER PERÚ | F16: C.T. FENIX | G16: CT | H16: CENTRAL | I16: Restricción de temperatura de la CT FENIX, ver valor en el modelo de despacho
B17: 26/07/2025 | C17: 00:00 | D17: 24:00 | E17: FENIX POWER PERÚ | F17: C.T. FENIX | G17: CT | H17: CENTRAL | I17: De acuerdo con lo comunicado en el correo del día 06.05.2024, la CT Fenix cuenta con TMO de 168 hrs en todos su modos de operación.
... B40: 26/07/2025 | C40: 00:00 | D40: 24:00 | E40: TERMOSELVA | F40: C.T. AGUAYTÍA | G40: CT | H40: CENTRAL | I40: Disponibilidad de 23.5 MMSCF para la CT Aguaytía.

Sheet MANTENIMIENTO EJECUTADOS
B3: sábado, 26 de Julio del 2025
B5: Mantenimiento Ejecutado
B6: Empresa | C6: Ubicación | D6: Equipo | E6: Inicio | F6: Final | G6: Descripción | H6: MW Indisp. | I6: Prog. | J6: Dispon | K6: Interrupc. | L6: Tipo | M6: CodEq | N6: TipoEq_Osinerg
B7: ATLANTICA TRANSMISION SUR S.A. | C7: MONTALVO | D7: AUT-5672 | E7: 26/07/2025 00:00 | F7: 26/07/2025 18:00 | G7: Proyecto Refuerzos: Energizacion en vacio por 34 horas de AUT-5672 a traves del INT-5622 (INT-5652 e INT-5672 abiertos) | H7: 0 | I7: P | J7: E/S | K7: N | L7: P.ENERG | M7: 24276 | N7: T
B8: ATLANTICA TRANSMISION SUR S.A. | C8: MONTALVO | D8: BARRA A_220KV | E8: 26/07/2025 00:00 | F8: 27/07/2025 00:00 | G8: Proyecto Refuerzos: Indisponibilidad de la proteccion diferencial de barras 220 kV por Conexion de la nueva UB-87B hacia la UC existente,Configuracion y Pruebas. | H8: 0 | I8: P | J8: E/S | K8: N | L8: P.ENERG | M8: 13869 | N8: T
B9: ATLANTICA TRANSMISION SUR S.A. | C9: MONTALVO | D9: BARRA A_500KV | E9: 26/07/2025 00:00 | F9: 27/07/2025 00:00 | G9: Proyecto Refuerzos: Indisponibilidad de la proteccion diferencial de barras 500kV por conexion de nueva UB-87B hacia la UC existente, Configuracion y Pruebas. | H9: 0 | I9: P | J9: E/S | K9: N | L9: P.ENERG | M9: 13870 | N9: T
B10: ATLANTICA TRANSMISION SUR S.A. | C10: MONTALVO | D10: BARRA B_220kV | E10: 26/07/2025 00:00 | F10: 27/07/2025 00:00 | G10: Proyecto Refuerzos: Indisponibilidad de la proteccion diferencial de barras 220 kV por Conexion de la nueva UB-87B hacia la UC existente,Configuracion y Pruebas. | H10: 0 | I10: P | J10: E/S | K10: N | L10: P.ENERG | M10: 14765 | N10: T
B11: ATLANTICA TRANSMISION SUR S.A. | C11: MONTALVO | D11: BARRA B_500KV | E11: 26/07/2025 00:00 | F11: 27/07/2025 00:00 | G11: Proyecto Refuerzos: Indisponibilidad de la proteccion diferencial de barras 500kV por conexion de nueva UB-87B hacia la UC existente, Configuracion y Pruebas. | H11: 0 | I11: P | J11: E/S | K11: N | L11: P.ENERG | M11: 13871 | N11: T
B12: ATLANTICA TRANSMISION SUR S.A. | C12: MONTALVO | D12: INT-5622 | E12: 26/07/2025 00:00 | F12: 26/07/2025 18:00 | G12: Proyecto Refuerzos: Puesta en servicio de nueva celda INT-5622. Energizacion en vacio por 34 horas de AUT-5672. Prueba con nuevo rele de mando sincronizado PSD | H12: 0 | I12: P | J12: E/S | K12: N | L12: P.ENERG | M12: 24278 | N12: T
B13: ATLANTICA TRANSMISION SUR S.A. | C13: MONTALVO | D13: AUT-5672 | E13: 26/07/2025 08:00 | F13: 26/07/2025 18:00 | G13: Proyecto Refuerzos: verificacion de maestro-seguidor, subir / bajar taps del AUT5671 (1 Tap hacia arriba y 1 Tap hacia abajo, desde Tap en operacion) AUT-5672 energizado en vacio por el lado 220kV | H13: 0 | I13: P | J13: E/S | K13: N | L13: P.ENERG | M13: 24276 | N13: T
B14: ATLANTICA TRANSMISION SUR S.A. | C14: OCONA | D14: INT-5450 | E14: 26/07/2025 00:00 | F14: 27/07/2025 00:00 | G14: Interruptor INT-5450 cerrado con restriccion operativa, REB-5450 en servicio y suministrando los SS.AA. de la S.E. Oco?a. | H14: 0 | I14: P | J14: E/S | K14: N | L14: OTROS | M14: 13761 | N14: T
B15: ATLANTICA TRANSMISION SUR S.A. | C15: OCONA | D15: INT-5462 | E15: 26/07/2025 00:00 | F15: 27/07/2025 00:00 | G15: Seccionador SBA-5462 fase T indisponible por problemas mecanicos, el seccionador permanece cerrado y bloqueado | H15: 0 | I15: P | J15: E/S | K15: N | L15: OTROS | M15: 13758 | N15: T
B16: ATLANTICA TRANSMISION SUR S.A. | C16: POROMA | D16: AUT-5372 | E16: 26/07/2025 00:00 | F16: 27/07/2025 00:00 | G16: Energizado por pruebas de puesta de servicio previo a su integracion. | H16: 0 | I16: P | J16: E/S | K16: N | L16: PRUEBA | M16: 24298 | N16: T
B17: ATLANTICA TRANSMISION SUR S.A. | C17: POROMA | D17: INT-5361 | E17: 26/07/2025 00:00 | F17: 27/07/2025 00:00 | G17: Seccionador SBA-5361 fase R indisponible por problemas mecanicos, el seccionador permanece cerrado y bloqueado | H17: 0 | I17: P | J17: E/S | K17: N | L17: OTROS | M17: 13746 | N17: T
B18: ATLANTICA TRANSMISION SUR S.A. | C18: POROMA | D18: REB-5350 | E18: 26/07/2025 00:00 | F18: 27/07/2025 00:00 | G18: Fuera de servicio po falla en el equipo. | H18: 0 | I18: P | J18: F/S | K18: N | L18: OTROS | M18: 13771 | N18: T
... B123: TRANSMANTARO | C123: YARABAMBA | D123: IN-5120 | E123: 26/07/2025 00:00 | F123: 27/07/2025 00:00 | G123: INTERRUPTOR INDISPONIBLE POR FALLA EN LOS MANDOS DE CONTROL DE N1, N2 Y N3. | H123: 0 | I123: P | J123: F/S | K123: N | L123: OTROS | M123: 17437 | N123: T

Sheet INGRESO OC
A3: sábado, 26 de Julio del 2025
A5: INGRESO A OPERACIÓN COMERCIAL
A6: EMPRESA | B6: TIPO DE EQUIPO | C6: UBICACIÓN | D6: EQUIPO | E6: Fecha y hora de Ingreso a Operación Comercial

Sheet DESPACHO_EJECUTADO
B3: sábado, 26 de Julio del 2025
A5: POTENCIA ACTIVA EJECUTADA DE LAS UNIDADES DE GENERACIÓN DEL SEIN (MW) | FM5: CENTRALES NO INTEGRANTES COES
A6: FECHA | B6: HORA | C6: 65333 | D6: 101 | E6: 102 | F6: 42667 | G6: 42668 | H6: 126 | I6: 127 | J6: 138 | K6: 139 | L6: 197 | M6: 203 | N6: 204 | O6: 230 | P6: 209 | Q6: 56677 | R6: 796 | S6: 2146 | T6: 142 | U6: 143 | V6: 125 | W6: 187 | X6: 163 | Y6: 298 | Z6: 299 | AA6: 219 | AB6: 151 | AC6: 152 | AD6: 153 | AE6: 154 | AF6: 756 | AG6: 156 | AH6: 155 | AI6: 182 | AJ6: 212 | AK6: 758 | AL6: 263 | AM6: 265 | AN6: 775 | AO6: 777 | AP6: 2154 | AQ6: 150 | AR6: 149 | AS6: 188 | AT6: 2131 | AU6: 755 | AV6: 252 | AW6: 249 | AX6: 250 | AY6: 117 | AZ6: 267 | BA6: 268 | BB6: 119 | BC6: 120 | BD6: 189 | BE6: 122 | BF6: 266 | BG6: 337 | BH6: 338 | BI6: 251 | BJ6: 115 | BK6: 239 | BL6: 288 | BM6: 240 | BN6: 241 | BO6: 242 | BP6: 191 | BQ6: 194 | BR6: 196 | BS6: 207 | BT6: 236 | BU6: 795 | BV6: 285 | BW6: 995 | BX6: 996 | BY6: 997 | BZ6: 766 | CA6: 926 | CB6: 924 | CC6: 121 | CD6: 103 | CE6: 104 | CF6: 106 | CG6: 105 | CH6: 107 | CI6: 110 | CJ6: 109 | CK6: 144 | CL6: 113 | CM6: 114 | CN6: 193 | CO6: 208 | CP6: 786 | CQ6: 787 | CR6: 788 | CS6: 789 | CT6: 248 | CU6: 2159 | CV6: 303 | CW6: 59715 | CX6: 62255 | CY6: 1263 | CZ6: 61800 | DA6: 2194 | DB6: 69125 | DC6: 216 | DD6: 198 | DE6: 49607 | DF6: 214 | DG6: 260 | DH6: 2152 | DI6: 2128 | DJ6: 247 | DK6: 228 | DL6: 2135 | DM6: 261 | DN6: 237 | DO6: 253 | DP6: 770 | DQ6: 225 | DR6: 2201 | DS6: 2171 | DT6: 760 | DU6: 235 | DV6: 238 | DW6: 2184 | DX6: 61855 | DY6: 223 | DZ6: 226 | EA6: 201 | EB6: 258 | EC6: 259 | ED6: 920 | EE6: 257 | EF6: 256 | EG6: 2148 | EH6: 58288 | EI6: 58289 | EJ6: 58839 | EK6: 58840 | EL6: 296 | EM6: 297 | EN6: 211 | EO6: 2175 | EP6: 2178 | EQ6: 2181 | ER6: 1262 | ES6: 63425 | ET6: 233 | EU6: 2150 | EV6: 2165 | EW6: 2161 | EX6: 61197 | EY6: 58851 | EZ6: 234 | FA6: 215 | FB6: 917 | FC6: 289 | FD6: 58333 | FE6: 58336 | FF6: 213 | FG6: 232 | FH6: 2190 | FI6: 202 | FJ6: 58487 | FK6: TOTAL COES | FM6: 221 | FN6: 222 | FO6: 224 | FP6: 2187 | FQ6: 227 | FR6: 49400 | FS6: 199 | FT6: 200 | FU6: TOTAL NO COES
C7: SUR | D7: CENTRO | E7: CENTRO | F7: NORTE | G7: NORTE | H7: NORTE | I7: NORTE | J7: CENTRO | K7: CENTRO | L7: CENTRO | M7: CENTRO | N7: CENTRO | O7: CENTRO | P7: CENTRO | Q7: CENTRO | R7: CENTRO | S7: CENTRO | T7: CENTRO | U7: CENTRO | V7: CENTRO | W7: CENTRO | X7: SUR | Y7: SUR | Z7: SUR | AA7: CENTRO | AB7: SUR | AC7: SUR | AD7: SUR | AE7: SUR | AF7: SUR | AG7: SUR | AH7: SUR | AI7: SUR | AJ7: CENTRO | AK7: NORTE | AL7: NORTE | AM7: NORTE | AN7: CENTRO | AO7: CENTRO | AP7: CENTRO | AQ7: CENTRO | AR7: CENTRO | AS7: CENTRO | AT7: CENTRO | AU7: SUR | AV7: CENTRO | AW7: CENTRO | AX7: CENTRO | AY7: CENTRO | AZ7: CENTRO | BA7: CENTRO | BB7: CENTRO | BC7: CENTRO | BD7: SUR | BE7: NORTE | BF7: CENTRO | BG7: CENTRO | BH7: CENTRO | BI7: CENTRO | BJ7: NORTE | BK7: NORTE | BL7: NORTE | BM7: SUR | BN7: SUR | BO7: SUR | BP7: CENTRO | BQ7: CENTRO | BR7: CENTRO | BS7: CENTRO | BT7: CENTRO | BU7: CENTRO | BV7: CENTRO | BW7: SUR | BX7: SUR | BY7: SUR | BZ7: NORTE | CA7: SUR | CB7: CENTRO | CC7: NORTE | CD7: CENTRO | CE7: CENTRO | CF7: CENTRO | CG7: CENTRO | CH7: CENTRO | CI7: CENTRO | CJ7: CENTRO | CK7: CENTRO | CL7: CENTRO | CM7: CENTRO | CN7: CENTRO | CO7: CENTRO | CP7: SUR | CQ7: SUR | CR7: SUR | CS7: SUR | CT7: CENTRO | CU7: CENTRO | CV7: CENTRO | CW7: CENTRO | CX7: SUR | CY7: NORTE | CZ7: NORTE | DA7: NORTE | DB7: CENTRO | DC7: NORTE | DD7: NORTE | DE7: SUR | DF7: CENTRO | DG7: CENTRO | DH7: CENTRO | DI7: NORTE | DJ7: NORTE | DK7: CENTRO | DL7: CENTRO | DM7: SUR | DN7: SUR | DO7: CENTRO | DP7: CENTRO | DQ7: CENTRO | DR7: CENTRO | DS7: CENTRO | DT7: CENTRO | DU7: SUR | DV7: CENTRO | DW7: CENTRO | DX7: NORTE | DY7: CENTRO | DZ7: CENTRO | EA7: NORTE | EB7: CENTRO | EC7: CENTRO | ED7: CENTRO | EE7: NORTE | EF7: NORTE | EG7: SUR | EH7: CENTRO | EI7: CENTRO | EJ7: CENTRO | EK7: CENTRO | EL7: CENTRO | EM7: CENTRO | EN7: SUR | EO7: SUR | EP7: SUR | EQ7: SUR | ER7: NORTE | ES7: SUR | ET7: SUR | EU7: SUR | EV7: CENTRO | EW7: CENTRO | EX7: CENTRO | EY7: SUR | EZ7: SUR | FA7: NORTE | FB7: CENTRO | FC7: NORTE | FD7: NORTE | FE7: NORTE | FF7: CENTRO | FG7: NORTE | FH7: NORTE | FI7: CENTRO | FJ7: CENTRO | FM7: NORTE | FN7: CENTRO | FO7: NORTE | FP7: NORTE | FQ7: NORTE | FR7: NORTE | FS7: NORTE | FT7: NORTE
C8: HIDROELÉCTRICA | D8: HIDROELÉCTRICA | E8: HIDROELÉCTRICA | F8: TERMOELÉCTRICA | G8: TERMOELÉCTRICA | H8: HIDROELÉCTRICA | I8: HIDROELÉCTRICA | J8: TERMOELÉCTRICA | K8: TERMOELÉCTRICA | L8: TERMOELÉCTRICA | M8: TERMOELÉCTRICA | N8: TERMOELÉCTRICA | O8: TERMOELÉCTRICA | P8: TERMOELÉCTRICA | Q8: TERMOELÉCTRICA | R8: HIDROELÉCTRICA | S8: HIDROELÉCTRICA | T8: TERMOELÉCTRICA | U8: TERMOELÉCTRICA | V8: TERMOELÉCTRICA | W8: TERMOELÉCTRICA | X8: HIDROELÉCTRICA | Y8: HIDROELÉCTRICA | Z8: HIDROELÉCTRICA | AA8: TERMOELÉCTRICA | AB8: HIDROELÉCTRICA | AC8: HIDROELÉCTRICA | AD8: HIDROELÉCTRICA | AE8: HIDROELÉCTRICA | AF8: TERMOELÉCTRICA | AG8: TERMOELÉCTRICA | AH8: TERMOELÉCTRICA | AI8: HIDROELÉCTRICA | AJ8: HIDROELÉCTRICA | AK8: TERMOELÉCTRICA | AL8: TERMOELÉCTRICA | AM8: TERMOELÉCTRICA | AN8: HIDROELÉCTRICA | AO8: HIDROELÉCTRICA | AP8: HIDROELÉCTRICA | AQ8: HIDROELÉCTRICA | AR8: HIDROELÉCTRICA | AS8: HIDROELÉCTRICA | AT8: HIDROELÉCTRICA | AU8: HIDROELÉCTRICA | AV8: TERMOELÉCTRICA | AW8: TERMOELÉCTRICA | AX8: TERMOELÉCTRICA | AY8: HIDROELÉCTRICA | AZ8: HIDROELÉCTRICA | BA8: HIDROELÉCTRICA | BB8: HIDROELÉCTRICA | BC8: HIDROELÉCTRICA | BD8: HIDROELÉCTRICA | BE8: HIDROELÉCTRICA | BF8: HIDROELÉCTRICA | BG8: HIDROELÉCTRICA | BH8: HIDROELÉCTRICA | BI8: HIDROELÉCTRICA | BJ8: TERMOELÉCTRICA | BK8: TERMOELÉCTRICA | BL8: TERMOELÉCTRICA | BM8: TERMOELÉCTRICA | BN8: TERMOELÉCTRICA | BO8: TERMOELÉCTRICA | BP8: HIDROELÉCTRICA | BQ8: TERMOELÉCTRICA | BR8: TERMOELÉCTRICA | BS8: TERMOELÉCTRICA | BT8: TERMOELÉCTRICA | BU8: TERMOELÉCTRICA | BV8: TERMOELÉCTRICA | BW8: TERMOELÉCTRICA | BX8: TERMOELÉCTRICA | BY8: TERMOELÉCTRICA | BZ8: HIDROELÉCTRICA | CA8: TERMOELÉCTRICA | CB8: TERMOELÉCTRICA | CC8: HIDROELÉCTRICA | CD8: HIDROELÉCTRICA | CE8: HIDROELÉCTRICA | CF8: HIDROELÉCTRICA | CG8: HIDROELÉCTRICA | CH8: HIDROELÉCTRICA | CI8: TERMOELÉCTRICA | CJ8: TERMOELÉCTRICA | CK8: TERMOELÉCTRICA | CL8: TERMOELÉCTRICA | CM8: TERMOELÉCTRICA | CN8: TERMOELÉCTRICA | CO8: TERMOELÉCTRICA | CP8: TERMOELÉCTRICA | CQ8: TERMOELÉCTRICA | CR8: TERMOELÉCTRICA | CS8: TERMOELÉCTRICA | CT8: TERMOELÉCTRICA | CU8: TERMOELÉCTRICA | CV8: SOLAR | CW8: EÓLICA | CX8: SOLAR | CY8: EÓLICA | CZ8: SOLAR | DA8: HIDROELÉCTRICA | DB8: HIDROELÉCTRICA | DC8: HIDROELÉCTRICA | DD8: HIDROELÉCTRICA | DE8: HIDROELÉCTRICA | DF8: HIDROELÉCTRICA | DG8: HIDROELÉCTRICA | DH8: HIDROELÉCTRICA | DI8: HIDROELÉCTRICA | DJ8: HIDROELÉCTRICA | DK8: HIDROELÉCTRICA | DL8: HIDROELÉCTRICA | DM8: SOLAR | DN8: SOLAR | DO8: EÓLICA | DP8: EÓLICA | DQ8: TERMOELÉCTRICA | DR8: TERMOELÉCTRICA | DS8: TERMOELÉCTRICA | DT8: TERMOELÉCTRICA | DU8: SOLAR | DV8: HIDROELÉCTRICA | DW8: HIDROELÉCTRICA | DX8: HIDROELÉCTRICA | DY8: HIDROELÉCTRICA | DZ8: HIDROELÉCTRICA | EA8: HIDROELÉCTRICA | EB8: HIDROELÉCTRICA | EC8: HIDROELÉCTRICA | ED8: HIDROELÉCTRICA | EE8: EÓLICA | EF8: EÓLICA | EG8: SOLAR | EH8: EÓLICA | EI8: EÓLICA | EJ8: EÓLICA | EK8: EÓLICA | EL8: HIDROELÉCTRICA | EM8: HIDROELÉCTRICA | EN8: HIDROELÉCTRICA | EO8: HIDROELÉCTRICA | EP8: HIDROELÉCTRICA | EQ8: HIDROELÉCTRICA | ER8: EÓLICA | ES8: SOLAR | ET8: SOLAR | EU8: SOLAR | EV8: HIDROELÉCTRICA | EW8: EÓLICA | EX8: EÓLICA | EY8: SOLAR | EZ8: SOLAR | FA8: HIDROELÉCTRICA | FB8: HIDROELÉCTRICA | FC8: TERMOELÉCTRICA | FD8: TERMOELÉCTRICA | FE8: TERMOELÉCTRICA | FF8: TERMOELÉCTRICA | FG8: TERMOELÉCTRICA | FH8: TERMOELÉCTRICA | FI8: TERMOELÉCTRICA | FJ8: TERMOELÉCTRICA | FM8: HIDROELÉCTRICA | FN8: HIDROELÉCTRICA | FO8: HIDROELÉCTRICA | FP8: HIDROELÉCTRICA | FQ8: TERMOELÉCTRICA | FR8: TERMOELÉCTRICA | FS8: HIDROELÉCTRICA | FT8: HIDROELÉCTRICA
C9: HYDRO GLOBAL PERÚ S.A.C. | D9: ELECTROPERU | E9: ELECTROPERU | F9: ELECTROPERU | G9: ELECTROPERU | H9: ORAZUL ENERGY PERÚ | I9: ORAZUL ENERGY PERÚ | J9: TERMOSELVA | K9: TERMOSELVA | L9: KALLPA GENERACION S.A. | M9: KALLPA GENERACION S.A. | N9: KALLPA GENERACION S.A. | O9: KALLPA GENERACION S.A. | P9: KALLPA GENERACION S.A. | Q9: KALLPA GENERACION S.A. | R9: KALLPA GENERACION S.A. | S9: KALLPA GENERACION S.A. | T9: SHOUGESA | U9: SHOUGESA | V9: SHOUGESA | W9: SHOUGESA | X9: EGEMSA | Y9: EGESUR | Z9: EGESUR | AA9: EGESUR | AB9: EGASA | AC9: EGASA | AD9: EGASA | AE9: EGASA | AF9: EGASA | AG9: EGASA | AH9: EGASA | AI9: SAN GABAN | AJ9: CELEPSA | AK9: MINERA CERRO VERDE | AL9: PLANTA DE RESERVA FRIA DE GENERACION DE ETEN S.A. | AM9: PLANTA DE RESERVA FRIA DE GENERACION DE ETEN S.A. | AN9: EMPRESA DE GENERACION HUALLAGA | AO9: EMPRESA DE GENERACION HUALLAGA | AP9: LA VIRGEN | AQ9: CHINANGO S.A.C. | AR9: CHINANGO S.A.C. | AS9: HIDROELECTRICA HUANCHOR S.A.C. | AT9: CELEPSA RENOVABLES S.R.L. | AU9: INLAND ENERGY SAC | AV9: FENIX POWER PERÚ | AW9: FENIX POWER PERÚ | AX9: FENIX POWER PERÚ | AY9: STATKRAFT S.A | AZ9: STATKRAFT S.A | BA9: STATKRAFT S.A | BB9: STATKRAFT S.A | BC9: STATKRAFT S.A | BD9: STATKRAFT S.A | BE9: STATKRAFT S.A | BF9: STATKRAFT S.A | BG9: CENTRALES SANTA ROSA S.A.C. | BH9: CENTRALES SANTA ROSA S.A.C. | BI9: EMPRESA DE GENERACION HUANZA | BJ9: ENEL GENERACION PIURA S.A. | BK9: ENEL GENERACION PIURA S.A. | BL9: ENEL GENERACION PIURA S.A. | BM9: ENGIE | BN9: ENGIE | BO9: ENGIE | BP9: ENGIE | BQ9: ENGIE | BR9: ENGIE | BS9: ENGIE | BT9: ENGIE | BU9: ENGIE | BV9: ENGIE | BW9: ENGIE | BX9: ENGIE | BY9: ENGIE | BZ9: ENGIE | CA9: INFRAESTRUCTURAS Y ENERGIAS DEL PERU S.A.C. | CB9: INFRAESTRUCTURAS Y ENERGIAS DEL PERU S.A.C. | CC9: INVERSIONES SHAQSHA S.A.C. | CD9: ORYGEN PERU S.A.A. | CE9: ORYGEN PERU S.A.A. | CF9: ORYGEN PERU S.A.A. | CG9: ORYGEN PERU S.A.A. | CH9: ORYGEN PERU S.A.A. | CI9: ORYGEN PERU S.A.A. | CJ9: ORYGEN PERU S.A.A. | CK9: ORYGEN PERU S.A.A. | CL9: ORYGEN PERU S.A.A. | CM9: ORYGEN PERU S.A.A. | CN9: ORYGEN PERU S.A.A. | CO9: ORYGEN PERU S.A.A. | CP9: SAMAY I S.A.C | CQ9: SAMAY I S.A.C | CR9: SAMAY I S.A.C | CS9: SAMAY I S.A.C | CT9: TERMOCHILCA S.A.C. | CU9: TERMOCHILCA S.A.C. | CV9: COLCA SOLAR S.A.C. | CW9: ENERGIA RENOVABLE DEL SUR S.A. | CX9: GR CORTARRAMA SOCIEDAD ANONIMA CERRADA | CY9: GR TARUCA SOCIEDAD ANONIMA CERRADA | CZ9: KONDU SAC | DA9: PERUANA DE INVERSIONES EN ENERGIAS RENOVABLES S.A. | DB9: VARI ENERGIA S.A.C. | DC9: ORAZUL ENERGY PERÚ | DD9: ORAZUL ENERGY PERÚ | DE9: SAN GABAN | DF9: MAJA ENERGIA S.A.C. | DG9: EMPRESA DE GENERACION ELECTRICA CANCHAYLLO SAC | DH9: EMPRESA DE GENERACION ELECTRICA SANTA ANA S.A.C. | DI9: EMPRESA ELECTRICA AGUA AZUL | DJ9: EMPRESA ELECTRICA RIO DOBLE | DK9: HIDROCAÑETE S.A. | DL9: HUAURA POWER GROUP S.A. | DM9: MOQUEGUA FV S.A.C. | DN9: PANAMERICANA SOLAR SAC. | DO9: PARQUE EOLICO MARCONA S.A.C. | DP9: PARQUE EOLICO TRES HERMANAS S.A.C. | DQ9: PETRAMAS | DR9: PETRAMAS | DS9: PETRAMAS | DT9: PETRAMAS | DU9: TACNA SOLAR SAC. | DV9: ELECTRICA YANAPAMPA SAC | DW9: ANDEAN POWER S.A.C. | DX9: ASOCIACIÓN SANTA LUCIA DE CHACAS | DY9: ATRIA ENERGIA S.A.C. | DZ9: EGEJUNIN | EA9: EGEJUNIN | EB9: EGEJUNIN | EC9: EGEJUNIN | ED9: EMPRESA DE GENERACION ELECTRICA RIO BAÑOS S.A.C. | EE9: ENERGÍA EÓLICA S.A. | EF9: ENERGÍA EÓLICA S.A. | EG9: ENGIE | EH9: ENGIE | EI9: ENGIE | EJ9: ENGIE | EK9: ENGIE | EL9: GENERACIÓN ANDINA S.A.C. | EM9: GENERACIÓN ANDINA S.A.C. | EN9: GENERADORA DE ENERGÍA DEL PERÚ | EO9: GENERADORA DE ENERGÍA DEL PERÚ | EP9: GENERADORA DE ENERGÍA DEL PERÚ | EQ9: GENERADORA DE ENERGÍA DEL PERÚ | ER9: GR PAINO SOCIEDAD ANONIMA CERRADA | ES9: JOYA SOLAR S.A.C. | ET9: MAJES ARCUS S.A.C. | EU9: ORYGEN PERU S.A.A. | EV9: ORYGEN PERU S.A.A. | EW9: ORYGEN PERU S.A.A. | EX9: ORYGEN PERU S.A.A. | EY9: ORYGEN PERU S.A.A. | EZ9: REPARTICIÓN ARCUS S.A.C. | FA9: SINERSA | FB9: SINERSA | FC9: BIOENERGIA DEL CHIRA S.A. | FD9: GM OPERACIONES S.A.C. | FE9: GM OPERACIONES S.A.C. | FF9: AGRO INDUSTRIAL PARAMONGA S.A. | FG9: AGROAURORA S.A.C. | FH9: AGROINDUSTRIAS SAN JACINTO S.A.A. | FI9: SDF ENERGIA SAC | FJ9: SDF ENERGIA SAC | FM9: UNACEM PERU S.A. | FN9: ELECTRO ORIENTE | FO9: AGUAS Y ENERGIA PERU | FP9: ELECTRO ZAÑA S.A.C. | FQ9: ELECTRONOROESTE S.A. | FR9: SDE PIURA | FS9: SINERSA | FT9: SINERSA
C10: SAN GABAN III | D10: MANTARO | E10: RESTITUCION | F10: TUMBES MAK 1 | G10: TUMBES MAK 2 | H10: CARHUAQUERO | I10: CAÑON DEL PATO | J10: AGUAYTIA TG1 | K10: AGUAYTIA TG2 | L10: KALLPA TG1 | M10: KALLPA TG2 | N10: KALLPA TG3 | O10: KALLPA TV | P10: LFLORES TG1 | Q10: LFLORES TV | R10: CERRO DEL AGUILA | S10: CERRODELAGUILAG4 | T10: SHOUGESA TV1 | U10: SHOUGESA TV2 | V10: SHOUGESA TV3 | W10: SHOUGESA CUMMINS | X10: MACHUPICCHU | Y10: ARICOTA 1 | Z10: ARICOTA 2 | AA10: INDEPENDENCIA | AB10: CHARCANI I,II,III | AC10: CHARCANI IV | AD10: CHARCANI V | AE10: CHARCANI VI | AF10: CHILINA TG | AG10: MOLLENDO 1, 2, 3 | AH10: CHILINA (SULZ 1,2) | AI10: SAN GABAN II | AJ10: PLATANAL | AK10: RECKA | AL10: RF ETEN TG1 | AM10: RF ETEN TG2 | AN10: CHAGLLA GP1 | AO10: CHAGLLA | AP10: LA VIRGEN | AQ10: CHIMAY | AR10: YANANGO | AS10: HUANCHOR | AT10: MARAÑON | AU10: STA TERESA | AV10: FENIX GT11 | AW10: FENIX GT12 | AX10: FENIX TV10 | AY10: YAUPI | AZ10: OROYA | BA10: PACHACHACA | BB10: MALPASO | BC10: CAHUA | BD10: ARCATA | BE10: GALLITO CIEGO | BF10: CHEVES | BG10: SANTA ROSA 1 | BH10: SANTA ROSA 2 | BI10: HUANZA | BJ10: MALACAS2 TG4 | BK10: MALACAS3 TG 5 | BL10: MALACAS1 TG6 | BM10: RF ILO2 TG1 | BN10: RF ILO2 TG2 | BO10: RF ILO2 TG3 | BP10: YUNCAN | BQ10: CHILCA1 TG1 | BR10: CHILCA1 TG2 | BS10: CHILCA1 TG3 | BT10: CHILCA-TV | BU10: CHILCA2 TG41 | BV10: CHILCA2-TV | BW10: CTNEPI_TG41 | BX10: CTNEPI_TG42 | BY10: CTNEPI_TG43 | BZ10: QUITARACSA | CA10: RF PTO MALDONADO | CB10: RF PUCALLPA | CC10: PARIAC | CD10: HUINCO | CE10: MATUCANA | CF10: MOYOPAMPA | CG10: CALLAHUANCA | CH10: HUAMPANI | CI10: STA ROSA WEST TG7 | CJ10: UTI_5 | CK10: UTI_6 | CL10: VENTANILLA 3 | CM10: VENTANILLA 4 | CN10: VENTANILLA TV | CO10: STAROSA TG8 | CP10: PTO_BRVO TG1 | CQ10: PTO_BRVO TG2 | CR10: PTO_BRVO TG3 | CS10: PTO_BRVO TG4 | CT10: OLLEROS TG1 | CU10: OLLEROS TV | CV10: CS YARUCAYA | CW10: SAN JUAN | CX10: MATARANI | CY10: DUNA | CZ10: CARHUAQUERO (CS) | DA10: MANTA I | DB10: ANASHIRONI | DC10: CARHUAQUERO4 | DD10: CAÑA BRAVA | DE10: TUPURI | DF10: RONCADOR | DG10: CANCHAYLLO | DH10: RENOVANDESH1 | DI10: POTRERO | DJ10: PIZARRAS | DK10: NIMPERIAL | DL10: YARUCAYA | DM10: MOQUEGUA-SOLAR | DN10: PANAMERICANA-SOLAR | DO10: PQE-EOLICO-MARCONA | DP10: PQE-EOLICO-3-HERMANAS | DQ10: HUAYCOLORO | DR10: CALLAO | DS10: DONA_CATALINA | DT10: LAGRINGAV | DU10: TACNA-SOLAR | DV10: YANAPAMPA | DW10: CARHUAC | DX10: HUALLIN | DY10: PURMACANA | DZ10: HUASAHUASI | EA10: STACRUZ_1_2 | EB10: RUNATULLO_II | EC10: RUNATULLO_III | ED10: RUCUY | EE10: PQE-EOLICO-TALARA | EF10: PQE-EOLICO-CUPISNIQUE | EG10: INTIPAMPA | EH10: PUNTA LOMITAS-BL1 | EI10: PUNTA LOMITAS-BL2 | EJ10: PUN LOMITAS_EXP-BL1 | EK10: PUN LOMITAS_EXP-BL2 | EL10: 8AGOSTO | EM10: EL CARMEN | EN10: LA JOYA | EO10: ANGEL_I | EP10: ANGEL_II | EQ10: ANGEL_III | ER10: HUAMBOS | ES10: SAN MARTIN SOLAR | ET10: MAJES | EU10: RUBI | EV10: CH_HER1 | EW10: WAYRA-I | EX10: WAYRA EXTENSION | EY10: CLEMESI | EZ10: REPARTICION | FA10: POECHOS2 | FB10: CHANCAY | FC10: CANA BRAVA | FD10: REFINERIA TALARA TV1 | FE10: REFINERÍA TALARA TV2 | FF10: PARAMONGA | FG10: MAPLE | FH10: SAN_JACINTO | FI10: OQUENDO TG1 | FJ10: OQUENDO TV1 | FK10: MW | FM10: CARPAPATA | FN10: CENTRALES ELOR | FO10: PIAS1 | FP10: ZANA | FQ10: TABLAZO | FR10: TALLANCA | FS10: CURUMUY | FT10: POECHOS1 | FU10: MW
A11: 26/07/2025 | B11: 00:30 | C11: 146.1 | D11: 641 | E11: 215.4 | H11: 59.9 | I11: 76 | J11: 67.2 | L11: 0 | M11: 205.2 | N11: 205.7 | O11: 181.2 | P11: 216 | Q11: 111.3 | R11: 443.8 | S11: 4.2 | X11: 104.4 | Y11: 7.7 | Z11: 5.3 | AA11: 0 | AB11: 6.8 | AC11: 11.8 | AD11: 74.2 | AI11: 60.1 | AJ11: 164.5 | AN11: 6.5 | AO11: 185.3 | AP11: 28.3 | AQ11: 30.6 | AR11: 18.5 | AS11: 18.6 | AT11: 12.6 | AU11: 56.7 | AV11: 181 | AW11: 181 | AX11: 183.4 | AY11: 81.5 | AZ11: 4.6 | BA11: 0 | BB11: 36 | BC11: 30.8 | BD11: 2 | BE11: 17.2 | BF11: 49.6 | BI11: 21.5 | BL11: 47.3 | BP11: 65.8 | BQ11: 177.5 | BR11: 175.1 | BS11: 200 | BT11: 273.5 | CC11: 1 | CD11: 107.7 | CE11: 75 | CF11: 64 | CG11: 73.9 | CH11: 29.9 | CL11: 146.2 | CM11: 148.7 | CN11: 150 | CO11: 0 | CT11: 217.8 | CU11: 104.3 | CV11: 0 | CW11: 15.9 | CX11: 0 | CY11: 9 | CZ11: 0 | DA11: 7.4 | DB11: 5 | DC11: 9.9 | DD11: 4.9 | DE11: 0.3 | DF11: 1.5 | DG11: 1.9 | DH11: 18.5 | DI11: 7.2 | DJ11: 4 | DK11: 3.4 | DL11: 18.5 | DM11: 0 | DN11: 0 | DO11: 5 | DP11: 15.8 | DQ11: 4.5 | DR11: 1.2 | DS11: 2.4 | DT11: 2.6 | DU11: 0 | DV11: 1.9 | DW11: 7.2 | DX11: 1.5 | DY11: 0.4 | DZ11: 4 | EA11: 3.9 | EB11: 3.4 | EC11: 4.7 | ED11: 11 | EE11: 11.8 | EF11: 20.8 | EG11: 0 | EH11: 28 | EI11: 44.6 | EJ11: 2.8 | EK11: 1.4 | EL11: 5 | EM11: 2 | EN11: 7.4 | EO11: 3.8 | EP11: 4.4 | EQ11: 4.6 | ER11: 5.1 | ES11: 0 | ET11: 0 | EU11: 0 | EV11: 0.6 | EW11: 10.4 | EX11: 18.3 | EY11: 0 | EZ11: 0 | FA11: 6.6 | FB11: 19.7 | FC11: 8.9 | FD11: 36.3 | FE11: 18.4 | FF11: 14.5 | FG11: 19 | FH11: 8.4 | FK11: 6690.9 | FM11: 19.08728 | FN11: 0 | FO11: 6.076 | FP11: 7.5 | FQ11: 27.30137 | FR11: 18.9 | FS11: 3.6 | FT11: 6.9 | FU11: 89.36465
A12: 26/07/2025 | B12: 01:00 | C12: 24.2 | D12: 641.6 | E12: 215.1 | H12: 59.7 | I12: 77.3 | J12: 40.4 | L12: 0 | M12: 208.7 | N12: 211.2 | O12: 199.5 | P12: 217.7 | Q12: 110.9 | R12: 452.3 | S12: 4.2 | X12: 104.3 | Y12: 7.5 | Z12: 5.3 | AA12: 0 | AB12: 6.8 | AC12: 10.9 | AD12: 39.2 | AI12: 56.1 | AJ12: 133.7 | AN12: 6.5 | AO12: 229.2 | AP12: 28 | AQ12: 0 | AR12: 17.6 | AS12: 18.6 | AT12: 12.6 | AU12: 55.9 | AV12: 181.1 | AW12: 180.7 | AX12: 183.4 | AY12: 83.1 | AZ12: 4.4 | BA12: 0 | BB12: 32.6 | BC12: 33 | BD12: 2 | BE12: 0 | BF12: 49.4 | BI12: 47.5 | BL12: 47.4 | BP12: 65.3 | BQ12: 178.8 | BR12: 176.2 | BS12: 200 | BT12: 274.1 | CC12: 1 | CD12: 71 | CE12: 72.7 | CF12: 63.8 | CG12: 74.1 | CH12: 29.9 | CL12: 147.5 | CM12: 149.7 | CN12: 151.5 | CO12: 0 | CT12: 216.9 | CU12: 104.3 | CV12: 0 | CW12: 14.6 | CX12: 0 | CY12: 7.1 | CZ12: 0 | DA12: 7.4 | DB12: 5.1 | DC12: 9.9 | DD12: 4.9 | DE12: 0.3 | DF12: 1.5 | DG12: 1.9 | DH12: 18.4 | DI12: 7.2 | DJ12: 4 | DK12: 3.4 | DL12: 18.5 | DM12: 0 | DN12: 0 | DO12: 3.2 | DP12: 11.8 | DQ12: 4.5 | DR12: 1.2 | DS12: 2.4 | DT12: 2.6 | DU12: 0 | DV12: 1.9 | DW12: 7.7 | DX12: 1.4 | DY12: 0.4 | DZ12: 4 | EA12: 4 | EB12: 3.3 | EC12: 4.7 | ED12: 10 | EE12: 13.9 | EF12: 20.3 | EG12: 0 | EH12: 31.1 | EI12: 45.9 | EJ12: 4.1 | EK12: 2.5 | EL12: 5 | EM12: 2 | EN12: 7.4 | EO12: 3.8 | EP12: 4.4 | EQ12: 4.6 | ER12: 5.8 | ES12: 0 | ET12: 0 | EU12: 0 | EV12: 0.6 | EW12: 16.5 | EX12: 20.1 | EY12: 0 | EZ12: 0 | FA12: 6.6 | FB12: 20 | FC12: 9.4 | FD12: 35.6 | FE12: 17.9 | FF12: 14.2 | FG12: 19.1 | FH12: 7.6 | FK12: 6502.1 | FM12: 19.50009 | FN12: 0 | FO12: 6.076 | FP12: 7.5 | FQ12: 27.33749 | FR12: 18.54942 | FS12: 3.6 | FT12: 7 | FU12: 89.563
A13: 26/07/2025 | B13: 01:30 | C13: 26 | D13: 638.8 | E13: 214.4 | H13: 0 | I13: 78.9 | J13: 41.5 | L13: 0 | M13: 208 | N13: 211.2 | O13: 200.3 | P13: 217 | Q13: 111.4 | R13: 482.9 | S13: 4.2 | X13: 104.5 | Y13: 7.5 | Z13: 4.8 | AA13: 0 | AB13: 6.9 | AC13: 10.2 | AD13: 40 | AI13: 56.1 | AJ13: 0 | AN13: 6.4 | AO13: 230.4 | AP13: 28 | AQ13: 0 | AR13: 18.6 | AS13: 18.6 | AT13: 12.6 | AU13: 56.6 | AV13: 183.4 | AW13: 183.9 | AX13: 183.8 | AY13: 81.7 | AZ13: 4.3 | BA13: 0 | BB13: 34.6 | BC13: 35.5 | BD13: 2 | BE13: 0 | BF13: 48.6 | BI13: 47.4 | BL13: 47.3 | BP13: 66 | BQ13: 178 | BR13: 175.5 | BS13: 200 | BT13: 272.9 | CC13: 1.1 | CD13: 75.3 | CE13: 78.9 | CF13: 63.9 | CG13: 74 | CH13: 29.9 | CL13: 147.3 | CM13: 149.3 | CN13: 151.3 | CO13: 0 | CT13: 217.7 | CU13: 104.3 | CV13: 0 | CW13: 13.4 | CX13: 0 | CY13: 5.7 | CZ13: 0 | DA13: 7.3 | DB13: 5.1 | DC13: 0 | DD13: 0.6 | DE13: 0.3 | DF13: 1.5 | DG13: 1.8 | DH13: 18.6 | DI13: 7.2 | DJ13: 4 | DK13: 3.4 | DL13: 18.5 | DM13: 0 | DN13: 0 | DO13: 3.1 | DP13: 9.7 | DQ13: 4.5 | DR13: 1.2 | DS13: 2.4 | DT13: 2.6 | DU13: 0 | DV13: 1.9 | DW13: 10.3 | DX13: 1.5 | DY13: 0.4 | DZ13: 4 | EA13: 3.9 | EB13: 3.2 | EC13: 4.6 | ED13: 10 | EE13: 16.3 | EF13: 18.8 | EG13: 0 | EH13: 37.3 | EI13: 55.3 | EJ13: 3.7 | EK13: 2.7 | EL13: 5 | EM13: 2 | EN13: 7.4 | EO13: 3.8 | EP13: 4.4 | EQ13: 4.5 | ER13: 3 | ES13: 0 | ET13: 0 | EU13: 0 | EV13: 0.6 | EW13: 20.6 | EX13: 17.2 | EY13: 0 | EZ13: 0 | FA13: 6.7 | FB13: 20 | FC13: 9.3 | FD13: 36.7 | FE13: 17.7 | FF13: 13.7 | FG13: 19.1 | FH13: 7.4 | FK13: 6357.6 | FM13: 20.02708 | FN13: 0 | FO13: 6.072 | FP13: 7.5 | FQ13: 27.35258 | FR13: 18.54998 | FS13: 3.6 | FT13: 7 | FU13: 90.10164
A14: 26/07/2025 | B14: 02:00 | C14: 22.5 | D14: 644.2 | E14: 216.6 | H14: 0 | I14: 81.1 | J14: 41.9 | L14: 0 | M14: 206.5 | N14: 211.2 | O14: 198.5 | P14: 216.3 | Q14: 111.2 | R14: 527.8 | S14: 4.2 | X14: 102.2 | Y14: 7.9 | Z14: 4.9 | AA14: 0 | AB14: 7.1 | AC14: 10.2 | AD14: 40.8 | AI14: 56.6 | AJ14: 0 | AN14: 6.5 | AO14: 230.3 | AP14: 28 | AQ14: 0 | AR14: 20.2 | AS14: 18.6 | AT14: 12.6 | AU14: 57 | AV14: 183.2 | AW14: 183.9 | AX14: 184.2 | AY14: 81.9 | AZ14: 4.3 | BA14: 0 | BB14: 34.3 | BC14: 36.4 | BD14: 2 | BE14: 0 | BF14: 63.2 | BI14: 47.6 | BL14: 47.5 | BP14: 66.3 | BQ14: 177.8 | BR14: 175.1 | BS14: 200 | BT14: 273.2 | CC14: 1 | CD14: 72.5 | CE14: 77.1 | CF14: 64.3 | CG14: 74 | CH14: 29 | CL14: 146.5 | CM14: 149 | CN14: 149.5 | CO14: 0 | CT14: 217.8 | CU14: 104.5 | CV14: 0 | CW14: 9.9 | CX14: 0 | CY14: 4.6 | CZ14: 0 | DA14: 7.4 | DB14: 5.1 | DC14: 0 | DD14: 0 | DE14: 0.3 | DF14: 1.5 | DG14: 1.9 | DH14: 18.6 | DI14: 7.2 | DJ14: 4 | DK14: 3.4 | DL14: 18.5 | DM14: 0 | DN14: 0 | DO14: 3.6 | DP14: 10.5 | DQ14: 4.5 | DR14: 1.2 | DS14: 2.4 | DT14: 2.6 | DU14: 0 | DV14: 1.8 | DW14: 10.3 | DX14: 1.4 | DY14: 0.4 | DZ14: 4 | EA14: 4 | EB14: 3.5 | EC14: 4.8 | ED14: 13.7 | EE14: 15.4 | EF14: 19.3 | EG14: 0 | EH14: 35.8 | EI14: 49.2 | EJ14: 3.8 | EK14: 2.4 | EL14: 5 | EM14: 2 | EN14: 7.4 | EO14: 3.8 | EP14: 4.4 | EQ14: 4.5 | ER14: 2.9 | ES14: 0 | ET14: 0 | EU14: 0 | EV14: 0.6 | EW14: 17.3 | EX14: 19.8 | EY14: 0 | EZ14: 0 | FA14: 6.7 | FB14: 20 | FC14: 9 | FD14: 36.6 | FE14: 17.5 | FF14: 13.5 | FG14: 19.1 | FH14: 7.4 | FK14: 6405.5 | FM14: 20.48264 | FN14: 0 | FO14: 6.072 | FP14: 7.5 | FQ14: 27.34445 | FR14: 18.54976 | FS14: 3.7 | FT14: 6.9 | FU14: 90.54885
A15: 26/07/2025 | B15: 02:30 | C15: 24.1 | D15: 646.6 | E15: 217.7 | H15: 0 | I15: 82.8 | J15: 37.1 | L15: 0 | M15: 208.1 | N15: 209 | O15: 198.4 | P15: 215.6 | Q15: 111.3 | R15: 412.6 | S15: 4.3 | X15: 106.3 | Y15: 8.3 | Z15: 5 | AA15: 0 | AB15: 7 | AC15: 10.2 | AD15: 41.1 | AI15: 33 | AJ15: 0 | AN15: 6.5 | AO15: 229.7 | AP15: 30.9 | AQ15: 0 | AR15: 22.4 | AS15: 18.6 | AT15: 12.6 | AU15: 57.8 | AV15: 184.2 | AW15: 184.4 | AX15: 183.4 | AY15: 82.2 | AZ15: 4.1 | BA15: 0 | BB15: 34.2 | BC15: 33.7 | BD15: 2 | BE15: 0 | BF15: 53.2 | BI15: 47.6 | BL15: 47.2 | BP15: 66.2 | BQ15: 177.1 | BR15: 173.8 | BS15: 200 | BT15: 272.4 | CC15: 1.1 | CD15: 112.8 | CE15: 90 | CF15: 65.6 | CG15: 70.9 | CH15: 28.7 | CL15: 146 | CM15: 147.8 | CN15: 149.8 | CO15: 0 | CT15: 217.5 | CU15: 104.4 | CV15: 0 | CW15: 8.6 | CX15: 0 | CY15: 7.9 | CZ15: 0 | DA15: 7.4 | DB15: 5.1 | DC15: 0 | DD15: 0 | DE15: 0.3 | DF15: 1.5 | DG15: 2.1 | DH15: 18.9 | DI15: 7.2 | DJ15: 4 | DK15: 3.4 | DL15: 18.5 | DM15: 0 | DN15: 0 | DO15: 3 | DP15: 9.3 | DQ15: 4.5 | DR15: 1.2 | DS15: 2.4 | DT15: 2.6 | DU15: 0 | DV15: 1.8 | DW15: 10.3 | DX15: 1.4 | DY15: 0.4 | DZ15: 4 | EA15: 4 | EB15: 3.6 | EC15: 5 | ED15: 14 | EE15: 18.3 | EF15: 20.5 | EG15: 0 | EH15: 37.4 | EI15: 52.7 | EJ15: 3.9 | EK15: 3.9 | EL15: 5 | EM15: 2 | EN15: 7.7 | EO15: 3.6 | EP15: 4.4 | EQ15: 4.3 | ER15: 4.9 | ES15: 0 | ET15: 0 | EU15: 0 | EV15: 0.6 | EW15: 24.7 | EX15: 31.9 | EY15: 0 | EZ15: 0 | FA15: 6.7 | FB15: 18.8 | FC15: 8.7 | FD15: 36.3 | FE15: 17.6 | FF15: 14.1 | FG15: 19 | FH15: 6.7 | FK15: 6343.4 | FM15: 20.62182 | FN15: 0 | FO15: 6.076 | FP15: 7.5 | FQ15: 27.32882 | FR15: 18.54934 | FS15: 3.6 | FT15: 6.9 | FU15: 90.57598
A16: 26/07/2025 | B16: 03:00 | C16: 29.2 | D16: 642.8 | E16: 216.6 | H16: 0 | I16: 81.8 | J16: 35.1 | L16: 0 | M16: 208.5 | N16: 210.8 | O16: 199.1 | P16: 217.7 | Q16: 111.1 | R16: 445.8 | S16: 4.3 | X16: 106.1 | Y16: 8 | Z16: 4.9 | AA16: 0 | AB16: 6.9 | AC16: 10.4 | AD16: 40.3 | AI16: 33 | AJ16: 0 | AN16: 6.5 | AO16: 229.2 | AP16: 32 | AQ16: 0 | AR16: 22.3 | AS16: 18.6 | AT16: 12.6 | AU16: 56.9 | AV16: 184.6 | AW16: 185 | AX16: 183.4 | AY16: 82.6 | AZ16: 4 | BA16: 0 | BB16: 19.1 | BC16: 35.3 | BD16: 2 | BE16: 0 | BF16: 52.8 | BI16: 47.6 | BL16: 47.5 | BP16: 66.2 | BQ16: 177.4 | BR16: 175 | BS16: 200 | BT16: 274.2 | CC16: 1.1 | CD16: 111.1 | CE16: 112.1 | CF16: 65.4 | CG16: 69.9 | CH16: 28.7 | CL16: 146.4 | CM16: 148.7 | CN16: 150.1 | CO16: 0 | CT16: 218.1 | CU16: 104.4 | CV16: 0 | CW16: 12 | CX16: 0 | CY16: 7 | CZ16: 0 | DA16: 7.4 | DB16: 5.2 | DC16: 0 | DD16: 0 | DE16: 0.3 | DF16: 1.5 | DG16: 2.1 | DH16: 18.8 | DI16: 7.2 | DJ16: 4 | DK16: 3.4 | DL16: 18.5 | DM16: 0 | DN16: 0 | DO16: 2.9 | DP16: 13.2 | DQ16: 4.5 | DR16: 1.2 | DS16: 2.4 | DT16: 2.6 | DU16: 0 | DV16: 1.9 | DW16: 10.3 | DX16: 1.4 | DY16: 0.4 | DZ16: 4 | EA16: 4 | EB16: 3.5 | EC16: 4.9 | ED16: 13.6 | EE16: 20.1 | EF16: 17 | EG16: 0 | EH16: 26.4 | EI16: 40.9 | EJ16: 2.2 | EK16: 1.2 | EL16: 5 | EM16: 2 | EN16: 7.6 | EO16: 3.6 | EP16: 4.4 | EQ16: 4.3 | ER16: 4.2 | ES16: 0 | ET16: 0 | EU16: 0 | EV16: 0.6 | EW16: 18 | EX16: 19.1 | EY16: 0 | EZ16: 0 | FA16: 6.6 | FB16: 18.7 | FC16: 9.3 | FD16: 35.7 | FE16: 21 | FF16: 14 | FG16: 19.1 | FH16: 8 | FK16: 6350.4 | FM16: 20.72309 | FN16: 0 | FO16: 6.072 | FP16: 7.5 | FQ16: 27.26492 | FR16: 18.54968 | FS16: 3.5 | FT16: 6.9 | FU16: 90.50969
A17: 26/07/2025 | B17: 03:30 | C17: 16.6 | D17: 645.8 | E17: 217.3 | H17: 0 | I17: 82.2 | J17: 35.6 | L17: 0 | M17: 209.2 | N17: 212.4 | O17: 200.5 | P17: 217.2 | Q17: 112.3 | R17: 493.3 | S17: 4.1 | X17: 104.7 | Y17: 7.8 | Z17: 5.2 | AA17: 0 | AB17: 7.1 | AC17: 10.4 | AD17: 40.2 | AI17: 34.2 | AJ17: 0 | AN17: 6.5 | AO17: 227.6 | AP17: 32 | AQ17: 0 | AR17: 21.2 | AS17: 18.6 | AT17: 12.6 | AU17: 56.1 | AV17: 180.7 | AW17: 180.9 | AX17: 185.1 | AY17: 81.2 | AZ17: 4.1 | BA17: 0 | BB17: 33.6 | BC17: 24.1 | BD17: 2 | BE17: 0 | BF17: 51 | BI17: 47.3 | BL17: 47.6 | BP17: 64.6 | BQ17: 179.2 | BR17: 176.7 | BS17: 200 | BT17: 273.9 | CC17: 1 | CD17: 64.6 | CE17: 107 | CF17: 64.7 | CG17: 66.9 | CH17: 28.1 | CL17: 148 | CM17: 150.3 | CN17: 151.5 | CO17: 0 | CT17: 217.9 | CU17: 104.4 | CV17: 0 | CW17: 20.4 | CX17: 0 | CY17: 8.1 | CZ17: 0 | DA17: 7.4 | DB17: 5 | DC17: 0 | DD17: 0 | DE17: 0.3 | DF17: 1.5 | DG17: 2.1 | DH17: 18.9 | DI17: 7.2 | DJ17: 4 | DK17: 3.4 | DL17: 18.5 | DM17: 0 | DN17: 0 | DO17: 5 | DP17: 19.8 | DQ17: 4.5 | DR17: 1.2 | DS17: 2.4 | DT17: 2.6 | DU17: 0 | DV17: 2.3 | DW17: 10.3 | DX17: 1.4 | DY17: 0.4 | DZ17: 4 | EA17: 4 | EB17: 3.5 | EC17: 4.8 | ED17: 13.6 | EE17: 19.6 | EF17: 18.4 | EG17: 0 | EH17: 26.2 | EI17: 40.6 | EJ17: 3 | EK17: 2.4 | EL17: 5 | EM17: 2 | EN17: 7.6 | EO17: 3.6 | EP17: 4.4 | EQ17: 4.1 | ER17: 4.2 | ES17: 0 | ET17: 0 | EU17: 0 | EV17: 0.6 | EW17: 11.9 | EX17: 7.7 | EY17: 0 | EZ17: 0 | FA17: 6.8 | FB17: 18.7 | FC17: 9.4 | FD17: 36.4 | FE17: 19.5 | FF17: 13.5 | FG17: 19.1 | FH17: 8 | FK17: 6336.4 | FM17: 20.52331 | FN17: 0 | FO17: 6.076 | FP17: 7.5 | FQ17: 27.18441 | FR17: 18.54965 | FS17: 3.6 | FT17: 7 | FU17: 90.43337
A18: 26/07/2025 | B18: 04:00 | C18: 25 | D18: 648.5 | E18: 218.2 | H18: 0 | I18: 81 | J18: 29.6 | L18: 0 | M18: 209.8 | N18: 210.4 | O18: 198.7 | P18: 217.5 | Q18: 111.5 | R18: 475.9 | S18: 4.3 | X18: 105.6 | Y18: 8.1 | Z18: 5.2 | AA18: 0 | AB18: 7 | AC18: 10.4 | AD18: 41.6 | AI18: 34.8 | AJ18: 0 | AN18: 6.5 | AO18: 229.2 | AP18: 32 | AQ18: 0 | AR18: 22.4 | AS18: 18.6 | AT18: 12.6 | AU18: 56.9 | AV18: 184.5 | AW18: 184.8 | AX18: 184.6 | AY18: 83 | AZ18: 4 | BA18: 0 | BB18: 34.5 | BC18: 24.5 | BD18: 2 | BE18: 0 | BF18: 52.7 | BI18: 45.9 | BL18: 47.4 | BP18: 66.3 | BQ18: 177.8 | BR18: 175.6 | BS18: 200 | BT18: 274 | CC18: 1 | CD18: 46.8 | CE18: 105.6 | CF18: 65.7 | CG18: 67 | CH18: 29.3 | CL18: 147 | CM18: 149.2 | CN18: 150.7 | CO18: 0 | CT18: 217.7 | CU18: 104.4 | CV18: 0 | CW18: 17.9 | CX18: 0 | CY18: 7.3 | CZ18: 0 | DA18: 7.4 | DB18: 5.2 | DC18: 0 | DD18: 0 | DE18: 0.3 | DF18: 1.5 | DG18: 2.1 | DH18: 18.8 | DI18: 7.2 | DJ18: 4 | DK18: 3.4 | DL18: 18.5 | DM18: 0 | DN18: 0 | DO18: 5.5 | DP18: 19.3 | DQ18: 4.5 | DR18: 1.2 | DS18: 2.4 | DT18: 2.6 | DU18: 0 | DV18: 2.3 | DW18: 10.3 | DX18: 1.4 | DY18: 0.4 | DZ18: 4 | EA18: 4 | EB18: 3.6 | EC18: 4.9 | ED18: 13.8 | EE18: 18.7 | EF18: 12.9 | EG18: 0 | EH18: 25.9 | EI18: 49.7 | EJ18: 2.1 | EK18: 1.7 | EL18: 5 | EM18: 2 | EN18: 7.6 | EO18: 3.6 | EP18: 4.2 | EQ18: 4.1 | ER18: 6.8 | ES18: 0 | ET18: 0 | EU18: 0 | EV18: 0.6 | EW18: 12 | EX18: 6.3 | EY18: 0 | EZ18: 0 | FA18: 6.6 | FB18: 18.5 | FC18: 8.3 | FD18: 36.2 | FE18: 20.1 | FF18: 13.6 | FG18: 19.1 | FH18: 8.2 | FK18: 6314.9 | FM18: 20.94337 | FN18: 0 | FO18: 6.072 | FP18: 7.5 | FQ18: 27.11903 | FR18: 18.55034 | FS18: 3.5 | FT18: 7 | FU18: 90.68474
A19: 26/07/2025 | B19: 04:30 | C19: 59.5 | D19: 643 | E19: 216.5 | H19: 0 | I19: 81.1 | J19: 27.2 | L19: 0 | M19: 206.4 | N19: 210.4 | O19: 199.5 | P19: 215.3 | Q19: 111.7 | R19: 492.5 | S19: 4.3 | X19: 106.1 | Y19: 7.1 | Z19: 5.4 | AA19: 0 | AB19: 7 | AC19: 10.4 | AD19: 40.4 | AI19: 60.4 | AJ19: 0 | AN19: 6.5 | AO19: 227.5 | AP19: 32 | AQ19: 0 | AR19: 22.1 | AS19: 18.6 | AT19: 12.5 | AU19: 55.9 | AV19: 182.2 | AW19: 182.5 | AX19: 184.5 | AY19: 81.6 | AZ19: 4.2 | BA19: 0 | BB19: 35.9 | BC19: 31.9 | BD19: 2 | BE19: 0 | BF19: 50.5 | BI19: 22.3 | BL19: 47.3 | BP19: 65.9 | BQ19: 177.2 | BR19: 174.7 | BS19: 200 | BT19: 273.5 | CC19: 1 | CD19: 53.2 | CE19: 108 | CF19: 65.1 | CG19: 67 | CH19: 29.2 | CL19: 146.5 | CM19: 148.9 | CN19: 149.8 | CO19: 0 | CT19: 217.9 | CU19: 104.4 | CV19: 0 | CW19: 16 | CX19: 0 | CY19: 9.5 | CZ19: 0 | DA19: 7.6 | DB19: 5.1 | DC19: 0 | DD19: 0 | DE19: 0.3 | DF19: 1.5 | DG19: 2 | DH19: 18.5 | DI19: 7.2 | DJ19: 4 | DK19: 3.4 | DL19: 18.5 | DM19: 0 | DN19: 0 | DO19: 4.7 | DP19: 11.7 | DQ19: 4.5 | DR19: 1.2 | DS19: 2.4 | DT19: 2.6 | DU19: 0 | DV19: 2.2 | DW19: 7.9 | DX19: 1.4 | DY19: 0.4 | DZ19: 4 | EA19: 4 | EB19: 3.5 | EC19: 4.8 | ED19: 13.8 | EE19: 21.8 | EF19: 6.1 | EG19: 0 | EH19: 24.6 | EI19: 43.7 | EJ19: 2.7 | EK19: 2.4 | EL19: 5 | EM19: 2 | EN19: 7.6 | EO19: 3.6 | EP19: 4.1 | EQ19: 4.1 | ER19: 5.3 | ES19: 0 | ET19: 0 | EU19: 0 | EV19: 0.6 | EW19: 18.1 | EX19: 9.8 | EY19: 0 | EZ19: 0 | FA19: 6.7 | FB19: 18.5 | FC19: 8.9 | FD19: 36.7 | FE19: 22.2 | FF19: 13.7 | FG19: 19.1 | FH19: 8.4 | FK19: 6344.9 | FM19: 21.00848 | FN19: 0 | FO19: 6.072 | FP19: 7.5 | FQ19: 27.1004 | FR19: 18.55023 | FS19: 3.6 | FT19: 6.9 | FU19: 90.73111
A20: 26/07/2025 | B20: 05:00 | C20: 58.1 | D20: 644.7 | E20: 217 | H20: 11.2 | I20: 81 | J20: 26.8 | L20: 0 | M20: 206.4 | N20: 209.6 | O20: 199.2 | P20: 217.2 | Q20: 111.3 | R20: 449.8 | S20: 4.3 | X20: 107 | Y20: 7.1 | Z20: 5.1 | AA20: 0 | AB20: 6.8 | AC20: 10.4 | AD20: 70.8 | AI20: 60.5 | AJ20: 0 | AN20: 6.5 | AO20: 0 | AP20: 32.5 | AQ20: 45.1 | AR20: 23.1 | AS20: 18.6 | AT20: 12.6 | AU20: 57 | AV20: 182.8 | AW20: 183.8 | AX20: 184.5 | AY20: 81.5 | AZ20: 4.5 | BA20: 0 | BB20: 33.8 | BC20: 30 | BD20: 2 | BE20: 0 | BF20: 50.9 | BI20: 22.4 | BL20: 46.7 | BP20: 66.1 | BQ20: 177.5 | BR20: 174.9 | BS20: 200 | BT20: 273.6 | CC20: 1.1 | CD20: 55.4 | CE20: 98.6 | CF20: 65.2 | CG20: 72 | CH20: 29.3 | CL20: 146.7 | CM20: 149.2 | CN20: 150.2 | CO20: 0 | CT20: 217.8 | CU20: 104.4 | CV20: 0 | CW20: 11.9 | CX20: 0 | CY20: 9.8 | CZ20: 0 | DA20: 7.6 | DB20: 5.1 | DC20: 9.9 | DD20: 0 | DE20: 0.3 | DF20: 1.5 | DG20: 2 | DH20: 18.4 | DI20: 7.4 | DJ20: 4 | DK20: 3.4 | DL20: 18.5 | DM20: 0 | DN20: 0 | DO20: 4.4 | DP20: 9.8 | DQ20: 4.5 | DR20: 1.2 | DS20: 2.4 | DT20: 2.6 | DU20: 0 | DV20: 1.5 | DW20: 7.3 | DX20: 1.3 | DY20: 0.4 | DZ20: 4 | EA20: 3.9 | EB20: 3.5 | EC20: 4.8 | ED20: 14 | EE20: 22.4 | EF20: 2.6 | EG20: 0 | EH20: 22.9 | EI20: 43.7 | EJ20: 1.9 | EK20: 1.8 | EL20: 5 | EM20: 2 | EN20: 7.7 | EO20: 3.6 | EP20: 4.1 | EQ20: 4.1 | ER20: 7.1 | ES20: 0 | ET20: 0 | EU20: 0 | EV20: 0.6 | EW20: 24.5 | EX20: 29.7 | EY20: 0 | EZ20: 0 | FA20: 6.8 | FB20: 18.5 | FC20: 10.3 | FD20: 36.4 | FE20: 22.8 | FF20: 14.2 | FG20: 19.1 | FH20: 8 | FK20: 6189.8 | FM20: 20.75343 | FN20: 0 | FO20: 6.072 | FP20: 7.5 | FQ20: 27.1496 | FR20: 18.55013 | FS20: 3.5 | FT20: 7 | FU20: 90.52516
A21: 26/07/2025 | B21: 05:30 | C21: 64.9 | D21: 645.6 | E21: 217.2 | H21: 11.5 | I21: 84 | J21: 27 | L21: 0 | M21: 200.6 | N21: 210.8 | O21: 196.1 | P21: 215 | Q21: 111.2 | R21: 450.3 | S21: 4.4 | X21: 108.6 | Y21: 7.4 | Z21: 4.8 | AA21: 0 | AB21: 7 | AC21: 10.4 | AD21: 71 | AI21: 61.5 | AJ21: 5.8 | AN21: 6.4 | AO21: 0 | AP21: 34 | AQ21: 45.9 | AR21: 22.7 | AS21: 18.6 | AT21: 12.6 | AU21: 57.8 | AV21: 184.7 | AW21: 185.1 | AX21: 183.7 | AY21: 82.7 | AZ21: 4.5 | BA21: 0 | BB21: 34.6 | BC21: 30.5 | BD21: 2 | BE21: 0 | BF21: 52.4 | BI21: 22.8 | BL21: 47 | BP21: 66.8 | BQ21: 177 | BR21: 174.6 | BS21: 200 | BT21: 273.1 | CC21: 1.1 | CD21: 57.4 | CE21: 101.6 | CF21: 62.8 | CG21: 72 | CH21: 30.3 | CL21: 146.3 | CM21: 148.8 | CN21: 149.7 | CO21: 0 | CT21: 218 | CU21: 104.4 | CV21: 0 | CW21: 13.7 | CX21: 0 | CY21: 10 | CZ21: 0 | DA21: 7.5 | DB21: 5.3 | DC21: 9.9 | DD21: 0.5 | DE21: 0.3 | DF21: 1.5 | DG21: 2 | DH21: 18.6 | DI21: 7.7 | DJ21: 4 | DK21: 3.4 | DL21: 18.5 | DM21: 0 | DN21: 0 | DO21: 3.5 | DP21: 8.1 | DQ21: 4.5 | DR21: 1.2 | DS21: 2.4 | DT21: 2.6 | DU21: 0 | DV21: 1.4 | DW21: 7.3 | DX21: 1.4 | DY21: 0.4 | DZ21: 4 | EA21: 2.3 | EB21: 3.5 | EC21: 4.9 | ED21: 14 | EE21: 20.2 | EF21: 5.1 | EG21: 0 | EH21: 25.4 | EI21: 42.9 | EJ21: 2.1 | EK21: 2.8 | EL21: 5 | EM21: 2 | EN21: 7.7 | EO21: 3.6 | EP21: 4.1 | EQ21: 4.1 | ER21: 5.2 | ES21: 0 | ET21: 0 | EU21: 0 | EV21: 0.6 | EW21: 78 | EX21: 109.4 | EY21: 0 | EZ21: 0 | FA21: 6.7 | FB21: 18.5 | FC21: 9.9 | FD21: 36.3 | FE21: 22.3 | FF21: 13.8 | FG21: 19.1 | FH21: 7.8 | FK21: 6344 | FM21: 20.95507 | FN21: 0 | FO21: 6.076 | FP21: 7.5 | FQ21: 27.18495 | FR21: 18.55006 | FS21: 3.6 | FT21: 6.9 | FU21: 90.76608
A22: 26/07/2025 | B22: 06:00 | C22: 52.7 | D22: 643.4 | E22: 216.4 | H22: 11 | I22: 84.9 | J22: 27.2 | L22: 0 | M22: 205.9 | N22: 207.3 | O22: 195 | P22: 217.3 | Q22: 111.3 | R22: 436.6 | S22: 4.2 | X22: 109.1 | Y22: 7.3 | Z22: 4.7 | AA22: 0 | AB22: 6.9 | AC22: 10.5 | AD22: 49.6 | AI22: 40.1 | AJ22: 52.5 | AN22: 6.4 | AO22: 0 | AP22: 33.1 | AQ22: 39.5 | AR22: 21.7 | AS22: 18.6 | AT22: 12.6 | AU22: 56.5 | AV22: 181.6 | AW22: 182 | AX22: 183.7 | AY22: 81.6 | AZ22: 4.8 | BA22: 0 | BB22: 31.2 | BC22: 29.7 | BD22: 2 | BE22: 0 | BF22: 48.9 | BI22: 22.2 | BL22: 46.9 | BP22: 65.9 | BQ22: 177.6 | BR22: 175.1 | BS22: 200 | BT22: 273.6 | CC22: 1 | CD22: 51.5 | CE22: 100.3 | CF22: 61.9 | CG22: 75.4 | CH22: 29.5 | CL22: 146.5 | CM22: 149 | CN22: 149.9 | CO22: 0 | CT22: 217.8 | CU22: 104.4 | CV22: 0 | CW22: 17.4 | CX22: 0 | CY22: 9.4 | CZ22: 0 | DA22: 7.6 | DB22: 5.1 | DC22: 9.9 | DD22: 1.6 | DE22: 0.3 | DF22: 1.5 | DG22: 2 | DH22: 18.3 | DI22: 8.1 | DJ22: 4 | DK22: 3.4 | DL22: 18.5 | DM22: 0.1 | DN22: 0 | DO22: 6.9 | DP22: 14.4 | DQ22: 4.5 | DR22: 1.2 | DS22: 2.4 | DT22: 2.6 | DU22: 0 | DV22: 1.4 | DW22: 7.3 | DX22: 1.4 | DY22: 0.4 | DZ22: 4 | EA22: 0.4 | EB22: 3.4 | EC22: 4.8 | ED22: 14 | EE22: 21 | EF22: 7 | EG22: 0 | EH22: 25.5 | EI22: 39.8 | EJ22: 2.6 | EK22: 2.3 | EL22: 5 | EM22: 2 | EN22: 7.7 | EO22: 3.6 | EP22: 4.1 | EQ22: 4.1 | ER22: 4.8 | ES22: 0 | ET22: 0 | EU22: 0 | EV22: 0.6 | EW22: 104.7 | EX22: 125.1 | EY22: 0 | EZ22: 0 | FA22: 6.6 | FB22: 18.5 | FC22: 9.6 | FD22: 36.7 | FE22: 22.5 | FF22: 13.6 | FG22: 19.1 | FH22: 8.7 | FK22: 6347.8 | FM22: 20.8285 | FN22: 0 | FO22: 6.072 | FP22: 7.5 | FQ22: 27.24554 | FR22: 18.54963 | FS22: 3.6 | FT22: 6.9 | FU22: 90.69567
... A58: 27/07/2025 | B58: 00:00 | C58: 125.1 | D58: 603.9 | E58: 205.6 | H58: 25.3 | I58: 80.5 | J58: 50.2 | L58: 104.9 | M58: 105 | N58: 104.9 | O58: 205.2 | P58: 214.4 | Q58: 110.9 | R58: 338.7 | S58: 4.1 | X58: 108.8 | Y58: 7.9 | Z58: 5.1 | AA58: 0 | AB58: 7 | AC58: 12.6 | AD58: 140.7 | AI58: 57.2 | AJ58: 105.2 | AN58: 6.4 | AO58: 0 | AP58: 29.3 | AQ58: 73.8 | AR58: 19.8 | AS58: 18.6 | AT58: 12.4 | AU58: 56.6663 | AV58: 125.2 | AW58: 125.7 | AX58: 157.4 | AY58: 83.1 | AZ58: 6 | BA58: 1.9 | BB58: 31.5 | BC58: 31.4 | BD58: 2 | BE58: 0 | BF58: 53.3 | BI58: 52.5 | BL58: 47.3 | BP58: 65.7 | BQ58: 149.7 | BR58: 174.6 | BS58: 200 | BT58: 261.9 | CC58: 1 | CD58: 193.7 | CE58: 96.1 | CF58: 65.5 | CG58: 71.4 | CH58: 30.3 | CL58: 111.5 | CM58: 111.2 | CN58: 126.8 | CO58: 0 | CT58: 137.1 | CU58: 77.5 | CV58: 0 | CW58: 118.2 | CX58: 0 | CY58: 14.3 | CZ58: 0 | DA58: 7.3 | DB58: 5.3 | DC58: 10 | DD58: 2.2 | DE58: 0.3 | DF58: 1.5 | DG58: 2 | DH58: 18.6 | DI58: 6.3 | DJ58: 3.9 | DK58: 3.4 | DL58: 18.5 | DM58: 0 | DN58: 0 | DO58: 31.8 | DP58: 86.1 | DQ58: 4.5 | DR58: 1.1 | DS58: 2.4 | DT58: 2.6 | DU58: 0 | DV58: 2.1 | DW58: 13.7 | DX58: 1.4 | DY58: 0.4 | DZ58: 4.5 | EA58: 0 | EB58: 3.5 | EC58: 5.1 | ED58: 14 | EE58: 20.2 | EF58: 26.9 | EG58: 0 | EH58: 101.6 | EI58: 104.7 | EJ58: 16.4 | EK58: 9.6 | EL58: 5 | EM58: 2.2 | EN58: 7.4 | EO58: 3.8 | EP58: 4.2 | EQ58: 4.4 | ER58: 11.3 | ES58: 0 | ET58: 0 | EU58: 0 | EV58: 0.6 | EW58: 105.1 | EX58: 90.8 | EY58: 0 | EZ58: 0 | FA58: 6.6 | FB58: 18.3 | FC58: 9.1 | FD58: 36.7 | FE58: 27.9 | FF58: 13.7 | FG58: 18.9 | FH58: 8.6 | FK58: 6570.4663 | FM58: 19.53428 | FN58: 0 | FO58: 6.148 | FP58: 7.5 | FQ58: 27.24754 | FR58: 18.55647 | FS58: 4 | FT58: 16 | FU58: 98.98629
A59: EJEC | C59: 1777.3 | D59: 14697.5 | E59: 4972.2 | F59: 0 | G59: 0 | H59: 582.65 | I59: 1977.45 | J59: 1287.75 | K59: 0 | L59: 555.05 | M59: 4243.8 | N59: 4290.5 | O59: 4573.1 | P59: 5140.45 | Q59: 2660.6 | R59: 7540.25 | S59: 100.1 | T59: 0 | U59: 0 | V59: 0 | W59: 0 | X59: 2598.45 | Y59: 180.45 | Z59: 120.1 | AA59: 235 | AB59: 167.3 | AC59: 283.8 | AD59: 1800.3 | AE59: 0 | AF59: 0 | AG59: 0 | AH59: 0 | AI59: 1472.55 | AJ59: 2146.8 | AK59: 0 | AL59: 0 | AM59: 0 | AN59: 155.5 | AO59: 1009.2 | AP59: 724.7 | AQ59: 967.15 | AR59: 467.05 | AS59: 446.15 | AT59: 300.45 | AU59: 1359.6328 | AV59: 4341.15 | AW59: 4350.4 | AX59: 4396.4 | AY59: 1732.4 | AZ59: 114.7 | BA59: 16.9 | BB59: 707.1 | BC59: 747.25 | BD59: 47.65 | BE59: 219.55 | BF59: 1536.4 | BG59: 0 | BH59: 0 | BI59: 1179.7 | BJ59: 0 | BK59: 0 | BL59: 1118.25 | BM59: 0 | BN59: 0 | BO59: 0 | BP59: 1419.5 | BQ59: 4229.8 | BR59: 4181 | BS59: 4800 | BT59: 6528.8 | BU59: 0 | BV59: 0 | BW59: 0 | BX59: 0 | BY59: 0 | BZ59: 0 | CA59: 0 | CB59: 0 | CC59: 26.2 | CD59: 2600.45 | CE59: 2251.15 | CF59: 1530.8 | CG59: 1737.4 | CH59: 698.7 | CI59: 0 | CJ59: 0 | CK59: 0 | CL59: 3470.75 | CM59: 3523.6 | CN59: 3700.65 | CO59: 2032 | CP59: 0 | CQ59: 0 | CR59: 0 | CS59: 0 | CT59: 5052.2 | CU59: 2442.1 | CV59: 8.3 | CW59: 1712.85 | CX59: 598.85 | CY59: 267.85 | CZ59: 2.85 | DA59: 177.25 | DB59: 122.9 | DC59: 203.15 | DD59: 48.8 | DE59: 6.7 | DF59: 36 | DG59: 46 | DH59: 441.8 | DI59: 172.15 | DJ59: 101 | DK59: 80.55 | DL59: 444 | DM59: 121.25 | DN59: 147.1 | DO59: 432.3 | DP59: 1243.5 | DQ59: 108 | DR59: 27.25 | DS59: 57.6 | DT59: 61.85 | DU59: 137.85 | DV59: 49.35 | DW59: 311.4 | DX59: 32.4 | DY59: 9.5 | DZ59: 108.3 | EA59: 21.2 | EB59: 82.6 | EC59: 117.4 | ED59: 329.7 | EE59: 476.55 | EF59: 788.4 | EG59: 267.65 | EH59: 1638.4 | EI59: 1875.9 | EJ59: 258.55 | EK59: 177.6 | EL59: 120.65 | EM59: 51.25 | EN59: 186.2 | EO59: 87.3 | EP59: 98.9 | EQ59: 100.6 | ER59: 215.2 | ES59: 1998.4 | ET59: 117.5 | EU59: 1119.6 | EV59: 14.4 | EW59: 1596.2 | EX59: 1784.85 | EY59: 812.65 | EZ59: 117.8 | FA59: 160.6 | FB59: 444.5 | FC59: 222.15 | FD59: 868.75 | FE59: 549.1 | FF59: 334.05 | FG59: 433.8 | FH59: 191.55 | FI59: 0 | FJ59: 0 | FK59: 164544.83 | FM59: 478.48568 | FN59: 39.994 | FO59: 141.626 | FP59: 179.85 | FQ59: 644.35898 | FR59: 445.4479 | FS59: 78.75 | FT59: 224.6 | FU59: 2233.1126

Sheet REACTIVA
B3: sábado, 26 de Julio del 2025
A5: POTENCIA REACTIVA EJECUTADA DE LAS UNIDADES DE GENERACIÓN DEL COES (MVAR) | FM5: CENTRALES NO INTEGRANTES COES
A6: FECHA | B6: HORA | C6: 65333 | D6: 101 | E6: 102 | F6: 42667 | G6: 42668 | H6: 126 | I6: 127 | J6: 138 | K6: 139 | L6: 197 | M6: 203 | N6: 204 | O6: 230 | P6: 209 | Q6: 56677 | R6: 796 | S6: 2146 | T6: 142 | U6: 143 | V6: 125 | W6: 187 | X6: 163 | Y6: 298 | Z6: 299 | AA6: 219 | AB6: 151 | AC6: 152 | AD6: 153 | AE6: 154 | AF6: 756 | AG6: 156 | AH6: 155 | AI6: 182 | AJ6: 212 | AK6: 758 | AL6: 263 | AM6: 265 | AN6: 775 | AO6: 777 | AP6: 2154 | AQ6: 150 | AR6: 149 | AS6: 188 | AT6: 2131 | AU6: 755 | AV6: 252 | AW6: 249 | AX6: 250 | AY6: 117 | AZ6: 267 | BA6: 268 | BB6: 119 | BC6: 120 | BD6: 189 | BE6: 122 | BF6: 266 | BG6: 337 | BH6: 338 | BI6: 251 | BJ6: 115 | BK6: 239 | BL6: 288 | BM6: 240 | BN6: 241 | BO6: 242 | BP6: 191 | BQ6: 194 | BR6: 196 | BS6: 207 | BT6: 236 | BU6: 795 | BV6: 285 | BW6: 995 | BX6: 996 | BY6: 997 | BZ6: 766 | CA6: 926 | CB6: 924 | CC6: 121 | CD6: 103 | CE6: 104 | CF6: 106 | CG6: 105 | CH6: 107 | CI6: 110 | CJ6: 109 | CK6: 144 | CL6: 113 | CM6: 114 | CN6: 193 | CO6: 208 | CP6: 786 | CQ6: 787 | CR6: 788 | CS6: 789 | CT6: 248 | CU6: 2159 | CV6: 303 | CW6: 59715 | CX6: 62255 | CY6: 1263 | CZ6: 61800 | DA6: 2194 | DB6: 69125 | DC6: 216 | DD6: 198 | DE6: 49607 | DF6: 214 | DG6: 260 | DH6: 2152 | DI6: 2128 | DJ6: 247 | DK6: 228 | DL6: 2135 | DM6: 261 | DN6: 237 | DO6: 253 | DP6: 770 | DQ6: 225 | DR6: 2201 | DS6: 2171 | DT6: 760 | DU6: 235 | DV6: 238 | DW6: 2184 | DX6: 61855 | DY6: 223 | DZ6: 226 | EA6: 201 | EB6: 258 | EC6: 259 | ED6: 920 | EE6: 257 | EF6: 256 | EG6: 2148 | EH6: 58288 | EI6: 58289 | EJ6: 58839 | EK6: 58840 | EL6: 296 | EM6: 297 | EN6: 211 | EO6: 2175 | EP6: 2178 | EQ6: 2181 | ER6: 1262 | ES6: 63425 | ET6: 233 | EU6: 2150 | EV6: 2165 | EW6: 2161 | EX6: 61197 | EY6: 58851 | EZ6: 234 | FA6: 215 | FB6: 917 | FC6: 289 | FD6: 58333 | FE6: 58336 | FF6: 213 | FG6: 232 | FH6: 2190 | FI6: 202 | FJ6: 58487 | FK6: TOTAL COES | FM6: 221 | FN6: 222 | FO6: 224 | FP6: 2187 | FQ6: 227 | FR6: 49400 | FS6: 199 | FT6: 200 | FU6: TOTAL NO COES
C7: SUR | D7: CENTRO | E7: CENTRO | F7: NORTE | G7: NORTE | H7: NORTE | I7: NORTE | J7: CENTRO | K7: CENTRO | L7: CENTRO | M7: CENTRO | N7: CENTRO | O7: CENTRO | P7: CENTRO | Q7: CENTRO | R7: CENTRO | S7: CENTRO | T7: CENTRO | U7: CENTRO | V7: CENTRO | W7: CENTRO | X7: SUR | Y7: SUR | Z7: SUR | AA7: CENTRO | AB7: SUR | AC7: SUR | AD7: SUR | AE7: SUR | AF7: SUR | AG7: SUR | AH7: SUR | AI7: SUR | AJ7: CENTRO | AK7: NORTE | AL7: NORTE | AM7: NORTE | AN7: CENTRO | AO7: CENTRO | AP7: CENTRO | AQ7: CENTRO | AR7: CENTRO | AS7: CENTRO | AT7: CENTRO | AU7: SUR | AV7: CENTRO | AW7: CENTRO | AX7: CENTRO | AY7: CENTRO | AZ7: CENTRO | BA7: CENTRO | BB7: CENTRO | BC7: CENTRO | BD7: SUR | BE7: NORTE | BF7: CENTRO | BG7: CENTRO | BH7: CENTRO | BI7: CENTRO | BJ7: NORTE | BK7: NORTE | BL7: NORTE | BM7: SUR | BN7: SUR | BO7: SUR | BP7: CENTRO | BQ7: CENTRO | BR7: CENTRO | BS7: CENTRO | BT7: CENTRO | BU7: CENTRO | BV7: CENTRO | BW7: SUR | BX7: SUR | BY7: SUR | BZ7: NORTE | CA7: SUR | CB7: CENTRO | CC7: NORTE | CD7: CENTRO | CE7: CENTRO | CF7: CENTRO | CG7: CENTRO | CH7: CENTRO | CI7: CENTRO | CJ7: CENTRO | CK7: CENTRO | CL7: CENTRO | CM7: CENTRO | CN7: CENTRO | CO7: CENTRO | CP7: SUR | CQ7: SUR | CR7: SUR | CS7: SUR | CT7: CENTRO | CU7: CENTRO | CV7: CENTRO | CW7: CENTRO | CX7: SUR | CY7: NORTE | CZ7: NORTE | DA7: NORTE | DB7: CENTRO | DC7: NORTE | DD7: NORTE | DE7: SUR | DF7: CENTRO | DG7: CENTRO | DH7: CENTRO | DI7: NORTE | DJ7: NORTE | DK7: CENTRO | DL7: CENTRO | DM7: SUR | DN7: SUR | DO7: CENTRO | DP7: CENTRO | DQ7: CENTRO | DR7: CENTRO | DS7: CENTRO | DT7: CENTRO | DU7: SUR | DV7: CENTRO | DW7: CENTRO | DX7: NORTE | DY7: CENTRO | DZ7: CENTRO | EA7: NORTE | EB7: CENTRO | EC7: CENTRO | ED7: CENTRO | EE7: NORTE | EF7: NORTE | EG7: SUR | EH7: CENTRO | EI7: CENTRO | EJ7: CENTRO | EK7: CENTRO | EL7: CENTRO | EM7: CENTRO | EN7: SUR | EO7: SUR | EP7: SUR | EQ7: SUR | ER7: NORTE | ES7: SUR | ET7: SUR | EU7: SUR | EV7: CENTRO | EW7: CENTRO | EX7: CENTRO | EY7: SUR | EZ7: SUR | FA7: NORTE | FB7: CENTRO | FC7: NORTE | FD7: NORTE | FE7: NORTE | FF7: CENTRO | FG7: NORTE | FH7: NORTE | FI7: CENTRO | FJ7: CENTRO | FM7: NORTE | FN7: CENTRO | FO7: NORTE | FP7: NORTE | FQ7: NORTE | FR7: NORTE | FS7: NORTE | FT7: NORTE
C8: HIDROELÉCTRICA | D8: HIDROELÉCTRICA | E8: HIDROELÉCTRICA | F8: TERMOELÉCTRICA | G8: TERMOELÉCTRICA | H8: HIDROELÉCTRICA | I8: HIDROELÉCTRICA | J8: TERMOELÉCTRICA | K8: TERMOELÉCTRICA | L8: TERMOELÉCTRICA | M8: TERMOELÉCTRICA | N8: TERMOELÉCTRICA | O8: TERMOELÉCTRICA | P8: TERMOELÉCTRICA | Q8: TERMOELÉCTRICA | R8: HIDROELÉCTRICA | S8: HIDROELÉCTRICA | T8: TERMOELÉCTRICA | U8: TERMOELÉCTRICA | V8: TERMOELÉCTRICA | W8: TERMOELÉCTRICA | X8: HIDROELÉCTRICA | Y8: HIDROELÉCTRICA | Z8: HIDROELÉCTRICA | AA8: TERMOELÉCTRICA | AB8: HIDROELÉCTRICA | AC8: HIDROELÉCTRICA | AD8: HIDROELÉCTRICA | AE8: HIDROELÉCTRICA | AF8: TERMOELÉCTRICA | AG8: TERMOELÉCTRICA | AH8: TERMOELÉCTRICA | AI8: HIDROELÉCTRICA | AJ8: HIDROELÉCTRICA | AK8: TERMOELÉCTRICA | AL8: TERMOELÉCTRICA | AM8: TERMOELÉCTRICA | AN8: HIDROELÉCTRICA | AO8: HIDROELÉCTRICA | AP8: HIDROELÉCTRICA | AQ8: HIDROELÉCTRICA | AR8: HIDROELÉCTRICA | AS8: HIDROELÉCTRICA | AT8: HIDROELÉCTRICA | AU8: HIDROELÉCTRICA | AV8: TERMOELÉCTRICA | AW8: TERMOELÉCTRICA | AX8: TERMOELÉCTRICA | AY8: HIDROELÉCTRICA | AZ8: HIDROELÉCTRICA | BA8: HIDROELÉCTRICA | BB8: HIDROELÉCTRICA | BC8: HIDROELÉCTRICA | BD8: HIDROELÉCTRICA | BE8: HIDROELÉCTRICA | BF8: HIDROELÉCTRICA | BG8: HIDROELÉCTRICA | BH8: HIDROELÉCTRICA | BI8: HIDROELÉCTRICA | BJ8: TERMOELÉCTRICA | BK8: TERMOELÉCTRICA | BL8: TERMOELÉCTRICA | BM8: TERMOELÉCTRICA | BN8: TERMOELÉCTRICA | BO8: TERMOELÉCTRICA | BP8: HIDROELÉCTRICA | BQ8: TERMOELÉCTRICA | BR8: TERMOELÉCTRICA | BS8: TERMOELÉCTRICA | BT8: TERMOELÉCTRICA | BU8: TERMOELÉCTRICA | BV8: TERMOELÉCTRICA | BW8: TERMOELÉCTRICA | BX8: TERMOELÉCTRICA | BY8: TERMOELÉCTRICA | BZ8: HIDROELÉCTRICA | CA8: TERMOELÉCTRICA | CB8: TERMOELÉCTRICA | CC8: HIDROELÉCTRICA | CD8: HIDROELÉCTRICA | CE8: HIDROELÉCTRICA | CF8: HIDROELÉCTRICA | CG8: HIDROELÉCTRICA | CH8: HIDROELÉCTRICA | CI8: TERMOELÉCTRICA | CJ8: TERMOELÉCTRICA | CK8: TERMOELÉCTRICA | CL8: TERMOELÉCTRICA | CM8: TERMOELÉCTRICA | CN8: TERMOELÉCTRICA | CO8: TERMOELÉCTRICA | CP8: TERMOELÉCTRICA | CQ8: TERMOELÉCTRICA | CR8: TERMOELÉCTRICA | CS8: TERMOELÉCTRICA | CT8: TERMOELÉCTRICA | CU8: TERMOELÉCTRICA | CV8: SOLAR | CW8: EÓLICA | CX8: SOLAR | CY8: EÓLICA | CZ8: SOLAR | DA8: HIDROELÉCTRICA | DB8: HIDROELÉCTRICA | DC8: HIDROELÉCTRICA | DD8: HIDROELÉCTRICA | DE8: HIDROELÉCTRICA | DF8: HIDROELÉCTRICA | DG8: HIDROELÉCTRICA | DH8: HIDROELÉCTRICA | DI8: HIDROELÉCTRICA | DJ8: HIDROELÉCTRICA | DK8: HIDROELÉCTRICA | DL8: HIDROELÉCTRICA | DM8: SOLAR | DN8: SOLAR | DO8: EÓLICA | DP8: EÓLICA | DQ8: TERMOELÉCTRICA | DR8: TERMOELÉCTRICA | DS8: TERMOELÉCTRICA | DT8: TERMOELÉCTRICA | DU8: SOLAR | DV8: HIDROELÉCTRICA | DW8: HIDROELÉCTRICA | DX8: HIDROELÉCTRICA | DY8: HIDROELÉCTRICA | DZ8: HIDROELÉCTRICA | EA8: HIDROELÉCTRICA | EB8: HIDROELÉCTRICA | EC8: HIDROELÉCTRICA | ED8: HIDROELÉCTRICA | EE8: EÓLICA | EF8: EÓLICA | EG8: SOLAR | EH8: EÓLICA | EI8: EÓLICA | EJ8: EÓLICA | EK8: EÓLICA | EL8: HIDROELÉCTRICA | EM8: HIDROELÉCTRICA | EN8: HIDROELÉCTRICA | EO8: HIDROELÉCTRICA | EP8: HIDROELÉCTRICA | EQ8: HIDROELÉCTRICA | ER8: EÓLICA | ES8: SOLAR | ET8: SOLAR | EU8: SOLAR | EV8: HIDROELÉCTRICA | EW8: EÓLICA | EX8: EÓLICA | EY8: SOLAR | EZ8: SOLAR | FA8: HIDROELÉCTRICA | FB8: HIDROELÉCTRICA | FC8: TERMOELÉCTRICA | FD8: TERMOELÉCTRICA | FE8: TERMOELÉCTRICA | FF8: TERMOELÉCTRICA | FG8: TERMOELÉCTRICA | FH8: TERMOELÉCTRICA | FI8: TERMOELÉCTRICA | FJ8: TERMOELÉCTRICA | FM8: HIDROELÉCTRICA | FN8: HIDROELÉCTRICA | FO8: HIDROELÉCTRICA | FP8: HIDROELÉCTRICA | FQ8: TERMOELÉCTRICA | FR8: TERMOELÉCTRICA | FS8: HIDROELÉCTRICA | FT8: HIDROELÉCTRICA
C9: HYDRO GLOBAL PERÚ S.A.C. | D9: ELECTROPERU | E9: ELECTROPERU | F9: ELECTROPERU | G9: ELECTROPERU | H9: ORAZUL ENERGY PERÚ | I9: ORAZUL ENERGY PERÚ | J9: TERMOSELVA | K9: TERMOSELVA | L9: KALLPA GENERACION S.A. | M9: KALLPA GENERACION S.A. | N9: KALLPA GENERACION S.A. | O9: KALLPA GENERACION S.A. | P9: KALLPA GENERACION S.A. | Q9: KALLPA GENERACION S.A. | R9: KALLPA GENERACION S.A. | S9: KALLPA GENERACION S.A. | T9: SHOUGESA | U9: SHOUGESA | V9: SHOUGESA | W9: SHOUGESA | X9: EGEMSA | Y9: EGESUR | Z9: EGESUR | AA9: EGESUR | AB9: EGASA | AC9: EGASA | AD9: EGASA | AE9: EGASA | AF9: EGASA | AG9: EGASA | AH9: EGASA | AI9: SAN GABAN | AJ9: CELEPSA | AK9: MINERA CERRO VERDE | AL9: PLANTA DE RESERVA FRIA DE GENERACION DE ETEN S.A. | AM9: PLANTA DE RESERVA FRIA DE GENERACION DE ETEN S.A. | AN9: EMPRESA DE GENERACION HUALLAGA | AO9: EMPRESA DE GENERACION HUALLAGA | AP9: LA VIRGEN | AQ9: CHINANGO S.A.C. | AR9: CHINANGO S.A.C. | AS9: HIDROELECTRICA HUANCHOR S.A.C. | AT9: CELEPSA RENOVABLES S.R.L. | AU9: INLAND ENERGY SAC | AV9: FENIX POWER PERÚ | AW9: FENIX POWER PERÚ | AX9: FENIX POWER PERÚ | AY9: STATKRAFT S.A | AZ9: STATKRAFT S.A | BA9: STATKRAFT S.A | BB9: STATKRAFT S.A | BC9: STATKRAFT S.A | BD9: STATKRAFT S.A | BE9: STATKRAFT S.A | BF9: STATKRAFT S.A | BG9: CENTRALES SANTA ROSA S.A.C. | BH9: CENTRALES SANTA ROSA S.A.C. | BI9: EMPRESA DE GENERACION HUANZA | BJ9: ENEL GENERACION PIURA S.A. | BK9: ENEL GENERACION PIURA S.A. | BL9: ENEL GENERACION PIURA S.A. | BM9: ENGIE | BN9: ENGIE | BO9: ENGIE | BP9: ENGIE | BQ9: ENGIE | BR9: ENGIE | BS9: ENGIE | BT9: ENGIE | BU9: ENGIE | BV9: ENGIE | BW9: ENGIE | BX9: ENGIE | BY9: ENGIE | BZ9: ENGIE | CA9: INFRAESTRUCTURAS Y ENERGIAS DEL PERU S.A.C. | CB9: INFRAESTRUCTURAS Y ENERGIAS DEL PERU S.A.C. | CC9: INVERSIONES SHAQSHA S.A.C. | CD9: ORYGEN PERU S.A.A. | CE9: ORYGEN PERU S.A.A. | CF9: ORYGEN PERU S.A.A. | CG9: ORYGEN PERU S.A.A. | CH9: ORYGEN PERU S.A.A. | CI9: ORYGEN PERU S.A.A. | CJ9: ORYGEN PERU S.A.A. | CK9: ORYGEN PERU S.A.A. | CL9: ORYGEN PERU S.A.A. | CM9: ORYGEN PERU S.A.A. | CN9: ORYGEN PERU S.A.A. | CO9: ORYGEN PERU S.A.A. | CP9: SAMAY I S.A.C | CQ9: SAMAY I S.A.C | CR9: SAMAY I S.A.C | CS9: SAMAY I S.A.C | CT9: TERMOCHILCA S.A.C. | CU9: TERMOCHILCA S.A.C. | CV9: COLCA SOLAR S.A.C. | CW9: ENERGIA RENOVABLE DEL SUR S.A. | CX9: GR CORTARRAMA SOCIEDAD ANONIMA CERRADA | CY9: GR TARUCA SOCIEDAD ANONIMA CERRADA | CZ9: KONDU SAC | DA9: PERUANA DE INVERSIONES EN ENERGIAS RENOVABLES S.A. | DB9: VARI ENERGIA S.A.C. | DC9: ORAZUL ENERGY PERÚ | DD9: ORAZUL ENERGY PERÚ | DE9: SAN GABAN | DF9: MAJA ENERGIA S.A.C. | DG9: EMPRESA DE GENERACION ELECTRICA CANCHAYLLO SAC | DH9: EMPRESA DE GENERACION ELECTRICA SANTA ANA S.A.C. | DI9: EMPRESA ELECTRICA AGUA AZUL | DJ9: EMPRESA ELECTRICA RIO DOBLE | DK9: HIDROCAÑETE S.A. | DL9: HUAURA POWER GROUP S.A. | DM9: MOQUEGUA FV S.A.C. | DN9: PANAMERICANA SOLAR SAC. | DO9: PARQUE EOLICO MARCONA S.A.C. | DP9: PARQUE EOLICO TRES HERMANAS S.A.C. | DQ9: PETRAMAS | DR9: PETRAMAS | DS9: PETRAMAS | DT9: PETRAMAS | DU9: TACNA SOLAR SAC. | DV9: ELECTRICA YANAPAMPA SAC | DW9: ANDEAN POWER S.A.C. | DX9: ASOCIACIÓN SANTA LUCIA DE CHACAS | DY9: ATRIA ENERGIA S.A.C. | DZ9: EGEJUNIN | EA9: EGEJUNIN | EB9: EGEJUNIN | EC9: EGEJUNIN | ED9: EMPRESA DE GENERACION ELECTRICA RIO BAÑOS S.A.C. | EE9: ENERGÍA EÓLICA S.A. | EF9: ENERGÍA EÓLICA S.A. | EG9: ENGIE | EH9: ENGIE | EI9: ENGIE | EJ9: ENGIE | EK9: ENGIE | EL9: GENERACIÓN ANDINA S.A.C. | EM9: GENERACIÓN ANDINA S.A.C. | EN9: GENERADORA DE ENERGÍA DEL PERÚ | EO9: GENERADORA DE ENERGÍA DEL PERÚ | EP9: GENERADORA DE ENERGÍA DEL PERÚ | EQ9: GENERADORA DE ENERGÍA DEL PERÚ | ER9: GR PAINO SOCIEDAD ANONIMA CERRADA | ES9: JOYA SOLAR S.A.C. | ET9: MAJES ARCUS S.A.C. | EU9: ORYGEN PERU S.A.A. | EV9: ORYGEN PERU S.A.A. | EW9: ORYGEN PERU S.A.A. | EX9: ORYGEN PERU S.A.A. | EY9: ORYGEN PERU S.A.A. | EZ9: REPARTICIÓN ARCUS S.A.C. | FA9: SINERSA | FB9: SINERSA | FC9: BIOENERGIA DEL CHIRA S.A. | FD9: GM OPERACIONES S.A.C. | FE9: GM OPERACIONES S.A.C. | FF9: AGRO INDUSTRIAL PARAMONGA S.A. | FG9: AGROAURORA S.A.C. | FH9: AGROINDUSTRIAS SAN JACINTO S.A.A. | FI9: SDF ENERGIA SAC | FJ9: SDF ENERGIA SAC | FM9: UNACEM PERU S.A. | FN9: ELECTRO ORIENTE | FO9: AGUAS Y ENERGIA PERU | FP9: ELECTRO ZAÑA S.A.C. | FQ9: ELECTRONOROESTE S.A. | FR9: SDE PIURA | FS9: SINERSA | FT9: SINERSA
C10: SAN GABAN III | D10: MANTARO | E10: RESTITUCION | F10: TUMBES MAK 1 | G10: TUMBES MAK 2 | H10: CARHUAQUERO | I10: CAÑON DEL PATO | J10: AGUAYTIA TG1 | K10: AGUAYTIA TG2 | L10: KALLPA TG1 | M10: KALLPA TG2 | N10: KALLPA TG3 | O10: KALLPA TV | P10: LFLORES TG1 | Q10: LFLORES TV | R10: CERRO DEL AGUILA | S10: CERRODELAGUILAG4 | T10: SHOUGESA TV1 | U10: SHOUGESA TV2 | V10: SHOUGESA TV3 | W10: SHOUGESA CUMMINS | X10: MACHUPICCHU | Y10: ARICOTA 1 | Z10: ARICOTA 2 | AA10: INDEPENDENCIA | AB10: CHARCANI I,II,III | AC10: CHARCANI IV | AD10: CHARCANI V | AE10: CHARCANI VI | AF10: CHILINA TG | AG10: MOLLENDO 1, 2, 3 | AH10: CHILINA (SULZ 1,2) | AI10: SAN GABAN II | AJ10: PLATANAL | AK10: RECKA | AL10: RF ETEN TG1 | AM10: RF ETEN TG2 | AN10: CHAGLLA GP1 | AO10: CHAGLLA | AP10: LA VIRGEN | AQ10: CHIMAY | AR10: YANANGO | AS10: HUANCHOR | AT10: MARAÑON | AU10: STA TERESA | AV10: FENIX GT11 | AW10: FENIX GT12 | AX10: FENIX TV10 | AY10: YAUPI | AZ10: OROYA | BA10: PACHACHACA | BB10: MALPASO | BC10: CAHUA | BD10: ARCATA | BE10: GALLITO CIEGO | BF10: CHEVES | BG10: SANTA ROSA 1 | BH10: SANTA ROSA 2 | BI10: HUANZA | BJ10: MALACAS2 TG4 | BK10: MALACAS3 TG 5 | BL10: MALACAS1 TG6 | BM10: RF ILO2 TG1 | BN10: RF ILO2 TG2 | BO10: RF ILO2 TG3 | BP10: YUNCAN | BQ10: CHILCA1 TG1 | BR10: CHILCA1 TG2 | BS10: CHILCA1 TG3 | BT10: CHILCA-TV | BU10: CHILCA2 TG41 | BV10: CHILCA2-TV | BW10: CTNEPI_TG41 | BX10: CTNEPI_TG42 | BY10: CTNEPI_TG43 | BZ10: QUITARACSA | CA10: RF PTO MALDONADO | CB10: RF PUCALLPA | CC10: PARIAC | CD10: HUINCO | CE10: MATUCANA | CF10: MOYOPAMPA | CG10: CALLAHUANCA | CH10: HUAMPANI | CI10: STA ROSA WEST TG7 | CJ10: UTI_5 | CK10: UTI_6 | CL10: VENTANILLA 3 | CM10: VENTANILLA 4 | CN10: VENTANILLA TV | CO10: STAROSA TG8 | CP10: PTO_BRVO TG1 | CQ10: PTO_BRVO TG2 | CR10: PTO_BRVO TG3 | CS10: PTO_BRVO TG4 | CT10: OLLEROS TG1 | CU10: OLLEROS TV | CV10: CS YARUCAYA | CW10: SAN JUAN | CX10: MATARANI | CY10: DUNA | CZ10: CARHUAQUERO (CS) | DA10: MANTA I | DB10: ANASHIRONI | DC10: CARHUAQUERO4 | DD10: CAÑA BRAVA | DE10: TUPURI | DF10: RONCADOR | DG10: CANCHAYLLO | DH10: RENOVANDESH1 | DI10: POTRERO | DJ10: PIZARRAS | DK10: NIMPERIAL | DL10: YARUCAYA | DM10: MOQUEGUA-SOLAR | DN10: PANAMERICANA-SOLAR | DO10: PQE-EOLICO-MARCONA | DP10: PQE-EOLICO-3-HERMANAS | DQ10: HUAYCOLORO | DR10: CALLAO | DS10: DONA_CATALINA | DT10: LAGRINGAV | DU10: TACNA-SOLAR | DV10: YANAPAMPA | DW10: CARHUAC | DX10: HUALLIN | DY10: PURMACANA | DZ10: HUASAHUASI | EA10: STACRUZ_1_2 | EB10: RUNATULLO_II | EC10: RUNATULLO_III | ED10: RUCUY | EE10: PQE-EOLICO-TALARA | EF10: PQE-EOLICO-CUPISNIQUE | EG10: INTIPAMPA | EH10: PUNTA LOMITAS-BL1 | EI10: PUNTA LOMITAS-BL2 | EJ10: PUN LOMITAS_EXP-BL1 | EK10: PUN LOMITAS_EXP-BL2 | EL10: 8AGOSTO | EM10: EL CARMEN | EN10: LA JOYA | EO10: ANGEL_I | EP10: ANGEL_II | EQ10: ANGEL_III | ER10: HUAMBOS | ES10: SAN MARTIN SOLAR | ET10: MAJES | EU10: RUBI | EV10: CH_HER1 | EW10: WAYRA-I | EX10: WAYRA EXTENSION | EY10: CLEMESI | EZ10: REPARTICION | FA10: POECHOS2 | FB10: CHANCAY | FC10: CANA BRAVA | FD10: REFINERIA TALARA TV1 | FE10: REFINERÍA TALARA TV2 | FF10: PARAMONGA | FG10: MAPLE | FH10: SAN_JACINTO | FI10: OQUENDO TG1 | FJ10: OQUENDO TV1 | FK10: MVAR | FM10: CARPAPATA | FN10: CENTRALES ELOR | FO10: PIAS1 | FP10: ZANA | FQ10: TABLAZO | FR10: TALLANCA | FS10: CURUMUY | FT10: POECHOS1 | FU10: MVAR
A11: 26/07/2025 | B11: 00:30 | C11: -4.8 | D11: 23.9 | E11: 12.5 | H11: -7 | I11: 14 | J11: 1.3 | L11: 0 | M11: -18.1 | N11: -9.1 | O11: 3.2 | P11: 4.8 | Q11: 9.4 | R11: 42.2 | S11: 0.1 | X11: 3.9 | Y11: 1 | Z11: 1.5 | AA11: 0 | AB11: -3.5 | AC11: 4.6 | AD11: 6.1 | AH11: 0 | AI11: -9.4 | AJ11: 2.2 | AN11: -1.8 | AO11: -5.9 | AP11: 1.4 | AQ11: 8.9 | AR11: 5.8 | AS11: -0.2 | AT11: 1.8 | AU11: -0.3 | AV11: 19.8 | AW11: 6.3 | AX11: -39.9 | AY11: -1 | AZ11: -2.7 | BA11: 0 | BB11: -2.2 | BC11: 5.1 | BD11: 0.5 | BE11: -0.1 | BF11: 0.3 | BI11: -5.8 | BL11: -4.8 | BP11: 1.2 | BQ11: -21.4 | BR11: -22.1 | BS11: 0 | BT11: 0.4 | CC11: -0.6 | CD11: 12 | CE11: 12.3 | CF11: -0.1 | CG11: 1.5 | CH11: 0 | CL11: -9.2 | CM11: -7.1 | CN11: -36.4 | CO11: 0 | CT11: -1 | CU11: 1 | CW11: -9.6 | CX11: 0 | DA11: 0.5 | DC11: 0 | DD11: -0.3 | DF11: 0.1 | DG11: 0.5 | DH11: 0 | DI11: 0.2 | DJ11: 0.1 | DK11: 0.5 | DM11: 0 | DN11: 0 | DO11: 3.9 | DP11: 12.2 | DQ11: 1.4 | DR11: 0.4 | DS11: 0.8 | DT11: 1.2 | DU11: 0 | DV11: 0.1 | DW11: 0.2 | DX11: 0.2 | DZ11: -1.3 | EA11: 0.2 | EB11: 0.4 | EC11: 0.4 | ED11: 0.1 | EE11: 0.8 | EF11: 24.7 | EG11: 0 | EH11: -8.7 | EI11: -9.6 | EL11: 0.9 | EM11: 0.1 | EN11: 1.4 | EO11: 0.1 | EP11: 0.1 | EQ11: 0.1 | ES11: 0 | ET11: 0 | EU11: 0 | EV11: -0.2 | EW11: 4.9 | EX11: 3.5 | EY11: 0 | EZ11: 0 | FA11: 0.2 | FB11: 0.2 | FC11: 1.9 | FD11: 9.3 | FE11: 4.4 | FF11: 3.3 | FG11: 0 | FH11: 2.5 | FK11: 46.6 | FM11: 1.14368 | FN11: 0 | FO11: 1.344 | FP11: 0.9 | FQ11: 0.30742 | FR11: 0.24175 | FS11: -0.1 | FT11: 1 | FU11: 4.83685
A12: 26/07/2025 | B12: 01:00 | C12: -7.4 | D12: 37.9 | E12: 14.9 | H12: -5.9 | I12: 9.1 | J12: 0 | L12: 0 | M12: -16.5 | N12: -6.7 | O12: -1.2 | P12: 4.3 | Q12: 8.2 | R12: 48.4 | S12: 0.4 | X12: 9.1 | Y12: 1.2 | Z12: 0.9 | AA12: 0 | AB12: -3.5 | AC12: 5.2 | AD12: 6.5 | AH12: 0 | AI12: -6.9 | AJ12: -0.1 | AN12: -1.5 | AO12: -1 | AP12: 1.5 | AQ12: 0 | AR12: 6 | AS12: -0.5 | AT12: 1.8 | AU12: 0.9 | AV12: 16.8 | AW12: 3.9 | AX12: -43.1 | AY12: -2.3 | AZ12: -2.7 | BA12: 0 | BB12: 0.5 | BC12: 7.5 | BD12: 0.5 | BE12: 0 | BF12: 6.5 | BI12: -6.1 | BL12: -5.1 | BP12: 2.2 | BQ12: -22.6 | BR12: -23.5 | BS12: 0 | BT12: -1 | CC12: -0.6 | CD12: 8.7 | CE12: 11.7 | CF12: -1.3 | CG12: 1.8 | CH12: 0.1 | CL12: -13 | CM12: -11.2 | CN12: -41.7 | CO12: 0 | CT12: -1.5 | CU12: 0.8 | CW12: -9.1 | CX12: 0 | DA12: 0.5 | DC12: 0 | DD12: -0.3 | DF12: 0.2 | DG12: 0.5 | DH12: 0 | DI12: 0.2 | DJ12: 0.1 | DK12: 0.5 | DM12: 0 | DN12: 0 | DO12: 4.3 | DP12: 18.1 | DQ12: 1.4 | DR12: 0.4 | DS12: 0.8 | DT12: 1.2 | DU12: 0 | DV12: 0.1 | DW12: 0.1 | DX12: 0.2 | DZ12: -1.3 | EA12: 0.2 | EB12: 0.4 | EC12: 0.3 | ED12: 0 | EE12: 0.8 | EF12: 17.9 | EG12: 0 | EH12: -8.8 | EI12: -9.3 | EL12: 0.9 | EM12: 0.1 | EN12: 1.4 | EO12: 0.1 | EP12: 0.1 | EQ12: 0.1 | ES12: 0 | ET12: 0 | EU12: 0 | EV12: -0.2 | EW12: 4.7 | EX12: 3.4 | EY12: 0 | EZ12: 0 | FA12: 0.2 | FB12: 0 | FC12: 2.1 | FD12: 8.2 | FE12: 3.2 | FF12: 3.7 | FG12: 0 | FH12: 2.7 | FK12: 40.5 | FM12: 1.24114 | FN12: 0 | FO12: 1.394 | FP12: 0.9 | FQ12: 0.30372 | FR12: 0.20492 | FS12: -0.2 | FT12: 0.8 | FU12: 4.64378
A13: 26/07/2025 | B13: 01:30 | C13: -3.9 | D13: 36 | E13: 14.8 | H13: 0 | I13: 14.4 | J13: 0 | L13: 0 | M13: -26.1 | N13: -16.6 | O13: -1.8 | P13: 1.6 | Q13: 6.5 | R13: 60.6 | S13: 0 | X13: 10.6 | Y13: 0.9 | Z13: 1 | AA13: 0 | AB13: -3.5 | AC13: 5.1 | AD13: 6.8 | AH13: 0 | AI13: -4.6 | AJ13: 0 | AN13: -1.5 | AO13: 7.7 | AP13: 1.6 | AQ13: 0 | AR13: 5.5 | AS13: 0 | AT13: 1.8 | AU13: 0.1 | AV13: 12.7 | AW13: -7.4 | AX13: -37.3 | AY13: -0.8 | AZ13: -2.6 | BA13: 0 | BB13: -2.9 | BC13: 2.7 | BD13: 0.5 | BE13: 0 | BF13: -2.6 | BI13: -0.4 | BL13: -5 | BP13: 5.8 | BQ13: -24.5 | BR13: -25.6 | BS13: 0 | BT13: -5.3 | CC13: -0.6 | CD13: 9.7 | CE13: 12.5 | CF13: -0.1 | CG13: 1.8 | CH13: 0.1 | CL13: -1.1 | CM13: 0.9 | CN13: -24 | CO13: 0 | CT13: -8.3 | CU13: -3.3 | CW13: -8.5 | CX13: 0 | DA13: 0.5 | DC13: 0 | DD13: 0 | DF13: 0.1 | DG13: 0.5 | DH13: 0 | DI13: 0.7 | DJ13: 0.1 | DK13: 0.6 | DM13: 0 | DN13: 0 | DO13: 4.7 | DP13: 19.3 | DQ13: 1.4 | DR13: 0.4 | DS13: 0.8 | DT13: 1.2 | DU13: 0 | DV13: 0 | DW13: 0.2 | DX13: 0.2 | DZ13: -1.3 | EA13: 0.1 | EB13: 0.3 | EC13: 0.1 | ED13: 0.3 | EE13: 0.8 | EF13: 3.1 | EG13: 0 | EH13: -9.4 | EI13: -10.4 | EL13: 0.9 | EM13: 0.1 | EN13: 1.4 | EO13: 0.1 | EP13: 0.1 | EQ13: 0.1 | ES13: 0 | ET13: 0 | EU13: 0 | EV13: -0.2 | EW13: 4.6 | EX13: 3.4 | EY13: 0 | EZ13: 0 | FA13: 0.2 | FB13: 0.8 | FC13: 2.1 | FD13: 9 | FE13: 4 | FF13: 3.4 | FG13: 0 | FH13: 2 | FK13: 49.7 | FM13: 1.26535 | FN13: 0 | FO13: 1.794 | FP13: 1 | FQ13: 0.31041 | FR13: 0.23373 | FS13: -0.1 | FT13: 1.1 | FU13: 5.60349
A14: 26/07/2025 | B14: 02:00 | C14: -4.2 | D14: 44.9 | E14: 15.5 | H14: 0 | I14: 22.5 | J14: 0.7 | L14: 0 | M14: -29.2 | N14: -17.2 | O14: -3.5 | P14: 1.3 | Q14: 6.9 | R14: 69.5 | S14: -0.1 | X14: 10.3 | Y14: 0.6 | Z14: 1 | AA14: 0 | AB14: -3.5 | AC14: 5.3 | AD14: 7.5 | AH14: 0 | AI14: -5 | AJ14: 0 | AN14: -1.5 | AO14: 7.7 | AP14: 1.3 | AQ14: 0 | AR14: 5.6 | AS14: -0.4 | AT14: 1.8 | AU14: 0.3 | AV14: 13.4 | AW14: -7.2 | AX14: -36.6 | AY14: 0.3 | AZ14: -2.6 | BA14: 0 | BB14: -2.9 | BC14: 3.4 | BD14: 0.5 | BE14: 0 | BF14: 0.3 | BI14: -7.9 | BL14: -4.1 | BP14: 6.3 | BQ14: -24.9 | BR14: -25.8 | BS14: 0 | BT14: -4.7 | CC14: -0.6 | CD14: 8.7 | CE14: 12.7 | CF14: 0.3 | CG14: 2.3 | CH14: -0.2 | CL14: -1.8 | CM14: 0.5 | CN14: -25.8 | CO14: 0 | CT14: -8.3 | CU14: -3.3 | CW14: -7.9 | CX14: 0 | DA14: 0.5 | DC14: 0 | DD14: 0 | DF14: 0.2 | DG14: 0.5 | DH14: 0.2 | DI14: 0.9 | DJ14: 0.1 | DK14: 0.5 | DM14: 0 | DN14: 0 | DO14: 4.5 | DP14: 19 | DQ14: 1.4 | DR14: 0.4 | DS14: 0.8 | DT14: 1.2 | DU14: 0 | DV14: 0 | DW14: 0.2 | DX14: 0.2 | DZ14: -1.3 | EA14: 0.2 | EB14: 0.4 | EC14: 0.2 | ED14: 0.9 | EE14: 0.8 | EF14: 0 | EG14: 0 | EH14: -8.6 | EI14: -9.2 | EL14: 0.9 | EM14: 0.1 | EN14: 1.4 | EO14: 0.1 | EP14: 0.1 | EQ14: 0.1 | ES14: 0 | ET14: 0 | EU14: 0 | EV14: -0.2 | EW14: 4.7 | EX14: 3.4 | EY14: 0 | EZ14: 0 | FA14: 0.2 | FB14: 1 | FC14: 2 | FD14: 8.8 | FE14: 4 | FF14: 4 | FG14: 0 | FH14: 1.7 | FK14: 68.5 | FM14: 1.17272 | FN14: 0 | FO14: 1.724 | FP14: 1 | FQ14: 0.30907 | FR14: 0.25652 | FS14: -0.2 | FT14: 1.1 | FU14: 5.36231
A15: 26/07/2025 | B15: 02:30 | C15: -3.4 | D15: 38.1 | E15: 15.2 | H15: 0 | I15: 22.7 | J15: 2.4 | L15: 0 | M15: -27.7 | N15: -18.7 | O15: -8.1 | P15: 0.8 | Q15: 6.5 | R15: 49.1 | S15: 0 | X15: 11.8 | Y15: 0.7 | Z15: 1.2 | AA15: 0 | AB15: -3.5 | AC15: 5.3 | AD15: 7.7 | AH15: 0 | AI15: -3 | AJ15: 0 | AN15: -1.6 | AO15: 7.9 | AP15: 2 | AQ15: 0 | AR15: 5.2 | AS15: -0.1 | AT15: 1.8 | AU15: 0.2 | AV15: 12.6 | AW15: -8.4 | AX15: -37.4 | AY15: 0.2 | AZ15: -2.5 | BA15: 0 | BB15: -3.2 | BC15: 2.6 | BD15: 0.5 | BE15: 0 | BF15: -1.4 | BI15: -9 | BL15: -4.9 | BP15: 5.3 | BQ15: -26.3 | BR15: -27.3 | BS15: 0 | BT15: -6.1 | CC15: -0.6 | CD15: 8.5 | CE15: 12.5 | CF15: 0 | CG15: 1.5 | CH15: 0 | CL15: -3.9 | CM15: -1.5 | CN15: -28.4 | CO15: 0 | CT15: -8.4 | CU15: -3.4 | CW15: -7.4 | CX15: 0 | DA15: 0.5 | DC15: 0 | DD15: 0 | DF15: 0.1 | DG15: 0.6 | DH15: 0.1 | DI15: 0.3 | DJ15: 0.1 | DK15: 0.6 | DM15: 0 | DN15: 0 | DO15: 4.6 | DP15: 19.2 | DQ15: 1.4 | DR15: 0.4 | DS15: 0.8 | DT15: 1.2 | DU15: 0 | DV15: 0 | DW15: 0.2 | DX15: 0.2 | DZ15: -1.3 | EA15: 0.2 | EB15: 0.4 | EC15: 0.1 | ED15: 0.7 | EE15: 0.8 | EF15: 0.5 | EG15: 0 | EH15: -9.2 | EI15: -9.7 | EL15: 0.9 | EM15: 0.1 | EN15: 1.5 | EO15: 0.1 | EP15: 0.1 | EQ15: 0.1 | ES15: 0 | ET15: 0 | EU15: 0 | EV15: -0.2 | EW15: 4.4 | EX15: 3.3 | EY15: 0 | EZ15: 0 | FA15: 0.2 | FB15: 0.9 | FC15: 1.9 | FD15: 8.7 | FE15: 3.7 | FF15: 3 | FG15: 0 | FH15: 1.8 | FK15: 19.4 | FM15: 1.6176 | FN15: 0 | FO15: 1.506 | FP15: 0.9 | FQ15: 0.30756 | FR15: 0.22169 | FS15: -0.2 | FT15: 1 | FU15: 5.35285
A16: 26/07/2025 | B16: 03:00 | C16: -2.3 | D16: 45.7 | E16: 16.4 | H16: 0 | I16: 21.7 | J16: 1.9 | L16: 0 | M16: -25.6 | N16: -16.6 | O16: -5.8 | P16: 1.1 | Q16: 6.3 | R16: 58.6 | S16: 0.1 | X16: 13.8 | Y16: 1.2 | Z16: 1.6 | AA16: 0 | AB16: -3.4 | AC16: 5.6 | AD16: 8.2 | AH16: 0 | AI16: -1.7 | AJ16: 0 | AN16: -1.5 | AO16: 7.7 | AP16: 2 | AQ16: 0 | AR16: 5.1 | AS16: -0.3 | AT16: 1.8 | AU16: 0.1 | AV16: 12.4 | AW16: -8 | AX16: -37.8 | AY16: -0.7 | AZ16: -2.5 | BA16: 0 | BB16: -1.1 | BC16: 2.9 | BD16: 0.5 | BE16: 0 | BF16: 0.1 | BI16: -9 | BL16: -4.3 | BP16: 5 | BQ16: -25.6 | BR16: -26.9 | BS16: 0 | BT16: -3.6 | CC16: -0.6 | CD16: 9.1 | CE16: 12.4 | CF16: -0.1 | CG16: 1.5 | CH16: -0.1 | CL16: -3.6 | CM16: -1.4 | CN16: -28.2 | CO16: 0 | CT16: -8.5 | CU16: -3.5 | CW16: -7.3 | CX16: 0 | DA16: 0.5 | DC16: 0 | DD16: 0 | DF16: 0.1 | DG16: 0.5 | DH16: 0.1 | DI16: 0.6 | DJ16: 0.1 | DK16: 0.5 | DM16: 0 | DN16: 0 | DO16: 3.5 | DP16: 15.5 | DQ16: 1.4 | DR16: 0.4 | DS16: 0.8 | DT16: 1.2 | DU16: 0 | DV16: 0 | DW16: 0.2 | DX16: 0.2 | DZ16: -1.3 | EA16: 0 | EB16: 0.4 | EC16: 0.1 | ED16: 0.7 | EE16: 0.8 | EF16: 0.5 | EG16: 0 | EH16: -8 | EI16: -8.7 | EL16: 0.9 | EM16: 0.1 | EN16: 1.5 | EO16: 0.1 | EP16: 0.1 | EQ16: 0.1 | ES16: 0 | ET16: 0 | EU16: 0 | EV16: -0.2 | EW16: 4.6 | EX16: 3.5 | EY16: 0 | EZ16: 0 | FA16: 0.2 | FB16: 0.8 | FC16: 2.1 | FD16: 8.9 | FE16: 4.1 | FF16: 2.5 | FG16: 0 | FH16: 1.7 | FK16: 53.9 | FM16: 1.56446 | FN16: 0 | FO16: 1.456 | FP16: 0.9 | FQ16: 0.30679 | FR16: 0.23738 | FS16: -0.2 | FT16: 1 | FU16: 5.26463
A17: 26/07/2025 | B17: 03:30 | C17: -3.5 | D17: 40.7 | E17: 17.3 | H17: 0 | I17: 18.1 | J17: 0 | L17: 0 | M17: -27.3 | N17: -16.6 | O17: -7.3 | P17: -1.4 | Q17: 5 | R17: 69.2 | S17: 0.1 | X17: 11.5 | Y17: 0.8 | Z17: 1.3 | AA17: 0 | AB17: -3.4 | AC17: 3.9 | AD17: 8.7 | AH17: 0 | AI17: -1.3 | AJ17: 0 | AN17: -1.6 | AO17: 7.7 | AP17: 2.4 | AQ17: 0 | AR17: 4.8 | AS17: -0.2 | AT17: 1.8 | AU17: 0.5 | AV17: 9.9 | AW17: -10.1 | AX17: -40 | AY17: -0.4 | AZ17: -2.5 | BA17: 0 | BB17: -3 | BC17: 5.1 | BD17: 0.5 | BE17: 0 | BF17: -1.9 | BI17: -7.9 | BL17: -6.6 | BP17: 3.8 | BQ17: -26 | BR17: -27.3 | BS17: 0 | BT17: -4 | CC17: -0.7 | CD17: 12.3 | CE17: 10 | CF17: -1.8 | CG17: 1.8 | CH17: 0 | CL17: -5.5 | CM17: -3.4 | CN17: -30.4 | CO17: 0 | CT17: -8.7 | CU17: -3.6 | CW17: -7.5 | CX17: 0 | DA17: 0.5 | DC17: 0 | DD17: 0 | DF17: 0.1 | DG17: 0.6 | DH17: -0.1 | DI17: 0.9 | DJ17: 0.1 | DK17: 0.5 | DM17: 0 | DN17: 0 | DO17: 3.4 | DP17: 15.4 | DQ17: 1.4 | DR17: 0.4 | DS17: 0.8 | DT17: 1.2 | DU17: 0 | DV17: 0.1 | DW17: 0.2 | DX17: 0.2 | DZ17: -1.3 | EA17: 0.2 | EB17: 0.4 | EC17: 0.1 | ED17: 0.7 | EE17: 0.8 | EF17: 0.7 | EG17: 0 | EH17: -7.3 | EI17: -8.5 | EL17: 0.9 | EM17: 0.1 | EN17: 1.5 | EO17: 0.1 | EP17: 0.1 | EQ17: 0.1 | ES17: 0 | ET17: 0 | EU17: 0 | EV17: -0.2 | EW17: 4.8 | EX17: 3.6 | EY17: 0 | EZ17: 0 | FA17: 0.2 | FB17: 0.8 | FC17: 2.1 | FD17: 8.9 | FE17: 4 | FF17: 1.1 | FG17: 0 | FH17: 1.3 | FK17: 24.2 | FM17: 1.68606 | FN17: 0 | FO17: 1.466 | FP17: 0.9 | FQ17: 0.30946 | FR17: 0.12307 | FS17: -0.1 | FT17: 0.9 | FU17: 5.28459
A18: 26/07/2025 | B18: 04:00 | C18: -3.9 | D18: 48.8 | E18: 17.2 | H18: 0 | I18: 12.6 | J18: 1.2 | L18: 0 | M18: -25.8 | N18: -16.2 | O18: -0.3 | P18: 1.1 | Q18: 6.3 | R18: 66.9 | S18: 0 | X18: 13.5 | Y18: 1.3 | Z18: 1.9 | AA18: 0 | AB18: -3.4 | AC18: 5.3 | AD18: 8.4 | AH18: 0 | AI18: -1.6 | AJ18: 0 | AN18: -1.6 | AO18: 7.4 | AP18: 2.1 | AQ18: 0 | AR18: 5.3 | AS18: 0.1 | AT18: 1.8 | AU18: 0.1 | AV18: 13.4 | AW18: -7.3 | AX18: -37.2 | AY18: -1 | AZ18: -2.5 | BA18: 0 | BB18: -2.7 | BC18: 2.5 | BD18: 0.5 | BE18: 0 | BF18: -1.4 | BI18: -6.8 | BL18: -5 | BP18: 6.2 | BQ18: -24.1 | BR18: -25.3 | BS18: 0 | BT18: -3.5 | CC18: -0.6 | CD18: 6.3 | CE18: 12 | CF18: -0.2 | CG18: 1.7 | CH18: 0 | CL18: -3.5 | CM18: -1.1 | CN18: -27.5 | CO18: 0 | CT18: -8.7 | CU18: -3.5 | CW18: -8.5 | CX18: 0 | DA18: 0.5 | DC18: 0 | DD18: 0 | DF18: 0.1 | DG18: 0.5 | DH18: 0.1 | DI18: 0.6 | DJ18: 0.1 | DK18: 0.5 | DM18: 0 | DN18: 0 | DO18: 3.6 | DP18: 16.1 | DQ18: 1.4 | DR18: 0.4 | DS18: 0.8 | DT18: 1.2 | DU18: 0 | DV18: 0.1 | DW18: 0.2 | DX18: 0.2 | DZ18: -1.3 | EA18: 0.2 | EB18: 0.4 | EC18: 0.1 | ED18: 0.7 | EE18: 0.8 | EF18: 0.4 | EG18: 0 | EH18: -6 | EI18: -7 | EL18: 0.9 | EM18: 0.1 | EN18: 1.5 | EO18: 0.1 | EP18: 0.1 | EQ18: 0.1 | ES18: 0 | ET18: 0 | EU18: 0 | EV18: -0.2 | EW18: 4.8 | EX18: 3.6 | EY18: 0 | EZ18: 0 | FA18: 0.2 | FB18: 0.8 | FC18: 1.8 | FD18: 8.8 | FE18: 3.9 | FF18: 2.7 | FG18: 0 | FH18: 1.8 | FK18: 66.4 | FM18: 1.60987 | FN18: 0 | FO18: 1.52 | FP18: 1 | FQ18: 0.31342 | FR18: 0.11008 | FS18: -0.1 | FT18: 1 | FU18: 5.45337
A19: 26/07/2025 | B19: 04:30 | C19: -3.6 | D19: 37.3 | E19: 14.7 | H19: 0 | I19: 20.5 | J19: 2.3 | L19: 0 | M19: -31 | N19: -17.7 | O19: -6.5 | P19: -0.3 | Q19: 6 | R19: 63.6 | S19: 0 | X19: 10.7 | Y19: 1.4 | Z19: 1.6 | AA19: 0 | AB19: -3.5 | AC19: 5.3 | AD19: 8.2 | AH19: 0 | AI19: -3.3 | AJ19: 0 | AN19: -1.3 | AO19: 7.5 | AP19: 2.5 | AQ19: 0 | AR19: 5.1 | AS19: -0.7 | AT19: 1.8 | AU19: -0.4 | AV19: 11.1 | AW19: -9.2 | AX19: -43.2 | AY19: -0.9 | AZ19: -2.6 | BA19: 0 | BB19: -3.5 | BC19: 3 | BD19: 0.5 | BE19: 0 | BF19: -0.6 | BI19: -7.2 | BL19: -3.4 | BP19: 4.8 | BQ19: -26.3 | BR19: -27.3 | BS19: 0 | BT19: -4.7 | CC19: -0.6 | CD19: 5.8 | CE19: 13.1 | CF19: 0.2 | CG19: 2 | CH19: -0.1 | CL19: -4.3 | CM19: -1.8 | CN19: -29.3 | CO19: 0 | CT19: 0 | CU19: -4.3 | CW19: -9.2 | CX19: 0 | DA19: 0.5 | DC19: 0 | DD19: 0 | DF19: 0 | DG19: 0.6 | DH19: 0 | DI19: 0.4 | DJ19: 0.1 | DK19: 0.6 | DM19: 0 | DN19: 0 | DO19: 2.9 | DP19: 14.6 | DQ19: 1.4 | DR19: 0.4 | DS19: 0.8 | DT19: 1.2 | DU19: 0 | DV19: 0.1 | DW19: 0.2 | DX19: 0.2 | DZ19: -1.3 | EA19: 0.3 | EB19: 0.4 | EC19: 0.1 | ED19: 0.7 | EE19: 0.8 | EF19: 0 | EG19: 0 | EH19: -8.5 | EI19: -10.3 | EL19: 0.9 | EM19: 0.1 | EN19: 1.5 | EO19: 0.1 | EP19: 0.1 | EQ19: 0.1 | ES19: 0 | ET19: 0 | EU19: 0 | EV19: -0.2 | EW19: 4.7 | EX19: 3.6 | EY19: 0 | EZ19: 0 | FA19: 0.2 | FB19: 0.8 | FC19: 1.9 | FD19: 9.4 | FE19: 4.5 | FF19: 2.8 | FG19: 0 | FH19: 1.6 | FK19: 20.5 | FM19: 1.67777 | FN19: 0 | FO19: 1.662 | FP19: 1 | FQ19: 0.30703 | FR19: 0.11552 | FS19: 0.1 | FT19: 1 | FU19: 5.86232
A20: 26/07/2025 | B20: 05:00 | C20: -4.3 | D20: 20.9 | E20: 11.8 | H20: -2.9 | I20: 21.9 | J20: 1.3 | L20: 0 | M20: -33.9 | N20: -18.8 | O20: -8.5 | P20: -0.8 | Q20: 5.2 | R20: 47.7 | S20: 0 | X20: 8.6 | Y20: 1.3 | Z20: 1.6 | AA20: 0 | AB20: -3.5 | AC20: 5 | AD20: 6.8 | AH20: 0 | AI20: -3.4 | AJ20: 0 | AN20: -1.4 | AO20: 0 | AP20: 2.1 | AQ20: -1.1 | AR20: 5.3 | AS20: -0.6 | AT20: 1.8 | AU20: -0.2 | AV20: 10.9 | AW20: -9.5 | AX20: -43.8 | AY20: -1 | AZ20: -2.5 | BA20: 0 | BB20: -2.4 | BC20: 3.2 | BD20: 0.5 | BE20: 0 | BF20: -0.7 | BI20: -7.2 | BL20: -2.6 | BP20: 4.3 | BQ20: -26.6 | BR20: -27.5 | BS20: 0 | BT20: -6.2 | CC20: -0.6 | CD20: 6.3 | CE20: 12.8 | CF20: 0.1 | CG20: 1.7 | CH20: -0.2 | CL20: -3.5 | CM20: -1.2 | CN20: -27.8 | CO20: 0 | CT20: 2 | CU20: -5.3 | CW20: -8.4 | CX20: 0 | DA20: 0.5 | DC20: 0 | DD20: 0 | DF20: 0.1 | DG20: 0.5 | DH20: 0.1 | DI20: 0.2 | DJ20: 0.1 | DK20: 0.6 | DM20: 0 | DN20: 0 | DO20: 2.1 | DP20: 12.3 | DQ20: 1.4 | DR20: 0.4 | DS20: 0.8 | DT20: 1.2 | DU20: 0.2 | DV20: 0 | DW20: 0.2 | DX20: 0.1 | DZ20: -1.4 | EA20: 0.3 | EB20: 0.4 | EC20: 0.1 | ED20: 0.7 | EE20: 0.8 | EF20: 0 | EG20: 0.4 | EH20: -12.1 | EI20: -13.2 | EL20: 0.9 | EM20: 0.1 | EN20: 1.5 | EO20: 0.1 | EP20: 0.1 | EQ20: 0.1 | ES20: 0 | ET20: 0 | EU20: 0 | EV20: -0.2 | EW20: 4.5 | EX20: 3.4 | EY20: 0 | EZ20: 0 | FA20: 0.2 | FB20: 0.8 | FC20: 2.2 | FD20: 9.9 | FE20: 5 | FF20: 2.9 | FG20: 0 | FH20: 1.9 | FK20: -43.1 | FM20: 1.57791 | FN20: 0 | FO20: 1.574 | FP20: 1 | FQ20: 0.3004 | FR20: 0.15031 | FS20: 0.2 | FT20: 1.1 | FU20: 5.90262
A21: 26/07/2025 | B21: 05:30 | C21: -3.3 | D21: 27.2 | E21: 13.5 | H21: -3.1 | I21: 20.6 | J21: 2 | L21: 0 | M21: -27.8 | N21: -16.8 | O21: -3.5 | P21: 0.6 | Q21: 6.6 | R21: 47.1 | S21: 0.1 | X21: 8.4 | Y21: 1.2 | Z21: 1.6 | AA21: 0 | AB21: -3.4 | AC21: 4.9 | AD21: 6.5 | AH21: 0 | AI21: -3.5 | AJ21: -2.8 | AN21: -1.4 | AO21: 0 | AP21: 2.6 | AQ21: -1 | AR21: 5.5 | AS21: -0.9 | AT21: 1.8 | AU21: 0.1 | AV21: 11.6 | AW21: -8.8 | AX21: -43 | AY21: -2 | AZ21: -2.5 | BA21: 0 | BB21: -1.6 | BC21: 3.4 | BD21: 0.5 | BE21: 0 | BF21: -1 | BI21: -7.8 | BL21: -0.1 | BP21: 4.1 | BQ21: -25.8 | BR21: -26.7 | BS21: 0 | BT21: -5.4 | CC21: -0.6 | CD21: 6.1 | CE21: 12.6 | CF21: -0.3 | CG21: 1.5 | CH21: -0.1 | CL21: -2.5 | CM21: 0.1 | CN21: -26.6 | CO21: 0 | CT21: 2.7 | CU21: -4.9 | CW21: -8.6 | CX21: 0 | DA21: 0.5 | DC21: 0 | DD21: 0 | DF21: 0.1 | DG21: 0.5 | DH21: 0.2 | DI21: 0.2 | DJ21: 0.1 | DK21: 0.5 | DM21: 0 | DN21: 0 | DO21: 2.9 | DP21: 14.4 | DQ21: 1.4 | DR21: 0.4 | DS21: 0.8 | DT21: 1.2 | DU21: 0.2 | DV21: 0.1 | DW21: 0.2 | DX21: 0.1 | DZ21: -1.3 | EA21: 0.1 | EB21: 0.4 | EC21: 0.1 | ED21: 0.7 | EE21: 0.8 | EF21: 0 | EG21: 0.4 | EH21: -8.2 | EI21: -9.1 | EL21: 0.9 | EM21: 0.1 | EN21: 1.5 | EO21: 0.1 | EP21: 0.1 | EQ21: 0.1 | ES21: 0 | ET21: 0 | EU21: 0 | EV21: -0.2 | EW21: 1.3 | EX21: 0.9 | EY21: 0 | EZ21: 0 | FA21: 0.2 | FB21: 0.9 | FC21: 2.1 | FD21: 8.9 | FE21: 4.1 | FF21: 3 | FG21: 0 | FH21: 1.7 | FK21: -9.5 | FM21: 1.78847 | FN21: 0 | FO21: 1.32 | FP21: 1 | FQ21: 0.29823 | FR21: 0.19467 | FS21: 0.4 | FT21: 1 | FU21: 6.00137
A22: 26/07/2025 | B22: 06:00 | C22: -2.5 | D22: 21.2 | E22: 11.8 | H22: -3 | I22: 14.1 | J22: 1.7 | L22: 0 | M22: -29.4 | N22: -20.3 | O22: -5.7 | P22: -1.4 | Q22: 5.3 | R22: 43.7 | S22: 0 | X22: 9.4 | Y22: 1 | Z22: 1.5 | AA22: 0 | AB22: -3.4 | AC22: 5 | AD22: 5.6 | AH22: 2.5 | AI22: -3.3 | AJ22: -8.1 | AN22: -1.4 | AO22: 0 | AP22: 2.3 | AQ22: 12.7 | AR22: 3.7 | AS22: -0.7 | AT22: 1.8 | AU22: 0.3 | AV22: 9.7 | AW22: -10.7 | AX22: -44.7 | AY22: -0.2 | AZ22: -2.4 | BA22: 0 | BB22: -0.8 | BC22: 2.9 | BD22: 0.5 | BE22: 0 | BF22: -2 | BI22: -7.9 | BL22: -1.1 | BP22: 2.4 | BQ22: -26.4 | BR22: -27.2 | BS22: 0 | BT22: -5.5 | CC22: -0.6 | CD22: 5.9 | CE22: 12.6 | CF22: 0.4 | CG22: 1.5 | CH22: -0.1 | CL22: -3.8 | CM22: -1.4 | CN22: -28.3 | CO22: 0 | CT22: 3.3 | CU22: -4.5 | CW22: -8.9 | CX22: 0 | DA22: 0.5 | DC22: 0 | DD22: 0 | DF22: 0 | DG22: 0.6 | DH22: -0.2 | DI22: 0.7 | DJ22: 0.1 | DK22: 0.5 | DM22: 0 | DN22: 0 | DO22: 2.7 | DP22: 14.3 | DQ22: 1.4 | DR22: 0.4 | DS22: 0.8 | DT22: 1.2 | DU22: 0.4 | DV22: 0 | DW22: 0.2 | DX22: 0.1 | DZ22: -1.3 | EA22: 0 | EB22: 0.4 | EC22: 0.1 | ED22: 0.8 | EE22: 0.8 | EF22: 0 | EG22: 0.3 | EH22: -10.1 | EI22: -11.2 | EL22: 0.9 | EM22: 0.1 | EN22: 1.3 | EO22: 0.1 | EP22: 0.1 | EQ22: 0.1 | ES22: 0 | ET22: 0 | EU22: 0 | EV22: -0.2 | EW22: 8.9 | EX22: 0 | EY22: 0 | EZ22: 0 | FA22: 0.2 | FB22: 1 | FC22: 2.1 | FD22: 8.9 | FE22: 4.1 | FF22: 1.1 | FG22: 0 | FH22: 1.8 | FK22: -38.9 | FM22: 1.65578 | FN22: 0 | FO22: 1.414 | FP22: 1 | FQ22: 0.30518 | FR22: 0.26946 | FS22: 0.3 | FT22: 0.9 | FU22: 5.84442
... A58: 27/07/2025 | B58: 00:00 | C58: -3.6 | D58: -0.2 | E58: 7.3 | H58: -0.6 | I58: 27.2 | J58: 0.7 | L58: -11.9 | M58: -31.7 | N58: -31.8 | O58: 3.7 | P58: -8.9 | Q58: 4 | R58: 20.4 | S58: 0.1 | X58: 3 | Y58: 0.9 | Z58: 1.1 | AA58: 0 | AB58: 0 | AC58: 0 | AD58: 0 | AH58: 0 | AI58: -1.5 | AJ58: -20 | AN58: -1.3 | AO58: 0 | AP58: 1.1 | AQ58: 0 | AR58: 0 | AS58: 1.2 | AT58: 1.8 | AU58: 0 | AV58: 6.3 | AW58: -14.3 | AX58: -46.8 | AY58: -2.9 | AZ58: -2.9 | BA58: -0.3 | BB58: -1.4 | BC58: 5.3 | BD58: 0.5 | BE58: 0 | BF58: 0.1 | BI58: -7.6 | BL58: 2.6 | BP58: -1.9 | BQ58: -37.3 | BR58: -22 | BS58: -3.9 | BT58: 46.4 | CC58: -0.6 | CD58: 0 | CE58: 0 | CF58: 0 | CG58: 0 | CH58: 0 | CL58: 0 | CM58: 0 | CN58: 0 | CO58: 0 | CT58: -31.7 | CU58: -17.9 | CW58: -5.9 | CX58: 0 | DA58: 0.5 | DC58: 0 | DD58: 0 | DF58: 0.1 | DG58: 0.6 | DH58: 0 | DI58: 0.9 | DJ58: 0 | DK58: 0.6 | DM58: 0 | DN58: 0 | DO58: 2.7 | DP58: 9.9 | DQ58: 1.4 | DR58: 0.4 | DS58: 0.8 | DT58: 1.2 | DU58: 0 | DV58: 0 | DW58: 0.2 | DX58: 0.2 | DZ58: -1.6 | EA58: 0 | EB58: 0.4 | EC58: 0.4 | ED58: 0.1 | EE58: 0.8 | EF58: 4 | EG58: 0 | EH58: -7.5 | EI58: -8.7 | EL58: 0.9 | EM58: 0.1 | EN58: 1.3 | EO58: 0.1 | EP58: 0.1 | EQ58: 0.1 | ES58: 0 | ET58: 0 | EU58: 0 | EV58: 0 | EW58: 0 | EX58: 0 | EY58: 0 | EZ58: 0 | FA58: 0.4 | FB58: 0.4 | FC58: 2.2 | FD58: 9.1 | FE58: 9 | FF58: 2.7 | FG58: 1.8 | FH58: 2.2 | FK58: -137.4 | FM58: 1.19957 | FN58: 0 | FO58: 1.538 | FP58: 1 | FQ58: 0.26089 | FR58: 0.31771 | FS58: 0.7 | FT58: 0.4 | FU58: 5.41617
A59: EJEC | C59: -111.1 | D59: 394.45 | E59: 254 | F59: 0 | G59: 0 | H59: -18.75 | I59: 602.4 | J59: 88.7 | K59: 0 | L59: 3.05 | M59: -427.9 | N59: -281.5 | O59: 188.2 | P59: 54 | Q59: 241.15 | R59: 521.65 | S59: 0.95 | T59: 0 | U59: 0 | V59: 0 | W59: 0 | X59: 143.95 | Y59: 27.45 | Z59: 31.45 | AA59: 26.7 | AB59: -78.2 | AC59: 105.55 | AD59: 208.45 | AE59: 0 | AF59: 0 | AG59: 0 | AH59: 1.25 | AI59: 37.45 | AJ59: -27.1 | AK59: 0 | AL59: 0 | AM59: 0 | AN59: -24.25 | AO59: 23.35 | AP59: 42.55 | AQ59: 221.25 | AR59: 199.3 | AS59: -1.8 | AT59: 43.2 | AU59: 6.75 | AV59: 461.5 | AW59: 117.5 | AX59: -1003.25 | AY59: -11.55 | AZ59: -61.85 | BA59: -2.45 | BB59: -36.75 | BC59: 50.3 | BD59: 12 | BE59: 0.5 | BF59: -30.8 | BG59: 0 | BH59: 0 | BI59: -67.75 | BJ59: 0 | BK59: 0 | BL59: -32.9 | BM59: 0 | BN59: 0 | BO59: 0 | BP59: 80.2 | BQ59: -572.35 | BR59: -303.45 | BS59: -4.5 | BT59: 83.45 | BU59: 0 | BV59: 0 | BW59: 0 | BX59: 0 | BY59: 0 | BZ59: 0 | CA59: 0 | CB59: 0 | CC59: -14.4 | CD59: 507.25 | CE59: 412.45 | CF59: 103.6 | CG59: 189.1 | CH59: 46.8 | CI59: 0 | CJ59: 0 | CK59: 0 | CL59: 138.3 | CM59: 193.3 | CN59: -498.15 | CO59: -25.15 | CP59: 0 | CQ59: 0 | CR59: 0 | CS59: 0 | CT59: 37 | CU59: -20.65 | CV59: 0 | CW59: -177.6 | CX59: 54.95 | CY59: 0 | CZ59: 0 | DA59: 12 | DB59: 0 | DC59: 0.15 | DD59: -0.2 | DE59: 0 | DF59: 0.85 | DG59: 14.3 | DH59: 1.2 | DI59: 19.55 | DJ59: 2.55 | DK59: 12.45 | DL59: 0 | DM59: -6.5 | DN59: -13.55 | DO59: 54.35 | DP59: 246.7 | DQ59: 33.6 | DR59: 9.6 | DS59: 19.2 | DT59: 28.8 | DU59: -20.45 | DV59: 0.8 | DW59: 3.45 | DX59: 4.65 | DY59: 0 | DZ59: -36.8 | EA59: 1 | EB59: 8.9 | EC59: 7 | ED59: 13.7 | EE59: 35.75 | EF59: 81.5 | EG59: 18.05 | EH59: -168.6 | EI59: -190.3 | EJ59: 0 | EK59: 0 | EL59: 21.6 | EM59: 2.4 | EN59: 37.75 | EO59: 2.4 | EP59: 2.4 | EQ59: 2.4 | ER59: 0 | ES59: 18.45 | ET59: 13.1 | EU59: 113 | EV59: -4.6 | EW59: 199.65 | EX59: 127.25 | EY59: 6.7 | EZ59: 11.95 | FA59: 15.15 | FB59: 18.5 | FC59: 48.55 | FD59: 243.7 | FE59: 156.15 | FF59: 62.35 | FG59: 17.9 | FH59: 52.4 | FI59: 0 | FJ59: 0 | FK59: 3484.1 | FM59: 32.05794 | FN59: -3.8375 | FO59: 34.283 | FP59: 22.95 | FQ59: 7.01288 | FR59: 6.478325 | FS59: 12.5 | FT59: 27 | FU59: 138.44465

Sheet DEMANDA_AREAS
B3: sábado, 26 de Julio del 2025
B5: REPORTE DE LA DEMANDA POR ÁREAS Y SUBAREAS OPERATIVAS (MW)
B6: FECHA HORA | C6: DEMANDA | E6: AREA | H6: SUBAREAS
C7: INTERCAMBIOS INTERNACIONALES | D7: SEIN | E7: NORTE | F7: CENTRO | G7: SUR | H7: ELECTROANDES
B8: 00:30 | C8: 0 | D8: 6690.9 | E8: 975.8605 | F8: 3776.7761 | G8: 1938.2634 | H8: 246.9911
B9: 01:00 | C9: 0 | D9: 6502.1 | E9: 950.2105 | F9: 3776.5261 | G9: 1775.3634 | H9: 248.0916
B10: 01:30 | C10: 0 | D10: 6357.6 | E10: 890.9365 | F10: 3689.0001 | G10: 1777.6634 | H10: 244.5989
B11: 02:00 | C11: 0 | D11: 6405.5 | E11: 896.4945 | F11: 3734.7421 | G11: 1774.2634 | H11: 249.6277
B12: 02:30 | C12: 0 | D12: 6343.4 | E12: 903.7035 | F12: 3668.8904 | G12: 1770.8061 | H12: 251.509
B13: 03:00 | C13: 0 | D13: 6350.4 | E13: 887.4646 | F13: 3668.195 | G13: 1794.7404 | H13: 254.6566
B14: 03:30 | C14: 0 | D14: 6336.4 | E14: 859.0465 | F14: 3707.2442 | G14: 1770.1093 | H14: 253.3857
B15: 04:00 | C15: 0 | D15: 6314.9 | E15: 856.6325 | F15: 3681.8584 | G15: 1776.4091 | H15: 255.0153
B16: 04:30 | C16: 0 | D16: 6344.9 | E16: 906.9433 | F16: 3650.3177 | G16: 1787.639 | H16: 248.8134
B17: 05:00 | C17: 0 | D17: 6189.8 | E17: 900.8208 | F17: 3519.0009 | G17: 1769.9783 | H17: 248.3997
B18: 05:30 | C18: 0 | D18: 6344 | E18: 900.6533 | F18: 3678.0319 | G18: 1765.3148 | H18: 243.3905
B19: 06:00 | C19: 0 | D19: 6347.8 | E19: 883.2192 | F19: 3683.9242 | G19: 1780.6566 | H19: 235.7169
... B59: ENERGÍA | C59: 0 | D59: 164544.83 | E59: 24343.623 | F59: 96039.402 | G59: 44161.808 | H59: 5779.1748
B61: LEYENDA:
D63: Potencia recibida del Ecuador
D64: Potencia entregada al Ecuador

Sheet DEMANDA_UL
B3: sábado, 26 de Julio del 2025
B5: POTENCIA DE LOS GRANDES USUARIOS LIBRES (MW)
B6: FECHA HORA | C6: GRANDES USUARIOS LIBRES DEL ÁREA NORTE | X6: GRANDES USUARIOS LIBRES DEL ÁREA CENTRO | BP6: GRANDES USUARIOS LIBRES DEL ÁREA SUR
C7: ARCA CONTINENTAL LINDLEY S.A. | D7: AUSTRAL GROUP S.A.A | E7: CEMENTOS PACASMAYO | F7: CONSORCIO MINERO HORIZONTE S.R.L. | G7: CORPORACIÓN PESQUERA INCA S.A.C. | H7: CREDITEX: CIA IND.TEXTIL CREDISA | I7: HIPERMERCADOS TOTTUS S.A | J7: INDUSTRIA TEXTIL PIURA | K7: MINERA BOROO MISQUICHILCA S.A. | L7: MINERA GOLD FIELDS | M7: MINERA MARSA | N7: MINERA MISKY MAYO | O7: MINERA YANACOCHA | P7: OPEN PLAZA | Q7: PESQUERA DIAMANTE | R7: PETROPERU | S7: REAL PLAZA S.R.L. | T7: SIDER PERU | U7: SUPERMERCADOS PERUANOS S.A. | V7: TRUPAL S.A. | W7: UNIÓN DE CERVECERÍAS PERUANAS BACKUS Y JOHNSTON S. | X7: ACEROS AREQUIPA | Y7: ADMINISTRADORA JOCKEY PLAZA SHOPPING CENTER S.A. | Z7: ALICORP | AA7: ARCA CONTINENTAL LINDLEY S.A. | AB7: AUSTRAL GROUP S.A.A | AC7: COMPAÑIA MINERA CONDESTABLE | AD7: CORPORACIÓN PESQUERA INCA S.A.C. | AE7: CREDITEX: CIA IND.TEXTIL CREDISA | AF7: FUNDICION CHILCA S.A. | AG7: HIPERMERCADOS TOTTUS S.A | AH7: INMOBILIARIA KANPU S.A. | AI7: INMUEBLES PANAMERICANA S.A. | AJ7: KIMBERLY-CLARK PERU | AK7: LECHE GLORIA S.A. | AL7: MALL AVENTURA S.A. | AM7: MARCOBRE S.A.C. | AN7: MINERA ANTAMINA | AO7: MINERA ARES | AP7: MINERA BUENAVENTURA | AQ7: MINERA CHINALCO PERÚ S.A. | AR7: MINERA SHOUXIN PERU S.A. | AS7: MINERA VOLCAN | AT7: MINSUR | AU7: MOLYCOP-ADESUR | AV7: NEXA RESOURCES CAJAMARQUILLA S.A. | AW7: NEXA RESOURCES PERÚ S.A.A. | AX7: OPEN PLAZA | AY7: OPP FILM | AZ7: OWENS-ILLINOIS PERÚ S.A. | BA7: PAPELERA NACIONAL S.A. | BB7: PESQUERA DIAMANTE | BC7: QUIMPAC S.A. | BD7: REAL PLAZA S.R.L. | BE7: REFINERIA LA PAMPILLA S.A.A | BF7: SAGA FALABELLA | BG7: SAN MIGUEL INDUSTRIAS PET S.A. | BH7: SHOUGANG HIERRO PERU | BI7: SOFTYS PERU S.A.C. | BJ7: SUPERMERCADOS PERUANOS S.A. | BK7: TEJIDOS SAN JACINTO | BL7: TREN URBANO DE LIMA S.A. | BM7: TRUPAL S.A. | BN7: UNACEM PERU S.A. | BO7: UNIÓN DE CERVECERÍAS PERUANAS BACKUS Y JOHNSTON S. | BP7: ANGLO AMERICAN QUELLAVECO S.A. | BQ7: ARCA CONTINENTAL LINDLEY S.A. | BR7: CAL & CEMENTO SUR S.A. | BS7: COMPAÑIA MINERA ANTAPACCAY S.A. | BT7: COMPAÑÍA MINERA CHUNGAR SAC | BU7: COMPAÑIA MINERA SAN IGNACIO DE MOROCOCHA S.A.A. | BV7: EL BROCAL .S.A. | BW7: EMPRESA ADMINISTRADORA CERRO S.A.C. | BX7: EMPRESA MINERA LOS QUENUALES S.A.C. | BY7: HIPERMERCADOS TOTTUS S.A | BZ7: HUDBAY PERU S.A.C. | CA7: INDUSTRIA CACHIMAYO | CB7: MALL AVENTURA S.A. | CC7: MINERA ARES | CD7: MINERA BUENAVENTURA | CE7: MINERA CERRO VERDE | CF7: MINERA CORONA | CG7: MINERA LAS BAMBAS S.A. | CH7: MINERA VOLCAN | CI7: MINSUR | CJ7: MOLYCOP-ADESUR | CK7: NEXA RESOURCES PERÚ S.A.A. | CL7: OXIDOS DE PASCO S.A.C. | CM7: PESQUERA DIAMANTE | CN7: REAL PLAZA S.R.L. | CO7: SOBREANDES S.A.C. | CP7: SOUTHERN PERU CC | CQ7: SUPERMERCADOS PERUANOS S.A. | CR7: UNACEM PERU S.A. | CS7: UNIÓN DE CERVECERÍAS PERUANAS BACKUS Y JOHNSTON S. | CT7: YURA
B8: 00:30 | E8: 43.0482 | F8: 11.647 | L8: 25.7817 | M8: 13.56628 | N8: 9.47 | O8: 32.336 | R8: 44.943 | T8: 42.2076 | V8: 9.6 | X8: 147.67983 | AC8: 13.93 | AJ8: 5.33786 | AK8: 0 | AM8: 45.6721 | AN8: 132.14285 | AO8: 27.5132 | AP8: 0.81 | AQ8: 166.77113 | AR8: 26.28869 | AS8: 38.75145 | AT8: 32.42445 | AV8: 194.10523 | AW8: 36.82794 | BA8: 2.6 | BC8: 73.42588 | BE8: 20.5 | BI8: 16.284 | BN8: 23.802 | BO8: 1.93 | BP8: 142.70433 | BR8: 4.6387 | BS8: 133.69936 | BT8: 15.1459 | BV8: 33.8354 | BW8: 3.85819 | BZ8: 91.36338 | CA8: 24.78634 | CC8: 0.61 | CD8: 22.2991 | CE8: 362.76242 | CG8: 160.5021 | CH8: 18.15831 | CK8: 17.3458 | CL8: 5.12254 | CO8: 15.9955 | CP8: 290.11 | CR8: 26.915
B9: 01:00 | E9: 42.9197 | F9: 11.821 | L9: 26.1642 | M9: 13.30215 | N9: 9.14 | O9: 32.576 | R9: 44.369 | T9: 36.0265 | V9: 9.6 | X9: 139.64403 | AC9: 14 | AJ9: 5.33431 | AK9: 0 | AM9: 45.3581 | AN9: 129.23103 | AO9: 27.1259 | AP9: 0.7 | AQ9: 165.07702 | AR9: 25.879 | AS9: 39.11446 | AT9: 25.3239 | AV9: 195.84415 | AW9: 35.79586 | BA9: 2.6 | BC9: 73.63445 | BE9: 20.5 | BI9: 16.39013 | BN9: 23.936 | BO9: 1.93 | BP9: 139.92818 | BR9: 4.6459 | BS9: 132.16585 | BT9: 15.36778 | BV9: 34.0964 | BW9: 3.96348 | BZ9: 90.46869 | CA9: 24.80279 | CC9: 0.62 | CD9: 22.87995 | CE9: 357.8229 | CG9: 161.5923 | CH9: 18.2606 | CK9: 17.0419 | CL9: 5.11823 | CO9: 15.75526 | CP9: 287.89 | CR9: 24.819
B10: 01:30 | E10: 43.3049 | F10: 11.893 | L10: 26.2063 | M10: 14.2194 | N10: 9.14 | O10: 32.468 | R10: 44.461 | T10: 51.3906 | V10: 9.6 | X10: 119.00255 | AC10: 14.28 | AJ10: 5.31128 | AK10: 0 | AM10: 44.5599 | AN10: 129.77215 | AO10: 27.4699 | AP10: 0.64 | AQ10: 163.9563 | AR10: 26.19981 | AS10: 39.35731 | AT10: 25.55597 | AV10: 195.60474 | AW10: 35.55507 | BA10: 2.6 | BC10: 73.69849 | BE10: 20.5 | BI10: 16.39648 | BN10: 24.187 | BO10: 1.95 | BP10: 141.65989 | BR10: 4.6665 | BS10: 131.47635 | BT10: 15.57523 | BV10: 34.3652 | BW10: 4.0073 | BZ10: 90.98827 | CA10: 24.81073 | CC10: 0.61 | CD10: 23.31293 | CE10: 395.63372 | CG10: 162.8886 | CH10: 17.99424 | CK10: 17.8522 | CL10: 5.08262 | CO10: 16.02733 | CP10: 277.99 | CR10: 23.232
B11: 02:00 | E11: 43.0512 | F11: 11.7895 | L11: 26.1634 | M11: 14.6023 | N11: 9.47 | O11: 32.38 | R11: 44.34 | T11: 49.1309 | V11: 9 | X11: 110.78571 | AC11: 14.55 | AJ11: 5.27359 | AK11: 0 | AM11: 46.7118 | AN11: 130.18519 | AO11: 27.0458 | AP11: 0.44 | AQ11: 165.82606 | AR11: 26.67189 | AS11: 38.88532 | AT11: 26.16512 | AV11: 196.20402 | AW11: 35.81166 | BA11: 2.5 | BC11: 74.02584 | BE11: 20.5 | BI11: 16.4355 | BN11: 21.984 | BO11: 2 | BP11: 143.09898 | BR11: 4.6304 | BS11: 128.91533 | BT11: 16.01358 | BV11: 35.8649 | BW11: 3.7307 | BZ11: 90.28798 | CA11: 24.85772 | CC11: 0.6 | CD11: 24.87148 | CE11: 437.47329 | CG11: 155.0452 | CH11: 18.74529 | CK11: 17.4625 | CL11: 4.95638 | CO11: 15.59425 | CP11: 280.42 | CR11: 23.218
B12: 02:30 | E12: 43.4354 | F12: 11.686 | L12: 26.2594 | M12: 14.44397 | N12: 9.52 | O12: 32.29 | R12: 44.92 | T12: 52.4037 | V12: 8.8 | X12: 117.47364 | AC12: 14.57 | AJ12: 5.22184 | AK12: 0 | AM12: 46.0239 | AN12: 129.19503 | AO12: 27.7613 | AP12: 0.41 | AQ12: 166.2622 | AR12: 26.25826 | AS12: 38.93615 | AT12: 29.12305 | AV12: 199.53856 | AW12: 36.93509 | BA12: 2.6 | BC12: 74.03212 | BE12: 20.5 | BI12: 16.55975 | BN12: 19.278 | BO12: 2.05 | BP12: 142.09766 | BR12: 4.7844 | BS12: 130.75201 | BT12: 15.92162 | BV12: 35.8424 | BW12: 3.87202 | BZ12: 92.09253 | CA12: 24.80365 | CC12: 0.63 | CD12: 25.83055 | CE12: 454.95209 | CG12: 158.1428 | CH12: 18.57497 | CK12: 16.913 | CL12: 4.67981 | CO12: 15.80854 | CP12: 279.61 | CR12: 28.858
B13: 03:00 | E13: 43.6906 | F13: 11.728 | L13: 26.193 | M13: 14.50239 | N13: 9.53 | O13: 33.24 | R13: 44.86 | T13: 36.4482 | V13: 8.6 | X13: 165.58145 | AC13: 14.23 | AJ13: 4.81592 | AK13: 0 | AM13: 46.3462 | AN13: 133.89446 | AO13: 27.6005 | AP13: 0.67 | AQ13: 166.53184 | AR13: 26.28912 | AS13: 40.7993 | AT13: 30.29022 | AV13: 199.20753 | AW13: 34.72902 | BA13: 2.5 | BC13: 73.83201 | BE13: 20.5 | BI13: 16.56122 | BN13: 19.246 | BO13: 1.94 | BP13: 141.85665 | BR13: 4.6686 | BS13: 132.63209 | BT13: 15.37067 | BV13: 36.6157 | BW13: 3.96593 | BZ13: 92.31511 | CA13: 24.92078 | CC13: 0.6 | CD13: 25.3222 | CE13: 455.21829 | CG13: 157.7205 | CH13: 18.60092 | CK13: 17.2873 | CL13: 4.66537 | CO13: 15.34677 | CP13: 290.08 | CR13: 29.154
B14: 03:30 | E14: 43.3375 | F14: 12.382 | L14: 26.2225 | M14: 14.3286 | N14: 9.54 | O14: 33.328 | R14: 44.608 | T14: 44.9621 | V14: 8.7 | X14: 144.49619 | AC14: 14.18 | AJ14: 5.05719 | AK14: 0 | AM14: 46.557 | AN14: 133.66872 | AO14: 27.3426 | AP14: 0.48 | AQ14: 166.54954 | AR14: 26.73686 | AS14: 39.76241 | AT14: 31.76485 | AV14: 198.05548 | AW14: 35.21856 | BA14: 2.6 | BC14: 73.80429 | BE14: 20.5 | BI14: 16.23681 | BN14: 19.101 | BO14: 1.95 | BP14: 141.87954 | BR14: 4.5914 | BS14: 133.343 | BT14: 15.071 | BV14: 36.2161 | BW14: 4.02736 | BZ14: 91.88604 | CA14: 24.93249 | CC14: 0.6 | CD14: 24.89991 | CE14: 454.12945 | CG14: 153.618 | CH14: 18.00648 | CK14: 16.8769 | CL14: 4.68329 | CO14: 15.80428 | CP14: 280.01 | CR14: 29.704
B15: 04:00 | E15: 43.1952 | F15: 12.5025 | L15: 26.1429 | M15: 14.09013 | N15: 9.5 | O15: 32.97 | R15: 44.898 | T15: 50.609 | V15: 8.5 | X15: 140.06403 | AC15: 14.09 | AJ15: 5.19055 | AK15: 0 | AM15: 49.7446 | AN15: 132.08081 | AO15: 27.2867 | AP15: 0.18 | AQ15: 164.35938 | AR15: 26.58159 | AS15: 39.46582 | AT15: 32.57459 | AV15: 199.81674 | AW15: 35.83819 | BA15: 2.6 | BC15: 73.82298 | BE15: 20.5 | BI15: 16.32642 | BN15: 18.643 | BO15: 1.82 | BP15: 141.18487 | BR15: 4.6473 | BS15: 133.63761 | BT15: 14.23829 | BV15: 35.6477 | BW15: 3.88656 | BZ15: 90.94892 | CA15: 24.93445 | CC15: 0.62 | CD15: 24.98733 | CE15: 455.48476 | CG15: 152.162 | CH15: 18.25229 | CK15: 17.1127 | CL15: 5.0017 | CO15: 15.70779 | CP15: 282.91 | CR15: 29.024
B16: 04:30 | E16: 43.1064 | F16: 12.007 | L16: 26.5036 | M16: 14.88973 | N16: 9.52 | O16: 33.704 | R16: 45.394 | T16: 58.3962 | V16: 8.8 | X16: 101.22684 | AC16: 13.99 | AJ16: 5.28152 | AK16: 0 | AM16: 49.398 | AN16: 129.33787 | AO16: 27.3825 | AP16: 1.65 | AQ16: 167.99258 | AR16: 26.6033 | AS16: 39.304 | AT16: 31.76148 | AV16: 199.20882 | AW16: 34.93302 | BA16: 2.5 | BC16: 73.84405 | BE16: 20.5 | BI16: 16.42628 | BN16: 19.174 | BO16: 1.99 | BP16: 145.86109 | BR16: 4.6842 | BS16: 133.28043 | BT16: 11.78324 | BV16: 36.5852 | BW16: 3.90366 | BZ16: 90.89138 | CA16: 24.95741 | CC16: 0.6 | CD16: 24.81362 | CE16: 457.13402 | CG16: 154.098 | CH16: 18.26815 | CK16: 16.5458 | CL16: 5.03813 | CO16: 15.53019 | CP16: 290.27 | CR16: 31.923
B17: 05:00 | E17: 42.9133 | F17: 11.058 | L17: 25.9677 | M17: 15.05393 | N17: 9.52 | O17: 33.246 | R17: 45.146 | T17: 51.7047 | V17: 9.1 | X17: 107.54092 | AC17: 14.23 | AJ17: 5.03627 | AK17: 0 | AM17: 49.4184 | AN17: 130.59443 | AO17: 26.7539 | AP17: 2.1 | AQ17: 169.69287 | AR17: 26.25489 | AS17: 38.44598 | AT17: 31.65724 | AV17: 198.29727 | AW17: 35.50114 | BA17: 2.5 | BC17: 73.99456 | BE17: 20.5 | BI17: 16.42857 | BN17: 19.053 | BO17: 1.8 | BP17: 135.8661 | BR17: 4.6253 | BS17: 132.10686 | BT17: 12.75889 | BV17: 35.6432 | BW17: 4.37541 | BZ17: 91.09259 | CA17: 24.96285 | CC17: 0.62 | CD17: 23.77426 | CE17: 458.33551 | CG17: 141.0601 | CH17: 18.30825 | CK17: 16.3313 | CL17: 5.08341 | CO17: 15.38781 | CP17: 293.54 | CR17: 32.005
B18: 05:30 | E18: 43.4201 | F18: 10.471 | L18: 26.4705 | M18: 15.11905 | N18: 9.58 | O18: 31.824 | R18: 45.152 | T18: 44.8984 | V18: 9.7 | X18: 139.78684 | AC18: 14.33 | AJ18: 5.08865 | AK18: 0 | AM18: 50.2106 | AN18: 130.01127 | AO18: 26.9267 | AP18: 1.93 | AQ18: 169.18903 | AR18: 26.57358 | AS18: 36.70962 | AT18: 30.88305 | AV18: 199.62515 | AW18: 34.6792 | BA18: 2.6 | BC18: 73.93318 | BE18: 20.5 | BI18: 16.66839 | BN18: 19.459 | BO18: 1.78 | BP18: 122.49345 | BR18: 4.4501 | BS18: 130.659 | BT18: 13.54449 | BV18: 34.4443 | BW18: 3.85894 | BZ18: 92.34037 | CA18: 24.96101 | CC18: 0.58 | CD18: 23.75793 | CE18: 460.42279 | CG18: 141.075 | CH18: 17.4793 | CK18: 16.4968 | CL18: 4.92674 | CO18: 14.86558 | CP18: 291.1 | CR18: 32.578
B19: 06:00 | E19: 43.5357 | F19: 9.39 | L19: 26.2831 | M19: 15.25784 | N19: 9.6 | O19: 32.618 | R19: 45.683 | T19: 48.0343 | V19: 9.7 | X19: 95.52324 | AC19: 14.65 | AJ19: 5.10208 | AK19: 0 | AM19: 50.8281 | AN19: 133.76681 | AO19: 24.4228 | AP19: 1.54 | AQ19: 167.90056 | AR19: 26.58669 | AS19: 34.67507 | AT19: 31.43728 | AV19: 197.73421 | AW19: 33.20384 | BA19: 2.7 | BC19: 73.75231 | BE19: 20.5 | BI19: 16.58026 | BN19: 18.247 | BO19: 1.69 | BP19: 138.32718 | BR19: 4.4103 | BS19: 132.21803 | BT19: 13.22818 | BV19: 33.8823 | BW19: 3.65085 | BZ19: 91.25648 | CA19: 24.98183 | CC19: 0.6 | CD19: 23.29923 | CE19: 457.77098 | CG19: 135.0934 | CH19: 17.61236 | CK19: 16.4188 | CL19: 4.6314 | CO19: 14.39283 | CP19: 281.81 | CR19: 32.502
... B55: 00:00 | E55: 41.0687 | F55: 12.384 | L55: 26.1559 | M55: 13.49062 | N55: 11.8 | O55: 32.304 | R55: 51.188 | T55: 52.8528 | V55: 8.6 | X55: 128.13605 | AC55: 15.92 | AJ55: 5.27586 | AK55: 0 | AM55: 46.505 | AN55: 138.94406 | AO55: 27.6388 | AP55: 0.83 | AQ55: 163.87221 | AR55: 26.60738 | AS55: 37.57109 | AT55: 30.26187 | AV55: 195.07683 | AW55: 35.99083 | BA55: 1.9 | BC55: 50.3575 | BE55: 19.9 | BI55: 17.00262 | BN55: 23.847 | BO55: 2.08 | BP55: 142.98863 | BR55: 4.7627 | BS55: 136.36462 | BT55: 14.83889 | BV55: 36.0997 | BW55: 3.83695 | BZ55: 94.18877 | CA55: 24.94066 | CC55: 0.54 | CD55: 24.15158 | CE55: 459.52237 | CG55: 153.8559 | CH55: 17.7276 | CK55: 20.2245 | CL55: 5.05149 | CO55: 15.56118 | CP55: 292.83 | CR55: 24.528
B56: MWh | C56: 0 | D56: 0 | E56: 959.52315 | F56: 272.31425 | G56: 0 | H56: 0 | I56: 0 | J56: 0 | K56: 0 | L56: 644.65005 | M56: 310.76256 | N56: 236.055 | O56: 772.458 | P56: 0 | Q56: 0 | R56: 1110.4595 | S56: 0 | T56: 1052.0333 | U56: 0 | V56: 203.45 | W56: 0 | X56: 2198.7065 | Y56: 0 | Z56: 0 | AA56: 0 | AB56: 0 | AC56: 366.15 | AD56: 0 | AE56: 0 | AF56: 0 | AG56: 0 | AH56: 0 | AI56: 0 | AJ56: 118.96792 | AK56: 0 | AL56: 0 | AM56: 1125.8196 | AN56: 3194.5128 | AO56: 642.3253 | AP56: 18.01 | AQ56: 3678.0998 | AR56: 622.4724 | AS56: 891.35684 | AT56: 749.21512 | AU56: 0 | AV56: 4408.4256 | AW56: 825.68195 | AX56: 0 | AY56: 0 | AZ56: 0 | BA56: 47.2 | BB56: 0 | BC56: 1501.5654 | BD56: 0 | BE56: 483.1 | BF56: 0 | BG56: 0 | BH56: 0 | BI56: 401.22852 | BJ56: 0 | BK56: 0 | BL56: 0 | BM56: 0 | BN56: 419.3785 | BO56: 45.775 | BP56: 3380.3101 | BQ56: 0 | BR56: 110.25305 | BS56: 3132.5426 | BT56: 327.72887 | BU56: 0 | BV56: 811.22325 | BW56: 93.42783 | BX56: 0 | BY56: 0 | BZ56: 2197.3514 | CA56: 522.18745 | CB56: 0 | CC56: 14.215 | CD56: 545.17246 | CE56: 10878.275 | CF56: 0 | CG56: 3575.8604 | CH56: 333.08527 | CI56: 0 | CJ56: 0 | CK56: 407.1136 | CL56: 113.6847 | CM56: 0 | CN56: 0 | CO56: 361.71679 | CP56: 6770.275 | CQ56: 0 | CR56: 680.6725 | CS56: 0 | CT56: 0
B59: Nota :
B60: Información proporcionada por la empresas
C62: DATOS ESTIMADOS
C64: SIN DATOS

Sheet TIPO_RECURSO
B3: sábado, 26 de Julio del 2025
B5: REPORTE POTENCIA GENERADA POR TIPO DE RECURSO
B6: HORA | C6: H. PASADA | D6: H. REGULACION | E6: GAS DE CAMISEA | F6: GAS DE MALACAS | G6: GAS DE AGUAYTIA | H6: DIÉSEL | I6: RESIDUAL | J6: NAFTA+GAS DE REFINERIA | K6: FLEXIGAS+GAS DE REFINERIA | L6: BAGAZO | M6: BIOGÁS | N6: SOLAR | O6: EÓLICA | P6: TOTAL | U6: EMPRESA | V6: CENTRAL | W6: HIDROELECTRICA DE PASADA | X6: HIDROELECTRICA DE REGULACION
B7: 00:30 | C7: 832.1 | D7: 2381.3 | E7: 3057.9 | F7: 47.3 | G7: 67.2 | J7: =+DESPACHO_EJECUTADO!FD11+DESPACHO_EJECUTADO!FE11 -> 54.7 | L7: 50.8 | M7: 10.7 | N7: 0 | O7: 188.9 | P7: =+SUM(C7:O7) -> 6690.9 | U7: ANDEAN POWER S.A.C. | V7: C.H.CARHUAC | W7: 311.4
B8: 01:00 | C8: 833.1 | D8: 2177.6 | E8: 3092.2 | F8: 47.4 | G8: 40.4 | J8: =+DESPACHO_EJECUTADO!FD12+DESPACHO_EJECUTADO!FE12 -> 53.5 | L8: 50.3 | M8: 10.7 | N8: 0 | O8: 196.9 | P8: =+SUM(C8:O8) -> 6502.1 | U8: ASOCIACIÓN SANTA LUCIA DE CHACAS | V8: C.H. HUALLIN | W8: 32.4
B9: 01:30 | C9: 823.7 | D9: 2028.4 | E9: 3095.3 | F9: 47.3 | G9: 41.5 | J9: =+DESPACHO_EJECUTADO!FD13+DESPACHO_EJECUTADO!FE13 -> 54.4 | L9: 49.5 | M9: 10.7 | N9: 0 | O9: 206.8 | P9: =+SUM(C9:O9) -> 6357.6 | U9: ATRIA ENERGIA S.A.C. | V9: C.H. PURMACANA | W9: 9.5
B10: 02:00 | C10: 830.1 | D10: 2089.3 | E10: 3088.4 | F10: 47.5 | G10: 41.9 | J10: =+DESPACHO_EJECUTADO!FD14+DESPACHO_EJECUTADO!FE14 -> 54.1 | L10: 49 | M10: 10.7 | N10: 0 | O10: 194.5 | P10: =+SUM(C10:O10) -> 6405.5 | U10: CELEPSA | V10: C.H. EL PLATANAL | X10: 2146.8
B11: 02:30 | C11: 836.6 | D11: 1999.2 | E11: 3083.2 | F11: 47.2 | G11: 37.1 | J11: =+DESPACHO_EJECUTADO!FD15+DESPACHO_EJECUTADO!FE15 -> 53.9 | L11: 48.5 | M11: 10.7 | N11: 0 | O11: 227 | P11: =+SUM(C11:O11) -> 6343.4 | U11: CELEPSA RENOVABLES S.R.L. | V11: C.H. MARAÑON | W11: 300.45
B12: 03:00 | C12: 835.1 | D12: 2036.2 | E12: 3094.5 | F12: 47.5 | G12: 35.1 | J12: =+DESPACHO_EJECUTADO!FD16+DESPACHO_EJECUTADO!FE16 -> 56.7 | L12: 50.4 | M12: 10.7 | N12: 0 | O12: 184.2 | P12: =+SUM(C12:O12) -> 6350.4 | U12: CHINANGO S.A.C. | V12: C.H. CHIMAY | X12: 967.15
B13: 03:30 | C13: 818.8 | D13: 2030.3 | E13: 3100.2 | F13: 47.6 | G13: 35.6 | J13: =+DESPACHO_EJECUTADO!FD17+DESPACHO_EJECUTADO!FE17 -> 55.9 | L13: 50 | M13: 10.7 | N13: 0 | O13: 187.3 | P13: =+SUM(C13:O13) -> 6336.4 | V13: C.H. YANANGO | W13: 467.05
B14: 04:00 | C14: 826.9 | D14: 2010.5 | E14: 3098.2 | F14: 47.4 | G14: 29.6 | J14: =+DESPACHO_EJECUTADO!FD18+DESPACHO_EJECUTADO!FE18 -> 56.3 | L14: 49.2 | M14: 10.7 | N14: 0 | O14: 186.1 | P14: =+SUM(C14:O14) -> 6314.9 | U14: EGASA | V14: C.H. CHARCANI III | W14: 167.3
B15: 04:30 | C15: 826.8 | D15: 2062.1 | E15: 3085.4 | F15: 47.3 | G15: 27.2 | J15: =+DESPACHO_EJECUTADO!FD19+DESPACHO_EJECUTADO!FE19 -> 58.9 | L15: 50.1 | M15: 10.7 | N15: 0 | O15: 176.4 | P15: =+SUM(C15:O15) -> 6344.9 | V15: C.H. CHARCANI IV | X15: 283.8
B16: 05:00 | C16: 837.7 | D16: 1875.5 | E16: 3089.1 | F16: 46.7 | G16: 26.8 | J16: =+DESPACHO_EJECUTADO!FD20+DESPACHO_EJECUTADO!FE20 -> 59.2 | L16: 51.6 | M16: 10.7 | N16: 0 | O16: 192.5 | P16: =+SUM(C16:O16) -> 6189.8 | V16: C.H. CHARCANI V | X16: 1800.3
B17: 05:30 | C17: 839.9 | D17: 1904.7 | E17: 3079.1 | F17: 47 | G17: 27 | J17: =+DESPACHO_EJECUTADO!FD21+DESPACHO_EJECUTADO!FE21 -> 58.6 | L17: 50.6 | M17: 10.7 | N17: 0 | O17: 326.4 | P17: =+SUM(C17:O17) -> 6344 | U17: EGEJUNIN | V17: C.H. HUASAHUASI I | W17: 108.3
B18: 06:00 | C18: 832.5 | D18: 1861.3 | E18: 3078 | F18: 46.9 | G18: 27.2 | J18: =+DESPACHO_EJECUTADO!FD22+DESPACHO_EJECUTADO!FE22 -> 59.2 | L18: 51 | M18: 10.7 | N18: 0.1 | O18: 380.9 | P18: =+SUM(C18:O18) -> 6347.8 | V18: C.H. RUNATULLO II | W18: 82.6
B19: 06:30 | C19: 826.1 | D19: 1758.2 | E19: 3079.7 | F19: 46.8 | G19: 26.9 | J19: =+DESPACHO_EJECUTADO!FD23+DESPACHO_EJECUTADO!FE23 -> 58.3 | L19: 50.9 | M19: 10.7 | N19: 14.7 | O19: 379.7 | P19: =+SUM(C19:O19) -> 6252 | V19: C.H. RUNATULLO III | W19: 117.4
B20: 07:00 | C20: 816.5 | D20: 1838.1 | E20: 2975.8 | F20: 47.2 | G20: 27.4 | J20: =+DESPACHO_EJECUTADO!FD24+DESPACHO_EJECUTADO!FE24 -> 57.9 | L20: 52 | M20: 10.7 | N20: 165.4 | O20: 299.4 | P20: =+SUM(C20:O20) -> 6290.4 | V20: C.H. SANTA CRUZ I | W20: 21.2
B21: 07:30 | C21: 830.4 | D21: 2063.4 | E21: 2806.8 | F21: 46.8 | G21: 31.9 | J21: =+DESPACHO_EJECUTADO!FD25+DESPACHO_EJECUTADO!FE25 -> 58.4 | L21: 52 | M21: 10.7 | N21: 376.6 | O21: 205.4 | P21: =+SUM(C21:O21) -> 6482.4 | U21: EGEMSA | V21: C.H. MACHUPICCHU | W21: 2598.45
B22: 08:00 | C22: 805.6 | D22: 1925.2 | E22: 2887.5 | F22: 47.1 | G22: 34.2 | J22: =+DESPACHO_EJECUTADO!FD26+DESPACHO_EJECUTADO!FE26 -> 58.6 | L22: 51.2 | M22: 10.7 | N22: 539.1 | O22: 179.9 | P22: =+SUM(C22:O22) -> 6539.1 | U22: EGESUR | V22: C.H. ARICOTA I | X22: 180.45
B23: 08:30 | C23: 818.4 | D23: 1975.3 | E23: 3033 | F23: 46.7 | G23: 39.5 | J23: =+DESPACHO_EJECUTADO!FD27+DESPACHO_EJECUTADO!FE27 -> 58 | L23: 50.4 | M23: 10.7 | N23: 570 | O23: 193.7 | P23: =+SUM(C23:O23) -> 6795.7 | V23: C.H. ARICOTA II | X23: 120.1
B24: 09:00 | C24: 817.7 | D24: 2013.3 | E24: 3040 | F24: 46.6 | G24: 44.4 | J24: =+DESPACHO_EJECUTADO!FD28+DESPACHO_EJECUTADO!FE28 -> 58.2 | L24: 50.8 | M24: 10.6 | N24: 584 | O24: 239.1 | P24: =+SUM(C24:O24) -> 6904.7 | U24: ELECTRICA YANAPAMPA SAC | V24: C.H. YANAPAMPA | W24: 49.35
B25: 09:30 | C25: 826 | D25: 2164.5 | E25: 3105.4 | F25: 46.7 | G25: 50.3 | J25: =+DESPACHO_EJECUTADO!FD29+DESPACHO_EJECUTADO!FE29 -> 57.9 | L25: 49.6 | M25: 10.6 | N25: 592.1 | O25: 218.9 | P25: =+SUM(C25:O25) -> 7122 | U25: ELECTROPERU | V25: C.H. MANTARO | X25: 14697.5
B26: 10:00 | C26: 829.4 | D26: 2197.2 | E26: 3096.5 | F26: 46.3 | G26: 55 | J26: =+DESPACHO_EJECUTADO!FD30+DESPACHO_EJECUTADO!FE30 -> 58.4 | L26: 49 | M26: 10.6 | N26: 593 | O26: 263.1 | P26: =+SUM(C26:O26) -> 7198.5 | V26: C.H. RESTITUCION | W26: 4972.2
B27: 10:30 | C27: 818.6 | D27: 2135.3 | E27: 3075.7 | F27: 45.9 | G27: 52.9 | J27: =+DESPACHO_EJECUTADO!FD31+DESPACHO_EJECUTADO!FE31 -> 58.4 | L27: 50.3 | M27: 10.6 | N27: 594.8 | O27: 292.7 | P27: =+SUM(C27:O27) -> 7135.2 | U27: EMPRESA DE GENERACION ELECTRICA CANCHAYLLO SAC | V27: C.H. CANCHAYLLO | W27: 46
B28: 11:00 | C28: 823.6 | D28: 2127.9 | E28: 3155.2 | F28: 45.6 | G28: 58.8 | J28: =+DESPACHO_EJECUTADO!FD32+DESPACHO_EJECUTADO!FE32 -> 58 | L28: 48.7 | M28: 10.6 | N28: 594.7 | O28: 320.7 | P28: =+SUM(C28:O28) -> 7243.8 | U28: EMPRESA DE GENERACION ELECTRICA RIO BAÑOS S.A.C. | V28: C.H. RUCUY | W28: 329.7
B29: 11:30 | C29: 818.2 | D29: 2082.4 | E29: 3135.9 | F29: 45.4 | G29: 63.4 | J29: =+DESPACHO_EJECUTADO!FD33+DESPACHO_EJECUTADO!FE33 -> 57.6 | L29: 47.8 | M29: 10.6 | N29: 597.7 | O29: 361.6 | P29: =+SUM(C29:O29) -> 7220.6 | U29: EMPRESA DE GENERACION ELECTRICA SANTA ANA S.A.C. | V29: C.H. RENOVANDES H1 | W29: 441.8
B30: 12:00 | C30: 839 | D30: 2072.5 | E30: 3151.2 | F30: 45.2 | G30: 66.4 | J30: =+DESPACHO_EJECUTADO!FD34+DESPACHO_EJECUTADO!FE34 -> 58.3 | L30: 47.6 | M30: 10.5 | N30: 599.7 | O30: 387.7 | P30: =+SUM(C30:O30) -> 7278.1 | U30: EMPRESA DE GENERACION HUALLAGA | V30: C.H. CHAGLLA | X30: 1009.2
B31: 12:30 | C31: 813.5 | D31: 1903.7 | E31: 3136.5 | F31: 44.8 | G31: 63.3 | J31: =+DESPACHO_EJECUTADO!FD35+DESPACHO_EJECUTADO!FE35 -> 58.1 | L31: 47.4 | M31: 10.5 | N31: 603.1 | O31: 444.5 | P31: =+SUM(C31:O31) -> 7125.4 | V31: P.C.H. CHAGLLA | W31: 155.5
B32: 13:00 | C32: 819.8 | D32: 1768.6 | E32: 3215 | F32: 45.4 | G32: 63.6 | J32: =+DESPACHO_EJECUTADO!FD36+DESPACHO_EJECUTADO!FE36 -> 58.2 | L32: 47.8 | M32: 10.5 | N32: 606.8 | O32: 499.7 | P32: =+SUM(C32:O32) -> 7135.4 | U32: EMPRESA DE GENERACION HUANZA | V32: C.H. HUANZA | X32: 1179.7
B33: 13:30 | C33: 812.5 | D33: 1575.3 | E33: 3201.6 | F33: 45.2 | G33: 64.1 | J33: =+DESPACHO_EJECUTADO!FD37+DESPACHO_EJECUTADO!FE37 -> 57.2 | L33: 47.9 | M33: 10.5 | N33: 603.5 | O33: 638.5 | P33: =+SUM(C33:O33) -> 7056.3 | U33: EMPRESA ELECTRICA AGUA AZUL | V33: C.H. POTRERO | W33: 172.15
B34: 14:00 | C34: 800 | D34: 1574.2 | E34: 3114 | F34: 45.2 | G34: 64.4 | J34: =+DESPACHO_EJECUTADO!FD38+DESPACHO_EJECUTADO!FE38 -> 57.4 | L34: 45.6 | M34: 10.5 | N34: 601.5 | O34: 733.8 | P34: =+SUM(C34:O34) -> 7046.6 | U34: EMPRESA ELECTRICA RIO DOBLE | V34: C.H. LAS PIZARRAS | W34: 101
B35: 14:30 | C35: 823.1 | D35: 1455.8 | E35: 3176.2 | F35: 45.5 | G35: 65 | J35: =+DESPACHO_EJECUTADO!FD39+DESPACHO_EJECUTADO!FE39 -> 57.3 | L35: 47.5 | M35: 10.5 | N35: 602.2 | O35: 789.9 | P35: =+SUM(C35:O35) -> 7073 | U35: ENGIE | V35: C.H. YUNCAN | X35: 1419.5
B36: 15:00 | C36: 814.4 | D36: 1427.1 | E36: 3175.6 | F36: 45.9 | G36: 63.4 | J36: =+DESPACHO_EJECUTADO!FD40+DESPACHO_EJECUTADO!FE40 -> 55.9 | L36: 47.9 | M36: 10.5 | N36: 597.2 | O36: 839.5 | P36: =+SUM(C36:O36) -> 7077.4 | U36: GENERACIÓN ANDINA S.A.C. | V36: C.H. 8 DE AGOSTO | W36: 120.65
B37: 15:30 | C37: 783 | D37: 1417.5 | E37: 3164.2 | F37: 46.4 | G37: 63.4 | J37: =+DESPACHO_EJECUTADO!FD41+DESPACHO_EJECUTADO!FE41 -> 57 | L37: 46 | M37: 10.5 | N37: 573.2 | O37: 870.3 | P37: =+SUM(C37:O37) -> 7031.5 | V37: C.H. EL CARMEN | W37: 51.25
B38: 16:00 | C38: 782.6 | D38: 1453 | E38: 3171.9 | F38: 46.1 | G38: 65.2 | J38: =+DESPACHO_EJECUTADO!FD42+DESPACHO_EJECUTADO!FE42 -> 58.5 | L38: 45.4 | M38: 10.5 | N38: 494.1 | O38: 879.8 | P38: =+SUM(C38:O38) -> 7007.1 | U38: GENERADORA DE ENERGÍA DEL PERÚ | V38: C.H. ÁNGEL I | W38: 87.3
B39: 16:30 | C39: 791.5 | D39: 1644.3 | E39: 3163.8 | F39: 45.6 | G39: 63.9 | J39: =+DESPACHO_EJECUTADO!FD43+DESPACHO_EJECUTADO!FE43 -> 60.4 | L39: 46.2 | M39: 10.5 | N39: 298.7 | O39: 853 | P39: =+SUM(C39:O39) -> 6977.9 | V39: C.H. ÁNGEL II | W39: 98.9
B40: 17:00 | C40: 795.5 | D40: 1771.7 | E40: 3178.6 | F40: 46.1 | G40: 63.1 | J40: =+DESPACHO_EJECUTADO!FD44+DESPACHO_EJECUTADO!FE44 -> 60.2 | L40: 45.4 | M40: 10.5 | N40: 94.5 | O40: 875.7 | P40: =+SUM(C40:O40) -> 6941.3 | V40: C.H. ÁNGEL III | W40: 100.6
B41: 17:30 | C41: 773.7 | D41: 1923 | E41: 3184.9 | F41: 46.3 | G41: 64.1 | J41: =+DESPACHO_EJECUTADO!FD45+DESPACHO_EJECUTADO!FE45 -> 60.4 | L41: 48 | M41: 10.6 | N41: 2.6 | O41: 847.8 | P41: =+SUM(C41:O41) -> 6961.4 | V41: C.H. LA JOYA | W41: 186.2
B42: 18:00 | C42: 781.5 | D42: 1885.1 | E42: 3185.9 | F42: 46.3 | G42: 64.1 | J42: =+DESPACHO_EJECUTADO!FD46+DESPACHO_EJECUTADO!FE46 -> 60.4 | L42: 48.1 | M42: 10.6 | N42: 0 | O42: 846.3 | P42: =+SUM(C42:O42) -> 6928.3 | U42: HIDROCAÑETE S.A. | V42: C.H. IMPERIAL | W42: 80.55
B43: 18:30 | C43: 789.6 | D43: 2112.4 | E43: 3278.5 | F43: 46.3 | G43: 79.4 | J43: =+DESPACHO_EJECUTADO!FD47+DESPACHO_EJECUTADO!FE47 -> 61.8 | L43: 48.4 | M43: 10.6 | N43: 0 | O43: 851.7 | P43: =+SUM(C43:O43) -> 7278.7 | U43: HIDROELECTRICA HUANCHOR S.A.C. | V43: C.H. HUANCHOR | W43: 446.15
B44: 19:00 | C44: 835.1 | D44: 2106.7 | E44: 3290.8 | F44: 46.6 | G44: 79.5 | J44: =+DESPACHO_EJECUTADO!FD48+DESPACHO_EJECUTADO!FE48 -> 62.7 | L44: 49.7 | M44: 10.6 | N44: 0 | O44: 855 | P44: =+SUM(C44:O44) -> 7336.7 | U44: HUAURA POWER GROUP S.A. | V44: C.H. YARUCAYA | W44: 444
B45: 19:30 | C45: 830.2 | D45: 2137.3 | E45: 3296.2 | F45: 47.1 | G45: 79.7 | J45: =+DESPACHO_EJECUTADO!FD49+DESPACHO_EJECUTADO!FE49 -> 62.2 | L45: 49.9 | M45: 10.6 | N45: 0 | O45: 846 | P45: =+SUM(C45:O45) -> 7359.2 | U45: HYDRO GLOBAL PERÚ S.A.C. | V45: CH SAN GABAN III | X45: 1777.3
B46: 20:00 | C46: 831.4 | D46: 2066.6 | E46: 3302.7 | F46: 46.8 | G46: 78.3 | J46: =+DESPACHO_EJECUTADO!FD50+DESPACHO_EJECUTADO!FE50 -> 62.6 | L46: 50.5 | M46: 10.6 | N46: 0.1 | O46: 845.3 | P46: =+SUM(C46:O46) -> 7294.9 | U46: INLAND ENERGY SAC | V46: C.H. SANTA TERESA | W46: 1359.6328
B47: 20:30 | C47: 833.7 | D47: 2256.6 | E47: 3164.1 | F47: 46.8 | G47: 78.8 | J47: =+DESPACHO_EJECUTADO!FD51+DESPACHO_EJECUTADO!FE51 -> 62.8 | L47: 49.6 | M47: 10.6 | N47: 0.1 | O47: 785.7 | P47: =+SUM(C47:O47) -> 7288.8 | U47: INVERSIONES SHAQSHA S.A.C. | V47: C.H. PARIAC | W47: 26.2
B48: 21:00 | C48: 827.6 | D48: 2154.8 | E48: 3240.7 | F48: 47 | G48: 78.7 | J48: =+DESPACHO_EJECUTADO!FD52+DESPACHO_EJECUTADO!FE52 -> 62.8 | L48: 50.4 | M48: 10.6 | N48: 0.1 | O48: 799.7 | P48: =+SUM(C48:O48) -> 7272.4 | U48: KALLPA GENERACION S.A. | V48: C.H. CERRO DEL AGUILA | X48: 7540.25
B49: 21:30 | C49: 831.9 | D49: 1970.6 | E49: 3389.8 | F49: 47.2 | G49: 78.8 | J49: =+DESPACHO_EJECUTADO!FD53+DESPACHO_EJECUTADO!FE53 -> 63.7 | L49: 49.2 | M49: 10.6 | N49: 0 | O49: 815 | P49: =+SUM(C49:O49) -> 7256.8 | V49: M.C.H. CERRO DEL AGUILA | W49: 100.1
B50: 22:00 | C50: 825.9 | D50: 1926.8 | E50: 3355.9 | F50: 47.4 | G50: 70.1 | J50: =+DESPACHO_EJECUTADO!FD54+DESPACHO_EJECUTADO!FE54 -> 63.4 | L50: 49.2 | M50: 10.6 | N50: 0 | O50: 837.3 | P50: =+SUM(C50:O50) -> 7186.6 | U50: LA VIRGEN | V50: C.H. LA VIRGEN | X50: 724.7
B51: 22:30 | C51: 830.3 | D51: 2175.8 | E51: 3134.2 | F51: 47.3 | G51: 50.1 | J51: =+DESPACHO_EJECUTADO!FD55+DESPACHO_EJECUTADO!FE55 -> 65.1 | L51: 50.4 | M51: 10.6 | N51: 0 | O51: 817.3 | P51: =+SUM(C51:O51) -> 7181.1 | U51: MAJA ENERGIA S.A.C. | V51: C.H. RONCADOR | W51: 36
B52: 23:00 | C52: 835.34 | D52: 2061.1 | E52: 2990.5 | F52: 47 | G52: 47.3 | J52: =+DESPACHO_EJECUTADO!FD56+DESPACHO_EJECUTADO!FE56 -> 64.8 | L52: 50.5 | M52: 10.6 | N52: 0 | O52: 837.6 | P52: =+SUM(C52:O52) -> 6944.74 | U52: ORAZUL ENERGY PERÚ | V52: C.H. CAÑA BRAVA | W52: 48.8
B53: 23:30 | C53: 833.9593 | D53: 2115.7 | E53: 2795 | F53: 47.5 | G53: 49.3 | J53: =+DESPACHO_EJECUTADO!FD57+DESPACHO_EJECUTADO!FE57 -> 64.8 | L53: 50.5 | M53: 10.6 | N53: 0 | O53: 800.1 | P53: =+SUM(C53:O53) -> 6767.4593 | V53: C.H. CAÑON DEL PATO | X53: 1977.45
B54: 00:00 | C54: 837.0663 | D54: 2169.5 | E54: 2603.9 | F54: 47.3 | G54: 50.2 | J54: =+DESPACHO_EJECUTADO!FD58+DESPACHO_EJECUTADO!FE58 -> 64.6 | L54: 50.3 | M54: 10.6 | N54: 0 | O54: 737 | P54: =+SUM(C54:O54) -> 6570.4663 | V54: C.H. CARHUAQUERO | X54: 582.65
B55: TOTAL MWh | C55: =+SUM(C7:C54)/2 -> 19687.983 | D55: =+SUM(D7:D54)/2 -> 46931.45 | E55: =+SUM(E7:E54)/2 -> 74747.35 | F55: =+SUM(F7:F54)/2 -> 1118.25 | G55: =+SUM(G7:G54)/2 -> 1287.75 | H55: =+SUM(H7:H54)/2 -> 0 | I55: =+SUM(I7:I54)/2 -> 0 | J55: =+SUM(J7:J54)/2 -> 1417.85 | ... P55: =+SUM(P7:P54)/2 -> 164544.83 | V55: C.H. CARHUAQUERO IV | W55: 203.15
B56: % | C56: =+C55*100/$P$55 -> 11.965118 | D56: =+D55*100/$P$55 -> 28.521983 | E56: =+E55*100/$P$55 -> 45.426738 | F56: =+F55*100/$P$55 -> 0.67960202 | G56: =+G55*100/$P$55 -> 0.78261345 | H56: =+H55*100/$P$55 -> 0 | I56: =+I55*100/$P$55 -> 0 | J56: =+J55*100/$P$55 -> 0.86168005 | ... O56: =+O55*100/$P$55 -> 7.5773574 | P56: 100.00 | U56: ORYGEN PERU S.A.A. | V56: C.H. CALLAHUANCA | X56: 1737.4
V57: C.H. HER 1 | W57: 14.4
V58: C.H. HUAMPANI | W58: 698.7
V59: C.H. HUINCO | X59: 2600.45
V60: C.H. MATUCANA | X60: 2251.15
V61: C.H. MOYOPAMPA | W61: 1530.8
U62: PERUANA DE INVERSIONES EN ENERGIAS RENOVABLES S.A. | V62: C.H. MANTA I | W62: 177.25
U63: SAN GABAN | V63: C.H. SAN GABAN II | X63: 1472.55
V64: PCH TUPURI | W64: 6.7
U65: SINERSA | V65: C.H. CHANCAY | W65: 444.5
V66: C.H. POECHOS II | W66: 160.6
U67: STATKRAFT S.A | V67: C.H. ARCATA | W67: 47.65
V68: C.H. CAHUA | W68: 747.25
V69: C.H. CHEVES | X69: 1536.4
V70: C.H. GALLITO CIEGO | X70: 219.55
V71: C.H. MALPASO | X71: 707.1
V72: C.H. OROYA | W72: 114.7
V73: C.H. PACHACHACA | W73: 16.9
V74: C.H. YAUPI | W74: 1732.4
U75: VARI ENERGIA S.A.C. | V75: C.H. ANASHIRONI | W75: 122.9
U76: TOTAL MWh | W76: 19687.983 | X76: 46931.45

Sheet GENERACION RER
B3: sábado, 26 de Julio del 2025
B5: GENERACIÓN ELÉCTRICA DE LAS CENTRALES RER (MW)
B6: HORA | C6: AGRO INDUSTRIAL PARAMONGA S.A. | D6: AGROAURORA S.A.C. | E6: AGROINDUSTRIAS SAN JACINTO S.A.A. | F6: ANDEAN POWER S.A.C. | G6: ASOCIACIÓN SANTA LUCIA DE CHACAS | H6: ATRIA ENERGIA S.A.C. | I6: BIOENERGIA DEL CHIRA S.A. | J6: COLCA SOLAR S.A.C. | K6: EGEJUNIN | P6: ELECTRICA YANAPAMPA SAC | Q6: EMPRESA DE GENERACION ELECTRICA CANCHAYLLO SAC | R6: EMPRESA DE GENERACION ELECTRICA RIO BAÑOS S.A.C. | S6: EMPRESA DE GENERACION ELECTRICA SANTA ANA S.A.C. | T6: EMPRESA ELECTRICA AGUA AZUL | U6: EMPRESA ELECTRICA RIO DOBLE | V6: ENERGÍA EÓLICA S.A. | X6: ENERGIA RENOVABLE DEL SUR S.A. | Y6: ENGIE | AD6: GENERACIÓN ANDINA S.A.C. | AF6: GENERADORA DE ENERGÍA DEL PERÚ | AJ6: GR CORTARRAMA SOCIEDAD ANONIMA CERRADA | AK6: GR PAINO SOCIEDAD ANONIMA CERRADA | AL6: GR TARUCA SOCIEDAD ANONIMA CERRADA | AM6: HIDROCAÑETE S.A. | AN6: HUAURA POWER GROUP S.A. | AO6: HYDRO PATAPO S.A.C. | AP6: JOYA SOLAR S.A.C. | AQ6: KONDU SAC | AR6: MAJA ENERGIA S.A.C. | AS6: MAJES ARCUS S.A.C. | AT6: MOQUEGUA FV S.A.C. | AU6: ORAZUL ENERGY PERÚ | AW6: ORYGEN PERU S.A.A. | BB6: PANAMERICANA SOLAR SAC. | BC6: PARQUE EOLICO MARCONA S.A.C. | BD6: PARQUE EOLICO TRES HERMANAS S.A.C. | BE6: PERUANA DE INVERSIONES EN ENERGIAS RENOVABLES S.A. | BF6: PETRAMAS | BJ6: REPARTICIÓN ARCUS S.A.C. | BK6: SAN GABAN | BL6: SDF ENERGIA SAC | BM6: SINERSA | BO6: TACNA SOLAR SAC. | BP6: VARI ENERGIA S.A.C. | BQ6: TOTAL RER
C7: C.T. PARAMONGA | D7: C.T. MAPLE | E7: C.T SAN JACINTO | F7: C.H. CARHUAC | G7: C.H. HUALLIN | H7: C.H. PURMACANA | I7: C.T. CAÑA BRAVA | K7: C.H. HUASAHUASI I | L7: C.H. HUASAHUASI II | M7: C.H. RUNATULLO II | N7: C.H. RUNATULLO III | O7: C.H. STA CRUZ I y II | P7: C.H. YANAPAMPA | Q7: C.H. CANCHAYLLO | R7: C.H. RUCUY | S7: C.H. RENOVANDES H1 | T7: C.H. POTRERO | U7: C.H. LAS PIZARRAS | AD7: C.H. 8 DE AGOSTO | AE7: C.H. EL CARMEN | AF7: C.H. ANGEL I | AG7: C.H. ANGEL II | AH7: C.H. ANGEL III | AI7: C.H. LA JOYA | AM7: C.H. NUEVAIMPERIAL | AN7: C.H. YARUCAYA | AO7: MCH PATAPO | AR7: C.H. RONCADOR | AU7: C.H. CANA BRAVA | AV7: C.H. CARHUAQUERO4 | BA7: C.H. HER 1 | BE7: C.H. MANTA | BF7: C.T. HUAYCOLORO | BG7: C.T. LA GRINGA V | BH7: CTB CALLAO | BI7: CTB. DONA CATALINA | BK7: C.H. TUPURI | BL7: C.T. OQUENDO | BM7: C.H. CHANCAY | BN7: C.H. POECHOS2 | BP7: C.H. ANASHIRONI | BQ7: MW
B8: 0:30 | C8: 14.5 | D8: 19 | E8: 8.4 | F8: 7.2 | G8: 1.5 | H8: 0.4 | I8: 8.9 | K8: 4 | M8: 3.4 | N8: 4.7 | O8: 3.9 | P8: 1.9 | Q8: 1.9 | R8: 11 | S8: 18.5 | T8: 7.2 | U8: 4 | V8: 11.8 | W8: 20.8 | X8: 15.9 | Z8: 28 | AA8: 44.6 | AB8: 2.8 | AC8: 1.4 | AD8: 5 | AE8: 2 | AF8: 3.8 | AG8: 4.4 | AH8: 4.6 | AI8: 7.4 | AK8: 5.1 | AL8: 9 | AM8: 3.4 | AN8: 18.5 | AR8: 1.5 | AU8: 4.9 | AV8: 9.9 | AW8: 18.3 | AY8: 10.4 | BA8: 0.6 | BC8: 5 | BD8: 15.8 | BE8: 7.4 | BF8: 4.5 | BG8: 2.6 | BH8: 1.2 | BI8: 2.4 | BK8: 0.3 | BM8: 19.7 | BN8: 6.6 | BP8: 5 | BQ8: 425
B9: 1:00 | C9: 14.2 | D9: 19.1 | E9: 7.6 | F9: 7.7 | G9: 1.4 | H9: 0.4 | I9: 9.4 | K9: 4 | M9: 3.3 | N9: 4.7 | O9: 4 | P9: 1.9 | Q9: 1.9 | R9: 10 | S9: 18.4 | T9: 7.2 | U9: 4 | V9: 13.9 | W9: 20.3 | X9: 14.6 | Z9: 31.1 | AA9: 45.9 | AB9: 4.1 | AC9: 2.5 | AD9: 5 | AE9: 2 | AF9: 3.8 | AG9: 4.4 | AH9: 4.6 | AI9: 7.4 | AK9: 5.8 | AL9: 7.1 | AM9: 3.4 | AN9: 18.5 | AR9: 1.5 | AU9: 4.9 | AV9: 9.9 | AW9: 20.1 | AY9: 16.5 | BA9: 0.6 | BC9: 3.2 | BD9: 11.8 | BE9: 7.4 | BF9: 4.5 | BG9: 2.6 | BH9: 1.2 | BI9: 2.4 | BK9: 0.3 | BM9: 20 | BN9: 6.6 | BP9: 5.1 | BQ9: 432.2
B10: 1:30 | C10: 13.7 | D10: 19.1 | E10: 7.4 | F10: 10.3 | G10: 1.5 | H10: 0.4 | I10: 9.3 | K10: 4 | M10: 3.2 | N10: 4.6 | O10: 3.9 | P10: 1.9 | Q10: 1.8 | R10: 10 | S10: 18.6 | T10: 7.2 | U10: 4 | V10: 16.3 | W10: 18.8 | X10: 13.4 | Z10: 37.3 | AA10: 55.3 | AB10: 3.7 | AC10: 2.7 | AD10: 5 | AE10: 2 | AF10: 3.8 | AG10: 4.4 | AH10: 4.5 | AI10: 7.4 | AK10: 3 | AL10: 5.7 | AM10: 3.4 | AN10: 18.5 | AR10: 1.5 | AU10: 0.6 | AW10: 17.2 | AY10: 20.6 | BA10: 0.6 | BC10: 3.1 | BD10: 9.7 | BE10: 7.3 | BF10: 4.5 | BG10: 2.6 | BH10: 1.2 | BI10: 2.4 | BK10: 0.3 | BM10: 20 | BN10: 6.7 | BP10: 5.1 | BQ10: 429.5
B11: 2:00 | C11: 13.5 | D11: 19.1 | E11: 7.4 | F11: 10.3 | G11: 1.4 | H11: 0.4 | I11: 9 | K11: 4 | M11: 3.5 | N11: 4.8 | O11: 4 | P11: 1.8 | Q11: 1.9 | R11: 13.7 | S11: 18.6 | T11: 7.2 | U11: 4 | V11: 15.4 | W11: 19.3 | X11: 9.9 | Z11: 35.8 | AA11: 49.2 | AB11: 3.8 | AC11: 2.4 | AD11: 5 | AE11: 2 | AF11: 3.8 | AG11: 4.4 | AH11: 4.5 | AI11: 7.4 | AK11: 2.9 | AL11: 4.6 | AM11: 3.4 | AN11: 18.5 | AR11: 1.5 | AW11: 19.8 | AY11: 17.3 | BA11: 0.6 | BC11: 3.6 | BD11: 10.5 | BE11: 7.4 | BF11: 4.5 | BG11: 2.6 | BH11: 1.2 | BI11: 2.4 | BK11: 0.3 | BM11: 20 | BN11: 6.7 | BP11: 5.1 | BQ11: 420.4
B12: 2:30 | C12: 14.1 | D12: 19 | E12: 6.7 | F12: 10.3 | G12: 1.4 | H12: 0.4 | I12: 8.7 | K12: 4 | M12: 3.6 | N12: 5 | O12: 4 | P12: 1.8 | Q12: 2.1 | R12: 14 | S12: 18.9 | T12: 7.2 | U12: 4 | V12: 18.3 | W12: 20.5 | X12: 8.6 | Z12: 37.4 | AA12: 52.7 | AB12: 3.9 | AC12: 3.9 | AD12: 5 | AE12: 2 | AF12: 3.6 | AG12: 4.4 | AH12: 4.3 | AI12: 7.7 | AK12: 4.9 | AL12: 7.9 | AM12: 3.4 | AN12: 18.5 | AR12: 1.5 | AW12: 31.9 | AY12: 24.7 | BA12: 0.6 | BC12: 3 | BD12: 9.3 | BE12: 7.4 | BF12: 4.5 | BG12: 2.6 | BH12: 1.2 | BI12: 2.4 | BK12: 0.3 | BM12: 18.8 | BN12: 6.7 | BP12: 5.1 | BQ12: 452.2
B13: 3:00 | C13: 14 | D13: 19.1 | E13: 8 | F13: 10.3 | G13: 1.4 | H13: 0.4 | I13: 9.3 | K13: 4 | M13: 3.5 | N13: 4.9 | O13: 4 | P13: 1.9 | Q13: 2.1 | R13: 13.6 | S13: 18.8 | T13: 7.2 | U13: 4 | V13: 20.1 | W13: 17 | X13: 12 | Z13: 26.4 | AA13: 40.9 | AB13: 2.2 | AC13: 1.2 | AD13: 5 | AE13: 2 | AF13: 3.6 | AG13: 4.4 | AH13: 4.3 | AI13: 7.6 | AK13: 4.2 | AL13: 7 | AM13: 3.4 | AN13: 18.5 | AR13: 1.5 | AW13: 19.1 | AY13: 18 | BA13: 0.6 | BC13: 2.9 | BD13: 13.2 | BE13: 7.4 | BF13: 4.5 | BG13: 2.6 | BH13: 1.2 | BI13: 2.4 | BK13: 0.3 | BM13: 18.7 | BN13: 6.6 | BP13: 5.2 | BQ13: 410.5
B14: 3:30 | C14: 13.5 | D14: 19.1 | E14: 8 | F14: 10.3 | G14: 1.4 | H14: 0.4 | I14: 9.4 | K14: 4 | M14: 3.5 | N14: 4.8 | O14: 4 | P14: 2.3 | Q14: 2.1 | R14: 13.6 | S14: 18.9 | T14: 7.2 | U14: 4 | V14: 19.6 | W14: 18.4 | X14: 20.4 | Z14: 26.2 | AA14: 40.6 | AB14: 3 | AC14: 2.4 | AD14: 5 | AE14: 2 | AF14: 3.6 | AG14: 4.4 | AH14: 4.1 | AI14: 7.6 | AK14: 4.2 | AL14: 8.1 | AM14: 3.4 | AN14: 18.5 | AR14: 1.5 | AW14: 7.7 | AY14: 11.9 | BA14: 0.6 | BC14: 5 | BD14: 19.8 | BE14: 7.4 | BF14: 4.5 | BG14: 2.6 | BH14: 1.2 | BI14: 2.4 | BK14: 0.3 | BM14: 18.7 | BN14: 6.8 | BP14: 5 | BQ14: 413.4
B15: 4:00 | C15: 13.6 | D15: 19.1 | E15: 8.2 | F15: 10.3 | G15: 1.4 | H15: 0.4 | I15: 8.3 | K15: 4 | M15: 3.6 | N15: 4.9 | O15: 4 | P15: 2.3 | Q15: 2.1 | R15: 13.8 | S15: 18.8 | T15: 7.2 | U15: 4 | V15: 18.7 | W15: 12.9 | X15: 17.9 | Z15: 25.9 | AA15: 49.7 | AB15: 2.1 | AC15: 1.7 | AD15: 5 | AE15: 2 | AF15: 3.6 | AG15: 4.2 | AH15: 4.1 | AI15: 7.6 | AK15: 6.8 | AL15: 7.3 | AM15: 3.4 | AN15: 18.5 | AR15: 1.5 | AW15: 6.3 | AY15: 12 | BA15: 0.6 | BC15: 5.5 | BD15: 19.3 | BE15: 7.4 | BF15: 4.5 | BG15: 2.6 | BH15: 1.2 | BI15: 2.4 | BK15: 0.3 | BM15: 18.5 | BN15: 6.6 | BP15: 5.2 | BQ15: 411.3
B16: 4:30 | C16: 13.7 | D16: 19.1 | E16: 8.4 | F16: 7.9 | G16: 1.4 | H16: 0.4 | I16: 8.9 | K16: 4 | M16: 3.5 | N16: 4.8 | O16: 4 | P16: 2.2 | Q16: 2 | R16: 13.8 | S16: 18.5 | T16: 7.2 | U16: 4 | V16: 21.8 | W16: 6.1 | X16: 16 | Z16: 24.6 | AA16: 43.7 | AB16: 2.7 | AC16: 2.4 | AD16: 5 | AE16: 2 | AF16: 3.6 | AG16: 4.1 | AH16: 4.1 | AI16: 7.6 | AK16: 5.3 | AL16: 9.5 | AM16: 3.4 | AN16: 18.5 | AR16: 1.5 | AW16: 9.8 | AY16: 18.1 | BA16: 0.6 | BC16: 4.7 | BD16: 11.7 | BE16: 7.6 | BF16: 4.5 | BG16: 2.6 | BH16: 1.2 | BI16: 2.4 | BK16: 0.3 | BM16: 18.5 | BN16: 6.7 | BP16: 5.1 | BQ16: 399.5
B17: 5:00 | C17: 14.2 | D17: 19.1 | E17: 8 | F17: 7.3 | G17: 1.3 | H17: 0.4 | I17: 10.3 | K17: 4 | M17: 3.5 | N17: 4.8 | O17: 3.9 | P17: 1.5 | Q17: 2 | R17: 14 | S17: 18.4 | T17: 7.4 | U17: 4 | V17: 22.4 | W17: 2.6 | X17: 11.9 | Z17: 22.9 | AA17: 43.7 | AB17: 1.9 | AC17: 1.8 | AD17: 5 | AE17: 2 | AF17: 3.6 | AG17: 4.1 | AH17: 4.1 | AI17: 7.7 | AK17: 7.1 | AL17: 9.8 | AM17: 3.4 | AN17: 18.5 | AR17: 1.5 | AV17: 9.9 | AW17: 29.7 | AY17: 24.5 | BA17: 0.6 | BC17: 4.4 | BD17: 9.8 | BE17: 7.6 | BF17: 4.5 | BG17: 2.6 | BH17: 1.2 | BI17: 2.4 | BK17: 0.3 | BM17: 18.5 | BN17: 6.8 | BP17: 5.1 | BQ17: 426
B18: 5:30 | C18: 13.8 | D18: 19.1 | E18: 7.8 | F18: 7.3 | G18: 1.4 | H18: 0.4 | I18: 9.9 | K18: 4 | M18: 3.5 | N18: 4.9 | O18: 2.3 | P18: 1.4 | Q18: 2 | R18: 14 | S18: 18.6 | T18: 7.7 | U18: 4 | V18: 20.2 | W18: 5.1 | X18: 13.7 | Z18: 25.4 | AA18: 42.9 | AB18: 2.1 | AC18: 2.8 | AD18: 5 | AE18: 2 | AF18: 3.6 | AG18: 4.1 | AH18: 4.1 | AI18: 7.7 | AK18: 5.2 | AL18: 10 | AM18: 3.4 | AN18: 18.5 | AR18: 1.5 | AU18: 0.5 | AV18: 9.9 | AW18: 109.4 | AY18: 78 | BA18: 0.6 | BC18: 3.5 | BD18: 8.1 | BE18: 7.5 | BF18: 4.5 | BG18: 2.6 | BH18: 1.2 | BI18: 2.4 | BK18: 0.3 | BM18: 18.5 | BN18: 6.7 | BP18: 5.3 | BQ18: 558.4
B19: 6:00 | C19: 13.6 | D19: 19.1 | E19: 8.7 | F19: 7.3 | G19: 1.4 | H19: 0.4 | I19: 9.6 | K19: 4 | M19: 3.4 | N19: 4.8 | O19: 0.4 | P19: 1.4 | Q19: 2 | R19: 14 | S19: 18.3 | T19: 8.1 | U19: 4 | V19: 21 | W19: 7 | X19: 17.4 | Z19: 25.5 | AA19: 39.8 | AB19: 2.6 | AC19: 2.3 | AD19: 5 | AE19: 2 | AF19: 3.6 | AG19: 4.1 | AH19: 4.1 | AI19: 7.7 | AK19: 4.8 | AL19: 9.4 | AM19: 3.4 | AN19: 18.5 | AR19: 1.5 | AT19: 0.1 | AU19: 1.6 | AV19: 9.9 | AW19: 125.1 | AY19: 104.7 | BA19: 0.6 | BC19: 6.9 | BD19: 14.4 | BE19: 7.6 | BF19: 4.5 | BG19: 2.6 | BH19: 1.2 | BI19: 2.4 | BK19: 0.3 | BM19: 18.5 | BN19: 6.6 | BP19: 5.1 | BQ19: 612.3
B20: 6:30 | C20: 13.8 | D20: 19.1 | E20: 8 | F20: 7.3 | G20: 1.3 | H20: 0.4 | I20: 10 | K20: 4.8 | M20: 3.2 | N20: 4.6 | P20: 2.2 | Q20: 1.9 | R20: 14 | S20: 18.3 | T20: 8.1 | U20: 4 | V20: 16.4 | W20: 6 | X20: 26 | Y20: 0.4 | Z20: 25.9 | AA20: 43 | AB20: 2.9 | AC20: 1.6 | AD20: 5 | AE20: 2 | AF20: 3.4 | AG20: 4 | AH20: 4 | AI20: 8.3 | AJ20: 0.7 | AK20: 4.2 | AL20: 6.9 | AM20: 3.4 | AN20: 18.5 | AP20: 3.4 | AR20: 1.5 | AT20: 2.4 | AU20: 0.9 | AV20: 9.9 | AW20: 111.7 | AX20: 3 | AY20: 112.2 | AZ20: 2.3 | BA20: 0.6 | BB20: 2.4 | BC20: 7.9 | BD20: 15 | BE20: 7.5 | BF20: 4.5 | BG20: 2.6 | BH20: 1.2 | BI20: 2.4 | BK20: 0.3 | BM20: 18.5 | BN20: 6.7 | BO20: 0.1 | BP20: 5.1 | BQ20: 625.7
B21: 7:00 | C21: 14.9 | D21: 19.1 | E21: 7.9 | F21: 7.5 | G21: 1.3 | H21: 0.4 | I21: 10.1 | K21: 4.8 | M21: 3.5 | N21: 4.9 | P21: 2.2 | Q21: 1.9 | R21: 14 | S21: 18.6 | T21: 8.1 | U21: 4 | V21: 12.8 | W21: 8.4 | X21: 33.7 | Y21: 6 | Z21: 26.2 | AA21: 46.2 | AB21: 2.2 | AC21: 1.3 | AD21: 5 | AE21: 2 | AF21: 3.4 | AG21: 4 | AH21: 4 | AI21: 8.3 | AJ21: 16.6 | AK21: 5.8 | AL21: 11.7 | AM21: 3.4 | AN21: 18.5 | AP21: 57.3 | AR21: 1.5 | AS21: 1.8 | AT21: 9.4 | AU21: 1.1 | AV21: 9.9 | AW21: 59.6 | AX21: 31 | AY21: 59.7 | AZ21: 25.9 | BA21: 0.6 | BB21: 10.5 | BC21: 8.8 | BD21: 23 | BE21: 7.6 | BF21: 4.5 | BG21: 2.6 | BH21: 1.2 | BI21: 2.4 | BJ21: 1.8 | BK21: 0.3 | BM21: 18.5 | BN21: 6.8 | BO21: 5.1 | BP21: 5.2 | BQ21: 698.8
B22: 7:30 | C22: 14.5 | D22: 19.1 | E22: 8.2 | F22: 7.5 | G22: 1.3 | H22: 0.4 | I22: 10.2 | K22: 4.9 | M22: 3.5 | N22: 5.2 | P22: 2.2 | Q22: 1.9 | R22: 14.1 | S22: 18.5 | T22: 8.1 | U22: 4 | V22: 17.3 | W22: 9.4 | X22: 39.7 | Y22: 15.5 | Z22: 27.2 | AA22: 39 | AB22: 2.3 | AC22: 1.9 | AD22: 5 | AE22: 2 | AF22: 3.4 | AG22: 3.8 | AH22: 3.8 | AI22: 8.3 | AJ22: 39.9 | AK22: 6.1 | AL22: 8.1 | AM22: 3.4 | AN22: 18.5 | AP22: 139.8 | AR22: 1.5 | AS22: 4.3 | AT22: 10.9 | AU22: 1 | AV22: 9.9 | AW22: 10.3 | AX22: 75.5 | AY22: 10.3 | AZ22: 60.1 | BA22: 0.6 | BB22: 13.3 | BC22: 8 | BD22: 25.8 | BE22: 7.7 | BF22: 4.5 | BG22: 2.6 | BH22: 1.2 | BI22: 2.4 | BJ22: 4.2 | BK22: 0.3 | BM22: 18.5 | BN22: 6.7 | BO22: 13.1 | BP22: 5.1 | BQ22: 815.8
B23: 8:00 | C23: 14 | D23: 19.1 | E23: 7.9 | F23: 7.5 | G23: 1.2 | H23: 0.4 | I23: 10.2 | J23: 0.1 | K23: 4.8 | M23: 3.1 | N23: 4.9 | P23: 2.2 | Q23: 1.9 | R23: 14 | S23: 18.1 | T23: 8.1 | U23: 4 | V23: 18.1 | W23: 10.2 | X23: 46.2 | Y23: 24.5 | Z23: 16.5 | AA23: 39.6 | AB23: 0.8 | AC23: 1 | AD23: 5 | AE23: 2 | AF23: 3.4 | AG23: 3.8 | AH23: 3.8 | AI23: 8.3 | AJ23: 60.5 | AK23: 5 | AL23: 5.6 | AM23: 3.4 | AN23: 18.5 | AP23: 199.5 | AQ23: 0.1 | AR23: 1.5 | AS23: 6.8 | AT23: 12.9 | AU23: 1 | AV23: 9.9 | AX23: 115.1 | AZ23: 82 | BA23: 0.6 | BB23: 15.7 | BC23: 12.3 | BD23: 24.6 | BE23: 7.7 | BF23: 4.5 | BG23: 2.6 | BH23: 1.2 | BI23: 2.4 | BJ23: 6.7 | BK23: 0.3 | BM23: 18.3 | BN23: 6.7 | BO23: 15.2 | BP23: 4.9 | BQ23: 950.2
B24: 8:30 | C24: 14.6 | D24: 18.9 | E24: 6.9 | F24: 7.5 | G24: 1.2 | H24: 0.4 | I24: 10 | J24: 0.6 | K24: 4.9 | M24: 3.3 | N24: 5.1 | P24: 2.2 | Q24: 1.9 | R24: 14 | S24: 18.4 | T24: 8.4 | U24: 4 | V24: 15.3 | W24: 14 | X24: 38.4 | Y24: 29.3 | Z24: 25.2 | AA24: 50.2 | AB24: 3.4 | AC24: 3.2 | AD24: 5 | AE24: 2 | AF24: 3.4 | AG24: 3.8 | AH24: 3.8 | AI24: 8.2 | AJ24: 63.6 | AK24: 4.6 | AL24: 7.2 | AM24: 3.4 | AN24: 18.5 | AP24: 208.4 | AQ24: 0.2 | AR24: 1.5 | AS24: 8.9 | AT24: 13.3 | AU24: 2.5 | AV24: 9.9 | AX24: 120.1 | AZ24: 85.3 | BA24: 0.6 | BB24: 16 | BC24: 7.8 | BD24: 24.4 | BE24: 7.6 | BF24: 4.5 | BG24: 2.6 | BH24: 1.2 | BI24: 2.4 | BJ24: 8.9 | BK24: 0.3 | BM24: 18.4 | BN24: 6.7 | BO24: 15.4 | BP24: 5.1 | BQ24: 996.8
B25: 9:00 | C25: 14.5 | D25: 18.6 | E25: 7.5 | F25: 11.6 | G25: 1.3 | H25: 0.4 | I25: 10.2 | J25: 0.8 | K25: 4.8 | M25: 3.4 | N25: 5.2 | P25: 2.2 | Q25: 1.9 | R25: 14 | S25: 18.5 | T25: 8.4 | U25: 4 | V25: 12.1 | W25: 22.9 | X25: 44.3 | Y25: 29.7 | Z25: 47.2 | AA25: 57.6 | AB25: 3.7 | AC25: 3.7 | AD25: 5 | AE25: 2 | AF25: 3.4 | AG25: 3.8 | AH25: 3.8 | AI25: 8.3 | AJ25: 64.7 | AK25: 5.4 | AL25: 9.2 | AM25: 3.4 | AN25: 18.5 | AP25: 211.9 | AQ25: 0.2 | AR25: 1.5 | AS25: 10.8 | AT25: 13.2 | AU25: 2.6 | AV25: 9.9 | AX25: 122.7 | AZ25: 86.9 | BA25: 0.6 | BB25: 15.7 | BC25: 8.5 | BD25: 24.5 | BE25: 7.6 | BF25: 4.5 | BG25: 2.6 | BH25: 1.1 | BI25: 2.4 | BJ25: 11 | BK25: 0.3 | BM25: 18.3 | BN25: 6.7 | BO25: 16.4 | BP25: 5.1 | BQ25: 1061
B26: 9:30 | C26: 14.4 | D26: 19.1 | E26: 7.1 | F26: 20.1 | G26: 1.3 | H26: 0.4 | I26: 9 | J26: 0.9 | K26: 4.8 | M26: 3.5 | N26: 5.2 | P26: 2.2 | Q26: 1.8 | R26: 14 | S26: 18.5 | T26: 8.2 | U26: 4 | V26: 15.1 | W26: 22.7 | X26: 47 | Y26: 30 | Z26: 29 | AA26: 45.5 | AB26: 5 | AC26: 1.8 | AD26: 5 | AE26: 2 | AF26: 3.4 | AG26: 3.8 | AH26: 3.8 | AI26: 8.1 | AJ26: 65.4 | AK26: 8.2 | AL26: 8.6 | AM26: 3.3 | AN26: 18.5 | AP26: 213.6 | AQ26: 0.3 | AR26: 1.5 | AS26: 12.5 | AT26: 13.1 | AU26: 2.6 | AV26: 9.9 | AX26: 123.6 | AZ26: 88.1 | BA26: 0.6 | BB26: 15.7 | BC26: 8.6 | BD26: 27.4 | BE26: 7.6 | BF26: 4.5 | BG26: 2.6 | BH26: 1.1 | BI26: 2.4 | BJ26: 12.6 | BK26: 0.3 | BM26: 18.3 | BN26: 6.7 | BO26: 16.3 | BP26: 5.1 | BQ26: 1055.7
B27: 10:00 | C27: 13.8 | D27: 19.1 | E27: 6.8 | F27: 20.2 | G27: 1.2 | H27: 0.4 | I27: 9.3 | J27: 1 | K27: 4.9 | M27: 3.5 | N27: 5.2 | P27: 2.2 | Q27: 1.8 | R27: 14 | S27: 18.6 | T27: 8.2 | U27: 4 | V27: 20.1 | W27: 17.6 | X27: 64.7 | Y27: 30.2 | Z27: 40 | AA27: 52.8 | AB27: 5.9 | AC27: 3.6 | AD27: 5 | AE27: 2 | AF27: 3.4 | AG27: 3.8 | AH27: 3.8 | AI27: 8.1 | AJ27: 66.1 | AK27: 10.6 | AL27: 10.8 | AM27: 3.3 | AN27: 18.5 | AP27: 213.5 | AQ27: 0.3 | AR27: 1.5 | AS27: 13.9 | AT27: 12.9 | AU27: 2.6 | AV27: 9.9 | AX27: 124 | AZ27: 85.1 | BA27: 0.6 | BB27: 15.8 | BC27: 8.8 | BD27: 28.2 | BE27: 7.6 | BF27: 4.5 | BG27: 2.6 | BH27: 1.1 | BI27: 2.4 | BJ27: 13.9 | BK27: 0.3 | BM27: 18.3 | BN27: 6.7 | BO27: 16.3 | BP27: 5.1 | BQ27: 1100.4
B28: 10:30 | C28: 13.7 | D28: 18.5 | E28: 8.7 | F28: 20.2 | G28: 1.2 | H28: 0.4 | I28: 9.4 | J28: 1.1 | K28: 4.8 | M28: 3.2 | N28: 5 | P28: 2.2 | Q28: 1.8 | R28: 14 | S28: 18.4 | T28: 8.2 | U28: 4 | V28: 16.4 | W28: 19 | X28: 83.5 | Y28: 30.1 | Z28: 45.1 | AA28: 58.5 | AB28: 5.3 | AC28: 4 | AD28: 5 | AE28: 2 | AF28: 3.4 | AG28: 3.8 | AH28: 3.8 | AI28: 7.9 | AJ28: 65.6 | AK28: 9.9 | AL28: 12.2 | AM28: 3.3 | AN28: 18.5 | AP28: 213.8 | AQ28: 0.3 | AR28: 1.5 | AS28: 14.9 | AT28: 12.8 | AU28: 4.1 | AV28: 9.9 | AX28: 123.8 | AZ28: 85.6 | BA28: 0.6 | BB28: 15.5 | BC28: 11.8 | BD28: 27 | BE28: 7.6 | BF28: 4.5 | BG28: 2.6 | BH28: 1.1 | BI28: 2.4 | BJ28: 15 | BK28: 0.3 | BM28: 18.6 | BN28: 6.6 | BO28: 16.3 | BP28: 5.1 | BQ28: 1133.8
B29: 11:00 | C29: 14.5 | D29: 17.6 | E29: 7.6 | F29: 20.2 | G29: 1.2 | H29: 0.3 | I29: 9 | J29: 1.2 | K29: 5 | M29: 3.4 | N29: 5.2 | P29: 2.2 | Q29: 1.8 | R29: 14 | S29: 18.5 | T29: 7.9 | U29: 4 | V29: 16.8 | W29: 20.4 | X29: 84.5 | Y29: 29.9 | Z29: 45.8 | AA29: 50.3 | AB29: 8.4 | AC29: 5.1 | AD29: 5 | AE29: 2 | AF29: 3.4 | AG29: 3.8 | AH29: 3.8 | AI29: 7.9 | AJ29: 65.8 | AK29: 11.5 | AL29: 12.5 | AM29: 3.3 | AN29: 18.5 | AP29: 213.3 | AQ29: 0.4 | AR29: 1.5 | AS29: 15.6 | AT29: 12.9 | AU29: 4 | AV29: 9.9 | AX29: 122.6 | AZ29: 85 | BA29: 0.6 | BB29: 15.8 | BC29: 16.4 | BD29: 49 | BE29: 7.6 | BF29: 4.5 | BG29: 2.6 | BH29: 1.1 | BI29: 2.4 | BJ29: 15.8 | BK29: 0.3 | BM29: 18.9 | BN29: 6.7 | BO29: 16.4 | BP29: 5.1 | BQ29: 1160.7
B30: 11:30 | C30: 14.6 | D30: 15.1 | E30: 8.8 | F30: 20.2 | G30: 1.3 | H30: 0.3 | I30: 9.3 | J30: 1.2 | K30: 4.9 | M30: 3.2 | N30: 5 | P30: 2.2 | Q30: 1.8 | R30: 14 | S30: 18 | T30: 7.9 | U30: 7.5 | V30: 19 | W30: 28.3 | X30: 93.5 | Y30: 29.6 | Z30: 49.2 | AA30: 69.2 | AB30: 7.7 | AC30: 5.6 | AD30: 5 | AE30: 2 | AF30: 3.4 | AG30: 3.8 | AH30: 3.8 | AI30: 7.7 | AJ30: 65.5 | AK30: 10.8 | AL30: 11.3 | AM30: 3.3 | AN30: 18.5 | AP30: 215.8 | AQ30: 0.4 | AR30: 1.5 | AS30: 16.1 | AT30: 12.9 | AU30: 4.1 | AV30: 9.9 | AX30: 122.2 | AZ30: 85.2 | BA30: 0.6 | BB30: 16.1 | BC30: 15 | BD30: 52 | BE30: 7.6 | BF30: 4.5 | BG30: 2.6 | BH30: 1.1 | BI30: 2.4 | BJ30: 16.1 | BK30: 0.3 | BM30: 18.8 | BN30: 6.7 | BO30: 16.6 | BP30: 5 | BQ30: 1206
B31: 12:00 | C31: 14.5 | D31: 15.1 | E31: 8.4 | F31: 20.2 | G31: 1.3 | H31: 0.4 | I31: 9.6 | J31: 1.2 | K31: 5 | M31: 3.6 | N31: 5.3 | P31: 2.3 | Q31: 2.2 | R31: 14 | S31: 19 | T31: 7.9 | U31: 7.5 | V31: 18.3 | W31: 39.7 | X31: 85.8 | Y31: 29.5 | Z31: 52.5 | AA31: 68.7 | AB31: 6.6 | AC31: 4.4 | AD31: 5 | AE31: 2.1 | AF31: 3.8 | AG31: 4 | AH31: 4 | AI31: 7.7 | AJ31: 65.9 | AK31: 12.8 | AL31: 11.3 | AM31: 3.2 | AN31: 18.5 | AP31: 218.3 | AQ31: 0.4 | AR31: 1.5 | AS31: 17 | AT31: 11.5 | AU31: 4 | AV31: 9.9 | AX31: 122.6 | AZ31: 85.5 | BA31: 0.6 | BB31: 14.6 | BC31: 18.1 | BD31: 69.5 | BE31: 7.6 | BF31: 4.5 | BG31: 2.5 | BH31: 1.1 | BI31: 2.4 | BJ31: 16.6 | BK31: 0.3 | BM31: 18.7 | BN31: 6.7 | BO31: 16.6 | BP31: 5.6 | BQ31: 1237.4
B32: 12:30 | C32: 13.9 | D32: 15.8 | E32: 8.5 | F32: 20.1 | G32: 1.3 | H32: 0.4 | I32: 9.2 | J32: 1.2 | K32: 4.2 | M32: 3.2 | N32: 5 | P32: 2.3 | Q32: 2.2 | R32: 14 | S32: 18.2 | T32: 7.9 | U32: 7.5 | V32: 15.9 | W32: 49.3 | X32: 59.8 | Y32: 29.8 | Z32: 81.6 | AA32: 93.6 | AB32: 13.3 | AC32: 10 | AD32: 5 | AE32: 2.1 | AF32: 3.8 | AG32: 4 | AH32: 4 | AI32: 7.7 | AJ32: 66.9 | AK32: 14.9 | AL32: 14.9 | AM32: 3.3 | AN32: 18.5 | AP32: 220.9 | AQ32: 0.4 | AR32: 1.5 | AS32: 16.9 | AT32: 11.5 | AU32: 4.1 | AV32: 9.9 | AW32: 2.5 | AX32: 122.9 | AZ32: 85.8 | BA32: 0.6 | BB32: 14.5 | BC32: 21.3 | BD32: 67.4 | BE32: 7.6 | BF32: 4.5 | BG32: 2.5 | BH32: 1.1 | BI32: 2.4 | BJ32: 16.7 | BK32: 0.3 | BM32: 18.4 | BN32: 6.8 | BO32: 15.6 | BP32: 5 | BQ32: 1294.4
B33: 13:00 | C33: 13.9 | D33: 15.9 | E33: 8.7 | F33: 20.1 | G33: 1.3 | H33: 0.4 | I33: 9.3 | J33: 1.2 | K33: 4.2 | M33: 3.4 | N33: 4.7 | P33: 2.4 | Q33: 2.1 | R33: 14 | S33: 18.1 | T33: 7.9 | U33: 7.5 | V33: 21.9 | W33: 66.3 | X33: 54.2 | Y33: 29.9 | Z33: 86.3 | AA33: 100.7 | AB33: 14 | AC33: 11.1 | AD33: 5 | AE33: 2.1 | AF33: 3.6 | AG33: 4 | AH33: 4.2 | AI33: 7.7 | AJ33: 67.6 | AK33: 16.2 | AL33: 14.8 | AM33: 3.3 | AN33: 18.5 | AP33: 221.6 | AQ33: 0.4 | AR33: 1.5 | AS33: 16.4 | AT33: 11.2 | AU33: 4 | AV33: 10 | AW33: 50 | AX33: 123.2 | AY33: 0.7 | AZ33: 90.2 | BA33: 0.6 | BB33: 14.5 | BC33: 13.8 | BD33: 49.7 | BE33: 7.5 | BF33: 4.5 | BG33: 2.5 | BH33: 1.1 | BI33: 2.4 | BJ33: 16.3 | BK33: 0.3 | BM33: 18.5 | BN33: 6.7 | BO33: 14.3 | BP33: 5.1 | BQ33: 1353.5
B34: 13:30 | C34: 14 | D34: 15.9 | E34: 8.7 | F34: 18.8 | G34: 1.2 | H34: 0.4 | I34: 9.3 | J34: 1.2 | K34: 4.2 | M34: 3.3 | N34: 4.6 | P34: 2 | Q34: 2.1 | R34: 14 | S34: 18.4 | T34: 7.8 | U34: 4 | V34: 26.2 | W34: 67.5 | X34: 70.1 | Y34: 30.3 | Z34: 86 | AA34: 92.4 | AB34: 12.7 | AC34: 8.5 | AD34: 5 | AE34: 2.1 | AF34: 3.6 | AG34: 4 | AH34: 4.2 | AI34: 7.4 | AJ34: 68 | AK34: 17.3 | AL34: 16.1 | AM34: 3.3 | AN34: 18.5 | AP34: 219.8 | AQ34: 0.4 | AR34: 1.5 | AS34: 15.6 | AT34: 12.4 | AU34: 2.4 | AV34: 10 | AW34: 103 | AX34: 123.2 | AY34: 73.2 | AZ34: 89.6 | BA34: 0.6 | BB34: 15.6 | BC34: 14.2 | BD34: 51.3 | BE34: 7.5 | BF34: 4.5 | BG34: 2.5 | BH34: 1.1 | BI34: 2.4 | BJ34: 15.6 | BK34: 0.3 | BM34: 18.5 | BN34: 6.7 | BO34: 11.8 | BP34: 5.1 | BQ34: 1481.9
B35: 14:00 | C35: 14.8 | D35: 16.3 | E35: 5.7 | F35: 9.4 | G35: 1.2 | H35: 0.4 | I35: 8.8 | J35: 1.1 | K35: 4.2 | M35: 3.4 | N35: 4.7 | P35: 2.1 | Q35: 2 | R35: 14 | S35: 18.5 | T35: 7.5 | U35: 4 | V35: 27.6 | W35: 67.9 | X35: 89 | Y35: 30.7 | Z35: 78.1 | AA35: 93.7 | AB35: 14.1 | AC35: 8 | AD35: 5 | AE35: 2.1 | AF35: 3.8 | AG35: 4 | AH35: 4.2 | AI35: 7.3 | AJ35: 67.3 | AK35: 15.5 | AL35: 15.4 | AM35: 3.3 | AN35: 18.5 | AP35: 219.4 | AQ35: 0.4 | AR35: 1.5 | AS35: 14.6 | AT35: 13.2 | AU35: 1.9 | AV35: 9.9 | AW35: 130.9 | AX35: 123.7 | AY35: 112.2 | AZ35: 90.1 | BA35: 0.6 | BB35: 16 | BC35: 20 | BD35: 61.4 | BE35: 7.5 | BF35: 4.5 | BG35: 2.5 | BH35: 1.1 | BI35: 2.4 | BJ35: 14.6 | BM35: 18.5 | BN35: 6.6 | BO35: 10.4 | BP35: 5.1 | BQ35: 1562.6
B36: 14:30 | C36: 13.8 | D36: 16.3 | E36: 8.8 | F36: 10 | G36: 1.2 | H36: 0.4 | I36: 8.6 | J36: 1 | K36: 4.2 | M36: 3.6 | N36: 4.6 | P36: 2.1 | Q36: 1.9 | R36: 14 | S36: 18.7 | T36: 7.5 | U36: 3.7 | V36: 29.2 | W36: 60.6 | X36: 100.8 | Y36: 30.5 | Z36: 87 | AA36: 94.1 | AB36: 14.4 | AC36: 10.3 | AD36: 5 | AE36: 2.1 | AF36: 3.8 | AG36: 4.2 | AH36: 4.2 | AI36: 7.3 | AJ36: 67 | AK36: 15.2 | AL36: 14.9 | AM36: 3.3 | AN36: 18.5 | AP36: 221 | AQ36: 0.3 | AR36: 1.5 | AS36: 13.1 | AT36: 13.1 | AU36: 2.1 | AV36: 9.9 | AW36: 139.1 | AX36: 125.1 | AY36: 125.4 | AZ36: 90.5 | BA36: 0.6 | BB36: 15.9 | BC36: 24.4 | BD36: 74.5 | BE36: 7.4 | BF36: 4.5 | BG36: 2.5 | BH36: 1.1 | BI36: 2.4 | BJ36: 13.2 | BM36: 18.5 | BN36: 6.8 | BO36: 11.5 | BP36: 5.2 | BQ36: 1622.4
B37: 15:00 | C37: 13.5 | D37: 16.3 | E37: 8.9 | F37: 10 | G37: 1.2 | H37: 0.4 | I37: 9.2 | J37: 0.9 | K37: 4.5 | M37: 3.3 | N37: 4.3 | P37: 2.1 | Q37: 1.8 | R37: 14 | S37: 18.4 | T37: 6.8 | U37: 3.8 | V37: 27.6 | W37: 62.7 | X37: 108.9 | Y37: 30.4 | Z37: 95.5 | AA37: 99.7 | AB37: 12.8 | AC37: 10.5 | AD37: 5 | AE37: 2.1 | AF37: 3.8 | AG37: 4.2 | AH37: 4.4 | AI37: 7.3 | AJ37: 65.8 | AK37: 14.2 | AL37: 14.3 | AM37: 3.3 | AN37: 18.5 | AP37: 217.5 | AQ37: 0.3 | AR37: 1.5 | AS37: 11.5 | AT37: 12.9 | AU37: 2 | AV37: 9.9 | AW37: 157.4 | AX37: 125.1 | AY37: 126.7 | AZ37: 90 | BA37: 0.6 | BB37: 15.5 | BC37: 28.9 | BD37: 80.3 | BE37: 7.3 | BF37: 4.5 | BG37: 2.5 | BH37: 1.1 | BI37: 2.4 | BJ37: 11.7 | BM37: 18.3 | BN37: 6.7 | BO37: 15.6 | BP37: 5.1 | BQ37: 1665.7
B38: 15:30 | C38: 13.5 | D38: 16.3 | E38: 7.3 | F38: 9.9 | G38: 1.2 | H38: 0.4 | I38: 8.9 | J38: 0.8 | K38: 4.9 | M38: 3.6 | N38: 4.5 | P38: 2.1 | Q38: 1.8 | R38: 14 | S38: 18.5 | T38: 6.8 | U38: 3.8 | V38: 24.7 | W38: 66.9 | X38: 113.8 | Y38: 29.7 | Z38: 106.9 | AA38: 108.9 | AB38: 19.2 | AC38: 13.2 | AD38: 5 | AE38: 2.1 | AF38: 3.6 | AG38: 4.2 | AH38: 4.4 | AI38: 7.6 | AJ38: 63.3 | AK38: 13.2 | AL38: 15.1 | AM38: 3.3 | AN38: 18.5 | AP38: 210.9 | AQ38: 0.3 | AR38: 1.5 | AS38: 9.5 | AT38: 12.2 | AU38: 2 | AV38: 9.9 | AW38: 148.8 | AX38: 120.8 | AY38: 126.8 | AZ38: 86.4 | BA38: 0.6 | BB38: 14.8 | BC38: 27.9 | BD38: 84.9 | BE38: 7.4 | BF38: 4.5 | BG38: 2.5 | BH38: 1.1 | BI38: 2.4 | BJ38: 9.7 | BK38: 0.2 | BM38: 18.4 | BN38: 6.8 | BO38: 14.8 | BP38: 5.1 | BQ38: 1672.1
B39: 16:00 | C39: 13.5 | D39: 16.3 | E39: 6.6 | F39: 9.8 | G39: 1.2 | H39: 0.4 | I39: 9 | J39: 0.6 | K39: 4.9 | M39: 3.5 | N39: 4.4 | P39: 2.1 | Q39: 1.9 | R39: 14 | S39: 18.2 | T39: 6.8 | U39: 3.8 | V39: 21.1 | W39: 64.5 | X39: 121.1 | Y39: 21.4 | Z39: 108.4 | AA39: 112.8 | AB39: 19.5 | AC39: 12.3 | AD39: 5.1 | AE39: 2.2 | AF39: 3.6 | AG39: 4.2 | AH39: 4.4 | AI39: 7.7 | AJ39: 53.4 | AK39: 14.6 | AL39: 14.2 | AM39: 3.3 | AN39: 18.5 | AP39: 192 | AQ39: 0.2 | AR39: 1.5 | AS39: 7.2 | AT39: 11 | AU39: 2 | AV39: 10 | AW39: 154.7 | AX39: 96.9 | AY39: 126.4 | AZ39: 78.7 | BA39: 0.6 | BB39: 13 | BC39: 29.3 | BD39: 80.9 | BE39: 7.4 | BF39: 4.5 | BG39: 2.5 | BH39: 1.1 | BI39: 2.4 | BJ39: 7.5 | BK39: 0.3 | BM39: 18.4 | BN39: 6.7 | BO39: 12.2 | BP39: 5.1 | BQ39: 1601.8
B40: 16:30 | C40: 13.8 | D40: 16.3 | E40: 7.2 | F40: 9.8 | G40: 1.2 | H40: 0.4 | I40: 8.9 | J40: 0.4 | K40: 4.9 | M40: 3.7 | N40: 5.1 | P40: 2.1 | Q40: 1.8 | R40: 14 | S40: 18.4 | T40: 6.8 | U40: 3.8 | V40: 23.7 | W40: 57.9 | X40: 119.6 | Y40: 13.8 | Z40: 101 | AA40: 108.8 | AB40: 18.1 | AC40: 15.5 | AD40: 5.1 | AE40: 2.3 | AF40: 3.6 | AG40: 4.2 | AH40: 4.4 | AI40: 7.7 | AJ40: 28.6 | AK40: 11.3 | AL40: 14.2 | AM40: 3.3 | AN40: 18.5 | AP40: 121.9 | AQ40: 0.2 | AR40: 1.5 | AS40: 4.8 | AT40: 6 | AU40: 2 | AV40: 9.8 | AW40: 141.3 | AX40: 55.9 | AY40: 126.3 | AZ40: 50.3 | BA40: 0.6 | BB40: 6.6 | BC40: 30.2 | BD40: 85.1 | BE40: 7.3 | BF40: 4.5 | BG40: 2.5 | BH40: 1.1 | BI40: 2.4 | BJ40: 5 | BK40: 0.3 | BM40: 18.4 | BN40: 6.7 | BO40: 5.2 | BP40: 5.1 | BQ40: 1381.2
B41: 17:00 | C41: 13.9 | D41: 16.3 | E41: 6.8 | F41: 9.8 | G41: 1.3 | H41: 0.4 | I41: 8.4 | J41: 0.1 | K41: 4.9 | M41: 3.5 | N41: 5 | P41: 2.1 | Q41: 1.7 | R41: 14 | S41: 18.2 | T41: 6.8 | U41: 3.8 | V41: 26.1 | W41: 50.9 | X41: 121.1 | Y41: 4.1 | Z41: 107 | AA41: 115 | AB41: 20.1 | AC41: 14.3 | AD41: 5.1 | AE41: 2.3 | AF41: 3.6 | AG41: 4.2 | AH41: 4.4 | AI41: 7.7 | AJ41: 9.5 | AK41: 12 | AL41: 15.3 | AM41: 3.3 | AN41: 18.5 | AP41: 41.9 | AQ41: 0.1 | AR41: 1.5 | AS41: 2.3 | AT41: 0.7 | AU41: 2.1 | AV41: 9.9 | AW41: 150.8 | AX41: 16 | AY41: 126.9 | AZ41: 16.3 | BA41: 0.6 | BB41: 0.7 | BC41: 29.8 | BD41: 86.4 | BE41: 7.2 | BF41: 4.5 | BG41: 2.5 | BH41: 1.1 | BI41: 2.4 | BJ41: 2.4 | BK41: 0.3 | BM41: 18.1 | BN41: 6.7 | BO41: 0.4 | BP41: 5.1 | BQ41: 1198.2
B42: 17:30 | C42: 14.2 | D42: 16.3 | E42: 8.9 | F42: 9.8 | G42: 1.3 | H42: 0.4 | I42: 8.6 | K42: 4.9 | M42: 3.5 | N42: 5 | P42: 2.1 | Q42: 1.7 | R42: 14 | S42: 18.1 | T42: 6.3 | U42: 3.8 | V42: 28.1 | W42: 45.5 | X42: 117.9 | Z42: 107.2 | AA42: 113.3 | AB42: 18.7 | AC42: 13 | AD42: 5.1 | AE42: 2.3 | AF42: 3.6 | AG42: 4.2 | AH42: 4.4 | AI42: 7.9 | AK42: 13.3 | AL42: 15.6 | AM42: 3.3 | AN42: 18.5 | AP42: 1.3 | AQ42: 0.1 | AR42: 1.5 | AS42: 0.2 | AU42: 2.1 | AV42: 9.9 | AW42: 134.2 | AX42: 0.2 | AY42: 124.6 | AZ42: 0.4 | BA42: 0.6 | BC42: 30.5 | BD42: 85.9 | BE42: 7.2 | BF42: 4.5 | BG42: 2.6 | BH42: 1.1 | BI42: 2.4 | BJ42: 0.3 | BK42: 0.3 | BM42: 17.9 | BN42: 6.7 | BO42: 0.1 | BP42: 5.1 | BQ42: 1080.5
B43: 18:00 | C43: 13.5 | D43: 17.3 | E43: 9.2 | F43: 9.9 | G43: 1.4 | H43: 0.4 | I43: 8.1 | K43: 4.9 | M43: 3.3 | N43: 4.8 | P43: 2.1 | Q43: 1.7 | R43: 14 | S43: 18 | T43: 6.3 | U43: 3.8 | V43: 27.6 | W43: 48.2 | X43: 114.3 | Z43: 112.9 | AA43: 112.6 | AB43: 20.6 | AC43: 15 | AD43: 5.1 | AE43: 2.3 | AF43: 3.6 | AG43: 4 | AH43: 4.4 | AI43: 8.2 | AK43: 13.5 | AL43: 14 | AM43: 3.3 | AN43: 18.5 | AR43: 1.5 | AU43: 2 | AV43: 9.9 | AW43: 128.2 | AY43: 125.6 | BA43: 0.6 | BC43: 30.4 | BD43: 83.4 | BE43: 7.2 | BF43: 4.5 | BG43: 2.6 | BH43: 1.1 | BI43: 2.4 | BK43: 0.3 | BM43: 17.9 | BN43: 6.7 | BP43: 5.1 | BQ43: 1076.2
B44: 18:30 | C44: 13.5 | D44: 18.2 | E44: 8 | F44: 10.2 | G44: 1.5 | H44: 0.4 | I44: 8.7 | K44: 4.7 | M44: 3.6 | N44: 5 | P44: 1.9 | Q44: 1.7 | R44: 14 | S44: 18.4 | T44: 6.3 | U44: 3.8 | V44: 23.8 | W44: 51 | X44: 114.8 | Z44: 110.5 | AA44: 113.2 | AB44: 20.4 | AC44: 11.9 | AD44: 5.1 | AE44: 2.5 | AF44: 3.6 | AG44: 4 | AH44: 4.2 | AI44: 8.2 | AK44: 11.6 | AL44: 14.9 | AM44: 3.3 | AN44: 18.5 | AR44: 1.5 | AU44: 2.1 | AV44: 9.9 | AW44: 135.1 | AY44: 125.4 | BA44: 0.6 | BC44: 31.8 | BD44: 87.3 | BE44: 7.2 | BF44: 4.5 | BG44: 2.6 | BH44: 1.1 | BI44: 2.4 | BK44: 0.3 | BM44: 17.9 | BN44: 6.7 | BP44: 5.2 | BQ44: 1083
B45: 19:00 | C45: 14.2 | D45: 18.2 | E45: 8.2 | F45: 19.6 | G45: 1.5 | H45: 0.4 | I45: 9.1 | K45: 4.7 | M45: 3.6 | N45: 5 | P45: 2 | Q45: 1.7 | R45: 13.8 | S45: 18.6 | T45: 6 | U45: 3.8 | V45: 19.5 | W45: 58.5 | X45: 117.1 | Z45: 111.7 | AA45: 110.6 | AB45: 19.9 | AC45: 14.7 | AD45: 5.1 | AE45: 2.6 | AF45: 3.8 | AG45: 4 | AH45: 4.2 | AI45: 8.2 | AK45: 10.1 | AL45: 13.4 | AM45: 3.4 | AN45: 18.5 | AR45: 1.5 | AU45: 2 | AV45: 9.9 | AW45: 133.6 | AY45: 125.9 | BA45: 0.6 | BC45: 31.8 | BD45: 88.2 | BE45: 7.1 | BF45: 4.5 | BG45: 2.6 | BH45: 1.1 | BI45: 2.4 | BK45: 0.3 | BM45: 18.2 | BN45: 6.7 | BP45: 5.1 | BQ45: 1097.2
B46: 19:30 | C46: 14 | D46: 18.2 | E46: 8.4 | F46: 19.7 | G46: 1.6 | H46: 0.4 | I46: 9.3 | K46: 4.7 | M46: 3.7 | N46: 5 | P46: 1.5 | Q46: 1.7 | R46: 14 | S46: 18.1 | T46: 6 | U46: 3.8 | V46: 21.7 | W46: 53.2 | X46: 121.1 | Z46: 112.5 | AA46: 109.7 | AB46: 20 | AC46: 10.8 | AD46: 5.1 | AE46: 2.6 | AF46: 3.8 | AG46: 4.2 | AH46: 4.2 | AI46: 7.9 | AK46: 9.8 | AL46: 13.3 | AM46: 3.4 | AN46: 18.5 | AR46: 1.5 | AU46: 2.1 | AV46: 9.9 | AW46: 128.6 | AY46: 125 | BA46: 0.6 | BC46: 31.9 | BD46: 88.4 | BE46: 7.1 | BF46: 4.5 | BG46: 2.6 | BH46: 1.1 | BI46: 2.4 | BK46: 0.3 | BM46: 18.3 | BN46: 6.7 | BP46: 5.1 | BQ46: 1088
B47: 20:00 | C47: 14 | D47: 18.6 | E47: 8 | F47: 19.4 | G47: 1.6 | H47: 0.4 | I47: 9.9 | K47: 4.8 | M47: 3.6 | N47: 4.9 | P47: 2.2 | Q47: 1.8 | R47: 13.8 | S47: 18 | T47: 6 | U47: 3.8 | V47: 23.5 | W47: 51.8 | X47: 122.4 | Z47: 115.3 | AA47: 114.8 | AB47: 19.8 | AC47: 11.6 | AD47: 5.1 | AE47: 2.6 | AF47: 3.8 | AG47: 4.4 | AH47: 4.2 | AI47: 7.9 | AK47: 8.3 | AL47: 12.6 | AM47: 3.4 | AN47: 18.5 | AR47: 1.5 | AS47: 0.1 | AU47: 2.1 | AV47: 10 | AW47: 121.3 | AY47: 123.7 | BA47: 0.6 | BC47: 31.9 | BD47: 88.3 | BE47: 7.1 | BF47: 4.5 | BG47: 2.6 | BH47: 1.1 | BI47: 2.4 | BK47: 0.3 | BM47: 17.9 | BN47: 6.7 | BP47: 5.1 | BQ47: 1088
B48: 20:30 | C48: 13.5 | D48: 18.7 | E48: 7.8 | F48: 19.5 | G48: 1.5 | H48: 0.4 | I48: 9.6 | K48: 4.5 | M48: 3.4 | N48: 4.9 | P48: 2.2 | Q48: 1.9 | R48: 14 | S48: 18 | T48: 6 | U48: 3.8 | V48: 24.4 | W48: 49.5 | X48: 117.9 | Z48: 109.6 | AA48: 114.9 | AB48: 19.4 | AC48: 12.6 | AD48: 5.1 | AE48: 2.4 | AF48: 3.8 | AG48: 4.4 | AH48: 4.4 | AI48: 7.9 | AK48: 7.5 | AL48: 11.1 | AM48: 3.4 | AN48: 18.5 | AR48: 1.5 | AS48: 0.1 | AU48: 2.2 | AV48: 9.9 | AW48: 87.5 | AY48: 110.7 | BA48: 0.6 | BC48: 32 | BD48: 88.6 | BE48: 7.1 | BF48: 4.5 | BG48: 2.6 | BH48: 1.1 | BI48: 2.4 | BK48: 0.3 | BM48: 18 | BN48: 6.7 | BP48: 5.1 | BQ48: 1027.4
B49: 21:00 | C49: 13.4 | D49: 19 | E49: 8.7 | F49: 19.5 | G49: 1.5 | H49: 0.4 | I49: 9.3 | K49: 4.6 | M49: 3.4 | N49: 4.9 | P49: 2.1 | Q49: 2 | R49: 14.2 | S49: 18.3 | T49: 6 | U49: 3.8 | V49: 20.4 | W49: 52.3 | X49: 113.3 | Z49: 107 | AA49: 114.4 | AB49: 19.2 | AC49: 13.1 | AD49: 5.1 | AE49: 2.3 | AF49: 3.8 | AG49: 4.4 | AH49: 4.4 | AI49: 7.9 | AK49: 6.7 | AL49: 10.9 | AM49: 3.4 | AN49: 18.5 | AR49: 1.5 | AS49: 0.1 | AU49: 2.2 | AV49: 9.9 | AW49: 110.6 | AY49: 112.5 | BA49: 0.6 | BC49: 31.3 | BD49: 88 | BE49: 7 | BF49: 4.5 | BG49: 2.6 | BH49: 1.1 | BI49: 2.4 | BK49: 0.3 | BM49: 18.5 | BN49: 6.7 | BP49: 5.2 | BQ49: 1043.2
B50: 21:30 | C50: 13.5 | D50: 19 | E50: 7.3 | F50: 19.5 | G50: 1.5 | H50: 0.4 | I50: 9.4 | K50: 4.6 | M50: 3.4 | N50: 4.9 | P50: 2.2 | Q50: 2 | R50: 14 | S50: 18.2 | T50: 6.1 | U50: 3.8 | V50: 16.1 | W50: 35.6 | X50: 113.3 | Z50: 109.2 | AA50: 114.6 | AB50: 17.3 | AC50: 12.2 | AD50: 5.1 | AE50: 2.3 | AF50: 3.8 | AG50: 4.4 | AH50: 4.4 | AI50: 7.6 | AK50: 5.5 | AL50: 8.4 | AM50: 3.4 | AN50: 18.5 | AR50: 1.5 | AU50: 2.2 | AV50: 9.9 | AW50: 138 | AY50: 125.3 | BA50: 0.6 | BC50: 31.8 | BD50: 87.7 | BE50: 7.1 | BF50: 4.5 | BG50: 2.6 | BH50: 1.1 | BI50: 2.4 | BK50: 0.3 | BM50: 18.5 | BN50: 6.7 | BP50: 5.1 | BQ50: 1056.8
B51: 22:00 | C51: 13.5 | D51: 19 | E51: 7.7 | F51: 17.1 | G51: 1.4 | H51: 0.4 | I51: 9 | K51: 4.6 | M51: 3.2 | N51: 4.7 | P51: 1.9 | Q51: 2 | R51: 14 | S51: 17.9 | T51: 6.1 | U51: 3.8 | V51: 12.3 | W51: 28.8 | X51: 110 | Z51: 118.3 | AA51: 115.8 | AB51: 20.5 | AC51: 14.8 | AD51: 5.1 | AE51: 2.2 | AF51: 3.8 | AG51: 4.2 | AH51: 4.4 | AI51: 7.6 | AK51: 9.1 | AL51: 11.5 | AM51: 3.4 | AN51: 18.5 | AR51: 1.5 | AU51: 2.2 | AV51: 9.9 | AW51: 149.9 | AY51: 126.9 | BA51: 0.6 | BC51: 31.5 | BD51: 87.9 | BE51: 7.1 | BF51: 4.5 | BG51: 2.6 | BH51: 1.1 | BI51: 2.4 | BK51: 0.3 | BM51: 18.3 | BN51: 6.7 | BP51: 5.1 | BQ51: 1075.1
B52: 22:30 | C52: 13.4 | D52: 19 | E52: 8.9 | F52: 13.4 | G52: 1.4 | H52: 0.4 | I52: 9.1 | K52: 4.6 | M52: 3.6 | N52: 5.1 | P52: 1.9 | Q52: 2 | R52: 14 | S52: 18.4 | T52: 6.2 | U52: 3.8 | V52: 13 | W52: 22.8 | X52: 106.9 | Z52: 114.4 | AA52: 108.5 | AB52: 19.9 | AC52: 12.2 | AD52: 5 | AE52: 2.2 | AF52: 3.8 | AG52: 4.2 | AH52: 4.4 | AI52: 7.6 | AK52: 6.9 | AL52: 9.7 | AM52: 3.3 | AN52: 18.5 | AR52: 1.5 | AU52: 2.2 | AV52: 9.9 | AW52: 157.7 | AY52: 127 | BA52: 0.6 | BC52: 31.7 | BD52: 86.6 | BE52: 7 | BF52: 4.5 | BG52: 2.6 | BH52: 1.1 | BI52: 2.4 | BK52: 0.3 | BM52: 18.3 | BN52: 6.7 | BP52: 5.1 | BQ52: 1053.7
B53: 23:00 | C53: 13.5 | D53: 19.1 | E53: 8.7 | F53: 13.5 | G53: 1.5 | H53: 0.4 | I53: 9.2 | K53: 4.5 | M53: 3.5 | N53: 5.1 | P53: 2 | Q53: 2 | R53: 14 | S53: 18.3 | T53: 6.3 | U53: 3.8 | V53: 20.2 | W53: 22.8 | X53: 109.7 | Z53: 116.6 | AA53: 109.6 | AB53: 19.3 | AC53: 14.3 | AD53: 5 | AE53: 2.2 | AF53: 3.8 | AG53: 4.2 | AH53: 4.4 | AI53: 7.4 | AK53: 9 | AL53: 11.9 | AM53: 3.4 | AN53: 18.5 | AR53: 1.5 | AU53: 2.2 | AV53: 9.9 | AW53: 157.3 | AY53: 127.1 | BA53: 0.6 | BC53: 31.9 | BD53: 87.9 | BE53: 7.1 | BF53: 4.5 | BG53: 2.6 | BH53: 1.1 | BI53: 2.4 | BK53: 0.3 | BM53: 18.2 | BN53: 6.6 | BP53: 5.2 | BQ53: 1074.1
B54: 23:30 | C54: 13.4 | D54: 19 | E54: 9.1 | F54: 13.8 | G54: 1.4 | H54: 0.4 | I54: 9 | K54: 4.5 | M54: 3.5 | N54: 5 | P54: 2.3 | Q54: 2 | R54: 14 | S54: 18.4 | T54: 6.3 | U54: 3.8 | V54: 21.1 | W54: 28 | X54: 111.4 | Z54: 115.9 | AA54: 105.8 | AB54: 18.4 | AC54: 11 | AD54: 5 | AE54: 2.2 | AF54: 3.8 | AG54: 4.2 | AH54: 4.4 | AI54: 7.4 | AK54: 9.2 | AL54: 14.1 | AM54: 3.4 | AN54: 18.5 | AR54: 1.5 | AU54: 2.2 | AV54: 9.9 | AW54: 122.4 | AY54: 124.1 | BA54: 0.6 | BC54: 31.7 | BD54: 87 | BE54: 7.1 | BF54: 4.5 | BG54: 2.6 | BH54: 1.1 | BI54: 2.4 | BK54: 0.3 | BM54: 18.3 | BN54: 6.6 | BP54: 5.1 | BQ54: 1037.1
B55: 0:00 | C55: 13.7 | D55: 18.9 | E55: 8.6 | F55: 13.7 | G55: 1.4 | H55: 0.4 | I55: 9.1 | K55: 4.5 | M55: 3.5 | N55: 5.1 | P55: 2.1 | Q55: 2 | R55: 14 | S55: 18.6 | T55: 6.3 | U55: 3.9 | V55: 20.2 | W55: 26.9 | X55: 118.2 | Z55: 101.6 | AA55: 104.7 | AB55: 16.4 | AC55: 9.6 | AD55: 5 | AE55: 2.2 | AF55: 3.8 | AG55: 4.2 | AH55: 4.4 | AI55: 7.4 | AK55: 11.3 | AL55: 14.3 | AM55: 3.4 | AN55: 18.5 | AR55: 1.5 | AU55: 2.2 | AV55: 10 | AW55: 90.8 | AY55: 105.1 | BA55: 0.6 | BC55: 31.8 | BD55: 86.1 | BE55: 7.3 | BF55: 4.5 | BG55: 2.6 | BH55: 1.1 | BI55: 2.4 | BK55: 0.3 | BM55: 18.3 | BN55: 6.6 | BP55: 5.3 | BQ55: 974.4
B56: EJEC MWh | C56: 334.05 | D56: 433.8 | E56: 191.55 | F56: 311.4 | G56: 32.4 | H56: 9.5 | I56: 222.15 | J56: 8.3 | K56: 108.3 | L56: 0 | M56: 82.6 | N56: 117.4 | O56: 21.2 | P56: 49.35 | Q56: 46 | R56: 329.7 | S56: 441.8 | T56: 172.15 | U56: 101 | V56: 476.55 | W56: 788.4 | X56: 1712.85 | Y56: 267.65 | Z56: 1638.4 | AA56: 1875.9 | AB56: 258.55 | AC56: 177.6 | AD56: 120.65 | AE56: 51.25 | AF56: 87.3 | AG56: 98.9 | AH56: 100.6 | AI56: 186.2 | AJ56: 598.85 | AK56: 215.2 | AL56: 267.85 | AM56: 80.55 | AN56: 444 | AO56: 0 | AP56: 1998.4 | AQ56: 2.85 | AR56: 36 | AS56: 117.5 | AT56: 121.25 | AU56: 48.8 | AV56: 203.15 | AW56: 1784.85 | AX56: 1119.6 | AY56: 1596.2 | AZ56: 812.65 | BA56: 14.4 | BB56: 147.1 | BC56: 432.3 | BD56: 1243.5 | BE56: 177.25 | BF56: 108 | BG56: 61.85 | BH56: 27.25 | BI56: 57.6 | BJ56: 117.8 | BK56: 6.7 | BL56: 0 | BM56: 444.5 | BN56: 160.6 | BO56: 137.85 | BP56: 122.9 | BQ56: 23560.75
L70: TERMOELÉCTRICA | M70: 1436.25 | N70: 6.0959435 | O70: #FFA975
L71: HIDROELÉCTRICA | M71: 4206.55 | N71: 17.854058 | O71: #98D2FF
L72: SOLAR | M72: 5449.8 | N72: 23.130843 | O72: #FFD272
L73: EÓLICA | M73: 12468.15 | N73: 52.919156 | O73: #B9ACFF

Sheet COGENERACIÓN
B3: sábado, 26 de Julio del 2025
B5: CENTRALES DE COGENERACIÓN DEL SEIN
B6: HORA | C6: AGRO INDUSTRIAL PARAMONGA S.A. | D6: AGROAURORA S.A.C. | E6: AGROINDUSTRIAS SAN JACINTO S.A.A. | F6: BIOENERGIA DEL CHIRA S.A. | G6: GM OPERACIONES S.A.C. | H6: SDF ENERGIA SAC | I6: TOTAL COGENERACION
C7: C.T. PARAMONGA | D7: C.T. MAPLE | E7: C.T SAN JACINTO | F7: C.T. CAÑA BRAVA | G7: C.T. REFINERÍA TALARA | H7: C.T. OQUENDO | I7: MW
B8: 0:30 | C8: 14.5 | D8: 19 | E8: 8.4 | F8: 8.9 | G8: 54.7 | I8: 105.5
B9: 1:00 | C9: 14.2 | D9: 19.1 | E9: 7.6 | F9: 9.4 | G9: 53.5 | I9: 103.8
B10: 1:30 | C10: 13.7 | D10: 19.1 | E10: 7.4 | F10: 9.3 | G10: 54.4 | I10: 103.9
B11: 2:00 | C11: 13.5 | D11: 19.1 | E11: 7.4 | F11: 9 | G11: 54.1 | I11: 103.1
B12: 2:30 | C12: 14.1 | D12: 19 | E12: 6.7 | F12: 8.7 | G12: 53.9 | I12: 102.4
B13: 3:00 | C13: 14 | D13: 19.1 | E13: 8 | F13: 9.3 | G13: 56.7 | I13: 107.1
B14: 3:30 | C14: 13.5 | D14: 19.1 | E14: 8 | F14: 9.4 | G14: 55.9 | I14: 105.9
B15: 4:00 | C15: 13.6 | D15: 19.1 | E15: 8.2 | F15: 8.3 | G15: 56.3 | I15: 105.5
B16: 4:30 | C16: 13.7 | D16: 19.1 | E16: 8.4 | F16: 8.9 | G16: 58.9 | I16: 109
B17: 5:00 | C17: 14.2 | D17: 19.1 | E17: 8 | F17: 10.3 | G17: 59.2 | I17: 110.8
B18: 5:30 | C18: 13.8 | D18: 19.1 | E18: 7.8 | F18: 9.9 | G18: 58.6 | I18: 109.2
B19: 6:00 | C19: 13.6 | D19: 19.1 | E19: 8.7 | F19: 9.6 | G19: 59.2 | I19: 110.2
... B55: 0:00 | C55: 13.7 | D55: 18.9 | E55: 8.6 | F55: 9.1 | G55: 64.6 | I55: 114.9
B56: EJEC MWh | C56: 334.05 | D56: 433.8 | E56: 191.55 | F56: 222.15 | G56: 1417.85 | H56: 0 | I56: 2599.4

Sheet EVO_PRO_ENE
B3: martes, 1 de Julio del 2025 - sábado, 26 de Julio del 2025
B5: EVOLUCIÓN DE LA PRODUCCIÓN DE LA ENERGÍA DIARIA DE LOS INTEGRANTES DEL COES (MWh)
B6: EMPRESA | C6: CENTRAL | D6: UNIDAD | E6: TIPO | F6: Julio
F7: 1 | G7: 2 | H7: 3 | I7: 4 | J7: 5 | K7: 6 | L7: 7 | M7: 8 | N7: 9 | O7: 10 | P7: 11 | Q7: 12 | R7: 13 | S7: 14 | T7: 15 | U7: 16 | V7: 17 | W7: 18 | X7: 19 | Y7: 20 | Z7: 21 | AA7: 22 | AB7: 23 | AC7: 24 | AD7: 25 | AE7: 26 | AF7: TOTAL
B8: AGRO INDUSTRIAL PARAMONGA S.A. | C8: C.T. PARAMONGA | D8: TV-01 | E8: TERMOELÉCTRICA | H8: 66.2 | I8: 335.95 | J8: 305.4 | K8: 314.4 | L8: 355.2 | M8: 274.05 | N8: 344.35 | O8: 213.4 | P8: 296.3 | Q8: 368.45 | R8: 370 | S8: 378.7 | T8: 368.65 | U8: 337.7 | V8: 346.2 | W8: 355.25 | X8: 348.7 | Y8: 341.8 | Z8: 328.35 | AA8: 344.05 | AB8: 341.75 | AC8: 344.15 | AD8: 342.15 | AE8: 334.05 | AF8: 7755.2
B9: AGROAURORA S.A.C. | C9: C.T. MAPLE ETANOL | D9: TV | E9: TERMOELÉCTRICA | S9: 57 | T9: 96.65 | U9: 300.8 | V9: 351.6 | W9: 332.9 | X9: 334.05 | Y9: 423.55 | Z9: 442.55 | AA9: 450.4 | AB9: 457.95 | AC9: 463.4 | AD9: 452.8 | AE9: 433.8 | AF9: 4597.45
B10: AGROINDUSTRIAS SAN JACINTO S.A.A. | C10: C.T. SAN JACINTO | D10: CENTRAL | E10: TERMOELÉCTRICA | F10: 181.65 | G10: 167.65 | H10: 167.1 | I10: 171.1 | J10: 183.75 | K10: 190.76 | L10: 182.3 | M10: 189.95 | N10: 191.6 | O10: 187.4 | P10: 195.35 | Q10: 194.5 | R10: 195.2 | S10: 194.3 | T10: 184.06 | U10: 195.5 | V10: 194.785 | W10: 188.55 | X10: 198.8 | Y10: 200.05 | Z10: 189.65 | AA10: 194.05 | AB10: 199.8 | AC10: 197.55 | AD10: 194.25 | AE10: 191.55 | AF10: 4921.205
B11: ANDEAN POWER S.A.C. | C11: C.H.CARHUAC | D11: CENTRAL | E11: HIDROELÉCTRICA | F11: 316.65 | G11: 284.2 | H11: 324.2 | I11: 330.65 | J11: 301.1 | K11: 343.65 | L11: 325 | M11: 374.9 | N11: 346.2 | O11: 402.25 | P11: 397.2 | Q11: 390.25 | R11: 370.5 | S11: 318.85 | T11: 327.35 | U11: 313.55 | V11: 308 | W11: 301.95 | X11: 323.4 | Y11: 294.25 | Z11: 294.85 | AA11: 298 | AB11: 287.25 | AC11: 289.45 | AD11: 297.35 | AE11: 311.4 | AF11: 8472.4
B12: ASOCIACIÓN SANTA LUCIA DE CHACAS | C12: C.H. HUALLIN | D12: CENTRAL | E12: HIDROELÉCTRICA | F12: 33.25 | G12: 32.748 | H12: 31.4 | I12: 30.55 | J12: 30.1 | K12: 15.55 | L12: 29.7 | M12: 30.5 | N12: 32.5 | O12: 32.8 | P12: 33.9 | Q12: 32.8 | R12: 31.65 | S12: 31.65 | T12: 31.95 | U12: 31.4 | V12: 32.35 | W12: 32.05 | X12: 30.35 | Y12: 30.3 | Z12: 31.1 | AA12: 31.55 | AB12: 31.4 | AC12: 30 | AD12: 31.7 | AE12: 32.4 | AF12: 805.648
B13: ATRIA ENERGIA S.A.C. | C13: C.H. PURMACANA | D13: CENTRAL | E13: HIDROELÉCTRICA | I13: 4.4 | J13: 7.2 | K13: 7.2 | L13: 3.35 | P13: 4.5 | Q13: 6.85 | R13: 7.2 | S13: 3.8 | W13: 3.8 | X13: 7.5 | Y13: 7.35 | Z13: 3.3 | AD13: 5.85 | AE13: 9.5 | AF13: 81.8
B14: BIOENERGIA DEL CHIRA S.A. | C14: C.T. CAÑA BRAVA | D14: CENTRAL | E14: TERMOELÉCTRICA | F14: 201.95 | G14: 229.7 | H14: 227.6 | I14: 229.65 | J14: 232.45 | K14: 228.9 | L14: 228.9 | M14: 209.9 | N14: 238.5 | O14: 224 | P14: 220.85 | Q14: 233.0473 | R14: 220.6 | S14: 237 | T14: 225 | U14: 175.8 | V14: 230.45 | W14: 225.95 | X14: 223.25 | Y14: 243.1 | Z14: 233.1 | AA14: 242.3 | AB14: 203.4 | AC14: 228.25 | AD14: 228.9 | AE14: 222.15 | AF14: 5844.6973
B15: CELEPSA | C15: C.H. EL PLATANAL | D15: CENTRAL | E15: HIDROELÉCTRICA | F15: 2672.3 | G15: 2594.5 | H15: 2573.75 | I15: 2535.35 | J15: 2588 | K15: 2493.65 | L15: 2389.45 | M15: 2356.6 | N15: 2455.4 | O15: 2344.4 | P15: 2280.95 | Q15: 2421.3185 | R15: 2231.7 | S15: 2315.35 | T15: 2272.5 | U15: 2243.05 | V15: 2212.2 | W15: 2211.55 | X15: 2247.25 | Y15: 2104 | Z15: 2097.7 | AA15: 2074.4 | AB15: 2009.4 | AC15: 2031 | AD15: 2236.75 | AE15: 2146.8 | AF15: 60139.319
B16: CELEPSA RENOVABLES S.R.L. | C16: C.H. MARAÑON | D16: CENTRAL | E16: HIDROELÉCTRICA | F16: 474.4 | G16: 475.2 | H16: 473.9 | I16: 467.5 | J16: 444.55 | K16: 427.65 | L16: 416.95 | M16: 408.25 | N16: 398.55 | O16: 389.1 | P16: 381 | Q16: 369.72195 | R16: 362.8 | S16: 358 | T16: 347.75 | U16: 339.55 | V16: 333.9 | W16: 339.7 | X16: 300.3 | Y16: 351.75 | Z16: 334.05 | AA16: 318.45 | AB16: 312.95 | AC16: 307.85 | AD16: 303.95 | AE16: 300.45 | AF16: 9738.2219
B17: CENTRALES SANTA ROSA S.A.C. | C17: C.H. SANTA ROSA I | D17: CENTRAL | E17: HIDROELÉCTRICA | AF17: 0
B18: CENTRALES SANTA ROSA S.A.C. | C18: C.H. SANTA ROSA II | D18: CENTRAL | E18: HIDROELÉCTRICA | AF18: 0
B19: CHINANGO S.A.C. | C19: C.H. CHIMAY | D19: CENTRAL | E19: HIDROELÉCTRICA | F19: 1885.7 | G19: 2270.7 | H19: 1903.7 | I19: 1723.05 | J19: 1487.75 | K19: 1501.45 | L19: 1894.35 | M19: 1467.9 | N19: 1384.7 | O19: 1322.2 | P19: 1350.05 | Q19: 1365.5 | R19: 1406.65 | S19: 1320.4 | T19: 1210.55 | U19: 1364.35 | V19: 1129.65 | W19: 1463.25 | X19: 1260.45 | Y19: 1317.9 | Z19: 1202.45 | AA19: 1214.5 | AB19: 906.6 | AC19: 1244.7 | AD19: 1141.85 | AE19: 967.15 | AF19: 36707.5
B20: CHINANGO S.A.C. | C20: C.H. YANANGO | D20: CENTRAL | E20: HIDROELÉCTRICA | F20: 690.8 | G20: 692.3 | H20: 684.2 | I20: 664.4 | J20: 650.95 | K20: 630.75 | L20: 611.4 | M20: 596.1 | N20: 589.3 | O20: 568.65 | P20: 589.55 | Q20: 513.65 | R20: 560.15 | S20: 531.45 | T20: 533.35 | U20: 524.15 | V20: 520.35 | W20: 540.55 | X20: 547.1 | Y20: 546.75 | Z20: 510.4 | AA20: 496.3 | AB20: 492.6 | AC20: 484.3 | AD20: 486.8 | AE20: 467.05 | AF20: 14723.35
B21: COLCA SOLAR S.A.C. | C21: C.S. YARUCAYA | D21: CENTRAL | E21: SOLAR | F21: 6.55 | G21: 8.25 | H21: 8.25 | I21: 8.35 | J21: 8.4 | K21: 8.6 | L21: 8.4 | M21: 8.4 | N21: 8.4 | O21: 8.35 | P21: 8.3 | Q21: 8.15 | R21: 8.15 | S21: 8.15 | T21: 8.2 | U21: 8.35 | V21: 8.2 | W21: 8.3 | X21: 7.7 | Y21: 8.2 | Z21: 8.15 | AA21: 8.1 | AB21: 8.3 | AC21: 8.3 | AD21: 8.3 | AE21: 8.3 | AF21: 213.1
B22: EGASA | C22: C.H. CHARCANI III | D22: CENTRAL | E22: HIDROELÉCTRICA | F22: 164.65 | G22: 164.15 | H22: 164.45 | I22: 164.15 | J22: 163.65 | K22: 164.905 | L22: 163.85 | M22: 164.25 | N22: 164.45 | O22: 166.95 | P22: 167.95 | Q22: 165.0995 | R22: 168.85 | S22: 164.11 | T22: 158.3 | U22: 150.05 | V22: 148.3835 | W22: 158.05 | X22: 164.55 | Y22: 165.45 | Z22: 164.95 | AA22: 156.85 | AB22: 165.2 | AC22: 105.1 | AD22: 136.75 | AE22: 167.3 | AF22: 4152.398
B23: EGASA | C23: C.H. CHARCANI IV | D23: CENTRAL | E23: HIDROELÉCTRICA | F23: 291.2 | G23: 289.3 | H23: 290.9 | I23: 286.25 | J23: 287.25 | K23: 289.015 | L23: 286.85 | M23: 278.45 | N23: 283.4 | O23: 280.75 | P23: 284.4 | Q23: 288.86 | R23: 286.7 | S23: 289.155 | T23: 265.7 | U23: 232.1 | V23: 230.6295 | W23: 267.75 | X23: 312.8 | Y23: 308.85 | Z23: 312.55 | AA23: 316.95 | AB23: 313 | AC23: 302.9 | AD23: 286.05 | AE23: 283.8 | AF23: 7445.5595
B24: EGASA | C24: C.H. CHARCANI V | D24: CENTRAL | E24: HIDROELÉCTRICA | F24: 1784.8 | G24: 1768.85 | H24: 1801 | I24: 1817.7 | J24: 1760.1 | K24: 1774.745 | L24: 1799 | M24: 1794.75 | N24: 1788.7 | O24: 1773.9 | P24: 1788.55 | Q24: 1803.691 | R24: 1794.4 | S24: 1765.69 | T24: 1668.75 | U24: 1435.9 | V24: 1470.9575 | W24: 1665.35 | X24: 1944.25 | Y24: 1943.15 | Z24: 1936.55 | AA24: 1962.2 | AB24: 1959.35 | AC24: 1908.4 | AD24: 1772.15 | AE24: 1800.3 | AF24: 46483.183
B25: EGASA | C25: C.H. CHARCANI VI | D25: CENTRAL | E25: HIDROELÉCTRICA | AF25: 0
B26: EGASA | C26: C.T. CHILINA DIESEL | D26: CENTRAL | E26: TERMOELÉCTRICA | AF26: 0
B27: EGASA | C27: C.T. CHILINA DIESEL | D27: TG | E27: TERMOELÉCTRICA | M27: 9.4 | AF27: 9.4
B28: EGASA | C28: C.T. MOLLENDO DIESEL | D28: CENTRAL | E28: TERMOELÉCTRICA | N28: 28.45 | AF28: 28.45
B29: EGEJUNIN | C29: C.H. HUASAHUASI I | D29: CENTRAL | E29: HIDROELÉCTRICA | F29: 228.3 | G29: 223.85 | H29: 209.5 | I29: 197.15 | J29: 186.85 | K29: 77.8 | L29: 166.05 | M29: 163.8 | N29: 150.1 | O29: 146.3 | P29: 145.65 | Q29: 142.95 | R29: 140.1 | S29: 127.8 | T29: 125.8 | U29: 122.8 | V29: 125.55 | W29: 130.45 | X29: 131.25 | Y29: 132.2 | Z29: 123.45 | AA29: 113.55 | AB29: 106.15 | AC29: 99 | AD29: 99.05 | AE29: 108.3 | AF29: 3723.75
B30: EGEJUNIN | C30: C.H. RUNATULLO II | D30: CENTRAL | E30: HIDROELÉCTRICA | F30: 131.55 | G30: 128.35 | H30: 128.1 | I30: 122.9 | J30: 115.05 | K30: 113.3 | L30: 105.95 | M30: 100.65 | N30: 102.85 | O30: 103.7 | P30: 100.05 | Q30: 98.35 | R30: 94.8 | S30: 94.5 | T30: 92.25 | U30: 91.6 | V30: 88.75 | W30: 104.2 | X30: 97.55 | Y30: 95.15 | Z30: 89.7 | AA30: 86.05 | AB30: 85 | AC30: 84.6 | AD30: 83.45 | AE30: 82.6 | AF30: 2621
B31: EGEJUNIN | C31: C.H. RUNATULLO III | D31: CENTRAL | E31: HIDROELÉCTRICA | F31: 185.4 | G31: 190.6 | H31: 180.2 | I31: 176.25 | J31: 163.8 | K31: 161.6 | L31: 153.25 | M31: 151.8 | N31: 143.6 | O31: 148.2 | P31: 141.3 | Q31: 139.3 | R31: 138.2 | S31: 133.45 | T31: 129.6 | U31: 130.4 | V31: 123.25 | W31: 151.45 | X31: 137.9 | Y31: 135 | Z31: 130.45 | AA31: 120.25 | AB31: 120.35 | AC31: 116.5 | AD31: 120.85 | AE31: 117.4 | AF31: 3740.35
B32: EGEJUNIN | C32: C.H. SANTA CRUZ I | D32: CENTRAL | E32: HIDROELÉCTRICA | F32: 94.8 | G32: 96.2 | H32: 89.9 | I32: 79.75 | J32: 73.85 | K32: 65.1 | L32: 72.5 | M32: 75.65 | N32: 73.35 | O32: 75.65 | P32: 74.95 | Q32: 69.15 | R32: 69 | S32: 76.55 | T32: 63.1 | U32: 74.15 | V32: 78.75 | W32: 82.4 | X32: 84.15 | Y32: 80.75 | Z32: 74.75 | AA32: 82.5 | AB32: 80.3 | AC32: 78.65 | AD32: 80.1 | AE32: 21.2 | AF32: 1967.2
B33: EGEMSA | C33: C.H. MACHUPICCHU | D33: CENTRAL | E33: HIDROELÉCTRICA | F33: 3354.25 | G33: 3343.75 | H33: 3285.5 | I33: 3300.8 | J33: 3296.3 | K33: 3238.9 | L33: 3171.6 | M33: 3051.65 | N33: 3000.4 | O33: 2939 | P33: 2909.4 | Q33: 2914.85 | R33: 2879.6 | S33: 2876.2 | T33: 2831.2 | U33: 2796.8 | V33: 2788.35 | W33: 2777.75 | X33: 2787.3 | Y33: 2751.3 | Z33: 2740.7 | AA33: 2674.7 | AB33: 2641.75 | AC33: 2618.25 | AD33: 2570.45 | AE33: 2598.45 | AF33: 76139.2
B34: EGESUR | C34: C.H. ARICOTA I | D34: CENTRAL | E34: HIDROELÉCTRICA | F34: 173.8 | G34: 173.85 | H34: 177.45 | I34: 176.8 | J34: 174.3 | K34: 176.8 | L34: 177 | M34: 178.3 | N34: 178.6 | O34: 175.05 | P34: 171.2 | Q34: 172.7 | R34: 171.85 | S34: 171.2 | T34: 172.15 | U34: 176.7 | V34: 177.55 | W34: 176.6 | X34: 128 | Y34: 178.2 | Z34: 179.3 | AA34: 177.75 | AB34: 179.2 | AC34: 179.6 | AD34: 179.55 | AE34: 180.45 | AF34: 4533.95
B35: EGESUR | C35: C.H. ARICOTA II | D35: CENTRAL | E35: HIDROELÉCTRICA | F35: 126 | G35: 124.65 | H35: 127.35 | I35: 126.2 | J35: 119.55 | K35: 131.5 | L35: 131.95 | M35: 136.75 | N35: 136.55 | O35: 136.05 | P35: 135.25 | Q35: 138.8 | R35: 134.95 | S35: 128.35 | T35: 128.2 | U35: 135.65 | V35: 137.05 | W35: 138.15 | X35: 115.9 | Y35: 125.3 | Z35: 123.85 | AA35: 122.4 | AB35: 120.05 | AC35: 118.05 | AD35: 117.35 | AE35: 120.1 | AF35: 3335.95
B36: EGESUR | C36: C.T. INDEPENDENCIA | D36: CENTRAL | E36: TERMOELÉCTRICA | G36: 20.35 | J36: 175.85 | V36: 200.8 | W36: 140.35 | AC36: 391.15 | AD36: 451.8 | AE36: 235 | AF36: 1615.3
B37: ELECTRICA YANAPAMPA SAC | C37: C.H. YANAPAMPA | D37: CENTRAL | E37: HIDROELÉCTRICA | F37: 53.1 | G37: 53.6 | H37: 54.9 | I37: 51.15 | J37: 48.9 | K37: 49.5 | L37: 46.7 | M37: 47.45 | N37: 46.25 | O37: 56.2 | P37: 56.55 | Q37: 57.6 | R37: 57.6 | S37: 57.45 | T37: 57.1 | U37: 56.65 | V37: 55.9 | W37: 56.65 | X37: 57.1 | Y37: 56.45 | Z37: 56.4 | AA37: 55.3 | AB37: 52.55 | AC37: 54.55 | AD37: 51.45 | AE37: 49.35 | AF37: 1396.4
B38: ELECTROPERU | C38: C.H. MANTARO | D38: CENTRAL | E38: HIDROELÉCTRICA | F38: 15565.4 | G38: 15560.2 | H38: 15569.3 | I38: 14799.655 | J38: 15557.05 | K38: 15072.3 | L38: 15551.25 | M38: 15569.5 | N38: 15583.025 | O38: 15549.3 | P38: 15536.35 | Q38: 15554.4 | R38: 15121.65 | S38: 15521.96 | T38: 15538.3 | U38: 15526.8 | V38: 15353.05 | W38: 14825.2 | X38: 15493.7 | Y38: 15024.5 | Z38: 15431.15 | AA38: 14879.7 | AB38: 15271.85 | AC38: 15421.75 | AD38: 15400.75 | AE38: 14697.5 | AF38: 398975.59
B39: ELECTROPERU | C39: C.H. RESTITUCION | D39: CENTRAL | E39: HIDROELÉCTRICA | F39: 5165.4 | G39: 5164.05 | H39: 5166.25 | I39: 4977.64 | J39: 5174.2 | K39: 5037.95 | L39: 5170.3 | M39: 5173.75 | N39: 5178.555 | O39: 5172 | P39: 5174.5 | Q39: 5175.4 | R39: 5079.95 | S39: 5179.57 | T39: 5176.05 | U39: 5177.45 | V39: 5132.45 | W39: 5000.15 | X39: 5184.3 | Y39: 5055.85 | Z39: 5148.3 | AA39: 4190.25 | AB39: 5098.9 | AC39: 5146.3 | AD39: 5152.6 | AE39: 4972.2 | AF39: 132424.32
B40: ELECTROPERU | C40: C.T. TUMBES | D40: MAK1 | E40: TERMOELÉCTRICA | AF40: 0
B41: ELECTROPERU | C41: C.T. TUMBES | D41: MAK2 | E41: TERMOELÉCTRICA | AF41: 0
B42: EMPRESA DE GENERACION ELECTRICA CANCHAYLLO SAC | C42: C.H. CANCHAYLLO | D42: CENTRAL | E42: HIDROELÉCTRICA | F42: 62.4 | G42: 62.4 | H42: 62.4 | I42: 62.2 | J42: 60.2 | K42: 61.55 | L42: 61.95 | M42: 60 | N42: 58.25 | O42: 58.65 | P42: 57.6 | Q42: 57.45 | R42: 54.1 | S42: 54.95 | T42: 54.4 | U42: 54.4 | V42: 50.7 | W42: 47.25 | X42: 48.25 | Y42: 48.05 | Z42: 47.7 | AA42: 48.15 | AB42: 46.1 | AC42: 44.05 | AD42: 47.3 | AE42: 46 | AF42: 1416.45
B43: EMPRESA DE GENERACION ELECTRICA RIO BAÑOS S.A.C. | C43: C.H. RUCUY | D43: CENTRAL | E43: HIDROELÉCTRICA | F43: 346.4 | G43: 343.95 | H43: 330.3 | I43: 325.9 | J43: 323.7 | K43: 282.55 | L43: 240.05 | M43: 240 | N43: 240.1 | O43: 239.8 | P43: 239.7 | Q43: 246.2 | R43: 324.55 | S43: 313.9 | T43: 268.35 | U43: 239.9 | V43: 238.95 | W43: 296.85 | X43: 384.85 | Y43: 382.3 | Z43: 376.1 | AA43: 370.6 | AB43: 361.6 | AC43: 356.65 | AD43: 292 | AE43: 329.7 | AF43: 7934.95
B44: EMPRESA DE GENERACION ELECTRICA SANTA ANA S.A.C. | C44: C.H. RENOVANDES H1 | D44: CENTRAL | E44: HIDROELÉCTRICA | F44: 279.35 | G44: 389.65 | H44: 432 | I44: 480.1 | J44: 484.9 | K44: 467.45 | L44: 434.45 | M44: 481.15 | N44: 482.7 | O44: 480.5 | P44: 480.5 | Q44: 484.45 | R44: 483.55 | S44: 484.2 | T44: 484.5 | U44: 483.25 | V44: 479.3 | W44: 480.8 | X44: 483.65 | Y44: 478.95 | Z44: 465.8 | AA44: 455.6 | AB44: 454.4 | AC44: 453.3 | AD44: 442.85 | AE44: 441.8 | AF44: 11949.15
B45: EMPRESA DE GENERACION HUALLAGA | C45: C.H. CHAGLLA | D45: CENTRAL | E45: HIDROELÉCTRICA | F45: 5030.8 | G45: 3596 | H45: 4892.05 | I45: 3924.95 | J45: 4277.25 | K45: 1374.25 | L45: 2647.85 | M45: 4842.1 | N45: 1639.75 | O45: 2282.8 | P45: 4071.6 | Q45: 3361.9 | R45: 761.90749 | S45: 3443.2 | T45: 1902.6 | U45: 2606.6351 | V45: 4062.2 | W45: 3839 | X45: 1442.65 | Y45: 585.15 | Z45: 3222.5 | AA45: 3187.25 | AB45: 2735.6 | AC45: 4417.2 | AD45: 336.6 | AE45: 1009.2 | AF45: 75492.993
B46: EMPRESA DE GENERACION HUALLAGA | C46: P.C.H. CHAGLLA | D46: CENTRAL | E46: HIDROELÉCTRICA | F46: 156 | G46: 116.8 | H46: 35.75 | I46: 155.45 | J46: 153.75 | K46: 153.8 | L46: 154.3 | M46: 154.15 | N46: 154.1 | O46: 154.5 | P46: 154.85 | Q46: 100.35 | R46: 155.05718 | S46: 156.15 | T46: 156.05 | U46: 155.5038 | V46: 155.95 | W46: 156 | X46: 156 | Y46: 156 | Z46: 156 | AA46: 151.45 | AB46: 154.3 | AC46: 154.4 | AD46: 154.95 | AE46: 155.5 | AF46: 3817.111
B47: EMPRESA DE GENERACION HUANZA | C47: C.H. HUANZA | D47: CENTRAL | E47: HIDROELÉCTRICA | F47: 1180 | G47: 1228.7 | H47: 1318.5 | I47: 1274.25 | J47: 1274.7 | K47: 1309.7 | L47: 1358.1 | M47: 1441.2 | N47: 1461.5 | O47: 1553.45 | P47: 1573.25 | Q47: 1530.4 | R47: 1515.7 | S47: 1269.2 | T47: 1231.05 | U47: 1193.85 | V47: 1189.6 | W47: 1128.9 | X47: 1198.9 | Y47: 1145.95 | Z47: 1039.85 | AA47: 1133.25 | AB47: 1043.95 | AC47: 1055.6 | AD47: 1089.25 | AE47: 1179.7 | AF47: 32918.5
B48: EMPRESA ELECTRICA AGUA AZUL | C48: C.H. POTRERO | D48: CENTRAL | E48: HIDROELÉCTRICA | F48: 367.35 | G48: 353.2 | H48: 327.85 | I48: 314.5 | J48: 295.6 | K48: 274.55 | L48: 253.95 | M48: 244.65 | N48: 240 | O48: 183.3 | P48: 236.35 | Q48: 229.2 | R48: 226.3 | S48: 221.3 | T48: 216.05 | U48: 182.55 | V48: 189.6 | W48: 186.55 | X48: 192.6 | Y48: 184.85 | Z48: 176.1 | AA48: 178.75 | AB48: 183.5 | AC48: 175.6 | AD48: 169.55 | AE48: 172.15 | AF48: 5975.95
B49: EMPRESA ELECTRICA RIO DOBLE | C49: C.H. LAS PIZARRAS | D49: CENTRAL | E49: HIDROELÉCTRICA | F49: 235.35 | G49: 228.5 | H49: 219.35 | I49: 204.8 | J49: 183.05 | K49: 188.05 | L49: 173.55 | M49: 177.8 | N49: 171.5 | O49: 167.75 | P49: 163.5 | Q49: 95.75 | R49: 94.15 | S49: 143.65 | T49: 143.5 | U49: 115.6 | V49: 136 | W49: 129.9 | X49: 129 | Y49: 122.85 | Z49: 116.2 | AA49: 120 | AB49: 110 | AC49: 106.8 | AD49: 110 | AE49: 101 | AF49: 3887.6
B50: ENEL GENERACION PIURA S.A. | C50: C.T. MALACAS 1 | D50: TG6 | E50: TERMOELÉCTRICA | F50: 1117.05 | G50: 1045.15 | H50: 1106 | I50: 818.85 | J50: 1114.3 | K50: 1111.85 | L50: 686.05 | M50: 802.6 | N50: 758.9 | O50: 814.3 | P50: 838.45 | Q50: 1131.3 | R50: 1125.6 | S50: 1142.85 | T50: 1135.55 | U50: 824.1 | V50: 1135.15 | W50: 1128.35 | X50: 1135.1 | Y50: 1122.2 | Z50: 1120.4 | AA50: 819.05 | AB50: 606.7 | AC50: 809.6 | AD50: 1117.15 | AE50: 1118.25 | AF50: 25684.85
B51: ENEL GENERACION PIURA S.A. | C51: C.T. MALACAS 2 | D51: TG4 | E51: TERMOELÉCTRICA | M51: 2.95 | N51: 273.7 | O51: 140.9 | P51: 241.75 | AB51: 764.9 | AF51: 1424.2
B52: ENEL GENERACION PIURA S.A. | C52: C.T. RF DE GENERACION TALARA | D52: TG5 | E52: TERMOELÉCTRICA | AF52: 0
B53: ENERGÍA EÓLICA S.A. | C53: C.E. CUPISNIQUE | D53: CENTRAL | E53: EÓLICA | F53: 622.15 | G53: 405.7 | H53: 167 | I53: 262.7 | J53: 646.05 | K53: 532.75 | L53: 309.25 | M53: 378.85 | N53: 588.95 | O53: 387.3 | P53: 827.5 | Q53: 573.25 | R53: 740.95 | S53: 933.2 | T53: 525.3 | U53: 540.2 | V53: 265.7 | W53: 100.35 | X53: 120.2 | Y53: 684 | Z53: 508.75 | AA53: 542.3 | AB53: 803.35 | AC53: 685.05 | AD53: 870.85 | AE53: 788.4 | AF53: 13810.05
B54: ENERGÍA EÓLICA S.A. | C54: C.E. TALARA | D54: CENTRAL | E54: EÓLICA | F54: 352.9 | G54: 178.65 | H54: 64.65 | I54: 132.1 | J54: 272.3 | K54: 429.25 | L54: 390.15 | M54: 572.2 | N54: 686.05 | O54: 348.8 | P54: 356 | Q54: 263.1 | R54: 260.9 | S54: 604.6 | T54: 527.55 | U54: 551.4 | V54: 574.7 | W54: 586.8 | X54: 323.4 | Y54: 391.3 | Z54: 296.85 | AA54: 297.35 | AB54: 402.2 | AC54: 553.45 | AD54: 545.25 | AE54: 476.55 | AF54: 10438.45
B55: ENERGIA RENOVABLE DEL SUR S.A. | C55: C.E. SAN JUAN | D55: CENTRAL | E55: EÓLICA | F55: 1374.1 | G55: 624.4 | H55: 219.55 | I55: 80.45 | J55: 437.75 | K55: 1310.25 | L55: 1611.85 | M55: 1015.6 | N55: 1278.4 | O55: 2049.6 | P55: 1360.9 | Q55: 1677 | R55: 1565.4 | S55: 1522.7 | T55: 2738.55 | U55: 2279.55 | V55: 1279.45 | W55: 1767.9 | X55: 1449.85 | Y55: 1265.7 | Z55: 1419.25 | AA55: 1576.2 | AB55: 1297.7 | AC55: 1087.8 | AD55: 992.25 | AE55: 1712.85 | AF55: 34995
B56: ENGIE | C56: C.E. PUNTA LOMITAS | D56: PL-BL1 | E56: EÓLICA | F56: 738.25 | G56: 347.05 | H56: 35.15 | I56: 54.8 | J56: 367.15 | K56: 1390.2 | L56: 1461.85 | M56: 526.75 | N56: 1461.8 | O56: 1741.9 | P56: 1127.7 | Q56: 986.85 | R56: 815 | S56: 1588.8 | T56: 1902.85 | U56: 1938.4 | V56: 965.84 | W56: 1150.45 | X56: 1066.2 | Y56: 867.9 | Z56: 871.25 | AA56: 896.6 | AB56: 959.15 | AC56: 781.85 | AD56: 935.55 | AE56: 1638.4 | AF56: 26617.69
B57: ENGIE | C57: C.E. PUNTA LOMITAS | D57: PL-BL2 | E57: EÓLICA | F57: 942.95 | G57: 588.1 | H57: 91 | I57: 96.2 | J57: 526.25 | K57: 1479.6 | L57: 1529.85 | M57: 669.35 | N57: 1570.75 | O57: 1843.75 | P57: 1274.35 | Q57: 1306.4 | R57: 1104.95 | S57: 1817.1 | T57: 1888.3 | U57: 1914.2 | V57: 1239.1 | W57: 1599.15 | X57: 1455.75 | Y57: 1174.1 | Z57: 1236.35 | AA57: 1291.2 | AB57: 1312.05 | AC57: 994.4 | AD57: 1135.3 | AE57: 1875.9 | AF57: 31956.4
B58: ENGIE | C58: C.E. PUNTA LOMITAS_EXP | D58: PUN LOM_EXP-BL1 | E58: EÓLICA | F58: 101.9 | G58: 31.7 | H58: 0.95 | I58: 6.5 | J58: 49.6 | K58: 199.5 | L58: 226.45 | M58: 57.5 | N58: 186.5 | O58: 258.15 | P58: 152.45 | Q58: 147.6 | R58: 112.3 | S58: 247.7 | T58: 323.45 | U58: 277.9 | V58: 128.005 | W58: 153.55 | X58: 152.4 | Y58: 119.65 | Z58: 127.3 | AA58: 127.45 | AB58: 124.95 | AC58: 110.75 | AD58: 132.15 | AE58: 258.55 | AF58: 3814.905
B59: ENGIE | C59: C.E. PUNTA LOMITAS_EXP | D59: PUN LOM_EXP-BL2 | E59: EÓLICA | F59: 69.15 | G59: 15.15 | H59: 0.05 | I59: 2.9 | J59: 25.4 | K59: 145.6 | L59: 176.4 | M59: 45 | N59: 156.7 | O59: 210.1 | P59: 108.75 | Q59: 73.05 | R59: 65.15 | S59: 197.05 | T59: 264.65 | U59: 236.8 | V59: 78.42 | W59: 88.8 | X59: 98.5 | Y59: 86.4 | Z59: 79.5 | AA59: 79.3 | AB59: 91.45 | AC59: 75.05 | AD59: 101.25 | AE59: 177.6 | AF59: 2748.17
B60: ENGIE | C60: C.H. QUITARACSA | D60: CENTRAL | E60: HIDROELÉCTRICA | F60: 354 | I60: 379.9 | K60: 216.55 | N60: 319.6 | Q60: 299.2 | T60: 309.65 | W60: 161.95 | Z60: 301.15 | AC60: 300.6 | AF60: 2642.6
B61: ENGIE | C61: C.H. YUNCAN | D61: CENTRAL | E61: HIDROELÉCTRICA | F61: 1370.3 | G61: 1583.5 | H61: 1360.3 | I61: 1331.7 | J61: 1307.85 | K61: 1085.85 | L61: 1146.1 | M61: 1245.65 | N61: 1164.9 | O61: 889.05 | P61: 1310.3 | Q61: 1074.8 | R61: 1023.45 | S61: 1055.6 | T61: 1017.35 | U61: 955.7 | V61: 1026.41 | W61: 1011.4 | X61: 1135.85 | Y61: 1202.55 | Z61: 1574.7 | AA61: 1610.3 | AB61: 1300.95 | AC61: 1574 | AD61: 1345 | AE61: 1419.5 | AF61: 32123.06
B62: ENGIE | C62: C.S. INTIPAMPA | D62: CENTRAL | E62: SOLAR | F62: 216.9 | G62: 244.45 | H62: 244.5 | I62: 249.9 | J62: 246.9 | K62: 252.75 | L62: 251.8 | M62: 252.55 | N62: 254.1 | O62: 255.65 | P62: 256.45 | Q62: 257.05 | R62: 257.7 | S62: 258.95 | T62: 256.85 | U62: 261.55 | V62: 258.95 | W62: 185.5 | X62: 262.65 | Y62: 263.9 | Z62: 257.95 | AA62: 264.75 | AB62: 264.45 | AC62: 264.25 | AD62: 266.05 | AE62: 267.65 | AF62: 6574.15
B63: ENGIE | C63: C.T. CHILCA 1 | D63: TG1 | E63: TERMOELÉCTRICA | F63: 4265.65 | G63: 4246.3 | H63: 4254.15 | I63: 4241.4 | J63: 4273.85 | K63: 4183.4 | L63: 4243.2 | M63: 4217.15 | N63: 4237.05 | O63: 4253 | P63: 4237.85 | Q63: 4231.55 | R63: 4248 | S63: 4256.8 | T63: 4260 | U63: 4254.3 | V63: 4245.08 | W63: 4254.25 | X63: 4258.65 | Y63: 4227.9 | Z63: 4254.1 | AA63: 4258.15 | AB63: 4266.9 | AC63: 4264.25 | AD63: 4252.85 | AE63: 4229.8 | AF63: 110415.58
B64: ENGIE | C64: C.T. CHILCA 1 | D64: TG2 | E64: TERMOELÉCTRICA | F64: 4221.55 | G64: 4202.2 | H64: 4208.7 | I64: 4194 | J64: 4224.25 | K64: 4144.55 | L64: 4195.4 | M64: 4176 | N64: 4188.35 | O64: 4202.75 | P64: 4188.9 | Q64: 4180.55 | R64: 4189.75 | S64: 4205 | T64: 4205.1 | U64: 4199.15 | V64: 4185.82 | W64: 4196.15 | X64: 4200.75 | Y64: 4177.85 | Z64: 4195.7 | AA64: 4199.8 | AB64: 4207.55 | AC64: 4204.2 | AD64: 4191.25 | AE64: 4181 | AF64: 109066.27
B65: ENGIE | C65: C.T. CHILCA 1 | D65: TG3 | E65: TERMOELÉCTRICA | F65: 4800 | G65: 4800 | H65: 4800 | I65: 4800 | J65: 4800 | K65: 4627.6 | L65: 4800 | M65: 4800 | N65: 4800 | O65: 4800 | P65: 4800 | Q65: 4800 | R65: 5000.1 | S65: 5005.05 | T65: 5007.45 | U65: 4999.8 | V65: 4997.125 | W65: 5015.75 | X65: 5012.6 | Y65: 4852.55 | Z65: 5001.4 | AA65: 5018.05 | AB65: 5027.65 | AC65: 4800 | AD65: 5006.6 | AE65: 4800 | AF65: 126971.73
B66: ENGIE | C66: C.T. CHILCA 1 | D66: TV | E66: TERMOELÉCTRICA | F66: 6582.75 | G66: 6568.75 | H66: 6578.55 | I66: 6568.4 | J66: 6596 | K66: 6466.75 | L66: 6560.7 | M66: 6558.7 | N66: 6557.45 | O66: 6579.55 | P66: 6572.95 | Q66: 6545.75 | R66: 6556.95 | S66: 6569.25 | T66: 6567.85 | U66: 6565.85 | V66: 6544.615 | W66: 6561.05 | X66: 6565.05 | Y66: 6491.55 | Z66: 6562.05 | AA66: 6560.35 | AB66: 6566.9 | AC66: 6566.65 | AD66: 6544.95 | AE66: 6528.8 | AF66: 170488.17
B67: ENGIE | C67: C.T. CHILCA 2 | D67: TG41 | E67: TERMOELÉCTRICA | V67: 737.025 | AF67: 737.025
B68: ENGIE | C68: C.T. CHILCA 2 | D68: TV42 | E68: TERMOELÉCTRICA | AF68: 0
B69: ENGIE | C69: C.T. NEPI | D69: TG41 | E69: TERMOELÉCTRICA | AF69: 0
B70: ENGIE | C70: C.T. NEPI | D70: TG42 | E70: TERMOELÉCTRICA | AF70: 0
B71: ENGIE | C71: C.T. NEPI | D71: TG43 | E71: TERMOELÉCTRICA | AF71: 0
B72: ENGIE | C72: C.T. RF PLANTA ILO | D72: TG1 | E72: TERMOELÉCTRICA | AF72: 0
B73: ENGIE | C73: C.T. RF PLANTA ILO | D73: TG2 | E73: TERMOELÉCTRICA | AF73: 0
B74: ENGIE | C74: C.T. RF PLANTA ILO | D74: TG3 | E74: TERMOELÉCTRICA | AF74: 0
B75: FENIX POWER PERÚ | C75: C.T. FENIX | D75: GT11 | E75: TERMOELÉCTRICA | F75: 4086.3 | G75: 4372.2 | H75: 4385.4981 | I75: 4284.1525 | J75: 4350.1 | K75: 4123.85 | L75: 4373.75 | M75: 4382.1 | N75: 4374.75 | O75: 4377.5 | P75: 4361.45 | Q75: 4377.3 | R75: 4368.75 | S75: 4366.9 | T75: 4374.5 | U75: 4367.2 | V75: 4361.75 | W75: 4371.45 | X75: 4377.1504 | Y75: 3838.2175 | Z75: 4297.25 | AA75: 4383.7 | AB75: 4373.85 | AC75: 4376.35 | AD75: 4367.1 | AE75: 4341.15 | AF75: 112414.27
B76: FENIX POWER PERÚ | C76: C.T. FENIX | D76: GT12 | E76: TERMOELÉCTRICA | F76: 4092.05 | G76: 4383.15 | H76: 4396.2114 | I76: 4196.948 | J76: 544 | K76: 4134.25 | L76: 4380.7 | M76: 4392.15 | N76: 4386.65 | O76: 4386.05 | P76: 4371.5 | Q76: 4386.1 | R76: 4380.1 | S76: 4377 | T76: 4383.85 | U76: 4376 | V76: 4372.05 | W76: 4381.15 | X76: 4384.4421 | Y76: 3847.8753 | Z76: 4306.25 | AA76: 4393 | AB76: 4385.4 | AC76: 4385.7 | AD76: 4377.75 | AE76: 4350.4 | AF76: 108750.73
B77: FENIX POWER PERÚ | C77: C.T. FENIX | D77: TV10 | E77: TERMOELÉCTRICA | F77: 4264.7 | G77: 4413.8 | H77: 4413.8397 | I77: 4319.5261 | J77: 2413.1 | K77: 4283.65 | L77: 4411.85 | M77: 4416.7 | N77: 4418.85 | O77: 4405.65 | P77: 4410.25 | Q77: 4416.15 | R77: 4411 | S77: 4407.4 | T77: 4410.05 | U77: 4409.95 | V77: 4403.6 | W77: 4412.45 | X77: 4413.9265 | Y77: 4128.7961 | Z77: 4375.2 | AA77: 4419.25 | AB77: 4413.85 | AC77: 4412.45 | AD77: 4407.55 | AE77: 4396.4 | AF77: 112009.94
B78: GENERACIÓN ANDINA S.A.C. | C78: C.H. 8 DE AGOSTO | D78: CENTRAL | E78: HIDROELÉCTRICA | F78: 245.55 | G78: 252 | H78: 252 | I78: 252 | J78: 245.85 | K78: 223.7 | L78: 206.85 | M78: 196.5 | N78: 187.8 | O78: 177.4 | P78: 168.8 | Q78: 157.3 | R78: 158.25 | S78: 152.2 | T78: 146.25 | U78: 139.95 | V78: 134.8 | W78: 238.85 | X78: 237.85 | Y78: 225.1915 | Z78: 170.25 | AA78: 138.7 | AB78: 131.7 | AC78: 125.3 | AD78: 121.05 | AE78: 120.65 | AF78: 4806.7415
B79: GENERACIÓN ANDINA S.A.C. | C79: C.H. EL CARMEN | D79: CENTRAL | E79: HIDROELÉCTRICA | F79: 113.7 | G79: 140.6 | H79: 113.3 | I79: 86.1 | J79: 74.65 | K79: 68.7 | L79: 65.95 | M79: 63.4 | N79: 60.8 | O79: 60 | P79: 58.85 | Q79: 57.65 | R79: 56.7 | S79: 55.2 | T79: 54.55 | U79: 52.8 | V79: 52.8 | W79: 78.9 | X79: 70.5 | Y79: 56.532 | Z79: 47.15 | AA79: 47.75 | AB79: 48.2 | AC79: 48 | AD79: 48 | AE79: 51.25 | AF79: 1732.032
B80: GENERADORA DE ENERGÍA DEL PERÚ | C80: C.H. ÁNGEL I | D80: CENTRAL | E80: HIDROELÉCTRICA | F80: 142.1 | G80: 135.2 | H80: 130.3 | I80: 124.55 | J80: 120.95 | K80: 117.25 | L80: 114.3 | M80: 111.2 | N80: 109.6 | O80: 107.05 | P80: 104.5 | Q80: 104.7 | R80: 102.4 | S80: 99.3 | T80: 97.2 | U80: 96.3 | V80: 117.8 | W80: 122.9 | X80: 119.15 | Y80: 112.05 | Z80: 101.95 | AA80: 96.05 | AB80: 92.1 | AC80: 91.3 | AD80: 89.4 | AE80: 87.3 | AF80: 2846.9
B81: GENERADORA DE ENERGÍA DEL PERÚ | C81: C.H. ÁNGEL II | D81: CENTRAL | E81: HIDROELÉCTRICA | F81: 154.7 | G81: 147.75 | H81: 142.95 | I81: 134.15 | J81: 133.25 | K81: 129.6 | L81: 126.7 | M81: 122.45 | N81: 122.1 | O81: 118.55 | P81: 117.7 | Q81: 116.4 | R81: 117.8 | S81: 111.6 | T81: 110.4 | U81: 108.65 | V81: 130.3 | W81: 135.4 | X81: 129.35 | Y81: 124 | Z81: 114.6 | AA81: 107.85 | AB81: 101.85 | AC81: 103.2 | AD81: 101.4 | AE81: 98.9 | AF81: 3161.6
B82: GENERADORA DE ENERGÍA DEL PERÚ | C82: C.H. ÁNGEL III | D82: CENTRAL | E82: HIDROELÉCTRICA | F82: 156.7 | G82: 141.8 | H82: 142.55 | I82: 134.5 | J82: 133.45 | K82: 129.7 | L82: 127.7 | M82: 123.4 | N82: 122.85 | O82: 114.6 | P82: 119.75 | Q82: 117.45 | R82: 117.7 | S82: 114 | T82: 109 | U82: 98.65 | V82: 126.5 | W82: 132.55 | X82: 126.5 | Y82: 127.45 | Z82: 114.3 | AA82: 104.15 | AB82: 98.95 | AC82: 99.5 | AD82: 98.15 | AE82: 100.6 | AF82: 3132.45
B83: GENERADORA DE ENERGÍA DEL PERÚ | C83: C.H. LA JOYA | D83: CENTRAL | E83: HIDROELÉCTRICA | F83: 202.1 | G83: 201.35 | H83: 180.15 | I83: 189 | J83: 175.2 | K83: 172.65 | L83: 176.2 | M83: 184.15 | N83: 178.45 | O83: 178.35 | P83: 183.85 | Q83: 178.65 | R83: 187.15 | S83: 191.15 | T83: 179.75 | X83: 21.4 | Y83: 177.25 | Z83: 211.65 | AA83: 215.95 | AB83: 205.85 | AC83: 209.6 | AD83: 190.7 | AE83: 186.2 | AF83: 4176.75
B84: GM OPERACIONES S.A.C. | C84: CT REFINERIA TALARA | D84: TV1 REF TALARA | E84: TERMOELÉCTRICA | F84: 1026.8 | G84: 1034.95 | H84: 1023.95 | I84: 880.19 | J84: 56.45 | S84: 103.88 | T84: 390 | U84: 832.95 | V84: 805.1343 | W84: 856.6 | X84: 856.8 | Y84: 862.3 | Z84: 885.05 | AA84: 888.1 | AB84: 876.83 | AC84: 856.9215 | AD84: 865.7 | AE84: 868.75 | AF84: 13971.356
B85: GM OPERACIONES S.A.C. | C85: CT REFINERIA TALARA | D85: TV2 REF TALARA | E85: TERMOELÉCTRICA | F85: 807.7 | G85: 840.5 | H85: 841.85 | I85: 707.585 | U85: 35 | V85: 434.74265 | W85: 618 | X85: 607.55 | Y85: 609 | Z85: 646.6 | AA85: 665.6 | AB85: 644.64 | AC85: 612.015 | AD85: 611.65 | AE85: 549.1 | AF85: 9231.5326
B86: GR CORTARRAMA SOCIEDAD ANONIMA CERRADA | C86: C.S. MATARANI | D86: C.S. MATARANI | E86: SOLAR | F86: 492.05 | G86: 559.35 | H86: 561.7 | I86: 555.35 | J86: 566.4 | K86: 571.15 | L86: 452.65 | M86: 457.5 | N86: 578.95 | O86: 586.55 | P86: 574.85 | Q86: 566.3 | R86: 568.55 | S86: 577.25 | T86: 584.65 | U86: 592.4 | V86: 583 | W86: 479.25 | X86: 587.1 | Y86: 587.4 | Z86: 590.7 | AA86: 596.95 | AB86: 597.4 | AC86: 601.8 | AD86: 600.55 | AE86: 598.85 | AF86: 14668.65
B87: GR PAINO SOCIEDAD ANONIMA CERRADA | C87: C.E. HUAMBOS | D87: CENTRAL | E87: EÓLICA | F87: 245.8 | G87: 312 | H87: 403.65 | I87: 249.85 | J87: 276 | K87: 334.15 | L87: 343.15 | M87: 277 | N87: 207.8 | O87: 266.4 | P87: 276 | Q87: 52.25 | R87: 13.55 | S87: 311.95 | T87: 134 | U87: 82.25 | V87: 382.05 | W87: 381.75 | X87: 339.9 | Y87: 238.6 | Z87: 276.25 | AA87: 288.6 | AB87: 330.3 | AC87: 296.05 | AD87: 277.75 | AE87: 215.2 | AF87: 6812.25
B88: GR TARUCA SOCIEDAD ANONIMA CERRADA | C88: C.E. DUNA | D88: CENTRAL | E88: EÓLICA | F88: 328.75 | G88: 363.55 | H88: 422.95 | I88: 334.35 | J88: 362.6 | K88: 400.4 | L88: 399.55 | M88: 341.95 | N88: 285.4 | O88: 350.15 | P88: 358 | Q88: 85.2 | R88: 13.55 | S88: 334.15 | T88: 85.1 | U88: 73.25 | V88: 400.25 | W88: 424.7 | X88: 379.95 | Y88: 290.8 | Z88: 340.25 | AA88: 356 | AB88: 382.2 | AC88: 348.4 | AD88: 328.4 | AE88: 267.85 | AF88: 8057.7
B89: HIDROCAÑETE S.A. | C89: C.H. IMPERIAL | D89: CENTRAL | E89: HIDROELÉCTRICA | F89: 83.65 | G89: 79.1 | H89: 78.4 | I89: 80.05 | J89: 80 | K89: 80.75 | L89: 82 | M89: 82.75 | N89: 79.85 | O89: 79.8 | P89: 78.75 | Q89: 79 | R89: 80.4 | S89: 80.55 | T89: 80.45 | U89: 81 | V89: 79.7 | W89: 78.3 | X89: 78.95 | Y89: 79.2 | Z89: 78.5 | AA89: 78.35 | AB89: 81.9 | AC89: 83.35 | AD89: 81.5 | AE89: 80.55 | AF89: 2086.8
B90: HIDROELECTRICA HUANCHOR S.A.C. | C90: C.H. HUANCHOR | D90: CENTRAL | E90: HIDROELÉCTRICA | F90: 440.7 | G90: 437.5 | H90: 433.85 | I90: 431.85 | J90: 429.35 | K90: 429.2 | L90: 425.6 | M90: 424.4 | N90: 421.35 | O90: 401.4 | P90: 416.3 | Q90: 424.1 | R90: 441.5 | S90: 433.9 | T90: 440.85 | U90: 444.15 | V90: 445.35 | W90: 446.1 | X90: 446.16226 | Y90: 446.05 | Z90: 445.7 | AA90: 445.25 | AB90: 445.4 | AC90: 437.5 | AD90: 445.25 | AE90: 446.15 | AF90: 11324.912
B91: HUAURA POWER GROUP S.A. | C91: C.H. YARUCAYA | D91: CENTRAL | E91: HIDROELÉCTRICA | F91: 444 | G91: 444 | H91: 444 | I91: 444 | J91: 444 | K91: 444 | L91: 444 | M91: 444 | N91: 444 | O91: 443.3 | P91: 439.9 | Q91: 331.3 | R91: 441.6 | S91: 441.6 | T91: 441.6 | U91: 437.55 | V91: 435.4 | W91: 438.55 | X91: 441.6 | Y91: 441.6 | Z91: 435.5 | AA91: 432.05 | AB91: 436.15 | AC91: 439.25 | AD91: 444 | AE91: 444 | AF91: 11360.95
B92: HYDRO GLOBAL PERÚ S.A.C. | C92: CH SAN GABAN III | D92: CENTRAL | E92: HIDROELÉCTRICA | F92: 2406.3 | G92: 2325.45 | H92: 2320.95 | I92: 2321.55 | J92: 2370.8 | K92: 1902.5 | L92: 2153.8 | M92: 2086 | N92: 1894.9 | O92: 2056.2 | P92: 2014.7 | Q92: 1894 | R92: 1775.2 | S92: 1827.65 | T92: 1653.15 | U92: 1841.15 | V92: 1798.05 | W92: 1886.55 | X92: 1935.4 | Y92: 1869.85 | Z92: 1724.05 | AA92: 1689.65 | AB92: 1708.8 | AC92: 1778.5 | AD92: 1648 | AE92: 1777.3 | AF92: 50660.45
B93: INFRAESTRUCTURAS Y ENERGIAS DEL PERU S.A.C. | C93: C.T. RF PTO MALDONADO | D93: CENTRAL | E93: TERMOELÉCTRICA | N93: 0.9 | AF93: 0.9
B94: INFRAESTRUCTURAS Y ENERGIAS DEL PERU S.A.C. | C94: C.T. RF PUCALLPA | D94: CENTRAL | E94: TERMOELÉCTRICA | F94: 1.65 | R94: 445.45 | AA94: 16.3 | AF94: 463.4
B95: INLAND ENERGY SAC | C95: C.H. SANTA TERESA | D95: CENTRAL | E95: HIDROELÉCTRICA | F95: 1814.3 | G95: 1789.25 | H95: 1755.55 | I95: 1759.55 | J95: 1758.45 | K95: 1716.15 | L95: 1678.5 | M95: 1608.05 | N95: 1576.35 | O95: 1549.5 | P95: 1520.35 | Q95: 1524.7 | R95: 1498.95 | S95: 1493.4 | T95: 1468.35 | U95: 1442 | V95: 1435.45 | W95: 1428.65 | X95: 1419.8 | Y95: 1414.8 | Z95: 1402.65 | AA95: 1367.45 | AB95: 1350.95 | AC95: 1346.7 | AD95: 1364.95 | AE95: 1359.6328 | AF95: 39844.433
B96: INVERSIONES SHAQSHA S.A.C. | C96: C.H. PARIAC | D96: CENTRAL | E96: HIDROELÉCTRICA | F96: 34.5 | G96: 29.75 | H96: 29.75 | I96: 29.45 | J96: 30.1 | K96: 29.65 | L96: 30.5 | M96: 30.4 | N96: 28.8 | O96: 30.55 | P96: 30.05 | Q96: 28.8 | R96: 29.1 | S96: 28.8 | T96: 28.7 | U96: 27.7 | V96: 26.5 | W96: 24.2 | X96: 23.6 | Y96: 21.45 | Z96: 23.75 | AA96: 25.5 | AB96: 26.35 | AC96: 25.5 | AD96: 26.1 | AE96: 26.2 | AF96: 725.75
B97: JOYA SOLAR S.A.C. | C97: C.S. SAN MARTIN SOLAR | D97: CENTRAL | E97: SOLAR | F97: 1597.3 | G97: 1904.35 | H97: 1887.6 | I97: 1886.85 | J97: 1909.55 | K97: 1948.7 | L97: 1959.55 | M97: 1909.75 | N97: 1941.7 | O97: 1965.2 | P97: 1940 | Q97: 1917.25 | R97: 1931.3 | S97: 1974.9 | T97: 1990.05 | U97: 1983.65 | V97: 1959.35 | W97: 1605.9 | X97: 1974.2 | Y97: 1973.25 | Z97: 1979.95 | AA97: 107.8 | AB97: 1848.5 | AC97: 2015.85 | AD97: 2003.75 | AE97: 1998.4 | AF97: 48114.65
B98: KALLPA GENERACION S.A. | C98: C.H. CERRO DEL AGUILA | D98: CENTRAL | E98: HIDROELÉCTRICA | F98: 10774.75 | G98: 9516.15 | H98: 9537.2 | I98: 9202.7 | J98: 9620.7 | K98: 7140.65 | L98: 9066.05 | M98: 8791.3 | N98: 7296.65 | O98: 6824.55 | P98: 7960.05 | Q98: 8315.7 | R98: 7399.35 | S98: 7734.2 | T98: 6725.85 | U98: 6717.8 | V98: 7466 | W98: 7766.55 | X98: 6655.5 | Y98: 6636.9 | Z98: 7925.05 | AA98: 8142.85 | AB98: 6869.95 | AC98: 8318.65 | AD98: 7794.45 | AE98: 7540.25 | AF98: 207739.8
B99: KALLPA GENERACION S.A. | C99: C.T. KALLPA | D99: TG1 | E99: TERMOELÉCTRICA | F99: 3800.5 | G99: 4078.25 | H99: 4318.55 | I99: 4329.25 | J99: 4102 | K99: 3439.75 | L99: 4100.4 | M99: 4306.15 | N99: 4336.45 | O99: 4253.9 | P99: 4308.6 | Q99: 4406.65 | R99: 3854.3 | S99: 4054.4 | T99: 3878.7 | U99: 3924.8 | V99: 4204.35 | W99: 4304.25 | X99: 4325.8 | Y99: 3493.65 | Z99: 4368.35 | AA99: 4493.7 | AB99: 4131.35 | AC99: 4465.45 | AD99: 4346.3 | AE99: 555.05 | AF99: 104180.9
B100: KALLPA GENERACION S.A. | C100: C.T. KALLPA | D100: TG2 | E100: TERMOELÉCTRICA | F100: 3838.85 | G100: 4136.05 | H100: 4496.35 | I100: 4499.85 | J100: 4211.4 | K100: 3464.05 | L100: 4176 | M100: 4459.4 | N100: 4538.3 | O100: 4406.3 | P100: 4449.95 | Q100: 4619.95 | R100: 3936.3 | S100: 4289.55 | T100: 4033.35 | U100: 4130.85 | V100: 4407.3 | W100: 4493.4 | X100: 4471.9 | Y100: 4134.25 | Z100: 4621.05 | AA100: 4957.65 | AB100: 4380.35 | AC100: 4888.2 | AD100: 4852.1 | AE100: 4243.8 | AF100: 113136.5
B101: KALLPA GENERACION S.A. | C101: C.T. KALLPA | D101: TG3 | E101: TERMOELÉCTRICA | F101: 3835.2 | G101: 4138.35 | H101: 4501.1 | I101: 4512.4 | J101: 4213.55 | K101: 3465.9 | L101: 4184.6 | M101: 4472.15 | N101: 4548.65 | O101: 4413.9 | P101: 4434.5 | Q101: 4677.8 | R101: 3949.8 | S101: 4335.2 | T101: 4053 | U101: 4142 | V101: 4423.7 | W101: 4488.9 | X101: 4475.5 | Y101: 3588.45 | Z101: 4414.6 | AA101: 5030.95 | AB101: 4396.6 | AC101: 4947.9 | AD101: 4906.95 | AE101: 4290.5 | AF101: 112842.15
B102: KALLPA GENERACION S.A. | C102: C.T. KALLPA | D102: TV | E102: TERMOELÉCTRICA | F102: 6014.25 | G102: 6303.2 | H102: 6572.85 | I102: 6606.1 | J102: 6284.15 | K102: 5779.4 | L102: 6368 | M102: 6577.9 | N102: 6584.1 | O102: 6544.9 | P102: 6539.45 | Q102: 6650.25 | R102: 6084.5 | S102: 6354.1 | T102: 6195.75 | U102: 6294.6 | V102: 6506.5 | W102: 6518.15 | X102: 6596.65 | Y102: 6017.55 | Z102: 6616.95 | AA102: 6915.6 | AB102: 6483.15 | AC102: 6906.3 | AD102: 6774.35 | AE102: 4573.1 | AF102: 165661.8
B103: KALLPA GENERACION S.A. | C103: C.T. LAS FLORES | D103: TG1 | E103: TERMOELÉCTRICA | F103: 4820.85 | G103: 4680.8 | H103: 4055.95 | I103: 5138.05 | J103: 5172.7 | K103: 4487.05 | L103: 5143.8 | M103: 5131.75 | N103: 5134.15 | O103: 5162.95 | P103: 5148.1 | Q103: 5132.75 | R103: 5139.6 | S103: 5152.35 | T103: 5169 | U103: 5175 | V103: 5149 | W103: 5165.15 | X103: 5188.35 | Y103: 5039.8 | Z103: 5176.15 | AA103: 5162.75 | AB103: 5172.45 | AC103: 5086.5 | AD103: 5152.7 | AE103: 5140.45 | AF103: 131278.15
...

Sheet G_AREAS
B3: sábado, 26 de Julio del 2025
B5: HORA | C5: RESUMEN DE GENERACIÓN POR ÁREAS DEL SEIN | D5: RESUMEN DE GENERACIÓN POR ÁREAS DEL SEIN | E5: RESUMEN DE GENERACIÓN POR ÁREAS DEL SEIN | F5: RESUMEN DE GENERACIÓN POR ÁREAS DEL SEIN | G5: RESUMEN DE GENERACIÓN POR ÁREAS DEL SEIN | H5: RESUMEN DE GENERACIÓN POR ÁREAS DEL SEIN | I5: RESUMEN DE GENERACIÓN POR ÁREAS DEL SEIN | J5: RESUMEN DE GENERACIÓN POR ÁREAS DEL SEIN | K5: RESUMEN DE GENERACIÓN POR ÁREAS DEL SEIN | L5: RESUMEN DE GENERACIÓN POR ÁREAS DEL SEIN | M5: RESUMEN DE GENERACIÓN POR ÁREAS DEL SEIN | N5: RESUMEN DE GENERACIÓN POR ÁREAS DEL SEIN | O5: RESUMEN DE GENERACIÓN POR ÁREAS DEL SEIN | P5: RESUMEN DE GENERACIÓN POR ÁREAS DEL SEIN | Q5: RESUMEN DE GENERACIÓN POR ÁREAS DEL SEIN | R5: RESUMEN DE GENERACIÓN POR ÁREAS DEL SEIN | S5: HORA | T5: GENERACIÓN POR TIPO DE GENERACIÓN | U5: GENERACIÓN POR TIPO DE GENERACIÓN | V5: GENERACIÓN POR TIPO DE GENERACIÓN | W5: GENERACIÓN POR TIPO DE GENERACIÓN | X5: GENERACIÓN POR TIPO DE GENERACIÓN | Y5: HORA | Z5: GENERACIÓN POR TIPO DE GENERACIÓN | AA5: GENERACIÓN POR TIPO DE GENERACIÓN | AB5: GENERACIÓN POR TIPO DE GENERACIÓN | AC5: GENERACIÓN POR TIPO DE GENERACIÓN | AD5: GENERACIÓN POR TIPO DE GENERACIÓN
C6: NORTE | D6: NORTE | E6: NORTE | F6: NORTE | G6: CENTRO | H6: CENTRO | I6: CENTRO | J6: CENTRO | K6: SUR | L6: SUR | M6: SUR | N6: SUR | O6: GENERACIÓN INTEGRANTES COES | P6: GENERACIÓN INTEGRANTES COES | Q6: GENERACIÓN INTEGRANTES COES | R6: GENERACIÓN INTEGRANTES COES | T6: INTEGRANTES COES | U6: INTEGRANTES COES | V6: INTEGRANTES COES | W6: INTEGRANTES COES | X6: INTEGRANTES COES | Z6: INTEGRANTES COES RER | AA6: INTEGRANTES COES RER | AB6: INTEGRANTES COES RER | AC6: INTEGRANTES COES RER | AD6: INTEGRANTES COES RER
C7: GENERACIÓN HIDROELÉCTRICA NORTE | D7: GENERACIÓN TERMOELÉCTRICA NORTE | E7: GENERACIÓN SOLAR NORTE | F7: GENERACIÓN EÓLICA NORTE | G7: GENERACIÓN HIDROELÉCTRICA CENTRO | H7: GENERACIÓN TERMOELÉCTRICA CENTRO | I7: GENERACIÓN SOLAR CENTRO | J7: GENERACIÓN EÓLICA CENTRO | K7: GENERACIÓN HIDROELÉCTRICA SUR | L7: GENERACIÓN TERMOELÉCTRICA SUR | M7: GENERACIÓN SOLAR SUR | N7: GENERACIÓN EÓLICA SUR | O7: GENERACIÓN COES NORTE | P7: GENERACIÓN COES CENTRO | Q7: GENERACIÓN COES SUR | R7: TOTAL GENERACION | T7: HIDROELÉCTRICA | U7: TERMOELÉCTRICA | V7: SOLAR | W7: EÓLICA | X7: TOTAL GENERACION | Z7: HIDROELÉCTRICA RER | AA7: TERMOELÉCTRICA RER | AB7: SOLAR RER | AC7: EÓLICA RER | AD7: TOTAL RER
B8: 00:30 | C8: 199.5 | D8: 138.3 | E8: 0 | F8: 46.7 | G8: 2518.3 | H8: 3150.3 | I8: 0 | J8: 142.2 | K8: 495.6 | L8: 0 | M8: 0 | N8: 0 | O8: 384.5 | P8: 5810.8 | Q8: 495.6 | R8: 6690.9 | S8: 00:30 | T8: 3213.4 | U8: 3288.6 | V8: 0 | W8: 188.9 | X8: 6690.9 | Y8: 00:30 | Z8: 174.6 | AA8: 61.5 | AB8: 0 | AC8: 188.9 | AD8: 425
B9: 01:00 | C9: 183.4 | D9: 137 | E9: 0 | F9: 47.1 | G9: 2494.6 | H9: 3157.5 | I9: 0 | J9: 149.8 | K9: 332.7 | L9: 0 | M9: 0 | N9: 0 | O9: 367.5 | P9: 5801.9 | Q9: 332.7 | R9: 6502.1 | S9: 01:00 | T9: 3010.7 | U9: 3294.5 | V9: 0 | W9: 196.9 | X9: 6502.1 | Y9: 01:00 | Z9: 174.3 | AA9: 61 | AB9: 0 | AC9: 196.9 | AD9: 432.2
B10: 01:30 | C10: 111.2 | D10: 137.5 | E10: 0 | F10: 43.8 | G10: 2405.9 | H10: 3161.2 | I10: 0 | J10: 163 | K10: 335 | L10: 0 | M10: 0 | N10: 0 | O10: 292.5 | P10: 5730.1 | Q10: 335 | R10: 6357.6 | S10: 01:30 | T10: 2852.1 | U10: 3298.7 | V10: 0 | W10: 206.8 | X10: 6357.6 | Y10: 01:30 | Z10: 162.5 | AA10: 60.2 | AB10: 0 | AC10: 206.8 | AD10: 429.5
B11: 02:00 | C11: 112.8 | D11: 137.1 | E11: 0 | F11: 42.2 | G11: 2475 | H11: 3154.5 | I11: 0 | J11: 152.3 | K11: 331.6 | L11: 0 | M11: 0 | N11: 0 | O11: 292.1 | P11: 5781.8 | Q11: 331.6 | R11: 6405.5 | S11: 02:00 | T11: 2919.4 | U11: 3291.6 | V11: 0 | W11: 194.5 | X11: 6405.5 | Y11: 02:00 | Z11: 166.2 | AA11: 59.7 | AB11: 0 | AC11: 194.5 | AD11: 420.4
B12: 02:30 | C12: 114.6 | D12: 135.5 | E12: 0 | F12: 51.6 | G12: 2406.1 | H12: 3145.1 | I12: 0 | J12: 175.4 | K12: 315.1 | L12: 0 | M12: 0 | N12: 0 | O12: 301.7 | P12: 5726.6 | Q12: 315.1 | R12: 6343.4 | S12: 02:30 | T12: 2835.8 | U12: 3280.6 | V12: 0 | W12: 227 | X12: 6343.4 | Y12: 02:30 | Z12: 166 | AA12: 59.2 | AB12: 0 | AC12: 227 | AD12: 452.2
B13: 03:00 | C13: 113.5 | D13: 140.6 | E13: 0 | F13: 48.3 | G13: 2439.9 | H13: 3154.3 | I13: 0 | J13: 135.9 | K13: 317.9 | L13: 0 | M13: 0 | N13: 0 | O13: 302.4 | P13: 5730.1 | Q13: 317.9 | R13: 6350.4 | S13: 03:00 | T13: 2871.3 | U13: 3294.9 | V13: 0 | W13: 184.2 | X13: 6350.4 | Y13: 03:00 | Z13: 165.2 | AA13: 61.1 | AB13: 0 | AC13: 184.2 | AD13: 410.5
B14: 03:30 | C14: 114 | D14: 140 | E14: 0 | F14: 50.3 | G14: 2430.8 | H14: 3160 | I14: 0 | J14: 137 | K14: 304.3 | L14: 0 | M14: 0 | N14: 0 | O14: 304.3 | P14: 5727.8 | Q14: 304.3 | R14: 6336.4 | S14: 03:30 | T14: 2849.1 | U14: 3300 | V14: 0 | W14: 187.3 | X14: 6336.4 | Y14: 03:30 | Z14: 165.4 | AA14: 60.7 | AB14: 0 | AC14: 187.3 | AD14: 413.4
B15: 04:00 | C15: 112.6 | D15: 139.3 | E15: 0 | F15: 45.7 | G15: 2408.4 | H15: 3152.1 | I15: 0 | J15: 140.4 | K15: 316.4 | L15: 0 | M15: 0 | N15: 0 | O15: 297.6 | P15: 5700.9 | Q15: 316.4 | R15: 6314.9 | S15: 04:00 | T15: 2837.4 | U15: 3291.4 | V15: 0 | W15: 186.1 | X15: 6314.9 | Y15: 04:00 | Z15: 165.3 | AA15: 59.9 | AB15: 0 | AC15: 186.1 | AD15: 411.3
B16: 04:30 | C16: 113 | D16: 142.6 | E16: 0 | F16: 42.7 | G16: 2402 | H16: 3137 | I16: 0 | J16: 133.7 | K16: 373.9 | L16: 0 | M16: 0 | N16: 0 | O16: 298.3 | P16: 5672.7 | Q16: 373.9 | R16: 6344.9 | S16: 04:30 | T16: 2888.9 | U16: 3279.6 | V16: 0 | W16: 176.4 | X16: 6344.9 | Y16: 04:30 | Z16: 162.3 | AA16: 60.8 | AB16: 0 | AC16: 176.4 | AD16: 399.5
B17: 05:00 | C17: 134.2 | D17: 143.3 | E17: 0 | F17: 41.9 | G17: 2174.4 | H17: 3140.8 | I17: 0 | J17: 150.6 | K17: 404.6 | L17: 0 | M17: 0 | N17: 0 | O17: 319.4 | P17: 5465.8 | Q17: 404.6 | R17: 6189.8 | S17: 05:00 | T17: 2713.2 | U17: 3284.1 | V17: 0 | W17: 192.5 | X17: 6189.8 | Y17: 05:00 | Z17: 171.2 | AA17: 62.3 | AB17: 0 | AC17: 192.5 | AD17: 426
B18: 05:30 | C18: 136.6 | D18: 142.4 | E18: 0 | F18: 40.5 | G18: 2192.8 | H18: 3130.6 | I18: 0 | J18: 285.9 | K18: 415.2 | L18: 0 | M18: 0 | N18: 0 | O18: 319.5 | P18: 5609.3 | Q18: 415.2 | R18: 6344 | S18: 05:30 | T18: 2744.6 | U18: 3273 | V18: 0 | W18: 326.4 | X18: 6344 | Y18: 05:30 | Z18: 170.7 | AA18: 61.3 | AB18: 0 | AC18: 326.4 | AD18: 558.4
B19: 06:00 | C19: 136.5 | D19: 143.5 | E19: 0 | F19: 42.2 | G19: 2198.1 | H19: 3129.5 | I19: 0 | J19: 338.7 | K19: 359.2 | L19: 0 | M19: 0.1 | N19: 0 | O19: 322.2 | P19: 5666.3 | Q19: 359.3 | R19: 6347.8 | S19: 06:00 | T19: 2693.8 | U19: 3273 | V19: 0.1 | W19: 380.9 | X19: 6347.8 | Y19: 06:00 | Z19: 169.6 | AA19: 61.7 | AB19: 0.1 | AC19: 380.9 | AD19: 612.3
... B56: TOTAL MWh | C56: 3722.4 | D56: 3383.6 | E56: 2.85 | F56: 1748 | G56: 52609.8 | H56: 76623.85 | I56: 8.3 | J56: 10720.15 | K56: 10287.233 | L56: 0 | M56: 5438.65 | N56: 0 | O56: 8856.85 | P56: 139962.1 | Q56: 15725.883 | R56: 164544.83 | S56: TOTAL MWh | T56: 66619.433 | U56: 80007.45 | V56: 5449.8 | W56: 12468.15 | X56: 164544.83 | Y56: TOTAL MWh | Z56: 4206.55 | AA56: 1436.25 | AB56: 5449.8 | AC56: 12468.15 | AD56: 23560.75

Sheet HOP
B3: sábado, 26 de Julio del 2025
B5: Reporte de Horas de Operación
B6: Empresa | C6: Central | D6: Grupo | E6: Modo de Operación | F6: Inicio | G6: Final | H6: O. Arranque | I6: O. Parada | J6: Tipo Operación | K6: Ensayo de Potencia Efectiva | L6: Ensayo de Potencia Mínima | M6: Sistema | N6: Lim. Transm. | O6: Causa | P6: Observación
B7: AGRO INDUSTRIAL PARAMONGA S.A. | C7: C.T. PARAMONGA | D7: CENTRAL | E7: PARAMONGA - BAGAZO | F7: 26/07/2025 00:00:00 | G7: 27/07/2025 00:00:00 | J7: NO IDENTIFICADO | O7: ...
B8: AGROAURORA S.A.C. | C8: C.T. MAPLE ETANOL | D8: CENTRAL | E8: MAPLE- BAGAZO | F8: 26/07/2025 00:00:00 | G8: 27/07/2025 00:00:00 | J8: NO IDENTIFICADO | O8: ...
B9: AGROINDUSTRIAS SAN JACINTO S.A.A. | C9: C.T. SAN JACINTO | D9: CENTRAL | E9: SAN_JACINTO - BAGAZO | F9: 26/07/2025 00:00:00 | G9: 27/07/2025 00:00:00 | J9: NO IDENTIFICADO | O9: ...
B10: BIOENERGIA DEL CHIRA S.A. | C10: C.T. CAÑA BRAVA | D10: G-1 | E10: CANA BRAVA TV1 - BAGAZO | F10: 26/07/2025 00:00:00 | G10: 26/07/2025 04:59:00 | J10: NO IDENTIFICADO | O10: ...
B11: BIOENERGIA DEL CHIRA S.A. | C11: C.T. CAÑA BRAVA | D11: CENTRAL | E11: CANA BRAVA TV1 & TV2 - BAGAZO | F11: 26/07/2025 04:59:00 | G11: 26/07/2025 09:10:00 | J11: NO IDENTIFICADO | O11: ...
B12: BIOENERGIA DEL CHIRA S.A. | C12: C.T. CAÑA BRAVA | D12: G-1 | E12: CANA BRAVA TV1 - BAGAZO | F12: 26/07/2025 09:10:00 | G12: 26/07/2025 18:35:00 | J12: NO IDENTIFICADO | O12: ...
B13: BIOENERGIA DEL CHIRA S.A. | C13: C.T. CAÑA BRAVA | D13: CENTRAL | E13: CANA BRAVA TV1 & TV2 - BAGAZO | F13: 26/07/2025 18:35:00 | G13: 26/07/2025 20:32:00 | J13: NO IDENTIFICADO | O13: ...
B14: BIOENERGIA DEL CHIRA S.A. | C14: C.T. CAÑA BRAVA | D14: G-1 | E14: CANA BRAVA TV1 - BAGAZO | F14: 26/07/2025 20:32:00 | G14: 27/07/2025 00:00:00 | J14: NO IDENTIFICADO | O14: ...
B15: EGESUR | C15: C.T. INDEPENDENCIA | D15: CENTRAL | E15: INDEPENDENCIA GAS | F15: 26/07/2025 00:00:00 | G15: 26/07/2025 00:14:00 | J15: POR POTENCIA O ENERGIA | O15: ...
B16: EGESUR | C16: C.T. INDEPENDENCIA | D16: CENTRAL | E16: INDEPENDENCIA GAS | F16: 26/07/2025 00:14:00 | G16: 26/07/2025 00:25:00 | I16: 26/07/2025 00:14:01 | J16: A MINIMA CARGA | O16: ...
