Workbook

Sheet EVENTOS
B3: jueves, 15 de Mayo del 2025
B5: INFORMACIÓN DE EVENTOS PRINCIPALES EN SUS INSTALACIONES
B6: TIPO DE EVENTO | C6: EMPRESA | D6: UBICACIÓN | E6: TIPO DE EQUIPO | F6: EQUIPO | G6: INICIO | H6: FINAL | I6: DESCRIPCIÓN | J6: MW INDISP. | K6: INTERRUPCIÓN (SI/NO) | L6: TENSIÓN DE FALLA (kV)
B7: P.ENERG | C7: CONCESIONARIA LINEA DE TRANSMISIÓN LA NIÑA S.A.C. | D7: LA NIÑA - MIGUEL GRAU | E7: LINEA DE TRANSMISION | F7: L-5012 | G7: 15/05/2025 17:46:00 | H7: 15/05/2025 17:46:00 | I7: PRIMERA ENERGIZACIÓN DE LA LÍNEA L-5012 (LA NIÑA - MIGUEL GRAU) DE 500 KV Y DE LA S.E. MIGUEL GRAU 500 KV | K7: NO
B8: EVENTO | C8: CONELSUR LT SAC | D8: PORTILLO | E8: SUBESTACION | F8: SS.EE. | G8: 15/05/2025 00:00:00 | H8: 16/05/2025 00:00:00 | I8: DECLARACIÓN DE SITUACIÓN EXCEPCIONAL EN LA S.E. PORTILLO DE 60 kV | K8: NO
B9: FALLA | C9: ELECTRONOROESTE S.A. | D9: PIURA OESTE - CATACAOS | E9: LINEA DE TRANSMISION | F9: L-6560 | G9: 15/05/2025 12:40:08 | H9: 15/05/2025 18:11:00 | I9: DESCONEXION DE LA LÍNEA L-6560 (PIURA OESTE - CATACAOS) 60 KV | J9: 17.79 | K9: SI | L9: 60
B10: FALLA | C10: EMPRESA DE GENERACION HUALLAGA | D10: CHAGLLA | E10: GENERADOR HIDROELÉCTRICO | F10: G1 | G10: 15/05/2025 08:56:19 | H10: 15/05/2025 09:24:43 | I10: DESCONEXIÓN DEL GRUPO G1 DE LA C.H. CHAGLLA | K10: NO | L10: 13.8

Sheet RESTRIC_OPE
B3: jueves, 15 de Mayo del 2025
B5: RESTRICCIONES OPERATIVAS
B6: FECHA | C6: HORA INICIO | D6: HORA FINAL | E6: EMPRESA | F6: UBICACIÓN | G6: T.Eq. | H6: EQUIPO | I6: DESCRIPCIÓN
B7: 15/05/2025 | C7: 00:00 | D7: 24:00 | E7: CELEPSA | F7: C.H. EL PLATANAL | G7: CH | H7: CENTRAL | I7: Debido al incremento del caudal del rio cañete y establecimiento de la temporada de avenida, se declara la C.H. El Platanal como CENTRAL HIDRÁULICA DE PASADA (correo 03/01/2025).
B8: 15/05/2025 | C8: 00:00 | D8: 24:00 | E8: EGASA | F8: C.H. CHARCANI II | G8: GH | H8: G2 | I8: El Grupo N°02 esta operando con una potencia no mayor a 0.07MW en referencia a 0.18MW de su potencia efectiva, con el fin de no generar daños mayores hasta la reparación de su cojinete.
B9: 15/05/2025 | C9: 00:00 | D9: 24:00 | E9: EGASA | F9: C.H. CHARCANI V | G9: EMB | H9: CAMPANARIO | I9: La CH Charcani V no puede despachar menor a 70 MW aprox. dado que debe controlar el caudal de salida del dique de Campanario, de acuerdo con lo comunicado el día 12.05.2025
B10: 15/05/2025 | C10: 00:00 | D10: 24:00 | E10: EGASA | F10: S.E. CONVERTIDOR | G10: BARRA | H10: BARRA138KV | I10: EGASA limitó la capacidad del transformador 138 kV/33 kV a 50 MVA por deterioro del aislamiento.
B11: 15/05/2025 | C11: 00:00 | D11: 24:00 | E11: ENEL GENERACION PIURA S.A. | F11: C.T. MALACAS | G11: CT | H11: CENTRAL | I11: De acuerdo con la comunicación vía correo del día 24.10.2024. ENEL GENERACIÓN PIURA informa una restricción de potencia para alcanzar 105 MW en simultaneo (TG6+TGN4).
B12: 15/05/2025 | C12: 00:00 | D12: 24:00 | E12: ENGIE | F12: C.E. PUNTA LOMITAS | G12: CE | H12: CENTRAL | I12: De acuerdo a la carta ENG/737-2024 (Exp:202400007555). Limitación de cables de media tensión a 100 MW de los transformadores PLT1 y PLT2 de la CE Punta Lomitas. Quedan limitados a 200 MW la generación de CE Punta Lomitas y Punta Lomitas Extensión.
B13: 15/05/2025 | C13: 00:00 | D13: 24:00 | E13: ENGIE | F13: C.H. QUITARACSA | G13: CH | H13: CENTRAL | I13: De acuerdo con el correo del 23.04 se considera la operación continua de la CH Quitaracsa debido a que el sistema de refrigeración de la CH Cañón del Pato se alimenta desde la descarga del caudal turbinado por la CH Quitaracsa.
B14: 15/05/2025 | C14: 00:00 | D14: 24:00 | E14: ENGIE | F14: C.H. YUNCÁN | G14: GH | H14: G3 | I14: Según la carta N° ENG/ 198-2024 enviada por su representada, se opera de forma continua el G3 de la CH Yuncán, debido a la ejecución de mantenimientos necesarios para evitar daños en los sellos de seguridad de la válvula esférica del grupo.
B15: 15/05/2025 | C15: 00:00 | D15: 24:00 | E15: ENGIE | F15: C.T. CHILCA 1 | G15: CT | H15: CENTRAL | I15: Restricción de temperatura de la C.T Chilca, ver valor en el modelo de despacho.
B16: 15/05/2025 | C16: 00:00 | D16: 24:00 | E16: ENGIE | F16: C.T. CHILCA 1 | G16: CT | H16: CENTRAL | I16: Con carta ENG/971-2023, indica que no puede cumplir con las IO considerada en el PDO_17122023 dado que vulneran la seguridad de sus activos. Indican que se debe tomar TMO=168h.
B17: 15/05/2025 | C17: 00:00 | D17: 24:00 | E17: ENGIE | F17: C.T. CHILCA 2 | G17: CT | H17: CENTRAL | I17: Con carta ENG/971-2023, indica que no puede cumplir con las IO considerada en el PDO_17122023 dado que vulneran la seguridad de sus activos. Indican que se debe tomar TMO=168h.
... B52: 15/05/2025 | C52: 00:00 | D52: 24:00 | E52: TERMOSELVA | F52: C.T. AGUAYTÍA | G52: CT | H52: CENTRAL | I52: Restricción de 19 MMPCD de GN para la CT Aguaytía.

Sheet MANTENIMIENTO EJECUTADOS
B3: jueves, 15 de Mayo del 2025
B5: Mantenimiento Ejecutado
B6: Empresa | C6: Ubicación | D6: Equipo | E6: Inicio | F6: Final | G6: Descripción | H6: MW Indisp. | I6: Prog. | J6: Dispon | K6: Interrupc. | L6: Tipo | M6: CodEq | N6: TipoEq_Osinerg
B7: AGROAURORA S.A.C. | C7: MAPLE ETANOL | D7: CENTRAL | E7: 15/05/2025 00:00 | F7: 16/05/2025 00:00 | G7: CENTRAL TERMOELECTRICA FUERA DE SERVICIO POR FALTA DE MATERIA PRIMA PARA LOS REQUERIMIENTOS DE CALOR UTIL EN FABRICA. | H7: 17 | I7: P | J7: F/S | K7: N | L7: OTROS | M7: 13417 | N7: G
B8: AGROAURORA S.A.C. | C8: MAPLE ETANOL | D8: CENTRAL | E8: 15/05/2025 00:00 | F8: 16/05/2025 00:00 | G8: MANTENIMIENTO PREVENTIVO PROGRAMADO DE LA CENTRAL TERMOELECTRICA Y EQUIPOS AUXILIARES. | H8: 17 | I8: P | J8: F/S | K8: N | L8: PREV. | M8: 13417 | N8: G
B9: AGROINDUSTRIAS SAN JACINTO S.A.A. | C9: SAN JACINTO | D9: CENTRAL | E9: 15/05/2025 00:00 | F9: 16/05/2025 00:00 | G9: Mantenimiento Anual. | H9: 8.15 | I9: P | J9: F/S | K9: N | L9: PREV. | M9: 19865 | N9: G
B10: ASOCIACION SANTA LUCIA DE CHACAS | C10: CH HUALLIN | D10: CENTRAL | E10: 15/05/2025 08:00 | F10: 15/05/2025 10:07 | G10: DESARENADO DE BOCATOMA | H10: 2.7 | I10: P | J10: F/S | K10: N | L10: PREV. | M10: 23678 | N10: G
B11: ATLANTICA TRANSMISION SUR S.A. | C11: MONTALVO | D11: ACOPLE 220 | E11: 15/05/2025 00:00 | F11: 16/05/2025 00:00 | G11: Proyecto Refuerzos: Reemplazo del HMI existente, Pruebas y Configuracion. No se contara con nivel 1 de operacion. | H11: 0 | I11: P | J11: E/S | K11: N | L11: P.ENERG | M11: 14767 | N11: T
B12: ATLANTICA TRANSMISION SUR S.A. | C12: MONTALVO | D12: BARRA A_220KV | E12: 15/05/2025 00:00 | F12: 16/05/2025 00:00 | G12: Proyecto Refuerzos: Indisponibilidad de la proteccion diferencial de barras 220 kV por Conexion de la nueva UB-87B hacia la UC existente,Configuracion y Pruebas. | H12: 0 | I12: P | J12: E/S | K12: N | L12: P.ENERG | M12: 13869 | N12: T
B13: ATLANTICA TRANSMISION SUR S.A. | C13: MONTALVO | D13: BARRA A_500KV | E13: 15/05/2025 00:00 | F13: 16/05/2025 00:00 | G13: Proyecto Refuerzos: Indisponibilidad de la proteccion diferencial de barras 500kV por conexion de nueva UB-87B hacia la UC existente, Configuracion y Pruebas. | H13: 0 | I13: P | J13: E/S | K13: N | L13: P.ENERG | M13: 13870 | N13: T
B14: ATLANTICA TRANSMISION SUR S.A. | C14: MONTALVO | D14: BARRA B_220kV | E14: 15/05/2025 00:00 | F14: 16/05/2025 00:00 | G14: Proyecto Refuerzos: Indisponibilidad de la proteccion diferencial de barras 220 kV por Conexion de la nueva UB-87B hacia la UC existente,Configuracion y Pruebas. | H14: 0 | I14: P | J14: E/S | K14: N | L14: P.ENERG | M14: 14765 | N14: T
B15: ATLANTICA TRANSMISION SUR S.A. | C15: MONTALVO | D15: BARRA B_500KV | E15: 15/05/2025 00:00 | F15: 16/05/2025 00:00 | G15: Proyecto Refuerzos: Indisponibilidad de la proteccion diferencial de barras 500kV por conexion de nueva UB-87B hacia la UC existente, Configuracion y Pruebas. | H15: 0 | I15: P | J15: E/S | K15: N | L15: P.ENERG | M15: 13871 | N15: T
B16: ATLANTICA TRANSMISION SUR S.A. | C16: MONTALVO | D16: CL-2057 | E16: 15/05/2025 00:00 | F16: 16/05/2025 00:00 | G16: Proyecto Refuerzos: Reemplazo del HMI existente, Pruebas y Configuracion. No se contara con nivel 1 de operacion. | H16: 0 | I16: P | J16: E/S | K16: N | L16: P.ENERG | M16: 13812 | N16: T
B17: ATLANTICA TRANSMISION SUR S.A. | C17: MONTALVO | D17: CL-AUT-5671_500 | E17: 15/05/2025 00:00 | F17: 16/05/2025 00:00 | G17: Proyecto Refuerzos: Reemplazo del HMI existente, Pruebas y Configuracion. No se contara con nivel 1 de operacion en INT-5671, INT-5652 y SAT-5671. | H17: 0 | I17: P | J17: E/S | K17: N | L17: P.ENERG | M17: 13809 | N17: T
B18: ATLANTICA TRANSMISION SUR S.A. | C18: MONTALVO | D18: INT-5652 | E18: 15/05/2025 00:00 | F18: 16/05/2025 00:00 | G18: Proyecto Refuerzos:Indisponible por Implementacion de conexion de corrientes, disparos, posiciones, enclavamientos hacia los equipos del nuevos Autotransformador. AUT-5671 en servicio solo por Barra A 500kV. | H18: 0 | I18: P | J18: F/S | K18: N | L18: P.ENERG | M18: 13765 | N18: T
... B170: TRANSMISORA ELECTRICA DEL SUR S.A.C | C170: TINTAYA NUEVA | D170: TINTA220B | E170: 15/05/2025 13:05 | F170: 15/05/2025 16:47 | G170: INDISPONIBLE A SOLICITUD DE ATN1, DEBIDO A MANTENIMIENTO EN CL-2024. | H170: 0 | I170: P | J170: F/S | K170: N | L170: OTROS | M170: 13851 | N170: T

Sheet INGRESO OC
A3: jueves, 15 de Mayo del 2025
A5: INGRESO A OPERACIÓN COMERCIAL
A6: EMPRESA | B6: TIPO DE EQUIPO | C6: UBICACIÓN | D6: EQUIPO | E6: Fecha y hora de Ingreso a Operación Comercial

Sheet DESPACHO_EJECUTADO
B3: jueves, 15 de Mayo del 2025
A5: POTENCIA ACTIVA EJECUTADA DE LAS UNIDADES DE GENERACIÓN DEL SEIN (MW) | FL5: CENTRALES NO INTEGRANTES COES
A6: FECHA | B6: HORA | C6: 65333 | D6: 101 | E6: 102 | F6: 42667 | G6: 42668 | H6: 126 | I6: 127 | J6: 138 | K6: 139 | L6: 197 | M6: 203 | N6: 204 | O6: 230 | P6: 209 | Q6: 56677 | R6: 796 | S6: 2146 | T6: 142 | U6: 143 | V6: 125 | W6: 187 | X6: 163 | Y6: 298 | Z6: 299 | AA6: 219 | AB6: 151 | AC6: 152 | AD6: 153 | AE6: 154 | AF6: 756 | AG6: 156 | AH6: 155 | AI6: 182 | AJ6: 212 | AK6: 758 | AL6: 263 | AM6: 265 | AN6: 775 | AO6: 777 | AP6: 2154 | AQ6: 150 | AR6: 149 | AS6: 188 | AT6: 2131 | AU6: 755 | AV6: 252 | AW6: 249 | AX6: 250 | AY6: 117 | AZ6: 267 | BA6: 268 | BB6: 119 | BC6: 120 | BD6: 189 | BE6: 122 | BF6: 266 | BG6: 337 | BH6: 338 | BI6: 251 | BJ6: 115 | BK6: 239 | BL6: 288 | BM6: 240 | BN6: 241 | BO6: 242 | BP6: 191 | BQ6: 194 | BR6: 196 | BS6: 207 | BT6: 236 | BU6: 795 | BV6: 285 | BW6: 995 | BX6: 996 | BY6: 997 | BZ6: 766 | CA6: 926 | CB6: 924 | CC6: 121 | CD6: 103 | CE6: 104 | CF6: 106 | CG6: 105 | CH6: 107 | CI6: 110 | CJ6: 109 | CK6: 144 | CL6: 113 | CM6: 114 | CN6: 193 | CO6: 208 | CP6: 786 | CQ6: 787 | CR6: 788 | CS6: 789 | CT6: 248 | CU6: 2159 | CV6: 303 | CW6: 59715 | CX6: 62255 | CY6: 1263 | CZ6: 61800 | DA6: 2194 | DB6: 216 | DC6: 198 | DD6: 49607 | DE6: 214 | DF6: 260 | DG6: 2152 | DH6: 2128 | DI6: 247 | DJ6: 228 | DK6: 2135 | DL6: 261 | DM6: 237 | DN6: 253 | DO6: 770 | DP6: 225 | DQ6: 2201 | DR6: 2171 | DS6: 760 | DT6: 235 | DU6: 238 | DV6: 2184 | DW6: 61855 | DX6: 223 | DY6: 226 | DZ6: 201 | EA6: 258 | EB6: 259 | EC6: 920 | ED6: 257 | EE6: 256 | EF6: 2148 | EG6: 58288 | EH6: 58289 | EI6: 58839 | EJ6: 58840 | EK6: 296 | EL6: 297 | EM6: 211 | EN6: 2175 | EO6: 2178 | EP6: 2181 | EQ6: 1262 | ER6: 63425 | ES6: 233 | ET6: 2150 | EU6: 2165 | EV6: 2161 | EW6: 61197 | EX6: 58851 | EY6: 234 | EZ6: 215 | FA6: 917 | FB6: 289 | FC6: 58333 | FD6: 58336 | FE6: 202 | FF6: 58487 | FG6: 213 | FH6: 232 | FI6: 2190 | FJ6: TOTAL COES | FL6: 221 | FM6: 222 | FN6: 224 | FO6: 2187 | FP6: 227 | FQ6: 49400 | FR6: 199 | FS6: 200 | FT6: TOTAL NO COES
C7: SUR | D7: CENTRO | E7: CENTRO | F7: NORTE | G7: NORTE | H7: NORTE | I7: NORTE | J7: CENTRO | K7: CENTRO | L7: CENTRO | M7: CENTRO | N7: CENTRO | O7: CENTRO | P7: CENTRO | Q7: CENTRO | R7: CENTRO | S7: CENTRO | T7: CENTRO | U7: CENTRO | V7: CENTRO | W7: CENTRO | X7: SUR | Y7: SUR | Z7: SUR | AA7: CENTRO | AB7: SUR | AC7: SUR | AD7: SUR | AE7: SUR | AF7: SUR | AG7: SUR | AH7: SUR | AI7: SUR | AJ7: CENTRO | AK7: NORTE | AL7: NORTE | AM7: NORTE | AN7: CENTRO | AO7: CENTRO | AP7: CENTRO | AQ7: CENTRO | AR7: CENTRO | AS7: CENTRO | AT7: CENTRO | AU7: SUR | AV7: CENTRO | AW7: CENTRO | AX7: CENTRO | AY7: CENTRO | AZ7: CENTRO | BA7: CENTRO | BB7: CENTRO | BC7: CENTRO | BD7: SUR | BE7: NORTE | BF7: CENTRO | BG7: CENTRO | BH7: CENTRO | BI7: CENTRO | BJ7: NORTE | BK7: NORTE | BL7: NORTE | BM7: SUR | BN7: SUR | BO7: SUR | BP7: CENTRO | BQ7: CENTRO | BR7: CENTRO | BS7: CENTRO | BT7: CENTRO | BU7: CENTRO | BV7: CENTRO | BW7: SUR | BX7: SUR | BY7: SUR | BZ7: NORTE | CA7: SUR | CB7: CENTRO | CC7: NORTE | CD7: CENTRO | CE7: CENTRO | CF7: CENTRO | CG7: CENTRO | CH7: CENTRO | CI7: CENTRO | CJ7: CENTRO | CK7: CENTRO | CL7: CENTRO | CM7: CENTRO | CN7: CENTRO | CO7: CENTRO | CP7: SUR | CQ7: SUR | CR7: SUR | CS7: SUR | CT7: CENTRO | CU7: CENTRO | CV7: CENTRO | CW7: CENTRO | CX7: SUR | CY7: NORTE | CZ7: NORTE | DA7: NORTE | DB7: NORTE | DC7: NORTE | DD7: SUR | DE7: CENTRO | DF7: CENTRO | DG7: CENTRO | DH7: NORTE | DI7: NORTE | DJ7: CENTRO | DK7: CENTRO | DL7: SUR | DM7: SUR | DN7: CENTRO | DO7: CENTRO | DP7: CENTRO | DQ7: CENTRO | DR7: CENTRO | DS7: CENTRO | DT7: SUR | DU7: CENTRO | DV7: CENTRO | DW7: NORTE | DX7: CENTRO | DY7: CENTRO | DZ7: NORTE | EA7: CENTRO | EB7: CENTRO | EC7: CENTRO | ED7: NORTE | EE7: NORTE | EF7: SUR | EG7: CENTRO | EH7: CENTRO | EI7: CENTRO | EJ7: CENTRO | EK7: CENTRO | EL7: CENTRO | EM7: SUR | EN7: SUR | EO7: SUR | EP7: SUR | EQ7: NORTE | ER7: SUR | ES7: SUR | ET7: SUR | EU7: CENTRO | EV7: CENTRO | EW7: CENTRO | EX7: SUR | EY7: SUR | EZ7: NORTE | FA7: CENTRO | FB7: NORTE | FC7: NORTE | FD7: NORTE | FE7: CENTRO | FF7: CENTRO | FG7: CENTRO | FH7: NORTE | FI7: NORTE | FL7: NORTE | FM7: CENTRO | FN7: NORTE | FO7: NORTE | FP7: NORTE | FQ7: NORTE | FR7: NORTE | FS7: NORTE
C8: HIDROELÉCTRICA | D8: HIDROELÉCTRICA | E8: HIDROELÉCTRICA | F8: TERMOELÉCTRICA | G8: TERMOELÉCTRICA | H8: HIDROELÉCTRICA | I8: HIDROELÉCTRICA | J8: TERMOELÉCTRICA | K8: TERMOELÉCTRICA | L8: TERMOELÉCTRICA | M8: TERMOELÉCTRICA | N8: TERMOELÉCTRICA | O8: TERMOELÉCTRICA | P8: TERMOELÉCTRICA | Q8: TERMOELÉCTRICA | R8: HIDROELÉCTRICA | S8: HIDROELÉCTRICA | T8: TERMOELÉCTRICA | U8: TERMOELÉCTRICA | V8: TERMOELÉCTRICA | W8: TERMOELÉCTRICA | X8: HIDROELÉCTRICA | Y8: HIDROELÉCTRICA | Z8: HIDROELÉCTRICA | AA8: TERMOELÉCTRICA | AB8: HIDROELÉCTRICA | AC8: HIDROELÉCTRICA | AD8: HIDROELÉCTRICA | AE8: HIDROELÉCTRICA | AF8: TERMOELÉCTRICA | AG8: TERMOELÉCTRICA | AH8: TERMOELÉCTRICA | AI8: HIDROELÉCTRICA | AJ8: HIDROELÉCTRICA | AK8: TERMOELÉCTRICA | AL8: TERMOELÉCTRICA | AM8: TERMOELÉCTRICA | AN8: HIDROELÉCTRICA | AO8: HIDROELÉCTRICA | AP8: HIDROELÉCTRICA | AQ8: HIDROELÉCTRICA | AR8: HIDROELÉCTRICA | AS8: HIDROELÉCTRICA | AT8: HIDROELÉCTRICA | AU8: HIDROELÉCTRICA | AV8: TERMOELÉCTRICA | AW8: TERMOELÉCTRICA | AX8: TERMOELÉCTRICA | AY8: HIDROELÉCTRICA | AZ8: HIDROELÉCTRICA | BA8: HIDROELÉCTRICA | BB8: HIDROELÉCTRICA | BC8: HIDROELÉCTRICA | BD8: HIDROELÉCTRICA | BE8: HIDROELÉCTRICA | BF8: HIDROELÉCTRICA | BG8: HIDROELÉCTRICA | BH8: HIDROELÉCTRICA | BI8: HIDROELÉCTRICA | BJ8: TERMOELÉCTRICA | BK8: TERMOELÉCTRICA | BL8: TERMOELÉCTRICA | BM8: TERMOELÉCTRICA | BN8: TERMOELÉCTRICA | BO8: TERMOELÉCTRICA | BP8: HIDROELÉCTRICA | BQ8: TERMOELÉCTRICA | BR8: TERMOELÉCTRICA | BS8: TERMOELÉCTRICA | BT8: TERMOELÉCTRICA | BU8: TERMOELÉCTRICA | BV8: TERMOELÉCTRICA | BW8: TERMOELÉCTRICA | BX8: TERMOELÉCTRICA | BY8: TERMOELÉCTRICA | BZ8: HIDROELÉCTRICA | CA8: TERMOELÉCTRICA | CB8: TERMOELÉCTRICA | CC8: HIDROELÉCTRICA | CD8: HIDROELÉCTRICA | CE8: HIDROELÉCTRICA | CF8: HIDROELÉCTRICA | CG8: HIDROELÉCTRICA | CH8: HIDROELÉCTRICA | CI8: TERMOELÉCTRICA | CJ8: TERMOELÉCTRICA | CK8: TERMOELÉCTRICA | CL8: TERMOELÉCTRICA | CM8: TERMOELÉCTRICA | CN8: TERMOELÉCTRICA | CO8: TERMOELÉCTRICA | CP8: TERMOELÉCTRICA | CQ8: TERMOELÉCTRICA | CR8: TERMOELÉCTRICA | CS8: TERMOELÉCTRICA | CT8: TERMOELÉCTRICA | CU8: TERMOELÉCTRICA | CV8: SOLAR | CW8: EÓLICA | CX8: SOLAR | CY8: EÓLICA | CZ8: SOLAR | DA8: HIDROELÉCTRICA | DB8: HIDROELÉCTRICA | DC8: HIDROELÉCTRICA | DD8: HIDROELÉCTRICA | DE8: HIDROELÉCTRICA | DF8: HIDROELÉCTRICA | DG8: HIDROELÉCTRICA | DH8: HIDROELÉCTRICA | DI8: HIDROELÉCTRICA | DJ8: HIDROELÉCTRICA | DK8: HIDROELÉCTRICA | DL8: SOLAR | DM8: SOLAR | DN8: EÓLICA | DO8: EÓLICA | DP8: TERMOELÉCTRICA | DQ8: TERMOELÉCTRICA | DR8: TERMOELÉCTRICA | DS8: TERMOELÉCTRICA | DT8: SOLAR | DU8: HIDROELÉCTRICA | DV8: HIDROELÉCTRICA | DW8: HIDROELÉCTRICA | DX8: HIDROELÉCTRICA | DY8: HIDROELÉCTRICA | DZ8: HIDROELÉCTRICA | EA8: HIDROELÉCTRICA | EB8: HIDROELÉCTRICA | EC8: HIDROELÉCTRICA | ED8: EÓLICA | EE8: EÓLICA | EF8: SOLAR | EG8: EÓLICA | EH8: EÓLICA | EI8: EÓLICA | EJ8: EÓLICA | EK8: HIDROELÉCTRICA | EL8: HIDROELÉCTRICA | EM8: HIDROELÉCTRICA | EN8: HIDROELÉCTRICA | EO8: HIDROELÉCTRICA | EP8: HIDROELÉCTRICA | EQ8: EÓLICA | ER8: SOLAR | ES8: SOLAR | ET8: SOLAR | EU8: HIDROELÉCTRICA | EV8: EÓLICA | EW8: EÓLICA | EX8: SOLAR | EY8: SOLAR | EZ8: HIDROELÉCTRICA | FA8: HIDROELÉCTRICA | FB8: TERMOELÉCTRICA | FC8: TERMOELÉCTRICA | FD8: TERMOELÉCTRICA | FE8: TERMOELÉCTRICA | FF8: TERMOELÉCTRICA | FG8: TERMOELÉCTRICA | FH8: TERMOELÉCTRICA | FI8: TERMOELÉCTRICA | FL8: HIDROELÉCTRICA | FM8: HIDROELÉCTRICA | FN8: HIDROELÉCTRICA | FO8: HIDROELÉCTRICA | FP8: TERMOELÉCTRICA | FQ8: TERMOELÉCTRICA | FR8: HIDROELÉCTRICA | FS8: HIDROELÉCTRICA
C9: HYDRO GLOBAL PERÚ S.A.C. | D9: ELECTROPERU | E9: ELECTROPERU | F9: ELECTROPERU | G9: ELECTROPERU | H9: ORAZUL ENERGY PERÚ | I9: ORAZUL ENERGY PERÚ | J9: TERMOSELVA | K9: TERMOSELVA | L9: KALLPA GENERACION S.A. | M9: KALLPA GENERACION S.A. | N9: KALLPA GENERACION S.A. | O9: KALLPA GENERACION S.A. | P9: KALLPA GENERACION S.A. | Q9: KALLPA GENERACION S.A. | R9: KALLPA GENERACION S.A. | S9: KALLPA GENERACION S.A. | T9: SHOUGESA | U9: SHOUGESA | V9: SHOUGESA | W9: SHOUGESA | X9: EGEMSA | Y9: EGESUR | Z9: EGESUR | AA9: EGESUR | AB9: EGASA | AC9: EGASA | AD9: EGASA | AE9: EGASA | AF9: EGASA | AG9: EGASA | AH9: EGASA | AI9: SAN GABAN | AJ9: CELEPSA | AK9: MINERA CERRO VERDE | AL9: PLANTA DE RESERVA FRIA DE GENERACION DE ETEN S.A. | AM9: PLANTA DE RESERVA FRIA DE GENERACION DE ETEN S.A. | AN9: EMPRESA DE GENERACION HUALLAGA | AO9: EMPRESA DE GENERACION HUALLAGA | AP9: LA VIRGEN | AQ9: CHINANGO S.A.C. | AR9: CHINANGO S.A.C. | AS9: HIDROELECTRICA HUANCHOR S.A.C. | AT9: CELEPSA RENOVABLES S.R.L. | AU9: INLAND ENERGY SAC | AV9: FENIX POWER PERÚ | AW9: FENIX POWER PERÚ | AX9: FENIX POWER PERÚ | AY9: STATKRAFT S.A | AZ9: STATKRAFT S.A | BA9: STATKRAFT S.A | BB9: STATKRAFT S.A | BC9: STATKRAFT S.A | BD9: STATKRAFT S.A | BE9: STATKRAFT S.A | BF9: STATKRAFT S.A | BG9: CENTRALES SANTA ROSA S.A.C. | BH9: CENTRALES SANTA ROSA S.A.C. | BI9: EMPRESA DE GENERACION HUANZA | BJ9: ENEL GENERACION PIURA S.A. | BK9: ENEL GENERACION PIURA S.A. | BL9: ENEL GENERACION PIURA S.A. | BM9: ENGIE | BN9: ENGIE | BO9: ENGIE | BP9: ENGIE | BQ9: ENGIE | BR9: ENGIE | BS9: ENGIE | BT9: ENGIE | BU9: ENGIE | BV9: ENGIE | BW9: ENGIE | BX9: ENGIE | BY9: ENGIE | BZ9: ENGIE | CA9: INFRAESTRUCTURAS Y ENERGIAS DEL PERU S.A.C. | CB9: INFRAESTRUCTURAS Y ENERGIAS DEL PERU S.A.C. | CC9: INVERSIONES SHAQSHA S.A.C. | CD9: ORYGEN PERU S.A.A. | CE9: ORYGEN PERU S.A.A. | CF9: ORYGEN PERU S.A.A. | CG9: ORYGEN PERU S.A.A. | CH9: ORYGEN PERU S.A.A. | CI9: ORYGEN PERU S.A.A. | CJ9: ORYGEN PERU S.A.A. | CK9: ORYGEN PERU S.A.A. | CL9: ORYGEN PERU S.A.A. | CM9: ORYGEN PERU S.A.A. | CN9: ORYGEN PERU S.A.A. | CO9: ORYGEN PERU S.A.A. | CP9: SAMAY I S.A.C | CQ9: SAMAY I S.A.C | CR9: SAMAY I S.A.C | CS9: SAMAY I S.A.C | CT9: TERMOCHILCA S.A.C. | CU9: TERMOCHILCA S.A.C. | CV9: COLCA SOLAR S.A.C. | CW9: ENERGIA RENOVABLE DEL SUR S.A. | CX9: GR CORTARRAMA SOCIEDAD ANONIMA CERRADA | CY9: GR TARUCA SOCIEDAD ANONIMA CERRADA | CZ9: KONDU SAC | DA9: PERUANA DE INVERSIONES EN ENERGIAS RENOVABLES S.A. | DB9: ORAZUL ENERGY PERÚ | DC9: ORAZUL ENERGY PERÚ | DD9: SAN GABAN | DE9: MAJA ENERGIA S.A.C. | DF9: EMPRESA DE GENERACION ELECTRICA CANCHAYLLO SAC | DG9: EMPRESA DE GENERACION ELECTRICA SANTA ANA S.A.C. | DH9: EMPRESA ELECTRICA AGUA AZUL | DI9: EMPRESA ELECTRICA RIO DOBLE | DJ9: HIDROCAÑETE S.A. | DK9: HUAURA POWER GROUP S.A. | DL9: MOQUEGUA FV S.A.C. | DM9: PANAMERICANA SOLAR SAC. | DN9: PARQUE EOLICO MARCONA S.A.C. | DO9: PARQUE EOLICO TRES HERMANAS S.A.C. | DP9: PETRAMAS | DQ9: PETRAMAS | DR9: PETRAMAS | DS9: PETRAMAS | DT9: TACNA SOLAR SAC. | DU9: ELECTRICA YANAPAMPA SAC | DV9: ANDEAN POWER S.A.C. | DW9: ASOCIACIÓN SANTA LUCIA DE CHACAS | DX9: ATRIA ENERGIA S.A.C. | DY9: EGEJUNIN | DZ9: EGEJUNIN | EA9: EGEJUNIN | EB9: EGEJUNIN | EC9: EMPRESA DE GENERACION ELECTRICA RIO BAÑOS S.A.C. | ED9: ENERGÍA EÓLICA S.A. | EE9: ENERGÍA EÓLICA S.A. | EF9: ENGIE | EG9: ENGIE | EH9: ENGIE | EI9: ENGIE | EJ9: ENGIE | EK9: GENERACIÓN ANDINA S.A.C. | EL9: GENERACIÓN ANDINA S.A.C. | EM9: GENERADORA DE ENERGÍA DEL PERÚ | EN9: GENERADORA DE ENERGÍA DEL PERÚ | EO9: GENERADORA DE ENERGÍA DEL PERÚ | EP9: GENERADORA DE ENERGÍA DEL PERÚ | EQ9: GR PAINO SOCIEDAD ANONIMA CERRADA | ER9: JOYA SOLAR S.A.C. | ES9: MAJES ARCUS S.A.C. | ET9: ORYGEN PERU S.A.A. | EU9: ORYGEN PERU S.A.A. | EV9: ORYGEN PERU S.A.A. | EW9: ORYGEN PERU S.A.A. | EX9: ORYGEN PERU S.A.A. | EY9: REPARTICIÓN ARCUS S.A.C. | EZ9: SINERSA | FA9: SINERSA | FB9: BIOENERGIA DEL CHIRA S.A. | FC9: GM OPERACIONES S.A.C. | FD9: GM OPERACIONES S.A.C. | FE9: SDF ENERGIA SAC | FF9: SDF ENERGIA SAC | FG9: AGRO INDUSTRIAL PARAMONGA S.A. | FH9: AGROAURORA S.A.C. | FI9: AGROINDUSTRIAS SAN JACINTO S.A.A. | FL9: UNACEM PERU S.A. | FM9: ELECTRO ORIENTE | FN9: AGUAS Y ENERGIA PERU | FO9: ELECTRO ZAÑA S.A.C. | FP9: ELECTRONOROESTE S.A. | FQ9: SDE PIURA | FR9: SINERSA | FS9: SINERSA
C10: SAN GABAN III | D10: MANTARO | E10: RESTITUCION | F10: TUMBES MAK 1 | G10: TUMBES MAK 2 | H10: CARHUAQUERO | I10: CAÑON DEL PATO | J10: AGUAYTIA TG1 | K10: AGUAYTIA TG2 | L10: KALLPA TG1 | M10: KALLPA TG2 | N10: KALLPA TG3 | O10: KALLPA TV | P10: LFLORES TG1 | Q10: LFLORES TV | R10: CERRO DEL AGUILA | S10: CERRODELAGUILAG4 | T10: SHOUGESA TV1 | U10: SHOUGESA TV2 | V10: SHOUGESA TV3 | W10: SHOUGESA CUMMINS | X10: MACHUPICCHU | Y10: ARICOTA 1 | Z10: ARICOTA 2 | AA10: INDEPENDENCIA | AB10: CHARCANI I,II,III | AC10: CHARCANI IV | AD10: CHARCANI V | AE10: CHARCANI VI | AF10: CHILINA TG | AG10: MOLLENDO 1, 2, 3 | AH10: CHILINA (SULZ 1,2) | AI10: SAN GABAN II | AJ10: PLATANAL | AK10: RECKA | AL10: RF ETEN TG1 | AM10: RF ETEN TG2 | AN10: CHAGLLA GP1 | AO10: CHAGLLA | AP10: LA VIRGEN | AQ10: CHIMAY | AR10: YANANGO | AS10: HUANCHOR | AT10: MARAÑON | AU10: STA TERESA | AV10: FENIX GT11 | AW10: FENIX GT12 | AX10: FENIX TV10 | AY10: YAUPI | AZ10: OROYA | BA10: PACHACHACA | BB10: MALPASO | BC10: CAHUA | BD10: ARCATA | BE10: GALLITO CIEGO | BF10: CHEVES | BG10: SANTA ROSA 1 | BH10: SANTA ROSA 2 | BI10: HUANZA | BJ10: MALACAS2 TG4 | BK10: MALACAS3 TG 5 | BL10: MALACAS1 TG6 | BM10: RF ILO2 TG1 | BN10: RF ILO2 TG2 | BO10: RF ILO2 TG3 | BP10: YUNCAN | BQ10: CHILCA1 TG1 | BR10: CHILCA1 TG2 | BS10: CHILCA1 TG3 | BT10: CHILCA-TV | BU10: CHILCA2 TG41 | BV10: CHILCA2-TV | BW10: CTNEPI_TG41 | BX10: CTNEPI_TG42 | BY10: CTNEPI_TG43 | BZ10: QUITARACSA | CA10: RF PTO MALDONADO | CB10: RF PUCALLPA | CC10: PARIAC | CD10: HUINCO | CE10: MATUCANA | CF10: MOYOPAMPA | CG10: CALLAHUANCA | CH10: HUAMPANI | CI10: STA ROSA WEST TG7 | CJ10: UTI_5 | CK10: UTI_6 | CL10: VENTANILLA 3 | CM10: VENTANILLA 4 | CN10: VENTANILLA TV | CO10: STAROSA TG8 | CP10: PTO_BRVO TG1 | CQ10: PTO_BRVO TG2 | CR10: PTO_BRVO TG3 | CS10: PTO_BRVO TG4 | CT10: OLLEROS TG1 | CU10: OLLEROS TV | CV10: CS YARUCAYA | CW10: SAN JUAN | CX10: MATARANI | CY10: DUNA | CZ10: CARHUAQUERO (CS) | DA10: MANTA I | DB10: CARHUAQUERO4 | DC10: CAÑA BRAVA | DD10: TUPURI | DE10: RONCADOR | DF10: CANCHAYLLO | DG10: RENOVANDESH1 | DH10: POTRERO | DI10: PIZARRAS | DJ10: NIMPERIAL | DK10: YARUCAYA | DL10: MOQUEGUA-SOLAR | DM10: PANAMERICANA-SOLAR | DN10: PQE-EOLICO-MARCONA | DO10: PQE-EOLICO-3-HERMANAS | DP10: HUAYCOLORO | DQ10: CALLAO | DR10: DONA_CATALINA | DS10: LAGRINGAV | DT10: TACNA-SOLAR | DU10: YANAPAMPA | DV10: CARHUAC | DW10: HUALLIN | DX10: PURMACANA | DY10: HUASAHUASI | DZ10: STACRUZ_1_2 | EA10: RUNATULLO_II | EB10: RUNATULLO_III | EC10: RUCUY | ED10: PQE-EOLICO-TALARA | EE10: PQE-EOLICO-CUPISNIQUE | EF10: INTIPAMPA | EG10: PUNTA LOMITAS-BL1 | EH10: PUNTA LOMITAS-BL2 | EI10: PUN LOMITAS_EXP-BL1 | EJ10: PUN LOMITAS_EXP-BL2 | EK10: 8AGOSTO | EL10: EL CARMEN | EM10: LA JOYA | EN10: ANGEL_I | EO10: ANGEL_II | EP10: ANGEL_III | EQ10: HUAMBOS | ER10: SAN MARTIN SOLAR | ES10: MAJES | ET10: RUBI | EU10: CH_HER1 | EV10: WAYRA-I | EW10: WAYRA EXTENSION | EX10: CLEMESI | EY10: REPARTICION | EZ10: POECHOS2 | FA10: CHANCAY | FB10: CANA BRAVA | FC10: REFINERIA TALARA TV1 | FD10: REFINERÍA TALARA TV2 | FE10: OQUENDO TG1 | FF10: OQUENDO TV1 | FG10: PARAMONGA | FH10: MAPLE | FI10: SAN_JACINTO | FJ10: MW | FL10: CARPAPATA | FM10: CENTRALES ELOR | FN10: PIAS1 | FO10: ZANA | FP10: TABLAZO | FQ10: TALLANCA | FR10: CURUMUY | FS10: POECHOS1 | FT10: MW
A11: 15/05/2025 | B11: 00:30 | C11: 99.5 | D11: 647.7 | E11: 215.2 | F11: 0 | G11: 0 | H11: 89.7 | I11: 211.2 | L11: 106.4 | M11: 106.5 | N11: 106.6 | O11: 207 | P11: 213.2 | Q11: 110.8 | R11: 553.5 | S11: 10.4 | X11: 166 | Y11: 7.2 | Z11: 4.7 | AB11: 6.7 | AC11: 13.9 | AD11: 84.8 | AG11: 0 | AI11: 111 | AJ11: 196.3 | AN11: 6.5 | AO11: 229.8 | AP11: 73 | AQ11: 136.5 | AR11: 39.2 | AS11: 9.4 | AT11: 19.7 | AU11: 91.4 | AV11: 123.9 | AX11: 75 | AY11: 110.5 | AZ11: 8.2 | BA11: 4.3 | BB11: 46.4 | BD11: 4 | BE11: 37.6 | BF11: 133.1 | BI11: 48 | BJ11: 0 | BK11: 102.1 | BL11: 45.6 | BP11: 86.2 | BR11: 175.7 | BS11: 200 | BT11: 181.9 | CC11: 4.6 | CD11: 100.9 | CE11: 119.8 | CF11: 65.3 | CG11: 78.9 | CH11: 30.3 | CL11: 103.3 | CM11: 104.1 | CN11: 122.8 | CV11: 0 | CW11: 41.2 | CX11: 0 | CY11: 9.7 | CZ11: 0 | DA11: 20 | DB11: 9.9 | DC11: 5.4 | DD11: 1 | DF11: 4.834 | DG11: 20.5 | DH11: 20 | DI11: 18.8 | DJ11: 3.7 | DK11: 18.5 | DL11: 0 | DM11: 0 | DN11: 3.7 | DO11: 10.7 | DP11: 4.5 | DQ11: 1 | DR11: 2.2 | DS11: 0 | DT11: 0 | DU11: 3.3 | DV11: 14.4 | DW11: 2.6 | DX11: 0 | DY11: 17.1 | DZ11: 8 | EA11: 11.3 | EB11: 14.5 | EC11: 19.9 | ED11: 6.1 | EE11: 44.9 | EF11: 0 | EG11: 19 | EH11: 36.6 | EI11: 0.6 | EJ11: 0 | EK11: 17.7 | EL11: 4.8 | EM11: 8 | EN11: 15.2 | EO11: 16 | EP11: 15.8 | EQ11: 4.6 | ER11: 0 | ES11: 0 | ET11: 0 | EU11: 0.6 | EV11: 0 | EW11: 0 | EX11: 0 | EY11: 0 | EZ11: 9.6 | FA11: 20 | FB11: 9.5 | FC11: 0 | FG11: 18.3 | FJ11: 6520.334 | FL11: 24.72332 | FM11: 7.919 | FO11: 13.2 | FP11: 26.53976 | FQ11: 18.91146 | FR11: 12 | FS11: 15.8 | FT11: 119.09354
A12: 15/05/2025 | B12: 01:00 | C12: 99.8 | D12: 647.2 | E12: 214.6 | F12: 3.5 | G12: 3.6 | H12: 90.3 | I12: 211.2 | L12: 105.4 | M12: 105.4 | N12: 104.9 | O12: 206.9 | P12: 211.1 | Q12: 110 | R12: 566.7 | S12: 10.4 | X12: 168 | Y12: 7.7 | Z12: 4.7 | AB12: 6.7 | AC12: 13.6 | AD12: 86 | AG12: 0 | AI12: 111 | AJ12: 147.7 | AN12: 6.5 | AO12: 231.7 | AP12: 72.8 | AQ12: 135.1 | AR12: 39.6 | AS12: 9.3 | AT12: 19.7 | AU12: 88 | AV12: 122.7 | AX12: 75.6 | AY12: 110.1 | AZ12: 8.2 | BA12: 4.3 | BB12: 46.8 | BD12: 4 | BE12: 37.6 | BF12: 128.1 | BI12: 47.9 | BJ12: 0 | BK12: 30.2 | BL12: 46.8 | BP12: 86.5 | BR12: 175.6 | BS12: 200 | BT12: 183 | CC12: 4.6 | CD12: 88.4 | CE12: 118.1 | CF12: 62.8 | CG12: 79.1 | CH12: 30.5 | CL12: 103.8 | CM12: 100.6 | CN12: 123.8 | CV12: 0 | CW12: 38.2 | CX12: 0 | CY12: 9.3 | CZ12: 0 | DA12: 20 | DB12: 9.9 | DC12: 5.4 | DD12: 1 | DF12: 4.799 | DG12: 20.6 | DH12: 20 | DI12: 19.1 | DJ12: 3.7 | DK12: 18.5 | DL12: 0 | DM12: 0 | DN12: 6.2 | DO12: 7.8 | DP12: 4.5 | DQ12: 1 | DR12: 2.2 | DS12: 0 | DT12: 0 | DU12: 3.3 | DV12: 14.4 | DW12: 2.6 | DX12: 0 | DY12: 17.1 | DZ12: 8 | EA12: 11.3 | EB12: 14.8 | EC12: 19.8 | ED12: 5.2 | EE12: 41.2 | EF12: 0 | EG12: 13.4 | EH12: 29.3 | EI12: 0.4 | EJ12: 0 | EK12: 17.6 | EL12: 4.8 | EM12: 8 | EN12: 15.2 | EO12: 16 | EP12: 15.8 | EQ12: 4.6 | ER12: 0 | ES12: 0 | ET12: 0 | EU12: 0.6 | EV12: 0 | EW12: 0 | EX12: 0 | EY12: 0 | EZ12: 9.5 | FA12: 19.8 | FB12: 9.5 | FC12: 0 | FG12: 17.8 | FJ12: 6370.399 | FL12: 24.72039 | FM12: 7.16 | FO12: 13.1 | FP12: 26.61729 | FQ12: 18.91095 | FR12: 12 | FS12: 15.9 | FT12: 118.40863
A13: 15/05/2025 | B13: 01:30 | C13: 99 | D13: 646.3 | E13: 215.1 | F13: 3.7 | G13: 3.6 | H13: 89.6 | I13: 207.9 | L13: 106.5 | M13: 106.8 | N13: 106.6 | O13: 206.7 | P13: 211.2 | Q13: 110.3 | R13: 557.1 | S13: 10.4 | X13: 163.7 | Y13: 7.4 | Z13: 4.7 | AB13: 6.7 | AC13: 13.8 | AD13: 69.9 | AG13: 0 | AI13: 111 | AJ13: 180.9 | AN13: 6.5 | AO13: 231.9 | AP13: 73.5 | AQ13: 126 | AR13: 39.1 | AS13: 9.4 | AT13: 19.7 | AU13: 92.8 | AV13: 123.1 | AX13: 74.4 | AY13: 109.7 | AZ13: 8.2 | BA13: 4.3 | BB13: 46.7 | BD13: 4 | BE13: 37.5 | BF13: 115.4 | BI13: 48 | BJ13: 0 | BK13: 0 | BL13: 46.5 | BP13: 86.1 | BR13: 175.6 | BS13: 200 | BT13: 182.6 | CC13: 4.6 | CD13: 72.6 | CE13: 113.9 | CF13: 62.1 | CG13: 78.8 | CH13: 30.2 | CL13: 103 | CM13: 102.5 | CN13: 123.1 | CV13: 0 | CW13: 32 | CX13: 0 | CY13: 6.5 | CZ13: 0 | DA13: 20 | DB13: 9.9 | DC13: 5.4 | DD13: 1 | DF13: 5.034 | DG13: 20.3 | DH13: 20 | DI13: 18.9 | DJ13: 3.7 | DK13: 18.5 | DL13: 0 | DM13: 0 | DN13: 3.9 | DO13: 6.1 | DP13: 4.5 | DQ13: 1 | DR13: 2.2 | DS13: 0 | DT13: 0 | DU13: 2.5 | DV13: 14.4 | DW13: 2.6 | DX13: 0 | DY13: 17.2 | DZ13: 8 | EA13: 11.1 | EB13: 14.8 | EC13: 20 | ED13: 5.4 | EE13: 29 | EF13: 0 | EG13: 9.9 | EH13: 20.8 | EI13: 0.3 | EJ13: 0 | EK13: 17.3 | EL13: 4.8 | EM13: 8 | EN13: 15.4 | EO13: 16.3 | EP13: 15.8 | EQ13: 2.6 | ER13: 0 | ES13: 0 | ET13: 0 | EU13: 0.6 | EV13: 0 | EW13: 0 | EX13: 0 | EY13: 0 | EZ13: 9.4 | FA13: 20 | FB13: 9 | FC13: 0 | FG13: 17.5 | FJ13: 6262.334 | FL13: 24.72239 | FM13: 6.599 | FO13: 13.2 | FP13: 26.64498 | FQ13: 18.91006 | FR13: 11.9 | FS13: 15.9 | FT13: 117.87643
A14: 15/05/2025 | B14: 02:00 | C14: 100.6 | D14: 646.6 | E14: 214.6 | F14: 3.9 | G14: 3.7 | H14: 90.3 | I14: 210.2 | L14: 105.7 | M14: 106.2 | N14: 105.6 | O14: 206.6 | P14: 211.2 | Q14: 110.3 | R14: 561.1 | S14: 10.5 | X14: 165.1 | Y14: 7.6 | Z14: 5.2 | AB14: 6.7 | AC14: 12 | AD14: 69.9 | AG14: 0 | AI14: 110.9 | AJ14: 172.1 | AN14: 6.5 | AO14: 231.2 | AP14: 74 | AQ14: 135.4 | AR14: 38.9 | AS14: 9.4 | AT14: 19.7 | AU14: 89.4 | AV14: 124.8 | AX14: 74.8 | AY14: 110.1 | AZ14: 8.2 | BA14: 4.3 | BB14: 47.1 | BD14: 4 | BE14: 38.2 | BF14: 144.8 | BI14: 48 | BJ14: 0 | BK14: 0 | BL14: 46.7 | BP14: 86.2 | BR14: 134.2 | BS14: 164.1 | BT14: 157.6 | CC14: 4.6 | CD14: 85.2 | CE14: 124 | CF14: 62 | CG14: 79.6 | CH14: 30.1 | CL14: 102.8 | CM14: 102.3 | CN14: 122.4 | CV14: 0 | CW14: 33 | CX14: 0 | CY14: 7.5 | CZ14: 0 | DA14: 20 | DB14: 9.9 | DC14: 5.4 | DD14: 1 | DF14: 5.026 | DG14: 20.3 | DH14: 20 | DI14: 18.9 | DJ14: 3.7 | DK14: 18.5 | DL14: 0 | DM14: 0 | DN14: 2.9 | DO14: 5 | DP14: 4.5 | DQ14: 1 | DR14: 2.2 | DS14: 0 | DT14: 0 | DU14: 3.3 | DV14: 14.4 | DW14: 2.6 | DX14: 0 | DY14: 17.1 | DZ14: 8 | EA14: 11.1 | EB14: 15.1 | EC14: 20 | ED14: 5.7 | EE14: 34.1 | EF14: 0 | EG14: 8.6 | EH14: 20.2 | EI14: 0 | EJ14: 0 | EK14: 17.3 | EL14: 4.8 | EM14: 8 | EN14: 15.4 | EO14: 16.3 | EP14: 15.8 | EQ14: 3.4 | ER14: 0 | ES14: 0 | ET14: 0 | EU14: 0.6 | EV14: 0 | EW14: 0 | EX14: 0 | EY14: 0 | EZ14: 9.3 | FA14: 20 | FB14: 9.2 | FC14: 0 | FG14: 17.5 | FJ14: 6223.826 | FL14: 24.71785 | FM14: 5.417 | FO14: 13.2 | FP14: 26.66759 | FQ14: 18.91 | FR14: 12 | FS14: 15.9 | FT14: 116.81244
A15: 15/05/2025 | B15: 02:30 | C15: 99.9 | D15: 648.3 | E15: 214.9 | F15: 3.5 | G15: 3.6 | H15: 91.4 | I15: 214.2 | L15: 109.8 | M15: 110.2 | N15: 110.4 | O15: 209.8 | P15: 210 | Q15: 109.8 | R15: 561.1 | S15: 10.4 | X15: 166.6 | Y15: 7.9 | Z15: 5.2 | AB15: 6.7 | AC15: 12 | AD15: 69.9 | AG15: 0 | AI15: 111.4 | AJ15: 223.6 | AN15: 6.5 | AO15: 229.8 | AP15: 75 | AQ15: 148.6 | AR15: 39.3 | AS15: 9.4 | AT15: 19.7 | AU15: 90.4 | AV15: 124.2 | AX15: 74.7 | AY15: 110.3 | AZ15: 8.2 | BA15: 4.3 | BB15: 47.1 | BD15: 4 | BE15: 37.9 | BF15: 171.7 | BI15: 48 | BJ15: 0 | BK15: 0 | BL15: 45.6 | BP15: 86.5 | BR15: 84.1 | BS15: 84.4 | BT15: 108 | CC15: 4.6 | CD15: 141.5 | CE15: 130.9 | CF15: 62.5 | CG15: 79.8 | CH15: 30.4 | CL15: 101.8 | CM15: 102.5 | CN15: 122 | CV15: 0 | CW15: 31.8 | CX15: 0 | CY15: 6.8 | CZ15: 0 | DA15: 20 | DB15: 9.8 | DC15: 5.5 | DD15: 1 | DF15: 5.049 | DG15: 20.4 | DH15: 20 | DI15: 18.9 | DJ15: 3.7 | DK15: 18.5 | DL15: 0 | DM15: 0 | DN15: 3.7 | DO15: 4.7 | DP15: 4.5 | DQ15: 1 | DR15: 2.2 | DS15: 0 | DT15: 0 | DU15: 3.4 | DV15: 14.4 | DW15: 2.6 | DX15: 0 | DY15: 17.1 | DZ15: 7.9 | EA15: 11.4 | EB15: 15.3 | EC15: 20 | ED15: 7.7 | EE15: 29.2 | EF15: 0 | EG15: 6.9 | EH15: 16.8 | EI15: 0 | EJ15: 0 | EK15: 17.5 | EL15: 4.8 | EM15: 8.2 | EN15: 15.4 | EO15: 16.3 | EP15: 15.8 | EQ15: 2.7 | ER15: 0 | ES15: 0 | ET15: 0 | EU15: 0.6 | EV15: 0 | EW15: 0 | EX15: 0 | EY15: 0 | EZ15: 9.4 | FA15: 20 | FB15: 9.5 | FC15: 0 | FG15: 17.5 | FJ15: 6212.249 | FL15: 24.71614 | FM15: 5.098 | FO15: 13.2 | FP15: 26.71292 | FQ15: 18.91047 | FR15: 12 | FS15: 15.9 | FT15: 116.53753
A16: 15/05/2025 | B16: 03:00 | C16: 101 | D16: 650.7 | E16: 215.3 | F16: 3.8 | G16: 3.9 | H16: 90.1 | I16: 211.4 | L16: 128.2 | M16: 128.2 | N16: 128.3 | O16: 224 | P16: 209.9 | Q16: 110.1 | R16: 563.9 | S16: 10.5 | X16: 160.1 | Y16: 7.8 | Z16: 5.4 | AB16: 6.7 | AC16: 11.3 | AD16: 70.9 | AG16: 0 | AI16: 111.2 | AJ16: 223.6 | AN16: 6.5 | AO16: 231.9 | AP16: 75.4 | AQ16: 114 | AR16: 40.4 | AS16: 9.4 | AT16: 19.7 | AU16: 89.2 | AV16: 123.9 | AX16: 75.2 | AY16: 110.4 | AZ16: 8.3 | BA16: 4.3 | BB16: 47.2 | BD16: 4 | BE16: 37.9 | BF16: 167.7 | BI16: 48.1 | BJ16: 0 | BK16: 0 | BL16: 46.2 | BP16: 86.3 | BR16: 85.1 | BS16: 84.9 | BT16: 105.7 | CC16: 4.6 | CD16: 116.9 | CE16: 131.4 | CF16: 62.3 | CG16: 79.8 | CH16: 30.3 | CL16: 102.4 | CM16: 102.3 | CN16: 122.8 | CV16: 0 | CW16: 27.2 | CX16: 0 | CY16: 9.4 | CZ16: 0 | DA16: 20 | DB16: 9.9 | DC16: 5.5 | DD16: 1 | DF16: 4.97 | DG16: 20.4 | DH16: 20 | DI16: 18.9 | DJ16: 3.7 | DK16: 18.5 | DL16: 0 | DM16: 0 | DN16: 3 | DO16: 4.6 | DP16: 4.5 | DQ16: 1 | DR16: 2.2 | DS16: 0 | DT16: 0 | DU16: 3.2 | DV16: 14.4 | DW16: 2.6 | DX16: 0 | DY16: 17.1 | DZ16: 7.9 | EA16: 11.3 | EB16: 15.2 | EC16: 20 | ED16: 6.5 | EE16: 18.8 | EF16: 0 | EG16: 3.4 | EH16: 11.5 | EI16: 0 | EJ16: 0 | EK16: 17.5 | EL16: 4.8 | EM16: 8.4 | EN16: 15.4 | EO16: 16.3 | EP16: 16 | EQ16: 3.8 | ER16: 0 | ES16: 0 | ET16: 0 | EU16: 0.6 | EV16: 0 | EW16: 0 | EX16: 0 | EY16: 0 | EZ16: 9.5 | FA16: 20 | FB16: 9.1 | FC16: 0 | FG16: 17.5 | FJ16: 6196.37 | FL16: 24.71684 | FM16: 5.093 | FO16: 13.2 | FP16: 26.72958 | FQ16: 18.91048 | FR16: 12 | FS16: 16 | FT16: 116.6499
A17: 15/05/2025 | B17: 03:30 | C17: 100.7 | D17: 649.3 | E17: 214.8 | F17: 3.7 | G17: 3.6 | H17: 89.9 | I17: 212.4 | L17: 118.5 | M17: 117.7 | N17: 116.5 | O17: 209.4 | P17: 209.5 | Q17: 110.1 | R17: 567.3 | S17: 10.4 | X17: 167.4 | Y17: 7.6 | Z17: 5.4 | AB17: 6.7 | AC17: 11.3 | AD17: 70.9 | AG17: 0 | AI17: 110.8 | AJ17: 220.5 | AN17: 6.5 | AO17: 228.8 | AP17: 76.2 | AQ17: 132.9 | AR17: 39.9 | AS17: 9.4 | AT17: 19.7 | AU17: 91.2 | AV17: 124.5 | AX17: 74.8 | AY17: 109.9 | AZ17: 8.2 | BA17: 4.3 | BB17: 47 | BD17: 4 | BE17: 37.9 | BF17: 170.3 | BI17: 47.9 | BJ17: 0 | BK17: 0 | BL17: 46.2 | BP17: 86.1 | BR17: 84 | BS17: 84 | BT17: 106.3 | CC17: 4.6 | CD17: 97.4 | CE17: 131.8 | CF17: 62 | CG17: 79.7 | CH17: 30.1 | CL17: 102.5 | CM17: 102.1 | CN17: 121.9 | CV17: 0 | CW17: 37.3 | CX17: 0 | CY17: 8.4 | CZ17: 0 | DA17: 20 | DB17: 9.9 | DC17: 5.5 | DD17: 1 | DF17: 4.841 | DG17: 20.2 | DH17: 20 | DI17: 18.8 | DJ17: 3.7 | DK17: 18.5 | DL17: 0 | DM17: 0 | DN17: 3.3 | DO17: 5.1 | DP17: 4.5 | DQ17: 1 | DR17: 2.2 | DS17: 0 | DT17: 0 | DU17: 3.4 | DV17: 14.4 | DW17: 2.6 | DX17: 0 | DY17: 17 | DZ17: 7.9 | EA17: 11 | EB17: 15.7 | EC17: 20 | ED17: 6.3 | EE17: 14.4 | EF17: 0 | EG17: 1.4 | EH17: 7.4 | EI17: 0 | EJ17: 0 | EK17: 17.5 | EL17: 4.8 | EM17: 8.3 | EN17: 15.5 | EO17: 16.5 | EP17: 16 | EQ17: 4.5 | ER17: 0 | ES17: 0 | ET17: 0 | EU17: 0.6 | EV17: 0 | EW17: 0 | EX17: 0 | EY17: 0 | EZ17: 9.4 | FA17: 20 | FB17: 9 | FC17: 0 | FG17: 17.6 | FJ17: 6151.941 | FL17: 24.71456 | FM17: 5.086 | FO17: 13.2 | FP17: 26.78858 | FQ17: 18.91028 | FR17: 11.9 | FS17: 15.6 | FT17: 116.19942
A18: 15/05/2025 | B18: 04:00 | C18: 98.1 | D18: 643.3 | E18: 214.4 | F18: 3.6 | G18: 3.6 | H18: 89.8 | I18: 210.1 | L18: 117.7 | M18: 116.5 | N18: 116.6 | O18: 221.5 | P18: 210 | Q18: 110.2 | R18: 555.2 | S18: 10.3 | X18: 162.3 | Y18: 6.8 | Z18: 5.2 | AB18: 6.7 | AC18: 11.3 | AD18: 69.7 | AG18: 0 | AI18: 110 | AJ18: 222.6 | AN18: 6.5 | AO18: 227.6 | AP18: 75.3 | AQ18: 139.8 | AR18: 39.4 | AS18: 9.4 | AT18: 19.7 | AU18: 90.8 | AV18: 120.9 | AX18: 75.3 | AY18: 108.9 | AZ18: 8.3 | BA18: 4.4 | BB18: 46.6 | BD18: 4 | BE18: 37.2 | BF18: 162 | BI18: 47.6 | BJ18: 0 | BK18: 0 | BL18: 45.3 | BP18: 85.8 | BR18: 85.1 | BS18: 84.6 | BT18: 106.4 | CC18: 4.6 | CD18: 91.2 | CE18: 129.9 | CF18: 61.3 | CG18: 78.3 | CH18: 29.7 | CL18: 102.3 | CM18: 101.6 | CN18: 122.5 | CV18: 0 | CW18: 43.4 | CX18: 0 | CY18: 8.2 | CZ18: 0 | DA18: 20 | DB18: 9.9 | DC18: 5.4 | DD18: 1 | DF18: 4.835 | DG18: 20 | DH18: 20 | DI18: 18.9 | DJ18: 3.7 | DK18: 18.5 | DL18: 0 | DM18: 0 | DN18: 5.4 | DO18: 4.6 | DP18: 4.5 | DQ18: 1 | DR18: 2.2 | DS18: 0 | DT18: 0 | DU18: 3.3 | DV18: 14.4 | DW18: 2.6 | DX18: 0 | DY18: 17 | DZ18: 7.9 | EA18: 10.5 | EB18: 15.4 | EC18: 20 | ED18: 4.9 | EE18: 14.1 | EF18: 0 | EG18: 2.9 | EH18: 10.8 | EI18: 0 | EJ18: 0 | EK18: 17.5 | EL18: 4.8 | EM18: 8.3 | EN18: 15.5 | EO18: 16.5 | EP18: 16.3 | EQ18: 4.9 | ER18: 0 | ES18: 0 | ET18: 0 | EU18: 0.6 | EV18: 0 | EW18: 0 | EX18: 0 | EY18: 0 | EZ18: 9.5 | FA18: 20 | FB18: 8.9 | FC18: 0 | FG18: 17.5 | FJ18: 6123.435 | FL18: 24.71772 | FM18: 5.067 | FO18: 13.2 | FP18: 26.85731 | FQ18: 18.90996 | FR18: 11.9 | FS18: 15.8 | FT18: 116.45199
A19: 15/05/2025 | B19: 04:30 | C19: 98.6 | D19: 642.3 | E19: 213.5 | F19: 3.8 | G19: 3.7 | H19: 90.2 | I19: 210 | L19: 111.8 | M19: 112.4 | N19: 113.1 | O19: 216.8 | P19: 208.2 | Q19: 109.4 | R19: 553.9 | S19: 10.4 | X19: 163.3 | Y19: 7 | Z19: 5.3 | AB19: 6.7 | AC19: 11.3 | AD19: 69.8 | AG19: 0 | AI19: 110.5 | AJ19: 221.1 | AN19: 6.5 | AO19: 230.7 | AP19: 75 | AQ19: 134.1 | AR19: 39.9 | AS19: 9.4 | AT19: 19.7 | AU19: 89.6 | AV19: 124.2 | AX19: 73.9 | AY19: 109.9 | AZ19: 8.4 | BA19: 4.3 | BB19: 47 | BD19: 4 | BE19: 38.2 | BF19: 166.8 | BI19: 47.7 | BJ19: 0 | BK19: 0 | BL19: 45.5 | BP19: 85.8 | BR19: 84.3 | BS19: 84.5 | BT19: 107.8 | CC19: 4.6 | CD19: 133.7 | CE19: 131.4 | CF19: 61.7 | CG19: 78.8 | CH19: 30.1 | CL19: 102.8 | CM19: 101.7 | CN19: 121.7 | CV19: 0 | CW19: 53.9 | CX19: 0 | CY19: 7.8 | CZ19: 0 | DA19: 20 | DB19: 10 | DC19: 5.4 | DD19: 1 | DF19: 4.852 | DG19: 20.2 | DH19: 20 | DI19: 18.9 | DJ19: 3.7 | DK19: 18.5 | DL19: 0 | DM19: 0 | DN19: 7 | DO19: 6.7 | DP19: 4.5 | DQ19: 1 | DR19: 2.2 | DS19: 0 | DT19: 0 | DU19: 3.3 | DV19: 14.4 | DW19: 2.6 | DX19: 0 | DY19: 17.1 | DZ19: 7.9 | EA19: 10.5 | EB19: 15.3 | EC19: 20 | ED19: 7 | EE19: 7.3 | EF19: 0 | EG19: 1.5 | EH19: 8.1 | EI19: 0 | EJ19: 0 | EK19: 17.5 | EL19: 4.8 | EM19: 8.3 | EN19: 15.5 | EO19: 16.5 | EP19: 16.3 | EQ19: 4.5 | ER19: 0 | ES19: 0 | ET19: 0 | EU19: 0.6 | EV19: 0 | EW19: 0 | EX19: 0 | EY19: 0 | EZ19: 9.5 | FA19: 20 | FB19: 9 | FC19: 0 | FG19: 17.7 | FJ19: 6157.652 | FL19: 24.71228 | FM19: 5.042 | FO19: 13.2 | FP19: 26.98783 | FQ19: 18.90959 | FR19: 12 | FS19: 15.9 | FT19: 116.7517
A20: 15/05/2025 | B20: 05:00 | C20: 99.7 | D20: 647.8 | E20: 214.9 | F20: 3.6 | G20: 3.7 | H20: 89.7 | I20: 211.8 | L20: 113 | M20: 112.5 | N20: 113.2 | O20: 209.8 | P20: 210.2 | Q20: 110.3 | R20: 560 | S20: 10.4 | X20: 163.7 | Y20: 7.3 | Z20: 5.4 | AB20: 6.7 | AC20: 11.2 | AD20: 70.1 | AG20: 0 | AI20: 110.9 | AJ20: 222.5 | AN20: 6.5 | AO20: 228.3 | AP20: 75 | AQ20: 132.5 | AR20: 40.2 | AS20: 9.4 | AT20: 19.7 | AU20: 86.2 | AV20: 124.2 | AX20: 74.7 | AY20: 109.8 | AZ20: 8.3 | BA20: 4.3 | BB20: 47 | BD20: 4 | BE20: 37.8 | BF20: 169.7 | BI20: 47.9 | BJ20: 0 | BK20: 0 | BL20: 45.7 | BP20: 85.9 | BR20: 84.6 | BS20: 84.9 | BT20: 106 | CC20: 4.6 | CD20: 101.5 | CE20: 131.8 | CF20: 62 | CG20: 78.9 | CH20: 30.3 | CL20: 102.7 | CM20: 102.9 | CN20: 121.7 | CV20: 0 | CW20: 51.3 | CX20: 0 | CY20: 8.7 | CZ20: 0 | DA20: 20 | DB20: 10 | DC20: 5.4 | DD20: 1 | DF20: 4.85 | DG20: 20.4 | DH20: 20 | DI20: 18.9 | DJ20: 3.7 | DK20: 18.5 | DL20: 0 | DM20: 0 | DN20: 4.7 | DO20: 8.7 | DP20: 4.5 | DQ20: 1 | DR20: 2.2 | DS20: 0 | DT20: 0 | DU20: 3.3 | DV20: 14.4 | DW20: 2.6 | DX20: 0 | DY20: 17 | DZ20: 7.9 | EA20: 10.8 | EB20: 15.6 | EC20: 20 | ED20: 9.2 | EE20: 9.5 | EF20: 0 | EG20: 0.4 | EH20: 5.4 | EI20: 0 | EJ20: 0 | EK20: 17.5 | EL20: 4.8 | EM20: 8.3 | EN20: 15.4 | EO20: 16.5 | EP20: 16.3 | EQ20: 3.5 | ER20: 0 | ES20: 0 | ET20: 0 | EU20: 0.6 | EV20: 0 | EW20: 0 | EX20: 0 | EY20: 0 | EZ20: 9.5 | FA20: 20 | FB20: 9.2 | FC20: 0 | FG20: 17.6 | FJ20: 6136.55 | FL20: 24.71282 | FM20: 5.049 | FO20: 13.2 | FP20: 27.06484 | FQ20: 18.90952 | FR20: 12 | FS20: 15.9 | FT20: 116.83618
A21: 15/05/2025 | B21: 05:30 | C21: 100.2 | D21: 649.8 | E21: 215.1 | F21: 3.6 | G21: 3.8 | H21: 92.3 | I21: 214.4 | L21: 120.4 | M21: 121.1 | N21: 120.2 | O21: 215.9 | P21: 209.2 | Q21: 109.7 | R21: 562.1 | S21: 10.6 | X21: 165.5 | Y21: 7.5 | Z21: 5 | AB21: 6.7 | AC21: 11.3 | AD21: 70.2 | AG21: 0 | AI21: 110.9 | AJ21: 222.7 | AN21: 6.5 | AO21: 228.6 | AP21: 75 | AQ21: 140.7 | AR21: 40.4 | AS21: 9.4 | AT21: 19.7 | AU21: 91.7 | AV21: 123.9 | AX21: 74.2 | AY21: 110.4 | AZ21: 8.3 | BA21: 4.3 | BB21: 47.5 | BD21: 4 | BE21: 38.6 | BF21: 170.3 | BI21: 48.3 | BJ21: 0 | BK21: 0 | BL21: 46 | BP21: 86.8 | BR21: 154 | BS21: 153.7 | BT21: 153.5 | CC21: 4.5 | CD21: 123.1 | CE21: 133.4 | CF21: 62.8 | CG21: 79 | CH21: 30.4 | CL21: 102.1 | CM21: 101.3 | CN21: 122.1 | CV21: 0 | CW21: 56.3 | CX21: 0 | CY21: 9.4 | CZ21: 0 | DA21: 20 | DB21: 10 | DC21: 5.5 | DD21: 1 | DF21: 4.869 | DG21: 20.3 | DH21: 20 | DI21: 18.9 | DJ21: 3.7 | DK21: 18.5 | DL21: 0 | DM21: 0 | DN21: 7.6 | DO21: 10 | DP21: 4.5 | DQ21: 1 | DR21: 2.2 | DS21: 0 | DT21: 0 | DU21: 3.3 | DV21: 14.4 | DW21: 2.5 | DX21: 0 | DY21: 17 | DZ21: 7.9 | EA21: 10.9 | EB21: 15.6 | EC21: 20 | ED21: 13.4 | EE21: 11.1 | EF21: 0 | EG21: 0.4 | EH21: 3.3 | EI21: 0 | EJ21: 0 | EK21: 17.5 | EL21: 4.8 | EM21: 8.3 | EN21: 15.4 | EO21: 16.5 | EP21: 16.3 | EQ21: 6.6 | ER21: 0 | ES21: 0 | ET21: 0 | EU21: 0.6 | EV21: 0 | EW21: 0 | EX21: 0 | EY21: 0 | EZ21: 9.4 | FA21: 20 | FB21: 9.1 | FC21: 0 | FG21: 18 | FJ21: 6418.769 | FL21: 24.70265 | FM21: 6.389 | FO21: 13.2 | FP21: 27.09486 | FQ21: 18.90837 | FR21: 11.9 | FS21: 15.8 | FT21: 117.99488
A22: 15/05/2025 | B22: 06:00 | C22: 99.4 | D22: 647.4 | E22: 214.8 | F22: 3.7 | G22: 3.7 | H22: 90.2 | I22: 213.9 | L22: 103.7 | M22: 103.2 | N22: 103.9 | O22: 215.5 | P22: 211.8 | Q22: 109.8 | R22: 556.2 | S22: 10.5 | X22: 169.3 | Y22: 6.7 | Z22: 4.9 | AB22: 6.7 | AC22: 11.4 | AD22: 70.3 | AG22: 0 | AI22: 111 | AJ22: 215.1 | AN22: 6.5 | AO22: 232.1 | AP22: 75 | AQ22: 139 | AR22: 41.3 | AS22: 9.4 | AT22: 19.7 | AU22: 92.6 | AV22: 125 | AX22: 74.5 | AY22: 110.1 | AZ22: 8.3 | BA22: 4.3 | BB22: 47 | BD22: 4 | BE22: 38.2 | BF22: 170.9 | BI22: 48 | BJ22: 0 | BK22: 35.8 | BL22: 45.6 | BP22: 86.3 | BR22: 174.3 | BS22: 200 | BT22: 174.3 | CC22: 4.6 | CD22: 99.5 | CE22: 132.1 | CF22: 62.3 | CG22: 76.9 | CH22: 30.4 | CL22: 102.7 | CM22: 101.9 | CN22: 122.7 | CV22: 0 | CW22: 67.7 | CX22: 0 | CY22: 11 | CZ22: 0 | DA22: 20 | DB22: 9.9 | DC22: 5.4 | DD22: 1 | DF22: 4.884 | DG22: 20.5 | DH22: 20 | DI22: 18.9 | DJ22: 3.8 | DK22: 18.5 | DL22: 0.4 | DM22: 0.3 | DN22: 8 | DO22: 13.1 | DP22: 4.5 | DQ22: 1 | DR22: 2.2 | DS22: 0 | DT22: 0 | DU22: 3.3 | DV22: 14.4 | DW22: 2.5 | DX22: 0 | DY22: 17 | DZ22: 7.9 | EA22: 10.8 | EB22: 15.5 | EC22: 20 | ED22: 14.9 | EE22: 8.1 | EF22: 0 | EG22: 0 | EH22: 0.6 | EI22: 0 | EJ22: 0 | EK22: 17.5 | EL22: 4.8 | EM22: 8.6 | EN22: 15.4 | EO22: 16.5 | EP22: 16.3 | EQ22: 6.1 | ER22: 0.1 | ES22: 0 | ET22: 0 | EU22: 0.6 | EV22: 0 | EW22: 0 | EX22: 0 | EY22: 0 | EZ22: 9.5 | FA22: 20 | FB22: 9.4 | FC22: 0 | FG22: 17.8 | FJ22: 6467.084 | FL22: 24.70297 | FM22: 6.857 | FO22: 13.2 | FP22: 27.1817 | FQ22: 18.90858 | FR22: 11.9 | FS22: 15.8 | FT22: 118.55025
... A58: 16/05/2025 | B58: 00:00 | C58: 100.7 | D58: 650.5 | E58: 215.1 | F58: 0 | G58: 0 | H58: 90 | I58: 208.5 | L58: 105.7 | M58: 105.9 | N58: 105.8 | O58: 207.8 | P58: 208.8 | Q58: 110.7 | R58: 559.5 | S58: 10.4 | X58: 167.9 | Y58: 7.4 | Z58: 5.4 | AB58: 6.7 | AC58: 11.8 | AD58: 76.4 | AG58: 0 | AI58: 111.2 | AJ58: 203.2 | AN58: 6.5 | AO58: 377.7 | AP58: 70.4 | AQ58: 116.4 | AR58: 38 | AS58: 9.4 | AT58: 19.7 | AU58: 90 | AV58: 184.3 | AX58: 90.7 | AY58: 110.3 | AZ58: 8.4 | BA58: 4.3 | BB58: 46.9 | BD58: 4 | BE58: 37.7 | BF58: 138.3 | BI58: 48.3 | BJ58: 0 | BK58: 0 | BL58: 46.2 | BP58: 86.5 | BR58: 174.8 | BS58: 200 | BT58: 182.4 | CC58: 4.5 | CD58: 150.5 | CE58: 127.3 | CF58: 65.8 | CG58: 79.5 | CH58: 30.5 | CL58: 116.1 | CM58: 116 | CN58: 125.8 | CV58: 0 | CW58: 76.2 | CX58: 0 | CY58: 0.6 | CZ58: 0 | DA58: 20 | DB58: 9.9 | DC58: 5.4 | DD58: 1 | DF58: 4.997 | DG58: 20.7 | DH58: 20 | DI58: 18.9 | DJ58: 3.6 | DK58: 18.5 | DL58: 0 | DM58: 0 | DN58: 4.5 | DO58: 6.9 | DP58: 2.1 | DQ58: 1.2 | DR58: 1.2 | DS58: 1.2 | DT58: 0 | DU58: 3.32 | DV58: 17.8 | DW58: 2.6 | DX58: 0 | DY58: 15.7 | DZ58: 8.1 | EA58: 10.8 | EB58: 14.4 | EC58: 20 | ED58: 1.9 | EE58: 30.7 | EF58: 0 | EG58: 6.4 | EH58: 19.1 | EI58: 0 | EJ58: 0 | EK58: 16 | EL58: 4.7 | EM58: 7.7 | EN58: 14.5 | EO58: 15.5 | EP58: 15.5 | EQ58: 0 | ER58: 0 | ES58: 0 | ET58: 0 | EU58: 0.6 | EV58: 0 | EW58: 0 | EX58: 0 | EY58: 0 | EZ58: 9.5 | FA58: 20 | FB58: 9.5 | FC58: 28.9 | FG58: 17.7 | FJ58: 6704.417 | FL58: 24.60394 | FM58: 8.054 | FO58: 13.2 | FP58: 26.54454 | FQ58: 18.9112 | FR58: 11.9 | FS58: 15.8 | FT58: 119.01368
A59: EJEC | C59: 2400.3 | D59: 15556.75 | E59: 5157.8 | F59: 20.2 | G59: 20.25 | H59: 2163.7 | I59: 5031.9 | J59: 0 | K59: 0 | L59: 2877.65 | M59: 2876.5 | N59: 2877.6 | O59: 5238.5 | P59: 4999.3 | Q59: 2633.45 | R59: 13446.7 | S59: 250.1 | T59: 0 | U59: 0 | V59: 0 | W59: 0 | X59: 3962.2 | Y59: 175.45 | Z59: 124.5 | AA59: 0 | AB59: 159.2 | AC59: 282.2 | AD59: 1920.5 | AE59: 0 | AF59: 0 | AG59: 16.8 | AH59: 0 | AI59: 2660.6 | AJ59: 4974.75 | AK59: 0 | AL59: 0 | AM59: 0 | AN59: 156 | AO59: 7196.3 | AP59: 1727.2 | AQ59: 3114.6 | AR59: 928.25 | AS59: 225.5 | AT59: 466.95 | AU59: 2159.05 | AV59: 3752.65 | AW59: 0 | AX59: 2006.5 | AY59: 2641 | AZ59: 198.95 | BA59: 103.75 | BB59: 1126.9 | BC59: 0 | BD59: 96 | BE59: 909.1 | BF59: 3663.95 | BG59: 0 | BH59: 0 | BI59: 1152.85 | BJ59: 137.15 | BK59: 1249 | BL59: 1099.35 | BM59: 0 | BN59: 0 | BO59: 0 | BP59: 2068 | BQ59: 0 | BR59: 3829.45 | BS59: 4333.75 | BT59: 4029.7 | BU59: 0 | BV59: 0 | BW59: 0 | BX59: 0 | BY59: 0 | BZ59: 0 | CA59: 0 | CB59: 0 | CC59: 110.3 | CD59: 3355.55 | CE59: 3115.25 | CF59: 1530.9 | CG59: 1895.2 | CH59: 725.55 | CI59: 0 | CJ59: 0 | CK59: 0 | CL59: 2823.85 | CM59: 2814.75 | CN59: 3161.5 | CO59: 0 | CP59: 0 | CQ59: 0 | CR59: 0 | CS59: 0 | CT59: 0 | CU59: 0 | CV59: 8.65 | CW59: 1750.15 | CX59: 632.3 | CY59: 220.75 | CZ59: 2.9 | DA59: 480.35 | DB59: 237.85 | DC59: 130.05 | DD59: 24 | DE59: 0 | DF59: 117.3805 | DG59: 488.25 | DH59: 480 | DI59: 453.2 | DJ59: 86.8 | DK59: 444 | DL59: 124.05 | DM59: 150.3 | DN59: 251.2 | DO59: 635.95 | DP59: 104.9 | DQ59: 22.05 | DR59: 51.55 | DS59: 21.9 | DT59: 151 | DU59: 78.7815 | DV59: 362.1 | DW59: 56.45 | DX59: 1.85 | DY59: 397.5 | DZ59: 185.05 | EA59: 257.05 | EB59: 364.9 | EC59: 479.3 | ED59: 195.85 | EE59: 640.2 | EF59: 269.55 | EG59: 645.1 | EH59: 1000.85 | EI59: 54.6 | EJ59: 20.3 | EK59: 405.75 | EL59: 117.05 | EM59: 189.6 | EN59: 361.9 | EO59: 386.45 | EP59: 382.8 | EQ59: 163.2 | ER59: 1966.6 | ES59: 120.6 | ET59: 1120.9 | EU59: 14.4 | EV59: 623.05 | EW59: 579.25 | EX59: 830.6 | EY59: 116 | EZ59: 227.05 | FA59: 479.45 | FB59: 232.7 | FC59: 435.4 | FD59: 0 | FE59: 0 | FF59: 0 | FG59: 422.4 | FH59: 0 | FI59: 0 | FJ59: 168985.76 | FL59: 591.24957 | FM59: 150.4285 | FN59: 0 | FO59: 316.75 | FP59: 634.55717 | FQ59: 453.90693 | FR59: 281.45 | FS59: 379 | FT59: 2807.3422

Sheet REACTIVA
B3: jueves, 15 de Mayo del 2025
A5: POTENCIA REACTIVA EJECUTADA DE LAS UNIDADES DE GENERACIÓN DEL COES (MVAR) | FK5: CENTRALES NO INTEGRANTES COES
A6: FECHA | B6: HORA | C6: 65333 | D6: 101 | E6: 102 | F6: 42667 | G6: 42668 | H6: 126 | I6: 127 | J6: 138 | K6: 139 | L6: 197 | M6: 203 | N6: 204 | O6: 230 | P6: 209 | Q6: 56677 | R6: 796 | S6: 2146 | T6: 142 | U6: 143 | V6: 125 | W6: 187 | X6: 163 | Y6: 298 | Z6: 219 | AA6: 151 | AB6: 152 | AC6: 153 | AD6: 154 | AE6: 756 | AF6: 156 | AG6: 155 | AH6: 182 | AI6: 212 | AJ6: 758 | AK6: 263 | AL6: 265 | AM6: 775 | AN6: 777 | AO6: 2154 | AP6: 150 | AQ6: 149 | AR6: 188 | AS6: 2131 | AT6: 755 | AU6: 252 | AV6: 249 | AW6: 250 | AX6: 117 | AY6: 267 | AZ6: 268 | BA6: 119 | BB6: 120 | BC6: 189 | BD6: 122 | BE6: 266 | BF6: 337 | BG6: 338 | BH6: 251 | BI6: 115 | BJ6: 239 | BK6: 288 | BL6: 240 | BM6: 241 | BN6: 242 | BO6: 191 | BP6: 194 | BQ6: 196 | BR6: 207 | BS6: 236 | BT6: 795 | BU6: 285 | BV6: 995 | BW6: 996 | BX6: 997 | BY6: 766 | BZ6: 926 | CA6: 924 | CB6: 121 | CC6: 103 | CD6: 104 | CE6: 106 | CF6: 105 | CG6: 107 | CH6: 110 | CI6: 109 | CJ6: 144 | CK6: 113 | CL6: 114 | CM6: 193 | CN6: 208 | CO6: 786 | CP6: 787 | CQ6: 788 | CR6: 789 | CS6: 248 | CT6: 2159 | CU6: 303 | CV6: 59715 | CW6: 62255 | CX6: 1263 | CY6: 61800 | CZ6: 2194 | DA6: 216 | DB6: 198 | DC6: 49607 | DD6: 214 | DE6: 260 | DF6: 2152 | DG6: 2128 | DH6: 247 | DI6: 228 | DJ6: 2135 | DK6: 261 | DL6: 237 | DM6: 253 | DN6: 770 | DO6: 225 | DP6: 2201 | DQ6: 2171 | DR6: 760 | DS6: 235 | DT6: 238 | DU6: 2184 | DV6: 61855 | DW6: 223 | DX6: 226 | DY6: 201 | DZ6: 258 | EA6: 259 | EB6: 920 | EC6: 257 | ED6: 256 | EE6: 2148 | EF6: 58288 | EG6: 58289 | EH6: 58839 | EI6: 58840 | EJ6: 296 | EK6: 297 | EL6: 211 | EM6: 2175 | EN6: 2178 | EO6: 2181 | EP6: 1262 | EQ6: 63425 | ER6: 233 | ES6: 2150 | ET6: 2165 | EU6: 2161 | EV6: 61197 | EW6: 58851 | EX6: 234 | EY6: 215 | EZ6: 917 | FA6: 289 | FB6: 58333 | FC6: 58336 | FD6: 202 | FE6: 58487 | FF6: 213 | FG6: 232 | FH6: 2190 | FI6: TOTAL COES | FK6: 221 | FL6: 222 | FM6: 224 | FN6: 2187 | FO6: 227 | FP6: 49400 | FQ6: 199 | FR6: 200 | FS6: TOTAL NO COES
C7: SUR | D7: CENTRO | E7: CENTRO | F7: NORTE | G7: NORTE | H7: NORTE | I7: NORTE | J7: CENTRO | K7: CENTRO | L7: CENTRO | M7: CENTRO | N7: CENTRO | O7: CENTRO | P7: CENTRO | Q7: CENTRO | R7: CENTRO | S7: CENTRO | T7: CENTRO | U7: CENTRO | V7: CENTRO | W7: CENTRO | X7: SUR | Y7: SUR | Z7: CENTRO | AA7: SUR | AB7: SUR | AC7: SUR | AD7: SUR | AE7: SUR | AF7: SUR | AG7: SUR | AH7: SUR | AI7: CENTRO | AJ7: NORTE | AK7: NORTE | AL7: NORTE | AM7: CENTRO | AN7: CENTRO | AO7: CENTRO | AP7: CENTRO | AQ7: CENTRO | AR7: CENTRO | AS7: CENTRO | AT7: SUR | AU7: CENTRO | AV7: CENTRO | AW7: CENTRO | AX7: CENTRO | AY7: CENTRO | AZ7: CENTRO | BA7: CENTRO | BB7: CENTRO | BC7: SUR | BD7: NORTE | BE7: CENTRO | BF7: CENTRO | BG7: CENTRO | BH7: CENTRO | BI7: NORTE | BJ7: NORTE | BK7: NORTE | BL7: SUR | BM7: SUR | BN7: SUR | BO7: CENTRO | BP7: CENTRO | BQ7: CENTRO | BR7: CENTRO | BS7: CENTRO | BT7: CENTRO | BU7: CENTRO | BV7: SUR | BW7: SUR | BX7: SUR | BY7: NORTE | BZ7: SUR | CA7: CENTRO | CB7: NORTE | CC7: CENTRO | CD7: CENTRO | CE7: CENTRO | CF7: CENTRO | CG7: CENTRO | CH7: CENTRO | CI7: CENTRO | CJ7: CENTRO | CK7: CENTRO | CL7: CENTRO | CM7: CENTRO | CN7: CENTRO | CO7: SUR | CP7: SUR | CQ7: SUR | CR7: SUR | CS7: CENTRO | CT7: CENTRO | CU7: CENTRO | CV7: CENTRO | CW7: SUR | CX7: NORTE | CY7: NORTE | CZ7: NORTE | DA7: NORTE | DB7: NORTE | DC7: SUR | DD7: CENTRO | DE7: CENTRO | DF7: CENTRO | DG7: NORTE | DH7: NORTE | DI7: CENTRO | DJ7: CENTRO | DK7: SUR | DL7: SUR | DM7: CENTRO | DN7: CENTRO | DO7: CENTRO | DP7: CENTRO | DQ7: CENTRO | DR7: CENTRO | DS7: SUR | DT7: CENTRO | DU7: CENTRO | DV7: NORTE | DW7: CENTRO | DX7: CENTRO | DY7: NORTE | DZ7: CENTRO | EA7: CENTRO | EB7: CENTRO | EC7: NORTE | ED7: NORTE | EE7: SUR | EF7: CENTRO | EG7: CENTRO | EH7: CENTRO | EI7: CENTRO | EJ7: CENTRO | EK7: CENTRO | EL7: SUR | EM7: SUR | EN7: SUR | EO7: SUR | EP7: NORTE | EQ7: SUR | ER7: SUR | ES7: SUR | ET7: CENTRO | EU7: CENTRO | EV7: CENTRO | EW7: SUR | EX7: SUR | EY7: NORTE | EZ7: CENTRO | FA7: NORTE | FB7: NORTE | FC7: NORTE | FD7: CENTRO | FE7: CENTRO | FF7: CENTRO | FG7: NORTE | FH7: NORTE | FK7: NORTE | FL7: CENTRO | FM7: NORTE | FN7: NORTE | FO7: NORTE | FP7: NORTE | FQ7: NORTE | FR7: NORTE
C8: HIDROELÉCTRICA | D8: HIDROELÉCTRICA | E8: HIDROELÉCTRICA | F8: TERMOELÉCTRICA | G8: TERMOELÉCTRICA | H8: HIDROELÉCTRICA | I8: HIDROELÉCTRICA | J8: TERMOELÉCTRICA | K8: TERMOELÉCTRICA | L8: TERMOELÉCTRICA | M8: TERMOELÉCTRICA | N8: TERMOELÉCTRICA | O8: TERMOELÉCTRICA | P8: TERMOELÉCTRICA | Q8: TERMOELÉCTRICA | R8: HIDROELÉCTRICA | S8: HIDROELÉCTRICA | T8: TERMOELÉCTRICA | U8: TERMOELÉCTRICA | V8: TERMOELÉCTRICA | W8: TERMOELÉCTRICA | X8: HIDROELÉCTRICA | Y8: HIDROELÉCTRICA | Z8: TERMOELÉCTRICA | AA8: HIDROELÉCTRICA | AB8: HIDROELÉCTRICA | AC8: HIDROELÉCTRICA | AD8: HIDROELÉCTRICA | AE8: TERMOELÉCTRICA | AF8: TERMOELÉCTRICA | AG8: TERMOELÉCTRICA | AH8: HIDROELÉCTRICA | AI8: HIDROELÉCTRICA | AJ8: TERMOELÉCTRICA | AK8: TERMOELÉCTRICA | AL8: TERMOELÉCTRICA | AM8: HIDROELÉCTRICA | AN8: HIDROELÉCTRICA | AO8: HIDROELÉCTRICA | AP8: HIDROELÉCTRICA | AQ8: HIDROELÉCTRICA | AR8: HIDROELÉCTRICA | AS8: HIDROELÉCTRICA | AT8: HIDROELÉCTRICA | AU8: TERMOELÉCTRICA | AV8: TERMOELÉCTRICA | AW8: TERMOELÉCTRICA | AX8: HIDROELÉCTRICA | AY8: HIDROELÉCTRICA | AZ8: HIDROELÉCTRICA | BA8: HIDROELÉCTRICA | BB8: HIDROELÉCTRICA | BC8: HIDROELÉCTRICA | BD8: HIDROELÉCTRICA | BE8: HIDROELÉCTRICA | BF8: HIDROELÉCTRICA | BG8: HIDROELÉCTRICA | BH8: HIDROELÉCTRICA | BI8: TERMOELÉCTRICA | BJ8: TERMOELÉCTRICA | BK8: TERMOELÉCTRICA | BL8: TERMOELÉCTRICA | BM8: TERMOELÉCTRICA | BN8: TERMOELÉCTRICA | BO8: HIDROELÉCTRICA | BP8: TERMOELÉCTRICA | BQ8: TERMOELÉCTRICA | BR8: TERMOELÉCTRICA | BS8: TERMOELÉCTRICA | BT8: TERMOELÉCTRICA | BU8: TERMOELÉCTRICA | BV8: TERMOELÉCTRICA | BW8: TERMOELÉCTRICA | BX8: TERMOELÉCTRICA | BY8: HIDROELÉCTRICA | BZ8: TERMOELÉCTRICA | CA8: TERMOELÉCTRICA | CB8: HIDROELÉCTRICA | CC8: HIDROELÉCTRICA | CD8: HIDROELÉCTRICA | CE8: HIDROELÉCTRICA | CF8: HIDROELÉCTRICA | CG8: HIDROELÉCTRICA | CH8: TERMOELÉCTRICA | CI8: TERMOELÉCTRICA | CJ8: TERMOELÉCTRICA | CK8: TERMOELÉCTRICA | CL8: TERMOELÉCTRICA | CM8: TERMOELÉCTRICA | CN8: TERMOELÉCTRICA | CO8: TERMOELÉCTRICA | CP8: TERMOELÉCTRICA | CQ8: TERMOELÉCTRICA | CR8: TERMOELÉCTRICA | CS8: TERMOELÉCTRICA | CT8: TERMOELÉCTRICA | CU8: SOLAR | CV8: EÓLICA | CW8: SOLAR | CX8: EÓLICA | CY8: SOLAR | CZ8: HIDROELÉCTRICA | DA8: HIDROELÉCTRICA | DB8: HIDROELÉCTRICA | DC8: HIDROELÉCTRICA | DD8: HIDROELÉCTRICA | DE8: HIDROELÉCTRICA | DF8: HIDROELÉCTRICA | DG8: HIDROELÉCTRICA | DH8: HIDROELÉCTRICA | DI8: HIDROELÉCTRICA | DJ8: HIDROELÉCTRICA | DK8: SOLAR | DL8: SOLAR | DM8: EÓLICA | DN8: EÓLICA | DO8: TERMOELÉCTRICA | DP8: TERMOELÉCTRICA | DQ8: TERMOELÉCTRICA | DR8: TERMOELÉCTRICA | DS8: SOLAR | DT8: HIDROELÉCTRICA | DU8: HIDROELÉCTRICA | DV8: HIDROELÉCTRICA | DW8: HIDROELÉCTRICA | DX8: HIDROELÉCTRICA | DY8: HIDROELÉCTRICA | DZ8: HIDROELÉCTRICA | EA8: HIDROELÉCTRICA | EB8: HIDROELÉCTRICA | EC8: EÓLICA | ED8: EÓLICA | EE8: SOLAR | EF8: EÓLICA | EG8: EÓLICA | EH8: EÓLICA | EI8: EÓLICA | EJ8: HIDROELÉCTRICA | EK8: HIDROELÉCTRICA | EL8: HIDROELÉCTRICA | EM8: HIDROELÉCTRICA | EN8: HIDROELÉCTRICA | EO8: HIDROELÉCTRICA | EP8: EÓLICA | EQ8: SOLAR | ER8: SOLAR | ES8: SOLAR | ET8: HIDROELÉCTRICA | EU8: EÓLICA | EV8: EÓLICA | EW8: SOLAR | EX8: SOLAR | EY8: HIDROELÉCTRICA | EZ8: HIDROELÉCTRICA | FA8: TERMOELÉCTRICA | FB8: TERMOELÉCTRICA | FC8: TERMOELÉCTRICA | FD8: TERMOELÉCTRICA | FE8: TERMOELÉCTRICA | FF8: TERMOELÉCTRICA | FG8: TERMOELÉCTRICA | FH8: TERMOELÉCTRICA | FK8: HIDROELÉCTRICA | FL8: HIDROELÉCTRICA | FM8: HIDROELÉCTRICA | FN8: HIDROELÉCTRICA | FO8: TERMOELÉCTRICA | FP8: TERMOELÉCTRICA | FQ8: HIDROELÉCTRICA | FR8: HIDROELÉCTRICA
C9: HYDRO GLOBAL PERÚ S.A.C. | D9: ELECTROPERU | E9: ELECTROPERU | F9: ELECTROPERU | G9: ELECTROPERU | H9: ORAZUL ENERGY PERÚ | I9: ORAZUL ENERGY PERÚ | J9: TERMOSELVA | K9: TERMOSELVA | L9: KALLPA GENERACION S.A. | M9: KALLPA GENERACION S.A. | N9: KALLPA GENERACION S.A. | O9: KALLPA GENERACION S.A. | P9: KALLPA GENERACION S.A. | Q9: KALLPA GENERACION S.A. | R9: KALLPA GENERACION S.A. | S9: KALLPA GENERACION S.A. | T9: SHOUGESA | U9: SHOUGESA | V9: SHOUGESA | W9: SHOUGESA | X9: EGEMSA | Y9: EGESUR | Z9: EGESUR | AA9: EGASA | AB9: EGASA | AC9: EGASA | AD9: EGASA | AE9: EGASA | AF9: EGASA | AG9: EGASA | AH9: SAN GABAN | AI9: CELEPSA | AJ9: MINERA CERRO VERDE | AK9: PLANTA DE RESERVA FRIA DE GENERACION DE ETEN S.A. | AL9: PLANTA DE RESERVA FRIA DE GENERACION DE ETEN S.A. | AM9: EMPRESA DE GENERACION HUALLAGA | AN9: EMPRESA DE GENERACION HUALLAGA | AO9: LA VIRGEN | AP9: CHINANGO S.A.C. | AQ9: CHINANGO S.A.C. | AR9: HIDROELECTRICA HUANCHOR S.A.C. | AS9: CELEPSA RENOVABLES S.R.L. | AT9: INLAND ENERGY SAC | AU9: FENIX POWER PERÚ | AV9: FENIX POWER PERÚ | AW9: FENIX POWER PERÚ | AX9: STATKRAFT S.A | AY9: STATKRAFT S.A | AZ9: STATKRAFT S.A | BA9: STATKRAFT S.A | BB9: STATKRAFT S.A | BC9: STATKRAFT S.A | BD9: STATKRAFT S.A | BE9: STATKRAFT S.A | BF9: CENTRALES SANTA ROSA S.A.C. | BG9: CENTRALES SANTA ROSA S.A.C. | BH9: EMPRESA DE GENERACION HUANZA | BI9: ENEL GENERACION PIURA S.A. | BJ9: ENEL GENERACION PIURA S.A. | BK9: ENEL GENERACION PIURA S.A. | BL9: ENGIE | BM9: ENGIE | BN9: ENGIE | BO9: ENGIE | BP9: ENGIE | BQ9: ENGIE | BR9: ENGIE | BS9: ENGIE | BT9: ENGIE | BU9: ENGIE | BV9: ENGIE | BW9: ENGIE | BX9: ENGIE | BY9: ENGIE | BZ9: INFRAESTRUCTURAS Y ENERGIAS DEL PERU S.A.C. | CA9: INFRAESTRUCTURAS Y ENERGIAS DEL PERU S.A.C. | CB9: INVERSIONES SHAQSHA S.A.C. | CC9: ORYGEN PERU S.A.A. | CD9: ORYGEN PERU S.A.A. | CE9: ORYGEN PERU S.A.A. | CF9: ORYGEN PERU S.A.A. | CG9: ORYGEN PERU S.A.A. | CH9: ORYGEN PERU S.A.A. | CI9: ORYGEN PERU S.A.A. | CJ9: ORYGEN PERU S.A.A. | CK9: ORYGEN PERU S.A.A. | CL9: ORYGEN PERU S.A.A. | CM9: ORYGEN PERU S.A.A. | CN9: ORYGEN PERU S.A.A. | CO9: SAMAY I S.A.C | CP9: SAMAY I S.A.C | CQ9: SAMAY I S.A.C | CR9: SAMAY I S.A.C | CS9: TERMOCHILCA S.A.C. | CT9: TERMOCHILCA S.A.C. | CU9: COLCA SOLAR S.A.C. | CV9: ENERGIA RENOVABLE DEL SUR S.A. | CW9: GR CORTARRAMA SOCIEDAD ANONIMA CERRADA | CX9: GR TARUCA SOCIEDAD ANONIMA CERRADA | CY9: KONDU SAC | CZ9: PERUANA DE INVERSIONES EN ENERGIAS RENOVABLES S.A. | DA9: ORAZUL ENERGY PERÚ | DB9: ORAZUL ENERGY PERÚ | DC9: SAN GABAN | DD9: MAJA ENERGIA S.A.C. | DE9: EMPRESA DE GENERACION ELECTRICA CANCHAYLLO SAC | DF9: EMPRESA DE GENERACION ELECTRICA SANTA ANA S.A.C. | DG9: EMPRESA ELECTRICA AGUA AZUL | DH9: EMPRESA ELECTRICA RIO DOBLE | DI9: HIDROCAÑETE S.A. | DJ9: HUAURA POWER GROUP S.A. | DK9: MOQUEGUA FV S.A.C. | DL9: PANAMERICANA SOLAR SAC. | DM9: PARQUE EOLICO MARCONA S.A.C. | DN9: PARQUE EOLICO TRES HERMANAS S.A.C. | DO9: PETRAMAS | DP9: PETRAMAS | DQ9: PETRAMAS | DR9: PETRAMAS | DS9: TACNA SOLAR SAC. | DT9: ELECTRICA YANAPAMPA SAC | DU9: ANDEAN POWER S.A.C. | DV9: ASOCIACIÓN SANTA LUCIA DE CHACAS | DW9: ATRIA ENERGIA S.A.C. | DX9: EGEJUNIN | DY9: EGEJUNIN | DZ9: EGEJUNIN | EA9: EGEJUNIN | EB9: EMPRESA DE GENERACION ELECTRICA RIO BAÑOS S.A.C. | EC9: ENERGÍA EÓLICA S.A. | ED9: ENERGÍA EÓLICA S.A. | EE9: ENGIE | EF9: ENGIE | EG9: ENGIE | EH9: ENGIE | EI9: ENGIE | EJ9: GENERACIÓN ANDINA S.A.C. | EK9: GENERACIÓN ANDINA S.A.C. | EL9: GENERADORA DE ENERGÍA DEL PERÚ | EM9: GENERADORA DE ENERGÍA DEL PERÚ | EN9: GENERADORA DE ENERGÍA DEL PERÚ | EO9: GENERADORA DE ENERGÍA DEL PERÚ | EP9: GR PAINO SOCIEDAD ANONIMA CERRADA | EQ9: JOYA SOLAR S.A.C. | ER9: MAJES ARCUS S.A.C. | ES9: ORYGEN PERU S.A.A. | ET9: ORYGEN PERU S.A.A. | EU9: ORYGEN PERU S.A.A. | EV9: ORYGEN PERU S.A.A. | EW9: ORYGEN PERU S.A.A. | EX9: REPARTICIÓN ARCUS S.A.C. | EY9: SINERSA | EZ9: SINERSA | FA9: BIOENERGIA DEL CHIRA S.A. | FB9: GM OPERACIONES S.A.C. | FC9: GM OPERACIONES S.A.C. | FD9: SDF ENERGIA SAC | FE9: SDF ENERGIA SAC | FF9: AGRO INDUSTRIAL PARAMONGA S.A. | FG9: AGROAURORA S.A.C. | FH9: AGROINDUSTRIAS SAN JACINTO S.A.A. | FK9: UNACEM PERU S.A. | FL9: ELECTRO ORIENTE | FM9: AGUAS Y ENERGIA PERU | FN9: ELECTRO ZAÑA S.A.C. | FO9: ELECTRONOROESTE S.A. | FP9: SDE PIURA | FQ9: SINERSA | FR9: SINERSA
C10: SAN GABAN III | D10: MANTARO | E10: RESTITUCION | F10: TUMBES MAK 1 | G10: TUMBES MAK 2 | H10: CARHUAQUERO | I10: CAÑON DEL PATO | J10: AGUAYTIA TG1 | K10: AGUAYTIA TG2 | L10: KALLPA TG1 | M10: KALLPA TG2 | N10: KALLPA TG3 | O10: KALLPA TV | P10: LFLORES TG1 | Q10: LFLORES TV | R10: CERRO DEL AGUILA | S10: CERRODELAGUILAG4 | T10: SHOUGESA TV1 | U10: SHOUGESA TV2 | V10: SHOUGESA TV3 | W10: SHOUGESA CUMMINS | X10: MACHUPICCHU | Y10: ARICOTA 1 | Z10: INDEPENDENCIA | AA10: CHARCANI I,II,III | AB10: CHARCANI IV | AC10: CHARCANI V | AD10: CHARCANI VI | AE10: CHILINA TG | AF10: MOLLENDO 1, 2, 3 | AG10: CHILINA (SULZ 1,2) | AH10: SAN GABAN II | AI10: PLATANAL | AJ10: RECKA | AK10: RF ETEN TG1 | AL10: RF ETEN TG2 | AM10: CHAGLLA GP1 | AN10: CHAGLLA | AO10: LA VIRGEN | AP10: CHIMAY | AQ10: YANANGO | AR10: HUANCHOR | AS10: MARAÑON | AT10: STA TERESA | AU10: FENIX GT11 | AV10: FENIX GT12 | AW10: FENIX TV10 | AX10: YAUPI | AY10: OROYA | AZ10: PACHACHACA | BA10: MALPASO | BB10: CAHUA | BC10: ARCATA | BD10: GALLITO CIEGO | BE10: CHEVES | BF10: SANTA ROSA 1 | BG10: SANTA ROSA 2 | BH10: HUANZA | BI10: MALACAS2 TG4 | BJ10: MALACAS3 TG 5 | BK10: MALACAS1 TG6 | BL10: RF ILO2 TG1 | BM10: RF ILO2 TG2 | BN10: RF ILO2 TG3 | BO10: YUNCAN | BP10: CHILCA1 TG1 | BQ10: CHILCA1 TG2 | BR10: CHILCA1 TG3 | BS10: CHILCA-TV | BT10: CHILCA2 TG41 | BU10: CHILCA2-TV | BV10: CTNEPI_TG41 | BW10: CTNEPI_TG42 | BX10: CTNEPI_TG43 | BY10: QUITARACSA | BZ10: RF PTO MALDONADO | CA10: RF PUCALLPA | CB10: PARIAC | CC10: HUINCO | CD10: MATUCANA | CE10: MOYOPAMPA | CF10: CALLAHUANCA | CG10: HUAMPANI | CH10: STA ROSA WEST TG7 | CI10: UTI_5 | CJ10: UTI_6 | CK10: VENTANILLA 3 | CL10: VENTANILLA 4 | CM10: VENTANILLA TV | CN10: STAROSA TG8 | CO10: PTO_BRVO TG1 | CP10: PTO_BRVO TG2 | CQ10: PTO_BRVO TG3 | CR10: PTO_BRVO TG4 | CS10: OLLEROS TG1 | CT10: OLLEROS TV | CU10: CS YARUCAYA | CV10: SAN JUAN | CW10: MATARANI | CX10: DUNA | CY10: CARHUAQUERO (CS) | CZ10: MANTA I | DA10: CARHUAQUERO4 | DB10: CAÑA BRAVA | DC10: TUPURI | DD10: RONCADOR | DE10: CANCHAYLLO | DF10: RENOVANDESH1 | DG10: POTRERO | DH10: PIZARRAS | DI10: NIMPERIAL | DJ10: YARUCAYA | DK10: MOQUEGUA-SOLAR | DL10: PANAMERICANA-SOLAR | DM10: PQE-EOLICO-MARCONA | DN10: PQE-EOLICO-3-HERMANAS | DO10: HUAYCOLORO | DP10: CALLAO | DQ10: DONA_CATALINA | DR10: LAGRINGAV | DS10: TACNA-SOLAR | DT10: YANAPAMPA | DU10: CARHUAC | DV10: HUALLIN | DW10: PURMACANA | DX10: HUASAHUASI | DY10: STACRUZ_1_2 | DZ10: RUNATULLO_II | EA10: RUNATULLO_III | EB10: RUCUY | EC10: PQE-EOLICO-TALARA | ED10: PQE-EOLICO-CUPISNIQUE | EE10: INTIPAMPA | EF10: PUNTA LOMITAS-BL1 | EG10: PUNTA LOMITAS-BL2 | EH10: PUN LOMITAS_EXP-BL1 | EI10: PUN LOMITAS_EXP-BL2 | EJ10: 8AGOSTO | EK10: EL CARMEN | EL10: LA JOYA | EM10: ANGEL_I | EN10: ANGEL_II | EO10: ANGEL_III | EP10: HUAMBOS | EQ10: SAN MARTIN SOLAR | ER10: MAJES | ES10: RUBI | ET10: CH_HER1 | EU10: WAYRA-I | EV10: WAYRA EXTENSION | EW10: CLEMESI | EX10: REPARTICION | EY10: POECHOS2 | EZ10: CHANCAY | FA10: CANA BRAVA | FB10: REFINERIA TALARA TV1 | FC10: REFINERÍA TALARA TV2 | FD10: OQUENDO TG1 | FE10: OQUENDO TV1 | FF10: PARAMONGA | FG10: MAPLE | FH10: SAN_JACINTO | FI10: MVAR | FK10: CARPAPATA | FL10: CENTRALES ELOR | FM10: PIAS1 | FN10: ZANA | FO10: TABLAZO | FP10: TALLANCA | FQ10: CURUMUY | FR10: POECHOS1 | FS10: MVAR
A11: 15/05/2025 | B11: 00:30 | C11: 6.4 | D11: 4.2 | E11: 17.3 | F11: 0 | G11: 0 | H11: -21.2 | I11: -8.4 | L11: -37.7 | M11: -34.7 | N11: -18.4 | O11: 22 | P11: -8.4 | Q11: -6.3 | R11: 54.7 | S11: 0 | X11: -1.6 | Y11: 0.8 | AA11: -3.3 | AB11: 3.9 | AC11: -4 | AF11: 0 | AH11: 3 | AI11: 16.4 | AM11: -1.5 | AN11: -8.1 | AO11: 6.5 | AP11: 1.4 | AQ11: -0.1 | AR11: 0 | AS11: 2.7 | AT11: 0.7 | AU11: -28.7 | AW11: -66.6 | AX11: 5.6 | AY11: -1.9 | AZ11: 0.9 | BA11: -4.9 | BC11: 1 | BD11: -0.1 | BE11: 7.6 | BH11: -8.1 | BI11: 0 | BJ11: 3.1 | BK11: -0.7 | BO11: 0.4 | BQ11: -31.9 | BR11: -7.1 | BS11: 6 | CB11: -0.4 | CC11: 23 | CD11: 23.5 | CE11: -0.9 | CF11: 4.4 | CG11: -0.3 | CK11: 3.1 | CL11: 1.8 | CM11: -43.5 | CV11: -5.2 | CW11: 0 | CZ11: 1.2 | DA11: 0 | DB11: -0.9 | DE11: 1.003 | DF11: 1.6 | DG11: -1.5 | DH11: 0.9 | DI11: 0.6 | DK11: 0 | DL11: 0 | DM11: -2.1 | DN11: -6.3 | DO11: 1.8 | DP11: 0.2 | DQ11: 0.7 | DR11: 0 | DS11: 0 | DT11: 0 | DU11: 0.6 | DV11: 0.4 | DX11: -4.1 | DY11: 0.2 | DZ11: 0.4 | EA11: -1.5 | EB11: 0.9 | EC11: 0.8 | ED11: 4 | EE11: 0 | EF11: -6.7 | EG11: -11.9 | EJ11: 2.2 | EK11: 0 | EL11: 1.9 | EM11: 0.2 | EN11: 0.2 | EO11: 0.2 | EQ11: 0 | ER11: 0 | ES11: 0 | ET11: -0.2 | EU11: 0 | EV11: 3.7 | EW11: 0 | EX11: 0 | EY11: 0.4 | EZ11: 1.2 | FA11: 3.1 | FB11: 0 | FF11: 1.8 | FI11: -138.597 | FK11: 1.67477 | FL11: -0.057 | FN11: 1.6 | FO11: 0 | FP11: 3.87362 | FQ11: -0.5 | FR11: 2 | FS11: 8.59139
A12: 15/05/2025 | B12: 01:00 | C12: 6.7 | D12: 10.4 | E12: 18.5 | F12: 0.9 | G12: 1 | H12: -17.2 | I12: 12.4 | L12: -37.5 | M12: -29.6 | N12: -14.8 | O12: 20.6 | P12: -5 | Q12: -3.6 | R12: 55.6 | S12: 0 | X12: -1.5 | Y12: 0.6 | AA12: -3.3 | AB12: 3.9 | AC12: -4 | AF12: 0 | AH12: 1.7 | AI12: 0 | AM12: -1.3 | AN12: -8.8 | AO12: 6.3 | AP12: 2.4 | AQ12: -0.4 | AR12: -0.2 | AS12: 2.7 | AT12: 0.3 | AU12: -19.1 | AW12: -58.5 | AX12: 1 | AY12: -1.9 | AZ12: 0.6 | BA12: -3.6 | BC12: 1 | BD12: 0 | BE12: 6.6 | BH12: -6.6 | BI12: 0 | BJ12: 7.4 | BK12: 1.2 | BO12: 1.8 | BQ12: -29 | BR12: -3 | BS12: 10.4 | CB12: -0.4 | CC12: 23.3 | CD12: 14.8 | CE12: 0.3 | CF12: 2 | CG12: -0.3 | CK12: 7.7 | CL12: 5.3 | CM12: -37.5 | CV12: -5.2 | CW12: 0 | CZ12: 1.2 | DA12: 0 | DB12: -0.9 | DE12: 0.957 | DF12: 1.6 | DG12: -1.3 | DH12: 1.3 | DI12: 0.5 | DK12: 0 | DL12: 0 | DM12: -1.8 | DN12: -6.2 | DO12: 1.8 | DP12: 0.2 | DQ12: 0.7 | DR12: 0 | DS12: 0 | DT12: 0 | DU12: 0.6 | DV12: 0.4 | DX12: -4.2 | DY12: 0.1 | DZ12: 0.4 | EA12: -1.5 | EB12: 0.9 | EC12: 0.8 | ED12: 4 | EE12: 0 | EF12: -5.5 | EG12: -9.5 | EJ12: 2.2 | EK12: 0 | EL12: 1.9 | EM12: 0.2 | EN12: 0.2 | EO12: 0.2 | EQ12: 0 | ER12: 0 | ES12: 0 | ET12: -0.2 | EU12: 0 | EV12: 3.7 | EW12: 0 | EX12: 0 | EY12: 0.4 | EZ12: 1.2 | FA12: 2.8 | FB12: 0 | FF12: 3.1 | FI12: -64.643 | FK12: 1.70867 | FL12: 0.198 | FN12: 1.7 | FO12: 0 | FP12: 3.86954 | FQ12: -0.2 | FR12: 2.2 | FS12: 9.47621
A13: 15/05/2025 | B13: 01:30 | C13: 6.8 | D13: 7.8 | E13: 17.3 | F13: 1 | G13: 1 | H13: -16.4 | I13: 7 | L13: -36.9 | M13: -36.8 | N13: -19.1 | O13: 22.6 | P13: -4.8 | Q13: -3.9 | R13: 56.2 | S13: 0.1 | X13: -2.8 | Y13: 0.9 | AA13: -3.3 | AB13: 3.7 | AC13: -4.2 | AF13: 0 | AH13: 2.7 | AI13: 5.7 | AM13: -1.3 | AN13: -8.4 | AO13: 6.8 | AP13: 2.7 | AQ13: 0 | AR13: -0.2 | AS13: 2.7 | AT13: 1.4 | AU13: -20.7 | AW13: -58.7 | AX13: 3.5 | AY13: -1.9 | AZ13: 0.8 | BA13: -4.6 | BC13: 1.1 | BD13: -0.2 | BE13: 6.1 | BH13: -6.8 | BI13: 0 | BJ13: 0 | BK13: 9 | BO13: 2.3 | BQ13: -28.7 | BR13: -3.3 | BS13: 9.7 | CB13: -0.4 | CC13: 21.2 | CD13: 15.5 | CE13: -0.6 | CF13: 2.2 | CG13: -0.1 | CK13: 6 | CL13: 4.9 | CM13: -39.1 | CV13: -5.4 | CW13: 0 | CZ13: 1.2 | DA13: -0.1 | DB13: -0.9 | DE13: 0.959 | DF13: 1.6 | DG13: -1.2 | DH13: 1.4 | DI13: 0.6 | DK13: 0 | DL13: 0 | DM13: -1.8 | DN13: -4.4 | DO13: 1.8 | DP13: 0.2 | DQ13: 0.7 | DR13: 0 | DS13: 0 | DT13: 0 | DU13: 0.6 | DV13: 0.4 | DX13: -4.2 | DY13: 0.2 | DZ13: 0.4 | EA13: -1.6 | EB13: 1.1 | EC13: 0.8 | ED13: 4 | EE13: 0 | EF13: -6.5 | EG13: -11.5 | EJ13: 2.2 | EK13: -0.1 | EL13: 1.9 | EM13: 0.2 | EN13: 0.2 | EO13: 0.2 | EQ13: 0 | ER13: 0 | ES13: 0 | ET13: -0.2 | EU13: 0 | EV13: 3.7 | EW13: 0 | EX13: 0 | EY13: 0.4 | EZ13: 1.4 | FA13: 2.8 | FB13: 0 | FF13: 2.5 | FI13: -80.941 | FK13: 1.7484 | FL13: 0.402 | FN13: 1.7 | FO13: 0 | FP13: 3.84817 | FQ13: 1.4 | FR13: 2.1 | FS13: 11.19857
A14: 15/05/2025 | B14: 02:00 | C14: 6.8 | D14: 13.5 | E14: 18.2 | F14: 0.7 | G14: 0.8 | H14: -17.4 | I14: -2.8 | L14: -37.3 | M14: -33.9 | N14: -17.7 | O14: 21.4 | P14: -8.1 | Q14: -5.5 | R14: 53.7 | S14: 0.3 | X14: -2.6 | Y14: 0.4 | AA14: -3.3 | AB14: 4 | AC14: -5.1 | AF14: 0 | AH14: 3.4 | AI14: 3.2 | AM14: -1.3 | AN14: -8.1 | AO14: 7.2 | AP14: 3.1 | AQ14: -0.6 | AR14: 0.2 | AS14: 2.7 | AT14: 0.4 | AU14: -23.2 | AW14: -63.2 | AX14: 1.6 | AY14: -1.9 | AZ14: 0.8 | BA14: -2.7 | BC14: 1 | BD14: -0.1 | BE14: 10.9 | BH14: -7.7 | BI14: 0 | BJ14: 0 | BK14: 7.7 | BO14: -0.2 | BQ14: -36.3 | BR14: -11.2 | BS14: 4.2 | CB14: -0.4 | CC14: 21.1 | CD14: 16.3 | CE14: -0.2 | CF14: 2.2 | CG14: -0.1 | CK14: 3.1 | CL14: 2.1 | CM14: -43.5 | CV14: -5.4 | CW14: 0 | CZ14: 1.2 | DA14: 0 | DB14: -0.9 | DE14: 0.99 | DF14: 1.6 | DG14: -1.3 | DH14: 1.4 | DI14: 0.6 | DK14: 0 | DL14: 0 | DM14: -1.9 | DN14: -4 | DO14: 1.8 | DP14: 0.2 | DQ14: 0.7 | DR14: 0 | DS14: 0 | DT14: -0.2 | DU14: 0.6 | DV14: 0.4 | DX14: -4.2 | DY14: 0.5 | DZ14: 0.3 | EA14: -1.6 | EB14: 1.1 | EC14: 0.8 | ED14: 4 | EE14: 0 | EF14: -5.5 | EG14: -10 | EJ14: 2.2 | EK14: -0.1 | EL14: 1.8 | EM14: 0.2 | EN14: 0.2 | EO14: 0.2 | EQ14: 0 | ER14: 0 | ES14: 0 | ET14: -0.2 | EU14: 0 | EV14: 3.7 | EW14: 0 | EX14: 0 | EY14: 0.4 | EZ14: 1.4 | FA14: 2.8 | FB14: 0 | FF14: 2.2 | FI14: -127.41 | FK14: 1.83039 | FL14: 0.396 | FN14: 1.7 | FO14: 0 | FP14: 3.84412 | FQ14: 0.7 | FR14: 1.9 | FS14: 10.37051
A15: 15/05/2025 | B15: 02:30 | C15: 6.7 | D15: 13.7 | E15: 17.5 | F15: 0.8 | G15: 0.8 | H15: -14.8 | I15: 16.6 | L15: -33.9 | M15: -36.2 | N15: -18.9 | O15: 26.2 | P15: -10.9 | Q15: -6.1 | R15: 55.3 | S15: 0 | X15: -1.2 | Y15: 0.4 | AA15: -3.3 | AB15: 4 | AC15: -5.1 | AF15: 0 | AH15: 1.6 | AI15: 15 | AM15: -1.4 | AN15: -8.6 | AO15: 7.3 | AP15: 3.8 | AQ15: -0.2 | AR15: 0 | AS15: 2.7 | AT15: 2.3 | AU15: -21.9 | AW15: -62.8 | AX15: 3.5 | AY15: -1.9 | AZ15: 0.9 | BA15: -4.5 | BC15: 1 | BD15: -0.2 | BE15: 6.7 | BH15: -7.7 | BI15: 0 | BJ15: 0 | BK15: 7.7 | BO15: 2 | BQ15: -40.4 | BR15: -17.5 | BS15: -3.2 | CB15: -0.4 | CC15: 20.7 | CD15: 17.5 | CE15: 0.8 | CF15: 2.1 | CG15: -0.1 | CK15: 4.5 | CL15: 3.5 | CM15: -42 | CV15: -5.4 | CW15: 0 | CZ15: 1.2 | DA15: 0 | DB15: -0.9 | DE15: 0.991 | DF15: 1.6 | DG15: -1.3 | DH15: 1.5 | DI15: 0.5 | DK15: 0 | DL15: 0 | DM15: -1.9 | DN15: -3.7 | DO15: 1.8 | DP15: 0.2 | DQ15: 0.7 | DR15: 0 | DS15: 0 | DT15: 0.1 | DU15: 0.6 | DV15: 0.4 | DX15: -4.1 | DY15: 0.4 | DZ15: 0.4 | EA15: -1.6 | EB15: 0.9 | EC15: 0.8 | ED15: 4 | EE15: 0 | EF15: -5.1 | EG15: -9.6 | EJ15: 2.2 | EK15: -0.1 | EL15: 2 | EM15: 0.2 | EN15: 0.2 | EO15: 0.2 | EQ15: 0 | ER15: 0 | ES15: 0 | ET15: -0.2 | EU15: 0 | EV15: 3.7 | EW15: 0 | EX15: 0 | EY15: 0.4 | EZ15: 1.2 | FA15: 2.9 | FB15: 0 | FF15: 2.9 | FI15: -99.509 | FK15: 1.72537 | FL15: 0.454 | FN15: 1.6 | FO15: 0 | FP15: 3.8343 | FQ15: 0.7 | FR15: 2 | FS15: 10.31367
A16: 15/05/2025 | B16: 03:00 | C16: 7.8 | D16: 12.8 | E16: 18.1 | F16: 0.9 | G16: 0.8 | H16: -16.9 | I16: 8.1 | L16: -33.1 | M16: -35.5 | N16: -19.1 | O16: 27.6 | P16: -10.1 | Q16: -7.5 | R16: 60.4 | S16: 0 | X16: -2.3 | Y16: 1 | AA16: -3.3 | AB16: 4.8 | AC16: -2 | AF16: 0 | AH16: 3.1 | AI16: 14.6 | AM16: -1.4 | AN16: -8.4 | AO16: 7.5 | AP16: 3.4 | AQ16: 0.3 | AR16: -0.1 | AS16: 2.7 | AT16: 1.8 | AU16: -24.7 | AW16: -62.7 | AX16: 3.7 | AY16: -1.9 | AZ16: 0.6 | BA16: -4.6 | BC16: 1.1 | BD16: -0.1 | BE16: 7.1 | BH16: -7.9 | BI16: 0 | BJ16: 0 | BK16: 6.4 | BO16: 2 | BQ16: -40 | BR16: -17.5 | BS16: -2 | CB16: -0.4 | CC16: 21.5 | CD16: 16.2 | CE16: -0.4 | CF16: 2.2 | CG16: -0.1 | CK16: 4.4 | CL16: 3.2 | CM16: -41.3 | CV16: -5.5 | CW16: 0 | CZ16: 1.2 | DA16: -0.1 | DB16: -0.9 | DE16: 0.99 | DF16: 1.6 | DG16: -1.3 | DH16: 1.4 | DI16: 0.6 | DK16: 0 | DL16: 0 | DM16: -1.6 | DN16: -3.5 | DO16: 1.8 | DP16: 0.2 | DQ16: 0.7 | DR16: 0 | DS16: 0 | DT16: 0 | DU16: 0.6 | DV16: 0.4 | DX16: -4.2 | DY16: 0 | DZ16: 0.4 | EA16: -1.6 | EB16: 0.9 | EC16: 0.8 | ED16: 4 | EE16: 0 | EF16: -3.9 | EG16: -8.1 | EJ16: 2.2 | EK16: -0.1 | EL16: 1.9 | EM16: 0.2 | EN16: 0.2 | EO16: 0.2 | EQ16: 0 | ER16: 0 | ES16: 0 | ET16: -0.2 | EU16: 0 | EV16: 3.7 | EW16: 0 | EX16: 0 | EY16: 0.4 | EZ16: 1.2 | FA16: 2.8 | FB16: 0 | FF16: 3.1 | FI16: -98.71 | FK16: 1.76781 | FL16: 0.396 | FN16: 1.7 | FO16: 0 | FP16: 3.84152 | FQ16: 0.5 | FR16: 2 | FS16: 10.20533
A17: 15/05/2025 | B17: 03:30 | C17: 7.2 | D17: 14.2 | E17: 18 | F17: 0.7 | G17: 1 | H17: -16.4 | I17: 0.4 | L17: -37 | M17: -33.7 | N17: -20.9 | O17: 22.3 | P17: -11.1 | Q17: -8.2 | R17: 57.2 | S17: 0.1 | X17: -1.1 | Y17: 0.6 | AA17: -3.3 | AB17: 4.8 | AC17: -2 | AF17: 0 | AH17: 3.4 | AI17: 13.6 | AM17: -1.4 | AN17: -8.6 | AO17: 7.8 | AP17: 3.1 | AQ17: -0.3 | AR17: -0.1 | AS17: 2.7 | AT17: 0.9 | AU17: -25.4 | AW17: -65.2 | AX17: 3.6 | AY17: -2 | AZ17: 0.6 | BA17: -4.1 | BC17: 1.1 | BD17: -0.2 | BE17: 8.7 | BH17: -8.1 | BI17: 0 | BJ17: 0 | BK17: 6.7 | BO17: -0.1 | BQ17: -41.8 | BR17: -19.2 | BS17: -3.5 | CB17: -0.4 | CC17: 20.4 | CD17: 16.1 | CE17: 0.2 | CF17: 2.1 | CG17: -0.1 | CK17: 1.7 | CL17: 0.9 | CM17: -45.3 | CV17: -5.3 | CW17: 0 | CZ17: 1.2 | DA17: 0 | DB17: -0.9 | DE17: 0.989 | DF17: 1.6 | DG17: -1.1 | DH17: 1.4 | DI17: 0.5 | DK17: 0 | DL17: 0 | DM17: -1.8 | DN17: -4.1 | DO17: 1.8 | DP17: 0.2 | DQ17: 0.7 | DR17: 0 | DS17: 0 | DT17: 0 | DU17: 0.5 | DV17: 0.4 | DX17: -4.2 | DY17: 0.1 | DZ17: 0.4 | EA17: -0.8 | EB17: 0.9 | EC17: 0.8 | ED17: 4 | EE17: 0 | EF17: -2 | EG17: -6 | EJ17: 2.2 | EK17: -0.1 | EL17: 2 | EM17: 0.2 | EN17: 0.2 | EO17: 0.2 | EQ17: 0 | ER17: 0 | ES17: 0 | ET17: -0.2 | EU17: 0 | EV17: 3.7 | EW17: 0 | EX17: 0 | EY17: 0.4 | EZ17: 1.2 | FA17: 2.7 | FB17: 0 | FF17: 3.6 | FI17: -134.011 | FK17: 1.82812 | FL17: 0.495 | FN17: 1.7 | FO17: 2.31418 | FP17: 3.84489 | FQ17: 0.4 | FR17: 2 | FS17: 12.58219
A18: 15/05/2025 | B18: 04:00 | C18: 6.8 | D18: 1.5 | E18: 15.7 | F18: 1.1 | G18: 1 | H18: -16.1 | I18: 10.6 | L18: -37 | M18: -41.3 | N18: -24.6 | O18: 24.8 | P18: -13.6 | Q18: -10.1 | R18: 54.3 | S18: -0.2 | X18: -2.3 | Y18: 1 | AA18: -3.3 | AB18: 4.9 | AC18: 1.2 | AF18: 0 | AH18: 1.9 | AI18: 14.7 | AM18: -1.4 | AN18: -8.7 | AO18: 7.4 | AP18: 1.1 | AQ18: -4.3 | AR18: 0.1 | AS18: 2.7 | AT18: 0.1 | AU18: -32 | AW18: -68.6 | AX18: 0.8 | AY18: -1.7 | AZ18: 0.9 | BA18: -6.7 | BC18: 1.1 | BD18: -0.1 | BE18: 4.8 | BH18: -3.2 | BI18: 0 | BJ18: 0 | BK18: 7.1 | BO18: 2 | BQ18: -43 | BR18: -20.9 | BS18: -6.1 | CB18: -0.4 | CC18: 21.4 | CD18: 16.2 | CE18: 0.4 | CF18: 2.2 | CG18: 0 | CK18: 11.2 | CL18: 10.3 | CM18: -31.4 | CV18: -5.1 | CW18: 0 | CZ18: 1.2 | DA18: 0 | DB18: -0.9 | DE18: 0.994 | DF18: 1.6 | DG18: -1.1 | DH18: 1.3 | DI18: 0.6 | DK18: 0 | DL18: 0 | DM18: -2.2 | DN18: -4.7 | DO18: 1.8 | DP18: 0.2 | DQ18: 0.7 | DR18: 0 | DS18: 0 | DT18: -0.1 | DU18: 0.6 | DV18: 0.3 | DX18: -4.1 | DY18: 0.2 | DZ18: 0.3 | EA18: -0.8 | EB18: 1.3 | EC18: 0.8 | ED18: 4 | EE18: 0 | EF18: -3.7 | EG18: -10 | EJ18: 2.2 | EK18: -0.1 | EL18: 2 | EM18: 0.2 | EN18: 0.2 | EO18: 0.2 | EQ18: 0 | ER18: 0 | ES18: 0 | ET18: -0.2 | EU18: 0 | EV18: 3.7 | EW18: 0 | EX18: 0 | EY18: 0.4 | EZ18: 1.6 | FA18: 2.7 | FB18: 0 | FF18: 3.8 | FI18: -147.806 | FK18: 1.84009 | FL18: 0.528 | FN18: 1.8 | FO18: 2.31523 | FP18: 3.84637 | FQ18: 0.7 | FR18: 2.2 | FS18: 13.22969
A19: 15/05/2025 | B19: 04:30 | C19: 6.4 | D19: 11.2 | E19: 17.4 | F19: 0.8 | G19: 0.8 | H19: -16.3 | I19: 0.2 | L19: -38.5 | M19: -31.1 | N19: -13.8 | O19: 20.7 | P19: -15 | Q19: -10.6 | R19: 49.5 | S19: 0.3 | X19: -2.8 | Y19: 1.1 | AA19: -3.3 | AB19: 4.9 | AC19: 1.4 | AF19: 0 | AH19: 3.6 | AI19: 14.1 | AM19: -1.4 | AN19: -8.4 | AO19: 7.4 | AP19: 0.8 | AQ19: -4.4 | AR19: 0.1 | AS19: 2.7 | AT19: 0.3 | AU19: -31.7 | AW19: -64.3 | AX19: 4.3 | AY19: -2 | AZ19: 0.6 | BA19: -3 | BC19: 1 | BD19: -0.2 | BE19: 11.1 | BH19: -3.2 | BI19: 0 | BJ19: 0 | BK19: 7.3 | BO19: -1.8 | BQ19: -45.7 | BR19: -23 | BS19: -4.5 | CB19: -0.4 | CC19: 20.3 | CD19: 16.1 | CE19: -0.1 | CF19: 2.3 | CG19: -0.1 | CK19: 8.9 | CL19: 8.2 | CM19: -34.9 | CV19: -4.8 | CW19: 0 | CZ19: 1.2 | DA19: 0 | DB19: -0.9 | DE19: 0.974 | DF19: 1.6 | DG19: -1.3 | DH19: 1.3 | DI19: 0.6 | DK19: 0 | DL19: 0 | DM19: -2.4 | DN19: -5.6 | DO19: 1.8 | DP19: 0.2 | DQ19: 0.7 | DR19: 0 | DS19: 0 | DT19: 0.1 | DU19: 0.6 | DV19: 0.3 | DX19: -4.1 | DY19: 0.3 | DZ19: 0.3 | EA19: -0.8 | EB19: 1.3 | EC19: 0.8 | ED19: 4 | EE19: 0 | EF19: -2.9 | EG19: -7.8 | EJ19: 2.2 | EK19: -0.1 | EL19: 2 | EM19: 0.2 | EN19: 0.2 | EO19: 0.2 | EQ19: 0 | ER19: 0 | ES19: 0 | ET19: -0.2 | EU19: 0 | EV19: 3.7 | EW19: 0 | EX19: 0 | EY19: 0.4 | EZ19: 1.6 | FA19: 2.9 | FB19: 0 | FF19: 3 | FI19: -135.126 | FK19: 1.87787 | FL19: 0.627 | FN19: 1.5 | FO19: 2.3193 | FP19: 3.83883 | FQ19: 0.3 | FR19: 1.9 | FS19: 12.363
A20: 15/05/2025 | B20: 05:00 | C20: 6.9 | D20: 3.9 | E20: 16.5 | F20: 0.9 | G20: 0.9 | H20: -17 | I20: -0.9 | L20: -37.8 | M20: -33.9 | N20: -16.4 | O20: 21 | P20: -14.6 | Q20: -10.7 | R20: 53.8 | S20: 0.1 | X20: -2.2 | Y20: 1 | AA20: -3.3 | AB20: 5.1 | AC20: 1.7 | AF20: 0 | AH20: 2.8 | AI20: 14.1 | AM20: -1.4 | AN20: -9.6 | AO20: 7.2 | AP20: 0.2 | AQ20: -4.1 | AR20: 0.1 | AS20: 2.7 | AT20: 1.5 | AU20: -32.9 | AW20: -63 | AX20: 2.2 | AY20: -2 | AZ20: 0.5 | BA20: -4.6 | BC20: 1 | BD20: -0.1 | BE20: 8.9 | BH20: -3.6 | BI20: 0 | BJ20: 0 | BK20: 7 | BO20: -1.4 | BQ20: -44.9 | BR20: -22.4 | BS20: -6.8 | CB20: -0.4 | CC20: 21.3 | CD20: 16 | CE20: -0.3 | CF20: 2.2 | CG20: -0.2 | CK20: 10.4 | CL20: 9.5 | CM20: -32.6 | CV20: -4.9 | CW20: 0 | CZ20: 1.2 | DA20: 0 | DB20: -0.9 | DE20: 0.943 | DF20: 1.6 | DG20: -1.3 | DH20: 1.4 | DI20: 0.6 | DK20: 0 | DL20: 0 | DM20: -2.3 | DN20: -5.5 | DO20: 1.8 | DP20: 0.2 | DQ20: 0.7 | DR20: 0 | DS20: 0.2 | DT20: 0.1 | DU20: 0.6 | DV20: 0.3 | DX20: -4.2 | DY20: 0.3 | DZ20: 0.4 | EA20: -0.8 | EB20: 1.3 | EC20: 0.8 | ED20: 4 | EE20: 0.4 | EF20: -1.6 | EG20: -8.1 | EJ20: 2.2 | EK20: -0.1 | EL20: 2 | EM20: 0.2 | EN20: 0.2 | EO20: 0.2 | EQ20: 0 | ER20: 0 | ES20: 0 | ET20: -0.2 | EU20: 0 | EV20: 3.7 | EW20: 0 | EX20: 0 | EY20: 0.4 | EZ20: 1.6 | FA20: 2.7 | FB20: 0 | FF20: 3.3 | FI20: -144.257 | FK20: 1.75874 | FL20: 0.696 | FN20: 1.7 | FO20: 2.31755 | FP20: 3.8431 | FQ20: 0.5 | FR20: 1.8 | FS20: 12.61539
A21: 15/05/2025 | B21: 05:30 | C21: 7.3 | D21: 24 | E21: 18.5 | F21: 0.8 | G21: 0.8 | H21: -14.2 | I21: 3.4 | L21: -28.9 | M21: -29.8 | N21: -14.3 | O21: 32.2 | P21: -7.2 | Q21: -5.8 | R21: 57.2 | S21: 0.1 | X21: 1.2 | Y21: 1.1 | AA21: -3.3 | AB21: 5.1 | AC21: 1.9 | AF21: 0 | AH21: 3.3 | AI21: 16.1 | AM21: -1.3 | AN21: -8.7 | AO21: 7 | AP21: 2.5 | AQ21: -4.1 | AR21: 0 | AS21: 2.7 | AT21: 1 | AU21: -23.7 | AW21: -54.9 | AX21: 0.5 | AY21: -1.9 | AZ21: 0.9 | BA21: -3.6 | BC21: 1.1 | BD21: -0.1 | BE21: 8.7 | BH21: -1.5 | BI21: 0 | BJ21: 0 | BK21: 3.5 | BO21: 0.7 | BQ21: -33.7 | BR21: -11 | BS21: 4.2 | CB21: -0.4 | CC21: 20.1 | CD21: 17.4 | CE21: 1.5 | CF21: 2.2 | CG21: 0.1 | CK21: 16.3 | CL21: 15.6 | CM21: -24.3 | CV21: -4.7 | CW21: 0 | CZ21: 1.2 | DA21: 0 | DB21: -0.9 | DE21: 0.951 | DF21: 1.6 | DG21: -0.9 | DH21: 1.3 | DI21: 0.6 | DK21: 0 | DL21: 0 | DM21: -1.8 | DN21: -4.2 | DO21: 1.8 | DP21: 0.2 | DQ21: 0.7 | DR21: 0 | DS21: 0.3 | DT21: 0 | DU21: 0.6 | DV21: 0.4 | DX21: -4.1 | DY21: 0.3 | DZ21: 0.5 | EA21: -0.8 | EB21: 1.5 | EC21: 0.8 | ED21: 4 | EE21: 0.4 | EF21: -0.7 | EG21: -4.2 | EJ21: 2.2 | EK21: -0.1 | EL21: 2 | EM21: 0.2 | EN21: 0.2 | EO21: 0.2 | EQ21: 0 | ER21: 0 | ES21: 0 | ET21: -0.2 | EU21: 0 | EV21: 3.7 | EW21: 0 | EX21: 0 | EY21: 0.4 | EZ21: 1.8 | FA21: 2.7 | FB21: 0 | FF21: 2.8 | FI21: 17.051 | FK21: 1.71755 | FL21: 0.577 | FN21: 1.8 | FO21: 2.31944 | FP21: 3.84851 | FQ21: -0.8 | FR21: 2.1 | FS21: 11.5625
A22: 15/05/2025 | B22: 06:00 | C22: 8.1 | D22: 16.8 | E22: 19.4 | F22: 0.9 | G22: 0.9 | H22: -16.8 | I22: -0.8 | L22: -31.4 | M22: -27.7 | N22: -9.7 | O22: 31 | P22: -2.7 | Q22: -4.9 | R22: 57.1 | S22: 0.1 | X22: 0.9 | Y22: 1.3 | AA22: -3.3 | AB22: 5.1 | AC22: 2 | AF22: 0 | AH22: 3.7 | AI22: 14.9 | AM22: -1.2 | AN22: -7.6 | AO22: 7.6 | AP22: 0 | AQ22: -3.9 | AR22: -0.1 | AS22: 2.7 | AT22: 1.2 | AU22: -23.7 | AW22: -52.5 | AX22: 4.2 | AY22: -1.7 | AZ22: 0.6 | BA22: -4.2 | BC22: 1.1 | BD22: -0.1 | BE22: 9.8 | BH22: -0.8 | BI22: 0 | BJ22: -10.9 | BK22: 3.3 | BO22: 0.6 | BQ22: -29.5 | BR22: -4 | BS22: 7.1 | CB22: -0.4 | CC22: 21.6 | CD22: 15.8 | CE22: -0.6 | CF22: 2.2 | CG22: 0 | CK22: 17.6 | CL22: 16.7 | CM22: -22.1 | CV22: -4.3 | CW22: 0 | CZ22: 1.2 | DA22: 0 | DB22: -0.9 | DE22: 0.98 | DF22: 1.6 | DG22: -1.3 | DH22: 1.4 | DI22: 0.6 | DK22: 0 | DL22: 0 | DM22: -2.2 | DN22: -4.8 | DO22: 1.8 | DP22: 0.2 | DQ22: 0.7 | DR22: 0 | DS22: 0.4 | DT22: 0.1 | DU22: 0.5 | DV22: 0.3 | DX22: -4.1 | DY22: 0.3 | DZ22: 0.5 | EA22: -0.7 | EB22: 1.4 | EC22: 0.8 | ED22: 4 | EE22: 0.3 | EF22: 0 | EG22: -3.1 | EJ22: 2.2 | EK22: -0.1 | EL22: 2.1 | EM22: 0.2 | EN22: 0.2 | EO22: 0.2 | EQ22: 0.3 | ER22: 0 | ES22: 0 | ET22: -0.2 | EU22: 0 | EV22: 3.7 | EW22: 0 | EX22: 0 | EY22: 0.4 | EZ22: 1.7 | FA22: 2.9 | FB22: 0 | FF22: 2.5 | FI22: 25.48 | FK22: 1.87893 | FL22: 0.449 | FN22: 1.9 | FO22: 2.3203 | FP22: 3.84246 | FQ22: -0.8 | FR22: 1.8 | FS22: 11.39069
... A58: 16/05/2025 | B58: 00:00 | C58: 9.5 | D58: 29.5 | E58: 17.6 | F58: 0 | G58: 0 | H58: -16.5 | I58: -1.3 | L58: -25 | M58: -35.8 | N58: -24.6 | O58: 13.4 | P58: 20.5 | Q58: 17.2 | R58: 70.7 | S58: 0 | X58: 12.5 | Y58: 1 | AA58: -3.3 | AB58: 5.1 | AC58: 4.2 | AF58: 0 | AH58: 4.1 | AI58: 3.9 | AM58: -1.4 | AN58: 52.5 | AO58: 7.4 | AP58: 4.6 | AQ58: -0.9 | AR58: -0.8 | AS58: 2.7 | AT58: 0.8 | AU58: -33.3 | AW58: -62 | AX58: 8.1 | AY58: -1 | AZ58: 0.7 | BA58: -5.1 | BC58: 1 | BD58: -0.1 | BE58: 5 | BH58: -4.1 | BI58: 0 | BJ58: 0 | BK58: -6.6 | BO58: 4.9 | BQ58: 0 | BR58: 0 | BS58: 27.5 | CB58: -0.4 | CC58: 40.5 | CD58: 25 | CE58: 4.8 | CF58: 8.1 | CG58: -0.9 | CK58: 2.1 | CL58: 1 | CM58: -39 | CV58: -4 | CW58: 0 | CZ58: 1.2 | DA58: 0 | DB58: -0.9 | DE58: 1.267 | DF58: 2.2 | DG58: 1.1 | DH58: 1.2 | DI58: 0.6 | DK58: 0 | DL58: 0 | DM58: -3.9 | DN58: -1.5 | DO58: 0.9 | DP58: 0.3 | DQ58: 0.4 | DR58: 0.4 | DS58: 0 | DT58: 0 | DU58: 0.2 | DV58: 0.6 | DX58: -3.9 | DY58: 0 | DZ58: 0.4 | EA58: -1.1 | EB58: 1.1 | EC58: 0.8 | ED58: 4 | EE58: 0 | EF58: -4.1 | EG58: -7.7 | EJ58: 1.9 | EK58: -0.1 | EL58: 1.8 | EM58: 0.2 | EN58: 0.2 | EO58: 0.2 | EQ58: 0 | ER58: 0 | ES58: 0 | ET58: -0.2 | EU58: 0 | EV58: 1.4 | EW58: 0 | EX58: 0 | EY58: 0.4 | EZ58: 1.4 | FA58: 2.5 | FB58: 14.3 | FF58: 2 | FI58: 159.367 | FK58: 2.11545 | FL58: -0.719 | FN58: 1.7 | FO58: 2.33659 | FP58: 2.66383 | FQ58: 0.6 | FR58: 2.4 | FS58: 11.09687
A59: EJEC | C59: 211.9 | D59: 1722 | E59: 728.05 | F59: 4.75 | G59: 4.9 | H59: -257.05 | I59: 223.95 | J59: 0 | K59: 0 | L59: -29.3 | M59: -39.65 | N59: 162.95 | O59: 743.5 | P59: 337.95 | Q59: 281.55 | R59: 1138.65 | S59: 1.2 | T59: 0 | U59: 0 | V59: 0 | W59: 0 | X59: 183.85 | Y59: 23.5 | Z59: 0 | AA59: -78.2 | AB59: 120.75 | AC59: 180.05 | AD59: 0 | AE59: 0 | AF59: 3.05 | AG59: 0 | AH59: 171.75 | AI59: 311.7 | AJ59: 0 | AK59: 0 | AL59: 0 | AM59: -19.55 | AN59: 416.55 | AO59: 169.7 | AP59: 78.3 | AQ59: -9.95 | AR59: -5.05 | AS59: 63.9 | AT59: 23.35 | AU59: -495.15 | AV59: 0 | AW59: -1258.7 | AX59: 148.2 | AY59: -38.85 | AZ59: 18.2 | BA59: -80.85 | BB59: 0 | BC59: 25.2 | BD59: -1.45 | BE59: 188.95 | BF59: 0 | BG59: 0 | BH59: -35.35 | BI59: 2.6 | BJ59: -92.45 | BK59: 72 | BL59: 0 | BM59: 0 | BN59: 0 | BO59: 128.5 | BP59: 0 | BQ59: -273.85 | BR59: -83.5 | BS59: 518 | BT59: 0 | BU59: 0 | BV59: 0 | BW59: 0 | BX59: 0 | BY59: 0 | BZ59: 0 | CA59: 0 | CB59: -9.4 | CC59: 1034.4 | CD59: 824.15 | CE59: 200.35 | CF59: 215.05 | CG59: 29.75 | CH59: 0 | CI59: 0 | CJ59: 0 | CK59: 857.4 | CL59: 832.5 | CM59: -395.4 | CN59: 0 | CO59: 0 | CP59: 0 | CQ59: 0 | CR59: 0 | CS59: 0 | CT59: 0 | CU59: 0 | CV59: -91 | CW59: 61.75 | CX59: 0 | CY59: 0 | CZ59: 28.8 | DA59: -0.4 | DB59: -21.65 | DC59: 0 | DD59: 0 | DE59: 27.253 | DF59: 45.95 | DG59: 4.1 | DH59: 33.25 | DI59: 13.9 | DJ59: 0 | DK59: -6.55 | DL59: -13.95 | DM59: -208.25 | DN59: -41.45 | DO59: 41.95 | DP59: 5.3 | DQ59: 15.45 | DR59: 8.05 | DS59: -23.75 | DT59: 0.3 | DU59: 12.1 | DV59: 11.05 | DW59: 0 | DX59: -96.15 | DY59: 5.7 | DZ59: 10.75 | EA59: 3.75 | EB59: 32.75 | EC59: 18.35 | ED59: 96 | EE59: 18.35 | EF59: -161.15 | EG59: -227.3 | EH59: 0 | EI59: 0 | EJ59: 50.9 | EK59: -2.15 | EL59: 45.4 | EM59: 4.8 | EN59: 4.8 | EO59: 4.8 | EP59: 0 | EQ59: 10.25 | ER59: 14.35 | ES59: 121.4 | ET59: -4.8 | EU59: 3.05 | EV59: 58.9 | EW59: 75.7 | EX59: 11.65 | EY59: 19.2 | EZ59: 40.55 | FA59: 68.25 | FB59: 135.05 | FC59: 0 | FD59: 0 | FE59: 0 | FF59: 73.2 | FG59: 0 | FH59: 0 | FI59: 9537.903 | FK59: 46.4905 | FL59: -6.6115 | FM59: 0 | FN59: 42.1 | FO59: 47.26848 | FP59: 92.105415 | FQ59: 15.85 | FR59: 58.8 | FS59: 296.0029

Sheet DEMANDA_AREAS
B3: jueves, 15 de Mayo del 2025
B5: REPORTE DE LA DEMANDA POR ÁREAS Y SUBAREAS OPERATIVAS (MW)
B6: FECHA HORA | C6: DEMANDA | E6: AREA | H6: SUBAREAS
C7: INTERCAMBIOS INTERNACIONALES | D7: SEIN | E7: NORTE | F7: CENTRO | G7: SUR | H7: ELECTROANDES
B8: 00:30 | C8: 0 | D8: 6520.334 | E8: 959.0393 | F8: 3896.695 | G8: 1664.5997 | H8: 208.2827
B9: 01:00 | C9: 0 | D9: 6370.399 | E9: 984.281 | F9: 3751.7644 | G9: 1634.3536 | H9: 208.6559
B10: 01:30 | C10: 0 | D10: 6262.334 | E10: 956.8966 | F10: 3661.1685 | G10: 1644.2689 | H10: 214.0197
B11: 02:00 | C11: 0 | D11: 6223.826 | E11: 906.7837 | F11: 3688.911 | G11: 1628.1313 | H11: 209.9094
B12: 02:30 | C12: 0 | D12: 6212.249 | E12: 942.3065 | F12: 3636.8207 | G12: 1633.1218 | H12: 210.9868
B13: 03:00 | C13: 0 | D13: 6196.37 | E13: 944.6486 | F13: 3610.7222 | G13: 1640.9992 | H13: 208.2316
B14: 03:30 | C14: 0 | D14: 6151.941 | E14: 915.3322 | F14: 3594.7606 | G14: 1641.8482 | H14: 211.4424
B15: 04:00 | C15: 0 | D15: 6123.435 | E15: 953.9348 | F15: 3524.478 | G15: 1645.0222 | H15: 211.8914
B16: 04:30 | C16: 0 | D16: 6157.652 | E16: 931.0068 | F16: 3573.65 | G16: 1652.9952 | H16: 206.8413
B17: 05:00 | C17: 0 | D17: 6136.55 | E17: 922.7623 | F17: 3562.1788 | G17: 1651.6089 | H17: 199.7096
B18: 05:30 | C18: 0 | D18: 6418.769 | E18: 965.0433 | F18: 3775.6706 | G18: 1678.0551 | H18: 204.6483
B19: 06:00 | C19: 0 | D19: 6467.084 | E19: 983.2602 | F19: 3772.8866 | G19: 1710.9372 | H19: 196.7721
... B59: ENERGÍA | C59: 0 | D59: 168985.76 | E59: 26246.493 | F59: 102078.78 | G59: 40660.492 | H59: 4734.5039
B61: LEYENDA:
D63: Potencia recibida del Ecuador
D64: Potencia entregada al Ecuador

Sheet DEMANDA_UL
B3: jueves, 15 de Mayo del 2025
B5: POTENCIA DE LOS GRANDES USUARIOS LIBRES (MW)
B6: FECHA HORA | C6: GRANDES USUARIOS LIBRES DEL ÁREA NORTE | X6: GRANDES USUARIOS LIBRES DEL ÁREA CENTRO | BP6: GRANDES USUARIOS LIBRES DEL ÁREA SUR
C7: ARCA CONTINENTAL LINDLEY S.A. | D7: AUSTRAL GROUP S.A.A | E7: CEMENTOS PACASMAYO | F7: CONSORCIO MINERO HORIZONTE S.R.L. | G7: CORPORACIÓN PESQUERA INCA S.A.C. | H7: CREDITEX: CIA IND.TEXTIL CREDISA | I7: HIPERMERCADOS TOTTUS S.A | J7: INDUSTRIA TEXTIL PIURA | K7: MINERA BOROO MISQUICHILCA S.A. | L7: MINERA GOLD FIELDS | M7: MINERA MARSA | N7: MINERA MISKY MAYO | O7: MINERA YANACOCHA | P7: OPEN PLAZA | Q7: PESQUERA DIAMANTE | R7: PETROPERU | S7: REAL PLAZA S.R.L. | T7: SIDER PERU | U7: SUPERMERCADOS PERUANOS S.A. | V7: TRUPAL S.A. | W7: UNIÓN DE CERVECERÍAS PERUANAS BACKUS Y JOHNSTON S. | X7: ACEROS AREQUIPA | Y7: ADMINISTRADORA JOCKEY PLAZA SHOPPING CENTER S.A. | Z7: ALICORP | AA7: ARCA CONTINENTAL LINDLEY S.A. | AB7: AUSTRAL GROUP S.A.A | AC7: COMPAÑIA MINERA CONDESTABLE | AD7: CORPORACIÓN PESQUERA INCA S.A.C. | AE7: CREDITEX: CIA IND.TEXTIL CREDISA | AF7: FUNDICION CHILCA S.A. | AG7: HIPERMERCADOS TOTTUS S.A | AH7: INMOBILIARIA KANPU S.A. | AI7: INMUEBLES PANAMERICANA S.A. | AJ7: KIMBERLY-CLARK PERU | AK7: LECHE GLORIA S.A. | AL7: MALL AVENTURA S.A. | AM7: MARCOBRE S.A.C. | AN7: MINERA ANTAMINA | AO7: MINERA ARES | AP7: MINERA BUENAVENTURA | AQ7: MINERA CHINALCO PERÚ S.A. | AR7: MINERA SHOUXIN PERU S.A. | AS7: MINERA VOLCAN | AT7: MINSUR | AU7: MOLYCOP-ADESUR | AV7: NEXA RESOURCES CAJAMARQUILLA S.A. | AW7: NEXA RESOURCES PERÚ S.A.A. | AX7: OPEN PLAZA | AY7: OPP FILM | AZ7: OWENS-ILLINOIS PERÚ S.A. | BA7: PAPELERA NACIONAL S.A. | BB7: PESQUERA DIAMANTE | BC7: QUIMPAC S.A. | BD7: REAL PLAZA S.R.L. | BE7: REFINERIA LA PAMPILLA S.A.A | BF7: SAGA FALABELLA | BG7: SAN MIGUEL INDUSTRIAS PET S.A. | BH7: SHOUGANG HIERRO PERU | BI7: SOFTYS PERU S.A.C. | BJ7: SUPERMERCADOS PERUANOS S.A. | BK7: TEJIDOS SAN JACINTO | BL7: TREN URBANO DE LIMA S.A. | BM7: TRUPAL S.A. | BN7: UNACEM PERU S.A. | BO7: UNIÓN DE CERVECERÍAS PERUANAS BACKUS Y JOHNSTON S. | BP7: ANGLO AMERICAN QUELLAVECO S.A. | BQ7: ARCA CONTINENTAL LINDLEY S.A. | BR7: CAL & CEMENTO SUR S.A. | BS7: COMPAÑIA MINERA ANTAPACCAY S.A. | BT7: COMPAÑÍA MINERA CHUNGAR SAC | BU7: COMPAÑIA MINERA SAN IGNACIO DE MOROCOCHA S.A.A. | BV7: EL BROCAL .S.A. | BW7: EMPRESA ADMINISTRADORA CERRO S.A.C. | BX7: EMPRESA MINERA LOS QUENUALES S.A.C. | BY7: HIPERMERCADOS TOTTUS S.A | BZ7: HUDBAY PERU S.A.C. | CA7: INDUSTRIA CACHIMAYO | CB7: MALL AVENTURA S.A. | CC7: MINERA ARES | CD7: MINERA BUENAVENTURA | CE7: MINERA CERRO VERDE | CF7: MINERA CORONA | CG7: MINERA LAS BAMBAS S.A. | CH7: MINERA VOLCAN | CI7: MINSUR | CJ7: MOLYCOP-ADESUR | CK7: NEXA RESOURCES PERÚ S.A.A. | CL7: OXIDOS DE PASCO S.A.C. | CM7: PESQUERA DIAMANTE | CN7: REAL PLAZA S.R.L. | CO7: SOBREANDES S.A.C. | CP7: SOUTHERN PERU CC | CQ7: SUPERMERCADOS PERUANOS S.A. | CR7: UNACEM PERU S.A. | CS7: UNIÓN DE CERVECERÍAS PERUANAS BACKUS Y JOHNSTON S. | CT7: YURA
B8: 00:30 | E8: 33.54009 | F8: 12.443 | K8: 19.55054 | L8: 26.74496 | M8: 13.166 | N8: 14.54 | O8: 32.466 | R8: 38.014 | T8: 42.6373 | V8: 8.4 | X8: 132.00316 | Z8: 9.46243 | AF8: 3.8 | AH8: 4.9088 | AJ8: 5.33786 | AK8: 0 | AM8: 49.4246 | AN8: 128.11 | AO8: 29.2342 | AP8: 0.81 | AQ8: 160.92852 | AR8: 22.88642 | AS8: 37.19127 | AT8: 32.38 | AV8: 193.5058 | AW8: 34.38745 | AY8: 7.03 | BA8: 5.3 | BC8: 73.22073 | BE8: 20.4 | BI8: 17.54803 | BK8: 5.50673 | BM8: 7.231 | BN8: 61.42 | BP8: 135.48871 | BR8: 4.4849 | BS8: 126.14011 | BT8: 15.89071 | BV8: 34.6204 | BW8: 3.85819 | BX8: 10.75 | BZ8: 4.0697 | CA8: 24.8023 | CC8: 0.645 | CD8: 26.41411 | CE8: 413.60807 | CG8: 157.3428 | CH8: 17.82792 | CK8: 14.0626 | CL8: 4.88971 | CO8: 15.16887 | CP8: 296.51 | CR8: 26.259 | CT8: 23.55443
B9: 01:00 | E9: 36.67242 | F9: 11.986 | K9: 20.17287 | L9: 26.2374 | M9: 14.068 | N9: 14.38 | O9: 32.822 | R9: 37.919 | T9: 33.9981 | V9: 8.5 | X9: 84.33944 | Z9: 9.20126 | AF9: 2.2 | AH9: 3.43 | AJ9: 5.33431 | AK9: 0 | AM9: 49.3765 | AN9: 128.42485 | AO9: 28.4845 | AP9: 0.7 | AQ9: 161.63615 | AR9: 23.04348 | AS9: 37.94232 | AT9: 31.26 | AV9: 194.2661 | AW9: 34.19335 | AY9: 6.62 | BA9: 5.2 | BC9: 73.15435 | BE9: 20.4 | BI9: 17.22438 | BK9: 5.58028 | BM9: 7.621 | BN9: 61.4 | BP9: 132.67285 | BR9: 4.4079 | BS9: 125.42832 | BT9: 15.45721 | BV9: 33.9913 | BW9: 3.96348 | BX9: 10.79 | BZ9: 3.8654 | CA9: 24.3893 | CC9: 0.617 | CD9: 26.65319 | CE9: 411.10049 | CG9: 157.5852 | CH9: 17.84197 | CK9: 14.3117 | CL9: 4.9795 | CO9: 15.12323 | CP9: 296.96 | CR9: 26.062 | CT9: 23.7456
B10: 01:30 | E10: 36.76236 | F10: 12.863 | K10: 20.15753 | L10: 26.30645 | M10: 14.262 | N10: 14.6 | O10: 32.22 | R10: 38.07 | T10: 38.4244 | V10: 9 | X10: 141.69323 | Z10: 9.37536 | AF10: 3.8 | AH10: 4.9712 | AJ10: 5.31128 | AK10: 0 | AM10: 48.39772 | AN10: 125.33232 | AO10: 27.7045 | AP10: 0.64 | AQ10: 162.17074 | AR10: 23.71774 | AS10: 37.68345 | AT10: 30.42 | AV10: 193.4859 | AW10: 34.71007 | AY10: 6.71 | BA10: 4.5 | BC10: 73.31301 | BE10: 20.4 | BI10: 17.23876 | BK10: 5.72653 | BM10: 7.621 | BN10: 60.58 | BP10: 137.26729 | BR10: 4.3619 | BS10: 126.75077 | BT10: 15.11926 | BV10: 34.5577 | BW10: 4.0073 | BX10: 11.24 | BZ10: 3.9022 | CA10: 24.40366 | CC10: 0.63 | CD10: 27.79234 | CE10: 411.83155 | CG10: 156.6721 | CH10: 17.89372 | CK10: 14.203 | CL10: 4.91681 | CO10: 15.14965 | CP10: 301.51 | CR10: 26.094 | CT10: 23.59582
B11: 02:00 | E11: 36.81036 | F11: 12.53 | K11: 20.42606 | L11: 26.37861 | M11: 14.284 | N11: 14.11 | O11: 31.952 | R11: 38.477 | T11: 43.7438 | V11: 9.1 | X11: 137.28528 | Z11: 9.18854 | AF11: 2 | AH11: 3.5494 | AJ11: 5.27359 | AK11: 0 | AM11: 49.30304 | AN11: 124.59449 | AO11: 28.6782 | AP11: 0.44 | AQ11: 160.56094 | AR11: 22.69444 | AS11: 36.79431 | AT11: 31.07 | AV11: 194.8451 | AW11: 34.21542 | AY11: 6.82 | BA11: 4.7 | BC11: 73.37251 | BE11: 20.4 | BI11: 17.18335 | BK11: 5.57509 | BM11: 7.621 | BN11: 61.77 | BP11: 137.13733 | BR11: 4.4213 | BS11: 127.60602 | BT11: 15.73467 | BV11: 35.1644 | BW11: 3.7307 | BX11: 11.06 | BZ11: 3.9177 | CA11: 24.40528 | CC11: 0.59 | CD11: 26.95428 | CE11: 409.66056 | CG11: 153.4923 | CH11: 17.777 | CK11: 14.2996 | CL11: 4.65053 | CO11: 14.96596 | CP11: 292.55 | CR11: 26.19 | CT11: 23.73193
B12: 02:30 | E12: 36.74056 | F12: 12.712 | K12: 20.50286 | L12: 26.34441 | M12: 14.639 | N12: 14.1 | O12: 32.448 | R12: 38.475 | T12: 20.4423 | V12: 9.2 | X12: 131.38839 | Z12: 9.01532 | AF12: 1.2 | AH12: 3.4389 | AJ12: 5.22184 | AK12: 0 | AM12: 48.77878 | AN12: 126.00409 | AO12: 28.2701 | AP12: 0.41 | AQ12: 159.35961 | AR12: 22.79776 | AS12: 37.41441 | AT12: 30.52 | AV12: 193.9037 | AW12: 35.37693 | AY12: 7.1 | BA12: 4.7 | BC12: 73.47038 | BE12: 20.4 | BI12: 16.93749 | BK12: 5.60101 | BM12: 6.942 | BN12: 62.11 | BP12: 130.48902 | BR12: 4.3658 | BS12: 128.91649 | BT12: 15.78478 | BV12: 32.9712 | BW12: 3.87202 | BX12: 11.01 | BZ12: 3.9397 | CA12: 24.62362 | CC12: 0.615 | CD12: 27.02733 | CE12: 420.97172 | CG12: 152.2517 | CH12: 17.42808 | CK12: 14.5665 | CL12: 4.65169 | CO12: 14.61899 | CP12: 288.75 | CR12: 24.379 | CT12: 23.62621
B13: 03:00 | E13: 33.55101 | F13: 12.664 | K13: 20.71338 | L13: 26.58448 | M13: 14.563 | N13: 14.3 | O13: 32.318 | R13: 38.833 | T13: 46.1686 | V13: 9.4 | X13: 104.8784 | Z13: 9.2664 | AF13: 1.4 | AH13: 4.8535 | AJ13: 4.81592 | AK13: 0 | AM13: 48.36494 | AN13: 124.55476 | AO13: 28.9788 | AP13: 0.67 | AQ13: 159.57658 | AR13: 22.6512 | AS13: 38.7142 | AT13: 30.29 | AV13: 194.6608 | AW13: 33.30273 | AY13: 7.28 | BA13: 4.6 | BC13: 73.13087 | BE13: 20.4 | BI13: 16.78997 | BK13: 5.58813 | BM13: 6.987 | BN13: 61.67 | BP13: 132.96285 | BR13: 4.3719 | BS13: 129.10153 | BT13: 16.15185 | BV13: 33.4149 | BW13: 3.96593 | BX13: 10.55 | BZ13: 3.8957 | CA13: 24.61618 | CC13: 0.636 | CD13: 26.453 | CE13: 419.24016 | CG13: 153.0068 | CH13: 17.1426 | CK13: 13.9232 | CL13: 4.66192 | CO13: 15.15949 | CP13: 295.99 | CR13: 24.863 | CT13: 23.5881
B14: 03:30 | E14: 38.73893 | F14: 13.216 | K14: 20.2663 | L14: 26.49292 | M14: 14.476 | N14: 14.56 | O14: 32.344 | R14: 38.757 | T14: 36.1912 | V14: 9.5 | X14: 111.22968 | Z14: 9.46657 | AF14: 1.7 | AH14: 3.8057 | AJ14: 5.05719 | AK14: 0 | AM14: 50.13255 | AN14: 125.74543 | AO14: 29.7334 | AP14: 0.48 | AQ14: 159.16989 | AR14: 23.23771 | AS14: 38.25163 | AT14: 30.43 | AV14: 194.2142 | AW14: 35.27045 | AY14: 7.07 | BA14: 4.3 | BC14: 72.94157 | BE14: 20.4 | BI14: 15.40898 | BK14: 5.69741 | BM14: 7.231 | BN14: 60.43 | BP14: 135.76356 | BR14: 4.479 | BS14: 128.96345 | BT14: 15.55956 | BV14: 34.5524 | BW14: 4.02736 | BX14: 10.62 | BZ14: 4.0045 | CA14: 24.61389 | CC14: 0.625 | CD14: 25.37151 | CE14: 420.27474 | CG14: 153.6925 | CH14: 17.1907 | CK14: 14.2741 | CL14: 4.65735 | CO14: 15.43345 | CP14: 285.81 | CR14: 27.27 | CT14: 23.71619
B15: 04:00 | E15: 38.79995 | F15: 12.149 | K15: 20.3565 | L15: 26.78398 | M15: 14.5 | N15: 13.75 | O15: 32.632 | R15: 40.616 | T15: 40.141 | V15: 9.6 | X15: 150.55941 | Z15: 9.38328 | AF15: 1.5 | AH15: 3.6265 | AJ15: 5.19055 | AK15: 0 | AM15: 49.04828 | AN15: 126.14475 | AO15: 28.8655 | AP15: 0.18 | AQ15: 161.11649 | AR15: 22.80579 | AS15: 38.29042 | AT15: 29.79 | AV15: 193.9115 | AW15: 34.47305 | AY15: 7.28 | BA15: 5.1 | BC15: 73.15714 | BE15: 20.4 | BI15: 14.69921 | BK15: 5.74153 | BM15: 7.621 | BN15: 58.62 | BP15: 135.15308 | BR15: 4.5994 | BS15: 130.45211 | BT15: 15.26299 | BV15: 34.6882 | BW15: 3.88656 | BX15: 10.5 | BZ15: 3.9093 | CA15: 24.6285 | CC15: 0.641 | CD15: 24.79754 | CE15: 419.37673 | CG15: 152.0233 | CH15: 17.33453 | CK15: 13.0833 | CL15: 4.66544 | CO15: 15.87721 | CP15: 288.08 | CR15: 28.184 | CT15: 23.87213
B16: 04:30 | E16: 38.70777 | F16: 12.657 | K16: 20.0399 | L16: 26.43861 | M16: 14.968 | N16: 11.97 | O16: 33.094 | R16: 40.618 | T16: 40.8626 | V16: 9.4 | X16: 127.23199 | Z16: 9.35263 | AF16: 1.4 | AH16: 4.3246 | AJ16: 5.28152 | AK16: 0 | AM16: 48.9852 | AN16: 127.67379 | AO16: 28.5638 | AP16: 1.65 | AQ16: 159.70856 | AR16: 22.68605 | AS16: 37.76329 | AT16: 30.19 | AV16: 192.4905 | AW16: 34.64029 | AY16: 7.09 | BA16: 5.4 | BC16: 72.88405 | BE16: 20.4 | BI16: 13.62406 | BK16: 5.75674 | BM16: 7.621 | BN16: 59.2 | BP16: 135.06294 | BR16: 4.441 | BS16: 127.09842 | BT16: 15.08369 | BV16: 34.6802 | BW16: 3.90366 | BX16: 10.31 | BZ16: 3.9606 | CA16: 24.67347 | CC16: 0.624 | CD16: 23.30972 | CE16: 397.26823 | CG16: 155.3672 | CH16: 17.65325 | CK16: 13.9602 | CL16: 4.63652 | CO16: 15.17044 | CP16: 296.22 | CR16: 28.662 | CT16: 23.99842
B17: 05:00 | E17: 38.57468 | F17: 12.067 | K17: 20.16926 | L17: 25.94563 | M17: 15.647 | N17: 11.86 | O17: 32.88 | R17: 40.913 | T17: 19.4541 | V17: 9.3 | X17: 50.1929 | Z17: 9.4642 | AF17: 1.3 | AH17: 3.6481 | AJ17: 5.03627 | AK17: 0 | AM17: 47.8547 | AN17: 128.05583 | AO17: 28.7292 | AP17: 2.1 | AQ17: 157.93105 | AR17: 22.55835 | AS17: 35.87071 | AT17: 29.92 | AV17: 193.1334 | AW17: 34.66651 | AY17: 6.72 | BA17: 5.3 | BC17: 72.98595 | BE17: 20.4 | BI17: 13.95858 | BK17: 5.67899 | BM17: 7.621 | BN17: 63.5 | BP17: 139.14707 | BR17: 4.5155 | BS17: 123.4942 | BT17: 14.8436 | BV17: 33.1012 | BW17: 4.37541 | BX17: 10.06 | BZ17: 3.9718 | CA17: 24.66296 | CC17: 0.661 | CD17: 23.29684 | CE17: 407.48445 | CG17: 152.8937 | CH17: 16.88402 | CK17: 13.5996 | CL17: 4.6628 | CO17: 14.83373 | CP17: 298.3 | CR17: 28.769 | CT17: 23.83944
B18: 05:30 | E18: 38.83935 | F18: 11.287 | K18: 19.90533 | L18: 26.33374 | M18: 15.834 | N18: 11.33 | O18: 32.952 | R18: 41.204 | T18: 35.6083 | V18: 9.2 | X18: 108.8883 | Z18: 9.40688 | AF18: 0.9 | AH18: 3.291 | AJ18: 5.08865 | AK18: 0 | AM18: 48.54002 | AN18: 129.26701 | AO18: 28.0141 | AP18: 1.93 | AQ18: 158.0945 | AR18: 23.31916 | AS18: 36.01453 | AT18: 29.77 | AV18: 192.6449 | AW18: 34.31154 | AY18: 6.51 | BA18: 5.2 | BC18: 73.05331 | BE18: 20.4 | BI18: 12.0593 | BK18: 5.6135 | BM18: 6.942 | BN18: 63.03 | BP18: 140.76735 | BR18: 4.3426 | BS18: 123.31246 | BT18: 14.89769 | BV18: 31.6254 | BW18: 3.85894 | BX18: 9.76 | BZ18: 3.9823 | CA18: 24.64724 | CC18: 0.602 | CD18: 23.54931 | CE18: 417.444 | CG18: 158.6147 | CH18: 17.12185 | CK18: 13.4787 | CL18: 4.65378 | CO18: 13.52705 | CP18: 289.83 | CR18: 28.853 | CT18: 23.73545
B19: 06:00 | E19: 38.80405 | F19: 10.649 | K19: 20.2509 | L19: 26.79571 | M19: 16.008 | N19: 11.35 | O19: 33.084 | R19: 41.397 | T19: 38.9859 | V19: 8.6 | X19: 102.22079 | Z19: 9.73029 | AF19: 0.9 | AH19: 5.1226 | AJ19: 5.10208 | AK19: 0 | AM19: 50.2272 | AN19: 129.59339 | AO19: 27.9701 | AP19: 1.54 | AQ19: 156.14631 | AR19: 22.79446 | AS19: 35.07754 | AT19: 31.72 | AV19: 190.3216 | AW19: 32.44159 | AY19: 6.36 | BA19: 5.4 | BC19: 73.30672 | BE19: 20.4 | BI19: 11.50654 | BK19: 5.63903 | BM19: 6.987 | BN19: 64 | BP19: 138.8238 | BR19: 4.3919 | BS19: 127.24876 | BT19: 14.48899 | BV19: 32.8811 | BW19: 3.65085 | BX19: 9.51 | BZ19: 3.9101 | CA19: 24.67553 | CC19: 0.684 | CD19: 21.95647 | CE19: 426.80276 | CG19: 149.3406 | CH19: 17.61803 | CK19: 13.695 | CL19: 4.62577 | CO19: 12.97769 | CP19: 295.5 | CR19: 28.943 | CT19: 23.52356
... B55: 00:00 | E55: 37.01358 | F55: 12.975 | K55: 20.162 | L55: 26.34019 | M55: 13.995 | N55: 13.56 | O55: 33.172 | R55: 41.425 | T55: 42.4029 | V55: 9.3 | X55: 152.65295 | Z55: 9.38852 | AF55: 2.6 | AH55: 6.09 | AJ55: 5.27586 | AK55: 0 | AM55: 52.9055 | AN55: 130.55497 | AO55: 28.455 | AP55: 0.83 | AQ55: 159.11555 | AR55: 22.30985 | AS55: 37.29635 | AT55: 30.08 | AV55: 187.9551 | AW55: 34.96734 | AY55: 7 | BA55: 4.7 | BC55: 71.78735 | BE55: 20.3 | BI55: 17.97163 | BK55: 5.43469 | BM55: 6.987 | BN55: 56.34 | BP55: 135.6492 | BR55: 4.6023 | BS55: 130.07244 | BT55: 15.92104 | BV55: 32.5623 | BW55: 3.83695 | BX55: 11.59 | BZ55: 2.2877 | CA55: 24.69859 | CC55: 0.67 | CD55: 20.4192 | CE55: 420.21389 | CG55: 155.3383 | CH55: 17.77968 | CK55: 17.3967 | CL55: 5.23824 | CO55: 15.04101 | CP55: 296.51 | CR55: 28.756 | CT55: 23.49023
B56: MWh | C56: 0 | D56: 0 | E56: 803.05581 | F56: 289.106 | G56: 0 | H56: 0 | I56: 0 | J56: 0 | K56: 475.32732 | L56: 645.38767 | M56: 317.5455 | N56: 305.22 | O56: 759.961 | P56: 0 | Q56: 0 | R56: 961.8425 | S56: 0 | T56: 776.91295 | U56: 0 | V56: 212.6 | W56: 0 | X56: 2458.9491 | Y56: 0 | Z56: 227.43661 | AA56: 0 | AB56: 0 | AC56: 0 | AD56: 0 | AE56: 0 | AF56: 56.1 | AG56: 0 | AH56: 70.43705 | AI56: 0 | AJ56: 118.96792 | AK56: 0 | AL56: 0 | AM56: 1174.6352 | AN56: 3035.3196 | AO56: 676.5119 | AP56: 18.01 | AQ56: 3815.6423 | AR56: 536.61406 | AS56: 870.31393 | AT56: 730.375 | AU56: 0 | AV56: 4044.5107 | AW56: 808.12158 | AX56: 0 | AY56: 175.88 | AZ56: 0 | BA56: 116 | BB56: 0 | BC56: 1610.2955 | BD56: 0 | BE56: 486.25 | BF56: 0 | BG56: 0 | BH56: 0 | BI56: 393.23316 | BJ56: 0 | BK56: 133.28388 | BL56: 0 | BM56: 176.092 | BN56: 1149.475 | BO56: 0 | BP56: 3133.9642 | BQ56: 0 | BR56: 105.88795 | BS56: 3065.0483 | BT56: 345.05745 | BU56: 0 | BV56: 773.9679 | BW56: 93.66595 | BX56: 235.97 | BY56: 0 | BZ56: 39.23525 | CA56: 510.50815 | CB56: 0 | CC56: 15.259 | CD56: 515.17839 | CE56: 9407.1125 | CF56: 0 | CG56: 3647.351 | CH56: 409.66944 | CI56: 0 | CJ56: 0 | CK56: 344.9483 | CL56: 114.24806 | CM56: 0 | CN56: 0 | CO56: 336.65866 | CP56: 6823.01 | CQ56: 0 | CR56: 666.5115 | CS56: 0 | CT56: 410.14281
B59: Nota :
B60: Información proporcionada por la empresas
C62: DATOS ESTIMADOS
C64: SIN DATOS

Sheet TIPO_RECURSO
B3: jueves, 15 de Mayo del 2025
B5: REPORTE POTENCIA GENERADA POR TIPO DE RECURSO
B6: HORA | C6: H. PASADA | D6: H. REGULACION | E6: GAS DE CAMISEA | F6: GAS DE MALACAS | G6: DIÉSEL | H6: BAGAZO | I6: RESIDUAL | J6: NAFTA+GAS DE REFINERIA | K6: FLEXIGAS+GAS DE REFINERIA | L6: BIOGÁS | M6: SOLAR | N6: EÓLICA | O6: TOTAL | T6: EMPRESA | U6: CENTRAL | V6: HIDROELECTRICA DE PASADA | W6: HIDROELECTRICA DE REGULACION
B7: 00:30 | C7: 1113.134 | D7: 3109.7 | E7: 1937.2 | F7: 147.7 | G7: 0 | H7: 27.8 | J7: =+DESPACHO_EJECUTADO!FC11 -> 0 | L7: 7.7 | M7: 0 | N7: 177.1 | O7: =+SUM(C7:N7) -> 6520.334 | T7: ANDEAN POWER S.A.C. | U7: C.H.CARHUAC | V7: 362.1
B8: 01:00 | C8: 1108.899 | D8: 3058 | E8: 1928.8 | F8: 77 | G8: 7.1 | H8: 27.3 | J8: =+DESPACHO_EJECUTADO!FC12 -> 0 | L8: 7.7 | M8: 0 | N8: 155.6 | O8: =+SUM(C8:N8) -> 6370.399 | T8: ASOCIACIÓN SANTA LUCIA DE CHACAS | U8: C.H. HUALLIN | V8: 56.45
B9: 01:30 | C9: 1107.434 | D9: 3018 | E9: 1932.4 | F9: 46.5 | G9: 7.3 | H9: 26.5 | J9: =+DESPACHO_EJECUTADO!FC13 -> 0 | L9: 7.7 | M9: 0 | N9: 116.5 | O9: =+SUM(C9:N9) -> 6262.334 | T9: ATRIA ENERGIA S.A.C. | U9: C.H. PURMACANA | V9: 1.85
B10: 02:00 | C10: 1105.926 | D10: 3080.2 | E10: 1828.6 | F10: 46.7 | G10: 7.6 | H10: 26.7 | J10: =+DESPACHO_EJECUTADO!FC14 -> 0 | L10: 7.7 | M10: 0 | N10: 120.4 | O10: =+SUM(C10:N10) -> 6223.826 | T10: CELEPSA | U10: C.H. EL PLATANAL | W10: 4974.75
B11: 02:30 | C11: 1111.149 | D11: 3241.7 | E11: 1661.7 | F11: 45.6 | G11: 7.1 | H11: 27 | J11: =+DESPACHO_EJECUTADO!FC15 -> 0 | L11: 7.7 | M11: 0 | N11: 110.3 | O11: =+SUM(C11:N11) -> 6212.249 | T11: CELEPSA RENOVABLES S.R.L. | U11: C.H. MARAÑON | V11: 466.95
B12: 03:00 | C12: 1105.07 | D12: 3183.9 | E12: 1731 | F12: 46.2 | G12: 7.7 | H12: 26.6 | J12: =+DESPACHO_EJECUTADO!FC16 -> 0 | L12: 7.7 | M12: 0 | N12: 88.2 | O12: =+SUM(C12:N12) -> 6196.37 | T12: CHINANGO S.A.C. | U12: C.H. CHIMAY | W12: 3114.6
B13: 03:30 | C13: 1112.141 | D13: 3182.1 | E13: 1681.8 | F13: 46.2 | G13: 7.3 | H13: 26.6 | J13: =+DESPACHO_EJECUTADO!FC17 -> 0 | L13: 7.7 | M13: 0 | N13: 88.1 | O13: =+SUM(C13:N13) -> 6151.941 | U13: C.H. YANANGO | V13: 928.25
B14: 04:00 | C14: 1103.035 | D14: 3143.4 | E14: 1691.2 | F14: 45.3 | G14: 7.2 | H14: 26.4 | J14: =+DESPACHO_EJECUTADO!FC18 -> 0 | L14: 7.7 | M14: 0 | N14: 99.2 | O14: =+SUM(C14:N14) -> 6123.435 | T14: EGASA | U14: C.H. CHARCANI III | V14: 159.2
B15: 04:30 | C15: 1104.652 | D15: 3189.2 | E15: 1672.6 | F15: 45.5 | G15: 7.5 | H15: 26.7 | J15: =+DESPACHO_EJECUTADO!FC19 -> 0 | L15: 7.7 | M15: 0 | N15: 103.8 | O15: =+SUM(C15:N15) -> 6157.652 | U15: C.H. CHARCANI IV | W15: 282.2
B16: 05:00 | C16: 1104.25 | D16: 3172.7 | E16: 1670.7 | F16: 45.7 | G16: 7.3 | H16: 26.8 | J16: =+DESPACHO_EJECUTADO!FC20 -> 0 | L16: 7.7 | M16: 0 | N16: 101.4 | O16: =+SUM(C16:N16) -> 6136.55 | U16: C.H. CHARCANI V | W16: 1920.5
B17: 05:30 | C17: 1113.469 | D17: 3217.7 | E17: 1881.3 | F17: 46 | G17: 7.4 | H17: 27.1 | J17: =+DESPACHO_EJECUTADO!FC21 -> 0 | L17: 7.7 | M17: 0 | N17: 118.1 | O17: =+SUM(C17:N17) -> 6418.769 | T17: EGEJUNIN | U17: C.H. HUASAHUASI I | V17: 397.5
B18: 06:00 | C18: 1118.284 | D18: 3171.5 | E18: 1923.3 | F18: 81.4 | G18: 7.4 | H18: 27.2 | J18: =+DESPACHO_EJECUTADO!FC22 -> 0 | L18: 7.7 | M18: 0.8 | N18: 129.5 | O18: =+SUM(C18:N18) -> 6467.084 | U18: C.H. RUNATULLO II | V18: 257.05
B19: 06:30 | C19: 1109.342 | D19: 3141.6 | E19: 1933.7 | F19: 147.5 | G19: 0 | H19: 26.9 | J19: =+DESPACHO_EJECUTADO!FC23 -> 0 | L19: 7.7 | M19: 46.2 | N19: 142.4 | O19: =+SUM(C19:N19) -> 6555.342 | U19: C.H. RUNATULLO III | V19: 364.9
B20: 07:00 | C20: 1107.53 | D20: 3077.8 | E20: 1919.7 | F20: 147.1 | G20: 0 | H20: 25.7 | J20: =+DESPACHO_EJECUTADO!FC24 -> 0 | L20: 7.7 | M20: 237.7 | N20: 118.2 | O20: =+SUM(C20:N20) -> 6641.43 | U20: C.H. SANTA CRUZ I | V20: 185.05
B21: 07:30 | C21: 1106.216 | D21: 3060.3 | E21: 1924.5 | F21: 147.5 | G21: 0 | H21: 26.7 | J21: =+DESPACHO_EJECUTADO!FC25 -> 0 | L21: 7.7 | M21: 441 | N21: 99.7 | O21: =+SUM(C21:N21) -> 6813.616 | T21: EGEMSA | U21: C.H. MACHUPICCHU | V21: 3962.2
B22: 08:00 | C22: 1104.902 | D22: 3057.4 | E22: 1931.8 | F22: 151.2 | G22: 0 | H22: 27.4 | J22: =+DESPACHO_EJECUTADO!FC26 -> 0 | L22: 7.7 | M22: 559.3 | N22: 103.3 | O22: =+SUM(C22:N22) -> 6943.002 | T22: EGESUR | U22: C.H. ARICOTA I | W22: 175.45
B23: 08:30 | C23: 1119.879 | D23: 3169.1 | E23: 1926.7 | F23: 148.8 | G23: 0 | H23: 27.1 | J23: =+DESPACHO_EJECUTADO!FC27 -> 0 | L23: 6.7 | M23: 583 | N23: 112.1 | O23: =+SUM(C23:N23) -> 7093.379 | U23: C.H. ARICOTA II | W23: 124.5
B24: 09:00 | C24: 1110.953 | D24: 2957.1 | E24: 2191.5 | F24: 147.7 | G24: 0 | H24: 27.5 | J24: =+DESPACHO_EJECUTADO!FC28 -> 0 | L24: 6.7 | M24: 597.4 | N24: 130.3 | O24: =+SUM(C24:N24) -> 7169.153 | T24: ELECTRICA YANAPAMPA SAC | U24: C.H. YANAPAMPA | V24: 78.7815
B25: 09:30 | C25: 1099.427 | D25: 3067.4 | E25: 2299.8 | F25: 148.9 | G25: 0 | H25: 26.7 | J25: =+DESPACHO_EJECUTADO!FC29 -> 0 | L25: 6.7 | M25: 604.7 | N25: 136.6 | O25: =+SUM(C25:N25) -> 7390.227 | T25: ELECTROPERU | U25: C.H. MANTARO | W25: 15556.75
B26: 10:00 | C26: 1106.858 | D26: 3244.8 | E26: 2103.2 | F26: 149.5 | G26: 0 | H26: 27.5 | J26: =+DESPACHO_EJECUTADO!FC30 -> 0 | L26: 6.6 | M26: 610.1 | N26: 158 | O26: =+SUM(C26:N26) -> 7406.558 | U26: C.H. RESTITUCION | V26: 5157.8
B27: 10:30 | C27: 1114.259 | D27: 3210.5 | E27: 2094.2 | F27: 147.5 | G27: 8.5 | H27: 26.7 | J27: =+DESPACHO_EJECUTADO!FC31 -> 0 | L27: 6.7 | M27: 612.8 | N27: 177.2 | O27: =+SUM(C27:N27) -> 7398.359 | T27: EMPRESA DE GENERACION ELECTRICA CANCHAYLLO SAC | U27: C.H. CANCHAYLLO | V27: 117.3805
B28: 11:00 | C28: 1110.647 | D28: 3282.8 | E28: 2194.5 | F28: 147.8 | G28: 8.4 | H28: 27.2 | J28: =+DESPACHO_EJECUTADO!FC32 -> 7 | L28: 6.6 | M28: 611.9 | N28: 216 | O28: =+SUM(C28:N28) -> 7612.847 | T28: EMPRESA DE GENERACION ELECTRICA RIO BAÑOS S.A.C. | U28: C.H. RUCUY | V28: 479.3
B29: 11:30 | C29: 1104.926 | D29: 3153.4 | E29: 2289.7 | F29: 150.2 | G29: 0 | H29: 27.8 | J29: =+DESPACHO_EJECUTADO!FC33 -> 18.9 | L29: 6.6 | M29: 614.7 | N29: 274.2 | O29: =+SUM(C29:N29) -> 7640.426 | T29: EMPRESA DE GENERACION ELECTRICA SANTA ANA S.A.C. | U29: C.H. RENOVANDES H1 | V29: 488.25
B30: 12:00 | C30: 1082.903 | D30: 2992.9 | E30: 2296 | F30: 145.6 | G30: 0 | H30: 28.1 | J30: =+DESPACHO_EJECUTADO!FC34 -> 20 | L30: 7.6 | M30: 615.3 | N30: 305.1 | O30: =+SUM(C30:N30) -> 7493.503 | T30: EMPRESA DE GENERACION HUALLAGA | U30: C.H. CHAGLLA | W30: 7196.3
B31: 12:30 | C31: 1114.165 | D31: 3124.9 | E31: 2089.3 | F31: 146.1 | G31: 8.4 | H31: 27.7 | J31: =+DESPACHO_EJECUTADO!FC35 -> 30.4 | L31: 7.8 | M31: 617.2 | N31: 337.1 | O31: =+SUM(C31:N31) -> 7503.065 | U31: P.C.H. CHAGLLA | V31: 156
B32: 13:00 | C32: 1098.165 | D32: 2989.5 | E32: 1999.6 | F32: 148.6 | G32: 8.3 | H32: 27.5 | J32: =+DESPACHO_EJECUTADO!FC36 -> 35.3 | L32: 7.8 | M32: 619.8 | N32: 379.9 | O32: =+SUM(C32:N32) -> 7314.465 | T32: EMPRESA DE GENERACION HUANZA | U32: C.H. HUANZA | W32: 1152.85
B33: 13:30 | C33: 1109.612 | D33: 3132.5 | E33: 1814.2 | F33: 145 | G33: 0 | H33: 27.2 | J33: =+DESPACHO_EJECUTADO!FC37 -> 35.2 | L33: 8.8 | M33: 618.6 | N33: 473.3 | O33: =+SUM(C33:N33) -> 7364.412 | T33: EMPRESA ELECTRICA AGUA AZUL | U33: C.H. POTRERO | V33: 480
B34: 14:00 | C34: 1110.475 | D34: 3212.5 | E34: 1756.8 | F34: 145.7 | G34: 0 | H34: 27.8 | J34: =+DESPACHO_EJECUTADO!FC38 -> 34.9 | L34: 9 | M34: 613 | N34: 486.6 | O34: =+SUM(C34:N34) -> 7396.775 | T34: EMPRESA ELECTRICA RIO DOBLE | U34: C.H. LAS PIZARRAS | V34: 453.2
B35: 14:30 | C35: 1112.039 | D35: 3200.5 | E35: 1870.9 | F35: 122.8 | G35: 0 | H35: 28 | J35: =+DESPACHO_EJECUTADO!FC39 -> 34.5 | L35: 9.1 | M35: 601.3 | N35: 518.5 | O35: =+SUM(C35:N35) -> 7497.639 | T35: ENGIE | U35: C.H. YUNCAN | W35: 2068
B36: 15:00 | C36: 1106.865 | D36: 3197.9 | E36: 1945.2 | F36: 70.9 | G36: 0 | H36: 28.6 | J36: =+DESPACHO_EJECUTADO!FC40 -> 33.2 | L36: 9.1 | M36: 578.5 | N36: 499.4 | O36: =+SUM(C36:N36) -> 7469.665 | T36: GENERACIÓN ANDINA S.A.C. | U36: C.H. 8 DE AGOSTO | V36: 405.75
B37: 15:30 | C37: 1108.12 | D37: 3215.4 | E37: 2126.6 | F37: 70.8 | G37: 0 | H37: 28.6 | J37: =+DESPACHO_EJECUTADO!FC41 -> 34.8 | L37: 9.1 | M37: 538.1 | N37: 531.5 | O37: =+SUM(C37:N37) -> 7663.02 | U37: C.H. EL CARMEN | V37: 117.05
B38: 16:00 | C38: 1104.281 | D38: 3280.8 | E38: 2113 | F38: 75.3 | G38: 0 | H38: 28.2 | J38: =+DESPACHO_EJECUTADO!FC42 -> 35.3 | L38: 9.1 | M38: 413.7 | N38: 515.7 | O38: =+SUM(C38:N38) -> 7575.381 | T38: GENERADORA DE ENERGÍA DEL PERÚ | U38: C.H. ÁNGEL I | V38: 361.9
B39: 16:30 | C39: 1091.851 | D39: 3401.2 | E39: 2176.6 | F39: 70.9 | G39: 0 | H39: 27.9 | J39: =+DESPACHO_EJECUTADO!FC43 -> 35.4 | L39: 9.2 | M39: 209.4 | N39: 523.5 | O39: =+SUM(C39:N39) -> 7545.951 | U39: C.H. ÁNGEL II | V39: 386.45
B40: 17:00 | C40: 1108.629 | D40: 3367 | E40: 2282.3 | F40: 70.8 | G40: 0 | H40: 27.3 | J40: =+DESPACHO_EJECUTADO!FC44 -> 35.2 | L40: 9.2 | M40: 42.3 | N40: 521.9 | O40: =+SUM(C40:N40) -> 7464.629 | U40: C.H. ÁNGEL III | V40: 382.8
B41: 17:30 | C41: 1106.231 | D41: 3360.7 | E41: 2261.2 | F41: 70.2 | G41: 0 | H41: 27.6 | J41: =+DESPACHO_EJECUTADO!FC45 -> 34.9 | L41: 9.2 | M41: 0.1 | N41: 550.7 | O41: =+SUM(C41:N41) -> 7420.831 | U41: C.H. LA JOYA | V41: 189.6
B42: 18:00 | C42: 1108.151 | D42: 3456.1 | E42: 2144.6 | F42: 70.6 | G42: 0 | H42: 27.4 | J42: =+DESPACHO_EJECUTADO!FC46 -> 35.2 | L42: 10.3 | M42: 0 | N42: 554.2 | O42: =+SUM(C42:N42) -> 7406.551 | T42: HIDROCAÑETE S.A. | U42: C.H. IMPERIAL | V42: 86.8
B43: 18:30 | C43: 1104.247 | D43: 3507.4 | E43: 2159.8 | F43: 71.5 | G43: 0 | H43: 27.5 | J43: =+DESPACHO_EJECUTADO!FC47 -> 35 | L43: 10.5 | M43: 0 | N43: 645.6 | O43: =+SUM(C43:N43) -> 7561.547 | T43: HIDROELECTRICA HUANCHOR S.A.C. | U43: C.H. HUANCHOR | V43: 225.5
B44: 19:00 | C44: 1103.305 | D44: 3454.2 | E44: 2132.7 | F44: 111.8 | G44: 0 | H44: 27.6 | J44: =+DESPACHO_EJECUTADO!FC48 -> 34.8 | L44: 10.5 | M44: 0 | N44: 647.9 | O44: =+SUM(C44:N44) -> 7522.805 | T44: HUAURA POWER GROUP S.A. | U44: C.H. YARUCAYA | V44: 444
B45: 19:30 | C45: 1109.957 | D45: 3484.4 | E45: 2098.6 | F45: 146.8 | G45: 0 | H45: 27.6 | J45: =+DESPACHO_EJECUTADO!FC49 -> 35 | L45: 10.5 | M45: 0 | N45: 554.5 | O45: =+SUM(C45:N45) -> 7467.357 | T45: HYDRO GLOBAL PERÚ S.A.C. | U45: CH SAN GABAN III | W45: 2400.3
B46: 20:00 | C46: 1101.355 | D46: 3571.7 | E46: 2062.9 | F46: 145.5 | G46: 0 | H46: 27.2 | J46: =+DESPACHO_EJECUTADO!FC50 -> 34.9 | L46: 10.5 | M46: 0 | N46: 485.3 | O46: =+SUM(C46:N46) -> 7439.355 | T46: INLAND ENERGY SAC | U46: C.H. SANTA TERESA | V46: 2159.05
B47: 20:30 | C47: 1107.804 | D47: 3590 | E47: 2097.7 | F47: 143.8 | G47: 0 | H47: 27.7 | J47: =+DESPACHO_EJECUTADO!FC51 -> 34.9 | L47: 10.6 | M47: 0 | N47: 398.2 | O47: =+SUM(C47:N47) -> 7410.704 | T47: INVERSIONES SHAQSHA S.A.C. | U47: C.H. PARIAC | V47: 110.3
B48: 21:00 | C48: 1108.728 | D48: 3603.4 | E48: 2219.4 | F48: 146.3 | G48: 0 | H48: 26.9 | J48: =+DESPACHO_EJECUTADO!FC52 -> 34.8 | L48: 10.6 | M48: 0 | N48: 285.1 | O48: =+SUM(C48:N48) -> 7435.228 | T48: KALLPA GENERACION S.A. | U48: C.H. CERRO DEL AGUILA | W48: 13446.7
B49: 21:30 | C49: 1104.241 | D49: 3593.5 | E49: 2191.3 | F49: 146.6 | G49: 0 | H49: 27.4 | J49: =+DESPACHO_EJECUTADO!FC53 -> 35.5 | L49: 10.6 | M49: 0 | N49: 216.5 | O49: =+SUM(C49:N49) -> 7325.641 | U49: M.C.H. CERRO DEL AGUILA | V49: 250.1
B50: 22:00 | C50: 1105.205 | D50: 3542.4 | E50: 2058.5 | F50: 145.7 | G50: 0 | H50: 27.5 | J50: =+DESPACHO_EJECUTADO!FC54 -> 34.9 | L50: 10.6 | M50: 0 | N50: 240.5 | O50: =+SUM(C50:N50) -> 7165.305 | T50: LA VIRGEN | U50: C.H. LA VIRGEN | W50: 1727.2
B51: 22:30 | C51: 1101.572 | D51: 3508.3 | E51: 2129.5 | F51: 69.3 | G51: 0 | H51: 27.7 | J51: =+DESPACHO_EJECUTADO!FC55 -> 35.8 | L51: 10.6 | M51: 0 | N51: 285.5 | O51: =+SUM(C51:N51) -> 7168.272 | T51: ORAZUL ENERGY PERÚ | U51: C.H. CAÑA BRAVA | V51: 130.05
B52: 23:00 | C52: 1091.342 | D52: 3431 | E52: 2098 | F52: 45.3 | G52: 0 | H52: 27.1 | J52: =+DESPACHO_EJECUTADO!FC56 -> 35.4 | L52: 10.6 | M52: 0 | N52: 228.7 | O52: =+SUM(C52:N52) -> 6967.442 | U52: C.H. CAÑON DEL PATO | W52: 5031.9
B53: 23:30 | C53: 1108.782 | D53: 3411.9 | E53: 2000.9 | F53: 45.4 | G53: 0 | H53: 27 | J53: =+DESPACHO_EJECUTADO!FC57 -> 30.7 | L53: 4.4 | M53: 0 | N53: 153.2 | O53: =+SUM(C53:N53) -> 6782.282 | U53: C.H. CARHUAQUERO | W53: 2163.7
B54: 00:00 | C54: 1111.217 | D54: 3304.1 | E54: 2034.8 | F54: 46.2 | G54: 0 | H54: 27.2 | J54: =+DESPACHO_EJECUTADO!FC58 -> 28.9 | L54: 5.7 | M54: 0 | N54: 146.3 | O54: =+SUM(C54:N54) -> 6704.417 | U54: C.H. CARHUAQUERO IV | V54: 237.85
B55: TOTAL MWh | C55: 26560.812 | D55: 78062.25 | E55: =SUM(E7:E54)/2 -> 48255.15 | F55: =SUM(F7:F54)/2 -> 2485.5 | G55: =SUM(G7:G54)/2 -> 57.25 | H55: =SUM(H7:H54)/2 -> 655.1 | I55: =SUM(I7:I54)/2 -> 0 | J55: =SUM(J7:J54)/2 -> 435.4 | K55: =SUM(K7:K54)/2 -> 0 | L55: =SUM(L7:L54)/2 -> 200.4 | ... O55: =SUM(O7:O54)/2 -> 168985.76 | T55: ORYGEN PERU S.A.A. | U55: C.H. CALLAHUANCA | W55: 1895.2
B56: % | C56: =+C55/$O$55 -> 0.15717781 | D56: =+D55/$O$55 -> 0.46194572 | E56: =+E55/$O$55 -> 0.28555749 | F56: =+F55/$O$55 -> 0.01470834 | G56: =+G55/$O$55 -> 0.00033878594 | H56: =+H55/$O$55 -> 0.003876658 | I56: =+I55/$O$55 -> 0 | J56: =+J55/$O$55 -> 0.0025765484 | ... O56: =+O55/$O$55 -> 1 | U56: C.H. HER 1 | V56: 14.4
U57: C.H. HUAMPANI | V57: 725.55
U58: C.H. HUINCO | W58: 3355.55
U59: C.H. MATUCANA | W59: 3115.25
U60: C.H. MOYOPAMPA | V60: 1530.9
T61: PERUANA DE INVERSIONES EN ENERGIAS RENOVABLES S.A. | U61: C.H. MANTA I | V61: 480.35
T62: SAN GABAN | U62: C.H. SAN GABAN II | W62: 2660.6
U63: PCH TUPURI | V63: 24
T64: SINERSA | U64: C.H. CHANCAY | V64: 479.45
U65: C.H. POECHOS II | V65: 227.05
T66: STATKRAFT S.A | U66: C.H. ARCATA | V66: 96
U67: C.H. CHEVES | W67: 3663.95
U68: C.H. GALLITO CIEGO | W68: 909.1
U69: C.H. MALPASO | W69: 1126.9
U70: C.H. OROYA | V70: 198.95
U71: C.H. PACHACHACA | V71: 103.75
U72: C.H. YAUPI | V72: 2641
T73: TOTAL MWh | V73: 26560.812 | W73: 78062.25

Sheet GENERACION RER
B3: jueves, 15 de Mayo del 2025
B5: GENERACIÓN ELÉCTRICA DE LAS CENTRALES RER (MW)
B6: HORA | C6: AGRO INDUSTRIAL PARAMONGA S.A. | D6: AGROAURORA S.A.C. | E6: AGROINDUSTRIAS SAN JACINTO S.A.A. | F6: ANDEAN POWER S.A.C. | G6: ASOCIACIÓN SANTA LUCIA DE CHACAS | H6: ATRIA ENERGIA S.A.C. | I6: BIOENERGIA DEL CHIRA S.A. | J6: COLCA SOLAR S.A.C. | K6: EGEJUNIN | P6: ELECTRICA YANAPAMPA SAC | Q6: EMPRESA DE GENERACION ELECTRICA CANCHAYLLO SAC | R6: EMPRESA DE GENERACION ELECTRICA RIO BAÑOS S.A.C. | S6: EMPRESA DE GENERACION ELECTRICA SANTA ANA S.A.C. | T6: EMPRESA ELECTRICA AGUA AZUL | U6: EMPRESA ELECTRICA RIO DOBLE | V6: ENERGÍA EÓLICA S.A. | X6: ENERGIA RENOVABLE DEL SUR S.A. | Y6: ENGIE | AD6: GENERACIÓN ANDINA S.A.C. | AF6: GENERADORA DE ENERGÍA DEL PERÚ | AJ6: GR CORTARRAMA SOCIEDAD ANONIMA CERRADA | AK6: GR PAINO SOCIEDAD ANONIMA CERRADA | AL6: GR TARUCA SOCIEDAD ANONIMA CERRADA | AM6: HIDROCAÑETE S.A. | AN6: HUAURA POWER GROUP S.A. | AO6: HYDRO PATAPO S.A.C. | AP6: JOYA SOLAR S.A.C. | AQ6: KONDU SAC | AR6: MAJA ENERGIA S.A.C. | AS6: MAJES ARCUS S.A.C. | AT6: MOQUEGUA FV S.A.C. | AU6: ORAZUL ENERGY PERÚ | AW6: ORYGEN PERU S.A.A. | BB6: PANAMERICANA SOLAR SAC. | BC6: PARQUE EOLICO MARCONA S.A.C. | BD6: PARQUE EOLICO TRES HERMANAS S.A.C. | BE6: PERUANA DE INVERSIONES EN ENERGIAS RENOVABLES S.A. | BF6: PETRAMAS | BJ6: REPARTICIÓN ARCUS S.A.C. | BK6: SAN GABAN | BL6: SDF ENERGIA SAC | BM6: SINERSA | BO6: TACNA SOLAR SAC. | BP6: TOTAL RER
C7: C.T. PARAMONGA | D7: C.T. MAPLE | E7: C.T SAN JACINTO | F7: C.H. CARHUAC | G7: C.H. HUALLIN | H7: C.H. PURMACANA | I7: C.T. CAÑA BRAVA | K7: C.H. HUASAHUASI I | L7: C.H. HUASAHUASI II | M7: C.H. RUNATULLO II | N7: C.H. RUNATULLO III | O7: C.H. STA CRUZ I y II | P7: C.H. YANAPAMPA | Q7: C.H. CANCHAYLLO | R7: C.H. RUCUY | S7: C.H. RENOVANDES H1 | T7: C.H. POTRERO | U7: C.H. LAS PIZARRAS | AD7: C.H. 8 DE AGOSTO | AE7: C.H. EL CARMEN | AF7: C.H. ANGEL I | AG7: C.H. ANGEL II | AH7: C.H. ANGEL III | AI7: C.H. LA JOYA | AM7: C.H. NUEVAIMPERIAL | AN7: C.H. YARUCAYA | AO7: MCH PATAPO | AR7: C.H. RONCADOR | AU7: C.H. CANA BRAVA | AV7: C.H. CARHUAQUERO4 | BA7: C.H. HER 1 | BE7: C.H. MANTA | BF7: C.T. HUAYCOLORO | BG7: C.T. LA GRINGA V | BH7: CTB CALLAO | BI7: CTB. DONA CATALINA | BK7: C.H. TUPURI | BL7: C.T. OQUENDO | BM7: C.H. CHANCAY | BN7: C.H. POECHOS2 | BP7: MW
B8: 0:30 | C8: 18.3 | F8: 14.4 | G8: 2.6 | I8: 9.5 | K8: 17.1 | M8: 11.3 | N8: 14.5 | O8: 8 | P8: 3.3 | Q8: 4.834 | R8: 19.9 | S8: 20.5 | T8: 20 | U8: 18.8 | V8: 6.1 | W8: 44.9 | X8: 41.2 | Y8: 19 | Z8: 36.6 | AB8: 0.6 | AD8: 17.7 | AE8: 4.8 | AF8: 15.2 | AG8: 16 | AH8: 15.8 | AI8: 8 | AK8: 4.6 | AL8: 9.7 | AM8: 3.7 | AN8: 18.5 | AU8: 5.4 | AV8: 9.9 | BA8: 0.6 | BC8: 3.7 | BD8: 10.7 | BE8: 20 | BF8: 4.5 | BH8: 1 | BI8: 2.2 | BK8: 1 | BM8: 20 | BN8: 9.6 | BP8: 534.034
B9: 1:00 | C9: 17.8 | F9: 14.4 | G9: 2.6 | I9: 9.5 | K9: 17.1 | M9: 11.3 | N9: 14.8 | O9: 8 | P9: 3.3 | Q9: 4.799 | R9: 19.8 | S9: 20.6 | T9: 20 | U9: 19.1 | V9: 5.2 | W9: 41.2 | X9: 38.2 | Y9: 13.4 | Z9: 29.3 | AB9: 0.4 | AD9: 17.6 | AE9: 4.8 | AF9: 15.2 | AG9: 16 | AH9: 15.8 | AI9: 8 | AK9: 4.6 | AL9: 9.3 | AM9: 3.7 | AN9: 18.5 | AU9: 5.4 | AV9: 9.9 | BA9: 0.6 | BC9: 6.2 | BD9: 7.8 | BE9: 20 | BF9: 4.5 | BH9: 1 | BI9: 2.2 | BK9: 1 | BM9: 19.8 | BN9: 9.5 | BP9: 512.199
B10: 1:30 | C10: 17.5 | F10: 14.4 | G10: 2.6 | I10: 9 | K10: 17.2 | M10: 11.1 | N10: 14.8 | O10: 8 | P10: 2.5 | Q10: 5.034 | R10: 20 | S10: 20.3 | T10: 20 | U10: 18.9 | V10: 5.4 | W10: 29 | X10: 32 | Y10: 9.9 | Z10: 20.8 | AB10: 0.3 | AD10: 17.3 | AE10: 4.8 | AF10: 15.4 | AG10: 16.3 | AH10: 15.8 | AI10: 8 | AK10: 2.6 | AL10: 6.5 | AM10: 3.7 | AN10: 18.5 | AU10: 5.4 | AV10: 9.9 | BA10: 0.6 | BC10: 3.9 | BD10: 6.1 | BE10: 20 | BF10: 4.5 | BH10: 1 | BI10: 2.2 | BK10: 1 | BM10: 20 | BN10: 9.4 | BP10: 471.634
B11: 2:00 | C11: 17.5 | F11: 14.4 | G11: 2.6 | I11: 9.2 | K11: 17.1 | M11: 11.1 | N11: 15.1 | O11: 8 | P11: 3.3 | Q11: 5.026 | R11: 20 | S11: 20.3 | T11: 20 | U11: 18.9 | V11: 5.7 | W11: 34.1 | X11: 33 | Y11: 8.6 | Z11: 20.2 | AD11: 17.3 | AE11: 4.8 | AF11: 15.4 | AG11: 16.3 | AH11: 15.8 | AI11: 8 | AK11: 3.4 | AL11: 7.5 | AM11: 3.7 | AN11: 18.5 | AU11: 5.4 | AV11: 9.9 | BA11: 0.6 | BC11: 2.9 | BD11: 5 | BE11: 20 | BF11: 4.5 | BH11: 1 | BI11: 2.2 | BK11: 1 | BM11: 20 | BN11: 9.3 | BP11: 476.626
B12: 2:30 | C12: 17.5 | F12: 14.4 | G12: 2.6 | I12: 9.5 | K12: 17.1 | M12: 11.4 | N12: 15.3 | O12: 7.9 | P12: 3.4 | Q12: 5.049 | R12: 20 | S12: 20.4 | T12: 20 | U12: 18.9 | V12: 7.7 | W12: 29.2 | X12: 31.8 | Y12: 6.9 | Z12: 16.8 | AD12: 17.5 | AE12: 4.8 | AF12: 15.4 | AG12: 16.3 | AH12: 15.8 | AI12: 8.2 | AK12: 2.7 | AL12: 6.8 | AM12: 3.7 | AN12: 18.5 | AU12: 5.5 | AV12: 9.8 | BA12: 0.6 | BC12: 3.7 | BD12: 4.7 | BE12: 20 | BF12: 4.5 | BH12: 1 | BI12: 2.2 | BK12: 1 | BM12: 20 | BN12: 9.4 | BP12: 467.949
B13: 3:00 | C13: 17.5 | F13: 14.4 | G13: 2.6 | I13: 9.1 | K13: 17.1 | M13: 11.3 | N13: 15.2 | O13: 7.9 | P13: 3.2 | Q13: 4.97 | R13: 20 | S13: 20.4 | T13: 20 | U13: 18.9 | V13: 6.5 | W13: 18.8 | X13: 27.2 | Y13: 3.4 | Z13: 11.5 | AD13: 17.5 | AE13: 4.8 | AF13: 15.4 | AG13: 16.3 | AH13: 16 | AI13: 8.4 | AK13: 3.8 | AL13: 9.4 | AM13: 3.7 | AN13: 18.5 | AU13: 5.5 | AV13: 9.9 | BA13: 0.6 | BC13: 3 | BD13: 4.6 | BE13: 20 | BF13: 4.5 | BH13: 1 | BI13: 2.2 | BK13: 1 | BM13: 20 | BN13: 9.5 | BP13: 445.57
B14: 3:30 | C14: 17.6 | F14: 14.4 | G14: 2.6 | I14: 9 | K14: 17 | M14: 11 | N14: 15.7 | O14: 7.9 | P14: 3.4 | Q14: 4.841 | R14: 20 | S14: 20.2 | T14: 20 | U14: 18.8 | V14: 6.3 | W14: 14.4 | X14: 37.3 | Y14: 1.4 | Z14: 7.4 | AD14: 17.5 | AE14: 4.8 | AF14: 15.5 | AG14: 16.5 | AH14: 16 | AI14: 8.3 | AK14: 4.5 | AL14: 8.4 | AM14: 3.7 | AN14: 18.5 | AU14: 5.5 | AV14: 9.9 | BA14: 0.6 | BC14: 3.3 | BD14: 5.1 | BE14: 20 | BF14: 4.5 | BH14: 1 | BI14: 2.2 | BK14: 1 | BM14: 20 | BN14: 9.4 | BP14: 445.441
B15: 4:00 | C15: 17.5 | F15: 14.4 | G15: 2.6 | I15: 8.9 | K15: 17 | M15: 10.5 | N15: 15.4 | O15: 7.9 | P15: 3.3 | Q15: 4.835 | R15: 20 | S15: 20 | T15: 20 | U15: 18.9 | V15: 4.9 | W15: 14.1 | X15: 43.4 | Y15: 2.9 | Z15: 10.8 | AD15: 17.5 | AE15: 4.8 | AF15: 15.5 | AG15: 16.5 | AH15: 16.3 | AI15: 8.3 | AK15: 4.9 | AL15: 8.2 | AM15: 3.7 | AN15: 18.5 | AU15: 5.4 | AV15: 9.9 | BA15: 0.6 | BC15: 5.4 | BD15: 4.6 | BE15: 20 | BF15: 4.5 | BH15: 1 | BI15: 2.2 | BK15: 1 | BM15: 20 | BN15: 9.5 | BP15: 455.635
B16: 4:30 | C16: 17.7 | F16: 14.4 | G16: 2.6 | I16: 9 | K16: 17.1 | M16: 10.5 | N16: 15.3 | O16: 7.9 | P16: 3.3 | Q16: 4.852 | R16: 20 | S16: 20.2 | T16: 20 | U16: 18.9 | V16: 7 | W16: 7.3 | X16: 53.9 | Y16: 1.5 | Z16: 8.1 | AD16: 17.5 | AE16: 4.8 | AF16: 15.5 | AG16: 16.5 | AH16: 16.3 | AI16: 8.3 | AK16: 4.5 | AL16: 7.8 | AM16: 3.7 | AN16: 18.5 | AU16: 5.4 | AV16: 10 | BA16: 0.6 | BC16: 7 | BD16: 6.7 | BE16: 20 | BF16: 4.5 | BH16: 1 | BI16: 2.2 | BK16: 1 | BM16: 20 | BN16: 9.5 | BP16: 460.852
B17: 5:00 | C17: 17.6 | F17: 14.4 | G17: 2.6 | I17: 9.2 | K17: 17 | M17: 10.8 | N17: 15.6 | O17: 7.9 | P17: 3.3 | Q17: 4.85 | R17: 20 | S17: 20.4 | T17: 20 | U17: 18.9 | V17: 9.2 | W17: 9.5 | X17: 51.3 | Y17: 0.4 | Z17: 5.4 | AD17: 17.5 | AE17: 4.8 | AF17: 15.4 | AG17: 16.5 | AH17: 16.3 | AI17: 8.3 | AK17: 3.5 | AL17: 8.7 | AM17: 3.7 | AN17: 18.5 | AU17: 5.4 | AV17: 10 | BA17: 0.6 | BC17: 4.7 | BD17: 8.7 | BE17: 20 | BF17: 4.5 | BH17: 1 | BI17: 2.2 | BK17: 1 | BM17: 20 | BN17: 9.5 | BP17: 459.15
B18: 5:30 | C18: 18 | F18: 14.4 | G18: 2.5 | I18: 9.1 | K18: 17 | M18: 10.9 | N18: 15.6 | O18: 7.9 | P18: 3.3 | Q18: 4.869 | R18: 20 | S18: 20.3 | T18: 20 | U18: 18.9 | V18: 13.4 | W18: 11.1 | X18: 56.3 | Y18: 0.4 | Z18: 3.3 | AD18: 17.5 | AE18: 4.8 | AF18: 15.4 | AG18: 16.5 | AH18: 16.3 | AI18: 8.3 | AK18: 6.6 | AL18: 9.4 | AM18: 3.7 | AN18: 18.5 | AU18: 5.5 | AV18: 10 | BA18: 0.6 | BC18: 7.6 | BD18: 10 | BE18: 20 | BF18: 4.5 | BH18: 1 | BI18: 2.2 | BK18: 1 | BM18: 20 | BN18: 9.4 | BP18: 476.069
B19: 6:00 | C19: 17.8 | F19: 14.4 | G19: 2.5 | I19: 9.4 | K19: 17 | M19: 10.8 | N19: 15.5 | O19: 7.9 | P19: 3.3 | Q19: 4.884 | R19: 20 | S19: 20.5 | T19: 20 | U19: 18.9 | V19: 14.9 | W19: 8.1 | X19: 67.7 | Z19: 0.6 | AD19: 17.5 | AE19: 4.8 | AF19: 15.4 | AG19: 16.5 | AH19: 16.3 | AI19: 8.6 | AK19: 6.1 | AL19: 11 | AM19: 3.8 | AN19: 18.5 | AP19: 0.1 | AT19: 0.4 | AU19: 5.4 | AV19: 9.9 | BA19: 0.6 | BB19: 0.3 | BC19: 8 | BD19: 13.1 | BE19: 20 | BF19: 4.5 | BH19: 1 | BI19: 2.2 | BK19: 1 | BM19: 20 | BN19: 9.5 | BP19: 488.684
B20: 6:30 | C20: 17.6 | F20: 14.4 | G20: 2.5 | I20: 9.3 | K20: 17 | M20: 10.8 | N20: 15.6 | O20: 7.9 | P20: 3.4 | Q20: 4.942 | R20: 20 | S20: 20.5 | T20: 20 | U20: 18.9 | V20: 20.9 | W20: 6.1 | X20: 66.8 | Y20: 0.6 | Z20: 4.2 | AA20: 1.2 | AD20: 17.5 | AE20: 4.8 | AF20: 15.4 | AG20: 16.5 | AH20: 16.3 | AI20: 8.4 | AJ20: 5 | AK20: 5.9 | AL20: 10.7 | AM20: 3.8 | AN20: 18.5 | AP20: 12.4 | AS20: 0.1 | AT20: 4.9 | AU20: 5.4 | AV20: 9.9 | AX20: 9.2 | AZ20: 6.6 | BA20: 0.6 | BB20: 5.4 | BC20: 9.5 | BD20: 17.7 | BE20: 20 | BF20: 4.5 | BH20: 1 | BI20: 2.2 | BJ20: 0.1 | BK20: 1 | BM20: 20 | BN20: 9.4 | BO20: 1.3 | BP20: 546.642
B21: 7:00 | C21: 17 | F21: 14.4 | G21: 2.4 | I21: 8.7 | K21: 17 | M21: 10.9 | N21: 15.5 | O21: 7.9 | P21: 3.3 | Q21: 4.93 | R21: 20 | S21: 20.2 | T21: 20 | U21: 18.9 | V21: 19.3 | W21: 4.6 | X21: 50.3 | Y21: 0.5 | Z21: 4 | AA21: 9.8 | AD21: 17.5 | AE21: 5 | AF21: 15.4 | AG21: 16.5 | AH21: 16.3 | AI21: 8.3 | AJ21: 26 | AK21: 7 | AL21: 10.7 | AM21: 3.8 | AN21: 18.5 | AP21: 76.7 | AS21: 2.6 | AT21: 10.5 | AU21: 5.4 | AV21: 9.9 | AX21: 48 | AZ21: 37.2 | BA21: 0.6 | BB21: 12.3 | BC21: 7.1 | BD21: 14.7 | BE21: 20 | BF21: 4.5 | BH21: 1 | BI21: 2.2 | BJ21: 2.3 | BK21: 1 | BM21: 20 | BN21: 9.5 | BO21: 12.3 | BP21: 712.43
B22: 7:30 | C22: 17.4 | F22: 14.4 | G22: 2.5 | I22: 9.3 | J22: 0.1 | K22: 17 | M22: 10.8 | N22: 15.5 | O22: 7.9 | P22: 3.4 | Q22: 4.916 | R22: 20 | S22: 20.4 | T22: 20 | U22: 18.8 | V22: 19.4 | W22: 4.5 | X22: 39.6 | Z22: 0.8 | AA22: 19.7 | AD22: 17.5 | AE22: 5 | AF22: 15.4 | AG22: 16.5 | AH22: 16.3 | AI22: 4.2 | AJ22: 49.2 | AK22: 7.3 | AL22: 11.5 | AM22: 3.8 | AN22: 18.5 | AP22: 155.6 | AS22: 5.2 | AT22: 11.8 | AU22: 5.5 | AV22: 9.9 | AX22: 92.7 | AZ22: 71.8 | BA22: 0.6 | BB22: 14.8 | BC22: 4.5 | BD22: 12.1 | BE22: 20 | BF22: 4.5 | BH22: 1 | BI22: 2.2 | BJ22: 4.8 | BK22: 1 | BM22: 20 | BN22: 9.5 | BO22: 15.3 | BP22: 894.416
B23: 8:00 | C23: 17.7 | F23: 14.4 | G23: 2.5 | I23: 9.7 | J23: 0.3 | K23: 17.1 | M23: 11 | N23: 15.6 | O23: 7.9 | P23: 3.4 | Q23: 4.902 | R23: 20 | S23: 20.6 | T23: 20 | U23: 18.9 | V23: 19.6 | W23: 3.5 | X23: 51.5 | Z23: 0.2 | AA23: 28.3 | AD23: 17.5 | AE23: 5 | AF23: 15.4 | AG23: 16.5 | AH23: 16.3 | AI23: 4.2 | AJ23: 64.8 | AK23: 7 | AL23: 9.2 | AM23: 3.8 | AN23: 18.5 | AP23: 198.9 | AQ23: 0.1 | AS23: 7.6 | AT23: 12.9 | AU23: 5.5 | AV23: 9.7 | AX23: 121.2 | AZ23: 86.3 | BA23: 0.6 | BB23: 15.6 | BC23: 3.2 | BD23: 9.1 | BE23: 20 | BF23: 4.5 | BH23: 1 | BI23: 2.2 | BJ23: 7.2 | BK23: 1 | BM23: 20 | BN23: 9.4 | BO23: 16.1 | BP23: 1017.402
B24: 8:30 | C24: 17.5 | F24: 14.4 | I24: 9.6 | J24: 0.7 | K24: 17 | M24: 11.3 | N24: 15.7 | O24: 7.9 | P24: 3.3 | Q24: 4.879 | R24: 20 | S24: 20.9 | T24: 20 | U24: 18.9 | V24: 16.6 | W24: 3.5 | X24: 45.2 | Y24: 2.2 | Z24: 6.3 | AA24: 29.7 | AD24: 17.5 | AE24: 5 | AF24: 15.4 | AG24: 16.5 | AH24: 16.5 | AI24: 4.2 | AJ24: 67.5 | AK24: 9.5 | AL24: 12.6 | AM24: 3.8 | AN24: 18.5 | AP24: 207.9 | AQ24: 0.2 | AS24: 9.8 | AT24: 13.2 | AU24: 5.5 | AV24: 10 | AX24: 123.5 | AZ24: 88.8 | BA24: 0.6 | BB24: 15.9 | BC24: 4.6 | BD24: 11.6 | BE24: 20.2 | BF24: 4.5 | BI24: 2.2 | BJ24: 9.4 | BK24: 1 | BM24: 20 | BN24: 9.5 | BO24: 16.4 | BP24: 1047.379
B25: 9:00 | C25: 17.7 | F25: 14.5 | I25: 9.8 | J25: 0.8 | K25: 17 | M25: 11.8 | N25: 16.2 | O25: 7.8 | P25: 3.3 | Q25: 4.853 | R25: 20 | S25: 20.6 | T25: 20 | U25: 18.9 | V25: 17.8 | W25: 5.4 | X25: 51.1 | Y25: 4.4 | Z25: 15.5 | AA25: 30.2 | AD25: 17.4 | AE25: 5 | AF25: 15.4 | AG25: 16.5 | AH25: 16.3 | AI25: 4.2 | AJ25: 69.5 | AK25: 8.5 | AL25: 13.4 | AM25: 3.8 | AN25: 18.5 | AP25: 213.6 | AQ25: 0.3 | AS25: 11.7 | AT25: 13.1 | AU25: 5.4 | AV25: 10 | AX25: 124.5 | AZ25: 89.9 | BA25: 0.6 | BB25: 15.8 | BC25: 3.7 | BD25: 10.5 | BE25: 20 | BF25: 4.5 | BI25: 2.2 | BJ25: 11.3 | BK25: 1 | BM25: 20.2 | BN25: 9.4 | BO25: 16.7 | BP25: 1080.553
B26: 9:30 | C26: 17.5 | F26: 14.2 | I26: 9.2 | J26: 1 | K26: 17 | M26: 10.5 | N26: 15.4 | O26: 7.5 | P26: 3.3 | Q26: 4.827 | R26: 20 | S26: 20.3 | T26: 20 | U26: 18.9 | V26: 17.5 | W26: 6.9 | X26: 48.8 | Y26: 8.6 | Z26: 19.8 | AA26: 30.2 | AD26: 17 | AE26: 5 | AF26: 15.4 | AG26: 16.5 | AH26: 16.3 | AI26: 4.1 | AJ26: 70 | AK26: 9 | AL26: 11.3 | AM26: 3.8 | AN26: 18.5 | AP26: 216.7 | AQ26: 0.3 | AS26: 13.4 | AT26: 13 | AU26: 5.4 | AV26: 9.9 | AX26: 124.5 | AZ26: 90.4 | BA26: 0.6 | BB26: 15.7 | BC26: 3.6 | BD26: 11.1 | BE26: 20 | BF26: 4.5 | BI26: 2.2 | BJ26: 12.9 | BK26: 1 | BM26: 20.1 | BN26: 9.4 | BO26: 16.6 | BP26: 1089.627
B27: 10:00 | C27: 17.5 | F27: 14 | I27: 10 | J27: 1.1 | K27: 17 | M27: 11.1 | N27: 15.6 | O27: 7.4 | P27: 3.3 | Q27: 4.858 | R27: 19.8 | S27: 20.5 | T27: 20 | U27: 18.9 | V27: 14.9 | W27: 13.5 | X27: 43.2 | Y27: 13.9 | Z27: 32.9 | AA27: 29.9 | AB27: 0.1 | AD27: 16.9 | AE27: 5 | AF27: 15.4 | AG27: 16.5 | AH27: 16.3 | AI27: 6.9 | AJ27: 70.3 | AK27: 10.7 | AL27: 13 | AM27: 3.8 | AN27: 18.5 | AP27: 218.3 | AQ27: 0.4 | AS27: 14.8 | AT27: 13.1 | AU27: 5.4 | AV27: 9.8 | AW27: 3.1 | AX27: 124.5 | AY27: 0.1 | AZ27: 90.8 | BA27: 0.6 | BB27: 16.1 | BC27: 2.8 | BD27: 9.8 | BE27: 20 | BF27: 4.5 | BI27: 2.1 | BJ27: 14.3 | BK27: 1 | BM27: 20 | BN27: 9.6 | BO27: 16.5 | BP27: 1120.358
B28: 10:30 | C28: 17 | F28: 14.1 | G28: 2.5 | I28: 9.7 | J28: 1.2 | K28: 16.9 | M28: 10.8 | N28: 15.5 | O28: 7.4 | P28: 3.3 | Q28: 4.959 | R28: 20 | S28: 20.5 | T28: 20 | U28: 18.9 | V28: 10.6 | W28: 18.5 | X28: 48.6 | Y28: 23.1 | Z28: 38.3 | AA28: 30.1 | AB28: 0.2 | AD28: 16.9 | AE28: 5 | AF28: 15.4 | AG28: 16.3 | AH28: 16.3 | AI28: 7.2 | AJ28: 69.9 | AK28: 11.8 | AL28: 14.1 | AM28: 3.7 | AN28: 18.5 | AP28: 219.2 | AQ28: 0.4 | AS28: 15.9 | AT28: 13.3 | AU28: 5.4 | AV28: 9.9 | AW28: 1.1 | AX28: 123.8 | AZ28: 90.9 | BA28: 0.6 | BB28: 16.1 | BC28: 2.3 | BD28: 8.6 | BE28: 20.1 | BF28: 4.5 | BI28: 2.2 | BJ28: 15.5 | BK28: 1 | BM28: 20 | BN28: 9.4 | BO28: 16.5 | BP28: 1143.959
B29: 11:00 | C29: 17.1 | F29: 14.1 | G29: 2.5 | I29: 10.1 | J29: 1.2 | K29: 16.6 | M29: 11.1 | N29: 15.6 | O29: 7.4 | P29: 3.3 | Q29: 4.947 | R29: 20 | S29: 20.4 | T29: 20 | U29: 18.9 | V29: 8.4 | W29: 22.8 | X29: 69.2 | Y29: 26.3 | Z29: 42.6 | AA29: 29.9 | AB29: 0.7 | AC29: 0.2 | AD29: 16.9 | AE29: 5 | AF29: 15.4 | AG29: 16.3 | AH29: 16.1 | AI29: 8.3 | AJ29: 69.8 | AK29: 13 | AL29: 13.6 | AM29: 3.6 | AN29: 18.5 | AP29: 217 | AQ29: 0.4 | AS29: 16.7 | AT29: 13.4 | AU29: 5.3 | AV29: 9.9 | AX29: 123.9 | AZ29: 90.8 | BA29: 0.6 | BB29: 16.2 | BC29: 4.8 | BD29: 14.4 | BE29: 20 | BF29: 4.4 | BI29: 2.2 | BJ29: 16.3 | BK29: 1 | BM29: 20.2 | BN29: 9.4 | BO29: 16.3 | BP29: 1183.047
B30: 11:30 | C30: 17.5 | F30: 14.1 | G30: 2.5 | H30: 0.3 | I30: 10.3 | J30: 1.3 | K30: 16.6 | M30: 10.8 | N30: 15.5 | O30: 7.5 | P30: 3.3 | Q30: 4.926 | R30: 20 | S30: 20.4 | T30: 20 | U30: 18.9 | V30: 6.4 | W30: 23.2 | X30: 82.5 | Y30: 36.8 | Z30: 59.8 | AA30: 30.1 | AB30: 2.6 | AC30: 0.8 | AD30: 16.9 | AE30: 5 | AF30: 15.2 | AG30: 16.3 | AH30: 16.1 | AI30: 8.3 | AJ30: 70.2 | AK30: 13.7 | AL30: 15.5 | AM30: 3.6 | AN30: 18.5 | AP30: 218.5 | AQ30: 0.4 | AS30: 17.3 | AT30: 13.3 | AU30: 5.4 | AV30: 9.9 | AW30: 0.2 | AX30: 123.7 | AZ30: 90.7 | BA30: 0.6 | BB30: 16.2 | BC30: 8.8 | BD30: 23.9 | BE30: 20 | BF30: 4.4 | BI30: 2.2 | BJ30: 16.7 | BK30: 1 | BM30: 20 | BN30: 9.5 | BO30: 16.3 | BP30: 1244.426
B31: 12:00 | C31: 17.8 | F31: 14.1 | G31: 2.5 | H31: 0.4 | I31: 10.3 | J31: 1.3 | K31: 16.6 | M31: 10.4 | N31: 15.3 | O31: 7.6 | P31: 3.4 | Q31: 4.903 | R31: 20 | S31: 19.7 | T31: 20 | U31: 18.9 | V31: 5.8 | W31: 23.4 | X31: 93.3 | Y31: 40.1 | Z31: 55.9 | AA31: 29.9 | AB31: 3.5 | AC31: 1 | AD31: 16.9 | AE31: 5 | AF31: 15.2 | AG31: 16.3 | AH31: 16.1 | AI31: 8.6 | AJ31: 71.3 | AK31: 15.8 | AL31: 17.3 | AM31: 3.6 | AN31: 18.5 | AP31: 218.9 | AQ31: 0.4 | AS31: 17.3 | AT31: 13.2 | AU31: 5.4 | AV31: 9.9 | AX31: 123.2 | AZ31: 90.8 | BA31: 0.6 | BB31: 16.1 | BC31: 13 | BD31: 36 | BE31: 20 | BF31: 4.5 | BH31: 0.9 | BI31: 2.2 | BJ31: 16.8 | BK31: 1 | BM31: 20 | BN31: 9.5 | BO31: 16.1 | BP31: 1276.503
B32: 12:30 | C32: 17.7 | F32: 14 | G32: 2.4 | H32: 0.4 | I32: 10 | J32: 1.3 | K32: 16.6 | M32: 11 | N32: 15.6 | O32: 7.5 | P32: 3.288 | Q32: 4.877 | R32: 19.8 | S32: 20.3 | T32: 20 | U32: 18.9 | V32: 10.2 | W32: 23.1 | X32: 100.6 | Y32: 46.2 | Z32: 60.4 | AA32: 29.7 | AB32: 3.3 | AC32: 2.2 | AD32: 16.9 | AE32: 5 | AF32: 15 | AG32: 16.3 | AH32: 16.1 | AI32: 9 | AJ32: 72.4 | AK32: 15.3 | AL32: 17 | AM32: 3.5 | AN32: 18.5 | AP32: 221 | AQ32: 0.4 | AS32: 17.2 | AT32: 13.1 | AU32: 5.3 | AV32: 9.9 | AX32: 122.7 | AZ32: 90.4 | BA32: 0.6 | BB32: 16.1 | BC32: 15.8 | BD32: 43 | BE32: 20 | BF32: 4.5 | BH32: 1.1 | BI32: 2.2 | BJ32: 16.5 | BK32: 1 | BM32: 20 | BN32: 9.5 | BO32: 16.4 | BP32: 1311.065
B33: 13:00 | C33: 17.7 | F33: 14.1 | G33: 2.5 | H33: 0.4 | I33: 9.8 | J33: 1.2 | K33: 16.7 | M33: 10.4 | N33: 15.3 | O33: 7.5 | P33: 3.273 | Q33: 4.892 | R33: 20 | S33: 20.2 | T33: 20 | U33: 18.9 | V33: 9.1 | W33: 31.9 | X33: 98.5 | Y33: 55.9 | Z33: 73.5 | AA33: 30.1 | AB33: 3.7 | AC33: 2.8 | AD33: 16.9 | AE33: 5 | AF33: 15 | AG33: 16 | AH33: 16.1 | AI33: 9 | AJ33: 72.4 | AK33: 15.5 | AL33: 17.1 | AM33: 3.5 | AN33: 18.5 | AP33: 223.9 | AQ33: 0.4 | AS33: 16.6 | AT33: 12.7 | AU33: 5.4 | AV33: 9.9 | AW33: 4.8 | AX33: 123.2 | AZ33: 90.6 | BA33: 0.6 | BB33: 16.1 | BC33: 16.3 | BD33: 50.8 | BE33: 20 | BF33: 4.5 | BH33: 1.1 | BI33: 2.2 | BJ33: 16.1 | BK33: 1 | BM33: 20 | BN33: 9.5 | BO33: 16.5 | BP33: 1355.565
B34: 13:30 | C34: 17.1 | F34: 14 | G34: 2.4 | H34: 0.4 | I34: 10.1 | J34: 1.2 | K34: 16.7 | M34: 10.9 | N34: 15.2 | O34: 7.5 | P34: 3.274 | Q34: 4.938 | R34: 19.8 | S34: 20.5 | T34: 20 | U34: 18.9 | V34: 9.8 | W34: 40.2 | X34: 92.9 | Y34: 60.8 | Z34: 77.3 | AA34: 30.7 | AB34: 5.9 | AC34: 3.4 | AD34: 16.9 | AE34: 5 | AF34: 15 | AG34: 16 | AH34: 15.9 | AI34: 9 | AJ34: 72.3 | AK34: 16.4 | AL34: 17.2 | AM34: 3.5 | AN34: 18.5 | AP34: 223.1 | AQ34: 0.4 | AS34: 15.7 | AT34: 13.2 | AU34: 5.4 | AV34: 10 | AW34: 56.1 | AX34: 123.8 | AY34: 28 | AZ34: 90.4 | BA34: 0.6 | BB34: 16.1 | BC34: 14.7 | BD34: 50.6 | BE34: 20 | BF34: 4.5 | BG34: 1 | BH34: 1.1 | BI34: 2.2 | BJ34: 15.1 | BK34: 1 | BM34: 19.8 | BN34: 9.4 | BO34: 16.6 | BP34: 1448.412
B35: 14:00 | C35: 17.5 | F35: 14.2 | G35: 2.4 | H35: 0.4 | I35: 10.3 | J35: 1.1 | K35: 16.7 | M35: 11 | N35: 15.2 | O35: 7.5 | P35: 3.266 | Q35: 4.909 | R35: 20 | S35: 20.4 | T35: 20 | U35: 18.9 | V35: 7.6 | W35: 41.7 | X35: 95 | Y35: 49 | Z35: 70.2 | AA35: 30.7 | AB35: 4.6 | AC35: 2.2 | AD35: 16.9 | AE35: 5 | AF35: 15 | AG35: 16 | AH35: 15.9 | AI35: 9.2 | AJ35: 71.6 | AK35: 15.6 | AL35: 16.3 | AM35: 3.4 | AN35: 18.5 | AP35: 221.1 | AQ35: 0.5 | AS35: 14.5 | AT35: 13.1 | AU35: 5.4 | AV35: 10 | AW35: 58.3 | AX35: 123.8 | AY35: 70.9 | AZ35: 90.1 | BA35: 0.6 | BB35: 16 | BC35: 11.5 | BD35: 43.7 | BE35: 20 | BF35: 4.3 | BG35: 1.4 | BH35: 1.1 | BI35: 2.2 | BJ35: 14 | BK35: 1 | BM35: 20 | BN35: 9.4 | BO35: 16.5 | BP35: 1457.575
B36: 14:30 | C36: 17.4 | F36: 14.4 | G36: 2.5 | H36: 0.4 | I36: 10.6 | J36: 1 | K36: 16.6 | M36: 10.9 | N36: 15.2 | O36: 7.6 | P36: 3.286 | Q36: 4.953 | R36: 20 | S36: 20.2 | T36: 20 | U36: 18.9 | V36: 6.7 | W36: 37.9 | X36: 95.5 | Y36: 49.5 | Z36: 65.1 | AA36: 30.3 | AB36: 6.1 | AC36: 2.2 | AD36: 16.9 | AE36: 5 | AF36: 15 | AG36: 16 | AH36: 15.9 | AI36: 9.2 | AJ36: 70.3 | AK36: 14.6 | AL36: 16.2 | AM36: 3.4 | AN36: 18.5 | AP36: 216.4 | AQ36: 0.3 | AS36: 13 | AT36: 13 | AU36: 5.4 | AV36: 9.9 | AW36: 77.8 | AX36: 123.3 | AY36: 90.7 | AZ36: 89.3 | BA36: 0.6 | BB36: 15.7 | BC36: 13.5 | BD36: 42.7 | BE36: 20 | BF36: 4.4 | BG36: 1.4 | BH36: 1.1 | BI36: 2.2 | BJ36: 12.4 | BK36: 1 | BM36: 20 | BN36: 9.5 | BO36: 16.3 | BP36: 1478.139
B37: 15:00 | C37: 17.9 | F37: 14.5 | G37: 2.5 | H37: 0.4 | I37: 10.7 | J37: 0.9 | K37: 16.6 | M37: 10.7 | N37: 15 | O37: 7.5 | P37: 3.272 | Q37: 4.993 | R37: 20 | S37: 20.2 | T37: 20 | U37: 18.9 | V37: 5.8 | W37: 40.5 | X37: 93.1 | Y37: 43.8 | Z37: 64.5 | AA37: 29.9 | AB37: 4.1 | AC37: 2.2 | AD37: 16.6 | AE37: 4.9 | AF37: 15 | AG37: 16 | AH37: 15.9 | AI37: 9.2 | AJ37: 67.6 | AK37: 14 | AL37: 15.3 | AM37: 3.5 | AN37: 18.5 | AP37: 206.9 | AQ37: 0.2 | AS37: 11.1 | AT37: 12.5 | AU37: 5.5 | AV37: 9.9 | AW37: 71.5 | AX37: 120.7 | AY37: 88.4 | AZ37: 87.1 | BA37: 0.6 | BB37: 15.2 | BC37: 12.5 | BD37: 43.7 | BE37: 20.2 | BF37: 4.4 | BG37: 1.4 | BH37: 1.1 | BI37: 2.2 | BJ37: 10.6 | BK37: 1 | BM37: 20.2 | BN37: 9.5 | BO37: 15.8 | BP37: 1436.665
B38: 15:30 | C38: 17.9 | F38: 14.6 | G38: 2.5 | H38: 0.4 | I38: 10.7 | J38: 0.7 | K38: 16.5 | M38: 10.7 | N38: 15 | O38: 7.5 | P38: 3.255 | Q38: 4.965 | R38: 20.1 | S38: 20.2 | T38: 20 | U38: 18.9 | V38: 4.1 | W38: 40.5 | X38: 94.7 | Y38: 55.3 | Z38: 70.4 | AA38: 28.1 | AB38: 7 | AC38: 3.1 | AD38: 16.6 | AE38: 4.9 | AF38: 15 | AG38: 16 | AH38: 15.9 | AI38: 9.1 | AJ38: 63 | AK38: 13.6 | AL38: 16.2 | AM38: 3.4 | AN38: 18.5 | AP38: 190.9 | AQ38: 0.3 | AS38: 9 | AT38: 11.7 | AU38: 5.4 | AV38: 10 | AW38: 84.5 | AX38: 114.7 | AY38: 93.3 | AZ38: 83 | BA38: 0.6 | BB38: 14.1 | BC38: 10.9 | BD38: 37.9 | BE38: 20 | BF38: 4.4 | BG38: 1.4 | BH38: 1.1 | BI38: 2.2 | BJ38: 8.5 | BK38: 1 | BM38: 20.2 | BN38: 9.5 | BO38: 14.1 | BP38: 1428.02
B39: 16:00 | C39: 17.9 | F39: 14.6 | G39: 2.4 | H39: 0.2 | I39: 10.3 | J39: 0.5 | K39: 16.4 | M39: 10.7 | N39: 15.1 | O39: 7.5 | P39: 3.246 | Q39: 4.935 | R39: 19.9 | S39: 20.1 | T39: 20 | U39: 18.9 | V39: 3.8 | W39: 37.4 | X39: 93.1 | Y39: 47.9 | Z39: 68.2 | AA39: 19.5 | AB39: 5.7 | AC39: 2 | AD39: 16.6 | AE39: 4.9 | AF39: 15 | AG39: 16 | AH39: 15.9 | AI39: 9.1 | AJ39: 45.2 | AK39: 12.5 | AL39: 16.1 | AM39: 3.4 | AN39: 18.5 | AP39: 153.7 | AQ39: 0.1 | AS39: 6.5 | AT39: 9.1 | AU39: 5.4 | AV39: 9.9 | AW39: 82.4 | AX39: 81.2 | AY39: 85.4 | AZ39: 70.8 | BA39: 0.6 | BB39: 10.8 | BC39: 12.4 | BD39: 48.8 | BE39: 20 | BF39: 4.4 | BG39: 1.4 | BH39: 1.1 | BI39: 2.2 | BJ39: 6.1 | BK39: 1 | BM39: 20 | BN39: 9.5 | BO39: 10.2 | BP39: 1286.481
B40: 16:30 | C40: 17.5 | F40: 14.7 | G40: 2.5 | I40: 10.4 | J40: 0.3 | K40: 16.3 | M40: 10.7 | N40: 15.1 | O40: 7.4 | P40: 3.244 | Q40: 4.907 | R40: 20 | S40: 20 | T40: 20 | U40: 18.9 | V40: 5.3 | W40: 44.3 | X40: 96.6 | Y40: 50.8 | Z40: 72.3 | AA40: 9.6 | AB40: 8 | AC40: 2.4 | AD40: 16.6 | AE40: 4.9 | AF40: 15 | AG40: 16 | AH40: 15.9 | AI40: 9.1 | AJ40: 21.6 | AK40: 13.1 | AL40: 14 | AM40: 3.5 | AN40: 18.5 | AP40: 83.8 | AQ40: 0.1 | AS40: 3.8 | AT40: 3.4 | AU40: 5.5 | AV40: 9.9 | AW40: 76.8 | AX40: 39 | AY40: 72.1 | AZ40: 37 | BA40: 0.6 | BB40: 3.9 | BC40: 16.7 | BD40: 51.1 | BE40: 20 | BF40: 4.5 | BG40: 1.4 | BH40: 1.1 | BI40: 2.2 | BJ40: 3.7 | BK40: 1 | BM40: 20 | BN40: 9.4 | BO40: 3.2 | BP40: 1089.651
B41: 17:00 | C41: 17.1 | F41: 14.8 | G41: 2.6 | I41: 10.2 | J41: 0.1 | K41: 16.1 | M41: 10.7 | N41: 15 | O41: 7.4 | P41: 3.247 | Q41: 4.882 | R41: 20 | S41: 20.4 | T41: 20 | U41: 18.9 | V41: 6.1 | W41: 44.1 | X41: 100.7 | Y41: 49.4 | Z41: 74.7 | AA41: 1.5 | AB41: 6.9 | AC41: 2.3 | AD41: 16.6 | AE41: 4.9 | AF41: 15 | AG41: 16 | AH41: 15.9 | AI41: 9.1 | AJ41: 4.7 | AK41: 8.3 | AL41: 11.4 | AM41: 3.5 | AN41: 18.5 | AP41: 18.6 | AQ41: 0.1 | AS41: 1.4 | AT41: 0.2 | AU41: 5.4 | AV41: 9.9 | AW41: 77.7 | AX41: 6.7 | AY41: 76.9 | AZ41: 7.5 | BA41: 0.6 | BB41: 0.1 | BC41: 14.6 | BD41: 48.8 | BE41: 20 | BF41: 4.5 | BG41: 1.4 | BH41: 1.1 | BI41: 2.2 | BJ41: 1.4 | BK41: 1 | BM41: 18.5 | BN41: 9.4 | BP41: 919.029
B42: 17:30 | C42: 17.3 | F42: 14.8 | G42: 2.6 | I42: 10.3 | K42: 16.1 | M42: 10.3 | N42: 15.2 | O42: 7.4 | P42: 3.284 | Q42: 4.847 | R42: 20 | S42: 20.2 | T42: 20 | U42: 18.8 | V42: 5.8 | W42: 45.5 | X42: 98.4 | Y42: 55.5 | Z42: 73.3 | AB42: 5 | AC42: 1.4 | AD42: 16.6 | AE42: 4.9 | AF42: 15 | AG42: 16 | AH42: 15.9 | AI42: 8.3 | AK42: 7.3 | AL42: 10.2 | AM42: 3.5 | AN42: 18.5 | AQ42: 0.1 | AU42: 5.4 | AV42: 9.9 | AW42: 82.6 | AY42: 90 | BA42: 0.6 | BC42: 19.2 | BD42: 56.5 | BE42: 20 | BF42: 4.5 | BG42: 1.4 | BH42: 1.1 | BI42: 2.2 | BK42: 1 | BM42: 20 | BN42: 9.4 | BP42: 906.131
B43: 18:00 | C43: 17 | F43: 14.8 | G43: 2.7 | I43: 10.4 | K43: 15.9 | M43: 10.3 | N43: 15.2 | O43: 7.3 | P43: 3.241 | Q43: 4.81 | R43: 19.5 | S43: 20.3 | T43: 20 | U43: 18.8 | V43: 6.2 | W43: 36.7 | X43: 99.4 | Y43: 57 | Z43: 81.1 | AB43: 6.1 | AC43: 2.5 | AD43: 16.6 | AE43: 4.9 | AF43: 15 | AG43: 16 | AH43: 15.9 | AI43: 8.2 | AK43: 1.9 | AL43: 3.4 | AM43: 3.5 | AN43: 18.5 | AU43: 5.4 | AV43: 9.9 | AW43: 87.7 | AY43: 89.9 | BA43: 0.6 | BC43: 22 | BD43: 60.3 | BE43: 20 | BF43: 4.5 | BG43: 2.5 | BH43: 1.1 | BI43: 2.2 | BK43: 1 | BM43: 19.7 | BN43: 9.4 | BP43: 909.351
B44: 18:30 | C44: 17.5 | F44: 14.8 | G44: 2.7 | I44: 10 | K44: 15.9 | M44: 10.4 | N44: 15.2 | O44: 7.1 | P44: 3.251 | Q44: 4.796 | R44: 20 | S44: 20.2 | T44: 20 | U44: 18.9 | V44: 6.4 | W44: 35.9 | X44: 107.1 | Y44: 69.9 | Z44: 94.9 | AB44: 6.8 | AC44: 2.1 | AD44: 16.6 | AE44: 4.8 | AF44: 15 | AG44: 16 | AH44: 15.9 | AI44: 8.2 | AK44: 0.1 | AL44: 1 | AM44: 3.5 | AN44: 18.5 | AU44: 5.4 | AV44: 9.9 | AW44: 115.8 | AY44: 115.5 | BA44: 0.6 | BC44: 23 | BD44: 67.1 | BE44: 20 | BF44: 4.5 | BG44: 2.7 | BH44: 1.1 | BI44: 2.2 | BK44: 1 | BM44: 20 | BN44: 9.5 | BP44: 1001.747
B45: 19:00 | C45: 17.7 | F45: 14.8 | G45: 2.6 | I45: 9.9 | K45: 15.9 | M45: 10.3 | N45: 15 | O45: 7.1 | P45: 3.32 | Q45: 4.985 | R45: 20 | S45: 20.2 | T45: 20 | U45: 18.8 | V45: 4.6 | W45: 39.3 | X45: 110.9 | Y45: 68 | Z45: 95.3 | AB45: 6.1 | AC45: 2.5 | AD45: 16.4 | AE45: 4.8 | AF45: 15 | AG45: 16 | AH45: 15.9 | AI45: 8.2 | AK45: 1.2 | AL45: 2.1 | AM45: 3.5 | AN45: 18.5 | AU45: 5.4 | AV45: 9.9 | AW45: 116.6 | AY45: 113.4 | BA45: 0.6 | BC45: 24.8 | BD45: 63.1 | BE45: 20 | BF45: 4.5 | BG45: 2.7 | BH45: 1.1 | BI45: 2.2 | BK45: 1 | BM45: 20 | BN45: 9.4 | BP45: 1003.605
B46: 19:30 | C46: 17.5 | F46: 17.3 | G46: 2.7 | I46: 10.1 | K46: 15.9 | M46: 10.6 | N46: 15.3 | O46: 7.3 | P46: 3.219 | Q46: 4.938 | R46: 20 | S46: 20.6 | T46: 20 | U46: 18.8 | V46: 3 | W46: 34.5 | X46: 106.6 | Y46: 59.1 | Z46: 80.8 | AB46: 5.2 | AC46: 1.3 | AD46: 16.2 | AE46: 4.8 | AF46: 15 | AG46: 16 | AH46: 15.9 | AI46: 8 | AK46: 0.2 | AL46: 0.3 | AM46: 3.5 | AN46: 18.5 | AU46: 5.4 | AV46: 10 | AW46: 79 | AY46: 100.9 | BA46: 0.6 | BC46: 22.6 | BD46: 61 | BE46: 20 | BF46: 4.5 | BG46: 2.7 | BH46: 1.1 | BI46: 2.2 | BK46: 1 | BM46: 20 | BN46: 9.5 | BP46: 913.657
B47: 20:00 | C47: 17.6 | F47: 17.4 | G47: 2.7 | I47: 9.6 | K47: 15.9 | M47: 10.4 | N47: 15.2 | O47: 7.6 | P47: 3.257 | Q47: 4.898 | R47: 20 | S47: 20.3 | T47: 20 | U47: 18.8 | V47: 1.8 | W47: 27 | X47: 107.5 | Y47: 53 | Z47: 79.8 | AB47: 5 | AC47: 2.3 | AD47: 16.2 | AE47: 4.8 | AF47: 15 | AG47: 16 | AH47: 15.9 | AI47: 7.9 | AL47: 0.6 | AM47: 3.5 | AN47: 18.5 | AU47: 5.5 | AV47: 9.9 | AW47: 45.9 | AY47: 72.9 | BA47: 0.6 | BC47: 26.2 | BD47: 63.3 | BE47: 20 | BF47: 4.5 | BG47: 2.7 | BH47: 1.1 | BI47: 2.2 | BK47: 1 | BM47: 20 | BN47: 9.4 | BP47: 843.655
B48: 20:30 | C48: 17.4 | F48: 17.8 | G48: 2.6 | I48: 10.3 | K48: 15.9 | M48: 10.6 | N48: 15.3 | O48: 7.7 | P48: 3.237 | Q48: 4.867 | R48: 20 | S48: 20.4 | T48: 20 | U48: 18.8 | V48: 2 | W48: 31.2 | X48: 97.5 | Y48: 51.6 | Z48: 74.5 | AB48: 5.4 | AC48: 1.1 | AD48: 16.2 | AE48: 4.8 | AF48: 14.5 | AG48: 16 | AH48: 15.9 | AI48: 8.2 | AK48: 1 | AL48: 1.7 | AM48: 3.5 | AN48: 18.5 | AU48: 5.4 | AV48: 10 | AW48: 27.9 | AY48: 37.4 | BA48: 0.6 | BC48: 22.8 | BD48: 44.1 | BE48: 20.2 | BF48: 4.5 | BG48: 2.7 | BH48: 1.2 | BI48: 2.2 | BK48: 1 | BM48: 20 | BN48: 9.5 | BP48: 758.004
B49: 21:00 | C49: 17.9 | F49: 17.9 | G49: 2.6 | I49: 9 | K49: 15.8 | M49: 10.4 | N49: 15.1 | O49: 7.9 | P49: 3.283 | Q49: 4.845 | R49: 20 | S49: 20.4 | T49: 20 | U49: 18.9 | V49: 1.9 | W49: 30.9 | X49: 93.4 | Y49: 35.4 | Z49: 63.1 | AB49: 2.2 | AC49: 0.3 | AD49: 16.2 | AE49: 4.8 | AF49: 14.5 | AG49: 15.5 | AH49: 15.5 | AI49: 8.3 | AL49: 0.3 | AM49: 3.5 | AN49: 18.5 | AU49: 5.4 | AV49: 9.9 | AW49: 7.2 | AY49: 17 | BA49: 0.6 | BC49: 12.9 | BD49: 20.5 | BE49: 20 | BF49: 4.5 | BG49: 2.7 | BH49: 1.2 | BI49: 2.2 | BK49: 1 | BM49: 20.2 | BN49: 9.5 | BP49: 643.128
B50: 21:30 | C50: 17.8 | F50: 17.8 | G50: 2.6 | I50: 9.6 | K50: 15.9 | M50: 10 | N50: 15 | O50: 8.1 | P50: 3.32 | Q50: 4.821 | R50: 20 | S50: 20.5 | T50: 20 | U50: 18.8 | V50: 2.5 | W50: 30.4 | X50: 90.8 | Y50: 17 | Z50: 38.3 | AB50: 0.2 | AD50: 16.2 | AE50: 4.8 | AF50: 14.5 | AG50: 15.5 | AH50: 15.5 | AI50: 8.3 | AL50: 0.1 | AM50: 3.6 | AN50: 18.5 | AU50: 5.4 | AV50: 9.9 | AW50: 1.5 | AY50: 3.2 | BA50: 0.6 | BC50: 10.4 | BD50: 22.1 | BE50: 20 | BF50: 4.5 | BG50: 2.7 | BH50: 1.2 | BI50: 2.2 | BK50: 1 | BM50: 20 | BN50: 9.6 | BP50: 574.741
B51: 22:00 | C51: 18.1 | F51: 17.8 | G51: 2.7 | I51: 9.4 | K51: 15.9 | M51: 9.6 | N51: 14.4 | O51: 8.1 | P51: 3.32 | Q51: 4.785 | R51: 20 | S51: 20.2 | T51: 20 | U51: 18.9 | V51: 3.1 | W51: 35.7 | X51: 87.8 | Y51: 25 | Z51: 43 | AB51: 1.2 | AD51: 16.2 | AE51: 4.8 | AF51: 14 | AG51: 15 | AH51: 15 | AI51: 8.2 | AK51: 0.9 | AL51: 1.2 | AM51: 3.6 | AN51: 18.5 | AU51: 5.4 | AV51: 9.9 | AY51: 0.1 | BA51: 0.6 | BC51: 14.4 | BD51: 28.1 | BE51: 20 | BF51: 4.5 | BG51: 2.7 | BH51: 1.2 | BI51: 2.2 | BK51: 1 | BM51: 20 | BN51: 9.4 | BP51: 595.905
B52: 22:30 | C52: 18.5 | F52: 17.8 | G52: 2.7 | I52: 9.2 | K52: 15.8 | M52: 9.6 | N52: 14.5 | O52: 8.1 | P52: 3.32 | Q52: 4.752 | R52: 20 | S52: 20.2 | T52: 20 | U52: 18.9 | V52: 5.1 | W52: 43.6 | X52: 91.4 | Y52: 36.9 | Z52: 58.5 | AB52: 1.8 | AC52: 0.3 | AD52: 16.2 | AE52: 4.8 | AF52: 14 | AG52: 15 | AH52: 15 | AI52: 8.1 | AK52: 1.7 | AL52: 2.8 | AM52: 3.6 | AN52: 18.5 | AU52: 5.4 | AV52: 9.9 | BA52: 0.6 | BC52: 16.1 | BD52: 27.3 | BE52: 20 | BF52: 4.5 | BG52: 2.7 | BH52: 1.2 | BI52: 2.2 | BK52: 1 | BM52: 20 | BN52: 9.4 | BP52: 640.972
B53: 23:00 | C53: 17.7 | F53: 17.8 | G53: 2.8 | I53: 9.4 | K53: 15.8 | M53: 9.1 | N53: 14.2 | O53: 8 | P53: 3.32 | Q53: 4.722 | R53: 20 | S53: 20.2 | T53: 20 | U53: 18.9 | V53: 5.2 | W53: 42.3 | X53: 91 | Y53: 19.2 | Z53: 40.7 | AB53: 0.5 | AD53: 16.1 | AE53: 4.8 | AF53: 14.2 | AG53: 15.2 | AH53: 15.2 | AI53: 7.4 | AK53: 1.6 | AL53: 2.8 | AM53: 3.6 | AN53: 18.5 | AU53: 5.5 | AV53: 9.8 | BA53: 0.6 | BC53: 9.9 | BD53: 15.5 | BE53: 20 | BF53: 4.5 | BG53: 2.7 | BH53: 1.2 | BI53: 2.2 | BK53: 1 | BM53: 20 | BN53: 9.5 | BP53: 582.642
B54: 23:30 | C54: 17.8 | F54: 17.8 | G54: 2.7 | I54: 9.2 | K54: 15.8 | M54: 10.7 | N54: 14.3 | O54: 8.1 | P54: 3.32 | Q54: 4.762 | R54: 20 | S54: 20.5 | T54: 20 | U54: 18.9 | V54: 4.2 | W54: 37.5 | X54: 78.2 | Y54: 3.3 | Z54: 11.6 | AD54: 16 | AE54: 4.7 | AF54: 14.5 | AG54: 15.5 | AH54: 15.5 | AI54: 7.6 | AK54: 0.6 | AL54: 2 | AM54: 3.6 | AN54: 18.5 | AU54: 5.4 | AV54: 9.9 | BA54: 0.6 | BC54: 7.4 | BD54: 8.4 | BE54: 20 | BF54: 1.5 | BG54: 0.9 | BH54: 1.2 | BI54: 0.8 | BK54: 1 | BM54: 20 | BN54: 9.5 | BP54: 503.782
B55: 0:00 | C55: 17.7 | F55: 17.8 | G55: 2.6 | I55: 9.5 | K55: 15.7 | M55: 10.8 | N55: 14.4 | O55: 8.1 | P55: 3.32 | Q55: 4.997 | R55: 20 | S55: 20.7 | T55: 20 | U55: 18.9 | V55: 1.9 | W55: 30.7 | X55: 76.2 | Y55: 6.4 | Z55: 19.1 | AD55: 16 | AE55: 4.7 | AF55: 14.5 | AG55: 15.5 | AH55: 15.5 | AI55: 7.7 | AL55: 0.6 | AM55: 3.6 | AN55: 18.5 | AU55: 5.4 | AV55: 9.9 | BA55: 0.6 | BC55: 4.5 | BD55: 6.9 | BE55: 20 | BF55: 2.1 | BG55: 1.2 | BH55: 1.2 | BI55: 1.2 | BK55: 1 | BM55: 20 | BN55: 9.5 | BP55: 498.917
B56: EJEC MWh | C56: 422.4 | D56: 0 | E56: 0 | F56: 362.1 | G56: 56.45 | H56: 1.85 | I56: 232.7 | J56: 8.65 | K56: 397.5 | L56: 0 | M56: 257.05 | N56: 364.9 | O56: 185.05 | P56: 78.7815 | Q56: 117.3805 | R56: 479.3 | S56: 488.25 | T56: 480 | U56: 453.2 | V56: 195.85 | W56: 640.2 | X56: 1750.15 | Y56: 645.1 | Z56: 1000.85 | AA56: 269.55 | AB56: 54.6 | AC56: 20.3 | AD56: 405.75 | AE56: 117.05 | AF56: 361.9 | AG56: 386.45 | AH56: 382.8 | AI56: 189.6 | AJ56: 632.3 | AK56: 163.2 | AL56: 220.75 | AM56: 86.8 | AN56: 444 | AO56: 0 | AP56: 1966.6 | AQ56: 2.9 | AR56: 0 | AS56: 120.6 | AT56: 124.05 | AU56: 130.05 | AV56: 237.85 | AW56: 579.25 | AX56: 1120.9 | AY56: 623.05 | AZ56: 830.6 | BA56: 14.4 | BB56: 150.3 | BC56: 251.2 | BD56: 635.95 | BE56: 480.35 | BF56: 104.9 | BG56: 21.9 | BH56: 22.05 | BI56: 51.55 | BJ56: 116 | BK56: 24 | BL56: 0 | BM56: 479.45 | BN56: 227.05 | BO56: 151 | BP56: 20818.712
L70: TERMOELÉCTRICA | M70: 855.5 | N70: 4.109284 | O70: #FFA975
L71: SOLAR | M71: 5493.45 | N71: 26.387079 | O71: #FFD272
L72: EÓLICA | M72: 6780.45 | N72: 32.569018 | O72: #B9ACFF
L73: HIDROELÉCTRICA | M73: 7689.312 | N73: 36.934619 | O73: #98D2FF

Sheet COGENERACIÓN
B3: jueves, 15 de Mayo del 2025
B5: CENTRALES DE COGENERACIÓN DEL SEIN
B6: HORA | C6: AGRO INDUSTRIAL PARAMONGA S.A. | D6: AGROAURORA S.A.C. | E6: AGROINDUSTRIAS SAN JACINTO S.A.A. | F6: BIOENERGIA DEL CHIRA S.A. | G6: GM OPERACIONES S.A.C. | H6: SDF ENERGIA SAC | I6: TOTAL COGENERACION
C7: C.T. PARAMONGA | D7: C.T. MAPLE | E7: C.T SAN JACINTO | F7: C.T. CAÑA BRAVA | G7: C.T. REFINERÍA TALARA | H7: C.T. OQUENDO | I7: MW
B8: 0:30 | C8: 18.3 | F8: 9.5 | I8: 27.8
B9: 1:00 | C9: 17.8 | F9: 9.5 | I9: 27.3
B10: 1:30 | C10: 17.5 | F10: 9 | I10: 26.5
B11: 2:00 | C11: 17.5 | F11: 9.2 | I11: 26.7
B12: 2:30 | C12: 17.5 | F12: 9.5 | I12: 27
B13: 3:00 | C13: 17.5 | F13: 9.1 | I13: 26.6
B14: 3:30 | C14: 17.6 | F14: 9 | I14: 26.6
B15: 4:00 | C15: 17.5 | F15: 8.9 | I15: 26.4
B16: 4:30 | C16: 17.7 | F16: 9 | I16: 26.7
B17: 5:00 | C17: 17.6 | F17: 9.2 | I17: 26.8
B18: 5:30 | C18: 18 | F18: 9.1 | I18: 27.1
B19: 6:00 | C19: 17.8 | F19: 9.4 | I19: 27.2
... B28: 10:30 | C28: 17 | F28: 9.7 | I28: 26.7
B29: 11:00 | C29: 17.1 | F29: 10.1 | G29: 7 | I29: 34.2
B30: 11:30 | C30: 17.5 | F30: 10.3 | G30: 18.9 | I30: 46.7
B31: 12:00 | C31: 17.8 | F31: 10.3 | G31: 20 | I31: 48.1
B32: 12:30 | C32: 17.7 | F32: 10 | G32: 30.4 | I32: 58.1
B33: 13:00 | C33: 17.7 | F33: 9.8 | G33: 35.3 | I33: 62.8
B34: 13:30 | C34: 17.1 | F34: 10.1 | G34: 35.2 | I34: 62.4
B35: 14:00 | C35: 17.5 | F35: 10.3 | G35: 34.9 | I35: 62.7
B36: 14:30 | C36: 17.4 | F36: 10.6 | G36: 34.5 | I36: 62.5
B37: 15:00 | C37: 17.9 | F37: 10.7 | G37: 33.2 | I37: 61.8
B38: 15:30 | C38: 17.9 | F38: 10.7 | G38: 34.8 | I38: 63.4
B39: 16:00 | C39: 17.9 | F39: 10.3 | G39: 35.3 | I39: 63.5
B40: 16:30 | C40: 17.5 | F40: 10.4 | G40: 35.4 | I40: 63.3
... B55: 0:00 | C55: 17.7 | F55: 9.5 | G55: 28.9 | I55: 56.1
B56: EJEC MWh | C56: 422.4 | D56: 0 | E56: 0 | F56: 232.7 | G56: 435.4 | H56: 0 | I56: 1090.5

Sheet EVO_PRO_ENE
B3: jueves, 1 de Mayo del 2025 - jueves, 15 de Mayo del 2025
B5: EVOLUCIÓN DE LA PRODUCCIÓN DE LA ENERGÍA DIARIA DE LOS INTEGRANTES DEL COES (MWh)
B6: EMPRESA | C6: CENTRAL | D6: UNIDAD | E6: TIPO | F6: Mayo
F7: 1 | G7: 2 | H7: 3 | I7: 4 | J7: 5 | K7: 6 | L7: 7 | M7: 8 | N7: 9 | O7: 10 | P7: 11 | Q7: 12 | R7: 13 | S7: 14 | T7: 15 | U7: TOTAL
B8: AGRO INDUSTRIAL PARAMONGA S.A. | C8: C.T. PARAMONGA | D8: TV-01 | E8: TERMOELÉCTRICA | G8: 138.9 | H8: 376.5 | I8: 395.45 | J8: 401.05 | K8: 409.7 | L8: 400.15 | M8: 403.9 | N8: 411.4 | O8: 405.45 | P8: 404.4 | Q8: 407.85 | R8: 414.7 | S8: 420.75 | T8: 422.4 | U8: 5412.6
B9: AGROAURORA S.A.C. | C9: C.T. MAPLE ETANOL | D9: TV | E9: TERMOELÉCTRICA | U9: 0
B10: AGROINDUSTRIAS SAN JACINTO S.A.A. | C10: C.T. SAN JACINTO | D10: CENTRAL | E10: TERMOELÉCTRICA | U10: 0
B11: ANDEAN POWER S.A.C. | C11: C.H.CARHUAC | D11: CENTRAL | E11: HIDROELÉCTRICA | F11: 421.45 | G11: 451.4 | H11: 485.05 | I11: 485 | J11: 485.75 | K11: 485.9 | L11: 466.95 | M11: 485.55 | N11: 477.35 | O11: 474.8 | P11: 477.05 | Q11: 451.6 | R11: 376.65 | S11: 359.15 | T11: 362.1 | U11: 6745.75
B12: ASOCIACIÓN SANTA LUCIA DE CHACAS | C12: C.H. HUALLIN | D12: CENTRAL | E12: HIDROELÉCTRICA | F12: 74.05 | G12: 74 | H12: 74.32 | I12: 74.1 | J12: 73.35 | K12: 73.5 | L12: 73.85 | M12: 73.6 | N12: 72.4 | O12: 70.35 | P12: 68.95 | Q12: 65.6 | R12: 62.4 | S12: 61.05 | T12: 56.45 | U12: 1047.97
B13: ATRIA ENERGIA S.A.C. | C13: C.H. PURMACANA | D13: CENTRAL | E13: HIDROELÉCTRICA | G13: 0.6 | N13: 6.15 | O13: 9.25 | P13: 5.85 | T13: 1.85 | U13: 23.7
B14: BIOENERGIA DEL CHIRA S.A. | C14: C.T. CAÑA BRAVA | D14: CENTRAL | E14: TERMOELÉCTRICA | F14: 226.85 | G14: 195.65 | H14: 215.5 | I14: 216.4 | J14: 194.4 | K14: 228.85 | L14: 227.3 | M14: 230.85 | N14: 242.25 | O14: 233.75 | P14: 227.65 | Q14: 234.1 | R14: 235.55 | S14: 212.8 | T14: 232.7 | U14: 3354.6
B15: CELEPSA | C15: C.H. EL PLATANAL | D15: CENTRAL | E15: HIDROELÉCTRICA | F15: 5086.85 | G15: 4956.25 | H15: 4948 | I15: 4914.05 | J15: 5043.5 | K15: 5166.2 | L15: 5106.6 | M15: 5025.2 | N15: 4887.85 | O15: 5091.15 | P15: 4548.3 | Q15: 4959.7 | R15: 4953.8 | S15: 5068.75 | T15: 4974.75 | U15: 74730.95
B16: CELEPSA RENOVABLES S.R.L. | C16: C.H. MARAÑON | D16: CENTRAL | E16: HIDROELÉCTRICA | F16: 465.7 | G16: 470.95 | H16: 472.8 | I16: 470.1 | J16: 472.8 | K16: 462.5 | L16: 472.8 | M16: 472.8 | N16: 472.8 | O16: 472.8 | P16: 472.8 | Q16: 472.8 | R16: 472.8 | S16: 472.8 | T16: 466.95 | U16: 7064.2
B17: CENTRALES SANTA ROSA S.A.C. | C17: C.H. SANTA ROSA I | D17: CENTRAL | E17: HIDROELÉCTRICA | U17: 0
B18: CENTRALES SANTA ROSA S.A.C. | C18: C.H. SANTA ROSA II | D18: CENTRAL | E18: HIDROELÉCTRICA | U18: 0
B19: CHINANGO S.A.C. | C19: C.H. CHIMAY | D19: CENTRAL | E19: HIDROELÉCTRICA | F19: 3549.35 | G19: 3333.55 | H19: 3459.45 | I19: 3208.2 | J19: 3508.3 | K19: 3521.55 | L19: 3520.75 | M19: 3469.95 | N19: 3044.3 | O19: 3070.4 | P19: 3077.8 | Q19: 3500.7 | R19: 3420.85 | S19: 2791.85 | T19: 3114.6 | U19: 49591.6
B20: CHINANGO S.A.C. | C20: C.H. YANANGO | D20: CENTRAL | E20: HIDROELÉCTRICA | F20: 1016.35 | G20: 1015.2 | H20: 1014.65 | I20: 1014.65 | J20: 1014.55 | K20: 1014.3 | L20: 1014.15 | M20: 943.3 | N20: 994.2 | O20: 984.4 | P20: 986.4 | Q20: 1000.95 | R20: 1002.7 | S20: 961.5 | T20: 928.25 | U20: 14905.55
B21: COLCA SOLAR S.A.C. | C21: C.S. YARUCAYA | D21: CENTRAL | E21: SOLAR | F21: 6.7 | G21: 5.85 | H21: 7 | I21: 1.7 | J21: 7.15 | K21: 6.05 | L21: 8.75 | M21: 8.9 | N21: 8.65 | O21: 8.6 | P21: 6.4 | Q21: 8.95 | R21: 8.5 | S21: 8.55 | T21: 8.65 | U21: 110.4
B22: EGASA | C22: C.H. CHARCANI III | D22: CENTRAL | E22: HIDROELÉCTRICA | F22: 155.2 | G22: 160.75 | H22: 161.6 | I22: 161.8 | J22: 160.9 | K22: 130.9 | L22: 143.9 | M22: 113.4 | N22: 149.05 | O22: 160.4 | P22: 160.85 | Q22: 155.75 | R22: 160.8 | S22: 160.65 | T22: 159.2 | U22: 2295.15
B23: EGASA | C23: C.H. CHARCANI IV | D23: CENTRAL | E23: HIDROELÉCTRICA | F23: 253.6 | G23: 242.2 | H23: 251.45 | I23: 254.05 | J23: 255.05 | K23: 253.7 | L23: 134.5 | M23: 220.15 | N23: 260.85 | O23: 316.8 | P23: 305.75 | Q23: 312.35 | R23: 303.75 | S23: 298.55 | T23: 282.2 | U23: 3944.95
B24: EGASA | C24: C.H. CHARCANI V | D24: CENTRAL | E24: HIDROELÉCTRICA | F24: 1792.9 | G24: 1776.9 | H24: 1778.95 | I24: 1802.5 | J24: 1802 | K24: 1658.45 | L24: 1465.3 | M24: 1456.85 | N24: 1718.3 | O24: 1989.75 | P24: 2030.25 | Q24: 2019.75 | R24: 1980.05 | S24: 2008.85 | T24: 1920.5 | U24: 27201.3
B25: EGASA | C25: C.H. CHARCANI VI | D25: CENTRAL | E25: HIDROELÉCTRICA | F25: 125.6 | G25: 134.35 | H25: 135.3 | I25: 134.75 | J25: 136.25 | K25: 133.8 | L25: 70.15 | M25: 118.7 | N25: 48.4 | U25: 1037.3
B26: EGASA | C26: C.T. CHILINA DIESEL | D26: CENTRAL | E26: TERMOELÉCTRICA | R26: 17.45 | U26: 17.45
B27: EGASA | C27: C.T. CHILINA DIESEL | D27: TG | E27: TERMOELÉCTRICA | K27: 24.65 | R27: 14.65 | U27: 39.3
B28: EGASA | C28: C.T. MOLLENDO DIESEL | D28: CENTRAL | E28: TERMOELÉCTRICA | L28: 19.8 | S28: 0.85 | T28: 16.8 | U28: 37.45
B29: EGEJUNIN | C29: C.H. HUASAHUASI I | D29: CENTRAL | E29: HIDROELÉCTRICA | F29: 474.75 | G29: 475.45 | H29: 475.2 | I29: 474.3 | J29: 475.2 | K29: 475.2 | L29: 465.6 | M29: 432.65 | N29: 402.65 | O29: 386.45 | P29: 460.15 | Q29: 473.6 | R29: 465.6 | S29: 426.8 | T29: 397.5 | U29: 6761.1
B30: EGEJUNIN | C30: C.H. RUNATULLO II | D30: CENTRAL | E30: HIDROELÉCTRICA | F30: 446.9 | G30: 410.85 | H30: 386.4 | I30: 371.2 | J30: 356.7 | K30: 354.65 | L30: 318.4 | M30: 298.55 | N30: 292.2 | O30: 288.15 | P30: 361.55 | Q30: 332.25 | R30: 300.45 | S30: 275.05 | T30: 257.05 | U30: 5050.35
B31: EGEJUNIN | C31: C.H. RUNATULLO III | D31: CENTRAL | E31: HIDROELÉCTRICA | F31: 486.05 | G31: 485.45 | H31: 485.4 | I31: 485.65 | J31: 481.85 | K31: 481.4 | L31: 443.4 | M31: 414.35 | N31: 406.5 | O31: 401.95 | P31: 456.05 | Q31: 463.55 | R31: 416.55 | S31: 386.95 | T31: 364.9 | U31: 6660
B32: EGEJUNIN | C32: C.H. SANTA CRUZ I | D32: CENTRAL | E32: HIDROELÉCTRICA | F32: 229.5 | G32: 241.55 | H32: 295.9 | I32: 307.65 | J32: 309.9 | K32: 302.6 | L32: 307.9 | M32: 303.1 | N32: 286.25 | O32: 269.2 | P32: 252.85 | Q32: 237.55 | R32: 212.25 | S32: 192.2 | T32: 185.05 | U32: 3933.45
B33: EGEMSA | C33: C.H. MACHUPICCHU | D33: CENTRAL | E33: HIDROELÉCTRICA | F33: 3480.3 | G33: 3954.6 | H33: 3940.45 | I33: 3971.85 | J33: 3943.65 | K33: 3967.2 | L33: 3930.7 | M33: 3948.15 | N33: 3967.35 | O33: 3936.15 | P33: 3919.55 | Q33: 3960.4 | R33: 3970.75 | S33: 3965.55 | T33: 3962.2 | U33: 58818.85
B34: EGESUR | C34: C.H. ARICOTA I | D34: CENTRAL | E34: HIDROELÉCTRICA | F34: 177.4 | G34: 175.4 | H34: 174.9 | I34: 170.9 | J34: 174 | K34: 175.3 | L34: 174.8 | M34: 177.3 | N34: 174.6 | O34: 173.95 | P34: 174.2 | Q34: 173.35 | R34: 175.1 | S34: 173.4 | T34: 175.45 | U34: 2620.05
B35: EGESUR | C35: C.H. ARICOTA II | D35: CENTRAL | E35: HIDROELÉCTRICA | F35: 86.25 | G35: 85 | H35: 85.55 | I35: 48.7 | J35: 74.2 | K35: 82.45 | L35: 89.9 | M35: 93.5 | N35: 94.15 | O35: 96.25 | P35: 96.1 | Q35: 101 | R35: 111.05 | S35: 121.65 | T35: 124.5 | U35: 1390.25
B36: EGESUR | C36: C.T. INDEPENDENCIA | D36: CENTRAL | E36: TERMOELÉCTRICA | F36: 156.35 | G36: 339.35 | H36: 100.2 | I36: 182.65 | J36: 21.6 | K36: 138.8 | L36: 161.95 | M36: 64.7 | N36: 69.25 | P36: 103.15 | Q36: 80.25 | R36: 54.1 | U36: 1472.35
B37: ELECTRICA YANAPAMPA SAC | C37: C.H. YANAPAMPA | D37: CENTRAL | E37: HIDROELÉCTRICA | F37: 55.8 | G37: 80.4 | H37: 81.35 | I37: 81.2 | J37: 75.7 | K37: 80.8 | L37: 81.2 | M37: 80.85 | N37: 81.25 | O37: 81.05 | P37: 65.4 | Q37: 75.15 | R37: 79.45 | S37: 77.7 | T37: 78.7815 | U37: 1156.0815
B38: ELECTROPERU | C38: C.H. MANTARO | D38: CENTRAL | E38: HIDROELÉCTRICA | F38: 15548.35 | G38: 15398.4 | H38: 15514.7 | I38: 14781.5 | J38: 15509.95 | K38: 15099.45 | L38: 15517.7 | M38: 15542.85 | N38: 15215.9 | O38: 15462.355 | P38: 13960.595 | Q38: 15460.01 | R38: 15257.85 | S38: 15526.6 | T38: 15556.75 | U38: 229352.96
B39: ELECTROPERU | C39: C.H. RESTITUCION | D39: CENTRAL | E39: HIDROELÉCTRICA | F39: 5178.95 | G39: 5135.7 | H39: 5174.45 | I39: 4961 | J39: 5174 | K39: 5026.15 | L39: 5182.5 | M39: 5184.85 | N39: 5057.4 | O39: 5124.305 | P39: 4625.5 | Q39: 5173 | R39: 5060.2 | S39: 5149.15 | T39: 5157.8 | U39: 76364.955
B40: ELECTROPERU | C40: C.T. TUMBES | D40: MAK1 | E40: TERMOELÉCTRICA | J40: 59.35 | K40: 52.15 | L40: 44.7 | Q40: 18 | S40: 17.65 | T40: 20.2 | U40: 212.05
B41: ELECTROPERU | C41: C.T. TUMBES | D41: MAK2 | E41: TERMOELÉCTRICA | J41: 59.65 | K41: 52.95 | L41: 44.65 | Q41: 17.25 | S41: 14 | T41: 20.25 | U41: 208.75
B42: EMPRESA DE GENERACION ELECTRICA CANCHAYLLO SAC | C42: C.H. CANCHAYLLO | D42: CENTRAL | E42: HIDROELÉCTRICA | F42: 122.85 | G42: 123.45 | H42: 123.75 | I42: 124.05 | J42: 124.35 | K42: 123.8 | L42: 123.25 | M42: 122.8 | N42: 122.2 | O42: 122.9 | P42: 123.25 | Q42: 122.95 | R42: 122.8 | S42: 118.6 | T42: 117.3805 | U42: 1838.3805
B43: EMPRESA DE GENERACION ELECTRICA RIO BAÑOS S.A.C. | C43: C.H. RUCUY | D43: CENTRAL | E43: HIDROELÉCTRICA | F43: 479.95 | G43: 479.55 | H43: 479.4 | I43: 479.15 | J43: 479.55 | K43: 480.4 | L43: 479.95 | M43: 479.3 | N43: 479.7 | O43: 479.75 | P43: 480 | Q43: 479.1 | R43: 370.05 | S43: 479.45 | T43: 479.3 | U43: 7084.6
B44: EMPRESA DE GENERACION ELECTRICA SANTA ANA S.A.C. | C44: C.H. RENOVANDES H1 | D44: CENTRAL | E44: HIDROELÉCTRICA | F44: 487.8 | G44: 486 | H44: 372.68 | I44: 475.3 | J44: 484.35 | K44: 485.75 | L44: 484.5 | M44: 485.45 | N44: 484.65 | O44: 484.7 | P44: 397.4 | Q44: 485.7 | R44: 486.9 | S44: 486.85 | T44: 488.25 | U44: 7076.28
B45: EMPRESA DE GENERACION HUALLAGA | C45: C.H. CHAGLLA | D45: CENTRAL | E45: HIDROELÉCTRICA | F45: 5142.4 | G45: 5208.65 | H45: 4911.4 | I45: 4791.8 | J45: 5162.15 | K45: 5553.15 | L45: 5505.4 | M45: 5424.25 | N45: 5354.45 | O45: 5345.3 | P45: 4809.95 | Q45: 5258.1 | R45: 5501.7 | S45: 5515.7 | T45: 7196.3 | U45: 80680.7
B46: EMPRESA DE GENERACION HUALLAGA | C46: P.C.H. CHAGLLA | D46: CENTRAL | E46: HIDROELÉCTRICA | F46: 156 | G46: 156 | H46: 156 | I46: 156 | J46: 156 | K46: 156 | L46: 156 | M46: 156 | N46: 156 | O46: 156 | P46: 156 | Q46: 156.1 | R46: 156.65 | S46: 156.6 | T46: 156 | U46: 2341.35
B47: EMPRESA DE GENERACION HUANZA | C47: C.H. HUANZA | D47: CENTRAL | E47: HIDROELÉCTRICA | G47: 666.6 | H47: 1141.4 | I47: 1142.55 | J47: 1139.75 | K47: 1143.85 | L47: 1142.65 | M47: 1143.55 | N47: 780.75 | O47: 589.95 | P47: 233.05 | Q47: 670.05 | R47: 1149.35 | S47: 1148.35 | T47: 1152.85 | U47: 13244.7
B48: EMPRESA ELECTRICA AGUA AZUL | C48: C.H. POTRERO | D48: CENTRAL | E48: HIDROELÉCTRICA | F48: 322.85 | G48: 438.7 | H48: 392.45 | I48: 401.3 | J48: 395.25 | K48: 284.3 | L48: 240 | M48: 240 | N48: 240 | O48: 329.9 | P48: 364.6 | Q48: 479.2 | R48: 480 | T48: 480 | U48: 5088.55
B49: EMPRESA ELECTRICA RIO DOBLE | C49: C.H. LAS PIZARRAS | D49: CENTRAL | E49: HIDROELÉCTRICA | F49: 423.65 | G49: 448.8 | H49: 449.35 | I49: 444.5 | J49: 392.05 | K49: 400.4 | L49: 450.15 | M49: 451.19 | N49: 454.4 | O49: 453.55 | P49: 451.715 | Q49: 453.2 | R49: 453.5 | S49: 453.55 | T49: 453.2 | U49: 6633.205
B50: ENEL GENERACION PIURA S.A. | C50: C.T. MALACAS 1 | D50: TG6 | E50: TERMOELÉCTRICA | F50: 1114.9 | G50: 795.2 | H50: 363 | Q50: 425.25 | R50: 760.35 | S50: 447.55 | T50: 1099.35 | U50: 5005.6
B51: ENEL GENERACION PIURA S.A. | C51: C.T. MALACAS 2 | D51: TG4 | E51: TERMOELÉCTRICA | J51: 578.5 | K51: 753.3 | L51: 834.5 | M51: 47.95 | N51: 504.4 | Q51: 459.3 | R51: 62.25 | S51: 461.4 | T51: 137.15 | U51: 3838.75
B52: ENEL GENERACION PIURA S.A. | C52: C.T. RF DE GENERACION TALARA | D52: TG5 | E52: TERMOELÉCTRICA | Q52: 437.3 | S52: 1475.8 | T52: 1249 | U52: 3162.1
B53: ENERGÍA EÓLICA S.A. | C53: C.E. CUPISNIQUE | D53: CENTRAL | E53: EÓLICA | F53: 1245.85 | G53: 1135.5 | H53: 1112.15 | I53: 1208.55 | J53: 996.2 | K53: 1164 | L53: 978.35 | M53: 1220.9 | N53: 1368.9 | O53: 1226.1 | P53: 996.4 | Q53: 1065.8 | R53: 904.35 | S53: 575 | T53: 640.2 | U53: 15838.25
B54: ENERGÍA EÓLICA S.A. | C54: C.E. TALARA | D54: CENTRAL | E54: EÓLICA | F54: 437.85 | G54: 434.45 | H54: 355.8 | I54: 226.9 | J54: 225.25 | K54: 579.7 | L54: 297.9 | M54: 399 | N54: 493.4 | O54: 570.75 | P54: 236.8 | Q54: 449.05 | R54: 452.65 | S54: 257.75 | T54: 195.85 | U54: 5613.1
B55: ENERGIA RENOVABLE DEL SUR S.A. | C55: C.E. SAN JUAN | D55: CENTRAL | E55: EÓLICA | F55: 2082.5 | G55: 2558.45 | H55: 1799.8 | I55: 1720.65 | J55: 2118.55 | K55: 2285.45 | L55: 2195.9 | M55: 1895.7 | N55: 1814.6 | O55: 1966.75 | P55: 1690.85 | Q55: 1133.4 | R55: 1140.2 | S55: 1095.55 | T55: 1750.15 | U55: 27248.5
B56: ENGIE | C56: C.E. PUNTA LOMITAS | D56: PL-BL1 | E56: EÓLICA | F56: 1647.45 | G56: 1826.25 | H56: 2034.05 | I56: 1257.6 | J56: 1064.15 | K56: 1223.4 | L56: 944.35 | M56: 1253.5 | N56: 1449.4 | O56: 1129.45 | P56: 1279.95 | Q56: 1139.9 | R56: 1185.05 | S56: 580.3 | T56: 645.1 | U56: 18659.9
B57: ENGIE | C57: C.E. PUNTA LOMITAS | D57: PL-BL2 | E57: EÓLICA | F57: 1892.6 | G57: 2008.15 | H57: 2127.35 | I57: 1671.25 | J57: 1455.2 | K57: 1930.7 | L57: 1726.05 | M57: 1753.9 | N57: 1910.75 | O57: 1608.85 | P57: 1630.2 | Q57: 1447.75 | R57: 1408.6 | S57: 917.65 | T57: 1000.85 | U57: 24489.85
B58: ENGIE | C58: C.E. PUNTA LOMITAS_EXP | D58: PUN LOM_EXP-BL1 | E58: EÓLICA | F58: 205.1 | G58: 248.6 | H58: 292.4 | I58: 163.85 | J58: 123.9 | K58: 190.75 | L58: 204.45 | M58: 247.65 | N58: 241.8 | O58: 198.8 | P58: 192.5 | Q58: 149.95 | R58: 153.5 | S58: 49.65 | T58: 54.6 | U58: 2717.5
B59: ENGIE | C59: C.E. PUNTA LOMITAS_EXP | D59: PUN LOM_EXP-BL2 | E59: EÓLICA | F59: 141.95 | G59: 170.85 | H59: 199.6 | I59: 96.45 | J59: 74.3 | K59: 78.2 | L59: 86.25 | M59: 119.65 | N59: 132.3 | O59: 75.45 | P59: 79.85 | Q59: 84.8 | R59: 94.1 | S59: 26.5 | T59: 20.3 | U59: 1480.55
B60: ENGIE | C60: C.H. QUITARACSA | D60: CENTRAL | E60: HIDROELÉCTRICA | U60: 0
B61: ENGIE | C61: C.H. YUNCAN | D61: CENTRAL | E61: HIDROELÉCTRICA | F61: 1084.9 | G61: 1002.2 | H61: 961.25 | I61: 1039.2 | J61: 1046 | K61: 2101.2 | L61: 2101.25 | M61: 2089.2 | N61: 2077.95 | O61: 2078.35 | P61: 2077.75 | Q61: 2062.95 | R61: 2064.7 | S61: 2066.6 | T61: 2068 | U61: 25921.5
B62: ENGIE | C62: C.S. INTIPAMPA | D62: CENTRAL | E62: SOLAR | F62: 117.45 | G62: 276.95 | H62: 250.5 | I62: 259.45 | J62: 274.7 | K62: 270.15 | L62: 278.8 | M62: 275.9 | N62: 279.5 | O62: 273.9 | P62: 270.45 | Q62: 267.3 | R62: 267.8 | S62: 219.4 | T62: 269.55 | U62: 3851.8
B63: ENGIE | C63: C.T. CHILCA 1 | D63: TG1 | E63: TERMOELÉCTRICA | F63: 269.95 | G63: 1404.75 | L63: 913.15 | M63: 513.7 | N63: 670.2 | O63: 150.2 | Q63: 13.45 | R63: 533.2 | U63: 4468.6
B64: ENGIE | C64: C.T. CHILCA 1 | D64: TG2 | E64: TERMOELÉCTRICA | F64: 912.6 | G64: 4039.75 | H64: 3915.5 | I64: 3914.85 | J64: 3904.35 | K64: 3925.05 | L64: 3929.85 | M64: 3919.6 | N64: 3910.55 | O64: 3903.45 | P64: 954.2 | Q64: 2414.45 | R64: 3820.35 | S64: 3763.5 | T64: 3829.45 | U64: 51057.5
B65: ENGIE | C65: C.T. CHILCA 1 | D65: TG3 | E65: TERMOELÉCTRICA | H65: 362 | I65: 663.85 | J65: 604.5 | K65: 874.05 | L65: 1118.5 | Q65: 2130.35 | R65: 4363.55 | S65: 4274.1 | T65: 4333.75 | U65: 18724.65
B66: ENGIE | C66: C.T. CHILCA 1 | D66: TV | E66: TERMOELÉCTRICA | F66: 264.65 | G66: 1699.25 | H66: 1634.05 | I66: 1640.25 | J66: 1639.05 | K66: 1657.15 | L66: 1650.3 | M66: 1651.15 | N66: 1634.6 | O66: 1629.5 | Q66: 1725 | R66: 4075.3 | S66: 3986.6 | T66: 4029.7 | U66: 28916.55
B67: ENGIE | C67: C.T. CHILCA 2 | D67: TG41 | E67: TERMOELÉCTRICA | F67: 158.7 | G67: 511.65 | H67: 333.5 | I67: 341.55 | U67: 1345.4
B68: ENGIE | C68: C.T. CHILCA 2 | D68: TV42 | E68: TERMOELÉCTRICA | U68: 0
B69: ENGIE | C69: C.T. NEPI | D69: TG41 | E69: TERMOELÉCTRICA | U69: 0
B70: ENGIE | C70: C.T. NEPI | D70: TG42 | E70: TERMOELÉCTRICA | U70: 0
B71: ENGIE | C71: C.T. NEPI | D71: TG43 | E71: TERMOELÉCTRICA | U71: 0
B72: ENGIE | C72: C.T. RF PLANTA ILO | D72: TG1 | E72: TERMOELÉCTRICA | U72: 0
B73: ENGIE | C73: C.T. RF PLANTA ILO | D73: TG2 | E73: TERMOELÉCTRICA | U73: 0
B74: ENGIE | C74: C.T. RF PLANTA ILO | D74: TG3 | E74: TERMOELÉCTRICA | U74: 0
B75: FENIX POWER PERÚ | C75: C.T. FENIX | D75: GT11 | E75: TERMOELÉCTRICA | F75: 540.9 | G75: 2068.35 | H75: 3811.2 | I75: 1160 | J75: 3221.5 | K75: 181.35 | N75: 2177.4925 | O75: 3600.45 | P75: 3450.25 | Q75: 3789 | R75: 3580.6 | S75: 3761.4 | T75: 3752.65 | U75: 35095.142
B76: FENIX POWER PERÚ | C76: C.T. FENIX | D76: GT12 | E76: TERMOELÉCTRICA | F76: 3349.35 | G76: 2142.9 | H76: 2465.15 | I76: 1809.2 | J76: 3719.85 | K76: 3820.7 | L76: 3603.55 | M76: 3461.8 | N76: 3852.1673 | O76: 3611.25 | P76: 3451.05 | Q76: 3793.7 | R76: 3584.4 | S76: 3769.35 | U76: 46434.417
B77: FENIX POWER PERÚ | C77: C.T. FENIX | D77: TV10 | E77: TERMOELÉCTRICA | F77: 1911.5 | G77: 906.1 | H77: 3346.85 | I77: 1152.95 | J77: 3700.35 | K77: 2137.05 | L77: 1394.6 | M77: 1680.45 | N77: 3124.3722 | O77: 4018.4 | P77: 3931.2 | Q77: 4124.05 | R77: 4001.7 | S77: 4120.5 | T77: 2006.5 | U77: 41556.572
B78: GENERACIÓN ANDINA S.A.C. | C78: C.H. 8 DE AGOSTO | D78: CENTRAL | E78: HIDROELÉCTRICA | F78: 501.9 | G78: 501.6 | H78: 501.6 | I78: 501.6 | J78: 426.3 | K78: 412.05 | L78: 502.55 | M78: 491.7 | N78: 446.9 | O78: 446.1 | P78: 499.15 | Q78: 499.6 | R78: 449.7 | S78: 417.35 | T78: 405.75 | U78: 7003.85
B79: GENERACIÓN ANDINA S.A.C. | C79: C.H. EL CARMEN | D79: CENTRAL | E79: HIDROELÉCTRICA | F79: 162.35 | G79: 157.9 | H79: 171.4 | I79: 186.45 | J79: 190.75 | K79: 185.35 | L79: 145.25 | M79: 127.55 | N79: 119.2 | O79: 133.15 | P79: 182.2 | Q79: 142.2 | R79: 124.9 | S79: 117.8 | T79: 117.05 | U79: 2263.5
B80: GENERADORA DE ENERGÍA DEL PERÚ | C80: C.H. ÁNGEL I | D80: CENTRAL | E80: HIDROELÉCTRICA | F80: 489.6 | G80: 489.6 | H80: 453.9 | I80: 489.6 | J80: 489.6 | K80: 489.6 | L80: 489.6 | M80: 479.4 | N80: 489.6 | O80: 487.1 | P80: 478.3 | Q80: 435.75 | R80: 412.95 | S80: 385.5 | T80: 361.9 | U80: 6922
B81: GENERADORA DE ENERGÍA DEL PERÚ | C81: C.H. ÁNGEL II | D81: CENTRAL | E81: HIDROELÉCTRICA | F81: 489.6 | G81: 489.6 | H81: 464.1 | I81: 489.6 | J81: 489.6 | K81: 489.6 | L81: 489.6 | M81: 481.8 | N81: 489.6 | O81: 489.6 | P81: 489.6 | Q81: 453.1 | R81: 434.9 | S81: 407 | T81: 386.45 | U81: 7033.75
B82: GENERADORA DE ENERGÍA DEL PERÚ | C82: C.H. ÁNGEL III | D82: CENTRAL | E82: HIDROELÉCTRICA | F82: 484.8 | G82: 484.8 | H82: 459.55 | I82: 484.8 | J82: 484.8 | K82: 484.8 | L82: 484.8 | M82: 472.1 | N82: 484.8 | O82: 484.8 | P82: 484.8 | Q82: 443.5 | R82: 426.95 | S82: 401.1 | T82: 382.8 | U82: 6949.2
B83: GENERADORA DE ENERGÍA DEL PERÚ | C83: C.H. LA JOYA | D83: CENTRAL | E83: HIDROELÉCTRICA | F83: 198 | G83: 188.9 | H83: 188.2 | I83: 176.6 | J83: 175.8 | K83: 187.6 | L83: 1.4 | O83: 26.35 | P83: 113.75 | Q83: 125.05 | R83: 151.8 | S83: 200.4 | T83: 189.6 | U83: 1923.45
B84: GM OPERACIONES S.A.C. | C84: CT REFINERIA TALARA | D84: TV1 REF TALARA | E84: TERMOELÉCTRICA | F84: 713 | G84: 65.7 | T84: 435.4 | U84: 1214.1
B85: GM OPERACIONES S.A.C. | C85: CT REFINERIA TALARA | D85: TV2 REF TALARA | E85: TERMOELÉCTRICA | U85: 0
B86: GR CORTARRAMA SOCIEDAD ANONIMA CERRADA | C86: C.S. MATARANI | D86: C.S. MATARANI | E86: SOLAR | F86: 295.6 | G86: 631.65 | H86: 552.5 | I86: 657.55 | J86: 575.1 | K86: 575.95 | L86: 655 | M86: 642.5 | N86: 656.05 | O86: 649.25 | P86: 638.5 | Q86: 649.55 | R86: 647.25 | S86: 576.5 | T86: 632.3 | U86: 9035.25
B87: GR PAINO SOCIEDAD ANONIMA CERRADA | C87: C.E. HUAMBOS | D87: CENTRAL | E87: EÓLICA | F87: 69.95 | G87: 74.1 | H87: 183.9 | I87: 119.35 | J87: 80.55 | K87: 65.5 | L87: 87.75 | M87: 172.9 | N87: 236.3 | O87: 321.3 | P87: 209.45 | Q87: 224.85 | R87: 283.35 | S87: 246.35 | T87: 163.2 | U87: 2538.8
B88: GR TARUCA SOCIEDAD ANONIMA CERRADA | C88: C.E. DUNA | D88: CENTRAL | E88: EÓLICA | F88: 92.8 | G88: 92.65 | H88: 243.4 | I88: 161.75 | J88: 107.5 | K88: 91.1 | L88: 131.8 | M88: 226.5 | N88: 314.65 | O88: 371.75 | P88: 314.45 | Q88: 329.2 | R88: 366.4 | S88: 320.85 | T88: 220.75 | U88: 3385.55
B89: HIDROCAÑETE S.A. | C89: C.H. IMPERIAL | D89: CENTRAL | E89: HIDROELÉCTRICA | F89: 89.4 | G89: 89.1 | H89: 85.8 | I89: 86.15 | J89: 86.25 | K89: 85.8 | L89: 88.5 | M89: 87.75 | N89: 87.4 | O89: 88.1 | P89: 87.9 | Q89: 87.95 | R89: 87.2 | S89: 76.05 | T89: 86.8 | U89: 1300.15
B90: HIDROELECTRICA HUANCHOR S.A.C. | C90: C.H. HUANCHOR | D90: CENTRAL | E90: HIDROELÉCTRICA | F90: 447.7 | G90: 448.1 | H90: 170.9 | I90: 212.8 | J90: 220.55 | K90: 225.8 | L90: 225.4 | M90: 225.25 | N90: 225.65 | O90: 224.75 | P90: 224.05 | Q90: 225.3 | R90: 225.25 | S90: 224.75 | T90: 225.5 | U90: 3751.75
B91: HUAURA POWER GROUP S.A. | C91: C.H. YARUCAYA | D91: CENTRAL | E91: HIDROELÉCTRICA | F91: 444.6 | G91: 444 | H91: 442.8 | I91: 285.1 | J91: 445.6 | K91: 446.4 | L91: 446.4 | M91: 446.4 | N91: 444.85 | O91: 436.45 | P91: 446.4 | Q91: 397.75 | R91: 444 | S91: 444 | T91: 444 | U91: 6458.75
B92: HYDRO GLOBAL PERÚ S.A.C. | C92: CH SAN GABAN III | D92: CHSAN GABAN III | E92: HIDROELÉCTRICA | J92: 676.6 | K92: 2411.2 | L92: 1645.55 | M92: 2398.15 | N92: 1702.45 | O92: 1752.85 | P92: 1441.35 | Q92: 2344.8 | R92: 1899.45 | S92: 185.8 | T92: 2400.3 | U92: 18858.5
B93: INFRAESTRUCTURAS Y ENERGIAS DEL PERU S.A.C. | C93: C.T. RF PTO MALDONADO | D93: CENTRAL | E93: TERMOELÉCTRICA | U93: 0
B94: INFRAESTRUCTURAS Y ENERGIAS DEL PERU S.A.C. | C94: C.T. RF PUCALLPA | D94: CENTRAL | E94: TERMOELÉCTRICA | F94: 1.6 | N94: 1.65 | U94: 3.25
B95: INLAND ENERGY SAC | C95: C.H. SANTA TERESA | D95: CENTRAL | E95: HIDROELÉCTRICA | F95: 2173.4 | G95: 2158.6 | H95: 2161.25 | I95: 2158.5 | J95: 2163.5 | K95: 2153.3 | L95: 2151.35 | M95: 2152.75 | N95: 2154 | O95: 2138.7 | P95: 2153.65 | Q95: 2160.3 | R95: 2158.9 | S95: 2147.4 | T95: 2159.05 | U95: 32344.65
B96: INVERSIONES SHAQSHA S.A.C. | C96: C.H. PARIAC | D96: CENTRAL | E96: HIDROELÉCTRICA | F96: 78.75 | G96: 93.5 | H96: 84.2 | I96: 92.65 | J96: 111.35 | K96: 111.6 | L96: 109.7 | M96: 108.01 | N96: 110.2 | O96: 108.6 | P96: 109.4 | Q96: 101.05 | R96: 108.7 | S96: 110.35 | T96: 110.3 | U96: 1548.36
B97: JOYA SOLAR S.A.C. | C97: C.S. SAN MARTIN SOLAR | D97: CENTRAL | E97: SOLAR | F97: 954.125 | G97: 1810.2 | H97: 1441.3 | I97: 1842.5 | J97: 1600.15 | K97: 1629.7 | L97: 1968.55 | M97: 1312.6 | N97: 1590.5 | O97: 2019.75 | P97: 651.4 | Q97: 164.6 | R97: 192.4 | S97: 1954.5 | T97: 1966.6 | U97: 21098.875
B98: KALLPA GENERACION S.A. | C98: C.H. CERRO DEL AGUILA | D98: CENTRAL | E98: HIDROELÉCTRICA | F98: 13431.75 | G98: 13414.4 | H98: 13386.95 | I98: 13277.5 | J98: 13411.8 | K98: 13445.15 | L98: 13400.2 | M98: 13441.35 | N98: 13313.3 | O98: 12158.55 | P98: 12947.45 | Q98: 13398.5 | R98: 13405.4 | S98: 13394.4 | T98: 13446.7 | U98: 199273.4
B99: KALLPA GENERACION S.A. | C99: C.T. KALLPA | D99: TG1 | E99: TERMOELÉCTRICA | F99: 3153.8 | G99: 3234.1 | H99: 3155.85 | I99: 3059.85 | J99: 3178.95 | K99: 3234.35 | L99: 3200.7 | M99: 3246.7 | N99: 2996.05 | O99: 2973.15 | P99: 2886.8 | Q99: 3042.25 | R99: 3131.05 | S99: 2901.1 | T99: 2877.65 | U99: 46272.35
B100: KALLPA GENERACION S.A. | C100: C.T. KALLPA | D100: TG2 | E100: TERMOELÉCTRICA | F100: 3153.4 | G100: 3237.9 | H100: 3167.7 | I100: 3058.3 | J100: 3188.75 | K100: 3273.25 | L100: 3202.35 | M100: 3236.95 | N100: 2994.4 | O100: 2969.2 | P100: 2898.9 | Q100: 3046.9 | R100: 3132.45 | S100: 2901.9 | T100: 2876.5 | U100: 46338.85
B101: KALLPA GENERACION S.A. | C101: C.T. KALLPA | D101: TG3 | E101: TERMOELÉCTRICA | F101: 3155.65 | G101: 3237.95 | H101: 3169.9 | I101: 3059.55 | J101: 3190.7 | K101: 3275.2 | L101: 3198.4 | M101: 3238.5 | N101: 2995.9 | O101: 2968.95 | P101: 2899.7 | Q101: 3052.75 | R101: 3131.3 | S101: 2903.75 | T101: 2877.6 | U101: 46355.8
B102: KALLPA GENERACION S.A. | C102: C.T. KALLPA | D102: TV | E102: TERMOELÉCTRICA | F102: 5501.65 | G102: 5581.05 | H102: 5524.65 | I102: 5384.6 | J102: 5490.1 | K102: 5588.5 | L102: 5538.65 | M102: 5556.8 | N102: 5344.25 | O102: 5332.2 | P102: 5251.15 | Q102: 5392.55 | R102: 5452.05 | S102: 5287.05 | T102: 5238.5 | U102: 81463.75
B103: KALLPA GENERACION S.A. | C103: C.T. LAS FLORES | D103: TG1 | E103: TERMOELÉCTRICA | F103: 4663.35 | G103: 4355.35 | H103: 4728.6 | I103: 4153.4 | J103: 4307.05 | K103: 4265.05 | L103: 4414.75 | M103: 4344.15 | N103: 18.5 | R103: 3195.45 | S103: 4923.75 | T103: 4999.3 | U103: 48368.7
...

Sheet G_AREAS
B3: jueves, 15 de Mayo del 2025
B5: HORA | C5: RESUMEN DE GENERACIÓN POR ÁREAS DEL SEIN | D5: RESUMEN DE GENERACIÓN POR ÁREAS DEL SEIN | E5: RESUMEN DE GENERACIÓN POR ÁREAS DEL SEIN | F5: RESUMEN DE GENERACIÓN POR ÁREAS DEL SEIN | G5: RESUMEN DE GENERACIÓN POR ÁREAS DEL SEIN | H5: RESUMEN DE GENERACIÓN POR ÁREAS DEL SEIN | I5: RESUMEN DE GENERACIÓN POR ÁREAS DEL SEIN | J5: RESUMEN DE GENERACIÓN POR ÁREAS DEL SEIN | K5: RESUMEN DE GENERACIÓN POR ÁREAS DEL SEIN | L5: RESUMEN DE GENERACIÓN POR ÁREAS DEL SEIN | M5: RESUMEN DE GENERACIÓN POR ÁREAS DEL SEIN | N5: RESUMEN DE GENERACIÓN POR ÁREAS DEL SEIN | O5: RESUMEN DE GENERACIÓN POR ÁREAS DEL SEIN | P5: RESUMEN DE GENERACIÓN POR ÁREAS DEL SEIN | Q5: RESUMEN DE GENERACIÓN POR ÁREAS DEL SEIN | R5: RESUMEN DE GENERACIÓN POR ÁREAS DEL SEIN | S5: HORA | T5: GENERACIÓN POR TIPO DE GENERACIÓN | U5: GENERACIÓN POR TIPO DE GENERACIÓN | V5: GENERACIÓN POR TIPO DE GENERACIÓN | W5: GENERACIÓN POR TIPO DE GENERACIÓN | X5: GENERACIÓN POR TIPO DE GENERACIÓN | Y5: HORA | Z5: GENERACIÓN POR TIPO DE GENERACIÓN | AA5: GENERACIÓN POR TIPO DE GENERACIÓN | AB5: GENERACIÓN POR TIPO DE GENERACIÓN | AC5: GENERACIÓN POR TIPO DE GENERACIÓN | AD5: GENERACIÓN POR TIPO DE GENERACIÓN
C6: NORTE | D6: NORTE | E6: NORTE | F6: NORTE | G6: CENTRO | H6: CENTRO | I6: CENTRO | J6: CENTRO | K6: SUR | L6: SUR | M6: SUR | N6: SUR | O6: GENERACIÓN INTEGRANTES COES | P6: GENERACIÓN INTEGRANTES COES | Q6: GENERACIÓN INTEGRANTES COES | R6: GENERACIÓN INTEGRANTES COES | T6: INTEGRANTES COES | U6: INTEGRANTES COES | V6: INTEGRANTES COES | W6: INTEGRANTES COES | X6: INTEGRANTES COES | Z6: INTEGRANTES COES RER | AA6: INTEGRANTES COES RER | AB6: INTEGRANTES COES RER | AC6: INTEGRANTES COES RER | AD6: INTEGRANTES COES RER
C7: GENERACIÓN HIDROELÉCTRICA NORTE | D7: GENERACIÓN TERMOELÉCTRICA NORTE | E7: GENERACIÓN SOLAR NORTE | F7: GENERACIÓN EÓLICA NORTE | G7: GENERACIÓN HIDROELÉCTRICA CENTRO | H7: GENERACIÓN TERMOELÉCTRICA CENTRO | I7: GENERACIÓN SOLAR CENTRO | J7: GENERACIÓN EÓLICA CENTRO | K7: GENERACIÓN HIDROELÉCTRICA SUR | L7: GENERACIÓN TERMOELÉCTRICA SUR | M7: GENERACIÓN SOLAR SUR | N7: GENERACIÓN EÓLICA SUR | O7: GENERACIÓN COES NORTE | P7: GENERACIÓN COES CENTRO | Q7: GENERACIÓN COES SUR | R7: TOTAL GENERACION | T7: HIDROELÉCTRICA | U7: TERMOELÉCTRICA | V7: SOLAR | W7: EÓLICA | X7: TOTAL GENERACION | Z7: HIDROELÉCTRICA RER | AA7: TERMOELÉCTRICA RER | AB7: SOLAR RER | AC7: EÓLICA RER | AD7: TOTAL RER
B8: 00:30 | C8: 437.4 | D8: 157.2 | E8: 0 | F8: 65.3 | G8: 3140.234 | H8: 1963.2 | I8: 0 | J8: 111.8 | K8: 645.2 | L8: 0 | M8: 0 | N8: 0 | O8: 659.9 | P8: 5215.234 | Q8: 645.2 | R8: 6520.334 | S8: 00:30 | T8: 4222.834 | U8: 2120.4 | V8: 0 | W8: 177.1 | X8: 6520.334 | Y8: 00:30 | Z8: 321.434 | AA8: 35.5 | AB8: 0 | AC8: 177.1 | AD8: 534.034
B9: 01:00 | C9: 438.2 | D9: 93.6 | E9: 0 | F9: 60.3 | G9: 3083.199 | H9: 1954.3 | I9: 0 | J9: 95.3 | K9: 645.5 | L9: 0 | M9: 0 | N9: 0 | O9: 592.1 | P9: 5132.799 | Q9: 645.5 | R9: 6370.399 | S9: 01:00 | T9: 4166.899 | U9: 2047.9 | V9: 0 | W9: 155.6 | X9: 6370.399 | Y9: 01:00 | Z9: 321.599 | AA9: 35 | AB9: 0 | AC9: 155.6 | AD9: 512.199
B10: 01:30 | C10: 433.8 | D10: 62.8 | E10: 0 | F10: 43.5 | G10: 3062.134 | H10: 1957.6 | I10: 0 | J10: 73 | K10: 629.5 | L10: 0 | M10: 0 | N10: 0 | O10: 540.1 | P10: 5092.734 | Q10: 629.5 | R10: 6262.334 | S10: 01:30 | T10: 4125.434 | U10: 2020.4 | V10: 0 | W10: 116.5 | X10: 6262.334 | Y10: 01:30 | Z10: 320.934 | AA10: 34.2 | AB10: 0 | AC10: 116.5 | AD10: 471.634
B11: 02:00 | C11: 437.4 | D11: 63.5 | E11: 0 | F11: 50.7 | G11: 3120.826 | H11: 1853.8 | I11: 0 | J11: 69.7 | K11: 627.9 | L11: 0 | M11: 0 | N11: 0 | O11: 551.6 | P11: 5044.326 | Q11: 627.9 | R11: 6223.826 | S11: 02:00 | T11: 4186.126 | U11: 1917.3 | V11: 0 | W11: 120.4 | X11: 6223.826 | Y11: 02:00 | Z11: 321.826 | AA11: 34.4 | AB11: 0 | AC11: 120.4 | AD11: 476.626
B12: 02:30 | C12: 442.2 | D12: 62.2 | E12: 0 | F12: 46.4 | G12: 3279.949 | H12: 1686.9 | I12: 0 | J12: 63.9 | K12: 630.7 | L12: 0 | M12: 0 | N12: 0 | O12: 550.8 | P12: 5030.749 | Q12: 630.7 | R12: 6212.249 | S12: 02:30 | T12: 4352.849 | U12: 1749.1 | V12: 0 | W12: 110.3 | X12: 6212.249 | Y12: 02:30 | Z12: 322.949 | AA12: 34.7 | AB12: 0 | AC12: 110.3 | AD12: 467.949
B13: 03:00 | C13: 438.3 | D13: 63 | E13: 0 | F13: 38.5 | G13: 3225.97 | H13: 1756.2 | I13: 0 | J13: 49.7 | K13: 624.7 | L13: 0 | M13: 0 | N13: 0 | O13: 539.8 | P13: 5031.87 | Q13: 624.7 | R13: 6196.37 | S13: 03:00 | T13: 4288.97 | U13: 1819.2 | V13: 0 | W13: 88.2 | X13: 6196.37 | Y13: 03:00 | Z13: 323.07 | AA13: 34.3 | AB13: 0 | AC13: 88.2 | AD13: 445.57
B14: 03:30 | C14: 438.9 | D14: 62.5 | E14: 0 | F14: 33.6 | G14: 3222.041 | H14: 1707.1 | I14: 0 | J14: 54.5 | K14: 633.3 | L14: 0 | M14: 0 | N14: 0 | O14: 535 | P14: 4983.641 | Q14: 633.3 | R14: 6151.941 | S14: 03:30 | T14: 4294.241 | U14: 1769.6 | V14: 0 | W14: 88.1 | X14: 6151.941 | Y14: 03:30 | Z14: 323.041 | AA14: 34.3 | AB14: 0 | AC14: 88.1 | AD14: 445.441
B15: 04:00 | C15: 435.9 | D15: 61.4 | E15: 0 | F15: 32.1 | G15: 3188.035 | H15: 1716.4 | I15: 0 | J15: 67.1 | K15: 622.5 | L15: 0 | M15: 0 | N15: 0 | O15: 529.4 | P15: 4971.535 | Q15: 622.5 | R15: 6123.435 | S15: 04:00 | T15: 4246.435 | U15: 1777.8 | V15: 0 | W15: 99.2 | X15: 6123.435 | Y15: 04:00 | Z15: 322.335 | AA15: 34.1 | AB15: 0 | AC15: 99.2 | AD15: 455.635
B16: 04:30 | C16: 437.3 | D16: 62 | E16: 0 | F16: 26.6 | G16: 3232.852 | H16: 1698 | I16: 0 | J16: 77.2 | K16: 623.7 | L16: 0 | M16: 0 | N16: 0 | O16: 525.9 | P16: 5008.052 | Q16: 623.7 | R16: 6157.652 | S16: 04:30 | T16: 4293.852 | U16: 1760 | V16: 0 | W16: 103.8 | X16: 6157.652 | Y16: 04:30 | Z16: 322.652 | AA16: 34.4 | AB16: 0 | AC16: 103.8 | AD16: 460.852
B17: 05:00 | C17: 438.2 | D17: 62.2 | E17: 0 | F17: 30.9 | G17: 3216.05 | H17: 1696 | I17: 0 | J17: 70.5 | K17: 622.7 | L17: 0 | M17: 0 | N17: 0 | O17: 531.3 | P17: 4982.55 | Q17: 622.7 | R17: 6136.55 | S17: 05:00 | T17: 4276.95 | U17: 1758.2 | V17: 0 | W17: 101.4 | X17: 6136.55 | Y17: 05:00 | Z17: 323.25 | AA17: 34.5 | AB17: 0 | AC17: 101.4 | AD17: 459.15
B18: 05:30 | C18: 444 | D18: 62.5 | E18: 0 | F18: 40.5 | G18: 3256.669 | H18: 1907 | I18: 0 | J18: 77.6 | K18: 630.5 | L18: 0 | M18: 0 | N18: 0 | O18: 547 | P18: 5241.269 | Q18: 630.5 | R18: 6418.769 | S18: 05:30 | T18: 4331.169 | U18: 1969.5 | V18: 0 | W18: 118.1 | X18: 6418.769 | Y18: 05:30 | Z18: 323.169 | AA18: 34.8 | AB18: 0 | AC18: 118.1 | AD18: 476.069
B19: 06:00 | C19: 441 | D19: 98.2 | E19: 0 | F19: 40.1 | G19: 3214.684 | H19: 1948.8 | I19: 0 | J19: 89.4 | K19: 634.1 | L19: 0 | M19: 0.8 | N19: 0 | O19: 579.3 | P19: 5252.884 | Q19: 634.9 | R19: 6467.084 | S19: 06:00 | T19: 4289.784 | U19: 2047 | V19: 0.8 | W19: 129.5 | X19: 6467.084 | Y19: 06:00 | Z19: 323.484 | AA19: 34.9 | AB19: 0.8 | AC19: 129.5 | AD19: 488.684
... B56: TOTAL MWh | C56: 10465 | D56: 3194.05 | E56: 2.9 | F56: 1220 | G56: 78873.312 | H56: 48877.95 | I56: 8.65 | J56: 5560.45 | K56: 15284.75 | L56: 16.8 | M56: 5481.9 | N56: 0 | O56: 14881.95 | P56: 133320.36 | Q56: 20783.45 | R56: 168985.76 | S56: TOTAL MWh | T56: 104623.06 | U56: 52088.8 | V56: 5493.45 | W56: 6780.45 | X56: 168985.76 | Y56: TOTAL MWh | Z56: 7689.312 | AA56: 855.5 | AB56: 5493.45 | AC56: 6780.45 | AD56: 20818.712

Sheet HOP
B3: jueves, 15 de Mayo del 2025
B5: Reporte de Horas de Operación
B6: Empresa | C6: Central | D6: Grupo | E6: Modo de Operación | F6: Inicio | G6: Final | H6: O. Arranque | I6: O. Parada | J6: Tipo Operación | K6: Ensayo de Potencia Efectiva | L6: Ensayo de Potencia Mínima | M6: Sistema | N6: Lim. Transm. | O6: Causa | P6: Observación
B7: AGRO INDUSTRIAL PARAMONGA S.A. | C7: C.T. PARAMONGA | D7: CENTRAL | E7: PARAMONGA - BAGAZO | F7: 15/05/2025 00:00:00 | G7: 16/05/2025 00:00:00 | J7: POR COGENERACION | O7: ...
B8: BIOENERGIA DEL CHIRA S.A. | C8: C.T. CAÑA BRAVA | D8: G-1 | E8: CANA BRAVA TV1 - BAGAZO | F8: 15/05/2025 00:00:00 | G8: 15/05/2025 09:49:00 | J8: POR COGENERACION | O8: ...
B9: BIOENERGIA DEL CHIRA S.A. | C9: C.T. CAÑA BRAVA | D9: CENTRAL | E9: CANA BRAVA TV1 & TV2 - BAGAZO | F9: 15/05/2025 09:49:00 | G9: 15/05/2025 20:52:00 | J9: POR COGENERACION | O9: ...
B10: BIOENERGIA DEL CHIRA S.A. | C10: C.T. CAÑA BRAVA | D10: G-1 | E10: CANA BRAVA TV1 - BAGAZO | F10: 15/05/2025 20:52:00 | G10: 16/05/2025 00:00:00 | J10: POR COGENERACION | O10: ...
B11: EGASA | C11: C.T. MOLLENDO DIESEL | D11: GD1 | E11: MOLLENDO 123 - D2 | F11: 15/05/2025 10:08:00 | G11: 15/05/2025 11:14:00 | H11: 15/05/2025 09:59:00 | J11: POR PRUEBAS | O11: ...
B12: EGASA | C12: C.T. MOLLENDO DIESEL | D12: GD3 | E12: MOLLENDO 123 - D2 | F12: 15/05/2025 12:01:00 | G12: 15/05/2025 13:18:00 | J12: POR PRUEBAS | O12: ...
B13: ELECTROPERU | C13: C.T. TUMBES | D13: MAK1 | E13: TUMBES MAK 1 - D2 | F13: 15/05/2025 00:30:00 | G13: 15/05/2025 06:14:00 | H13: 15/05/2025 00:10:00 | I13: 15/05/2025 06:10:00 | J13: A MINIMA CARGA | O13: ...
B14: ELECTROPERU | C14: C.T. TUMBES | D14: MAK2 | E14: TUMBES MAK 2 - D2 | F14: 15/05/2025 00:35:00 | G14: 15/05/2025 06:14:00 | H14: 15/05/2025 00:10:00 | I14: 15/05/2025 06:10:00 | J14: A MINIMA CARGA | O14: ...
B15: ENEL GENERACION PIURA S.A. | C15: C.T. MALACAS 1 | D15: CENTRAL | E15: MALACAS1 TG6 - GAS | F15: 15/05/2025 00:00:00 | G15: 16/05/2025 00:00:00 | J15: POR POTENCIA O ENERGIA | O15: ...
B16: ENEL GENERACION PIURA S.A. | C16: C.T. MALACAS 2 | D16: CENTRAL | E16: MALACAS2 TG4 - GAS | F16: 15/05/2025 00:00:00 | G16: 15/05/2025 00:14:00 | I16: 15/05/2025 00:08:00 | J16: A MINIMA CARGA | O16: ...
B17: ENEL GENERACION PIURA S.A. | C17: C.T. MALACAS 2 | D17: CENTRAL | E17: MALACAS2 TG4 - GAS | F17: 15/05/2025 14:19:00 | G17: 15/05/2025 15:48:00 | H17: 15/05/2025 14:01:00 | J17: A MINIMA CARGA | O17: ...
B18: ENEL GENERACION PIURA S.A. | C18: C.T. MALACAS 2 | D18: CENTRAL | E18: MALACAS2 TG4 - GAS | F18: 15/05/2025 15:48:00 | G18: 15/05/2025 16:04:00 | J18: POR POTENCIA O ENERGIA | N18: xLT | O18: ... | P18: Se subió a 30 MW
B19: ENEL GENERACION PIURA S.A. | C19: C.T. MALACAS 2 | D19: CENTRAL | E19: MALACAS2 TG4 - GAS | F19: 15/05/2025 16:04:00 | G19: 15/05/2025 18:29:00 | J19: A MINIMA CARGA | O19: ...
B20: ENEL GENERACION PIURA S.A. | C20: C.T. MALACAS 2 | D20: CENTRAL | E20: MALACAS2 TG4 - GAS | F20: 15/05/2025 18:29:00 | G20: 15/05/2025 18:58:00 | J20: POR POTENCIA O ENERGIA | N20: xLT | O20: ...
B21: ENEL GENERACION PIURA S.A. | C21: C.T. MALACAS 2 | D21: CENTRAL | E21: MALACAS2 TG4 - GAS | F21: 15/05/2025 18:59:00 | G21: 15/05/2025 19:10:00 | I21: 15/05/2025 18:59:01 | J21: A MINIMA CARGA | O21: ...
B22: ENEL GENERACION PIURA S.A. | C22: C.T. RF DE GENERACION TALARA | D22: CENTRAL | E22: MALACAS3 TG5 - D2 | F22: 15/05/2025 00:00:00 | G22: 15/05/2025 01:05:00 | H22: 15/05/2025 00:00:00 | I22: 15/05/2025 00:44:00 | J22: POR SEGURIDAD | O22: ...
B23: ENEL GENERACION PIURA S.A. | C23: C.T. RF DE GENERACION TALARA | D23: CENTRAL | E23: MALACAS3 TG5 - D2 | F23: 15/05/2025 05:53:00 | G23: 15/05/2025 14:38:00 | H23: 15/05/2025 05:29:00 | I23: 15/05/2025 14:21:00 | J23: POR SEGURIDAD | O23: ...
B24: ENEL GENERACION PIURA S.A. | C24: C.T. RF DE GENERACION TALARA | D24: CENTRAL | E24: MALACAS3 TG5 - D2 | F24: 15/05/2025 18:57:00 | G24: 15/05/2025 22:23:00 | H24: 15/05/2025 18:27:00 | I24: 15/05/2025 22:16:00 | J24: POR SEGURIDAD | O24: ...
B25: ENGIE | C25: C.T. CHILCA 1 | D25: CENTRAL | E25: CHILCA1 CCOMB TG2 & TG3 - GAS | F25: 15/05/2025 00:00:00 | G25: 15/05/2025 02:05:00 | J25: POR POTENCIA O ENERGIA | O25: ... | P25: A las 01:46 h, S/C generar a 450 MW.
B26: ENGIE | C26: C.T. CHILCA 1 | D26: CENTRAL | E26: CHILCA1 CCOMB TG2 & TG3 - GAS | F26: 15/05/2025 02:05:00 | G26: 15/05/2025 05:06:00 | J26: A MINIMA CARGA | O26: ...
B27: ENGIE | C27: C.T. CHILCA 1 | D27: CENTRAL | E27: CHILCA1 CCOMB TG2 & TG3 - GAS | F27: 15/05/2025 05:06:00 | G27: 16/05/2025 00:00:00 | J27: POR POTENCIA O ENERGIA | O27: ... | P27: A las 05:06 h, S/C generar a 400 MW. A las 05:38 h, S/C generar a máximo. A las 13:06 h, S/C generar a 400 MW. A las 14:11 h, S/C generar a 500 MW. A las 14:49 h, S/C generar a máximo.
B28: FENIX POWER PERÚ | C28: C.T. FENIX | D28: CENTRAL | E28: FENIX CCOMB GT11 & GT12 - GAS | F28: 15/05/2025 00:00:00 | G28: 15/05/2025 00:06:00 | J28: POR POTENCIA O ENERGIA | O28: ...
B29: FENIX POWER PERÚ | C29: C.T. FENIX | D29: CENTRAL | E29: FENIX CCOMB GT11 - GAS | F29: 15/05/2025 00:06:00 | G29: 15/05/2025 08:15:00 | J29: A MINIMA CARGA | O29: ...
B30: FENIX POWER PERÚ | C30: C.T. FENIX | D30: GT12 | E30: FENIX GT12 - GAS | F30: 15/05/2025 00:06:00 | G30: 15/05/2025 00:08:00 | J30: A MINIMA CARGA | O30: ... | P30: En proceso de parada.
B31: FENIX POWER PERÚ | C31: C.T. FENIX | D31: CENTRAL | E31: FENIX CCOMB GT11 - GAS | F31: 15/05/2025 08:15:00 | G31: 15/05/2025 13:03:00 | J31: POR POTENCIA O ENERGIA | O31: ...
B32: FENIX POWER PERÚ | C32: C.T. FENIX | D32: CENTRAL | E32: FENIX CCOMB GT11 - GAS | F32: 15/05/2025 13:03:00 | G32: 15/05/2025 15:13:00 | J32: A MINIMA CARGA | O32: ...
B33: FENIX POWER PERÚ | C33: C.T. FENIX | D33: CENTRAL | E33: FENIX CCOMB GT11 - GAS | F33: 15/05/2025 15:13:00 | G33: 16/05/2025 00:00:00 | J33: POR POTENCIA O ENERGIA | O33: ...
B34: GM OPERACIONES S.A.C. | C34: CT REFINERIA TALARA | D34: TV1 REF TALARA | E34: REF_TALARA TV1 - NLH_RFG | F34: 15/05/2025 10:54:00 | G34: 16/05/2025 00:00:00 | J34: POR COGENERACION | O34: ...
B35: KALLPA GENERACION S.A. | C35: C.T. KALLPA | D35: CENTRAL | E35: KALLPA CCOMB TG1 & TG2 & TG3 - GAS | F35: 15/05/2025 00:00:00 | G35: 15/05/2025 08:57:00 | J35: POR RSF | O35: ...
B36: KALLPA GENERACION S.A. | C36: C.T. KALLPA | D36: CENTRAL | E36: KALLPA CCOMB TG1 & TG2 & TG3 - GAS | F36: 15/05/2025 08:57:00 | G36: 15/05/2025 09:37:00 | J36: POR POTENCIA O ENERGIA | O36: ...
B37: KALLPA GENERACION S.A. | C37: C.T. KALLPA | D37: CENTRAL | E37: KALLPA CCOMB TG1 & TG2 & TG3 - GAS | F37: 15/05/2025 09:37:00 | G37: 15/05/2025 11:22:00 | J37: POR RSF | O37: ...
B38: KALLPA GENERACION S.A. | C38: C.T. KALLPA | D38: CENTRAL | E38: KALLPA CCOMB TG1 & TG2 & TG3 - GAS | F38: 15/05/2025 11:22:00 | G38: 15/05/2025 12:10:00 | J38: POR POTENCIA O ENERGIA | O38: ...
B39: KALLPA GENERACION S.A. | C39: C.T. KALLPA | D39: CENTRAL | E39: KALLPA CCOMB TG1 & TG2 & TG3 - GAS | F39: 15/05/2025 12:10:00 | G39: 16/05/2025 00:00:00 | J39: POR RSF | O39: ...
B40: KALLPA GENERACION S.A. | C40: C.T. LAS FLORES | D40: CENTRAL | E40: LAS FLORES CCOMB TG1 - GAS | F40: 15/05/2025 00:00:00 | G40: 16/05/2025 00:00:00 | J40: POR POTENCIA O ENERGIA | O40: ...
B41: ORYGEN PERU S.A.A. | C41: C.T. VENTANILLA | D41: CENTRAL | E41: VENTANILLA CCOMB TG3 & TG4 - GAS | F41: 15/05/2025 00:00:00 | G41: 15/05/2025 08:38:00 | J41: A MINIMA CARGA | O41: ...
B42: ORYGEN PERU S.A.A. | C42: C.T. VENTANILLA | D42: CENTRAL | E42: VENTANILLA CCOMB TG3 & TG4 - GAS | F42: 15/05/2025 08:38:00 | G42: 15/05/2025 12:45:00 | J42: POR POTENCIA O ENERGIA | O42: ...
... B47: PETRAMAS | C47: C.T. HUAYCOLORO | D47: CENTRAL | E47: HUAYCOLORO - BIOGAS | F47: 15/05/2025 00:00:00 | G47: 16/05/2025 00:00:00 | J47: POR POTENCIA O ENERGIA | O47: ...
B48: PETRAMAS | C48: C.T. LA GRINGA | D48: CENTRAL | E48: LA GRINGA V - BIOGAS | F48: 15/05/2025 13:11:00 | G48: 16/05/2025 00:00:00 | H48: 15/05/2025 13:08:00 | J48: POR POTENCIA O ENERGIA | O48: ...
B49: PETRAMAS | C49: C.T.B DOÑA CATALINA | D49: CENTRAL | E49: DONA CATALINA - BIOGAS | F49: 15/05/2025 00:00:00 | G49: 16/05/2025 00:00:00 | J49: POR POTENCIA O ENERGIA | O49: ...
B50: PETRAMAS | C50: C.T.B. CALLAO | D50: G1 CALLAO | E50: CALLAO - BIOGAS | F50: 15/05/2025 00:00:00 | G50: 15/05/2025 08:06:00 | I50: 15/05/2025 08:01:00 | J50: POR POTENCIA O ENERGIA | O50: ...
B51: PETRAMAS | C51: C.T.B. CALLAO | D51: G1 CALLAO | E51: CALLAO - BIOGAS | F51: 15/05/2025 11:42:00 | G51: 16/05/2025 00:00:00 | H51: 15/05/2025 11:40:00 | J51: POR POTENCIA O ENERGIA | O51: ...

Sheet INDISP
B3: jueves, 15 de Mayo del 2025
B5: Hora Inicio y Fin de Indisponibilidades de las Unidades de Generación SEIN
B6: Empresa | C6: Ubicación | D6: Equipo | E6: Inicio | F6: Final | G6: Descripción | H6: MW Indisp. | I6: Prog. | J6: Dispon | K6: Interrupc. | L6: Tipo | M6: CodEq | N6: TipoEq_Osinerg
B7: AGROAURORA S.A.C. | C7: MAPLE ETANOL | D7: CENTRAL | E7: 15/05/2025 00:00 | F7: 16/05/2025 00:00 | G7: MANTENIMIENTO PREVENTIVO PROGRAMADO DE LA CENTRAL TERMOELECTRICA Y EQUIPOS AUXILIARES. | H7: 17 | I7: P | J7: F/S | K7: N | L7: PREV. | M7: 13417 | N7: G
B8: AGROAURORA S.A.C. | C8: MAPLE ETANOL | D8: CENTRAL | E8: 15/05/2025 00:00 | F8: 16/05/2025 00:00 | G8: CENTRAL TERMOELECTRICA FUERA DE SERVICIO POR FALTA DE MATERIA PRIMA PARA LOS REQUERIMIENTOS DE CALOR ÚTIL EN FÁBRICA. | H8: 17 | I8: P | J8: F/S | K8: N | L8: OTROS | M8: 13417 | N8: G
B9: AGROINDUSTRIAS SAN JACINTO S.A.A. | C9: SAN JACINTO | D9: CENTRAL | E9: 15/05/2025 00:00 | F9: 16/05/2025 00:00 | G9: Mantenimiento Anual. | H9: 8.15 | I9: P | J9: F/S | K9: N | L9: PREV. | M9: 19865 | N9: G
B10: ASOCIACIÓN SANTA LUCIA DE CHACAS | C10: CH HUALLIN | D10: CENTRAL | E10: 15/05/2025 08:00 | F10: 15/05/2025 10:07 | G10: DESARENADO DE BOCATOMA | H10: 2.7 | I10: P | J10: F/S | K10: N | L10: PREV. | M10: 23678 | N10: G
B11: EGASA | C11: CHARCANI VI | D11: G1 | E11: 15/05/2025 00:00 | F11: 16/05/2025 00:00 | G11: Mantenimiento Generador | H11: 8.9 | I11: P | J11: F/S | K11: N | L11: PREV. | M11: 188 | N11: G
B12: EGASA | C12: MOLLENDO D | D12: GD1 | E12: 15/05/2025 08:32 | F12: 15/05/2025 14:30 | G12: Mantenimiento Bimensual (Incluye pruebas a plena carga). | H12: 8.4 | I12: P | J12: F/S | K12: N | L12: PREV. | M12: 177 | N12: G
B13: EMPRESA DE GENERACION HUALLAGA | C13: CHAGLLA | D13: G2 | E13: 15/05/2025 00:00 | F13: 15/05/2025 16:53 | G13: MANTENIMIENTO ANUAL UG2*********** | H13: 235 | I13: P | J13: F/S | K13: N | L13: PREV. | M13: 14972 | N13: G
B14: EMPRESA DE GENERACION HUALLAGA | C14: CHAGLLA | D14: G1 | E14: 15/05/2025 08:56 | F14: 15/05/2025 09:24 | G14: Desconexión de la unidad debido a falla que se encuentra en investigación. | H14: 227.3 | I14: F | J14: F/S | K14: N | L14: OTROS | M14: 14971 | N14: G
B15: EMPRESA DE GENERACION HUANZA | C15: HUANZA | D15: 1GER | E15: 15/05/2025 00:00 | F15: 16/05/2025 00:00 | G15: CAMBIO DE VÁLVULA ESFERICA EN GRUPO G1 | H15: 47 | I15: P | J15: F/S | K15: N | L15: PREV. | M15: 14006 | N15: G
B16: ENGIE | C16: CHILCA 2 | D16: TG41 | E16: 15/05/2025 00:00 | F16: 16/05/2025 00:00 | G16: INSPECCION BOROSCOPICA Y MANTENIMIENTO SIST AUXILIARES. CAMBIO DE FILTROS DE AIRE.CAMBIO DE TRANSFORMADOR AUXILIAR********************* | H16: 74 | I16: P | J16: F/S | K16: N | L16: PREV. | M16: 15680 | N16: G
B17: ENGIE | C17: CHILCA 2 | D17: TV42 | E17: 15/05/2025 00:00 | F17: 16/05/2025 00:00 | G17: MANTENIMIENTO ANUAL DE UNIDAD Y SISTEMAS AUXILIARES********** | H17: 38 | I17: P | J17: F/S | K17: N | L17: PREV. | M17: 16325 | N17: G
B18: ENGIE | C18: QUITARACSA | D18: CENTRAL | E18: 15/05/2025 00:00 | F18: 16/05/2025 00:00 | G18: FUERA DE SERVICIO DEBIDO A INDISPONIBILIDAD DE BOCATOMA QUITARACSA Y SAN MATEO POR CAIDA DE ROCAS EN LA ZONA. NO SE PUEDE CAPTAR AGUA. | H18: 110 | I18: P | J18: F/S | K18: N | L18: PREV. | M18: 14448 | N18: G
... B31: TERMOSELVA | C31: AGUAYTÍA | D31: TG2 | E31: 15/05/2025 00:00 | F31: 15/05/2025 10:46 | G31: CAMBIO DE MECANISMO HIDRÁULICO DEL INTERRUPTOR Y PRUEBAS ELECTRICAS TG-2. | H31: 80 | I31: P | J31: F/S | K31: N | L31: PREV. | M31: 99 | N31: G

Sheet RESERVA_FRÍA
B3: 15/05/2025 | E3: EJECUTADO | L3: Jueves 15 de Mayo del 2025 / SEM N° 19 | V3: EJECUTADO | AC3: Jueves 15 de Mayo del 2025 / SEM N° 19 | EE3: ENERGIA RENOVABLES | GP3: COGENERACION | GY3: NO INTEGRANTES
B4: Jueves | C4: HYDROG | D4: ELECTROPERU | H4: ORAZU | J4: TER | L4: KALLPA GENERACION S.A. | T4: SHOUGESA | X4: EGM | Y4: EGESUR | AB4: EGASA | AI4: SGB | AJ4: CELEP | AK4: MINCVE | AL4: ETEN | AN4: HUALLA | AP4: LAVI | AQ4: CHIN | AS4: HUANCH | AT4: CELER | AU4: INLD | AV4: FENIX POWER PERÚ | AY4: STATKRAFT S.A | BG4: STARO | BI4: HUANZA | BJ4: ENEL GENERACION PIURA S.A. | BM4: ENGIE | CA4: IYEP | CC4: SHAQSH | CD4: ORYGEN PERU S.A.A. | CP4: SAMAY I S.A.C | CT4: TCHILC | CV4: GENERACION | CY4: SALIDAS YUPANA | DC4: FLUJO EN LINEAS | DO4: COSTOS MARGINALES | DS4: RESERVA | DX4: DEMANDA POR AREAS | EE4: ACHI | EF4: COLCA | EG4: ERSUR | EH4: GRCOR | EI4: TARU | EJ4: KONDU | EK4: PIEREN | EL4: ORAZU | EN4: SGB | EO4: AIPSA | EP4: MAJA | EQ4: EGECSA | ER4: STANA | ES4: AGUAA | ET4: RDOBLE | EU4: HIDRO | EV4: HUARA | EW4: MOQUE | EX4: PANAM | EY4: PARQU | EZ4: PE3HER | FA4: PETRAMAS | FE4: TACNA | FF4: EYSAC | FG4: AURORA | FH4: AGROIN | FI4: ANDEA | FJ4: ASLC | FK4: ATRIA | FL4: EGEJUNIN | FP4: EGERBA | FQ4: EOL | FS4: ENGIE | FX4: GENE | FZ4: GENERADORA DE ENERGÍA DEL PERÚ | GD4: PAINO | GE4: JOYAS | GF4: SARCUS | GG4: ORYGEN PERU S.A.A. | GL4: RARCUS | GM4: SINERS | GP4: ACHI | GQ4: GM OP | GS4: SDF | GU4: AIPSA | GV4: AURORA | GW4: AGROIN | GY4: UNACEM | GZ4: EOR | HA4: AYEP | HB4: ELZANA | HC4: ENOSA | HD4: SDE | HE4: SINERS
C5: 65333 | D5: 101 | E5: 102 | F5: 42667 | G5: 42668 | H5: 126 | I5: 127 | J5: 138 | K5: 139 | L5: 197 | M5: 203 | N5: 204 | O5: 230 | P5: 209 | Q5: 56677 | R5: 796 | S5: 2146 | T5: 142 | U5: 143 | V5: 125 | W5: 187 | X5: 163 | Y5: 298 | Z5: 299 | AA5: 219 | AB5: 151 | AC5: 152 | AD5: 153 | AE5: 154 | AF5: 756 | AG5: 156 | AH5: 155 | AI5: 182 | AJ5: 212 | AK5: 758 | AL5: 263 | AM5: 265 | AN5: 775 | AO5: 777 | AP5: 2154 | AQ5: 150 | AR5: 149 | AS5: 188 | AT5: 2131 | AU5: 755 | AV5: 252 | AW5: 249 | AX5: 250 | AY5: 117 | AZ5: 267 | BA5: 268 | BB5: 119 | BC5: 120 | BD5: 189 | BE5: 122 | BF5: 266 | BG5: 337 | BH5: 338 | BI5: 251 | BJ5: 115 | BK5: 239 | BL5: 288 | BM5: 240 | BN5: 241 | BO5: 242 | BP5: 191 | BQ5: 194 | BR5: 196 | BS5: 207 | BT5: 236 | BU5: 795 | BV5: 285 | BW5: 995 | BX5: 996 | BY5: 997 | BZ5: 766 | CA5: 926 | CB5: 924 | CC5: 121 | CD5: 103 | CE5: 104 | CF5: 106 | CG5: 105 | CH5: 107 | CI5: 110 | CJ5: 109 | CK5: 144 | CL5: 113 | CM5: 114 | CN5: 193 | CO5: 208 | CP5: 786 | CQ5: 787 | CR5: 788 | CS5: 789 | CT5: 248 | CU5: 2159 | CV5: -1222 | CW5: -1223 | CX5: -1224 | CY5: 1221 | CZ5: 1222 | DA5: 1223 | DB5: 1224 | DC5: 1250 | DD5: 1251 | DE5: 1252 | DF5: 1253 | DG5: 1254 | DH5: 1255 | DI5: 1256 | DJ5: 1257 | DK5: 1258 | DL5: 1259 | DM5: 1260 | DN5: 1261 | DO5: 1226 | DP5: 1219 | DQ5: 1220 | DR5: -1203 | DS5: 1227 | DT5: 1205 | DU5: 1207 | DV5: 1206 | DW5: 1218 | DX5: 1211 | DY5: 1212 | DZ5: 1213 | EA5: 1214 | EB5: 1229 | EC5: -1221 | EE5: 289 | EF5: 303 | EG5: 59715 | EH5: 62255 | EI5: 1263 | EJ5: 61800 | EK5: 2194 | EL5: 216 | EM5: 198 | EN5: 49607 | EO5: 213 | EP5: 214 | EQ5: 260 | ER5: 2152 | ES5: 2128 | ET5: 247 | EU5: 228 | EV5: 2135 | EW5: 261 | EX5: 237 | EY5: 253 | EZ5: 770 | FA5: 225 | FB5: 2201 | FC5: 2171 | FD5: 760 | FE5: 235 | FF5: 238 | FG5: 232 | FH5: 2190 | FI5: 2184 | FJ5: 61855 | FK5: 223 | FL5: 226 | FM5: 201 | FN5: 258 | FO5: 259 | FP5: 920 | FQ5: 257 | FR5: 256 | FS5: 2148 | FT5: 58288 | FU5: 58289 | FV5: 58839 | FW5: 58840 | FX5: 296 | FY5: 297 | FZ5: 211 | GA5: 2175 | GB5: 2178 | GC5: 2181 | GD5: 1262 | GE5: 63425 | GF5: 233 | GG5: 2150 | GH5: 2165 | GI5: 2161 | GJ5: 61197 | GK5: 58851 | GL5: 234 | GM5: 215 | GN5: 917 | GP5: 289 | GQ5: 58333 | GR5: 58336 | GS5: 202 | GT5: 58487 | GU5: 213 | GV5: 232 | GW5: 2190 | GY5: 221 | GZ5: 222 | HA5: 224 | HB5: 2187 | HC5: 227 | HD5: 49400 | HE5: 199 | HF5: 200 | HH5: 7000 | HI5: 7001 | HJ5: 7002
