Workbook

Sheet EVENTOS
B3: martes, 21 de Enero del 2025
B5: INFORMACIÓN DE EVENTOS PRINCIPALES EN SUS INSTALACIONES
B6: TIPO DE EVENTO | C6: EMPRESA | D6: UBICACIÓN | E6: TIPO DE EQUIPO | F6: EQUIPO | G6: INICIO | H6: FINAL | I6: DESCRIPCIÓN | J6: MW INDISP. | K6: INTERRUPCIÓN (SI/NO) | L6: TENSIÓN DE FALLA (kV)
B7: FALLA | C7: ARUNTANI S.A.C. | D7: PUNO - TUCARI | E7: LINEA DE TRANSMISION | F7: L-6007 | G7: 21/01/2025 01:43:44 | H7: 21/01/2025 03:26:00 | I7: DESCONEXIÓN DE LA LÍNEA L-6007 (PUNO - TUCARI) DE 60 KV | J7: 0.51 | K7: SI | L7: 60
B8: FALLA | C8: ARUNTANI S.A.C. | D8: PUNO - TUCARI | E8: LINEA DE TRANSMISION | F8: L-6007 | G8: 21/01/2025 06:25:39 | H8: 21/01/2025 07:38:00 | I8: DESCONEXIÓN DE LA LÍNEA L-6007 (PUNO - TUCARI) DE 60 kV | J8: 0.12 | K8: SI | L8: 60
B9: EVENTO | C9: CONELSUR LT SAC | D9: PORTILLO | E9: SUBESTACION | F9: SS.EE. | G9: 21/01/2025 00:00:00 | H9: 22/01/2025 00:00:00 | I9: DECLARACIÓN DE SITUACIÓN EXCEPCIONAL EN LA S.E. PORTILLO DE 60 kV | K9: NO
B10: FALLA | C10: GENERADORA DE ENERGÍA DEL PERÚ | D10: ÁNGEL III | E10: CENTRAL HIDROELÉCTRICA | F10: CENTRAL | G10: 21/01/2025 08:16:00 | H10: 21/01/2025 08:45:00 | I10: DESCONEXIÓN DE LAS CC.HH. ÁNGEL I, II y II. | K10: NO | L10: 6.6
B11: FALLA | C11: HIDRANDINA | D11: KIMAN AYLLU - SIHUAS | E11: LINEA DE TRANSMISION | F11: L-1132 | G11: 21/01/2025 11:13:16 | H11: 21/01/2025 11:32:00 | I11: DESCONEXIÓN DE LA LÍNEA L-1132 (KIMAN AYLLU - SIHUAS) DE 138 KV | K11: SI | L11: 138
B12: FALLA | C12: MINERA BUENAVENTURA | D12: ARES - HUANCARAMA | E12: LINEA DE TRANSMISION | F12: L-6017 | G12: 21/01/2025 13:16:00 | H12: 21/01/2025 13:21:00 | I12: DESCONEXIÓN DE LA LÍNEA L-6017 (ARES - HUANCARAMA) 66 KV | K12: SI | L12: 66
B13: EVENTO | C13: RED DE ENERGIA DEL PERU S.A. | D13: TINGO MARÍA - AUCAYACU | E13: LINEA DE TRANSMISION | F13: L-1122 | G13: 21/01/2025 18:51:00 | H13: 21/01/2025 20:30:00 | I13: DECLARACIÓN DE SITUACIÓN EXCEPCIONAL EN LA LÍNEA L-1122 (TINGO MARÍA - AUCAYACU) DE 138 KV | K13: NO
B14: FALLA | C14: SAN GABAN | D14: SAN GABÁN II | E14: GENERADOR HIDROELÉCTRICO | F14: G2 | G14: 21/01/2025 09:23:00 | H14: 21/01/2025 09:29:00 | I14: DESCONEXIÓN DEL GRUPO G2 DE LA C.H. SAN GABAN II | K14: NO | L14: 13.8

Sheet RESTRIC_OPE
B3: martes, 21 de Enero del 2025
B5: RESTRICCIONES OPERATIVAS
B6: FECHA | C6: HORA INICIO | D6: HORA FINAL | E6: EMPRESA | F6: UBICACIÓN | G6: T.Eq. | H6: EQUIPO | I6: DESCRIPCIÓN
B7: 21/01/2025 | C7: 00:00 | D7: 24:00 | E7: CELEPSA | F7: C.H. EL PLATANAL | G7: CH | H7: CENTRAL | I7: Debido al incremento del caudal del rio cañete y establecimiento de la temporada de avenida, se declara la C.H. El Platanal como CENTRAL HIDRÁULICA DE PASADA (correo 03/01/2025).
B8: 21/01/2025 | C8: 00:00 | D8: 24:00 | E8: EGASA | F8: S.E. CONVERTIDOR | G8: BARRA | H8: BARRA138KV | I8: EGASA limitó la capacidad del transformador 138 kV/33 kV a 50 MVA por deterioro del aislamiento.
B9: 21/01/2025 | C9: 00:00 | D9: 24:00 | E9: ENEL GENERACION PIURA S.A. | F9: C.T. MALACAS | G9: CT | H9: CENTRAL | I9: De acuerdo con la comunicación vía correo del día 24.10.2024. ENEL GENERACIÓN PIURA informa una restricción de potencia para alcanzar 105 MW en simultaneo (TG6+TGN4).
B10: 21/01/2025 | C10: 00:00 | D10: 24:00 | E10: ENGIE | F10: C.E. PUNTA LOMITAS | G10: CE | H10: CENTRAL | I10: De acuerdo a la carta ENG/737-2024 (Exp:202400007555). Limitación de cables de media tensión a 100 MW de los transformadores PLT1 y PLT2 de la CE Punta Lomitas. Quedan limitados a 200 MW la generación de CE Punta Lomitas y Punta Lomitas Extensión.
B11: 21/01/2025 | C11: 00:00 | D11: 24:00 | E11: ENGIE | F11: C.H. QUITARACSA | G11: CH | H11: CENTRAL | I11: De acuerdo con el correo del 23.04 se considera la operación continua de la CH Quitaracsa debido a que el sistema de refrigeración de la CH Cañón del Pato se alimenta desde la descarga del caudal turbinado por la CH Quitaracsa.
B12: 21/01/2025 | C12: 00:00 | D12: 24:00 | E12: ENGIE | F12: C.H. YUNCÁN | G12: GH | H12: G3 | I12: Según la carta N° ENG/ 198-2024 enviada por su representada, se opera de forma continua el G3 de la CH Yuncán, debido a la ejecución de mantenimientos necesarios para evitar daños en los sellos de seguridad de la válvula esférica del grupo.
B13: 21/01/2025 | C13: 00:00 | D13: 24:00 | E13: ENGIE | F13: C.T. CHILCA 1 | G13: CT | H13: CENTRAL | I13: Con carta ENG/971-2023, indica que no puede cumplir con las IO considerada en el PDO_17122023 dado que vulneran la seguridad de sus activos. Indican que se debe tomar TMO=168h.
B14: 21/01/2025 | C14: 00:00 | D14: 24:00 | E14: ENGIE | F14: C.T. CHILCA 1 | G14: CT | H14: CENTRAL | I14: Restricción de temperatura de la C.T Chilca, ver valor en el modelo de despacho.
B15: 21/01/2025 | C15: 00:00 | D15: 24:00 | E15: ENGIE | F15: C.T. CHILCA 2 | G15: CT | H15: CENTRAL | I15: Restricción de temperatura de la C.T Chilca2, ver valor en el modelo de despacho.
B16: 21/01/2025 | C16: 00:00 | D16: 24:00 | E16: ENGIE | F16: C.T. CHILCA 2 | G16: CT | H16: CENTRAL | I16: Con carta ENG/971-2023, indica que no puede cumplir con las IO considerada en el PDO_17122023 dado que vulneran la seguridad de sus activos. Indican que se debe tomar TMO=168h.
B17: 21/01/2025 | C17: 00:00 | D17: 24:00 | E17: FENIX POWER PERÚ | F17: C.T. FENIX | G17: CT | H17: CENTRAL | I17: De acuerdo con el correo del 20/01/2025 a las 10:54 h: La unidad TG11 y TG12 cuentan no cuentan con arranques, en cualquiera de sus modos de operación para el día de mañana 21 de enero de 00:00h a 24:00h.
... B38: 21/01/2025 | C38: 00:00 | D38: 24:00 | E38: TRANSMANTARO | F38: S.E. SOCABAYA | G38: SSEE | H38: S.E. | I38: Opera en simple barra en 220 kV por indisponibilidad de la protección diferencial de barras por alarma.

Sheet MANTENIMIENTO EJECUTADOS
B3: martes, 21 de Enero del 2025
B5: Mantenimiento Ejecutado
B6: Empresa | C6: Ubicación | D6: Equipo | E6: Inicio | F6: Final | G6: Descripción | H6: MW Indisp. | I6: Prog. | J6: Dispon | K6: Interrupc. | L6: Tipo | M6: CodEq | N6: TipoEq_Osinerg
B7: ATLANTICA TRANSMISION SUR S.A. | C7: CHILCA-CTM | D7: INT-5261 | E7: 21/01/2025 00:00 | F7: 22/01/2025 00:00 | G7: Seccionador SBB-5261 fase S indisponible para maniobras de apertura y cierre por anomalia en tapa de tanque de compresion, el seccionador permanece cerrado y bloqueado. | H7: 0 | I7: P | J7: E/S | K7: N | L7: OTROS | M7: 13854 | N7: T
B8: ATLANTICA TRANSMISION SUR S.A. | C8: OCONA | D8: INT-5450 | E8: 21/01/2025 00:00 | F8: 22/01/2025 00:00 | G8: RESTRICCION OPERATIVA EN INTERRUPTOR INT-5450, POSICION CERRADA, REB-5450 EN SERVICIO SUMINISTRANDO LOS SS.AA. DE S.E. OCO?A | H8: 0 | I8: P | J8: E/S | K8: N | L8: OTROS | M8: 13761 | N8: T
B9: ATLANTICA TRANSMISION SUR S.A. | C9: OCONA | D9: INT-5462 | E9: 21/01/2025 00:00 | F9: 22/01/2025 00:00 | G9: Seccionador SBA-5462 fase T indisponible por problemas mecanicos, el seccionador permanece cerrado y bloqueado | H9: 0 | I9: P | J9: E/S | K9: N | L9: OTROS | M9: 13758 | N9: T
B10: ATLANTICA TRANSMISION SUR S.A. | C10: POROMA | D10: INT-5361 | E10: 21/01/2025 00:00 | F10: 22/01/2025 00:00 | G10: Seccionador SBA-5361 fase R indisponible por problemas mecanicos, el seccionador permanece cerrado y bloqueado | H10: 0 | I10: P | J10: E/S | K10: N | L10: OTROS | M10: 13746 | N10: T
B11: ATLANTICA TRANSMISION SUR S.A. | C11: POROMA | D11: REB-5350 | E11: 21/01/2025 00:00 | F11: 22/01/2025 00:00 | G11: FUERA DE SERVICIO POR FALLA EN EL EQUIPO. | H11: 0 | I11: P | J11: F/S | K11: N | L11: OTROS | M11: 13771 | N11: T
B12: ATN S.A. | C12: ISHCAYUCRO | D12: CL-2365 | E12: 21/01/2025 09:23 | F12: 21/01/2025 14:52 | G12: A solicitud de Conelsur: Tendido de Conductor ACSR y OPGW de T01 a Portico S.E. Ishcayucro. | H12: 0 | I12: P | J12: F/S | K12: N | L12: OTROS | M12: 23900 | N12: T
B13: ATRIA ENERGIA S.A.C. | C13: PURMACANA | D13: G1 | E13: 21/01/2025 00:00 | F13: 22/01/2025 00:00 | G13: OVERHAUL DE TURBINA | H13: 0.7 | I13: P | J13: F/S | K13: N | L13: PREV. | M13: 13133 | N13: G
B14: CHINANGO S.A.C. | C14: CHIMAY | D14: CENTRAL | E14: 21/01/2025 00:00 | F14: 21/01/2025 07:54 | G14: FUERA DE SERVICIO POR ACUMULACION DE SOLIDOS | H14: 0 | I14: F | J14: F/S | K14: N | L14: OTROS | M14: 1191 | N14: G
B15: CHINANGO S.A.C. | C15: CHIMAY | D15: G1 | E15: 21/01/2025 08:00 | F15: 22/01/2025 00:00 | G15: Reparacion de valvula bypass manual de VVMM | H15: 75 | I15: F | J15: F/S | K15: N | L15: CORR. | M15: 109 | N15: G
B16: CONELSUR LT SAC | C16: CAJAMARQUILLA | D16: BARRA A 220kV | E16: 21/01/2025 00:00 | F16: 21/01/2025 12:27 | G16: POR SEGURIDAD POR MANTENIMIENTO DE PORTICOS. La indisponibilidad de la Barra A culmino el dia 19.01, por motivo de apoyo de maniobras de NEXA no se pudo retornar a la configuracion normal de la subestacion. Por lo que se programo el 21.01.25 11:00hrs normalizar la configuracion. | H16: 0 | I16: P | J16: F/S | K16: N | L16: SEG.PER | M16: 1103 | N16: T
B17: CONELSUR LT SAC | C17: LOMERA | D17: BARRA A 220 kV | E17: 21/01/2025 00:00 | F17: 22/01/2025 00:00 | G17: POR REEMPLAZO DE COMPONENTES Y GAS SF6 EN CL2117. LOMERA OPERA EN BARRA SIMPLE | H17: 0 | I17: P | J17: F/S | K17: N | L17: OTROS | M17: 16951 | N17: T
B18: CONELSUR LT SAC | C18: LOMERA | D18: CL-2117 | E18: 21/01/2025 00:00 | F18: 22/01/2025 00:00 | G18: REEMPLAZO DE COMPONENTES Y GAS SF6 | H18: 0 | I18: P | J18: F/S | K18: N | L18: OTROS | M18: 14198 | N18: T
... B90: TRANSMANTARO | C90: YARABAMBA | D90: AT-104 523 | E90: 21/01/2025 00:00 | F90: 22/01/2025 00:00 | G90: NO SE TIENE MANDO REMOTO PARA CONTROLAR LOS TAPS DEL AUTOTRANSFORMADOR POR PROBLEMAS EN EL TRANSDUCTOR. LA MANIOBRA ES LOCAL Y REQUIERE AL ASISTENTE EN LA SUBESTACION PARA LAS MANIOBRAS. | H90: 0 | I90: P | J90: E/S | K90: N | L90: OTROS | M90: 17433 | N90: T

Sheet INGRESO OC
A3: martes, 21 de Enero del 2025
A5: INGRESO A OPERACIÓN COMERCIAL
A6: EMPRESA | B6: TIPO DE EQUIPO | C6: UBICACIÓN | D6: EQUIPO | E6: Fecha y hora de Ingreso a Operación Comercial

Sheet DESPACHO_EJECUTADO
B3: martes, 21 de Enero del 2025
A5: POTENCIA ACTIVA EJECUTADA DE LAS UNIDADES DE GENERACIÓN DEL SEIN (MW) | FH5: CENTRALES NO INTEGRANTES COES
A6: FECHA | B6: HORA | C6: 337 | D6: 338 | E6: 121 | F6: 101 | G6: 102 | H6: 42667 | I6: 42668 | J6: 126 | K6: 127 | L6: 138 | M6: 139 | N6: 197 | O6: 203 | P6: 204 | Q6: 230 | R6: 209 | S6: 56677 | T6: 796 | U6: 2146 | V6: 142 | W6: 143 | X6: 125 | Y6: 187 | Z6: 163 | AA6: 298 | AB6: 219 | AC6: 151 | AD6: 152 | AE6: 153 | AF6: 154 | AG6: 756 | AH6: 156 | AI6: 155 | AJ6: 182 | AK6: 212 | AL6: 758 | AM6: 263 | AN6: 265 | AO6: 775 | AP6: 777 | AQ6: 2154 | AR6: 150 | AS6: 149 | AT6: 188 | AU6: 2131 | AV6: 755 | AW6: 252 | AX6: 249 | AY6: 250 | AZ6: 117 | BA6: 267 | BB6: 268 | BC6: 119 | BD6: 120 | BE6: 189 | BF6: 122 | BG6: 266 | BH6: 251 | BI6: 115 | BJ6: 239 | BK6: 288 | BL6: 240 | BM6: 241 | BN6: 242 | BO6: 191 | BP6: 194 | BQ6: 196 | BR6: 207 | BS6: 236 | BT6: 795 | BU6: 285 | BV6: 995 | BW6: 996 | BX6: 997 | BY6: 766 | BZ6: 926 | CA6: 924 | CB6: 103 | CC6: 104 | CD6: 106 | CE6: 105 | CF6: 107 | CG6: 110 | CH6: 109 | CI6: 144 | CJ6: 113 | CK6: 114 | CL6: 193 | CM6: 208 | CN6: 786 | CO6: 787 | CP6: 788 | CQ6: 789 | CR6: 248 | CS6: 2159 | CT6: 303 | CU6: 59715 | CV6: 62255 | CW6: 1263 | CX6: 61800 | CY6: 2194 | CZ6: 216 | DA6: 198 | DB6: 214 | DC6: 260 | DD6: 2152 | DE6: 2128 | DF6: 247 | DG6: 228 | DH6: 2135 | DI6: 261 | DJ6: 237 | DK6: 253 | DL6: 770 | DM6: 225 | DN6: 2201 | DO6: 2171 | DP6: 760 | DQ6: 235 | DR6: 238 | DS6: 2184 | DT6: 61855 | DU6: 223 | DV6: 226 | DW6: 201 | DX6: 258 | DY6: 259 | DZ6: 920 | EA6: 257 | EB6: 256 | EC6: 2148 | ED6: 58288 | EE6: 58289 | EF6: 58839 | EG6: 58840 | EH6: 296 | EI6: 297 | EJ6: 211 | EK6: 2175 | EL6: 2178 | EM6: 2181 | EN6: 1262 | EO6: 233 | EP6: 2150 | EQ6: 2165 | ER6: 2161 | ES6: 61197 | ET6: 58851 | EU6: 234 | EV6: 215 | EW6: 917 | EX6: 289 | EY6: 58333 | EZ6: 58336 | FA6: 202 | FB6: 58487 | FC6: 213 | FD6: 232 | FE6: 2190 | FF6: TOTAL COES | FH6: 221 | FI6: 49607 | FJ6: 222 | FK6: 224 | FL6: 2187 | FM6: 227 | FN6: 49400 | FO6: 199 | FP6: 200 | FQ6: TOTAL NO COES
C7: CENTRO | D7: CENTRO | E7: NORTE | F7: CENTRO | G7: CENTRO | H7: NORTE | I7: NORTE | J7: NORTE | K7: NORTE | L7: CENTRO | M7: CENTRO | N7: CENTRO | O7: CENTRO | P7: CENTRO | Q7: CENTRO | R7: CENTRO | S7: CENTRO | T7: CENTRO | U7: CENTRO | V7: CENTRO | W7: CENTRO | X7: CENTRO | Y7: CENTRO | Z7: SUR | AA7: SUR | AB7: CENTRO | AC7: SUR | AD7: SUR | AE7: SUR | AF7: SUR | AG7: SUR | AH7: SUR | AI7: SUR | AJ7: SUR | AK7: CENTRO | AL7: NORTE | AM7: NORTE | AN7: NORTE | AO7: CENTRO | AP7: CENTRO | AQ7: CENTRO | AR7: CENTRO | AS7: CENTRO | AT7: CENTRO | AU7: CENTRO | AV7: SUR | AW7: CENTRO | AX7: CENTRO | AY7: CENTRO | AZ7: CENTRO | BA7: CENTRO | BB7: CENTRO | BC7: CENTRO | BD7: CENTRO | BE7: SUR | BF7: NORTE | BG7: CENTRO | BH7: CENTRO | BI7: NORTE | BJ7: NORTE | BK7: NORTE | BL7: SUR | BM7: SUR | BN7: SUR | BO7: CENTRO | BP7: CENTRO | BQ7: CENTRO | BR7: CENTRO | BS7: CENTRO | BT7: CENTRO | BU7: CENTRO | BV7: SUR | BW7: SUR | BX7: SUR | BY7: NORTE | BZ7: SUR | CA7: CENTRO | CB7: CENTRO | CC7: CENTRO | CD7: CENTRO | CE7: CENTRO | CF7: CENTRO | CG7: CENTRO | CH7: CENTRO | CI7: CENTRO | CJ7: CENTRO | CK7: CENTRO | CL7: CENTRO | CM7: CENTRO | CN7: SUR | CO7: SUR | CP7: SUR | CQ7: SUR | CR7: CENTRO | CS7: CENTRO | CT7: CENTRO | CU7: CENTRO | CV7: SUR | CW7: NORTE | CX7: NORTE | CY7: NORTE | CZ7: NORTE | DA7: NORTE | DB7: CENTRO | DC7: CENTRO | DD7: CENTRO | DE7: NORTE | DF7: NORTE | DG7: CENTRO | DH7: CENTRO | DI7: SUR | DJ7: SUR | DK7: CENTRO | DL7: CENTRO | DM7: CENTRO | DN7: CENTRO | DO7: CENTRO | DP7: CENTRO | DQ7: SUR | DR7: CENTRO | DS7: CENTRO | DT7: NORTE | DU7: CENTRO | DV7: CENTRO | DW7: NORTE | DX7: CENTRO | DY7: CENTRO | DZ7: CENTRO | EA7: NORTE | EB7: NORTE | EC7: SUR | ED7: CENTRO | EE7: CENTRO | EF7: CENTRO | EG7: CENTRO | EH7: CENTRO | EI7: CENTRO | EJ7: SUR | EK7: SUR | EL7: SUR | EM7: SUR | EN7: NORTE | EO7: SUR | EP7: SUR | EQ7: CENTRO | ER7: CENTRO | ES7: CENTRO | ET7: SUR | EU7: SUR | EV7: NORTE | EW7: CENTRO | EX7: NORTE | EY7: NORTE | EZ7: NORTE | FA7: CENTRO | FB7: CENTRO | FC7: CENTRO | FD7: NORTE | FE7: NORTE | FH7: NORTE | FI7: SUR | FJ7: CENTRO | FK7: NORTE | FL7: NORTE | FM7: NORTE | FN7: NORTE | FO7: NORTE | FP7: NORTE
C8: HIDROELÉCTRICA | D8: HIDROELÉCTRICA | E8: HIDROELÉCTRICA | F8: HIDROELÉCTRICA | G8: HIDROELÉCTRICA | H8: TERMOELÉCTRICA | I8: TERMOELÉCTRICA | J8: HIDROELÉCTRICA | K8: HIDROELÉCTRICA | L8: TERMOELÉCTRICA | M8: TERMOELÉCTRICA | N8: TERMOELÉCTRICA | O8: TERMOELÉCTRICA | P8: TERMOELÉCTRICA | Q8: TERMOELÉCTRICA | R8: TERMOELÉCTRICA | S8: TERMOELÉCTRICA | T8: HIDROELÉCTRICA | U8: HIDROELÉCTRICA | V8: TERMOELÉCTRICA | W8: TERMOELÉCTRICA | X8: TERMOELÉCTRICA | Y8: TERMOELÉCTRICA | Z8: HIDROELÉCTRICA | AA8: HIDROELÉCTRICA | AB8: TERMOELÉCTRICA | AC8: HIDROELÉCTRICA | AD8: HIDROELÉCTRICA | AE8: HIDROELÉCTRICA | AF8: HIDROELÉCTRICA | AG8: TERMOELÉCTRICA | AH8: TERMOELÉCTRICA | AI8: TERMOELÉCTRICA | AJ8: HIDROELÉCTRICA | AK8: HIDROELÉCTRICA | AL8: TERMOELÉCTRICA | AM8: TERMOELÉCTRICA | AN8: TERMOELÉCTRICA | AO8: HIDROELÉCTRICA | AP8: HIDROELÉCTRICA | AQ8: HIDROELÉCTRICA | AR8: HIDROELÉCTRICA | AS8: HIDROELÉCTRICA | AT8: HIDROELÉCTRICA | AU8: HIDROELÉCTRICA | AV8: HIDROELÉCTRICA | AW8: TERMOELÉCTRICA | AX8: TERMOELÉCTRICA | AY8: TERMOELÉCTRICA | AZ8: HIDROELÉCTRICA | BA8: HIDROELÉCTRICA | BB8: HIDROELÉCTRICA | BC8: HIDROELÉCTRICA | BD8: HIDROELÉCTRICA | BE8: HIDROELÉCTRICA | BF8: HIDROELÉCTRICA | BG8: HIDROELÉCTRICA | BH8: HIDROELÉCTRICA | BI8: TERMOELÉCTRICA | BJ8: TERMOELÉCTRICA | BK8: TERMOELÉCTRICA | BL8: TERMOELÉCTRICA | BM8: TERMOELÉCTRICA | BN8: TERMOELÉCTRICA | BO8: HIDROELÉCTRICA | BP8: TERMOELÉCTRICA | BQ8: TERMOELÉCTRICA | BR8: TERMOELÉCTRICA | BS8: TERMOELÉCTRICA | BT8: TERMOELÉCTRICA | BU8: TERMOELÉCTRICA | BV8: TERMOELÉCTRICA | BW8: TERMOELÉCTRICA | BX8: TERMOELÉCTRICA | BY8: HIDROELÉCTRICA | BZ8: TERMOELÉCTRICA | CA8: TERMOELÉCTRICA | CB8: HIDROELÉCTRICA | CC8: HIDROELÉCTRICA | CD8: HIDROELÉCTRICA | CE8: HIDROELÉCTRICA | CF8: HIDROELÉCTRICA | CG8: TERMOELÉCTRICA | CH8: TERMOELÉCTRICA | CI8: TERMOELÉCTRICA | CJ8: TERMOELÉCTRICA | CK8: TERMOELÉCTRICA | CL8: TERMOELÉCTRICA | CM8: TERMOELÉCTRICA | CN8: TERMOELÉCTRICA | CO8: TERMOELÉCTRICA | CP8: TERMOELÉCTRICA | CQ8: TERMOELÉCTRICA | CR8: TERMOELÉCTRICA | CS8: TERMOELÉCTRICA | CT8: SOLAR | CU8: EÓLICA | CV8: SOLAR | CW8: EÓLICA | CX8: SOLAR | CY8: HIDROELÉCTRICA | CZ8: HIDROELÉCTRICA | DA8: HIDROELÉCTRICA | DB8: HIDROELÉCTRICA | DC8: HIDROELÉCTRICA | DD8: HIDROELÉCTRICA | DE8: HIDROELÉCTRICA | DF8: HIDROELÉCTRICA | DG8: HIDROELÉCTRICA | DH8: HIDROELÉCTRICA | DI8: SOLAR | DJ8: SOLAR | DK8: EÓLICA | DL8: EÓLICA | DM8: TERMOELÉCTRICA | DN8: TERMOELÉCTRICA | DO8: TERMOELÉCTRICA | DP8: TERMOELÉCTRICA | DQ8: SOLAR | DR8: HIDROELÉCTRICA | DS8: HIDROELÉCTRICA | DT8: HIDROELÉCTRICA | DU8: HIDROELÉCTRICA | DV8: HIDROELÉCTRICA | DW8: HIDROELÉCTRICA | DX8: HIDROELÉCTRICA | DY8: HIDROELÉCTRICA | DZ8: HIDROELÉCTRICA | EA8: EÓLICA | EB8: EÓLICA | EC8: SOLAR | ED8: EÓLICA | EE8: EÓLICA | EF8: EÓLICA | EG8: EÓLICA | EH8: HIDROELÉCTRICA | EI8: HIDROELÉCTRICA | EJ8: HIDROELÉCTRICA | EK8: HIDROELÉCTRICA | EL8: HIDROELÉCTRICA | EM8: HIDROELÉCTRICA | EN8: EÓLICA | EO8: SOLAR | EP8: SOLAR | EQ8: HIDROELÉCTRICA | ER8: EÓLICA | ES8: EÓLICA | ET8: SOLAR | EU8: SOLAR | EV8: HIDROELÉCTRICA | EW8: HIDROELÉCTRICA | EX8: TERMOELÉCTRICA | EY8: TERMOELÉCTRICA | EZ8: TERMOELÉCTRICA | FA8: TERMOELÉCTRICA | FB8: TERMOELÉCTRICA | FC8: TERMOELÉCTRICA | FD8: TERMOELÉCTRICA | FE8: TERMOELÉCTRICA | FH8: HIDROELÉCTRICA | FI8: HIDROELÉCTRICA | FJ8: HIDROELÉCTRICA | FK8: HIDROELÉCTRICA | FL8: HIDROELÉCTRICA | FM8: TERMOELÉCTRICA | FN8: TERMOELÉCTRICA | FO8: HIDROELÉCTRICA | FP8: HIDROELÉCTRICA
C9: CENTRALES SANTA ROSA S.A.C. | D9: CENTRALES SANTA ROSA S.A.C. | E9: INVERSIONES SHAQSHA S.A.C. | F9: ELECTROPERU | G9: ELECTROPERU | H9: ELECTROPERU | I9: ELECTROPERU | J9: ORAZUL ENERGY PERÚ | K9: ORAZUL ENERGY PERÚ | L9: TERMOSELVA | M9: TERMOSELVA | N9: KALLPA GENERACION S.A. | O9: KALLPA GENERACION S.A. | P9: KALLPA GENERACION S.A. | Q9: KALLPA GENERACION S.A. | R9: KALLPA GENERACION S.A. | S9: KALLPA GENERACION S.A. | T9: KALLPA GENERACION S.A. | U9: KALLPA GENERACION S.A. | V9: SHOUGESA | W9: SHOUGESA | X9: SHOUGESA | Y9: SHOUGESA | Z9: EGEMSA | AA9: EGESUR | AB9: EGESUR | AC9: EGASA | AD9: EGASA | AE9: EGASA | AF9: EGASA | AG9: EGASA | AH9: EGASA | AI9: EGASA | AJ9: SAN GABAN | AK9: CELEPSA | AL9: MINERA CERRO VERDE | AM9: PLANTA DE RESERVA FRIA DE GENERACION DE ETEN S.A. | AN9: PLANTA DE RESERVA FRIA DE GENERACION DE ETEN S.A. | AO9: EMPRESA DE GENERACION HUALLAGA | AP9: EMPRESA DE GENERACION HUALLAGA | AQ9: LA VIRGEN | AR9: CHINANGO S.A.C. | AS9: CHINANGO S.A.C. | AT9: HIDROELECTRICA HUANCHOR S.A.C. | AU9: CELEPSA RENOVABLES S.R.L. | AV9: INLAND ENERGY SAC | AW9: FENIX POWER PERÚ | AX9: FENIX POWER PERÚ | AY9: FENIX POWER PERÚ | AZ9: STATKRAFT S.A | BA9: STATKRAFT S.A | BB9: STATKRAFT S.A | BC9: STATKRAFT S.A | BD9: STATKRAFT S.A | BE9: STATKRAFT S.A | BF9: STATKRAFT S.A | BG9: STATKRAFT S.A | BH9: EMPRESA DE GENERACION HUANZA | BI9: ENEL GENERACION PIURA S.A. | BJ9: ENEL GENERACION PIURA S.A. | BK9: ENEL GENERACION PIURA S.A. | BL9: ENGIE | BM9: ENGIE | BN9: ENGIE | BO9: ENGIE | BP9: ENGIE | BQ9: ENGIE | BR9: ENGIE | BS9: ENGIE | BT9: ENGIE | BU9: ENGIE | BV9: ENGIE | BW9: ENGIE | BX9: ENGIE | BY9: ENGIE | BZ9: INFRAESTRUCTURAS Y ENERGIAS DEL PERU S.A.C. | CA9: INFRAESTRUCTURAS Y ENERGIAS DEL PERU S.A.C. | CB9: ORYGEN PERU S.A.A. | CC9: ORYGEN PERU S.A.A. | CD9: ORYGEN PERU S.A.A. | CE9: ORYGEN PERU S.A.A. | CF9: ORYGEN PERU S.A.A. | CG9: ORYGEN PERU S.A.A. | CH9: ORYGEN PERU S.A.A. | CI9: ORYGEN PERU S.A.A. | CJ9: ORYGEN PERU S.A.A. | CK9: ORYGEN PERU S.A.A. | CL9: ORYGEN PERU S.A.A. | CM9: ORYGEN PERU S.A.A. | CN9: SAMAY I S.A.C | CO9: SAMAY I S.A.C | CP9: SAMAY I S.A.C | CQ9: SAMAY I S.A.C | CR9: TERMOCHILCA S.A.C. | CS9: TERMOCHILCA S.A.C. | CT9: COLCA SOLAR S.A.C. | CU9: ENERGIA RENOVABLE DEL SUR S.A. | CV9: GR CORTARRAMA SOCIEDAD ANONIMA CERRADA | CW9: GR TARUCA SOCIEDAD ANONIMA CERRADA | CX9: KONDU SAC | CY9: PERUANA DE INVERSIONES EN ENERGIAS RENOVABLES S.A. | CZ9: ORAZUL ENERGY PERÚ | DA9: ORAZUL ENERGY PERÚ | DB9: MAJA ENERGIA S.A.C. | DC9: EMPRESA DE GENERACION ELECTRICA CANCHAYLLO SAC | DD9: EMPRESA DE GENERACION ELECTRICA SANTA ANA S.A.C. | DE9: EMPRESA ELECTRICA AGUA AZUL | DF9: EMPRESA ELECTRICA RIO DOBLE | DG9: HIDROCAÑETE S.A. | DH9: HUAURA POWER GROUP S.A. | DI9: MOQUEGUA FV S.A.C. | DJ9: PANAMERICANA SOLAR SAC. | DK9: PARQUE EOLICO MARCONA S.A.C. | DL9: PARQUE EOLICO TRES HERMANAS S.A.C. | DM9: PETRAMAS | DN9: PETRAMAS | DO9: PETRAMAS | DP9: PETRAMAS | DQ9: TACNA SOLAR SAC. | DR9: ELECTRICA YANAPAMPA SAC | DS9: ANDEAN POWER S.A.C. | DT9: ASOCIACIÓN SANTA LUCIA DE CHACAS | DU9: ATRIA ENERGIA S.A.C. | DV9: EGEJUNIN | DW9: EGEJUNIN | DX9: EGEJUNIN | DY9: EGEJUNIN | DZ9: EMPRESA DE GENERACION ELECTRICA RIO BAÑOS S.A.C. | EA9: ENERGÍA EÓLICA S.A. | EB9: ENERGÍA EÓLICA S.A. | EC9: ENGIE | ED9: ENGIE | EE9: ENGIE | EF9: ENGIE | EG9: ENGIE | EH9: GENERACIÓN ANDINA S.A.C. | EI9: GENERACIÓN ANDINA S.A.C. | EJ9: GENERADORA DE ENERGÍA DEL PERÚ | EK9: GENERADORA DE ENERGÍA DEL PERÚ | EL9: GENERADORA DE ENERGÍA DEL PERÚ | EM9: GENERADORA DE ENERGÍA DEL PERÚ | EN9: GR PAINO SOCIEDAD ANONIMA CERRADA | EO9: MAJES ARCUS S.A.C. | EP9: ORYGEN PERU S.A.A. | EQ9: ORYGEN PERU S.A.A. | ER9: ORYGEN PERU S.A.A. | ES9: ORYGEN PERU S.A.A. | ET9: ORYGEN PERU S.A.A. | EU9: REPARTICIÓN ARCUS S.A.C. | EV9: SINERSA | EW9: SINERSA | EX9: BIOENERGIA DEL CHIRA S.A. | EY9: GM OPERACIONES S.A.C. | EZ9: GM OPERACIONES S.A.C. | FA9: SDF ENERGIA SAC | FB9: SDF ENERGIA SAC | FC9: AGRO INDUSTRIAL PARAMONGA S.A. | FD9: AGROAURORA S.A.C. | FE9: AGROINDUSTRIAS SAN JACINTO S.A.A. | FH9: UNACEM PERU S.A. | FI9: SAN GABAN | FJ9: ELECTRO ORIENTE | FK9: AGUAS Y ENERGIA PERU | FL9: ELECTRO ZAÑA S.A.C. | FM9: ELECTRONOROESTE S.A. | FN9: SDE PIURA | FO9: SINERSA | FP9: SINERSA
C10: SANTA ROSA 1 | D10: SANTA ROSA 2 | E10: PARIAC | F10: MANTARO | G10: RESTITUCION | H10: TUMBES MAK 1 | I10: TUMBES MAK 2 | J10: CARHUAQUERO | K10: CAÑON DEL PATO | L10: AGUAYTIA TG1 | M10: AGUAYTIA TG2 | N10: KALLPA TG1 | O10: KALLPA TG2 | P10: KALLPA TG3 | Q10: KALLPA TV | R10: LFLORES TG1 | S10: LFLORES TV | T10: CERRO DEL AGUILA | U10: CERRODELAGUILAG4 | V10: SHOUGESA TV1 | W10: SHOUGESA TV2 | X10: SHOUGESA TV3 | Y10: SHOUGESA CUMMINS | Z10: MACHUPICCHU | AA10: ARICOTA 1 | AB10: INDEPENDENCIA | AC10: CHARCANI I,II,III | AD10: CHARCANI IV | AE10: CHARCANI V | AF10: CHARCANI VI | AG10: CHILINA TG | AH10: MOLLENDO 1, 2, 3 | AI10: CHILINA (SULZ 1,2) | AJ10: SAN GABAN II | AK10: PLATANAL | AL10: RECKA | AM10: RF ETEN TG1 | AN10: RF ETEN TG2 | AO10: CHAGLLA GP1 | AP10: CHAGLLA | AQ10: LA VIRGEN | AR10: CHIMAY | AS10: YANANGO | AT10: HUANCHOR | AU10: MARAÑON | AV10: STA TERESA | AW10: FENIX GT11 | AX10: FENIX GT12 | AY10: FENIX TV10 | AZ10: YAUPI | BA10: OROYA | BB10: PACHACHACA | BC10: MALPASO | BD10: CAHUA | BE10: ARCATA | BF10: GALLITO CIEGO | BG10: CHEVES | BH10: HUANZA | BI10: MALACAS2 TG4 | BJ10: MALACAS3 TG 5 | BK10: MALACAS1 TG6 | BL10: RF ILO2 TG1 | BM10: RF ILO2 TG2 | BN10: RF ILO2 TG3 | BO10: YUNCAN | BP10: CHILCA1 TG1 | BQ10: CHILCA1 TG2 | BR10: CHILCA1 TG3 | BS10: CHILCA-TV | BT10: CHILCA2 TG41 | BU10: CHILCA2-TV | BV10: CTNEPI_TG41 | BW10: CTNEPI_TG42 | BX10: CTNEPI_TG43 | BY10: QUITARACSA | BZ10: RF PTO MALDONADO | CA10: RF PUCALLPA | CB10: HUINCO | CC10: MATUCANA | CD10: MOYOPAMPA | CE10: CALLAHUANCA | CF10: HUAMPANI | CG10: STA ROSA WEST TG7 | CH10: UTI_5 | CI10: UTI_6 | CJ10: VENTANILLA 3 | CK10: VENTANILLA 4 | CL10: VENTANILLA TV | CM10: STAROSA TG8 | CN10: PTO_BRVO TG1 | CO10: PTO_BRVO TG2 | CP10: PTO_BRVO TG3 | CQ10: PTO_BRVO TG4 | CR10: OLLEROS TG1 | CS10: OLLEROS TV | CT10: CS YARUCAYA | CU10: SAN JUAN | CV10: MATARANI | CW10: DUNA | CX10: CARHUAQUERO (CS) | CY10: MANTA I | CZ10: CARHUAQUERO4 | DA10: CAÑA BRAVA | DB10: RONCADOR | DC10: CANCHAYLLO | DD10: RENOVANDESH1 | DE10: POTRERO | DF10: PIZARRAS | DG10: NIMPERIAL | DH10: YARUCAYA | DI10: MOQUEGUA-SOLAR | DJ10: PANAMERICANA-SOLAR | DK10: PQE-EOLICO-MARCONA | DL10: PQE-EOLICO-3-HERMANAS | DM10: HUAYCOLORO | DN10: CALLAO | DO10: DONA_CATALINA | DP10: LAGRINGAV | DQ10: TACNA-SOLAR | DR10: YANAPAMPA | DS10: CARHUAC | DT10: HUALLIN | DU10: PURMACANA | DV10: HUASAHUASI | DW10: STACRUZ_1_2 | DX10: RUNATULLO_II | DY10: RUNATULLO_III | DZ10: RUCUY | EA10: PQE-EOLICO-TALARA | EB10: PQE-EOLICO-CUPISNIQUE | EC10: INTIPAMPA | ED10: PUNTA LOMITAS-BL1 | EE10: PUNTA LOMITAS-BL2 | EF10: PUN LOMITAS_EXP-BL1 | EG10: PUN LOMITAS_EXP-BL2 | EH10: 8AGOSTO | EI10: EL CARMEN | EJ10: LA JOYA | EK10: ANGEL_I | EL10: ANGEL_II | EM10: ANGEL_III | EN10: HUAMBOS | EO10: MAJES | EP10: RUBI | EQ10: CH_HER1 | ER10: WAYRA-I | ES10: WAYRA EXTENSION | ET10: CLEMESI | EU10: REPARTICION | EV10: POECHOS2 | EW10: CHANCAY | EX10: CANA BRAVA | EY10: REFINERIA TALARA TV1 | EZ10: REFINERÍA TALARA TV2 | FA10: OQUENDO TG1 | FB10: OQUENDO TV1 | FC10: PARAMONGA | FD10: MAPLE | FE10: SAN_JACINTO | FF10: MW | FH10: CARPAPATA | FI10: TUPURI | FJ10: CENTRALES ELOR | FK10: PIAS1 | FL10: ZANA | FM10: TABLAZO | FN10: TALLANCA | FO10: CURUMUY | FP10: POECHOS1 | FQ10: MW
A11: 21/01/2025 | B11: 00:30 | C11: 1.1 | D11: 1.6 | E11: 4.3 | F11: 585.6 | G11: 196.6 | J11: 88.2 | K11: 237.3 | N11: 116.8 | O11: 116.6 | P11: 117.3 | Q11: 224 | R11: 205.7 | S11: 108.7 | T11: 545.9 | U11: 10.3 | Z11: 160.2 | AA11: 7 | AB11: 0 | AC11: 6.8 | AD11: 5 | AE11: 75.9 | AF11: 8.6 | AJ11: 109.2 | AK11: 222.9 | AO11: 6.5 | AP11: 409.4 | AQ11: 70.9 | AR11: 0 | AS11: 41 | AT11: 18.4 | AU11: 19.8 | AV11: 89.7 | AW11: 177 | AX11: 177.2 | AY11: 182.8 | AZ11: 108.1 | BA11: 7.7 | BB11: 9 | BC11: 34.7 | BD11: 46.1 | BE11: 3.8 | BF11: 31.3 | BG11: 152.1 | BH11: 20.4 | BK11: 47.6 | BO11: 116 | BQ11: 0 | BT11: 0 | BY11: 56.2 | CB11: 48.8 | CC11: 122.8 | CD11: 61.9 | CE11: 81.1 | CF11: 30 | CJ11: 145.2 | CK11: 144.3 | CL11: 147.8 | CT11: 0 | CU11: 67.4 | CV11: 0 | CW11: 0 | CX11: 0 | CY11: 20 | CZ11: 9.9 | DA11: 5.3 | DB11: 3.6 | DC11: 5 | DD11: 19.8 | DE11: 20 | DF11: 18.75 | DG11: 3.5 | DH11: 18.7 | DI11: 0 | DJ11: 0 | DK11: 17.2 | DL11: 43.1 | DM11: 4.7 | DN11: 2.4 | DO11: 2.4 | DP11: 2.9 | DQ11: 0 | DR11: 3.5 | DS11: 12.3 | DT11: 2 | DV11: 14.5 | DW11: 9.1 | DX11: 19.9 | DY11: 20.3 | DZ11: 20 | EA11: 24.8 | EB11: 38.6 | EC11: 0 | ED11: 45.7 | EE11: 66.4 | EF11: 3.8 | EG11: 1.9 | EH11: 21 | EI11: 7.2 | EJ11: 7.6 | EK11: 20 | EL11: 20 | EM11: 10 | EN11: 0 | EO11: 0 | EP11: 0 | EQ11: 0.6 | ER11: 30 | ES11: 35.3 | ET11: 0 | EU11: 0 | EV11: 5.5 | EW11: 20 | EX11: 10.5 | EY11: 14.9 | EZ11: 35.4 | FA11: 29.1 | FB11: 3.3 | FC11: 14 | FD11: 17.6 | FE11: 8.4 | FF11: 6621.05 | FH11: 24.02809 | FI11: 1.3 | FJ11: 5.86 | FK11: 6.13025 | FL11: 7.8 | FN11: 18.91607 | FO11: 4.6 | FP11: 4.2 | FQ11: 72.83441
A12: 21/01/2025 | B12: 01:00 | C12: 1.1 | D12: 1.6 | E12: 4.3 | F12: 599.4 | G12: 199.1 | J12: 90.3 | K12: 239.3 | N12: 107.8 | O12: 107.8 | P12: 108.3 | Q12: 209.4 | R12: 205.8 | S12: 109.4 | T12: 560.5 | U12: 10.6 | Z12: 167 | AA12: 7.8 | AB12: 0 | AC12: 6.8 | AD12: 5 | AE12: 77.7 | AF12: 8.8 | AJ12: 111.2 | AK12: 221.5 | AO12: 6.5 | AP12: 373.1 | AQ12: 80.8 | AR12: 0 | AS12: 42.1 | AT12: 18.3 | AU12: 19.8 | AV12: 93.2 | AW12: 179.8 | AX12: 180.6 | AY12: 183.3 | AZ12: 108.8 | BA12: 7.6 | BB12: 9 | BC12: 35.9 | BD12: 47.2 | BE12: 3.8 | BF12: 31.5 | BG12: 154.1 | BH12: 21.7 | BK12: 47.3 | BO12: 118 | BQ12: 0 | BT12: 0 | BY12: 57.1 | CB12: 68.6 | CC12: 122.9 | CD12: 63.6 | CE12: 81.6 | CF12: 30.5 | CJ12: 144.8 | CK12: 143.8 | CL12: 148.1 | CT12: 0 | CU12: 66.6 | CV12: 0 | CW12: 0 | CX12: 0 | CY12: 20 | CZ12: 9.9 | DA12: 5.4 | DB12: 3.6 | DC12: 5.2 | DD12: 20.3 | DE12: 20 | DF12: 18.7 | DG12: 3.5 | DH12: 18.7 | DI12: 0 | DJ12: 0 | DK12: 15.8 | DL12: 41.1 | DM12: 4.7 | DN12: 2.4 | DO12: 2.4 | DP12: 2.9 | DQ12: 0 | DR12: 3.5 | DS12: 7.2 | DT12: 2 | DV12: 14.6 | DW12: 9.1 | DX12: 20.1 | DY12: 20.3 | DZ12: 19.8 | EA12: 25 | EB12: 30.4 | EC12: 0 | ED12: 44.5 | EE12: 56.8 | EF12: 6.4 | EG12: 2.5 | EH12: 21 | EI12: 7.2 | EJ12: 7.6 | EK12: 20 | EL12: 20 | EM12: 10 | EN12: 0 | EO12: 0 | EP12: 0 | EQ12: 0.6 | ER12: 33.8 | ES12: 30.3 | ET12: 0 | EU12: 0 | EV12: 5.5 | EW12: 19.8 | EX12: 9.9 | EY12: 14.9 | EZ12: 35.8 | FA12: 29.2 | FB12: 3.3 | FC12: 14.1 | FD12: 17.2 | FE12: 8.1 | FF12: 6615.6 | FH12: 23.96628 | FI12: 1.3 | FJ12: 5.216 | FK12: 6.12975 | FL12: 7.8 | FN12: 18.91522 | FO12: 4.6 | FP12: 4.1 | FQ12: 72.02725
A13: 21/01/2025 | B13: 01:30 | C13: 1.1 | D13: 1.6 | E13: 4.3 | F13: 589.5 | G13: 197.9 | J13: 87.6 | K13: 239.1 | N13: 107.5 | O13: 107.8 | P13: 107.6 | Q13: 207.7 | R13: 207.1 | S13: 108.8 | T13: 540 | U13: 10.2 | Z13: 163.2 | AA13: 7 | AB13: 0 | AC13: 6.8 | AD13: 5 | AE13: 75.3 | AF13: 8.1 | AJ13: 109 | AK13: 221.4 | AO13: 6.5 | AP13: 363.5 | AQ13: 80.8 | AR13: 0 | AS13: 40.8 | AT13: 18.3 | AU13: 19.8 | AV13: 88.1 | AW13: 146.8 | AX13: 147 | AY13: 167.8 | AZ13: 107.6 | BA13: 7.7 | BB13: 9 | BC13: 34.5 | BD13: 45.9 | BE13: 3.8 | BF13: 31.3 | BG13: 151 | BH13: 20.1 | BK13: 47.4 | BO13: 115.7 | BQ13: 0 | BT13: 0 | BY13: 55.9 | CB13: 46.8 | CC13: 114.2 | CD13: 61.6 | CE13: 80.4 | CF13: 29.9 | CJ13: 144.5 | CK13: 143.8 | CL13: 148.1 | CT13: 0 | CU13: 73 | CV13: 0 | CW13: 0.1 | CX13: 0 | CY13: 20 | CZ13: 9.9 | DA13: 5.3 | DB13: 3.7 | DC13: 5.2 | DD13: 19.7 | DE13: 20 | DF13: 18.64 | DG13: 3.4 | DH13: 18.7 | DI13: 0 | DJ13: 0 | DK13: 17.4 | DL13: 48.2 | DM13: 4.7 | DN13: 2.4 | DO13: 2.4 | DP13: 2.9 | DQ13: 0 | DR13: 3.5 | DS13: 7.1 | DT13: 2 | DV13: 14.5 | DW13: 9.2 | DX13: 19.5 | DY13: 20.1 | DZ13: 19.8 | EA13: 25.2 | EB13: 29.8 | EC13: 0 | ED13: 32.3 | EE13: 51.7 | EF13: 2 | EG13: 1.2 | EH13: 20.9 | EI13: 7.1 | EJ13: 7.6 | EK13: 20 | EL13: 20 | EM13: 10 | EN13: 0 | EO13: 0 | EP13: 0 | EQ13: 0.6 | ER13: 27.6 | ES13: 26.5 | ET13: 0 | EU13: 0 | EV13: 5.5 | EW13: 19.8 | EX13: 10 | EY13: 14.9 | EZ13: 36.2 | FA13: 29.2 | FB13: 3.3 | FC13: 14.3 | FD13: 17.2 | FE13: 8.4 | FF13: 6404.84 | FH13: 24.00742 | FI13: 1.3 | FJ13: 5.202 | FK13: 6.13 | FL13: 7.8 | FN13: 18.9142 | FO13: 4.7 | FP13: 4.1 | FQ13: 72.15362
A14: 21/01/2025 | B14: 02:00 | C14: 1.1 | D14: 1.6 | E14: 4.3 | F14: 598.4 | G14: 200.2 | J14: 90.1 | K14: 239.4 | N14: 107.7 | O14: 107.8 | P14: 107.5 | Q14: 207.5 | R14: 205.7 | S14: 109.1 | T14: 556.6 | U14: 10.5 | Z14: 166 | AA14: 7.9 | AB14: 0 | AC14: 6.8 | AD14: 5 | AE14: 40.2 | AF14: 8.1 | AJ14: 110.9 | AK14: 223 | AO14: 6.5 | AP14: 416.9 | AQ14: 25.3 | AR14: 0 | AS14: 42 | AT14: 18.4 | AU14: 19.8 | AV14: 87.7 | AW14: 130.4 | AX14: 130.7 | AY14: 155.8 | AZ14: 108.7 | BA14: 7.6 | BB14: 9 | BC14: 35.9 | BD14: 46.8 | BE14: 3.8 | BF14: 31.3 | BG14: 153.8 | BH14: 21.5 | BK14: 47.2 | BO14: 118 | BQ14: 0 | BT14: 0 | BY14: 57 | CB14: 65.5 | CC14: 126.7 | CD14: 63.3 | CE14: 81.4 | CF14: 30.4 | CJ14: 144.7 | CK14: 144 | CL14: 147.9 | CT14: 0 | CU14: 70.6 | CV14: 0 | CW14: 0 | CX14: 0 | CY14: 20 | CZ14: 9.9 | DA14: 5.4 | DB14: 3.7 | DC14: 5.2 | DD14: 20.2 | DE14: 20 | DF14: 18.29 | DG14: 3.5 | DH14: 18.7 | DI14: 0 | DJ14: 0 | DK14: 17.1 | DL14: 41.2 | DM14: 4.7 | DN14: 2.4 | DO14: 2.4 | DP14: 2.9 | DQ14: 0 | DR14: 3.5 | DS14: 7.1 | DT14: 2 | DV14: 14.6 | DW14: 9.3 | DX14: 19.4 | DY14: 20.3 | DZ14: 19.8 | EA14: 23.3 | EB14: 31 | EC14: 0 | ED14: 37.7 | EE14: 54 | EF14: 3 | EG14: 1.3 | EH14: 20.9 | EI14: 7 | EJ14: 7.9 | EK14: 20 | EL14: 20 | EM14: 10 | EN14: 0 | EO14: 0 | EP14: 0 | EQ14: 0.6 | ER14: 39.6 | ES14: 36 | ET14: 0 | EU14: 0 | EV14: 5.6 | EW14: 19.8 | EX14: 10.3 | EY14: 15 | EZ14: 35.6 | FA14: 29.2 | FB14: 3.4 | FC14: 14.6 | FD14: 17.4 | FE14: 7.7 | FF14: 6426.49 | FH14: 24.14923 | FI14: 1.3 | FJ14: 5.193 | FK14: 6.12975 | FL14: 7.8 | FN14: 18.91412 | FO14: 4.8 | FP14: 4.1 | FQ14: 72.3861
A15: 21/01/2025 | B15: 02:30 | C15: 1.1 | D15: 1.6 | E15: 4.3 | F15: 599.1 | G15: 199.8 | J15: 90.1 | K15: 239.2 | N15: 108.2 | O15: 108.2 | P15: 109 | Q15: 208.5 | R15: 205.4 | S15: 108.6 | T15: 559.8 | U15: 10.5 | Z15: 163.9 | AA15: 7.9 | AB15: 0 | AC15: 6.8 | AD15: 5 | AE15: 40.4 | AF15: 7.9 | AJ15: 110.9 | AK15: 159.3 | AO15: 6.5 | AP15: 465.9 | AQ15: 69 | AR15: 0 | AS15: 42 | AT15: 18.4 | AU15: 19.8 | AV15: 89.8 | AW15: 143.7 | AX15: 144.1 | AY15: 161.3 | AZ15: 108.7 | BA15: 7.2 | BB15: 8.9 | BC15: 43.9 | BD15: 47 | BE15: 3.8 | BF15: 31.5 | BG15: 95.2 | BH15: 7.9 | BK15: 47.6 | BO15: 118 | BQ15: 0 | BT15: 0 | BY15: 16.2 | CB15: 40.9 | CC15: 131.1 | CD15: 63.6 | CE15: 81.5 | CF15: 30.4 | CJ15: 145.7 | CK15: 144.9 | CL15: 148.3 | CT15: 0 | CU15: 77.7 | CV15: 0 | CW15: 0 | CX15: 0 | CY15: 20 | CZ15: 9.9 | DA15: 5.2 | DB15: 3.6 | DC15: 5.2 | DD15: 20.3 | DE15: 20 | DF15: 18.35 | DG15: 3.5 | DH15: 18.7 | DI15: 0 | DJ15: 0 | DK15: 19.6 | DL15: 42.9 | DM15: 4.7 | DN15: 2.4 | DO15: 2.4 | DP15: 2.9 | DQ15: 0 | DR15: 3.5 | DS15: 7.1 | DT15: 2 | DV15: 14.5 | DW15: 9.2 | DX15: 19.3 | DY15: 20.3 | DZ15: 19.8 | EA15: 23.4 | EB15: 23.3 | EC15: 0 | ED15: 52.1 | EE15: 55.9 | EF15: 2 | EG15: 1 | EH15: 21 | EI15: 7 | EJ15: 7.9 | EK15: 20 | EL15: 20 | EM15: 10 | EN15: 0 | EO15: 0 | EP15: 0 | EQ15: 0.6 | ER15: 43.5 | ES15: 40.2 | ET15: 0 | EU15: 0 | EV15: 5.5 | EW15: 19.8 | EX15: 10.1 | EY15: 15 | EZ15: 35.9 | FA15: 29.1 | FB15: 3.3 | FC15: 13.8 | FD15: 17.6 | FE15: 8 | FF15: 6397.35 | FH15: 24.13155 | FI15: 1.3 | FJ15: 5.083 | FK15: 6.1305 | FL15: 7.8 | FN15: 18.91392 | FO15: 4.8 | FP15: 4.1 | FQ15: 72.25897
A16: 21/01/2025 | B16: 03:00 | C16: 1.1 | D16: 1.6 | E16: 4.3 | F16: 602.9 | G16: 200.2 | J16: 89.9 | K16: 240.9 | N16: 108 | O16: 105.8 | P16: 110 | Q16: 208 | R16: 205.9 | S16: 109.2 | T16: 564.6 | U16: 10.5 | Z16: 168.1 | AA16: 8.5 | AB16: 0 | AC16: 6.8 | AD16: 5 | AE16: 40.7 | AF16: 4.7 | AJ16: 111.2 | AK16: 164.2 | AO16: 6.5 | AP16: 468.9 | AQ16: 81.6 | AR16: 0 | AS16: 42.2 | AT16: 18.4 | AU16: 19.8 | AV16: 93.1 | AW16: 60.8 | AX16: 120.3 | AY16: 148.4 | AZ16: 109.5 | BA16: 7.2 | BB16: 9 | BC16: 43.6 | BD16: 47.8 | BE16: 3.8 | BF16: 31.4 | BG16: 96.4 | BH16: 8.6 | BK16: 47.2 | BO16: 118.6 | BQ16: 0 | BT16: 0 | BY16: 16.4 | CB16: 44.3 | CC16: 131.5 | CD16: 65.9 | CE16: 81.8 | CF16: 30.7 | CJ16: 145.6 | CK16: 144.7 | CL16: 148 | CT16: 0 | CU16: 83.1 | CV16: 0 | CW16: 0 | CX16: 0 | CY16: 20 | CZ16: 9.9 | DA16: 5.3 | DB16: 3.7 | DC16: 5.2 | DD16: 20.6 | DE16: 20 | DF16: 18.34 | DG16: 3.5 | DH16: 18.7 | DI16: 0 | DJ16: 0 | DK16: 18.9 | DL16: 49.7 | DM16: 4.7 | DN16: 2.4 | DO16: 2.4 | DP16: 2.9 | DQ16: 0 | DR16: 3.5 | DS16: 4 | DT16: 2 | DV16: 14.6 | DW16: 9.2 | DX16: 19.3 | DY16: 20.3 | DZ16: 19.8 | EA16: 26 | EB16: 19.9 | EC16: 0 | ED16: 38.1 | EE16: 54.2 | EF16: 4.7 | EG16: 1.1 | EH16: 21 | EI16: 6.9 | EJ16: 7.9 | EK16: 20 | EL16: 20 | EM16: 10 | EN16: 0 | EO16: 0 | EP16: 0 | EQ16: 0.6 | ER16: 47 | ES16: 32 | ET16: 0 | EU16: 0 | EV16: 5.5 | EW16: 19.8 | EX16: 10.1 | EY16: 15.1 | EZ16: 35.7 | FA16: 29.1 | FB16: 3.3 | FC16: 14.5 | FD16: 17.6 | FE16: 7.1 | FF16: 6313.34 | FH16: 24.13608 | FI16: 1.3 | FJ16: 5.094 | FK16: 6.13025 | FL16: 7.8 | FN16: 18.91372 | FO16: 4.9 | FP16: 4.2 | FQ16: 72.47405
A17: 21/01/2025 | B17: 03:30 | C17: 1.1 | D17: 1.6 | E17: 4.3 | F17: 598.3 | G17: 197.4 | J17: 87.2 | K17: 238.3 | N17: 128.8 | O17: 129.1 | P17: 128.2 | Q17: 236.4 | R17: 206.9 | S17: 109.1 | T17: 563.1 | U17: 10.3 | Z17: 166.5 | AA17: 7.4 | AB17: 0 | AC17: 6.8 | AD17: 5 | AE17: 40.8 | AF17: 6.1 | AJ17: 110.2 | AK17: 220 | AO17: 6.5 | AP17: 388.6 | AQ17: 81.6 | AR17: 0 | AS17: 42.1 | AT17: 18.2 | AU17: 19.8 | AV17: 92.2 | AW17: 121 | AX17: 116 | AY17: 68.2 | AZ17: 108.9 | BA17: 7.2 | BB17: 8.9 | BC17: 41.8 | BD17: 46.6 | BE17: 3.8 | BF17: 31.7 | BG17: 93.7 | BH17: 6.4 | BK17: 47.6 | BO17: 116.7 | BQ17: 0 | BT17: 0 | BY17: 15.4 | CB17: 46 | CC17: 121.7 | CD17: 64.3 | CE17: 80.9 | CF17: 30 | CJ17: 145.6 | CK17: 144.8 | CL17: 147.9 | CT17: 0 | CU17: 85.7 | CV17: 0 | CW17: 0 | CX17: 0 | CY17: 20 | CZ17: 9.8 | DA17: 5.4 | DB17: 3.7 | DC17: 5.2 | DD17: 20 | DE17: 20 | DF17: 18.34 | DG17: 3.5 | DH17: 18.7 | DI17: 0 | DJ17: 0 | DK17: 22.6 | DL17: 54.8 | DM17: 4.7 | DN17: 2.4 | DO17: 2.4 | DP17: 2.9 | DQ17: 0 | DR17: 3.6 | DS17: 6 | DT17: 2 | DV17: 14.6 | DW17: 9.2 | DX17: 19.4 | DY17: 20.2 | DZ17: 19.8 | EA17: 24 | EB17: 19.8 | EC17: 0 | ED17: 57.5 | EE17: 71 | EF17: 2.9 | EG17: 2.8 | EH17: 21 | EI17: 6.8 | EJ17: 7.6 | EK17: 20 | EL17: 20 | EM17: 10 | EN17: 0 | EO17: 0 | EP17: 0 | EQ17: 0.6 | ER17: 42 | ES17: 27.6 | ET17: 0 | EU17: 0 | EV17: 5.6 | EW17: 19.9 | EX17: 10 | EY17: 15 | EZ17: 35.8 | FA17: 29.2 | FB17: 3.3 | FC17: 14.3 | FD17: 16.3 | FE17: 6.7 | FF17: 6351.64 | FH17: 24.12149 | FI17: 1.3 | FJ17: 5.105 | FK17: 6.1305 | FL17: 7.8 | FN17: 18.90809 | FO17: 4.8 | FP17: 4.2 | FQ17: 72.36508
A18: 21/01/2025 | B18: 04:00 | C18: 1.1 | D18: 1.6 | E18: 4.3 | F18: 604.9 | G18: 199.2 | J18: 90.7 | K18: 241.4 | N18: 131.7 | O18: 130.8 | P18: 131.9 | Q18: 230 | R18: 208.8 | S18: 108.7 | T18: 570.6 | U18: 10.5 | Z18: 173.1 | AA18: 8.3 | AB18: 0 | AC18: 6.8 | AD18: 5 | AE18: 41.6 | AF18: 6.1 | AJ18: 111.3 | AK18: 222.2 | AO18: 6.5 | AP18: 362.7 | AQ18: 81.8 | AR18: 0 | AS18: 42.2 | AT18: 18.3 | AU18: 19.8 | AV18: 93.8 | AW18: 127.7 | AX18: 128.5 | AY18: 0 | AZ18: 110.3 | BA18: 7.2 | BB18: 9 | BC18: 44.5 | BD18: 47.9 | BE18: 3.8 | BF18: 31.1 | BG18: 97.7 | BH18: 7.5 | BK18: 47.6 | BO18: 118.8 | BQ18: 0 | BT18: 0 | BY18: 17 | CB18: 49.7 | CC18: 123.1 | CD18: 66.2 | CE18: 82 | CF18: 30.8 | CJ18: 146.3 | CK18: 145.5 | CL18: 148.9 | CT18: 0 | CU18: 85.4 | CV18: 0 | CW18: 0 | CX18: 0 | CY18: 20 | CZ18: 9.9 | DA18: 5.4 | DB18: 3.7 | DC18: 5.2 | DD18: 20.7 | DE18: 20 | DF18: 18.32 | DG18: 3.5 | DH18: 18.7 | DI18: 0 | DJ18: 0 | DK18: 23.9 | DL18: 58.7 | DM18: 4.7 | DN18: 2.4 | DO18: 2.4 | DP18: 2.9 | DQ18: 0 | DR18: 3.5 | DS18: 3.7 | DT18: 2 | DV18: 14.6 | DW18: 9.2 | DX18: 19.2 | DY18: 20.3 | DZ18: 20 | EA18: 21.2 | EB18: 26.4 | EC18: 0 | ED18: 65.1 | EE18: 76.5 | EF18: 4.6 | EG18: 3.5 | EH18: 21 | EI18: 6.7 | EJ18: 7.8 | EK18: 20 | EL18: 20 | EM18: 10 | EN18: 0 | EO18: 0 | EP18: 0 | EQ18: 0.6 | ER18: 36 | ES18: 26.3 | ET18: 0 | EU18: 0 | EV18: 5.5 | EW18: 20 | EX18: 9.6 | EY18: 14.9 | EZ18: 35.5 | FA18: 29.3 | FB18: 3.2 | FC18: 14.3 | FD18: 16.1 | FE18: 7.7 | FF18: 6356.92 | FH18: 24.07265 | FI18: 1.3 | FJ18: 5.104 | FK18: 6.1325 | FL18: 7.8 | FN18: 18.91289 | FO18: 4.9 | FP18: 4.1 | FQ18: 72.32204
A19: 21/01/2025 | B19: 04:30 | C19: 1.1 | D19: 1.6 | E19: 4.3 | F19: 596.2 | G19: 200.9 | J19: 88.3 | K19: 238.6 | N19: 131 | O19: 130.2 | P19: 131.1 | Q19: 230.7 | R19: 208 | S19: 109.6 | T19: 557.7 | U19: 10.3 | Z19: 163.6 | AA19: 6.9 | AB19: 0 | AC19: 6.8 | AD19: 5 | AE19: 40.5 | AF19: 6.3 | AJ19: 109.7 | AK19: 223.4 | AO19: 6.5 | AP19: 443.8 | AQ19: 81.9 | AR19: 0 | AS19: 41.4 | AT19: 18.4 | AU19: 19.9 | AV19: 89.2 | AW19: 122.9 | AX19: 123.4 | AY19: 0 | AZ19: 105.7 | BA19: 7.2 | BB19: 9 | BC19: 41.6 | BD19: 46.5 | BE19: 3.8 | BF19: 31.6 | BG19: 93.4 | BH19: 5.7 | BK19: 47.7 | BO19: 117.1 | BQ19: 0 | BT19: 0 | BY19: 15.5 | CB19: 74.1 | CC19: 128.4 | CD19: 64 | CE19: 80 | CF19: 29.9 | CJ19: 146.6 | CK19: 145.5 | CL19: 148.8 | CT19: 0 | CU19: 83.8 | CV19: 0 | CW19: 1.4 | CX19: 0 | CY19: 20 | CZ19: 9.8 | DA19: 5.5 | DB19: 3.6 | DC19: 5.2 | DD19: 19.8 | DE19: 20 | DF19: 18.37 | DG19: 3.5 | DH19: 18.7 | DI19: 0 | DJ19: 0 | DK19: 23.7 | DL19: 57.5 | DM19: 4.7 | DN19: 2.4 | DO19: 2.4 | DP19: 2.9 | DQ19: 0 | DR19: 3.5 | DS19: 3.2 | DT19: 2 | DV19: 14.6 | DW19: 9.2 | DX19: 19 | DY19: 20.2 | DZ19: 20 | EA19: 23.8 | EB19: 32.1 | EC19: 0 | ED19: 72.9 | EE19: 83.9 | EF19: 3.8 | EG19: 3.3 | EH19: 21 | EI19: 6.6 | EJ19: 7.9 | EK19: 20 | EL19: 20 | EM19: 10 | EN19: 0.1 | EO19: 0 | EP19: 0 | EQ19: 0.6 | ER19: 61.2 | ES19: 44.3 | ET19: 0 | EU19: 0 | EV19: 5.6 | EW19: 20 | EX19: 9.8 | EY19: 15.3 | EZ19: 36 | FA19: 29.3 | FB19: 3.3 | FC19: 14.3 | FD19: 15.5 | FE19: 8.2 | FF19: 6455.07 | FH19: 24.12588 | FI19: 1.3 | FJ19: 3.317 | FK19: 6.13175 | FL19: 7.8 | FN19: 18.91284 | FO19: 4.8 | FP19: 4.1 | FQ19: 70.48747
A20: 21/01/2025 | B20: 05:00 | C20: 1.1 | D20: 1.6 | E20: 4.3 | F20: 599.2 | G20: 201.2 | J20: 90.9 | K20: 239.8 | N20: 129.8 | O20: 129.2 | P20: 129 | Q20: 230.2 | R20: 208.2 | S20: 109.2 | T20: 558.7 | U20: 10.5 | Z20: 166.7 | AA20: 7.7 | AB20: 0 | AC20: 6.8 | AD20: 5 | AE20: 40.9 | AF20: 6.2 | AJ20: 111.2 | AK20: 223.3 | AO20: 6.5 | AP20: 450.7 | AQ20: 81.6 | AR20: 0 | AS20: 42 | AT20: 18.4 | AU20: 19.8 | AV20: 87.2 | AW20: 126.8 | AX20: 126.8 | AY20: 0 | AZ20: 108.2 | BA20: 7.2 | BB20: 9 | BC20: 43.9 | BD20: 47 | BE20: 3.8 | BF20: 30.5 | BG20: 95.6 | BH20: 6.7 | BK20: 47.6 | BO20: 118.5 | BQ20: 0 | BT20: 0 | BY20: 16.4 | CB20: 86.4 | CC20: 131.1 | CD20: 65.1 | CE20: 80.3 | CF20: 30.5 | CJ20: 144.9 | CK20: 144.3 | CL20: 147.4 | CT20: 0 | CU20: 83.4 | CV20: 0 | CW20: 1.3 | CX20: 0 | CY20: 20 | CZ20: 9.9 | DA20: 5.5 | DB20: 3.7 | DC20: 5.2 | DD20: 20.3 | DE20: 20 | DF20: 18.38 | DG20: 3.5 | DH20: 18.7 | DI20: 0 | DJ20: 0 | DK20: 22.8 | DL20: 54.7 | DM20: 4.7 | DN20: 2.4 | DO20: 2.4 | DP20: 3 | DQ20: 0 | DR20: 3.5 | DS20: 3.4 | DT20: 2 | DV20: 15 | DW20: 9.1 | DX20: 19 | DY20: 20.2 | DZ20: 20 | EA20: 25.1 | EB20: 22.9 | EC20: 0 | ED20: 66.9 | EE20: 88.1 | EF20: 4.7 | EG20: 3.7 | EH20: 21 | EI20: 6.6 | EJ20: 8 | EK20: 20 | EL20: 20 | EM20: 10 | EN20: 0 | EO20: 0 | EP20: 0 | EQ20: 0.6 | ER20: 62.4 | ES20: 41.2 | ET20: 0 | EU20: 0 | EV20: 5.4 | EW20: 20 | EX20: 9.6 | EY20: 14.9 | EZ20: 35.5 | FA20: 29.3 | FB20: 3.3 | FC20: 14.3 | FD20: 16.5 | FE20: 7.9 | FF20: 6484.88 | FH20: 24.10548 | FI20: 1.3 | FJ20: 3.43 | FK20: 6.13125 | FL20: 7.8 | FN20: 18.91221 | FO20: 4.7 | FP20: 4.1 | FQ20: 70.47894
A21: 21/01/2025 | B21: 05:30 | C21: 1.1 | D21: 1.6 | E21: 4.3 | F21: 602.1 | G21: 203.7 | J21: 91.8 | K21: 241.2 | N21: 175.4 | O21: 185.1 | P21: 184.6 | Q21: 273.1 | R21: 207.3 | S21: 108.8 | T21: 561.4 | U21: 10.7 | Z21: 168.3 | AA21: 8 | AB21: 0 | AC21: 6.8 | AD21: 5 | AE21: 40.7 | AF21: 5.9 | AJ21: 111.1 | AK21: 224 | AO21: 6.5 | AP21: 302.8 | AQ21: 81.8 | AR21: 0 | AS21: 42.2 | AT21: 18.4 | AU21: 19.8 | AV21: 88.7 | AW21: 148.5 | AX21: 86.1 | AY21: 0 | AZ21: 111 | BA21: 7.4 | BB21: 9 | BC21: 45.7 | BD21: 47.4 | BE21: 3.8 | BF21: 31 | BG21: 96.6 | BH21: 7.1 | BK21: 47.1 | BO21: 118.8 | BQ21: 0 | BT21: 0 | BY21: 16.8 | CB21: 46.4 | CC21: 133.6 | CD21: 65.2 | CE21: 80.6 | CF21: 30.7 | CJ21: 145.1 | CK21: 144.4 | CL21: 147.9 | CT21: 0 | CU21: 81.7 | CV21: 0 | CW21: 2.1 | CX21: 0 | CY21: 20 | CZ21: 10 | DA21: 5.5 | DB21: 3.6 | DC21: 5.2 | DD21: 20.5 | DE21: 20 | DF21: 18.35 | DG21: 3.4 | DH21: 18.7 | DI21: 0.3 | DJ21: 0.1 | DK21: 21.7 | DL21: 60.7 | DM21: 4.7 | DN21: 2.4 | DO21: 2.4 | DP21: 3 | DQ21: 0.7 | DR21: 3.6 | DS21: 3.4 | DT21: 2 | DV21: 15.6 | DW21: 9 | DX21: 19.1 | DY21: 20.2 | DZ21: 20 | EA21: 26.9 | EB21: 18.9 | EC21: 0 | ED21: 63.2 | EE21: 89.2 | EF21: 3.4 | EG21: 2.8 | EH21: 21 | EI21: 6.3 | EJ21: 8.1 | EK21: 20 | EL21: 20 | EM21: 10 | EN21: 0.3 | EO21: 0 | EP21: 0 | EQ21: 0.6 | ER21: 76.1 | ES21: 60.3 | ET21: 0.1 | EU21: 0 | EV21: 5.4 | EW21: 20 | EX21: 8 | EY21: 15.1 | EZ21: 35.7 | FA21: 29.4 | FB21: 3.3 | FC21: 14.5 | FD21: 17.5 | FE21: 8.6 | FF21: 6535.05 | FH21: 24.1065 | FI21: 1.3 | FJ21: 2.964 | FK21: 6.13325 | FL21: 7.8 | FN21: 18.91132 | FO21: 4.8 | FP21: 4.1 | FQ21: 70.11507
A22: 21/01/2025 | B22: 06:00 | C22: 1 | D22: 1.6 | E22: 4.3 | F22: 603.4 | G22: 200.2 | J22: 90.1 | K22: 240 | N22: 175.8 | O22: 201 | P22: 200.8 | Q22: 273.6 | R22: 208.7 | S22: 108.7 | T22: 566.2 | U22: 10.6 | Z22: 162.7 | AA22: 8.3 | AB22: 0 | AC22: 6.8 | AD22: 5 | AE22: 40.7 | AF22: 6 | AJ22: 111 | AK22: 223.6 | AO22: 6.5 | AP22: 307.7 | AQ22: 78.9 | AR22: 0 | AS22: 42.1 | AT22: 18.4 | AU22: 19.8 | AV22: 93.7 | AW22: 180 | AX22: 45.9 | AY22: 0 | AZ22: 110.7 | BA22: 7.7 | BB22: 9 | BC22: 44.6 | BD22: 47.2 | BE22: 3.8 | BF22: 31.2 | BG22: 96.5 | BH22: 6.8 | BK22: 47.5 | BO22: 118.2 | BQ22: 0 | BT22: 0 | BY22: 16.4 | CB22: 52 | CC22: 133.5 | CD22: 64.5 | CE22: 81.6 | CF22: 30.6 | CJ22: 145.6 | CK22: 145.1 | CL22: 148.8 | CT22: 0 | CU22: 69 | CV22: 1.6 | CW22: 0.9 | CX22: 0 | CY22: 20 | CZ22: 9.9 | DA22: 5.3 | DB22: 3.6 | DC22: 5.2 | DD22: 20.5 | DE22: 20 | DF22: 18.37 | DG22: 3.4 | DH22: 18.7 | DI22: 1.2 | DJ22: 0.9 | DK22: 20.3 | DL22: 56.1 | DM22: 4.7 | DN22: 2.4 | DO22: 2.4 | DP22: 3 | DQ22: 2.5 | DR22: 3.6 | DS22: 3.3 | DT22: 2 | DV22: 15.5 | DW22: 9.1 | DX22: 19.4 | DY22: 20.2 | DZ22: 20 | EA22: 28 | EB22: 13.4 | EC22: 2.5 | ED22: 64.5 | EE22: 85.2 | EF22: 3.7 | EG22: 3.4 | EH22: 21 | EI22: 6.2 | EJ22: 8 | EK22: 20 | EL22: 20 | EM22: 10 | EN22: 0 | EO22: 0 | EP22: 2.5 | EQ22: 0.6 | ER22: 66.1 | ES22: 50.7 | ET22: 2.4 | EU22: 0 | EV22: 5.5 | EW22: 20 | EX22: 10 | EY22: 15.1 | EZ22: 35.4 | FA22: 29.4 | FB22: 3.2 | FC22: 14.5 | FD22: 17.2 | FE22: 8.6 | FF22: 6534.57 | FH22: 24.1531 | FI22: 1.3 | FJ22: 2.949 | FK22: 6.13175 | FL22: 7.8 | FN22: 18.91062 | FO22: 4.8 | FP22: 4.1 | FQ22: 70.14447
... A58: 22/01/2025 | B58: 00:00 | C58: 1 | D58: 1.6 | E58: 4.3 | F58: 650.2 | G58: 220.5 | J58: 90.7 | K58: 239.3 | N58: 141.4 | O58: 142.1 | P58: 141.2 | Q58: 235.7 | R58: 204.3 | S58: 108.4 | T58: 563.7 | U58: 10.5 | Z58: 164.9 | AA58: 8.2 | AB58: 0 | AC58: 6.9 | AD58: 5.1 | AE58: 80.8 | AF58: 8.4 | AJ58: 111.4 | AK58: 222.4 | AO58: 6.5 | AP58: 461.2 | AQ58: 78.8 | AR58: 67.9 | AS58: 42 | AT58: 18.4 | AU58: 19.8 | AV58: 96.7 | AW58: 168.5 | AX58: 169.3 | AY58: 182.1 | AZ58: 109 | BA58: 7.9 | BB58: 2.1 | BC58: 44.4 | BD58: 47.3 | BE58: 3.8 | BF58: 31.6 | BG58: 95.1 | BH58: 46.3 | BK58: 47.3 | BO58: 131.5 | BQ58: 0 | BT58: 0 | BY58: 73 | CB58: 42 | CC58: 132.9 | CD58: 63.7 | CE58: 81.2 | CF58: 30.7 | CJ58: 144.6 | CK58: 144 | CL58: 147.7 | CT58: 0 | CU58: 64.9 | CV58: 0 | CW58: 4.8 | CX58: 0 | CY58: 20 | CZ58: 9.9 | DA58: 5.4 | DB58: 3.6 | DC58: 5.2 | DD58: 20.5 | DE58: 20 | DF58: 17.77 | DG58: 3.4 | DH58: 18.7 | DI58: 0 | DJ58: 0 | DK58: 19.3 | DL58: 51.3 | DM58: 4.7 | DN58: 2.4 | DO58: 2.4 | DP58: 2.9 | DQ58: 0 | DR58: 3.6 | DS58: 12.8 | DT58: 2 | DV58: 15.4 | DW58: 8.4 | DX58: 19.9 | DY58: 20.3 | DZ58: 19.9 | EA58: 11.6 | EB58: 42.8 | EC58: 0 | ED58: 43.8 | EE58: 68.9 | EF58: 2.2 | EG58: 1.2 | EH58: 21 | EI58: 6 | EJ58: 7.8 | EK58: 20 | EL58: 20 | EM58: 10 | EN58: 2.1 | EO58: 0 | EP58: 0 | EQ58: 0.6 | ER58: 0.8 | ES58: 1.6 | ET58: 0 | EU58: 0 | EV58: 6 | EW58: 19.9 | EX58: 9.9 | EY58: 14.9 | EZ58: 36 | FA58: 29 | FB58: 3.4 | FC58: 13.6 | FD58: 17.2 | FE58: 7.9 | FF58: 6897.97 | FH58: 24.04072 | FI58: 1.3 | FJ58: 8.005 | FK58: 6.12425 | FL58: 7.8 | FN58: 18.91156 | FO58: 5.7 | FP58: 16 | FQ58: 87.88153
A59: EJEC | C59: 24.55 | D59: 38.1 | E59: 103.2 | F59: 15205.1 | G59: 5134.35 | H59: 0 | I59: 0 | J59: 2158.4 | K59: 5732.3 | L59: 0 | M59: 0 | N59: 3614.3 | O59: 3653.5 | P59: 3657.35 | Q59: 5958.9 | R59: 4897.25 | S59: 2597 | T59: 13401.7 | U59: 252.05 | V59: 0 | W59: 0 | X59: 0 | Y59: 0 | Z59: 3984.45 | AA59: 183.15 | AB59: 240.85 | AC59: 163.9 | AD59: 121.15 | AE59: 1801.45 | AF59: 170.8 | AG59: 0 | AH59: 0 | AI59: 0 | AJ59: 1997.45 | AK59: 5275.15 | AL59: 0 | AM59: 0 | AN59: 0 | AO59: 156 | AP59: 10536.25 | AQ59: 1846.6 | AR59: 1126.4 | AS59: 1000.85 | AT59: 440.75 | AU59: 475.45 | AV59: 2176.85 | AW59: 4003.8 | AX59: 3690.9 | AY59: 3372 | AZ59: 2609.25 | BA59: 188.95 | BB59: 151.45 | BC59: 1031.2 | BD59: 1126.05 | BE59: 89.3 | BF59: 751.25 | BG59: 3138.85 | BH59: 1069.2 | BI59: 0 | BJ59: 0 | BK59: 1126.05 | BL59: 0 | BM59: 0 | BN59: 0 | BO59: 3070.9 | BP59: 0 | BQ59: 1818.95 | BR59: 0 | BS59: 0 | BT59: 164.9 | BU59: 0 | BV59: 0 | BW59: 0 | BX59: 0 | BY59: 1733.2 | BZ59: 0 | CA59: 0 | CB59: 2761.7 | CC59: 3090.35 | CD59: 1524.95 | CE59: 1943.4 | CF59: 731.45 | CG59: 0 | CH59: 0 | CI59: 0 | CJ59: 3458.35 | CK59: 3436.6 | CL59: 3538 | CM59: 0 | CN59: 0 | CO59: 0 | CP59: 0 | CQ59: 0 | CR59: 0 | CS59: 0 | CT59: 5.05 | CU59: 2080.4 | CV59: 503.9 | CW59: 59.75 | CX59: 1.95 | CY59: 479.85 | CZ59: 237.75 | DA59: 128.55 | DB59: 86.15 | DC59: 124.05 | DD59: 484.55 | DE59: 479.95 | DF59: 437.035 | DG59: 82.6 | DH59: 448.8 | DI59: 100.9 | DJ59: 122.1 | DK59: 521.2 | DL59: 1462.8 | DM59: 110.9 | DN59: 56.1 | DO59: 57.4 | DP59: 67.6 | DQ59: 145.5 | DR59: 85.15 | DS59: 285.4 | DT59: 46.25 | DU59: 0 | DV59: 360.7 | DW59: 206.35 | DX59: 476.9 | DY59: 485.45 | DZ59: 478.85 | EA59: 443.55 | EB59: 1002.6 | EC59: 240 | ED59: 1457.65 | EE59: 1766.25 | EF59: 147.15 | EG59: 129.35 | EH59: 503.9 | EI59: 160.6 | EJ59: 192.4 | EK59: 450 | EL59: 437.5 | EM59: 222.25 | EN59: 42.55 | EO59: 102.7 | EP59: 1109.4 | EQ59: 14.4 | ER59: 1362.25 | ES59: 1269.7 | ET59: 922.55 | EU59: 117.9 | EV59: 140.1 | EW59: 479 | EX59: 240.15 | EY59: 359.15 | EZ59: 857.2 | FA59: 694.1 | FB59: 82.3 | FC59: 331.15 | FD59: 408.2 | FE59: 159.85 | FF59: 174302.29 | FH59: 578.7329 | FI59: 31.2 | FJ59: 129.6705 | FK59: 139.174 | FL59: 185.7 | FM59: 0 | FN59: 451.25068 | FO59: 118.8 | FP59: 187.9 | FQ59: 1822.4281

Sheet REACTIVA
B3: martes, 21 de Enero del 2025
A5: POTENCIA REACTIVA EJECUTADA DE LAS UNIDADES DE GENERACIÓN DEL COES (MVAR) | FH5: CENTRALES NO INTEGRANTES COES
A6: FECHA | B6: HORA | C6: 337 | D6: 338 | E6: 121 | F6: 101 | G6: 102 | H6: 42667 | I6: 42668 | J6: 126 | K6: 127 | L6: 138 | M6: 139 | N6: 197 | O6: 203 | P6: 204 | Q6: 230 | R6: 209 | S6: 56677 | T6: 796 | U6: 2146 | V6: 142 | W6: 143 | X6: 125 | Y6: 187 | Z6: 163 | AA6: 298 | AB6: 219 | AC6: 151 | AD6: 152 | AE6: 153 | AF6: 154 | AG6: 756 | AH6: 156 | AI6: 155 | AJ6: 182 | AK6: 212 | AL6: 758 | AM6: 263 | AN6: 265 | AO6: 775 | AP6: 777 | AQ6: 2154 | AR6: 150 | AS6: 149 | AT6: 188 | AU6: 2131 | AV6: 755 | AW6: 252 | AX6: 249 | AY6: 250 | AZ6: 117 | BA6: 267 | BB6: 268 | BC6: 119 | BD6: 120 | BE6: 189 | BF6: 122 | BG6: 266 | BH6: 251 | BI6: 115 | BJ6: 239 | BK6: 288 | BL6: 240 | BM6: 241 | BN6: 242 | BO6: 191 | BP6: 194 | BQ6: 196 | BR6: 207 | BS6: 236 | BT6: 795 | BU6: 285 | BV6: 995 | BW6: 996 | BX6: 997 | BY6: 766 | BZ6: 926 | CA6: 924 | CB6: 103 | CC6: 104 | CD6: 106 | CE6: 105 | CF6: 107 | CG6: 110 | CH6: 109 | CI6: 144 | CJ6: 113 | CK6: 114 | CL6: 193 | CM6: 208 | CN6: 786 | CO6: 787 | CP6: 788 | CQ6: 789 | CR6: 248 | CS6: 2159 | CT6: 303 | CU6: 59715 | CV6: 62255 | CW6: 1263 | CX6: 61800 | CY6: 2194 | CZ6: 216 | DA6: 198 | DB6: 214 | DC6: 260 | DD6: 2152 | DE6: 2128 | DF6: 247 | DG6: 228 | DH6: 2135 | DI6: 261 | DJ6: 237 | DK6: 253 | DL6: 770 | DM6: 225 | DN6: 2201 | DO6: 2171 | DP6: 760 | DQ6: 235 | DR6: 238 | DS6: 2184 | DT6: 61855 | DU6: 223 | DV6: 226 | DW6: 201 | DX6: 258 | DY6: 259 | DZ6: 920 | EA6: 257 | EB6: 256 | EC6: 2148 | ED6: 58288 | EE6: 58289 | EF6: 58839 | EG6: 58840 | EH6: 296 | EI6: 297 | EJ6: 211 | EK6: 2175 | EL6: 2178 | EM6: 2181 | EN6: 1262 | EO6: 233 | EP6: 2150 | EQ6: 2165 | ER6: 2161 | ES6: 61197 | ET6: 58851 | EU6: 234 | EV6: 215 | EW6: 917 | EX6: 289 | EY6: 58333 | EZ6: 58336 | FA6: 202 | FB6: 58487 | FC6: 213 | FD6: 232 | FE6: 2190 | FF6: TOTAL COES | FH6: 221 | FI6: 49607 | FJ6: 222 | FK6: 224 | FL6: 2187 | FM6: 227 | FN6: 49400 | FO6: 199 | FP6: 200 | FQ6: TOTAL NO COES
C7: CENTRO | D7: CENTRO | E7: NORTE | F7: CENTRO | G7: CENTRO | H7: NORTE | I7: NORTE | J7: NORTE | K7: NORTE | L7: CENTRO | M7: CENTRO | N7: CENTRO | O7: CENTRO | P7: CENTRO | Q7: CENTRO | R7: CENTRO | S7: CENTRO | T7: CENTRO | U7: CENTRO | V7: CENTRO | W7: CENTRO | X7: CENTRO | Y7: CENTRO | Z7: SUR | AA7: SUR | AB7: CENTRO | AC7: SUR | AD7: SUR | AE7: SUR | AF7: SUR | AG7: SUR | AH7: SUR | AI7: SUR | AJ7: SUR | AK7: CENTRO | AL7: NORTE | AM7: NORTE | AN7: NORTE | AO7: CENTRO | AP7: CENTRO | AQ7: CENTRO | AR7: CENTRO | AS7: CENTRO | AT7: CENTRO | AU7: CENTRO | AV7: SUR | AW7: CENTRO | AX7: CENTRO | AY7: CENTRO | AZ7: CENTRO | BA7: CENTRO | BB7: CENTRO | BC7: CENTRO | BD7: CENTRO | BE7: SUR | BF7: NORTE | BG7: CENTRO | BH7: CENTRO | BI7: NORTE | BJ7: NORTE | BK7: NORTE | BL7: SUR | BM7: SUR | BN7: SUR | BO7: CENTRO | BP7: CENTRO | BQ7: CENTRO | BR7: CENTRO | BS7: CENTRO | BT7: CENTRO | BU7: CENTRO | BV7: SUR | BW7: SUR | BX7: SUR | BY7: NORTE | BZ7: SUR | CA7: CENTRO | CB7: CENTRO | CC7: CENTRO | CD7: CENTRO | CE7: CENTRO | CF7: CENTRO | CG7: CENTRO | CH7: CENTRO | CI7: CENTRO | CJ7: CENTRO | CK7: CENTRO | CL7: CENTRO | CM7: CENTRO | CN7: SUR | CO7: SUR | CP7: SUR | CQ7: SUR | CR7: CENTRO | CS7: CENTRO | CT7: CENTRO | CU7: CENTRO | CV7: SUR | CW7: NORTE | CX7: NORTE | CY7: NORTE | CZ7: NORTE | DA7: NORTE | DB7: CENTRO | DC7: CENTRO | DD7: CENTRO | DE7: NORTE | DF7: NORTE | DG7: CENTRO | DH7: CENTRO | DI7: SUR | DJ7: SUR | DK7: CENTRO | DL7: CENTRO | DM7: CENTRO | DN7: CENTRO | DO7: CENTRO | DP7: CENTRO | DQ7: SUR | DR7: CENTRO | DS7: CENTRO | DT7: NORTE | DU7: CENTRO | DV7: CENTRO | DW7: NORTE | DX7: CENTRO | DY7: CENTRO | DZ7: CENTRO | EA7: NORTE | EB7: NORTE | EC7: SUR | ED7: CENTRO | EE7: CENTRO | EF7: CENTRO | EG7: CENTRO | EH7: CENTRO | EI7: CENTRO | EJ7: SUR | EK7: SUR | EL7: SUR | EM7: SUR | EN7: NORTE | EO7: SUR | EP7: SUR | EQ7: CENTRO | ER7: CENTRO | ES7: CENTRO | ET7: SUR | EU7: SUR | EV7: NORTE | EW7: CENTRO | EX7: NORTE | EY7: NORTE | EZ7: NORTE | FA7: CENTRO | FB7: CENTRO | FC7: CENTRO | FD7: NORTE | FE7: NORTE | FH7: NORTE | FI7: SUR | FJ7: CENTRO | FK7: NORTE | FL7: NORTE | FM7: NORTE | FN7: NORTE | FO7: NORTE | FP7: NORTE
C8: HIDROELÉCTRICA | D8: HIDROELÉCTRICA | E8: HIDROELÉCTRICA | F8: HIDROELÉCTRICA | G8: HIDROELÉCTRICA | H8: TERMOELÉCTRICA | I8: TERMOELÉCTRICA | J8: HIDROELÉCTRICA | K8: HIDROELÉCTRICA | L8: TERMOELÉCTRICA | M8: TERMOELÉCTRICA | N8: TERMOELÉCTRICA | O8: TERMOELÉCTRICA | P8: TERMOELÉCTRICA | Q8: TERMOELÉCTRICA | R8: TERMOELÉCTRICA | S8: TERMOELÉCTRICA | T8: HIDROELÉCTRICA | U8: HIDROELÉCTRICA | V8: TERMOELÉCTRICA | W8: TERMOELÉCTRICA | X8: TERMOELÉCTRICA | Y8: TERMOELÉCTRICA | Z8: HIDROELÉCTRICA | AA8: HIDROELÉCTRICA | AB8: TERMOELÉCTRICA | AC8: HIDROELÉCTRICA | AD8: HIDROELÉCTRICA | AE8: HIDROELÉCTRICA | AF8: HIDROELÉCTRICA | AG8: TERMOELÉCTRICA | AH8: TERMOELÉCTRICA | AI8: TERMOELÉCTRICA | AJ8: HIDROELÉCTRICA | AK8: HIDROELÉCTRICA | AL8: TERMOELÉCTRICA | AM8: TERMOELÉCTRICA | AN8: TERMOELÉCTRICA | AO8: HIDROELÉCTRICA | AP8: HIDROELÉCTRICA | AQ8: HIDROELÉCTRICA | AR8: HIDROELÉCTRICA | AS8: HIDROELÉCTRICA | AT8: HIDROELÉCTRICA | AU8: HIDROELÉCTRICA | AV8: HIDROELÉCTRICA | AW8: TERMOELÉCTRICA | AX8: TERMOELÉCTRICA | AY8: TERMOELÉCTRICA | AZ8: HIDROELÉCTRICA | BA8: HIDROELÉCTRICA | BB8: HIDROELÉCTRICA | BC8: HIDROELÉCTRICA | BD8: HIDROELÉCTRICA | BE8: HIDROELÉCTRICA | BF8: HIDROELÉCTRICA | BG8: HIDROELÉCTRICA | BH8: HIDROELÉCTRICA | BI8: TERMOELÉCTRICA | BJ8: TERMOELÉCTRICA | BK8: TERMOELÉCTRICA | BL8: TERMOELÉCTRICA | BM8: TERMOELÉCTRICA | BN8: TERMOELÉCTRICA | BO8: HIDROELÉCTRICA | BP8: TERMOELÉCTRICA | BQ8: TERMOELÉCTRICA | BR8: TERMOELÉCTRICA | BS8: TERMOELÉCTRICA | BT8: TERMOELÉCTRICA | BU8: TERMOELÉCTRICA | BV8: TERMOELÉCTRICA | BW8: TERMOELÉCTRICA | BX8: TERMOELÉCTRICA | BY8: HIDROELÉCTRICA | BZ8: TERMOELÉCTRICA | CA8: TERMOELÉCTRICA | CB8: HIDROELÉCTRICA | CC8: HIDROELÉCTRICA | CD8: HIDROELÉCTRICA | CE8: HIDROELÉCTRICA | CF8: HIDROELÉCTRICA | CG8: TERMOELÉCTRICA | CH8: TERMOELÉCTRICA | CI8: TERMOELÉCTRICA | CJ8: TERMOELÉCTRICA | CK8: TERMOELÉCTRICA | CL8: TERMOELÉCTRICA | CM8: TERMOELÉCTRICA | CN8: TERMOELÉCTRICA | CO8: TERMOELÉCTRICA | CP8: TERMOELÉCTRICA | CQ8: TERMOELÉCTRICA | CR8: TERMOELÉCTRICA | CS8: TERMOELÉCTRICA | CT8: SOLAR | CU8: EÓLICA | CV8: SOLAR | CW8: EÓLICA | CX8: SOLAR | CY8: HIDROELÉCTRICA | CZ8: HIDROELÉCTRICA | DA8: HIDROELÉCTRICA | DB8: HIDROELÉCTRICA | DC8: HIDROELÉCTRICA | DD8: HIDROELÉCTRICA | DE8: HIDROELÉCTRICA | DF8: HIDROELÉCTRICA | DG8: HIDROELÉCTRICA | DH8: HIDROELÉCTRICA | DI8: SOLAR | DJ8: SOLAR | DK8: EÓLICA | DL8: EÓLICA | DM8: TERMOELÉCTRICA | DN8: TERMOELÉCTRICA | DO8: TERMOELÉCTRICA | DP8: TERMOELÉCTRICA | DQ8: SOLAR | DR8: HIDROELÉCTRICA | DS8: HIDROELÉCTRICA | DT8: HIDROELÉCTRICA | DU8: HIDROELÉCTRICA | DV8: HIDROELÉCTRICA | DW8: HIDROELÉCTRICA | DX8: HIDROELÉCTRICA | DY8: HIDROELÉCTRICA | DZ8: HIDROELÉCTRICA | EA8: EÓLICA | EB8: EÓLICA | EC8: SOLAR | ED8: EÓLICA | EE8: EÓLICA | EF8: EÓLICA | EG8: EÓLICA | EH8: HIDROELÉCTRICA | EI8: HIDROELÉCTRICA | EJ8: HIDROELÉCTRICA | EK8: HIDROELÉCTRICA | EL8: HIDROELÉCTRICA | EM8: HIDROELÉCTRICA | EN8: EÓLICA | EO8: SOLAR | EP8: SOLAR | EQ8: HIDROELÉCTRICA | ER8: EÓLICA | ES8: EÓLICA | ET8: SOLAR | EU8: SOLAR | EV8: HIDROELÉCTRICA | EW8: HIDROELÉCTRICA | EX8: TERMOELÉCTRICA | EY8: TERMOELÉCTRICA | EZ8: TERMOELÉCTRICA | FA8: TERMOELÉCTRICA | FB8: TERMOELÉCTRICA | FC8: TERMOELÉCTRICA | FD8: TERMOELÉCTRICA | FE8: TERMOELÉCTRICA | FH8: HIDROELÉCTRICA | FI8: HIDROELÉCTRICA | FJ8: HIDROELÉCTRICA | FK8: HIDROELÉCTRICA | FL8: HIDROELÉCTRICA | FM8: TERMOELÉCTRICA | FN8: TERMOELÉCTRICA | FO8: HIDROELÉCTRICA | FP8: HIDROELÉCTRICA
C9: CENTRALES SANTA ROSA S.A.C. | D9: CENTRALES SANTA ROSA S.A.C. | E9: INVERSIONES SHAQSHA S.A.C. | F9: ELECTROPERU | G9: ELECTROPERU | H9: ELECTROPERU | I9: ELECTROPERU | J9: ORAZUL ENERGY PERÚ | K9: ORAZUL ENERGY PERÚ | L9: TERMOSELVA | M9: TERMOSELVA | N9: KALLPA GENERACION S.A. | O9: KALLPA GENERACION S.A. | P9: KALLPA GENERACION S.A. | Q9: KALLPA GENERACION S.A. | R9: KALLPA GENERACION S.A. | S9: KALLPA GENERACION S.A. | T9: KALLPA GENERACION S.A. | U9: KALLPA GENERACION S.A. | V9: SHOUGESA | W9: SHOUGESA | X9: SHOUGESA | Y9: SHOUGESA | Z9: EGEMSA | AA9: EGESUR | AB9: EGESUR | AC9: EGASA | AD9: EGASA | AE9: EGASA | AF9: EGASA | AG9: EGASA | AH9: EGASA | AI9: EGASA | AJ9: SAN GABAN | AK9: CELEPSA | AL9: MINERA CERRO VERDE | AM9: PLANTA DE RESERVA FRIA DE GENERACION DE ETEN S.A. | AN9: PLANTA DE RESERVA FRIA DE GENERACION DE ETEN S.A. | AO9: EMPRESA DE GENERACION HUALLAGA | AP9: EMPRESA DE GENERACION HUALLAGA | AQ9: LA VIRGEN | AR9: CHINANGO S.A.C. | AS9: CHINANGO S.A.C. | AT9: HIDROELECTRICA HUANCHOR S.A.C. | AU9: CELEPSA RENOVABLES S.R.L. | AV9: INLAND ENERGY SAC | AW9: FENIX POWER PERÚ | AX9: FENIX POWER PERÚ | AY9: FENIX POWER PERÚ | AZ9: STATKRAFT S.A | BA9: STATKRAFT S.A | BB9: STATKRAFT S.A | BC9: STATKRAFT S.A | BD9: STATKRAFT S.A | BE9: STATKRAFT S.A | BF9: STATKRAFT S.A | BG9: STATKRAFT S.A | BH9: EMPRESA DE GENERACION HUANZA | BI9: ENEL GENERACION PIURA S.A. | BJ9: ENEL GENERACION PIURA S.A. | BK9: ENEL GENERACION PIURA S.A. | BL9: ENGIE | BM9: ENGIE | BN9: ENGIE | BO9: ENGIE | BP9: ENGIE | BQ9: ENGIE | BR9: ENGIE | BS9: ENGIE | BT9: ENGIE | BU9: ENGIE | BV9: ENGIE | BW9: ENGIE | BX9: ENGIE | BY9: ENGIE | BZ9: INFRAESTRUCTURAS Y ENERGIAS DEL PERU S.A.C. | CA9: INFRAESTRUCTURAS Y ENERGIAS DEL PERU S.A.C. | CB9: ORYGEN PERU S.A.A. | CC9: ORYGEN PERU S.A.A. | CD9: ORYGEN PERU S.A.A. | CE9: ORYGEN PERU S.A.A. | CF9: ORYGEN PERU S.A.A. | CG9: ORYGEN PERU S.A.A. | CH9: ORYGEN PERU S.A.A. | CI9: ORYGEN PERU S.A.A. | CJ9: ORYGEN PERU S.A.A. | CK9: ORYGEN PERU S.A.A. | CL9: ORYGEN PERU S.A.A. | CM9: ORYGEN PERU S.A.A. | CN9: SAMAY I S.A.C | CO9: SAMAY I S.A.C | CP9: SAMAY I S.A.C | CQ9: SAMAY I S.A.C | CR9: TERMOCHILCA S.A.C. | CS9: TERMOCHILCA S.A.C. | CT9: COLCA SOLAR S.A.C. | CU9: ENERGIA RENOVABLE DEL SUR S.A. | CV9: GR CORTARRAMA SOCIEDAD ANONIMA CERRADA | CW9: GR TARUCA SOCIEDAD ANONIMA CERRADA | CX9: KONDU SAC | CY9: PERUANA DE INVERSIONES EN ENERGIAS RENOVABLES S.A. | CZ9: ORAZUL ENERGY PERÚ | DA9: ORAZUL ENERGY PERÚ | DB9: MAJA ENERGIA S.A.C. | DC9: EMPRESA DE GENERACION ELECTRICA CANCHAYLLO SAC | DD9: EMPRESA DE GENERACION ELECTRICA SANTA ANA S.A.C. | DE9: EMPRESA ELECTRICA AGUA AZUL | DF9: EMPRESA ELECTRICA RIO DOBLE | DG9: HIDROCAÑETE S.A. | DH9: HUAURA POWER GROUP S.A. | DI9: MOQUEGUA FV S.A.C. | DJ9: PANAMERICANA SOLAR SAC. | DK9: PARQUE EOLICO MARCONA S.A.C. | DL9: PARQUE EOLICO TRES HERMANAS S.A.C. | DM9: PETRAMAS | DN9: PETRAMAS | DO9: PETRAMAS | DP9: PETRAMAS | DQ9: TACNA SOLAR SAC. | DR9: ELECTRICA YANAPAMPA SAC | DS9: ANDEAN POWER S.A.C. | DT9: ASOCIACIÓN SANTA LUCIA DE CHACAS | DU9: ATRIA ENERGIA S.A.C. | DV9: EGEJUNIN | DW9: EGEJUNIN | DX9: EGEJUNIN | DY9: EGEJUNIN | DZ9: EMPRESA DE GENERACION ELECTRICA RIO BAÑOS S.A.C. | EA9: ENERGÍA EÓLICA S.A. | EB9: ENERGÍA EÓLICA S.A. | EC9: ENGIE | ED9: ENGIE | EE9: ENGIE | EF9: ENGIE | EG9: ENGIE | EH9: GENERACIÓN ANDINA S.A.C. | EI9: GENERACIÓN ANDINA S.A.C. | EJ9: GENERADORA DE ENERGÍA DEL PERÚ | EK9: GENERADORA DE ENERGÍA DEL PERÚ | EL9: GENERADORA DE ENERGÍA DEL PERÚ | EM9: GENERADORA DE ENERGÍA DEL PERÚ | EN9: GR PAINO SOCIEDAD ANONIMA CERRADA | EO9: MAJES ARCUS S.A.C. | EP9: ORYGEN PERU S.A.A. | EQ9: ORYGEN PERU S.A.A. | ER9: ORYGEN PERU S.A.A. | ES9: ORYGEN PERU S.A.A. | ET9: ORYGEN PERU S.A.A. | EU9: REPARTICIÓN ARCUS S.A.C. | EV9: SINERSA | EW9: SINERSA | EX9: BIOENERGIA DEL CHIRA S.A. | EY9: GM OPERACIONES S.A.C. | EZ9: GM OPERACIONES S.A.C. | FA9: SDF ENERGIA SAC | FB9: SDF ENERGIA SAC | FC9: AGRO INDUSTRIAL PARAMONGA S.A. | FD9: AGROAURORA S.A.C. | FE9: AGROINDUSTRIAS SAN JACINTO S.A.A. | FH9: UNACEM PERU S.A. | FI9: SAN GABAN | FJ9: ELECTRO ORIENTE | FK9: AGUAS Y ENERGIA PERU | FL9: ELECTRO ZAÑA S.A.C. | FM9: ELECTRONOROESTE S.A. | FN9: SDE PIURA | FO9: SINERSA | FP9: SINERSA
C10: SANTA ROSA 1 | D10: SANTA ROSA 2 | E10: PARIAC | F10: MANTARO | G10: RESTITUCION | H10: TUMBES MAK 1 | I10: TUMBES MAK 2 | J10: CARHUAQUERO | K10: CAÑON DEL PATO | L10: AGUAYTIA TG1 | M10: AGUAYTIA TG2 | N10: KALLPA TG1 | O10: KALLPA TG2 | P10: KALLPA TG3 | Q10: KALLPA TV | R10: LFLORES TG1 | S10: LFLORES TV | T10: CERRO DEL AGUILA | U10: CERRODELAGUILAG4 | V10: SHOUGESA TV1 | W10: SHOUGESA TV2 | X10: SHOUGESA TV3 | Y10: SHOUGESA CUMMINS | Z10: MACHUPICCHU | AA10: ARICOTA 1 | AB10: INDEPENDENCIA | AC10: CHARCANI I,II,III | AD10: CHARCANI IV | AE10: CHARCANI V | AF10: CHARCANI VI | AG10: CHILINA TG | AH10: MOLLENDO 1, 2, 3 | AI10: CHILINA (SULZ 1,2) | AJ10: SAN GABAN II | AK10: PLATANAL | AL10: RECKA | AM10: RF ETEN TG1 | AN10: RF ETEN TG2 | AO10: CHAGLLA GP1 | AP10: CHAGLLA | AQ10: LA VIRGEN | AR10: CHIMAY | AS10: YANANGO | AT10: HUANCHOR | AU10: MARAÑON | AV10: STA TERESA | AW10: FENIX GT11 | AX10: FENIX GT12 | AY10: FENIX TV10 | AZ10: YAUPI | BA10: OROYA | BB10: PACHACHACA | BC10: MALPASO | BD10: CAHUA | BE10: ARCATA | BF10: GALLITO CIEGO | BG10: CHEVES | BH10: HUANZA | BI10: MALACAS2 TG4 | BJ10: MALACAS3 TG 5 | BK10: MALACAS1 TG6 | BL10: RF ILO2 TG1 | BM10: RF ILO2 TG2 | BN10: RF ILO2 TG3 | BO10: YUNCAN | BP10: CHILCA1 TG1 | BQ10: CHILCA1 TG2 | BR10: CHILCA1 TG3 | BS10: CHILCA-TV | BT10: CHILCA2 TG41 | BU10: CHILCA2-TV | BV10: CTNEPI_TG41 | BW10: CTNEPI_TG42 | BX10: CTNEPI_TG43 | BY10: QUITARACSA | BZ10: RF PTO MALDONADO | CA10: RF PUCALLPA | CB10: HUINCO | CC10: MATUCANA | CD10: MOYOPAMPA | CE10: CALLAHUANCA | CF10: HUAMPANI | CG10: STA ROSA WEST TG7 | CH10: UTI_5 | CI10: UTI_6 | CJ10: VENTANILLA 3 | CK10: VENTANILLA 4 | CL10: VENTANILLA TV | CM10: STAROSA TG8 | CN10: PTO_BRVO TG1 | CO10: PTO_BRVO TG2 | CP10: PTO_BRVO TG3 | CQ10: PTO_BRVO TG4 | CR10: OLLEROS TG1 | CS10: OLLEROS TV | CT10: CS YARUCAYA | CU10: SAN JUAN | CV10: MATARANI | CW10: DUNA | CX10: CARHUAQUERO (CS) | CY10: MANTA I | CZ10: CARHUAQUERO4 | DA10: CAÑA BRAVA | DB10: RONCADOR | DC10: CANCHAYLLO | DD10: RENOVANDESH1 | DE10: POTRERO | DF10: PIZARRAS | DG10: NIMPERIAL | DH10: YARUCAYA | DI10: MOQUEGUA-SOLAR | DJ10: PANAMERICANA-SOLAR | DK10: PQE-EOLICO-MARCONA | DL10: PQE-EOLICO-3-HERMANAS | DM10: HUAYCOLORO | DN10: CALLAO | DO10: DONA_CATALINA | DP10: LAGRINGAV | DQ10: TACNA-SOLAR | DR10: YANAPAMPA | DS10: CARHUAC | DT10: HUALLIN | DU10: PURMACANA | DV10: HUASAHUASI | DW10: STACRUZ_1_2 | DX10: RUNATULLO_II | DY10: RUNATULLO_III | DZ10: RUCUY | EA10: PQE-EOLICO-TALARA | EB10: PQE-EOLICO-CUPISNIQUE | EC10: INTIPAMPA | ED10: PUNTA LOMITAS-BL1 | EE10: PUNTA LOMITAS-BL2 | EF10: PUN LOMITAS_EXP-BL1 | EG10: PUN LOMITAS_EXP-BL2 | EH10: 8AGOSTO | EI10: EL CARMEN | EJ10: LA JOYA | EK10: ANGEL_I | EL10: ANGEL_II | EM10: ANGEL_III | EN10: HUAMBOS | EO10: MAJES | EP10: RUBI | EQ10: CH_HER1 | ER10: WAYRA-I | ES10: WAYRA EXTENSION | ET10: CLEMESI | EU10: REPARTICION | EV10: POECHOS2 | EW10: CHANCAY | EX10: CANA BRAVA | EY10: REFINERIA TALARA TV1 | EZ10: REFINERÍA TALARA TV2 | FA10: OQUENDO TG1 | FB10: OQUENDO TV1 | FC10: PARAMONGA | FD10: MAPLE | FE10: SAN_JACINTO | FF10: MVAR | FH10: CARPAPATA | FI10: TUPURI | FJ10: CENTRALES ELOR | FK10: PIAS1 | FL10: ZANA | FM10: TABLAZO | FN10: TALLANCA | FO10: CURUMUY | FP10: POECHOS1 | FQ10: MVAR
A11: 21/01/2025 | B11: 00:30 | C11: 0.2 | E11: -0.2 | F11: 12.8 | G11: 13.8 | J11: -19.1 | K11: 6.7 | N11: -36 | O11: -45.2 | P11: -15 | Q11: 20.2 | R11: 16.5 | S11: -7.4 | T11: 78.1 | U11: 0.1 | Z11: 3.9 | AA11: 1.1 | AB11: 0 | AC11: -3.3 | AD11: 1.6 | AE11: 9.1 | AF11: 1.3 | AJ11: 11.4 | AK11: 16.6 | AO11: -1.5 | AP11: 35.7 | AQ11: 7.7 | AR11: 0 | AS11: 0.2 | AT11: 0.8 | AU11: 2.7 | AV11: 0.9 | AW11: 4.9 | AX11: -10.3 | AY11: -44.9 | AZ11: 7.2 | BA11: -0.7 | BB11: 0 | BC11: -1.4 | BD11: 4.7 | BE11: 0.9 | BF11: -0.1 | BG11: 3.8 | BH11: 1.8 | BK11: -4.1 | BO11: 6.8 | BQ11: 0 | BT11: 0 | BY11: -3.9 | CB11: 10 | CC11: 18 | CD11: -3.4 | CE11: 13.5 | CF11: 0 | CJ11: 13.7 | CK11: 13.6 | CL11: -17.7 | CU11: -4.4 | CV11: 0 | CY11: 1.2 | CZ11: 0 | DA11: -0.8 | DB11: 0.4 | DC11: 1.3 | DD11: 1.8 | DE11: -1.2 | DF11: 1.81 | DG11: 0.5 | DI11: 0 | DJ11: 0 | DK11: -6.9 | DL11: -12.6 | DM11: 1.5 | DN11: 0.5 | DO11: 0.7 | DP11: 0.9 | DQ11: 0 | DR11: -0.1 | DS11: 0.5 | DT11: 0.2 | DV11: -3.2 | DW11: 0.2 | DX11: 2.7 | DY11: 2.2 | DZ11: 1.1 | EA11: 0.8 | EB11: 4 | EC11: 0 | ED11: -4.7 | EE11: -5.1 | EF11: 5.3 | EG11: 5.1 | EH11: 2.6 | EI11: 0 | EJ11: 1.5 | EK11: 0.2 | EL11: 0.2 | EM11: 0.1 | EN11: 0 | EO11: 0 | EP11: 0 | EQ11: -0.2 | ER11: 0 | ES11: 3.2 | ET11: 0 | EU11: 0 | EV11: 1.2 | EW11: 1.4 | EX11: 2.6 | EY11: 5.3 | EZ11: 5.1 | FA11: 0.8 | FB11: 1.7 | FC11: 3.8 | FD11: 1.6 | FE11: 3.8 | FF11: 154.71 | FH11: 2.88656 | FJ11: 0.111 | FK11: 1.534 | FL11: 1 | FN11: 0.13148 | FO11: -0.4 | FP11: 1 | FQ11: 6.26304
A12: 21/01/2025 | B12: 01:00 | C12: 0.2 | E12: -0.2 | F12: 26.8 | G12: 15.8 | J12: -15 | K12: 23 | N12: -33.4 | O12: -44.2 | P12: -16.6 | Q12: 23.1 | R12: 16 | S12: -7.1 | T12: 79.3 | U12: 0 | Z12: 5.2 | AA12: 0.6 | AB12: 0 | AC12: -3.4 | AD12: 1.5 | AE12: 9.3 | AF12: 1.2 | AJ12: 12 | AK12: 15.4 | AO12: -1.7 | AP12: 10.7 | AQ12: 10.6 | AR12: 0 | AS12: -0.1 | AT12: 1 | AU12: 2.7 | AV12: 1 | AW12: 3.5 | AX12: -11.7 | AY12: -46.5 | AZ12: 5.7 | BA12: -0.8 | BB12: 0 | BC12: -3.1 | BD12: 4.6 | BE12: 1 | BF12: -0.1 | BG12: 0 | BH12: 2.2 | BK12: 4.8 | BO12: 6.5 | BQ12: 0 | BT12: 0 | BY12: -5.8 | CB12: 9.4 | CC12: 18.8 | CD12: -2.4 | CE12: 13.4 | CF12: -0.1 | CJ12: 15.9 | CK12: 15.7 | CL12: -14.6 | CU12: -4.4 | CV12: 0 | CY12: 1.2 | CZ12: -0.1 | DA12: -0.8 | DB12: 0.2 | DC12: 1.2 | DD12: 1.8 | DE12: 0.7 | DF12: 1.97 | DG12: 0.6 | DI12: 0 | DJ12: 0 | DK12: -6.2 | DL12: -16.2 | DM12: 1.5 | DN12: 0.5 | DO12: 0.7 | DP12: 0.9 | DQ12: 0 | DR12: -0.3 | DS12: 0.3 | DT12: 0.2 | DV12: -3.3 | DW12: 0.2 | DX12: 2.9 | DY12: 2.3 | DZ12: 1.3 | EA12: 0.8 | EB12: 4 | EC12: 0 | ED12: 0.2 | EE12: -0.3 | EF12: 5.2 | EG12: 8.6 | EH12: 2.6 | EI12: 0 | EJ12: 1.4 | EK12: 0.2 | EL12: 0.2 | EM12: 0.1 | EN12: 0 | EO12: 0 | EP12: 0 | EQ12: -0.2 | ER12: 1.8 | ES12: 3.3 | ET12: 0 | EU12: 0 | EV12: 1.2 | EW12: 1.6 | EX12: 2.5 | EY12: 5.2 | EZ12: 8.6 | FA12: 0.8 | FB12: 1.6 | FC12: 3.2 | FD12: 2.9 | FE12: 3.4 | FF12: 196.17 | FH12: 2.86964 | FJ12: 0.431 | FK12: 1.432 | FL12: 1.1 | FN12: 0.10917 | FO12: 0.4 | FP12: 1.1 | FQ12: 7.44181
A13: 21/01/2025 | B13: 01:30 | C13: 0.2 | E13: -0.1 | F13: 8.3 | G13: 12.8 | J13: -17.9 | K13: 10 | N13: -39.5 | O13: -49.7 | P13: -20.6 | Q13: 14.5 | R13: 11.5 | S13: -10.8 | T13: 69.6 | U13: 0 | Z13: 4.6 | AA13: 0.9 | AB13: 0 | AC13: -3.4 | AD13: 1.6 | AE13: 9 | AF13: 1.5 | AJ13: 11.9 | AK13: 15.2 | AO13: -1.7 | AP13: 17.7 | AQ13: 10.3 | AR13: 0 | AS13: -0.1 | AT13: 0.7 | AU13: 2.7 | AV13: 1.3 | AW13: -5.5 | AX13: -20.5 | AY13: -54 | AZ13: 6.6 | BA13: -0.9 | BB13: 0 | BC13: -2.3 | BD13: 4.1 | BE13: 1 | BF13: -0.1 | BG13: 1.6 | BH13: 0.4 | BK13: 3 | BO13: 1.5 | BQ13: 0 | BT13: 0 | BY13: -5.2 | CB13: 9.9 | CC13: 17.6 | CD13: -3.6 | CE13: 14.8 | CF13: 0 | CJ13: 10.4 | CK13: 10.3 | CL13: -22.6 | CU13: -4.1 | CV13: 0 | CY13: 1.2 | CZ13: 0 | DA13: -0.7 | DB13: 0.1 | DC13: 1.2 | DD13: 1.7 | DE13: 0.5 | DF13: 1.99 | DG13: 0.6 | DI13: 0 | DJ13: 0 | DK13: -6.5 | DL13: -17.3 | DM13: 1.5 | DN13: 0.5 | DO13: 0.7 | DP13: 0.9 | DQ13: 0 | DR13: -0.2 | DS13: 0.3 | DT13: 0.2 | DV13: -3.3 | DW13: 0.2 | DX13: 2.3 | DY13: 2.2 | DZ13: 1.2 | EA13: 0.8 | EB13: 4 | EC13: 0 | ED13: -4.6 | EE13: -5.4 | EF13: 5.2 | EG13: 7.8 | EH13: 2.6 | EI13: 0 | EJ13: 1.4 | EK13: 0.2 | EL13: 0.2 | EM13: 0.1 | EN13: 0 | EO13: 0 | EP13: 0 | EQ13: -0.2 | ER13: 0.4 | ES13: 3.4 | ET13: 0 | EU13: 0 | EV13: 1.2 | EW13: 1.5 | EX13: 2.6 | EY13: 5.2 | EZ13: 7.8 | FA13: 0.8 | FB13: 1.5 | FC13: 3.3 | FD13: 3.2 | FE13: 3.4 | FF13: 58.59 | FH13: 2.90686 | FJ13: 0.222 | FK13: 1.428 | FL13: 1.1 | FN13: 0.05191 | FO13: 0.1 | FP13: 1 | FQ13: 6.80877
A14: 21/01/2025 | B14: 02:00 | C14: 0.2 | E14: -0.1 | F14: 18.2 | G14: 15.1 | J14: -17.6 | K14: 8.6 | N14: -37.3 | O14: -48 | P14: -19 | Q14: 17.5 | R14: 12 | S14: -10.1 | T14: 76.4 | U14: 0 | Z14: 4 | AA14: 1 | AB14: 0 | AC14: -3.4 | AD14: 1.6 | AE14: 8.8 | AF14: 1.5 | AJ14: 12 | AK14: 15 | AO14: -1.8 | AP14: 20 | AQ14: 0.2 | AR14: 0 | AS14: -0.5 | AT14: 0.6 | AU14: 2.7 | AV14: 1.3 | AW14: -6.3 | AX14: -21.5 | AY14: -55 | AZ14: 6.4 | BA14: -1 | BB14: -0.1 | BC14: -4.5 | BD14: 4.1 | BE14: 1 | BF14: -0.1 | BG14: 1 | BH14: 0.4 | BK14: 2.7 | BO14: 4.8 | BQ14: 0 | BT14: 0 | BY14: -5.8 | CB14: 10.1 | CC14: 16.9 | CD14: -3 | CE14: 13.4 | CF14: 0 | CJ14: 10 | CK14: 10 | CL14: -23.5 | CU14: -4.2 | CV14: 0 | CY14: 1.2 | CZ14: 0 | DA14: -0.8 | DB14: 0 | DC14: 1.1 | DD14: 1.8 | DE14: -0.8 | DF14: 1.96 | DG14: 0.6 | DI14: 0 | DJ14: 0 | DK14: -6.5 | DL14: -16.7 | DM14: 1.5 | DN14: 0.5 | DO14: 0.7 | DP14: 0.9 | DQ14: 0 | DR14: -0.2 | DS14: 0.3 | DT14: 0.2 | DV14: -3.8 | DW14: 0.2 | DX14: 2.4 | DY14: 2.2 | DZ14: 1.1 | EA14: 0.8 | EB14: 4 | EC14: 0 | ED14: -2.6 | EE14: -3.4 | EF14: 5.2 | EG14: 7.3 | EH14: 2.6 | EI14: 0 | EJ14: 1.6 | EK14: 0.2 | EL14: 0.2 | EM14: 0.1 | EN14: 0 | EO14: 0 | EP14: 0 | EQ14: -0.2 | ER14: 1.3 | ES14: 3.2 | ET14: 0 | EU14: 0 | EV14: 1.2 | EW14: 1.4 | EX14: 2.7 | EY14: 5.2 | EZ14: 7.3 | FA14: 0.8 | FB14: 1.9 | FC14: 2.3 | FD14: 2.6 | FE14: 4 | FF14: 72.26 | FH14: 1.81846 | FJ14: 0.217 | FK14: 1.522 | FL14: 1 | FN14: 0.05349 | FO14: 0 | FP14: 1 | FQ14: 5.61095
A15: 21/01/2025 | B15: 02:30 | C15: 0.2 | E15: 0 | F15: 22.4 | G15: 15.7 | J15: -16.7 | K15: 17.7 | N15: -40.4 | O15: -48.4 | P15: -17.7 | Q15: 17.6 | R15: 11.1 | S15: -10.8 | T15: 79.8 | U15: 0 | Z15: 4.2 | AA15: 0.8 | AB15: 0 | AC15: -3.5 | AD15: 1.5 | AE15: 6.9 | AF15: 1.4 | AJ15: 11.6 | AK15: 0.6 | AO15: -1.5 | AP15: 45.8 | AQ15: 9.4 | AR15: 0 | AS15: -0.5 | AT15: 0.6 | AU15: 2.7 | AV15: 1.3 | AW15: -4.7 | AX15: -19.8 | AY15: -53.8 | AZ15: 9.2 | BA15: -0.5 | BB15: 0.4 | BC15: -0.5 | BD15: 4 | BE15: 1 | BF15: -0.1 | BG15: 0.5 | BH15: 0 | BK15: 2.7 | BO15: 13.8 | BQ15: 0 | BT15: 0 | BY15: -4.8 | CB15: 10.6 | CC15: 17.5 | CD15: -3.2 | CE15: 13.5 | CF15: 0.1 | CJ15: 9.8 | CK15: 9.7 | CL15: -23.8 | CU15: -3.9 | CV15: 0 | CY15: 1.2 | CZ15: 0 | DA15: -0.7 | DB15: 0.2 | DC15: 1.4 | DD15: 1.8 | DE15: -0.7 | DF15: 1.92 | DG15: 0.6 | DI15: 0 | DJ15: 0 | DK15: -6.5 | DL15: -16.8 | DM15: 1.5 | DN15: 0.5 | DO15: 0.7 | DP15: 0.9 | DQ15: 0 | DR15: 0.2 | DS15: 0.3 | DT15: 0.2 | DV15: -3.7 | DW15: 0.2 | DX15: 2.4 | DY15: 2.2 | DZ15: 1 | EA15: 0.8 | EB15: 4 | EC15: 0 | ED15: -0.8 | EE15: -1.6 | EF15: 5.3 | EG15: 7.4 | EH15: 2.6 | EI15: 0 | EJ15: 1.5 | EK15: 0.2 | EL15: 0.2 | EM15: 0.1 | EN15: 0 | EO15: 0 | EP15: 0 | EQ15: -0.2 | ER15: 1.9 | ES15: 3 | ET15: 0 | EU15: 0 | EV15: 1.2 | EW15: 1.2 | EX15: 2.6 | EY15: 5.3 | EZ15: 7.4 | FA15: 0.8 | FB15: 1.6 | FC15: 1.8 | FD15: 2.5 | FE15: 3.5 | FF15: 130.62 | FH15: 3.42101 | FJ15: 0.618 | FK15: 1.35 | FL15: 1.1 | FN15: 0.0563 | FO15: 0.1 | FP15: 1 | FQ15: 7.64531
A16: 21/01/2025 | B16: 03:00 | C16: 0.2 | E16: -0.1 | F16: 21.2 | G16: 16.6 | J16: -19.7 | K16: 4.8 | N16: -40.9 | O16: -50.8 | P16: -17.1 | Q16: 15.1 | R16: 9.7 | S16: -11.2 | T16: 80.6 | U16: 0.1 | Z16: 4.4 | AA16: 1.4 | AB16: 0 | AC16: -3.5 | AD16: 1.6 | AE16: 9.5 | AF16: 2.1 | AJ16: 13.2 | AK16: 1.3 | AO16: -1.6 | AP16: 45.8 | AQ16: 12.4 | AR16: 0 | AS16: -0.2 | AT16: 0.9 | AU16: 2.7 | AV16: 0.7 | AW16: -9.6 | AX16: -22.8 | AY16: -56.6 | AZ16: 9.8 | BA16: -0.5 | BB16: 0.2 | BC16: 0.1 | BD16: 3.2 | BE16: 1 | BF16: -0.1 | BG16: 1.1 | BH16: 0 | BK16: 1.1 | BO16: 14.4 | BQ16: 0 | BT16: 0 | BY16: -5.7 | CB16: 10.8 | CC16: 16.4 | CD16: -4.2 | CE16: 15.5 | CF16: -0.2 | CJ16: 9.2 | CK16: 8.9 | CL16: -24.9 | CU16: -3.6 | CV16: 0 | CY16: 1.2 | CZ16: 0 | DA16: -0.8 | DB16: 0.2 | DC16: 1.4 | DD16: 1.9 | DE16: -0.7 | DF16: 1.95 | DG16: 0.6 | DI16: 0 | DJ16: 0 | DK16: -8.5 | DL16: -17.1 | DM16: 1.5 | DN16: 0.5 | DO16: 0.7 | DP16: 0.9 | DQ16: 0 | DR16: 0.3 | DS16: 0.3 | DT16: 0.2 | DV16: -3.8 | DW16: 0.2 | DX16: 2.4 | DY16: 2.2 | DZ16: 1.1 | EA16: 0.8 | EB16: 4 | EC16: 0 | ED16: -2.5 | EE16: -3.3 | EF16: 5.2 | EG16: 7.1 | EH16: 2.6 | EI16: 0 | EJ16: 1.5 | EK16: 0.2 | EL16: 0.2 | EM16: 0.1 | EN16: 0 | EO16: 0 | EP16: 0 | EQ16: -0.2 | ER16: 1.6 | ES16: 3.2 | ET16: 0 | EU16: 0 | EV16: 1.2 | EW16: 1.4 | EX16: 2.6 | EY16: 5.2 | EZ16: 7.1 | FA16: 0.8 | FB16: 1.8 | FC16: 0.2 | FD16: 2.4 | FE16: 3.4 | FF16: 95.95 | FH16: 3.43083 | FJ16: 0.575 | FK16: 1.358 | FL16: 1 | FN16: 0.05369 | FO16: -0.1 | FP16: 0.9 | FQ16: 7.21752
A17: 21/01/2025 | B17: 03:30 | C17: 0.2 | E17: -0.2 | F17: 11.6 | G17: 14 | J17: -21.1 | K17: 3.2 | N17: -37.8 | O17: -52.9 | P17: -24.7 | Q17: 22.9 | R17: 11.5 | S17: -10 | T17: 80.7 | U17: 0 | Z17: 3.3 | AA17: 1.2 | AB17: 0 | AC17: -3.5 | AD17: 1.6 | AE17: 9.5 | AF17: 1.9 | AJ17: 10.9 | AK17: 13.4 | AO17: -1.7 | AP17: -1.3 | AQ17: 11.2 | AR17: 0 | AS17: -0.2 | AT17: 0.9 | AU17: 2.7 | AV17: 0.7 | AW17: -8.4 | AX17: -23.4 | AY17: -61.5 | AZ17: 6.4 | BA17: -0.5 | BB17: 0.2 | BC17: -4.2 | BD17: 1.4 | BE17: 1 | BF17: -0.1 | BG17: -5.4 | BH17: 0 | BK17: 0.3 | BO17: 6.5 | BQ17: 0 | BT17: 0 | BY17: -11.2 | CB17: 10.5 | CC17: 16.9 | CD17: -3 | CE17: 13.3 | CF17: 0 | CJ17: 8.5 | CK17: 8.3 | CL17: -25.4 | CU17: -3.4 | CV17: 0 | CY17: 1.3 | CZ17: -0.1 | DA17: -0.9 | DB17: 0 | DC17: 1.3 | DD17: 1.8 | DE17: -0.9 | DF17: 1.94 | DG17: 0.5 | DI17: 0 | DJ17: 0 | DK17: -8.5 | DL17: -16.5 | DM17: 1.5 | DN17: 0.5 | DO17: 0.7 | DP17: 0.9 | DQ17: 0 | DR17: 0.1 | DS17: 0.2 | DT17: 0.2 | DV17: -3.9 | DW17: 0.2 | DX17: 2.3 | DY17: 2.2 | DZ17: 1.3 | EA17: 0.8 | EB17: 4 | EC17: 0 | ED17: -2.2 | EE17: -2.3 | EF17: 5.2 | EG17: 6.8 | EH17: 2.6 | EI17: 0 | EJ17: 1.7 | EK17: 0.2 | EL17: 0.2 | EM17: 0.1 | EN17: 0 | EO17: 0 | EP17: 0 | EQ17: -0.2 | ER17: 1.9 | ES17: 3.3 | ET17: 0 | EU17: 0 | EV17: 1.2 | EW17: 1.6 | EX17: 2.5 | EY17: 5.2 | EZ17: 6.8 | FA17: 0.8 | FB17: 1.7 | FC17: 3 | FD17: 2.3 | FE17: 3.6 | FF17: 11.74 | FH17: 2.74693 | FJ17: 0.446 | FK17: 1.232 | FL17: 1 | FN17: 0.05191 | FO17: -0.1 | FP17: 0.9 | FQ17: 6.27684
A18: 21/01/2025 | B18: 04:00 | C18: 0.2 | E18: -0.1 | F18: 6.9 | G18: 12.5 | J18: -20.4 | K18: 10 | N18: -39.9 | O18: -49.9 | P18: -19.3 | Q18: 17.7 | R18: 6.1 | S18: -15.1 | T18: 78.3 | U18: 0.1 | Z18: 5.2 | AA18: 1.3 | AB18: 0 | AC18: -3.5 | AD18: 1.6 | AE18: 9.8 | AF18: 1.9 | AJ18: 12 | AK18: 13.4 | AO18: -1.7 | AP18: 23.4 | AQ18: 11.2 | AR18: 0 | AS18: -0.4 | AT18: 1.2 | AU18: 2.7 | AV18: 1.3 | AW18: -17.5 | AX18: -32.2 | AY18: 0 | AZ18: 6.1 | BA18: -0.8 | BB18: -0.1 | BC18: -3 | BD18: 3.3 | BE18: 0.9 | BF18: -0.1 | BG18: 1.5 | BH18: -1.8 | BK18: -0.3 | BO18: 3.6 | BQ18: 0 | BT18: 0 | BY18: -7.8 | CB18: 10.5 | CC18: 17.6 | CD18: -3.8 | CE18: 13.7 | CF18: 0.2 | CJ18: 5 | CK18: 5 | CL18: -30 | CU18: -3.4 | CV18: 0 | CY18: 1.3 | CZ18: 0 | DA18: -0.8 | DB18: 0 | DC18: 1.2 | DD18: 1.9 | DE18: -0.8 | DF18: 1.99 | DG18: 0.5 | DI18: 0 | DJ18: 0 | DK18: -8.7 | DL18: -17.1 | DM18: 1.5 | DN18: 0.5 | DO18: 0.7 | DP18: 0.9 | DQ18: 0 | DR18: 0.1 | DS18: 0.3 | DT18: 0.2 | DV18: -3.8 | DW18: 0.2 | DX18: 2.3 | DY18: 2.2 | DZ18: 1.2 | EA18: 0.8 | EB18: 4 | EC18: 0 | ED18: -3.5 | EE18: -3.1 | EF18: 5.2 | EG18: 5.1 | EH18: 2.6 | EI18: 0 | EJ18: 1.6 | EK18: 0.2 | EL18: 0.2 | EM18: 0.1 | EN18: 0 | EO18: 0 | EP18: 0 | EQ18: -0.2 | ER18: 1.2 | ES18: 3.3 | ET18: 0 | EU18: 0 | EV18: 1.2 | EW18: 1.5 | EX18: 2.5 | EY18: 5.2 | EZ18: 5.1 | FA18: 0.8 | FB18: 1.5 | FC18: 0.2 | FD18: 2.3 | FE18: 3.8 | FF18: 60.49 | FH18: 2.99759 | FJ18: 0.47 | FK18: 1.028 | FL18: 1 | FN18: 0.05034 | FO18: -0.3 | FP18: 0.9 | FQ18: 6.14593
A19: 21/01/2025 | B19: 04:30 | C19: 0.2 | E19: -0.2 | F19: 3.7 | G19: 12.6 | J19: -23.2 | K19: 1.9 | N19: -37.2 | O19: -58.3 | P19: -28.5 | Q19: 20.6 | R19: 6.8 | S19: -14.6 | T19: 77.5 | U19: -0.1 | Z19: 3.9 | AA19: 1.8 | AB19: 0 | AC19: -3.3 | AD19: 1.7 | AE19: 11.4 | AF19: 2.1 | AJ19: 10 | AK19: 14.4 | AO19: -1.5 | AP19: 43 | AQ19: 11.5 | AR19: 0 | AS19: 0.3 | AT19: 1.1 | AU19: 2.7 | AV19: 0.5 | AW19: -16.6 | AX19: -31.4 | AY19: 0 | AZ19: 9.9 | BA19: -0.5 | BB19: 0.2 | BC19: -5.4 | BD19: 0.1 | BE19: 0.9 | BF19: -0.1 | BG19: -6 | BH19: -0.7 | BK19: -2.7 | BO19: 14.2 | BQ19: 0 | BT19: 0 | BY19: -11.4 | CB19: 11.4 | CC19: 18 | CD19: -3 | CE19: 13.5 | CF19: -2 | CJ19: 7.1 | CK19: 6.8 | CL19: -27.5 | CU19: -3.5 | CV19: 0 | CY19: 1.3 | CZ19: -0.1 | DA19: -0.9 | DB19: 0 | DC19: 1.3 | DD19: 1.8 | DE19: -1.3 | DF19: 1.98 | DG19: 0.5 | DI19: 0 | DJ19: 0 | DK19: -9.5 | DL19: -19.4 | DM19: 1.5 | DN19: 0.5 | DO19: 0.7 | DP19: 0.9 | DQ19: 0 | DR19: 0 | DS19: 0.3 | DT19: 0.2 | DV19: -3.9 | DW19: 0.2 | DX19: 2.3 | DY19: 2.2 | DZ19: 1.1 | EA19: 0.8 | EB19: 4 | EC19: 0 | ED19: -3.8 | EE19: -3.5 | EF19: 5.2 | EG19: 5.2 | EH19: 2.6 | EI19: -0.1 | EJ19: 1.7 | EK19: 0.2 | EL19: 0.2 | EM19: 0.1 | EN19: 0 | EO19: 0 | EP19: 0 | EQ19: -0.2 | ER19: 5.9 | ES19: 3 | ET19: 0 | EU19: 0 | EV19: 1.2 | EW19: 1.4 | EX19: 2.5 | EY19: 5.2 | EZ19: 5.2 | FA19: 0.8 | FB19: 1.6 | FC19: 0.3 | FD19: 0.7 | FE19: 3.8 | FF19: 57.78 | FH19: 3.23709 | FJ19: 0.323 | FK19: 1.202 | FL19: 1.2 | FN19: 0.04725 | FO19: -0.2 | FP19: 1.2 | FQ19: 7.00934
A20: 21/01/2025 | B20: 05:00 | C20: 0.2 | E20: -0.1 | F20: 20.6 | G20: 14.8 | J20: -21 | K20: 2.7 | N20: -34.9 | O20: -48.5 | P20: -20.2 | Q20: 21.4 | R20: 7.1 | S20: -13 | T20: 75.6 | U20: 0 | Z20: 4.8 | AA20: 1.7 | AB20: 0 | AC20: -3.4 | AD20: 1.7 | AE20: 11.3 | AF20: 2.1 | AJ20: 11.6 | AK20: 14.2 | AO20: -1.6 | AP20: 33.2 | AQ20: 10.9 | AR20: 0 | AS20: 0.3 | AT20: 0.4 | AU20: 2.7 | AV20: 1 | AW20: -17.2 | AX20: -32 | AY20: 0 | AZ20: 8.2 | BA20: -0.7 | BB20: 0 | BC20: -3.7 | BD20: 2.3 | BE20: 1 | BF20: -0.1 | BG20: -1.4 | BH20: -0.7 | BK20: -2.8 | BO20: 10.9 | BQ20: 0 | BT20: 0 | BY20: -9 | CB20: 10.1 | CC20: 17.1 | CD20: -2.1 | CE20: 14 | CF20: -1.9 | CJ20: 6.4 | CK20: 6.3 | CL20: -29 | CU20: -3.5 | CV20: 0 | CY20: 1.3 | CZ20: 0 | DA20: -0.9 | DB20: 0 | DC20: 1.2 | DD20: 1.8 | DE20: -1 | DF20: 1.97 | DG20: 0.6 | DI20: 0 | DJ20: 0 | DK20: -9.6 | DL20: -19.8 | DM20: 1.5 | DN20: 0.5 | DO20: 0.7 | DP20: 0.9 | DQ20: 0.3 | DR20: 0.3 | DS20: 0.3 | DT20: 0.2 | DV20: -4 | DW20: 0.3 | DX20: 2.3 | DY20: 2.2 | DZ20: 1.1 | EA20: 0.8 | EB20: 4 | EC20: 0.4 | ED20: 0.1 | EE20: 0.2 | EF20: 5.2 | EG20: 9.4 | EH20: 2.6 | EI20: 0 | EJ20: 1.7 | EK20: 0.2 | EL20: 0.2 | EM20: 0.1 | EN20: 0 | EO20: 0 | EP20: 0 | EQ20: -0.2 | ER20: 6.4 | ES20: 3.1 | ET20: 0 | EU20: 0 | EV20: 1.2 | EW20: 1.4 | EX20: 2.4 | EY20: 5.2 | EZ20: 9.4 | FA20: 0.8 | FB20: 1.6 | FC20: 0.1 | FD20: 0.5 | FE20: 3.9 | FF20: 110.67 | FH20: 3.0933 | FJ20: 0.616 | FK20: 1.32 | FL20: 1.1 | FN20: 0.05506 | FO20: -0.4 | FP20: 1.1 | FQ20: 6.88436
A21: 21/01/2025 | B21: 05:30 | C21: 0.2 | E21: -0.1 | F21: 15.7 | G21: 15.2 | J21: -19.1 | K21: -0.7 | N21: -30.4 | O21: -36.4 | P21: -7.1 | Q21: 29.4 | R21: 8.2 | S21: -12.1 | T21: 73.9 | U21: 0.1 | Z21: 5.1 | AA21: 1.7 | AB21: 0 | AC21: -3.3 | AD21: 1.7 | AE21: 11.3 | AF21: 2.2 | AJ21: 12.4 | AK21: 15.6 | AO21: -1.7 | AP21: -0.6 | AQ21: 10.7 | AR21: 0 | AS21: -0.2 | AT21: -0.2 | AU21: 2.7 | AV21: 1.3 | AW21: -15.3 | AX21: -33.4 | AY21: 0 | AZ21: 5.3 | BA21: -0.9 | BB21: -0.3 | BC21: -2.1 | BD21: 3.6 | BE21: 0.9 | BF21: 0 | BG21: 5 | BH21: -1.1 | BK21: -1.8 | BO21: -2.6 | BQ21: 0 | BT21: 0 | BY21: -6.3 | CB21: 10.1 | CC21: 18.5 | CD21: -3.8 | CE21: 13.5 | CF21: -1.9 | CJ21: 6.6 | CK21: 7 | CL21: -28 | CU21: -3.6 | CV21: 0 | CY21: 1.3 | CZ21: -0.1 | DA21: -0.8 | DB21: 0 | DC21: 1.2 | DD21: 1.8 | DE21: -1.4 | DF21: 1.51 | DG21: 0.6 | DI21: 0 | DJ21: 0 | DK21: -9.5 | DL21: -20.2 | DM21: 1.5 | DN21: 0.5 | DO21: 0.7 | DP21: 0.9 | DQ21: 0.3 | DR21: 0 | DS21: 0.3 | DT21: 0.2 | DV21: -4.2 | DW21: 0.3 | DX21: 2.4 | DY21: 2.2 | DZ21: 1.3 | EA21: 0.8 | EB21: 4 | EC21: 0.3 | ED21: 0.3 | EE21: -0.3 | EF21: 5.2 | EG21: 9.8 | EH21: 2.6 | EI21: -0.1 | EJ21: 1.7 | EK21: 0.2 | EL21: 0.2 | EM21: 0.1 | EN21: 0 | EO21: 0 | EP21: 0 | EQ21: -0.2 | ER21: 8.3 | ES21: 2.3 | ET21: 1.2 | EU21: 0 | EV21: 1.2 | EW21: 1.6 | EX21: 2.1 | EY21: 5.2 | EZ21: 9.8 | FA21: 0.8 | FB21: 1.8 | FC21: 0.9 | FD21: 0.5 | FE21: 3.9 | FF21: 109.91 | FH21: 2.84538 | FJ21: 0.641 | FK21: 1.044 | FL21: 1 | FN21: 0.0512 | FO21: -0.2 | FP21: 0.6 | FQ21: 5.98158
A22: 21/01/2025 | B22: 06:00 | C22: 0.2 | E22: -0.1 | F22: 7.8 | G22: 14 | J22: -20.9 | K22: 4.5 | N22: -32.2 | O22: -34.4 | P22: -4.3 | Q22: 28.5 | R22: 8.8 | S22: -13.4 | T22: 75.3 | U22: 0.1 | Z22: 1 | AA22: 1.2 | AB22: 0 | AC22: -3.4 | AD22: 1.6 | AE22: 8.7 | AF22: 2 | AJ22: 11.4 | AK22: 15.4 | AO22: -1.7 | AP22: -10.4 | AQ22: 8.5 | AR22: 0 | AS22: -0.3 | AT22: 0 | AU22: 2.7 | AV22: 0.9 | AW22: -12.1 | AX22: -33.5 | AY22: 0 | AZ22: 5.6 | BA22: -1 | BB22: -0.1 | BC22: -1.8 | BD22: 2.6 | BE22: 0.9 | BF22: -0.1 | BG22: 5.8 | BH22: -0.7 | BK22: -2.1 | BO22: -2.2 | BQ22: 0 | BT22: 0 | BY22: -6 | CB22: 11.1 | CC22: 16.6 | CD22: -4.6 | CE22: 13.4 | CF22: -2 | CJ22: 6.2 | CK22: 6.2 | CL22: -28 | CU22: -4.2 | CV22: 2 | CY22: 1.3 | CZ22: 0 | DA22: -0.8 | DB22: 0 | DC22: 1.1 | DD22: 1.8 | DE22: -1.6 | DF22: 0.56 | DG22: 0.5 | DI22: 0 | DJ22: 0 | DK22: -9.6 | DL22: -20.5 | DM22: 1.5 | DN22: 0.5 | DO22: 0.7 | DP22: 0.9 | DQ22: 0.3 | DR22: 0.2 | DS22: 0.2 | DT22: 0.2 | DV22: -4.3 | DW22: 0.3 | DX22: 2.4 | DY22: 2.2 | DZ22: 1.3 | EA22: 0.8 | EB22: 4 | EC22: -0.2 | ED22: -0.2 | EE22: -0.4 | EF22: 5.2 | EG22: 10.2 | EH22: 2.6 | EI22: 0 | EJ22: 1.5 | EK22: 0.2 | EL22: 0.2 | EM22: 0.1 | EN22: 0 | EO22: 0 | EP22: 0 | EQ22: -0.2 | ER22: 5.4 | ES22: 2.7 | ET22: 1.2 | EU22: 0 | EV22: 1.2 | EW22: 1.6 | EX22: 2.6 | EY22: 5.2 | EZ22: 10.2 | FA22: 0.8 | FB22: 1.7 | FC22: 2.3 | FD22: 0.6 | FE22: 3.6 | FF22: 85.56 | FH22: 2.67197 | FJ22: 0.035 | FK22: 1.252 | FL22: 1 | FN22: 0.04387 | FO22: -0.1 | FP22: 1 | FQ22: 5.90284
... A58: 22/01/2025 | B58: 00:00 | C58: 0.2 | E58: -0.2 | F58: 48.1 | G58: 19.6 | J58: -11.5 | K58: 9.2 | N58: -20.9 | O58: -21.5 | P58: 0.5 | Q58: 29 | R58: 22.6 | S58: -2.5 | T58: 91.5 | U58: 0 | Z58: 5.6 | AA58: 1.2 | AB58: 0 | AC58: -3.3 | AD58: 1.5 | AE58: 16.6 | AF58: 1.4 | AJ58: 12.3 | AK58: 17.3 | AO58: -1.3 | AP58: 48.9 | AQ58: 10.5 | AR58: 4.8 | AS58: 2.2 | AT58: 0.3 | AU58: 2.7 | AV58: 0.7 | AW58: 23.6 | AX58: -4.1 | AY58: -43.3 | AZ58: 9.6 | BA58: -0.8 | BB58: 1.4 | BC58: -1.4 | BD58: 3.8 | BE58: 1 | BF58: -0.1 | BG58: 0.7 | BH58: 2.7 | BK58: -4.3 | BO58: 18.2 | BQ58: 0 | BT58: 0 | BY58: -9.7 | CB58: 4.1 | CC58: 16.6 | CD58: 0.4 | CE58: 1.7 | CF58: -4 | CJ58: 17.3 | CK58: 17.1 | CL58: -23.5 | CU58: -3.2 | CV58: 0 | CY58: 1.3 | CZ58: -0.1 | DA58: -0.9 | DB58: 0 | DC58: 1.4 | DD58: 1.8 | DE58: -0.4 | DF58: 1.99 | DG58: 0.5 | DI58: 0 | DJ58: 0 | DK58: 0 | DL58: 0 | DM58: 1.5 | DN58: 0.5 | DO58: 0.7 | DP58: 0.8 | DQ58: 0 | DR58: -0.1 | DS58: 0.2 | DT58: 0.2 | DV58: -3.9 | DW58: 0 | DX58: 2.3 | DY58: 2.9 | DZ58: 1.1 | EA58: 0.8 | EB58: 4 | EC58: 0 | ED58: 1.8 | EE58: 0.8 | EF58: 5.3 | EG58: 2.3 | EH58: 2.6 | EI58: -0.1 | EJ58: 1.5 | EK58: 0.2 | EL58: 0.2 | EM58: 0.1 | EN58: 0 | EO58: 0 | EP58: 0 | EQ58: -0.2 | ER58: 1.5 | ES58: 3.6 | ET58: 0 | EU58: 0 | EV58: 0.4 | EW58: 1.4 | EX58: 2.5 | EY58: 5.3 | EZ58: 2.3 | FA58: 0.9 | FB58: 1.3 | FC58: 1.4 | FD58: 1 | FE58: 2.8 | FF58: 364.79 | FH58: 2.91532 | FJ58: 0.507 | FK58: 1.312 | FL58: 1 | FN58: 1.36352 | FO58: -0.3 | FP58: 2.4 | FQ58: 9.19784
A59: EJEC | C59: 4.8 | D59: 0 | E59: -0.45 | F59: 1699.65 | G59: 683.4 | H59: 0 | I59: 0 | J59: -236.25 | K59: 394.7 | L59: 0 | M59: 0 | N59: -278.25 | O59: -267.35 | P59: -4.7 | Q59: 1038.55 | R59: 523.7 | S59: -85.2 | T59: 1585.2 | U59: 0.45 | V59: 0 | W59: 0 | X59: 0 | Y59: 0 | Z59: 82.15 | AA59: 24.85 | AB59: 30.95 | AC59: -80.7 | AD59: 39.95 | AE59: 424.25 | AF59: 43 | AG59: 0 | AH59: 0 | AI59: 0 | AJ59: 239.2 | AK59: 394.4 | AL59: 0 | AM59: 0 | AN59: 0 | AO59: -32.85 | AP59: 938.65 | AQ59: 228.1 | AR59: 82.85 | AS59: 28.55 | AT59: 4.75 | AU59: 64.8 | AV59: 26.9 | AW59: 275 | AX59: -107.6 | AY59: -152.75 | AZ59: 217.8 | BA59: -23.4 | BB59: 13.35 | BC59: -63.3 | BD59: 101.75 | BE59: 22.95 | BF59: 0.15 | BG59: 19.75 | BH59: 113.75 | BI59: 0 | BJ59: 0 | BK59: 29.15 | BL59: 0 | BM59: 0 | BN59: 0 | BO59: 299.4 | BP59: 0 | BQ59: -17.75 | BR59: 0 | BS59: 0 | BT59: 22.35 | BU59: 0 | BV59: 0 | BW59: 0 | BX59: 0 | BY59: -86.6 | BZ59: 0 | CA59: 0 | CB59: 1224.1 | CC59: 809.4 | CD59: 106.25 | CE59: 288.95 | CF59: 15.95 | CG59: 0 | CH59: 0 | CI59: 0 | CJ59: 799.75 | CK59: 797.85 | CL59: -271.7 | CM59: 0 | CN59: 0 | CO59: 0 | CP59: 0 | CQ59: 0 | CR59: 0 | CS59: 0 | CT59: 0 | CU59: -77.7 | CV59: 82.35 | CW59: 0 | CX59: 0 | CY59: 30 | CZ59: -1.75 | DA59: -19.45 | DB59: -1.8 | DC59: 39.6 | DD59: 42.75 | DE59: -15.3 | DF59: 42.43 | DG59: 13.5 | DH59: 0 | DI59: -5.15 | DJ59: -11.1 | DK59: -73.9 | DL59: -98.25 | DM59: 35.7 | DN59: 12.7 | DO59: 16.4 | DP59: 19.95 | DQ59: -24.2 | DR59: 0.55 | DS59: 8.2 | DT59: 8.1 | DU59: 0 | DV59: -93.55 | DW59: 5.1 | DX59: 65.3 | DY59: 61.55 | DZ59: 36.85 | EA59: 19.2 | EB59: 95.7 | EC59: 18.5 | ED59: -69.5 | EE59: -67.6 | EF59: 126.25 | EG59: 243.8 | EH59: 62.4 | EI59: -0.75 | EJ59: 39.95 | EK59: 4.5 | EL59: 4.55 | EM59: 2.35 | EN59: 0.2 | EO59: 12.15 | EP59: 116.55 | EQ59: -4.8 | ER59: 100.8 | ES59: 57.75 | ET59: -44.45 | EU59: 13.8 | EV59: 29.9 | EW59: 44.5 | EX59: 60.85 | EY59: 126.25 | EZ59: 243.8 | FA59: 19.7 | FB59: 39.2 | FC59: 60.65 | FD59: 36.6 | FE59: 74.85 | FF59: 13599.13 | FH59: 68.62833 | FI59: 0 | FJ59: -3.4375 | FK59: 31.917 | FL59: 25.5 | FM59: 0 | FN59: 52.382135 | FO59: 9.5 | FP59: 41.05 | FQ59: 225.53996

Sheet DEMANDA_AREAS
B3: martes, 21 de Enero del 2025
B5: REPORTE DE LA DEMANDA POR ÁREAS Y SUBAREAS OPERATIVAS (MW)
B6: FECHA HORA | C6: DEMANDA | E6: AREA | H6: SUBAREAS
C7: INTERCAMBIOS INTERNACIONALES | D7: SEIN | E7: NORTE | F7: CENTRO | G7: SUR | H7: ELECTROANDES
B8: 00:30 | C8: 0 | D8: 6621.05 | E8: 980.005 | F8: 3866.695 | G8: 1774.35 | H8: 201.814
B9: 01:00 | C9: 0 | D9: 6615.6 | E9: 992.818 | F9: 3857.422 | G9: 1765.36 | H9: 207.236
B10: 01:30 | C10: 0 | D10: 6404.84 | E10: 948.173 | F10: 3708.137 | G10: 1748.53 | H10: 209.936
B11: 02:00 | C11: 0 | D11: 6426.49 | E11: 929.908 | F11: 3767.672 | G11: 1728.91 | H11: 212.314
B12: 02:30 | C12: 0 | D12: 6397.35 | E12: 967.053 | F12: 3699.527 | G12: 1730.77 | H12: 196.641
B13: 03:00 | C13: 0 | D13: 6313.34 | E13: 919.411 | F13: 3662.709 | G13: 1731.22 | H13: 208.08
B14: 03:30 | C14: 0 | D14: 6351.64 | E14: 910.52 | F14: 3695.49 | G14: 1745.63 | H14: 205.422
B15: 04:00 | C15: 0 | D15: 6356.92 | E15: 920.207 | F15: 3690.953 | G15: 1745.76 | H15: 206.637
B16: 04:30 | C16: 0 | D16: 6455.07 | E16: 916.917 | F16: 3777.703 | G16: 1760.45 | H16: 205.377
B17: 05:00 | C17: 0 | D17: 6484.88 | E17: 911.764 | F17: 3803.706 | G17: 1769.41 | H17: 203.559
B18: 05:30 | C18: 0 | D18: 6535.05 | E18: 928.67 | F18: 3840.17 | G18: 1766.21 | H18: 203.482
B19: 06:00 | C19: 0 | D19: 6534.57 | E19: 969.925 | F19: 3829.445 | G19: 1735.2 | H19: 196.172
... B59: ENERGÍA | C59: 0 | D59: 174302.29 | E59: 26035.57 | F59: 105372.06 | G59: 42894.66 | H59: 4765.8235
B61: LEYENDA:
D63: Potencia recibida del Ecuador
D64: Potencia entregada al Ecuador

Sheet DEMANDA_UL
B3: martes, 21 de Enero del 2025
B5: POTENCIA DE LOS GRANDES USUARIOS LIBRES (MW)
B6: FECHA HORA | C6: GRANDES USUARIOS LIBRES DEL ÁREA NORTE | X6: GRANDES USUARIOS LIBRES DEL ÁREA CENTRO | BP6: GRANDES USUARIOS LIBRES DEL ÁREA SUR
C7: ARCA CONTINENTAL LINDLEY S.A. | D7: AUSTRAL GROUP S.A.A | E7: CEMENTOS PACASMAYO | F7: CORPORACIÓN PESQUERA INCA S.A.C. | G7: CREDITEX: CIA IND.TEXTIL CREDISA | H7: HIPERMERCADOS TOTTUS S.A | I7: INDUSTRIA TEXTIL PIURA | J7: MINERA BOROO MISQUICHILCA S.A. | K7: MINERA GOLD FIELDS | L7: MINERA HORIZONTE | M7: MINERA MARSA | N7: MINERA MISKY MAYO | O7: MINERA YANACOCHA | P7: OPEN PLAZA | Q7: PESQUERA DIAMANTE | R7: PETROPERU | S7: REAL PLAZA S.R.L. | T7: SIDER PERU | U7: SUPERMERCADOS PERUANOS S.A. | V7: TRUPAL S.A. | W7: UNIÓN DE CERVECERÍAS PERUANAS BACKUS Y JOHNSTON S. | X7: ACEROS AREQUIPA | Y7: ADMINISTRADORA JOCKEY PLAZA SHOPPING CENTER S.A. | Z7: ALICORP | AA7: ARCA CONTINENTAL LINDLEY S.A. | AB7: AUSTRAL GROUP S.A.A | AC7: COMPAÑIA MINERA CONDESTABLE | AD7: CORPORACIÓN PESQUERA INCA S.A.C. | AE7: CREDITEX: CIA IND.TEXTIL CREDISA | AF7: FUNDICION CHILCA S.A. | AG7: HIPERMERCADOS TOTTUS S.A | AH7: INMOBILIARIA KANPU S.A. | AI7: INMUEBLES PANAMERICANA S.A. | AJ7: KIMBERLY-CLARK PERU | AK7: LECHE GLORIA S.A. | AL7: MALL AVENTURA S.A. | AM7: MARCOBRE S.A.C. | AN7: MINERA ANTAMINA | AO7: MINERA ARES | AP7: MINERA BUENAVENTURA | AQ7: MINERA CHINALCO PERÚ S.A. | AR7: MINERA SHOUXIN PERU S.A. | AS7: MINERA VOLCAN | AT7: MINSUR | AU7: MOLYCOP-ADESUR | AV7: NEXA RESOURCES CAJAMARQUILLA S.A. | AW7: NEXA RESOURCES PERÚ S.A.A. | AX7: OPEN PLAZA | AY7: OPP FILM | AZ7: OWENS-ILLINOIS PERÚ S.A. | BA7: PAPELERA NACIONAL S.A. | BB7: PESQUERA DIAMANTE | BC7: QUIMPAC S.A. | BD7: REAL PLAZA S.R.L. | BE7: REFINERIA LA PAMPILLA S.A.A | BF7: SAGA FALABELLA | BG7: SAN MIGUEL INDUSTRIAS PET S.A. | BH7: SHOUGANG HIERRO PERU | BI7: SOFTYS PERU S.A.C. | BJ7: SUPERMERCADOS PERUANOS S.A. | BK7: TEJIDOS SAN JACINTO | BL7: TREN URBANO DE LIMA S.A. | BM7: TRUPAL S.A. | BN7: UNACEM PERU S.A. | BO7: UNIÓN DE CERVECERÍAS PERUANAS BACKUS Y JOHNSTON S. | BP7: ANGLO AMERICAN QUELLAVECO S.A. | BQ7: ARCA CONTINENTAL LINDLEY S.A. | BR7: CAL & CEMENTO SUR S.A. | BS7: COMPAÑIA MINERA ANTAPACCAY S.A. | BT7: COMPAÑÍA MINERA CHUNGAR SAC | BU7: COMPAÑIA MINERA SAN IGNACIO DE MOROCOCHA S.A.A. | BV7: EL BROCAL .S.A. | BW7: EMPRESA ADMINISTRADORA CERRO S.A.C. | BX7: EMPRESA MINERA LOS QUENUALES S.A.C. | BY7: HIPERMERCADOS TOTTUS S.A | BZ7: HUDBAY PERU S.A.C. | CA7: INDUSTRIA CACHIMAYO | CB7: MALL AVENTURA S.A. | CC7: MINERA ARES | CD7: MINERA BUENAVENTURA | CE7: MINERA CERRO VERDE | CF7: MINERA CORONA | CG7: MINERA LAS BAMBAS S.A. | CH7: MINERA VOLCAN | CI7: MINSUR | CJ7: MOLYCOP-ADESUR | CK7: NEXA RESOURCES PERÚ S.A.A. | CL7: OXIDOS DE PASCO S.A.C. | CM7: PESQUERA DIAMANTE | CN7: REAL PLAZA S.R.L. | CO7: SOBREANDES S.A.C. | CP7: SOUTHERN PERU CC | CQ7: SUPERMERCADOS PERUANOS S.A. | CR7: UNACEM PERU S.A. | CS7: UNIÓN DE CERVECERÍAS PERUANAS BACKUS Y JOHNSTON S. | CT7: YURA
B8: 00:30 | E8: 30.3625 | J8: 20.4708 | K8: 25.5399 | L8: 12.138 | M8: 14.5689 | N8: 12.17 | O8: 28.818 | R8: 40.041 | T8: 19.9293 | V8: 0.6 | X8: 117.34996 | Z8: 7.98934 | AH8: 7.6071 | AJ8: 5.33786 | AK8: 0 | AL8: 1.4718 | AM8: 43.42138 | AN8: 41.98253 | AO8: 26.6187 | AP8: 0.81 | AQ8: 147.31 | AS8: 36.81362 | AT8: 28.72816 | AV8: 196.3933 | AW8: 36.743 | AY8: 3.06504 | BA8: 4.8 | BC8: 71.64499 | BE8: 18.9 | BI8: 22.72409 | BK8: 5.67907 | BM8: 6.909 | BN8: 29.83 | BP8: 140.83819 | BR8: 4.44398 | BS8: 127.4889 | BT8: 11.435 | BV8: 32.1415 | BW8: 3.85819 | BZ8: 91.0024 | CA8: 22.37935 | CB8: 0.4846 | CC8: 0.733 | CD8: 27.9511 | CE8: 454.71284 | CF8: 11.7802 | CG8: 157.251 | CH8: 17.60867 | CK8: 13.8838 | CL8: 4.99205 | CO8: 14.63471 | CP8: 267.78 | CR8: 36.929 | CS8: 2.18299
B9: 01:00 | E9: 31.1776 | J9: 20.0311 | K9: 25.1255 | L9: 12.561 | M9: 14.1411 | N9: 12.4 | O9: 28.654 | R9: 40.03 | T9: 41.4216 | V9: 0.7 | X9: 105.05838 | Z9: 7.78087 | AH9: 6.374 | AJ9: 5.33431 | AK9: 0 | AL9: 1.3557 | AM9: 42.93017 | AN9: 44.76898 | AO9: 26.7757 | AP9: 0.7 | AQ9: 147.09 | AS9: 37.28341 | AT9: 28.85582 | AV9: 195.5604 | AW9: 36.3906 | AY9: 3.08286 | BA9: 4.8 | BC9: 69.69994 | BE9: 18.9 | BI9: 22.57252 | BK9: 5.80424 | BM9: 7.133 | BN9: 24.4 | BP9: 142.79337 | BR9: 4.4564 | BS9: 125.1703 | BT9: 11.66292 | BV9: 33.2997 | BW9: 3.96348 | BZ9: 91.2143 | CA9: 22.39809 | CB9: 0.4502 | CC9: 0.734 | CD9: 27.51295 | CE9: 451.71015 | CF9: 11.9169 | CG9: 155.606 | CH9: 17.90235 | CK9: 14.0951 | CL9: 5.01613 | CO9: 14.97606 | CP9: 272.97 | CR9: 36.931 | CS9: 2.61971
B10: 01:30 | E10: 30.5239 | J10: 20.3428 | K10: 25.3486 | L10: 12.913 | M10: 13.4336 | N10: 12.43 | O10: 29.256 | R10: 39.836 | T10: 43.0088 | V10: 0.7 | X10: 135.82692 | Z10: 7.84909 | AH10: 8.7233 | AJ10: 5.31128 | AK10: 0 | AL10: 1.2139 | AM10: 46.38775 | AN10: 42.19661 | AO10: 26.6126 | AP10: 0.64 | AQ10: 148.11 | AS10: 37.03763 | AT10: 29.66332 | AV10: 193.0323 | AW10: 36.2292 | AY10: 3.05171 | BA10: 4.8 | BC10: 67.49006 | BE10: 18.9 | BI10: 22.57409 | BK10: 5.68123 | BM10: 7.132 | BN10: 23.85 | BP10: 141.93686 | BR10: 4.41228 | BS10: 124.947 | BT10: 11.53461 | BV10: 32.376 | BW10: 4.0073 | BZ10: 91.371 | CA10: 22.43233 | CB10: 0.4094 | CC10: 0.73 | CD10: 27.65493 | CE10: 450.47189 | CF10: 11.8494 | CG10: 154.477 | CH10: 17.56501 | CK10: 14.3729 | CL10: 4.87274 | CO10: 14.76185 | CP10: 274.27 | CR10: 36.861 | CS10: 2.41199
B11: 02:00 | E11: 29.3616 | J11: 20.3833 | K11: 25.2313 | L11: 13.217 | M11: 12.8792 | N11: 12.37 | O11: 29.148 | R11: 39.575 | T11: 30.974 | V11: 0.7 | X11: 146.91763 | Z11: 7.098 | AH11: 8.8691 | AJ11: 5.27359 | AK11: 0 | AL11: 1.1744 | AM11: 46.05475 | AN11: 44.62475 | AO11: 27.0496 | AP11: 0.44 | AQ11: 146.94 | AS11: 36.7863 | AT11: 29.21812 | AV11: 192.2321 | AW11: 35.1294 | AY11: 3.05462 | BA11: 4.9 | BC11: 64.34858 | BE11: 18.9 | BI11: 22.70312 | BK11: 5.55619 | BM11: 6.889 | BN11: 27.7 | BP11: 141.26788 | BR11: 4.46008 | BS11: 126.0544 | BT11: 11.61152 | BV11: 31.9324 | BW11: 3.7307 | BZ11: 91.774 | CA11: 22.44566 | CB11: 0.3833 | CC11: 0.707 | CD11: 28.26548 | CE11: 427.32221 | CF11: 11.7916 | CG11: 151.486 | CH11: 17.71922 | CK11: 14.446 | CL11: 4.76301 | CO11: 14.84613 | CP11: 272.19 | CR11: 36.833 | CS11: 2.43473
B12: 02:30 | E12: 30.7097 | J12: 19.9876 | K12: 25.0389 | L12: 13.311 | M12: 11.6834 | N12: 12.4 | O12: 30.074 | R12: 39.735 | T12: 39.9049 | V12: 0.7 | X12: 137.40425 | Z12: 7.13133 | AH12: 3.8114 | AJ12: 5.22184 | AK12: 0 | AL12: 1.1454 | AM12: 46.06633 | AN12: 45.57812 | AO12: 26.9406 | AP12: 0.41 | AQ12: 147.47 | AS12: 36.35068 | AT12: 29.13425 | AV12: 192.1381 | AW12: 36.1828 | AY12: 3.08035 | BA12: 4.8 | BC12: 63.52176 | BE12: 18.9 | BI12: 22.74748 | BK12: 5.58824 | BM12: 6.896 | BN12: 32.57 | BP12: 141.52416 | BR12: 4.41426 | BS12: 126.7199 | BT12: 12.08704 | BV12: 30.4931 | BW12: 3.87202 | BZ12: 91.0741 | CA12: 22.45507 | CB12: 0.3849 | CC12: 0.72 | CD12: 28.00755 | CE12: 447.90977 | CF12: 11.8377 | CG12: 154.626 | CH12: 17.81844 | CK12: 14.5053 | CL12: 4.58528 | CO12: 14.87146 | CP12: 267.52 | CR12: 38.091 | CS12: 2.373
B13: 03:00 | E13: 30.8332 | J13: 20.3069 | K13: 25.0808 | L13: 12.97 | M13: 12.0579 | N13: 12.39 | O13: 30.102 | R13: 39.669 | T13: 44.6865 | V13: 0.7 | X13: 126.25662 | Z13: 7.09416 | AH13: 2.4955 | AJ13: 4.81592 | AK13: 0 | AL13: 1.1042 | AM13: 46.1322 | AN13: 48.70689 | AO13: 27.3271 | AP13: 0.67 | AQ13: 147.49 | AS13: 36.49354 | AT13: 29.32808 | AV13: 193.9509 | AW13: 36.3892 | AY13: 3.10756 | BA13: 4.9 | BC13: 68.65998 | BE13: 18.9 | BI13: 22.67542 | BK13: 5.7125 | BM13: 6.866 | BN13: 32.51 | BP13: 141.20142 | BR13: 4.29995 | BS13: 126.693 | BT13: 12.48452 | BV13: 31.615 | BW13: 3.96593 | BZ13: 91.7865 | CA13: 22.47382 | CB13: 0.3681 | CC13: 0.733 | CD13: 27.4042 | CE13: 430.90004 | CF13: 11.8919 | CG13: 153.931 | CH13: 17.88143 | CK13: 14.6648 | CL13: 4.6227 | CO13: 14.92974 | CP13: 276.29 | CR13: 37.984 | CS13: 2.43525
B14: 03:30 | E14: 30.6874 | J14: 19.6543 | K14: 25.3954 | L14: 13.118 | M14: 12.1682 | N14: 12.56 | O14: 29.882 | R14: 39.78 | T14: 36.6632 | V14: 0.7 | X14: 101.88763 | Z14: 6.99279 | AH14: 2.3034 | AJ14: 5.05719 | AK14: 0 | AL14: 1.0853 | AM14: 44.97481 | AN14: 53.02293 | AO14: 25.8647 | AP14: 0.48 | AQ14: 148.63 | AS14: 36.7094 | AT14: 28.98099 | AV14: 191.6154 | AW14: 38.0199 | AY14: 3.09904 | BA14: 4.9 | BC14: 70.75752 | BE14: 18.9 | BI14: 22.47481 | BK14: 5.71995 | BM14: 6.912 | BN14: 30.15 | BP14: 142.34762 | BR14: 4.25399 | BS14: 126.3088 | BT14: 11.73666 | BV14: 32.756 | BW14: 4.02736 | BZ14: 91.4885 | CA14: 22.46491 | CB14: 0.3535 | CC14: 0.705 | CD14: 26.95391 | CE14: 449.82334 | CF14: 11.7883 | CG14: 156.031 | CH14: 17.65729 | CK14: 14.3476 | CL14: 4.80961 | CO14: 15.29312 | CP14: 269.57 | CR14: 37.191 | CS14: 2.60898
B15: 04:00 | E15: 30.6467 | J15: 19.8836 | K15: 25.5965 | L15: 12.398 | M15: 12.4923 | N15: 12.6 | O15: 30.226 | R15: 39.51 | T15: 18.5735 | V15: 0.7 | X15: 105.00314 | Z15: 6.90949 | AH15: 7.5119 | AJ15: 5.19055 | AK15: 0 | AL15: 1.0633 | AM15: 46.07887 | AN15: 78.19981 | AO15: 25.6966 | AP15: 0.18 | AQ15: 149.94 | AS15: 35.42051 | AT15: 28.44689 | AV15: 191.1363 | AW15: 36.9282 | AY15: 3.04479 | BA15: 4.8 | BC15: 70.40557 | BE15: 18.9 | BI15: 22.47063 | BK15: 5.782 | BM15: 6.848 | BN15: 31.95 | BP15: 140.58168 | BR15: 4.29158 | BS15: 126.911 | BT15: 11.8398 | BV15: 32.9082 | BW15: 3.88656 | BZ15: 90.9666 | CA15: 22.45736 | CB15: 0.3438 | CC15: 0.747 | CD15: 26.73933 | CE15: 449.10072 | CF15: 11.526 | CG15: 154.392 | CH15: 17.77825 | CK15: 13.9249 | CL15: 4.72567 | CO15: 15.04606 | CP15: 274.94 | CR15: 36.924 | CS15: 2.45709
B16: 04:30 | E16: 29.7017 | J16: 19.7701 | K16: 25.6245 | L16: 12.513 | M16: 12.8583 | N16: 12.63 | O16: 30.126 | R16: 39.92 | T16: 33.3559 | V16: 0.7 | X16: 163.00831 | Z16: 6.94062 | AH16: 5.4303 | AJ16: 5.28152 | AK16: 0 | AL16: 1.0571 | AM16: 46.84425 | AN16: 103.35797 | AO16: 25.9854 | AP16: 1.65 | AQ16: 150.29 | AS16: 35.69325 | AT16: 27.70795 | AV16: 190.1684 | AW16: 36.2471 | AY16: 2.98964 | BA16: 4.9 | BC16: 71.35476 | BE16: 18.9 | BI16: 22.27421 | BK16: 5.84502 | BM16: 6.959 | BN16: 33.15 | BP16: 143.92467 | BR16: 4.29156 | BS16: 126.0071 | BT16: 11.42248 | BV16: 33.9266 | BW16: 3.90366 | BZ16: 92.2782 | CA16: 22.44741 | CB16: 0.3392 | CC16: 0.712 | CD16: 26.10062 | CE16: 451.59983 | CF16: 11.6785 | CG16: 154.818 | CH16: 17.68413 | CK16: 13.6759 | CL16: 4.77579 | CO16: 14.89212 | CP16: 279.02 | CR16: 37.523 | CS16: 2.52934
B17: 05:00 | E17: 29.0242 | J17: 19.6558 | K17: 25.7833 | L17: 12.331 | M17: 12.8642 | N17: 12.38 | O17: 29.682 | R17: 41.683 | T17: 37.6529 | V17: 0.8 | X17: 141.84608 | Z17: 7.11945 | AH17: 7.7857 | AJ17: 5.03627 | AK17: 0 | AL17: 1.0811 | AM17: 46.7084 | AN17: 101.07434 | AO17: 26.0781 | AP17: 2.1 | AQ17: 152.52 | AS17: 33.88779 | AT17: 27.37385 | AV17: 190.0308 | AW17: 35.8363 | AY17: 2.99674 | BA17: 4.3 | BC17: 71.23933 | BE17: 18.9 | BI17: 22.43275 | BK17: 5.87935 | BM17: 7.027 | BN17: 33.22 | BP17: 143.74818 | BR17: 4.39629 | BS17: 127.0484 | BT17: 12.04915 | BV17: 33.5598 | BW17: 4.37541 | BZ17: 91.1356 | CA17: 22.4441 | CB17: 0.3347 | CC17: 0.764 | CD17: 24.29726 | CE17: 448.78172 | CF17: 11.5378 | CG17: 151.634 | CH17: 17.65573 | CK17: 13.7083 | CL17: 4.78604 | CO17: 14.21556 | CP17: 279.28 | CR17: 37.625 | CS17: 2.44182
B18: 05:30 | E18: 29.715 | J18: 20.7033 | K18: 26.1082 | L18: 10.839 | M18: 13.138 | N18: 12.4 | O18: 30.494 | R18: 39.735 | T18: 43.1585 | V18: 0.7 | X18: 131.04123 | Z18: 6.94841 | AH18: 6.3878 | AJ18: 5.08865 | AK18: 0 | AL18: 1.0714 | AM18: 46.75695 | AN18: 105.38294 | AO18: 25.5199 | AP18: 1.93 | AQ18: 153.19 | AS18: 32.81146 | AT18: 26.95151 | AV18: 193.3912 | AW18: 34.95 | AY18: 3.01324 | BA18: 4.3 | BC18: 70.63737 | BE18: 18.9 | BI18: 22.53693 | BK18: 5.70749 | BM18: 6.957 | BN18: 32.86 | BP18: 143.09657 | BR18: 4.30327 | BS18: 125.6995 | BT18: 11.41274 | BV18: 33.015 | BW18: 3.85894 | BZ18: 91.7001 | CA18: 22.43621 | CB18: 0.3365 | CC18: 0.711 | CD18: 25.13093 | CE18: 444.59724 | CF18: 11.5006 | CG18: 152.766 | CH18: 18.05089 | CK18: 13.6349 | CL18: 4.8278 | CO18: 13.50249 | CP18: 279.98 | CR18: 37.58 | CS18: 2.3886
B19: 06:00 | E19: 29.9552 | J19: 20.726 | K19: 26.1136 | L19: 10.354 | M19: 13.017 | N19: 12.35 | O19: 31.238 | R19: 39.542 | T19: 48.1042 | V19: 0.7 | X19: 87.60337 | Z19: 7.15389 | AH19: 4.7145 | AJ19: 5.10208 | AK19: 0 | AL19: 1.094 | AM19: 46.36394 | AN19: 102.96231 | AO19: 24.4043 | AP19: 1.54 | AQ19: 154.05 | AS19: 32.88425 | AT19: 27.72835 | AV19: 193.0317 | AW19: 33.1644 | AY19: 3.03147 | BA19: 4.2 | BC19: 70.42627 | BE19: 18.9 | BI19: 22.33308 | BK19: 5.87294 | BM19: 7.004 | BN19: 33.12 | BP19: 143.9836 | BR19: 4.2733 | BS19: 124.872 | BT19: 10.86673 | BV19: 32.4162 | BW19: 3.65085 | BZ19: 91.6063 | CA19: 22.42956 | CB19: 0.3289 | CC19: 0.741 | CD19: 24.81623 | CE19: 439.61743 | CF19: 11.0078 | CG19: 154.778 | CH19: 17.8852 | CK19: 13.4752 | CL19: 4.74129 | CO19: 13.47994 | CP19: 278.2 | CR19: 38.219 | CS19: 2.56146
... B55: 00:00 | E55: 30.5609 | J55: 20.2602 | K55: 27.3517 | L55: 11.777 | M55: 11.768 | N55: 11.67 | O55: 32.306 | R55: 39.765 | T55: 13.1707 | V55: 1 | X55: 142.04038 | Z55: 7.87127 | AH55: 7.2478 | AJ55: 5.27586 | AK55: 0 | AL55: 2.3982 | AM55: 47.96408 | AN55: 131.5016 | AO55: 26.6434 | AP55: 0.83 | AQ55: 151.66 | AS55: 37.00717 | AT55: 28.42395 | AV55: 195.1319 | AW55: 37.0991 | AY55: 3.20677 | BA55: 5 | BC55: 72.43827 | BE55: 20.1 | BI55: 19.29538 | BK55: 5.41974 | BM55: 6.914 | BN55: 51.02 | BP55: 139.42623 | BR55: 4.53821 | BS55: 123.0274 | BT55: 12.43864 | BV55: 33.2296 | BW55: 3.83695 | BZ55: 90.2212 | CA55: 22.50696 | CB55: 0.9455 | CC55: 0.743 | CD55: 24.82958 | CE55: 448.09447 | CF55: 11.565 | CG55: 145.885 | CH55: 18.01714 | CK55: 14.6177 | CL55: 4.96076 | CO55: 15.12874 | CP55: 238.32 | CR55: 31.521 | CS55: 2.08667
B56: MWh | C56: 0 | D56: 0 | E56: 710.90025 | F56: 0 | G56: 0 | H56: 0 | I56: 0 | J56: 470.9835 | K56: 623.99965 | L56: 265.8395 | M56: 257.6191 | N56: 296.395 | O56: 735.072 | P56: 0 | Q56: 0 | R56: 951.578 | S56: 0 | T56: 638.2572 | U56: 0 | V56: 25.9 | W56: 0 | X56: 2567.2335 | Y56: 0 | Z56: 179.70293 | AA56: 0 | AB56: 0 | AC56: 0 | AD56: 0 | AE56: 0 | AF56: 0 | AG56: 0 | AH56: 87.73875 | AI56: 0 | AJ56: 118.96792 | AK56: 0 | AL56: 80.96585 | AM56: 1066.2976 | AN56: 2561.9429 | AO56: 620.786 | AP56: 18.01 | AQ56: 3587.48 | AR56: 0 | AS56: 835.66888 | AT56: 716.2619 | AU56: 0 | AV56: 3853.787 | AW56: 841.82075 | AX56: 0 | AY56: 72.656455 | AZ56: 0 | BA56: 114.55 | BB56: 0 | BC56: 1533.7578 | BD56: 0 | BE56: 470.6 | BF56: 0 | BG56: 0 | BH56: 0 | BI56: 495.51821 | BJ56: 0 | BK56: 137.52788 | BL56: 0 | BM56: 165.5995 | BN56: 694.17 | BO56: 0 | BP56: 3376.6236 | BQ56: 0 | BR56: 107.26614 | BS56: 2951.8178 | BT56: 266.86687 | BU56: 0 | BV56: 755.01035 | BW56: 93.491925 | BX56: 0 | BY56: 0 | BZ56: 2176.4664 | CA56: 432.46687 | CB56: 25.1451 | CC56: 17.6205 | CD56: 625.52346 | CE56: 10439.094 | CF56: 271.10515 | CG56: 3635.8045 | CH56: 414.62993 | CI56: 0 | CJ56: 0 | CK56: 322.5622 | CL56: 112.79681 | CM56: 0 | CN56: 0 | CO56: 344.6472 | CP56: 6076.765 | CQ56: 0 | CR56: 838.2025 | CS56: 52.87128 | CT56: 0
B59: Nota :
B60: Información proporcionada por la empresas
C62: DATOS ESTIMADOS
C64: SIN DATOS

Sheet TIPO_RECURSO
B3: martes, 21 de Enero del 2025
B5: REPORTE POTENCIA GENERADA POR TIPO DE RECURSO
B6: HORA | C6: H. PASADA | D6: H. REGULACION | E6: GAS DE CAMISEA | F6: GAS DE MALACAS | G6: GAS DE AGUAYTÍA | H6: RESIDUAL R500 | I6: DIESEL | J6: NAFTA+GAS DE REFINERIA | K6: FLEXIGAS+GAS DE REFINERIA | L6: BAGAZO | M6: BIOGAS | N6: SOLAR | O6: EOLICA | P6: TOTAL | U6: EMPRESA | V6: CENTRAL | W6: HIDROELECTRICA DE PASADA | X6: HIDROELECTRICA DE REGULACION
B7: 00:30 | C7: 1160.95 | D7: 3029.3 | E7: 1895.8 | F7: 47.6 | J7: =DESPACHO_EJECUTADO!EY11+DESPACHO_EJECUTADO!EZ11 -> 50.3 | L7: 50.5 | M7: 12.4 | N7: 0 | O7: 374.2 | P7: =SUM(C7:O7) -> 6621.05 | U7: ANDEAN POWER S.A.C. | V7: C.H. CARHUAC | W7: 285.4
B8: 01:00 | C8: 1174.5 | D8: 3066.8 | E8: 1861.4 | F8: 47.3 | J8: =DESPACHO_EJECUTADO!EY12+DESPACHO_EJECUTADO!EZ12 -> 50.7 | L8: 49.3 | M8: 12.4 | N8: 0 | O8: 353.2 | P8: =SUM(C8:O8) -> 6615.6 | U8: ASOCIACIÓN SANTA LUCIA DE CHACAS | V8: C.H. HUALLIN | W8: 46.25
B9: 01:30 | C9: 1155.84 | D9: 2976.2 | E9: 1777 | F9: 47.4 | J9: =DESPACHO_EJECUTADO!EY13+DESPACHO_EJECUTADO!EZ13 -> 51.1 | L9: 49.9 | M9: 12.4 | N9: 0 | O9: 335 | P9: =SUM(C9:O9) -> 6404.84 | U9: CELEPSA | V9: C.H. EL PLATANAL | X9: 5275.15
B10: 02:00 | C10: 1167.19 | D10: 3012.9 | E10: 1731.4 | F10: 47.2 | J10: =DESPACHO_EJECUTADO!EY14+DESPACHO_EJECUTADO!EZ14 -> 50.6 | L10: 50 | M10: 12.4 | N10: 0 | O10: 354.8 | P10: =SUM(C10:O10) -> 6426.49 | U10: CELEPSA RENOVABLES S.R.L. | V10: C.H. MARAÑON | W10: 475.45
B11: 02:30 | C11: 1166.35 | D11: 2920.7 | E11: 1768.3 | F11: 47.6 | J11: =DESPACHO_EJECUTADO!EY15+DESPACHO_EJECUTADO!EZ15 -> 50.9 | L11: 49.5 | M11: 12.4 | N11: 0 | O11: 381.6 | P11: =SUM(C11:O11) -> 6397.35 | U11: CENTRALES SANTA ROSA S.A.C. | V11: C.H. SANTA ROSA I | W11: 24.55
B12: 03:00 | C12: 1176.14 | D12: 2955.7 | E12: 1647.1 | F12: 47.2 | J12: =DESPACHO_EJECUTADO!EY16+DESPACHO_EJECUTADO!EZ16 -> 50.8 | L12: 49.3 | M12: 12.4 | N12: 0 | O12: 374.7 | P12: =SUM(C12:O12) -> 6313.34 | V12: C.H. SANTA ROSA II | W12: 38.1
B13: 03:30 | C13: 1167.44 | D13: 2900.9 | E13: 1714.5 | F13: 47.6 | J13: =DESPACHO_EJECUTADO!EY17+DESPACHO_EJECUTADO!EZ17 -> 50.8 | L13: 47.3 | M13: 12.4 | N13: 0 | O13: 410.7 | P13: =SUM(C13:O13) -> 6351.64 | U13: CHINANGO S.A.C. | V13: C.H. CHIMAY | X13: 1126.4
B14: 04:00 | C14: 1181.92 | D14: 2918 | E14: 1671.3 | F14: 47.6 | J14: =DESPACHO_EJECUTADO!EY18+DESPACHO_EJECUTADO!EZ18 -> 50.4 | L14: 47.7 | M14: 12.4 | N14: 0 | O14: 427.6 | P14: =SUM(C14:O14) -> 6356.92 | V14: C.H. YANANGO | W14: 1000.85
B15: 04:30 | C15: 1157.97 | D15: 2985.7 | E15: 1660.4 | F15: 47.7 | J15: =DESPACHO_EJECUTADO!EY19+DESPACHO_EJECUTADO!EZ19 -> 51.3 | L15: 47.8 | M15: 12.4 | N15: 0 | O15: 491.8 | P15: =SUM(C15:O15) -> 6455.07 | U15: EGASA | V15: C.H. CHARCANI III | W15: 163.9
B16: 05:00 | C16: 1165.88 | D16: 3024.6 | E16: 1658.4 | F16: 47.6 | J16: =DESPACHO_EJECUTADO!EY20+DESPACHO_EJECUTADO!EZ20 -> 50.4 | L16: 48.3 | M16: 12.5 | N16: 0 | O16: 477.2 | P16: =SUM(C16:O16) -> 6484.88 | V16: C.H. CHARCANI IV | X16: 121.15
B17: 05:30 | C17: 1176.15 | D17: 2852.4 | E17: 1839 | F17: 47.1 | J17: =DESPACHO_EJECUTADO!EY21+DESPACHO_EJECUTADO!EZ21 -> 50.8 | L17: 48.6 | M17: 12.5 | N17: 1.2 | O17: 507.3 | P17: =SUM(C17:O17) -> 6535.05 | V17: C.H. CHARCANI V | X17: 1801.45
B18: 06:00 | C18: 1170.57 | D18: 2861.7 | E18: 1866.6 | F18: 47.5 | J18: =DESPACHO_EJECUTADO!EY22+DESPACHO_EJECUTADO!EZ22 -> 50.5 | L18: 50.3 | M18: 12.5 | N18: 13.6 | O18: 461.3 | P18: =SUM(C18:O18) -> 6534.57 | V18: C.H. CHARCANI VI | X18: 170.8
B19: 06:30 | C19: 1164.25 | D19: 2990 | E19: 1864.9 | F19: 47.6 | J19: =DESPACHO_EJECUTADO!EY23+DESPACHO_EJECUTADO!EZ23 -> 50.5 | L19: 50.7 | M19: 12.5 | N19: 51.6 | O19: 340.9 | P19: =SUM(C19:O19) -> 6572.95 | U19: EGEJUNIN | V19: C.H. HUASAHUASI I | W19: 360.7
B20: 07:00 | C20: 1184.69 | D20: 3035.8 | E20: 1797.9 | F20: 47.5 | J20: =DESPACHO_EJECUTADO!EY24+DESPACHO_EJECUTADO!EZ24 -> 50.2 | L20: 51.5 | M20: 12.5 | N20: 90.2 | O20: 282.2 | P20: =SUM(C20:O20) -> 6552.49 | V20: C.H. RUNATULLO II | W20: 476.9
B21: 07:30 | C21: 1206.58 | D21: 3228.8 | E21: 1850.3 | F21: 47.5 | J21: =DESPACHO_EJECUTADO!EY25+DESPACHO_EJECUTADO!EZ25 -> 50.8 | L21: 51.4 | M21: 12.5 | N21: 172.3 | O21: 258.5 | P21: =SUM(C21:O21) -> 6878.68 | V21: C.H. RUNATULLO III | W21: 485.45
B22: 08:00 | C22: 1195.24 | D22: 3235 | E22: 2008.6 | F22: 47.3 | J22: =DESPACHO_EJECUTADO!EY26+DESPACHO_EJECUTADO!EZ26 -> 50.1 | L22: 50.3 | M22: 12.4 | N22: 300.3 | O22: 237.5 | P22: =SUM(C22:O22) -> 7136.74 | V22: C.H. SANTA CRUZ I | W22: 206.35
B23: 08:30 | C23: 1146.66 | D23: 3431.5 | E23: 2088.9 | F23: 47.2 | J23: =DESPACHO_EJECUTADO!EY27+DESPACHO_EJECUTADO!EZ27 -> 50.8 | L23: 46.8 | M23: 12.4 | N23: 323.8 | O23: 255.4 | P23: =SUM(C23:O23) -> 7403.46 | U23: EGEMSA | V23: C.H. MACHUPICCHU | W23: 3984.45
B24: 09:00 | C24: 1166.41 | D24: 3454.3 | E24: 2100.3 | F24: 46.8 | J24: =DESPACHO_EJECUTADO!EY28+DESPACHO_EJECUTADO!EZ28 -> 50.4 | L24: 48.2 | M24: 12.3 | N24: 354.8 | O24: 275.6 | P24: =SUM(C24:O24) -> 7509.11 | U24: EGESUR | V24: C.H. ARICOTA I | X24: 183.15
B25: 09:30 | C25: 1170.73 | D25: 3418.2 | E25: 2204.6 | F25: 46.5 | J25: =DESPACHO_EJECUTADO!EY29+DESPACHO_EJECUTADO!EZ29 -> 50.5 | L25: 49.4 | M25: 12.3 | N25: 357.5 | O25: 338.5 | P25: =SUM(C25:O25) -> 7648.23 | U25: ELECTRICA YANAPAMPA SAC | V25: C.H. YANAPAMPA | W25: 85.15
B26: 10:00 | C26: 1161.82 | D26: 3377 | E26: 2174.6 | F26: 45.9 | J26: =DESPACHO_EJECUTADO!EY30+DESPACHO_EJECUTADO!EZ30 -> 50.8 | L26: 46.8 | M26: 12.3 | N26: 428.5 | O26: 363.1 | P26: =SUM(C26:O26) -> 7660.82 | U26: ELECTROPERU | V26: C.H. MANTARO | X26: 15205.1
B27: 10:30 | C27: 1183.4 | D27: 3453.6 | E27: 2291.8 | F27: 45.1 | J27: =DESPACHO_EJECUTADO!EY31+DESPACHO_EJECUTADO!EZ31 -> 50.7 | L27: 43.8 | M27: 12.3 | N27: 403.4 | O27: 372.9 | P27: =SUM(C27:O27) -> 7857 | V27: C.H. RESTITUCION | W27: 5134.35
B28: 11:00 | C28: 1195.15 | D28: 3447.6 | E28: 2257.1 | F28: 45.1 | J28: =DESPACHO_EJECUTADO!EY32+DESPACHO_EJECUTADO!EZ32 -> 50.6 | L28: 44.4 | M28: 12.2 | N28: 420.6 | O28: 411.1 | P28: =SUM(C28:O28) -> 7883.85 | U28: EMPRESA DE GENERACION ELECTRICA CANCHAYLLO SAC | V28: C.H. CANCHAYLLO | W28: 124.05
B29: 11:30 | C29: 1200.87 | D29: 3434 | E29: 2275.8 | F29: 45.3 | J29: =DESPACHO_EJECUTADO!EY33+DESPACHO_EJECUTADO!EZ33 -> 50.5 | L29: 44.3 | M29: 11.7 | N29: 472.3 | O29: 448.5 | P29: =SUM(C29:O29) -> 7983.27 | U29: EMPRESA DE GENERACION ELECTRICA RIO BAÑOS S.A.C. | V29: C.H. RUCUY | W29: 478.85
B30: 12:00 | C30: 1196.38 | D30: 3423.5 | E30: 2235.3 | F30: 45.6 | J30: =DESPACHO_EJECUTADO!EY34+DESPACHO_EJECUTADO!EZ34 -> 50.3 | L30: 46.4 | M30: 11.7 | N30: 434.2 | O30: 527.7 | P30: =SUM(C30:O30) -> 7971.08 | U30: EMPRESA DE GENERACION ELECTRICA SANTA ANA S.A.C. | V30: C.H. RENOVANDES H1 | W30: 484.55
B31: 12:30 | C31: 1199.02 | D31: 3306 | E31: 2229.7 | F31: 45.6 | J31: =DESPACHO_EJECUTADO!EY35+DESPACHO_EJECUTADO!EZ35 -> 49.9 | L31: 46.8 | M31: 11.7 | N31: 443.7 | O31: 591.7 | P31: =SUM(C31:O31) -> 7924.12 | U31: EMPRESA DE GENERACION HUALLAGA | V31: C.H. CHAGLLA | X31: 10536.25
B32: 13:00 | C32: 1185.62 | D32: 3189 | E32: 2191.1 | F32: 46.4 | J32: =DESPACHO_EJECUTADO!EY36+DESPACHO_EJECUTADO!EZ36 -> 50.3 | L32: 46.9 | M32: 11.7 | N32: 438.4 | O32: 630.6 | P32: =SUM(C32:O32) -> 7790.02 | V32: P.C.H. CHAGLLA | W32: 156
B33: 13:30 | C33: 1196.77 | D33: 3283.8 | E33: 2146.7 | F33: 46.3 | J33: =DESPACHO_EJECUTADO!EY37+DESPACHO_EJECUTADO!EZ37 -> 50.3 | L33: 44.7 | M33: 11.6 | N33: 427.8 | O33: 667.1 | P33: =SUM(C33:O33) -> 7875.07 | U33: EMPRESA DE GENERACION HUANZA | V33: C.H. HUANZA | X33: 1069.2
B34: 14:00 | C34: 1188.57 | D34: 3259.7 | E34: 2188 | F34: 46.4 | J34: =DESPACHO_EJECUTADO!EY38+DESPACHO_EJECUTADO!EZ38 -> 50.4 | L34: 44.7 | M34: 11.6 | N34: 405.3 | O34: 691 | P34: =SUM(C34:O34) -> 7885.67 | U34: EMPRESA ELECTRICA AGUA AZUL | V34: C.H. POTRERO | W34: 479.95
B35: 14:30 | C35: 1197.9 | D35: 3331.7 | E35: 2262.4 | F35: 46.3 | J35: =DESPACHO_EJECUTADO!EY39+DESPACHO_EJECUTADO!EZ39 -> 50.3 | L35: 44.7 | M35: 11.5 | N35: 355.1 | O35: 710.4 | P35: =SUM(C35:O35) -> 8010.3 | U35: EMPRESA ELECTRICA RIO DOBLE | V35: C.H. LAS PIZARRAS | W35: 437.035
B36: 15:00 | C36: 1193.81 | D36: 3331.2 | E36: 2134.5 | F36: 46.5 | J36: =DESPACHO_EJECUTADO!EY40+DESPACHO_EJECUTADO!EZ40 -> 50.1 | L36: 44.4 | M36: 11.4 | N36: 353 | O36: 725.6 | P36: =SUM(C36:O36) -> 7890.51 | U36: ENGIE | V36: C.H. QUITARACSA | X36: 1733.2
B37: 15:30 | C37: 1195.88 | D37: 3390.4 | E37: 2286.4 | F37: 46.4 | J37: =DESPACHO_EJECUTADO!EY41+DESPACHO_EJECUTADO!EZ41 -> 50.6 | L37: 45.7 | M37: 11.4 | N37: 199.5 | O37: 759.5 | P37: =SUM(C37:O37) -> 7985.78 | V37: C.H. YUNCAN | X37: 3070.9
B38: 16:00 | C38: 1192.68 | D38: 3489.1 | E38: 2315.4 | F38: 46.3 | J38: =DESPACHO_EJECUTADO!EY42+DESPACHO_EJECUTADO!EZ42 -> 50.7 | L38: 46.4 | M38: 11.4 | N38: 88.9 | O38: 742.8 | P38: =SUM(C38:O38) -> 7983.68 | U38: GENERACIÓN ANDINA S.A.C. | V38: C.H. 8 DE AGOSTO | W38: 503.9
B39: 16:30 | C39: 1191.77 | D39: 3484.4 | E39: 2311.5 | F39: 46.6 | J39: =DESPACHO_EJECUTADO!EY43+DESPACHO_EJECUTADO!EZ43 -> 50.4 | L39: 46.6 | M39: 11.4 | N39: 76.1 | O39: 741.6 | P39: =SUM(C39:O39) -> 7960.37 | V39: C.H. EL CARMEN | W39: 160.6
B40: 17:00 | C40: 1170.35 | D40: 3329.8 | E40: 2102.1 | F40: 46.7 | J40: =DESPACHO_EJECUTADO!EY44+DESPACHO_EJECUTADO!EZ44 -> 50.5 | L40: 47.6 | M40: 11.5 | N40: 85.6 | O40: 756.6 | P40: =SUM(C40:O40) -> 7600.75 | U40: GENERADORA DE ENERGÍA DEL PERÚ | V40: C.H. ÁNGEL I | W40: 450
B41: 17:30 | C41: 1180.65 | D41: 3123.9 | E41: 2119.8 | F41: 46.5 | J41: =DESPACHO_EJECUTADO!EY45+DESPACHO_EJECUTADO!EZ45 -> 51.2 | L41: 44.7 | M41: 11.9 | N41: 33.5 | O41: 761.3 | P41: =SUM(C41:O41) -> 7373.45 | V41: C.H. ÁNGEL II | W41: 437.5
B42: 18:00 | C42: 1182.13 | D42: 3097.4 | E42: 2023.5 | F42: 46.5 | J42: =DESPACHO_EJECUTADO!EY46+DESPACHO_EJECUTADO!EZ46 -> 50.3 | L42: 46.6 | M42: 11.9 | N42: 12.4 | O42: 768.3 | P42: =SUM(C42:O42) -> 7239.03 | V42: C.H. ÁNGEL III | W42: 222.25
B43: 18:30 | C43: 1184.32 | D43: 3164.6 | E43: 2025.6 | F43: 46.9 | J43: =DESPACHO_EJECUTADO!EY47+DESPACHO_EJECUTADO!EZ47 -> 50.5 | L43: 46.9 | M43: 11.9 | N43: 0.3 | O43: 747 | P43: =SUM(C43:O43) -> 7278.02 | V43: C.H. LA JOYA | W43: 192.4
B44: 19:00 | C44: 1178.92 | D44: 3413.8 | E44: 2122.6 | F44: 47.1 | J44: =DESPACHO_EJECUTADO!EY48+DESPACHO_EJECUTADO!EZ48 -> 50.8 | L44: 47.4 | M44: 12.3 | N44: 0 | O44: 727 | P44: =SUM(C44:O44) -> 7599.92 | U44: HIDROCAÑETE S.A. | V44: C.H. IMPERIAL | W44: 82.6
B45: 19:30 | C45: 1195.21 | D45: 3471.8 | E45: 2167.6 | F45: 47.3 | J45: =DESPACHO_EJECUTADO!EY49+DESPACHO_EJECUTADO!EZ49 -> 50.8 | L45: 47.4 | M45: 12.3 | N45: 0 | O45: 671.9 | P45: =SUM(C45:O45) -> 7664.31 | U45: HIDROELECTRICA HUANCHOR S.A.C. | V45: C.H. HUANCHOR | W45: 440.75
B46: 20:00 | C46: 1201.11 | D46: 3498.1 | E46: 2226.5 | F46: 47.3 | J46: =DESPACHO_EJECUTADO!EY50+DESPACHO_EJECUTADO!EZ50 -> 50.9 | L46: 46.5 | M46: 12.5 | N46: 0 | O46: 557.2 | P46: =SUM(C46:O46) -> 7640.11 | U46: HUAURA POWER GROUP S.A. | V46: C.H. YARUCAYA | W46: 448.8
B47: 20:30 | C47: 1200.84 | D47: 3532.2 | E47: 2208.7 | F47: 47.6 | J47: =DESPACHO_EJECUTADO!EY51+DESPACHO_EJECUTADO!EZ51 -> 51 | L47: 45.5 | M47: 12.5 | N47: 0 | O47: 493.1 | P47: =SUM(C47:O47) -> 7591.44 | U47: INLAND ENERGY SAC | V47: C.H. SANTA TERESA | W47: 2176.85
B48: 21:00 | C48: 1198.55 | D48: 3547.8 | E48: 2225 | F48: 47.2 | J48: =DESPACHO_EJECUTADO!EY52+DESPACHO_EJECUTADO!EZ52 -> 51.2 | L48: 44.7 | M48: 12.5 | N48: 0 | O48: 428.7 | P48: =SUM(C48:O48) -> 7555.65 | U48: INVERSIONES SHAQSHA S.A.C. | V48: C.H. PARIAC | W48: 103.2
B49: 21:30 | C49: 1200.75 | D49: 3558.5 | E49: 2145.2 | F49: 47.6 | J49: =DESPACHO_EJECUTADO!EY53+DESPACHO_EJECUTADO!EZ53 -> 51.2 | L49: 46.9 | M49: 12.5 | N49: 0 | O49: 437.4 | P49: =SUM(C49:O49) -> 7500.05 | U49: KALLPA GENERACION S.A. | V49: C.H. CERRO DEL AGUILA | X49: 13401.7
B50: 22:00 | C50: 1189.66 | D50: 3544.6 | E50: 2105.7 | F50: 47.5 | J50: =DESPACHO_EJECUTADO!EY54+DESPACHO_EJECUTADO!EZ54 -> 51.2 | L50: 48.2 | M50: 12.5 | N50: 0 | O50: 383.9 | P50: =SUM(C50:O50) -> 7383.26 | V50: M.C.H. CERRO DEL AGUILA | W50: 252.05
B51: 22:30 | C51: 1173.66 | D51: 3508.2 | E51: 2066.9 | F51: 47.8 | J51: =DESPACHO_EJECUTADO!EY55+DESPACHO_EJECUTADO!EZ55 -> 51.7 | L51: 47.7 | M51: 12.5 | N51: 0 | O51: 396.2 | P51: =SUM(C51:O51) -> 7304.66 | U51: LA VIRGEN | V51: C.H. LA VIRGEN | X51: 1846.6
B52: 23:00 | C52: 1193.89 | D52: 3417.6 | E52: 1886.5 | F52: 47.6 | J52: =DESPACHO_EJECUTADO!EY56+DESPACHO_EJECUTADO!EZ56 -> 51.5 | L52: 47.9 | M52: 12.5 | N52: 0 | O52: 383.2 | P52: =SUM(C52:O52) -> 7040.69 | U52: MAJA ENERGIA S.A.C. | V52: C.H. RONCADOR | W52: 86.15
B53: 23:30 | C53: 1191.96 | D53: 3318 | E53: 2063.7 | F53: 47.6 | J53: =DESPACHO_EJECUTADO!EY57+DESPACHO_EJECUTADO!EZ57 -> 51.2 | L53: 48.7 | M53: 12.4 | N53: 0 | O53: 341.7 | P53: =SUM(C53:O53) -> 7075.26 | U53: ORAZUL ENERGY PERÚ | V53: C.H. CAÑA BRAVA | W53: 128.55
B54: 00:00 | C54: 1195.67 | D54: 3266.1 | E54: 1961.7 | F54: 47.3 | J54: =DESPACHO_EJECUTADO!EY58+DESPACHO_EJECUTADO!EZ58 -> 50.9 | L54: 48.6 | M54: 12.4 | N54: 0 | O54: 315.3 | P54: =SUM(C54:O54) -> 6897.97 | V54: C.H. CAÑON DEL PATO | X54: 5732.3
B55: TOTAL MWh | C55: 28386.385 | D55: 78145.95 | E55: 48879.05 | F55: 1126.05 | G55: =+SUM(G7:G54)/2 -> 0 | H55: =+SUM(H7:H54)/2 -> 0 | I55: =+SUM(I7:I54)/2 -> 0 | J55: =+SUM(J7:J54)/2 -> 1216.35 | K55: =+SUM(K7:K54)/2 -> 0 | L55: 1139.35 | M55: 292 | N55: 3371.95 | O55: 11745.2 | P55: =SUM(P7:P54)/2 -> 174302.28 | V55: C.H. CARHUAQUERO | X55: 2158.4
B56: % | C56: =+C55*100/$P$55 -> 16.285722 | D56: =+D55*100/$P$55 -> 44.833577 | E56: =+E55*100/$P$55 -> 28.04269 | F56: =+F55*100/$P$55 -> 0.64603284 | G56: =+G55*100/$P$55 -> 0 | H56: =+H55*100/$P$55 -> 0 | I56: =+I55*100/$P$55 -> 0 | J56: =+J55*100/$P$55 -> 0.69783939 | ... P56: =+P55*100/$P$55 -> 100 | V56: C.H. CARHUAQUERO IV | W56: 237.75
U57: ORYGEN PERU S.A.A. | V57: C.H. CALLAHUANCA | X57: 1943.4
V58: C.H. HER 1 | W58: 14.4
V59: C.H. HUAMPANI | W59: 731.45
V60: C.H. HUINCO | X60: 2761.7
V61: C.H. MATUCANA | X61: 3090.35
V62: C.H. MOYOPAMPA | W62: 1524.95
U63: PERUANA DE INVERSIONES EN ENERGIAS RENOVABLES S.A. | V63: C.H. MANTA I | W63: 479.85
U64: SAN GABAN | V64: C.H. SAN GABAN II | X64: 1997.45
U65: SINERSA | V65: C.H. CHANCAY | W65: 479
V66: C.H. POECHOS II | W66: 140.1
U67: STATKRAFT S.A | V67: C.H. ARCATA | W67: 89.3
V68: C.H. CAHUA | W68: 1126.05
V69: C.H. CHEVES | X69: 3138.85
V70: C.H. GALLITO CIEGO | X70: 751.25
V71: C.H. MALPASO | X71: 1031.2
V72: C.H. OROYA | W72: 188.95
V73: C.H. PACHACHACA | W73: 151.45
V74: C.H. YAUPI | W74: 2609.25
U75: TOTAL MWh | W75: 28386.385 | X75: 78145.95

Sheet GENERACION RER
B3: martes, 21 de Enero del 2025
B5: GENERACIÓN ELÉCTRICA DE LAS CENTRALES RER (MW)
B6: HORA | C6: AGRO INDUSTRIAL PARAMONGA S.A. | D6: AGROAURORA S.A.C. | E6: AGROINDUSTRIAS SAN JACINTO S.A.A. | F6: ANDEAN POWER S.A.C. | G6: ASOCIACIÓN SANTA LUCIA DE CHACAS | H6: ATRIA ENERGIA S.A.C. | I6: BIOENERGIA DEL CHIRA S.A. | J6: COLCA SOLAR S.A.C. | K6: EGEJUNIN | P6: ELECTRICA YANAPAMPA SAC | Q6: EMPRESA DE GENERACION ELECTRICA CANCHAYLLO SAC | R6: EMPRESA DE GENERACION ELECTRICA RIO BAÑOS S.A.C. | S6: EMPRESA DE GENERACION ELECTRICA SANTA ANA S.A.C. | T6: EMPRESA ELECTRICA AGUA AZUL | U6: EMPRESA ELECTRICA RIO DOBLE | V6: ENERGÍA EÓLICA S.A. | X6: ENERGIA RENOVABLE DEL SUR S.A. | Y6: ENGIE | AD6: GENERACIÓN ANDINA S.A.C. | AF6: GENERADORA DE ENERGÍA DEL PERÚ | AJ6: GR CORTARRAMA SOCIEDAD ANONIMA CERRADA | AK6: GR PAINO SOCIEDAD ANONIMA CERRADA | AL6: GR TARUCA SOCIEDAD ANONIMA CERRADA | AM6: HIDROCAÑETE S.A. | AN6: HUAURA POWER GROUP S.A. | AO6: HYDRO PATAPO S.A.C. | AP6: KONDU SAC | AQ6: MAJA ENERGIA S.A.C. | AR6: MAJES ARCUS S.A.C. | AS6: MOQUEGUA FV S.A.C. | AT6: ORAZUL ENERGY PERÚ | AV6: ORYGEN PERU S.A.A. | BA6: PANAMERICANA SOLAR SAC. | BB6: PARQUE EOLICO MARCONA S.A.C. | BC6: PARQUE EOLICO TRES HERMANAS S.A.C. | BD6: PERUANA DE INVERSIONES EN ENERGIAS RENOVABLES S.A. | BE6: PETRAMAS | BI6: REPARTICIÓN ARCUS S.A.C. | BJ6: SDF ENERGIA SAC | BK6: SINERSA | BM6: TACNA SOLAR SAC. | BN6: TOTAL RER
C7: C.T. PARAMONGA | D7: C.T. MAPLE | E7: C.T SAN JACINTO | F7: C.H. CARHUAC | G7: C.H. HUALLIN | H7: C.H. PURMACANA | I7: C.T. CAÑA BRAVA | K7: C.H. HUASAHUASI I | L7: C.H. HUASAHUASI II | M7: C.H. RUNATULLO II | N7: C.H. RUNATULLO III | O7: C.H. STA CRUZ I y II | P7: C.H. YANAPAMPA | Q7: C.H. CANCHAYLLO | R7: C.H. RUCUY | S7: C.H. RENOVANDES H1 | T7: C.H. POTRERO | U7: C.H. LAS PIZARRAS | AD7: C.H. 8 DE AGOSTO | AE7: C.H. EL CARMEN | AF7: C.H. ANGEL I | AG7: C.H. ANGEL II | AH7: C.H. ANGEL III | AI7: C.H. LA JOYA | AM7: C.H. NUEVAIMPERIAL | AN7: C.H. YARUCAYA | AO7: MCH PATAPO | AQ7: C.H. RONCADOR | AT7: C.H. CANA BRAVA | AU7: C.H. CARHUAQUERO4 | AZ7: C.H. HER 1 | BD7: C.H. MANTA | BE7: C.T. HUAYCOLORO | BF7: C.T. LA GRINGA V | BG7: CTB CALLAO | BH7: CTB. DONA CATALINA | BJ7: C.T. OQUENDO | BK7: C.H. CHANCAY | BL7: C.H. POECHOS2 | BN7: MW
B8: 0:30 | C8: 14 | D8: 17.6 | E8: 8.4 | F8: 12.3 | G8: 2 | I8: 10.5 | K8: 14.5 | M8: 19.9 | N8: 20.3 | O8: 9.1 | P8: 3.5 | Q8: 5 | R8: 20 | S8: 19.8 | T8: 20 | U8: 18.75 | V8: 24.8 | W8: 38.6 | X8: 67.4 | Y8: 45.7 | Z8: 66.4 | AB8: 3.8 | AC8: 1.9 | AD8: 21 | AE8: 7.2 | AF8: 20 | AG8: 20 | AH8: 10 | AI8: 7.6 | AM8: 3.5 | AN8: 18.7 | AQ8: 3.6 | AT8: 5.3 | AU8: 9.9 | AV8: 35.3 | AX8: 30 | AZ8: 0.6 | BB8: 17.2 | BC8: 43.1 | BD8: 20 | BE8: 4.7 | BF8: 2.9 | BG8: 2.4 | BH8: 2.4 | BK8: 20 | BL8: 5.5 | BN8: 775.15
B9: 1:00 | C9: 14.1 | D9: 17.2 | E9: 8.1 | F9: 7.2 | G9: 2 | I9: 9.9 | K9: 14.6 | M9: 20.1 | N9: 20.3 | O9: 9.1 | P9: 3.5 | Q9: 5.2 | R9: 19.8 | S9: 20.3 | T9: 20 | U9: 18.7 | V9: 25 | W9: 30.4 | X9: 66.6 | Y9: 44.5 | Z9: 56.8 | AB9: 6.4 | AC9: 2.5 | AD9: 21 | AE9: 7.2 | AF9: 20 | AG9: 20 | AH9: 10 | AI9: 7.6 | AM9: 3.5 | AN9: 18.7 | AQ9: 3.6 | AT9: 5.4 | AU9: 9.9 | AV9: 30.3 | AX9: 33.8 | AZ9: 0.6 | BB9: 15.8 | BC9: 41.1 | BD9: 20 | BE9: 4.7 | BF9: 2.9 | BG9: 2.4 | BH9: 2.4 | BK9: 19.8 | BL9: 5.5 | BN9: 748.5
B10: 1:30 | C10: 14.3 | D10: 17.2 | E10: 8.4 | F10: 7.1 | G10: 2 | I10: 10 | K10: 14.5 | M10: 19.5 | N10: 20.1 | O10: 9.2 | P10: 3.5 | Q10: 5.2 | R10: 19.8 | S10: 19.7 | T10: 20 | U10: 18.64 | V10: 25.2 | W10: 29.8 | X10: 73 | Y10: 32.3 | Z10: 51.7 | AB10: 2 | AC10: 1.2 | AD10: 20.9 | AE10: 7.1 | AF10: 20 | AG10: 20 | AH10: 10 | AI10: 7.6 | AL10: 0.1 | AM10: 3.4 | AN10: 18.7 | AQ10: 3.7 | AT10: 5.3 | AU10: 9.9 | AV10: 26.5 | AX10: 27.6 | AZ10: 0.6 | BB10: 17.4 | BC10: 48.2 | BD10: 20 | BE10: 4.7 | BF10: 2.9 | BG10: 2.4 | BH10: 2.4 | BK10: 19.8 | BL10: 5.5 | BN10: 729.04
B11: 2:00 | C11: 14.6 | D11: 17.4 | E11: 7.7 | F11: 7.1 | G11: 2 | I11: 10.3 | K11: 14.6 | M11: 19.4 | N11: 20.3 | O11: 9.3 | P11: 3.5 | Q11: 5.2 | R11: 19.8 | S11: 20.2 | T11: 20 | U11: 18.29 | V11: 23.3 | W11: 31 | X11: 70.6 | Y11: 37.7 | Z11: 54 | AB11: 3 | AC11: 1.3 | AD11: 20.9 | AE11: 7 | AF11: 20 | AG11: 20 | AH11: 10 | AI11: 7.9 | AM11: 3.5 | AN11: 18.7 | AQ11: 3.7 | AT11: 5.4 | AU11: 9.9 | AV11: 36 | AX11: 39.6 | AZ11: 0.6 | BB11: 17.1 | BC11: 41.2 | BD11: 20 | BE11: 4.7 | BF11: 2.9 | BG11: 2.4 | BH11: 2.4 | BK11: 19.8 | BL11: 5.6 | BN11: 749.89
B12: 2:30 | C12: 13.8 | D12: 17.6 | E12: 8 | F12: 7.1 | G12: 2 | I12: 10.1 | K12: 14.5 | M12: 19.3 | N12: 20.3 | O12: 9.2 | P12: 3.5 | Q12: 5.2 | R12: 19.8 | S12: 20.3 | T12: 20 | U12: 18.35 | V12: 23.4 | W12: 23.3 | X12: 77.7 | Y12: 52.1 | Z12: 55.9 | AB12: 2 | AC12: 1 | AD12: 21 | AE12: 7 | AF12: 20 | AG12: 20 | AH12: 10 | AI12: 7.9 | AM12: 3.5 | AN12: 18.7 | AQ12: 3.6 | AT12: 5.2 | AU12: 9.9 | AV12: 40.2 | AX12: 43.5 | AZ12: 0.6 | BB12: 19.6 | BC12: 42.9 | BD12: 20 | BE12: 4.7 | BF12: 2.9 | BG12: 2.4 | BH12: 2.4 | BK12: 19.8 | BL12: 5.5 | BN12: 775.75
B13: 3:00 | C13: 14.5 | D13: 17.6 | E13: 7.1 | F13: 4 | G13: 2 | I13: 10.1 | K13: 14.6 | M13: 19.3 | N13: 20.3 | O13: 9.2 | P13: 3.5 | Q13: 5.2 | R13: 19.8 | S13: 20.6 | T13: 20 | U13: 18.34 | V13: 26 | W13: 19.9 | X13: 83.1 | Y13: 38.1 | Z13: 54.2 | AB13: 4.7 | AC13: 1.1 | AD13: 21 | AE13: 6.9 | AF13: 20 | AG13: 20 | AH13: 10 | AI13: 7.9 | AM13: 3.5 | AN13: 18.7 | AQ13: 3.7 | AT13: 5.3 | AU13: 9.9 | AV13: 32 | AX13: 47 | AZ13: 0.6 | BB13: 18.9 | BC13: 49.7 | BD13: 20 | BE13: 4.7 | BF13: 2.9 | BG13: 2.4 | BH13: 2.4 | BK13: 19.8 | BL13: 5.5 | BN13: 766.04
B14: 3:30 | C14: 14.3 | D14: 16.3 | E14: 6.7 | F14: 6 | G14: 2 | I14: 10 | K14: 14.6 | M14: 19.4 | N14: 20.2 | O14: 9.2 | P14: 3.6 | Q14: 5.2 | R14: 19.8 | S14: 20 | T14: 20 | U14: 18.34 | V14: 24 | W14: 19.8 | X14: 85.7 | Y14: 57.5 | Z14: 71 | AB14: 2.9 | AC14: 2.8 | AD14: 21 | AE14: 6.8 | AF14: 20 | AG14: 20 | AH14: 10 | AI14: 7.6 | AM14: 3.5 | AN14: 18.7 | AQ14: 3.7 | AT14: 5.4 | AU14: 9.8 | AV14: 27.6 | AX14: 42 | AZ14: 0.6 | BB14: 22.6 | BC14: 54.8 | BD14: 20 | BE14: 4.7 | BF14: 2.9 | BG14: 2.4 | BH14: 2.4 | BK14: 19.9 | BL14: 5.6 | BN14: 801.34
B15: 4:00 | C15: 14.3 | D15: 16.1 | E15: 7.7 | F15: 3.7 | G15: 2 | I15: 9.6 | K15: 14.6 | M15: 19.2 | N15: 20.3 | O15: 9.2 | P15: 3.5 | Q15: 5.2 | R15: 20 | S15: 20.7 | T15: 20 | U15: 18.32 | V15: 21.2 | W15: 26.4 | X15: 85.4 | Y15: 65.1 | Z15: 76.5 | AB15: 4.6 | AC15: 3.5 | AD15: 21 | AE15: 6.7 | AF15: 20 | AG15: 20 | AH15: 10 | AI15: 7.8 | AM15: 3.5 | AN15: 18.7 | AQ15: 3.7 | AT15: 5.4 | AU15: 9.9 | AV15: 26.3 | AX15: 36 | AZ15: 0.6 | BB15: 23.9 | BC15: 58.7 | BD15: 20 | BE15: 4.7 | BF15: 2.9 | BG15: 2.4 | BH15: 2.4 | BK15: 20 | BL15: 5.5 | BN15: 817.22
B16: 4:30 | C16: 14.3 | D16: 15.5 | E16: 8.2 | F16: 3.2 | G16: 2 | I16: 9.8 | K16: 14.6 | M16: 19 | N16: 20.2 | O16: 9.2 | P16: 3.5 | Q16: 5.2 | R16: 20 | S16: 19.8 | T16: 20 | U16: 18.37 | V16: 23.8 | W16: 32.1 | X16: 83.8 | Y16: 72.9 | Z16: 83.9 | AB16: 3.8 | AC16: 3.3 | AD16: 21 | AE16: 6.6 | AF16: 20 | AG16: 20 | AH16: 10 | AI16: 7.9 | AK16: 0.1 | AL16: 1.4 | AM16: 3.5 | AN16: 18.7 | AQ16: 3.6 | AT16: 5.5 | AU16: 9.8 | AV16: 44.3 | AX16: 61.2 | AZ16: 0.6 | BB16: 23.7 | BC16: 57.5 | BD16: 20 | BE16: 4.7 | BF16: 2.9 | BG16: 2.4 | BH16: 2.4 | BK16: 20 | BL16: 5.6 | BN16: 879.87
B17: 5:00 | C17: 14.3 | D17: 16.5 | E17: 7.9 | F17: 3.4 | G17: 2 | I17: 9.6 | K17: 15 | M17: 19 | N17: 20.2 | O17: 9.1 | P17: 3.5 | Q17: 5.2 | R17: 20 | S17: 20.3 | T17: 20 | U17: 18.38 | V17: 25.1 | W17: 22.9 | X17: 83.4 | Y17: 66.9 | Z17: 88.1 | AB17: 4.7 | AC17: 3.7 | AD17: 21 | AE17: 6.6 | AF17: 20 | AG17: 20 | AH17: 10 | AI17: 8 | AL17: 1.3 | AM17: 3.5 | AN17: 18.7 | AQ17: 3.7 | AT17: 5.5 | AU17: 9.9 | AV17: 41.2 | AX17: 62.4 | AZ17: 0.6 | BB17: 22.8 | BC17: 54.7 | BD17: 20 | BE17: 4.7 | BF17: 3 | BG17: 2.4 | BH17: 2.4 | BK17: 20 | BL17: 5.4 | BN17: 866.98
B18: 5:30 | C18: 14.5 | D18: 17.5 | E18: 8.6 | F18: 3.4 | G18: 2 | I18: 8 | K18: 15.6 | M18: 19.1 | N18: 20.2 | O18: 9 | P18: 3.6 | Q18: 5.2 | R18: 20 | S18: 20.5 | T18: 20 | U18: 18.35 | V18: 26.9 | W18: 18.9 | X18: 81.7 | Y18: 63.2 | Z18: 89.2 | AB18: 3.4 | AC18: 2.8 | AD18: 21 | AE18: 6.3 | AF18: 20 | AG18: 20 | AH18: 10 | AI18: 8.1 | AK18: 0.3 | AL18: 2.1 | AM18: 3.4 | AN18: 18.7 | AQ18: 3.6 | AS18: 0.3 | AT18: 5.5 | AU18: 10 | AV18: 60.3 | AX18: 76.1 | AY18: 0.1 | AZ18: 0.6 | BA18: 0.1 | BB18: 21.7 | BC18: 60.7 | BD18: 20 | BE18: 4.7 | BF18: 3 | BG18: 2.4 | BH18: 2.4 | BK18: 20 | BL18: 5.4 | BM18: 0.7 | BN18: 899.15
B19: 6:00 | C19: 14.5 | D19: 17.2 | E19: 8.6 | F19: 3.3 | G19: 2 | I19: 10 | K19: 15.5 | M19: 19.4 | N19: 20.2 | O19: 9.1 | P19: 3.6 | Q19: 5.2 | R19: 20 | S19: 20.5 | T19: 20 | U19: 18.37 | V19: 28 | W19: 13.4 | X19: 69 | Y19: 64.5 | Z19: 85.2 | AA19: 2.5 | AB19: 3.7 | AC19: 3.4 | AD19: 21 | AE19: 6.2 | AF19: 20 | AG19: 20 | AH19: 10 | AI19: 8 | AJ19: 1.6 | AL19: 0.9 | AM19: 3.4 | AN19: 18.7 | AQ19: 3.6 | AS19: 1.2 | AT19: 5.3 | AU19: 9.9 | AV19: 50.7 | AW19: 2.5 | AX19: 66.1 | AY19: 2.4 | AZ19: 0.6 | BA19: 0.9 | BB19: 20.3 | BC19: 56.1 | BD19: 20 | BE19: 4.7 | BF19: 3 | BG19: 2.4 | BH19: 2.4 | BK19: 20 | BL19: 5.5 | BM19: 2.5 | BN19: 867.07
B20: 6:30 | C20: 14.5 | D20: 17.6 | E20: 8.4 | F20: 3.4 | G20: 2 | I20: 10.2 | K20: 15.4 | M20: 19.1 | N20: 20.2 | O20: 9 | P20: 3.6 | Q20: 5.2 | R20: 20 | S20: 20.5 | T20: 20 | U20: 18.35 | V20: 27.3 | W20: 11.5 | X20: 59.9 | Y20: 41.5 | Z20: 66.6 | AA20: 5.7 | AB20: 2.7 | AC20: 2.3 | AD20: 21 | AE20: 6.2 | AF20: 20 | AG20: 20 | AH20: 10 | AI20: 7.5 | AJ20: 2.5 | AM20: 3.5 | AN20: 18.7 | AQ20: 3.6 | AR20: 0.2 | AS20: 2.7 | AT20: 5.3 | AU20: 9.9 | AV20: 30.8 | AW20: 16.9 | AX20: 41.9 | AY20: 14.7 | AZ20: 0.6 | BA20: 3 | BB20: 14.4 | BC20: 42 | BD20: 20 | BE20: 4.7 | BF20: 3 | BG20: 2.4 | BH20: 2.4 | BI20: 0.4 | BK20: 20 | BL20: 5.5 | BM20: 5.5 | BN20: 784.25
B21: 7:00 | C21: 14.4 | D21: 17.6 | E21: 9.2 | F21: 8.4 | G21: 2 | I21: 10.3 | J21: 0.1 | K21: 15.4 | M21: 19.7 | N21: 20.2 | O21: 8.8 | P21: 3.6 | Q21: 5.2 | R21: 19.8 | S21: 20 | T21: 20 | U21: 18.39 | V21: 26.7 | W21: 11.5 | X21: 50.1 | Y21: 31.5 | Z21: 54.4 | AA21: 17.3 | AB21: 0.9 | AC21: 1 | AD21: 21 | AE21: 6.3 | AF21: 20 | AG21: 20 | AH21: 10 | AI21: 8.1 | AJ21: 7.2 | AK21: 0.1 | AL21: 0.1 | AM21: 3.5 | AN21: 18.7 | AQ21: 3.7 | AR21: 0.8 | AS21: 2.3 | AT21: 5.3 | AU21: 9.9 | AV21: 24.8 | AW21: 28.5 | AX21: 34.6 | AY21: 26.6 | AZ21: 0.6 | BA21: 2.3 | BB21: 12.4 | BC21: 34.1 | BD21: 20 | BE21: 4.7 | BF21: 3 | BG21: 2.4 | BH21: 2.4 | BI21: 1.2 | BK21: 19.8 | BL21: 5.5 | BM21: 3.9 | BN21: 770.29
B22: 7:30 | C22: 14.5 | D22: 17.6 | E22: 9.1 | F22: 7.6 | G22: 2 | I22: 10.2 | J22: 0.1 | K22: 15.4 | M22: 20 | N22: 20.2 | O22: 8.6 | P22: 3.5 | Q22: 5.2 | R22: 20 | S22: 20.5 | T22: 20 | U22: 18.38 | V22: 25.7 | W22: 14.4 | X22: 45.2 | Y22: 25.1 | Z22: 49.5 | AA22: 33.8 | AB22: 0.8 | AC22: 0.8 | AD22: 21 | AE22: 6.4 | AF22: 20 | AG22: 20 | AH22: 10 | AI22: 8.1 | AJ22: 11 | AL22: 0.2 | AM22: 3.5 | AN22: 18.7 | AQ22: 3.7 | AR22: 1.3 | AS22: 2.8 | AT22: 5.3 | AU22: 9.9 | AV22: 18.7 | AW22: 56.9 | AX22: 26.5 | AY22: 56 | AZ22: 0.6 | BA22: 3.5 | BB22: 11.7 | BC22: 39.9 | BD22: 19.9 | BE22: 4.7 | BF22: 3 | BG22: 2.4 | BH22: 2.4 | BI22: 2.3 | BK22: 20 | BL22: 5.5 | BM22: 4.6 | BN22: 828.68
B23: 8:00 | C23: 14.3 | D23: 17.5 | E23: 8.8 | F23: 6.3 | G23: 2 | I23: 9.7 | J23: 0.2 | K23: 15.4 | M23: 19.8 | N23: 20.1 | O23: 8.6 | P23: 3.6 | Q23: 5.2 | R23: 20 | S23: 20.4 | T23: 20 | U23: 18.34 | V23: 24.4 | W23: 15.5 | X23: 41.5 | Y23: 20.7 | Z23: 43.3 | AA23: 35.3 | AB23: 2.3 | AC23: 2.1 | AD23: 21 | AE23: 6.5 | AF23: 20 | AG23: 20 | AH23: 10 | AI23: 8.1 | AJ23: 17.8 | AL23: 0.3 | AM23: 3.4 | AN23: 18.7 | AP23: 0.1 | AQ23: 3.5 | AR23: 2 | AS23: 2.5 | AT23: 5.2 | AU23: 10 | AV23: 22.6 | AW23: 130.8 | AX23: 20.7 | AY23: 97.8 | AZ23: 0.6 | BA23: 3.3 | BB23: 11.2 | BC23: 32.9 | BD23: 19.9 | BE23: 4.7 | BF23: 2.9 | BG23: 2.4 | BH23: 2.4 | BI23: 4.9 | BK23: 20 | BL23: 5.6 | BM23: 5.6 | BN23: 932.74
B24: 8:30 | C24: 13.9 | D24: 15.5 | E24: 7.5 | F24: 8.9 | G24: 2 | I24: 9.9 | J24: 0.6 | K24: 15.4 | M24: 20 | N24: 20.2 | O24: 8.7 | P24: 3.6 | Q24: 5.1 | R24: 20 | S24: 20.4 | T24: 20 | U24: 18.36 | V24: 27.5 | W24: 13.1 | X24: 59.8 | Y24: 27.5 | Z24: 38.9 | AA24: 35.1 | AB24: 4.1 | AC24: 3 | AD24: 21 | AE24: 6.5 | AI24: 8.1 | AJ24: 24.8 | AL24: 0.1 | AM24: 3.4 | AN24: 18.7 | AP24: 0.2 | AQ24: 3.6 | AR24: 4.5 | AS24: 3.1 | AT24: 5.4 | AU24: 9.9 | AV24: 20.4 | AW24: 134.3 | AX24: 22.1 | AY24: 103.7 | AZ24: 0.6 | BA24: 2.4 | BB24: 9.3 | BC24: 29.6 | BD24: 20 | BE24: 4.7 | BF24: 2.9 | BG24: 2.4 | BH24: 2.4 | BI24: 7.4 | BK24: 20 | BL24: 5.6 | BM24: 7.7 | BN24: 923.86
B25: 9:00 | C25: 13.6 | D25: 17.6 | E25: 6.4 | F25: 16.2 | G25: 2 | I25: 10.6 | J25: 0.5 | K25: 15.4 | M25: 20 | N25: 20.2 | O25: 8.5 | P25: 3.5 | Q25: 5.1 | R25: 20 | S25: 20.5 | T25: 20 | U25: 18.41 | V25: 26.3 | W25: 16.3 | X25: 76.9 | Y25: 29.6 | Z25: 40.6 | AA25: 37.6 | AB25: 3.6 | AC25: 3.3 | AD25: 21 | AE25: 6.8 | AF25: 10 | AH25: 0.5 | AI25: 8.4 | AJ25: 30.6 | AK25: 3.3 | AL25: 4.8 | AM25: 3.4 | AN25: 18.7 | AP25: 0.1 | AQ25: 3.6 | AR25: 5.8 | AS25: 4.1 | AT25: 5.3 | AU25: 9.9 | AV25: 10.6 | AW25: 135.9 | AX25: 7.8 | AY25: 109.4 | AZ25: 0.6 | BA25: 5.2 | BB25: 14.4 | BC25: 38.1 | BD25: 20 | BE25: 4.7 | BF25: 2.8 | BG25: 2.4 | BH25: 2.4 | BI25: 10.5 | BK25: 20 | BL25: 6.1 | BM25: 15.1 | BN25: 995.01
B26: 9:30 | C26: 13.7 | D26: 17.9 | E26: 6.8 | F26: 16.3 | G26: 2 | I26: 11 | J26: 0.6 | K26: 15.5 | M26: 19.6 | N26: 20.2 | O26: 8.6 | P26: 3.5 | Q26: 5.1 | R26: 20 | S26: 20.3 | T26: 20 | U26: 18.43 | V26: 25.1 | W26: 27.5 | X26: 83.4 | Y26: 38.9 | Z26: 45.2 | AA26: 40.2 | AB26: 4.5 | AC26: 4.2 | AD26: 21 | AE26: 7 | AF26: 10 | AG26: 5 | AH26: 0.5 | AI26: 8.4 | AJ26: 28.4 | AK26: 10.4 | AL26: 11.1 | AM26: 3.4 | AN26: 18.7 | AP26: 0.2 | AQ26: 3.6 | AR26: 8.8 | AS26: 3.1 | AT26: 5.3 | AU26: 9.9 | AV26: 11.5 | AW26: 136 | AX26: 4.2 | AY26: 101.8 | AZ26: 0.6 | BA26: 4.3 | BB26: 19.5 | BC26: 53 | BD26: 20 | BE26: 4.7 | BF26: 2.8 | BG26: 2.4 | BH26: 2.4 | BI26: 14.2 | BK26: 20 | BL26: 6 | BM26: 19.9 | BN26: 1066.63
B27: 10:00 | C27: 14.3 | D27: 17.5 | E27: 5.1 | F27: 16.5 | G27: 2 | I27: 9.9 | J27: 0.7 | K27: 15.4 | M27: 19.9 | N27: 20.2 | O27: 8.5 | P27: 3.5 | Q27: 5.1 | R27: 20 | S27: 19.7 | T27: 20 | U27: 18.42 | V27: 20 | W27: 28.4 | X27: 94.3 | Y27: 34.3 | Z27: 41.4 | AA27: 38.2 | AB27: 4.6 | AC27: 3.8 | AD27: 21 | AE27: 7 | AF27: 10 | AG27: 10 | AH27: 5 | AI27: 8.4 | AJ27: 78.4 | AK27: 11.3 | AL27: 13.6 | AM27: 3.4 | AN27: 18.7 | AP27: 0.1 | AQ27: 3.6 | AR27: 13 | AS27: 5.3 | AT27: 5.4 | AU27: 10 | AV27: 21.1 | AW27: 137.1 | AX27: 14.6 | AY27: 112.5 | AZ27: 0.6 | BA27: 6.7 | BB27: 19.9 | BC27: 55.8 | BD27: 20 | BE27: 4.7 | BF27: 2.8 | BG27: 2.4 | BH27: 2.4 | BI27: 16.8 | BK27: 20 | BL27: 6 | BM27: 19.7 | BN27: 1169.02
B28: 10:30 | C28: 12.5 | D28: 17.6 | E28: 5.1 | F28: 16.5 | G28: 2 | I28: 8.6 | J28: 1.3 | K28: 15.2 | M28: 20.1 | N28: 20.2 | O28: 8.5 | P28: 3.6 | Q28: 5.1 | R28: 20 | S28: 20.2 | T28: 20 | U28: 18.4 | V28: 17.1 | W28: 31.7 | X28: 97.3 | Y28: 36.2 | Z28: 41.3 | AA28: 33.3 | AB28: 5.7 | AC28: 5 | AD28: 21 | AE28: 7 | AF28: 10 | AG28: 10 | AH28: 9.5 | AI28: 8.4 | AJ28: 80.4 | AK28: 7.9 | AL28: 10.7 | AM28: 3.5 | AN28: 18.7 | AP28: 0.2 | AQ28: 3.6 | AR28: 13.5 | AS28: 14 | AT28: 5.3 | AU28: 9.9 | AV28: 19.4 | AW28: 110.1 | AX28: 13 | AY28: 98.2 | AZ28: 0.6 | BA28: 15.4 | BB28: 22.2 | BC28: 65.4 | BD28: 20 | BE28: 4.7 | BF28: 2.8 | BG28: 2.4 | BH28: 2.4 | BI28: 17.3 | BK28: 20 | BL28: 6 | BM28: 19.7 | BN28: 1155.7
B29: 11:00 | C29: 14 | D29: 17.5 | E29: 5.3 | F29: 17.8 | G29: 2 | I29: 7.6 | J29: 1.3 | K29: 15.2 | M29: 20.2 | N29: 20.2 | O29: 8.6 | P29: 3.6 | Q29: 5.2 | R29: 20 | S29: 20.2 | T29: 20 | U29: 17.75 | V29: 14.9 | W29: 43.1 | X29: 96.5 | Y29: 47 | Z29: 56.3 | AA29: 32.5 | AB29: 5.5 | AC29: 6.5 | AD29: 21 | AE29: 7.1 | AF29: 20 | AG29: 10 | AH29: 9.5 | AI29: 8.4 | AJ29: 80.5 | AK29: 6.6 | AL29: 9.8 | AM29: 3.5 | AN29: 18.7 | AP29: 0.2 | AQ29: 3.6 | AR29: 17.5 | AS29: 15.1 | AT29: 5.4 | AU29: 9.9 | AV29: 24.5 | AW29: 117 | AX29: 9.4 | AY29: 100.2 | AZ29: 0.6 | BA29: 18.3 | BB29: 22.1 | BC29: 68.9 | BD29: 20 | BE29: 4.7 | BF29: 2.7 | BG29: 2.4 | BH29: 2.4 | BI29: 18.2 | BK29: 20 | BL29: 6 | BM29: 19.8 | BN29: 1222.75
B30: 11:30 | C30: 14 | D30: 16.1 | E30: 5 | F30: 20.2 | I30: 9.2 | J30: 0.7 | K30: 15 | M30: 20.2 | N30: 20.2 | O30: 8.5 | P30: 3.6 | Q30: 5.2 | R30: 20 | S30: 19.9 | T30: 20 | U30: 17.77 | V30: 11.7 | W30: 42.6 | X30: 98.1 | Y30: 43.1 | Z30: 65.2 | AA30: 40.6 | AB30: 7.2 | AC30: 7.6 | AD30: 21 | AE30: 7 | AF30: 20 | AG30: 20 | AH30: 9.5 | AI30: 8.4 | AJ30: 80.4 | AK30: 5.5 | AL30: 7.9 | AM30: 3.4 | AN30: 18.7 | AP30: 0.2 | AQ30: 3.6 | AR30: 18.5 | AS30: 15.3 | AT30: 5.4 | AU30: 10 | AV30: 38.8 | AW30: 146.3 | AX30: 22.3 | AY30: 113 | AZ30: 0.6 | BA30: 18.8 | BB30: 24.2 | BC30: 74.3 | BD30: 20 | BE30: 4.5 | BF30: 2.6 | BG30: 2.2 | BH30: 2.4 | BI30: 18.7 | BK30: 20 | BL30: 6 | BM30: 19.8 | BN30: 1320.97
B31: 12:00 | C31: 13.8 | D31: 17.5 | E31: 5.1 | F31: 20.2 | G31: 0.5 | I31: 10 | J31: 0.6 | K31: 15 | M31: 20.1 | N31: 20.3 | O31: 8.3 | P31: 3.6 | Q31: 5.1 | R31: 20 | S31: 20.1 | T31: 20 | U31: 17.78 | V31: 13.6 | W31: 44.3 | X31: 102.2 | Y31: 75.3 | Z31: 71.2 | AA31: 27.4 | AB31: 7.2 | AC31: 8.1 | AD31: 21 | AE31: 7 | AF31: 20 | AG31: 20 | AH31: 10 | AI31: 8.4 | AJ31: 80.5 | AK31: 4.9 | AL31: 7.3 | AM31: 3.4 | AN31: 18.7 | AP31: 0.2 | AQ31: 3.5 | AR31: 18.5 | AS31: 15 | AT31: 5.4 | AU31: 10 | AV31: 45.7 | AW31: 123.9 | AX31: 52.3 | AY31: 110.8 | AZ31: 0.6 | BA31: 18.4 | BB31: 24.1 | BC31: 71.5 | BD31: 20 | BE31: 4.5 | BF31: 2.6 | BG31: 2.2 | BH31: 2.4 | BI31: 19 | BK31: 20 | BL31: 6 | BM31: 19.9 | BN31: 1364.98
B32: 12:30 | C32: 13.9 | D32: 17.5 | E32: 5 | F32: 17.8 | G32: 2 | I32: 10.4 | J32: 0.7 | K32: 14.4 | M32: 20.2 | N32: 20.2 | O32: 8.3 | P32: 3.6 | Q32: 5.1 | R32: 20 | S32: 20.3 | T32: 20 | U32: 18.22 | V32: 17.6 | W32: 45.9 | X32: 100.2 | Y32: 73.8 | Z32: 83.9 | AA32: 38.4 | AB32: 11.8 | AC32: 10.1 | AD32: 21 | AE32: 7 | AF32: 20 | AG32: 20 | AH32: 10 | AI32: 8.4 | AJ32: 80.4 | AK32: 6.6 | AL32: 9.4 | AM32: 3.4 | AN32: 18.7 | AP32: 0.3 | AQ32: 3.5 | AR32: 18.4 | AS32: 14.9 | AT32: 5.3 | AU32: 9.9 | AV32: 66.7 | AW32: 141 | AX32: 62.3 | AY32: 113 | AZ32: 0.6 | BA32: 17.6 | BB32: 24 | BC32: 79.4 | BD32: 20 | BE32: 4.5 | BF32: 2.6 | BG32: 2.2 | BH32: 2.4 | BI32: 19 | BK32: 20 | BL32: 6 | BN32: 1437.82
B33: 13:00 | C33: 13.9 | D33: 17.5 | E33: 4.7 | F33: 7.3 | G33: 2 | I33: 10.8 | J33: 0.6 | K33: 14.6 | M33: 20.2 | N33: 20.2 | O33: 8.4 | P33: 3.6 | Q33: 5.1 | R33: 20 | S33: 19.9 | T33: 20 | U33: 18.22 | V33: 19.3 | W33: 51.3 | X33: 103.4 | Y33: 90.1 | Z33: 82.2 | AA33: 27.1 | AB33: 10.6 | AC33: 12.3 | AD33: 21 | AE33: 7.1 | AF33: 20 | AG33: 20 | AH33: 10 | AI33: 8.4 | AJ33: 80.4 | AK33: 5.9 | AL33: 7.4 | AM33: 3.4 | AN33: 18.7 | AP33: 0.2 | AQ33: 3.5 | AR33: 18.2 | AS33: 15.4 | AT33: 5.4 | AU33: 9.9 | AV33: 72.7 | AW33: 136.8 | AX33: 72 | AY33: 112.2 | AZ33: 0.6 | BA33: 19.1 | BB33: 25.6 | BC33: 77.8 | BD33: 20 | BE33: 4.5 | BF33: 2.6 | BG33: 2.2 | BH33: 2.4 | BI33: 15.9 | BK33: 20 | BL33: 6 | BM33: 12.5 | BN33: 1461.12
B34: 13:30 | C34: 13.9 | D34: 16.4 | E34: 4.6 | F34: 7.2 | G34: 2 | I34: 9.8 | J34: 0.6 | K34: 14.4 | M34: 20.2 | N34: 20.4 | O34: 8.4 | P34: 3.5 | Q34: 5.1 | R34: 19.9 | S34: 20.4 | T34: 20 | U34: 18.27 | V34: 20 | W34: 48 | X34: 102.9 | Y34: 88.5 | Z34: 80.7 | AA34: 12 | AB34: 11.8 | AC34: 9.7 | AD34: 21 | AE34: 7.1 | AF34: 20 | AG34: 20 | AH34: 10 | AI34: 8.4 | AJ34: 80.5 | AK34: 2.4 | AL34: 3.4 | AM34: 3.5 | AN34: 18.7 | AP34: 0.2 | AQ34: 3.6 | AR34: 17.5 | AS34: 13.5 | AT34: 5.2 | AU34: 9.9 | AV34: 97.5 | AW34: 138.3 | AX34: 96.3 | AY34: 113.1 | AZ34: 0.6 | BA34: 17.1 | BB34: 26.2 | BC34: 79.7 | BD34: 20 | BE34: 4.4 | BF34: 2.6 | BG34: 2.2 | BH34: 2.4 | BI34: 15.1 | BK34: 19.9 | BL34: 6 | BM34: 19.9 | BN34: 1484.87
B35: 14:00 | C35: 12.6 | D35: 17.5 | E35: 4.4 | F35: 8.7 | G35: 2 | I35: 10.2 | J35: 0.3 | K35: 14.9 | M35: 20.2 | N35: 20.4 | O35: 8.3 | P35: 3.5 | Q35: 5.1 | R35: 20 | S35: 20.2 | T35: 20 | U35: 18.27 | V35: 18.5 | W35: 51.2 | X35: 102.4 | Y35: 88.5 | Z35: 87.9 | AA35: 6.2 | AB35: 11.6 | AC35: 8.4 | AD35: 21 | AE35: 7.1 | AF35: 20 | AG35: 20 | AH35: 10 | AI35: 8.4 | AJ35: 65.6 | AK35: 1.9 | AL35: 4.2 | AM35: 3.5 | AN35: 18.7 | AP35: 0.5 | AQ35: 3.4 | AR35: 13.2 | AS35: 13 | AT35: 5.3 | AU35: 9.9 | AV35: 103.6 | AW35: 142.6 | AX35: 106.2 | AY35: 114.4 | AZ35: 0.6 | BA35: 17.3 | BB35: 26.1 | BC35: 80.5 | BD35: 20 | BE35: 4.4 | BF35: 2.6 | BG35: 2.2 | BH35: 2.4 | BI35: 13.3 | BK35: 20 | BL35: 6 | BM35: 18.9 | BN35: 1488.07
B36: 14:30 | C36: 12 | D36: 17 | E36: 6 | F36: 9.6 | G36: 2 | I36: 9.7 | J36: 0.3 | K36: 15 | M36: 20.2 | N36: 20.2 | O36: 8.4 | P36: 3.6 | Q36: 5.2 | R36: 19.8 | S36: 20.2 | T36: 20 | U36: 18.4 | V36: 19.6 | W36: 50.7 | X36: 105.9 | Y36: 88.8 | Z36: 84.2 | AA36: 5.4 | AB36: 12 | AC36: 14.5 | AD36: 21 | AE36: 7.1 | AF36: 20 | AG36: 20 | AH36: 10 | AI36: 8.1 | AJ36: 51.4 | AK36: 2.1 | AL36: 3.3 | AM36: 3.5 | AN36: 18.7 | AP36: 0.2 | AQ36: 3.5 | AR36: 9.9 | AS36: 13.5 | AT36: 5.3 | AU36: 9.9 | AV36: 110.6 | AW36: 120.6 | AX36: 119.1 | AY36: 107.2 | AZ36: 0.6 | BA36: 18.9 | BB36: 28.1 | BC36: 71.5 | BD36: 20 | BE36: 4.4 | BF36: 2.5 | BG36: 2.2 | BH36: 2.4 | BI36: 9.8 | BK36: 20 | BL36: 6 | BM36: 17.9 | BN36: 1458
B37: 15:00 | C37: 11.5 | D37: 17.6 | E37: 5 | F37: 16.8 | G37: 2 | I37: 10.3 | J37: 0.2 | K37: 15 | M37: 20.2 | N37: 20.2 | O37: 8.4 | P37: 3.6 | Q37: 5.1 | R37: 19.9 | S37: 20.1 | T37: 20 | U37: 18.41 | V37: 17.6 | W37: 46.3 | X37: 110.2 | Y37: 88.7 | Z37: 87.5 | AA37: 3.7 | AB37: 11.2 | AC37: 12.9 | AD37: 21 | AE37: 7 | AF37: 20 | AG37: 20 | AH37: 10 | AI37: 7.9 | AJ37: 55.1 | AK37: 0.9 | AL37: 3.1 | AM37: 3.5 | AN37: 18.7 | AP37: 0.5 | AQ37: 3.5 | AR37: 6.9 | AS37: 10.8 | AT37: 5.5 | AU37: 9.9 | AV37: 117 | AW37: 121.3 | AX37: 122.6 | AY37: 111 | AZ37: 0.6 | BA37: 14.5 | BB37: 25.4 | BC37: 82.2 | BD37: 20.1 | BE37: 4.4 | BF37: 2.5 | BG37: 2.2 | BH37: 2.3 | BI37: 9.4 | BK37: 19.9 | BL37: 6 | BM37: 19.6 | BN37: 1477.71
B38: 15:30 | C38: 12.8 | D38: 17.2 | E38: 5.2 | F38: 17.3 | G38: 2 | I38: 10.5 | J38: 0.2 | K38: 15 | M38: 20.2 | N38: 20.3 | O38: 8.3 | P38: 3.5 | Q38: 5.1 | R38: 20 | S38: 20.1 | T38: 20 | U38: 18.38 | V38: 16.8 | W38: 54.2 | X38: 113.3 | Y38: 88.2 | Z38: 88.1 | AA38: 2.4 | AB38: 13 | AC38: 12.2 | AD38: 21 | AE38: 7 | AF38: 20 | AG38: 20 | AH38: 10 | AI38: 7.9 | AJ38: 30.5 | AK38: 0.9 | AL38: 0.9 | AM38: 3.5 | AN38: 18.7 | AP38: 0.2 | AQ38: 3.5 | AR38: 5.2 | AS38: 6.7 | AT38: 5.4 | AU38: 9.8 | AV38: 130.5 | AW38: 68.5 | AX38: 123.8 | AY38: 56 | AZ38: 0.6 | BA38: 8.4 | BB38: 30.1 | BC38: 87.5 | BD38: 20 | BE38: 4.4 | BF38: 2.5 | BG38: 2.2 | BH38: 2.3 | BI38: 6.1 | BK38: 20 | BL38: 6 | BM38: 15.3 | BN38: 1359.68
B39: 16:00 | C39: 14 | D39: 17 | E39: 5.2 | F39: 14.1 | G39: 2 | I39: 10.2 | J39: 0.2 | K39: 15 | M39: 20.2 | N39: 20.4 | O39: 8.3 | P39: 3.5 | Q39: 5.1 | R39: 20 | S39: 20.2 | T39: 20 | U39: 18.38 | V39: 15.5 | W39: 57.2 | X39: 108.1 | Y39: 89.4 | Z39: 86.8 | AA39: 2 | AB39: 11.7 | AC39: 13.2 | AD39: 21 | AE39: 6.9 | AF39: 20 | AG39: 20 | AH39: 10 | AI39: 7.9 | AJ39: 17.1 | AL39: 0.1 | AM39: 3.4 | AN39: 18.7 | AP39: 0.1 | AQ39: 3.5 | AR39: 4.4 | AS39: 4.1 | AT39: 5.4 | AU39: 9.9 | AV39: 120.7 | AW39: 21.1 | AX39: 124.2 | AY39: 22.2 | AZ39: 0.6 | BA39: 5 | BB39: 30 | BC39: 85.9 | BD39: 20 | BE39: 4.4 | BF39: 2.5 | BG39: 2.2 | BH39: 2.3 | BI39: 6.8 | BK39: 20 | BL39: 6 | BM39: 5.9 | BN39: 1229.98
B40: 16:30 | C40: 13.9 | D40: 16.3 | E40: 5.5 | F40: 11.8 | G40: 2 | I40: 10.9 | J40: 0.1 | K40: 15 | M40: 20.2 | N40: 20.3 | O40: 8.3 | P40: 3.6 | Q40: 5.1 | R40: 20 | S40: 20.3 | T40: 20 | U40: 18.37 | V40: 13.3 | W40: 64.8 | X40: 110.6 | Y40: 88.1 | Z40: 87.6 | AA40: 1.7 | AB40: 11.3 | AC40: 12.3 | AD40: 21 | AE40: 6.8 | AF40: 20 | AG40: 20 | AH40: 10 | AI40: 7.8 | AJ40: 9.2 | AM40: 3.4 | AN40: 18.7 | AP40: 0.1 | AQ40: 3.5 | AR40: 2.9 | AS40: 10.1 | AT40: 5.4 | AU40: 9.9 | AV40: 119.7 | AW40: 15.6 | AX40: 124.5 | AY40: 16.3 | AZ40: 0.6 | BA40: 9.1 | BB40: 29.7 | BC40: 79.7 | BD40: 20 | BE40: 4.4 | BF40: 2.5 | BG40: 2.2 | BH40: 2.3 | BI40: 5.3 | BK40: 20 | BL40: 6 | BM40: 5.7 | BN40: 1213.77
B41: 17:00 | C41: 14 | D41: 17.1 | E41: 5.6 | F41: 11.5 | G41: 2 | I41: 10.9 | J41: 0.1 | K41: 15 | M41: 20.1 | N41: 20.1 | O41: 8.3 | P41: 3.6 | Q41: 5.2 | R41: 19.8 | S41: 19.8 | T41: 20 | U41: 18.35 | V41: 12.9 | W41: 69.4 | X41: 110.1 | Y41: 88.8 | Z41: 90.2 | AA41: 0.8 | AB41: 10 | AC41: 10.7 | AD41: 21 | AE41: 6.8 | AF41: 20 | AG41: 20 | AH41: 10 | AI41: 7.6 | AJ41: 7.6 | AM41: 3.4 | AN41: 18.7 | AQ41: 3.4 | AR41: 2 | AS41: 10.4 | AT41: 5.3 | AU41: 10 | AV41: 125.4 | AW41: 22.6 | AX41: 126.4 | AY41: 19.1 | AZ41: 0.6 | BA41: 11.8 | BB41: 30.6 | BC41: 82.1 | BD41: 20 | BE41: 4.4 | BF41: 2.5 | BG41: 2.2 | BH41: 2.4 | BI41: 2.7 | BK41: 19.8 | BL41: 6 | BM41: 8.5 | BN41: 1237.65
B42: 17:30 | C42: 13.3 | D42: 16.7 | E42: 5.5 | F42: 8.3 | G42: 2 | I42: 9.2 | J42: 0.1 | K42: 15.1 | M42: 20.1 | N42: 20.2 | O42: 8.3 | P42: 3.6 | Q42: 5.2 | R42: 20 | S42: 20.3 | T42: 20 | U42: 18.35 | V42: 12.8 | W42: 74.4 | X42: 111.9 | Y42: 88.6 | Z42: 88.4 | AA42: 0.4 | AB42: 12 | AC42: 13.2 | AD42: 21 | AE42: 6.7 | AF42: 20 | AG42: 20 | AH42: 10 | AI42: 7.6 | AJ42: 4.6 | AK42: 2 | AL42: 1.5 | AM42: 3.4 | AN42: 18.7 | AP42: 0.1 | AQ42: 3.6 | AR42: 1.8 | AS42: 2.2 | AT42: 5.4 | AU42: 9.9 | AV42: 119.2 | AW42: 9.9 | AX42: 125.1 | AY42: 9 | AZ42: 0.6 | BA42: 2.4 | BB42: 28.9 | BC42: 83.3 | BD42: 20 | BE42: 4.5 | BF42: 2.8 | BG42: 2.2 | BH42: 2.4 | BI42: 0.9 | BK42: 20 | BL42: 6 | BM42: 2.1 | BN42: 1185.75
B43: 18:00 | C43: 13.5 | D43: 16.7 | E43: 5.7 | F43: 7.8 | G43: 2 | I43: 10.7 | K43: 15.2 | M43: 20.1 | N43: 20.2 | O43: 8.3 | P43: 3.5 | Q43: 5.2 | R43: 20 | S43: 20.2 | T43: 19.9 | U43: 18.33 | V43: 12.4 | W43: 78.7 | X43: 112.7 | Y43: 83.7 | Z43: 87.9 | AA43: 0.4 | AB43: 11.2 | AC43: 10.7 | AD43: 21 | AE43: 6.7 | AF43: 20 | AG43: 20 | AH43: 10 | AI43: 8.3 | AJ43: 1.3 | AK43: 1.5 | AL43: 0.6 | AM43: 3.4 | AN43: 18.7 | AQ43: 3.6 | AR43: 0.6 | AS43: 0.4 | AT43: 5.2 | AU43: 9.9 | AV43: 129.9 | AW43: 4.3 | AX43: 128.4 | AY43: 4.2 | AZ43: 0.6 | BA43: 0.4 | BB43: 28.4 | BC43: 82.2 | BD43: 19.9 | BE43: 4.5 | BF43: 2.8 | BG43: 2.2 | BH43: 2.4 | BI43: 0.5 | BK43: 20 | BL43: 6 | BM43: 0.3 | BN43: 1173.23
B44: 18:30 | C44: 14 | D44: 16.8 | E44: 5.6 | F44: 7.9 | G44: 2 | I44: 10.5 | K44: 15.2 | M44: 20.1 | N44: 20.2 | O44: 8.3 | P44: 3.5 | Q44: 5.2 | R44: 20 | S44: 20 | T44: 20 | U44: 18.32 | V44: 11.5 | W44: 78 | X44: 108.7 | Y44: 86 | Z44: 89.1 | AB44: 8.9 | AC44: 8.5 | AD44: 21 | AE44: 6.6 | AF44: 20 | AG44: 20 | AH44: 10 | AI44: 8.2 | AK44: 0.7 | AM44: 3.4 | AN44: 18.7 | AQ44: 3.6 | AT44: 5.4 | AU44: 9.9 | AV44: 124.4 | AX44: 126.6 | AY44: 0.2 | AZ44: 0.6 | BB44: 26.9 | BC44: 77.7 | BD44: 19.9 | BE44: 4.5 | BF44: 2.8 | BG44: 2.2 | BH44: 2.4 | BI44: 0.1 | BK44: 20 | BL44: 6 | BN44: 1140.12
B45: 19:00 | C45: 14 | D45: 16.6 | E45: 6.1 | F45: 7.9 | G45: 2 | I45: 10.7 | K45: 15.2 | M45: 20.1 | N45: 20.2 | O45: 8.3 | P45: 3.6 | Q45: 5.2 | R45: 20 | S45: 20.1 | T45: 20 | U45: 18.32 | V45: 10.3 | W45: 78.3 | X45: 106.4 | Y45: 89.2 | Z45: 91.6 | AB45: 8.7 | AC45: 9.2 | AD45: 21 | AE45: 6.6 | AF45: 20 | AG45: 20 | AH45: 10 | AI45: 8.2 | AK45: 0.7 | AM45: 3.4 | AN45: 18.7 | AQ45: 3.6 | AT45: 5.3 | AU45: 9.9 | AV45: 109.8 | AX45: 118.7 | AZ45: 0.6 | BB45: 25.6 | BC45: 78.5 | BD45: 19.9 | BE45: 4.7 | BF45: 2.8 | BG45: 2.4 | BH45: 2.4 | BK45: 20 | BL45: 6 | BN45: 1120.82
B46: 19:30 | C46: 14 | D46: 16.8 | E46: 6.1 | F46: 17.1 | G46: 2 | I46: 10.5 | K46: 15.4 | M46: 20.1 | N46: 20.2 | O46: 8.3 | P46: 3.5 | Q46: 5.2 | R46: 20 | S46: 20.4 | T46: 20 | U46: 17.71 | V46: 10.5 | W46: 72.6 | X46: 105.3 | Y46: 81.2 | Z46: 95.5 | AB46: 6.4 | AC46: 5 | AD46: 21 | AE46: 6.5 | AF46: 20 | AG46: 20 | AH46: 10 | AI46: 8.2 | AK46: 0.8 | AM46: 3.4 | AN46: 18.7 | AQ46: 3.6 | AT46: 5.4 | AU46: 9.9 | AV46: 85.9 | AX46: 106.1 | AZ46: 0.6 | BB46: 27.8 | BC46: 74.8 | BD46: 20 | BE46: 4.7 | BF46: 2.8 | BG46: 2.4 | BH46: 2.4 | BK46: 20 | BL46: 6 | BN46: 1074.81
B47: 20:00 | C47: 14 | D47: 17.1 | E47: 5.3 | F47: 20.4 | G47: 2 | I47: 10.1 | K47: 15.3 | M47: 20.1 | N47: 20.2 | O47: 8.2 | P47: 3.5 | Q47: 5.1 | R47: 20 | S47: 20.1 | T47: 20 | U47: 17.71 | V47: 11.4 | W47: 70.7 | X47: 95.5 | Y47: 72.5 | Z47: 96 | AB47: 4.7 | AC47: 3.2 | AD47: 21 | AE47: 6.4 | AF47: 20 | AG47: 20 | AH47: 10 | AI47: 8.1 | AK47: 0.3 | AM47: 3.4 | AN47: 18.7 | AQ47: 3.6 | AT47: 5.5 | AU47: 9.9 | AV47: 53.2 | AX47: 60.5 | AZ47: 0.6 | BB47: 23.6 | BC47: 65.6 | BD47: 20 | BE47: 4.7 | BF47: 3 | BG47: 2.4 | BH47: 2.4 | BK47: 20 | BL47: 6 | BN47: 962.01
B48: 20:30 | C48: 14 | D48: 15.8 | E48: 5.9 | F48: 20.4 | G48: 2 | I48: 9.8 | K48: 14.9 | M48: 20.1 | N48: 20.2 | O48: 8.2 | P48: 3.6 | Q48: 5.2 | R48: 20 | S48: 20.1 | T48: 20 | U48: 17.74 | V48: 12.6 | W48: 61.6 | X48: 82.6 | Y48: 67.4 | Z48: 94.4 | AB48: 4.5 | AC48: 2.5 | AD48: 21 | AE48: 6.4 | AF48: 20 | AG48: 20 | AH48: 10 | AI48: 8 | AM48: 3.4 | AN48: 18.7 | AQ48: 3.6 | AT48: 5.4 | AU48: 9.9 | AV48: 41.3 | AX48: 51.8 | AZ48: 0.6 | BB48: 20.6 | BC48: 53.8 | BD48: 20 | BE48: 4.7 | BF48: 3 | BG48: 2.4 | BH48: 2.4 | BK48: 20 | BL48: 6 | BN48: 896.54
B49: 21:00 | C49: 14 | D49: 15.4 | E49: 6 | F49: 20.4 | G49: 2 | I49: 9.3 | K49: 14.7 | M49: 20.1 | N49: 20.2 | O49: 8.2 | P49: 3.5 | Q49: 5.2 | R49: 20 | S49: 20.4 | T49: 20 | U49: 17.75 | V49: 12.4 | W49: 56.8 | X49: 88.6 | Y49: 60.3 | Z49: 93.1 | AB49: 4.5 | AC49: 2 | AD49: 21 | AE49: 6.4 | AF49: 20 | AG49: 20 | AH49: 10 | AI49: 8 | AM49: 3.4 | AN49: 18.7 | AQ49: 3.6 | AT49: 5.3 | AU49: 9.9 | AV49: 18.9 | AX49: 28.1 | AZ49: 0.6 | BB49: 17 | BC49: 47 | BD49: 20 | BE49: 4.7 | BF49: 3 | BG49: 2.4 | BH49: 2.4 | BK49: 20 | BL49: 6 | BN49: 831.25
B50: 21:30 | C50: 14 | D50: 17.1 | E50: 5.6 | F50: 20.4 | G50: 2 | I50: 10.2 | K50: 14.6 | M50: 20 | N50: 20.2 | O50: 8.2 | P50: 3.6 | Q50: 5.2 | R50: 20 | S50: 20.3 | T50: 20 | U50: 17.75 | V50: 12.2 | W50: 61.6 | X50: 92.3 | Y50: 50.7 | Z50: 87.2 | AB50: 4.9 | AC50: 2.2 | AD50: 21 | AE50: 6.2 | AF50: 20 | AG50: 20 | AH50: 10 | AI50: 7.8 | AM50: 3.4 | AN50: 18.7 | AQ50: 3.6 | AT50: 5.5 | AU50: 9.9 | AV50: 22.1 | AX50: 20.6 | AZ50: 0.6 | BB50: 21 | BC50: 62.6 | BD50: 20 | BE50: 4.7 | BF50: 3 | BG50: 2.4 | BH50: 2.4 | BK50: 20 | BL50: 6 | BN50: 841.75
B51: 22:00 | C51: 14 | D51: 16.5 | E51: 7.4 | F51: 20.4 | G51: 2 | I51: 10.3 | K51: 14.9 | M51: 20 | N51: 20.2 | O51: 8.2 | P51: 3.5 | Q51: 5.2 | R51: 20 | S51: 20.1 | T51: 20 | U51: 17.76 | V51: 8.2 | W51: 54.6 | X51: 75.7 | Y51: 49.9 | Z51: 78.6 | AB51: 2.6 | AC51: 1.6 | AD51: 21 | AE51: 6.2 | AF51: 20 | AG51: 20 | AH51: 10 | AI51: 7.8 | AM51: 3.4 | AN51: 18.7 | AQ51: 3.6 | AT51: 5.3 | AU51: 9.9 | AV51: 15.7 | AX51: 16.3 | AZ51: 0.6 | BB51: 20.7 | BC51: 60 | BD51: 20 | BE51: 4.7 | BF51: 3 | BG51: 2.4 | BH51: 2.4 | BK51: 20 | BL51: 6 | BN51: 789.36
B52: 22:30 | C52: 13 | D52: 17 | E52: 7.5 | F52: 20.4 | G52: 2 | I52: 10.2 | K52: 15.2 | M52: 20 | N52: 20.2 | O52: 8.4 | P52: 3.6 | Q52: 5.2 | R52: 20 | S52: 19.7 | T52: 20 | U52: 17.76 | V52: 8.8 | W52: 50.3 | X52: 75.7 | Y52: 61.2 | Z52: 88.6 | AB52: 4.6 | AC52: 2.4 | AD52: 21 | AE52: 6.2 | AF52: 20 | AG52: 20 | AH52: 10 | AI52: 7.8 | AK52: 0.6 | AL52: 1.5 | AM52: 3.4 | AN52: 18.7 | AQ52: 3.6 | AT52: 5.3 | AU52: 9.8 | AV52: 8 | AX52: 16.2 | AZ52: 0.6 | BB52: 20.4 | BC52: 57.9 | BD52: 20 | BE52: 4.7 | BF52: 3 | BG52: 2.4 | BH52: 2.4 | BK52: 20 | BL52: 6 | BN52: 801.26
B53: 23:00 | C53: 12.6 | D53: 17.2 | E53: 8 | F53: 20.4 | G53: 2 | I53: 10.1 | K53: 15.5 | M53: 20 | N53: 20.2 | O53: 8.5 | P53: 3.5 | Q53: 5.3 | R53: 19.8 | S53: 19.9 | T53: 20 | U53: 17.79 | V53: 11.2 | W53: 42.4 | X53: 70.4 | Y53: 63 | Z53: 90.9 | AB53: 5.9 | AC53: 2.7 | AD53: 21 | AE53: 6 | AF53: 20 | AG53: 20 | AH53: 10 | AI53: 7.8 | AK53: 3.3 | AL53: 4.4 | AM53: 3.5 | AN53: 18.7 | AQ53: 3.6 | AT53: 5.4 | AU53: 9.9 | AV53: 3.7 | AX53: 8.8 | AZ53: 0.6 | BB53: 20.2 | BC53: 56.3 | BD53: 20.1 | BE53: 4.7 | BF53: 3 | BG53: 2.4 | BH53: 2.4 | BK53: 19.8 | BL53: 6.2 | BN53: 789.09
B54: 23:30 | C54: 12.8 | D54: 17.2 | E54: 8.7 | F54: 18 | G54: 2 | I54: 10 | K54: 15.6 | M54: 19.9 | N54: 20.2 | O54: 8.4 | P54: 3.5 | Q54: 5.3 | R54: 20 | S54: 20.1 | T54: 20 | U54: 17.76 | V54: 13.1 | W54: 37 | X54: 70.4 | Y54: 53.7 | Z54: 76.4 | AB54: 4.1 | AC54: 1.8 | AD54: 21 | AE54: 6 | AF54: 20 | AG54: 20 | AH54: 10 | AI54: 7.8 | AK54: 2 | AL54: 3.2 | AM54: 3.4 | AN54: 18.7 | AQ54: 3.6 | AT54: 5.3 | AU54: 10 | AV54: 1.7 | AX54: 4.4 | AZ54: 0.6 | BB54: 19.8 | BC54: 54.1 | BD54: 20 | BE54: 4.7 | BF54: 2.9 | BG54: 2.4 | BH54: 2.4 | BK54: 20 | BL54: 6.1 | BN54: 746.06
B55: 0:00 | C55: 13.6 | D55: 17.2 | E55: 7.9 | F55: 12.8 | G55: 2 | I55: 9.9 | K55: 15.4 | M55: 19.9 | N55: 20.3 | O55: 8.4 | P55: 3.6 | Q55: 5.2 | R55: 19.9 | S55: 20.5 | T55: 20 | U55: 17.77 | V55: 11.6 | W55: 42.8 | X55: 64.9 | Y55: 43.8 | Z55: 68.9 | AB55: 2.2 | AC55: 1.2 | AD55: 21 | AE55: 6 | AF55: 20 | AG55: 20 | AH55: 10 | AI55: 7.8 | AK55: 2.1 | AL55: 4.8 | AM55: 3.4 | AN55: 18.7 | AQ55: 3.6 | AT55: 5.4 | AU55: 9.9 | AV55: 1.6 | AX55: 0.8 | AZ55: 0.6 | BB55: 19.3 | BC55: 51.3 | BD55: 20 | BE55: 4.7 | BF55: 2.9 | BG55: 2.4 | BH55: 2.4 | BK55: 19.9 | BL55: 6 | BN55: 714.37
B56: EJEC MWh | C56: 331.15 | D56: 408.2 | E56: 159.85 | F56: 285.4 | G56: 46.25 | H56: 0 | I56: 240.15 | J56: 5.05 | K56: 360.7 | L56: 0 | M56: 476.9 | N56: 485.45 | O56: 206.35 | P56: 85.15 | Q56: 124.05 | R56: 478.85 | S56: 484.55 | T56: 479.95 | U56: 437.035 | V56: 443.55 | W56: 1002.6 | X56: 2080.4 | Y56: 1457.65 | Z56: 1766.25 | AA56: 240 | AB56: 147.15 | AC56: 129.35 | AD56: 503.9 | AE56: 160.6 | AF56: 450 | AG56: 437.5 | AH56: 222.25 | AI56: 192.4 | AJ56: 503.9 | AK56: 42.55 | AL56: 59.75 | AM56: 82.6 | AN56: 448.8 | AO56: 0 | AP56: 1.95 | AQ56: 86.15 | AR56: 102.7 | AS56: 100.9 | AT56: 128.55 | AU56: 237.75 | AV56: 1269.7 | AW56: 1109.4 | AX56: 1362.25 | AY56: 922.55 | AZ56: 14.4 | BA56: 122.1 | BB56: 521.2 | BC56: 1462.8 | BD56: 479.85 | BE56: 110.9 | BF56: 67.6 | BG56: 56.1 | BH56: 57.4 | BI56: 117.9 | BJ56: 0 | BK56: 479 | BL56: 140.1 | BM56: 145.5 | BN56: 24562.985
L70: TERMOELÉCTRICA | M70: 1431.35 | N70: 5.8272641 | O70: #FF0000
L71: SOLAR | M71: 3371.95 | N71: 13.72777 | O71: #FBFB00
L72: HIDROELÉCTRICA | M72: 8014.485 | N72: 32.628302 | O72: #00B0F0
L73: EÓLICA | M73: 11745.2 | N73: 47.816664 | O73: #FBBD00

Sheet COGENERACIÓN
B3: martes, 21 de Enero del 2025
B5: CENTRALES DE COGENERACIÓN DEL SEIN
B6: HORA | C6: AGRO INDUSTRIAL PARAMONGA S.A. | D6: AGROAURORA S.A.C. | E6: AGROINDUSTRIAS SAN JACINTO S.A.A. | F6: BIOENERGIA DEL CHIRA S.A. | G6: GM OPERACIONES S.A.C. | H6: SDF ENERGIA SAC | I6: TOTAL COGENERACION
C7: C.T. PARAMONGA | D7: C.T. MAPLE | E7: C.T SAN JACINTO | F7: C.T. CAÑA BRAVA | G7: C.T. REFINERÍA TALARA | H7: C.T. OQUENDO | I7: MW
B8: 0:30 | C8: 14 | D8: 17.6 | E8: 8.4 | F8: 10.5 | G8: 50.3 | H8: 32.4 | I8: 133.2
B9: 1:00 | C9: 14.1 | D9: 17.2 | E9: 8.1 | F9: 9.9 | G9: 50.7 | H9: 32.5 | I9: 132.5
B10: 1:30 | C10: 14.3 | D10: 17.2 | E10: 8.4 | F10: 10 | G10: 51.1 | H10: 32.5 | I10: 133.5
B11: 2:00 | C11: 14.6 | D11: 17.4 | E11: 7.7 | F11: 10.3 | G11: 50.6 | H11: 32.6 | I11: 133.2
B12: 2:30 | C12: 13.8 | D12: 17.6 | E12: 8 | F12: 10.1 | G12: 50.9 | H12: 32.4 | I12: 132.8
B13: 3:00 | C13: 14.5 | D13: 17.6 | E13: 7.1 | F13: 10.1 | G13: 50.8 | H13: 32.4 | I13: 132.5
B14: 3:30 | C14: 14.3 | D14: 16.3 | E14: 6.7 | F14: 10 | G14: 50.8 | H14: 32.5 | I14: 130.6
B15: 4:00 | C15: 14.3 | D15: 16.1 | E15: 7.7 | F15: 9.6 | G15: 50.4 | H15: 32.5 | I15: 130.6
B16: 4:30 | C16: 14.3 | D16: 15.5 | E16: 8.2 | F16: 9.8 | G16: 51.3 | H16: 32.6 | I16: 131.7
B17: 5:00 | C17: 14.3 | D17: 16.5 | E17: 7.9 | F17: 9.6 | G17: 50.4 | H17: 32.6 | I17: 131.3
B18: 5:30 | C18: 14.5 | D18: 17.5 | E18: 8.6 | F18: 8 | G18: 50.8 | H18: 32.7 | I18: 132.1
B19: 6:00 | C19: 14.5 | D19: 17.2 | E19: 8.6 | F19: 10 | G19: 50.5 | H19: 32.6 | I19: 133.4
... B56: EJEC MWh | C56: 331.15 | D56: 408.2 | E56: 159.85 | F56: 240.15 | G56: 1216.35 | H56: 776.4 | I56: 3132.1

Sheet EVO_PRO_ENE
B3: miércoles, 1 de Enero del 2025 - martes, 21 de Enero del 2025
B5: EVOLUCIÓN DE LA PRODUCCIÓN DE LA ENERGÍA DIARIA DE LOS INTEGRANTES DEL COES (MWh)
B6: EMPRESA | C6: CENTRAL | D6: UNIDAD | E6: TIPO | F6: Enero
F7: 1 | G7: 2 | H7: 3 | I7: 4 | J7: 5 | K7: 6 | L7: 7 | M7: 8 | N7: 9 | O7: 10 | P7: 11 | Q7: 12 | R7: 13 | S7: 14 | T7: 15 | U7: 16 | V7: 17 | W7: 18 | X7: 19 | Y7: 20 | Z7: 21 | AA7: TOTAL
B8: AGRO INDUSTRIAL PARAMONGA S.A. | C8: C.T. PARAMONGA | D8: TV-01 | E8: TERMOELÉCTRICA | L8: 224.55 | M8: 388.3 | N8: 387.45 | O8: 389.1 | P8: 389.05 | Q8: 381.85 | R8: 353.1 | S8: 355.3 | T8: 354.05 | U8: 346.3 | V8: 315.55 | W8: 319.35 | X8: 312.65 | Y8: 309.55 | Z8: 331.15 | AA8: 5157.3
B9: AGROAURORA S.A.C. | C9: C.T. MAPLE ETANOL | D9: TV | E9: TERMOELÉCTRICA | F9: 360 | H9: 179.75 | I9: 379.5 | J9: 393.65 | K9: 392.45 | L9: 383.75 | M9: 362.8 | N9: 358.2 | O9: 362.8 | P9: 359.2 | Q9: 375.75 | R9: 354.95 | S9: 349.4 | T9: 325.2 | U9: 355.95 | V9: 340.75 | W9: 305.8 | X9: 409.85 | Y9: 412.35 | Z9: 408.2 | AA9: 7170.3
B10: AGROINDUSTRIAS SAN JACINTO S.A.A. | C10: C.T. SAN JACINTO | D10: CENTRAL | E10: TERMOELÉCTRICA | K10: 58.45 | L10: 96.65 | M10: 161.7 | N10: 175.7 | O10: 179.9 | P10: 182.405 | Q10: 177.25 | R10: 172.8 | S10: 188.05 | T10: 187.3 | U10: 186.2334 | V10: 186.05 | W10: 187.85 | X10: 197.1 | Y10: 193 | Z10: 159.85 | AA10: 2690.2884
B11: ANDEAN POWER S.A.C. | C11: C.H. CARHUAC | D11: CENTRAL | E11: HIDROELÉCTRICA | F11: 436.45 | G11: 447.15 | H11: 484.25 | I11: 484.6 | J11: 483.35 | K11: 484 | L11: 450.25 | M11: 439.95 | N11: 429.3 | O11: 414.6 | P11: 437.75 | Q11: 418.5 | R11: 384.05 | S11: 410.75 | T11: 360.5 | U11: 432.65 | V11: 420.55 | W11: 384.55 | X11: 413.3 | Y11: 306.8 | Z11: 285.4 | AA11: 8808.7
B12: ASOCIACIÓN SANTA LUCIA DE CHACAS | C12: C.H. HUALLIN | D12: CENTRAL | E12: HIDROELÉCTRICA | F12: 48 | G12: 45.85 | H12: 48 | I12: 48 | J12: 48 | K12: 48 | L12: 48 | M12: 48 | N12: 48 | O12: 48 | P12: 29.55 | Q12: 48 | R12: 46.9 | S12: 48 | T12: 48 | U12: 48 | V12: 48 | W12: 48 | X12: 48 | Y12: 46.15 | Z12: 46.25 | AA12: 982.7
B13: ATRIA ENERGIA S.A.C. | C13: C.H. PURMACANA | D13: CENTRAL | E13: HIDROELÉCTRICA | AA13: 0
B14: BIOENERGIA DEL CHIRA S.A. | C14: C.T. CAÑA BRAVA | D14: CENTRAL | E14: TERMOELÉCTRICA | F14: 230.05 | G14: 4.15 | H14: 207.1 | I14: 231.25 | J14: 226.25 | K14: 229.1 | L14: 220.25 | M14: 242.55 | N14: 215 | O14: 246.75 | P14: 247.3 | Q14: 230.9 | R14: 230.2 | S14: 243 | T14: 240.05 | U14: 241.5 | V14: 213.8 | W14: 244.1 | X14: 238 | Y14: 244.65 | Z14: 240.15 | AA14: 4666.1
B15: CELEPSA | C15: C.H. EL PLATANAL | D15: CENTRAL | E15: HIDROELÉCTRICA | F15: 4523.65 | G15: 4474.1 | H15: 4762.5 | I15: 5166.1 | J15: 5163.45 | K15: 5266.75 | L15: 5280.35 | M15: 5023.05 | N15: 5010.85 | O15: 5120.1 | P15: 5245 | Q15: 5145.95 | R15: 5180.55 | S15: 5298.45 | T15: 5167.65 | U15: 5203.4 | V15: 5292.25 | W15: 5062.05 | X15: 5063.7 | Y15: 5258.25 | Z15: 5275.15 | AA15: 106983.3
B16: CELEPSA RENOVABLES S.R.L. | C16: C.H. MARAÑON | D16: CENTRAL | E16: HIDROELÉCTRICA | F16: 473.65 | G16: 473.1 | H16: 415.2 | I16: 360.25 | J16: 431.7 | K16: 469.85 | L16: 472.8 | M16: 472.8 | N16: 473.1415 | O16: 472.8 | P16: 472.8 | Q16: 472.8 | R16: 472.8 | S16: 472.8 | T16: 472.8 | U16: 472.8 | V16: 472.8 | W16: 472.8 | X16: 472.8 | Y16: 453.45 | Z16: 475.45 | AA16: 9699.3915
B17: CENTRALES SANTA ROSA S.A.C. | C17: C.H. SANTA ROSA I | D17: CENTRAL | E17: HIDROELÉCTRICA | F17: 25.45 | G17: 25.95 | H17: 19.75 | I17: 13.4 | J17: 18.1 | K17: 20.2 | L17: 22.1 | M17: 23.3 | N17: 24.3 | O17: 24.45 | P17: 25.2 | Q17: 25.2 | R17: 25.35 | S17: 23.95 | T17: 14.65 | U17: 25.4 | V17: 25.75 | W17: 26.2 | X17: 26.3 | Y17: 24.8 | Z17: 24.55 | AA17: 484.35
B18: CENTRALES SANTA ROSA S.A.C. | C18: C.H. SANTA ROSA II | D18: CENTRAL | E18: HIDROELÉCTRICA | F18: 37.7 | G18: 37.1 | H18: 31.9 | I18: 24.55 | J18: 31.45 | K18: 35.3 | L18: 35.95 | M18: 36.35 | N18: 37.05 | O18: 37.2 | P18: 38.45 | Q18: 38.2 | R18: 37.9 | S18: 36.25 | T18: 22.3 | U18: 36.7 | V18: 37.15 | W18: 39.2 | X18: 38.45 | Y18: 36.85 | Z18: 38.1 | AA18: 744.1
B19: CHINANGO S.A.C. | C19: C.H. CHIMAY | D19: CENTRAL | E19: HIDROELÉCTRICA | F19: 3094.35 | G19: 3340.85 | H19: 3399.5 | I19: 3452.55 | J19: 3481.7 | K19: 3446.85 | L19: 2227.35 | M19: 3331.064 | N19: 2748.9 | O19: 3452.7 | P19: 2273.8 | Q19: 3314.15 | R19: 3434.2 | S19: 3445.75 | T19: 3447 | U19: 3516.65 | V19: 3387.15 | W19: 3459.45 | X19: 3425.5 | Y19: 851.55 | Z19: 1126.4 | AA19: 63657.414
B20: CHINANGO S.A.C. | C20: C.H. YANANGO | D20: CENTRAL | E20: HIDROELÉCTRICA | F20: 816.75 | G20: 970.5 | H20: 1005.45 | I20: 1002.9 | J20: 1005 | K20: 1004.55 | L20: 1004.4 | M20: 1004.0105 | N20: 1004.4 | O20: 993.6 | P20: 999.4 | Q20: 1004.85 | R20: 993.1 | S20: 929.1 | T20: 853.8 | U20: 785.6 | V20: 742.25 | W20: 738.7 | X20: 823.5 | Y20: 510.57261 | Z20: 1000.85 | AA20: 19193.283
B21: COLCA SOLAR S.A.C. | C21: C.S. YARUCAYA | D21: CENTRAL | E21: SOLAR | F21: 4.85 | G21: 4.35 | H21: 6.75 | I21: 6.6 | J21: 7.6 | K21: 4.8 | L21: 5.35 | M21: 7.05 | N21: 7.3 | O21: 4.7 | P21: 6.9 | Q21: 7.95 | R21: 6.7 | S21: 6.95 | T21: 8.85 | U21: 6.85 | V21: 6.9 | W21: 6.7 | X21: 6.7 | Y21: 9 | Z21: 5.05 | AA21: 137.9
B22: EGASA | C22: C.H. CHARCANI III | D22: CENTRAL | E22: HIDROELÉCTRICA | F22: 144.4 | G22: 148.8 | H22: 151.3 | I22: 151.2 | J22: 154.25 | K22: 151.25 | L22: 151.15 | M22: 151.2 | N22: 151.2 | O22: 153.1 | P22: 156.51 | Q22: 156.7 | R22: 156.15 | S22: 155.05 | T22: 154.45 | U22: 158.35 | V22: 164.1 | W22: 163.65 | X22: 90.85 | Y22: 163.2 | Z22: 163.9 | AA22: 3190.76
B23: EGASA | C23: C.H. CHARCANI IV | D23: CENTRAL | E23: HIDROELÉCTRICA | F23: 239.55 | G23: 234.3 | H23: 245.4 | I23: 241.3 | J23: 241.65 | K23: 239.15 | L23: 234.75 | M23: 231.05 | N23: 231.35 | O23: 235.64 | P23: 230.91 | Q23: 236.25 | R23: 236.1 | S23: 231.15 | T23: 229.7 | U23: 233.5 | V23: 238.6 | W23: 172.1 | X23: 73.1 | Y23: 120 | Z23: 121.15 | AA23: 4496.7
B24: EGASA | C24: C.H. CHARCANI V | D24: CENTRAL | E24: HIDROELÉCTRICA | F24: 1540.9 | G24: 1524 | H24: 1529.2 | I24: 1526.8 | J24: 1554.35 | K24: 1503.95 | L24: 1515 | M24: 1511.6 | N24: 1504.7 | O24: 1496.02 | P24: 1512.455 | Q24: 1528 | R24: 1503.7 | S24: 1525.2 | T24: 1515.85 | U24: 1768.05 | V24: 1786.1 | W24: 1782.85 | X24: 1808.75 | Y24: 1817.45 | Z24: 1801.45 | AA24: 33556.375
B25: EGASA | C25: C.H. CHARCANI VI | D25: CENTRAL | E25: HIDROELÉCTRICA | F25: 134.95 | G25: 136.9 | H25: 144.1 | I25: 126 | J25: 140.8 | K25: 138.75 | L25: 141.85 | M25: 137.65 | N25: 139.9 | O25: 138.645 | P25: 139.425 | Q25: 141.25 | R25: 140.55 | S25: 137.7 | T25: 137.25 | U25: 139.15 | V25: 162.8 | W25: 168.9 | X25: 157.05 | Y25: 165.5 | Z25: 170.8 | AA25: 3039.92
B26: EGASA | C26: C.T. CHILINA DIESEL | D26: CENTRAL | E26: TERMOELÉCTRICA | G26: 4.25 | AA26: 4.25
B27: EGASA | C27: C.T. CHILINA DIESEL | D27: TG | E27: TERMOELÉCTRICA | AA27: 0
B28: EGASA | C28: C.T. MOLLENDO DIESEL | D28: CENTRAL | E28: TERMOELÉCTRICA | AA28: 0
B29: EGEJUNIN | C29: C.H. HUASAHUASI I | D29: CENTRAL | E29: HIDROELÉCTRICA | F29: 247.6 | G29: 430.95 | H29: 474.25 | I29: 475.2 | J29: 473.2 | K29: 475.2 | L29: 470.1 | M29: 472.65 | N29: 445.9 | O29: 414.8 | P29: 412.6 | Q29: 475.2 | R29: 464.3 | S29: 382.85 | T29: 325.1 | U29: 275.75 | V29: 261.35 | W29: 249.35 | X29: 248.6 | Y29: 402.3 | Z29: 360.7 | AA29: 8237.95
B30: EGEJUNIN | C30: C.H. RUNATULLO II | D30: CENTRAL | E30: HIDROELÉCTRICA | F30: 349.2 | G30: 426.2 | H30: 478.5 | I30: 478.35 | J30: 477.55 | K30: 477 | L30: 477.65 | M30: 478.6 | N30: 481.25 | O30: 481.2 | P30: 480 | Q30: 473.45 | R30: 475.35 | S30: 476.6 | T30: 478.8 | U30: 475.5 | V30: 464.45 | W30: 437.05 | X30: 467.85 | Y30: 474.8 | Z30: 476.9 | AA30: 9786.25
B31: EGEJUNIN | C31: C.H. RUNATULLO III | D31: CENTRAL | E31: HIDROELÉCTRICA | F31: 450.65 | G31: 490.95 | H31: 491.2 | I31: 490.75 | J31: 489.65 | K31: 490.05 | L31: 489.75 | M31: 489.8 | N31: 490.05 | O31: 490.15 | P31: 490.1 | Q31: 489.25 | R31: 489.35 | S31: 489.4 | T31: 489.05 | U31: 489.3 | V31: 489.4 | W31: 488.65 | X31: 488.4 | Y31: 485.75 | Z31: 485.45 | AA31: 10237.1
B32: EGEJUNIN | C32: C.H. SANTA CRUZ I | D32: CENTRAL | E32: HIDROELÉCTRICA | F32: 279.3 | G32: 256 | H32: 177.35 | I32: 234.2 | J32: 290.3 | K32: 280.9 | L32: 289.2 | M32: 288 | N32: 289.8 | O32: 276.3 | P32: 279.6 | Q32: 288.5 | R32: 287.6 | S32: 289.3 | T32: 289.7 | U32: 289.9 | V32: 250.4 | W32: 222.45 | X32: 143.4 | Y32: 216 | Z32: 206.35 | AA32: 5424.55
B33: EGEMSA | C33: C.H. MACHUPICCHU | D33: CENTRAL | E33: HIDROELÉCTRICA | F33: 4014.15 | G33: 3890.05 | H33: 4014.9 | I33: 3957.7 | J33: 3526.95 | K33: 4017.5 | L33: 4007.85 | M33: 3997.65 | N33: 3976.3 | O33: 4001.35 | P33: 3995.1 | Q33: 3227.3 | R33: 4003.9 | S33: 3993.295 | T33: 3981.75 | U33: 3999.55 | V33: 4000 | W33: 3980.55 | X33: 4005.15 | Y33: 3997 | Z33: 3984.45 | AA33: 82572.445
B34: EGESUR | C34: C.H. ARICOTA I | D34: CENTRAL | E34: HIDROELÉCTRICA | F34: 172.05 | G34: 172.05 | H34: 172.25 | I34: 171 | J34: 171.45 | K34: 170.85 | L34: 169.05 | M34: 169.55 | N34: 172.1 | O34: 179.4 | P34: 176.65 | Q34: 179.65 | R34: 200.4 | S34: 186.25 | T34: 187.3 | U34: 172.25 | V34: 183.85 | W34: 181.6 | X34: 182.65 | Y34: 184.05 | Z34: 183.15 | AA34: 3737.55
B35: EGESUR | C35: C.T. INDEPENDENCIA | D35: CENTRAL | E35: TERMOELÉCTRICA | G35: 48.3 | H35: 166.35 | I35: 140.45 | J35: 64.7 | K35: 212.35 | L35: 95 | M35: 108.5 | N35: 162.35 | O35: 129.65 | P35: 74.3 | Q35: 24.3 | R35: 122.15 | S35: 125.5 | T35: 123.85 | U35: 147.9 | V35: 221.9 | W35: 265.15 | X35: 89.45 | Y35: 142.55 | Z35: 240.85 | AA35: 2705.55
B36: ELECTRICA YANAPAMPA SAC | C36: C.H. YANAPAMPA | D36: CENTRAL | E36: HIDROELÉCTRICA | F36: 76.35 | G36: 78.35 | H36: 67.15 | I36: 71.6 | J36: 75.8 | K36: 79.4 | L36: 74.05 | M36: 82.95 | N36: 81.65 | O36: 83.5 | P36: 84 | Q36: 83.9 | R36: 85.8 | S36: 81.9 | T36: 85.9 | U36: 86.4 | V36: 82.45 | W36: 86.7 | X36: 86.55 | Y36: 84.35 | Z36: 85.15 | AA36: 1703.9
B37: ELECTROPERU | C37: C.H. MANTARO | D37: CENTRAL | E37: HIDROELÉCTRICA | F37: 15545.15 | G37: 15118.55 | H37: 15559.05 | I37: 14563.895 | J37: 15542.75 | K37: 15304.6 | L37: 15533.6 | M37: 15528.8 | N37: 14996.7 | O37: 15556.6 | P37: 15559.7 | Q37: 15542 | R37: 15555.85 | S37: 15532.55 | T37: 15518.25 | U37: 15549.2 | V37: 15546.15 | W37: 15533.25 | X37: 15023 | Y37: 15525.8 | Z37: 15205.1 | AA37: 323340.54
B38: ELECTROPERU | C38: C.H. RESTITUCION | D38: CENTRAL | E38: HIDROELÉCTRICA | F38: 5257.75 | G38: 5067.3 | H38: 5237.45 | I38: 4858.585 | J38: 5248.6 | K38: 5140.55 | L38: 5236.45 | M38: 5237.55 | N38: 5048.15 | O38: 5256.95 | P38: 3516.65 | Q38: 3595.4 | R38: 5258.55 | S38: 5249.2 | T38: 5260.2 | U38: 5268.25 | V38: 5268.85 | W38: 5273.25 | X38: 5069.5 | Y38: 5268.8 | Z38: 5134.35 | AA38: 105752.34
B39: ELECTROPERU | C39: C.T. TUMBES | D39: MAK1 | E39: TERMOELÉCTRICA | H39: 31.13 | I39: 14.71 | U39: 95.025 | V39: 138.045 | W39: 15.9 | AA39: 294.81
B40: ELECTROPERU | C40: C.T. TUMBES | D40: MAK2 | E40: TERMOELÉCTRICA | H40: 29.09 | I40: 14.83 | U40: 96.38 | V40: 137.56 | W40: 15.93 | AA40: 293.79
B41: EMPRESA DE GENERACION ELECTRICA CANCHAYLLO SAC | C41: C.H. CANCHAYLLO | D41: CENTRAL | E41: HIDROELÉCTRICA | F41: 114.5 | G41: 103.6 | H41: 121.4 | I41: 119.45 | J41: 115.45 | K41: 97.35 | L41: 122.9 | M41: 123.75 | N41: 123.75 | O41: 123 | P41: 123.65 | Q41: 123.35 | R41: 123.35 | S41: 121.85 | T41: 114.7 | U41: 108.15 | V41: 102.45 | W41: 101.2 | X41: 117 | Y41: 122.25 | Z41: 124.05 | AA41: 2447.15
B42: EMPRESA DE GENERACION ELECTRICA RIO BAÑOS S.A.C. | C42: C.H. RUCUY | D42: CENTRAL | E42: HIDROELÉCTRICA | F42: 479.95 | G42: 479.15 | H42: 479.65 | I42: 474 | J42: 479.15 | K42: 479.3 | L42: 479.45 | M42: 479.25 | N42: 479 | O42: 478.95 | P42: 479.25 | Q42: 479 | R42: 479.45 | S42: 478.9 | T42: 477.7 | U42: 478.65 | V42: 479.1 | W42: 479.7 | X42: 479.25 | Y42: 478.6 | Z42: 478.85 | AA42: 10056.3
B43: EMPRESA DE GENERACION ELECTRICA SANTA ANA S.A.C. | C43: C.H. RENOVANDES H1 | D43: CENTRAL | E43: HIDROELÉCTRICA | F43: 485 | G43: 423.7 | H43: 485.75 | I43: 484.65 | J43: 485.9 | K43: 465 | L43: 483.85 | M43: 484.4 | N43: 484.8 | O43: 486 | P43: 385.15 | Q43: 485.4 | R43: 486.5 | S43: 484.965 | T43: 464.4 | U43: 485.9 | V43: 486 | W43: 484.85 | X43: 486.5 | Y43: 484.95 | Z43: 484.55 | AA43: 9988.215
B44: EMPRESA DE GENERACION HUALLAGA | C44: C.H. CHAGLLA | D44: CENTRAL | E44: HIDROELÉCTRICA | F44: 3199.75 | G44: 7586.7 | H44: 10939.2 | I44: 8710.6 | J44: 10473.2 | K44: 10518.25 | L44: 10829.2 | M44: 10647.45 | N44: 10225.1 | O44: 10768.1 | P44: 10912.65 | Q44: 10121 | R44: 10631.6 | S44: 10732 | T44: 10715.3 | U44: 11168.8 | V44: 11387.7 | W44: 7963.15 | X44: 3828 | Y44: 9914.7 | Z44: 10536.25 | AA44: 201808.7
B45: EMPRESA DE GENERACION HUALLAGA | C45: P.C.H. CHAGLLA | D45: CENTRAL | E45: HIDROELÉCTRICA | F45: 156 | G45: 156 | H45: 156 | I45: 155.3 | J45: 156 | K45: 156 | L45: 156 | M45: 156 | N45: 156 | O45: 155.95 | P45: 156 | Q45: 156 | R45: 155.95 | S45: 156 | T45: 156 | U45: 156 | V45: 156 | W45: 156 | X45: 156 | Y45: 156 | Z45: 156 | AA45: 3275.2
B46: EMPRESA DE GENERACION HUANZA | C46: C.H. HUANZA | D46: CENTRAL | E46: HIDROELÉCTRICA | F46: 1305.9 | G46: 1930.85 | H46: 2249.7 | I46: 2277.7 | J46: 2270.7 | K46: 2002.5 | L46: 1713.8 | M46: 1676.2 | N46: 1549.45 | O46: 1463.3 | P46: 1644.65 | Q46: 1485.8 | R46: 1510.35 | S46: 1604.5 | T46: 1343.3 | U46: 1666.95 | V46: 1601.9 | W46: 1567.7 | X46: 1687.05 | Y46: 1223.6 | Z46: 1069.2 | AA46: 34845.1
B47: EMPRESA ELECTRICA AGUA AZUL | C47: C.H. POTRERO | D47: CENTRAL | E47: HIDROELÉCTRICA | F47: 476.9 | G47: 478.3 | H47: 471.8 | I47: 476.45 | J47: 475.2 | K47: 477.75 | L47: 474.7 | M47: 399.25 | N47: 425.5 | O47: 479.95 | P47: 478.8 | Q47: 477.1 | R47: 479.25 | S47: 469.8 | T47: 477.65 | U47: 478.55 | V47: 473.45 | W47: 479.75 | X47: 480 | Y47: 480 | Z47: 479.95 | AA47: 9890.1
B48: EMPRESA ELECTRICA RIO DOBLE | C48: C.H. LAS PIZARRAS | D48: CENTRAL | E48: HIDROELÉCTRICA | F48: 450.2 | G48: 451.5 | H48: 442.55 | I48: 428.7 | J48: 452.7 | K48: 454.2 | L48: 455.15 | M48: 454.15 | N48: 453.645 | O48: 453.2 | P48: 453.92 | Q48: 453.85 | R48: 453.5 | S48: 453.95 | T48: 453.3 | U48: 452 | V48: 451.705 | W48: 452.58 | X48: 452.55 | Y48: 453.215 | Z48: 437.035 | AA48: 9463.6
B49: ENEL GENERACION PIURA S.A. | C49: C.T. MALACAS 1 | D49: TG6 | E49: TERMOELÉCTRICA | F49: 355.85 | G49: 457.5 | H49: 359.15 | J49: 727.05 | L49: 441.55 | M49: 752.4 | N49: 738.3 | O49: 816.85 | P49: 771.75 | Q49: 766.15 | R49: 1105.15 | S49: 805.45 | T49: 816.45 | U49: 1131.85 | V49: 1135.25 | W49: 1118.5 | X49: 1129.65 | Y49: 1138.7 | Z49: 1126.05 | AA49: 15693.6
B50: ENEL GENERACION PIURA S.A. | C50: C.T. MALACAS 2 | D50: TG4 | E50: TERMOELÉCTRICA | H50: 663.05 | I50: 894.45 | J50: 44.65 | K50: 914.15 | L50: 74.85 | W50: 60.4 | AA50: 2651.55
B51: ENEL GENERACION PIURA S.A. | C51: C.T. RF DE GENERACION TALARA | D51: TG5 | E51: TERMOELÉCTRICA | H51: 407 | AA51: 407
B52: ENERGÍA EÓLICA S.A. | C52: C.E. CUPISNIQUE | D52: CENTRAL | E52: EÓLICA | F52: 826 | G52: 637.1 | H52: 565.05 | I52: 483.8 | J52: 446.9 | K52: 946.35 | L52: 1252.6 | M52: 1412.8 | N52: 1299.5 | O52: 1060.15 | P52: 721.65 | Q52: 1086.1 | R52: 1006 | S52: 1036.9 | T52: 845.9 | U52: 488.95 | V52: 523.6 | W52: 1059 | X52: 1452.95 | Y52: 1228.95 | Z52: 1002.6 | AA52: 19382.85
B53: ENERGÍA EÓLICA S.A. | C53: C.E. TALARA | D53: CENTRAL | E53: EÓLICA | F53: 344.35 | G53: 395.75 | H53: 384.4 | I53: 141.95 | J53: 94.85 | K53: 161.95 | L53: 465.35 | M53: 531.8 | N53: 530.7 | O53: 329.8 | P53: 230.45 | Q53: 302.4 | R53: 354.85 | S53: 305.55 | T53: 349.75 | U53: 151.05 | V53: 203.55 | W53: 391.2 | X53: 580.95 | Y53: 528.2 | Z53: 443.55 | AA53: 7222.4
B54: ENERGIA RENOVABLE DEL SUR S.A. | C54: C.E. SAN JUAN | D54: CENTRAL | E54: EÓLICA | F54: 2667.35 | G54: 1888.4 | H54: 1031.8 | I54: 1510.75 | J54: 862.7 | K54: 715 | L54: 1712.65 | M54: 1729.05 | N54: 1633.15 | O54: 1758.3 | P54: 2050.7 | Q54: 1899.4 | R54: 1355.45 | S54: 1224.5 | T54: 1889.8 | U54: 1369.1 | V54: 1364.4 | W54: 2019.15 | X54: 2070.8 | Y54: 1645.1 | Z54: 2080.4 | AA54: 34477.95
B55: ENGIE | C55: C.E. PUNTA LOMITAS | D55: PL-BL1 | E55: EÓLICA | F55: 1416 | G55: 1294.2 | H55: 490.05 | I55: 910.85 | J55: 885.7 | K55: 777.2 | L55: 1793.85 | M55: 1777.65 | N55: 1646.2 | O55: 1640.35 | P55: 1225.1 | Q55: 1266.85 | R55: 1046.65 | S55: 1040.35 | T55: 1134.95 | U55: 715.35 | V55: 819.45 | W55: 1316 | X55: 1883.9 | Y55: 1525.95 | Z55: 1457.65 | AA55: 26064.25
B56: ENGIE | C56: C.E. PUNTA LOMITAS | D56: PL-BL2 | E56: EÓLICA | F56: 1675.05 | G56: 1567.65 | H56: 664.2 | I56: 1146.85 | J56: 995.45 | K56: 964.6 | L56: 1911.45 | M56: 1824.7 | N56: 1813.75 | O56: 1862.9 | P56: 1474.45 | Q56: 1526 | R56: 1347.1 | S56: 1347.25 | T56: 1469.25 | U56: 1069.55 | V56: 1271.05 | W56: 1161.7 | X56: 1830.85 | Y56: 1690.2 | Z56: 1766.25 | AA56: 30380.25
B57: ENGIE | C57: C.E. PUNTA LOMITAS_EXP | D57: PUN LOM_EXP-BL1 | E57: EÓLICA | F57: 74.35 | G57: 61.95 | H57: 36.6 | I57: 85.7 | J57: 74.9 | K57: 54.35 | L57: 161.2 | M57: 173 | N57: 163.95 | O57: 163.25 | P57: 110.5 | Q57: 103.95 | R57: 99.75 | S57: 102.05 | T57: 110.1 | U57: 55.9 | V57: 63.7 | W57: 113.3 | X57: 165.05 | Y57: 159.2 | Z57: 147.15 | AA57: 2279.9
B58: ENGIE | C58: C.E. PUNTA LOMITAS_EXP | D58: PUN LOM_EXP-BL2 | E58: EÓLICA | F58: 98.4 | G58: 84.15 | H58: 33.8 | I58: 60.6 | J58: 70.6 | K58: 58.2 | L58: 158.1 | M58: 184.75 | N58: 174.55 | O58: 149.95 | P58: 94.75 | Q58: 89.05 | R58: 92.45 | S58: 89.7 | T58: 90.25 | U58: 60.6 | V58: 66.85 | W58: 90.8 | X58: 210.65 | Y58: 153.65 | Z58: 129.35 | AA58: 2241.2
B59: ENGIE | C59: C.H. QUITARACSA | D59: CENTRAL | E59: HIDROELÉCTRICA | F59: 1800.35 | G59: 2646.35 | H59: 2696.9 | I59: 2692.95 | J59: 2048.55 | K59: 2695.4 | L59: 2693 | M59: 2690.65 | N59: 2689.7 | O59: 2696.7 | P59: 2277.3 | Q59: 2005.8 | R59: 2068.5 | S59: 2671.3 | T59: 2690.35 | U59: 2661.4 | V59: 1839.15 | W59: 1972.35 | X59: 1967.15 | Y59: 1658.8 | Z59: 1733.2 | AA59: 48895.85
B60: ENGIE | C60: C.H. YUNCAN | D60: CENTRAL | E60: HIDROELÉCTRICA | F60: 2668.75 | G60: 3146.2 | H60: 3160.15 | I60: 3169.95 | J60: 3162.05 | K60: 3086.9 | L60: 2896.45 | M60: 3154.05 | N60: 3147.05 | O60: 3136.45 | P60: 2823.6 | Q60: 2843.2 | R60: 3128.7 | S60: 3147.75 | T60: 2892.7 | U60: 2920.1 | V60: 2776.2 | W60: 2584.85 | X60: 2461.85 | Y60: 2968.8 | Z60: 3070.9 | AA60: 62346.65
B61: ENGIE | C61: C.S. INTIPAMPA | D61: CENTRAL | E61: SOLAR | F61: 276.8 | G61: 239.4 | H61: 187.95 | I61: 218.3 | J61: 239.15 | K61: 174.4 | L61: 248.2 | M61: 341 | N61: 337.4 | O61: 395.5 | P61: 384.95 | Q61: 390.7 | R61: 385.5 | S61: 375.45 | T61: 363.05 | U61: 358.7 | V61: 176.2 | W61: 325.05 | X61: 322.5 | Y61: 281.6 | Z61: 240 | AA61: 6261.8
B62: ENGIE | C62: C.T. CHILCA 1 | D62: TG1 | E62: TERMOELÉCTRICA | F62: 2419.9 | G62: 3695.6 | N62: 354.9 | O62: 277.95 | R62: 475.3 | S62: 483.45 | W62: 1518.3 | X62: 394.35 | AA62: 9619.75
B63: ENGIE | C63: C.T. CHILCA 1 | D63: TG2 | E63: TERMOELÉCTRICA | F63: 2390.45 | G63: 82.1 | H63: 1769.5 | I63: 568.3 | J63: 704.45 | K63: 1146.55 | L63: 312.65 | N63: 504.15 | O63: 282.05 | R63: 1185.6 | S63: 1266.75 | T63: 525.55 | U63: 645.05 | V63: 2276.95 | W63: 1864.45 | X63: 821 | Y63: 623.8 | Z63: 1818.95 | AA63: 18788.3
B64: ENGIE | C64: C.T. CHILCA 1 | D64: TG3 | E64: TERMOELÉCTRICA | H64: 1835.4 | I64: 574.55 | J64: 598.85 | K64: 808.7 | O64: 1047 | R64: 1313.45 | AA64: 6177.95
B65: ENGIE | C65: C.T. CHILCA 1 | D65: TV | E65: TERMOELÉCTRICA | F65: 2850.4 | G65: 1646 | AA65: 4496.4
B66: ENGIE | C66: C.T. CHILCA 2 | D66: TG41 | E66: TERMOELÉCTRICA | J66: 182.9 | P66: 145.15 | Q66: 214.1 | W66: 150.2 | Z66: 164.9 | AA66: 857.25
B67: ENGIE | C67: C.T. CHILCA 2 | D67: TV42 | E67: TERMOELÉCTRICA | AA67: 0
B68: ENGIE | C68: C.T. NEPI | D68: TG41 | E68: TERMOELÉCTRICA | U68: 838.7 | V68: 2363.7 | W68: 391.65 | AA68: 3594.05
B69: ENGIE | C69: C.T. NEPI | D69: TG42 | E69: TERMOELÉCTRICA | AA69: 0
B70: ENGIE | C70: C.T. NEPI | D70: TG43 | E70: TERMOELÉCTRICA | AA70: 0
B71: ENGIE | C71: C.T. RF PLANTA ILO | D71: TG1 | E71: TERMOELÉCTRICA | H71: 367.5 | AA71: 367.5
B72: ENGIE | C72: C.T. RF PLANTA ILO | D72: TG2 | E72: TERMOELÉCTRICA | AA72: 0
B73: ENGIE | C73: C.T. RF PLANTA ILO | D73: TG3 | E73: TERMOELÉCTRICA | J73: 403.7 | AA73: 403.7
B74: FENIX POWER PERÚ | C74: C.T. FENIX | D74: GT11 | E74: TERMOELÉCTRICA | F74: 3326.015 | G74: 3251.75 | H74: 3326.1 | I74: 3474.85 | J74: 646.2 | K74: 3160.05 | L74: 3562.15 | O74: 252 | P74: 2747.3 | Q74: 1428.6 | R74: 3722.45 | S74: 3961.8 | T74: 3804.9 | Y74: 2585.65 | Z74: 4003.8 | AA74: 43253.615
B75: FENIX POWER PERÚ | C75: C.T. FENIX | D75: GT12 | E75: TERMOELÉCTRICA | F75: 3332.585 | G75: 3258.15 | H75: 3332.05 | I75: 3542.65 | J75: 1382.55 | K75: 3910.85 | L75: 3686.2 | M75: 3731.8985 | N75: 3661.85 | O75: 3940.25 | P75: 3722.85 | Q75: 1294.4 | R75: 3728.8 | S75: 3970.45 | T75: 3866.3 | U75: 2470.7 | Y75: 3053.05 | Z75: 3690.9 | AA75: 59576.484
B76: FENIX POWER PERÚ | C76: C.T. FENIX | D76: TV10 | E76: TERMOELÉCTRICA | F76: 3823.35 | G76: 3823.75 | H76: 3872 | I76: 3959.9 | J76: 596.15 | K76: 3672.25 | L76: 4004 | M76: 1994.0565 | N76: 1966.1 | O76: 2035.45 | P76: 3442.95 | Q76: 1211.8 | R76: 4080.15 | S76: 4224.3 | T76: 4122.1 | U76: 1199.75 | Y76: 2804.3 | Z76: 3372 | AA76: 54204.357
B77: GENERACIÓN ANDINA S.A.C. | C77: C.H. 8 DE AGOSTO | D77: CENTRAL | E77: HIDROELÉCTRICA | F77: 485.75 | G77: 428.15 | H77: 474.45 | I77: 501.2 | J77: 499.85 | K77: 501.3 | L77: 502.2 | M77: 502.8 | N77: 501.6 | O77: 502.65 | P77: 499.6 | Q77: 497.8 | R77: 497.9 | S77: 497.45 | T77: 467.65 | U77: 487.5 | V77: 484.9 | W77: 441.59429 | X77: 362.1 | Y77: 447.1 | Z77: 503.9 | AA77: 10087.444
B78: GENERACIÓN ANDINA S.A.C. | C78: C.H. EL CARMEN | D78: CENTRAL | E78: HIDROELÉCTRICA | F78: 177.2 | G78: 190.15 | H78: 200.05 | I78: 180.2 | J78: 195.1 | K78: 184.55 | L78: 193.8 | M78: 192.85 | N78: 191.5 | O78: 145.6 | P78: 45.75 | Q78: 200 | R78: 173.45 | S78: 149.35 | T78: 136.05 | U78: 140.8 | V78: 133.45 | W78: 118.7288 | X78: 115.95 | Y78: 120.25 | Z78: 160.6 | AA78: 3345.3788
B79: GENERADORA DE ENERGÍA DEL PERÚ | C79: C.H. ÁNGEL I | D79: CENTRAL | E79: HIDROELÉCTRICA | F79: 329.25 | G79: 489.6 | H79: 489.6 | I79: 489.6 | J79: 489.6 | K79: 489.6 | L79: 489.6 | M79: 489.6 | N79: 489.6 | O79: 469.2 | P79: 489.6 | Q79: 489.6 | R79: 489.6 | S79: 489.6 | T79: 489.6 | U79: 484.4 | V79: 489.6 | W79: 480 | X79: 240 | Y79: 480 | Z79: 450 | AA79: 9787.25
B80: GENERADORA DE ENERGÍA DEL PERÚ | C80: C.H. ÁNGEL II | D80: CENTRAL | E80: HIDROELÉCTRICA | F80: 331.75 | G80: 489.6 | H80: 489.6 | I80: 489.6 | J80: 489.6 | K80: 489.6 | L80: 489.6 | M80: 489.6 | N80: 478.3 | O80: 462.5 | P80: 489.6 | Q80: 489.6 | R80: 484.5 | S80: 489.6 | T80: 489.6 | U80: 484.4 | V80: 489.6 | W80: 475 | X80: 235 | Y80: 480 | Z80: 437.5 | AA80: 9744.15
B81: GENERADORA DE ENERGÍA DEL PERÚ | C81: C.H. ÁNGEL III | D81: CENTRAL | E81: HIDROELÉCTRICA | F81: 229.4 | G81: 244.8 | H81: 244.8 | I81: 244.8 | J81: 244.8 | K81: 244.8 | L81: 244.8 | M81: 244.8 | N81: 241.1 | O81: 142.8 | T81: 122.4 | U81: 244.8 | V81: 239.7 | W81: 240 | X81: 110.5 | Y81: 240 | Z81: 222.25 | AA81: 3746.55
B82: GENERADORA DE ENERGÍA DEL PERÚ | C82: C.H. LA JOYA | D82: CENTRAL | E82: HIDROELÉCTRICA | F82: 144.45 | G82: 141.75 | H82: 176.25 | I82: 174.1 | J82: 167.05 | K82: 181.15 | L82: 183.2 | M82: 157.05 | N82: 148.3 | O82: 149.1 | P82: 152.85 | Q82: 145.5 | R82: 142.95 | S82: 142.05 | T82: 140.45 | U82: 138.9 | V82: 173.7 | W82: 179.1 | X82: 175.55 | Y82: 184.75 | Z82: 192.4 | AA82: 3390.6
B83: GM OPERACIONES S.A.C. | C83: CT REFINERIA TALARA | D83: TV1 REF TALARA | E83: TERMOELÉCTRICA | K83: 65.7 | L83: 465.35 | M83: 328.55 | N83: 364.25 | O83: 471.9 | P83: 514.3 | Q83: 564.54 | R83: 595.2 | S83: 609.25 | T83: 606.3 | U83: 611.25 | V83: 624.95 | W83: 641.5 | X83: 510.25 | Y83: 351.95 | Z83: 359.15 | AA83: 7684.39
B84: GM OPERACIONES S.A.C. | C84: CT REFINERIA TALARA | D84: TV2 REF TALARA | E84: TERMOELÉCTRICA | F84: 796.2 | G84: 802.5 | H84: 837.05 | I84: 909.62 | J84: 904.05 | K84: 862.1 | L84: 722.75 | M84: 925.4 | N84: 926.5 | O84: 917.35 | P84: 887.2 | Q84: 871.88 | R84: 852.3 | S84: 835.1 | T84: 830.8 | U84: 831.65 | V84: 858.25 | W84: 847.5 | X84: 853 | Y84: 855.45 | Z84: 857.2 | AA84: 17983.85
B85: GR CORTARRAMA SOCIEDAD ANONIMA CERRADA | C85: C.S. MATARANI | D85: C.S. MATARANI | E85: SOLAR | F85: 538.8 | G85: 418.65 | H85: 457.4 | I85: 457.85 | J85: 742.5 | K85: 640.35 | L85: 688.7 | M85: 789.4 | N85: 775.45 | O85: 774.2 | P85: 806.2 | Q85: 783.65 | R85: 757.65 | S85: 799.4 | T85: 802.55 | U85: 813.3 | V85: 714.25 | W85: 609.75 | X85: 620.75 | Y85: 665.55 | Z85: 503.9 | AA85: 14160.25
B86: GR PAINO SOCIEDAD ANONIMA CERRADA | C86: C.E. HUAMBOS | D86: CENTRAL | E86: EÓLICA | F86: 61.9 | G86: 35.15 | H86: 23.85 | I86: 54.9 | J86: 127 | K86: 84.3 | L86: 43.3 | M86: 38.6 | N86: 74.3 | O86: 47.65 | P86: 163.55 | Q86: 161.9 | R86: 31.85 | S86: 93.25 | T86: 160.25 | U86: 124.15 | V86: 82.75 | W86: 54.85 | X86: 69.7 | Y86: 59.45 | Z86: 42.55 | AA86: 1635.2
B87: GR TARUCA SOCIEDAD ANONIMA CERRADA | C87: C.E. DUNA | D87: CENTRAL | E87: EÓLICA | F87: 56.9 | G87: 33.1 | H87: 39.4 | I87: 111.35 | J87: 188.4 | K87: 139.65 | L87: 63.4 | M87: 38.45 | N87: 49.65 | O87: 41.5 | P87: 225.7 | Q87: 205.2 | R87: 34.65 | S87: 70.05 | T87: 141.35 | U87: 89.75 | V87: 72.25 | W87: 56.5 | X87: 55.75 | Y87: 45.3 | Z87: 59.75 | AA87: 1818.05
B88: HIDROCAÑETE S.A. | C88: C.H. IMPERIAL | D88: CENTRAL | E88: HIDROELÉCTRICA | F88: 73.65 | G88: 81.05 | H88: 78.8 | I88: 79.95 | J88: 75.95 | K88: 80.5 | L88: 83.35 | M88: 83.4 | N88: 84.35 | O88: 84.25 | P88: 84.6 | Q88: 83.85 | R88: 84.45 | S88: 83.65 | T88: 85.3 | U88: 84.5 | V88: 83.55 | W88: 82.75 | X88: 82.3 | Y88: 83 | Z88: 82.6 | AA88: 1725.8
B89: HIDROELECTRICA HUANCHOR S.A.C. | C89: C.H. HUANCHOR | D89: CENTRAL | E89: HIDROELÉCTRICA | F89: 437 | G89: 438.4 | H89: 431.6 | I89: 432.55 | J89: 435.15 | K89: 439.7 | L89: 440.1 | M89: 440.4 | N89: 439.6 | O89: 440.45 | P89: 440.4 | Q89: 439.15 | R89: 440.5 | S89: 441 | T89: 439.25 | U89: 440.8 | V89: 441.25 | W89: 441.25 | X89: 440.6 | Y89: 441.05 | Z89: 440.75 | AA89: 9220.95
B90: HUAURA POWER GROUP S.A. | C90: C.H. YARUCAYA | D90: CENTRAL | E90: HIDROELÉCTRICA | F90: 451.15 | G90: 450.5 | H90: 425.05 | I90: 127.2 | J90: 250.7 | K90: 451.2 | L90: 451.1 | M90: 450.45 | N90: 451.2 | O90: 451.05 | P90: 449.74 | Q90: 450.85 | R90: 450.9 | S90: 408.735 | T90: 448.8 | U90: 428.05 | V90: 451.2 | W90: 451.2 | X90: 421 | Y90: 450.65 | Z90: 448.8 | AA90: 8819.525
B91: INFRAESTRUCTURAS Y ENERGIAS DEL PERU S.A.C. | C91: C.T. RF PTO MALDONADO | D91: CENTRAL | E91: TERMOELÉCTRICA | AA91: 0
B92: INFRAESTRUCTURAS Y ENERGIAS DEL PERU S.A.C. | C92: C.T. RF PUCALLPA | D92: CENTRAL | E92: TERMOELÉCTRICA | AA92: 0
B93: INLAND ENERGY SAC | C93: C.H. SANTA TERESA | D93: CENTRAL | E93: HIDROELÉCTRICA | F93: 2173 | G93: 1849.5 | H93: 2179.65 | I93: 1920.05 | J93: 1893.3 | K93: 2162.5 | L93: 2164.2 | M93: 2169.3 | N93: 2173.3 | O93: 2164.15 | P93: 2172.75 | Q93: 1768.4 | R93: 2162.75 | S93: 2173.095 | T93: 2069 | U93: 2173.3 | V93: 2171.55 | W93: 2186 | X93: 2179.3 | Y93: 2182.35 | Z93: 2176.85 | AA93: 44264.295
B94: INVERSIONES SHAQSHA S.A.C. | C94: C.H. PARIAC | D94: CENTRAL | E94: HIDROELÉCTRICA | N94: 17.55 | O94: 83.6 | P94: 98.75 | Q94: 99.25 | R94: 102 | S94: 100.75 | T94: 101.2 | U94: 101.7 | V94: 101.25 | W94: 101.15 | X94: 101.15 | Y94: 103.15 | Z94: 103.2 | AA94: 1214.7
B95: KALLPA GENERACION S.A. | C95: C.H. CERRO DEL AGUILA | D95: CENTRAL | E95: HIDROELÉCTRICA | F95: 10008.95 | G95: 13509.65 | H95: 13475.45 | I95: 13406.25 | J95: 13426.15 | K95: 13440.05 | L95: 13427.6 | M95: 13408.95 | N95: 13425.7 | O95: 13273.25 | P95: 13413.7 | Q95: 13404.15 | R95: 12851.8 | S95: 13407.95 | T95: 13388.45 | U95: 13737.95 | V95: 13760.7 | W95: 13519.6 | X95: 11115.5 | Y95: 13398.2 | Z95: 13401.7 | AA95: 276201.7
B96: KALLPA GENERACION S.A. | C96: C.T. KALLPA | D96: TG1 | E96: TERMOELÉCTRICA | I96: 2346.15 | J96: 3078.3 | K96: 3219.7 | L96: 3035.85 | M96: 2982.7 | N96: 3067.85 | O96: 3322.05 | P96: 3056.95 | Q96: 3063.4 | R96: 3222.65 | S96: 3400.75 | T96: 3131.8 | U96: 3359.65 | V96: 3706.3 | W96: 3682.5 | X96: 3629 | Y96: 3531.75 | Z96: 3614.3 | AA96: 58451.65
B97: KALLPA GENERACION S.A. | C97: C.T. KALLPA | D97: TG2 | E97: TERMOELÉCTRICA | G97: 1165.5 | H97: 4076 | I97: 3216.25 | J97: 3091.45 | K97: 3217.3 | L97: 3026.8 | M97: 2977.8 | N97: 3073 | O97: 3370.8 | P97: 3064.1 | Q97: 3067.15 | R97: 3236.6 | S97: 3454 | T97: 3135.95 | U97: 3401.15 | V97: 3753.6 | W97: 3820.75 | X97: 3714.65 | Y97: 3636.9 | Z97: 3653.5 | AA97: 65153.25
B98: KALLPA GENERACION S.A. | C98: C.T. KALLPA | D98: TG3 | E98: TERMOELÉCTRICA | G98: 3573.15 | H98: 4104.95 | I98: 3226.3 | J98: 3094.85 | K98: 3219.05 | L98: 3029.6 | M98: 2974.85 | N98: 3071.7 | O98: 2956.1 | P98: 3066.1 | Q98: 3067.1 | R98: 3238.95 | S98: 3453.1 | T98: 3138 | U98: 3401.55 | V98: 3754.45 | W98: 3823.65 | X98: 3713.6 | Y98: 3578.8 | Z98: 3657.35 | AA98: 67143.2
B99: KALLPA GENERACION S.A. | C99: C.T. KALLPA | D99: TV | E99: TERMOELÉCTRICA | G99: 2135.75 | H99: 4227.75 | I99: 5016.8 | J99: 5432.85 | K99: 5552.2 | L99: 5405.7 | M99: 5333.9 | N99: 5439.7 | O99: 5450.95 | P99: 5405.4 | Q99: 5429.3 | R99: 5614.6 | S99: 5780.95 | T99: 5514.1 | U99: 5758.35 | V99: 6036.9 | W99: 5996.7 | X99: 5988.6 | Y99: 5890.85 | Z99: 5958.9 | AA99: 107370.25
B100: KALLPA GENERACION S.A. | C100: C.T. LAS FLORES | D100: TG1 | E100: TERMOELÉCTRICA | F100: 454.1 | G100: 3712.5 | H100: 4774.05 | I100: 4599.6 | J100: 4401.6 | K100: 3835.95 | L100: 4318.35 | M100: 4046.45 | N100: 4041.85 | O100: 4524.3 | P100: 4427.85 | Q100: 4195.75 | R100: 4222.4 | S100: 4905.55 | T100: 4816.85 | U100: 4240.45 | V100: 4298.55 | W100: 4401.8 | X100: 4738.65 | Y100: 4887.5 | Z100: 4897.25 | AA100: 88741.35
B101: KALLPA GENERACION S.A. | C101: C.T. LAS FLORES | D101: TV | E101: TERMOELÉCTRICA | F101: 262.75 | G101: 1823.75 | H101: 2503.5 | I101: 2442.5 | J101: 2377.45 | K101: 1992.5 | L101: 2337.85 | M101: 2234.95 | N101: 2213.8 | O101: 2422.8 | P101: 2387.8 | Q101: 2292.2 | R101: 2298.6 | S101: 2588 | T101: 2567.7 | U101: 2313.05 | V101: 2352.05 | W101: 2383.35 | X101: 2533.45 | Y101: 2580.5 | Z101: 2597 | AA101: 47505.55
B102: KALLPA GENERACION S.A. | C102: M.C.H. CERRO DEL AGUILA | D102: CENTRAL | E102: HIDROELÉCTRICA | F102: 246.85 | G102: 251.7 | H102: 251.3 | I102: 252 | J102: 251.45 | K102: 245.85 | L102: 250.65 | M102: 251.6 | N102: 251.2 | O102: 252 | P102: 251.1 | Q102: 250.85 | R102: 221.05 | S102: 252.45 | T102: 251.7 | U102: 252.1 | V102: 252.1 | W102: 252.4 | X102: 252.5 | Y102: 252.7 | Z102: 252.05 | AA102: 5245.6
B103: KONDU SAC | C103: C.S. CARHUAQUERO | D103: CENTRAL | E103: SOLAR | F103: 2.1 | G103: 1.5 | H103: 2.1 | I103: 1.9 | J103: 2.1 | K103: 1.6 | L103: 2.1 | M103: 2.15 | N103: 2.75 | O103: 2.55 | P103: 1.05 | Q103: 1.95 | R103: 1.5 | S103: 1.85 | T103: 2.45 | U103: 2.8 | V103: 2.15 | W103: 2 | X103: 2.2 | Y103: 2.45 | Z103: 1.95 | AA103: 43.2
...

Sheet G_AREAS
B3: martes, 21 de Enero del 2025
B5: HORA | C5: RESUMEN DE GENERACIÓN POR ÁREAS DEL SEIN | D5: RESUMEN DE GENERACIÓN POR ÁREAS DEL SEIN | E5: RESUMEN DE GENERACIÓN POR ÁREAS DEL SEIN | F5: RESUMEN DE GENERACIÓN POR ÁREAS DEL SEIN | G5: RESUMEN DE GENERACIÓN POR ÁREAS DEL SEIN | H5: RESUMEN DE GENERACIÓN POR ÁREAS DEL SEIN | I5: RESUMEN DE GENERACIÓN POR ÁREAS DEL SEIN | J5: RESUMEN DE GENERACIÓN POR ÁREAS DEL SEIN | K5: RESUMEN DE GENERACIÓN POR ÁREAS DEL SEIN | L5: RESUMEN DE GENERACIÓN POR ÁREAS DEL SEIN | M5: RESUMEN DE GENERACIÓN POR ÁREAS DEL SEIN | N5: RESUMEN DE GENERACIÓN POR ÁREAS DEL SEIN | O5: RESUMEN DE GENERACIÓN POR ÁREAS DEL SEIN | P5: RESUMEN DE GENERACIÓN POR ÁREAS DEL SEIN | Q5: RESUMEN DE GENERACIÓN POR ÁREAS DEL SEIN | R5: RESUMEN DE GENERACIÓN POR ÁREAS DEL SEIN | S5: HORA | T5: GENERACIÓN POR TIPO DE GENERACIÓN | U5: GENERACIÓN POR TIPO DE GENERACIÓN | V5: GENERACIÓN POR TIPO DE GENERACIÓN | W5: GENERACIÓN POR TIPO DE GENERACIÓN | X5: GENERACIÓN POR TIPO DE GENERACIÓN | Y5: HORA | Z5: GENERACIÓN POR TIPO DE GENERACIÓN | AA5: GENERACIÓN POR TIPO DE GENERACIÓN | AB5: GENERACIÓN POR TIPO DE GENERACIÓN | AC5: GENERACIÓN POR TIPO DE GENERACIÓN | AD5: GENERACIÓN POR TIPO DE GENERACIÓN
C6: NORTE | D6: NORTE | E6: NORTE | F6: NORTE | G6: CENTRO | H6: CENTRO | I6: CENTRO | J6: CENTRO | K6: SUR | L6: SUR | M6: SUR | N6: SUR | O6: GENERACIÓN INTEGRANTES COES | P6: GENERACIÓN INTEGRANTES COES | Q6: GENERACIÓN INTEGRANTES COES | R6: GENERACIÓN INTEGRANTES COES | T6: INTEGRANTES COES | U6: INTEGRANTES COES | V6: INTEGRANTES COES | W6: INTEGRANTES COES | X6: INTEGRANTES COES | Z6: INTEGRANTES COES RER | AA6: INTEGRANTES COES RER | AB6: INTEGRANTES COES RER | AC6: INTEGRANTES COES RER | AD6: INTEGRANTES COES RER
C7: GENERACIÓN HIDROELÉCTRICA NORTE | D7: GENERACIÓN TERMOELÉCTRICA NORTE | E7: GENERACIÓN SOLAR NORTE | F7: GENERACIÓN EÓLICA NORTE | G7: GENERACIÓN HIDROELÉCTRICA CENTRO | H7: GENERACIÓN TERMOELÉCTRICA CENTRO | I7: GENERACIÓN SOLAR CENTRO | J7: GENERACIÓN EÓLICA CENTRO | K7: GENERACIÓN HIDROELÉCTRICA SUR | L7: GENERACIÓN TERMOELÉCTRICA SUR | M7: GENERACIÓN SOLAR SUR | N7: GENERACIÓN EÓLICA SUR | O7: GENERACIÓN COES NORTE | P7: GENERACIÓN COES CENTRO | Q7: GENERACIÓN COES SUR | R7: TOTAL GENERACION | T7: HIDROELÉCTRICA | U7: TERMOELÉCTRICA | V7: SOLAR | W7: EÓLICA | X7: TOTAL GENERACION | Z7: HIDROELÉCTRICA RER | AA7: TERMOELÉCTRICA RER | AB7: SOLAR RER | AC7: EÓLICA RER | AD7: TOTAL RER
B8: 00:30 | C8: 507.85 | D8: 134.4 | E8: 0 | F8: 63.4 | G8: 3158.6 | H8: 1922.2 | I8: 0 | J8: 310.8 | K8: 523.8 | L8: 0 | M8: 0 | N8: 0 | O8: 705.65 | P8: 5391.6 | Q8: 523.8 | R8: 6621.05 | S8: 00:30 | T8: 4190.25 | U8: 2056.6 | V8: 0 | W8: 374.2 | X8: 6621.05 | Y8: 00:30 | Z8: 338.05 | AA8: 62.9 | AB8: 0 | AC8: 374.2 | AD8: 775.15
B9: 01:00 | C9: 513.1 | D9: 133.2 | E9: 0 | F9: 55.4 | G9: 3189.3 | H9: 1887.9 | I9: 0 | J9: 297.8 | K9: 538.9 | L9: 0 | M9: 0 | N9: 0 | O9: 701.7 | P9: 5375 | Q9: 538.9 | R9: 6615.6 | S9: 01:00 | T9: 4241.3 | U9: 2021.1 | V9: 0 | W9: 353.2 | X9: 6615.6 | Y9: 01:00 | Z9: 333.6 | AA9: 61.7 | AB9: 0 | AC9: 353.2 | AD9: 748.5
B10: 01:30 | C10: 508.74 | D10: 134.1 | E10: 0 | F10: 55.1 | G10: 3099.4 | H10: 1803.7 | I10: 0 | J10: 279.9 | K10: 523.9 | L10: 0 | M10: 0 | N10: 0 | O10: 697.94 | P10: 5183 | Q10: 523.9 | R10: 6404.84 | S10: 01:30 | T10: 4132.04 | U10: 1937.8 | V10: 0 | W10: 335 | X10: 6404.84 | Y10: 01:30 | Z10: 331.74 | AA10: 62.3 | AB10: 0 | AC10: 335 | AD10: 729.04
B11: 02:00 | C11: 512.59 | D11: 133.2 | E11: 0 | F11: 54.3 | G11: 3173.2 | H11: 1758.4 | I11: 0 | J11: 300.5 | K11: 494.3 | L11: 0 | M11: 0 | N11: 0 | O11: 700.09 | P11: 5232.1 | Q11: 494.3 | R11: 6426.49 | S11: 02:00 | T11: 4180.09 | U11: 1891.6 | V11: 0 | W11: 354.8 | X11: 6426.49 | Y11: 02:00 | Z11: 332.69 | AA11: 62.4 | AB11: 0 | AC11: 354.8 | AD11: 749.89
B12: 02:30 | C12: 471.45 | D12: 134.2 | E12: 0 | F12: 46.7 | G12: 3121.3 | H12: 1794.5 | I12: 0 | J12: 334.9 | K12: 494.3 | L12: 0 | M12: 0 | N12: 0 | O12: 652.35 | P12: 5250.7 | Q12: 494.3 | R12: 6397.35 | S12: 02:30 | T12: 4087.05 | U12: 1928.7 | V12: 0 | W12: 381.6 | X12: 6397.35 | Y12: 02:30 | Z12: 332.25 | AA12: 61.9 | AB12: 0 | AC12: 381.6 | AD12: 775.75
B13: 03:00 | C13: 473.14 | D13: 132.8 | E13: 0 | F13: 45.9 | G13: 3158.9 | H13: 1674 | I13: 0 | J13: 328.8 | K13: 499.8 | L13: 0 | M13: 0 | N13: 0 | O13: 651.84 | P13: 5161.7 | Q13: 499.8 | R13: 6313.34 | S13: 03:00 | T13: 4131.84 | U13: 1806.8 | V13: 0 | W13: 374.7 | X13: 6313.34 | Y13: 03:00 | Z13: 329.64 | AA13: 61.7 | AB13: 0 | AC13: 374.7 | AD13: 766.04
B14: 03:30 | C14: 467.24 | D14: 131.4 | E14: 0 | F14: 43.8 | G14: 3104.7 | H14: 1741.2 | I14: 0 | J14: 366.9 | K14: 496.4 | L14: 0 | M14: 0 | N14: 0 | O14: 642.44 | P14: 5212.8 | Q14: 496.4 | R14: 6351.64 | S14: 03:30 | T14: 4068.34 | U14: 1872.6 | V14: 0 | W14: 410.7 | X14: 6351.64 | Y14: 03:30 | Z14: 330.94 | AA14: 59.7 | AB14: 0 | AC14: 410.7 | AD14: 801.34
B15: 04:00 | C15: 474.82 | D15: 131.4 | E15: 0 | F15: 47.6 | G15: 3117.5 | H15: 1698 | I15: 0 | J15: 380 | K15: 507.6 | L15: 0 | M15: 0 | N15: 0 | O15: 653.82 | P15: 5195.5 | Q15: 507.6 | R15: 6356.92 | S15: 04:00 | T15: 4099.92 | U15: 1829.4 | V15: 0 | W15: 427.6 | X15: 6356.92 | Y15: 04:00 | Z15: 329.52 | AA15: 60.1 | AB15: 0 | AC15: 427.6 | AD15: 817.22
B16: 04:30 | C16: 468.77 | D16: 132.5 | E16: 0 | F16: 57.4 | G16: 3185.2 | H16: 1687.1 | I16: 0 | J16: 434.4 | K16: 489.7 | L16: 0 | M16: 0 | N16: 0 | O16: 658.67 | P16: 5306.7 | Q16: 489.7 | R16: 6455.07 | S16: 04:30 | T16: 4143.67 | U16: 1819.6 | V16: 0 | W16: 491.8 | X16: 6455.07 | Y16: 04:30 | Z16: 327.87 | AA16: 60.2 | AB16: 0 | AC16: 491.8 | AD16: 879.87
B17: 05:00 | C17: 472.18 | D17: 132 | E17: 0 | F17: 49.3 | G17: 3224.8 | H17: 1685.2 | I17: 0 | J17: 427.9 | K17: 493.5 | L17: 0 | M17: 0 | N17: 0 | O17: 653.48 | P17: 5337.9 | Q17: 493.5 | R17: 6484.88 | S17: 05:00 | T17: 4190.48 | U17: 1817.2 | V17: 0 | W17: 477.2 | X17: 6484.88 | Y17: 05:00 | Z17: 328.98 | AA17: 60.8 | AB17: 0 | AC17: 477.2 | AD17: 866.98
B18: 05:30 | C18: 475.35 | D18: 132 | E18: 0 | F18: 48.2 | G18: 3056.8 | H18: 1866 | I18: 0 | J18: 459.1 | K18: 496.4 | L18: 0 | M18: 1.2 | N18: 0 | O18: 655.55 | P18: 5381.9 | Q18: 497.6 | R18: 6535.05 | S18: 05:30 | T18: 4028.55 | U18: 1998 | V18: 1.2 | W18: 507.3 | X18: 6535.05 | Y18: 05:30 | Z18: 329.55 | AA18: 61.1 | AB18: 1.2 | AC18: 507.3 | AD18: 899.15
B19: 06:00 | C19: 472.17 | D19: 133.8 | E19: 0 | F19: 42.3 | G19: 3064.1 | H19: 1893.6 | I19: 0 | J19: 419 | K19: 496 | L19: 0 | M19: 13.6 | N19: 0 | O19: 648.27 | P19: 5376.7 | Q19: 509.6 | R19: 6534.57 | S19: 06:00 | T19: 4032.27 | U19: 2027.4 | V19: 13.6 | W19: 461.3 | X19: 6534.57 | Y19: 06:00 | Z19: 329.37 | AA19: 62.8 | AB19: 13.6 | AC19: 461.3 | AD19: 867.07
... B56: TOTAL MWh | C56: 12634.185 | D56: 3150.6 | E56: 1.95 | F56: 1548.45 | G56: 81907.5 | H56: 49502.2 | I56: 5.05 | J56: 10196.75 | K56: 11990.65 | L56: 0 | M56: 3364.95 | N56: 0 | O56: 17335.185 | P56: 141611.5 | Q56: 15355.6 | R56: 174302.29 | S56: TOTAL MWh | T56: 106532.34 | U56: 52652.8 | V56: 3371.95 | W56: 11745.2 | X56: 174302.29 | Y56: TOTAL MWh | Z56: 8014.485 | AA56: 1431.35 | AB56: 3371.95 | AC56: 11745.2 | AD56: 24562.985

Sheet HOP
B3: martes, 21 de Enero del 2025
B5: Reporte de Horas de Operación
B6: Empresa | C6: Central | D6: Grupo | E6: Modo de Operación | F6: Inicio | G6: Final | H6: O. Arranque | I6: O. Parada | J6: Tipo Operación | K6: Ensayo de Potencia Efectiva | L6: Ensayo de Potencia Mínima | M6: Sistema | N6: Lim. Transm. | O6: Causa | P6: Observación
B7: AGRO INDUSTRIAL PARAMONGA S.A. | C7: C.T. PARAMONGA | D7: CENTRAL | E7: PARAMONGA - BAGAZO | F7: 21/01/2025 00:00:00 | G7: 22/01/2025 00:00:00 | J7: POR COGENERACION | O7: ...
B8: AGROAURORA S.A.C. | C8: C.T. MAPLE ETANOL | D8: CENTRAL | E8: MAPLE- BAGAZO | F8: 21/01/2025 00:00:00 | G8: 22/01/2025 00:00:00 | J8: POR COGENERACION | O8: ...
B9: AGROINDUSTRIAS SAN JACINTO S.A.A. | C9: C.T. SAN JACINTO | D9: CENTRAL | E9: SAN_JACINTO - BAGAZO | F9: 21/01/2025 00:00:00 | G9: 22/01/2025 00:00:00 | J9: POR COGENERACION | O9: ...
B10: BIOENERGIA DEL CHIRA S.A. | C10: C.T. CAÑA BRAVA | D10: CENTRAL | E10: CANA BRAVA TV1 & TV2 - BAGAZO | F10: 21/01/2025 00:00:00 | G10: 21/01/2025 05:24:00 | J10: POR COGENERACION | O10: ...
B11: BIOENERGIA DEL CHIRA S.A. | C11: C.T. CAÑA BRAVA | D11: G-1 | E11: CANA BRAVA TV1 - BAGAZO | F11: 21/01/2025 05:24:00 | G11: 21/01/2025 05:34:00 | J11: POR COGENERACION | O11: ...
B12: BIOENERGIA DEL CHIRA S.A. | C12: C.T. CAÑA BRAVA | D12: CENTRAL | E12: CANA BRAVA TV1 & TV2 - BAGAZO | F12: 21/01/2025 05:34:00 | G12: 22/01/2025 00:00:00 | J12: POR COGENERACION | O12: ...
B13: EGESUR | C13: C.T. INDEPENDENCIA | D13: CENTRAL | E13: INDEPENDENCIA GAS | F13: 21/01/2025 06:36:00 | G13: 21/01/2025 21:34:00 | H13: 21/01/2025 06:30:00 | I13: 21/01/2025 21:23:00 | J13: POR POTENCIA O ENERGIA | O13: ...
B14: ENEL GENERACION PIURA S.A. | C14: C.T. MALACAS 1 | D14: CENTRAL | E14: MALACAS1 TG6 - GAS | F14: 21/01/2025 00:00:00 | G14: 22/01/2025 00:00:00 | J14: POR POTENCIA O ENERGIA | O14: ...
B15: ENGIE | C15: C.T. CHILCA 1 | D15: TG2 | E15: CHILCA1 TG2 - GAS | F15: 21/01/2025 06:44:00 | G15: 21/01/2025 07:43:00 | H15: 21/01/2025 06:31:00 | J15: A MINIMA CARGA | O15: ...
B16: ENGIE | C16: C.T. CHILCA 1 | D16: TG2 | E16: CHILCA1 TG2 - GAS | F16: 21/01/2025 07:43:00 | G16: 21/01/2025 13:03:00 | J16: POR POTENCIA O ENERGIA | O16: ...
B17: ENGIE | C17: C.T. CHILCA 1 | D17: TG2 | E17: CHILCA1 TG2 - GAS | F17: 21/01/2025 13:03:00 | G17: 21/01/2025 14:11:00 | J17: A MINIMA CARGA | O17: ...
B18: ENGIE | C18: C.T. CHILCA 1 | D18: TG2 | E18: CHILCA1 TG2 - GAS | F18: 21/01/2025 14:11:00 | G18: 21/01/2025 17:17:00 | J18: POR POTENCIA O ENERGIA | O18: ...
B19: ENGIE | C19: C.T. CHILCA 1 | D19: TG2 | E19: CHILCA1 TG2 - GAS | F19: 21/01/2025 17:17:00 | G19: 21/01/2025 19:50:00 | J19: A MINIMA CARGA | O19: ...
B20: ENGIE | C20: C.T. CHILCA 1 | D20: TG2 | E20: CHILCA1 TG2 - GAS | F20: 21/01/2025 19:50:00 | G20: 21/01/2025 21:10:00 | J20: POR POTENCIA O ENERGIA | O20: ...
B21: ENGIE | C21: C.T. CHILCA 1 | D21: TG2 | E21: CHILCA1 TG2 - GAS | F21: 21/01/2025 21:10:00 | G21: 21/01/2025 21:37:00 | I21: 21/01/2025 21:23:00 | J21: A MINIMA CARGA | O21: ...
B22: ENGIE | C22: C.T. CHILCA 2 | D22: TG41 | E22: CHILCA2 TG41 - GAS | F22: 21/01/2025 11:45:00 | G22: 21/01/2025 14:13:00 | H22: 21/01/2025 11:12:00 | I22: 21/01/2025 13:45:00 | J22: POR POTENCIA O ENERGIA | O22: ...
B23: FENIX POWER PERÚ | C23: C.T. FENIX | D23: CENTRAL | E23: FENIX CCOMB GT11 & GT12 - GAS | F23: 21/01/2025 00:00:00 | G23: 21/01/2025 03:07:00 | J23: POR POTENCIA O ENERGIA | O23: ... | P23: A las 03:44 h paró por fuga de aceite hidráulico en el sistema de la unidad TV10. A las 03:07 h desacoplo TG11.
B24: FENIX POWER PERÚ | C24: C.T. FENIX | D24: CENTRAL | E24: FENIX CCOMB GT12 - GAS | F24: 21/01/2025 03:07:00 | G24: 21/01/2025 03:44:00 | J24: POR POTENCIA O ENERGIA | O24: ... | P24: En proceso de desacople por correctivo de TV
B25: FENIX POWER PERÚ | C25: C.T. FENIX | D25: GT11 | E25: FENIX GT11 - GAS | F25: 21/01/2025 03:07:00 | G25: 21/01/2025 05:26:00 | J25: A MINIMA CARGA | O25: ...
B26: FENIX POWER PERÚ | C26: C.T. FENIX | D26: GT12 | E26: FENIX GT12 - GAS | F26: 21/01/2025 03:44:00 | G26: 21/01/2025 05:21:00 | J26: A MINIMA CARGA | O26: ...
B27: FENIX POWER PERÚ | C27: C.T. FENIX | D27: GT12 | E27: FENIX GT12 - GAS | F27: 21/01/2025 05:21:00 | G27: 21/01/2025 07:11:00 | J27: A MINIMA CARGA | O27: ... | P27: En proceso de acople 1x1
B28: FENIX POWER PERÚ | C28: C.T. FENIX | D28: GT11 | E28: FENIX GT11 - GAS | F28: 21/01/2025 05:26:00 | G28: 21/01/2025 09:09:00 | J28: POR POTENCIA O ENERGIA | O28: ... | P28: A las 08:37 h, en proceso de acople 2x1
B29: FENIX POWER PERÚ | C29: C.T. FENIX | D29: CENTRAL | E29: FENIX CCOMB GT12 - GAS | F29: 21/01/2025 07:11:00 | G29: 21/01/2025 09:09:00 | J29: POR POTENCIA O ENERGIA | O29: ...
B30: FENIX POWER PERÚ | C30: C.T. FENIX | D30: CENTRAL | E30: FENIX CCOMB GT11 & GT12 - GAS | F30: 21/01/2025 09:09:00 | G30: 22/01/2025 00:00:00 | J30: POR POTENCIA O ENERGIA | O30: ...
B31: GM OPERACIONES S.A.C. | C31: CT REFINERIA TALARA | D31: TV1 REF TALARA | E31: REF_TALARA TV1 - NLH_RFG | F31: 21/01/2025 00:00:00 | G31: 22/01/2025 00:00:00 | J31: POR COGENERACION | O31: ...
B32: GM OPERACIONES S.A.C. | C32: CT REFINERIA TALARA | D32: TV2 REF TALARA | E32: REF_TALARA TV2 - NLH_RFG | F32: 21/01/2025 00:00:00 | G32: 22/01/2025 00:00:00 | J32: POR COGENERACION | O32: ...
B33: KALLPA GENERACION S.A. | C33: C.T. KALLPA | D33: CENTRAL | E33: KALLPA CCOMB TG1 & TG2 & TG3 - GAS | F33: 21/01/2025 00:00:00 | G33: 21/01/2025 01:30:00 | J33: POR RSF | O33: ...
B34: KALLPA GENERACION S.A. | C34: C.T. KALLPA | D34: CENTRAL | E34: KALLPA CCOMB TG1 & TG2 & TG3 - GAS | F34: 21/01/2025 01:30:00 | G34: 21/01/2025 02:00:00 | J34: A MINIMA CARGA | O34: ...
B35: KALLPA GENERACION S.A. | C35: C.T. KALLPA | D35: CENTRAL | E35: KALLPA CCOMB TG1 & TG2 & TG3 - GAS | F35: 21/01/2025 02:00:00 | G35: 21/01/2025 03:00:00 | J35: POR RSF | O35: ...
B36: KALLPA GENERACION S.A. | C36: C.T. KALLPA | D36: CENTRAL | E36: KALLPA CCOMB TG1 & TG2 & TG3 - GAS | F36: 21/01/2025 03:00:00 | G36: 21/01/2025 03:08:00 | J36: A MINIMA CARGA | O36: ...
B37: KALLPA GENERACION S.A. | C37: C.T. KALLPA | D37: CENTRAL | E37: KALLPA CCOMB TG1 & TG2 & TG3 - GAS | F37: 21/01/2025 03:08:00 | G37: 21/01/2025 22:48:00 | J37: POR POTENCIA O ENERGIA | O37: ... | P37: S/C generar a 700 MW.
B38: KALLPA GENERACION S.A. | C38: C.T. KALLPA | D38: CENTRAL | E38: KALLPA CCOMB TG1 & TG2 & TG3 - GAS | F38: 21/01/2025 22:48:00 | G38: 22/01/2025 00:00:00 | J38: POR RSF | O38: ...
B39: KALLPA GENERACION S.A. | C39: C.T. LAS FLORES | D39: CENTRAL | E39: LAS FLORES CCOMB TG1 - GAS | F39: 21/01/2025 00:00:00 | G39: 22/01/2025 00:00:00 | J39: POR POTENCIA O ENERGIA | O39: ...
B40: ORYGEN PERU S.A.A. | C40: C.T. VENTANILLA | D40: CENTRAL | E40: VENTANILLA CCOMB TG3 & TG4 - GAS | F40: 21/01/2025 00:00:00 | G40: 22/01/2025 00:00:00 | J40: POR POTENCIA O ENERGIA | O40: ...
B41: PETRAMAS | C41: C.T. HUAYCOLORO | D41: CENTRAL | E41: HUAYCOLORO - BIOGAS | F41: 21/01/2025 00:00:00 | G41: 22/01/2025 00:00:00 | J41: POR POTENCIA O ENERGIA | O41: ...
B42: PETRAMAS | C42: C.T. LA GRINGA | D42: CENTRAL | E42: LA GRINGA V - BIOGAS | F42: 21/01/2025 00:00:00 | G42: 22/01/2025 00:00:00 | J42: POR POTENCIA O ENERGIA | O42: ...
B43: PETRAMAS | C43: C.T.B DOÑA CATALINA | D43: CENTRAL | E43: DONA CATALINA - BIOGAS | F43: 21/01/2025 00:00:00 | G43: 22/01/2025 00:00:00 | J43: POR POTENCIA O ENERGIA | O43: ...
B44: PETRAMAS | C44: C.T.B. CALLAO | D44: CENTRAL | E44: CALLAO - BIOGAS | F44: 21/01/2025 00:00:00 | G44: 22/01/2025 00:00:00 | J44: POR POTENCIA O ENERGIA | O44: ...
B45: SDF ENERGIA SAC | C45: C.T. OQUENDO | D45: CENTRAL | E45: OQUENDO CCOMB TG1 - GAS | F45: 21/01/2025 00:00:00 | G45: 22/01/2025 00:00:00 | J45: POR COGENERACION | O45: ...

Sheet INDISP
B3: martes, 21 de Enero del 2025
B5: Hora Inicio y Fin de Indisponibilidades de las Unidades de Generación SEIN
B6: Empresa | C6: Ubicación | D6: Equipo | E6: Inicio | F6: Final | G6: Descripción | H6: MW Indisp. | I6: Prog. | J6: Dispon | K6: Interrupc. | L6: Tipo | M6: CodEq | N6: TipoEq_Osinerg
B7: ATRIA ENERGIA S.A.C. | C7: PURMACANA | D7: G1 | E7: 21/01/2025 00:00 | F7: 22/01/2025 00:00 | G7: OVERHAUL DE TURBINA | H7: 0.7 | I7: P | J7: F/S | K7: N | L7: PREV. | M7: 13133 | N7: G
B8: CHINANGO S.A.C. | C8: CHIMAY | D8: CENTRAL | E8: 21/01/2025 00:00 | F8: 21/01/2025 07:54 | G8: FUERA DE SERVICIO POR ACUMULACION DE SOLIDOS | H8: 0 | I8: F | J8: F/S | K8: N | L8: OTROS | M8: 1191 | N8: G
B9: CHINANGO S.A.C. | C9: CHIMAY | D9: G1 | E9: 21/01/2025 08:00 | F9: 22/01/2025 00:00 | G9: Reparación de válvula bypass manual de VVMM | H9: 75 | I9: F | J9: F/S | K9: N | L9: CORR. | M9: 109 | N9: G
