Workbook

Sheet EVENTOS
B3: miércoles, 9 de Abril del 2025
B5: INFORMACIÓN DE EVENTOS PRINCIPALES EN SUS INSTALACIONES
B6: TIPO DE EVENTO | C6: EMPRESA | D6: UBICACIÓN | E6: TIPO DE EQUIPO | F6: EQUIPO | G6: INICIO | H6: FINAL | I6: DESCRIPCIÓN | J6: MW INDISP. | K6: INTERRUPCIÓN (SI/NO) | L6: TENSIÓN DE FALLA (kV)
B7: EVENTO | C7: CONCESIONARIA LINEA DE TRANSMISION CCNCM S.A.C. | D7: CACLIC - BELAUNDE TERRY | E7: LINEA DE TRANSMISION | F7: L-2194 | G7: 09/04/2025 10:16:00 | H7: 09/04/2025 10:16:00 | I7: RECIERRE EXITOSO EN LA LÍNEA L-2194 (CACLIC - BELAUNDE TERRY) DE 220 KV | K7: NO
B8: EVENTO | C8: CONELSUR LT SAC | D8: PORTILLO | E8: SUBESTACION | F8: SS.EE. | G8: 09/04/2025 00:00:00 | H8: 10/04/2025 00:00:00 | I8: DECLARACIÓN DE SITUACIÓN EXCEPCIONAL EN LA S.E. PORTILLO DE 60 kV | K8: NO
B9: FALLA | C9: ELECTRO DUNAS | D9: ICA - SANTA MARGARITA | E9: LINEA DE TRANSMISION | F9: L-6624 | G9: 09/04/2025 11:50:41 | H9: 09/04/2025 12:03:56 | I9: DESCONEXIÓN DE LA LÍNEA L-6624 (ICA-SANTA MARGARITA) DE 60 KV | J9: 16.7 | K9: SI | L9: 60
B10: FALLA | C10: EMPRESA ELECTRICA AGUA AZUL | D10: POTRERO | E10: GENERADOR HIDROELÉCTRICO | F10: G2 | G10: 09/04/2025 23:51:10 | H10: 10/04/2025 01:15:23 | I10: DESCONEXIÓN DEL GRUPO G2 DE LA C.H. POTRERO | K10: NO | L10: 10
B11: EVENTO | C11: RED DE ENERGIA DEL PERU S.A. | D11: TINGO MARÍA - AUCAYACU | E11: LINEA DE TRANSMISION | F11: L-1122 | G11: 09/04/2025 10:54:00 | H11: 09/04/2025 16:57:00 | I11: DECLARACIÓN DE SITUACIÓN EXCEPCIONAL EN LA LÍNEA L-1122 (TINGO MARÍA - AUCAYACU) DE 138 kV | K11: NO
B12: EVENTO | C12: RED DE ENERGIA DEL PERU S.A. | D12: TINGO MARÍA - AUCAYACU | E12: LINEA DE TRANSMISION | F12: L-1122 | G12: 09/04/2025 18:30:00 | H12: 09/04/2025 20:54:00 | I12: DECLARACIÓN DE SITUACIÓN EXCEPCIONAL EN LA LÍNEA L-1122 (TINGO MARÍA - AUCAYACU) DE 138 kV | K12: NO
B13: EVENTO | C13: RED DE ENERGIA DEL PERU S.A. | D13: ZORRITOS - MACHALA | E13: LINEA DE TRANSMISION | F13: L-2280_old | G13: 09/04/2025 08:56:00 | H13: 09/04/2025 16:02:00 | I13: IMPORTACIÓN DE ENERGÍA DE ECUADOR | K13: NO
B14: EVENTO | C14: ATLANTICA TRANSMISION SUR S.A. | D14: POROMA - OCONA | E14: LINEA DE TRANSMISION | F14: L-5034 | G14: 09/04/2025 00:00:00 | H14: 09/04/2025 07:00:00 | I14: DECLARACIÓN DE SITUACION EXCEPCIONAL EN EL ENLACE CENTRO - SUR | K14: NO
B15: EVENTO | C15: ATLANTICA TRANSMISION SUR S.A. | D15: POROMA - OCONA | E15: LINEA DE TRANSMISION | F15: L-5034 | G15: 09/04/2025 16:45:00 | H15: 10/04/2025 00:00:00 | I15: DECLARACIÓN DE SITUACION EXCEPCIONAL EN EL ENLACE CENTRO - SUR | K15: NO

Sheet RESTRIC_OPE
B3: miércoles, 9 de Abril del 2025
B5: RESTRICCIONES OPERATIVAS
B6: FECHA | C6: HORA INICIO | D6: HORA FINAL | E6: EMPRESA | F6: UBICACIÓN | G6: T.Eq. | H6: EQUIPO | I6: DESCRIPCIÓN
B7: 09/04/2025 | C7: 00:00 | D7: 24:00 | E7: CELEPSA | F7: C.H. EL PLATANAL | G7: CH | H7: CENTRAL | I7: Debido al incremento del caudal del rio cañete y establecimiento de la temporada de avenida, se declara la C.H. El Platanal como CENTRAL HIDRÁULICA DE PASADA (correo 03/01/2025).
B8: 09/04/2025 | C8: 00:00 | D8: 24:00 | E8: EGASA | F8: C.H. CHARCANI II | G8: GH | H8: G2 | I8: El Grupo N°02 esta operando con una potencia no mayor a 0.07MW en referencia a 0.18MW de su potencia efectiva, con el fin de no generar daños mayores hasta la reparación de su cojinete.
B9: 09/04/2025 | C9: 00:00 | D9: 24:00 | E9: EGASA | F9: S.E. CONVERTIDOR | G9: BARRA | H9: BARRA138KV | I9: EGASA limitó la capacidad del transformador 138 kV/33 kV a 50 MVA por deterioro del aislamiento.
B10: 09/04/2025 | C10: 00:00 | D10: 24:00 | E10: ENEL GENERACION PIURA S.A. | F10: C.T. MALACAS | G10: CT | H10: CENTRAL | I10: De acuerdo con la comunicación vía correo del día 24.10.2024. ENEL GENERACIÓN PIURA informa una restricción de potencia para alcanzar 105 MW en simultaneo (TG6+TGN4).
B11: 09/04/2025 | C11: 00:00 | D11: 24:00 | E11: ENGIE | F11: C.E. PUNTA LOMITAS | G11: CE | H11: CENTRAL | I11: De acuerdo a la carta ENG/737-2024 (Exp:202400007555). Limitación de cables de media tensión a 100 MW de los transformadores PLT1 y PLT2 de la CE Punta Lomitas. Quedan limitados a 200 MW la generación de CE Punta Lomitas y Punta Lomitas Extensión.
B12: 09/04/2025 | C12: 00:00 | D12: 24:00 | E12: ENGIE | F12: C.H. QUITARACSA | G12: CH | H12: CENTRAL | I12: De acuerdo con el correo del 23.04 se considera la operación continua de la CH Quitaracsa debido a que el sistema de refrigeración de la CH Cañón del Pato se alimenta desde la descarga del caudal turbinado por la CH Quitaracsa.
B13: 09/04/2025 | C13: 00:00 | D13: 24:00 | E13: ENGIE | F13: C.H. YUNCÁN | G13: GH | H13: G3 | I13: Según la carta N° ENG/ 198-2024 enviada por su representada, se opera de forma continua el G3 de la CH Yuncán, debido a la ejecución de mantenimientos necesarios para evitar daños en los sellos de seguridad de la válvula esférica del grupo.
B14: 09/04/2025 | C14: 00:00 | D14: 24:00 | E14: ENGIE | F14: C.T. CHILCA 1 | G14: CT | H14: CENTRAL | I14: Con carta ENG/971-2023, indica que no puede cumplir con las IO considerada en el PDO_17122023 dado que vulneran la seguridad de sus activos. Indican que se debe tomar TMO=168h.
B15: 09/04/2025 | C15: 00:00 | D15: 24:00 | E15: ENGIE | F15: C.T. CHILCA 1 | G15: CT | H15: CENTRAL | I15: Restricción de temperatura de la C.T Chilca, ver valor en el modelo de despacho.
B16: 09/04/2025 | C16: 00:00 | D16: 24:00 | E16: ENGIE | F16: C.T. CHILCA 2 | G16: CT | H16: CENTRAL | I16: Con carta ENG/971-2023, indica que no puede cumplir con las IO considerada en el PDO_17122023 dado que vulneran la seguridad de sus activos. Indican que se debe tomar TMO=168h.
B17: 09/04/2025 | C17: 00:00 | D17: 24:00 | E17: ENGIE | F17: C.T. CHILCA 2 | G17: CT | H17: CENTRAL | I17: Restricción de temperatura de la C.T Chilca2, ver valor en el modelo de despacho.
... B50: 09/04/2025 | C50: 00:00 | D50: 24:00 | E50: TRANSMANTARO | F50: S.E. SOCABAYA | G50: SSEE | H50: S.E. | I50: Opera en simple barra en 220 kV por indisponibilidad de la protección diferencial de barras por alarma.

Sheet MANTENIMIENTO EJECUTADOS
B3: miércoles, 9 de Abril del 2025
B5: Mantenimiento Ejecutado
B6: Empresa | C6: Ubicación | D6: Equipo | E6: Inicio | F6: Final | G6: Descripción | H6: MW Indisp. | I6: Prog. | J6: Dispon | K6: Interrupc. | L6: Tipo | M6: CodEq | N6: TipoEq_Osinerg
B7: AGROAURORA S.A.C. | C7: MAPLE ETANOL | D7: CENTRAL | E7: 09/04/2025 00:00 | F7: 10/04/2025 00:00 | G7: CENTRAL TERMOELECTRICA FUERA DE SERVICIO POR FALTA DE MATERIA PRIMA PARA LOS REQUERIMIENTOS DE CALOR UTIL EN FABRICA. | H7: 14 | I7: P | J7: F/S | K7: N | L7: OTROS | M7: 13417 | N7: G
B8: AGROAURORA S.A.C. | C8: MAPLE ETANOL | D8: CENTRAL | E8: 09/04/2025 00:00 | F8: 10/04/2025 00:00 | G8: MANTENIMIENTO PREVENTIVO PROGRAMADO DE LA CENTRAL TERMOELECTRICA Y EQUIPOS AUXILIARES. | H8: 14 | I8: P | J8: F/S | K8: N | L8: PREV. | M8: 13417 | N8: G
B9: AGROINDUSTRIAS SAN JACINTO S.A.A. | C9: SAN JACINTO | D9: CENTRAL | E9: 09/04/2025 00:00 | F9: 10/04/2025 00:00 | G9: Mantenimiento Anual. | H9: 8.15 | I9: P | J9: F/S | K9: N | L9: PREV. | M9: 19865 | N9: G
B10: ATLANTICA TRANSMISION SUR S.A. | C10: CHILCA-CTM | D10: INT-5261 | E10: 09/04/2025 00:00 | F10: 10/04/2025 00:00 | G10: Seccionador SBB-5261 fase S indisponible para maniobras de apertura y cierre por anomalia en tapa de tanque de compresion, el seccionador permanece cerrado y bloqueado. | H10: 0 | I10: P | J10: E/S | K10: N | L10: OTROS | M10: 13854 | N10: T
B11: ATLANTICA TRANSMISION SUR S.A. | C11: MONTALVO | D11: ACOPLE 220 | E11: 09/04/2025 00:00 | F11: 10/04/2025 00:00 | G11: Proyecto Refuerzos: Reemplazo del HMI existente, Pruebas y Configuracion. No se contara con nivel 1 de operacion. | H11: 0 | I11: P | J11: E/S | K11: N | L11: P.ENERG | M11: 14767 | N11: T
B12: ATLANTICA TRANSMISION SUR S.A. | C12: MONTALVO | D12: CL-2057 | E12: 09/04/2025 00:00 | F12: 10/04/2025 00:00 | G12: Proyecto Refuerzos: Reemplazo del HMI existente, Pruebas y Configuracion. No se contara con nivel 1 de operacion. | H12: 0 | I12: P | J12: E/S | K12: N | L12: P.ENERG | M12: 13812 | N12: T
B13: ATLANTICA TRANSMISION SUR S.A. | C13: MONTALVO | D13: CL-AUT-5671_500 | E13: 09/04/2025 00:00 | F13: 10/04/2025 00:00 | G13: Proyecto Refuerzos: Reemplazo del HMI existente, Pruebas y Configuracion. No se contara con nivel 1 de operacion en INT-5671, INT-5652 y SAT-5671. | H13: 0 | I13: P | J13: E/S | K13: N | L13: P.ENERG | M13: 13809 | N13: T
B14: ATLANTICA TRANSMISION SUR S.A. | C14: MONTALVO | D14: INT-5652 | E14: 09/04/2025 00:00 | F14: 10/04/2025 00:00 | G14: Proyecto Refuerzos:Indisponible por Implementacion de conexion de corrientes, disparos, posiciones, enclavamientos hacia los equipos del nuevos Autotransformador. AUT-5671 en servicio solo por Barra A 500kV. | H14: 0 | I14: P | J14: F/S | K14: N | L14: P.ENERG | M14: 13765 | N14: T
B15: ATLANTICA TRANSMISION SUR S.A. | C15: OCONA | D15: INT-5450 | E15: 09/04/2025 00:00 | F15: 10/04/2025 00:00 | G15: Interruptor INT-5450 cerrado con restriccion operativa, REB-5450 en servicio y suministrando los SS.AA. de la S.E. Oco?a. | H15: 0 | I15: P | J15: E/S | K15: N | L15: OTROS | M15: 13761 | N15: T
B16: ATLANTICA TRANSMISION SUR S.A. | C16: OCONA | D16: INT-5462 | E16: 09/04/2025 00:00 | F16: 10/04/2025 00:00 | G16: Seccionador SBA-5462 fase T indisponible por problemas mecanicos, el seccionador permanece cerrado y bloqueado | H16: 0 | I16: P | J16: E/S | K16: N | L16: OTROS | M16: 13758 | N16: T
B17: ATLANTICA TRANSMISION SUR S.A. | C17: POROMA | D17: ACOPLE 220 | E17: 09/04/2025 00:00 | F17: 10/04/2025 00:00 | G17: Proyecto Refuerzos: Reemplazo del HMI existente, Pruebas y Configuracion. No se contara con nivel 1 de operacion. | H17: 0 | I17: P | J17: E/S | K17: N | L17: P.ENERG | M17: 13797 | N17: T
B18: ATLANTICA TRANSMISION SUR S.A. | C18: POROMA | D18: CL-2292 | E18: 09/04/2025 00:00 | F18: 10/04/2025 00:00 | G18: Proyecto Refuerzos: Reemplazo del HMI existente, Pruebas y Configuracion. No se contara con nivel 1 de operacion. | H18: 0 | I18: P | J18: E/S | K18: N | L18: P.ENERG | M18: 13798 | N18: T
... B168: TRANSMISORA ELECTRICA DEL SUR 4 S.A.C. - TESUR 4 | C168: PUMIRI | D168: BARRA A -220kV | E168: 09/04/2025 08:30 | F168: 09/04/2025 17:30 | G168: Solicitado por la empresa HYDRO GLOBAL para realizar revisiones y pruebas finales de envio de se?ales 87B Respaldo. Deshabilitacion de la proteccion diferencial. | H168: 0 | I168: R | J168: E/S | K168: N | L168: OTROS | M168: 22359 | N168: T

Sheet INGRESO OC
A3: miércoles, 9 de Abril del 2025
A5: INGRESO A OPERACIÓN COMERCIAL
A6: EMPRESA | B6: TIPO DE EQUIPO | C6: UBICACIÓN | D6: EQUIPO | E6: Fecha y hora de Ingreso a Operación Comercial

Sheet DESPACHO_EJECUTADO
B3: miércoles, 9 de Abril del 2025
A5: POTENCIA ACTIVA EJECUTADA DE LAS UNIDADES DE GENERACIÓN DEL SEIN (MW) | FK5: CENTRALES NO INTEGRANTES COES
A6: FECHA | B6: HORA | C6: 337 | D6: 338 | E6: 101 | F6: 102 | G6: 42667 | H6: 42668 | I6: 126 | J6: 127 | K6: 138 | L6: 139 | M6: 197 | N6: 203 | O6: 204 | P6: 230 | Q6: 209 | R6: 56677 | S6: 796 | T6: 2146 | U6: 142 | V6: 143 | W6: 125 | X6: 187 | Y6: 163 | Z6: 298 | AA6: 299 | AB6: 219 | AC6: 151 | AD6: 152 | AE6: 153 | AF6: 154 | AG6: 756 | AH6: 156 | AI6: 155 | AJ6: 182 | AK6: 212 | AL6: 758 | AM6: 263 | AN6: 265 | AO6: 775 | AP6: 777 | AQ6: 2154 | AR6: 150 | AS6: 149 | AT6: 188 | AU6: 2131 | AV6: 755 | AW6: 252 | AX6: 249 | AY6: 250 | AZ6: 117 | BA6: 267 | BB6: 268 | BC6: 119 | BD6: 120 | BE6: 189 | BF6: 122 | BG6: 266 | BH6: 251 | BI6: 115 | BJ6: 239 | BK6: 288 | BL6: 240 | BM6: 241 | BN6: 242 | BO6: 191 | BP6: 194 | BQ6: 196 | BR6: 207 | BS6: 236 | BT6: 795 | BU6: 285 | BV6: 995 | BW6: 996 | BX6: 997 | BY6: 766 | BZ6: 926 | CA6: 924 | CB6: 121 | CC6: 103 | CD6: 104 | CE6: 106 | CF6: 105 | CG6: 107 | CH6: 110 | CI6: 109 | CJ6: 144 | CK6: 113 | CL6: 114 | CM6: 193 | CN6: 208 | CO6: 786 | CP6: 787 | CQ6: 788 | CR6: 789 | CS6: 248 | CT6: 2159 | CU6: 303 | CV6: 59715 | CW6: 62255 | CX6: 1263 | CY6: 63425 | CZ6: 61800 | DA6: 2194 | DB6: 216 | DC6: 198 | DD6: 49607 | DE6: 214 | DF6: 260 | DG6: 2152 | DH6: 2128 | DI6: 247 | DJ6: 228 | DK6: 2135 | DL6: 261 | DM6: 237 | DN6: 253 | DO6: 770 | DP6: 225 | DQ6: 2201 | DR6: 2171 | DS6: 760 | DT6: 235 | DU6: 238 | DV6: 2184 | DW6: 61855 | DX6: 223 | DY6: 226 | DZ6: 201 | EA6: 258 | EB6: 259 | EC6: 920 | ED6: 257 | EE6: 256 | EF6: 2148 | EG6: 58288 | EH6: 58289 | EI6: 58839 | EJ6: 58840 | EK6: 296 | EL6: 297 | EM6: 211 | EN6: 2175 | EO6: 2178 | EP6: 2181 | EQ6: 1262 | ER6: 233 | ES6: 2150 | ET6: 2165 | EU6: 2161 | EV6: 61197 | EW6: 58851 | EX6: 234 | EY6: 215 | EZ6: 917 | FA6: 289 | FB6: 58333 | FC6: 58336 | FD6: 202 | FE6: 58487 | FF6: 213 | FG6: 232 | FH6: 2190 | FI6: TOTAL COES | FK6: 221 | FL6: 222 | FM6: 224 | FN6: 2187 | FO6: 227 | FP6: 49400 | FQ6: 199 | FR6: 200 | FS6: TOTAL NO COES
C7: CENTRO | D7: CENTRO | E7: CENTRO | F7: CENTRO | G7: NORTE | H7: NORTE | I7: NORTE | J7: NORTE | K7: CENTRO | L7: CENTRO | M7: CENTRO | N7: CENTRO | O7: CENTRO | P7: CENTRO | Q7: CENTRO | R7: CENTRO | S7: CENTRO | T7: CENTRO | U7: CENTRO | V7: CENTRO | W7: CENTRO | X7: CENTRO | Y7: SUR | Z7: SUR | AA7: SUR | AB7: CENTRO | AC7: SUR | AD7: SUR | AE7: SUR | AF7: SUR | AG7: SUR | AH7: SUR | AI7: SUR | AJ7: SUR | AK7: CENTRO | AL7: NORTE | AM7: NORTE | AN7: NORTE | AO7: CENTRO | AP7: CENTRO | AQ7: CENTRO | AR7: CENTRO | AS7: CENTRO | AT7: CENTRO | AU7: CENTRO | AV7: SUR | AW7: CENTRO | AX7: CENTRO | AY7: CENTRO | AZ7: CENTRO | BA7: CENTRO | BB7: CENTRO | BC7: CENTRO | BD7: CENTRO | BE7: SUR | BF7: NORTE | BG7: CENTRO | BH7: CENTRO | BI7: NORTE | BJ7: NORTE | BK7: NORTE | BL7: SUR | BM7: SUR | BN7: SUR | BO7: CENTRO | BP7: CENTRO | BQ7: CENTRO | BR7: CENTRO | BS7: CENTRO | BT7: CENTRO | BU7: CENTRO | BV7: SUR | BW7: SUR | BX7: SUR | BY7: NORTE | BZ7: SUR | CA7: CENTRO | CB7: NORTE | CC7: CENTRO | CD7: CENTRO | CE7: CENTRO | CF7: CENTRO | CG7: CENTRO | CH7: CENTRO | CI7: CENTRO | CJ7: CENTRO | CK7: CENTRO | CL7: CENTRO | CM7: CENTRO | CN7: CENTRO | CO7: SUR | CP7: SUR | CQ7: SUR | CR7: SUR | CS7: CENTRO | CT7: CENTRO | CU7: CENTRO | CV7: CENTRO | CW7: SUR | CX7: NORTE | CY7: SUR | CZ7: NORTE | DA7: NORTE | DB7: NORTE | DC7: NORTE | DD7: SUR | DE7: CENTRO | DF7: CENTRO | DG7: CENTRO | DH7: NORTE | DI7: NORTE | DJ7: CENTRO | DK7: CENTRO | DL7: SUR | DM7: SUR | DN7: CENTRO | DO7: CENTRO | DP7: CENTRO | DQ7: CENTRO | DR7: CENTRO | DS7: CENTRO | DT7: SUR | DU7: CENTRO | DV7: CENTRO | DW7: NORTE | DX7: CENTRO | DY7: CENTRO | DZ7: NORTE | EA7: CENTRO | EB7: CENTRO | EC7: CENTRO | ED7: NORTE | EE7: NORTE | EF7: SUR | EG7: CENTRO | EH7: CENTRO | EI7: CENTRO | EJ7: CENTRO | EK7: CENTRO | EL7: CENTRO | EM7: SUR | EN7: SUR | EO7: SUR | EP7: SUR | EQ7: NORTE | ER7: SUR | ES7: SUR | ET7: CENTRO | EU7: CENTRO | EV7: CENTRO | EW7: SUR | EX7: SUR | EY7: NORTE | EZ7: CENTRO | FA7: NORTE | FB7: NORTE | FC7: NORTE | FD7: CENTRO | FE7: CENTRO | FF7: CENTRO | FG7: NORTE | FH7: NORTE | FK7: NORTE | FL7: CENTRO | FM7: NORTE | FN7: NORTE | FO7: NORTE | FP7: NORTE | FQ7: NORTE | FR7: NORTE
C8: HIDROELÉCTRICA | D8: HIDROELÉCTRICA | E8: HIDROELÉCTRICA | F8: HIDROELÉCTRICA | G8: TERMOELÉCTRICA | H8: TERMOELÉCTRICA | I8: HIDROELÉCTRICA | J8: HIDROELÉCTRICA | K8: TERMOELÉCTRICA | L8: TERMOELÉCTRICA | M8: TERMOELÉCTRICA | N8: TERMOELÉCTRICA | O8: TERMOELÉCTRICA | P8: TERMOELÉCTRICA | Q8: TERMOELÉCTRICA | R8: TERMOELÉCTRICA | S8: HIDROELÉCTRICA | T8: HIDROELÉCTRICA | U8: TERMOELÉCTRICA | V8: TERMOELÉCTRICA | W8: TERMOELÉCTRICA | X8: TERMOELÉCTRICA | Y8: HIDROELÉCTRICA | Z8: HIDROELÉCTRICA | AA8: HIDROELÉCTRICA | AB8: TERMOELÉCTRICA | AC8: HIDROELÉCTRICA | AD8: HIDROELÉCTRICA | AE8: HIDROELÉCTRICA | AF8: HIDROELÉCTRICA | AG8: TERMOELÉCTRICA | AH8: TERMOELÉCTRICA | AI8: TERMOELÉCTRICA | AJ8: HIDROELÉCTRICA | AK8: HIDROELÉCTRICA | AL8: TERMOELÉCTRICA | AM8: TERMOELÉCTRICA | AN8: TERMOELÉCTRICA | AO8: HIDROELÉCTRICA | AP8: HIDROELÉCTRICA | AQ8: HIDROELÉCTRICA | AR8: HIDROELÉCTRICA | AS8: HIDROELÉCTRICA | AT8: HIDROELÉCTRICA | AU8: HIDROELÉCTRICA | AV8: HIDROELÉCTRICA | AW8: TERMOELÉCTRICA | AX8: TERMOELÉCTRICA | AY8: TERMOELÉCTRICA | AZ8: HIDROELÉCTRICA | BA8: HIDROELÉCTRICA | BB8: HIDROELÉCTRICA | BC8: HIDROELÉCTRICA | BD8: HIDROELÉCTRICA | BE8: HIDROELÉCTRICA | BF8: HIDROELÉCTRICA | BG8: HIDROELÉCTRICA | BH8: HIDROELÉCTRICA | BI8: TERMOELÉCTRICA | BJ8: TERMOELÉCTRICA | BK8: TERMOELÉCTRICA | BL8: TERMOELÉCTRICA | BM8: TERMOELÉCTRICA | BN8: TERMOELÉCTRICA | BO8: HIDROELÉCTRICA | BP8: TERMOELÉCTRICA | BQ8: TERMOELÉCTRICA | BR8: TERMOELÉCTRICA | BS8: TERMOELÉCTRICA | BT8: TERMOELÉCTRICA | BU8: TERMOELÉCTRICA | BV8: TERMOELÉCTRICA | BW8: TERMOELÉCTRICA | BX8: TERMOELÉCTRICA | BY8: HIDROELÉCTRICA | BZ8: TERMOELÉCTRICA | CA8: TERMOELÉCTRICA | CB8: HIDROELÉCTRICA | CC8: HIDROELÉCTRICA | CD8: HIDROELÉCTRICA | CE8: HIDROELÉCTRICA | CF8: HIDROELÉCTRICA | CG8: HIDROELÉCTRICA | CH8: TERMOELÉCTRICA | CI8: TERMOELÉCTRICA | CJ8: TERMOELÉCTRICA | CK8: TERMOELÉCTRICA | CL8: TERMOELÉCTRICA | CM8: TERMOELÉCTRICA | CN8: TERMOELÉCTRICA | CO8: TERMOELÉCTRICA | CP8: TERMOELÉCTRICA | CQ8: TERMOELÉCTRICA | CR8: TERMOELÉCTRICA | CS8: TERMOELÉCTRICA | CT8: TERMOELÉCTRICA | CU8: SOLAR | CV8: EÓLICA | CW8: SOLAR | CX8: EÓLICA | CY8: SOLAR | CZ8: SOLAR | DA8: HIDROELÉCTRICA | DB8: HIDROELÉCTRICA | DC8: HIDROELÉCTRICA | DD8: HIDROELÉCTRICA | DE8: HIDROELÉCTRICA | DF8: HIDROELÉCTRICA | DG8: HIDROELÉCTRICA | DH8: HIDROELÉCTRICA | DI8: HIDROELÉCTRICA | DJ8: HIDROELÉCTRICA | DK8: HIDROELÉCTRICA | DL8: SOLAR | DM8: SOLAR | DN8: EÓLICA | DO8: EÓLICA | DP8: TERMOELÉCTRICA | DQ8: TERMOELÉCTRICA | DR8: TERMOELÉCTRICA | DS8: TERMOELÉCTRICA | DT8: SOLAR | DU8: HIDROELÉCTRICA | DV8: HIDROELÉCTRICA | DW8: HIDROELÉCTRICA | DX8: HIDROELÉCTRICA | DY8: HIDROELÉCTRICA | DZ8: HIDROELÉCTRICA | EA8: HIDROELÉCTRICA | EB8: HIDROELÉCTRICA | EC8: HIDROELÉCTRICA | ED8: EÓLICA | EE8: EÓLICA | EF8: SOLAR | EG8: EÓLICA | EH8: EÓLICA | EI8: EÓLICA | EJ8: EÓLICA | EK8: HIDROELÉCTRICA | EL8: HIDROELÉCTRICA | EM8: HIDROELÉCTRICA | EN8: HIDROELÉCTRICA | EO8: HIDROELÉCTRICA | EP8: HIDROELÉCTRICA | EQ8: EÓLICA | ER8: SOLAR | ES8: SOLAR | ET8: HIDROELÉCTRICA | EU8: EÓLICA | EV8: EÓLICA | EW8: SOLAR | EX8: SOLAR | EY8: HIDROELÉCTRICA | EZ8: HIDROELÉCTRICA | FA8: TERMOELÉCTRICA | FB8: TERMOELÉCTRICA | FC8: TERMOELÉCTRICA | FD8: TERMOELÉCTRICA | FE8: TERMOELÉCTRICA | FF8: TERMOELÉCTRICA | FG8: TERMOELÉCTRICA | FH8: TERMOELÉCTRICA | FK8: HIDROELÉCTRICA | FL8: HIDROELÉCTRICA | FM8: HIDROELÉCTRICA | FN8: HIDROELÉCTRICA | FO8: TERMOELÉCTRICA | FP8: TERMOELÉCTRICA | FQ8: HIDROELÉCTRICA | FR8: HIDROELÉCTRICA
C9: CENTRALES SANTA ROSA S.A.C. | D9: CENTRALES SANTA ROSA S.A.C. | E9: ELECTROPERU | F9: ELECTROPERU | G9: ELECTROPERU | H9: ELECTROPERU | I9: ORAZUL ENERGY PERÚ | J9: ORAZUL ENERGY PERÚ | K9: TERMOSELVA | L9: TERMOSELVA | M9: KALLPA GENERACION S.A. | N9: KALLPA GENERACION S.A. | O9: KALLPA GENERACION S.A. | P9: KALLPA GENERACION S.A. | Q9: KALLPA GENERACION S.A. | R9: KALLPA GENERACION S.A. | S9: KALLPA GENERACION S.A. | T9: KALLPA GENERACION S.A. | U9: SHOUGESA | V9: SHOUGESA | W9: SHOUGESA | X9: SHOUGESA | Y9: EGEMSA | Z9: EGESUR | AA9: EGESUR | AB9: EGESUR | AC9: EGASA | AD9: EGASA | AE9: EGASA | AF9: EGASA | AG9: EGASA | AH9: EGASA | AI9: EGASA | AJ9: SAN GABAN | AK9: CELEPSA | AL9: MINERA CERRO VERDE | AM9: PLANTA DE RESERVA FRIA DE GENERACION DE ETEN S.A. | AN9: PLANTA DE RESERVA FRIA DE GENERACION DE ETEN S.A. | AO9: EMPRESA DE GENERACION HUALLAGA | AP9: EMPRESA DE GENERACION HUALLAGA | AQ9: LA VIRGEN | AR9: CHINANGO S.A.C. | AS9: CHINANGO S.A.C. | AT9: HIDROELECTRICA HUANCHOR S.A.C. | AU9: CELEPSA RENOVABLES S.R.L. | AV9: INLAND ENERGY SAC | AW9: FENIX POWER PERÚ | AX9: FENIX POWER PERÚ | AY9: FENIX POWER PERÚ | AZ9: STATKRAFT S.A | BA9: STATKRAFT S.A | BB9: STATKRAFT S.A | BC9: STATKRAFT S.A | BD9: STATKRAFT S.A | BE9: STATKRAFT S.A | BF9: STATKRAFT S.A | BG9: STATKRAFT S.A | BH9: EMPRESA DE GENERACION HUANZA | BI9: ENEL GENERACION PIURA S.A. | BJ9: ENEL GENERACION PIURA S.A. | BK9: ENEL GENERACION PIURA S.A. | BL9: ENGIE | BM9: ENGIE | BN9: ENGIE | BO9: ENGIE | BP9: ENGIE | BQ9: ENGIE | BR9: ENGIE | BS9: ENGIE | BT9: ENGIE | BU9: ENGIE | BV9: ENGIE | BW9: ENGIE | BX9: ENGIE | BY9: ENGIE | BZ9: INFRAESTRUCTURAS Y ENERGIAS DEL PERU S.A.C. | CA9: INFRAESTRUCTURAS Y ENERGIAS DEL PERU S.A.C. | CB9: INVERSIONES SHAQSHA S.A.C. | CC9: ORYGEN PERU S.A.A. | CD9: ORYGEN PERU S.A.A. | CE9: ORYGEN PERU S.A.A. | CF9: ORYGEN PERU S.A.A. | CG9: ORYGEN PERU S.A.A. | CH9: ORYGEN PERU S.A.A. | CI9: ORYGEN PERU S.A.A. | CJ9: ORYGEN PERU S.A.A. | CK9: ORYGEN PERU S.A.A. | CL9: ORYGEN PERU S.A.A. | CM9: ORYGEN PERU S.A.A. | CN9: ORYGEN PERU S.A.A. | CO9: SAMAY I S.A.C | CP9: SAMAY I S.A.C | CQ9: SAMAY I S.A.C | CR9: SAMAY I S.A.C | CS9: TERMOCHILCA S.A.C. | CT9: TERMOCHILCA S.A.C. | CU9: COLCA SOLAR S.A.C. | CV9: ENERGIA RENOVABLE DEL SUR S.A. | CW9: GR CORTARRAMA SOCIEDAD ANONIMA CERRADA | CX9: GR TARUCA SOCIEDAD ANONIMA CERRADA | CY9: JOYA SOLAR S.A.C. | CZ9: KONDU SAC | DA9: PERUANA DE INVERSIONES EN ENERGIAS RENOVABLES S.A. | DB9: ORAZUL ENERGY PERÚ | DC9: ORAZUL ENERGY PERÚ | DD9: SAN GABAN | DE9: MAJA ENERGIA S.A.C. | DF9: EMPRESA DE GENERACION ELECTRICA CANCHAYLLO SAC | DG9: EMPRESA DE GENERACION ELECTRICA SANTA ANA S.A.C. | DH9: EMPRESA ELECTRICA AGUA AZUL | DI9: EMPRESA ELECTRICA RIO DOBLE | DJ9: HIDROCAÑETE S.A. | DK9: HUAURA POWER GROUP S.A. | DL9: MOQUEGUA FV S.A.C. | DM9: PANAMERICANA SOLAR SAC. | DN9: PARQUE EOLICO MARCONA S.A.C. | DO9: PARQUE EOLICO TRES HERMANAS S.A.C. | DP9: PETRAMAS | DQ9: PETRAMAS | DR9: PETRAMAS | DS9: PETRAMAS | DT9: TACNA SOLAR SAC. | DU9: ELECTRICA YANAPAMPA SAC | DV9: ANDEAN POWER S.A.C. | DW9: ASOCIACIÓN SANTA LUCIA DE CHACAS | DX9: ATRIA ENERGIA S.A.C. | DY9: EGEJUNIN | DZ9: EGEJUNIN | EA9: EGEJUNIN | EB9: EGEJUNIN | EC9: EMPRESA DE GENERACION ELECTRICA RIO BAÑOS S.A.C. | ED9: ENERGÍA EÓLICA S.A. | EE9: ENERGÍA EÓLICA S.A. | EF9: ENGIE | EG9: ENGIE | EH9: ENGIE | EI9: ENGIE | EJ9: ENGIE | EK9: GENERACIÓN ANDINA S.A.C. | EL9: GENERACIÓN ANDINA S.A.C. | EM9: GENERADORA DE ENERGÍA DEL PERÚ | EN9: GENERADORA DE ENERGÍA DEL PERÚ | EO9: GENERADORA DE ENERGÍA DEL PERÚ | EP9: GENERADORA DE ENERGÍA DEL PERÚ | EQ9: GR PAINO SOCIEDAD ANONIMA CERRADA | ER9: MAJES ARCUS S.A.C. | ES9: ORYGEN PERU S.A.A. | ET9: ORYGEN PERU S.A.A. | EU9: ORYGEN PERU S.A.A. | EV9: ORYGEN PERU S.A.A. | EW9: ORYGEN PERU S.A.A. | EX9: REPARTICIÓN ARCUS S.A.C. | EY9: SINERSA | EZ9: SINERSA | FA9: BIOENERGIA DEL CHIRA S.A. | FB9: GM OPERACIONES S.A.C. | FC9: GM OPERACIONES S.A.C. | FD9: SDF ENERGIA SAC | FE9: SDF ENERGIA SAC | FF9: AGRO INDUSTRIAL PARAMONGA S.A. | FG9: AGROAURORA S.A.C. | FH9: AGROINDUSTRIAS SAN JACINTO S.A.A. | FK9: UNACEM PERU S.A. | FL9: ELECTRO ORIENTE | FM9: AGUAS Y ENERGIA PERU | FN9: ELECTRO ZAÑA S.A.C. | FO9: ELECTRONOROESTE S.A. | FP9: SDE PIURA | FQ9: SINERSA | FR9: SINERSA
C10: SANTA ROSA 1 | D10: SANTA ROSA 2 | E10: MANTARO | F10: RESTITUCION | G10: TUMBES MAK 1 | H10: TUMBES MAK 2 | I10: CARHUAQUERO | J10: CAÑON DEL PATO | K10: AGUAYTIA TG1 | L10: AGUAYTIA TG2 | M10: KALLPA TG1 | N10: KALLPA TG2 | O10: KALLPA TG3 | P10: KALLPA TV | Q10: LFLORES TG1 | R10: LFLORES TV | S10: CERRO DEL AGUILA | T10: CERRODELAGUILAG4 | U10: SHOUGESA TV1 | V10: SHOUGESA TV2 | W10: SHOUGESA TV3 | X10: SHOUGESA CUMMINS | Y10: MACHUPICCHU | Z10: ARICOTA 1 | AA10: ARICOTA 2 | AB10: INDEPENDENCIA | AC10: CHARCANI I,II,III | AD10: CHARCANI IV | AE10: CHARCANI V | AF10: CHARCANI VI | AG10: CHILINA TG | AH10: MOLLENDO 1, 2, 3 | AI10: CHILINA (SULZ 1,2) | AJ10: SAN GABAN II | AK10: PLATANAL | AL10: RECKA | AM10: RF ETEN TG1 | AN10: RF ETEN TG2 | AO10: CHAGLLA GP1 | AP10: CHAGLLA | AQ10: LA VIRGEN | AR10: CHIMAY | AS10: YANANGO | AT10: HUANCHOR | AU10: MARAÑON | AV10: STA TERESA | AW10: FENIX GT11 | AX10: FENIX GT12 | AY10: FENIX TV10 | AZ10: YAUPI | BA10: OROYA | BB10: PACHACHACA | BC10: MALPASO | BD10: CAHUA | BE10: ARCATA | BF10: GALLITO CIEGO | BG10: CHEVES | BH10: HUANZA | BI10: MALACAS2 TG4 | BJ10: MALACAS3 TG 5 | BK10: MALACAS1 TG6 | BL10: RF ILO2 TG1 | BM10: RF ILO2 TG2 | BN10: RF ILO2 TG3 | BO10: YUNCAN | BP10: CHILCA1 TG1 | BQ10: CHILCA1 TG2 | BR10: CHILCA1 TG3 | BS10: CHILCA-TV | BT10: CHILCA2 TG41 | BU10: CHILCA2-TV | BV10: CTNEPI_TG41 | BW10: CTNEPI_TG42 | BX10: CTNEPI_TG43 | BY10: QUITARACSA | BZ10: RF PTO MALDONADO | CA10: RF PUCALLPA | CB10: PARIAC | CC10: HUINCO | CD10: MATUCANA | CE10: MOYOPAMPA | CF10: CALLAHUANCA | CG10: HUAMPANI | CH10: STA ROSA WEST TG7 | CI10: UTI_5 | CJ10: UTI_6 | CK10: VENTANILLA 3 | CL10: VENTANILLA 4 | CM10: VENTANILLA TV | CN10: STAROSA TG8 | CO10: PTO_BRVO TG1 | CP10: PTO_BRVO TG2 | CQ10: PTO_BRVO TG3 | CR10: PTO_BRVO TG4 | CS10: OLLEROS TG1 | CT10: OLLEROS TV | CU10: CS YARUCAYA | CV10: SAN JUAN | CW10: MATARANI | CX10: DUNA | CY10: SAN MARTIN SOLAR | CZ10: CARHUAQUERO (CS) | DA10: MANTA I | DB10: CARHUAQUERO4 | DC10: CAÑA BRAVA | DD10: TUPURI | DE10: RONCADOR | DF10: CANCHAYLLO | DG10: RENOVANDESH1 | DH10: POTRERO | DI10: PIZARRAS | DJ10: NIMPERIAL | DK10: YARUCAYA | DL10: MOQUEGUA-SOLAR | DM10: PANAMERICANA-SOLAR | DN10: PQE-EOLICO-MARCONA | DO10: PQE-EOLICO-3-HERMANAS | DP10: HUAYCOLORO | DQ10: CALLAO | DR10: DONA_CATALINA | DS10: LAGRINGAV | DT10: TACNA-SOLAR | DU10: YANAPAMPA | DV10: CARHUAC | DW10: HUALLIN | DX10: PURMACANA | DY10: HUASAHUASI | DZ10: STACRUZ_1_2 | EA10: RUNATULLO_II | EB10: RUNATULLO_III | EC10: RUCUY | ED10: PQE-EOLICO-TALARA | EE10: PQE-EOLICO-CUPISNIQUE | EF10: INTIPAMPA | EG10: PUNTA LOMITAS-BL1 | EH10: PUNTA LOMITAS-BL2 | EI10: PUN LOMITAS_EXP-BL1 | EJ10: PUN LOMITAS_EXP-BL2 | EK10: 8AGOSTO | EL10: EL CARMEN | EM10: LA JOYA | EN10: ANGEL_I | EO10: ANGEL_II | EP10: ANGEL_III | EQ10: HUAMBOS | ER10: MAJES | ES10: RUBI | ET10: CH_HER1 | EU10: WAYRA-I | EV10: WAYRA EXTENSION | EW10: CLEMESI | EX10: REPARTICION | EY10: POECHOS2 | EZ10: CHANCAY | FA10: CANA BRAVA | FB10: REFINERIA TALARA TV1 | FC10: REFINERÍA TALARA TV2 | FD10: OQUENDO TG1 | FE10: OQUENDO TV1 | FF10: PARAMONGA | FG10: MAPLE | FH10: SAN_JACINTO | FI10: MW | FK10: CARPAPATA | FL10: CENTRALES ELOR | FM10: PIAS1 | FN10: ZANA | FO10: TABLAZO | FP10: TALLANCA | FQ10: CURUMUY | FR10: POECHOS1 | FS10: MW
A11: 09/04/2025 | B11: 00:30 | E11: 550.2 | F11: 178.7 | I11: 90.9 | J11: 239.3 | M11: 105.4 | N11: 105.5 | O11: 105.4 | P11: 208.2 | Q11: 108.7 | R11: 66.9 | S11: 562.7 | T11: 10.6 | Y11: 166.5 | Z11: 8.3 | AA11: 3.7 | AB11: 0 | AC11: 6.5 | AD11: 10.1 | AE11: 143.3 | AF11: 8.9 | AJ11: 111 | AK11: 214 | AO11: 6.5 | AP11: 335.8 | AQ11: 5 | AR11: 149.6 | AS11: 42.4 | AT11: 18.5 | AU11: 19.7 | AV11: 89.6 | AZ11: 65.6 | BA11: 0 | BB11: 9.2 | BC11: 46.3 | BD11: 42.5 | BE11: 3.8 | BF11: 36.6 | BG11: 169.2 | BH11: 94.9 | BK11: 0 | BO11: 86.7 | BP11: 0 | BR11: 139.1 | BS11: 67.8 | BT11: 0 | CB11: 4.6 | CC11: 267.6 | CD11: 133.3 | CE11: 63.3 | CF11: 79.4 | CG11: 30.2 | CK11: 102.7 | CL11: 102.5 | CM11: 118.2 | CS11: 191.8 | CT11: 102.9 | CU11: 0 | CV11: 81.5 | CW11: 0 | CX11: 10.2 | CZ11: 0 | DA11: 20 | DB11: 10.5 | DC11: 5.4 | DD11: 1.2 | DE11: 1.7 | DF11: 4.9 | DG11: 20.2 | DH11: 20 | DI11: 18.8 | DJ11: 3.5 | DK11: 9.3 | DL11: 0 | DM11: 0 | DN11: 26.2 | DO11: 51.6 | DP11: 4.4 | DQ11: 2.4 | DR11: 2.4 | DT11: 0 | DU11: 2.9 | DV11: 20.2 | DW11: 3 | DY11: 17.4 | DZ11: 9.8 | EA11: 20.3 | EB11: 20.3 | EC11: 20 | ED11: 13.6 | EE11: 35.1 | EF11: 0 | EG11: 30.7 | EH11: 74.6 | EI11: 2.1 | EJ11: 1.6 | EK11: 21 | EL11: 6.9 | EM11: 7.4 | EN11: 20.4 | EO11: 20.4 | EP11: 20.2 | EQ11: 7.3 | ER11: 0 | ES11: 0 | ET11: 0.6 | EU11: 74 | EV11: 58.3 | EW11: 0 | EX11: 0 | EY11: 7.9 | EZ11: 20 | FB11: 43.7 | FC11: 0 | FD11: 29 | FE11: 3.3 | FF11: 16.4 | FI11: 6552.7 | FK11: 24.4391 | FL11: 7.895 | FN11: 13.2 | FP11: 9.44018 | FQ11: 10.5 | FR11: 15.1 | FS11: 80.57428
A12: 09/04/2025 | B12: 01:00 | E12: 546.4 | F12: 179.7 | I12: 90 | J12: 236.9 | M12: 105.9 | N12: 104.3 | O12: 106 | P12: 206.7 | Q12: 108.2 | R12: 66.9 | S12: 552.3 | T12: 10.5 | Y12: 164.2 | Z12: 8.1 | AA12: 3.5 | AB12: 0 | AC12: 6.5 | AD12: 10.1 | AE12: 142.7 | AF12: 8.9 | AJ12: 111 | AK12: 185.4 | AO12: 6.5 | AP12: 296.5 | AQ12: 5 | AR12: 133.3 | AS12: 42.4 | AT12: 18.5 | AU12: 19.7 | AV12: 90.7 | AZ12: 64.6 | BA12: 0 | BB12: 9.2 | BC12: 45.2 | BD12: 42.1 | BE12: 3.8 | BF12: 35.8 | BG12: 168.4 | BH12: 94.4 | BK12: 0 | BO12: 86.6 | BP12: 0 | BR12: 139.4 | BS12: 67.8 | BT12: 0 | CB12: 4.6 | CC12: 227.9 | CD12: 120.5 | CE12: 63.1 | CF12: 77.3 | CG12: 30.2 | CK12: 102.4 | CL12: 102.1 | CM12: 118.6 | CS12: 191.8 | CT12: 103 | CU12: 0 | CV12: 87.9 | CW12: 0 | CX12: 9.1 | CZ12: 0 | DA12: 20 | DB12: 10.4 | DC12: 5.4 | DD12: 1.2 | DE12: 1.7 | DF12: 4.8 | DG12: 20.2 | DH12: 20 | DI12: 18.8 | DJ12: 3.6 | DK12: 9.3 | DL12: 0 | DM12: 0 | DN12: 26.2 | DO12: 57.9 | DP12: 4.4 | DQ12: 2.4 | DR12: 2.4 | DT12: 0 | DU12: 2.9 | DV12: 20.3 | DW12: 3 | DY12: 17.5 | DZ12: 9.8 | EA12: 20.1 | EB12: 20.3 | EC12: 20 | ED12: 18.6 | EE12: 34.7 | EF12: 0 | EG12: 33.6 | EH12: 66.5 | EI12: 2.9 | EJ12: 2.4 | EK12: 21 | EL12: 6.9 | EM12: 7.4 | EN12: 20.4 | EO12: 20.4 | EP12: 20.2 | EQ12: 6.2 | ER12: 0 | ES12: 0 | ET12: 0.6 | EU12: 37.7 | EV12: 26.1 | EW12: 0 | EX12: 0 | EY12: 7.8 | EZ12: 20 | FB12: 43.9 | FC12: 0 | FD12: 29 | FE12: 3.2 | FF12: 16.5 | FI12: 6331.2 | FK12: 24.43857 | FL12: 7.884 | FN12: 13.2 | FP12: 9.43985 | FQ12: 10.4 | FR12: 15.1 | FS12: 80.46242
A13: 09/04/2025 | B13: 01:30 | E13: 548.5 | F13: 178.4 | I13: 91.7 | J13: 237.4 | M13: 107.2 | N13: 107.1 | O13: 105.6 | P13: 209 | Q13: 109.7 | R13: 66.6 | S13: 561.4 | T13: 10.5 | Y13: 167 | Z13: 7.5 | AA13: 3.4 | AB13: 0 | AC13: 6.5 | AD13: 10.1 | AE13: 143.1 | AF13: 8.9 | AJ13: 110.5 | AK13: 154.3 | AO13: 6.5 | AP13: 296.1 | AQ13: 5 | AR13: 137.2 | AS13: 42.4 | AT13: 18.5 | AU13: 19.7 | AV13: 92.2 | AZ13: 66.3 | BA13: 0 | BB13: 9.2 | BC13: 46.5 | BD13: 41.9 | BE13: 3.8 | BF13: 36.9 | BG13: 167.2 | BH13: 95.4 | BK13: 0 | BO13: 86.2 | BP13: 0 | BR13: 140.3 | BS13: 67.2 | BT13: 0 | CB13: 4.6 | CC13: 216.4 | CD13: 121.2 | CE13: 62.8 | CF13: 77.7 | CG13: 30.2 | CK13: 103.9 | CL13: 103.6 | CM13: 118.8 | CS13: 191.8 | CT13: 103 | CU13: 0 | CV13: 90.5 | CW13: 0 | CX13: 13.7 | CZ13: 0 | DA13: 19.9 | DB13: 10.6 | DC13: 5.4 | DD13: 1.2 | DE13: 1.7 | DF13: 4.8 | DG13: 20.1 | DH13: 20 | DI13: 18.8 | DJ13: 3.5 | DK13: 9.3 | DL13: 0 | DM13: 0 | DN13: 25.1 | DO13: 61.5 | DP13: 4.4 | DQ13: 2.4 | DR13: 2.4 | DT13: 0 | DU13: 3 | DV13: 20.3 | DW13: 3 | DY13: 17.4 | DZ13: 9.7 | EA13: 20.1 | EB13: 20.3 | EC13: 19.9 | ED13: 18.8 | EE13: 33.4 | EF13: 0 | EG13: 32.4 | EH13: 65 | EI13: 3.1 | EJ13: 3 | EK13: 21 | EL13: 6.9 | EM13: 7.4 | EN13: 20.4 | EO13: 20.4 | EP13: 20.2 | EQ13: 11.3 | ER13: 0 | ES13: 0 | ET13: 0.6 | EU13: 15.4 | EV13: 10.2 | EW13: 0 | EX13: 0 | EY13: 7.8 | EZ13: 20 | FB13: 44.1 | FC13: 0 | FD13: 29 | FE13: 3.2 | FF13: 16.6 | FI13: 6296.1 | FK13: 24.43701 | FL13: 1.689 | FN13: 13.2 | FP13: 9.43948 | FQ13: 10.5 | FR13: 15 | FS13: 74.26549
A14: 09/04/2025 | B14: 02:00 | E14: 535.2 | F14: 177.9 | I14: 88.8 | J14: 234 | M14: 105.9 | N14: 105.3 | O14: 105.6 | P14: 208 | Q14: 109.1 | R14: 67.1 | S14: 540.3 | T14: 10.3 | Y14: 161.8 | Z14: 6.7 | AA14: 3 | AB14: 0 | AC14: 6.5 | AD14: 10.1 | AE14: 141.3 | AF14: 9 | AJ14: 108.9 | AK14: 166.3 | AO14: 6.5 | AP14: 288.6 | AQ14: 5 | AR14: 120.3 | AS14: 42.2 | AT14: 18.5 | AU14: 19.7 | AV14: 86.1 | AZ14: 63.1 | BA14: 0 | BB14: 9.2 | BC14: 44.4 | BD14: 41.6 | BE14: 3.8 | BF14: 34.5 | BG14: 164 | BH14: 93 | BK14: 0 | BO14: 85.1 | BP14: 0 | BR14: 139.5 | BS14: 67.2 | BT14: 0 | CB14: 4.6 | CC14: 162.5 | CD14: 106.4 | CE14: 61.2 | CF14: 76.6 | CG14: 29.4 | CK14: 102.7 | CL14: 101.9 | CM14: 118.8 | CS14: 191.8 | CT14: 102.9 | CU14: 0 | CV14: 90.7 | CW14: 0 | CX14: 15.4 | CZ14: 0 | DA14: 20 | DB14: 10.4 | DC14: 5.3 | DD14: 1.2 | DE14: 1.7 | DF14: 4.8 | DG14: 19.8 | DH14: 20 | DI14: 18.8 | DJ14: 3.6 | DK14: 9.3 | DL14: 0 | DM14: 0 | DN14: 23.5 | DO14: 64.3 | DP14: 4.4 | DQ14: 2.4 | DR14: 2.4 | DT14: 0 | DU14: 2.8 | DV14: 20.3 | DW14: 3 | DY14: 17.4 | DZ14: 9.8 | EA14: 20.1 | EB14: 20.2 | EC14: 19.9 | ED14: 20.7 | EE14: 27.9 | EF14: 0 | EG14: 47.4 | EH14: 87.7 | EI14: 5.9 | EJ14: 1.7 | EK14: 21 | EL14: 6.8 | EM14: 7.4 | EN14: 20.4 | EO14: 20.4 | EP14: 20.2 | EQ14: 13.2 | ER14: 0 | ES14: 0 | ET14: 0.6 | EU14: 5.1 | EV14: 4.9 | EW14: 0 | EX14: 0 | EY14: 7.9 | EZ14: 20 | FB14: 44.8 | FC14: 0 | FD14: 29 | FE14: 3.1 | FF14: 16.7 | FI14: 6156.5 | FK14: 24.43744 | FL14: 0 | FN14: 13.2 | FP14: 9.43905 | FQ14: 10.4 | FR14: 15.1 | FS14: 72.57649
A15: 09/04/2025 | B15: 02:30 | E15: 445.1 | F15: 146.1 | I15: 89.6 | J15: 236.1 | M15: 105.8 | N15: 105.1 | O15: 105.5 | P15: 207.3 | Q15: 109 | R15: 67.2 | S15: 557 | T15: 10.5 | Y15: 164.8 | Z15: 7.2 | AA15: 3.2 | AB15: 0 | AC15: 6.4 | AD15: 10.1 | AE15: 142.8 | AF15: 8.9 | AJ15: 110.3 | AK15: 199.5 | AO15: 6.5 | AP15: 308.7 | AQ15: 5 | AR15: 137.5 | AS15: 42.4 | AT15: 18.5 | AU15: 19.7 | AV15: 88.2 | AZ15: 31.9 | BA15: 0 | BB15: 9.2 | BC15: 45.2 | BD15: 41.9 | BE15: 3.8 | BF15: 35.3 | BG15: 166.5 | BH15: 94 | BK15: 0 | BO15: 86 | BP15: 0 | BR15: 139 | BS15: 68.1 | BT15: 0 | CB15: 4.6 | CC15: 193.4 | CD15: 122 | CE15: 63.5 | CF15: 77.3 | CG15: 29.9 | CK15: 102.2 | CL15: 103 | CM15: 118.3 | CS15: 191.7 | CT15: 102.8 | CU15: 0 | CV15: 84.5 | CW15: 0 | CX15: 13.5 | CZ15: 0 | DA15: 20 | DB15: 10.4 | DC15: 5.4 | DD15: 1.2 | DE15: 1.7 | DF15: 4.9 | DG15: 20 | DH15: 20 | DI15: 18.8 | DJ15: 3.6 | DK15: 9.3 | DL15: 0 | DM15: 0 | DN15: 23.2 | DO15: 63.6 | DP15: 4.4 | DQ15: 2.4 | DR15: 2.4 | DT15: 0 | DU15: 2.7 | DV15: 20.3 | DW15: 3 | DY15: 17.4 | DZ15: 9.8 | EA15: 19.9 | EB15: 20.2 | EC15: 20 | ED15: 19.6 | EE15: 24.5 | EF15: 0 | EG15: 64.2 | EH15: 90.4 | EI15: 7.8 | EJ15: 3.6 | EK15: 21 | EL15: 6.8 | EM15: 7.3 | EN15: 20.4 | EO15: 20.4 | EP15: 20.2 | EQ15: 12.6 | ER15: 0 | ES15: 0 | ET15: 0.6 | EU15: 2.7 | EV15: 2.8 | EW15: 0 | EX15: 0 | EY15: 8 | EZ15: 20 | FB15: 44.2 | FC15: 0 | FD15: 29 | FE15: 3.3 | FF15: 16.6 | FI15: 6162.2 | FK15: 24.4373 | FL15: 0 | FN15: 13.2 | FP15: 9.4385 | FQ15: 10.5 | FR15: 15.1 | FS15: 72.6758
A16: 09/04/2025 | B16: 03:00 | E16: 450.4 | F16: 144.2 | I16: 90.5 | J16: 237.2 | M16: 105.9 | N16: 105.6 | O16: 105.4 | P16: 209 | Q16: 108.7 | R16: 67.1 | S16: 564.5 | T16: 10.6 | Y16: 167.2 | Z16: 7.6 | AA16: 3.3 | AB16: 0 | AC16: 6.5 | AD16: 10.1 | AE16: 143.6 | AF16: 9 | AJ16: 111.1 | AK16: 181.5 | AO16: 6.5 | AP16: 317.2 | AQ16: 5 | AR16: 137.8 | AS16: 42.3 | AT16: 18.5 | AU16: 19.7 | AV16: 90.6 | AZ16: 32.7 | BA16: 0 | BB16: 9.2 | BC16: 45.5 | BD16: 42.5 | BE16: 3.8 | BF16: 35.6 | BG16: 168.1 | BH16: 94.6 | BK16: 0 | BO16: 86.9 | BP16: 0 | BR16: 139.8 | BS16: 66.6 | BT16: 0 | CB16: 4.6 | CC16: 190.9 | CD16: 123.5 | CE16: 64 | CF16: 77.3 | CG16: 30.2 | CK16: 101.9 | CL16: 103.5 | CM16: 118.8 | CS16: 191.6 | CT16: 102.8 | CU16: 0 | CV16: 75.5 | CW16: 0 | CX16: 13.3 | CZ16: 0 | DA16: 20 | DB16: 10.4 | DC16: 5.5 | DD16: 1.2 | DE16: 1.7 | DF16: 4.8 | DG16: 20.1 | DH16: 20 | DI16: 18.8 | DJ16: 3.6 | DK16: 9.3 | DL16: 0 | DM16: 0 | DN16: 19.9 | DO16: 55.1 | DP16: 4.4 | DQ16: 2.4 | DR16: 2.4 | DT16: 0 | DU16: 2.7 | DV16: 20.3 | DW16: 3 | DY16: 17.4 | DZ16: 9.8 | EA16: 19.9 | EB16: 20.3 | EC16: 19.9 | ED16: 24.7 | EE16: 26 | EF16: 0 | EG16: 55.6 | EH16: 71.9 | EI16: 7.3 | EJ16: 2.3 | EK16: 21 | EL16: 6.8 | EM16: 7.2 | EN16: 20.4 | EO16: 20.4 | EP16: 20.2 | EQ16: 11 | ER16: 0 | ES16: 0 | ET16: 0.6 | EU16: 18.2 | EV16: 20.5 | EW16: 0 | EX16: 0 | EY16: 7.9 | EZ16: 20 | FB16: 43.7 | FC16: 0 | FD16: 29 | FE16: 3.3 | FF16: 16.5 | FI16: 6167.2 | FK16: 24.43606 | FL16: 0 | FN16: 13.2 | FP16: 9.43817 | FQ16: 10.3 | FR16: 15.2 | FS16: 72.57423
A17: 09/04/2025 | B17: 03:30 | E17: 450.5 | F17: 144 | I17: 89.5 | J17: 238.9 | M17: 106 | N17: 105.7 | O17: 105.1 | P17: 207.7 | Q17: 110.2 | R17: 67 | S17: 560.5 | T17: 10.6 | Y17: 167.3 | Z17: 7.8 | AA17: 3.3 | AB17: 0 | AC17: 6.4 | AD17: 10.1 | AE17: 142.9 | AF17: 8.9 | AJ17: 111.1 | AK17: 184.8 | AO17: 6.5 | AP17: 297.1 | AQ17: 5 | AR17: 137 | AS17: 42.4 | AT17: 18.5 | AU17: 19.7 | AV17: 90.1 | AZ17: 32.8 | BA17: 0 | BB17: 9.2 | BC17: 45.7 | BD17: 42 | BE17: 3.8 | BF17: 35.5 | BG17: 169.3 | BH17: 94.8 | BK17: 0 | BO17: 86.7 | BP17: 0 | BR17: 139.1 | BS17: 67.2 | BT17: 0 | CB17: 4.6 | CC17: 201.9 | CD17: 122.6 | CE17: 63.5 | CF17: 77.6 | CG17: 30.3 | CK17: 103 | CL17: 102.3 | CM17: 118.3 | CS17: 191.5 | CT17: 102.8 | CU17: 0 | CV17: 71.2 | CW17: 0 | CX17: 12 | CZ17: 0 | DA17: 20 | DB17: 10.4 | DC17: 5.5 | DD17: 1.2 | DE17: 1.7 | DF17: 4.8 | DG17: 20.5 | DH17: 20 | DI17: 18.8 | DJ17: 3.5 | DK17: 9.3 | DL17: 0 | DM17: 0 | DN17: 17 | DO17: 46.4 | DP17: 4.4 | DQ17: 2.4 | DR17: 2.4 | DT17: 0 | DU17: 2.6 | DV17: 20.3 | DW17: 3 | DY17: 17.2 | DZ17: 9.8 | EA17: 19.8 | EB17: 20.3 | EC17: 19.9 | ED17: 29 | EE17: 25.7 | EF17: 0 | EG17: 49.9 | EH17: 72.3 | EI17: 5 | EJ17: 1.8 | EK17: 21 | EL17: 6.8 | EM17: 7.2 | EN17: 20.4 | EO17: 20.4 | EP17: 20.2 | EQ17: 10.3 | ER17: 0 | ES17: 0 | ET17: 0.6 | EU17: 20.6 | EV17: 16.8 | EW17: 0 | EX17: 0 | EY17: 7.8 | EZ17: 20 | FB17: 44 | FC17: 0 | FD17: 29 | FE17: 3.3 | FF17: 16.6 | FI17: 6132.2 | FK17: 24.43323 | FL17: 0 | FN17: 13.2 | FP17: 9.43783 | FQ17: 10.5 | FR17: 15.1 | FS17: 72.67106
A18: 09/04/2025 | B18: 04:00 | E18: 441.2 | F18: 144.2 | I18: 89.2 | J18: 235.2 | M18: 105.8 | N18: 105.6 | O18: 105.7 | P18: 208.7 | Q18: 108.8 | R18: 67.2 | S18: 552 | T18: 10.3 | Y18: 157.3 | Z18: 7 | AA18: 3.1 | AB18: 0 | AC18: 6.4 | AD18: 10.1 | AE18: 142.8 | AF18: 9 | AJ18: 109.4 | AK18: 185.3 | AO18: 6.5 | AP18: 293.5 | AQ18: 5 | AR18: 138.3 | AS18: 42.3 | AT18: 18.5 | AU18: 19.7 | AV18: 90.6 | AZ18: 31.3 | BA18: 0 | BB18: 9.2 | BC18: 44.6 | BD18: 43.6 | BE18: 3.8 | BF18: 35 | BG18: 164.2 | BH18: 93.4 | BK18: 0 | BO18: 85.8 | BP18: 0 | BR18: 139.9 | BS18: 68.2 | BT18: 0 | CB18: 4.6 | CC18: 173.6 | CD18: 112.9 | CE18: 62 | CF18: 76.9 | CG18: 29.3 | CK18: 102.1 | CL18: 103.5 | CM18: 119.1 | CS18: 191.5 | CT18: 102.7 | CU18: 0 | CV18: 70.6 | CW18: 0 | CX18: 13.1 | CZ18: 0 | DA18: 20 | DB18: 10.4 | DC18: 5.4 | DD18: 1.2 | DE18: 1.7 | DF18: 4.8 | DG18: 19.8 | DH18: 20 | DI18: 18.8 | DJ18: 3.6 | DK18: 9.3 | DL18: 0 | DM18: 0 | DN18: 13.1 | DO18: 37.3 | DP18: 4.4 | DQ18: 2.4 | DR18: 2.4 | DT18: 0 | DU18: 2.9 | DV18: 20.3 | DW18: 3 | DY18: 17.3 | DZ18: 9.8 | EA18: 19.7 | EB18: 20.2 | EC18: 20 | ED18: 29 | EE18: 23.4 | EF18: 0 | EG18: 44.7 | EH18: 65.8 | EI18: 6.9 | EJ18: 2.9 | EK18: 21 | EL18: 6.8 | EM18: 7.2 | EN18: 20.4 | EO18: 20.4 | EP18: 20.2 | EQ18: 11.4 | ER18: 0 | ES18: 0 | ET18: 0.6 | EU18: 23.3 | EV18: 17.7 | EW18: 0 | EX18: 0 | EY18: 7.9 | EZ18: 20 | FB18: 43.9 | FC18: 0 | FD18: 29.1 | FE18: 3.1 | FF18: 16.5 | FI18: 6029.6 | FK18: 24.43398 | FL18: 0 | FN18: 13.2 | FP18: 9.43743 | FQ18: 10.5 | FR18: 15.1 | FS18: 72.67141
A19: 09/04/2025 | B19: 04:30 | E19: 449.3 | F19: 145.9 | I19: 90.2 | J19: 236.6 | M19: 106.1 | N19: 106.2 | O19: 106.5 | P19: 207.3 | Q19: 107.8 | R19: 67.1 | S19: 560.6 | T19: 0 | Y19: 164.4 | Z19: 7.6 | AA19: 3.4 | AB19: 0 | AC19: 6.4 | AD19: 10.1 | AE19: 143.5 | AF19: 9 | AJ19: 111 | AK19: 222.2 | AO19: 6.5 | AP19: 336.5 | AQ19: 5 | AR19: 149.2 | AS19: 42.4 | AT19: 18.5 | AU19: 19.7 | AV19: 91 | AZ19: 32.4 | BA19: 0 | BB19: 9 | BC19: 45.7 | BD19: 44.1 | BE19: 3.8 | BF19: 35.4 | BG19: 168.7 | BH19: 94.6 | BK19: 0 | BO19: 86.5 | BP19: 0 | BR19: 139.5 | BS19: 67.3 | BT19: 0 | CB19: 4.6 | CC19: 235.8 | CD19: 132.8 | CE19: 63.3 | CF19: 77.4 | CG19: 30.1 | CK19: 102.8 | CL19: 103 | CM19: 118.8 | CS19: 191.6 | CT19: 102.8 | CU19: 0 | CV19: 71.9 | CW19: 0 | CX19: 10.8 | CZ19: 0 | DA19: 20 | DB19: 10.5 | DC19: 5.5 | DD19: 1.2 | DE19: 1.7 | DF19: 4.7 | DG19: 20.3 | DH19: 20 | DI19: 18.8 | DJ19: 3.6 | DK19: 9.3 | DL19: 0 | DM19: 0 | DN19: 13.1 | DO19: 35.5 | DP19: 4.4 | DQ19: 2.4 | DR19: 2.4 | DT19: 0 | DU19: 2.9 | DV19: 20.3 | DW19: 3 | DY19: 17.3 | DZ19: 9.8 | EA19: 19.8 | EB19: 20.3 | EC19: 20 | ED19: 24.5 | EE19: 29.8 | EF19: 0 | EG19: 22.6 | EH19: 45.3 | EI19: 2.5 | EJ19: 1.6 | EK19: 21 | EL19: 6.8 | EM19: 7.2 | EN19: 20.4 | EO19: 20.4 | EP19: 20.2 | EQ19: 9.4 | ER19: 0 | ES19: 0 | ET19: 0.6 | EU19: 21.9 | EV19: 19 | EW19: 0 | EX19: 0 | EY19: 7.9 | EZ19: 20 | FB19: 44.5 | FC19: 0 | FD19: 29.1 | FE19: 3.2 | FF19: 16.5 | FI19: 6183.9 | FK19: 24.43453 | FL19: 0 | FN19: 13.2 | FP19: 9.43724 | FQ19: 10.5 | FR19: 15.1 | FS19: 72.67177
A20: 09/04/2025 | B20: 05:00 | E20: 515.2 | F20: 166.5 | I20: 89.1 | J20: 236.9 | M20: 106 | N20: 106.1 | O20: 106.3 | P20: 207.1 | Q20: 109.4 | R20: 67 | S20: 556.5 | T20: 0 | Y20: 166 | Z20: 7.3 | AA20: 3.3 | AB20: 0 | AC20: 6.4 | AD20: 10.1 | AE20: 142.6 | AF20: 9 | AJ20: 110.5 | AK20: 217.7 | AO20: 6.5 | AP20: 300.5 | AQ20: 5 | AR20: 142.4 | AS20: 42.3 | AT20: 18.5 | AU20: 19.7 | AV20: 87.8 | AZ20: 32.1 | BA20: 0 | BB20: 9.2 | BC20: 45.7 | BD20: 44 | BE20: 3.8 | BF20: 34.9 | BG20: 167.1 | BH20: 94.2 | BK20: 0 | BO20: 86 | BP20: 0 | BR20: 139.7 | BS20: 68 | BT20: 0 | CB20: 4.6 | CC20: 222.1 | CD20: 126.4 | CE20: 62.8 | CF20: 77.4 | CG20: 30 | CK20: 103.1 | CL20: 102.2 | CM20: 118.6 | CS20: 191.4 | CT20: 102.6 | CU20: 0 | CV20: 71.1 | CW20: 0 | CX20: 12.4 | CZ20: 0 | DA20: 20.1 | DB20: 10.5 | DC20: 5.4 | DD20: 1.2 | DE20: 1.7 | DF20: 4.7 | DG20: 20.2 | DH20: 20 | DI20: 18.8 | DJ20: 3.6 | DK20: 9.3 | DL20: 0 | DM20: 0 | DN20: 18 | DO20: 35.4 | DP20: 4.4 | DQ20: 2.4 | DR20: 2.4 | DT20: 0 | DU20: 3.1 | DV20: 20.3 | DW20: 3 | DY20: 17.3 | DZ20: 9.7 | EA20: 19.7 | EB20: 20.3 | EC20: 20 | ED20: 23.2 | EE20: 31.9 | EF20: 0 | EG20: 16.7 | EH20: 42.2 | EI20: 0.8 | EJ20: 0.3 | EK20: 21 | EL20: 6.8 | EM20: 7.2 | EN20: 20.4 | EO20: 20.4 | EP20: 20.2 | EQ20: 11 | ER20: 0 | ES20: 0 | ET20: 0.6 | EU20: 19 | EV20: 13.4 | EW20: 0 | EX20: 0 | EY20: 8 | EZ20: 20 | FB20: 44.4 | FC20: 0 | FD20: 29 | FE20: 3.2 | FF20: 16.6 | FI20: 6178.9 | FK20: 24.43507 | FL20: 0 | FN20: 13.2 | FP20: 9.43703 | FQ20: 10.5 | FR20: 15.1 | FS20: 72.6721
A21: 09/04/2025 | B21: 05:30 | E21: 519.9 | F21: 168.9 | I21: 90.3 | J21: 237.7 | M21: 106.8 | N21: 106.3 | O21: 106 | P21: 207 | Q21: 109.6 | R21: 67 | S21: 565.7 | T21: 0 | Y21: 165.2 | Z21: 7.6 | AA21: 3.4 | AB21: 0 | AC21: 6.4 | AD21: 10.1 | AE21: 143.7 | AF21: 8.9 | AJ21: 110.9 | AK21: 219.5 | AO21: 6.5 | AP21: 387 | AQ21: 5.3 | AR21: 149.5 | AS21: 42.3 | AT21: 18.5 | AU21: 19.7 | AV21: 89.5 | AZ21: 64.6 | BA21: 0 | BB21: 9.2 | BC21: 45.6 | BD21: 44.4 | BE21: 3.8 | BF21: 35.7 | BG21: 167.8 | BH21: 94.6 | BK21: 0 | BO21: 86.2 | BP21: 0 | BR21: 139.9 | BS21: 66.1 | BT21: 0 | CB21: 4.6 | CC21: 269.2 | CD21: 132.6 | CE21: 63.3 | CF21: 79.4 | CG21: 30.2 | CK21: 103.1 | CL21: 102 | CM21: 118.8 | CS21: 191.4 | CT21: 102.6 | CU21: 0 | CV21: 63.7 | CW21: 0 | CX21: 12.2 | CZ21: 0 | DA21: 20 | DB21: 10.5 | DC21: 5.4 | DD21: 1.2 | DE21: 1.6 | DF21: 4.6 | DG21: 20.3 | DH21: 20 | DI21: 18.9 | DJ21: 3.6 | DK21: 9.3 | DL21: 0 | DM21: 0 | DN21: 21.2 | DO21: 36.6 | DP21: 4.4 | DQ21: 2.4 | DR21: 2.4 | DT21: 0 | DU21: 2.9 | DV21: 20.4 | DW21: 3 | DY21: 17.3 | DZ21: 9.8 | EA21: 20.2 | EB21: 20.3 | EC21: 20 | ED21: 18.5 | EE21: 18.8 | EF21: 0 | EG21: 16.8 | EH21: 35.9 | EI21: 0.6 | EJ21: 0 | EK21: 21 | EL21: 7.1 | EM21: 7.2 | EN21: 20.4 | EO21: 20.4 | EP21: 20.2 | EQ21: 8.3 | ER21: 0 | ES21: 0 | ET21: 0.6 | EU21: 17.6 | EV21: 11.4 | EW21: 0 | EX21: 0 | EY21: 8.1 | EZ21: 20 | FB21: 44.5 | FC21: 0 | FD21: 29.1 | FE21: 3.3 | FF21: 16.5 | FI21: 6352.8 | FK21: 24.42287 | FL21: 0 | FN21: 13.2 | FP21: 9.4366 | FQ21: 10.5 | FR21: 15.2 | FS21: 72.75947
A22: 09/04/2025 | B22: 06:00 | E22: 642.6 | F22: 205.9 | I22: 90 | J22: 237.5 | M22: 106 | N22: 105.8 | O22: 105.5 | P22: 207.2 | Q22: 108.3 | R22: 67.3 | S22: 557.4 | T22: 0 | Y22: 165 | Z22: 7.3 | AA22: 3.3 | AB22: 0 | AC22: 4.6 | AD22: 10.1 | AE22: 143.1 | AF22: 9 | AJ22: 110.3 | AK22: 220.9 | AO22: 6.4 | AP22: 352.9 | AQ22: 10.3 | AR22: 148.5 | AS22: 42.3 | AT22: 18.5 | AU22: 19.7 | AV22: 92.1 | AZ22: 81.5 | BA22: 0 | BB22: 9.2 | BC22: 45.8 | BD22: 44.1 | BE22: 3.8 | BF22: 36.2 | BG22: 166.2 | BH22: 94 | BK22: 0 | BO22: 86.2 | BP22: 0 | BR22: 139.5 | BS22: 67.4 | BT22: 0 | CB22: 4.6 | CC22: 255.1 | CD22: 131.1 | CE22: 62.7 | CF22: 79.3 | CG22: 29.9 | CK22: 102.6 | CL22: 101.3 | CM22: 118.3 | CS22: 191.6 | CT22: 102.7 | CU22: 0 | CV22: 77.2 | CW22: 0 | CX22: 14.5 | CZ22: 0 | DA22: 20 | DB22: 10.4 | DC22: 5.5 | DD22: 1.2 | DE22: 1.7 | DF22: 4.6 | DG22: 20 | DH22: 20 | DI22: 18.8 | DJ22: 3.6 | DK22: 9.3 | DL22: 1.4 | DM22: 1.4 | DN22: 19.4 | DO22: 42 | DP22: 4.4 | DQ22: 2.4 | DR22: 2.4 | DT22: 0 | DU22: 3 | DV22: 20.2 | DW22: 3 | DY22: 17.3 | DZ22: 9.8 | EA22: 20 | EB22: 20.2 | EC22: 20 | ED22: 21.7 | EE22: 13.1 | EF22: 0 | EG22: 20.1 | EH22: 48.6 | EI22: 1.6 | EJ22: 0 | EK22: 21 | EL22: 7 | EM22: 7.2 | EN22: 20.4 | EO22: 20.4 | EP22: 20.2 | EQ22: 11.5 | ER22: 0 | ES22: 0.8 | ET22: 0.6 | EU22: 7 | EV22: 2.7 | EW22: 0.7 | EX22: 0 | EY22: 8 | EZ22: 20 | FB22: 44 | FC22: 0 | FD22: 29.1 | FE22: 3.3 | FF22: 16.7 | FI22: 6490.3 | FK22: 24.4199 | FL22: 3.105 | FN22: 13.2 | FP22: 9.43637 | FQ22: 10.5 | FR22: 15.2 | FS22: 75.86127
... A58: 10/04/2025 | B58: 00:00 | E58: 642 | F58: 213.7 | I58: 87.2 | J58: 236.8 | M58: 118.7 | N58: 119.1 | O58: 119.2 | P58: 225.9 | Q58: 108.7 | R58: 67.8 | S58: 556.2 | T58: 0 | Y58: 164.2 | Z58: 6.9 | AA58: 3.1 | AB58: 0 | AC58: 6.6 | AD58: 10.1 | AE58: 142.8 | AF58: 9 | AJ58: 109.7 | AK58: 221.1 | AO58: 6.5 | AP58: 459.3 | AQ58: 82 | AR58: 147.4 | AS58: 42.3 | AT58: 18.5 | AU58: 19.7 | AV58: 89.3 | AZ58: 107.4 | BA58: 4.5 | BB58: 9.3 | BC58: 44.6 | BD58: 23.4 | BE58: 3.8 | BF58: 38.2 | BG58: 171.5 | BH58: 94.2 | BK58: 0 | BO58: 85.8 | BP58: 0 | BR58: 139.9 | BS58: 67.3 | BT58: 0 | CB58: 4.6 | CC58: 255.6 | CD58: 128 | CE58: 63 | CF58: 80 | CG58: 29.7 | CK58: 104.4 | CL58: 103 | CM58: 120 | CS58: 0 | CT58: 0 | CU58: 0 | CV58: 59.8 | CW58: 0 | CX58: 0 | CZ58: 0 | DA58: 20 | DB58: 10.4 | DC58: 5.4 | DD58: 1.2 | DE58: 1.5 | DF58: 5 | DG58: 19.9 | DH58: 14.3 | DI58: 18.6 | DJ58: 3.7 | DK58: 9.3 | DL58: 0 | DM58: 0 | DN58: 11.5 | DO58: 32.8 | DP58: 4.4 | DQ58: 2.4 | DR58: 2.4 | DT58: 0 | DU58: 2.8 | DV58: 20.4 | DW58: 2 | DY58: 16.3 | DZ58: 9.9 | EA58: 20.2 | EB58: 20.2 | EC58: 20 | ED58: 2.5 | EE58: 35.1 | EF58: 0 | EG58: 61.4 | EH58: 80.8 | EI58: 4.7 | EJ58: 3.4 | EK58: 21 | EL58: 7.3 | EM58: 8.6 | EN58: 20.4 | EO58: 20.4 | EP58: 20.2 | EQ58: 0 | ER58: 0 | ES58: 0 | ET58: 0.6 | EU58: 46.5 | EV58: 44 | EW58: 0 | EX58: 0 | EY58: 7.9 | EZ58: 20 | FB58: 43.5 | FC58: 16 | FD58: 29 | FE58: 3.2 | FF58: 16.5 | FI58: 6559.4 | FK58: 24.45668 | FL58: 8.069 | FN58: 0 | FP58: 9.44031 | FQ58: 10.5 | FR58: 15.1 | FS58: 67.56599
A59: EJEC | C59: 0 | D59: 0 | E59: 14716.15 | F59: 4891.8 | G59: 0 | H59: 0 | I59: 2129.8 | J59: 5700.85 | K59: 0 | L59: 0 | M59: 3021.95 | N59: 3023.4 | O59: 3023.5 | P59: 5411.45 | Q59: 3776.4 | R59: 2097.7 | S59: 13430.55 | T59: 41.95 | U59: 0 | V59: 0 | W59: 0 | X59: 0 | Y59: 3928.15 | Z59: 181.05 | AA59: 78.7 | AB59: 131.95 | AC59: 154.5 | AD59: 242.45 | AE59: 3197.05 | AF59: 215.15 | AG59: 0 | AH59: 0 | AI59: 0 | AJ59: 2657.35 | AK59: 4963.3 | AL59: 0 | AM59: 0 | AN59: 0 | AO59: 154.7 | AP59: 9951.85 | AQ59: 1495.9 | AR59: 3419.15 | AS59: 1016.6 | AT59: 444.6 | AU59: 472.8 | AV59: 2137.5 | AW59: 0 | AX59: 0 | AY59: 0 | AZ59: 2183 | BA59: 29.7 | BB59: 222.15 | BC59: 1097.35 | BD59: 724.5 | BE59: 91.2 | BF59: 849.65 | BG59: 4125.9 | BH59: 2165.15 | BI59: 0 | BJ59: 0 | BK59: 694.8 | BL59: 0 | BM59: 0 | BN59: 0 | BO59: 2074.6 | BP59: 230 | BQ59: 0 | BR59: 4027.9 | BS59: 1841.3 | BT59: 168.7 | BU59: 0 | BV59: 0 | BW59: 0 | BX59: 0 | BY59: 0 | BZ59: 0 | CA59: 0 | CB59: 110.4 | CC59: 5901.1 | CD59: 3064.65 | CE59: 1524.95 | CF59: 1902.5 | CG59: 725.65 | CH59: 0 | CI59: 0 | CJ59: 0 | CK59: 2946.95 | CL59: 2964.2 | CM59: 3218.45 | CN59: 0 | CO59: 0 | CP59: 0 | CQ59: 0 | CR59: 0 | CS59: 4198.5 | CT59: 2254 | CU59: 7.3 | CV59: 1750.95 | CW59: 692.7 | CX59: 201.25 | CY59: 0 | CZ59: 1.7 | DA59: 480.1 | DB59: 250.1 | DC59: 130.3 | DD59: 29.05 | DE59: 25.4 | DF59: 114.2 | DG59: 485.4 | DH59: 476.75 | DI59: 423.35 | DJ59: 75.9 | DK59: 223.2 | DL59: 134.8 | DM59: 166.55 | DN59: 356.4 | DO59: 1103.4 | DP59: 103.7 | DQ59: 57.6 | DR59: 57.6 | DS59: 0 | DT59: 166.45 | DU59: 65.8 | DV59: 486.95 | DW59: 71.35 | DX59: 0 | DY59: 407.15 | DZ59: 234.05 | EA59: 484.4 | EB59: 486.6 | EC59: 478.95 | ED59: 317.55 | EE59: 796.15 | EF59: 328.5 | EG59: 1026.85 | EH59: 1441.65 | EI59: 138.35 | EJ59: 92.7 | EK59: 504 | EL59: 166.9 | EM59: 185.35 | EN59: 489.6 | EO59: 489.6 | EP59: 484.8 | EQ59: 192.65 | ER59: 131.2 | ES59: 1274.95 | ET59: 14.4 | EU59: 1152 | EV59: 1129.65 | EW59: 946.4 | EX59: 130.65 | EY59: 191.25 | EZ59: 479.8 | FA59: 0 | FB59: 1042.8 | FC59: 115.2 | FD59: 690.45 | FE59: 77.05 | FF59: 397 | FG59: 0 | FH59: 0 | FI59: 170102.35 | FK59: 582.44458 | FL59: 135.6365 | FM59: 0 | FN59: 204.6 | FO59: 0 | FP59: 226.57273 | FQ59: 246.2 | FR59: 362.3 | FS59: 1757.7538

Sheet REACTIVA
B3: miércoles, 9 de Abril del 2025
A5: POTENCIA REACTIVA EJECUTADA DE LAS UNIDADES DE GENERACIÓN DEL COES (MVAR) | FJ5: CENTRALES NO INTEGRANTES COES
A6: FECHA | B6: HORA | C6: 337 | D6: 338 | E6: 101 | F6: 102 | G6: 42667 | H6: 42668 | I6: 126 | J6: 127 | K6: 138 | L6: 139 | M6: 197 | N6: 203 | O6: 204 | P6: 230 | Q6: 209 | R6: 56677 | S6: 796 | T6: 2146 | U6: 142 | V6: 143 | W6: 125 | X6: 187 | Y6: 163 | Z6: 298 | AA6: 219 | AB6: 151 | AC6: 152 | AD6: 153 | AE6: 154 | AF6: 756 | AG6: 156 | AH6: 155 | AI6: 182 | AJ6: 212 | AK6: 758 | AL6: 263 | AM6: 265 | AN6: 775 | AO6: 777 | AP6: 2154 | AQ6: 150 | AR6: 149 | AS6: 188 | AT6: 2131 | AU6: 755 | AV6: 252 | AW6: 249 | AX6: 250 | AY6: 117 | AZ6: 267 | BA6: 268 | BB6: 119 | BC6: 120 | BD6: 189 | BE6: 122 | BF6: 266 | BG6: 251 | BH6: 115 | BI6: 239 | BJ6: 288 | BK6: 240 | BL6: 241 | BM6: 242 | BN6: 191 | BO6: 194 | BP6: 196 | BQ6: 207 | BR6: 236 | BS6: 795 | BT6: 285 | BU6: 995 | BV6: 996 | BW6: 997 | BX6: 766 | BY6: 926 | BZ6: 924 | CA6: 121 | CB6: 103 | CC6: 104 | CD6: 106 | CE6: 105 | CF6: 107 | CG6: 110 | CH6: 109 | CI6: 144 | CJ6: 113 | CK6: 114 | CL6: 193 | CM6: 208 | CN6: 786 | CO6: 787 | CP6: 788 | CQ6: 789 | CR6: 248 | CS6: 2159 | CT6: 303 | CU6: 59715 | CV6: 62255 | CW6: 1263 | CX6: 63425 | CY6: 61800 | CZ6: 2194 | DA6: 216 | DB6: 198 | DC6: 49607 | DD6: 214 | DE6: 260 | DF6: 2152 | DG6: 2128 | DH6: 247 | DI6: 228 | DJ6: 2135 | DK6: 261 | DL6: 237 | DM6: 253 | DN6: 770 | DO6: 225 | DP6: 2201 | DQ6: 2171 | DR6: 760 | DS6: 235 | DT6: 238 | DU6: 2184 | DV6: 61855 | DW6: 223 | DX6: 226 | DY6: 201 | DZ6: 258 | EA6: 259 | EB6: 920 | EC6: 257 | ED6: 256 | EE6: 2148 | EF6: 58288 | EG6: 58289 | EH6: 58839 | EI6: 58840 | EJ6: 296 | EK6: 297 | EL6: 211 | EM6: 2175 | EN6: 2178 | EO6: 2181 | EP6: 1262 | EQ6: 233 | ER6: 2150 | ES6: 2165 | ET6: 2161 | EU6: 61197 | EV6: 58851 | EW6: 234 | EX6: 215 | EY6: 917 | EZ6: 289 | FA6: 58333 | FB6: 58336 | FC6: 202 | FD6: 58487 | FE6: 213 | FF6: 232 | FG6: 2190 | FH6: TOTAL COES | FJ6: 221 | FK6: 222 | FL6: 224 | FM6: 2187 | FN6: 227 | FO6: 49400 | FP6: 199 | FQ6: 200 | FR6: TOTAL NO COES
C7: CENTRO | D7: CENTRO | E7: CENTRO | F7: CENTRO | G7: NORTE | H7: NORTE | I7: NORTE | J7: NORTE | K7: CENTRO | L7: CENTRO | M7: CENTRO | N7: CENTRO | O7: CENTRO | P7: CENTRO | Q7: CENTRO | R7: CENTRO | S7: CENTRO | T7: CENTRO | U7: CENTRO | V7: CENTRO | W7: CENTRO | X7: CENTRO | Y7: SUR | Z7: SUR | AA7: CENTRO | AB7: SUR | AC7: SUR | AD7: SUR | AE7: SUR | AF7: SUR | AG7: SUR | AH7: SUR | AI7: SUR | AJ7: CENTRO | AK7: NORTE | AL7: NORTE | AM7: NORTE | AN7: CENTRO | AO7: CENTRO | AP7: CENTRO | AQ7: CENTRO | AR7: CENTRO | AS7: CENTRO | AT7: CENTRO | AU7: SUR | AV7: CENTRO | AW7: CENTRO | AX7: CENTRO | AY7: CENTRO | AZ7: CENTRO | BA7: CENTRO | BB7: CENTRO | BC7: CENTRO | BD7: SUR | BE7: NORTE | BF7: CENTRO | BG7: CENTRO | BH7: NORTE | BI7: NORTE | BJ7: NORTE | BK7: SUR | BL7: SUR | BM7: SUR | BN7: CENTRO | BO7: CENTRO | BP7: CENTRO | BQ7: CENTRO | BR7: CENTRO | BS7: CENTRO | BT7: CENTRO | BU7: SUR | BV7: SUR | BW7: SUR | BX7: NORTE | BY7: SUR | BZ7: CENTRO | CA7: NORTE | CB7: CENTRO | CC7: CENTRO | CD7: CENTRO | CE7: CENTRO | CF7: CENTRO | CG7: CENTRO | CH7: CENTRO | CI7: CENTRO | CJ7: CENTRO | CK7: CENTRO | CL7: CENTRO | CM7: CENTRO | CN7: SUR | CO7: SUR | CP7: SUR | CQ7: SUR | CR7: CENTRO | CS7: CENTRO | CT7: CENTRO | CU7: CENTRO | CV7: SUR | CW7: NORTE | CX7: SUR | CY7: NORTE | CZ7: NORTE | DA7: NORTE | DB7: NORTE | DC7: SUR | DD7: CENTRO | DE7: CENTRO | DF7: CENTRO | DG7: NORTE | DH7: NORTE | DI7: CENTRO | DJ7: CENTRO | DK7: SUR | DL7: SUR | DM7: CENTRO | DN7: CENTRO | DO7: CENTRO | DP7: CENTRO | DQ7: CENTRO | DR7: CENTRO | DS7: SUR | DT7: CENTRO | DU7: CENTRO | DV7: NORTE | DW7: CENTRO | DX7: CENTRO | DY7: NORTE | DZ7: CENTRO | EA7: CENTRO | EB7: CENTRO | EC7: NORTE | ED7: NORTE | EE7: SUR | EF7: CENTRO | EG7: CENTRO | EH7: CENTRO | EI7: CENTRO | EJ7: CENTRO | EK7: CENTRO | EL7: SUR | EM7: SUR | EN7: SUR | EO7: SUR | EP7: NORTE | EQ7: SUR | ER7: SUR | ES7: CENTRO | ET7: CENTRO | EU7: CENTRO | EV7: SUR | EW7: SUR | EX7: NORTE | EY7: CENTRO | EZ7: NORTE | FA7: NORTE | FB7: NORTE | FC7: CENTRO | FD7: CENTRO | FE7: CENTRO | FF7: NORTE | FG7: NORTE | FJ7: NORTE | FK7: CENTRO | FL7: NORTE | FM7: NORTE | FN7: NORTE | FO7: NORTE | FP7: NORTE | FQ7: NORTE
C8: HIDROELÉCTRICA | D8: HIDROELÉCTRICA | E8: HIDROELÉCTRICA | F8: HIDROELÉCTRICA | G8: TERMOELÉCTRICA | H8: TERMOELÉCTRICA | I8: HIDROELÉCTRICA | J8: HIDROELÉCTRICA | K8: TERMOELÉCTRICA | L8: TERMOELÉCTRICA | M8: TERMOELÉCTRICA | N8: TERMOELÉCTRICA | O8: TERMOELÉCTRICA | P8: TERMOELÉCTRICA | Q8: TERMOELÉCTRICA | R8: TERMOELÉCTRICA | S8: HIDROELÉCTRICA | T8: HIDROELÉCTRICA | U8: TERMOELÉCTRICA | V8: TERMOELÉCTRICA | W8: TERMOELÉCTRICA | X8: TERMOELÉCTRICA | Y8: HIDROELÉCTRICA | Z8: HIDROELÉCTRICA | AA8: TERMOELÉCTRICA | AB8: HIDROELÉCTRICA | AC8: HIDROELÉCTRICA | AD8: HIDROELÉCTRICA | AE8: HIDROELÉCTRICA | AF8: TERMOELÉCTRICA | AG8: TERMOELÉCTRICA | AH8: TERMOELÉCTRICA | AI8: HIDROELÉCTRICA | AJ8: HIDROELÉCTRICA | AK8: TERMOELÉCTRICA | AL8: TERMOELÉCTRICA | AM8: TERMOELÉCTRICA | AN8: HIDROELÉCTRICA | AO8: HIDROELÉCTRICA | AP8: HIDROELÉCTRICA | AQ8: HIDROELÉCTRICA | AR8: HIDROELÉCTRICA | AS8: HIDROELÉCTRICA | AT8: HIDROELÉCTRICA | AU8: HIDROELÉCTRICA | AV8: TERMOELÉCTRICA | AW8: TERMOELÉCTRICA | AX8: TERMOELÉCTRICA | AY8: HIDROELÉCTRICA | AZ8: HIDROELÉCTRICA | BA8: HIDROELÉCTRICA | BB8: HIDROELÉCTRICA | BC8: HIDROELÉCTRICA | BD8: HIDROELÉCTRICA | BE8: HIDROELÉCTRICA | BF8: HIDROELÉCTRICA | BG8: HIDROELÉCTRICA | BH8: TERMOELÉCTRICA | BI8: TERMOELÉCTRICA | BJ8: TERMOELÉCTRICA | BK8: TERMOELÉCTRICA | BL8: TERMOELÉCTRICA | BM8: TERMOELÉCTRICA | BN8: HIDROELÉCTRICA | BO8: TERMOELÉCTRICA | BP8: TERMOELÉCTRICA | BQ8: TERMOELÉCTRICA | BR8: TERMOELÉCTRICA | BS8: TERMOELÉCTRICA | BT8: TERMOELÉCTRICA | BU8: TERMOELÉCTRICA | BV8: TERMOELÉCTRICA | BW8: TERMOELÉCTRICA | BX8: HIDROELÉCTRICA | BY8: TERMOELÉCTRICA | BZ8: TERMOELÉCTRICA | CA8: HIDROELÉCTRICA | CB8: HIDROELÉCTRICA | CC8: HIDROELÉCTRICA | CD8: HIDROELÉCTRICA | CE8: HIDROELÉCTRICA | CF8: HIDROELÉCTRICA | CG8: TERMOELÉCTRICA | CH8: TERMOELÉCTRICA | CI8: TERMOELÉCTRICA | CJ8: TERMOELÉCTRICA | CK8: TERMOELÉCTRICA | CL8: TERMOELÉCTRICA | CM8: TERMOELÉCTRICA | CN8: TERMOELÉCTRICA | CO8: TERMOELÉCTRICA | CP8: TERMOELÉCTRICA | CQ8: TERMOELÉCTRICA | CR8: TERMOELÉCTRICA | CS8: TERMOELÉCTRICA | CT8: SOLAR | CU8: EÓLICA | CV8: SOLAR | CW8: EÓLICA | CX8: SOLAR | CY8: SOLAR | CZ8: HIDROELÉCTRICA | DA8: HIDROELÉCTRICA | DB8: HIDROELÉCTRICA | DC8: HIDROELÉCTRICA | DD8: HIDROELÉCTRICA | DE8: HIDROELÉCTRICA | DF8: HIDROELÉCTRICA | DG8: HIDROELÉCTRICA | DH8: HIDROELÉCTRICA | DI8: HIDROELÉCTRICA | DJ8: HIDROELÉCTRICA | DK8: SOLAR | DL8: SOLAR | DM8: EÓLICA | DN8: EÓLICA | DO8: TERMOELÉCTRICA | DP8: TERMOELÉCTRICA | DQ8: TERMOELÉCTRICA | DR8: TERMOELÉCTRICA | DS8: SOLAR | DT8: HIDROELÉCTRICA | DU8: HIDROELÉCTRICA | DV8: HIDROELÉCTRICA | DW8: HIDROELÉCTRICA | DX8: HIDROELÉCTRICA | DY8: HIDROELÉCTRICA | DZ8: HIDROELÉCTRICA | EA8: HIDROELÉCTRICA | EB8: HIDROELÉCTRICA | EC8: EÓLICA | ED8: EÓLICA | EE8: SOLAR | EF8: EÓLICA | EG8: EÓLICA | EH8: EÓLICA | EI8: EÓLICA | EJ8: HIDROELÉCTRICA | EK8: HIDROELÉCTRICA | EL8: HIDROELÉCTRICA | EM8: HIDROELÉCTRICA | EN8: HIDROELÉCTRICA | EO8: HIDROELÉCTRICA | EP8: EÓLICA | EQ8: SOLAR | ER8: SOLAR | ES8: HIDROELÉCTRICA | ET8: EÓLICA | EU8: EÓLICA | EV8: SOLAR | EW8: SOLAR | EX8: HIDROELÉCTRICA | EY8: HIDROELÉCTRICA | EZ8: TERMOELÉCTRICA | FA8: TERMOELÉCTRICA | FB8: TERMOELÉCTRICA | FC8: TERMOELÉCTRICA | FD8: TERMOELÉCTRICA | FE8: TERMOELÉCTRICA | FF8: TERMOELÉCTRICA | FG8: TERMOELÉCTRICA | FJ8: HIDROELÉCTRICA | FK8: HIDROELÉCTRICA | FL8: HIDROELÉCTRICA | FM8: HIDROELÉCTRICA | FN8: TERMOELÉCTRICA | FO8: TERMOELÉCTRICA | FP8: HIDROELÉCTRICA | FQ8: HIDROELÉCTRICA
C9: CENTRALES SANTA ROSA S.A.C. | D9: CENTRALES SANTA ROSA S.A.C. | E9: ELECTROPERU | F9: ELECTROPERU | G9: ELECTROPERU | H9: ELECTROPERU | I9: ORAZUL ENERGY PERÚ | J9: ORAZUL ENERGY PERÚ | K9: TERMOSELVA | L9: TERMOSELVA | M9: KALLPA GENERACION S.A. | N9: KALLPA GENERACION S.A. | O9: KALLPA GENERACION S.A. | P9: KALLPA GENERACION S.A. | Q9: KALLPA GENERACION S.A. | R9: KALLPA GENERACION S.A. | S9: KALLPA GENERACION S.A. | T9: KALLPA GENERACION S.A. | U9: SHOUGESA | V9: SHOUGESA | W9: SHOUGESA | X9: SHOUGESA | Y9: EGEMSA | Z9: EGESUR | AA9: EGESUR | AB9: EGASA | AC9: EGASA | AD9: EGASA | AE9: EGASA | AF9: EGASA | AG9: EGASA | AH9: EGASA | AI9: SAN GABAN | AJ9: CELEPSA | AK9: MINERA CERRO VERDE | AL9: PLANTA DE RESERVA FRIA DE GENERACION DE ETEN S.A. | AM9: PLANTA DE RESERVA FRIA DE GENERACION DE ETEN S.A. | AN9: EMPRESA DE GENERACION HUALLAGA | AO9: EMPRESA DE GENERACION HUALLAGA | AP9: LA VIRGEN | AQ9: CHINANGO S.A.C. | AR9: CHINANGO S.A.C. | AS9: HIDROELECTRICA HUANCHOR S.A.C. | AT9: CELEPSA RENOVABLES S.R.L. | AU9: INLAND ENERGY SAC | AV9: FENIX POWER PERÚ | AW9: FENIX POWER PERÚ | AX9: FENIX POWER PERÚ | AY9: STATKRAFT S.A | AZ9: STATKRAFT S.A | BA9: STATKRAFT S.A | BB9: STATKRAFT S.A | BC9: STATKRAFT S.A | BD9: STATKRAFT S.A | BE9: STATKRAFT S.A | BF9: STATKRAFT S.A | BG9: EMPRESA DE GENERACION HUANZA | BH9: ENEL GENERACION PIURA S.A. | BI9: ENEL GENERACION PIURA S.A. | BJ9: ENEL GENERACION PIURA S.A. | BK9: ENGIE | BL9: ENGIE | BM9: ENGIE | BN9: ENGIE | BO9: ENGIE | BP9: ENGIE | BQ9: ENGIE | BR9: ENGIE | BS9: ENGIE | BT9: ENGIE | BU9: ENGIE | BV9: ENGIE | BW9: ENGIE | BX9: ENGIE | BY9: INFRAESTRUCTURAS Y ENERGIAS DEL PERU S.A.C. | BZ9: INFRAESTRUCTURAS Y ENERGIAS DEL PERU S.A.C. | CA9: INVERSIONES SHAQSHA S.A.C. | CB9: ORYGEN PERU S.A.A. | CC9: ORYGEN PERU S.A.A. | CD9: ORYGEN PERU S.A.A. | CE9: ORYGEN PERU S.A.A. | CF9: ORYGEN PERU S.A.A. | CG9: ORYGEN PERU S.A.A. | CH9: ORYGEN PERU S.A.A. | CI9: ORYGEN PERU S.A.A. | CJ9: ORYGEN PERU S.A.A. | CK9: ORYGEN PERU S.A.A. | CL9: ORYGEN PERU S.A.A. | CM9: ORYGEN PERU S.A.A. | CN9: SAMAY I S.A.C | CO9: SAMAY I S.A.C | CP9: SAMAY I S.A.C | CQ9: SAMAY I S.A.C | CR9: TERMOCHILCA S.A.C. | CS9: TERMOCHILCA S.A.C. | CT9: COLCA SOLAR S.A.C. | CU9: ENERGIA RENOVABLE DEL SUR S.A. | CV9: GR CORTARRAMA SOCIEDAD ANONIMA CERRADA | CW9: GR TARUCA SOCIEDAD ANONIMA CERRADA | CX9: JOYA SOLAR S.A.C. | CY9: KONDU SAC | CZ9: PERUANA DE INVERSIONES EN ENERGIAS RENOVABLES S.A. | DA9: ORAZUL ENERGY PERÚ | DB9: ORAZUL ENERGY PERÚ | DC9: SAN GABAN | DD9: MAJA ENERGIA S.A.C. | DE9: EMPRESA DE GENERACION ELECTRICA CANCHAYLLO SAC | DF9: EMPRESA DE GENERACION ELECTRICA SANTA ANA S.A.C. | DG9: EMPRESA ELECTRICA AGUA AZUL | DH9: EMPRESA ELECTRICA RIO DOBLE | DI9: HIDROCAÑETE S.A. | DJ9: HUAURA POWER GROUP S.A. | DK9: MOQUEGUA FV S.A.C. | DL9: PANAMERICANA SOLAR SAC. | DM9: PARQUE EOLICO MARCONA S.A.C. | DN9: PARQUE EOLICO TRES HERMANAS S.A.C. | DO9: PETRAMAS | DP9: PETRAMAS | DQ9: PETRAMAS | DR9: PETRAMAS | DS9: TACNA SOLAR SAC. | DT9: ELECTRICA YANAPAMPA SAC | DU9: ANDEAN POWER S.A.C. | DV9: ASOCIACIÓN SANTA LUCIA DE CHACAS | DW9: ATRIA ENERGIA S.A.C. | DX9: EGEJUNIN | DY9: EGEJUNIN | DZ9: EGEJUNIN | EA9: EGEJUNIN | EB9: EMPRESA DE GENERACION ELECTRICA RIO BAÑOS S.A.C. | EC9: ENERGÍA EÓLICA S.A. | ED9: ENERGÍA EÓLICA S.A. | EE9: ENGIE | EF9: ENGIE | EG9: ENGIE | EH9: ENGIE | EI9: ENGIE | EJ9: GENERACIÓN ANDINA S.A.C. | EK9: GENERACIÓN ANDINA S.A.C. | EL9: GENERADORA DE ENERGÍA DEL PERÚ | EM9: GENERADORA DE ENERGÍA DEL PERÚ | EN9: GENERADORA DE ENERGÍA DEL PERÚ | EO9: GENERADORA DE ENERGÍA DEL PERÚ | EP9: GR PAINO SOCIEDAD ANONIMA CERRADA | EQ9: MAJES ARCUS S.A.C. | ER9: ORYGEN PERU S.A.A. | ES9: ORYGEN PERU S.A.A. | ET9: ORYGEN PERU S.A.A. | EU9: ORYGEN PERU S.A.A. | EV9: ORYGEN PERU S.A.A. | EW9: REPARTICIÓN ARCUS S.A.C. | EX9: SINERSA | EY9: SINERSA | EZ9: BIOENERGIA DEL CHIRA S.A. | FA9: GM OPERACIONES S.A.C. | FB9: GM OPERACIONES S.A.C. | FC9: SDF ENERGIA SAC | FD9: SDF ENERGIA SAC | FE9: AGRO INDUSTRIAL PARAMONGA S.A. | FF9: AGROAURORA S.A.C. | FG9: AGROINDUSTRIAS SAN JACINTO S.A.A. | FJ9: UNACEM PERU S.A. | FK9: ELECTRO ORIENTE | FL9: AGUAS Y ENERGIA PERU | FM9: ELECTRO ZAÑA S.A.C. | FN9: ELECTRONOROESTE S.A. | FO9: SDE PIURA | FP9: SINERSA | FQ9: SINERSA
C10: SANTA ROSA 1 | D10: SANTA ROSA 2 | E10: MANTARO | F10: RESTITUCION | G10: TUMBES MAK 1 | H10: TUMBES MAK 2 | I10: CARHUAQUERO | J10: CAÑON DEL PATO | K10: AGUAYTIA TG1 | L10: AGUAYTIA TG2 | M10: KALLPA TG1 | N10: KALLPA TG2 | O10: KALLPA TG3 | P10: KALLPA TV | Q10: LFLORES TG1 | R10: LFLORES TV | S10: CERRO DEL AGUILA | T10: CERRODELAGUILAG4 | U10: SHOUGESA TV1 | V10: SHOUGESA TV2 | W10: SHOUGESA TV3 | X10: SHOUGESA CUMMINS | Y10: MACHUPICCHU | Z10: ARICOTA 1 | AA10: INDEPENDENCIA | AB10: CHARCANI I,II,III | AC10: CHARCANI IV | AD10: CHARCANI V | AE10: CHARCANI VI | AF10: CHILINA TG | AG10: MOLLENDO 1, 2, 3 | AH10: CHILINA (SULZ 1,2) | AI10: SAN GABAN II | AJ10: PLATANAL | AK10: RECKA | AL10: RF ETEN TG1 | AM10: RF ETEN TG2 | AN10: CHAGLLA GP1 | AO10: CHAGLLA | AP10: LA VIRGEN | AQ10: CHIMAY | AR10: YANANGO | AS10: HUANCHOR | AT10: MARAÑON | AU10: STA TERESA | AV10: FENIX GT11 | AW10: FENIX GT12 | AX10: FENIX TV10 | AY10: YAUPI | AZ10: OROYA | BA10: PACHACHACA | BB10: MALPASO | BC10: CAHUA | BD10: ARCATA | BE10: GALLITO CIEGO | BF10: CHEVES | BG10: HUANZA | BH10: MALACAS2 TG4 | BI10: MALACAS3 TG 5 | BJ10: MALACAS1 TG6 | BK10: RF ILO2 TG1 | BL10: RF ILO2 TG2 | BM10: RF ILO2 TG3 | BN10: YUNCAN | BO10: CHILCA1 TG1 | BP10: CHILCA1 TG2 | BQ10: CHILCA1 TG3 | BR10: CHILCA-TV | BS10: CHILCA2 TG41 | BT10: CHILCA2-TV | BU10: CTNEPI_TG41 | BV10: CTNEPI_TG42 | BW10: CTNEPI_TG43 | BX10: QUITARACSA | BY10: RF PTO MALDONADO | BZ10: RF PUCALLPA | CA10: PARIAC | CB10: HUINCO | CC10: MATUCANA | CD10: MOYOPAMPA | CE10: CALLAHUANCA | CF10: HUAMPANI | CG10: STA ROSA WEST TG7 | CH10: UTI_5 | CI10: UTI_6 | CJ10: VENTANILLA 3 | CK10: VENTANILLA 4 | CL10: VENTANILLA TV | CM10: STAROSA TG8 | CN10: PTO_BRVO TG1 | CO10: PTO_BRVO TG2 | CP10: PTO_BRVO TG3 | CQ10: PTO_BRVO TG4 | CR10: OLLEROS TG1 | CS10: OLLEROS TV | CT10: CS YARUCAYA | CU10: SAN JUAN | CV10: MATARANI | CW10: DUNA | CX10: SAN MARTIN SOLAR | CY10: CARHUAQUERO (CS) | CZ10: MANTA I | DA10: CARHUAQUERO4 | DB10: CAÑA BRAVA | DC10: TUPURI | DD10: RONCADOR | DE10: CANCHAYLLO | DF10: RENOVANDESH1 | DG10: POTRERO | DH10: PIZARRAS | DI10: NIMPERIAL | DJ10: YARUCAYA | DK10: MOQUEGUA-SOLAR | DL10: PANAMERICANA-SOLAR | DM10: PQE-EOLICO-MARCONA | DN10: PQE-EOLICO-3-HERMANAS | DO10: HUAYCOLORO | DP10: CALLAO | DQ10: DONA_CATALINA | DR10: LAGRINGAV | DS10: TACNA-SOLAR | DT10: YANAPAMPA | DU10: CARHUAC | DV10: HUALLIN | DW10: PURMACANA | DX10: HUASAHUASI | DY10: STACRUZ_1_2 | DZ10: RUNATULLO_II | EA10: RUNATULLO_III | EB10: RUCUY | EC10: PQE-EOLICO-TALARA | ED10: PQE-EOLICO-CUPISNIQUE | EE10: INTIPAMPA | EF10: PUNTA LOMITAS-BL1 | EG10: PUNTA LOMITAS-BL2 | EH10: PUN LOMITAS_EXP-BL1 | EI10: PUN LOMITAS_EXP-BL2 | EJ10: 8AGOSTO | EK10: EL CARMEN | EL10: LA JOYA | EM10: ANGEL_I | EN10: ANGEL_II | EO10: ANGEL_III | EP10: HUAMBOS | EQ10: MAJES | ER10: RUBI | ES10: CH_HER1 | ET10: WAYRA-I | EU10: WAYRA EXTENSION | EV10: CLEMESI | EW10: REPARTICION | EX10: POECHOS2 | EY10: CHANCAY | EZ10: CANA BRAVA | FA10: REFINERIA TALARA TV1 | FB10: REFINERÍA TALARA TV2 | FC10: OQUENDO TG1 | FD10: OQUENDO TV1 | FE10: PARAMONGA | FF10: MAPLE | FG10: SAN_JACINTO | FH10: MVAR | FJ10: CARPAPATA | FK10: CENTRALES ELOR | FL10: PIAS1 | FM10: ZANA | FN10: TABLAZO | FO10: TALLANCA | FP10: CURUMUY | FQ10: POECHOS1 | FR10: MVAR
A11: 09/04/2025 | B11: 00:30 | E11: 13.1 | F11: 12.8 | I11: -11 | J11: 13 | M11: -32.4 | N11: -41.4 | O11: -36.9 | P11: 16.6 | Q11: -47.6 | R11: -17.6 | S11: 93.6 | T11: 0.3 | Y11: -3.2 | Z11: 2.1 | AA11: 0 | AB11: -3.3 | AC11: 2.7 | AD11: 12.5 | AE11: 2.1 | AI11: 12.2 | AJ11: 9.6 | AN11: -1.7 | AO11: -10.9 | AP11: -1.4 | AQ11: 12.8 | AR11: -0.3 | AS11: 1.5 | AT11: 2.7 | AU11: 1.1 | AY11: 0.3 | AZ11: 0 | BA11: -0.1 | BB11: -1.1 | BC11: -0.8 | BD11: 1 | BE11: -0.1 | BF11: 6.6 | BG11: -3.1 | BJ11: 0 | BN11: -5.8 | BO11: 0 | BQ11: -15.9 | BR11: -50.6 | BS11: 0 | CA11: -0.3 | CB11: 36.8 | CC11: 26.8 | CD11: -0.2 | CE11: 5.1 | CF11: -0.1 | CJ11: 1.7 | CK11: 4.7 | CL11: -41.3 | CR11: -18 | CS11: -16.5 | CU11: -3.4 | CV11: 0 | CW11: 0 | CZ11: 1.3 | DA11: -0.1 | DB11: -0.9 | DD11: 0.2 | DE11: 1 | DF11: 1.6 | DG11: 0.4 | DH11: 1.2 | DI11: 0.5 | DJ11: 0.1 | DK11: 0 | DL11: 0 | DM11: 2 | DN11: 13.5 | DO11: 1.6 | DP11: 0.5 | DQ11: 0.8 | DS11: 0 | DT11: 0.1 | DU11: 0.3 | DV11: 0.9 | DX11: -4 | DY11: 0.6 | DZ11: 2.3 | EA11: 2.5 | EB11: 1.4 | EC11: 0.8 | ED11: 4 | EE11: 0 | EF11: -1.2 | EG11: -1.3 | EH11: 0.1 | EI11: 0.5 | EJ11: 2.6 | EK11: 0 | EL11: 1.5 | EM11: 0.2 | EN11: 0.2 | EO11: 0.2 | EP11: 0 | EQ11: 0 | ER11: 0 | ES11: -0.2 | ET11: 3.9 | EU11: 0 | EV11: 0 | EW11: 0 | EX11: 0.2 | EY11: 1.4 | FA11: 13.7 | FB11: 0 | FC11: 1.1 | FD11: 1.9 | FE11: 1.7 | FH11: -14.2 | FJ11: 1.42915 | FK11: 0.317 | FM11: 1.6 | FO11: 3.11035 | FP11: 0.2 | FQ11: 0.8 | FR11: 7.4565
A12: 09/04/2025 | B12: 01:00 | E12: 1.3 | F12: 10.9 | I12: -14.3 | J12: -0.4 | M12: -38.2 | N12: -51.8 | O12: -45.9 | P12: 11.6 | Q12: -51.1 | R12: -19.9 | S12: 89.8 | T12: 0 | Y12: 8.3 | Z12: 1.9 | AA12: 0 | AB12: -3.3 | AC12: 2.6 | AD12: 12 | AE12: 2.1 | AI12: 11.8 | AJ12: 1.1 | AN12: -1.7 | AO12: -13.2 | AP12: -1 | AQ12: 6.5 | AR12: -0.5 | AS12: 1.6 | AT12: 2.7 | AU12: 0.6 | AY12: -2.1 | AZ12: 0 | BA12: -0.1 | BB12: -1.2 | BC12: -3.7 | BD12: 1 | BE12: -0.1 | BF12: 0.8 | BG12: -4.9 | BJ12: 0 | BN12: -8.1 | BO12: 0 | BQ12: -20.1 | BR12: -52.5 | BS12: 0 | CA12: -0.3 | CB12: 38.9 | CC12: 27.7 | CD12: -1.4 | CE12: 5.1 | CF12: 0.1 | CJ12: -4.1 | CK12: -1.2 | CL12: -49.2 | CR12: -22.6 | CS12: -19.1 | CU12: -3.1 | CV12: 0 | CW12: 0 | CZ12: 1.3 | DA12: 0 | DB12: -0.9 | DD12: 0.2 | DE12: 1.1 | DF12: 1.6 | DG12: 0.2 | DH12: 1.2 | DI12: 0.6 | DJ12: 0.1 | DK12: 0 | DL12: 0 | DM12: 2.1 | DN12: 13.1 | DO12: 1.6 | DP12: 0.5 | DQ12: 0.8 | DS12: 0 | DT12: 0.1 | DU12: 0.3 | DV12: 0.9 | DX12: -4.2 | DY12: 0.7 | DZ12: 2.2 | EA12: 2.4 | EB12: 1.4 | EC12: 0.8 | ED12: 4 | EE12: 0 | EF12: -3.6 | EG12: -4 | EH12: 0 | EI12: 0 | EJ12: 2.6 | EK12: 0 | EL12: 1.5 | EM12: 0.2 | EN12: 0.2 | EO12: 0.2 | EP12: 0 | EQ12: 0 | ER12: 0 | ES12: -0.2 | ET12: -0.5 | EU12: 0 | EV12: 0 | EW12: 0 | EX12: 0.2 | EY12: 1.4 | FA12: 13.4 | FB12: 0 | FC12: 1.1 | FD12: 1.6 | FE12: 1 | FH12: -149.5 | FJ12: 1.48667 | FK12: 0.249 | FM12: 1.7 | FO12: 2.9767 | FP12: -0.3 | FQ12: 1 | FR12: 7.11237
A13: 09/04/2025 | B13: 01:30 | E13: 15.7 | F13: 13.9 | I13: -13.8 | J13: 6.5 | M13: -39.7 | N13: -45 | O13: -39.2 | P13: 9.7 | Q13: -51 | R13: -21.2 | S13: 91.9 | T13: 0.5 | Y13: 9.1 | Z13: 2.1 | AA13: 0 | AB13: -3.3 | AC13: 2.6 | AD13: 11.9 | AE13: 2 | AI13: 14.1 | AJ13: -4.8 | AN13: -1.7 | AO13: -14.7 | AP13: -0.4 | AQ13: 4.9 | AR13: 0.4 | AS13: 1.5 | AT13: 2.7 | AU13: 2.3 | AY13: -2 | AZ13: 0 | BA13: 0.2 | BB13: 4.5 | BC13: -0.9 | BD13: 1 | BE13: -0.1 | BF13: 10.5 | BG13: -5.1 | BJ13: 0 | BN13: -10.1 | BO13: 0 | BQ13: -20.3 | BR13: -53 | BS13: 0 | CA13: -0.4 | CB13: 36.2 | CC13: 26.3 | CD13: -6.3 | CE13: 5.2 | CF13: 0 | CJ13: -4.1 | CK13: -1.6 | CL13: -50.5 | CR13: -25.3 | CS13: -20.7 | CU13: -2.9 | CV13: 0 | CW13: 0 | CZ13: 1.3 | DA13: 0 | DB13: -0.9 | DD13: 0.3 | DE13: 1.3 | DF13: 1.5 | DG13: 0 | DH13: 1.2 | DI13: 0.5 | DJ13: 0 | DK13: 0 | DL13: 0 | DM13: 2.1 | DN13: 12 | DO13: 1.6 | DP13: 0.5 | DQ13: 0.8 | DS13: 0 | DT13: 0 | DU13: 0.3 | DV13: 0.9 | DX13: -4.2 | DY13: 0.8 | DZ13: 2.2 | EA13: 2.4 | EB13: 1.2 | EC13: 0.8 | ED13: 4 | EE13: 0 | EF13: -2.7 | EG13: -3.1 | EH13: 0 | EI13: 0 | EJ13: 2.6 | EK13: 0 | EL13: 1.5 | EM13: 0.2 | EN13: 0.2 | EO13: 0.2 | EP13: 0 | EQ13: 0 | ER13: 0 | ES13: -0.2 | ET13: -2.4 | EU13: 0 | EV13: 0 | EW13: 0 | EX13: 0.2 | EY13: 1.2 | FA13: 12 | FB13: 0 | FC13: 1.1 | FD13: 2.1 | FE13: 1.2 | FH13: -117.7 | FJ13: 1.85934 | FK13: -0.034 | FM13: 1.7 | FO13: 2.75032 | FP13: -0.4 | FQ13: 0.8 | FR13: 6.67566
A14: 09/04/2025 | B14: 02:00 | E14: -18.5 | F14: 8.1 | I14: -16 | J14: -6.4 | M14: -43.8 | N14: -57.8 | O14: -52.9 | P14: 2.9 | Q14: -54.6 | R14: -22.5 | S14: 85.5 | T14: 0 | Y14: 4.7 | Z14: 1.8 | AA14: 0 | AB14: -3.3 | AC14: 2.5 | AD14: 11.3 | AE14: 2 | AI14: 10.6 | AJ14: -3.1 | AN14: -1.7 | AO14: -14.7 | AP14: -0.2 | AQ14: 3.1 | AR14: -2 | AS14: 1.7 | AT14: 2.7 | AU14: 0.3 | AY14: -4.8 | AZ14: 0 | BA14: 0.2 | BB14: 0.5 | BC14: -4.4 | BD14: 1 | BE14: -0.1 | BF14: 1.2 | BG14: -7.1 | BJ14: 0 | BN14: -10.4 | BO14: 0 | BQ14: -23.8 | BR14: -56.5 | BS14: 0 | CA14: -0.5 | CB14: 40.1 | CC14: 26.6 | CD14: -5.8 | CE14: 8.1 | CF14: -0.2 | CJ14: -8.3 | CK14: -5.6 | CL14: -55.8 | CR14: -25.6 | CS14: -21 | CU14: -2.9 | CV14: 0 | CW14: 0 | CZ14: 1.3 | DA14: -0.1 | DB14: -0.9 | DD14: 0.2 | DE14: 1.4 | DF14: 1.5 | DG14: 0 | DH14: 1.2 | DI14: 0.6 | DJ14: 0 | DK14: 0 | DL14: 0 | DM14: 1.9 | DN14: 11.3 | DO14: 1.6 | DP14: 0.5 | DQ14: 0.8 | DS14: 0 | DT14: 0.1 | DU14: 0.3 | DV14: 0.9 | DX14: -4.2 | DY14: 0.7 | DZ14: 2.2 | EA14: 2.3 | EB14: 1.2 | EC14: 0.8 | ED14: 4 | EE14: 0 | EF14: -7.7 | EG14: -8.4 | EH14: 0 | EI14: 0 | EJ14: 2.6 | EK14: 0 | EL14: 1.4 | EM14: 0.2 | EN14: 0.2 | EO14: 0.2 | EP14: 0 | EQ14: 0 | ER14: 0 | ES14: -0.2 | ET14: 4.9 | EU14: 0 | EV14: 0 | EW14: 0 | EX14: 0.2 | EY14: 1.2 | FA14: 10.8 | FB14: 0 | FC14: 1.1 | FD14: 2.3 | FE14: 1.3 | FH14: -275.7 | FJ14: 1.91046 | FK14: 0 | FM14: 1.7 | FO14: 2.7541 | FP14: -0.9 | FQ14: 0.9 | FR14: 6.36456
A15: 09/04/2025 | B15: 02:30 | E15: -21.4 | F15: 6.1 | I15: -16.3 | J15: -7.5 | M15: -40.6 | N15: -54.6 | O15: -49.6 | P15: 6.6 | Q15: -53.8 | R15: -21.7 | S15: 85.2 | T15: 0 | Y15: 5.2 | Z15: 1.7 | AA15: 0 | AB15: -3.3 | AC15: 2.5 | AD15: 10.7 | AE15: 2 | AI15: 10.7 | AJ15: 3.2 | AN15: -1.7 | AO15: -13.4 | AP15: -0.4 | AQ15: 2.9 | AR15: -2.4 | AS15: 1.3 | AT15: 2.7 | AU15: -0.2 | AY15: -7.5 | AZ15: 0 | BA15: 0.2 | BB15: -0.9 | BC15: -4.6 | BD15: 1 | BE15: -0.1 | BF15: 0.8 | BG15: -7.3 | BJ15: 0 | BN15: -11.7 | BO15: 0 | BQ15: -23 | BR15: -55.2 | BS15: 0 | CA15: -0.4 | CB15: 36.5 | CC15: 26.1 | CD15: -4.7 | CE15: 5.1 | CF15: -0.1 | CJ15: -8.6 | CK15: -5.4 | CL15: -55.4 | CR15: -26.3 | CS15: -21.3 | CU15: -3.3 | CV15: 0 | CW15: 0 | CZ15: 1.3 | DA15: 0 | DB15: -0.9 | DD15: 0.3 | DE15: 1.4 | DF15: 1.6 | DG15: 0.2 | DH15: 1.2 | DI15: 0.6 | DJ15: 0 | DK15: 0 | DL15: 0 | DM15: 1.7 | DN15: 10.7 | DO15: 1.6 | DP15: 0.5 | DQ15: 0.8 | DS15: 0 | DT15: 0 | DU15: 0.3 | DV15: 0.8 | DX15: -4.2 | DY15: 0.8 | DZ15: 2.2 | EA15: 2.3 | EB15: 1.4 | EC15: 0.8 | ED15: 4 | EE15: 0 | EF15: -5.1 | EG15: -5.4 | EH15: 0 | EI15: 0.1 | EJ15: 2.6 | EK15: 0 | EL15: 1.5 | EM15: 0.2 | EN15: 0.2 | EO15: 0.2 | EP15: 0 | EQ15: 0 | ER15: 0 | ES15: -0.2 | ET15: 4.9 | EU15: 0.1 | EV15: 0 | EW15: 0 | EX15: 0.2 | EY15: 1.4 | FA15: 11.1 | FB15: 0 | FC15: 1.1 | FD15: 2.1 | FE15: 1.5 | FH15: -266.3 | FJ15: 1.65582 | FK15: 0 | FM15: 1.6 | FO15: 2.75108 | FP15: -1 | FQ15: 0.9 | FR15: 5.9069
A16: 09/04/2025 | B16: 03:00 | E16: -19.2 | F16: 6.1 | I16: -16.7 | J16: 4.8 | M16: -39.1 | N16: -58.9 | O16: -55.1 | P16: 9 | Q16: -53 | R16: -21.3 | S16: 92.8 | T16: -0.1 | Y16: 7.2 | Z16: 2.1 | AA16: 0 | AB16: -3.3 | AC16: 2.5 | AD16: 11.4 | AE16: 2 | AI16: 11.8 | AJ16: -1.3 | AN16: -1.8 | AO16: -14.5 | AP16: -0.8 | AQ16: 3.3 | AR16: -2.1 | AS16: 2 | AT16: 2.7 | AU16: 0.2 | AY16: -7.5 | AZ16: 0 | BA16: 0.2 | BB16: -1.9 | BC16: -4.6 | BD16: 1 | BE16: -0.2 | BF16: 0.7 | BG16: -8.4 | BJ16: 0 | BN16: -10.4 | BO16: 0 | BQ16: -21.7 | BR16: -56.8 | BS16: 0 | CA16: -0.4 | CB16: 37.2 | CC16: 26.4 | CD16: -5.4 | CE16: 8.9 | CF16: -0.3 | CJ16: -7.3 | CK16: -4.3 | CL16: -54 | CR16: -27.9 | CS16: -22.3 | CU16: -3.8 | CV16: 0 | CW16: 0 | CZ16: 1.3 | DA16: -0.1 | DB16: -0.9 | DD16: 0.2 | DE16: 1.4 | DF16: 1.6 | DG16: 0.1 | DH16: 1.2 | DI16: 0.6 | DJ16: 0 | DK16: 0 | DL16: 0 | DM16: 0.5 | DN16: 12.5 | DO16: 1.6 | DP16: 0.5 | DQ16: 0.8 | DS16: 0 | DT16: 0.1 | DU16: 0.3 | DV16: 0.9 | DX16: -4.2 | DY16: 0.7 | DZ16: 2.3 | EA16: 2.5 | EB16: 1.3 | EC16: 0.8 | ED16: 4 | EE16: 0 | EF16: -5 | EG16: -5.2 | EH16: 0 | EI16: 0 | EJ16: 2.6 | EK16: 0 | EL16: 1.6 | EM16: 0.2 | EN16: 0.2 | EO16: 0.2 | EP16: 0 | EQ16: 0 | ER16: 0 | ES16: -0.2 | ET16: 4.7 | EU16: 0 | EV16: 0 | EW16: 0 | EX16: 0.2 | EY16: 1.3 | FA16: 9.7 | FB16: 0 | FC16: 1.1 | FD16: 2 | FE16: 0.6 | FH16: -248.1 | FJ16: 1.55569 | FK16: 0 | FM16: 1.7 | FO16: 2.7435 | FP16: -1.3 | FQ16: 1.2 | FR16: 5.89919
A17: 09/04/2025 | B17: 03:30 | E17: -23.4 | F17: 6 | I17: -12.1 | J17: 4.2 | M17: -43 | N17: -53.9 | O17: -51.4 | P17: 3.1 | Q17: -57.3 | R17: -24.4 | S17: 86.3 | T17: -0.1 | Y17: 7.7 | Z17: 1.4 | AA17: 0 | AB17: -3.3 | AC17: 2.4 | AD17: 10.9 | AE17: 1.9 | AI17: 10.9 | AJ17: -1.1 | AN17: -1.8 | AO17: -20.4 | AP17: -0.9 | AQ17: 3.2 | AR17: -2.2 | AS17: 1.7 | AT17: 2.7 | AU17: 1.2 | AY17: -7.8 | AZ17: 0 | BA17: -0.1 | BB17: -1.7 | BC17: -4.1 | BD17: 1 | BE17: 0 | BF17: 0.8 | BG17: -2.6 | BJ17: 0 | BN17: -13.1 | BO17: 0 | BQ17: -27 | BR17: -60.2 | BS17: 0 | CA17: -0.4 | CB17: 36.6 | CC17: 27 | CD17: -4.8 | CE17: 5 | CF17: -4.1 | CJ17: -1.6 | CK17: 0.9 | CL17: -35.7 | CR17: -35.6 | CS17: -26.8 | CU17: -4 | CV17: 0 | CW17: 0 | CZ17: 1.3 | DA17: 0 | DB17: -1 | DD17: 0.2 | DE17: 1.4 | DF17: 1.6 | DG17: -0.2 | DH17: 1.2 | DI17: 0.6 | DJ17: 0 | DK17: 0 | DL17: 0 | DM17: 0.5 | DN17: 10.3 | DO17: 1.6 | DP17: 0.5 | DQ17: 0.8 | DS17: 0 | DT17: 0.1 | DU17: 0.3 | DV17: 0.8 | DX17: -4.2 | DY17: 0.6 | DZ17: 2.4 | EA17: 2.5 | EB17: 1.1 | EC17: 0.8 | ED17: 4 | EE17: 0 | EF17: -5.8 | EG17: -6.7 | EH17: 0 | EI17: 0 | EJ17: 2.6 | EK17: 0 | EL17: 1.5 | EM17: 0.2 | EN17: 0.2 | EO17: 0.2 | EP17: 0 | EQ17: 0 | ER17: 0 | ES17: -0.2 | ET17: 4.6 | EU17: 0 | EV17: 0 | EW17: 0 | EX17: 0.2 | EY17: 1.4 | FA17: 14.4 | FB17: 0 | FC17: 1.1 | FD17: 2.3 | FE17: 1.9 | FH17: -264.9 | FJ17: 1.54341 | FK17: 0 | FM17: 1.8 | FO17: 2.73558 | FP17: 0.2 | FQ17: 1.1 | FR17: 7.37899
A18: 09/04/2025 | B18: 04:00 | E18: -34 | F18: 3.9 | I18: -13.9 | J18: -6 | M18: -43.3 | N18: -60.6 | O18: -55.9 | P18: 4.3 | Q18: -58.2 | R18: -24.7 | S18: 84.9 | T18: -0.1 | Y18: 4.6 | Z18: 2.1 | AA18: 0 | AB18: -3.4 | AC18: 2.5 | AD18: 11.1 | AE18: 2 | AI18: 9.7 | AJ18: -1.1 | AN18: -1.7 | AO18: -22.4 | AP18: -0.7 | AQ18: 2.6 | AR18: -2.2 | AS18: 1.7 | AT18: 2.7 | AU18: 0.3 | AY18: -8.5 | AZ18: 0 | BA18: 0.2 | BB18: -2.5 | BC18: -5 | BD18: 1 | BE18: -0.1 | BF18: 0.3 | BG18: -2.8 | BJ18: 0 | BN18: -14.2 | BO18: 0 | BQ18: -27.3 | BR18: -59.9 | BS18: 0 | CA18: -0.4 | CB18: 38.1 | CC18: 26.9 | CD18: -4.6 | CE18: 5.1 | CF18: -3.9 | CJ18: -2.5 | CK18: 0.5 | CL18: -35.8 | CR18: -35.4 | CS18: -26.7 | CU18: -4 | CV18: 0 | CW18: 0 | CZ18: 1.3 | DA18: 0 | DB18: -0.9 | DD18: 0 | DE18: 1.4 | DF18: 1.5 | DG18: 0 | DH18: 1.2 | DI18: 0.6 | DJ18: 0 | DK18: 0 | DL18: 0 | DM18: 1 | DN18: 10.9 | DO18: 1.6 | DP18: 0.5 | DQ18: 0.8 | DS18: 0 | DT18: 0.1 | DU18: 0.3 | DV18: 0.8 | DX18: -4.2 | DY18: 0.7 | DZ18: 2.2 | EA18: 2.4 | EB18: 1.3 | EC18: 0.8 | ED18: 4 | EE18: 0 | EF18: -7.2 | EG18: -8.2 | EH18: 0 | EI18: 0 | EJ18: 2.6 | EK18: 0 | EL18: 1.6 | EM18: 0.2 | EN18: 0.2 | EO18: 0.2 | EP18: 0 | EQ18: 0 | ER18: 0 | ES18: -0.2 | ET18: 4.4 | EU18: 0 | EV18: 0 | EW18: 0 | EX18: 0.2 | EY18: 1.6 | FA18: 14.1 | FB18: 0 | FC18: 1.1 | FD18: 2.5 | FE18: 0.6 | FH18: -315.3 | FJ18: 1.77094 | FK18: 0 | FM18: 1.9 | FO18: 2.7353 | FP18: 0 | FQ18: 1 | FR18: 7.40624
A19: 09/04/2025 | B19: 04:30 | E19: -18 | F19: 7.1 | I19: -12.5 | J19: 9.3 | M19: -39.2 | N19: -50.2 | O19: -44.9 | P19: 8.7 | Q19: -55.2 | R19: -23.1 | S19: 84.7 | T19: 0 | Y19: 6.6 | Z19: 1.9 | AA19: 0 | AB19: -3.4 | AC19: 2.6 | AD19: 11.3 | AE19: 2 | AI19: 10.3 | AJ19: 9.8 | AN19: -1.5 | AO19: -14.2 | AP19: -0.2 | AQ19: 1.7 | AR19: -2.1 | AS19: 1.4 | AT19: 2.7 | AU19: 1.2 | AY19: -7.5 | AZ19: 0 | BA19: 0.2 | BB19: 0.1 | BC19: -3.3 | BD19: 1 | BE19: 0 | BF19: 3.2 | BG19: -1.8 | BJ19: 0 | BN19: -11.5 | BO19: 0 | BQ19: -24.4 | BR19: -57 | BS19: 0 | CA19: -0.4 | CB19: 37.1 | CC19: 26 | CD19: -5.5 | CE19: 5.1 | CF19: -4 | CJ19: 1.1 | CK19: 4.1 | CL19: -31.2 | CR19: -32.5 | CS19: -25 | CU19: -3.9 | CV19: 0 | CW19: 0 | CZ19: 1.3 | DA19: 0 | DB19: -0.9 | DD19: 0.1 | DE19: 1.4 | DF19: 1.6 | DG19: 0 | DH19: 1.2 | DI19: 0.6 | DJ19: 0 | DK19: 0 | DL19: 0 | DM19: 1 | DN19: 11 | DO19: 1.6 | DP19: 0.5 | DQ19: 0.8 | DS19: 0 | DT19: 0.1 | DU19: 0.4 | DV19: 0.8 | DX19: -4.2 | DY19: 0.8 | DZ19: 2.4 | EA19: 2.6 | EB19: 1.3 | EC19: 0.8 | ED19: 4 | EE19: 0 | EF19: -4 | EG19: -5.8 | EH19: 0 | EI19: 0 | EJ19: 2.6 | EK19: 0 | EL19: 1.6 | EM19: 0.2 | EN19: 0.2 | EO19: 0.2 | EP19: 0 | EQ19: 0 | ER19: 0 | ES19: -0.2 | ET19: 4.5 | EU19: 0 | EV19: 0 | EW19: 0 | EX19: 0.2 | EY19: 1.6 | FA19: 14.6 | FB19: 0 | FC19: 1.1 | FD19: 2.2 | FE19: 1 | FH19: -184.1 | FJ19: 1.90082 | FK19: 0 | FM19: 1.7 | FO19: 2.73083 | FP19: 0.3 | FQ19: 1 | FR19: 7.63165
A20: 09/04/2025 | B20: 05:00 | E20: -17.3 | F20: 8.1 | I20: -13.6 | J20: 2.5 | M20: -41.9 | N20: -51.3 | O20: -45.4 | P20: 5.2 | Q20: -56.8 | R20: -24.1 | S20: 85.6 | T20: 0 | Y20: 8.1 | Z20: 1.8 | AA20: 0 | AB20: -3.3 | AC20: 2.7 | AD20: 11.5 | AE20: 2.1 | AI20: 10.6 | AJ20: 8.5 | AN20: -1.5 | AO20: -14.5 | AP20: -0.2 | AQ20: 1.4 | AR20: -1.7 | AS20: 0.6 | AT20: 2.7 | AU20: 1.6 | AY20: -7.8 | AZ20: 0 | BA20: 0.2 | BB20: -0.1 | BC20: -3.4 | BD20: 1 | BE20: -0.1 | BF20: 3.3 | BG20: -1.6 | BJ20: 0 | BN20: -13.6 | BO20: 0 | BQ20: -25.7 | BR20: -57.8 | BS20: 0 | CA20: -0.3 | CB20: 36.2 | CC20: 25.8 | CD20: -6 | CE20: 8 | CF20: -4.1 | CJ20: 1.1 | CK20: 3.5 | CL20: -31.4 | CR20: -32.4 | CS20: -25 | CU20: -4 | CV20: 0 | CW20: 0 | CZ20: 1.3 | DA20: 0 | DB20: -0.9 | DD20: 0 | DE20: 1.4 | DF20: 1.6 | DG20: -0.4 | DH20: 1.2 | DI20: 0.6 | DJ20: 0 | DK20: 0 | DL20: 0 | DM20: 0.5 | DN20: 10.9 | DO20: 1.6 | DP20: 0.5 | DQ20: 0.8 | DS20: 0.2 | DT20: 0 | DU20: 0.3 | DV20: 0.8 | DX20: -4.2 | DY20: 0.7 | DZ20: 2.4 | EA20: 2.6 | EB20: 1.3 | EC20: 0.8 | ED20: 4 | EE20: 0.4 | EF20: -4.3 | EG20: -7.6 | EH20: 0 | EI20: 0 | EJ20: 2.6 | EK20: 0 | EL20: 1.6 | EM20: 0.2 | EN20: 0.2 | EO20: 0.2 | EP20: 0 | EQ20: 0 | ER20: 0 | ES20: -0.2 | ET20: 4.6 | EU20: 0 | EV20: 0 | EW20: 0 | EX20: 0.2 | EY20: 1.6 | FA20: 10.7 | FB20: 0 | FC20: 1.1 | FD20: 1.9 | FE20: 1.2 | FH20: -210.4 | FJ20: 1.93394 | FK20: 0 | FM20: 1.5 | FO20: 2.73013 | FP20: -0.2 | FQ20: 1.2 | FR20: 7.16407
A21: 09/04/2025 | B21: 05:30 | E21: -0.3 | F21: 11.2 | I21: -9.1 | J21: 12.8 | M21: -35.9 | N21: -43.4 | O21: -37.7 | P21: 12.2 | Q21: -51.9 | R21: -20.8 | S21: 90.1 | T21: 0 | Y21: 9.9 | Z21: 2.1 | AA21: 0 | AB21: -3.2 | AC21: 3 | AD21: 13.5 | AE21: 2.3 | AI21: 12 | AJ21: 9.4 | AN21: -1.4 | AO21: -17.8 | AP21: -0.2 | AQ21: 1.7 | AR21: -2.3 | AS21: -0.4 | AT21: 2.7 | AU21: 0.8 | AY21: -1.7 | AZ21: 0 | BA21: -0.1 | BB21: 1.2 | BC21: -2.3 | BD21: 1 | BE21: -0.1 | BF21: 5.4 | BG21: -0.1 | BJ21: 0 | BN21: -5.9 | BO21: 0 | BQ21: -20.8 | BR21: -54.7 | BS21: 0 | CA21: -0.3 | CB21: 36.8 | CC21: 24.9 | CD21: -6.2 | CE21: 6.9 | CF21: -4.4 | CJ21: 7.4 | CK21: 10.3 | CL21: -22.1 | CR21: -29 | CS21: -23 | CU21: -4.2 | CV21: 0 | CW21: 0 | CZ21: 1.3 | DA21: -0.1 | DB21: -0.9 | DD21: 0.1 | DE21: 1.2 | DF21: 1.5 | DG21: -1 | DH21: 1.2 | DI21: 0.6 | DJ21: 0 | DK21: 0 | DL21: 0 | DM21: 0.2 | DN21: 10.9 | DO21: 1.6 | DP21: 0.5 | DQ21: 0.8 | DS21: 0.4 | DT21: 0 | DU21: 0.4 | DV21: 0.8 | DX21: -4.2 | DY21: 0.9 | DZ21: 2.5 | EA21: 2.6 | EB21: 1.4 | EC21: 0.8 | ED21: 4 | EE21: 0.4 | EF21: -2 | EG21: -3.9 | EH21: 0 | EI21: 0 | EJ21: 2.6 | EK21: 0 | EL21: 1.7 | EM21: 0.2 | EN21: 0.2 | EO21: 0.2 | EP21: 0 | EQ21: 0 | ER21: 0 | ES21: -0.2 | ET21: 4.7 | EU21: 0 | EV21: 0 | EW21: 0 | EX21: 0.2 | EY21: 1.7 | FA21: 13 | FB21: 0 | FC21: 1.1 | FD21: 2.3 | FE21: 2.3 | FH21: -69.7 | FJ21: 1.92556 | FK21: 0 | FM21: 1.8 | FO21: 2.73272 | FP21: 0.6 | FQ21: 1 | FR21: 8.05828
A22: 09/04/2025 | B22: 06:00 | E22: 26.5 | F22: 16.8 | I22: -10.9 | J22: 0.5 | M22: -31.9 | N22: -42.9 | O22: -38.3 | P22: 16.7 | Q22: -50.3 | R22: -19.4 | S22: 94.1 | T22: 0 | Y22: 12 | Z22: 2.4 | AA22: 0 | AB22: -2.9 | AC22: 3 | AD22: 12.5 | AE22: 2.3 | AI22: 11.6 | AJ22: 12 | AN22: -1.2 | AO22: 7.2 | AP22: 0.4 | AQ22: 2.6 | AR22: -2.3 | AS22: -0.1 | AT22: 2.7 | AU22: 0.9 | AY22: -2.1 | AZ22: 0 | BA22: 0.2 | BB22: 3.5 | BC22: -2.3 | BD22: 1 | BE22: -0.1 | BF22: 4.3 | BG22: 1 | BJ22: 0 | BN22: -5.4 | BO22: 0 | BQ22: -19 | BR22: -51.9 | BS22: 0 | CA22: -0.4 | CB22: 35.1 | CC22: 25.7 | CD22: -5.1 | CE22: 6.3 | CF22: -4.1 | CJ22: 10.1 | CK22: 13 | CL22: -17.7 | CR22: -24.5 | CS22: -20.3 | CU22: -3.7 | CV22: 0 | CW22: 0 | CZ22: 1.3 | DA22: 0 | DB22: -0.9 | DD22: 0 | DE22: 1.3 | DF22: 1.5 | DG22: 0.1 | DH22: 1.2 | DI22: 0.6 | DJ22: 0.1 | DK22: 0 | DL22: 0 | DM22: 0.4 | DN22: 10.4 | DO22: 1.6 | DP22: 0.5 | DQ22: 0.8 | DS22: 0.4 | DT22: 0.2 | DU22: 0.3 | DV22: 0.8 | DX22: -4.1 | DY22: 0.8 | DZ22: 2.5 | EA22: 2.6 | EB22: 1.5 | EC22: 0.8 | ED22: 4 | EE22: 0.3 | EF22: -2.2 | EG22: -4.3 | EH22: 0 | EI22: 0 | EJ22: 2.6 | EK22: 0 | EL22: 1.5 | EM22: 0.2 | EN22: 0.2 | EO22: 0.2 | EP22: 0 | EQ22: 0 | ER22: 2.2 | ES22: -0.2 | ET22: 4.9 | EU22: 0 | EV22: 0 | EW22: 0 | EX22: 0.2 | EY22: 1.8 | FA22: 13.4 | FB22: 0 | FC22: 1.1 | FD22: 1.9 | FE22: 2.3 | FH22: 22.4 | FJ22: 2.2494 | FK22: -0.478 | FM22: 1.8 | FO22: 2.73303 | FP22: 0.5 | FQ22: 0.9 | FR22: 7.70443
... A58: 10/04/2025 | B58: 00:00 | E58: 19.4 | F58: 20.1 | I58: -11.1 | J58: 4.6 | M58: -40.9 | N58: -42 | O58: -20.4 | P58: 29.3 | Q58: -27.1 | R58: -18 | S58: 87.3 | T58: 0 | Y58: 8.4 | Z58: 1.3 | AA58: 0 | AB58: -3.4 | AC58: 2.6 | AD58: 8.8 | AE58: 1.5 | AI58: 10.6 | AJ58: 9 | AN58: -1.8 | AO58: 52.2 | AP58: 7.8 | AQ58: 15.2 | AR58: 3 | AS58: 1.5 | AT58: 2.7 | AU58: 0.5 | AY58: 8.1 | AZ58: -1.4 | BA58: 0.2 | BB58: -0.5 | BC58: 4.4 | BD58: 1 | BE58: -0.1 | BF58: 1.2 | BG58: -0.2 | BJ58: 0 | BN58: 9.6 | BO58: 0 | BQ58: -22.3 | BR58: -54.4 | BS58: 0 | CA58: -0.3 | CB58: 41.9 | CC58: 25.5 | CD58: 5.1 | CE58: 5.8 | CF58: 1.8 | CJ58: 7.3 | CK58: 4.5 | CL58: -44.1 | CR58: 0 | CS58: 0 | CU58: 0 | CV58: 0 | CW58: 0 | CZ58: 1.3 | DA58: -0.1 | DB58: -0.9 | DD58: 0 | DE58: 1.3 | DF58: 2.1 | DG58: 0.9 | DH58: 0.1 | DI58: 0.6 | DJ58: 0 | DK58: 0 | DL58: 0 | DM58: -1.3 | DN58: 9.2 | DO58: 1.6 | DP58: 0.5 | DQ58: 0.8 | DS58: 0 | DT58: -0.1 | DU58: 0.4 | DV58: 0.2 | DX58: -3.8 | DY58: 0 | DZ58: 2.5 | EA58: 2.7 | EB58: 1.3 | EC58: 0.8 | ED58: 4 | EE58: 0 | EF58: -10 | EG58: -10.6 | EH58: 0 | EI58: 0 | EJ58: 2.6 | EK58: -0.3 | EL58: 1.6 | EM58: 0.2 | EN58: 0.2 | EO58: 0.2 | EP58: 0 | EQ58: 0 | ER58: 0 | ES58: -0.2 | ET58: 2.2 | EU58: 0.7 | EV58: 0 | EW58: 0 | EX58: 0.4 | EY58: 1.6 | FA58: 11.3 | FB58: 6.4 | FC58: 1.1 | FD58: 2.5 | FE58: 2.2 | FH58: 150.4 | FJ58: 2.42556 | FK58: 0.496 | FM58: 0 | FO58: 3.10132 | FP58: 0.8 | FQ58: 0.4 | FR58: 7.22288
A59: EJEC | C59: 0 | D59: 0 | E59: 1239.8 | F59: 552.7 | G59: 0 | H59: 0 | I59: -142.8 | J59: 374.5 | K59: 0 | L59: 0 | M59: -345.55 | N59: -448.2 | O59: -380.75 | P59: 968.45 | Q59: -435.15 | R59: -127.7 | S59: 2057.45 | T59: 0.25 | U59: 0 | V59: 0 | W59: 0 | X59: 0 | Y59: 215.05 | Z59: 32.55 | AA59: 15.85 | AB59: -78.75 | AC59: 75.95 | AD59: 337.45 | AE59: 50.1 | AF59: 0 | AG59: 0 | AH59: 0 | AI59: 351.6 | AJ59: 306.05 | AK59: 0 | AL59: 0 | AM59: 0 | AN59: -29.25 | AO59: 784.6 | AP59: 168.5 | AQ59: 301.3 | AR59: 62.4 | AS59: 5.85 | AT59: 64.8 | AU59: 19.4 | AV59: 0 | AW59: 0 | AX59: 0 | AY59: 121.3 | AZ59: -6.95 | BA59: 5.15 | BB59: 66.45 | BC59: 34.55 | BD59: 24 | BE59: -0.05 | BF59: 51.95 | BG59: 86.7 | BH59: 0 | BI59: 0 | BJ59: -18.8 | BK59: 0 | BL59: 0 | BM59: 0 | BN59: 126.75 | BO59: -35.35 | BP59: 0 | BQ59: -310.95 | BR59: -497.95 | BS59: 14.35 | BT59: 0 | BU59: 0 | BV59: 0 | BW59: 0 | BX59: 0 | BY59: 0 | BZ59: 0 | CA59: -6.3 | CB59: 1670.7 | CC59: 961.8 | CD59: 161.7 | CE59: 240.05 | CF59: 62.55 | CG59: 0 | CH59: 0 | CI59: 0 | CJ59: 800.9 | CK59: 816.9 | CL59: -48.8 | CM59: 0 | CN59: 0 | CO59: 0 | CP59: 0 | CQ59: 0 | CR59: -194.15 | CS59: -233.85 | CT59: 0 | CU59: -58.45 | CV59: 72.55 | CW59: 0.1 | CX59: 0 | CY59: 0 | CZ59: 31.2 | DA59: -1 | DB59: -22.05 | DC59: 0 | DD59: -0.45 | DE59: 30.8 | DF59: 42.7 | DG59: -17.95 | DH59: 28.05 | DI59: 12.6 | DJ59: 0.6 | DK59: -6.8 | DL59: -16.1 | DM59: 1.15 | DN59: 224.75 | DO59: 37.3 | DP59: 12 | DQ59: 17.85 | DR59: 0 | DS59: -28.95 | DT59: 0.75 | DU59: 10.15 | DV59: 20.5 | DW59: 0 | DX59: -96.9 | DY59: 16.35 | DZ59: 67.35 | EA59: 63.9 | EB59: 36.8 | EC59: 19.2 | ED59: 96 | EE59: 26.2 | EF59: -120.8 | EG59: -141.65 | EH59: 0.05 | EI59: 0.35 | EJ59: 62.3 | EK59: -0.55 | EL59: 39.7 | EM59: 4.8 | EN59: 4.8 | EO59: 4.8 | EP59: 0.2 | EQ59: 16.85 | ER59: 144.35 | ES59: -4.8 | ET59: 179.45 | EU59: 99.55 | EV59: 91.3 | EW59: 15.15 | EX59: 11.3 | EY59: 43.8 | EZ59: 0 | FA59: 241.1 | FB59: 32.1 | FC59: 25.95 | FD59: 46.4 | FE59: 53.55 | FF59: 0 | FG59: 0 | FH59: 11359.35 | FJ59: 58.471845 | FK59: -13.0415 | FL59: 0 | FM59: 26.75 | FN59: 0 | FO59: 71.78337 | FP59: 11.8 | FQ59: 43.8 | FR59: 199.56372

Sheet DEMANDA_AREAS
B3: miércoles, 9 de Abril del 2025
B5: REPORTE DE LA DEMANDA POR ÁREAS Y SUBAREAS OPERATIVAS (MW)
B6: FECHA HORA | C6: DEMANDA | E6: AREA | H6: SUBAREAS
C7: INTERCAMBIOS INTERNACIONALES | D7: SEIN | E7: NORTE | F7: CENTRO | G7: SUR | H7: ELECTROANDES
B8: 00:30 | C8: 0 | D8: 6552.7 | E8: 960.8267 | F8: 3908.4947 | G8: 1683.3786 | H8: 194.5988
B9: 01:00 | C9: 0 | D9: 6331.2 | E9: 896.9352 | F9: 3769.9737 | G9: 1664.2911 | H9: 200.5755
B10: 01:30 | C10: 0 | D10: 6296.1 | E10: 927.0381 | F10: 3706.5251 | G10: 1662.5368 | H10: 226.0002
B11: 02:00 | C11: 0 | D11: 6156.5 | E11: 885.8462 | F11: 3628.8299 | G11: 1641.8239 | H11: 218.7371
B12: 02:30 | C12: 0 | D12: 6162.2 | E12: 868.2347 | F12: 3658.0291 | G12: 1635.9362 | H12: 219.0244
B13: 03:00 | C13: 0 | D13: 6167.2 | E13: 891.5455 | F13: 3623.4674 | G13: 1652.1871 | H13: 217.6527
B14: 03:30 | C14: 0 | D14: 6132.2 | E14: 886.9393 | F14: 3616.1092 | G14: 1629.1515 | H14: 213.2295
B15: 04:00 | C15: 0 | D15: 6029.6 | E15: 859.1579 | F15: 3515.718 | G15: 1654.7241 | H15: 215.6838
B16: 04:30 | C16: 0 | D16: 6183.9 | E16: 886.9872 | F16: 3643.0794 | G16: 1653.8334 | H16: 209.5864
B17: 05:00 | C17: 0 | D17: 6178.9 | E17: 903.4005 | F17: 3611.4864 | G17: 1664.0131 | H17: 187.4776
B18: 05:30 | C18: 0 | D18: 6352.8 | E18: 934.8917 | F18: 3730.8842 | G18: 1687.0241 | H18: 179.9719
B19: 06:00 | C19: 0 | D19: 6490.3 | E19: 940.4954 | F19: 3872.3486 | G19: 1677.456 | H19: 171.7258
... B59: ENERGÍA | C59: -315.69376 | D59: 170418.04 | E59: 26663.388 | F59: 102478.26 | G59: 41276.397 | H59: 5192.908
B61: LEYENDA:
D63: Potencia recibida del Ecuador
D64: Potencia entregada al Ecuador

Sheet DEMANDA_UL
B3: miércoles, 9 de Abril del 2025
B5: POTENCIA DE LOS GRANDES USUARIOS LIBRES (MW)
B6: FECHA HORA | C6: GRANDES USUARIOS LIBRES DEL ÁREA NORTE | X6: GRANDES USUARIOS LIBRES DEL ÁREA CENTRO | BP6: GRANDES USUARIOS LIBRES DEL ÁREA SUR
C7: ARCA CONTINENTAL LINDLEY S.A. | D7: AUSTRAL GROUP S.A.A | E7: CEMENTOS PACASMAYO | F7: CORPORACIÓN PESQUERA INCA S.A.C. | G7: CREDITEX: CIA IND.TEXTIL CREDISA | H7: HIPERMERCADOS TOTTUS S.A | I7: INDUSTRIA TEXTIL PIURA | J7: MINERA BOROO MISQUICHILCA S.A. | K7: MINERA GOLD FIELDS | L7: MINERA HORIZONTE | M7: MINERA MARSA | N7: MINERA MISKY MAYO | O7: MINERA YANACOCHA | P7: OPEN PLAZA | Q7: PESQUERA DIAMANTE | R7: PETROPERU | S7: REAL PLAZA S.R.L. | T7: SIDER PERU | U7: SUPERMERCADOS PERUANOS S.A. | V7: TRUPAL S.A. | W7: UNIÓN DE CERVECERÍAS PERUANAS BACKUS Y JOHNSTON S. | X7: ACEROS AREQUIPA | Y7: ADMINISTRADORA JOCKEY PLAZA SHOPPING CENTER S.A. | Z7: ALICORP | AA7: ARCA CONTINENTAL LINDLEY S.A. | AB7: AUSTRAL GROUP S.A.A | AC7: COMPAÑIA MINERA CONDESTABLE | AD7: CORPORACIÓN PESQUERA INCA S.A.C. | AE7: CREDITEX: CIA IND.TEXTIL CREDISA | AF7: FUNDICION CHILCA S.A. | AG7: HIPERMERCADOS TOTTUS S.A | AH7: INMOBILIARIA KANPU S.A. | AI7: INMUEBLES PANAMERICANA S.A. | AJ7: KIMBERLY-CLARK PERU | AK7: LECHE GLORIA S.A. | AL7: MALL AVENTURA S.A. | AM7: MARCOBRE S.A.C. | AN7: MINERA ANTAMINA | AO7: MINERA ARES | AP7: MINERA BUENAVENTURA | AQ7: MINERA CHINALCO PERÚ S.A. | AR7: MINERA SHOUXIN PERU S.A. | AS7: MINERA VOLCAN | AT7: MINSUR | AU7: MOLYCOP-ADESUR | AV7: NEXA RESOURCES CAJAMARQUILLA S.A. | AW7: NEXA RESOURCES PERÚ S.A.A. | AX7: OPEN PLAZA | AY7: OPP FILM | AZ7: OWENS-ILLINOIS PERÚ S.A. | BA7: PAPELERA NACIONAL S.A. | BB7: PESQUERA DIAMANTE | BC7: QUIMPAC S.A. | BD7: REAL PLAZA S.R.L. | BE7: REFINERIA LA PAMPILLA S.A.A | BF7: SAGA FALABELLA | BG7: SAN MIGUEL INDUSTRIAS PET S.A. | BH7: SHOUGANG HIERRO PERU | BI7: SOFTYS PERU S.A.C. | BJ7: SUPERMERCADOS PERUANOS S.A. | BK7: TEJIDOS SAN JACINTO | BL7: TREN URBANO DE LIMA S.A. | BM7: TRUPAL S.A. | BN7: UNACEM PERU S.A. | BO7: UNIÓN DE CERVECERÍAS PERUANAS BACKUS Y JOHNSTON S. | BP7: ANGLO AMERICAN QUELLAVECO S.A. | BQ7: ARCA CONTINENTAL LINDLEY S.A. | BR7: CAL & CEMENTO SUR S.A. | BS7: COMPAÑIA MINERA ANTAPACCAY S.A. | BT7: COMPAÑÍA MINERA CHUNGAR SAC | BU7: COMPAÑIA MINERA SAN IGNACIO DE MOROCOCHA S.A.A. | BV7: EL BROCAL .S.A. | BW7: EMPRESA ADMINISTRADORA CERRO S.A.C. | BX7: EMPRESA MINERA LOS QUENUALES S.A.C. | BY7: HIPERMERCADOS TOTTUS S.A | BZ7: HUDBAY PERU S.A.C. | CA7: INDUSTRIA CACHIMAYO | CB7: MALL AVENTURA S.A. | CC7: MINERA ARES | CD7: MINERA BUENAVENTURA | CE7: MINERA CERRO VERDE | CF7: MINERA CORONA | CG7: MINERA LAS BAMBAS S.A. | CH7: MINERA VOLCAN | CI7: MINSUR | CJ7: MOLYCOP-ADESUR | CK7: NEXA RESOURCES PERÚ S.A.A. | CL7: OXIDOS DE PASCO S.A.C. | CM7: PESQUERA DIAMANTE | CN7: REAL PLAZA S.R.L. | CO7: SOBREANDES S.A.C. | CP7: SOUTHERN PERU CC | CQ7: SUPERMERCADOS PERUANOS S.A. | CR7: UNACEM PERU S.A. | CS7: UNIÓN DE CERVECERÍAS PERUANAS BACKUS Y JOHNSTON S. | CT7: YURA
B8: 00:30 | E8: 20.20288 | J8: 20.244 | K8: 26.4677 | L8: 12.932 | M8: 14.5741 | N8: 13.26 | O8: 32.32 | R8: 52.645 | T8: 38.6124 | V8: 9.2 | X8: 143.93228 | Z8: 9.71571 | AC8: 15.08 | AF8: 2.5 | AH8: 4.8439 | AJ8: 5.33786 | AK8: 0 | AM8: 48.63217 | AN8: 28.52737 | AO8: 29.06766 | AP8: 0.81 | AQ8: 161.95428 | AS8: 39.21877 | AT8: 31.10523 | AV8: 189.28714 | AW8: 13.2495 | AY8: 8.36 | BA8: 2.5 | BC8: 72.47959 | BE8: 20.4 | BI8: 17.30182 | BK8: 5.56915 | BN8: 39.3 | BO8: 1.96 | BP8: 150.63539 | BR8: 3.5962 | BS8: 123.98972 | BT8: 14.64444 | BV8: 37.2958 | BW8: 3.85819 | BZ8: 91.8186 | CA8: 0 | CC8: 0.74 | CD8: 26.6511 | CE8: 343.71139 | CF8: 11.2751 | CG8: 142.921 | CH8: 17.89481 | CK8: 14.21 | CL8: 4.61037 | CP8: 292.83 | CR8: 34.664 | CT8: 29.82199
B9: 01:00 | E9: 20.48546 | J9: 18.404 | K9: 27.2088 | L9: 12.817 | M9: 13.8653 | N9: 13.65 | O9: 32.256 | R9: 52.715 | T9: 35.4849 | V9: 9.2 | X9: 136.64994 | Z9: 8.93161 | AC9: 16.21 | AF9: 2.1 | AH9: 3.0189 | AJ9: 5.33431 | AK9: 0 | AM9: 47.53266 | AN9: 26.26305 | AO9: 28.88363 | AP9: 0.7 | AQ9: 157.60484 | AS9: 38.76865 | AT9: 32.5705 | AV9: 192.19302 | AW9: 13.2162 | AY9: 8.35 | BA9: 2.6 | BC9: 63.29458 | BE9: 20.4 | BI9: 17.28916 | BK9: 5.55235 | BN9: 44.79 | BO9: 1.89 | BP9: 154.47068 | BR9: 3.9674 | BS9: 123.34421 | BT9: 16.03015 | BV9: 36.7392 | BW9: 3.96348 | BZ9: 93.3793 | CA9: 0 | CC9: 0.69 | CD9: 26.86295 | CE9: 344.62373 | CF9: 11.323 | CG9: 141.676 | CH9: 17.89631 | CK9: 14.43 | CL9: 4.51998 | CP9: 293.47 | CR9: 34.416 | CT9: 29.56805
B10: 01:30 | E10: 20.30371 | J10: 17.8187 | K10: 27.1323 | L10: 13.682 | M10: 13.3442 | N10: 13.81 | O10: 31.016 | R10: 52.965 | T10: 28.0623 | V10: 9.3 | X10: 95.46098 | Z10: 9.27907 | AC10: 16.15 | AF10: 1.8 | AH10: 6.536 | AJ10: 5.31128 | AK10: 0 | AM10: 46.1963 | AN10: 21.54375 | AO10: 29.4071 | AP10: 0.64 | AQ10: 163.65988 | AS10: 38.8247 | AT10: 34.13275 | AV10: 192.06109 | AW10: 13.4684 | AY10: 8.29 | BA10: 2.8 | BC10: 66.24039 | BE10: 20.4 | BI10: 17.70011 | BK10: 5.54136 | BN10: 47.93 | BO10: 2.11 | BP10: 153.43235 | BR10: 4.0908 | BS10: 124.86932 | BT10: 15.59078 | BV10: 36.6811 | BW10: 4.0073 | BZ10: 93.7155 | CA10: 0 | CC10: 0.73 | CD10: 27.12493 | CE10: 346.98702 | CF10: 11.21 | CG10: 139.58 | CH10: 17.28981 | CK10: 15.1 | CL10: 4.47223 | CP10: 298.23 | CR10: 34.012 | CT10: 29.19871
B11: 02:00 | E11: 20.30617 | J11: 18.496 | K11: 27.0983 | L11: 13.982 | M11: 14.0439 | N11: 13.77 | O11: 29.822 | R11: 52.925 | T11: 46.0202 | V11: 9.4 | X11: 132.21795 | Z11: 9.67078 | AC11: 16.21 | AF11: 4.3 | AH11: 4.9655 | AJ11: 5.27359 | AK11: 0 | AM11: 48.10569 | AN11: 23.55609 | AO11: 28.98205 | AP11: 0.44 | AQ11: 160.97856 | AS11: 39.06402 | AT11: 33.96024 | AV11: 193.38476 | AW11: 13.2916 | AY11: 8.3 | BA11: 2.6 | BC11: 73.00208 | BE11: 20.4 | BI11: 17.71593 | BK11: 5.40372 | BN11: 52.47 | BO11: 2.13 | BP11: 155.26681 | BR11: 4.0444 | BS11: 125.10507 | BT11: 15.93072 | BV11: 36.4929 | BW11: 3.7307 | BZ11: 95.0244 | CA11: 0 | CC11: 0.69 | CD11: 27.23548 | CE11: 346.26076 | CF11: 11.2848 | CG11: 138.384 | CH11: 17.94139 | CK11: 14.4 | CL11: 4.44242 | CP11: 289.34 | CR11: 34.542 | CT11: 28.52186
B12: 02:30 | E12: 20.13133 | J12: 20.261 | K12: 26.981 | L12: 13.463 | M12: 13.8895 | N12: 13.66 | O12: 29.224 | R12: 52.476 | T12: 40.2817 | V12: 9.4 | X12: 150.2462 | Z12: 9.98886 | AC12: 15.78 | AF12: 5.8 | AH12: 3.3655 | AJ12: 5.22184 | AK12: 0 | AM12: 47.64424 | AN12: 23.66062 | AO12: 28.91415 | AP12: 0.41 | AQ12: 159.58529 | AS12: 39.62796 | AT12: 34.88884 | AV12: 194.4038 | AW12: 14.5097 | AY12: 8.46 | BA12: 2.6 | BC12: 72.3903 | BE12: 20.4 | BI12: 17.36799 | BK12: 5.36343 | BN12: 51.1 | BO12: 2.05 | BP12: 156.42041 | BR12: 3.9727 | BS12: 126.02039 | BT12: 15.72527 | BV12: 34.3747 | BW12: 3.87202 | BZ12: 92.1478 | CA12: 0 | CC12: 0.72 | CD12: 27.74755 | CE12: 343.08844 | CF12: 11.4154 | CG12: 136.44 | CH12: 18.23203 | CK12: 15.1 | CL12: 4.44864 | CP12: 285.22 | CR12: 31.545 | CT12: 28.55239
B13: 03:00 | E13: 20.05557 | J13: 21.8923 | K13: 26.863 | L13: 13.636 | M13: 14.8205 | N13: 13.74 | O13: 29.54 | R13: 52.699 | T13: 28.1086 | V13: 9.3 | X13: 135.9745 | Z13: 9.79016 | AC13: 15.38 | AF13: 1.9 | AH13: 4.6414 | AJ13: 4.81592 | AK13: 0 | AM13: 47.33534 | AN13: 22.72127 | AO13: 28.18146 | AP13: 0.67 | AQ13: 160.81305 | AS13: 38.36593 | AT13: 34.19668 | AV13: 194.41767 | AW13: 14.6305 | AY13: 8.19 | BA13: 2.6 | BC13: 72.87267 | BE13: 20.4 | BI13: 17.20415 | BK13: 5.25386 | BN13: 50.64 | BO13: 2.09 | BP13: 156.13967 | BR13: 4.0531 | BS13: 122.68903 | BT13: 16.08638 | BV13: 34.6528 | BW13: 3.96593 | BZ13: 91.6255 | CA13: 0.39452 | CC13: 0.69 | CD13: 27.3742 | CE13: 344.85398 | CF13: 11.7412 | CG13: 145.254 | CH13: 17.85299 | CK13: 15.51 | CL13: 4.46955 | CP13: 296.37 | CR13: 31.956 | CT13: 28.36323
B14: 03:30 | E14: 19.25549 | J14: 20.523 | K14: 27.2118 | L14: 13.331 | M14: 15.0986 | N14: 13.58 | O14: 29.184 | R14: 52.436 | T14: 34.6821 | V14: 9.2 | X14: 143.25822 | Z14: 9.65647 | AC14: 15.18 | AF14: 1.4 | AH14: 4.051 | AJ14: 5.05719 | AK14: 0 | AM14: 45.45303 | AN14: 22.16207 | AO14: 29.0488 | AP14: 0.48 | AQ14: 159.25783 | AS14: 39.53776 | AT14: 32.52678 | AV14: 194.41041 | AW14: 13.9308 | AY14: 6.27 | BA14: 2.5 | BC14: 72.84189 | BE14: 20.4 | BI14: 17.6282 | BK14: 5.35456 | BN14: 51.5 | BO14: 2.06 | BP14: 154.69465 | BR14: 3.8351 | BS14: 123.5605 | BT14: 16.21332 | BV14: 35.269 | BW14: 4.02736 | BZ14: 92.4602 | CA14: 0.5865 | CC14: 0.74 | CD14: 26.97391 | CE14: 326.71808 | CF14: 11.7715 | CG14: 142.253 | CH14: 17.00748 | CK14: 13.99 | CL14: 4.43756 | CP14: 284.27 | CR14: 34.678 | CT14: 28.72203
B15: 04:00 | E15: 19.5511 | J15: 19.9383 | K15: 27.0497 | L15: 14.205 | M15: 14.227 | N15: 13.24 | O15: 29.538 | R15: 53.05 | T15: 46.9528 | V15: 9 | X15: 117.60186 | Z15: 9.6239 | AC15: 15.26 | AF15: 1.5 | AH15: 4.6801 | AJ15: 5.19055 | AK15: 0 | AM15: 46.18225 | AN15: 21.28007 | AO15: 28.89017 | AP15: 0.18 | AQ15: 154.06528 | AS15: 38.82039 | AT15: 32.66249 | AV15: 195.32041 | AW15: 13.1961 | AY15: 7.34 | BA15: 2.7 | BC15: 72.86882 | BE15: 20.4 | BI15: 17.40073 | BK15: 5.34272 | BN15: 51 | BO15: 2.07 | BP15: 154.46994 | BR15: 3.7513 | BS15: 123.29068 | BT15: 16.39045 | BV15: 34.6386 | BW15: 3.88656 | BZ15: 92.8398 | CA15: 0.79364 | CC15: 0.71 | CD15: 27.04933 | CE15: 339.99257 | CF15: 11.6892 | CG15: 137.116 | CH15: 17.24721 | CK15: 14.61 | CL15: 4.73913 | CP15: 290.68 | CR15: 34.204 | CT15: 28.98824
B16: 04:30 | E16: 19.37521 | J16: 20.0331 | K16: 26.7609 | L16: 13.956 | M16: 15.1719 | N16: 13.57 | O16: 28.952 | R16: 52.691 | T16: 42.9014 | V16: 2.3 | X16: 161.85942 | Z16: 9.61041 | AC16: 14.72 | AF16: 1.6 | AH16: 3.9342 | AJ16: 5.28152 | AK16: 0 | AM16: 45.82459 | AN16: 20.997 | AO16: 28.63924 | AP16: 1.65 | AQ16: 159.45921 | AS16: 38.77761 | AT16: 31.43438 | AV16: 191.49552 | AW16: 13.134 | AY16: 8.59 | BA16: 2.7 | BC16: 72.86392 | BE16: 20.4 | BI16: 17.31183 | BK16: 5.48907 | BN16: 52.01 | BO16: 2.17 | BP16: 154.73111 | BR16: 3.7112 | BS16: 121.75737 | BT16: 15.9014 | BV16: 34.4265 | BW16: 3.90366 | BZ16: 93.1868 | CA16: 0.95993 | CC16: 0.72 | CD16: 25.22062 | CE16: 345.57008 | CF16: 11.5457 | CG16: 139.396 | CH16: 17.22539 | CK16: 13.38 | CL16: 4.73445 | CP16: 295.93 | CR16: 34.039 | CT16: 28.81628
B17: 05:00 | E17: 19.4871 | J17: 19.6455 | K17: 26.7831 | L17: 13.365 | M17: 15.0148 | N17: 13.42 | O17: 28.496 | R17: 52.77 | T17: 39.9856 | V17: 2 | X17: 146.97231 | Z17: 9.72937 | AC17: 14.69 | AF17: 1.5 | AH17: 5.4041 | AJ17: 5.03627 | AK17: 0 | AM17: 44.91825 | AN17: 21.94385 | AO17: 29.40141 | AP17: 2.1 | AQ17: 159.6908 | AS17: 38.71526 | AT17: 31.48787 | AV17: 191.92251 | AW17: 13.0458 | AY17: 9.09 | BA17: 2.7 | BC17: 73.00176 | BE17: 20.4 | BI17: 17.33708 | BK17: 5.5242 | BN17: 51.78 | BO17: 1.99 | BP17: 152.84055 | BR17: 3.4622 | BS17: 125.26278 | BT17: 16.75173 | BV17: 34.3019 | BW17: 4.37541 | BZ17: 92.3235 | CA17: 3.15712 | CC17: 0.7 | CD17: 24.48726 | CE17: 345.69697 | CF17: 11.4873 | CG17: 138.954 | CH17: 17.52785 | CK17: 14.27 | CL17: 4.75297 | CP17: 291.27 | CR17: 34.534 | CT17: 28.89492
B18: 05:30 | E18: 19.49467 | J18: 19.6523 | K18: 27.2759 | L18: 12.029 | M18: 14.7418 | N18: 13.22 | O18: 28.648 | R18: 52.973 | T18: 32.6803 | V18: 0.1 | X18: 59.8993 | Z18: 9.68365 | AC18: 15.01 | AF18: 2.2 | AH18: 6.7437 | AJ18: 5.08865 | AK18: 0 | AM18: 43.18166 | AN18: 23.94558 | AO18: 28.74 | AP18: 1.93 | AQ18: 161.09494 | AS18: 37.31085 | AT18: 31.38199 | AV18: 194.79463 | AW18: 13.4084 | AY18: 8.85 | BA18: 2.6 | BC18: 72.91766 | BE18: 20.4 | BI18: 17.1576 | BK18: 5.32441 | BN18: 52 | BO18: 1.97 | BP18: 152.30097 | BR18: 3.4611 | BS18: 125.06028 | BT18: 16.54204 | BV18: 33.3564 | BW18: 3.85894 | BZ18: 92.8859 | CA18: 4.16511 | CC18: 0.7 | CD18: 24.21093 | CE18: 344.89974 | CF18: 10.9936 | CG18: 137.445 | CH18: 18.19284 | CK18: 13.9 | CL18: 4.62531 | CP18: 293.97 | CR18: 34.64 | CT18: 28.94206
B19: 06:00 | E19: 20.40773 | J19: 19.4561 | K19: 28.0002 | L19: 11.33 | M19: 15.3881 | N19: 13.7 | O19: 28.868 | R19: 52.931 | T19: 36.6674 | V19: 0 | X19: 156.41675 | Z19: 9.57245 | AC19: 15.4 | AF19: 1.7 | AH19: 4.1897 | AJ19: 5.10208 | AK19: 0 | AM19: 44.35422 | AN19: 23.95392 | AO19: 25.73931 | AP19: 1.54 | AQ19: 161.11824 | AS19: 35.70283 | AT19: 31.74633 | AV19: 194.3586 | AW19: 13.4439 | AY19: 8.19 | BA19: 2.7 | BC19: 72.94064 | BE19: 20.4 | BI19: 17.23183 | BK19: 5.38222 | BN19: 50.45 | BO19: 1.94 | BP19: 153.1879 | BR19: 3.5701 | BS19: 124.55879 | BT19: 16.22221 | BV19: 33.5888 | BW19: 3.65085 | BZ19: 91.7533 | CA19: 4.11379 | CC19: 0.71 | CD19: 24.02623 | CE19: 337.30152 | CF19: 10.5401 | CG19: 136.752 | CH19: 18.38774 | CK19: 12.93 | CL19: 4.46612 | CP19: 292.6 | CR19: 33.722 | CT19: 28.32157
... B55: 00:00 | E55: 27.06872 | J55: 19.4241 | K55: 26.4674 | L55: 12.762 | M55: 14.2244 | N55: 13.52 | O55: 34.308 | R55: 54.053 | T55: 40.1488 | V55: 7 | X55: 45.78229 | Z55: 9.82773 | AC55: 14.43 | AF55: 2.6 | AH55: 3.8132 | AJ55: 5.27586 | AK55: 0 | AM55: 26.83078 | AN55: 22.22975 | AO55: 30.40686 | AP55: 0.83 | AQ55: 162.15059 | AS55: 36.74428 | AT55: 30.64831 | AV55: 188.39621 | AW55: 14.523 | AY55: 6.11 | BA55: 1.9 | BC55: 71.41379 | BE55: 19.5 | BI55: 18.05538 | BK55: 5.64556 | BN55: 54.59 | BO55: 2.14 | BP55: 155.53696 | BR55: 3.5482 | BS55: 123.01875 | BT55: 14.90806 | BV55: 32.8998 | BW55: 3.83695 | BZ55: 93.9112 | CA55: 3.31184 | CC55: 0.67 | CD55: 24.31958 | CE55: 346.6805 | CF55: 11.5556 | CG55: 136.407 | CH55: 17.68138 | CK55: 16.56 | CL55: 5.01503 | CP55: 292.58 | CR55: 34.59 | CT55: 23.9976
B56: MWh | C56: 0 | D56: 0 | E56: 510.40553 | F56: 0 | G56: 0 | H56: 0 | I56: 0 | J56: 479.89875 | K56: 654.9184 | L56: 296.1215 | M56: 317.55135 | N56: 319.28 | O56: 701.32 | P56: 0 | Q56: 0 | R56: 1268.88 | S56: 0 | T56: 829.12985 | U56: 0 | V56: 66.35 | W56: 0 | X56: 2198.1522 | Y56: 0 | Z56: 236.76698 | AA56: 0 | AB56: 0 | AC56: 367.055 | AD56: 0 | AE56: 0 | AF56: 56.05 | AG56: 0 | AH56: 88.49305 | AI56: 0 | AJ56: 118.96792 | AK56: 0 | AL56: 0 | AM56: 774.61806 | AN56: 527.93716 | AO56: 661.54283 | AP56: 18.01 | AQ56: 3848.3063 | AR56: 0 | AS56: 871.91373 | AT56: 767.5173 | AU56: 0 | AV56: 4148.6327 | AW56: 332.6008 | AX56: 0 | AY56: 164.245 | AZ56: 0 | BA56: 63.65 | BB56: 0 | BC56: 1565.9037 | BD56: 0 | BE56: 470.65 | BF56: 0 | BG56: 0 | BH56: 0 | BI56: 422.00582 | BJ56: 0 | BK56: 133.27384 | BL56: 0 | BM56: 0 | BN56: 1039.42 | BO56: 50.635 | BP56: 3670.9614 | BQ56: 0 | BR56: 85.6601 | BS56: 2892.4388 | BT56: 365.78048 | BU56: 0 | BV56: 799.89005 | BW56: 93.388145 | BX56: 0 | BY56: 0 | BZ56: 2232.5702 | CA56: 55.32233 | CB56: 0 | CC56: 16.935 | CD56: 597.81845 | CE56: 8079.4524 | CF56: 265.62675 | CG56: 3307.5805 | CH56: 420.25263 | CI56: 0 | CJ56: 0 | CK56: 353.015 | CL56: 109.25066 | CM56: 0 | CN56: 0 | CO56: 0 | CP56: 6895.805 | CQ56: 0 | CR56: 730.074 | CS56: 0 | CT56: 418.24395
B59: Nota :
B60: Información proporcionada por la empresas
C62: DATOS ESTIMADOS
C64: SIN DATOS

Sheet TIPO_RECURSO
B3: miércoles, 9 de Abril del 2025
B5: REPORTE POTENCIA GENERADA POR TIPO DE RECURSO
B6: HORA | C6: H. PASADA | D6: H. REGULACION | E6: GAS DE CAMISEA | F6: GAS DE MALACAS | G6: DIESEL | H6: RESIDUAL | I6: NAFTA+GAS DE REFINERIA | J6: FLEXIGAS+GAS DE REFINERIA | K6: BAGAZO | L6: BIOGAS | M6: SOLAR | N6: EOLICA | O6: TOTAL | T6: EMPRESA | U6: CENTRAL | V6: HIDROELECTRICA DE PASADA | W6: HIDROELECTRICA DE REGULACION
B7: 00:30 | C7: 1112.4 | D7: 3346.8 | E7: 1557.4 | F7: 0 | I7: =+DESPACHO_EJECUTADO!FB11+DESPACHO_EJECUTADO!FC11 -> 43.7 | K7: 16.4 | L7: 9.2 | M7: 0 | N7: 466.8 | O7: =+SUM(C7:N7) -> 6552.7 | T7: ANDEAN POWER S.A.C. | U7: C.H.CARHUAC | V7: 486.95
B8: 01:00 | C8: 1110.3 | D8: 3186.2 | E8: 1555.3 | F8: 0 | I8: =+DESPACHO_EJECUTADO!FB12+DESPACHO_EJECUTADO!FC12 -> 43.9 | K8: 16.5 | L8: 9.2 | M8: 0 | N8: 409.8 | O8: =+SUM(C8:N8) -> 6331.2 | T8: ASOCIACIÓN SANTA LUCIA DE CHACAS | U8: C.H. HUALLIN | V8: 71.35
B9: 01:30 | C9: 1114.2 | D9: 3162.6 | E9: 1566 | F9: 0 | I9: =+DESPACHO_EJECUTADO!FB13+DESPACHO_EJECUTADO!FC13 -> 44.1 | K9: 16.6 | L9: 9.2 | M9: 0 | N9: 383.4 | O9: =+SUM(C9:N9) -> 6296.1 | T9: CELEPSA | U9: C.H. EL PLATANAL | W9: 4963.3
B10: 02:00 | C10: 1095.5 | D10: 3024 | E10: 1557.9 | F10: 0 | I10: =+DESPACHO_EJECUTADO!FB14+DESPACHO_EJECUTADO!FC14 -> 44.8 | K10: 16.7 | L10: 9.2 | M10: 0 | N10: 408.4 | O10: =+SUM(C10:N10) -> 6156.5 | T10: CELEPSA RENOVABLES S.R.L. | U10: C.H. MARAÑON | V10: 472.8
B11: 02:30 | C11: 1041.2 | D11: 3080.7 | E11: 1557.3 | F11: 0 | I11: =+DESPACHO_EJECUTADO!FB15+DESPACHO_EJECUTADO!FC15 -> 44.2 | K11: 16.6 | L11: 9.2 | M11: 0 | N11: 413 | O11: =+SUM(C11:N11) -> 6162.2 | T11: CHINANGO S.A.C. | U11: C.H. CHIMAY | W11: 3419.15
B12: 03:00 | C12: 1046.3 | D12: 3091.2 | E12: 1559 | F12: 0 | I12: =+DESPACHO_EJECUTADO!FB16+DESPACHO_EJECUTADO!FC16 -> 43.7 | K12: 16.5 | L12: 9.2 | M12: 0 | N12: 401.3 | O12: =+SUM(C12:N12) -> 6167.2 | U12: C.H. YANANGO | V12: 1016.6
B13: 03:30 | C13: 1044.7 | D13: 3081.5 | E13: 1558.2 | F13: 0 | I13: =+DESPACHO_EJECUTADO!FB17+DESPACHO_EJECUTADO!FC17 -> 44 | K13: 16.6 | L13: 9.2 | M13: 0 | N13: 378 | O13: =+SUM(C13:N13) -> 6132.2 | T13: EGASA | U13: C.H. CHARCANI III | V13: 154.5
B14: 04:00 | C14: 1032.3 | D14: 3007.5 | E14: 1561 | F14: 0 | I14: =+DESPACHO_EJECUTADO!FB18+DESPACHO_EJECUTADO!FC18 -> 43.9 | K14: 16.5 | L14: 9.2 | M14: 0 | N14: 359.2 | O14: =+SUM(C14:N14) -> 6029.6 | U14: C.H. CHARCANI IV | W14: 242.45
B15: 04:30 | C15: 1035.6 | D15: 3211.1 | E15: 1559.1 | F15: 0 | I15: =+DESPACHO_EJECUTADO!FB19+DESPACHO_EJECUTADO!FC19 -> 44.5 | K15: 16.5 | L15: 9.2 | M15: 0 | N15: 307.9 | O15: =+SUM(C15:N15) -> 6183.9 | U15: C.H. CHARCANI V | W15: 3197.05
B16: 05:00 | C16: 1053.7 | D16: 3199.9 | E16: 1559.7 | F16: 0 | I16: =+DESPACHO_EJECUTADO!FB20+DESPACHO_EJECUTADO!FC20 -> 44.4 | K16: 16.6 | L16: 9.2 | M16: 0 | N16: 295.4 | O16: =+SUM(C16:N16) -> 6178.9 | U16: C.H. CHARCANI VI | W16: 215.15
B17: 05:30 | C17: 1091.4 | D17: 3370.6 | E17: 1559 | F17: 0 | I17: =+DESPACHO_EJECUTADO!FB21+DESPACHO_EJECUTADO!FC21 -> 44.5 | K17: 16.5 | L17: 9.2 | M17: 0 | N17: 261.6 | O17: =+SUM(C17:N17) -> 6352.8 | T17: EGEJUNIN | U17: C.H. HUASAHUASI I | V17: 407.15
B18: 06:00 | C18: 1143.7 | D18: 3437.1 | E18: 1555.9 | F18: 0 | I18: =+DESPACHO_EJECUTADO!FB22+DESPACHO_EJECUTADO!FC22 -> 44 | K18: 16.7 | L18: 9.2 | M18: 4.3 | N18: 279.4 | O18: =+SUM(C18:N18) -> 6490.3 | U18: C.H. RUNATULLO II | V18: 484.4
B19: 06:30 | C19: 1157.9 | D19: 3389.6 | E19: 1572.1 | F19: 0 | I19: =+DESPACHO_EJECUTADO!FB23+DESPACHO_EJECUTADO!FC23 -> 43.4 | K19: 16.5 | L19: 9.2 | M19: 64.7 | N19: 281.2 | O19: =+SUM(C19:N19) -> 6534.6 | U19: C.H. RUNATULLO III | V19: 486.6
B20: 07:00 | C20: 1163.5 | D20: 3294.9 | E20: 1560.2 | F20: 0 | I20: =+DESPACHO_EJECUTADO!FB24+DESPACHO_EJECUTADO!FC24 -> 43.8 | K20: 16.6 | L20: 9.2 | M20: 207.8 | N20: 242.4 | O20: =+SUM(C20:N20) -> 6538.4 | U20: C.H. SANTA CRUZ I | V20: 234.05
B21: 07:30 | C21: 1161.7 | D21: 3387.3 | E21: 1561.7 | F21: 0 | I21: =+DESPACHO_EJECUTADO!FB25+DESPACHO_EJECUTADO!FC25 -> 44.2 | K21: 16.5 | L21: 9.2 | M21: 330.5 | N21: 229 | O21: =+SUM(C21:N21) -> 6740.1 | T21: EGEMSA | U21: C.H. MACHUPICCHU | V21: 3928.15
B22: 08:00 | C22: 1161.7 | D22: 3448.9 | E22: 1583.4 | F22: 0 | I22: =+DESPACHO_EJECUTADO!FB26+DESPACHO_EJECUTADO!FC26 -> 44.6 | K22: 16.6 | L22: 9.2 | M22: 385.3 | N22: 189.8 | O22: =+SUM(C22:N22) -> 6839.5 | T22: EGESUR | U22: C.H. ARICOTA I | W22: 181.05
B23: 08:30 | C23: 1166.1 | D23: 3562.7 | E23: 1575.4 | F23: 46 | I23: =+DESPACHO_EJECUTADO!FB27+DESPACHO_EJECUTADO!FC27 -> 44 | K23: 16.6 | L23: 9.2 | M23: 399.1 | N23: 184.6 | O23: =+SUM(C23:N23) -> 7003.7 | U23: C.H. ARICOTA II | W23: 78.7
B24: 09:00 | C24: 1142.7 | D24: 3606.9 | E24: 1683.6 | F24: 45.7 | I24: =+DESPACHO_EJECUTADO!FB28+DESPACHO_EJECUTADO!FC28 -> 43.9 | K24: 16.6 | L24: 9.2 | M24: 410.9 | N24: 199.5 | O24: =+SUM(C24:N24) -> 7159 | T24: ELECTRICA YANAPAMPA SAC | U24: C.H. YANAPAMPA | V24: 65.8
B25: 09:30 | C25: 1144.2 | D25: 3602.9 | E25: 1753.9 | F25: 45.8 | I25: =+DESPACHO_EJECUTADO!FB29+DESPACHO_EJECUTADO!FC29 -> 44.1 | K25: 16.6 | L25: 9.2 | M25: 417.7 | N25: 214.5 | O25: =+SUM(C25:N25) -> 7248.9 | T25: ELECTROPERU | U25: C.H. MANTARO | W25: 14716.15
B26: 10:00 | C26: 1169.1 | D26: 3589.9 | E26: 1967.7 | F26: 45 | I26: =+DESPACHO_EJECUTADO!FB30+DESPACHO_EJECUTADO!FC30 -> 44.3 | K26: 16.5 | L26: 9.2 | M26: 421.5 | N26: 235.7 | O26: =+SUM(C26:N26) -> 7498.9 | U26: C.H. RESTITUCION | V26: 4891.8
B27: 10:30 | C27: 1144.5 | D27: 3551.8 | E27: 2094.5 | F27: 45.1 | I27: =+DESPACHO_EJECUTADO!FB31+DESPACHO_EJECUTADO!FC31 -> 44.5 | K27: 16.5 | L27: 9.1 | M27: 423.4 | N27: 207 | O27: =+SUM(C27:N27) -> 7536.4 | T27: EMPRESA DE GENERACION ELECTRICA CANCHAYLLO SAC | U27: C.H. CANCHAYLLO | V27: 114.2
B28: 11:00 | C28: 1174 | D28: 3655.7 | E28: 2107.9 | F28: 44.7 | I28: =+DESPACHO_EJECUTADO!FB32+DESPACHO_EJECUTADO!FC32 -> 44.7 | K28: 16.4 | L28: 9.1 | M28: 424.4 | N28: 191.7 | O28: =+SUM(C28:N28) -> 7668.6 | T28: EMPRESA DE GENERACION ELECTRICA RIO BAÑOS S.A.C. | U28: C.H. RUCUY | V28: 478.95
B29: 11:30 | C29: 1163.6 | D29: 3560.1 | E29: 2164 | F29: 44.8 | I29: =+DESPACHO_EJECUTADO!FB33+DESPACHO_EJECUTADO!FC33 -> 43.6 | K29: 16.6 | L29: 9.1 | M29: 425.8 | N29: 214.8 | O29: =+SUM(C29:N29) -> 7642.4 | T29: EMPRESA DE GENERACION ELECTRICA SANTA ANA S.A.C. | U29: C.H. RENOVANDES H1 | V29: 485.4
B30: 12:00 | C30: 1165.6 | D30: 3570.9 | E30: 2174 | F30: 45.4 | I30: =+DESPACHO_EJECUTADO!FB34+DESPACHO_EJECUTADO!FC34 -> 43.7 | K30: 16.6 | L30: 8.9 | M30: 428.8 | N30: 229.2 | O30: =+SUM(C30:N30) -> 7683.1 | T30: EMPRESA DE GENERACION HUALLAGA | U30: C.H. CHAGLLA | W30: 9951.85
B31: 12:30 | C31: 1163 | D31: 3539.6 | E31: 2072.7 | F31: 45.5 | I31: =+DESPACHO_EJECUTADO!FB35+DESPACHO_EJECUTADO!FC35 -> 43.8 | K31: 16 | L31: 8.9 | M31: 428.4 | N31: 280 | O31: =+SUM(C31:N31) -> 7597.9 | U31: P.C.H. CHAGLLA | V31: 154.7
B32: 13:00 | C32: 1159.9 | D32: 3464.6 | E32: 1951 | F32: 46 | I32: =+DESPACHO_EJECUTADO!FB36+DESPACHO_EJECUTADO!FC36 -> 44.2 | K32: 16 | L32: 8.9 | M32: 426.8 | N32: 354.3 | O32: =+SUM(C32:N32) -> 7471.7 | T32: EMPRESA DE GENERACION HUANZA | U32: C.H. HUANZA | W32: 2165.15
B33: 13:30 | C33: 1161.4 | D33: 3644.9 | E33: 1816.3 | F33: 46.2 | I33: =+DESPACHO_EJECUTADO!FB37+DESPACHO_EJECUTADO!FC37 -> 43.4 | K33: 16.4 | L33: 8.9 | M33: 426.8 | N33: 381.6 | O33: =+SUM(C33:N33) -> 7545.9 | T33: EMPRESA ELECTRICA AGUA AZUL | U33: C.H. POTRERO | V33: 476.75
B34: 14:00 | C34: 1169.5 | D34: 3636.5 | E34: 1835.3 | F34: 45.8 | I34: =+DESPACHO_EJECUTADO!FB38+DESPACHO_EJECUTADO!FC38 -> 43 | K34: 16.6 | L34: 8.9 | M34: 425.4 | N34: 415.3 | O34: =+SUM(C34:N34) -> 7596.3 | T34: EMPRESA ELECTRICA RIO DOBLE | U34: C.H. LAS PIZARRAS | V34: 423.35
B35: 14:30 | C35: 1162.7 | D35: 3607 | E35: 1931.9 | F35: 45.9 | I35: =+DESPACHO_EJECUTADO!FB39+DESPACHO_EJECUTADO!FC39 -> 40.8 | K35: 16.4 | L35: 8.9 | M35: 418.4 | N35: 506.1 | O35: =+SUM(C35:N35) -> 7738.1 | T35: ENGIE | U35: C.H. YUNCAN | W35: 2074.6
B36: 15:00 | C36: 1170 | D36: 3585.5 | E36: 1882.1 | F36: 45.9 | I36: =+DESPACHO_EJECUTADO!FB40+DESPACHO_EJECUTADO!FC40 -> 38.3 | K36: 16.6 | L36: 8.9 | M36: 409.9 | N36: 566.3 | O36: =+SUM(C36:N36) -> 7723.5 | T36: GENERACIÓN ANDINA S.A.C. | U36: C.H. 8 DE AGOSTO | V36: 504
B37: 15:30 | C37: 1173.9 | D37: 3641 | E37: 1814.4 | F37: 46.1 | I37: =+DESPACHO_EJECUTADO!FB41+DESPACHO_EJECUTADO!FC41 -> 38.1 | K37: 16.6 | L37: 8.9 | M37: 391.9 | N37: 573.9 | O37: =+SUM(C37:N37) -> 7704.8 | U37: C.H. EL CARMEN | V37: 166.9
B38: 16:00 | C38: 1014.9 | D38: 3611.3 | E38: 1945.7 | F38: 46.3 | I38: =+DESPACHO_EJECUTADO!FB42+DESPACHO_EJECUTADO!FC42 -> 39.7 | K38: 16.6 | L38: 8.9 | M38: 353.2 | N38: 600.9 | O38: =+SUM(C38:N38) -> 7637.5 | T38: GENERADORA DE ENERGÍA DEL PERÚ | U38: C.H. ÁNGEL I | V38: 489.6
B39: 16:30 | C39: 1163.9 | D39: 3649.2 | E39: 1906.5 | F39: 46.2 | I39: =+DESPACHO_EJECUTADO!FB43+DESPACHO_EJECUTADO!FC43 -> 39.5 | K39: 16.5 | L39: 8.9 | M39: 234.8 | N39: 680.6 | O39: =+SUM(C39:N39) -> 7746.1 | U39: C.H. ÁNGEL II | V39: 489.6
B40: 17:00 | C40: 1162.9 | D40: 3640 | E40: 1868.7 | F40: 46.5 | I40: =+DESPACHO_EJECUTADO!FB44+DESPACHO_EJECUTADO!FC44 -> 52.1 | K40: 16.6 | L40: 9.1 | M40: 94.6 | N40: 693.7 | O40: =+SUM(C40:N40) -> 7584.2 | U40: C.H. ÁNGEL III | V40: 484.8
B41: 17:30 | C41: 1156.6 | D41: 3656.7 | E41: 1891.7 | F41: 46.3 | I41: =+DESPACHO_EJECUTADO!FB45+DESPACHO_EJECUTADO!FC45 -> 58.5 | K41: 16.7 | L41: 9.1 | M41: 8 | N41: 668.9 | O41: =+SUM(C41:N41) -> 7512.5 | U41: C.H. LA JOYA | V41: 185.35
B42: 18:00 | C42: 1160.5 | D42: 3649.6 | E42: 1822.5 | F42: 46.5 | I42: =+DESPACHO_EJECUTADO!FB46+DESPACHO_EJECUTADO!FC46 -> 59.6 | K42: 16.7 | L42: 9.1 | M42: 0 | N42: 663.1 | O42: =+SUM(C42:N42) -> 7427.6 | T42: HIDROCAÑETE S.A. | U42: C.H. IMPERIAL | V42: 75.9
B43: 18:30 | C43: 1159.2 | D43: 3661.1 | E43: 2025.4 | F43: 46.5 | I43: =+DESPACHO_EJECUTADO!FB47+DESPACHO_EJECUTADO!FC47 -> 60.5 | K43: 16.4 | L43: 9.1 | M43: 0 | N43: 652.2 | O43: =+SUM(C43:N43) -> 7630.4 | T43: HIDROELECTRICA HUANCHOR S.A.C. | U43: C.H. HUANCHOR | V43: 444.6
B44: 19:00 | C44: 1163.3 | D44: 3654.6 | E44: 2060.5 | F44: 47.4 | I44: =+DESPACHO_EJECUTADO!FB48+DESPACHO_EJECUTADO!FC48 -> 59.7 | K44: 16.5 | L44: 9.1 | M44: 0 | N44: 603.4 | O44: =+SUM(C44:N44) -> 7614.5 | T44: HUAURA POWER GROUP S.A. | U44: C.H. YARUCAYA | V44: 223.2
B45: 19:30 | C45: 1163.2 | D45: 3638.5 | E45: 2117.4 | F45: 47.5 | I45: =+DESPACHO_EJECUTADO!FB49+DESPACHO_EJECUTADO!FC49 -> 59.6 | K45: 16.5 | L45: 9.2 | M45: 0 | N45: 600.1 | O45: =+SUM(C45:N45) -> 7652 | T45: INLAND ENERGY SAC | U45: C.H. SANTA TERESA | V45: 2137.5
B46: 20:00 | C46: 1169.2 | D46: 3650.2 | E46: 2109.3 | F46: 47.5 | I46: =+DESPACHO_EJECUTADO!FB50+DESPACHO_EJECUTADO!FC50 -> 59.8 | K46: 16.6 | L46: 9.2 | M46: 0 | N46: 534.7 | O46: =+SUM(C46:N46) -> 7596.5 | T46: INVERSIONES SHAQSHA S.A.C. | U46: C.H. PARIAC | V46: 110.4
B47: 20:30 | C47: 1149.5 | D47: 3664.6 | E47: 2133.9 | F47: 47.5 | I47: =+DESPACHO_EJECUTADO!FB51+DESPACHO_EJECUTADO!FC51 -> 59.8 | K47: 16.7 | L47: 9.2 | M47: 0 | N47: 513.7 | O47: =+SUM(C47:N47) -> 7594.9 | T47: KALLPA GENERACION S.A. | U47: C.H. CERRO DEL AGUILA | W47: 13430.55
B48: 21:00 | C48: 1137 | D48: 3617.6 | E48: 2046.1 | F48: 47.6 | I48: =+DESPACHO_EJECUTADO!FB52+DESPACHO_EJECUTADO!FC52 -> 59.3 | K48: 16.9 | L48: 9.2 | M48: 0 | N48: 529 | O48: =+SUM(C48:N48) -> 7462.7 | U48: M.C.H. CERRO DEL AGUILA | V48: 41.95
B49: 21:30 | C49: 1147.3 | D49: 3618.1 | E49: 1988.8 | F49: 47.4 | I49: =+DESPACHO_EJECUTADO!FB53+DESPACHO_EJECUTADO!FC53 -> 59.9 | K49: 16.7 | L49: 9.2 | M49: 0 | N49: 509.3 | O49: =+SUM(C49:N49) -> 7396.7 | T49: LA VIRGEN | U49: C.H. LA VIRGEN | W49: 1495.9
B50: 22:00 | C50: 1167.3 | D50: 3613.9 | E50: 1986.1 | F50: 47.4 | I50: =+DESPACHO_EJECUTADO!FB54+DESPACHO_EJECUTADO!FC54 -> 59.3 | K50: 16.4 | L50: 9.2 | M50: 0 | N50: 457.9 | O50: =+SUM(C50:N50) -> 7357.5 | T50: MAJA ENERGIA S.A.C. | U50: C.H. RONCADOR | V50: 25.4
B51: 22:30 | C51: 1169.8 | D51: 3539.2 | E51: 1890.1 | F51: 47.6 | I51: =+DESPACHO_EJECUTADO!FB55+DESPACHO_EJECUTADO!FC55 -> 59.9 | K51: 16.6 | L51: 9.2 | M51: 0 | N51: 438.8 | O51: =+SUM(C51:N51) -> 7171.2 | T51: ORAZUL ENERGY PERÚ | U51: C.H. CAÑA BRAVA | V51: 130.3
B52: 23:00 | C52: 1173.3 | D52: 3518.3 | E52: 1743.1 | F52: 47.5 | I52: =+DESPACHO_EJECUTADO!FB56+DESPACHO_EJECUTADO!FC56 -> 59.7 | K52: 16.5 | L52: 9.2 | M52: 0 | N52: 421.5 | O52: =+SUM(C52:N52) -> 6989.1 | U52: C.H. CAÑON DEL PATO | W52: 5700.85
B53: 23:30 | C53: 1169.5 | D53: 3586.1 | E53: 1537.8 | F53: 0 | I53: =+DESPACHO_EJECUTADO!FB57+DESPACHO_EJECUTADO!FC57 -> 59.5 | K53: 16.7 | L53: 9.2 | M53: 0 | N53: 387.7 | O53: =+SUM(C53:N53) -> 6766.5 | U53: C.H. CARHUAQUERO | W53: 2129.8
B54: 00:00 | C54: 1154 | D54: 3611.5 | E54: 1326.2 | F54: 0 | I54: =+DESPACHO_EJECUTADO!FB58+DESPACHO_EJECUTADO!FC58 -> 59.5 | K54: 16.5 | L54: 9.2 | M54: 0 | N54: 382.5 | O54: =+SUM(C54:N54) -> 6559.4 | U54: C.H. CARHUAQUERO IV | V54: 250.1
B55: TOTAL MWh | C55: =SUM(C7:C54)/2 -> 27288.85 | D55: =SUM(D7:D54)/2 -> 83560.2 | E55: =SUM(E7:E54)/2 -> 43103.85 | F55: =SUM(F7:F54)/2 -> 694.8 | G55: =SUM(G7:G54)/2 -> 0 | H55: =SUM(H7:H54)/2 -> 0 | I55: =SUM(I7:I54)/2 -> 1158 | J55: =SUM(J7:J54)/2 -> 0 | ... O55: =SUM(O7:O54)/2 -> 170102.35 | T55: ORYGEN PERU S.A.A. | U55: C.H. CALLAHUANCA | W55: 1902.5
B56: % | C56: 16.152567 | D56: 49.460192 | E56: 25.513638 | F56: 0.41125968 | K56: 0.23498862 | L56: 0.12956929 | M56: 2.3565156 | N56: 5.7412692 | O56: 100.00 | U56: C.H. HER 1 | V56: 14.4
U57: C.H. HUAMPANI | V57: 725.65
U58: C.H. HUINCO | W58: 5901.1
U59: C.H. MATUCANA | W59: 3064.65
U60: C.H. MOYOPAMPA | V60: 1524.95
T61: PERUANA DE INVERSIONES EN ENERGIAS RENOVABLES S.A. | U61: C.H. MANTA I | V61: 480.1
T62: SAN GABAN | U62: C.H. SAN GABAN II | W62: 2657.35
U63: MCH TUPURI | V63: 29.05
T64: SINERSA | U64: C.H. CHANCAY | V64: 479.8
U65: C.H. POECHOS II | V65: 191.25
T66: STATKRAFT S.A | U66: C.H. ARCATA | V66: 91.2
U67: C.H. CAHUA | V67: 724.5
U68: C.H. CHEVES | W68: 4125.9
U69: C.H. GALLITO CIEGO | W69: 849.65
U70: C.H. MALPASO | W70: 1097.35
U71: C.H. OROYA | V71: 29.7
U72: C.H. PACHACHACA | V72: 222.15
U73: C.H. YAUPI | V73: 2183
T74: TOTAL MWh | V74: 27288.85 | W74: 83560.2

Sheet GENERACION RER
B3: miércoles, 9 de Abril del 2025
B5: GENERACIÓN ELÉCTRICA DE LAS CENTRALES RER (MW)
B6: HORA | C6: AGRO INDUSTRIAL PARAMONGA S.A. | D6: AGROAURORA S.A.C. | E6: AGROINDUSTRIAS SAN JACINTO S.A.A. | F6: ANDEAN POWER S.A.C. | G6: ASOCIACIÓN SANTA LUCIA DE CHACAS | H6: ATRIA ENERGIA S.A.C. | I6: BIOENERGIA DEL CHIRA S.A. | J6: COLCA SOLAR S.A.C. | K6: EGEJUNIN | P6: ELECTRICA YANAPAMPA SAC | Q6: EMPRESA DE GENERACION ELECTRICA CANCHAYLLO SAC | R6: EMPRESA DE GENERACION ELECTRICA RIO BAÑOS S.A.C. | S6: EMPRESA DE GENERACION ELECTRICA SANTA ANA S.A.C. | T6: EMPRESA ELECTRICA AGUA AZUL | U6: EMPRESA ELECTRICA RIO DOBLE | V6: ENERGÍA EÓLICA S.A. | X6: ENERGIA RENOVABLE DEL SUR S.A. | Y6: ENGIE | AD6: GENERACIÓN ANDINA S.A.C. | AF6: GENERADORA DE ENERGÍA DEL PERÚ | AJ6: GR CORTARRAMA SOCIEDAD ANONIMA CERRADA | AK6: GR PAINO SOCIEDAD ANONIMA CERRADA | AL6: GR TARUCA SOCIEDAD ANONIMA CERRADA | AM6: HIDROCAÑETE S.A. | AN6: HUAURA POWER GROUP S.A. | AO6: HYDRO PATAPO S.A.C. | AP6: KONDU SAC | AQ6: MAJA ENERGIA S.A.C. | AR6: MAJES ARCUS S.A.C. | AS6: MOQUEGUA FV S.A.C. | AT6: ORAZUL ENERGY PERÚ | AV6: ORYGEN PERU S.A.A. | BA6: PANAMERICANA SOLAR SAC. | BB6: PARQUE EOLICO MARCONA S.A.C. | BC6: PARQUE EOLICO TRES HERMANAS S.A.C. | BD6: PERUANA DE INVERSIONES EN ENERGIAS RENOVABLES S.A. | BE6: PETRAMAS | BI6: REPARTICIÓN ARCUS S.A.C. | BJ6: SAN GABAN | BK6: SDF ENERGIA SAC | BL6: SINERSA | BN6: TACNA SOLAR SAC. | BO6: TOTAL RER
C7: C.T. PARAMONGA | D7: C.T. MAPLE | E7: C.T SAN JACINTO | F7: C.H. CARHUAC | G7: C.H. HUALLIN | H7: C.H. PURMACANA | I7: C.T. CAÑA BRAVA | K7: C.H. HUASAHUASI I | L7: C.H. HUASAHUASI II | M7: C.H. RUNATULLO II | N7: C.H. RUNATULLO III | O7: C.H. STA CRUZ I y II | P7: C.H. YANAPAMPA | Q7: C.H. CANCHAYLLO | R7: C.H. RUCUY | S7: C.H. RENOVANDES H1 | T7: C.H. POTRERO | U7: C.H. LAS PIZARRAS | AD7: C.H. 8 DE AGOSTO | AE7: C.H. EL CARMEN | AF7: C.H. ANGEL I | AG7: C.H. ANGEL II | AH7: C.H. ANGEL III | AI7: C.H. LA JOYA | AM7: C.H. NUEVAIMPERIAL | AN7: C.H. YARUCAYA | AO7: MCH PATAPO | AQ7: C.H. RONCADOR | AT7: C.H. CANA BRAVA | AU7: C.H. CARHUAQUERO4 | AZ7: C.H. HER 1 | BD7: C.H. MANTA | BE7: C.T. HUAYCOLORO | BF7: C.T. LA GRINGA V | BG7: CTB CALLAO | BH7: CTB. DONA CATALINA | BJ7: C.H. TUPURI | BK7: C.T. OQUENDO | BL7: C.H. CHANCAY | BM7: C.H. POECHOS2 | BO7: MW
B8: 0:30 | C8: 16.4 | F8: 20.2 | G8: 3 | K8: 17.4 | M8: 20.3 | N8: 20.3 | O8: 9.8 | P8: 2.9 | Q8: 4.9 | R8: 20 | S8: 20.2 | T8: 20 | U8: 18.8 | V8: 13.6 | W8: 35.1 | X8: 81.5 | Y8: 30.7 | Z8: 74.6 | AB8: 2.1 | AC8: 1.6 | AD8: 21 | AE8: 6.9 | AF8: 20.4 | AG8: 20.4 | AH8: 20.2 | AI8: 7.4 | AK8: 7.3 | AL8: 10.2 | AM8: 3.5 | AN8: 9.3 | AQ8: 1.7 | AT8: 5.4 | AU8: 10.5 | AV8: 58.3 | AX8: 74 | AZ8: 0.6 | BB8: 26.2 | BC8: 51.6 | BD8: 20 | BE8: 4.4 | BG8: 2.4 | BH8: 2.4 | BJ8: 1.2 | BL8: 20 | BM8: 7.9 | BO8: 846.6
B9: 1:00 | C9: 16.5 | F9: 20.3 | G9: 3 | K9: 17.5 | M9: 20.1 | N9: 20.3 | O9: 9.8 | P9: 2.9 | Q9: 4.8 | R9: 20 | S9: 20.2 | T9: 20 | U9: 18.8 | V9: 18.6 | W9: 34.7 | X9: 87.9 | Y9: 33.6 | Z9: 66.5 | AB9: 2.9 | AC9: 2.4 | AD9: 21 | AE9: 6.9 | AF9: 20.4 | AG9: 20.4 | AH9: 20.2 | AI9: 7.4 | AK9: 6.2 | AL9: 9.1 | AM9: 3.6 | AN9: 9.3 | AQ9: 1.7 | AT9: 5.4 | AU9: 10.4 | AV9: 26.1 | AX9: 37.7 | AZ9: 0.6 | BB9: 26.2 | BC9: 57.9 | BD9: 20 | BE9: 4.4 | BG9: 2.4 | BH9: 2.4 | BJ9: 1.2 | BL9: 20 | BM9: 7.8 | BO9: 789.5
B10: 1:30 | C10: 16.6 | F10: 20.3 | G10: 3 | K10: 17.4 | M10: 20.1 | N10: 20.3 | O10: 9.7 | P10: 3 | Q10: 4.8 | R10: 19.9 | S10: 20.1 | T10: 20 | U10: 18.8 | V10: 18.8 | W10: 33.4 | X10: 90.5 | Y10: 32.4 | Z10: 65 | AB10: 3.1 | AC10: 3 | AD10: 21 | AE10: 6.9 | AF10: 20.4 | AG10: 20.4 | AH10: 20.2 | AI10: 7.4 | AK10: 11.3 | AL10: 13.7 | AM10: 3.5 | AN10: 9.3 | AQ10: 1.7 | AT10: 5.4 | AU10: 10.6 | AV10: 10.2 | AX10: 15.4 | AZ10: 0.6 | BB10: 25.1 | BC10: 61.5 | BD10: 19.9 | BE10: 4.4 | BG10: 2.4 | BH10: 2.4 | BJ10: 1.2 | BL10: 20 | BM10: 7.8 | BO10: 762.9
B11: 2:00 | C11: 16.7 | F11: 20.3 | G11: 3 | K11: 17.4 | M11: 20.1 | N11: 20.2 | O11: 9.8 | P11: 2.8 | Q11: 4.8 | R11: 19.9 | S11: 19.8 | T11: 20 | U11: 18.8 | V11: 20.7 | W11: 27.9 | X11: 90.7 | Y11: 47.4 | Z11: 87.7 | AB11: 5.9 | AC11: 1.7 | AD11: 21 | AE11: 6.8 | AF11: 20.4 | AG11: 20.4 | AH11: 20.2 | AI11: 7.4 | AK11: 13.2 | AL11: 15.4 | AM11: 3.6 | AN11: 9.3 | AQ11: 1.7 | AT11: 5.3 | AU11: 10.4 | AV11: 4.9 | AX11: 5.1 | AZ11: 0.6 | BB11: 23.5 | BC11: 64.3 | BD11: 20 | BE11: 4.4 | BG11: 2.4 | BH11: 2.4 | BJ11: 1.2 | BL11: 20 | BM11: 7.9 | BO11: 787.4
B12: 2:30 | C12: 16.6 | F12: 20.3 | G12: 3 | K12: 17.4 | M12: 19.9 | N12: 20.2 | O12: 9.8 | P12: 2.7 | Q12: 4.9 | R12: 20 | S12: 20 | T12: 20 | U12: 18.8 | V12: 19.6 | W12: 24.5 | X12: 84.5 | Y12: 64.2 | Z12: 90.4 | AB12: 7.8 | AC12: 3.6 | AD12: 21 | AE12: 6.8 | AF12: 20.4 | AG12: 20.4 | AH12: 20.2 | AI12: 7.3 | AK12: 12.6 | AL12: 13.5 | AM12: 3.6 | AN12: 9.3 | AQ12: 1.7 | AT12: 5.4 | AU12: 10.4 | AV12: 2.8 | AX12: 2.7 | AZ12: 0.6 | BB12: 23.2 | BC12: 63.6 | BD12: 20 | BE12: 4.4 | BG12: 2.4 | BH12: 2.4 | BJ12: 1.2 | BL12: 20 | BM12: 8 | BO12: 792.1
B13: 3:00 | C13: 16.5 | F13: 20.3 | G13: 3 | K13: 17.4 | M13: 19.9 | N13: 20.3 | O13: 9.8 | P13: 2.7 | Q13: 4.8 | R13: 19.9 | S13: 20.1 | T13: 20 | U13: 18.8 | V13: 24.7 | W13: 26 | X13: 75.5 | Y13: 55.6 | Z13: 71.9 | AB13: 7.3 | AC13: 2.3 | AD13: 21 | AE13: 6.8 | AF13: 20.4 | AG13: 20.4 | AH13: 20.2 | AI13: 7.2 | AK13: 11 | AL13: 13.3 | AM13: 3.6 | AN13: 9.3 | AQ13: 1.7 | AT13: 5.5 | AU13: 10.4 | AV13: 20.5 | AX13: 18.2 | AZ13: 0.6 | BB13: 19.9 | BC13: 55.1 | BD13: 20 | BE13: 4.4 | BG13: 2.4 | BH13: 2.4 | BJ13: 1.2 | BL13: 20 | BM13: 7.9 | BO13: 780.2
B14: 3:30 | C14: 16.6 | F14: 20.3 | G14: 3 | K14: 17.2 | M14: 19.8 | N14: 20.3 | O14: 9.8 | P14: 2.6 | Q14: 4.8 | R14: 19.9 | S14: 20.5 | T14: 20 | U14: 18.8 | V14: 29 | W14: 25.7 | X14: 71.2 | Y14: 49.9 | Z14: 72.3 | AB14: 5 | AC14: 1.8 | AD14: 21 | AE14: 6.8 | AF14: 20.4 | AG14: 20.4 | AH14: 20.2 | AI14: 7.2 | AK14: 10.3 | AL14: 12 | AM14: 3.5 | AN14: 9.3 | AQ14: 1.7 | AT14: 5.5 | AU14: 10.4 | AV14: 16.8 | AX14: 20.6 | AZ14: 0.6 | BB14: 17 | BC14: 46.4 | BD14: 20 | BE14: 4.4 | BG14: 2.4 | BH14: 2.4 | BJ14: 1.2 | BL14: 20 | BM14: 7.8 | BO14: 756.8
B15: 4:00 | C15: 16.5 | F15: 20.3 | G15: 3 | K15: 17.3 | M15: 19.7 | N15: 20.2 | O15: 9.8 | P15: 2.9 | Q15: 4.8 | R15: 20 | S15: 19.8 | T15: 20 | U15: 18.8 | V15: 29 | W15: 23.4 | X15: 70.6 | Y15: 44.7 | Z15: 65.8 | AB15: 6.9 | AC15: 2.9 | AD15: 21 | AE15: 6.8 | AF15: 20.4 | AG15: 20.4 | AH15: 20.2 | AI15: 7.2 | AK15: 11.4 | AL15: 13.1 | AM15: 3.6 | AN15: 9.3 | AQ15: 1.7 | AT15: 5.4 | AU15: 10.4 | AV15: 17.7 | AX15: 23.3 | AZ15: 0.6 | BB15: 13.1 | BC15: 37.3 | BD15: 20 | BE15: 4.4 | BG15: 2.4 | BH15: 2.4 | BJ15: 1.2 | BL15: 20 | BM15: 7.9 | BO15: 737.6
B16: 4:30 | C16: 16.5 | F16: 20.3 | G16: 3 | K16: 17.3 | M16: 19.8 | N16: 20.3 | O16: 9.8 | P16: 2.9 | Q16: 4.7 | R16: 20 | S16: 20.3 | T16: 20 | U16: 18.8 | V16: 24.5 | W16: 29.8 | X16: 71.9 | Y16: 22.6 | Z16: 45.3 | AB16: 2.5 | AC16: 1.6 | AD16: 21 | AE16: 6.8 | AF16: 20.4 | AG16: 20.4 | AH16: 20.2 | AI16: 7.2 | AK16: 9.4 | AL16: 10.8 | AM16: 3.6 | AN16: 9.3 | AQ16: 1.7 | AT16: 5.5 | AU16: 10.5 | AV16: 19 | AX16: 21.9 | AZ16: 0.6 | BB16: 13.1 | BC16: 35.5 | BD16: 20 | BE16: 4.4 | BG16: 2.4 | BH16: 2.4 | BJ16: 1.2 | BL16: 20 | BM16: 7.9 | BO16: 687.1
B17: 5:00 | C17: 16.6 | F17: 20.3 | G17: 3 | K17: 17.3 | M17: 19.7 | N17: 20.3 | O17: 9.7 | P17: 3.1 | Q17: 4.7 | R17: 20 | S17: 20.2 | T17: 20 | U17: 18.8 | V17: 23.2 | W17: 31.9 | X17: 71.1 | Y17: 16.7 | Z17: 42.2 | AB17: 0.8 | AC17: 0.3 | AD17: 21 | AE17: 6.8 | AF17: 20.4 | AG17: 20.4 | AH17: 20.2 | AI17: 7.2 | AK17: 11 | AL17: 12.4 | AM17: 3.6 | AN17: 9.3 | AQ17: 1.7 | AT17: 5.4 | AU17: 10.5 | AV17: 13.4 | AX17: 19 | AZ17: 0.6 | BB17: 18 | BC17: 35.4 | BD17: 20.1 | BE17: 4.4 | BG17: 2.4 | BH17: 2.4 | BJ17: 1.2 | BL17: 20 | BM17: 8 | BO17: 674.7
B18: 5:30 | C18: 16.5 | F18: 20.4 | G18: 3 | K18: 17.3 | M18: 20.2 | N18: 20.3 | O18: 9.8 | P18: 2.9 | Q18: 4.6 | R18: 20 | S18: 20.3 | T18: 20 | U18: 18.9 | V18: 18.5 | W18: 18.8 | X18: 63.7 | Y18: 16.8 | Z18: 35.9 | AB18: 0.6 | AD18: 21 | AE18: 7.1 | AF18: 20.4 | AG18: 20.4 | AH18: 20.2 | AI18: 7.2 | AK18: 8.3 | AL18: 12.2 | AM18: 3.6 | AN18: 9.3 | AQ18: 1.6 | AT18: 5.4 | AU18: 10.5 | AV18: 11.4 | AX18: 17.6 | AZ18: 0.6 | BB18: 21.2 | BC18: 36.6 | BD18: 20 | BE18: 4.4 | BG18: 2.4 | BH18: 2.4 | BJ18: 1.2 | BL18: 20 | BM18: 8.1 | BO18: 641.6
B19: 6:00 | C19: 16.7 | F19: 20.2 | G19: 3 | K19: 17.3 | M19: 20 | N19: 20.2 | O19: 9.8 | P19: 3 | Q19: 4.6 | R19: 20 | S19: 20 | T19: 20 | U19: 18.8 | V19: 21.7 | W19: 13.1 | X19: 77.2 | Y19: 20.1 | Z19: 48.6 | AB19: 1.6 | AD19: 21 | AE19: 7 | AF19: 20.4 | AG19: 20.4 | AH19: 20.2 | AI19: 7.2 | AK19: 11.5 | AL19: 14.5 | AM19: 3.6 | AN19: 9.3 | AQ19: 1.7 | AS19: 1.4 | AT19: 5.5 | AU19: 10.4 | AV19: 2.7 | AW19: 0.8 | AX19: 7 | AY19: 0.7 | AZ19: 0.6 | BA19: 1.4 | BB19: 19.4 | BC19: 42 | BD19: 20 | BE19: 4.4 | BG19: 2.4 | BH19: 2.4 | BJ19: 1.2 | BL19: 20 | BM19: 8 | BO19: 663
B20: 6:30 | C20: 16.5 | F20: 20.2 | G20: 3 | K20: 17.4 | M20: 20.1 | N20: 20.3 | O20: 9.8 | P20: 2.9 | Q20: 4.8 | R20: 19.9 | S20: 20.2 | T20: 20 | U20: 18.8 | V20: 22.9 | W20: 14.2 | X20: 77.6 | Y20: 24 | Z20: 44.2 | AA20: 4.3 | AB20: 1.7 | AC20: 0.3 | AD20: 21 | AE20: 7 | AF20: 20.4 | AG20: 20.4 | AH20: 20.2 | AI20: 7.3 | AJ20: 9.4 | AK20: 12.1 | AL20: 14.7 | AM20: 3.5 | AN20: 9.3 | AQ20: 1.7 | AR20: 0.5 | AS20: 7.1 | AT20: 5.4 | AU20: 10.3 | AV20: 0.4 | AW20: 20 | AX20: 5.4 | AY20: 15.1 | AZ20: 0.6 | BA20: 7.7 | BB20: 17.7 | BC20: 46 | BD20: 20 | BE20: 4.4 | BG20: 2.4 | BH20: 2.4 | BI20: 0.6 | BJ20: 1.2 | BL20: 20 | BM20: 8 | BO20: 725.3
B21: 7:00 | C21: 16.6 | F21: 20.3 | G21: 3 | J21: 0.1 | K21: 17.3 | M21: 20.2 | N21: 20.3 | O21: 9.8 | P21: 2.7 | Q21: 4.8 | R21: 19.9 | S21: 20 | T21: 20 | U21: 18.8 | V21: 22.2 | W21: 9.1 | X21: 81.9 | Y21: 14.7 | Z21: 28.1 | AA21: 14.9 | AB21: 0.9 | AC21: 0.1 | AD21: 21 | AE21: 6.9 | AF21: 20.4 | AG21: 20.4 | AH21: 20.2 | AI21: 7.9 | AJ21: 32.3 | AK21: 10.1 | AL21: 13.8 | AM21: 3.5 | AN21: 9.3 | AQ21: 1.7 | AR21: 2.9 | AS21: 11.7 | AT21: 5.4 | AU21: 10.3 | AV21: 1.4 | AW21: 64.4 | AX21: 3.8 | AY21: 50.3 | AZ21: 0.6 | BA21: 14.2 | BB21: 16.2 | BC21: 40.1 | BD21: 20 | BE21: 4.4 | BG21: 2.4 | BH21: 2.4 | BI21: 2.8 | BJ21: 1.2 | BL21: 20 | BM21: 8 | BN21: 14.2 | BO21: 829.9
B22: 7:30 | C22: 16.5 | F22: 20.3 | G22: 3 | J22: 0.1 | K22: 17.4 | M22: 20.3 | N22: 20.3 | O22: 9.8 | P22: 2.8 | Q22: 4.8 | R22: 20 | S22: 20.2 | T22: 20 | U22: 18.9 | V22: 18 | W22: 8.1 | X22: 70.1 | Y22: 8.3 | Z22: 25.2 | AA22: 25.4 | AB22: 0.1 | AD22: 21 | AE22: 6.9 | AF22: 20.4 | AG22: 20.4 | AH22: 20.2 | AI22: 7.5 | AJ22: 56.4 | AK22: 9.7 | AL22: 11.9 | AM22: 3.5 | AN22: 9.3 | AQ22: 1.7 | AR22: 5.5 | AS22: 12.9 | AT22: 5.4 | AU22: 10.2 | AV22: 8.1 | AW22: 108.6 | AX22: 9.3 | AY22: 84.4 | AZ22: 0.6 | BA22: 15.8 | BB22: 15.5 | BC22: 44.7 | BD22: 20 | BE22: 4.4 | BG22: 2.4 | BH22: 2.4 | BI22: 5.4 | BJ22: 1.2 | BL22: 20 | BM22: 8 | BN22: 16 | BO22: 939.3
B23: 8:00 | C23: 16.6 | F23: 20.3 | G23: 3 | J23: 0.2 | K23: 17.4 | M23: 20.3 | N23: 20.3 | O23: 9.8 | P23: 2.9 | Q23: 4.8 | R23: 20 | S23: 20.2 | T23: 20 | U23: 18.9 | V23: 8.4 | W23: 8.7 | X23: 62.2 | Y23: 8.4 | Z23: 18.5 | AA23: 33 | AD23: 21 | AE23: 7 | AF23: 20.4 | AG23: 20.4 | AH23: 20.2 | AI23: 7.1 | AJ23: 67.7 | AK23: 9.1 | AL23: 11.1 | AM23: 3.6 | AN23: 9.3 | AP23: 0.1 | AQ23: 1.7 | AR23: 8.1 | AS23: 13.2 | AT23: 5.4 | AU23: 10.4 | AV23: 7 | AW23: 128.9 | AX23: 6.4 | AY23: 92.7 | AZ23: 0.6 | BA23: 16.4 | BB23: 14 | BC23: 36 | BD23: 20 | BE23: 4.4 | BG23: 2.4 | BH23: 2.4 | BI23: 7.9 | BJ23: 1.2 | BL23: 20 | BM23: 8 | BN23: 17.1 | BO23: 955.1
B24: 8:30 | C24: 16.6 | F24: 20.3 | G24: 3 | J24: 0.6 | K24: 17.4 | M24: 20.3 | N24: 20.3 | O24: 9.6 | P24: 2.7 | Q24: 4.8 | R24: 20 | S24: 20.3 | T24: 20 | U24: 18.9 | V24: 7.8 | W24: 8.3 | X24: 75.5 | Y24: 5.7 | Z24: 15.9 | AA24: 33.7 | AD24: 21 | AE24: 7.2 | AF24: 20.4 | AG24: 20.4 | AH24: 20.2 | AI24: 7.6 | AJ24: 69.8 | AK24: 11.4 | AL24: 14.6 | AM24: 3.6 | AN24: 9.3 | AP24: 0.1 | AQ24: 1.7 | AR24: 10.4 | AS24: 13.5 | AT24: 5.5 | AU24: 10.4 | AV24: 0.7 | AW24: 131.3 | AY24: 94.9 | AZ24: 0.6 | BA24: 17 | BB24: 14.3 | BC24: 30.4 | BD24: 20.1 | BE24: 4.4 | BG24: 2.4 | BH24: 2.4 | BI24: 10.3 | BJ24: 1.2 | BL24: 20 | BM24: 8 | BN24: 17.5 | BO24: 964.3
B25: 9:00 | C25: 16.6 | F25: 20.2 | G25: 3 | J25: 0.8 | K25: 17.4 | M25: 20.4 | N25: 20.3 | O25: 9.7 | P25: 2.9 | Q25: 4.8 | R25: 20 | S25: 20.3 | T25: 20 | U25: 18.9 | V25: 9.4 | W25: 6.4 | X25: 89.2 | Y25: 5.1 | Z25: 16.6 | AA25: 34.3 | AD25: 21 | AE25: 7.2 | AF25: 20.4 | AG25: 20.4 | AH25: 20.2 | AI25: 7.4 | AJ25: 71.4 | AK25: 12.6 | AL25: 12.7 | AM25: 3.6 | AN25: 9.3 | AP25: 0.2 | AQ25: 1.7 | AR25: 12.4 | AS25: 13.6 | AT25: 5.4 | AU25: 10.4 | AW25: 133.8 | AY25: 97.2 | AZ25: 0.6 | BA25: 17.3 | BB25: 11.9 | BC25: 35.6 | BD25: 20.1 | BE25: 4.4 | BG25: 2.4 | BH25: 2.4 | BI25: 12.3 | BJ25: 1.2 | BL25: 20 | BM25: 8 | BN25: 17.6 | BO25: 991
B26: 9:30 | C26: 16.6 | F26: 20.3 | G26: 3 | J26: 0.9 | K26: 17.3 | M26: 20.3 | N26: 20.3 | O26: 9.7 | P26: 2.7 | Q26: 4.8 | R26: 20 | S26: 20.4 | T26: 20 | U26: 18.8 | V26: 12.6 | W26: 10.9 | X26: 78 | Y26: 7.8 | Z26: 21.6 | AA26: 34.8 | AD26: 21 | AE26: 7 | AF26: 20.4 | AG26: 20.4 | AH26: 20.2 | AI26: 7.4 | AJ26: 72.4 | AK26: 13.6 | AL26: 11.7 | AM26: 3.6 | AN26: 9.3 | AP26: 0.3 | AQ26: 1.7 | AR26: 14.1 | AS26: 13.1 | AT26: 5.4 | AU26: 10.5 | AW26: 134.7 | AY26: 98.4 | AZ26: 0.6 | BA26: 17.4 | BB26: 12 | BC26: 46.3 | BD26: 20 | BE26: 4.4 | BG26: 2.4 | BH26: 2.4 | BI26: 14 | BJ26: 1.2 | BL26: 20 | BM26: 8 | BN26: 17.6 | BO26: 1012.3
B27: 10:00 | C27: 16.5 | F27: 20.2 | G27: 3 | J27: 1.1 | K27: 17.3 | M27: 20.2 | N27: 20.3 | O27: 9.6 | P27: 2.8 | Q27: 4.7 | R27: 20 | S27: 20.6 | T27: 20 | U27: 18.8 | V27: 10.6 | W27: 19.8 | X27: 64.7 | Y27: 17.5 | Z27: 30.5 | AA27: 35.2 | AB27: 1.5 | AC27: 0.5 | AD27: 21 | AE27: 6.8 | AF27: 20.4 | AG27: 20.4 | AH27: 20.2 | AI27: 7.4 | AJ27: 72.3 | AK27: 15.2 | AL27: 12.7 | AM27: 3.6 | AN27: 9.3 | AP27: 0.4 | AQ27: 1.7 | AR27: 15.5 | AS27: 13 | AT27: 5.4 | AU27: 10.5 | AW27: 135.1 | AY27: 98.9 | AZ27: 0.6 | BA27: 17 | BB27: 11.3 | BC27: 51.4 | BD27: 20.1 | BE27: 4.4 | BG27: 2.4 | BH27: 2.4 | BI27: 15.5 | BJ27: 1.2 | BL27: 20 | BM27: 8 | BN27: 17.5 | BO27: 1037
B28: 10:30 | C28: 16.5 | F28: 20.2 | G28: 3 | J28: 1.2 | K28: 17.3 | M28: 20.3 | N28: 20.2 | O28: 9.7 | P28: 3.1 | Q28: 4.7 | R28: 20 | S28: 19.6 | T28: 20 | U28: 18.8 | V28: 7 | W28: 17 | X28: 67.5 | Y28: 10.3 | Z28: 22 | AA28: 35.2 | AB28: 0.9 | AD28: 21 | AE28: 6.8 | AF28: 20.4 | AG28: 20.4 | AH28: 20.2 | AI28: 7.4 | AJ28: 72.8 | AK28: 15.5 | AL28: 14.3 | AM28: 3.6 | AN28: 9.3 | AP28: 0.5 | AQ28: 1.7 | AR28: 16.5 | AS28: 13.1 | AT28: 5.5 | AU28: 10.4 | AW28: 134.3 | AY28: 98.9 | AZ28: 0.6 | BA28: 17 | BB28: 10.5 | BC28: 42 | BD28: 20 | BE28: 4.3 | BG28: 2.4 | BH28: 2.4 | BI28: 16.5 | BJ28: 1.2 | BL28: 20 | BM28: 8 | BN28: 17.4 | BO28: 1009.4
B29: 11:00 | C29: 16.4 | F29: 20.2 | G29: 2.9 | J29: 1.3 | K29: 17.3 | M29: 20.4 | N29: 20.3 | O29: 9.6 | P29: 3.1 | Q29: 4.8 | R29: 19.9 | S29: 20.9 | T29: 20 | U29: 18.8 | V29: 6.1 | W29: 16.7 | X29: 66.5 | Y29: 8.5 | Z29: 17.4 | AA29: 35.2 | AB29: 0.6 | AC29: 0.3 | AD29: 21 | AE29: 6.9 | AF29: 20.4 | AG29: 20.4 | AH29: 20.2 | AI29: 7.4 | AJ29: 72.5 | AK29: 14.4 | AL29: 12.9 | AM29: 3.6 | AN29: 9.3 | AP29: 0.3 | AQ29: 1.7 | AR29: 17.4 | AS29: 13.3 | AT29: 5.4 | AU29: 10.5 | AW29: 134.1 | AY29: 98.8 | AZ29: 0.6 | BA29: 16.9 | BB29: 11.3 | BC29: 37 | BD29: 20 | BE29: 4.3 | BG29: 2.4 | BH29: 2.4 | BI29: 17.2 | BJ29: 1.2 | BL29: 20 | BM29: 8 | BN29: 17.4 | BO29: 996.4
B30: 11:30 | C30: 16.6 | F30: 20.2 | G30: 2.9 | J30: 1.3 | K30: 16.9 | M30: 20.2 | N30: 20.2 | O30: 9.7 | P30: 3.2 | Q30: 4.7 | R30: 19.9 | S30: 20.2 | T30: 20 | U30: 18.8 | V30: 7 | W30: 17.9 | X30: 74.4 | Y30: 12.2 | Z30: 26.5 | AA30: 34.8 | AB30: 1.4 | AC30: 0.7 | AD30: 21 | AE30: 6.9 | AF30: 20.4 | AG30: 20.4 | AH30: 20.2 | AI30: 7.3 | AJ30: 72.6 | AK30: 14.5 | AL30: 13.2 | AM30: 3.6 | AN30: 9.3 | AP30: 0.1 | AQ30: 1.7 | AR30: 17.8 | AS30: 13.8 | AT30: 5.5 | AU30: 10.5 | AW30: 134.3 | AY30: 99 | AZ30: 0.6 | BA30: 16.9 | BB30: 12.1 | BC30: 34.9 | BD30: 20 | BE30: 4.3 | BG30: 2.4 | BH30: 2.4 | BI30: 17.7 | BJ30: 1.2 | BL30: 19.9 | BM30: 8 | BN30: 17.5 | BO30: 1019.7
B31: 12:00 | C31: 16.6 | F31: 20.2 | G31: 3 | J31: 1.3 | K31: 16.8 | M31: 20.2 | N31: 20.2 | O31: 9.6 | P31: 3.2 | Q31: 4.7 | R31: 19.9 | S31: 20.2 | T31: 20 | U31: 18.9 | V31: 6 | W31: 23.8 | X31: 78.9 | Y31: 10.5 | Z31: 23.7 | AA31: 34.5 | AB31: 1.8 | AC31: 0.2 | AD31: 21 | AE31: 6.8 | AF31: 20.4 | AG31: 20.4 | AH31: 20.2 | AI31: 7.1 | AJ31: 74.6 | AK31: 14.9 | AL31: 14 | AM31: 3.6 | AN31: 9.3 | AP31: 0.1 | AQ31: 1.7 | AR31: 18.2 | AS31: 13.9 | AT31: 5.4 | AU31: 10.5 | AW31: 134.4 | AY31: 99.2 | AZ31: 0.6 | BA31: 16.9 | BB31: 13 | BC31: 42.4 | BD31: 20 | BE31: 4.1 | BG31: 2.4 | BH31: 2.4 | BI31: 18 | BJ31: 1.2 | BL31: 20 | BM31: 8 | BN31: 17.7 | BO31: 1036.6
B32: 12:30 | C32: 16 | F32: 20.2 | G32: 3 | J32: 1.3 | K32: 16.8 | M32: 20.3 | N32: 20.3 | O32: 9.7 | P32: 3 | Q32: 4.6 | R32: 19.8 | S32: 20.3 | T32: 20 | U32: 18.9 | V32: 4.2 | W32: 28.2 | X32: 80.2 | Y32: 21.2 | Z32: 38.9 | AA32: 34.5 | AB32: 2.8 | AC32: 1.4 | AD32: 21 | AE32: 6.8 | AF32: 20.4 | AG32: 20.4 | AH32: 20.2 | AI32: 7.1 | AJ32: 75.8 | AK32: 14.8 | AL32: 13.6 | AM32: 3.6 | AN32: 9.3 | AP32: 0.1 | AQ32: 1.7 | AR32: 18.4 | AS32: 13.9 | AT32: 5.4 | AU32: 10.5 | AV32: 15.8 | AW32: 133 | AY32: 98.8 | AZ32: 0.6 | BA32: 16.8 | BB32: 13.1 | BC32: 45.8 | BD32: 20 | BE32: 4.1 | BG32: 2.4 | BH32: 2.4 | BI32: 18 | BJ32: 1.2 | BL32: 19.9 | BM32: 8 | BN32: 17.8 | BO32: 1086.3
B33: 13:00 | C33: 16 | F33: 20.2 | G33: 3 | J33: 0.8 | K33: 16.9 | M33: 20.2 | N33: 20.3 | O33: 9.7 | P33: 3 | Q33: 4.6 | R33: 19.8 | S33: 20.1 | T33: 19.2 | U33: 18.9 | V33: 16.5 | W33: 28.7 | X33: 75.1 | Y33: 25.1 | Z33: 45.4 | AA33: 35 | AB33: 3.5 | AC33: 1.5 | AD33: 21 | AE33: 6.8 | AF33: 20.4 | AG33: 20.4 | AH33: 20.2 | AI33: 7.1 | AJ33: 75.8 | AK33: 14.8 | AL33: 14.4 | AM33: 3.6 | AN33: 9.3 | AP33: 0.1 | AQ33: 1.7 | AR33: 17.9 | AS33: 13.8 | AT33: 5.4 | AU33: 10.4 | AV33: 45.3 | AW33: 133.2 | AX33: 13.4 | AY33: 98.1 | AZ33: 0.6 | BA33: 16.7 | BB33: 14.2 | BC33: 56.4 | BD33: 19.9 | BE33: 4.1 | BG33: 2.4 | BH33: 2.4 | BI33: 17.6 | BJ33: 1.2 | BL33: 20 | BM33: 8 | BN33: 17.8 | BO33: 1157.9
B34: 13:30 | C34: 16.4 | F34: 20.2 | G34: 3 | J34: 0.8 | K34: 16.9 | M34: 20.3 | N34: 20.3 | O34: 9.7 | P34: 3 | Q34: 4.5 | R34: 20 | S34: 20.5 | T34: 20 | U34: 18.9 | V34: 18.1 | W34: 25.3 | X34: 70.5 | Y34: 35.6 | Z34: 49.5 | AA34: 35 | AB34: 7.1 | AC34: 4.1 | AD34: 21 | AE34: 6.8 | AF34: 20.4 | AG34: 20.4 | AH34: 20.2 | AI34: 7.1 | AJ34: 75.4 | AK34: 13.3 | AL34: 13 | AM34: 3.6 | AN34: 9.3 | AP34: 0.1 | AQ34: 1.7 | AR34: 17 | AS34: 13.9 | AT34: 5.4 | AU34: 10.5 | AV34: 40.3 | AW34: 135.5 | AX34: 38 | AY34: 97.7 | AZ34: 0.6 | BA34: 16.8 | BB34: 12 | BC34: 54.8 | BD34: 20 | BE34: 4.1 | BG34: 2.4 | BH34: 2.4 | BI34: 16.7 | BJ34: 1.3 | BL34: 20 | BM34: 8 | BN34: 17.9 | BO34: 1187.3
B35: 14:00 | C35: 16.6 | F35: 20.2 | G35: 3 | J35: 0.7 | K35: 16.9 | M35: 20.3 | N35: 20.3 | O35: 9.7 | P35: 3 | Q35: 4.5 | R35: 19.9 | S35: 20.4 | T35: 20 | U35: 18.8 | V35: 15.7 | W35: 24.7 | X35: 66 | Y35: 50.9 | Z35: 52.7 | AA35: 35 | AB35: 10.6 | AC35: 6 | AD35: 21 | AE35: 6.7 | AF35: 20.4 | AG35: 20.4 | AH35: 20.2 | AI35: 7.1 | AJ35: 74.9 | AK35: 12.8 | AL35: 11 | AM35: 3.6 | AN35: 9.3 | AP35: 0.1 | AQ35: 1.7 | AR35: 15.9 | AS35: 13.8 | AT35: 5.5 | AU35: 10.4 | AV35: 49.3 | AW35: 136.1 | AX35: 53.1 | AY35: 98.6 | AZ35: 0.6 | BA35: 16.7 | BB35: 11.5 | BC35: 51 | BD35: 20 | BE35: 4.1 | BG35: 2.4 | BH35: 2.4 | BI35: 15.8 | BJ35: 1.3 | BL35: 20 | BM35: 8 | BN35: 17.8 | BO35: 1219.4
B36: 14:30 | C36: 16.4 | F36: 20.2 | G36: 3 | J36: 0.8 | K36: 16.9 | M36: 20.2 | N36: 20.3 | O36: 9.7 | P36: 2.9 | Q36: 4.9 | R36: 20 | S36: 20.5 | T36: 20 | U36: 18.4 | V36: 17.5 | W36: 32.4 | X36: 74.8 | Y36: 47.1 | Z36: 57.7 | AA36: 35 | AB36: 11 | AC36: 4.4 | AD36: 21 | AE36: 6.7 | AF36: 20.4 | AG36: 20.4 | AH36: 20.2 | AI36: 6.4 | AJ36: 74.2 | AK36: 13.2 | AL36: 12.4 | AM36: 3.6 | AN36: 9.3 | AP36: 0.2 | AR36: 14.3 | AS36: 13.6 | AT36: 5.4 | AU36: 10.3 | AV36: 80.6 | AW36: 134.1 | AX36: 91.2 | AY36: 97.6 | AZ36: 0.6 | BA36: 16.6 | BB36: 10.6 | BC36: 53.2 | BD36: 19.9 | BE36: 4.1 | BG36: 2.4 | BH36: 2.4 | BI36: 14.3 | BJ36: 1.3 | BL36: 20 | BM36: 8 | BN36: 17.7 | BO36: 1300.3
B37: 15:00 | C37: 16.6 | F37: 20.2 | G37: 3 | J37: 0.5 | K37: 16.9 | M37: 20.3 | N37: 20.3 | O37: 9.7 | P37: 3 | Q37: 4.9 | R37: 19.8 | S37: 20.4 | T37: 20 | U37: 18.9 | V37: 14 | W37: 22.1 | X37: 67.6 | Y37: 64.3 | Z37: 57.7 | AA37: 35 | AB37: 12 | AC37: 9.4 | AD37: 21 | AE37: 6.7 | AF37: 20.4 | AG37: 20.4 | AH37: 20.2 | AI37: 8 | AJ37: 72.5 | AK37: 10.8 | AL37: 11.2 | AM37: 3.6 | AN37: 9.3 | AP37: 0.2 | AR37: 12.5 | AS37: 13.2 | AT37: 5.4 | AU37: 10.5 | AV37: 102.1 | AW37: 133.2 | AX37: 118.1 | AY37: 96.5 | AZ37: 0.6 | BA37: 16.4 | BB37: 14.7 | BC37: 62.3 | BD37: 20 | BE37: 4.1 | BG37: 2.4 | BH37: 2.4 | BI37: 12.7 | BJ37: 1.2 | BL37: 19.8 | BM37: 8 | BN37: 17.2 | BO37: 1354.2
B38: 15:30 | C38: 16.6 | F38: 20.2 | G38: 3 | J38: 0.4 | K38: 16.9 | M38: 20.2 | N38: 20.3 | O38: 9.7 | P38: 1.9 | Q38: 4.8 | R38: 20 | S38: 20.9 | T38: 20 | U38: 18.8 | V38: 11.2 | W38: 28.6 | X38: 65.3 | Y38: 62.7 | Z38: 49 | AA38: 33.9 | AB38: 10.4 | AC38: 9.1 | AD38: 21 | AE38: 6.7 | AF38: 20.4 | AG38: 20.4 | AH38: 20.2 | AI38: 8.2 | AJ38: 70.5 | AK38: 6.7 | AL38: 5.1 | AN38: 9.3 | AP38: 0.2 | AR38: 10.3 | AS38: 12.7 | AT38: 5.5 | AU38: 10.4 | AV38: 131.8 | AW38: 128.3 | AX38: 122 | AY38: 93.1 | AZ38: 0.6 | BA38: 15.7 | BB38: 13.9 | BC38: 58.1 | BD38: 20 | BE38: 4.1 | BG38: 2.4 | BH38: 2.4 | BI38: 10.6 | BJ38: 1.3 | BL38: 20 | BM38: 7.9 | BN38: 16.2 | BO38: 1339.9
B39: 16:00 | C39: 16.6 | F39: 20.3 | G39: 3 | J39: 0.2 | K39: 16.9 | M39: 20.3 | N39: 20.3 | O39: 9.7 | P39: 2.3 | Q39: 4.8 | R39: 19.9 | S39: 20 | T39: 20 | U39: 18.8 | V39: 9.4 | W39: 39.9 | X39: 84 | Y39: 48.9 | Z39: 64.8 | AA39: 29.7 | AB39: 11.3 | AC39: 7 | AD39: 21 | AE39: 6.8 | AF39: 20.4 | AG39: 20.4 | AH39: 20.2 | AI39: 8.2 | AJ39: 64.1 | AK39: 3.4 | AL39: 2.2 | AN39: 9.3 | AP39: 0.1 | AR39: 8 | AS39: 11.5 | AT39: 5.4 | AU39: 10.4 | AV39: 134.4 | AW39: 116.3 | AX39: 126.2 | AY39: 86.7 | AZ39: 0.6 | BA39: 14.2 | BB39: 14.6 | BC39: 54.8 | BD39: 20 | BE39: 4.1 | BG39: 2.4 | BH39: 2.4 | BI39: 8.2 | BJ39: 1.3 | BL39: 20 | BM39: 8 | BN39: 14.2 | BO39: 1327.9
B40: 16:30 | C40: 16.5 | F40: 20.2 | G40: 3 | J40: 0.1 | K40: 16.9 | M40: 20.3 | N40: 20.3 | O40: 9.7 | P40: 2.4 | Q40: 4.7 | R40: 19.9 | S40: 20.5 | T40: 20 | U40: 18.8 | V40: 10 | W40: 60.4 | X40: 84 | Y40: 62.9 | Z40: 92.2 | AA40: 19.9 | AB40: 8.2 | AC40: 8.2 | AD40: 21 | AE40: 6.8 | AF40: 20.4 | AG40: 20.4 | AH40: 20.2 | AI40: 8.2 | AJ40: 39.9 | AK40: 1 | AL40: 0.6 | AN40: 9.3 | AP40: 0.1 | AR40: 5.4 | AS40: 7.7 | AT40: 5.4 | AU40: 10.4 | AV40: 154.3 | AW40: 73.8 | AX40: 125.9 | AY40: 65.4 | AZ40: 0.6 | BA40: 9.1 | BB40: 17.6 | BC40: 55.3 | BD40: 20 | BE40: 4.1 | BG40: 2.4 | BH40: 2.4 | BI40: 5.6 | BJ40: 1.2 | BL40: 20 | BM40: 8 | BN40: 7.8 | BO40: 1289.4
B41: 17:00 | C41: 16.6 | F41: 20.2 | G41: 2.9 | J41: 0.1 | K41: 16.9 | M41: 20.1 | N41: 20.2 | O41: 9.7 | P41: 2.5 | Q41: 4.7 | R41: 20 | S41: 20.2 | T41: 20 | U41: 18.8 | V41: 8.8 | W41: 62.4 | X41: 78.6 | Y41: 74.7 | Z41: 89.4 | AA41: 8.2 | AB41: 10.1 | AC41: 10.8 | AD41: 21 | AE41: 6.8 | AF41: 20.4 | AG41: 20.4 | AH41: 20.2 | AI41: 8.2 | AJ41: 16.6 | AL41: 0.2 | AN41: 9.3 | AP41: 0.1 | AR41: 2.8 | AS41: 1.9 | AT41: 5.4 | AU41: 10.4 | AV41: 154.7 | AW41: 29.6 | AX41: 129 | AY41: 29.2 | AZ41: 0.6 | BA41: 2.2 | BB41: 16.8 | BC41: 58.2 | BD41: 20 | BE41: 4.3 | BG41: 2.4 | BH41: 2.4 | BI41: 2.9 | BJ41: 1.2 | BL41: 20 | BM41: 8 | BN41: 1 | BO41: 1162.1
B42: 17:30 | C42: 16.7 | F42: 20.4 | G42: 3 | K42: 16.9 | M42: 20.3 | N42: 20.3 | O42: 9.7 | P42: 2.5 | Q42: 4.7 | R42: 20 | S42: 20.1 | T42: 20 | U42: 18.8 | V42: 13.3 | W42: 63.5 | X42: 78.6 | Y42: 64.1 | Z42: 80.1 | AA42: 0.5 | AB42: 11.9 | AC42: 10.8 | AD42: 21 | AE42: 6.8 | AF42: 20.4 | AG42: 20.4 | AH42: 20.2 | AI42: 8.4 | AJ42: 1.5 | AN42: 9.3 | AR42: 0.6 | AT42: 5.5 | AU42: 10.4 | AV42: 146.6 | AW42: 2.1 | AX42: 128.8 | AY42: 2.6 | AZ42: 0.6 | BB42: 16.3 | BC42: 54.9 | BD42: 20 | BE42: 4.3 | BG42: 2.4 | BH42: 2.4 | BI42: 0.7 | BJ42: 1.2 | BL42: 20 | BM42: 8 | BO42: 1051.6
B43: 18:00 | C43: 16.7 | F43: 20.3 | G43: 3 | K43: 17 | M43: 20.2 | N43: 20.3 | O43: 9.7 | P43: 2.5 | Q43: 4.7 | R43: 20 | S43: 20.3 | T43: 20 | U43: 18.8 | V43: 15.3 | W43: 72.7 | X43: 73.5 | Y43: 56.4 | Z43: 81.5 | AB43: 8.6 | AC43: 7.1 | AD43: 21 | AE43: 6.8 | AF43: 20.4 | AG43: 20.4 | AH43: 20.2 | AI43: 8.2 | AK43: 1.4 | AL43: 0.2 | AM43: 0.8 | AN43: 9.3 | AT43: 5.5 | AU43: 10.4 | AV43: 144.5 | AX43: 129.4 | AZ43: 0.6 | BB43: 15.5 | BC43: 57 | BD43: 20.1 | BE43: 4.3 | BG43: 2.4 | BH43: 2.4 | BJ43: 1.2 | BL43: 20 | BM43: 8 | BO43: 1038.6
B44: 18:30 | C44: 16.4 | F44: 20.4 | G44: 3 | K44: 16.7 | M44: 20.4 | N44: 20.3 | O44: 9.8 | P44: 2.6 | Q44: 4.7 | R44: 20 | S44: 20.1 | T44: 20 | U44: 18.9 | V44: 11.4 | W44: 62.2 | X44: 73.5 | Y44: 56.5 | Z44: 83.8 | AB44: 6.4 | AC44: 7.7 | AD44: 21 | AE44: 6.8 | AF44: 20.4 | AG44: 20.4 | AH44: 20.2 | AI44: 8.2 | AK44: 13.6 | AL44: 8.4 | AM44: 3.6 | AN44: 9.3 | AT44: 5.4 | AU44: 10.5 | AV44: 128.4 | AX44: 128 | AZ44: 0.6 | BB44: 14.4 | BC44: 57.9 | BD44: 20 | BE44: 4.3 | BG44: 2.4 | BH44: 2.4 | BJ44: 1.2 | BL44: 20 | BM44: 7.9 | BO44: 1030.1
B45: 19:00 | C45: 16.5 | F45: 20.4 | G45: 3 | K45: 16.4 | M45: 20.2 | N45: 20.3 | O45: 9.8 | P45: 2.5 | Q45: 4.7 | R45: 20 | S45: 20.1 | T45: 20 | U45: 18.9 | V45: 10 | W45: 55.8 | X45: 69.3 | Y45: 57.6 | Z45: 80.9 | AB45: 7.6 | AC45: 7.5 | AD45: 21 | AE45: 6.8 | AF45: 20.4 | AG45: 20.4 | AH45: 20.2 | AI45: 8.6 | AK45: 1.4 | AL45: 1.5 | AM45: 3.6 | AN45: 9.3 | AT45: 5.5 | AU45: 10.3 | AV45: 117.3 | AX45: 125.6 | AZ45: 0.6 | BB45: 15.6 | BC45: 53.3 | BD45: 20 | BE45: 4.3 | BG45: 2.4 | BH45: 2.4 | BJ45: 1.2 | BL45: 20 | BM45: 8 | BO45: 981.2
B46: 19:30 | C46: 16.5 | F46: 20.4 | G46: 3 | K46: 16.3 | M46: 20.2 | N46: 20.2 | O46: 9.8 | P46: 2.6 | Q46: 4.6 | R46: 20 | S46: 20.1 | T46: 20 | U46: 19 | V46: 12.4 | W46: 45.2 | X46: 69.3 | Y46: 75.5 | Z46: 90.7 | AB46: 8.7 | AC46: 7.9 | AD46: 21 | AE46: 7.1 | AF46: 20.4 | AG46: 20.4 | AH46: 20.2 | AI46: 8.6 | AK46: 1.1 | AL46: 0.5 | AM46: 3.6 | AN46: 9.3 | AT46: 5.4 | AU46: 10.5 | AV46: 114.4 | AX46: 124.4 | AZ46: 0.6 | BB46: 10.4 | BC46: 39.6 | BD46: 20 | BE46: 4.4 | BG46: 2.4 | BH46: 2.4 | BJ46: 1.2 | BL46: 20 | BM46: 8 | BO46: 978.3
B47: 20:00 | C47: 16.6 | F47: 20.4 | G47: 3 | K47: 16.3 | M47: 20.2 | N47: 20.3 | O47: 9.9 | P47: 2.6 | Q47: 4.6 | R47: 20 | S47: 20.3 | T47: 20 | U47: 19.2 | V47: 10.6 | W47: 42.8 | X47: 64.2 | Y47: 75.4 | Z47: 91.1 | AB47: 7.3 | AC47: 8.1 | AD47: 21 | AE47: 7.4 | AF47: 20.4 | AG47: 20.4 | AH47: 20.2 | AI47: 8.6 | AM47: 3.6 | AN47: 9.3 | AT47: 5.4 | AU47: 10.4 | AV47: 83.1 | AX47: 103.8 | AZ47: 0.6 | BB47: 10.9 | BC47: 37.4 | BD47: 20 | BE47: 4.4 | BG47: 2.4 | BH47: 2.4 | BJ47: 1.2 | BL47: 20 | BM47: 8 | BO47: 913.8
B48: 20:30 | C48: 16.7 | F48: 20.4 | G48: 3 | K48: 16.3 | M48: 20.2 | N48: 20.3 | O48: 9.9 | P48: 2.6 | Q48: 4.7 | R48: 20 | S48: 20.4 | T48: 20 | V48: 10.6 | W48: 51.4 | X48: 64.2 | Y48: 70.6 | Z48: 93.6 | AB48: 9.9 | AC48: 7 | AD48: 21 | AE48: 7.4 | AF48: 20.4 | AG48: 20.4 | AH48: 20.2 | AI48: 8.5 | AM48: 3.6 | AN48: 9.3 | AT48: 5.4 | AU48: 10.5 | AV48: 71.3 | AX48: 88.4 | AZ48: 0.6 | BB48: 11.5 | BC48: 35.2 | BD48: 20 | BE48: 4.4 | BG48: 2.4 | BH48: 2.4 | BJ48: 1.2 | BL48: 20 | BM48: 8 | BO48: 873.9
B49: 21:00 | C49: 16.9 | F49: 20.4 | G49: 3 | K49: 16.3 | M49: 20.1 | N49: 20.2 | O49: 9.8 | P49: 2.1 | Q49: 4.7 | R49: 20 | S49: 19.9 | T49: 20 | V49: 7.5 | W49: 52.4 | X49: 62.5 | Y49: 88.8 | Z49: 91.6 | AB49: 12.6 | AC49: 8.6 | AD49: 21 | AE49: 7.4 | AF49: 20.4 | AG49: 20.4 | AH49: 20.2 | AI49: 8.6 | AK49: 0.4 | AL49: 0.4 | AM49: 3.6 | AN49: 9.3 | AT49: 5.5 | AU49: 10.4 | AV49: 70.9 | AX49: 82.5 | AZ49: 0.6 | BB49: 11.9 | BC49: 38.9 | BD49: 20 | BE49: 4.4 | BG49: 2.4 | BH49: 2.4 | BJ49: 1.2 | BL49: 20 | BM49: 8 | BO49: 888.2
B50: 21:30 | C50: 16.7 | F50: 20.4 | G50: 3 | K50: 16.3 | M50: 20.4 | N50: 20.3 | O50: 9.7 | P50: 2 | Q50: 4.6 | R50: 20 | S50: 20.4 | T50: 20 | V50: 5.6 | W50: 55.9 | X50: 62.5 | Y50: 86 | Z50: 94.3 | AB50: 12.5 | AC50: 5.9 | AD50: 21 | AE50: 7.4 | AF50: 20.4 | AG50: 20.4 | AH50: 20.2 | AI50: 8.5 | AM50: 3.6 | AN50: 9.3 | AT50: 5.4 | AU50: 10.4 | AV50: 63.3 | AX50: 73.9 | AZ50: 0.6 | BB50: 11.9 | BC50: 37.5 | BD50: 20 | BE50: 4.4 | BG50: 2.4 | BH50: 2.4 | BJ50: 1.2 | BL50: 20 | BM50: 8 | BO50: 868.7
B51: 22:00 | C51: 16.4 | F51: 20.4 | G51: 3 | K51: 16.3 | M51: 20.3 | N51: 20.3 | O51: 9.9 | P51: 2.5 | Q51: 4.9 | R51: 20 | S51: 20.1 | T51: 20 | U51: 19 | V51: 2.2 | W51: 65.7 | X51: 64.3 | Y51: 82.4 | Z51: 93.6 | AB51: 10.9 | AC51: 6.9 | AD51: 21 | AE51: 7.3 | AF51: 20.4 | AG51: 20.4 | AH51: 20.2 | AI51: 8.6 | AM51: 3.6 | AN51: 9.3 | AT51: 5.5 | AU51: 10.4 | AV51: 38.5 | AX51: 45.6 | AZ51: 0.6 | BB51: 10.2 | BC51: 37.6 | BD51: 20 | BE51: 4.4 | BG51: 2.4 | BH51: 2.4 | BJ51: 1.2 | BL51: 20 | BM51: 8 | BO51: 836.7
B52: 22:30 | C52: 16.6 | F52: 20.4 | G52: 3 | K52: 16.3 | M52: 20.2 | N52: 20.3 | O52: 9.7 | P52: 2.6 | Q52: 5.1 | R52: 19.9 | S52: 20.3 | T52: 20 | U52: 18.6 | V52: 2.5 | W52: 58.4 | X52: 64.3 | Y52: 78.5 | Z52: 94.5 | AB52: 10.6 | AC52: 6.1 | AD52: 21 | AE52: 7.3 | AF52: 20.4 | AG52: 20.4 | AH52: 20.2 | AI52: 8.5 | AM52: 3.7 | AN52: 9.3 | AT52: 5.4 | AU52: 10.2 | AV52: 38.9 | AX52: 42.2 | AZ52: 0.6 | BB52: 8.9 | BC52: 33.9 | BD52: 19.9 | BE52: 4.4 | BG52: 2.4 | BH52: 2.4 | BJ52: 1.2 | BL52: 20 | BM52: 7.9 | BO52: 817
B53: 23:00 | C53: 16.5 | F53: 20.3 | G53: 3 | K53: 16.3 | M53: 20.4 | N53: 20.3 | O53: 9.8 | P53: 2.6 | Q53: 5 | R53: 19.8 | S53: 20.3 | T53: 20 | U53: 18.6 | V53: 2.5 | W53: 54.5 | X53: 63.5 | Y53: 76.5 | Z53: 87.8 | AB53: 10.9 | AC53: 7 | AD53: 21 | AE53: 7.3 | AF53: 20.4 | AG53: 20.4 | AH53: 20.2 | AI53: 8.5 | AM53: 3.7 | AN53: 9.3 | AT53: 5.4 | AU53: 10.5 | AV53: 34.6 | AX53: 42.1 | AZ53: 0.6 | BB53: 9.4 | BC53: 32.7 | BD53: 20.1 | BE53: 4.4 | BG53: 2.4 | BH53: 2.4 | BJ53: 1.2 | BL53: 19.9 | BM53: 7.9 | BO53: 800
B54: 23:30 | C54: 16.7 | F54: 20.4 | G54: 3 | K54: 16.3 | M54: 20.2 | N54: 20.2 | O54: 9.9 | P54: 2.7 | Q54: 5 | R54: 20 | S54: 20.1 | T54: 20 | U54: 18.5 | V54: 3.4 | W54: 38.8 | X54: 63.5 | Y54: 62.9 | Z54: 85.3 | AB54: 11.7 | AC54: 6.2 | AD54: 21 | AE54: 7.3 | AF54: 20.4 | AG54: 20.4 | AH54: 20.2 | AI54: 8.6 | AM54: 3.7 | AN54: 9.3 | AQ54: 1.8 | AT54: 5.5 | AU54: 10.4 | AV54: 33.5 | AX54: 38.5 | AZ54: 0.6 | BB54: 9.7 | BC54: 34.2 | BD54: 20 | BE54: 4.4 | BG54: 2.4 | BH54: 2.4 | BJ54: 1.2 | BL54: 20.1 | BM54: 8 | BO54: 768.4
B55: 0:00 | C55: 16.5 | F55: 20.4 | G55: 2 | K55: 16.3 | M55: 20.2 | N55: 20.2 | O55: 9.9 | P55: 2.8 | Q55: 5 | R55: 20 | S55: 19.9 | T55: 14.3 | U55: 18.6 | V55: 2.5 | W55: 35.1 | X55: 59.8 | Y55: 61.4 | Z55: 80.8 | AB55: 4.7 | AC55: 3.4 | AD55: 21 | AE55: 7.3 | AF55: 20.4 | AG55: 20.4 | AH55: 20.2 | AI55: 8.6 | AM55: 3.7 | AN55: 9.3 | AQ55: 1.5 | AT55: 5.4 | AU55: 10.4 | AV55: 44 | AX55: 46.5 | AZ55: 0.6 | BB55: 11.5 | BC55: 32.8 | BD55: 20 | BE55: 4.4 | BG55: 2.4 | BH55: 2.4 | BJ55: 1.2 | BL55: 20 | BM55: 7.9 | BO55: 755.7
B56: EJEC MWh | C56: 397 | D56: 0 | E56: 0 | F56: 486.95 | G56: 71.35 | H56: 0 | I56: 0 | J56: 7.3 | K56: 407.15 | L56: 0 | M56: 484.4 | N56: 486.6 | O56: 234.05 | P56: 65.8 | Q56: 114.2 | R56: 478.95 | S56: 485.4 | T56: 476.75 | U56: 423.35 | V56: 317.55 | W56: 796.15 | X56: 1750.95 | Y56: 1026.85 | Z56: 1441.65 | AA56: 328.5 | AB56: 138.35 | AC56: 92.7 | AD56: 504 | AE56: 166.9 | AF56: 489.6 | AG56: 489.6 | AH56: 484.8 | AI56: 185.35 | AJ56: 692.7 | AK56: 192.65 | AL56: 201.25 | AM56: 75.9 | AN56: 223.2 | AO56: 0 | AP56: 1.7 | AQ56: 25.4 | AR56: 131.2 | AS56: 134.8 | AT56: 130.3 | AU56: 250.1 | AV56: 1129.65 | AW56: 1274.95 | AX56: 1152 | AY56: 946.4 | AZ56: 14.4 | BA56: 166.55 | BB56: 356.4 | BC56: 1103.4 | BD56: 480.1 | BE56: 103.7 | BF56: 0 | BG56: 57.6 | BH56: 57.6 | BI56: 130.65 | BJ56: 29.05 | BK56: 0 | BL56: 479.8 | BM56: 191.25 | BN56: 166.45 | BO56: 22731.35
L70: TERMOELÉCTRICA | M70: 615.9 | N70: 2.7094739 | O70: #FF0000
L71: SOLAR | M71: 3981.2 | N71: 17.514138 | O71: #FBFB00
L72: HIDROELÉCTRICA | M72: 8434.7 | N72: 37.106023 | O72: #00B0F0
L73: EÓLICA | M73: 9699.55 | N73: 42.670365 | O73: #FBBD00

Sheet COGENERACIÓN
B3: miércoles, 9 de Abril del 2025
B5: CENTRALES DE COGENERACIÓN DEL SEIN
B6: HORA | C6: AGRO INDUSTRIAL PARAMONGA S.A. | D6: AGROAURORA S.A.C. | E6: AGROINDUSTRIAS SAN JACINTO S.A.A. | F6: BIOENERGIA DEL CHIRA S.A. | G6: GM OPERACIONES S.A.C. | H6: SDF ENERGIA SAC | I6: TOTAL COGENERACION
C7: C.T. PARAMONGA | D7: C.T. MAPLE | E7: C.T SAN JACINTO | F7: C.T. CAÑA BRAVA | G7: C.T. REFINERÍA TALARA | H7: C.T. OQUENDO | I7: MW
B8: 0:30 | C8: 16.4 | G8: 43.7 | H8: 32.3 | I8: 92.4
B9: 1:00 | C9: 16.5 | G9: 43.9 | H9: 32.2 | I9: 92.6
B10: 1:30 | C10: 16.6 | G10: 44.1 | H10: 32.2 | I10: 92.9
B11: 2:00 | C11: 16.7 | G11: 44.8 | H11: 32.1 | I11: 93.6
B12: 2:30 | C12: 16.6 | G12: 44.2 | H12: 32.3 | I12: 93.1
B13: 3:00 | C13: 16.5 | G13: 43.7 | H13: 32.3 | I13: 92.5
B14: 3:30 | C14: 16.6 | G14: 44 | H14: 32.3 | I14: 92.9
B15: 4:00 | C15: 16.5 | G15: 43.9 | H15: 32.2 | I15: 92.6
B16: 4:30 | C16: 16.5 | G16: 44.5 | H16: 32.3 | I16: 93.3
B17: 5:00 | C17: 16.6 | G17: 44.4 | H17: 32.2 | I17: 93.2
B18: 5:30 | C18: 16.5 | G18: 44.5 | H18: 32.4 | I18: 93.4
B19: 6:00 | C19: 16.7 | G19: 44 | H19: 32.4 | I19: 93.1
... B55: 0:00 | C55: 16.5 | G55: 59.5 | H55: 32.2 | I55: 108.2
B56: EJEC MWh | C56: 397 | D56: 0 | E56: 0 | F56: 0 | G56: 1158 | H56: 767.5 | I56: 2322.5

Sheet EVO_PRO_ENE
B3: martes, 1 de Abril del 2025 - miércoles, 9 de Abril del 2025
B5: EVOLUCIÓN DE LA PRODUCCIÓN DE LA ENERGÍA DIARIA DE LOS INTEGRANTES DEL COES (MWh)
B6: EMPRESA | C6: CENTRAL | D6: UNIDAD | E6: TIPO | F6: Abril
F7: 1 | G7: 2 | H7: 3 | I7: 4 | J7: 5 | K7: 6 | L7: 7 | M7: 8 | N7: 9 | O7: TOTAL
B8: AGRO INDUSTRIAL PARAMONGA S.A. | C8: C.T. PARAMONGA | D8: TV-01 | E8: TERMOELÉCTRICA | F8: 169.5 | G8: 245.7 | H8: 400.2 | I8: 407.05 | J8: 368.75 | K8: 335.9 | L8: 386.5 | M8: 390.9 | N8: 397 | O8: 3101.5
B9: AGROAURORA S.A.C. | C9: C.T. MAPLE ETANOL | D9: TV | E9: TERMOELÉCTRICA | O9: 0
B10: AGROINDUSTRIAS SAN JACINTO S.A.A. | C10: C.T. SAN JACINTO | D10: CENTRAL | E10: TERMOELÉCTRICA | F10: 120.97 | G10: 109.3 | H10: 25.6 | O10: 255.87
B11: ANDEAN POWER S.A.C. | C11: C.H.CARHUAC | D11: CENTRAL | E11: HIDROELÉCTRICA | F11: 488.5 | G11: 480.45 | H11: 486.9 | I11: 484.9 | J11: 483.9 | K11: 480.35 | L11: 485.6 | M11: 486.15 | N11: 486.95 | O11: 4363.7
B12: ASOCIACIÓN SANTA LUCIA DE CHACAS | C12: C.H. HUALLIN | D12: CENTRAL | E12: HIDROELÉCTRICA | F12: 71.9 | G12: 70.3 | H12: 71.4 | I12: 71.5 | J12: 72 | K12: 72 | L12: 72 | M12: 71.95 | N12: 71.35 | O12: 644.4
B13: ATRIA ENERGIA S.A.C. | C13: C.H. PURMACANA | D13: CENTRAL | E13: HIDROELÉCTRICA | F13: 1.95 | G13: 1.2 | H13: 1.9 | I13: 2.5 | J13: 1.7 | O13: 9.25
B14: BIOENERGIA DEL CHIRA S.A. | C14: C.T. CAÑA BRAVA | D14: CENTRAL | E14: TERMOELÉCTRICA | O14: 0
B15: CELEPSA | C15: C.H. EL PLATANAL | D15: CENTRAL | E15: HIDROELÉCTRICA | F15: 5347.15 | G15: 5339.95 | H15: 1378.3 | I15: 5218.2 | J15: 5088.55 | K15: 4928.1 | L15: 4820.1 | M15: 4611.65 | N15: 4963.3 | O15: 41695.3
B16: CELEPSA RENOVABLES S.R.L. | C16: C.H. MARAÑON | D16: CENTRAL | E16: HIDROELÉCTRICA | F16: 473.53848 | G16: 472.8 | H16: 470.1 | I16: 472.4 | J16: 472.8 | K16: 472.8 | L16: 472.8 | M16: 472.8 | N16: 472.8 | O16: 4252.8385
B17: CENTRALES SANTA ROSA S.A.C. | C17: C.H. SANTA ROSA I | D17: CENTRAL | E17: HIDROELÉCTRICA | O17: 0
B18: CENTRALES SANTA ROSA S.A.C. | C18: C.H. SANTA ROSA II | D18: CENTRAL | E18: HIDROELÉCTRICA | O18: 0
B19: CHINANGO S.A.C. | C19: C.H. CHIMAY | D19: CENTRAL | E19: HIDROELÉCTRICA | F19: 3355.35 | G19: 3375.8 | H19: 3482.65 | I19: 3415.15 | J19: 3427.9 | K19: 3416.3 | L19: 3380.6 | M19: 3331.3 | N19: 3419.15 | O19: 30604.2
B20: CHINANGO S.A.C. | C20: C.H. YANANGO | D20: CENTRAL | E20: HIDROELÉCTRICA | F20: 1016.7 | G20: 1013.95 | H20: 1013.6 | I20: 1009.2 | J20: 186.5 | K20: 678.65 | L20: 1017.15 | M20: 1016.6 | N20: 1016.6 | O20: 7968.95
B21: COLCA SOLAR S.A.C. | C21: C.S. YARUCAYA | D21: CENTRAL | E21: SOLAR | F21: 5.2 | G21: 4.6 | H21: 5.55 | I21: 7.85 | J21: 5.6 | K21: 6.8 | L21: 8.05 | M21: 6.95 | N21: 7.3 | O21: 57.9
B22: EGASA | C22: C.H. CHARCANI III | D22: CENTRAL | E22: HIDROELÉCTRICA | F22: 156 | G22: 157.75 | H22: 158.4 | I22: 158.6 | J22: 157.05 | K22: 159.75 | L22: 158.4 | M22: 156.4 | N22: 154.5 | O22: 1416.85
B23: EGASA | C23: C.H. CHARCANI IV | D23: CENTRAL | E23: HIDROELÉCTRICA | F23: 242.5 | G23: 242.5 | H23: 242.45 | I23: 242.85 | J23: 242.9 | K23: 243.1 | L23: 242.5 | M23: 242.9 | N23: 242.45 | O23: 2184.15
B24: EGASA | C24: C.H. CHARCANI V | D24: CENTRAL | E24: HIDROELÉCTRICA | F24: 3149.6 | G24: 3430.2 | H24: 3438.15 | I24: 3168.35 | J24: 3422.5 | K24: 3434.9 | L24: 3434.9 | M24: 3050 | N24: 3197.05 | O24: 29725.65
B25: EGASA | C25: C.H. CHARCANI VI | D25: CENTRAL | E25: HIDROELÉCTRICA | F25: 210.05 | G25: 214.55 | H25: 215.4 | I25: 211.45 | J25: 214.7 | K25: 214.85 | L25: 215.25 | M25: 215.6 | N25: 215.15 | O25: 1927
B26: EGASA | C26: C.T. CHILINA DIESEL | D26: CENTRAL | E26: TERMOELÉCTRICA | F26: 9 | O26: 9
B27: EGASA | C27: C.T. CHILINA DIESEL | D27: TG | E27: TERMOELÉCTRICA | O27: 0
B28: EGASA | C28: C.T. MOLLENDO DIESEL | D28: CENTRAL | E28: TERMOELÉCTRICA | O28: 0
B29: EGEJUNIN | C29: C.H. HUASAHUASI I | D29: CENTRAL | E29: HIDROELÉCTRICA | F29: 475.4 | G29: 476.1 | H29: 475.8 | I29: 474.55 | J29: 471.75 | K29: 475.3 | L29: 474.1 | M29: 449.65 | N29: 407.15 | O29: 4179.8
B30: EGEJUNIN | C30: C.H. RUNATULLO II | D30: CENTRAL | E30: HIDROELÉCTRICA | F30: 483.85 | G30: 481.95 | H30: 482.9 | I30: 482.15 | J30: 473.65 | K30: 479.9 | L30: 480.75 | M30: 482.15 | N30: 484.4 | O30: 4331.7
B31: EGEJUNIN | C31: C.H. RUNATULLO III | D31: CENTRAL | E31: HIDROELÉCTRICA | F31: 486.55 | G31: 486.55 | H31: 486.6 | I31: 486.45 | J31: 486.4 | K31: 486.85 | L31: 486.85 | M31: 486.6 | N31: 486.6 | O31: 4379.45
B32: EGEJUNIN | C32: C.H. SANTA CRUZ I | D32: CENTRAL | E32: HIDROELÉCTRICA | F32: 235.65 | G32: 235.2 | H32: 237.35 | I32: 229.55 | J32: 235.75 | K32: 235.05 | L32: 234.25 | M32: 234.05 | N32: 234.05 | O32: 2110.9
B33: EGEMSA | C33: C.H. MACHUPICCHU | D33: CENTRAL | E33: HIDROELÉCTRICA | F33: 3962.35 | G33: 3952.55 | H33: 3937.9 | I33: 3946.1 | J33: 3906.6 | K33: 3890.85 | L33: 3968.85 | M33: 3960.7 | N33: 3928.15 | O33: 35454.05
B34: EGESUR | C34: C.H. ARICOTA I | D34: CENTRAL | E34: HIDROELÉCTRICA | F34: 178.75 | G34: 179.35 | H34: 180.65 | I34: 180.3 | J34: 177.6 | K34: 180.65 | L34: 180.45 | M34: 178.55 | N34: 181.05 | O34: 1617.35
B35: EGESUR | C35: C.H. ARICOTA II | D35: CENTRAL | E35: HIDROELÉCTRICA | F35: 78.25 | G35: 79.15 | H35: 78.25 | I35: 80.4 | J35: 79.6 | K35: 79.7 | L35: 79.65 | M35: 78.5 | N35: 78.7 | O35: 712.2
B36: EGESUR | C36: C.T. INDEPENDENCIA | D36: CENTRAL | E36: TERMOELÉCTRICA | F36: 6.95 | G36: 31.25 | H36: 237 | I36: 126.85 | J36: 55.15 | K36: 46.35 | N36: 131.95 | O36: 635.5
B37: ELECTRICA YANAPAMPA SAC | C37: C.H. YANAPAMPA | D37: CENTRAL | E37: HIDROELÉCTRICA | F37: 74.5 | G37: 69.1 | H37: 73.75 | I37: 67.1 | J37: 72.45 | K37: 70.3 | L37: 73.4 | M37: 73.4 | N37: 65.8 | O37: 639.8
B38: ELECTROPERU | C38: C.H. MANTARO | D38: CENTRAL | E38: HIDROELÉCTRICA | F38: 15574.5 | G38: 15381 | H38: 15127.05 | I38: 14878.9 | J38: 15509.65 | K38: 14698.4 | L38: 14679.5 | M38: 14286.7 | N38: 14716.15 | O38: 134851.85
B39: ELECTROPERU | C39: C.H. RESTITUCION | D39: CENTRAL | E39: HIDROELÉCTRICA | F39: 4479.45 | G39: 4692.25 | H39: 4788.4 | I39: 4812.75 | J39: 3560 | K39: 3195.95 | L39: 3320.5 | M39: 3487.05 | N39: 4891.8 | O39: 37228.15
B40: ELECTROPERU | C40: C.T. TUMBES | D40: MAK1 | E40: TERMOELÉCTRICA | O40: 0
B41: ELECTROPERU | C41: C.T. TUMBES | D41: MAK2 | E41: TERMOELÉCTRICA | O41: 0
B42: EMPRESA DE GENERACION ELECTRICA CANCHAYLLO SAC | C42: C.H. CANCHAYLLO | D42: CENTRAL | E42: HIDROELÉCTRICA | F42: 120.25 | G42: 96.8 | H42: 112.6 | I42: 117.35 | J42: 121 | K42: 120.05 | L42: 117.95 | M42: 116.65 | N42: 114.2 | O42: 1036.85
B43: EMPRESA DE GENERACION ELECTRICA RIO BAÑOS S.A.C. | C43: C.H. RUCUY | D43: CENTRAL | E43: HIDROELÉCTRICA | F43: 478.8 | G43: 360.9 | H43: 393 | I43: 246.75 | J43: 478.65 | K43: 478.7 | L43: 478 | M43: 478.8 | N43: 478.95 | O43: 3872.55
B44: EMPRESA DE GENERACION ELECTRICA SANTA ANA S.A.C. | C44: C.H. RENOVANDES H1 | D44: CENTRAL | E44: HIDROELÉCTRICA | F44: 487.75 | G44: 487.05 | H44: 487.75 | I44: 486.95 | J44: 417.7 | K44: 487.15 | L44: 486.95 | M44: 485.1 | N44: 485.4 | O44: 4311.8
B45: EMPRESA DE GENERACION HUALLAGA | C45: C.H. CHAGLLA | D45: CENTRAL | E45: HIDROELÉCTRICA | F45: 10661.95 | G45: 10629.55 | H45: 10754.5 | I45: 10970.9 | J45: 10660.45 | K45: 9385.5 | L45: 9964.75 | M45: 9993.5 | N45: 9951.85 | O45: 92972.95
B46: EMPRESA DE GENERACION HUALLAGA | C46: P.C.H. CHAGLLA | D46: CENTRAL | E46: HIDROELÉCTRICA | F46: 154.85 | G46: 154.95 | H46: 154.55 | I46: 155.55 | J46: 155.3 | K46: 155.05 | L46: 154.75 | M46: 154.35 | N46: 154.7 | O46: 1394.05
B47: EMPRESA DE GENERACION HUANZA | C47: C.H. HUANZA | D47: CENTRAL | E47: HIDROELÉCTRICA | F47: 2125.9 | G47: 2037.7 | H47: 2140 | I47: 2192.2 | J47: 2288.2 | K47: 2285.95 | L47: 2192.55 | M47: 2215.3 | N47: 2165.15 | O47: 19642.95
B48: EMPRESA ELECTRICA AGUA AZUL | C48: C.H. POTRERO | D48: CENTRAL | E48: HIDROELÉCTRICA | F48: 410.7 | G48: 458.1 | H48: 469.4 | I48: 431.05 | J48: 479.7 | K48: 474.6 | L48: 480 | M48: 480 | N48: 476.75 | O48: 4160.3
B49: EMPRESA ELECTRICA RIO DOBLE | C49: C.H. LAS PIZARRAS | D49: CENTRAL | E49: HIDROELÉCTRICA | G49: 198.25 | H49: 391.95 | I49: 457.5 | J49: 456.1 | K49: 455.35 | L49: 454.5 | M49: 453.9 | N49: 423.35 | O49: 3290.9
B50: ENEL GENERACION PIURA S.A. | C50: C.T. MALACAS 1 | D50: TG6 | E50: TERMOELÉCTRICA | F50: 1019 | G50: 814.1 | H50: 813.8 | I50: 823.7 | J50: 747.2 | K50: 34.7 | L50: 649.9 | M50: 669.5 | N50: 694.8 | O50: 6266.7
B51: ENEL GENERACION PIURA S.A. | C51: C.T. MALACAS 2 | D51: TG4 | E51: TERMOELÉCTRICA | O51: 0
B52: ENEL GENERACION PIURA S.A. | C52: C.T. RF DE GENERACION TALARA | D52: TG5 | E52: TERMOELÉCTRICA | O52: 0
B53: ENERGÍA EÓLICA S.A. | C53: C.E. CUPISNIQUE | D53: CENTRAL | E53: EÓLICA | F53: 1063.95 | G53: 1005.35 | H53: 861.2 | I53: 769 | J53: 801.95 | K53: 1122.55 | L53: 1183.5 | M53: 976.95 | N53: 796.15 | O53: 8580.6
B54: ENERGÍA EÓLICA S.A. | C54: C.E. TALARA | D54: CENTRAL | E54: EÓLICA | F54: 108.95 | G54: 206.5 | H54: 105.4 | I54: 241.5 | J54: 166.2 | K54: 297.3 | L54: 419.35 | M54: 198.75 | N54: 317.55 | O54: 2061.5
B55: ENERGIA RENOVABLE DEL SUR S.A. | C55: C.E. SAN JUAN | D55: CENTRAL | E55: EÓLICA | F55: 2690.05 | G55: 2781.75 | H55: 2483.9 | I55: 1829.25 | J55: 1028.15 | K55: 2249 | L55: 2083.9 | M55: 2008.95 | N55: 1750.95 | O55: 18905.9
B56: ENGIE | C56: C.E. PUNTA LOMITAS | D56: PL-BL1 | E56: EÓLICA | F56: 1634.25 | G56: 1352.8 | H56: 1500.95 | I56: 1406.8 | J56: 1156 | K56: 1529.45 | L56: 1744.1 | M56: 1646.8 | N56: 1026.85 | O56: 12998
B57: ENGIE | C57: C.E. PUNTA LOMITAS | D57: PL-BL2 | E57: EÓLICA | F57: 2042.2 | G57: 1773.95 | H57: 1973.35 | I57: 1691.25 | J57: 1734.7 | K57: 1740.05 | L57: 1825.15 | M57: 2006.15 | N57: 1441.65 | O57: 16228.45
B58: ENGIE | C58: C.E. PUNTA LOMITAS_EXP | D58: PUN LOM_EXP-BL1 | E58: EÓLICA | F58: 274.2 | G58: 191.35 | H58: 214.25 | I58: 233.5 | J58: 115.7 | K58: 171.2 | L58: 249.45 | M58: 277.2 | N58: 138.35 | O58: 1865.2
B59: ENGIE | C59: C.E. PUNTA LOMITAS_EXP | D59: PUN LOM_EXP-BL2 | E59: EÓLICA | F59: 142.75 | G59: 106.7 | H59: 127.9 | I59: 155 | J59: 130.95 | K59: 165.8 | L59: 211.9 | M59: 164.1 | N59: 92.7 | O59: 1297.8
B60: ENGIE | C60: C.H. QUITARACSA | D60: CENTRAL | E60: HIDROELÉCTRICA | O60: 0
B61: ENGIE | C61: C.H. YUNCAN | D61: CENTRAL | E61: HIDROELÉCTRICA | F61: 2071.75 | G61: 2068.6 | H61: 2071.6 | I61: 2070.9 | J61: 2071.95 | K61: 2071.7 | L61: 2073.7 | M61: 2070.35 | N61: 2074.6 | O61: 18645.15
B62: ENGIE | C62: C.S. INTIPAMPA | D62: CENTRAL | E62: SOLAR | F62: 277.95 | G62: 208.65 | H62: 294.3 | I62: 307.75 | J62: 328.15 | K62: 296.25 | L62: 328 | M62: 325.65 | N62: 328.5 | O62: 2695.2
B63: ENGIE | C63: C.T. CHILCA 1 | D63: TG1 | E63: TERMOELÉCTRICA | F63: 3436.15 | G63: 3474.7 | H63: 3658.45 | I63: 3920.3 | J63: 3531.45 | K63: 2517.7 | L63: 3192.3 | M63: 3117.85 | N63: 230 | O63: 27078.9
B64: ENGIE | C64: C.T. CHILCA 1 | D64: TG2 | E64: TERMOELÉCTRICA | O64: 0
B65: ENGIE | C65: C.T. CHILCA 1 | D65: TG3 | E65: TERMOELÉCTRICA | F65: 3042.95 | G65: 3618.95 | H65: 4172 | I65: 4513.65 | J65: 3512.8 | K65: 2669.6 | L65: 3571.05 | M65: 3665.75 | N65: 4027.9 | O65: 32794.65
B66: ENGIE | C66: C.T. CHILCA 1 | D66: TV | E66: TERMOELÉCTRICA | F66: 3048.95 | G66: 3682.95 | H66: 3961.4 | I66: 4167.25 | J66: 3614.7 | K66: 3011.9 | L66: 3559.1 | M66: 3503.35 | N66: 1841.3 | O66: 30390.9
B67: ENGIE | C67: C.T. CHILCA 2 | D67: TG41 | E67: TERMOELÉCTRICA | I67: 273.8 | N67: 168.7 | O67: 442.5
B68: ENGIE | C68: C.T. CHILCA 2 | D68: TV42 | E68: TERMOELÉCTRICA | O68: 0
B69: ENGIE | C69: C.T. NEPI | D69: TG41 | E69: TERMOELÉCTRICA | O69: 0
B70: ENGIE | C70: C.T. NEPI | D70: TG42 | E70: TERMOELÉCTRICA | O70: 0
B71: ENGIE | C71: C.T. NEPI | D71: TG43 | E71: TERMOELÉCTRICA | O71: 0
B72: ENGIE | C72: C.T. RF PLANTA ILO | D72: TG1 | E72: TERMOELÉCTRICA | J72: 216.2 | O72: 216.2
B73: ENGIE | C73: C.T. RF PLANTA ILO | D73: TG2 | E73: TERMOELÉCTRICA | O73: 0
B74: ENGIE | C74: C.T. RF PLANTA ILO | D74: TG3 | E74: TERMOELÉCTRICA | O74: 0
B75: FENIX POWER PERÚ | C75: C.T. FENIX | D75: GT11 | E75: TERMOELÉCTRICA | F75: 3186.75 | G75: 3118.65 | O75: 6305.4
B76: FENIX POWER PERÚ | C76: C.T. FENIX | D76: GT12 | E76: TERMOELÉCTRICA | F76: 3191.9 | G76: 3310.45 | H76: 3701 | O76: 10203.35
B77: FENIX POWER PERÚ | C77: C.T. FENIX | D77: TV10 | E77: TERMOELÉCTRICA | F77: 3798.4 | G77: 3735.75 | H77: 1934.9 | O77: 9469.05
B78: GENERACIÓN ANDINA S.A.C. | C78: C.H. 8 DE AGOSTO | D78: CENTRAL | E78: HIDROELÉCTRICA | F78: 503.5 | G78: 502.5 | H78: 503.8 | I78: 465.4 | J78: 504 | K78: 504 | L78: 504 | M78: 504 | N78: 504 | O78: 4495.2
B79: GENERACIÓN ANDINA S.A.C. | C79: C.H. EL CARMEN | D79: CENTRAL | E79: HIDROELÉCTRICA | F79: 200.85 | G79: 201.6 | H79: 201.45 | I79: 194.05 | J79: 201.35 | K79: 193.85 | L79: 182.4 | M79: 170.5 | N79: 166.9 | O79: 1712.95
B80: GENERADORA DE ENERGÍA DEL PERÚ | C80: C.H. ÁNGEL I | D80: CENTRAL | E80: HIDROELÉCTRICA | F80: 489.6 | G80: 489.6 | H80: 489.6 | I80: 489.6 | J80: 489.6 | K80: 489.6 | L80: 489.6 | M80: 489.6 | N80: 489.6 | O80: 4406.4
B81: GENERADORA DE ENERGÍA DEL PERÚ | C81: C.H. ÁNGEL II | D81: CENTRAL | E81: HIDROELÉCTRICA | F81: 489.6 | G81: 489.6 | H81: 489.6 | I81: 489.6 | J81: 489.6 | K81: 489.6 | L81: 489.6 | M81: 489.6 | N81: 489.6 | O81: 4406.4
B82: GENERADORA DE ENERGÍA DEL PERÚ | C82: C.H. ÁNGEL III | D82: CENTRAL | E82: HIDROELÉCTRICA | F82: 484.8 | G82: 484.8 | H82: 484.8 | I82: 484.8 | J82: 484.8 | K82: 484.8 | L82: 484.8 | M82: 484.8 | N82: 484.8 | O82: 4363.2
B83: GENERADORA DE ENERGÍA DEL PERÚ | C83: C.H. LA JOYA | D83: CENTRAL | E83: HIDROELÉCTRICA | F83: 184.05 | G83: 162.95 | H83: 194.25 | I83: 201.35 | J83: 218.05 | K83: 126.45 | L83: 225.25 | M83: 205.5 | N83: 185.35 | O83: 1703.2
B84: GM OPERACIONES S.A.C. | C84: CT REFINERIA TALARA | D84: TV1 REF TALARA | E84: TERMOELÉCTRICA | F84: 114.1 | G84: 432.7 | H84: 590.8 | I84: 789.4 | J84: 936.7 | K84: 1033.1 | L84: 1058.9 | M84: 1053.25 | N84: 1042.8 | O84: 7051.75
B85: GM OPERACIONES S.A.C. | C85: CT REFINERIA TALARA | D85: TV2 REF TALARA | E85: TERMOELÉCTRICA | N85: 115.2 | O85: 115.2
B86: GR CORTARRAMA SOCIEDAD ANONIMA CERRADA | C86: C.S. MATARANI | D86: C.S. MATARANI | E86: SOLAR | F86: 618.9 | G86: 610.2 | H86: 579.2 | I86: 677.1 | J86: 676.1 | K86: 10.9 | L86: 671.2 | M86: 679.3 | N86: 692.7 | O86: 5215.6
B87: GR PAINO SOCIEDAD ANONIMA CERRADA | C87: C.E. HUAMBOS | D87: CENTRAL | E87: EÓLICA | F87: 33.05 | G87: 79.4 | H87: 72.7 | I87: 186.65 | J87: 242.8 | K87: 230.25 | L87: 201.1 | M87: 146 | N87: 192.65 | O87: 1384.6
B88: GR TARUCA SOCIEDAD ANONIMA CERRADA | C88: C.E. DUNA | D88: CENTRAL | E88: EÓLICA | F88: 53.2 | G88: 103.5 | H88: 102 | I88: 241.35 | J88: 307.25 | K88: 285.6 | L88: 264.25 | M88: 198.1 | N88: 201.25 | O88: 1756.5
B89: HIDROCAÑETE S.A. | C89: C.H. IMPERIAL | D89: CENTRAL | E89: HIDROELÉCTRICA | F89: 84.85 | G89: 85.55 | H89: 86 | I89: 85.1 | J89: 87.1 | K89: 88.45 | L89: 87.1 | M89: 85.75 | N89: 75.9 | O89: 765.8
B90: HIDROELECTRICA HUANCHOR S.A.C. | C90: C.H. HUANCHOR | D90: CENTRAL | E90: HIDROELÉCTRICA | F90: 444.3032 | G90: 440.55 | H90: 442.15 | I90: 398.3 | J90: 437.4 | K90: 445.05 | L90: 443.95 | M90: 444.6 | N90: 444.6 | O90: 3940.9032
B91: HUAURA POWER GROUP S.A. | C91: C.H. YARUCAYA | D91: CENTRAL | E91: HIDROELÉCTRICA | F91: 444.35 | G91: 228.25 | H91: 94.55 | I91: 119.7 | J91: 221.3 | K91: 223.2 | L91: 223.2 | M91: 223.2 | N91: 223.2 | O91: 2000.95
B92: INFRAESTRUCTURAS Y ENERGIAS DEL PERU S.A.C. | C92: C.T. RF PTO MALDONADO | D92: CENTRAL | E92: TERMOELÉCTRICA | K92: 86.8 | L92: 32.15 | O92: 118.95
B93: INFRAESTRUCTURAS Y ENERGIAS DEL PERU S.A.C. | C93: C.T. RF PUCALLPA | D93: CENTRAL | E93: TERMOELÉCTRICA | K93: 131.5 | O93: 131.5
B94: INLAND ENERGY SAC | C94: C.H. SANTA TERESA | D94: CENTRAL | E94: HIDROELÉCTRICA | F94: 2165.05 | G94: 2166.25 | H94: 2155.3 | I94: 2162.95 | J94: 2125.4 | K94: 2133.9 | L94: 2177.15 | M94: 2161.6 | N94: 2137.5 | O94: 19385.1
B95: INVERSIONES SHAQSHA S.A.C. | C95: C.H. PARIAC | D95: CENTRAL | E95: HIDROELÉCTRICA | F95: 104.7 | G95: 103.2 | H95: 98.15 | I95: 105.6 | J95: 107.85 | K95: 108.45 | L95: 108.85 | M95: 110.4 | N95: 110.4 | O95: 957.6
B96: JOYA SOLAR S.A.C. | C96: C.S. SAN MARTIN SOLAR | D96: CENTRAL | E96: SOLAR | O96: 0
B97: KALLPA GENERACION S.A. | C97: C.H. CERRO DEL AGUILA | D97: CENTRAL | E97: HIDROELÉCTRICA | F97: 13408.8 | G97: 13394.55 | H97: 11308.8 | I97: 12224.1 | J97: 13304.26 | K97: 13006.1 | L97: 13406.05 | M97: 13384.85 | N97: 13430.55 | O97: 116868.06
B98: KALLPA GENERACION S.A. | C98: C.T. KALLPA | D98: TG1 | E98: TERMOELÉCTRICA | F98: 2961.8 | G98: 3023.25 | H98: 3288.05 | I98: 3169.85 | J98: 2972.61 | K98: 2797.85 | L98: 2792.7 | M98: 2742 | N98: 3021.95 | O98: 26770.06
B99: KALLPA GENERACION S.A. | C99: C.T. KALLPA | D99: TG2 | E99: TERMOELÉCTRICA | F99: 2959.1 | G99: 3018.55 | H99: 3285.95 | I99: 3170.8 | J99: 2968.27 | K99: 2795.35 | L99: 2779.1 | M99: 2737.2 | N99: 3023.4 | O99: 26737.72
B100: KALLPA GENERACION S.A. | C100: C.T. KALLPA | D100: TG3 | E100: TERMOELÉCTRICA | F100: 2957.85 | G100: 3016.15 | H100: 3287.2 | I100: 3171.45 | J100: 2968.445 | K100: 2793.95 | L100: 2779.95 | M100: 2740.55 | N100: 3023.5 | O100: 26739.045
B101: KALLPA GENERACION S.A. | C101: C.T. KALLPA | D101: TV | E101: TERMOELÉCTRICA | F101: 5369.05 | G101: 5402.15 | H101: 5621.85 | I101: 5538.9 | J101: 5386.72 | K101: 5219.1 | L101: 5197.2 | M101: 5143.1 | N101: 5411.45 | O101: 48289.52
B102: KALLPA GENERACION S.A. | C102: C.T. LAS FLORES | D102: TG1 | E102: TERMOELÉCTRICA | F102: 3812.95 | G102: 3553.5 | H102: 4147.65 | I102: 3984.75 | J102: 3519.735 | K102: 2961.75 | L102: 3331.55 | M102: 3351.35 | N102: 3776.4 | O102: 32439.635
B103: KALLPA GENERACION S.A. | C103: C.T. LAS FLORES | D103: TV | E103: TERMOELÉCTRICA | F103: 2114.1 | G103: 2005.85 | H103: 2242.05 | I103: 2162.75 | J103: 1989.645 | K103: 1772.35 | L103: 1918.55 | M103: 1921.75 | N103: 2097.7 | O103: 18224.745
...

Sheet G_AREAS
B3: miércoles, 9 de Abril del 2025
B5: HORA | C5: RESUMEN DE GENERACIÓN POR ÁREAS DEL SEIN | D5: RESUMEN DE GENERACIÓN POR ÁREAS DEL SEIN | E5: RESUMEN DE GENERACIÓN POR ÁREAS DEL SEIN | F5: RESUMEN DE GENERACIÓN POR ÁREAS DEL SEIN | G5: RESUMEN DE GENERACIÓN POR ÁREAS DEL SEIN | H5: RESUMEN DE GENERACIÓN POR ÁREAS DEL SEIN | I5: RESUMEN DE GENERACIÓN POR ÁREAS DEL SEIN | J5: RESUMEN DE GENERACIÓN POR ÁREAS DEL SEIN | K5: RESUMEN DE GENERACIÓN POR ÁREAS DEL SEIN | L5: RESUMEN DE GENERACIÓN POR ÁREAS DEL SEIN | M5: RESUMEN DE GENERACIÓN POR ÁREAS DEL SEIN | N5: RESUMEN DE GENERACIÓN POR ÁREAS DEL SEIN | O5: RESUMEN DE GENERACIÓN POR ÁREAS DEL SEIN | P5: RESUMEN DE GENERACIÓN POR ÁREAS DEL SEIN | Q5: RESUMEN DE GENERACIÓN POR ÁREAS DEL SEIN | R5: RESUMEN DE GENERACIÓN POR ÁREAS DEL SEIN | S5: HORA | T5: GENERACIÓN POR TIPO DE GENERACIÓN | U5: GENERACIÓN POR TIPO DE GENERACIÓN | V5: GENERACIÓN POR TIPO DE GENERACIÓN | W5: GENERACIÓN POR TIPO DE GENERACIÓN | X5: GENERACIÓN POR TIPO DE GENERACIÓN | Y5: HORA | Z5: GENERACIÓN POR TIPO DE GENERACIÓN | AA5: GENERACIÓN POR TIPO DE GENERACIÓN | AB5: GENERACIÓN POR TIPO DE GENERACIÓN | AC5: GENERACIÓN POR TIPO DE GENERACIÓN | AD5: GENERACIÓN POR TIPO DE GENERACIÓN
C6: NORTE | D6: NORTE | E6: NORTE | F6: NORTE | G6: CENTRO | H6: CENTRO | I6: CENTRO | J6: CENTRO | K6: SUR | L6: SUR | M6: SUR | N6: SUR | O6: GENERACIÓN INTEGRANTES COES | P6: GENERACIÓN INTEGRANTES COES | Q6: GENERACIÓN INTEGRANTES COES | R6: GENERACIÓN INTEGRANTES COES | T6: INTEGRANTES COES | U6: INTEGRANTES COES | V6: INTEGRANTES COES | W6: INTEGRANTES COES | X6: INTEGRANTES COES | Z6: INTEGRANTES COES RER | AA6: INTEGRANTES COES RER | AB6: INTEGRANTES COES RER | AC6: INTEGRANTES COES RER | AD6: INTEGRANTES COES RER
C7: GENERACIÓN HIDROELÉCTRICA NORTE | D7: GENERACIÓN TERMOELÉCTRICA NORTE | E7: GENERACIÓN SOLAR NORTE | F7: GENERACIÓN EÓLICA NORTE | G7: GENERACIÓN HIDROELÉCTRICA CENTRO | H7: GENERACIÓN TERMOELÉCTRICA CENTRO | I7: GENERACIÓN SOLAR CENTRO | J7: GENERACIÓN EÓLICA CENTRO | K7: GENERACIÓN HIDROELÉCTRICA SUR | L7: GENERACIÓN TERMOELÉCTRICA SUR | M7: GENERACIÓN SOLAR SUR | N7: GENERACIÓN EÓLICA SUR | O7: GENERACIÓN COES NORTE | P7: GENERACIÓN COES CENTRO | Q7: GENERACIÓN COES SUR | R7: TOTAL GENERACION | T7: HIDROELÉCTRICA | U7: TERMOELÉCTRICA | V7: SOLAR | W7: EÓLICA | X7: TOTAL GENERACION | Z7: HIDROELÉCTRICA RER | AA7: TERMOELÉCTRICA RER | AB7: SOLAR RER | AC7: EÓLICA RER | AD7: TOTAL RER
B8: 00:30 | C8: 466.8 | D8: 43.7 | E8: 0 | F8: 66.2 | G8: 3371.1 | H8: 1583 | I8: 0 | J8: 400.6 | K8: 621.3 | L8: 0 | M8: 0 | N8: 0 | O8: 576.7 | P8: 5354.7 | Q8: 621.3 | R8: 6552.7 | S8: 00:30 | T8: 4438.8 | U8: 1647.1 | V8: 0 | W8: 466.8 | X8: 6552.7 | Y8: 00:30 | Z8: 333.8 | AA8: 46 | AB8: 0 | AC8: 466.8 | AD8: 846.6
B9: 01:00 | C9: 462.5 | D9: 43.9 | E9: 0 | F9: 68.6 | G9: 3214.9 | H9: 1581 | I9: 0 | J9: 341.2 | K9: 619.1 | L9: 0 | M9: 0 | N9: 0 | O9: 575 | P9: 5137.1 | Q9: 619.1 | R9: 6331.2 | S9: 01:00 | T9: 4276.1 | U9: 1645.3 | V9: 0 | W9: 409.8 | X9: 6331.2 | Y9: 01:00 | Z9: 333.6 | AA9: 46.1 | AB9: 0 | AC9: 409.8 | AD9: 789.5
B10: 01:30 | C10: 465.8 | D10: 44.1 | E10: 0 | F10: 77.2 | G10: 3188.4 | H10: 1591.8 | I10: 0 | J10: 306.2 | K10: 622.6 | L10: 0 | M10: 0 | N10: 0 | O10: 587.1 | P10: 5086.4 | Q10: 622.6 | R10: 6296.1 | S10: 01:30 | T10: 4256.4 | U10: 1656.3 | V10: 0 | W10: 383.4 | X10: 6296.1 | Y10: 01:30 | Z10: 333.3 | AA10: 46.2 | AB10: 0 | AC10: 383.4 | AD10: 762.9
B11: 02:00 | C11: 457.1 | D11: 44.8 | E11: 0 | F11: 77.2 | G11: 3055.6 | H11: 1583.8 | I11: 0 | J11: 331.2 | K11: 606.8 | L11: 0 | M11: 0 | N11: 0 | O11: 579.1 | P11: 4970.6 | Q11: 606.8 | R11: 6156.5 | S11: 02:00 | T11: 4099.1 | U11: 1649 | V11: 0 | W11: 408.4 | X11: 6156.5 | Y11: 02:00 | Z11: 332.7 | AA11: 46.3 | AB11: 0 | AC11: 408.4 | AD11: 787.4
B12: 02:30 | C12: 461 | D12: 44.2 | E12: 0 | F12: 70.2 | G12: 3045.7 | H12: 1583.1 | I12: 0 | J12: 342.8 | K12: 615.2 | L12: 0 | M12: 0 | N12: 0 | O12: 575.4 | P12: 4971.6 | Q12: 615.2 | R12: 6162.2 | S12: 02:30 | T12: 4101.5 | U12: 1647.7 | V12: 0 | W12: 413 | X12: 6162.2 | Y12: 02:30 | Z12: 332.9 | AA12: 46.2 | AB12: 0 | AC12: 413 | AD12: 792.1
B13: 03:00 | C13: 463.3 | D13: 43.7 | E13: 0 | F13: 75 | G13: 3052 | H13: 1584.7 | I13: 0 | J13: 326.3 | K13: 622.2 | L13: 0 | M13: 0 | N13: 0 | O13: 582 | P13: 4963 | Q13: 622.2 | R13: 6167.2 | S13: 03:00 | T13: 4117.1 | U13: 1648.8 | V13: 0 | W13: 401.3 | X13: 6167.2 | Y13: 03:00 | Z13: 332.8 | AA13: 46.1 | AB13: 0 | AC13: 401.3 | AD13: 780.2
B14: 03:30 | C14: 463.8 | D14: 44 | E14: 0 | F14: 77 | G14: 3041.3 | H14: 1584 | I14: 0 | J14: 301 | K14: 621.1 | L14: 0 | M14: 0 | N14: 0 | O14: 584.8 | P14: 4926.3 | Q14: 621.1 | R14: 6132.2 | S14: 03:30 | T14: 4105.8 | U14: 1648.4 | V14: 0 | W14: 378 | X14: 6132.2 | Y14: 03:30 | Z14: 332.6 | AA14: 46.2 | AB14: 0 | AC14: 378 | AD14: 756.8
B15: 04:00 | C15: 459.3 | D15: 43.9 | E15: 0 | F15: 76.9 | G15: 2971.6 | H15: 1586.7 | I15: 0 | J15: 282.3 | K15: 608.9 | L15: 0 | M15: 0 | N15: 0 | O15: 580.1 | P15: 4840.6 | Q15: 608.9 | R15: 6029.6 | S15: 04:00 | T15: 4019.4 | U15: 1651 | V15: 0 | W15: 359.2 | X15: 6029.6 | Y15: 04:00 | Z15: 332.3 | AA15: 46.1 | AB15: 0 | AC15: 359.2 | AD15: 737.6
B16: 04:30 | C16: 462.3 | D16: 44.5 | E16: 0 | F16: 74.5 | G16: 3164.8 | H16: 1584.8 | I16: 0 | J16: 233.4 | K16: 619.6 | L16: 0 | M16: 0 | N16: 0 | O16: 581.3 | P16: 4983 | Q16: 619.6 | R16: 6183.9 | S16: 04:30 | T16: 4226.3 | U16: 1649.7 | V16: 0 | W16: 307.9 | X16: 6183.9 | Y16: 04:30 | Z16: 333.1 | AA16: 46.1 | AB16: 0 | AC16: 307.9 | AD16: 687.1
B17: 05:00 | C17: 461 | D17: 44.4 | E17: 0 | F17: 78.5 | G17: 3176.4 | H17: 1585.5 | I17: 0 | J17: 216.9 | K17: 616.2 | L17: 0 | M17: 0 | N17: 0 | O17: 583.9 | P17: 4978.8 | Q17: 616.2 | R17: 6178.9 | S17: 05:00 | T17: 4233.2 | U17: 1650.3 | V17: 0 | W17: 295.4 | X17: 6178.9 | Y17: 05:00 | Z17: 333.1 | AA17: 46.2 | AB17: 0 | AC17: 295.4 | AD17: 674.7
B18: 05:30 | C18: 464 | D18: 44.5 | E18: 0 | F18: 57.8 | G18: 3379.1 | H18: 1584.7 | I18: 0 | J18: 203.8 | K18: 618.9 | L18: 0 | M18: 0 | N18: 0 | O18: 566.3 | P18: 5167.6 | Q18: 618.9 | R18: 6352.8 | S18: 05:30 | T18: 4441.6 | U18: 1649.6 | V18: 0 | W18: 261.6 | X18: 6352.8 | Y18: 05:30 | Z18: 333.9 | AA18: 46.1 | AB18: 0 | AC18: 261.6 | AD18: 641.6
B19: 06:00 | C19: 463.8 | D19: 44 | E19: 0 | F19: 60.8 | G19: 3499 | H19: 1581.8 | I19: 0 | J19: 218.6 | K19: 618 | L19: 0 | M19: 4.3 | N19: 0 | O19: 568.6 | P19: 5299.4 | Q19: 622.3 | R19: 6490.3 | S19: 06:00 | T19: 4560.4 | U19: 1646.2 | V19: 4.3 | W19: 279.4 | X19: 6490.3 | Y19: 06:00 | Z19: 333 | AA19: 46.3 | AB19: 4.3 | AC19: 279.4 | AD19: 663
... B56: TOTAL MWh | C56: 11047.95 | D56: 1852.8 | E56: 1.7 | F56: 1507.6 | G56: 85239.6 | H56: 43719.75 | I56: 7.3 | J56: 8191.95 | K56: 14561.5 | L56: 0 | M56: 3972.2 | N56: 0 | O56: 14410.05 | P56: 137158.6 | Q56: 18533.7 | R56: 170102.35 | S56: TOTAL MWh | T56: 110359.45 | U56: 46062.15 | V56: 3981.2 | W56: 9699.55 | X56: 170102.35 | Y56: TOTAL MWh | Z56: 7945.1 | AA56: 1105.5 | AB56: 3981.2 | AC56: 9699.55 | AD56: 22731.35

Sheet HOP
B3: miércoles, 9 de Abril del 2025
B5: Reporte de Horas de Operación
B6: Empresa | C6: Central | D6: Grupo | E6: Modo de Operación | F6: Inicio | G6: Final | H6: O. Arranque | I6: O. Parada | J6: Tipo Operación | K6: Ensayo de Potencia Efectiva | L6: Ensayo de Potencia Mínima | M6: Sistema | N6: Lim. Transm. | O6: Causa | P6: Observación
B7: AGRO INDUSTRIAL PARAMONGA S.A. | C7: C.T. PARAMONGA | D7: CENTRAL | E7: PARAMONGA - BAGAZO | F7: 09/04/2025 00:00:00 | G7: 10/04/2025 00:00:00 | J7: POR COGENERACION | O7: ...
B8: EGESUR | C8: C.T. INDEPENDENCIA | D8: CENTRAL | E8: INDEPENDENCIA GAS | F8: 09/04/2025 09:44:00 | G8: 09/04/2025 12:47:00 | H8: 09/04/2025 09:38:00 | J8: POR POTENCIA O ENERGIA | O8: ...
B9: EGESUR | C9: C.T. INDEPENDENCIA | D9: CENTRAL | E9: INDEPENDENCIA GAS | F9: 09/04/2025 12:47:00 | G9: 09/04/2025 13:03:00 | I9: 09/04/2025 12:52:00 | J9: A MINIMA CARGA | O9: ...
B10: EGESUR | C10: C.T. INDEPENDENCIA | D10: INDEP_G1 | E10: INDEPENDENCIA GAS | F10: 09/04/2025 17:49:00 | G10: 09/04/2025 18:53:00 | H10: 09/04/2025 17:40:00 | J10: POR PRUEBAS | O10: REQ. PROPIO
B11: EGESUR | C11: C.T. INDEPENDENCIA | D11: CENTRAL | E11: INDEPENDENCIA GAS | F11: 09/04/2025 18:48:00 | G11: 09/04/2025 22:14:00 | J11: POR POTENCIA O ENERGIA | O11: ...
B12: EGESUR | C12: C.T. INDEPENDENCIA | D12: CENTRAL | E12: INDEPENDENCIA GAS | F12: 09/04/2025 22:14:00 | G12: 09/04/2025 22:25:00 | I12: 09/04/2025 22:14:01 | J12: A MINIMA CARGA | O12: ...
B13: ENEL GENERACION PIURA S.A. | C13: C.T. MALACAS 1 | D13: CENTRAL | E13: MALACAS1 TG6 - GAS | F13: 09/04/2025 08:01:00 | G13: 09/04/2025 23:01:00 | H13: 09/04/2025 07:48:00 | J13: POR POTENCIA O ENERGIA | O13: ...
B14: ENEL GENERACION PIURA S.A. | C14: C.T. MALACAS 1 | D14: CENTRAL | E14: MALACAS1 TG6 - GAS | F14: 09/04/2025 23:01:00 | G14: 09/04/2025 23:18:00 | I14: 09/04/2025 23:01:01 | J14: A MINIMA CARGA | O14: ...
B15: ENGIE | C15: C.T. CHILCA 1 | D15: CENTRAL | E15: CHILCA1 CCOMB TG3 - GAS | F15: 09/04/2025 00:00:00 | G15: 09/04/2025 09:39:00 | J15: A MINIMA CARGA | O15: ...
B16: ENGIE | C16: C.T. CHILCA 1 | D16: CENTRAL | E16: CHILCA1 CCOMB TG3 - GAS | F16: 09/04/2025 09:39:00 | G16: 09/04/2025 12:47:00 | J16: POR POTENCIA O ENERGIA | O16: ...
B17: ENGIE | C17: C.T. CHILCA 1 | D17: TG1 | E17: CHILCA1 TG1 - GAS | F17: 09/04/2025 10:40:00 | G17: 09/04/2025 12:11:00 | H17: 09/04/2025 10:02:00 | J17: POR POTENCIA O ENERGIA | O17: ...
B18: ENGIE | C18: C.T. CHILCA 1 | D18: TG1 | E18: CHILCA1 TG1 - GAS | F18: 09/04/2025 12:11:00 | G18: 09/04/2025 12:56:00 | I18: 09/04/2025 12:42:00 | J18: A MINIMA CARGA | O18: ...
B19: ENGIE | C19: C.T. CHILCA 1 | D19: CENTRAL | E19: CHILCA1 CCOMB TG3 - GAS | F19: 09/04/2025 12:47:00 | G19: 09/04/2025 14:32:00 | J19: A MINIMA CARGA | O19: ...
B20: ENGIE | C20: C.T. CHILCA 1 | D20: CENTRAL | E20: CHILCA1 CCOMB TG3 - GAS | F20: 09/04/2025 14:32:00 | G20: 09/04/2025 16:20:00 | J20: POR POTENCIA O ENERGIA | O20: ...
B21: ENGIE | C21: C.T. CHILCA 1 | D21: CENTRAL | E21: CHILCA1 CCOMB TG3 - GAS | F21: 09/04/2025 16:20:00 | G21: 09/04/2025 16:42:00 | J21: A MINIMA CARGA | O21: ...
B22: ENGIE | C22: C.T. CHILCA 1 | D22: CENTRAL | E22: CHILCA1 CCOMB TG3 - GAS | F22: 09/04/2025 16:42:00 | G22: 09/04/2025 22:48:00 | J22: POR POTENCIA O ENERGIA | O22: ...
B23: ENGIE | C23: C.T. CHILCA 1 | D23: CENTRAL | E23: CHILCA1 CCOMB TG3 - GAS | F23: 09/04/2025 22:48:00 | G23: 10/04/2025 00:00:00 | J23: A MINIMA CARGA | O23: ...
B24: ENGIE | C24: C.T. CHILCA 2 | D24: TG41 | E24: CHILCA2 TG41 - GAS | F24: 09/04/2025 19:25:00 | G24: 09/04/2025 20:25:00 | H24: 09/04/2025 18:44:00 | J24: A MINIMA CARGA | O24: ...
B25: ENGIE | C25: C.T. CHILCA 2 | D25: TG41 | E25: CHILCA2 TG41 - GAS | F25: 09/04/2025 20:25:00 | G25: 09/04/2025 22:13:00 | J25: POR POTENCIA O ENERGIA | O25: ...
B26: ENGIE | C26: C.T. CHILCA 2 | D26: TG41 | E26: CHILCA2 TG41 - GAS | F26: 09/04/2025 22:13:00 | G26: 09/04/2025 22:17:10 | I26: 09/04/2025 22:13:01 | J26: A MINIMA CARGA | O26: ...
B27: GM OPERACIONES S.A.C. | C27: CT REFINERIA TALARA | D27: TV1 REF TALARA | E27: REF_TALARA TV1 - NLH_RFG | F27: 09/04/2025 00:00:00 | G27: 10/04/2025 00:00:00 | J27: POR COGENERACION | O27: ...
B28: GM OPERACIONES S.A.C. | C28: CT REFINERIA TALARA | D28: TV2 REF TALARA | E28: REF_TALARA TV2 - NLH_RFG | F28: 09/04/2025 16:47:00 | G28: 10/04/2025 00:00:00 | H28: 09/04/2025 15:40:00 | J28: POR COGENERACION | O28: ... | P28: A mínimo por restricción de vapor
B29: KALLPA GENERACION S.A. | C29: C.T. KALLPA | D29: CENTRAL | E29: KALLPA CCOMB TG1 & TG2 & TG3 - GAS | F29: 09/04/2025 00:00:00 | G29: 09/04/2025 06:00:00 | J29: A MINIMA CARGA | O29: ...
B30: KALLPA GENERACION S.A. | C30: C.T. KALLPA | D30: CENTRAL | E30: KALLPA CCOMB TG1 & TG2 & TG3 - GAS | F30: 09/04/2025 06:00:00 | G30: 09/04/2025 09:39:00 | J30: POR RSF | O30: ...
B31: KALLPA GENERACION S.A. | C31: C.T. KALLPA | D31: CENTRAL | E31: KALLPA CCOMB TG1 & TG2 & TG3 - GAS | F31: 09/04/2025 09:39:00 | G31: 09/04/2025 12:47:00 | J31: POR POTENCIA O ENERGIA | O31: ...
B32: KALLPA GENERACION S.A. | C32: C.T. KALLPA | D32: CENTRAL | E32: KALLPA CCOMB TG1 & TG2 & TG3 - GAS | F32: 09/04/2025 12:47:00 | G32: 09/04/2025 14:32:00 | J32: POR RSF | O32: ...
B33: KALLPA GENERACION S.A. | C33: C.T. KALLPA | D33: CENTRAL | E33: KALLPA CCOMB TG1 & TG2 & TG3 - GAS | F33: 09/04/2025 14:32:00 | G33: 09/04/2025 22:54:00 | J33: POR POTENCIA O ENERGIA | O33: ...
B34: KALLPA GENERACION S.A. | C34: C.T. KALLPA | D34: CENTRAL | E34: KALLPA CCOMB TG1 & TG2 & TG3 - GAS | F34: 09/04/2025 22:54:00 | G34: 10/04/2025 00:00:00 | J34: POR RSF | O34: ...
B35: KALLPA GENERACION S.A. | C35: C.T. LAS FLORES | D35: CENTRAL | E35: LAS FLORES CCOMB TG1 - GAS | F35: 09/04/2025 00:00:00 | G35: 09/04/2025 09:22:00 | J35: A MINIMA CARGA | O35: ...
B36: KALLPA GENERACION S.A. | C36: C.T. LAS FLORES | D36: CENTRAL | E36: LAS FLORES CCOMB TG1 - GAS | F36: 09/04/2025 09:22:00 | G36: 09/04/2025 22:59:00 | J36: POR POTENCIA O ENERGIA | O36: ...
B37: KALLPA GENERACION S.A. | C37: C.T. LAS FLORES | D37: CENTRAL | E37: LAS FLORES CCOMB TG1 - GAS | F37: 09/04/2025 22:59:00 | G37: 10/04/2025 00:00:00 | J37: A MINIMA CARGA | O37: ...
B38: ORYGEN PERU S.A.A. | C38: C.T. VENTANILLA | D38: CENTRAL | E38: VENTANILLA CCOMB TG3 & TG4 - GAS | F38: 09/04/2025 00:00:00 | G38: 09/04/2025 09:38:00 | J38: A MINIMA CARGA | O38: ...
B39: ORYGEN PERU S.A.A. | C39: C.T. VENTANILLA | D39: CENTRAL | E39: VENTANILLA CCOMB TG3 & TG4 - GAS | F39: 09/04/2025 09:38:00 | G39: 09/04/2025 10:41:00 | J39: POR POTENCIA O ENERGIA | O39: ...
B40: ORYGEN PERU S.A.A. | C40: C.T. VENTANILLA | D40: CENTRAL | E40: VENTANILLA CCOMB TG3 & TG4 - GAS F.DIRECTO | F40: 09/04/2025 10:41:00 | G40: 09/04/2025 11:56:00 | J40: POR POTENCIA O ENERGIA | O40: ... | P40: 11:56 h s/c retirar F.A.
B41: ORYGEN PERU S.A.A. | C41: C.T. VENTANILLA | D41: CENTRAL | E41: VENTANILLA CCOMB TG3 & TG4 - GAS F.DIRECTO | F41: 09/04/2025 11:56:00 | G41: 09/04/2025 12:20:00 | J41: A MINIMA CARGA | O41: ...
B42: ORYGEN PERU S.A.A. | C42: C.T. VENTANILLA | D42: CENTRAL | E42: VENTANILLA CCOMB TG3 & TG4 - GAS | F42: 09/04/2025 12:20:00 | G42: 09/04/2025 12:59:00 | J42: POR POTENCIA O ENERGIA | O42: ...
B43: ORYGEN PERU S.A.A. | C43: C.T. VENTANILLA | D43: CENTRAL | E43: VENTANILLA CCOMB TG3 & TG4 - GAS | F43: 09/04/2025 12:59:00 | G43: 09/04/2025 14:28:00 | J43: A MINIMA CARGA | O43: ...
B44: ORYGEN PERU S.A.A. | C44: C.T. VENTANILLA | D44: CENTRAL | E44: VENTANILLA CCOMB TG3 & TG4 - GAS | F44: 09/04/2025 14:28:00 | G44: 09/04/2025 22:54:00 | J44: POR POTENCIA O ENERGIA | O44: ...
B45: ORYGEN PERU S.A.A. | C45: C.T. VENTANILLA | D45: CENTRAL | E45: VENTANILLA CCOMB TG3 & TG4 - GAS | F45: 09/04/2025 22:54:00 | G45: 10/04/2025 00:00:00 | J45: A MINIMA CARGA | O45: ...
B46: PETRAMAS | C46: C.T. HUAYCOLORO | D46: CENTRAL | E46: HUAYCOLORO - BIOGAS | F46: 09/04/2025 00:00:00 | G46: 10/04/2025 00:00:00 | J46: POR POTENCIA O ENERGIA | O46: ...
B47: PETRAMAS | C47: C.T.B DOÑA CATALINA | D47: CENTRAL | E47: DONA CATALINA - BIOGAS | F47: 09/04/2025 00:00:00 | G47: 10/04/2025 00:00:00 | J47: POR POTENCIA O ENERGIA | O47: ...
B48: PETRAMAS | C48: C.T.B. CALLAO | D48: CENTRAL | E48: CALLAO - BIOGAS | F48: 09/04/2025 00:00:00 | G48: 10/04/2025 00:00:00 | J48: POR POTENCIA O ENERGIA | O48: ...
B49: SDF ENERGIA SAC | C49: C.T. OQUENDO | D49: CENTRAL | E49: OQUENDO CCOMB TG1 - GAS | F49: 09/04/2025 00:00:00 | G49: 10/04/2025 00:00:00 | J49: POR COGENERACION | O49: ...
B50: TERMOCHILCA S.A.C. | C50: C.T. OLLEROS | D50: CENTRAL | E50: OLLEROS CCOMB TG1 - GAS | F50: 09/04/2025 00:00:00 | G50: 09/04/2025 14:31:00 | J50: POR PRUEBAS | O50: REQ. PROPIO
B51: TERMOCHILCA S.A.C. | C51: C.T. OLLEROS | D51: CENTRAL | E51: OLLEROS CCOMB TG1 - GAS | F51: 09/04/2025 14:31:00 | G51: 09/04/2025 14:53:00 | J51: POR POTENCIA O ENERGIA | O51: ... | P51: A las 14:28 h declaró el fin de las pruebas
B52: TERMOCHILCA S.A.C. | C52: C.T. OLLEROS | D52: CENTRAL | E52: OLLEROS CCOMB TG1 - GAS | F52: 09/04/2025 14:53:00 | G52: 09/04/2025 15:23:00 | J52: A MINIMA CARGA | O52: ...
B53: TERMOCHILCA S.A.C. | C53: C.T. OLLEROS | D53: CENTRAL | E53: OLLEROS CCOMB TG1 - GAS | F53: 09/04/2025 15:23:00 | G53: 09/04/2025 16:17:00 | J53: POR POTENCIA O ENERGIA | O53: ...
B54: TERMOCHILCA S.A.C. | C54: C.T. OLLEROS | D54: CENTRAL | E54: OLLEROS CCOMB TG1 - GAS | F54: 09/04/2025 16:17:00 | G54: 09/04/2025 18:31:00 | J54: A MINIMA CARGA | O54: ...
B55: TERMOCHILCA S.A.C. | C55: C.T. OLLEROS | D55: CENTRAL | E55: OLLEROS CCOMB TG1 - GAS | F55: 09/04/2025 18:31:00 | G55: 09/04/2025 22:24:00 | J55: POR POTENCIA O ENERGIA | O55: ...
B56: TERMOCHILCA S.A.C. | C56: C.T. OLLEROS | D56: CENTRAL | E56: OLLEROS CCOMB TG1 - GAS | F56: 09/04/2025 22:24:00 | G56: 09/04/2025 23:09:00 | I56: 09/04/2025 22:38:00 | J56: A MINIMA CARGA | O56: ...
B57: TERMOCHILCA S.A.C. | C57: C.T. OLLEROS | D57: TG1 | E57: OLLEROS TG1 - GAS | F57: 09/04/2025 23:09:00 | G57: 09/04/2025 23:36:00 | J57: A MINIMA CARGA | O57: ...

Sheet INDISP
B3: miércoles, 9 de Abril del 2025
B5: Hora Inicio y Fin de Indisponibilidades de las Unidades de Generación SEIN
B6: Empresa | C6: Ubicación | D6: Equipo | E6: Inicio | F6: Final | G6: Descripción | H6: MW Indisp. | I6: Prog. | J6: Dispon | K6: Interrupc. | L6: Tipo | M6: CodEq | N6: TipoEq_Osinerg
B7: AGROAURORA S.A.C. | C7: MAPLE ETANOL | D7: CENTRAL | E7: 09/04/2025 00:00 | F7: 10/04/2025 00:00 | G7: MANTENIMIENTO PREVENTIVO PROGRAMADO DE LA CENTRAL TERMOELECTRICA Y EQUIPOS AUXILIARES. | H7: 14 | I7: P | J7: F/S | K7: N | L7: PREV. | M7: 13417 | N7: G
B8: AGROAURORA S.A.C. | C8: MAPLE ETANOL | D8: CENTRAL | E8: 09/04/2025 00:00 | F8: 10/04/2025 00:00 | G8: CENTRAL TERMOELECTRICA FUERA DE SERVICIO POR FALTA DE MATERIA PRIMA PARA LOS REQUERIMIENTOS DE CALOR ÚTIL EN FÁBRICA. | H8: 14 | I8: P | J8: F/S | K8: N | L8: OTROS | M8: 13417 | N8: G
B9: AGROINDUSTRIAS SAN JACINTO S.A.A. | C9: SAN JACINTO | D9: CENTRAL | E9: 09/04/2025 00:00 | F9: 10/04/2025 00:00 | G9: Mantenimiento Anual. | H9: 8.15 | I9: P | J9: F/S | K9: N | L9: PREV. | M9: 19865 | N9: G
B10: BIOENERGIA DEL CHIRA S.A. | C10: CAÑA BRAVA | D10: CENTRAL | E10: 09/04/2025 00:00 | F10: 10/04/2025 00:00 | G10: Para Central Caña Brava debido a mantenimiento anual preventivo | H10: 12 | I10: P | J10: F/S | K10: N | L10: PREV. | M10: 20510 | N10: G
B11: EGASA | C11: CHARCANI II | D11: G2 | E11: 09/04/2025 00:00 | F11: 10/04/2025 00:00 | G11: Rebabitado cojinete de empuje | H11: 0.184 | I11: P | J11: F/S | K11: N | L11: CORR. | M11: 114 | N11: G
B12: EGASA | C12: CHARCANI II | D12: G3 | E12: 09/04/2025 07:54 | F12: 09/04/2025 13:34 | G12: Mantenimiento Electromecánico Plan 1 + END | H12: 0.209 | I12: P | J12: F/S | K12: N | L12: PREV. | M12: 115 | N12: G
B13: EGASA | C13: CHARCANI IV | D13: G3 | E13: 09/04/2025 00:00 | F13: 10/04/2025 00:00 | G13: Mantenimiento Generador | H13: 5.121 | I13: P | J13: F/S | K13: N | L13: PREV. | M13: 120 | N13: G
B14: EGASA | C14: CHARCANI V | D14: G1 | E14: 09/04/2025 07:44 | F14: 09/04/2025 12:55 | G14: Mantenimiento Preventivo Eléctrico LLTT+ Bahia acoplamiento | H14: 49.098 | I14: P | J14: F/S | K14: N | L14: PREV. | M14: 121 | N14: G
B15: EGASA | C15: CHILINA D | D15: SLZ2 | E15: 09/04/2025 08:03 | F15: 09/04/2025 14:54 | G15: Mantenimiento Bimensual | H15: 5.137 | I15: P | J15: F/S | K15: N | L15: PREV. | M15: 137 | N15: G
B16: EGASA | C16: CHILINA D | D16: TG | E16: 09/04/2025 11:13 | F16: 09/04/2025 15:58 | G16: Cambio de forros base chimenea | H16: 12.239 | I16: P | J16: F/S | K16: N | L16: PREV. | M16: 15110 | N16: G
B17: EGEJUNIN | C17: SANTA CRUZ II | D17: G2 | E17: 09/04/2025 00:00 | F17: 10/04/2025 00:00 | G17: Mantenimiento correctivo mayor de turbina del G2 | H17: 3.15 | I17: P | J17: F/S | K17: N | L17: CORR. | M17: 12651 | N17: G
B18: EGESUR | C18: INDEPENDENCIA | D18: INDEP_G1 | E18: 09/04/2025 00:00 | F18: 09/04/2025 17:49 | G18: Cambio de lubricante de unidad de generación | H18: 5.732 | I18: P | J18: F/S | K18: N | L18: PREV. | M18: 12777 | N18: G
... B32: STATKRAFT S.A | C32: CAHUA | D32: G2 | E32: 09/04/2025 11:00 | F32: 10/04/2025 00:00 | G32: CAMBIO DE TURBINA DYNAVEC FASE 3 POR DYNAVEC FASE 2 G2 | H32: 22.58 | I32: P | J32: F/S | K32: N | L32: PREV. | M32: 56 | N32: G

Sheet RESERVA_FRÍA
B3: 09/04/2025 | E3: EJECUTADO | L3: Miércoles 9 de Abril del 2025 / SEM N° 14 | V3: EJECUTADO | AC3: Miércoles 9 de Abril del 2025 / SEM N° 14 | ED3: ENERGIA RENOVABLES | GO3: COGENERACION | GX3: NO INTEGRANTES
B4: Miércoles | C4: STARO | E4: ELECTROPERU | I4: ORAZU | K4: TER | M4: KALLPA GENERACION S.A. | U4: SHOUGESA | Y4: EGM | Z4: EGESUR | AC4: EGASA | AJ4: SGB | AK4: CELEP | AL4: MINCVE | AM4: ETEN | AO4: HUALLA | AQ4: LAVI | AR4: CHIN | AT4: HUANCH | AU4: CELER | AV4: INLD | AW4: FENIX POWER PERÚ | AZ4: STATKRAFT S.A | BH4: HUANZA | BI4: ENEL GENERACION PIURA S.A. | BL4: ENGIE | BZ4: IYEP | CB4: SHAQSH | CC4: ORYGEN PERU S.A.A. | CO4: SAMAY I S.A.C | CS4: TCHILC | CU4: GENERACION | CX4: SALIDAS YUPANA | DB4: FLUJO EN LINEAS | DN4: COSTOS MARGINALES | DR4: RESERVA | DW4: DEMANDA POR AREAS | ED4: ACHI | EE4: COLCA | EF4: ERSUR | EG4: GRCOR | EH4: TARU | EI4: JOYAS | EJ4: KONDU | EK4: PIEREN | EL4: ORAZU | EN4: SGB | EO4: AIPSA | EP4: MAJA | EQ4: EGECSA | ER4: STANA | ES4: AGUAA | ET4: RDOBLE | EU4: HIDRO | EV4: HUARA | EW4: MOQUE | EX4: PANAM | EY4: PARQU | EZ4: PE3HER | FA4: PETRAMAS | FE4: TACNA | FF4: EYSAC | FG4: AURORA | FH4: AGROIN | FI4: ANDEA | FJ4: ASLC | FK4: ATRIA | FL4: EGEJUNIN | FP4: EGERBA | FQ4: EOL | FS4: ENGIE | FX4: GENE | FZ4: GENERADORA DE ENERGÍA DEL PERÚ | GD4: PAINO | GE4: SARCUS | GF4: ORYGEN PERU S.A.A. | GK4: RARCUS | GL4: SINERS | GO4: ACHI | GP4: GM OP | GR4: SDF | GT4: AIPSA | GU4: AURORA | GV4: AGROIN | GX4: UNACEM | GY4: EOR | GZ4: AYEP | HA4: ELZANA | HB4: ENOSA | HC4: SDE | HD4: SINERS
C5: 337 | D5: 338 | E5: 101 | F5: 102 | G5: 42667 | H5: 42668 | I5: 126 | J5: 127 | K5: 138 | L5: 139 | M5: 197 | N5: 203 | O5: 204 | P5: 230 | Q5: 209 | R5: 56677 | S5: 796 | T5: 2146 | U5: 142 | V5: 143 | W5: 125 | X5: 187 | Y5: 163 | Z5: 298 | AA5: 299 | AB5: 219 | AC5: 151 | AD5: 152 | AE5: 153 | AF5: 154 | AG5: 756 | AH5: 156 | AI5: 155 | AJ5: 182 | AK5: 212 | AL5: 758 | AM5: 263 | AN5: 265 | AO5: 775 | AP5: 777 | AQ5: 2154 | AR5: 150 | AS5: 149 | AT5: 188 | AU5: 2131 | AV5: 755 | AW5: 252 | AX5: 249 | AY5: 250 | AZ5: 117 | BA5: 267 | BB5: 268 | BC5: 119 | BD5: 120 | BE5: 189 | BF5: 122 | BG5: 266 | BH5: 251 | BI5: 115 | BJ5: 239 | BK5: 288 | BL5: 240 | BM5: 241 | BN5: 242 | BO5: 191 | BP5: 194 | BQ5: 196 | BR5: 207 | BS5: 236 | BT5: 795 | BU5: 285 | BV5: 995 | BW5: 996 | BX5: 997 | BY5: 766 | BZ5: 926 | CA5: 924 | CB5: 121 | CC5: 103 | CD5: 104 | CE5: 106 | CF5: 105 | CG5: 107 | CH5: 110 | CI5: 109 | CJ5: 144 | CK5: 113 | CL5: 114 | CM5: 193 | CN5: 208 | CO5: 786 | CP5: 787 | CQ5: 788 | CR5: 789 | CS5: 248 | CT5: 2159 | CU5: -1222 | CV5: -1223 | CW5: -1224 | CX5: 1221 | CY5: 1222 | CZ5: 1223 | DA5: 1224 | DB5: 1250 | DC5: 1251 | DD5: 1252 | DE5: 1253 | DF5: 1254 | DG5: 1255 | DH5: 1256 | DI5: 1257 | DJ5: 1258 | DK5: 1259 | DL5: 1260 | DM5: 1261 | DN5: 1226 | DO5: 1219 | DP5: 1220 | DQ5: -1203 | DR5: 1227 | DS5: 1205 | DT5: 1207 | DU5: 1206 | DV5: 1218 | DW5: 1211 | DX5: 1212 | DY5: 1213 | DZ5: 1214 | EA5: 1229 | EB5: -1221 | ED5: 289 | EE5: 303 | EF5: 59715 | EG5: 62255 | EH5: 1263 | EI5: 63425 | EJ5: 61800 | EK5: 2194 | EL5: 216 | EM5: 198 | EN5: 49607 | EO5: 213 | EP5: 214 | EQ5: 260 | ER5: 2152 | ES5: 2128 | ET5: 247 | EU5: 228 | EV5: 2135 | EW5: 261 | EX5: 237 | EY5: 253 | EZ5: 770 | FA5: 225 | FB5: 2201 | FC5: 2171 | FD5: 760 | FE5: 235 | FF5: 238 | FG5: 232 | FH5: 2190 | FI5: 2184 | FJ5: 61855 | FK5: 223 | FL5: 226 | FM5: 201 | FN5: 258 | FO5: 259 | FP5: 920 | FQ5: 257 | FR5: 256 | FS5: 2148 | FT5: 58288 | FU5: 58289 | FV5: 58839 | FW5: 58840 | FX5: 296 | FY5: 297 | FZ5: 211 | GA5: 2175 | GB5: 2178 | GC5: 2181 | GD5: 1262 | GE5: 233 | GF5: 2150 | GG5: 2165 | GH5: 2161 | GI5: 61197 | GJ5: 58851 | GK5: 234 | GL5: 215 | GM5: 917 | GO5: 289 | GP5: 58333 | GQ5: 58336 | GR5: 202 | GS5: 58487 | GT5: 213 | GU5: 232 | GV5: 2190 | GX5: 221 | GY5: 222 | GZ5: 224 | HA5: 2187 | HB5: 227 | HC5: 49400 | HD5: 199 | HE5: 200 | HG5: 7000 | HH5: 7001 | HI5: 7002
B6: Día Hora | C6: SANTA ROSA 1 | D6: SANTA ROSA 2 | E6: MANTARO | F6: RESTITUCION | G6: TUMBES MAK 1 | H6: TUMBES MAK 2 | I6: CARHUAQUERO | J6: CAÑON DEL PATO | K6: AGUAYTIA TG1 | L6: AGUAYTIA TG2 | M6: KALLPA TG1 | N6: KALLPA TG2 | O6: KALLPA TG3 | P6: KALLPA TV | Q6: LFLORES TG1 | R6: LFLORES TV | S6: CERRO DEL AGUILA | T6: CERRODELAGUILAG4 | U6: SHOUGESA TV1 | V6: SHOUGESA TV2 | W6: SHOUGESA TV3 | X6: SHOUGESA CUMMINS | Y6: MACHUPICCHU | Z6: ARICOTA 1 | AA6: ARICOTA 2 | AB6: INDEPENDENCIA | AC6: CHARCANI I,II,III | AD6: CHARCANI IV | AE6: CHARCANI V | AF6: CHARCANI VI | AG6: CHILINA TG | AH6: MOLLENDO 1, 2, 3 | AI6: CHILINA (SULZ 1,2) | AJ6: SAN GABAN II | AK6: PLATANAL | AL6: RECKA | AM6: RF ETEN TG1 | AN6: RF ETEN TG2 | AO6: CHAGLLA GP1 | AP6: CHAGLLA | AQ6: LA VIRGEN | AR6: CHIMAY | AS6: YANANGO | AT6: HUANCHOR | AU6: MARAÑON | AV6: STA TERESA | AW6: FENIX GT11 | AX6: FENIX GT12 | AY6: FENIX TV10 | AZ6: YAUPI | BA6: OROYA | BB6: PACHACHACA | BC6: MALPASO | BD6: CAHUA | BE6: ARCATA | BF6: GALLITO CIEGO | BG6: CHEVES | BH6: HUANZA | BI6: MALACAS2 TG4 | BJ6: MALACAS3 TG 5 | BK6: MALACAS1 TG6 | BL6: RF ILO2 TG1 | BM6: RF ILO2 TG2 | BN6: RF ILO2 TG3 | BO6: YUNCAN | BP6: CHILCA1 TG1 | BQ6: CHILCA1 TG2 | BR6: CHILCA1 TG3 | BS6: CHILCA-TV | BT6: CHILCA2 TG41 | BU6: CHILCA2-TV | BV6: CTNEPI_TG41 | BW6: CTNEPI_TG42 | BX6: CTNEPI_TG43 | BY6: QUITARACSA | BZ6: RF PTO MALDONADO | CA6: RF PUCALLPA | CB6: PARIAC | CC6: HUINCO | CD6: MATUCANA | CE6: MOYOPAMPA | CF6: CALLAHUANCA | CG6: HUAMPANI | CH6: STA ROSA WEST TG7 | CI6: UTI_5 | CJ6: UTI_6 | CK6: VENTANILLA 3 | CL6: VENTANILLA 4 | CM6: VENTANILLA TV | CN6: STAROSA TG8 | CO6: PTO_BRVO TG1 | CP6: PTO_BRVO TG2 | CQ6: PTO_BRVO TG3 | CR6: PTO_BRVO TG4 | CS6: OLLEROS TG1 | CT6: OLLEROS TV | CU6: Total CoGeneracion | CV6: Total Renovables | CW6: Total Generación COES | CX6: Demanda YUPANA | CY6: Oferta | CZ6: Perdidas YUPANA | DA6: Deficit YUPANA | DB6: FLUJO ENLACE CENTRO - SUR | DC6: FLUJO CHILCA CARAPONGO 500 KV | DD6: FLUJO CARAPONGO CARABAYLLO 500 KV | DE6: FLUJO CHIMBOTE TRUJILLO 500 KV | DF6: FLUJO TRUJILLO LA NIÑA 500 KV | DG6: FLUJO COLCABAMBA POROMA 500 KV | DH6: FLUJO CHILCA POROMA 500 KV | DI6: FLUJO POROMA YARABAMBA 500 KV | DJ6: FLUJO POROMA OCOÑA 500 KV | DK6: FLUJO YARABAMBA MOLTALVO 500 KV | DL6: FLUJO HUANCAVELICA - INDEPENDENCIA 220 KV | DM6: FLUJO CHILCA - SAN JUAN 220 KV | DN6: Cmg Santa Rosa YUPANA(US$/MWh) | DO6: Cmg Trujillo YUPANA(US$/MWh) | DP6: Cmg Socabaya YUPANA(US$/MWh) | DQ6: Nivel de Demanda | DR6: Reserva Fría Térmica | DS6: Reserva Eficiente | DT6: Reserva Eficiente Gas | DU6: Reserva Eficiente Carbón | DV6: Nivel Tablachaca | DW6: Demanda Centro | DX6: Demanda Norte | DY6: Demanda Sur | DZ6: Demanda Electroandes | EA6: Demanda Ecuador | EB6: Demanda COES | ED6: CANA BRAVA | EE6: CS YARUCAYA | EF6: SAN JUAN | EG6: MATARANI | EH6: DUNA | EI6: SAN MARTIN SOLAR | EJ6: CARHUAQUERO (CS) | EK6: MANTA I | EL6: CARHUAQUERO4 | EM6: CAÑA BRAVA | EN6: TUPURI | EO6: PARAMONGA | EP6: RONCADOR | EQ6: CANCHAYLLO | ER6: RENOVANDESH1 | ES6: POTRERO | ET6: PIZARRAS | EU6: NIMPERIAL | EV6: YARUCAYA | EW6: MOQUEGUA-SOLAR | EX6: PANAMERICANA-SOLAR | EY6: PQE-EOLICO-MARCONA | EZ6: PQE-EOLICO-3-HERMANAS | FA6: HUAYCOLORO | FB6: CALLAO | FC6: DONA_CATALINA | FD6: LAGRINGAV | FE6: TACNA-SOLAR | FF6: YANAPAMPA | FG6: MAPLE | FH6: SAN_JACINTO | FI6: CARHUAC | FJ6: HUALLIN | FK6: PURMACANA | FL6: HUASAHUASI | FM6: STACRUZ_1_2 | FN6: RUNATULLO_II | FO6: RUNATULLO_III | FP6: RUCUY | FQ6: PQE-EOLICO-TALARA | FR6: PQE-EOLICO-CUPISNIQUE | FS6: INTIPAMPA | FT6: PUNTA LOMITAS-BL1 | FU6: PUNTA LOMITAS-BL2 | FV6: PUN LOMITAS_EXP-BL1 | FW6: PUN LOMITAS_EXP-BL2 | FX6: 8AGOSTO | FY6: EL CARMEN | FZ6: LA JOYA | GA6: ANGEL_I | GB6: ANGEL_II | GC6: ANGEL_III | GD6: HUAMBOS | GE6: MAJES | GF6: RUBI | GG6: CH_HER1 | GH6: WAYRA-I | GI6: WAYRA EXTENSION | GJ6: CLEMESI | GK6: REPARTICION | GL6: POECHOS2 | GM6: CHANCAY | GO6: CANA BRAVA | GP6: REFINERIA TALARA TV1 | GQ6: REFINERÍA TALARA TV2 | GR6: OQUENDO TG1 | GS6: OQUENDO TV1 | GT6: PARAMONGA | GU6: MAPLE | GV6: SAN_JACINTO | GX6: CARPAPATA | GY6: CENTRALES ELOR | GZ6: PIAS1 | HA6: ZANA | HB6: TABLAZO | HC6: TALLANCA | HD6: CURUMUY | HE6: POECHOS1 | HG6: ReservaFriaTermica | HH6: ReservaFria Rapida Termica | HI6: ReservaFria Termica xMantenimiento
B7: 00:30 | G7: 8.82587 | H7: 8.51669 | K7: 60.21 | U7: 18.14123 | V7: 19.19196 | W7: 24.42536 | X7: 1.06127 | AB7: 17.31912 | AG7: 12.23925 | AH7: 24.4617 | AI7: 10.27692 | AL7: 179.37322 | AM7: 217.12263 | AN7: 7.93273 | BI7: 25 | BL7: 167.61232 | BM7: 166.56063 | BN7: 168.58997 | BU7: 110.49702 | BV7: 206.49456 | BW7: 206.11549 | BX7: 205.99003 | BZ7: 17.41583 | CA7: 44.05367 | CH7: 118.14735 | CI7: 47.90514 | CJ7: 53.71012 | CN7: 191.19621 | CO7: 180.55348 | CP7: 180.52451 | CQ7: 181.33356 | CR7: 181.02912 | HG7: 3061.827 | HH7: 3000.0684 | HI7: 1017.8167
B8: 01:00 | G8: 8.82587 | H8: 8.51669 | K8: 60.21 | U8: 18.14123 | V8: 19.19196 | W8: 24.42536 | X8: 1.06127 | AB8: 17.31912 | AG8: 12.23925 | AH8: 24.4617 | AI8: 10.27692 | AL8: 179.37322 | AM8: 217.12263 | AN8: 7.93273 | BI8: 25 | BL8: 167.61232 | BM8: 166.56063 | BN8: 168.58997 | BU8: 110.49702 | BV8: 206.49456 | BW8: 206.11549 | BX8: 205.99003 | BZ8: 17.41583 | CA8: 44.05367 | CH8: 118.14735 | CI8: 47.90514 | CJ8: 53.71012 | CN8: 191.19621 | CO8: 180.55348 | CP8: 180.52451 | CQ8: 181.33356 | CR8: 181.02912 | HG8: 3061.827 | HH8: 3000.0684 | HI8: 1017.8167
B9: 01:30 | G9: 8.82587 | H9: 8.51669 | K9: 60.21 | U9: 18.14123 | V9: 19.19196 | W9: 24.42536 | X9: 1.06127 | AB9: 17.31912 | AG9: 12.23925 | AH9: 24.4617 | AI9: 10.27692 | AL9: 179.37322 | AM9: 217.12263 | AN9: 7.93273 | BI9: 25 | BL9: 167.61232 | BM9: 166.56063 | BN9: 168.58997 | BU9: 110.49702 | BV9: 206.49456 | BW9: 206.11549 | BX9: 205.99003 | BZ9: 17.41583 | CA9: 44.05367 | CH9: 118.14735 | CI9: 47.90514 | CJ9: 53.71012 | CN9: 191.19621 | CO9: 180.55348 | CP9: 180.52451 | CQ9: 181.33356 | CR9: 181.02912 | HG9: 3061.827 | HH9: 3000.0684 | HI9: 1017.8167
B10: 02:00 | G10: 8.82587 | H10: 8.51669 | K10: 60.21 | U10: 18.14123 | V10: 19.19196 | W10: 24.42536 | X10: 1.06127 | AB10: 17.31912 | AG10: 12.23925 | AH10: 24.4617 | AI10: 10.27692 | AL10: 179.37322 | AM10: 217.12263 | AN10: 7.93273 | BI10: 25 | BL10: 167.61232 | BM10: 166.56063 | BN10: 168.58997 | BU10: 110.49702 | BV10: 206.49456 | BW10: 206.11549 | BX10: 205.99003 | BZ10: 17.41583 | CA10: 44.05367 | CH10: 118.14735 | CI10: 47.90514 | CJ10: 53.71012 | CN10: 191.19621 | CO10: 180.55348 | CP10: 180.52451 | CQ10: 181.33356 | CR10: 181.02912 | HG10: 3061.827 | HH10: 3000.0684 | HI10: 1017.8167
B11: 02:30 | G11: 8.82587 | H11: 8.51669 | K11: 60.21 | U11: 18.14123 | V11: 19.19196 | W11: 24.42536 | X11: 1.06127 | AB11: 17.31912 | AG11: 12.23925 | AH11: 24.4617 | AI11: 10.27692 | AL11: 179.37322 | AM11: 217.12263 | AN11: 7.93273 | BI11: 25 | BL11: 167.61232 | BM11: 166.56063 | BN11: 168.58997 | BU11: 110.49702 | BV11: 206.49456 | BW11: 206.11549 | BX11: 205.99003 | BZ11: 17.41583 | CA11: 44.05367 | CH11: 118.14735 | CI11: 47.90514 | CJ11: 53.71012 | CN11: 191.19621 | CO11: 180.55348 | CP11: 180.52451 | CQ11: 181.33356 | CR11: 181.02912 | HG11: 3061.827 | HH11: 3000.0684 | HI11: 1017.8167
B12: 03:00 | G12: 8.82587 | H12: 8.51669 | K12: 60.21 | U12: 18.14123 | V12: 19.19196 | W12: 24.42536 | X12: 1.06127 | AB12: 17.31912 | AG12: 12.23925 | AH12: 24.4617 | AI12: 10.27692 | AL12: 179.37322 | AM12: 217.12263 | AN12: 7.93273 | BI12: 25 | BL12: 167.61232 | BM12: 166.56063 | BN12: 168.58997 | BS12: 265.18944 | BU12: 110.49702 | BV12: 206.49456 | BW12: 206.11549 | BX12: 205.99003 | BZ12: 17.41583 | CA12: 44.05367 | CH12: 118.14735 | CI12: 47.90514 | CJ12: 53.71012 | CN12: 191.19621 | CO12: 180.55348 | CP12: 180.52451 | CQ12: 181.33356 | CR12: 181.02912 | HG12: 3327.0164 | HH12: 3265.2579 | HI12: 1016.3725
B13: 03:30 | G13: 8.82587 | H13: 8.51669 | K13: 60.21 | U13: 18.14123 | V13: 19.19196 | W13: 24.42536 | X13: 1.06127 | AB13: 17.31912 | AG13: 12.23925 | AH13: 24.4617 | AI13: 10.27692 | AL13: 179.37322 | AM13: 217.12263 | AN13: 7.93273 | BI13: 25 | BL13: 167.61232 | BM13: 166.56063 | BN13: 168.58997 | BS13: 265.18944 | BU13: 110.49702 | BV13: 206.49456 | BW13: 206.11549 | BX13: 205.99003 | BZ13: 17.41583 | CA13: 44.05367 | CH13: 118.14735 | CI13: 47.90514 | CJ13: 53.71012 | CN13: 191.19621 | CO13: 180.55348 | CP13: 180.52451 | CQ13: 181.33356 | CR13: 181.02912 | HG13: 3327.0164 | HH13: 3265.2579 | HI13: 1016.3725
