Workbook

Sheet EVENTOS
B3: domingo, 19 de Octubre del 2025
B5: INFORMACIÓN DE EVENTOS PRINCIPALES EN SUS INSTALACIONES
B6: TIPO DE EVENTO | C6: EMPRESA | D6: UBICACIÓN | E6: TIPO DE EQUIPO | F6: EQUIPO | G6: INICIO | H6: FINAL | I6: DESCRIPCIÓN | J6: MW INDISP. | K6: INTERRUPCIÓN (SI/NO) | L6: TENSIÓN DE FALLA (kV)
B7: EVENTO | C7: CONELSUR LT SAC | D7: PORTILLO | E7: SUBESTACION | F7: SS.EE. | G7: 19/10/2025 00:00:00 | H7: 19/10/2025 03:39:00 | I7: DECLARACIÓN DE SITUACIÓN EXCEPCIONAL EN LA S.E. PORTILLO DE 60 kV | K7: NO
B8: FALLA | C8: ELECTRO ORIENTE | D8: BELAUNDE TERRY - TARAPOTO | E8: LINEA DE TRANSMISION | F8: L-1018 | G8: 19/10/2025 13:03:23 | H8: 19/10/2025 13:18:45 | I8: DESCONEXIÓN DE LA LÍNEA L-1018 (BELAUNDE TERRY - TARAPOTO) DE 138 KV POR FALLA | J8: 31.97 | K8: SI | L8: 138
B9: FALLA | C9: INFRAESTRUCTURAS Y ENERGIAS DEL PERU S.A.C. | D9: PUCALLPA | E9: TRANSFORMADOR 2D | F9: TR35-163 | G9: 19/10/2025 19:09:27 | H9: 19/10/2025 19:11:55 | I9: DESCONEXIÓN DEL TRANSFORMADOR TR35 DE LA CTRF PUCALLPA POR FALLA EXTERNA | K9: NO | L9: 60
B10: FALLA | C10: RED DE ENERGIA DEL PERU S.A. | D10: PARAMONGA N. - CHIMBOTE 1 | E10: LINEA DE TRANSMISION | F10: L-2215 | G10: 19/10/2025 15:23:47 | H10: 19/10/2025 16:44:15 | I10: DESCONEXIÓN DE LA LÍNEA L-2215 (PARAMONGA NUEVA - CHIMBOTE 1) POR FALLA | K10: NO | L10: 220
B11: FALLA | C11: RED DE ENERGIA DEL PERU S.A. | D11: TRUJILLO NORTE | E11: SVC | F11: SVC-1 | G11: 19/10/2025 20:58:17 | H11: 19/10/2025 21:46:19 | I11: DESCONEXIÓN DEL SVC-1 DE LA SE TRUJILLO NORTE POR FALLA | K11: NO | L11: 0

Sheet RESTRIC_OPE
B3: domingo, 19 de Octubre del 2025
B5: RESTRICCIONES OPERATIVAS
B6: FECHA | C6: HORA INICIO | D6: HORA FINAL | E6: EMPRESA | F6: UBICACIÓN | G6: T.Eq. | H6: EQUIPO | I6: DESCRIPCIÓN
B7: 19/10/2025 | C7: 00:00 | D7: 24:00 | E7: EGASA | F7: S.E. CONVERTIDOR | G7: BARRA | H7: BARRA138KV | I7: EGASA limitó la capacidad del transformador 138 kV/33 kV a 50 MVA por deterioro del aislamiento.
B8: 19/10/2025 | C8: 00:00 | D8: 24:00 | E8: ELECTROPERU | F8: C.H. MANTARO | G8: CH | H8: CENTRAL | I8: De acuerdo con el correo del día 25.08.2025, la central tiene una limitación de potencia máxima de 650 MW por seguridad de la central.
B9: 19/10/2025 | C9: 00:00 | D9: 24:00 | E9: ENEL GENERACION PIURA S.A. | F9: C.T. MALACAS | G9: CT | H9: CENTRAL | I9: De acuerdo con la comunicación vía correo del día 24.10.2024. ENEL GENERACIÓN PIURA informa una restricción de potencia para alcanzar 105 MW en simultaneo (TG6+TGN4).
B10: 19/10/2025 | C10: 00:00 | D10: 24:00 | E10: ENEL GENERACION PIURA S.A. | F10: C.T. MALACAS | G10: GT | H10: TG4 | I10: De acuerdo a lo informado mediante correo electronico el día 04.07, la uniadTG4 puede operar a potencia efectiva durante 3 horas o con 80MW durante 4 horas, y el resto de los periodos a mínima generación.
B11: 19/10/2025 | C11: 00:00 | D11: 24:00 | E11: ENGIE ENERGIA PERU S.A.A. | F11: C.H. YUNCÁN | G11: GH | H11: G3 | I11: Según la carta N° ENG/ 198-2024 enviada por su representada, se opera de forma continua el G3 de la CH Yuncán, debido a la ejecución de mantenimientos necesarios para evitar daños en los sellos de seguridad de la válvula esférica del grupo.
B12: 19/10/2025 | C12: 00:00 | D12: 24:00 | E12: ENGIE ENERGIA PERU S.A.A. | F12: C.T. CHILCA 1 | G12: CT | H12: CENTRAL | I12: Con carta ENG/971-2023, indica que no puede cumplir con las IO considerada en el PDO_17122023 dado que vulneran la seguridad de sus activos. Indican que se debe tomar TMO=168h.
B13: 19/10/2025 | C13: 00:00 | D13: 24:00 | E13: ENGIE ENERGIA PERU S.A.A. | F13: C.T. CHILCA 1 | G13: CT | H13: CENTRAL | I13: Restricción de temperatura de la C.T Chilca, ver valor en el modelo de despacho.
B14: 19/10/2025 | C14: 00:00 | D14: 24:00 | E14: ENGIE ENERGIA PERU S.A.A. | F14: C.T. CHILCA 2 | G14: CT | H14: CENTRAL | I14: Con carta ENG/971-2023, indica que no puede cumplir con las IO considerada en el PDO_17122023 dado que vulneran la seguridad de sus activos. Indican que se debe tomar TMO=168h.
B15: 19/10/2025 | C15: 00:00 | D15: 24:00 | E15: FENIX POWER PERÚ | F15: C.T. FENIX | G15: CT | H15: CENTRAL | I15: De acuerdo con lo comunicado en el correo del día 06.05.2024, la CT Fenix cuenta con TMO de 168 hrs en todos su modos de operación.
B16: 19/10/2025 | C16: 00:00 | D16: 24:00 | E16: KALLPA GENERACION S.A. | F16: C.H. MINI CENTRAL CERRO DEL AGUILA | G16: CH | H16: CENTRAL | I16: Caudal ecológico de la Mini CH Cerro del Águila es de 6.1 m3/s correspondiente al mes de setiembre.
B17: 19/10/2025 | C17: 00:00 | D17: 24:00 | E17: KALLPA GENERACION S.A. | F17: C.H. MINI CENTRAL CERRO DEL AGUILA | G17: CH | H17: CENTRAL | I17: De acuerdo con lo informado por Kallpa el día 20.08.2025, la MCH Cerro del Águila tiene TA=0.07h, TMO=0.08h, TMA=0.16h.
... B47: 19/10/2025 | C47: 00:00 | D47: 24:00 | E47: UNACEM PERU S.A. | F47: S.E. CONDORCOCHA | G47: TRAFO3D | H47: T-3 138/44 kV | I47: De acuerdo con lo comunicado UNACEM mediante el informe INF_00142-2025, la transformador T3 de la SE Condorcocha esta limitado al 50% de su capacidad.

Sheet MANTENIMIENTO EJECUTADOS
B3: domingo, 19 de Octubre del 2025
B5: Mantenimiento Ejecutado
B6: Empresa | C6: Ubicación | D6: Equipo | E6: Inicio | F6: Final | G6: Descripción | H6: MW Indisp. | I6: Prog. | J6: Dispon | K6: Interrupc. | L6: Tipo | M6: CodEq | N6: TipoEq_Osinerg
B7: AGRO INDUSTRIAL PARAMONGA S.A. | C7: PARAMONGA | D7: CENTRAL | E7: 19/10/2025 07:00 | F7: 19/10/2025 17:00 | G7: Operara en sistema aislado debido al mantenimiento en la linea L-1101 y SE PARAMONGA EXISTENTE. | H7: 0 | I7: P | J7: E/S | K7: N | L7: OTROS | M7: 12815 | N7: G
B8: ATLANTICA TRANSMISION SUR S.A. | C8: MONTALVO | D8: BARRA A_220KV | E8: 19/10/2025 07:51 | F8: 19/10/2025 13:21 | G8: INDISPONIBLE DEBIDO A MANTENIMIENTO EN EQUIPOS DE CELDA 2057 | H8: 0 | I8: P | J8: F/S | K8: N | L8: OTROS | M8: 13869 | N8: T
B9: ATLANTICA TRANSMISION SUR S.A. | C9: MONTALVO | D9: CL-2057 | E9: 19/10/2025 08:24 | F9: 19/10/2025 16:34 | G9: MANTENIMIENTO PREVENTIVO EN EQUIPOS DE CELDA | H9: 0 | I9: P | J9: F/S | K9: N | L9: PREV. | M9: 13812 | N9: T
B10: ATLANTICA TRANSMISION SUR S.A. | C10: MONTALVO | D10: BARRA B_220kV | E10: 19/10/2025 13:30 | F10: 19/10/2025 16:41 | G10: INDISPONIBLE DEBIDO A MANTENIMIENTO EN EQUIPOS DE CELDA 2057 | H10: 0 | I10: P | J10: F/S | K10: N | L10: OTROS | M10: 14765 | N10: T
B11: ATLANTICA TRANSMISION SUR S.A. | C11: MONTALVO - MOQUEGUA | D11: L-2057 | E11: 19/10/2025 08:24 | F11: 19/10/2025 16:30 | G11: INDISPONIBLE DEBIDO A MANTENIMIENTO EN EQUIPOS DE CELDA | H11: 0 | I11: P | J11: F/S | K11: N | L11: OTROS | M11: 13815 | N11: T
B12: ATLANTICA TRANSMISION SUR S.A. | C12: MOQUEGUA | D12: CL-2057 | E12: 19/10/2025 08:24 | F12: 19/10/2025 16:33 | G12: MANTENIMIENTO PREVENTIVO EN EQUIPOS DE CELDA | H12: 0 | I12: P | J12: F/S | K12: N | L12: PREV. | M12: 13819 | N12: T
B13: ATLANTICA TRANSMISION SUR S.A. | C13: OCONA | D13: INT-5450 | E13: 19/10/2025 00:00 | F13: 20/10/2025 00:00 | G13: Interruptor INT-5450 cerrado con restriccion operativa, REB-5450 en servicio y suministrando los SS.AA. de la S.E. Oco?a. | H13: 0 | I13: P | J13: E/S | K13: N | L13: OTROS | M13: 13761 | N13: T
B14: ATLANTICA TRANSMISION SUR S.A. | C14: POROMA | D14: INT-5371 | E14: 19/10/2025 00:00 | F14: 20/10/2025 00:00 | G14: Seccionador SBB-5371 fase T indisponible por problemas mecanicos, el seccionador permanece cerrado y bloqueado | H14: 0 | I14: P | J14: E/S | K14: N | L14: OTROS | M14: 13751 | N14: T
B15: ATLANTICA TRANSMISION SUR S.A. | C15: POROMA | D15: REB-5350 | E15: 19/10/2025 00:00 | F15: 20/10/2025 00:00 | G15: Fuera de servicio po falla en el equipo. | H15: 0 | I15: P | J15: F/S | K15: N | L15: OTROS | M15: 13771 | N15: T
B16: ATN S.A. | C16: CARHUAMAYO | D16: CL-1707 | E16: 19/10/2025 08:33 | F16: 19/10/2025 15:37 | G16: Mantenimiento preventivo de equipos en celda | H16: 0 | I16: P | J16: F/S | K16: N | L16: PREV. | M16: 13722 | N16: T
B17: ATN S.A. | C17: CARHUAMAYO NUEVA | D17: CL-1707 | E17: 19/10/2025 08:33 | F17: 19/10/2025 15:43 | G17: Mantenimiento preventivo de equipos en celda | H17: 0 | I17: P | J17: F/S | K17: N | L17: PREV. | M17: 13721 | N17: T
B18: ATN S.A. | C18: CARHUAMAYO NUEVA | D18: AUT-201 | E18: 19/10/2025 08:34 | F18: 19/10/2025 15:33 | G18: Mantenimiento preventivo de equipos en celda | H18: 0 | I18: P | J18: F/S | K18: N | L18: PREV. | M18: 12850 | N18: T
... B158: TRANSMISORA ELECTRICA DEL SUR 2 S.A.C. | C158: SAN ROMAN | D158: BARRA B_138 kV | E158: 19/10/2025 07:44 | F158: 19/10/2025 14:36 | G158: LIMPIEZA DE AISLADORES Y MANTENIMIENTO ELECTROMECANICO DE EQUIPOS DE PATIO 138KV DE LAS CL-1012 Y CL-1046. | H158: 0 | I158: P | J158: F/S | K158: N | L158: OTROS | M158: 18574 | N158: T

Sheet INGRESO OC
A3: domingo, 19 de Octubre del 2025
A5: INGRESO A OPERACIÓN COMERCIAL
A6: EMPRESA | B6: TIPO DE EQUIPO | C6: UBICACIÓN | D6: EQUIPO | E6: Fecha y hora de Ingreso a Operación Comercial

Sheet DESPACHO_EJECUTADO
B3: domingo, 19 de Octubre del 2025
A5: POTENCIA ACTIVA EJECUTADA DE LAS UNIDADES DE GENERACIÓN DEL SEIN (MW) | FM5: CENTRALES NO INTEGRANTES COES
A6: FECHA | B6: HORA | C6: 65333 | D6: 101 | E6: 102 | F6: 42667 | G6: 42668 | H6: 126 | I6: 127 | J6: 138 | K6: 139 | L6: 197 | M6: 203 | N6: 204 | O6: 230 | P6: 209 | Q6: 56677 | R6: 796 | S6: 2146 | T6: 142 | U6: 143 | V6: 125 | W6: 187 | X6: 163 | Y6: 298 | Z6: 299 | AA6: 219 | AB6: 151 | AC6: 152 | AD6: 153 | AE6: 154 | AF6: 756 | AG6: 156 | AH6: 155 | AI6: 182 | AJ6: 212 | AK6: 758 | AL6: 263 | AM6: 265 | AN6: 775 | AO6: 777 | AP6: 2154 | AQ6: 150 | AR6: 149 | AS6: 188 | AT6: 2131 | AU6: 755 | AV6: 252 | AW6: 249 | AX6: 250 | AY6: 117 | AZ6: 267 | BA6: 268 | BB6: 119 | BC6: 120 | BD6: 189 | BE6: 122 | BF6: 266 | BG6: 337 | BH6: 338 | BI6: 251 | BJ6: 115 | BK6: 239 | BL6: 288 | BM6: 240 | BN6: 241 | BO6: 242 | BP6: 191 | BQ6: 194 | BR6: 196 | BS6: 207 | BT6: 236 | BU6: 795 | BV6: 285 | BW6: 995 | BX6: 996 | BY6: 997 | BZ6: 766 | CA6: 926 | CB6: 924 | CC6: 121 | CD6: 103 | CE6: 104 | CF6: 106 | CG6: 105 | CH6: 107 | CI6: 110 | CJ6: 109 | CK6: 144 | CL6: 113 | CM6: 114 | CN6: 193 | CO6: 208 | CP6: 786 | CQ6: 787 | CR6: 788 | CS6: 789 | CT6: 248 | CU6: 2159 | CV6: 303 | CW6: 59715 | CX6: 62255 | CY6: 1263 | CZ6: 61800 | DA6: 2194 | DB6: 69125 | DC6: 216 | DD6: 198 | DE6: 70400 | DF6: 49607 | DG6: 214 | DH6: 260 | DI6: 2152 | DJ6: 2128 | DK6: 247 | DL6: 228 | DM6: 2135 | DN6: 261 | DO6: 237 | DP6: 253 | DQ6: 770 | DR6: 235 | DS6: 238 | DT6: 2184 | DU6: 61855 | DV6: 223 | DW6: 226 | DX6: 201 | DY6: 258 | DZ6: 259 | EA6: 920 | EB6: 257 | EC6: 256 | ED6: 2148 | EE6: 58288 | EF6: 58289 | EG6: 58839 | EH6: 58840 | EI6: 296 | EJ6: 297 | EK6: 211 | EL6: 2175 | EM6: 2178 | EN6: 2181 | EO6: 1262 | EP6: 63425 | EQ6: 233 | ER6: 2150 | ES6: 2165 | ET6: 2161 | EU6: 61197 | EV6: 58851 | EW6: 225 | EX6: 2201 | EY6: 2171 | EZ6: 760 | FA6: 234 | FB6: 215 | FC6: 917 | FD6: 289 | FE6: 58333 | FF6: 58336 | FG6: 213 | FH6: 232 | FI6: 2190 | FJ6: 69867 | FK6: TOTAL COES | FM6: 221 | FN6: 222 | FO6: 224 | FP6: 2187 | FQ6: 227 | FR6: 49400 | FS6: 199 | FT6: 200 | FU6: TOTAL NO COES
C7: SUR | D7: CENTRO | E7: CENTRO | F7: NORTE | G7: NORTE | H7: NORTE | I7: NORTE | J7: CENTRO | K7: CENTRO | L7: CENTRO | M7: CENTRO | N7: CENTRO | O7: CENTRO | P7: CENTRO | Q7: CENTRO | R7: CENTRO | S7: CENTRO | T7: CENTRO | U7: CENTRO | V7: CENTRO | W7: CENTRO | X7: SUR | Y7: SUR | Z7: SUR | AA7: CENTRO | AB7: SUR | AC7: SUR | AD7: SUR | AE7: SUR | AF7: SUR | AG7: SUR | AH7: SUR | AI7: SUR | AJ7: CENTRO | AK7: NORTE | AL7: NORTE | AM7: NORTE | AN7: CENTRO | AO7: CENTRO | AP7: CENTRO | AQ7: CENTRO | AR7: CENTRO | AS7: CENTRO | AT7: CENTRO | AU7: SUR | AV7: CENTRO | AW7: CENTRO | AX7: CENTRO | AY7: CENTRO | AZ7: CENTRO | BA7: CENTRO | BB7: CENTRO | BC7: CENTRO | BD7: SUR | BE7: NORTE | BF7: CENTRO | BG7: CENTRO | BH7: CENTRO | BI7: CENTRO | BJ7: NORTE | BK7: NORTE | BL7: NORTE | BM7: SUR | BN7: SUR | BO7: SUR | BP7: CENTRO | BQ7: CENTRO | BR7: CENTRO | BS7: CENTRO | BT7: CENTRO | BU7: CENTRO | BV7: CENTRO | BW7: SUR | BX7: SUR | BY7: SUR | BZ7: NORTE | CA7: SUR | CB7: CENTRO | CC7: NORTE | CD7: CENTRO | CE7: CENTRO | CF7: CENTRO | CG7: CENTRO | CH7: CENTRO | CI7: CENTRO | CJ7: CENTRO | CK7: CENTRO | CL7: CENTRO | CM7: CENTRO | CN7: CENTRO | CO7: CENTRO | CP7: SUR | CQ7: SUR | CR7: SUR | CS7: SUR | CT7: CENTRO | CU7: CENTRO | CV7: CENTRO | CW7: CENTRO | CX7: SUR | CY7: NORTE | CZ7: NORTE | DA7: NORTE | DB7: CENTRO | DC7: NORTE | DD7: NORTE | DE7: SUR | DF7: SUR | DG7: CENTRO | DH7: CENTRO | DI7: CENTRO | DJ7: NORTE | DK7: NORTE | DL7: CENTRO | DM7: CENTRO | DN7: SUR | DO7: SUR | DP7: CENTRO | DQ7: CENTRO | DR7: SUR | DS7: CENTRO | DT7: CENTRO | DU7: NORTE | DV7: CENTRO | DW7: CENTRO | DX7: NORTE | DY7: CENTRO | DZ7: CENTRO | EA7: CENTRO | EB7: NORTE | EC7: NORTE | ED7: SUR | EE7: CENTRO | EF7: CENTRO | EG7: CENTRO | EH7: CENTRO | EI7: CENTRO | EJ7: CENTRO | EK7: SUR | EL7: SUR | EM7: SUR | EN7: SUR | EO7: NORTE | EP7: SUR | EQ7: SUR | ER7: SUR | ES7: CENTRO | ET7: CENTRO | EU7: CENTRO | EV7: SUR | EW7: CENTRO | EX7: CENTRO | EY7: CENTRO | EZ7: CENTRO | FA7: SUR | FB7: NORTE | FC7: CENTRO | FD7: NORTE | FE7: NORTE | FF7: NORTE | FG7: CENTRO | FH7: NORTE | FI7: NORTE | FJ7: NORTE | FM7: NORTE | FN7: CENTRO | FO7: NORTE | FP7: NORTE | FQ7: NORTE | FR7: NORTE | FS7: NORTE | FT7: NORTE
C8: HIDROELÉCTRICA | D8: HIDROELÉCTRICA | E8: HIDROELÉCTRICA | F8: TERMOELÉCTRICA | G8: TERMOELÉCTRICA | H8: HIDROELÉCTRICA | I8: HIDROELÉCTRICA | J8: TERMOELÉCTRICA | K8: TERMOELÉCTRICA | L8: TERMOELÉCTRICA | M8: TERMOELÉCTRICA | N8: TERMOELÉCTRICA | O8: TERMOELÉCTRICA | P8: TERMOELÉCTRICA | Q8: TERMOELÉCTRICA | R8: HIDROELÉCTRICA | S8: HIDROELÉCTRICA | T8: TERMOELÉCTRICA | U8: TERMOELÉCTRICA | V8: TERMOELÉCTRICA | W8: TERMOELÉCTRICA | X8: HIDROELÉCTRICA | Y8: HIDROELÉCTRICA | Z8: HIDROELÉCTRICA | AA8: TERMOELÉCTRICA | AB8: HIDROELÉCTRICA | AC8: HIDROELÉCTRICA | AD8: HIDROELÉCTRICA | AE8: HIDROELÉCTRICA | AF8: TERMOELÉCTRICA | AG8: TERMOELÉCTRICA | AH8: TERMOELÉCTRICA | AI8: HIDROELÉCTRICA | AJ8: HIDROELÉCTRICA | AK8: TERMOELÉCTRICA | AL8: TERMOELÉCTRICA | AM8: TERMOELÉCTRICA | AN8: HIDROELÉCTRICA | AO8: HIDROELÉCTRICA | AP8: HIDROELÉCTRICA | AQ8: HIDROELÉCTRICA | AR8: HIDROELÉCTRICA | AS8: HIDROELÉCTRICA | AT8: HIDROELÉCTRICA | AU8: HIDROELÉCTRICA | AV8: TERMOELÉCTRICA | AW8: TERMOELÉCTRICA | AX8: TERMOELÉCTRICA | AY8: HIDROELÉCTRICA | AZ8: HIDROELÉCTRICA | BA8: HIDROELÉCTRICA | BB8: HIDROELÉCTRICA | BC8: HIDROELÉCTRICA | BD8: HIDROELÉCTRICA | BE8: HIDROELÉCTRICA | BF8: HIDROELÉCTRICA | BG8: HIDROELÉCTRICA | BH8: HIDROELÉCTRICA | BI8: HIDROELÉCTRICA | BJ8: TERMOELÉCTRICA | BK8: TERMOELÉCTRICA | BL8: TERMOELÉCTRICA | BM8: TERMOELÉCTRICA | BN8: TERMOELÉCTRICA | BO8: TERMOELÉCTRICA | BP8: HIDROELÉCTRICA | BQ8: TERMOELÉCTRICA | BR8: TERMOELÉCTRICA | BS8: TERMOELÉCTRICA | BT8: TERMOELÉCTRICA | BU8: TERMOELÉCTRICA | BV8: TERMOELÉCTRICA | BW8: TERMOELÉCTRICA | BX8: TERMOELÉCTRICA | BY8: TERMOELÉCTRICA | BZ8: HIDROELÉCTRICA | CA8: TERMOELÉCTRICA | CB8: TERMOELÉCTRICA | CC8: HIDROELÉCTRICA | CD8: HIDROELÉCTRICA | CE8: HIDROELÉCTRICA | CF8: HIDROELÉCTRICA | CG8: HIDROELÉCTRICA | CH8: HIDROELÉCTRICA | CI8: TERMOELÉCTRICA | CJ8: TERMOELÉCTRICA | CK8: TERMOELÉCTRICA | CL8: TERMOELÉCTRICA | CM8: TERMOELÉCTRICA | CN8: TERMOELÉCTRICA | CO8: TERMOELÉCTRICA | CP8: TERMOELÉCTRICA | CQ8: TERMOELÉCTRICA | CR8: TERMOELÉCTRICA | CS8: TERMOELÉCTRICA | CT8: TERMOELÉCTRICA | CU8: TERMOELÉCTRICA | CV8: SOLAR | CW8: EÓLICA | CX8: SOLAR | CY8: EÓLICA | CZ8: SOLAR | DA8: HIDROELÉCTRICA | DB8: HIDROELÉCTRICA | DC8: HIDROELÉCTRICA | DD8: HIDROELÉCTRICA | DE8: SOLAR | DF8: HIDROELÉCTRICA | DG8: HIDROELÉCTRICA | DH8: HIDROELÉCTRICA | DI8: HIDROELÉCTRICA | DJ8: HIDROELÉCTRICA | DK8: HIDROELÉCTRICA | DL8: HIDROELÉCTRICA | DM8: HIDROELÉCTRICA | DN8: SOLAR | DO8: SOLAR | DP8: EÓLICA | DQ8: EÓLICA | DR8: SOLAR | DS8: HIDROELÉCTRICA | DT8: HIDROELÉCTRICA | DU8: HIDROELÉCTRICA | DV8: HIDROELÉCTRICA | DW8: HIDROELÉCTRICA | DX8: HIDROELÉCTRICA | DY8: HIDROELÉCTRICA | DZ8: HIDROELÉCTRICA | EA8: HIDROELÉCTRICA | EB8: EÓLICA | EC8: EÓLICA | ED8: SOLAR | EE8: EÓLICA | EF8: EÓLICA | EG8: EÓLICA | EH8: EÓLICA | EI8: HIDROELÉCTRICA | EJ8: HIDROELÉCTRICA | EK8: HIDROELÉCTRICA | EL8: HIDROELÉCTRICA | EM8: HIDROELÉCTRICA | EN8: HIDROELÉCTRICA | EO8: EÓLICA | EP8: SOLAR | EQ8: SOLAR | ER8: SOLAR | ES8: HIDROELÉCTRICA | ET8: EÓLICA | EU8: EÓLICA | EV8: SOLAR | EW8: TERMOELÉCTRICA | EX8: TERMOELÉCTRICA | EY8: TERMOELÉCTRICA | EZ8: TERMOELÉCTRICA | FA8: SOLAR | FB8: HIDROELÉCTRICA | FC8: HIDROELÉCTRICA | FD8: TERMOELÉCTRICA | FE8: TERMOELÉCTRICA | FF8: TERMOELÉCTRICA | FG8: TERMOELÉCTRICA | FH8: TERMOELÉCTRICA | FI8: TERMOELÉCTRICA | FJ8: TERMOELÉCTRICA | FM8: HIDROELÉCTRICA | FN8: HIDROELÉCTRICA | FO8: HIDROELÉCTRICA | FP8: HIDROELÉCTRICA | FQ8: TERMOELÉCTRICA | FR8: TERMOELÉCTRICA | FS8: HIDROELÉCTRICA | FT8: HIDROELÉCTRICA
C9: HYDRO GLOBAL PERÚ S.A.C. | D9: ELECTROPERU | E9: ELECTROPERU | F9: ELECTROPERU | G9: ELECTROPERU | H9: ORAZUL ENERGY PERÚ | I9: ORAZUL ENERGY PERÚ | J9: TERMOSELVA | K9: TERMOSELVA | L9: KALLPA GENERACION S.A. | M9: KALLPA GENERACION S.A. | N9: KALLPA GENERACION S.A. | O9: KALLPA GENERACION S.A. | P9: KALLPA GENERACION S.A. | Q9: KALLPA GENERACION S.A. | R9: KALLPA GENERACION S.A. | S9: KALLPA GENERACION S.A. | T9: SHOUGESA | U9: SHOUGESA | V9: SHOUGESA | W9: SHOUGESA | X9: EGEMSA | Y9: EGESUR | Z9: EGESUR | AA9: EGESUR | AB9: EGASA | AC9: EGASA | AD9: EGASA | AE9: EGASA | AF9: EGASA | AG9: EGASA | AH9: EGASA | AI9: SAN GABAN | AJ9: CELEPSA | AK9: MINERA CERRO VERDE | AL9: PLANTA DE RESERVA FRIA DE GENERACION DE ETEN S.A. | AM9: PLANTA DE RESERVA FRIA DE GENERACION DE ETEN S.A. | AN9: EMPRESA DE GENERACION HUALLAGA | AO9: EMPRESA DE GENERACION HUALLAGA | AP9: LA VIRGEN | AQ9: CHINANGO S.A.C. | AR9: CHINANGO S.A.C. | AS9: HIDROELECTRICA HUANCHOR S.A.C. | AT9: CELEPSA RENOVABLES S.R.L. | AU9: INLAND ENERGY SAC | AV9: FENIX POWER PERÚ | AW9: FENIX POWER PERÚ | AX9: FENIX POWER PERÚ | AY9: STATKRAFT S.A | AZ9: STATKRAFT S.A | BA9: STATKRAFT S.A | BB9: STATKRAFT S.A | BC9: STATKRAFT S.A | BD9: STATKRAFT S.A | BE9: STATKRAFT S.A | BF9: STATKRAFT S.A | BG9: CENTRALES SANTA ROSA S.A.C. | BH9: CENTRALES SANTA ROSA S.A.C. | BI9: EMPRESA DE GENERACION HUANZA | BJ9: ENEL GENERACION PIURA S.A. | BK9: ENEL GENERACION PIURA S.A. | BL9: ENEL GENERACION PIURA S.A. | BM9: ENGIE ENERGIA PERU S.A.A. | BN9: ENGIE ENERGIA PERU S.A.A. | BO9: ENGIE ENERGIA PERU S.A.A. | BP9: ENGIE ENERGIA PERU S.A.A. | BQ9: ENGIE ENERGIA PERU S.A.A. | BR9: ENGIE ENERGIA PERU S.A.A. | BS9: ENGIE ENERGIA PERU S.A.A. | BT9: ENGIE ENERGIA PERU S.A.A. | BU9: ENGIE ENERGIA PERU S.A.A. | BV9: ENGIE ENERGIA PERU S.A.A. | BW9: ENGIE ENERGIA PERU S.A.A. | BX9: ENGIE ENERGIA PERU S.A.A. | BY9: ENGIE ENERGIA PERU S.A.A. | BZ9: ENGIE ENERGIA PERU S.A.A. | CA9: INFRAESTRUCTURAS Y ENERGIAS DEL PERU S.A.C. | CB9: INFRAESTRUCTURAS Y ENERGIAS DEL PERU S.A.C. | CC9: INVERSIONES SHAQSHA S.A.C. | CD9: ORYGEN PERU S.A.A. | CE9: ORYGEN PERU S.A.A. | CF9: ORYGEN PERU S.A.A. | CG9: ORYGEN PERU S.A.A. | CH9: ORYGEN PERU S.A.A. | CI9: ORYGEN PERU S.A.A. | CJ9: ORYGEN PERU S.A.A. | CK9: ORYGEN PERU S.A.A. | CL9: ORYGEN PERU S.A.A. | CM9: ORYGEN PERU S.A.A. | CN9: ORYGEN PERU S.A.A. | CO9: ORYGEN PERU S.A.A. | CP9: SAMAY I S.A.C | CQ9: SAMAY I S.A.C | CR9: SAMAY I S.A.C | CS9: SAMAY I S.A.C | CT9: TERMOCHILCA S.A.C. | CU9: TERMOCHILCA S.A.C. | CV9: COLCA SOLAR S.A.C. | CW9: ENERGIA RENOVABLE DEL SUR S.A. | CX9: GR CORTARRAMA SOCIEDAD ANONIMA CERRADA | CY9: GR TARUCA SOCIEDAD ANONIMA CERRADA | CZ9: KONDU SAC | DA9: PERUANA DE INVERSIONES EN ENERGIAS RENOVABLES S.A. | DB9: VARI ENERGIA S.A.C. | DC9: ORAZUL ENERGY PERÚ | DD9: ORAZUL ENERGY PERÚ | DE9: KALLPA GENERACION S.A. | DF9: SAN GABAN | DG9: MAJA ENERGIA S.A.C. | DH9: EMPRESA DE GENERACION ELECTRICA CANCHAYLLO SAC | DI9: EMPRESA DE GENERACION ELECTRICA SANTA ANA S.A.C. | DJ9: EMPRESA ELECTRICA AGUA AZUL | DK9: EMPRESA ELECTRICA RIO DOBLE | DL9: HIDROCAÑETE S.A. | DM9: HUAURA POWER GROUP S.A. | DN9: MOQUEGUA FV S.A.C. | DO9: PANAMERICANA SOLAR SAC. | DP9: PARQUE EOLICO MARCONA S.A.C. | DQ9: PARQUE EOLICO TRES HERMANAS S.A.C. | DR9: TACNA SOLAR SAC. | DS9: ELECTRICA YANAPAMPA SAC | DT9: ANDEAN POWER S.A.C. | DU9: ASOCIACIÓN SANTA LUCIA DE CHACAS | DV9: ATRIA ENERGIA S.A.C. | DW9: EGEJUNIN | DX9: EGEJUNIN | DY9: EGEJUNIN | DZ9: EGEJUNIN | EA9: EMPRESA DE GENERACION ELECTRICA RIO BAÑOS S.A.C. | EB9: ENERGÍA EÓLICA S.A. | EC9: ENERGÍA EÓLICA S.A. | ED9: ENGIE ENERGIA PERU S.A.A. | EE9: ENGIE ENERGIA PERU S.A.A. | EF9: ENGIE ENERGIA PERU S.A.A. | EG9: ENGIE ENERGIA PERU S.A.A. | EH9: ENGIE ENERGIA PERU S.A.A. | EI9: GENERACIÓN ANDINA S.A.C. | EJ9: GENERACIÓN ANDINA S.A.C. | EK9: GENERADORA DE ENERGÍA DEL PERÚ | EL9: GENERADORA DE ENERGÍA DEL PERÚ | EM9: GENERADORA DE ENERGÍA DEL PERÚ | EN9: GENERADORA DE ENERGÍA DEL PERÚ | EO9: GR PAINO SOCIEDAD ANONIMA CERRADA | EP9: JOYA SOLAR S.A.C. | EQ9: MAJES ARCUS S.A.C. | ER9: ORYGEN PERU S.A.A. | ES9: ORYGEN PERU S.A.A. | ET9: ORYGEN PERU S.A.A. | EU9: ORYGEN PERU S.A.A. | EV9: ORYGEN PERU S.A.A. | EW9: PETRAMAS | EX9: PETRAMAS | EY9: PETRAMAS | EZ9: PETRAMAS | FA9: REPARTICIÓN ARCUS S.A.C. | FB9: SINERSA | FC9: SINERSA | FD9: BIOENERGIA DEL CHIRA S.A. | FE9: GM OPERACIONES S.A.C. | FF9: GM OPERACIONES S.A.C. | FG9: AGRO INDUSTRIAL PARAMONGA S.A. | FH9: AGROAURORA S.A.C. | FI9: AGROINDUSTRIAS SAN JACINTO S.A.A. | FJ9: AGROLMOS SOCIEDAD ANONIMA - AGROLMOS S.A. | FM9: UNACEM PERU S.A. | FN9: ELECTRO ORIENTE | FO9: AGUAS Y ENERGIA PERU | FP9: ELECTRO ZAÑA S.A.C. | FQ9: ELECTRONOROESTE S.A. | FR9: SDE PIURA | FS9: SINERSA | FT9: SINERSA
C10: SAN GABAN III | D10: MANTARO | E10: RESTITUCION | F10: TUMBES MAK 1 | G10: TUMBES MAK 2 | H10: CARHUAQUERO | I10: CAÑON DEL PATO | J10: AGUAYTIA TG1 | K10: AGUAYTIA TG2 | L10: KALLPA TG1 | M10: KALLPA TG2 | N10: KALLPA TG3 | O10: KALLPA TV | P10: LFLORES TG1 | Q10: LFLORES TV | R10: CERRO DEL AGUILA | S10: CERRODELAGUILAG4 | T10: SHOUGESA TV1 | U10: SHOUGESA TV2 | V10: SHOUGESA TV3 | W10: SHOUGESA CUMMINS | X10: MACHUPICCHU | Y10: ARICOTA 1 | Z10: ARICOTA 2 | AA10: INDEPENDENCIA | AB10: CHARCANI I,II,III | AC10: CHARCANI IV | AD10: CHARCANI V | AE10: CHARCANI VI | AF10: CHILINA TG | AG10: MOLLENDO 1, 2, 3 | AH10: CHILINA (SULZ 1,2) | AI10: SAN GABAN II | AJ10: PLATANAL | AK10: RECKA | AL10: RF ETEN TG1 | AM10: RF ETEN TG2 | AN10: CHAGLLA GP1 | AO10: CHAGLLA | AP10: LA VIRGEN | AQ10: CHIMAY | AR10: YANANGO | AS10: HUANCHOR | AT10: MARAÑON | AU10: STA TERESA | AV10: FENIX GT11 | AW10: FENIX GT12 | AX10: FENIX TV10 | AY10: YAUPI | AZ10: OROYA | BA10: PACHACHACA | BB10: MALPASO | BC10: CAHUA | BD10: ARCATA | BE10: GALLITO CIEGO | BF10: CHEVES | BG10: SANTA ROSA 1 | BH10: SANTA ROSA 2 | BI10: HUANZA | BJ10: MALACAS2 TG4 | BK10: MALACAS3 TG 5 | BL10: MALACAS1 TG6 | BM10: RF ILO2 TG1 | BN10: RF ILO2 TG2 | BO10: RF ILO2 TG3 | BP10: YUNCAN | BQ10: CHILCA1 TG1 | BR10: CHILCA1 TG2 | BS10: CHILCA1 TG3 | BT10: CHILCA-TV | BU10: CHILCA2 TG41 | BV10: CHILCA2-TV | BW10: CTNEPI_TG41 | BX10: CTNEPI_TG42 | BY10: CTNEPI_TG43 | BZ10: QUITARACSA | CA10: RF PTO MALDONADO | CB10: RF PUCALLPA | CC10: PARIAC | CD10: HUINCO | CE10: MATUCANA | CF10: MOYOPAMPA | CG10: CALLAHUANCA | CH10: HUAMPANI | CI10: STA ROSA WEST TG7 | CJ10: UTI_5 | CK10: UTI_6 | CL10: VENTANILLA 3 | CM10: VENTANILLA 4 | CN10: VENTANILLA TV | CO10: STAROSA TG8 | CP10: PTO_BRVO TG1 | CQ10: PTO_BRVO TG2 | CR10: PTO_BRVO TG3 | CS10: PTO_BRVO TG4 | CT10: OLLEROS TG1 | CU10: OLLEROS TV | CV10: CS YARUCAYA | CW10: SAN JUAN | CX10: MATARANI | CY10: DUNA | CZ10: CARHUAQUERO (CS) | DA10: MANTA I | DB10: ANASHIRONI | DC10: CARHUAQUERO4 | DD10: CAÑA BRAVA | DE10: SUNNY | DF10: TUPURI | DG10: RONCADOR | DH10: CANCHAYLLO | DI10: RENOVANDESH1 | DJ10: POTRERO | DK10: PIZARRAS | DL10: NIMPERIAL | DM10: YARUCAYA | DN10: MOQUEGUA-SOLAR | DO10: PANAMERICANA-SOLAR | DP10: PQE-EOLICO-MARCONA | DQ10: PQE-EOLICO-3-HERMANAS | DR10: TACNA-SOLAR | DS10: YANAPAMPA | DT10: CARHUAC | DU10: HUALLIN | DV10: PURMACANA | DW10: HUASAHUASI | DX10: STACRUZ_1_2 | DY10: RUNATULLO_II | DZ10: RUNATULLO_III | EA10: RUCUY | EB10: PQE-EOLICO-TALARA | EC10: PQE-EOLICO-CUPISNIQUE | ED10: INTIPAMPA | EE10: PUNTA LOMITAS-BL1 | EF10: PUNTA LOMITAS-BL2 | EG10: PUN LOMITAS_EXP-BL1 | EH10: PUN LOMITAS_EXP-BL2 | EI10: 8AGOSTO | EJ10: EL CARMEN | EK10: LA JOYA | EL10: ANGEL_I | EM10: ANGEL_II | EN10: ANGEL_III | EO10: HUAMBOS | EP10: SAN MARTIN SOLAR | EQ10: MAJES | ER10: RUBI | ES10: CH_HER1 | ET10: WAYRA-I | EU10: WAYRA EXTENSION | EV10: CLEMESI | EW10: HUAYCOLORO | EX10: CALLAO | EY10: DONA_CATALINA | EZ10: LAGRINGAV | FA10: REPARTICION | FB10: POECHOS2 | FC10: CHANCAY | FD10: CANA BRAVA | FE10: REFINERIA TALARA TV1 | FF10: REFINERÍA TALARA TV2 | FG10: PARAMONGA | FH10: MAPLE | FI10: SAN_JACINTO | FJ10: AGROLMOS | FK10: MW | FM10: CARPAPATA | FN10: CENTRALES ELOR | FO10: PIAS1 | FP10: ZANA | FQ10: TABLAZO | FR10: TALLANCA | FS10: CURUMUY | FT10: POECHOS1 | FU10: MW
A11: 19/10/2025 | B11: 00:30 | C11: 200.2 | D11: 601 | E11: 204.3 | H11: 21.6 | I11: 144.1 | L11: 127.7 | M11: 127.6 | N11: 128.7 | O11: 225.1 | P11: 213.5 | Q11: 110.7 | R11: 559.7 | S11: 3.3 | X11: 168.1 | Y11: 7.4 | Z11: 6.2 | AB11: 6.8 | AC11: 13.3 | AD11: 72.1 | AI11: 109.8 | AJ11: 150 | AK11: 0 | AN11: 6.5 | AO11: 355.2 | AP11: 45 | AQ11: 151.3 | AR11: 25.4 | AS11: 17 | AT11: 12.1 | AU11: 89.2 | AV11: 181.4 | AW11: 181.9 | AX11: 184.4 | AY11: 109.7 | AZ11: 7.3 | BA11: 8.8 | BB11: 32.8 | BC11: 21.1 | BD11: 2.2 | BE11: 13.2 | BF11: 55.3 | BI11: 86.1 | BJ11: 0 | BP11: 110.7 | BS11: 209.2 | BT11: 90.4 | CC11: 2.5 | CD11: 243.6 | CF11: 59.7 | CG11: 63 | CH11: 29.8 | CL11: 146.6 | CM11: 147.7 | CN11: 149.8 | CV11: 0 | CW11: 37.3 | CX11: 0 | CY11: 2 | CZ11: 0 | DA11: 20 | DB11: 18.3 | DC11: 9.9 | DD11: 4 | DE11: 0 | DF11: 0.7 | DG11: 3.4 | DH11: 5 | DI11: 19.9 | DJ11: 13.6 | DK11: 7.8 | DL11: 3.6 | DM11: 18.6 | DN11: 0 | DO11: 0 | DP11: 9.7 | DQ11: 28 | DR11: 0 | DS11: 3.4 | DT11: 20.1 | DU11: 2.8 | DW11: 9.6 | DX11: 6.6 | DY11: 19.8 | DZ11: 20.2 | EA11: 20 | EB11: 15.4 | EC11: 19.3 | ED11: 0 | EE11: 48.8 | EF11: 65.2 | EG11: 5 | EH11: 3.3 | EI11: 10.4 | EJ11: 7.5 | EK11: 7.2 | EL11: 20.4 | EM11: 20.4 | EN11: 19.6 | EO11: 1.1 | EP11: 0 | EQ11: 0 | ER11: 0 | ES11: 0.6 | ET11: 11.3 | EU11: 8.7 | EV11: 0 | EW11: 2.1 | EX11: 2.3 | EY11: 2 | EZ11: 1 | FA11: 0 | FB11: 6.9 | FC11: 20 | FD11: 9.3 | FE11: 26.8 | FF11: 34.3 | FG11: 15.1 | FH11: 0 | FI11: 7.6 | FJ11: 11.1 | FK11: 6747.1 | FM11: 21.4 | FN11: 5.602 | FO11: 6.133 | FP11: 6.57 | FQ11: 27.43412 | FR11: 18.92717 | FS11: 4.9 | FT11: 5.2 | FU11: 96.16629
A12: 19/10/2025 | B12: 01:00 | C12: 203.4 | D12: 600.5 | E12: 205.3 | H12: 22.5 | I12: 144.4 | L12: 133.3 | M12: 131.7 | N12: 132.7 | O12: 240.6 | P12: 214.7 | Q12: 110.5 | R12: 550.4 | S12: 3.4 | X12: 166.5 | Y12: 7.6 | Z12: 6.2 | AB12: 6.8 | AC12: 11.9 | AD12: 72.2 | AI12: 109.8 | AJ12: 150.2 | AK12: 0 | AN12: 6.5 | AO12: 295.9 | AP12: 44.8 | AQ12: 150.6 | AR12: 28.8 | AS12: 17 | AT12: 12.1 | AU12: 92.5 | AV12: 184.9 | AW12: 184.9 | AX12: 184.5 | AY12: 109.2 | AZ12: 7.5 | BA12: 8.9 | BB12: 33.6 | BC12: 21.1 | BD12: 2.2 | BE12: 12.1 | BF12: 55.2 | BI12: 86.5 | BJ12: 0 | BP12: 111.5 | BS12: 163.1 | BT12: 90.1 | CC12: 2.5 | CD12: 189.5 | CF12: 63.2 | CG12: 63 | CH12: 29.9 | CL12: 147.1 | CM12: 147.7 | CN12: 151.2 | CV12: 0 | CW12: 32.2 | CX12: 0 | CY12: 2 | CZ12: 0 | DA12: 20 | DB12: 19.1 | DC12: 9.8 | DD12: 1.5 | DE12: 0 | DF12: 0.7 | DG12: 3.4 | DH12: 5 | DI12: 19.8 | DJ12: 13.6 | DK12: 7.8 | DL12: 3.6 | DM12: 18.6 | DN12: 0 | DO12: 0 | DP12: 9.9 | DQ12: 29 | DR12: 0 | DS12: 3.5 | DT12: 20.1 | DU12: 2.7 | DW12: 9.6 | DX12: 6.6 | DY12: 19.7 | DZ12: 20.2 | EA12: 19.8 | EB12: 13.5 | EC12: 15.2 | ED12: 0 | EE12: 41.3 | EF12: 65.8 | EG12: 4.8 | EH12: 2.7 | EI12: 10.4 | EJ12: 7.4 | EK12: 7.2 | EL12: 20.4 | EM12: 20.4 | EN12: 19.6 | EO12: 1.2 | EP12: 0 | EQ12: 0 | ER12: 0 | ES12: 0.6 | ET12: 16.5 | EU12: 11.2 | EV12: 0 | EW12: 2.1 | EX12: 2.3 | EY12: 2 | EZ12: 1 | FA12: 0 | FB12: 7 | FC12: 19.9 | FD12: 9.4 | FE12: 27.1 | FF12: 34.5 | FG12: 14.1 | FH12: 0 | FI12: 8.2 | FJ12: 11.1 | FK12: 6617.3 | FM12: 21.9 | FN12: 5.346 | FO12: 6.132 | FP12: 6.63 | FQ12: 27.48612 | FR12: 18.9271 | FS12: 5 | FT12: 5.3 | FU12: 96.72122
A13: 19/10/2025 | B13: 01:30 | C13: 201.5 | D13: 602 | E13: 204.5 | H13: 21.8 | I13: 146.5 | L13: 171.1 | M13: 170.8 | N13: 169.9 | O13: 254.6 | P13: 214.4 | Q13: 110.5 | R13: 559.8 | S13: 3.3 | X13: 166.6 | Y13: 7.9 | Z13: 6.3 | AB13: 6.8 | AC13: 10.9 | AD13: 72.4 | AI13: 109.8 | AJ13: 150.6 | AK13: 0 | AN13: 6.5 | AO13: 294.7 | AP13: 45 | AQ13: 151.5 | AR13: 28 | AS13: 17.2 | AT13: 12.1 | AU13: 89.9 | AV13: 181.6 | AW13: 182.3 | AX13: 185.1 | AY13: 110.2 | AZ13: 7.6 | BA13: 8.8 | BB13: 33 | BC13: 22.1 | BD13: 2.2 | BE13: 12.3 | BF13: 56 | BI13: 86.5 | BJ13: 0 | BP13: 111.4 | BS13: 4.2 | BT13: 0 | CC13: 2.5 | CD13: 223.5 | CF13: 63.9 | CG13: 62.9 | CH13: 29.9 | CL13: 146.4 | CM13: 148.6 | CN13: 149.5 | CV13: 0 | CW13: 30.9 | CX13: 0 | CY13: 5.7 | CZ13: 0 | DA13: 20 | DB13: 17.7 | DC13: 9.9 | DD13: 2 | DE13: 0 | DF13: 0.6 | DG13: 3.4 | DH13: 5.1 | DI13: 20 | DJ13: 13.6 | DK13: 7.8 | DL13: 3.6 | DM13: 18.6 | DN13: 0 | DO13: 0 | DP13: 7.1 | DQ13: 24.3 | DR13: 0 | DS13: 3.5 | DT13: 20.2 | DU13: 2.7 | DW13: 9.6 | DX13: 6.6 | DY13: 19.2 | DZ13: 20.2 | EA13: 20 | EB13: 16.1 | EC13: 18.5 | ED13: 0 | EE13: 42.4 | EF13: 62.4 | EG13: 5 | EH13: 2.7 | EI13: 10.4 | EJ13: 7.3 | EK13: 7.2 | EL13: 20.4 | EM13: 20.4 | EN13: 19.6 | EO13: 3.2 | EP13: 0 | EQ13: 0 | ER13: 0 | ES13: 0.6 | ET13: 14.9 | EU13: 9.3 | EV13: 0 | EW13: 2.1 | EX13: 2.3 | EY13: 2 | EZ13: 1 | FA13: 0 | FB13: 6.8 | FC13: 20 | FD13: 9.1 | FE13: 27 | FF13: 34.4 | FG13: 14.5 | FH13: 0 | FI13: 7.1 | FJ13: 11.1 | FK13: 6527.5 | FM13: 22.3 | FN13: 5.435 | FO13: 6.131 | FP13: 7.47 | FQ13: 27.51566 | FR13: 18.92716 | FS13: 5 | FT13: 5.2 | FU13: 97.97882
A14: 19/10/2025 | B14: 02:00 | C14: 205.4 | D14: 601.5 | E14: 203.8 | H14: 22.7 | I14: 151.3 | L14: 130.5 | M14: 131 | N14: 131.2 | O14: 239 | P14: 214.9 | Q14: 110.6 | R14: 554.2 | S14: 3.2 | X14: 170.1 | Y14: 8 | Z14: 6.2 | AB14: 6.8 | AC14: 11.3 | AD14: 72.4 | AI14: 110.3 | AJ14: 148.8 | AK14: 0 | AN14: 6.5 | AO14: 295.5 | AP14: 47 | AQ14: 152.1 | AR14: 29.1 | AS14: 17 | AT14: 12.1 | AU14: 91.7 | AV14: 183.9 | AW14: 184.9 | AX14: 183.8 | AY14: 110.5 | AZ14: 7.6 | BA14: 8.8 | BB14: 33.9 | BC14: 22 | BD14: 2.2 | BE14: 13.6 | BF14: 56.7 | BI14: 87 | BJ14: 0 | BP14: 112.1 | BS14: 0 | BT14: 0 | CC14: 2.5 | CD14: 152.1 | CF14: 64.3 | CG14: 64.9 | CH14: 30.1 | CL14: 146.4 | CM14: 147.5 | CN14: 149.7 | CV14: 0 | CW14: 31.2 | CX14: 0 | CY14: 4.6 | CZ14: 0 | DA14: 20 | DB14: 13 | DC14: 9.9 | DD14: 1.9 | DE14: 0 | DF14: 0.6 | DG14: 3.4 | DH14: 5 | DI14: 20.3 | DJ14: 13.6 | DK14: 7.8 | DL14: 3.6 | DM14: 18.6 | DN14: 0 | DO14: 0 | DP14: 8.2 | DQ14: 26.9 | DR14: 0 | DS14: 3.5 | DT14: 20.1 | DU14: 2.6 | DW14: 9.6 | DX14: 6.6 | DY14: 19.3 | DZ14: 20.2 | EA14: 20 | EB14: 17.3 | EC14: 16 | ED14: 0 | EE14: 48.8 | EF14: 68.1 | EG14: 4.5 | EH14: 3.2 | EI14: 10.4 | EJ14: 7.2 | EK14: 7.2 | EL14: 20.4 | EM14: 20.4 | EN14: 19.6 | EO14: 2.8 | EP14: 0 | EQ14: 0 | ER14: 0 | ES14: 0.6 | ET14: 11 | EU14: 6.9 | EV14: 0 | EW14: 2.1 | EX14: 2.3 | EY14: 2 | EZ14: 1 | FA14: 0 | FB14: 6.9 | FC14: 20 | FD14: 9.3 | FE14: 27 | FF14: 33.8 | FG14: 14.5 | FH14: 0 | FI14: 7.6 | FJ14: 11.1 | FK14: 6341.2 | FM14: 22.5 | FN14: 5.331 | FO14: 6.129 | FP14: 7.49 | FQ14: 27.4806 | FR14: 18.92695 | FS14: 4.9 | FT14: 5.2 | FU14: 97.95755
A15: 19/10/2025 | B15: 02:30 | C15: 201.4 | D15: 603.8 | E15: 205.6 | H15: 21.8 | I15: 151.4 | L15: 143 | M15: 142.4 | N15: 142.5 | O15: 239.2 | P15: 215.8 | Q15: 111 | R15: 560.6 | S15: 3.2 | X15: 169.3 | Y15: 7.6 | Z15: 6.2 | AB15: 6.8 | AC15: 11.3 | AD15: 72.3 | AI15: 110.3 | AJ15: 149.3 | AK15: 0 | AN15: 6.5 | AO15: 296.7 | AP15: 48 | AQ15: 151.6 | AR15: 28.5 | AS15: 17 | AT15: 12.1 | AU15: 92.6 | AV15: 181.6 | AW15: 182.5 | AX15: 185.2 | AY15: 110.6 | AZ15: 7.6 | BA15: 8.8 | BB15: 32.6 | BC15: 22 | BD15: 2.2 | BE15: 12 | BF15: 56.5 | BI15: 86.5 | BJ15: 0 | BP15: 111.4 | BS15: 0 | BT15: 0 | CC15: 2.5 | CD15: 163.9 | CF15: 64.1 | CG15: 64.8 | CH15: 30 | CL15: 147.4 | CM15: 149.1 | CN15: 150 | CV15: 0 | CW15: 31.8 | CX15: 0 | CY15: 8.2 | CZ15: 0 | DA15: 19.9 | DB15: 6.8 | DC15: 9.9 | DD15: 2 | DE15: 0 | DF15: 0.6 | DG15: 3.4 | DH15: 5 | DI15: 9.4 | DJ15: 13.8 | DK15: 7.8 | DL15: 3.6 | DM15: 18.6 | DN15: 0 | DO15: 0 | DP15: 8.9 | DQ15: 27.3 | DR15: 0 | DS15: 3.5 | DT15: 20.1 | DU15: 2.6 | DW15: 9.6 | DX15: 6.6 | DY15: 19.2 | DZ15: 20.2 | EA15: 20 | EB15: 17.9 | EC15: 16.7 | ED15: 0 | EE15: 54.6 | EF15: 72.5 | EG15: 5.8 | EH15: 3 | EI15: 10.4 | EJ15: 7 | EK15: 7.2 | EL15: 20.4 | EM15: 20.4 | EN15: 19.6 | EO15: 5.2 | EP15: 0 | EQ15: 0 | ER15: 0 | ES15: 0.6 | ET15: 12.3 | EU15: 9 | EV15: 0 | EW15: 2.1 | EX15: 2.3 | EY15: 2 | EZ15: 1 | FA15: 0 | FB15: 7 | FC15: 20 | FD15: 9.5 | FE15: 27 | FF15: 34.5 | FG15: 14.5 | FH15: 0 | FI15: 7.5 | FJ15: 11.1 | FK15: 6399 | FM15: 22.6 | FN15: 5.304 | FO15: 6.129 | FP15: 7.49 | FQ15: 27.48795 | FR15: 18.92705 | FS15: 5 | FT15: 5.3 | FU15: 98.238
A16: 19/10/2025 | B16: 03:00 | C16: 202.4 | D16: 604 | E16: 206.3 | H16: 22.3 | I16: 155 | L16: 129.1 | M16: 130.7 | N16: 130.2 | O16: 230.6 | P16: 213.8 | Q16: 110.6 | R16: 560 | S16: 3.3 | X16: 168.3 | Y16: 8.1 | Z16: 6.2 | AB16: 6.8 | AC16: 11.3 | AD16: 72.4 | AI16: 110.5 | AJ16: 149.6 | AK16: 0 | AN16: 6.5 | AO16: 297.4 | AP16: 48 | AQ16: 153 | AR16: 31 | AS16: 17.2 | AT16: 12.1 | AU16: 88.7 | AV16: 160.8 | AW16: 161.1 | AX16: 172.5 | AY16: 111.1 | AZ16: 7.6 | BA16: 8.8 | BB16: 33.1 | BC16: 22.3 | BD16: 2.2 | BE16: 0 | BF16: 57.5 | BI16: 86.9 | BJ16: 0 | BP16: 112.5 | BS16: 0 | BT16: 0 | CC16: 2.5 | CD16: 176.7 | CF16: 64.9 | CG16: 65 | CH16: 30.3 | CL16: 147 | CM16: 149.1 | CN16: 149.7 | CV16: 0 | CW16: 31.4 | CX16: 0 | CY16: 8.2 | CZ16: 0 | DA16: 20 | DB16: 6.6 | DC16: 9.9 | DD16: 1.9 | DE16: 0 | DF16: 0.6 | DG16: 3.4 | DH16: 5.2 | DI16: 7.3 | DJ16: 14.2 | DK16: 7.7 | DL16: 3.6 | DM16: 18.6 | DN16: 0 | DO16: 0 | DP16: 8 | DQ16: 25.5 | DR16: 0 | DS16: 3.5 | DT16: 20.2 | DU16: 2.5 | DW16: 9.6 | DX16: 6.6 | DY16: 19.1 | DZ16: 20.3 | EA16: 19.9 | EB16: 16.2 | EC16: 14.1 | ED16: 0 | EE16: 57.2 | EF16: 77.4 | EG16: 5.3 | EH16: 4.1 | EI16: 10.4 | EJ16: 7 | EK16: 6.7 | EL16: 20.4 | EM16: 20.4 | EN16: 19.6 | EO16: 5.8 | EP16: 0 | EQ16: 0 | ER16: 0 | ES16: 0.6 | ET16: 19.6 | EU16: 15.9 | EV16: 0 | EW16: 2.1 | EX16: 2.3 | EY16: 2 | EZ16: 1 | FA16: 0 | FB16: 7 | FC16: 20 | FD16: 9.5 | FE16: 27 | FF16: 34 | FG16: 14.7 | FH16: 0 | FI16: 7.5 | FJ16: 11.1 | FK16: 6319.7 | FM16: 22.8 | FN16: 5.31 | FO16: 6.1285 | FP16: 7.48 | FQ16: 27.48058 | FR16: 18.92736 | FS16: 4.9 | FT16: 5.4 | FU16: 98.42644
A17: 19/10/2025 | B17: 03:30 | C17: 202.5 | D17: 602 | E17: 203.9 | H17: 54 | I17: 154.9 | L17: 116.9 | M17: 115.8 | N17: 116.4 | O17: 217.1 | P17: 213.8 | Q17: 110.5 | R17: 556.2 | S17: 3.3 | X17: 167.3 | Y17: 7.5 | Z17: 6.3 | AB17: 6.8 | AC17: 11.3 | AD17: 72.4 | AI17: 110 | AJ17: 149.5 | AK17: 0 | AN17: 6.5 | AO17: 295.6 | AP17: 48.8 | AQ17: 151.2 | AR17: 30.4 | AS17: 17.2 | AT17: 12.1 | AU17: 93.2 | AV17: 163.5 | AW17: 163.9 | AX17: 173.8 | AY17: 108.8 | AZ17: 7.6 | BA17: 8.8 | BB17: 33.5 | BC17: 21.5 | BD17: 2.2 | BE17: 0 | BF17: 55.9 | BI17: 86.6 | BJ17: 0 | BP17: 111.5 | BS17: 0 | BT17: 0 | CC17: 2.5 | CD17: 155.2 | CF17: 64 | CG17: 65 | CH17: 29.9 | CL17: 147.7 | CM17: 148.6 | CN17: 150.2 | CV17: 0 | CW17: 32.2 | CX17: 0 | CY17: 7.6 | CZ17: 0 | DA17: 20 | DB17: 6.4 | DC17: 9.9 | DD17: 3 | DE17: 0 | DF17: 0.6 | DG17: 3.4 | DH17: 5 | DI17: 6.9 | DJ17: 14.5 | DK17: 8.5 | DL17: 3.6 | DM17: 18.6 | DN17: 0 | DO17: 0 | DP17: 7.1 | DQ17: 23.6 | DR17: 0 | DS17: 3.3 | DT17: 20.2 | DU17: 2.4 | DW17: 9.6 | DX17: 6.6 | DY17: 18.9 | DZ17: 20.2 | EA17: 20 | EB17: 23.1 | EC17: 11.4 | ED17: 0 | EE17: 52 | EF17: 73.4 | EG17: 5.3 | EH17: 1.8 | EI17: 10.4 | EJ17: 6.8 | EK17: 6.7 | EL17: 20.4 | EM17: 20.4 | EN17: 19.6 | EO17: 6.1 | EP17: 0 | EQ17: 0 | ER17: 0 | ES17: 0.6 | ET17: 21.6 | EU17: 13.9 | EV17: 0 | EW17: 2.1 | EX17: 2.3 | EY17: 2 | EZ17: 1 | FA17: 0 | FB17: 6.9 | FC17: 20 | FD17: 9.5 | FE17: 27 | FF17: 34.7 | FG17: 14.5 | FH17: 0 | FI17: 9 | FJ17: 11.1 | FK17: 6259.8 | FM17: 23 | FN17: 5.389 | FO17: 6.129 | FP17: 7.48 | FQ17: 27.45785 | FR17: 18.92754 | FS17: 5 | FT17: 5.3 | FU17: 98.68339
A18: 19/10/2025 | B18: 04:00 | C18: 205.7 | D18: 604.9 | E18: 203.4 | H18: 54.9 | I18: 154.8 | L18: 114.4 | M18: 113.4 | N18: 113.6 | O18: 208.2 | P18: 214.7 | Q18: 110.2 | R18: 566.7 | S18: 3.3 | X18: 170.6 | Y18: 8.1 | Z18: 6.5 | AB18: 6.8 | AC18: 11.5 | AD18: 73.3 | AI18: 110.5 | AJ18: 149.4 | AK18: 0 | AN18: 6.5 | AO18: 296 | AP18: 49.7 | AQ18: 152.1 | AR18: 30.3 | AS18: 17.2 | AT18: 12.1 | AU18: 93 | AV18: 164.8 | AW18: 165.4 | AX18: 173.3 | AY18: 110.8 | AZ18: 7.6 | BA18: 8.8 | BB18: 34.3 | BC18: 22.3 | BD18: 2.2 | BE18: 0 | BF18: 57.2 | BI18: 87.1 | BJ18: 0 | BP18: 112.3 | BS18: 0 | BT18: 0 | CC18: 2.5 | CD18: 129.8 | CF18: 64.6 | CG18: 65 | CH18: 30.3 | CL18: 146.8 | CM18: 148 | CN18: 149.5 | CV18: 0 | CW18: 26.3 | CX18: 0 | CY18: 5.6 | CZ18: 0 | DA18: 20 | DB18: 6.5 | DC18: 9.9 | DD18: 4.2 | DE18: 0 | DF18: 0.6 | DG18: 3.4 | DH18: 5 | DI18: 7.1 | DJ18: 14.5 | DK18: 8.5 | DL18: 3.6 | DM18: 18.6 | DN18: 0 | DO18: 0 | DP18: 6.4 | DQ18: 20.4 | DR18: 0 | DS18: 3.4 | DT18: 20.2 | DU18: 2.4 | DW18: 9.6 | DX18: 6.6 | DY18: 18.4 | DZ18: 20.3 | EA18: 19.9 | EB18: 26.4 | EC18: 12.7 | ED18: 0 | EE18: 66.1 | EF18: 80.4 | EG18: 7.6 | EH18: 3.7 | EI18: 10.4 | EJ18: 6.7 | EK18: 6.7 | EL18: 20.4 | EM18: 20.4 | EN18: 19.6 | EO18: 4.5 | EP18: 0 | EQ18: 0 | ER18: 0 | ES18: 0.6 | ET18: 32.1 | EU18: 19.3 | EV18: 0 | EW18: 2.1 | EX18: 2.3 | EY18: 2 | EZ18: 1 | FA18: 0 | FB18: 6.9 | FC18: 20 | FD18: 9.6 | FE18: 26.9 | FF18: 34.3 | FG18: 14.9 | FH18: 0 | FI18: 7.3 | FJ18: 11.1 | FK18: 6281.8 | FM18: 23.1 | FN18: 5.396 | FO18: 6.1275 | FP18: 7.5 | FQ18: 27.45989 | FR18: 18.92749 | FS18: 5 | FT18: 5.3 | FU18: 98.81088
A19: 19/10/2025 | B19: 04:30 | C19: 200.7 | D19: 597.2 | E19: 203.3 | H19: 54.1 | I19: 153.8 | L19: 108.6 | M19: 109.6 | N19: 109.2 | O19: 222.8 | P19: 214.8 | Q19: 110.4 | R19: 545.7 | S19: 3.2 | X19: 161.9 | Y19: 7.4 | Z19: 6.2 | AB19: 6.8 | AC19: 11.6 | AD19: 71.6 | AI19: 109.3 | AJ19: 150 | AK19: 0 | AN19: 6.5 | AO19: 293.9 | AP19: 48.1 | AQ19: 150.4 | AR19: 31.4 | AS19: 17.2 | AT19: 12.1 | AU19: 92.5 | AV19: 122.7 | AW19: 123.2 | AX19: 155.1 | AY19: 108.9 | AZ19: 7.6 | BA19: 8.9 | BB19: 33.1 | BC19: 21.1 | BD19: 2.2 | BE19: 0 | BF19: 54.9 | BI19: 85.6 | BJ19: 0 | BP19: 127.2 | BS19: 0 | BT19: 0 | CC19: 2.5 | CD19: 153.9 | CF19: 63.6 | CG19: 64.8 | CH19: 29.7 | CL19: 146.9 | CM19: 147.7 | CN19: 150 | CV19: 0 | CW19: 29 | CX19: 0 | CY19: 7.3 | CZ19: 0 | DA19: 20 | DB19: 10.1 | DC19: 9.9 | DD19: 4.4 | DE19: 0 | DF19: 0.6 | DG19: 3.4 | DH19: 5 | DI19: 14.2 | DJ19: 14.3 | DK19: 8.5 | DL19: 3.6 | DM19: 18.6 | DN19: 0 | DO19: 0 | DP19: 6.2 | DQ19: 23 | DR19: 0 | DS19: 3.4 | DT19: 20.2 | DU19: 2.4 | DW19: 9.6 | DX19: 6.6 | DY19: 18.4 | DZ19: 20.1 | EA19: 20 | EB19: 26.5 | EC19: 11.1 | ED19: 0 | EE19: 52 | EF19: 77.4 | EG19: 4.6 | EH19: 2 | EI19: 10.4 | EJ19: 6.5 | EK19: 6.9 | EL19: 20.4 | EM19: 20.4 | EN19: 19.6 | EO19: 4.8 | EP19: 0 | EQ19: 0 | ER19: 0 | ES19: 0.6 | ET19: 40.1 | EU19: 28.9 | EV19: 0 | EW19: 2.1 | EX19: 2.3 | EY19: 2 | EZ19: 1 | FA19: 0 | FB19: 7 | FC19: 20 | FD19: 9.5 | FE19: 26.9 | FF19: 33.8 | FG19: 15.2 | FH19: 0 | FI19: 8.8 | FJ19: 11.1 | FK19: 6170.6 | FM19: 23 | FN19: 5.391 | FO19: 6.128 | FP19: 7.5 | FQ19: 27.47876 | FR19: 18.92765 | FS19: 5 | FT19: 5.3 | FU19: 98.72541
A20: 19/10/2025 | B20: 05:00 | C20: 198.5 | D20: 603.3 | E20: 205 | H20: 53.9 | I20: 155 | L20: 156 | M20: 156 | N20: 156.3 | O20: 239.6 | P20: 215.3 | Q20: 110.6 | R20: 562.4 | S20: 3.3 | X20: 115.8 | Y20: 8 | Z20: 6.1 | AB20: 6.8 | AC20: 11.6 | AD20: 73.1 | AI20: 109.9 | AJ20: 150.6 | AK20: 0 | AN20: 6.5 | AO20: 294.6 | AP20: 49.9 | AQ20: 149.7 | AR20: 33.2 | AS20: 17.2 | AT20: 12.1 | AU20: 89.7 | AV20: 122 | AW20: 122.3 | AX20: 154 | AY20: 109.3 | AZ20: 7.6 | BA20: 8.9 | BB20: 33.4 | BC20: 22 | BD20: 2.2 | BE20: 0 | BF20: 56.2 | BI20: 60.3 | BJ20: 0 | BP20: 127.1 | BS20: 0 | BT20: 0 | CC20: 2.5 | CD20: 173.2 | CF20: 63.9 | CG20: 64.8 | CH20: 29.8 | CL20: 147.2 | CM20: 148.3 | CN20: 150 | CV20: 0 | CW20: 27.3 | CX20: 0 | CY20: 8.8 | CZ20: 0 | DA20: 20 | DB20: 8.5 | DC20: 9.9 | DD20: 4.3 | DE20: 0 | DF20: 0.6 | DG20: 3.4 | DH20: 5 | DI20: 19.1 | DJ20: 14.3 | DK20: 8.5 | DL20: 3.6 | DM20: 18.6 | DN20: 0.1 | DO20: 0 | DP20: 6.3 | DQ20: 22.7 | DR20: 0 | DS20: 3.4 | DT20: 19.6 | DU20: 2.3 | DW20: 9.6 | DX20: 6.6 | DY20: 18.5 | DZ20: 20.2 | EA20: 20 | EB20: 25.9 | EC20: 14 | ED20: 0 | EE20: 47.8 | EF20: 77.1 | EG20: 5.1 | EH20: 3.1 | EI20: 10.4 | EJ20: 6.4 | EK20: 6.9 | EL20: 20.4 | EM20: 20.4 | EN20: 19.6 | EO20: 6.3 | EP20: 0 | EQ20: 0 | ER20: 0 | ES20: 0.6 | ET20: 45.4 | EU20: 35 | EV20: 0 | EW20: 2.1 | EX20: 2.3 | EY20: 2 | EZ20: 1 | FA20: 0 | FB20: 7 | FC20: 20 | FD20: 9.3 | FE20: 26.7 | FF20: 33.1 | FG20: 14.6 | FH20: 0 | FI20: 7.9 | FJ20: 11.1 | FK20: 6317.7 | FM20: 23 | FN20: 5.36 | FO20: 6.13 | FP20: 7.49 | FQ20: 27.56414 | FR20: 18.92808 | FS20: 4.9 | FT20: 5.3 | FU20: 98.67222
A21: 19/10/2025 | B21: 05:30 | C21: 202.3 | D21: 604.1 | E21: 206.5 | H21: 54.2 | I21: 158.5 | L21: 119.9 | M21: 119.6 | N21: 120 | O21: 224.1 | P21: 215.5 | Q21: 110.7 | R21: 561.9 | S21: 3.4 | X21: 82.9 | Y21: 7.9 | Z21: 6.1 | AB21: 6.8 | AC21: 11.6 | AD21: 72.6 | AI21: 110.2 | AJ21: 149.8 | AK21: 0 | AN21: 6.5 | AO21: 295.8 | AP21: 51 | AQ21: 151.3 | AR21: 32.7 | AS21: 17 | AT21: 12.1 | AU21: 68.8 | AV21: 138.1 | AW21: 138.2 | AX21: 161.3 | AY21: 109.7 | AZ21: 7.6 | BA21: 8.9 | BB21: 33.4 | BC21: 21.6 | BD21: 2.2 | BE21: 0 | BF21: 56.4 | BI21: 60.9 | BJ21: 0 | BP21: 127.8 | BS21: 0 | BT21: 0 | CC21: 2.5 | CD21: 230.9 | CF21: 64 | CG21: 65 | CH21: 29.9 | CL21: 147.9 | CM21: 148.6 | CN21: 151 | CV21: 0 | CW21: 34.5 | CX21: 0.5 | CY21: 11.3 | CZ21: 0 | DA21: 19.9 | DB21: 20 | DC21: 9.9 | DD21: 4.4 | DE21: 2.9 | DF21: 0.6 | DG21: 3.4 | DH21: 4.9 | DI21: 20 | DJ21: 14.9 | DK21: 8.5 | DL21: 3.6 | DM21: 18.6 | DN21: 3.2 | DO21: 3.3 | DP21: 10.7 | DQ21: 25.2 | DR21: 0.4 | DS21: 3.5 | DT21: 15.3 | DU21: 2.3 | DW21: 9.5 | DX21: 6.6 | DY21: 19.1 | DZ21: 20.2 | EA21: 20 | EB21: 23.1 | EC21: 17.3 | ED21: 0.5 | EE21: 48.8 | EF21: 70.6 | EG21: 4.7 | EH21: 1.5 | EI21: 10.4 | EJ21: 6.3 | EK21: 6.9 | EL21: 20.4 | EM21: 20.4 | EN21: 19.6 | EO21: 10.7 | EP21: 3.5 | EQ21: 0 | ER21: 3.2 | ES21: 0.6 | ET21: 43.2 | EU21: 32.4 | EV21: 2.5 | EW21: 2.1 | EX21: 2.3 | EY21: 2 | EZ21: 1 | FA21: 0 | FB21: 6.9 | FC21: 20 | FD21: 9.5 | FE21: 27 | FF21: 33.6 | FG21: 15.7 | FH21: 0 | FI21: 8.3 | FJ21: 11.1 | FK21: 6293 | FM21: 23 | FN21: 5.303 | FO21: 6.1315 | FP21: 7.51 | FQ21: 27.54742 | FR21: 18.92788 | FS21: 4.9 | FT21: 5.3 | FU21: 98.6198
A22: 19/10/2025 | B22: 06:00 | C22: 204 | D22: 603.4 | E22: 205.1 | H22: 54.6 | I22: 160.8 | L22: 122.2 | M22: 122 | N22: 121.1 | O22: 215.8 | P22: 213.7 | Q22: 110.9 | R22: 559.3 | S22: 3.3 | X22: 84 | Y22: 8.1 | Z22: 6.2 | AB22: 6.8 | AC22: 11.5 | AD22: 72.5 | AI22: 110.4 | AJ22: 89 | AK22: 0 | AN22: 6.5 | AO22: 147.3 | AP22: 51.9 | AQ22: 152.2 | AR22: 33.2 | AS22: 17 | AT22: 12.1 | AU22: 49.3 | AV22: 125.2 | AW22: 125.4 | AX22: 153.5 | AY22: 111.1 | AZ22: 7.6 | BA22: 9.1 | BB22: 33.1 | BC22: 22 | BD22: 2.2 | BE22: 0 | BF22: 57.6 | BI22: 60.8 | BJ22: 0 | BP22: 128.2 | BS22: 0 | BT22: 0 | CC22: 2.5 | CD22: 98.7 | CF22: 64.4 | CG22: 65.1 | CH22: 30.3 | CL22: 147.3 | CM22: 148.4 | CN22: 149.9 | CV22: 0 | CW22: 38.9 | CX22: 19.8 | CY22: 9.6 | CZ22: 0 | DA22: 19.9 | DB22: 20.3 | DC22: 9.9 | DD22: 4.4 | DE22: 38.5 | DF22: 0.6 | DG22: 3.4 | DH22: 4.9 | DI22: 20.5 | DJ22: 14.9 | DK22: 8.5 | DL22: 3.6 | DM22: 18.6 | DN22: 10.3 | DO22: 11.3 | DP22: 8.5 | DQ22: 22.9 | DR22: 1 | DS22: 3.3 | DT22: 15.1 | DU22: 2.3 | DW22: 9.4 | DX22: 6.6 | DY22: 19.3 | DZ22: 20.2 | EA22: 20 | EB22: 21 | EC22: 19.2 | ED22: 7.5 | EE22: 47.8 | EF22: 70.5 | EG22: 5.5 | EH22: 2.4 | EI22: 10.4 | EJ22: 6.2 | EK22: 7.1 | EL22: 20.4 | EM22: 20.4 | EN22: 19.6 | EO22: 6.6 | EP22: 62 | EQ22: 0.7 | ER22: 36.9 | ES22: 0.6 | ET22: 34.1 | EU22: 23.7 | EV22: 30.9 | EW22: 2.1 | EX22: 2.3 | EY22: 2 | EZ22: 1 | FA22: 0.7 | FB22: 6.6 | FC22: 20 | FD22: 9.5 | FE22: 27 | FF22: 33.6 | FG22: 15.7 | FH22: 3.1 | FI22: 7 | FJ22: 11.1 | FK22: 6078.3 | FM22: 23 | FN22: 5.307 | FO22: 6.1305 | FP22: 7.49 | FQ22: 27.55404 | FR22: 18.92788 | FS22: 4.9 | FT22: 5.2 | FU22: 98.50942
... A58: 20/10/2025 | B58: 00:00 | C58: 200.4 | D58: 627.9 | E58: 215.1 | H58: 79.2 | I58: 166 | L58: 103.6 | M58: 103.9 | N58: 103.7 | O58: 213.4 | P58: 216 | Q58: 110.2 | R58: 548 | S58: 3.1 | X58: 168.3 | Y58: 7.4 | Z58: 6.1 | AB58: 6.9 | AC58: 13.1 | AD58: 71.9 | AI58: 109.1 | AJ58: 87.6 | AK58: 0 | AN58: 6.4 | AO58: 295.6 | AP58: 49.9 | AQ58: 151.3 | AR58: 32.2 | AS58: 17.8 | AT58: 18.6 | AU58: 94.4 | AV58: 180 | AW58: 180.5 | AX58: 183.6 | AY58: 108.8 | AZ58: 7.5 | BA58: 8.9 | BB58: 33.1 | BC58: 0 | BD58: 2 | BE58: 12.2 | BF58: 50.7 | BI58: 94.5 | BJ58: 25.8 | BP58: 127 | BS58: 0 | BT58: 0 | CC58: 2.5 | CD58: 198.4 | CF58: 62.2 | CG58: 63.6 | CH58: 29.6 | CL58: 147.4 | CM58: 148.1 | CN58: 149.3 | CV58: 0 | CW58: 38.7 | CX58: 0 | CY58: 10.1 | CZ58: 0 | DA58: 17.5 | DB58: 12.1 | DC58: 10 | DD58: 5.2 | DE58: 0 | DF58: 1.2 | DG58: 3.4 | DH58: 5.1 | DI58: 20.3 | DJ58: 11.6 | DK58: 8.7 | DL58: 3.5 | DM58: 18.6 | DN58: 0 | DO58: 0 | DP58: 9.2 | DQ58: 27.6 | DR58: 0 | DS58: 3.1 | DT58: 20.2 | DU58: 2.9 | DW58: 10 | DX58: 6.6 | DY58: 20.1 | DZ58: 20.1 | EA58: 19.9 | EB58: 15.4 | EC58: 12.8 | ED58: 0 | EE58: 73.2 | EF58: 92.9 | EG58: 8.3 | EH58: 2.6 | EI58: 10.4 | EJ58: 8.3 | EK58: 7.3 | EL58: 20.4 | EM58: 20.4 | EN58: 19.6 | EO58: 9.4 | EP58: 0 | EQ58: 0 | ER58: 0 | ES58: 0.6 | ET58: 29.3 | EU58: 17.7 | EV58: 0 | EW58: 2.1 | EX58: 2.3 | EY58: 2 | EZ58: 1 | FA58: 0 | FB58: 7 | FC58: 20 | FD58: 8.5 | FE58: 27.9 | FF58: 33.9 | FG58: 14.5 | FH58: 19.1 | FI58: 7.7 | FJ58: 11 | FK58: 6454.1 | FM58: 22.1 | FN58: 7.911 | FO58: 6.1105 | FP58: 0 | FQ58: 27.31556 | FR58: 18.9291 | FS58: 4.9 | FT58: 7.1 | FU58: 94.36616
A59: EJEC | C59: 4855.05 | D59: 14832.6 | E59: 5051.45 | F59: 0 | G59: 0 | H59: 1545.7 | I59: 3682.6 | J59: 0 | K59: 0 | L59: 3140.85 | M59: 3142.55 | N59: 3141.4 | O59: 5516.9 | P59: 4053.95 | Q59: 2205.15 | R59: 11190.3 | S59: 78.15 | T59: 0 | U59: 0 | V59: 0 | W59: 0 | X59: 2989.35 | Y59: 184.85 | Z59: 146.75 | AA59: 0 | AB59: 163.15 | AC59: 290.6 | AD59: 1890.15 | AE59: 0 | AF59: 0 | AG59: 0 | AH59: 0 | AI59: 2633.25 | AJ59: 3544.5 | AK59: 133.75 | AL59: 0 | AM59: 0 | AN59: 155.8 | AO59: 5561 | AP59: 1184.45 | AQ59: 3407.25 | AR59: 742.5 | AS59: 404.65 | AT59: 344.95 | AU59: 1677.95 | AV59: 3647.2 | AW59: 3655.1 | AX59: 4036.25 | AY59: 2622.3 | AZ59: 180.65 | BA59: 214.45 | BB59: 799.85 | BC59: 141.6 | BD59: 51 | BE59: 432.5 | BF59: 1312.85 | BG59: 0 | BH59: 0 | BI59: 1778.25 | BJ59: 719.1 | BK59: 0 | BL59: 0 | BM59: 0 | BN59: 0 | BO59: 0 | BP59: 2928.2 | BQ59: 0 | BR59: 0 | BS59: 660.85 | BT59: 90.25 | BU59: 0 | BV59: 0 | BW59: 0 | BX59: 0 | BY59: 0 | BZ59: 0 | CA59: 0 | CB59: 0 | CC59: 60 | CD59: 3927.55 | CE59: 0 | CF59: 1542.65 | CG59: 1547.7 | CH59: 717.35 | CI59: 0 | CJ59: 0 | CK59: 0 | CL59: 3035.9 | CM59: 3032.55 | CN59: 3292.65 | CO59: 0 | CP59: 0 | CQ59: 0 | CR59: 0 | CS59: 0 | CT59: 0 | CU59: 0 | CV59: 9.2 | CW59: 1587.5 | CX59: 824.05 | CY59: 169.4 | CZ59: 3.3 | DA59: 449.95 | DB59: 350.95 | DC59: 237.9 | DD59: 105.2 | DE59: 2189.65 | DF59: 22.7 | DG59: 81.6 | DH59: 117.95 | DI59: 458.3 | DJ59: 322 | DK59: 196 | DL59: 84.55 | DM59: 446.4 | DN59: 164.7 | DO59: 200.5 | DP59: 384.7 | DQ59: 1162.95 | DR59: 177.45 | DS59: 79.3 | DT59: 408.85 | DU59: 55.05 | DV59: 0 | DW59: 237.3 | DX59: 150.05 | DY59: 458.45 | DZ59: 484.45 | EA59: 479.05 | EB59: 358.2 | EC59: 859.35 | ED59: 386.9 | EE59: 1726.95 | EF59: 1994.7 | EG59: 242.05 | EH59: 145.85 | EI59: 250.05 | EJ59: 177.5 | EK59: 167.25 | EL59: 489 | EM59: 489.6 | EN59: 470.4 | EO59: 172.45 | EP59: 2582 | EQ59: 139.85 | ER59: 1539.55 | ES59: 14.4 | ET59: 1349 | EU59: 1265.5 | EV59: 1137 | EW59: 50.4 | EX59: 55.2 | EY59: 48 | EZ59: 24 | FA59: 137.8 | FB59: 164.05 | FC59: 480.15 | FD59: 222.5 | FE59: 657.9 | FF59: 810.95 | FG59: 256.3 | FH59: 313.15 | FI59: 190.1 | FJ59: 260.4 | FK59: 160046.15 | FM59: 530.95 | FN59: 146.3205 | FO59: 146.952 | FP59: 73.755 | FQ59: 650.35741 | FR59: 454.22719 | FS59: 113.5 | FT59: 198.5 | FU59: 2314.5621

Sheet REACTIVA
B3: domingo, 19 de Octubre del 2025
A5: POTENCIA REACTIVA EJECUTADA DE LAS UNIDADES DE GENERACIÓN DEL COES (MVAR) | FM5: CENTRALES NO INTEGRANTES COES
A6: FECHA | B6: HORA | C6: 65333 | D6: 101 | E6: 102 | F6: 42667 | G6: 42668 | H6: 126 | I6: 127 | J6: 138 | K6: 139 | L6: 197 | M6: 203 | N6: 204 | O6: 230 | P6: 209 | Q6: 56677 | R6: 796 | S6: 2146 | T6: 142 | U6: 143 | V6: 125 | W6: 187 | X6: 163 | Y6: 298 | Z6: 299 | AA6: 219 | AB6: 151 | AC6: 152 | AD6: 153 | AE6: 154 | AF6: 756 | AG6: 156 | AH6: 155 | AI6: 182 | AJ6: 212 | AK6: 758 | AL6: 263 | AM6: 265 | AN6: 775 | AO6: 777 | AP6: 2154 | AQ6: 150 | AR6: 149 | AS6: 188 | AT6: 2131 | AU6: 755 | AV6: 252 | AW6: 249 | AX6: 250 | AY6: 117 | AZ6: 267 | BA6: 268 | BB6: 119 | BC6: 120 | BD6: 189 | BE6: 122 | BF6: 266 | BG6: 337 | BH6: 338 | BI6: 251 | BJ6: 115 | BK6: 239 | BL6: 288 | BM6: 240 | BN6: 241 | BO6: 242 | BP6: 191 | BQ6: 194 | BR6: 196 | BS6: 207 | BT6: 236 | BU6: 795 | BV6: 285 | BW6: 995 | BX6: 996 | BY6: 997 | BZ6: 766 | CA6: 926 | CB6: 924 | CC6: 121 | CD6: 103 | CE6: 104 | CF6: 106 | CG6: 105 | CH6: 107 | CI6: 110 | CJ6: 109 | CK6: 144 | CL6: 113 | CM6: 114 | CN6: 193 | CO6: 208 | CP6: 786 | CQ6: 787 | CR6: 788 | CS6: 789 | CT6: 248 | CU6: 2159 | CV6: 303 | CW6: 59715 | CX6: 62255 | CY6: 1263 | CZ6: 61800 | DA6: 2194 | DB6: 69125 | DC6: 216 | DD6: 198 | DE6: 70400 | DF6: 49607 | DG6: 214 | DH6: 260 | DI6: 2152 | DJ6: 2128 | DK6: 247 | DL6: 228 | DM6: 2135 | DN6: 261 | DO6: 237 | DP6: 253 | DQ6: 770 | DR6: 235 | DS6: 238 | DT6: 2184 | DU6: 61855 | DV6: 223 | DW6: 226 | DX6: 201 | DY6: 258 | DZ6: 259 | EA6: 920 | EB6: 257 | EC6: 256 | ED6: 2148 | EE6: 58288 | EF6: 58289 | EG6: 58839 | EH6: 58840 | EI6: 296 | EJ6: 297 | EK6: 211 | EL6: 2175 | EM6: 2178 | EN6: 2181 | EO6: 1262 | EP6: 63425 | EQ6: 233 | ER6: 2150 | ES6: 2165 | ET6: 2161 | EU6: 61197 | EV6: 58851 | EW6: 225 | EX6: 2201 | EY6: 2171 | EZ6: 760 | FA6: 234 | FB6: 215 | FC6: 917 | FD6: 289 | FE6: 58333 | FF6: 58336 | FG6: 213 | FH6: 232 | FI6: 2190 | FJ6: 69867 | FK6: TOTAL COES | FM6: 221 | FN6: 222 | FO6: 224 | FP6: 2187 | FQ6: 227 | FR6: 49400 | FS6: 199 | FT6: 200 | FU6: TOTAL NO COES
C7: SUR | D7: CENTRO | E7: CENTRO | F7: NORTE | G7: NORTE | H7: NORTE | I7: NORTE | J7: CENTRO | K7: CENTRO | L7: CENTRO | M7: CENTRO | N7: CENTRO | O7: CENTRO | P7: CENTRO | Q7: CENTRO | R7: CENTRO | S7: CENTRO | T7: CENTRO | U7: CENTRO | V7: CENTRO | W7: CENTRO | X7: SUR | Y7: SUR | Z7: SUR | AA7: CENTRO | AB7: SUR | AC7: SUR | AD7: SUR | AE7: SUR | AF7: SUR | AG7: SUR | AH7: SUR | AI7: SUR | AJ7: CENTRO | AK7: NORTE | AL7: NORTE | AM7: NORTE | AN7: CENTRO | AO7: CENTRO | AP7: CENTRO | AQ7: CENTRO | AR7: CENTRO | AS7: CENTRO | AT7: CENTRO | AU7: SUR | AV7: CENTRO | AW7: CENTRO | AX7: CENTRO | AY7: CENTRO | AZ7: CENTRO | BA7: CENTRO | BB7: CENTRO | BC7: CENTRO | BD7: SUR | BE7: NORTE | BF7: CENTRO | BG7: CENTRO | BH7: CENTRO | BI7: CENTRO | BJ7: NORTE | BK7: NORTE | BL7: NORTE | BM7: SUR | BN7: SUR | BO7: SUR | BP7: CENTRO | BQ7: CENTRO | BR7: CENTRO | BS7: CENTRO | BT7: CENTRO | BU7: CENTRO | BV7: CENTRO | BW7: SUR | BX7: SUR | BY7: SUR | BZ7: NORTE | CA7: SUR | CB7: CENTRO | CC7: NORTE | CD7: CENTRO | CE7: CENTRO | CF7: CENTRO | CG7: CENTRO | CH7: CENTRO | CI7: CENTRO | CJ7: CENTRO | CK7: CENTRO | CL7: CENTRO | CM7: CENTRO | CN7: CENTRO | CO7: CENTRO | CP7: SUR | CQ7: SUR | CR7: SUR | CS7: SUR | CT7: CENTRO | CU7: CENTRO | CV7: CENTRO | CW7: CENTRO | CX7: SUR | CY7: NORTE | CZ7: NORTE | DA7: NORTE | DB7: CENTRO | DC7: NORTE | DD7: NORTE | DE7: SUR | DF7: SUR | DG7: CENTRO | DH7: CENTRO | DI7: CENTRO | DJ7: NORTE | DK7: NORTE | DL7: CENTRO | DM7: CENTRO | DN7: SUR | DO7: SUR | DP7: CENTRO | DQ7: CENTRO | DR7: SUR | DS7: CENTRO | DT7: CENTRO | DU7: NORTE | DV7: CENTRO | DW7: CENTRO | DX7: NORTE | DY7: CENTRO | DZ7: CENTRO | EA7: CENTRO | EB7: NORTE | EC7: NORTE | ED7: SUR | EE7: CENTRO | EF7: CENTRO | EG7: CENTRO | EH7: CENTRO | EI7: CENTRO | EJ7: CENTRO | EK7: SUR | EL7: SUR | EM7: SUR | EN7: SUR | EO7: NORTE | EP7: SUR | EQ7: SUR | ER7: SUR | ES7: CENTRO | ET7: CENTRO | EU7: CENTRO | EV7: SUR | EW7: CENTRO | EX7: CENTRO | EY7: CENTRO | EZ7: CENTRO | FA7: SUR | FB7: NORTE | FC7: CENTRO | FD7: NORTE | FE7: NORTE | FF7: NORTE | FG7: CENTRO | FH7: NORTE | FI7: NORTE | FJ7: NORTE | FM7: NORTE | FN7: CENTRO | FO7: NORTE | FP7: NORTE | FQ7: NORTE | FR7: NORTE | FS7: NORTE | FT7: NORTE
C8: HIDROELÉCTRICA | D8: HIDROELÉCTRICA | E8: HIDROELÉCTRICA | F8: TERMOELÉCTRICA | G8: TERMOELÉCTRICA | H8: HIDROELÉCTRICA | I8: HIDROELÉCTRICA | J8: TERMOELÉCTRICA | K8: TERMOELÉCTRICA | L8: TERMOELÉCTRICA | M8: TERMOELÉCTRICA | N8: TERMOELÉCTRICA | O8: TERMOELÉCTRICA | P8: TERMOELÉCTRICA | Q8: TERMOELÉCTRICA | R8: HIDROELÉCTRICA | S8: HIDROELÉCTRICA | T8: TERMOELÉCTRICA | U8: TERMOELÉCTRICA | V8: TERMOELÉCTRICA | W8: TERMOELÉCTRICA | X8: HIDROELÉCTRICA | Y8: HIDROELÉCTRICA | Z8: HIDROELÉCTRICA | AA8: TERMOELÉCTRICA | AB8: HIDROELÉCTRICA | AC8: HIDROELÉCTRICA | AD8: HIDROELÉCTRICA | AE8: HIDROELÉCTRICA | AF8: TERMOELÉCTRICA | AG8: TERMOELÉCTRICA | AH8: TERMOELÉCTRICA | AI8: HIDROELÉCTRICA | AJ8: HIDROELÉCTRICA | AK8: TERMOELÉCTRICA | AL8: TERMOELÉCTRICA | AM8: TERMOELÉCTRICA | AN8: HIDROELÉCTRICA | AO8: HIDROELÉCTRICA | AP8: HIDROELÉCTRICA | AQ8: HIDROELÉCTRICA | AR8: HIDROELÉCTRICA | AS8: HIDROELÉCTRICA | AT8: HIDROELÉCTRICA | AU8: HIDROELÉCTRICA | AV8: TERMOELÉCTRICA | AW8: TERMOELÉCTRICA | AX8: TERMOELÉCTRICA | AY8: HIDROELÉCTRICA | AZ8: HIDROELÉCTRICA | BA8: HIDROELÉCTRICA | BB8: HIDROELÉCTRICA | BC8: HIDROELÉCTRICA | BD8: HIDROELÉCTRICA | BE8: HIDROELÉCTRICA | BF8: HIDROELÉCTRICA | BG8: HIDROELÉCTRICA | BH8: HIDROELÉCTRICA | BI8: HIDROELÉCTRICA | BJ8: TERMOELÉCTRICA | BK8: TERMOELÉCTRICA | BL8: TERMOELÉCTRICA | BM8: TERMOELÉCTRICA | BN8: TERMOELÉCTRICA | BO8: TERMOELÉCTRICA | BP8: HIDROELÉCTRICA | BQ8: TERMOELÉCTRICA | BR8: TERMOELÉCTRICA | BS8: TERMOELÉCTRICA | BT8: TERMOELÉCTRICA | BU8: TERMOELÉCTRICA | BV8: TERMOELÉCTRICA | BW8: TERMOELÉCTRICA | BX8: TERMOELÉCTRICA | BY8: TERMOELÉCTRICA | BZ8: HIDROELÉCTRICA | CA8: TERMOELÉCTRICA | CB8: TERMOELÉCTRICA | CC8: HIDROELÉCTRICA | CD8: HIDROELÉCTRICA | CE8: HIDROELÉCTRICA | CF8: HIDROELÉCTRICA | CG8: HIDROELÉCTRICA | CH8: HIDROELÉCTRICA | CI8: TERMOELÉCTRICA | CJ8: TERMOELÉCTRICA | CK8: TERMOELÉCTRICA | CL8: TERMOELÉCTRICA | CM8: TERMOELÉCTRICA | CN8: TERMOELÉCTRICA | CO8: TERMOELÉCTRICA | CP8: TERMOELÉCTRICA | CQ8: TERMOELÉCTRICA | CR8: TERMOELÉCTRICA | CS8: TERMOELÉCTRICA | CT8: TERMOELÉCTRICA | CU8: TERMOELÉCTRICA | CV8: SOLAR | CW8: EÓLICA | CX8: SOLAR | CY8: EÓLICA | CZ8: SOLAR | DA8: HIDROELÉCTRICA | DB8: HIDROELÉCTRICA | DC8: HIDROELÉCTRICA | DD8: HIDROELÉCTRICA | DE8: SOLAR | DF8: HIDROELÉCTRICA | DG8: HIDROELÉCTRICA | DH8: HIDROELÉCTRICA | DI8: HIDROELÉCTRICA | DJ8: HIDROELÉCTRICA | DK8: HIDROELÉCTRICA | DL8: HIDROELÉCTRICA | DM8: HIDROELÉCTRICA | DN8: SOLAR | DO8: SOLAR | DP8: EÓLICA | DQ8: EÓLICA | DR8: SOLAR | DS8: HIDROELÉCTRICA | DT8: HIDROELÉCTRICA | DU8: HIDROELÉCTRICA | DV8: HIDROELÉCTRICA | DW8: HIDROELÉCTRICA | DX8: HIDROELÉCTRICA | DY8: HIDROELÉCTRICA | DZ8: HIDROELÉCTRICA | EA8: HIDROELÉCTRICA | EB8: EÓLICA | EC8: EÓLICA | ED8: SOLAR | EE8: EÓLICA | EF8: EÓLICA | EG8: EÓLICA | EH8: EÓLICA | EI8: HIDROELÉCTRICA | EJ8: HIDROELÉCTRICA | EK8: HIDROELÉCTRICA | EL8: HIDROELÉCTRICA | EM8: HIDROELÉCTRICA | EN8: HIDROELÉCTRICA | EO8: EÓLICA | EP8: SOLAR | EQ8: SOLAR | ER8: SOLAR | ES8: HIDROELÉCTRICA | ET8: EÓLICA | EU8: EÓLICA | EV8: SOLAR | EW8: TERMOELÉCTRICA | EX8: TERMOELÉCTRICA | EY8: TERMOELÉCTRICA | EZ8: TERMOELÉCTRICA | FA8: SOLAR | FB8: HIDROELÉCTRICA | FC8: HIDROELÉCTRICA | FD8: TERMOELÉCTRICA | FE8: TERMOELÉCTRICA | FF8: TERMOELÉCTRICA | FG8: TERMOELÉCTRICA | FH8: TERMOELÉCTRICA | FI8: TERMOELÉCTRICA | FJ8: TERMOELÉCTRICA | FM8: HIDROELÉCTRICA | FN8: HIDROELÉCTRICA | FO8: HIDROELÉCTRICA | FP8: HIDROELÉCTRICA | FQ8: TERMOELÉCTRICA | FR8: TERMOELÉCTRICA | FS8: HIDROELÉCTRICA | FT8: HIDROELÉCTRICA
C9: HYDRO GLOBAL PERÚ S.A.C. | D9: ELECTROPERU | E9: ELECTROPERU | F9: ELECTROPERU | G9: ELECTROPERU | H9: ORAZUL ENERGY PERÚ | I9: ORAZUL ENERGY PERÚ | J9: TERMOSELVA | K9: TERMOSELVA | L9: KALLPA GENERACION S.A. | M9: KALLPA GENERACION S.A. | N9: KALLPA GENERACION S.A. | O9: KALLPA GENERACION S.A. | P9: KALLPA GENERACION S.A. | Q9: KALLPA GENERACION S.A. | R9: KALLPA GENERACION S.A. | S9: KALLPA GENERACION S.A. | T9: SHOUGESA | U9: SHOUGESA | V9: SHOUGESA | W9: SHOUGESA | X9: EGEMSA | Y9: EGESUR | Z9: EGESUR | AA9: EGESUR | AB9: EGASA | AC9: EGASA | AD9: EGASA | AE9: EGASA | AF9: EGASA | AG9: EGASA | AH9: EGASA | AI9: SAN GABAN | AJ9: CELEPSA | AK9: MINERA CERRO VERDE | AL9: PLANTA DE RESERVA FRIA DE GENERACION DE ETEN S.A. | AM9: PLANTA DE RESERVA FRIA DE GENERACION DE ETEN S.A. | AN9: EMPRESA DE GENERACION HUALLAGA | AO9: EMPRESA DE GENERACION HUALLAGA | AP9: LA VIRGEN | AQ9: CHINANGO S.A.C. | AR9: CHINANGO S.A.C. | AS9: HIDROELECTRICA HUANCHOR S.A.C. | AT9: CELEPSA RENOVABLES S.R.L. | AU9: INLAND ENERGY SAC | AV9: FENIX POWER PERÚ | AW9: FENIX POWER PERÚ | AX9: FENIX POWER PERÚ | AY9: STATKRAFT S.A | AZ9: STATKRAFT S.A | BA9: STATKRAFT S.A | BB9: STATKRAFT S.A | BC9: STATKRAFT S.A | BD9: STATKRAFT S.A | BE9: STATKRAFT S.A | BF9: STATKRAFT S.A | BG9: CENTRALES SANTA ROSA S.A.C. | BH9: CENTRALES SANTA ROSA S.A.C. | BI9: EMPRESA DE GENERACION HUANZA | BJ9: ENEL GENERACION PIURA S.A. | BK9: ENEL GENERACION PIURA S.A. | BL9: ENEL GENERACION PIURA S.A. | BM9: ENGIE ENERGIA PERU S.A.A. | BN9: ENGIE ENERGIA PERU S.A.A. | BO9: ENGIE ENERGIA PERU S.A.A. | BP9: ENGIE ENERGIA PERU S.A.A. | BQ9: ENGIE ENERGIA PERU S.A.A. | BR9: ENGIE ENERGIA PERU S.A.A. | BS9: ENGIE ENERGIA PERU S.A.A. | BT9: ENGIE ENERGIA PERU S.A.A. | BU9: ENGIE ENERGIA PERU S.A.A. | BV9: ENGIE ENERGIA PERU S.A.A. | BW9: ENGIE ENERGIA PERU S.A.A. | BX9: ENGIE ENERGIA PERU S.A.A. | BY9: ENGIE ENERGIA PERU S.A.A. | BZ9: ENGIE ENERGIA PERU S.A.A. | CA9: INFRAESTRUCTURAS Y ENERGIAS DEL PERU S.A.C. | CB9: INFRAESTRUCTURAS Y ENERGIAS DEL PERU S.A.C. | CC9: INVERSIONES SHAQSHA S.A.C. | CD9: ORYGEN PERU S.A.A. | CE9: ORYGEN PERU S.A.A. | CF9: ORYGEN PERU S.A.A. | CG9: ORYGEN PERU S.A.A. | CH9: ORYGEN PERU S.A.A. | CI9: ORYGEN PERU S.A.A. | CJ9: ORYGEN PERU S.A.A. | CK9: ORYGEN PERU S.A.A. | CL9: ORYGEN PERU S.A.A. | CM9: ORYGEN PERU S.A.A. | CN9: ORYGEN PERU S.A.A. | CO9: ORYGEN PERU S.A.A. | CP9: SAMAY I S.A.C | CQ9: SAMAY I S.A.C | CR9: SAMAY I S.A.C | CS9: SAMAY I S.A.C | CT9: TERMOCHILCA S.A.C. | CU9: TERMOCHILCA S.A.C. | CV9: COLCA SOLAR S.A.C. | CW9: ENERGIA RENOVABLE DEL SUR S.A. | CX9: GR CORTARRAMA SOCIEDAD ANONIMA CERRADA | CY9: GR TARUCA SOCIEDAD ANONIMA CERRADA | CZ9: KONDU SAC | DA9: PERUANA DE INVERSIONES EN ENERGIAS RENOVABLES S.A. | DB9: VARI ENERGIA S.A.C. | DC9: ORAZUL ENERGY PERÚ | DD9: ORAZUL ENERGY PERÚ | DE9: KALLPA GENERACION S.A. | DF9: SAN GABAN | DG9: MAJA ENERGIA S.A.C. | DH9: EMPRESA DE GENERACION ELECTRICA CANCHAYLLO SAC | DI9: EMPRESA DE GENERACION ELECTRICA SANTA ANA S.A.C. | DJ9: EMPRESA ELECTRICA AGUA AZUL | DK9: EMPRESA ELECTRICA RIO DOBLE | DL9: HIDROCAÑETE S.A. | DM9: HUAURA POWER GROUP S.A. | DN9: MOQUEGUA FV S.A.C. | DO9: PANAMERICANA SOLAR SAC. | DP9: PARQUE EOLICO MARCONA S.A.C. | DQ9: PARQUE EOLICO TRES HERMANAS S.A.C. | DR9: TACNA SOLAR SAC. | DS9: ELECTRICA YANAPAMPA SAC | DT9: ANDEAN POWER S.A.C. | DU9: ASOCIACIÓN SANTA LUCIA DE CHACAS | DV9: ATRIA ENERGIA S.A.C. | DW9: EGEJUNIN | DX9: EGEJUNIN | DY9: EGEJUNIN | DZ9: EGEJUNIN | EA9: EMPRESA DE GENERACION ELECTRICA RIO BAÑOS S.A.C. | EB9: ENERGÍA EÓLICA S.A. | EC9: ENERGÍA EÓLICA S.A. | ED9: ENGIE ENERGIA PERU S.A.A. | EE9: ENGIE ENERGIA PERU S.A.A. | EF9: ENGIE ENERGIA PERU S.A.A. | EG9: ENGIE ENERGIA PERU S.A.A. | EH9: ENGIE ENERGIA PERU S.A.A. | EI9: GENERACIÓN ANDINA S.A.C. | EJ9: GENERACIÓN ANDINA S.A.C. | EK9: GENERADORA DE ENERGÍA DEL PERÚ | EL9: GENERADORA DE ENERGÍA DEL PERÚ | EM9: GENERADORA DE ENERGÍA DEL PERÚ | EN9: GENERADORA DE ENERGÍA DEL PERÚ | EO9: GR PAINO SOCIEDAD ANONIMA CERRADA | EP9: JOYA SOLAR S.A.C. | EQ9: MAJES ARCUS S.A.C. | ER9: ORYGEN PERU S.A.A. | ES9: ORYGEN PERU S.A.A. | ET9: ORYGEN PERU S.A.A. | EU9: ORYGEN PERU S.A.A. | EV9: ORYGEN PERU S.A.A. | EW9: PETRAMAS | EX9: PETRAMAS | EY9: PETRAMAS | EZ9: PETRAMAS | FA9: REPARTICIÓN ARCUS S.A.C. | FB9: SINERSA | FC9: SINERSA | FD9: BIOENERGIA DEL CHIRA S.A. | FE9: GM OPERACIONES S.A.C. | FF9: GM OPERACIONES S.A.C. | FG9: AGRO INDUSTRIAL PARAMONGA S.A. | FH9: AGROAURORA S.A.C. | FI9: AGROINDUSTRIAS SAN JACINTO S.A.A. | FJ9: AGROLMOS SOCIEDAD ANONIMA - AGROLMOS S.A. | FM9: UNACEM PERU S.A. | FN9: ELECTRO ORIENTE | FO9: AGUAS Y ENERGIA PERU | FP9: ELECTRO ZAÑA S.A.C. | FQ9: ELECTRONOROESTE S.A. | FR9: SDE PIURA | FS9: SINERSA | FT9: SINERSA
C10: SAN GABAN III | D10: MANTARO | E10: RESTITUCION | F10: TUMBES MAK 1 | G10: TUMBES MAK 2 | H10: CARHUAQUERO | I10: CAÑON DEL PATO | J10: AGUAYTIA TG1 | K10: AGUAYTIA TG2 | L10: KALLPA TG1 | M10: KALLPA TG2 | N10: KALLPA TG3 | O10: KALLPA TV | P10: LFLORES TG1 | Q10: LFLORES TV | R10: CERRO DEL AGUILA | S10: CERRODELAGUILAG4 | T10: SHOUGESA TV1 | U10: SHOUGESA TV2 | V10: SHOUGESA TV3 | W10: SHOUGESA CUMMINS | X10: MACHUPICCHU | Y10: ARICOTA 1 | Z10: ARICOTA 2 | AA10: INDEPENDENCIA | AB10: CHARCANI I,II,III | AC10: CHARCANI IV | AD10: CHARCANI V | AE10: CHARCANI VI | AF10: CHILINA TG | AG10: MOLLENDO 1, 2, 3 | AH10: CHILINA (SULZ 1,2) | AI10: SAN GABAN II | AJ10: PLATANAL | AK10: RECKA | AL10: RF ETEN TG1 | AM10: RF ETEN TG2 | AN10: CHAGLLA GP1 | AO10: CHAGLLA | AP10: LA VIRGEN | AQ10: CHIMAY | AR10: YANANGO | AS10: HUANCHOR | AT10: MARAÑON | AU10: STA TERESA | AV10: FENIX GT11 | AW10: FENIX GT12 | AX10: FENIX TV10 | AY10: YAUPI | AZ10: OROYA | BA10: PACHACHACA | BB10: MALPASO | BC10: CAHUA | BD10: ARCATA | BE10: GALLITO CIEGO | BF10: CHEVES | BG10: SANTA ROSA 1 | BH10: SANTA ROSA 2 | BI10: HUANZA | BJ10: MALACAS2 TG4 | BK10: MALACAS3 TG 5 | BL10: MALACAS1 TG6 | BM10: RF ILO2 TG1 | BN10: RF ILO2 TG2 | BO10: RF ILO2 TG3 | BP10: YUNCAN | BQ10: CHILCA1 TG1 | BR10: CHILCA1 TG2 | BS10: CHILCA1 TG3 | BT10: CHILCA-TV | BU10: CHILCA2 TG41 | BV10: CHILCA2-TV | BW10: CTNEPI_TG41 | BX10: CTNEPI_TG42 | BY10: CTNEPI_TG43 | BZ10: QUITARACSA | CA10: RF PTO MALDONADO | CB10: RF PUCALLPA | CC10: PARIAC | CD10: HUINCO | CE10: MATUCANA | CF10: MOYOPAMPA | CG10: CALLAHUANCA | CH10: HUAMPANI | CI10: STA ROSA WEST TG7 | CJ10: UTI_5 | CK10: UTI_6 | CL10: VENTANILLA 3 | CM10: VENTANILLA 4 | CN10: VENTANILLA TV | CO10: STAROSA TG8 | CP10: PTO_BRVO TG1 | CQ10: PTO_BRVO TG2 | CR10: PTO_BRVO TG3 | CS10: PTO_BRVO TG4 | CT10: OLLEROS TG1 | CU10: OLLEROS TV | CV10: CS YARUCAYA | CW10: SAN JUAN | CX10: MATARANI | CY10: DUNA | CZ10: CARHUAQUERO (CS) | DA10: MANTA I | DB10: ANASHIRONI | DC10: CARHUAQUERO4 | DD10: CAÑA BRAVA | DE10: SUNNY | DF10: TUPURI | DG10: RONCADOR | DH10: CANCHAYLLO | DI10: RENOVANDESH1 | DJ10: POTRERO | DK10: PIZARRAS | DL10: NIMPERIAL | DM10: YARUCAYA | DN10: MOQUEGUA-SOLAR | DO10: PANAMERICANA-SOLAR | DP10: PQE-EOLICO-MARCONA | DQ10: PQE-EOLICO-3-HERMANAS | DR10: TACNA-SOLAR | DS10: YANAPAMPA | DT10: CARHUAC | DU10: HUALLIN | DV10: PURMACANA | DW10: HUASAHUASI | DX10: STACRUZ_1_2 | DY10: RUNATULLO_II | DZ10: RUNATULLO_III | EA10: RUCUY | EB10: PQE-EOLICO-TALARA | EC10: PQE-EOLICO-CUPISNIQUE | ED10: INTIPAMPA | EE10: PUNTA LOMITAS-BL1 | EF10: PUNTA LOMITAS-BL2 | EG10: PUN LOMITAS_EXP-BL1 | EH10: PUN LOMITAS_EXP-BL2 | EI10: 8AGOSTO | EJ10: EL CARMEN | EK10: LA JOYA | EL10: ANGEL_I | EM10: ANGEL_II | EN10: ANGEL_III | EO10: HUAMBOS | EP10: SAN MARTIN SOLAR | EQ10: MAJES | ER10: RUBI | ES10: CH_HER1 | ET10: WAYRA-I | EU10: WAYRA EXTENSION | EV10: CLEMESI | EW10: HUAYCOLORO | EX10: CALLAO | EY10: DONA_CATALINA | EZ10: LAGRINGAV | FA10: REPARTICION | FB10: POECHOS2 | FC10: CHANCAY | FD10: CANA BRAVA | FE10: REFINERIA TALARA TV1 | FF10: REFINERÍA TALARA TV2 | FG10: PARAMONGA | FH10: MAPLE | FI10: SAN_JACINTO | FJ10: AGROLMOS | FK10: MVAR | FM10: CARPAPATA | FN10: CENTRALES ELOR | FO10: PIAS1 | FP10: ZANA | FQ10: TABLAZO | FR10: TALLANCA | FS10: CURUMUY | FT10: POECHOS1 | FU10: MVAR
A11: 19/10/2025 | B11: 00:30 | C11: 31 | D11: 5.1 | E11: 10.4 | H11: -10.7 | I11: 0.4 | L11: -38.8 | M11: -32.8 | N11: -13.5 | O11: 8.7 | P11: 2.2 | Q11: 12.2 | R11: 59.4 | S11: 0.1 | X11: 3.9 | Y11: 0.2 | Z11: 0.7 | AB11: -3.4 | AC11: 5 | AD11: 3 | AI11: 11.1 | AJ11: 3.4 | AK11: 0 | AN11: -1.5 | AO11: 5.2 | AP11: 2 | AQ11: 13.7 | AR11: 2.1 | AS11: 0 | AT11: 1.7 | AU11: 1.2 | AV11: 1.1 | AW11: -42.2 | AX11: -47.8 | AY11: 7.1 | AZ11: -1.8 | BA11: -0.1 | BB11: -0.3 | BC11: -0.4 | BD11: 0.4 | BE11: 0.1 | BF11: 0.3 | BI11: -4 | BJ11: 0 | BP11: 1 | BS11: 19.7 | BT11: -49 | CC11: 0.1 | CD11: 0.5 | CF11: -0.7 | CG11: 0.2 | CH11: -4 | CL11: -11.7 | CM11: -7.5 | CN11: -33.6 | CW11: -5.3 | CX11: 0 | CY11: -4.2 | DA11: 1.3 | DB11: 0 | DC11: 0 | DD11: 0 | DE11: 0 | DG11: 0 | DH11: 1.2 | DI11: 0.2 | DJ11: -0.8 | DK11: 0.1 | DL11: 0.6 | DM11: 0 | DN11: 0 | DO11: 0 | DP11: 1.5 | DQ11: 10.2 | DR11: 0 | DS11: -0.1 | DT11: -0.1 | DU11: 1 | DW11: -2.8 | DX11: 0.1 | DY11: 2.6 | DZ11: 2.5 | EA11: 0.9 | EB11: 0 | EC11: 1 | ED11: 0 | EE11: -4.8 | EF11: -5.3 | EG11: -0.4 | EH11: -0.3 | EI11: 1.5 | EJ11: -0.1 | EK11: 1.4 | EL11: 0.2 | EM11: 0.2 | EN11: 0.2 | EO11: -3.7 | EP11: 0 | EQ11: 0 | ER11: 0 | ES11: -0.2 | ET11: -6 | EU11: 0 | EV11: 0 | EW11: 1 | EX11: 0.7 | EY11: 0.6 | EZ11: 0.3 | FA11: 0 | FB11: 0.4 | FC11: 1.1 | FD11: 2.4 | FE11: 7.5 | FF11: 0.1 | FG11: 2.6 | FH11: 0 | FI11: 3.7 | FJ11: 4.9 | FK11: -72.7 | FM11: 1.7 | FN11: 0.398 | FO11: 1.108 | FP11: 0.8 | FQ11: 0.32319 | FR11: 0.15628 | FS11: 0.2 | FT11: 0.7 | FU11: 5.38547
A12: 19/10/2025 | B12: 01:00 | C12: 32.1 | D12: -7 | E12: 7.5 | H12: -10.6 | I12: 10.1 | L12: -39.5 | M12: -42 | N12: -23 | O12: 12.5 | P12: -0.7 | Q12: 10.6 | R12: 56.8 | S12: -0.2 | X12: 2.1 | Y12: 0.8 | Z12: 1.2 | AB12: -3.4 | AC12: 4.8 | AD12: 2.7 | AI12: 10.4 | AJ12: 2.3 | AK12: 0 | AN12: -1.6 | AO12: -11.9 | AP12: 1.4 | AQ12: 13.9 | AR12: 2.2 | AS12: 0.2 | AT12: 1.7 | AU12: 1.3 | AV12: 0.3 | AW12: -42.9 | AX12: -43.8 | AY12: 4.8 | AZ12: -1.9 | BA12: -0.2 | BB12: -3.5 | BC12: -1 | BD12: 0.4 | BE12: 0.1 | BF12: -4.2 | BI12: -4.5 | BJ12: 0 | BP12: -1.7 | BS12: 13.3 | BT12: -50 | CC12: 0.1 | CD12: 1.5 | CF12: 0 | CG12: 0.2 | CH12: -4.1 | CL12: -11.5 | CM12: -7.4 | CN12: -33.7 | CW12: -6.2 | CX12: 0 | CY12: -4.2 | DA12: 1.3 | DB12: 0.1 | DC12: 0 | DD12: 0 | DE12: 0 | DG12: 0 | DH12: 1.2 | DI12: 0.2 | DJ12: -1 | DK12: 0.1 | DL12: 0.6 | DM12: 0 | DN12: 0 | DO12: 0 | DP12: 1.4 | DQ12: 10.4 | DR12: 0 | DS12: -0.1 | DT12: 0.4 | DU12: 1 | DW12: -2.8 | DX12: 0.1 | DY12: 2.6 | DZ12: 2.4 | EA12: 0.9 | EB12: 0 | EC12: 2.4 | ED12: 0 | EE12: -6.3 | EF12: -7 | EG12: -0.8 | EH12: -0.6 | EI12: 1.5 | EJ12: -0.1 | EK12: 1.4 | EL12: 0.2 | EM12: 0.2 | EN12: 0.2 | EO12: -3.7 | EP12: 0 | EQ12: 0 | ER12: 0 | ES12: -0.2 | ET12: -6 | EU12: 0 | EV12: 0 | EW12: 1 | EX12: 0.7 | EY12: 0.6 | EZ12: 0.3 | FA12: 0 | FB12: 0.4 | FC12: 1.2 | FD12: 2.5 | FE12: 7.8 | FF12: 0.3 | FG12: 1.2 | FH12: 0 | FI12: 3 | FJ12: 4.9 | FK12: -141.5 | FM12: 1.5 | FN12: 0.393 | FO12: 0.976 | FP12: 0.79 | FQ12: 0.31124 | FR12: 0.16527 | FS12: 0.3 | FT12: 0.9 | FU12: 5.33551
A13: 19/10/2025 | B13: 01:30 | C13: 30.5 | D13: -5.1 | E13: 8.8 | H13: -9.5 | I13: 16.1 | L13: -41.1 | M13: -33.8 | N13: -12.8 | O13: 7.5 | P13: -9.7 | Q13: 3.5 | R13: 54.8 | S13: 0.1 | X13: 1.5 | Y13: 0.7 | Z13: 1.2 | AB13: -3.4 | AC13: 5 | AD13: 1.5 | AI13: 10.8 | AJ13: 1 | AK13: 0 | AN13: -1.7 | AO13: -13.1 | AP13: 1.2 | AQ13: 13.5 | AR13: 2.1 | AS13: -0.2 | AT13: 1.7 | AU13: 0.5 | AV13: -40.2 | AW13: -41.7 | AX13: -47.2 | AY13: 8 | AZ13: -1.9 | BA13: -0.2 | BB13: -0.4 | BC13: 1 | BD13: 0.4 | BE13: 0 | BF13: 2.6 | BI13: -5.3 | BJ13: 0 | BP13: -0.6 | BS13: -2.8 | BT13: 0 | CC13: 0.1 | CD13: 0.1 | CF13: -1.4 | CG13: 1.6 | CH13: -4.2 | CL13: -14.7 | CM13: -10.6 | CN13: -38.2 | CW13: -6.4 | CX13: 0 | CY13: -4 | DA13: 1.3 | DB13: 0.1 | DC13: -0.1 | DD13: 0 | DE13: 0 | DG13: 0 | DH13: 1.1 | DI13: 0.2 | DJ13: -1 | DK13: 0.1 | DL13: 0.6 | DM13: 0 | DN13: 0 | DO13: 0 | DP13: 1.3 | DQ13: 9.5 | DR13: 0 | DS13: 0 | DT13: 0.4 | DU13: 1 | DW13: -2.8 | DX13: 0.1 | DY13: 2.4 | DZ13: 2.4 | EA13: 1 | EB13: 0 | EC13: 3.7 | ED13: 0 | EE13: -7.4 | EF13: -8.7 | EG13: -0.9 | EH13: -0.8 | EI13: 1.5 | EJ13: 0 | EK13: 1.6 | EL13: 0.2 | EM13: 0.2 | EN13: 0.2 | EO13: -5.5 | EP13: 0 | EQ13: 0 | ER13: 0 | ES13: -0.2 | ET13: -7.5 | EU13: 0 | EV13: 0 | EW13: 1 | EX13: 0.7 | EY13: 0.6 | EZ13: 0.3 | FA13: 0 | FB13: 0.4 | FC13: 1.3 | FD13: 2.5 | FE13: 7.7 | FF13: 0.2 | FG13: 2.4 | FH13: 0 | FI13: 4.3 | FJ13: 4.9 | FK13: -154.1 | FM13: 1.4 | FN13: 0.249 | FO13: 1.176 | FP13: 0.89 | FQ13: 0.30705 | FR13: 0.14269 | FS13: 0.2 | FT13: 0.7 | FU13: 5.06474
A14: 19/10/2025 | B14: 02:00 | C14: 35.2 | D14: -9.8 | E14: 7 | H14: -10.3 | I14: 14.2 | L14: -48.1 | M14: -46 | N14: -25.3 | O14: -0.2 | P14: -18.2 | Q14: -1.9 | R14: 49.7 | S14: 0.1 | X14: 5.3 | Y14: 1 | Z14: 1.4 | AB14: -3.4 | AC14: 5.8 | AD14: 11.6 | AI14: 12.1 | AJ14: -0.5 | AK14: 0 | AN14: -0.9 | AO14: -10.7 | AP14: 1.4 | AQ14: 14.1 | AR14: 2 | AS14: -0.1 | AT14: 1.7 | AU14: 1.1 | AV14: -43.1 | AW14: -43.2 | AX14: -50 | AY14: 7.5 | AZ14: -1.9 | BA14: -0.3 | BB14: -1.3 | BC14: 0.6 | BD14: 0.4 | BE14: 0.1 | BF14: 0.9 | BI14: -1 | BJ14: 0 | BP14: 0.7 | BS14: 0 | BT14: 0 | CC14: 0.1 | CD14: 0.6 | CF14: -0.5 | CG14: 0.2 | CH14: -3.9 | CL14: -6.1 | CM14: -2.1 | CN14: -25.4 | CW14: -3 | CX14: 0 | CY14: -4 | DA14: 1.3 | DB14: 0 | DC14: -0.1 | DD14: 0 | DE14: 0 | DG14: 0 | DH14: 1.1 | DI14: 0.2 | DJ14: -0.4 | DK14: 0 | DL14: 0.6 | DM14: 0 | DN14: 0 | DO14: 0 | DP14: 1.6 | DQ14: 10.5 | DR14: 0 | DS14: 0.1 | DT14: 0.4 | DU14: 1 | DW14: -2.8 | DX14: 0.2 | DY14: 2.4 | DZ14: 2.4 | EA14: 1.1 | EB14: 0 | EC14: 4.4 | ED14: 0 | EE14: -9.4 | EF14: -9.7 | EG14: -1.1 | EH14: -0.8 | EI14: 1.5 | EJ14: 0 | EK14: 1.5 | EL14: 0.2 | EM14: 0.2 | EN14: 0.2 | EO14: -5.4 | EP14: 0 | EQ14: 0 | ER14: 0 | ES14: -0.2 | ET14: -5.6 | EU14: 0.3 | EV14: 0 | EW14: 1 | EX14: 0.7 | EY14: 0.6 | EZ14: 0.3 | FA14: 0 | FB14: 0.4 | FC14: 1.4 | FD14: 2.5 | FE14: 7.6 | FF14: 0.5 | FG14: 3.5 | FH14: 0 | FI14: 3.4 | FJ14: 4.9 | FK14: -163.9 | FM14: 1.4 | FN14: 0.389 | FO14: 1.4 | FP14: 0.89 | FQ14: 0.3044 | FR14: 0.20133 | FS14: 0.2 | FT14: 0.8 | FU14: 5.58473
A15: 19/10/2025 | B15: 02:30 | C15: 32.2 | D15: -3.6 | E15: 9.3 | H15: -11.4 | I15: 12.4 | L15: -42.6 | M15: -39.2 | N15: -18 | O15: 6.5 | P15: -19.9 | Q15: -24.5 | R15: 59 | S15: 0.1 | X15: 4.2 | Y15: 1.2 | Z15: 1.5 | AB15: -3.4 | AC15: 5.5 | AD15: 10.5 | AI15: 11.3 | AJ15: 1.4 | AK15: 0 | AN15: -1 | AO15: -10.4 | AP15: 1.6 | AQ15: 12.3 | AR15: 2.5 | AS15: 0.2 | AT15: 1.7 | AU15: 1.4 | AV15: -34 | AW15: -34.5 | AX15: -40.9 | AY15: 9.9 | AZ15: -1.9 | BA15: 0 | BB15: -0.5 | BC15: 2.1 | BD15: 0.4 | BE15: 0.1 | BF15: 2.4 | BI15: 0.3 | BJ15: 0 | BP15: 0 | BS15: 0 | BT15: 0 | CC15: 0.1 | CD15: 1.1 | CF15: -1.7 | CG15: 0.2 | CH15: -4 | CL15: -7.6 | CM15: -2.8 | CN15: -18.7 | CW15: -2.1 | CX15: 0 | CY15: -4.2 | DA15: 1.3 | DB15: 0 | DC15: 0 | DD15: 0 | DE15: 0 | DG15: 0 | DH15: 1.2 | DI15: 0.3 | DJ15: -0.6 | DK15: 0 | DL15: 0.6 | DM15: 0 | DN15: 0 | DO15: 0 | DP15: 1.7 | DQ15: 11 | DR15: 0 | DS15: 0.2 | DT15: 0.4 | DU15: 1 | DW15: -2.8 | DX15: 0 | DY15: 2.4 | DZ15: 2.4 | EA15: 1.3 | EB15: 0 | EC15: 1.5 | ED15: 0 | EE15: -7.3 | EF15: -7.9 | EG15: -0.7 | EH15: -0.5 | EI15: 1.5 | EJ15: 0 | EK15: 1.6 | EL15: 0.2 | EM15: 0.2 | EN15: 0.2 | EO15: -5.6 | EP15: 0 | EQ15: 0 | ER15: 0 | ES15: -0.2 | ET15: -5.1 | EU15: 0 | EV15: 0 | EW15: 1 | EX15: 0.7 | EY15: 0.6 | EZ15: 0.3 | FA15: 0 | FB15: 0.4 | FC15: 1.6 | FD15: 2.5 | FE15: 7.8 | FF15: 0.3 | FG15: 1.3 | FH15: 0 | FI15: 3.5 | FJ15: 4.9 | FK15: -112.3 | FM15: 1.4 | FN15: 0.535 | FO15: 1.5 | FP15: 0.89 | FQ15: 0.29963 | FR15: 0.19577 | FS15: 0.2 | FT15: 0.8 | FU15: 5.8204
A16: 19/10/2025 | B16: 03:00 | C16: 33.8 | D16: -4 | E16: 9.2 | H16: -10.8 | I16: 13.1 | L16: -45 | M16: -39.8 | N16: -18.8 | O16: 6 | P16: -13.6 | Q16: -26.8 | R16: 58.4 | S16: 0 | X16: 3.9 | Y16: 0.5 | Z16: 1.2 | AB16: -3.4 | AC16: 5.5 | AD16: 11.1 | AI16: 11.4 | AJ16: 0.8 | AK16: 0 | AN16: -1 | AO16: -9.7 | AP16: 1.7 | AQ16: 13.2 | AR16: 2.2 | AS16: 0.2 | AT16: 1.7 | AU16: 0.6 | AV16: -37.9 | AW16: -38.2 | AX16: -44 | AY16: 8.6 | AZ16: -1.7 | BA16: 0 | BB16: -2.1 | BC16: 1.2 | BD16: 0.4 | BE16: 0 | BF16: -1.5 | BI16: 0.2 | BJ16: 0 | BP16: -0.3 | BS16: 0 | BT16: 0 | CC16: 0.1 | CD16: 0.8 | CF16: -0.8 | CG16: 0.2 | CH16: -4 | CL16: -8.2 | CM16: -3.4 | CN16: -19.3 | CW16: -2.4 | CX16: 0 | CY16: -4.2 | DA16: 1.3 | DB16: 0 | DC16: -0.1 | DD16: 0 | DE16: 0 | DG16: 0 | DH16: 1.2 | DI16: 0.2 | DJ16: -1 | DK16: 0 | DL16: 0.6 | DM16: 0 | DN16: 0 | DO16: 0 | DP16: 1.8 | DQ16: 11.3 | DR16: 0 | DS16: 0.2 | DT16: 0.4 | DU16: 0.9 | DW16: -2.9 | DX16: 0.3 | DY16: 2.4 | DZ16: 2.5 | EA16: 1.3 | EB16: 0 | EC16: 1.5 | ED16: 0 | EE16: -6.1 | EF16: -6.1 | EG16: -0.5 | EH16: -0.3 | EI16: 1.5 | EJ16: 0 | EK16: 1.5 | EL16: 0.2 | EM16: 0.2 | EN16: 0.2 | EO16: -5.6 | EP16: 0 | EQ16: 0 | ER16: 0 | ES16: -0.2 | ET16: -4.8 | EU16: 0 | EV16: 0 | EW16: 1 | EX16: 0.7 | EY16: 0.6 | EZ16: 0.3 | FA16: 0 | FB16: 0.4 | FC16: 1.6 | FD16: 2.5 | FE16: 7.8 | FF16: 0.3 | FG16: 1.1 | FH16: 0 | FI16: 3.3 | FJ16: 4.9 | FK16: -128.5 | FM16: 1.5 | FN16: 0.447 | FO16: 1.616 | FP16: 0.89 | FQ16: 0.30919 | FR16: 0.17508 | FS16: 0.1 | FT16: 0.7 | FU16: 5.73727
A17: 19/10/2025 | B17: 03:30 | C17: 32.1 | D17: -8 | E17: 6.9 | H17: -10.4 | I17: 1.7 | L17: -46.2 | M17: -46.6 | N17: -26.1 | O17: 1 | P17: -16.4 | Q17: -28.6 | R17: 51.4 | S17: -0.1 | X17: 3.2 | Y17: 0.8 | Z17: 1.3 | AB17: -3.4 | AC17: 5.4 | AD17: 10.5 | AI17: 10.6 | AJ17: 0 | AK17: 0 | AN17: -1.1 | AO17: -11.5 | AP17: 1.8 | AQ17: 14.2 | AR17: 2.2 | AS17: 0.2 | AT17: 1.7 | AU17: 1.5 | AV17: -41.1 | AW17: -41.7 | AX17: -47.2 | AY17: 5.8 | AZ17: -1.8 | BA17: 0 | BB17: -1.3 | BC17: 0.6 | BD17: 0.4 | BE17: 0 | BF17: -0.6 | BI17: -0.8 | BJ17: 0 | BP17: 0.3 | BS17: 0 | BT17: 0 | CC17: 0.1 | CD17: 1.1 | CF17: 0.2 | CG17: 0.2 | CH17: -4.1 | CL17: -11.1 | CM17: -6.5 | CN17: -24.1 | CW17: -2 | CX17: 0 | CY17: -4.1 | DA17: 1.3 | DB17: 0 | DC17: -0.1 | DD17: 0 | DE17: 0 | DG17: 0 | DH17: 1.2 | DI17: 0.2 | DJ17: -1 | DK17: 0 | DL17: 0.6 | DM17: 0 | DN17: 0 | DO17: 0 | DP17: 1.9 | DQ17: 11 | DR17: 0 | DS17: -0.1 | DT17: 0.3 | DU17: 0.9 | DW17: -2.9 | DX17: 0.1 | DY17: 2.4 | DZ17: 2.4 | EA17: 1.2 | EB17: 0 | EC17: 1.5 | ED17: 0 | EE17: -7.2 | EF17: -7.7 | EG17: -0.8 | EH17: -0.4 | EI17: 1.5 | EJ17: -0.1 | EK17: 1.4 | EL17: 0.2 | EM17: 0.2 | EN17: 0.2 | EO17: -5.6 | EP17: 0 | EQ17: 0 | ER17: 0 | ES17: -0.2 | ET17: -5.5 | EU17: 0 | EV17: 0 | EW17: 1 | EX17: 0.7 | EY17: 0.6 | EZ17: 0.3 | FA17: 0 | FB17: 0.4 | FC17: 1.5 | FD17: 2.3 | FE17: 10.7 | FF17: 0.2 | FG17: 0.6 | FH17: 0 | FI17: 3.7 | FJ17: 4.9 | FK17: -205.8 | FM17: 1.5 | FN17: 0.288 | FO17: 1.532 | FP17: 0.9 | FQ17: 0.30363 | FR17: 0.20343 | FS17: 0.7 | FT17: 0.8 | FU17: 6.22706
A18: 19/10/2025 | B18: 04:00 | C18: 35.1 | D18: -2.2 | E18: 7.5 | H18: -8.7 | I18: 14.1 | L18: -45.2 | M18: -45.8 | N18: -24.5 | O18: 1.5 | P18: -14.5 | Q18: -27.2 | R18: 54.9 | S18: 0 | X18: 3.7 | Y18: 1.3 | Z18: 1.7 | AB18: -3.4 | AC18: 5.4 | AD18: 11 | AI18: 11.3 | AJ18: 0 | AK18: 0 | AN18: -1.1 | AO18: -11.9 | AP18: 1.5 | AQ18: 14.6 | AR18: 1.8 | AS18: -0.1 | AT18: 1.7 | AU18: 1.1 | AV18: -39.6 | AW18: -39.8 | AX18: -45.8 | AY18: 5.1 | AZ18: -1.9 | BA18: -0.2 | BB18: -1.7 | BC18: 0.4 | BD18: 0.4 | BE18: 0 | BF18: 1 | BI18: -1.1 | BJ18: 0 | BP18: 2 | BS18: 0 | BT18: 0 | CC18: 0.1 | CD18: -0.5 | CF18: 0.5 | CG18: 0.3 | CH18: -4.2 | CL18: -9.9 | CM18: -5.6 | CN18: -21.6 | CW18: -1.1 | CX18: 0 | CY18: -4 | DA18: 1.3 | DB18: 0.1 | DC18: -0.1 | DD18: 0 | DE18: 0 | DG18: 0.1 | DH18: 1.1 | DI18: 0.1 | DJ18: -1.2 | DK18: 0 | DL18: 0.6 | DM18: 0 | DN18: 0 | DO18: 0 | DP18: 2.1 | DQ18: 11.8 | DR18: 0 | DS18: 0.1 | DT18: 0.4 | DU18: 0.9 | DW18: -2.9 | DX18: 0.9 | DY18: 2.4 | DZ18: 2.5 | EA18: 1.1 | EB18: 0 | EC18: 1.5 | ED18: 0 | EE18: -6.5 | EF18: -7.1 | EG18: -0.6 | EH18: -0.3 | EI18: 1.5 | EJ18: 0 | EK18: 1.5 | EL18: 0.2 | EM18: 0.2 | EN18: 0.2 | EO18: -5.6 | EP18: 0 | EQ18: 0 | ER18: 0 | ES18: -0.2 | ET18: -3.7 | EU18: 0 | EV18: 0 | EW18: 1 | EX18: 0.7 | EY18: 0.6 | EZ18: 0.3 | FA18: 0 | FB18: 0.4 | FC18: 1.4 | FD18: 2.1 | FE18: 10.9 | FF18: 0.1 | FG18: 0.6 | FH18: 0 | FI18: 3.4 | FJ18: 4.9 | FK18: -154.8 | FM18: 1.4 | FN18: 0.294 | FO18: 1.38 | FP18: 0.89 | FQ18: 0.30362 | FR18: 0.11179 | FS18: 0.7 | FT18: 0.8 | FU18: 5.87941
A19: 19/10/2025 | B19: 04:30 | C19: 31.6 | D19: -13.2 | E19: 6.3 | H19: -9.6 | I19: 2.4 | L19: -47.5 | M19: -47.6 | N19: -27.2 | O19: 0 | P19: -17.2 | Q19: -28.5 | R19: 49.3 | S19: 0 | X19: 2.4 | Y19: 0.6 | Z19: 1.2 | AB19: -3.4 | AC19: 5.4 | AD19: 10.6 | AI19: 9.8 | AJ19: 0.7 | AK19: 0 | AN19: -1.1 | AO19: -10.5 | AP19: 1.3 | AQ19: 14.4 | AR19: 1.9 | AS19: 0.1 | AT19: 1.7 | AU19: 1.3 | AV19: -45.3 | AW19: -45.3 | AX19: -50.1 | AY19: 5.7 | AZ19: -1.9 | BA19: -0.3 | BB19: -3.4 | BC19: 0 | BD19: 0.4 | BE19: 0 | BF19: -1.5 | BI19: -0.8 | BJ19: 0 | BP19: 2.3 | BS19: 0 | BT19: 0 | CC19: 0.1 | CD19: -0.1 | CF19: 0.1 | CG19: 0 | CH19: -4.2 | CL19: -11.3 | CM19: -7.3 | CN19: -23.8 | CW19: -1.1 | CX19: 0 | CY19: -4.7 | DA19: 1.3 | DB19: 0 | DC19: -0.1 | DD19: 0 | DE19: 0 | DG19: 0.2 | DH19: 1.1 | DI19: 0.2 | DJ19: -1.5 | DK19: 0 | DL19: 0.6 | DM19: 0 | DN19: 0 | DO19: 0 | DP19: 1.9 | DQ19: 11.8 | DR19: 0 | DS19: -0.1 | DT19: 0.4 | DU19: 0.9 | DW19: -2.9 | DX19: 0.3 | DY19: 2.2 | DZ19: 2.4 | EA19: 1.1 | EB19: 0 | EC19: 1.5 | ED19: 0 | EE19: -8.6 | EF19: -9.1 | EG19: -0.9 | EH19: -0.5 | EI19: 1.5 | EJ19: 0 | EK19: 1.5 | EL19: 0.2 | EM19: 0.2 | EN19: 0.2 | EO19: -6 | EP19: 0 | EQ19: 0 | ER19: 0 | ES19: -0.2 | ET19: -3.2 | EU19: 0 | EV19: 0 | EW19: 1 | EX19: 0.7 | EY19: 0.6 | EZ19: 0.3 | FA19: 0 | FB19: 0.4 | FC19: 1.4 | FD19: 2.1 | FE19: 10.7 | FF19: 0.1 | FG19: 1 | FH19: 0 | FI19: 2.9 | FJ19: 4.8 | FK19: -234.9 | FM19: 1.5 | FN19: 0.362 | FO19: 1.404 | FP19: 0.89 | FQ19: 0.30562 | FR19: 0.17952 | FS19: 0.7 | FT19: 0.8 | FU19: 6.14114
A20: 19/10/2025 | B20: 05:00 | C20: 30.5 | D20: -1.9 | E20: 8 | H20: -9.6 | I20: 2.6 | L20: -41.7 | M20: -44 | N20: -23.3 | O20: 7.3 | P20: -14.7 | Q20: -27.1 | R20: 57 | S20: -0.2 | X20: -3.1 | Y20: 0.9 | Z20: 1.5 | AB20: -3.4 | AC20: 5.4 | AD20: 10.5 | AI20: 9.6 | AJ20: 0.8 | AK20: 0 | AN20: -1.1 | AO20: -11.1 | AP20: 1.7 | AQ20: 14.8 | AR20: 1.9 | AS20: 0 | AT20: 1.7 | AU20: 1.4 | AV20: -42.9 | AW20: -43 | AX20: -47.7 | AY20: 4.5 | AZ20: -1.6 | BA20: -0.2 | BB20: -3.1 | BC20: -0.2 | BD20: 0.4 | BE20: 0 | BF20: -4 | BI20: -1.9 | BJ20: 0 | BP20: 2.3 | BS20: 0 | BT20: 0 | CC20: 0.1 | CD20: 0.6 | CF20: 1.2 | CG20: 0.1 | CH20: -4.1 | CL20: -10.2 | CM20: -5.8 | CN20: -21.8 | CW20: -0.1 | CX20: 0 | CY20: -4.8 | DA20: 1.3 | DB20: 0 | DC20: -0.1 | DD20: 0 | DE20: 10 | DG20: 0.2 | DH20: 1.1 | DI20: 0.2 | DJ20: -1.6 | DK20: 0 | DL20: 0.6 | DM20: 0 | DN20: 0 | DO20: 0 | DP20: 2.4 | DQ20: 12.5 | DR20: 0.5 | DS20: 0.2 | DT20: 0.4 | DU20: 0.9 | DW20: -2.9 | DX20: 0.1 | DY20: 2.4 | DZ20: 2.5 | EA20: 1.1 | EB20: 0 | EC20: 1.5 | ED20: 0.4 | EE20: -5.7 | EF20: -6.2 | EG20: -0.5 | EH20: -0.2 | EI20: 1.5 | EJ20: 0 | EK20: 1.3 | EL20: 0.2 | EM20: 0.2 | EN20: 0.2 | EO20: -6.1 | EP20: 0 | EQ20: 0 | ER20: 0 | ES20: -0.2 | ET20: -1.3 | EU20: 0 | EV20: 0 | EW20: 1 | EX20: 0.7 | EY20: 0.6 | EZ20: 0.3 | FA20: 0 | FB20: 0.4 | FC20: 1.4 | FD20: 2 | FE20: 10.4 | FF20: 0.4 | FG20: 1.7 | FH20: 0 | FI20: 3.6 | FJ20: 4.8 | FK20: -163.6 | FM20: 1.5 | FN20: 0.374 | FO20: 1.152 | FP20: 0.9 | FQ20: 0.30579 | FR20: 0.15051 | FS20: 0.7 | FT20: 0.8 | FU20: 5.8823
A21: 19/10/2025 | B21: 05:30 | C21: 34.1 | D21: -4.2 | E21: 8.1 | H21: -10.1 | I21: -1.4 | L21: -44.7 | M21: -47.8 | N21: -27.2 | O21: 5.1 | P21: -15.8 | Q21: -27.8 | R21: 58.9 | S21: -0.2 | X21: 4 | Y21: 0.9 | Z21: 1.5 | AB21: -3.4 | AC21: 5.2 | AD21: 9.8 | AI21: 10.1 | AJ21: 0.7 | AK21: 0 | AN21: -1.1 | AO21: -12.1 | AP21: 2.1 | AQ21: 14 | AR21: 2.4 | AS21: -0.4 | AT21: 1.7 | AU21: 1.9 | AV21: -41.6 | AW21: -41.9 | AX21: -46.9 | AY21: 5 | AZ21: -1.9 | BA21: -0.4 | BB21: -3.4 | BC21: 2.1 | BD21: 0.4 | BE21: 0 | BF21: -2.1 | BI21: -2.2 | BJ21: 0 | BP21: 1.2 | BS21: 0 | BT21: 0 | CC21: 0.1 | CD21: 2 | CF21: 0.4 | CG21: 0.2 | CH21: -4 | CL21: -10.3 | CM21: -5.9 | CN21: -23.1 | CW21: -3.8 | CX21: 0.1 | CY21: -5 | DA21: 1.3 | DB21: 0.1 | DC21: -0.1 | DD21: 0 | DE21: 10.1 | DG21: 0.2 | DH21: 1.1 | DI21: 0.2 | DJ21: -1.4 | DK21: 0 | DL21: 0.6 | DM21: 0 | DN21: -0.1 | DO21: 0 | DP21: 2 | DQ21: 12.6 | DR21: 0.3 | DS21: 0.2 | DT21: 0.6 | DU21: 0.8 | DW21: -2.9 | DX21: 0 | DY21: 2.4 | DZ21: 2.4 | EA21: 1.1 | EB21: 0 | EC21: 1.5 | ED21: 0.3 | EE21: -6.6 | EF21: -8 | EG21: -0.7 | EH21: -0.6 | EI21: 1.5 | EJ21: 0 | EK21: 1.3 | EL21: 0.2 | EM21: 0.2 | EN21: 0.2 | EO21: -6.3 | EP21: 0.9 | EQ21: 0 | ER21: 2.2 | ES21: -0.2 | ET21: -1.7 | EU21: 0 | EV21: 1.2 | EW21: 1 | EX21: 0.7 | EY21: 0.6 | EZ21: 0.3 | FA21: 0 | FB21: 0.4 | FC21: 1.4 | FD21: 2.5 | FE21: 10.4 | FF21: 0.5 | FG21: 0.5 | FH21: 0 | FI21: 3.5 | FJ21: 5 | FK21: -173 | FM21: 1.5 | FN21: 0.359 | FO21: 0.816 | FP21: 0.91 | FQ21: 0.30406 | FR21: 0.16859 | FS21: 0.7 | FT21: 0.8 | FU21: 5.55765
A22: 19/10/2025 | B22: 06:00 | C22: 32.2 | D22: -26.2 | E22: 4.4 | H22: -10.1 | I22: 3.8 | L22: -52.3 | M22: -49.9 | N22: -28.9 | O22: -6.4 | P22: -21.8 | Q22: -31.8 | R22: 41.2 | S22: 0 | X22: 10.2 | Y22: 0.3 | Z22: 0.9 | AB22: -3.5 | AC22: 4.9 | AD22: 6.7 | AI22: 9.1 | AJ22: -1.1 | AK22: 0 | AN22: -1.4 | AO22: -26.5 | AP22: 1.3 | AQ22: 13.5 | AR22: 2.1 | AS22: -0.7 | AT22: 1.7 | AU22: 0.5 | AV22: -50.7 | AW22: -50.9 | AX22: -55.8 | AY22: 3.9 | AZ22: -1.7 | BA22: -0.2 | BB22: -2 | BC22: 2.3 | BD22: 0.4 | BE22: 0 | BF22: -1.5 | BI22: -4.6 | BJ22: 0 | BP22: -4.3 | BS22: 0 | BT22: 0 | CC22: -0.2 | CD22: 1.4 | CF22: -0.6 | CG22: 0.2 | CH22: -4.2 | CL22: -19.2 | CM22: -14.8 | CN22: -35.5 | CW22: -11.4 | CX22: 0.4 | CY22: -5 | DA22: 1.3 | DB22: 0.1 | DC22: -0.1 | DD22: 0 | DE22: 10.9 | DG22: 0.2 | DH22: 1.1 | DI22: 0.2 | DJ22: -1.4 | DK22: 0 | DL22: 0.6 | DM22: 0 | DN22: -0.5 | DO22: -0.8 | DP22: 1 | DQ22: 9.1 | DR22: 0.3 | DS22: -0.2 | DT22: 0.5 | DU22: 0.8 | DW22: -3 | DX22: 0.1 | DY22: 2.5 | DZ22: 2.4 | EA22: 0.9 | EB22: 0 | EC22: 1.5 | ED22: 0 | EE22: -8.3 | EF22: -9 | EG22: -1 | EH22: -0.7 | EI22: 1.5 | EJ22: -0.1 | EK22: 1.2 | EL22: 0.2 | EM22: 0.2 | EN22: 0.2 | EO22: -6.2 | EP22: 1.1 | EQ22: 0 | ER22: 2.1 | ES22: -0.2 | ET22: -7.5 | EU22: 0 | EV22: 0.6 | EW22: 1 | EX22: 0.7 | EY22: 0.6 | EZ22: 0.3 | FA22: 0 | FB22: 0.4 | FC22: 1.2 | FD22: 2.5 | FE22: 9.9 | FF22: 0.5 | FG22: 2.3 | FH22: 0.3 | FI22: 4.2 | FJ22: 4.9 | FK22: -351.4 | FM22: 1.1 | FN22: 0.041 | FO22: 0.88 | FP22: 0.89 | FQ22: 0.30375 | FR22: 0.20905 | FS22: 0.6 | FT22: 0.8 | FU22: 4.8238
... A58: 20/10/2025 | B58: 00:00 | C58: 29.9 | D58: -22.1 | E58: 6.4 | H58: -15.9 | I58: -0.6 | L58: -55.2 | M58: -47.1 | N58: -26.7 | O58: 2.8 | P58: -21 | Q58: -30.6 | R58: 51.2 | S58: 0.2 | X58: 15.5 | Y58: 1.1 | Z58: 1.1 | AB58: -3.3 | AC58: 2.8 | AD58: 5.7 | AI58: 10.4 | AJ58: -25.9 | AK58: 0 | AN58: -1.2 | AO58: -16.3 | AP58: 3.8 | AQ58: 11 | AR58: -0.9 | AS58: -0.2 | AT58: 2.6 | AU58: 1.5 | AV58: -5.4 | AW58: -43.6 | AX58: -48.5 | AY58: 6.3 | AZ58: -1.9 | BA58: -0.2 | BB58: -0.2 | BC58: 0 | BD58: 0.4 | BE58: 0.1 | BF58: 2.8 | BI58: -2.9 | BJ58: -9.5 | BP58: -0.5 | BS58: 0 | BT58: 0 | CC58: 0 | CD58: 3.6 | CF58: -3 | CG58: 1.7 | CH58: -0.9 | CL58: -21.5 | CM58: -17.1 | CN58: -29.3 | CW58: -9 | CX58: 0 | CY58: -5 | DA58: 1.3 | DB58: 0 | DC58: -0.1 | DD58: -0.7 | DE58: 0 | DG58: 0.2 | DH58: 1.2 | DI58: 0.2 | DJ58: 0 | DK58: 0 | DL58: 0.6 | DM58: 0 | DN58: 0 | DO58: 0 | DP58: 0.4 | DQ58: 7.1 | DR58: 0 | DS58: 0 | DT58: 0 | DU58: 0.9 | DW58: -2.9 | DX58: -0.2 | DY58: 2.9 | DZ58: 2.8 | EA58: 0.9 | EB58: 0 | EC58: 1.5 | ED58: 0 | EE58: -12.2 | EF58: -12.5 | EG58: -1.4 | EH58: -0.7 | EI58: 1.5 | EJ58: -0.1 | EK58: 1.5 | EL58: 0.2 | EM58: 0.2 | EN58: 0.2 | EO58: -6.4 | EP58: 0 | EQ58: 0 | ER58: 0 | ES58: -0.2 | ET58: -9.4 | EU58: 0 | EV58: 0 | EW58: 1 | EX58: 0.7 | EY58: 0.6 | EZ58: 0.3 | FA58: 0 | FB58: 0.4 | FC58: 1.2 | FD58: 2.5 | FE58: 11.3 | FF58: 0.5 | FG58: 3.2 | FH58: 0 | FI58: 3.9 | FJ58: 4 | FK58: -298.2 | FM58: 2.1 | FN58: -0.116 | FO58: 1.828 | FP58: 0 | FQ58: 0.28766 | FR58: 0.11643 | FS58: -0.2 | FT58: 0.6 | FU58: 4.61609
A59: EJEC | C59: 819.5 | D59: -250.75 | E59: 191.45 | F59: 0 | G59: 0 | H59: -197.15 | I59: 237 | J59: 0 | K59: 0 | L59: -911.85 | M59: -855.85 | N59: -360 | O59: 377.3 | P59: -227.85 | Q59: -456.95 | R59: 1002.05 | S59: 0.7 | T59: 0 | U59: 0 | V59: 0 | W59: 0 | X59: 326.75 | Y59: 27.15 | Z59: 31.15 | AA59: 0 | AB59: -80.9 | AC59: 130 | AD59: 255.85 | AE59: 0 | AF59: 0 | AG59: 0 | AH59: 0 | AI59: 279.75 | AJ59: -28.6 | AK59: -12.9 | AL59: 0 | AM59: 0 | AN59: -25.6 | AO59: 52.9 | AP59: 97.85 | AQ59: 222.15 | AR59: 16.7 | AS59: -9.05 | AT59: 48.3 | AU59: 23.35 | AV59: -316.2 | AW59: -1005 | AX59: -1063.85 | AY59: 182.2 | AZ59: -41.65 | BA59: -7.35 | BB59: -19.8 | BC59: 5.45 | BD59: 9.7 | BE59: 0.15 | BF59: 56.3 | BG59: 0 | BH59: 0 | BI59: -33.9 | BJ59: -14.65 | BK59: 0 | BL59: 0 | BM59: 0 | BN59: 0 | BO59: 0 | BP59: 89.25 | BQ59: 0 | BR59: 0 | BS59: 41.05 | BT59: -49.5 | BU59: 0 | BV59: 0 | BW59: 0 | BX59: 0 | BY59: 0 | BZ59: 0 | CA59: 0 | CB59: 0 | CC59: 1.05 | CD59: 536.2 | CE59: 0 | CF59: 6.8 | CG59: 53.7 | CH59: -63.3 | CI59: 0 | CJ59: 0 | CK59: 0 | CL59: -83.25 | CM59: 11.8 | CN59: -409.3 | CO59: 0 | CP59: 0 | CQ59: 0 | CR59: 0 | CS59: 0 | CT59: 0 | CU59: 0 | CV59: 0 | CW59: -180.8 | CX59: 82.9 | CY59: -95.3 | CZ59: 0 | DA59: 31.05 | DB59: 0.65 | DC59: -1.35 | DD59: -10.65 | DE59: 420.1 | DF59: 0 | DG59: 1.35 | DH59: 33.4 | DI59: 4.2 | DJ59: 4.6 | DK59: 3.05 | DL59: 13.9 | DM59: 0.45 | DN59: -8.9 | DO59: -22.3 | DP59: 34.55 | DQ59: 239.25 | DR59: -34.85 | DS59: 0.75 | DT59: 1.75 | DU59: 17.9 | DV59: 0 | DW59: -69.65 | DX59: 3.25 | DY59: 62.6 | DZ59: 60.9 | EA59: 26.35 | EB59: 1.05 | EC59: 55.5 | ED59: 32.9 | EE59: -164.1 | EF59: -177.55 | EG59: -19.15 | EH59: -11.7 | EI59: 36 | EJ59: -1.3 | EK59: 36.3 | EL59: 4.8 | EM59: 4.8 | EN59: 4.8 | EO59: -128.1 | EP59: 42.05 | EQ59: 18.2 | ER59: 114.75 | ES59: -4.55 | ET59: -34.1 | EU59: 7.1 | EV59: -62.1 | EW59: 24 | EX59: 16.8 | EY59: 14.4 | EZ59: 7.2 | FA59: 16.6 | FB59: 9.5 | FC59: 34.25 | FD59: 57.75 | FE59: 288.35 | FF59: 6.65 | FG59: 73 | FH59: 14.15 | FI59: 84.85 | FJ59: 113.05 | FK59: -256.35 | FM59: 50.9 | FN59: 6.999 | FO59: 32.902 | FP59: 9.06 | FQ59: 7.22951 | FR59: 3.446965 | FS59: 14.1 | FT59: 35.2 | FU59: 159.83748

Sheet DEMANDA_AREAS
B3: domingo, 19 de Octubre del 2025
B5: REPORTE DE LA DEMANDA POR ÁREAS Y SUBAREAS OPERATIVAS (MW)
B6: FECHA HORA | C6: DEMANDA | E6: AREA | H6: SUBAREAS
C7: INTERCAMBIOS INTERNACIONALES | D7: SEIN | E7: NORTE | F7: CENTRO | G7: SUR | H7: ELECTROANDES
B8: 00:30 | C8: 0 | D8: 6747.1 | E8: 922.2749 | F8: 4007.8121 | G8: 1817.013 | H8: 243.6723
B9: 01:00 | C9: 0 | D9: 6617.3 | E9: 945.6773 | F9: 3862.4443 | G9: 1809.1784 | H9: 243.5229
B10: 01:30 | C10: 0 | D10: 6527.5 | E10: 941.5784 | F10: 3785.0401 | G10: 1800.8815 | H10: 243.2688
B11: 02:00 | C11: 0 | D11: 6341.2 | E11: 930.789 | F11: 3619.3148 | G11: 1791.0962 | H11: 244.0093
B12: 02:30 | C12: 0 | D12: 6399 | E12: 924.8064 | F12: 3694.334 | G12: 1779.8596 | H12: 233.5746
B13: 03:00 | C13: 0 | D13: 6319.7 | E13: 910.4834 | F13: 3643.3202 | G13: 1765.8964 | H13: 231.6259
B14: 03:30 | C14: 0 | D14: 6259.8 | E14: 872.2528 | F14: 3626.2684 | G14: 1761.2788 | H14: 234.5657
B15: 04:00 | C15: 0 | D15: 6281.8 | E15: 913.7206 | F15: 3598.7005 | G15: 1769.3789 | H15: 236.266
B16: 04:30 | C16: 0 | D16: 6170.6 | E16: 876.8431 | F16: 3508.8664 | G16: 1784.8905 | H16: 238.6866
B17: 05:00 | C17: 0 | D17: 6317.7 | E17: 876.8094 | F17: 3655.8434 | G17: 1785.0472 | H17: 239.5043
B18: 05:30 | C18: 0 | D18: 6293 | E18: 884.8689 | F18: 3633.6075 | G18: 1774.5236 | H18: 238.1111
B19: 06:00 | C19: 0 | D19: 6078.3 | E19: 923.1536 | F19: 3441.6362 | G19: 1713.5102 | H19: 220.6587
... B59: ENERGÍA | C59: 0 | D59: 160046.15 | E59: 22707.694 | F59: 93664.238 | G59: 43674.218 | H59: 5729.2302
B61: LEYENDA:
D63: Potencia recibida del Ecuador
D64: Potencia entregada al Ecuador

Sheet DEMANDA_UL
B3: domingo, 19 de Octubre del 2025
B5: POTENCIA DE LOS GRANDES USUARIOS LIBRES (MW)
B6: FECHA HORA | C6: GRANDES USUARIOS LIBRES DEL ÁREA NORTE | X6: GRANDES USUARIOS LIBRES DEL ÁREA CENTRO | BP6: GRANDES USUARIOS LIBRES DEL ÁREA SUR
C7: ARCA CONTINENTAL LINDLEY S.A. | D7: AUSTRAL GROUP S.A.A | E7: CEMENTOS PACASMAYO | F7: CONSORCIO MINERO HORIZONTE S.R.L. | G7: CORPORACIÓN PESQUERA INCA S.A.C. | H7: CREDITEX: CIA IND.TEXTIL CREDISA | I7: HIPERMERCADOS TOTTUS S.A | J7: INDUSTRIA TEXTIL PIURA | K7: MINERA BOROO MISQUICHILCA S.A. | L7: MINERA GOLD FIELDS | M7: MINERA MARSA | N7: MINERA MISKY MAYO | O7: MINERA YANACOCHA | P7: OPEN PLAZA | Q7: PESQUERA DIAMANTE | R7: PETROPERU | S7: REAL PLAZA S.R.L. | T7: SIDER PERU | U7: SUPERMERCADOS PERUANOS S.A. | V7: TRUPAL S.A. | W7: UNIÓN DE CERVECERÍAS PERUANAS BACKUS Y JOHNSTON S. | X7: ACEROS AREQUIPA | Y7: ADMINISTRADORA JOCKEY PLAZA SHOPPING CENTER S.A. | Z7: ALICORP | AA7: ARCA CONTINENTAL LINDLEY S.A. | AB7: AUSTRAL GROUP S.A.A | AC7: COMPAÑIA MINERA CONDESTABLE | AD7: CORPORACIÓN PESQUERA INCA S.A.C. | AE7: CREDITEX: CIA IND.TEXTIL CREDISA | AF7: FUNDICION CHILCA S.A. | AG7: HIPERMERCADOS TOTTUS S.A | AH7: INMOBILIARIA KANPU S.A. | AI7: INMUEBLES PANAMERICANA S.A. | AJ7: KIMBERLY-CLARK PERU | AK7: LECHE GLORIA S.A. | AL7: MALL AVENTURA S.A. | AM7: MARCOBRE S.A.C. | AN7: MINERA ANTAMINA | AO7: MINERA ARES | AP7: MINERA BUENAVENTURA | AQ7: MINERA CHINALCO PERÚ S.A. | AR7: MINERA SHOUXIN PERU S.A. | AS7: MINERA VOLCAN | AT7: MINSUR | AU7: MOLYCOP-ADESUR | AV7: NEXA RESOURCES CAJAMARQUILLA S.A. | AW7: NEXA RESOURCES PERÚ S.A.A. | AX7: OPEN PLAZA | AY7: OPP FILM | AZ7: OWENS-ILLINOIS PERÚ S.A. | BA7: PAPELERA NACIONAL S.A. | BB7: PESQUERA DIAMANTE | BC7: QUIMPAC S.A. | BD7: REAL PLAZA S.R.L. | BE7: REFINERIA LA PAMPILLA S.A.A | BF7: SAGA FALABELLA | BG7: SAN MIGUEL INDUSTRIAS PET S.A. | BH7: SHOUGANG HIERRO PERU | BI7: SOFTYS PERU S.A.C. | BJ7: SUPERMERCADOS PERUANOS S.A. | BK7: TEJIDOS SAN JACINTO | BL7: TREN URBANO DE LIMA S.A. | BM7: TRUPAL S.A. | BN7: UNACEM PERU S.A. | BO7: UNIÓN DE CERVECERÍAS PERUANAS BACKUS Y JOHNSTON S. | BP7: ANGLO AMERICAN QUELLAVECO S.A. | BQ7: ARCA CONTINENTAL LINDLEY S.A. | BR7: CAL & CEMENTO SUR S.A. | BS7: COMPAÑIA MINERA ANTAPACCAY S.A. | BT7: COMPAÑÍA MINERA CHUNGAR SAC | BU7: COMPAÑIA MINERA SAN IGNACIO DE MOROCOCHA S.A.A. | BV7: EL BROCAL .S.A. | BW7: EMPRESA ADMINISTRADORA CERRO S.A.C. | BX7: EMPRESA MINERA LOS QUENUALES S.A.C. | BY7: HIPERMERCADOS TOTTUS S.A | BZ7: HUDBAY PERU S.A.C. | CA7: INDUSTRIA CACHIMAYO | CB7: MALL AVENTURA S.A. | CC7: MINERA ARES | CD7: MINERA BUENAVENTURA | CE7: MINERA CERRO VERDE | CF7: MINERA CORONA | CG7: MINERA LAS BAMBAS S.A. | CH7: MINERA VOLCAN | CI7: MINSUR | CJ7: MOLYCOP-ADESUR | CK7: NEXA RESOURCES PERÚ S.A.A. | CL7: OXIDOS DE PASCO S.A.C. | CM7: PESQUERA DIAMANTE | CN7: REAL PLAZA S.R.L. | CO7: SOBREANDES S.A.C. | CP7: SOUTHERN PERU CC | CQ7: SUPERMERCADOS PERUANOS S.A. | CR7: UNACEM PERU S.A. | CS7: UNIÓN DE CERVECERÍAS PERUANAS BACKUS Y JOHNSTON S. | CT7: YURA
B8: 00:30 | E8: 30.5042 | F8: 11.398 | L8: 11.4606 | M8: 14.2764 | N8: 12.42 | O8: 28.292 | R8: 51.99 | T8: 55.30175 | V8: 9.3 | X8: 137.804 | AF8: 1 | AJ8: 5.33786 | AK8: 0 | AM8: 52.6263 | AN8: 123.34889 | AO8: 28.2561 | AQ8: 172.62 | AS8: 38.88368 | AT8: 32.43023 | AV8: 194.02549 | AW8: 38.7357 | AY8: 1.8734 | BA8: 2.5 | BC8: 52.5435 | BE8: 20.5 | BI8: 12.00934 | BM8: 6.781 | BN8: 28.539 | BO8: 2.08 | BP8: 146.56923 | BR8: 5.5143 | BS8: 127.67018 | BT8: 7.41012 | BW8: 3.85819 | BZ8: 92.93044 | CA8: 24.89831 | CC8: 0.653 | CE8: 462.99931 | CG8: 149.6049 | CH8: 17.5219 | CK8: 17.5666 | CL8: 5.16031 | CO8: 15.70267 | CP8: 288.53 | CR8: 39.837 | CT8: 33.692
B9: 01:00 | E9: 30.6573 | F9: 11.84 | L9: 11.2537 | M9: 14.0892 | N9: 11.9 | O9: 29.208 | R9: 51.887 | T9: 55.57993 | V9: 9.3 | X9: 120.02337 | AF9: 1 | AJ9: 5.33431 | AK9: 0 | AM9: 51.6808 | AN9: 124.14451 | AO9: 27.9777 | AQ9: 172.22 | AS9: 37.0306 | AT9: 32.18973 | AV9: 196.26845 | AW9: 37.7675 | AY9: 1.88314 | BA9: 2.3 | BC9: 54.50216 | BE9: 20.5 | BI9: 12.11421 | BM9: 6.891 | BN9: 31.929 | BO9: 2.1 | BP9: 145.34975 | BR9: 5.6267 | BS9: 128.45556 | BT9: 7.93029 | BW9: 3.96348 | BZ9: 92.65914 | CA9: 24.90281 | CC9: 0.652 | CE9: 463.10867 | CG9: 148.601 | CH9: 17.7396 | CK9: 17.3427 | CL9: 4.96944 | CO9: 16.03522 | CP9: 286.58 | CR9: 39.979 | CT9: 30.163
B10: 01:30 | E10: 31.4354 | F10: 12.649 | L10: 11.2155 | M10: 14.6523 | N10: 12.08 | O10: 29.99 | R10: 52.127 | T10: 47.35194 | V10: 9.9 | X10: 87.78589 | AF10: 0.9 | AJ10: 5.31128 | AK10: 0 | AM10: 51.2294 | AN10: 124.97494 | AO10: 28.6905 | AQ10: 172.89 | AS10: 37.63609 | AT10: 32.92343 | AV10: 193.80823 | AW10: 37.2656 | AY10: 1.88607 | BA10: 2.4 | BC10: 59.06391 | BE10: 20.5 | BI10: 11.99903 | BM10: 6.781 | BN10: 31.733 | BO10: 2.13 | BP10: 145.40504 | BR10: 5.6255 | BS10: 124.91003 | BT10: 7.64593 | BW10: 4.0073 | BZ10: 91.0788 | CA10: 24.89614 | CC10: 0.637 | CE10: 465.47879 | CG10: 149.2871 | CH10: 17.5997 | CK10: 17.8608 | CL10: 4.75679 | CO10: 15.4436 | CP10: 293.01 | CR10: 40.127 | CT10: 30.466
B11: 02:00 | E11: 31.8681 | F11: 12.53 | L11: 10.8185 | M11: 14.745 | N11: 12.4 | O11: 30.974 | R11: 52.326 | T11: 44.4369 | V11: 9.8 | X11: 103.93519 | AF11: 0.9 | AJ11: 5.27359 | AK11: 0 | AM11: 51.3725 | AN11: 125.2495 | AO11: 28.4233 | AQ11: 171.11 | AS11: 38.72638 | AT11: 32.69521 | AV11: 195.39637 | AW11: 37.7057 | AY11: 1.90834 | BA11: 2.3 | BC11: 59.77564 | BE11: 20.5 | BI11: 10.8554 | BM11: 6.789 | BN11: 31.742 | BO11: 2.06 | BP11: 146.09527 | BR11: 5.6988 | BS11: 125.12589 | BT11: 8.42721 | BW11: 3.7307 | BZ11: 89.81198 | CA11: 24.89512 | CC11: 0.665 | CE11: 463.85322 | CG11: 153.4647 | CH11: 17.44687 | CK11: 17.7936 | CL11: 4.6681 | CO11: 15.58389 | CP11: 282.75 | CR11: 38.386 | CT11: 31.305
B12: 02:30 | E12: 31.894 | F12: 13.256 | L12: 10.7957 | M12: 14.9576 | N12: 11.95 | O12: 30.934 | R12: 52.43 | T12: 36.88671 | V12: 10 | X12: 140.13473 | AF12: 0.7 | AJ12: 5.22184 | AK12: 0 | AM12: 49.4205 | AN12: 124.82985 | AO12: 27.8509 | AQ12: 171.63 | AS12: 37.24171 | AT12: 32.69731 | AV12: 192.70623 | AW12: 38.169 | AY12: 1.90067 | BA12: 2.3 | BC12: 59.67803 | BE12: 20.5 | BI12: 11.22103 | BM12: 6.987 | BN12: 31.24 | BO12: 1.48 | BP12: 148.70174 | BR12: 5.5173 | BS12: 123.73339 | BT12: 10.33364 | BW12: 3.87202 | BZ12: 89.03234 | CA12: 24.90254 | CC12: 0.617 | CE12: 465.75181 | CG12: 152.9974 | CH12: 17.49637 | CK12: 17.3399 | CL12: 4.64782 | CO12: 14.76372 | CP12: 284.01 | CR12: 38.026 | CT12: 32.441
B13: 03:00 | E13: 31.4194 | F13: 12.817 | L13: 10.9106 | M13: 15.0794 | N13: 12.53 | O13: 30.654 | R13: 52.492 | T13: 47.1621 | V13: 9.9 | X13: 104.9752 | AF13: 0.8 | AJ13: 4.81592 | AK13: 0 | AM13: 52.105 | AN13: 122.76802 | AO13: 27.7979 | AQ13: 171.95 | AS13: 38.09469 | AT13: 32.20227 | AV13: 193.95041 | AW13: 37.3534 | AY13: 1.88122 | BA13: 2.2 | BC13: 58.82996 | BE13: 20.5 | BI13: 11.28623 | BM13: 7.123 | BN13: 32.651 | BO13: 1.51 | BP13: 148.3767 | BR13: 5.4645 | BS13: 123.76897 | BT13: 11.85165 | BW13: 3.96593 | BZ13: 91.07484 | CA13: 24.92682 | CC13: 0.658 | CE13: 466.47027 | CG13: 144.5566 | CH13: 17.68831 | CK13: 16.9855 | CL13: 4.82002 | CO13: 15.83221 | CP13: 286.79 | CR13: 38.465 | CT13: 32.242
B14: 03:30 | E14: 31.7435 | F14: 13.482 | L14: 10.9171 | M14: 14.9483 | N14: 12.45 | O14: 30.654 | R14: 52.624 | T14: 53.37945 | V14: 9.9 | X14: 85.18081 | AF14: 0.8 | AJ14: 5.05719 | AK14: 0 | AM14: 50.9129 | AN14: 123.46974 | AO14: 27.9592 | AQ14: 170.88 | AS14: 35.74835 | AT14: 32.53816 | AV14: 190.65064 | AW14: 36.9436 | AY14: 1.85857 | BA14: 2.2 | BC14: 58.93231 | BE14: 20.5 | BI14: 11.40822 | BM14: 6.981 | BN14: 32.939 | BO14: 2.04 | BP14: 147.91011 | BR14: 5.5953 | BS14: 122.43936 | BT14: 12.27656 | BW14: 4.02736 | BZ14: 90.97139 | CA14: 24.95697 | CC14: 0.667 | CE14: 466.02527 | CG14: 146.0259 | CH14: 17.73134 | CK14: 17.3537 | CL14: 4.82307 | CO14: 16.17257 | CP14: 265.99 | CR14: 38.614 | CT14: 32.803
B15: 04:00 | E15: 31.7643 | F15: 12.668 | L15: 10.9668 | M15: 14.698 | N15: 12.51 | O15: 29.558 | R15: 52.996 | T15: 46.6355 | V15: 9.8 | X15: 102.43945 | AF15: 0.9 | AJ15: 5.19055 | AK15: 0 | AM15: 51.7456 | AN15: 122.94682 | AO15: 28.3165 | AQ15: 169.7 | AS15: 37.22229 | AT15: 32.72778 | AV15: 191.93575 | AW15: 37.4194 | AY15: 1.85047 | BA15: 2.2 | BC15: 60.07995 | BE15: 20.5 | BI15: 11.58814 | BM15: 6.871 | BN15: 35.9 | BO15: 1.79 | BP15: 150.96237 | BR15: 5.5543 | BS15: 124.62352 | BT15: 11.79303 | BW15: 3.88656 | BZ15: 90.88678 | CA15: 24.96082 | CC15: 0.687 | CE15: 462.60426 | CG15: 141.1857 | CH15: 17.05192 | CK15: 18.1779 | CL15: 4.8059 | CO15: 15.88208 | CP15: 275.77 | CR15: 38.652 | CT15: 32.714
B16: 04:30 | E16: 31.844 | F16: 12.179 | L16: 10.9877 | M16: 15.526 | N16: 12.95 | O16: 29.136 | R16: 53.18 | T16: 50.48745 | V16: 9.8 | X16: 142.20994 | AF16: 0.8 | AJ16: 5.28152 | AK16: 0 | AM16: 51.8815 | AN16: 126.4229 | AO16: 28.0899 | AQ16: 171.79 | AS16: 37.00961 | AT16: 33.98201 | AV16: 191.62734 | AW16: 37.8028 | AY16: 1.86416 | BA16: 2.19 | BC16: 60.10579 | BE16: 20.5 | BI16: 11.64286 | BM16: 6.925 | BN16: 36.03 | BO16: 1.77 | BP16: 151.18338 | BR16: 5.5004 | BS16: 124.47094 | BT16: 11.83961 | BW16: 3.90366 | BZ16: 89.58553 | CA16: 24.96234 | CC16: 0.659 | CE16: 466.42139 | CG16: 151.7227 | CH16: 17.8043 | CK16: 17.7853 | CL16: 4.82224 | CO16: 15.88568 | CP16: 285.21 | CR16: 38.759 | CT16: 32.394
B17: 05:00 | E17: 31.7696 | F17: 11.617 | L17: 10.977 | M17: 16.1367 | N17: 12.83 | O17: 28.572 | R17: 52.704 | T17: 43.55669 | V17: 9.8 | X17: 145.98227 | AF17: 0.9 | AJ17: 5.03627 | AK17: 0 | AM17: 51.2546 | AN17: 128.80705 | AO17: 27.8693 | AQ17: 166.8 | AS17: 36.65417 | AT17: 33.76348 | AV17: 194.83912 | AW17: 36.0146 | AY17: 1.86804 | BA17: 1.9 | BC17: 60.36834 | BE17: 20.5 | BI17: 11.59281 | BM17: 6.789 | BN17: 36.343 | BO17: 1.76 | BP17: 149.01526 | BR17: 5.3847 | BS17: 125.77509 | BT17: 11.00315 | BW17: 4.37541 | BZ17: 90.73731 | CA17: 24.95155 | CC17: 0.646 | CE17: 463.51666 | CG17: 152.5304 | CH17: 17.5695 | CK17: 17.4189 | CL17: 4.74237 | CO17: 16.07772 | CP17: 284.68 | CR17: 38.939 | CT17: 32.455
B18: 05:30 | E18: 31.7427 | F18: 10.846 | L18: 11.1004 | M18: 15.4848 | N18: 12.38 | O18: 28.948 | R18: 52.907 | T18: 46.90681 | V18: 9.9 | X18: 139.54488 | AF18: 0.9 | AJ18: 5.08865 | AK18: 0 | AM18: 51.8893 | AN18: 125.12344 | AO18: 27.607 | AQ18: 172.36 | AS18: 36.51095 | AT18: 33.2009 | AV18: 195.36001 | AW18: 35.4755 | AY18: 1.88486 | BA18: 1.2 | BC18: 52.41942 | BE18: 20.5 | BI18: 14.57835 | BM18: 6.781 | BN18: 36.56 | BO18: 1.75 | BP18: 150.57255 | BR18: 5.4909 | BS18: 128.79901 | BT18: 10.92688 | BW18: 3.85894 | BZ18: 90.80894 | CA18: 24.90297 | CC18: 0.654 | CE18: 456.06569 | CG18: 147.2497 | CH18: 17.56495 | CK18: 17.2215 | CL18: 4.52515 | CO18: 15.27371 | CP18: 284.8 | CR18: 36.621 | CT18: 32.179
B19: 06:00 | E19: 31.5761 | F19: 9.904 | L19: 11.5229 | M19: 15.4049 | N19: 12.7 | O19: 29.71 | R19: 52.94 | T19: 55.72864 | V19: 9.9 | X19: 115.25757 | AF19: 0.8 | AJ19: 5.10208 | AK19: 0 | AM19: 52.7578 | AN19: 129.76937 | AO19: 24.8585 | AQ19: 168.24 | AS19: 34.59057 | AT19: 33.03977 | AV19: 195.42307 | AW19: 33.7303 | AY19: 1.87891 | BA19: 1.3 | BC19: 36.70546 | BE19: 20.5 | BI19: 16.56923 | BM19: 6.891 | BN19: 36.456 | BO19: 1.71 | BP19: 149.73579 | BR19: 5.3194 | BS19: 125.87254 | BT19: 10.16188 | BW19: 3.65085 | BZ19: 90.27651 | CA19: 24.88771 | CC19: 0.573 | CE19: 450.51148 | CG19: 154.1499 | CH19: 17.50155 | CK19: 16.6788 | CL19: 4.5109 | CO19: 13.66067 | CP19: 287.22 | CR19: 36.08 | CT19: 30.913
... B55: 00:00 | E55: 23.8281 | F55: 11.889 | L55: 10.7406 | M55: 15.0566 | N55: 13.34 | O55: 34.076 | R55: 52.44 | T55: 53.28076 | V55: 8.5 | X55: 131.68461 | AF55: 0.7 | AJ55: 5.27586 | AK55: 0 | AM55: 51.2749 | AN55: 123.59036 | AO55: 28.735 | AQ55: 167.89 | AS55: 37.23657 | AT55: 26.66027 | AV55: 190.6281 | AW55: 37.022 | AY55: 2.32671 | BA55: 1.1 | BC55: 48.89991 | BE55: 20.3 | BI55: 13.5553 | BM55: 6.871 | BN55: 59.237 | BO55: 2.07 | BP55: 144.71608 | BR55: 5.1079 | BS55: 128.85059 | BT55: 10.71926 | BW55: 3.83695 | BZ55: 90.58696 | CA55: 24.76088 | CC55: 0.638 | CE55: 460.70178 | CG55: 153.9707 | CH55: 17.56005 | CK55: 19.6783 | CL55: 4.86299 | CO55: 15.97952 | CP55: 281.84 | CR55: 39.284 | CT55: 26.915
B56: MWh | C56: 0 | D56: 0 | E56: 704.91005 | F56: 277.08 | G56: 0 | H56: 0 | I56: 0 | J56: 0 | K56: 0 | L56: 277.7733 | M56: 327.25955 | N56: 311.28 | O56: 728.273 | P56: 0 | Q56: 0 | R56: 1249.8495 | S56: 0 | T56: 1133.2447 | U56: 0 | V56: 216.4 | W56: 0 | X56: 2383.9615 | Y56: 0 | Z56: 0 | AA56: 0 | AB56: 0 | AC56: 0 | AD56: 0 | AE56: 0 | AF56: 21.25 | AG56: 0 | AH56: 0 | AI56: 0 | AJ56: 118.96792 | AK56: 0 | AL56: 0 | AM56: 1205.7857 | AN56: 3007.414 | AO56: 653.5564 | AP56: 0 | AQ56: 4052.465 | AR56: 0 | AS56: 856.70754 | AT56: 722.33331 | AU56: 0 | AV56: 4640.8614 | AW56: 852.6048 | AX56: 0 | AY56: 46.065055 | AZ56: 0 | BA56: 16.695 | BB56: 0 | BC56: 955.41862 | BD56: 0 | BE56: 484.5 | BF56: 0 | BG56: 0 | BH56: 0 | BI56: 386.14559 | BJ56: 0 | BK56: 0 | BL56: 0 | BM56: 165.438 | BN56: 1187.831 | BO56: 47.6 | BP56: 3546.8584 | BQ56: 0 | BR56: 127.54095 | BS56: 3003.845 | BT56: 255.93079 | BU56: 0 | BV56: 0 | BW56: 93.445805 | BX56: 0 | BY56: 0 | BZ56: 2200.3183 | CA56: 594.90872 | CB56: 0 | CC56: 15.3675 | CD56: 0 | CE56: 11113.343 | CF56: 0 | CG56: 3491.8027 | CH56: 414.16167 | CI56: 0 | CJ56: 0 | CK56: 413.10085 | CL56: 111.94805 | CM56: 0 | CN56: 0 | CO56: 361.05359 | CP56: 6781.745 | CQ56: 0 | CR56: 889.3605 | CS56: 0 | CT56: 517.617
B59: Nota :
B60: Información proporcionada por la empresas
C62: DATOS ESTIMADOS
C64: SIN DATOS

Sheet TIPO_RECURSO
B3: domingo, 19 de Octubre del 2025
B5: REPORTE POTENCIA GENERADA POR TIPO DE RECURSO
B6: HORA | C6: H. PASADA | D6: H. REGULACION | E6: GAS DE CAMISEA | F6: GAS DE MALACAS | G6: GAS DE AGUAYTIA | H6: DIÉSEL | I6: RESIDUAL | J6: NAFTA+GAS DE REFINERIA | K6: FLEXIGAS+GAS DE REFINERIA | L6: DIÉSEL | M6: BAGAZO | N6: BIOGÁS | O6: SOLAR | P6: EÓLICA | Q6: TOTAL | V6: EMPRESA | W6: CENTRAL | X6: HIDROELECTRICA DE PASADA | Y6: HIDROELECTRICA DE REGULACION
B7: 00:30 | C7: 1114.1 | D7: 3041.6 | E7: 2224.7 | F7: 0 | H7: 0 | K7: =DESPACHO_EJECUTADO!FE11+DESPACHO_EJECUTADO!FF11 -> 61.1 | M7: 43.1 | N7: 7.4 | O7: 0 | P7: 255.1 | Q7: =SUM(C7:P7) -> 6747.1 | V7: ANDEAN POWER S.A.C. | W7: C.H.CARHUAC | X7: 408.85
B8: 01:00 | C8: 1121.4 | D8: 2921.8 | E8: 2217 | F8: 0 | H8: 0 | K8: =DESPACHO_EJECUTADO!FE12+DESPACHO_EJECUTADO!FF12 -> 61.6 | M8: 42.8 | N8: 7.4 | O8: 0 | P8: 245.3 | Q8: =SUM(C8:P8) -> 6617.3 | V8: ASOCIACIÓN SANTA LUCIA DE CHACAS | W8: C.H. HUALLIN | X8: 55.05
B9: 01:30 | C9: 1119.1 | D9: 2966.3 | E9: 2089 | F9: 0 | H9: 0 | K9: =DESPACHO_EJECUTADO!FE13+DESPACHO_EJECUTADO!FF13 -> 61.4 | M9: 41.8 | N9: 7.4 | O9: 0 | P9: 242.5 | Q9: =SUM(C9:P9) -> 6527.5 | V9: CELEPSA | W9: C.H. EL PLATANAL | Y9: 3544.5
B10: 02:00 | C10: 1120.6 | D10: 2907 | E10: 1953.4 | F10: 0 | H10: 0 | K10: =DESPACHO_EJECUTADO!FE14+DESPACHO_EJECUTADO!FF14 -> 60.8 | M10: 42.5 | N10: 7.4 | O10: 0 | P10: 249.5 | Q10: =SUM(C10:P10) -> 6341.2 | V10: CELEPSA RENOVABLES S.R.L. | W10: C.H. MARAÑON | X10: 344.95
B11: 02:30 | C11: 1104.6 | D11: 2920 | E11: 1989.7 | F11: 0 | H11: 0 | K11: =DESPACHO_EJECUTADO!FE15+DESPACHO_EJECUTADO!FF15 -> 61.5 | M11: 42.6 | N11: 7.4 | O11: 0 | P11: 273.2 | Q11: =SUM(C11:P11) -> 6399 | V11: CHINANGO S.A.C. | W11: C.H. CHIMAY | Y11: 3407.25
B12: 03:00 | C12: 1102.7 | D12: 2931.9 | E12: 1885.2 | F12: 0 | H12: 0 | K12: =DESPACHO_EJECUTADO!FE16+DESPACHO_EJECUTADO!FF16 -> 61 | M12: 42.8 | N12: 7.4 | O12: 0 | P12: 288.7 | Q12: =SUM(C12:P12) -> 6319.7 | W12: C.H. YANANGO | X12: 742.5
B13: 03:30 | C13: 1099.4 | D13: 2929.9 | E13: 1838.2 | F13: 0 | H13: 0 | K13: =DESPACHO_EJECUTADO!FE17+DESPACHO_EJECUTADO!FF17 -> 61.7 | M13: 44.1 | N13: 7.4 | O13: 0 | P13: 279.1 | Q13: =SUM(C13:P13) -> 6259.8 | V13: EGASA | W13: C.H. CHARCANI III | X13: 163.15
B14: 04:00 | C14: 1106.7 | D14: 2929.8 | E14: 1822.3 | F14: 0 | H14: 0 | K14: =DESPACHO_EJECUTADO!FE18+DESPACHO_EJECUTADO!FF18 -> 61.2 | M14: 42.9 | N14: 7.4 | O14: 0 | P14: 311.5 | Q14: =SUM(C14:P14) -> 6281.8 | W14: C.H. CHARCANI IV | Y14: 290.6
B15: 04:30 | C15: 1104.5 | D15: 2919.5 | E15: 1721 | F15: 0 | H15: 0 | K15: =DESPACHO_EJECUTADO!FE19+DESPACHO_EJECUTADO!FF19 -> 60.7 | M15: 44.6 | N15: 7.4 | O15: 0 | P15: 312.9 | Q15: =SUM(C15:P15) -> 6170.6 | W15: C.H. CHARCANI V | Y15: 1890.15
B16: 05:00 | C16: 1063.5 | D16: 2941.6 | E16: 1877.6 | F16: 0 | H16: 0 | K16: =DESPACHO_EJECUTADO!FE20+DESPACHO_EJECUTADO!FF20 -> 59.8 | M16: 42.9 | N16: 7.4 | O16: 0.1 | P16: 324.8 | Q16: =SUM(C16:P16) -> 6317.7 | V16: EGEJUNIN | W16: C.H. HUASAHUASI I | X16: 237.3
B17: 05:30 | C17: 1019.8 | D17: 3011.7 | E17: 1794.9 | F17: 0 | H17: 0 | K17: =DESPACHO_EJECUTADO!FE21+DESPACHO_EJECUTADO!FF21 -> 60.6 | M17: 44.6 | N17: 7.4 | O17: 20 | P17: 334 | Q17: =SUM(C17:P17) -> 6293 | W17: C.H. RUNATULLO II | X17: 458.45
B18: 06:00 | C18: 1003.5 | D18: 2674.7 | E18: 1755.4 | F18: 0 | H18: 0 | K18: =DESPACHO_EJECUTADO!FE22+DESPACHO_EJECUTADO!FF22 -> 60.6 | M18: 46.4 | N18: 7.4 | O18: 219.6 | P18: 310.7 | Q18: =SUM(C18:P18) -> 6078.3 | W18: C.H. RUNATULLO III | X18: 484.45
B19: 06:30 | C19: 1004.2 | D19: 2436.4 | E19: 1648 | F19: 0 | H19: 0 | K19: =DESPACHO_EJECUTADO!FE23+DESPACHO_EJECUTADO!FF23 -> 61.2 | M19: 48.3 | N19: 7.4 | O19: 495.9 | P19: 297.4 | Q19: =SUM(C19:P19) -> 5998.8 | W19: C.H. SANTA CRUZ I | X19: 150.05
B20: 07:00 | C20: 987.7 | D20: 2158.6 | E20: 1534.5 | F20: 0 | H20: 0 | K20: =DESPACHO_EJECUTADO!FE24+DESPACHO_EJECUTADO!FF24 -> 61 | M20: 38.6 | N20: 7.4 | O20: 789.7 | P20: 295.3 | Q20: =SUM(C20:P20) -> 5872.8 | V20: EGEMSA | W20: C.H. MACHUPICCHU | X20: 2989.35
B21: 07:30 | C21: 951.9 | D21: 2026.7 | E21: 1609.2 | F21: 24.2 | H21: 0 | K21: =DESPACHO_EJECUTADO!FE25+DESPACHO_EJECUTADO!FF25 -> 61.3 | M21: 40.6 | N21: 7.4 | O21: 862.8 | P21: 305.3 | Q21: =SUM(C21:P21) -> 5889.4 | V21: EGESUR | W21: C.H. ARICOTA I | Y21: 184.85
B22: 08:00 | C22: 973 | D22: 2261.7 | E22: 1462.1 | F22: 25.4 | H22: 0 | K22: =DESPACHO_EJECUTADO!FE26+DESPACHO_EJECUTADO!FF26 -> 60.9 | M22: 50.9 | N22: 7.4 | O22: 895.3 | P22: 362.8 | Q22: =SUM(C22:P22) -> 6099.5 | W22: C.H. ARICOTA II | Y22: 146.75
B23: 08:30 | C23: 982.2 | D23: 2313.5 | E23: 1487.3 | F23: 24.9 | H23: 0 | K23: =DESPACHO_EJECUTADO!FE27+DESPACHO_EJECUTADO!FF27 -> 61.1 | M23: 52.4 | N23: 7.4 | O23: 912.1 | P23: 375.8 | Q23: =SUM(C23:P23) -> 6216.7 | V23: ELECTRICA YANAPAMPA SAC | W23: C.H. YANAPAMPA | X23: 79.3
B24: 09:00 | C24: 981.3 | D24: 2352.2 | E24: 1484.8 | F24: 24.5 | H24: 0 | K24: =DESPACHO_EJECUTADO!FE28+DESPACHO_EJECUTADO!FF28 -> 62.7 | M24: 52.9 | N24: 7.4 | O24: 918.1 | P24: 421.6 | Q24: =SUM(C24:P24) -> 6305.5 | V24: ELECTROPERU | W24: C.H. MANTARO | Y24: 14832.6
B25: 09:30 | C25: 972 | D25: 2429.9 | E25: 1481.4 | F25: 24.4 | H25: 0 | K25: =DESPACHO_EJECUTADO!FE29+DESPACHO_EJECUTADO!FF29 -> 61.7 | M25: 53.5 | N25: 7.4 | O25: 922.3 | P25: 453.6 | Q25: =SUM(C25:P25) -> 6406.2 | W25: C.H. RESTITUCION | X25: 5051.45
B26: 10:00 | C26: 975.7 | D26: 2445.7 | E26: 1501.3 | F26: 35.9 | H26: 0 | K26: =DESPACHO_EJECUTADO!FE30+DESPACHO_EJECUTADO!FF30 -> 59.2 | M26: 53.2 | N26: 7.4 | O26: 945.2 | P26: 484.8 | Q26: =SUM(C26:P26) -> 6508.4 | V26: EMPRESA DE GENERACION ELECTRICA CANCHAYLLO SAC | W26: C.H. CANCHAYLLO | X26: 117.95
B27: 10:30 | C27: 984 | D27: 2533 | E27: 1558.5 | F27: 48.6 | H27: 0 | K27: =DESPACHO_EJECUTADO!FE31+DESPACHO_EJECUTADO!FF31 -> 61.2 | M27: 55.3 | N27: 7.4 | O27: 945.4 | P27: 497.5 | Q27: =SUM(C27:P27) -> 6690.9 | V27: EMPRESA DE GENERACION ELECTRICA RIO BAÑOS S.A.C. | W27: C.H. RUCUY | X27: 479.05
B28: 11:00 | C28: 985.4 | D28: 2531.4 | E28: 1546.2 | F28: 49.6 | H28: 0 | K28: =DESPACHO_EJECUTADO!FE32+DESPACHO_EJECUTADO!FF32 -> 60.6 | M28: 54.6 | N28: 7.4 | O28: 939.9 | P28: 528 | Q28: =SUM(C28:P28) -> 6703.1 | V28: EMPRESA DE GENERACION ELECTRICA SANTA ANA S.A.C. | W28: C.H. RENOVANDES H1 | X28: 458.3
B29: 11:30 | C29: 979.8 | D29: 2470.8 | E29: 1578 | F29: 50.6 | H29: 0 | K29: =DESPACHO_EJECUTADO!FE33+DESPACHO_EJECUTADO!FF33 -> 60.6 | M29: 55 | N29: 7.4 | O29: 953 | P29: 568.5 | Q29: =SUM(C29:P29) -> 6723.7 | V29: EMPRESA DE GENERACION HUALLAGA | W29: C.H. CHAGLLA | Y29: 5561
B30: 12:00 | C30: 975.1 | D30: 2639.7 | E30: 1478.6 | F30: 49.1 | H30: 0 | K30: =DESPACHO_EJECUTADO!FE34+DESPACHO_EJECUTADO!FF34 -> 60.9 | M30: 52.9 | N30: 7.4 | O30: 951.6 | P30: 571 | Q30: =SUM(C30:P30) -> 6786.3 | W30: P.C.H. CHAGLLA | X30: 155.8
B31: 12:30 | C31: 968.6 | D31: 2547.4 | E31: 1512.4 | F31: 50.1 | H31: 0 | K31: =DESPACHO_EJECUTADO!FE35+DESPACHO_EJECUTADO!FF35 -> 60.3 | M31: 53.4 | N31: 7.4 | O31: 953 | P31: 584.5 | Q31: =SUM(C31:P31) -> 6737.1 | V31: EMPRESA DE GENERACION HUANZA | W31: C.H. HUANZA | Y31: 1778.25
B32: 13:00 | C32: 981.8 | D32: 2587.7 | E32: 1526.1 | F32: 78.9 | H32: 0 | K32: =DESPACHO_EJECUTADO!FE36+DESPACHO_EJECUTADO!FF36 -> 59.6 | M32: 55.1 | N32: 7.4 | O32: 956.2 | P32: 610.7 | Q32: =SUM(C32:P32) -> 6863.5 | V32: EMPRESA ELECTRICA AGUA AZUL | W32: C.H. POTRERO | X32: 322
B33: 13:30 | C33: 963 | D33: 2464.1 | E33: 1503.2 | F33: 79.9 | H33: 0 | K33: =DESPACHO_EJECUTADO!FE37+DESPACHO_EJECUTADO!FF37 -> 61 | M33: 54.5 | N33: 7.4 | O33: 951.1 | P33: 621.3 | Q33: =SUM(C33:P33) -> 6705.5 | V33: EMPRESA ELECTRICA RIO DOBLE | W33: C.H. LAS PIZARRAS | X33: 196
B34: 14:00 | C34: 975.7 | D34: 2425 | E34: 1489.6 | F34: 80.1 | H34: 0 | K34: =DESPACHO_EJECUTADO!FE38+DESPACHO_EJECUTADO!FF38 -> 61.5 | M34: 54.2 | N34: 7.4 | O34: 940.7 | P34: 663.8 | Q34: =SUM(C34:P34) -> 6698 | V34: ENGIE ENERGIA PERU S.A.A. | W34: C.H. YUNCAN | Y34: 2928.2
B35: 14:30 | C35: 971.5 | D35: 2469.9 | E35: 1497.5 | F35: 80.3 | H35: 0 | K35: =DESPACHO_EJECUTADO!FE39+DESPACHO_EJECUTADO!FF39 -> 62.4 | M35: 53.1 | N35: 7.4 | O35: 932 | P35: 683.4 | Q35: =SUM(C35:P35) -> 6757.5 | V35: GENERACIÓN ANDINA S.A.C. | W35: C.H. 8 DE AGOSTO | X35: 250.05
B36: 15:00 | C36: 975 | D36: 2507.4 | E36: 1445.2 | F36: 79.2 | H36: 0 | K36: =DESPACHO_EJECUTADO!FE40+DESPACHO_EJECUTADO!FF40 -> 61.3 | M36: 55.8 | N36: 7.4 | O36: 907.2 | P36: 703.3 | Q36: =SUM(C36:P36) -> 6741.8 | W36: C.H. EL CARMEN | X36: 177.5
B37: 15:30 | C37: 976.1 | D37: 2573.3 | E37: 1446.2 | F37: 79.1 | H37: 0 | K37: =DESPACHO_EJECUTADO!FE41+DESPACHO_EJECUTADO!FF41 -> 60.9 | M37: 53 | N37: 7.4 | O37: 851.3 | P37: 702.7 | Q37: =SUM(C37:P37) -> 6750 | V37: GENERADORA DE ENERGÍA DEL PERÚ | W37: C.H. ÁNGEL I | X37: 489
B38: 16:00 | C38: 942 | D38: 2534.9 | E38: 1402.7 | F38: 85 | H38: 58 | K38: =DESPACHO_EJECUTADO!FE42+DESPACHO_EJECUTADO!FF42 -> 61 | M38: 54.5 | N38: 7.4 | O38: 802.7 | P38: 687.8 | Q38: =SUM(C38:P38) -> 6636 | W38: C.H. ÁNGEL II | X38: 489.6
B39: 16:30 | C39: 959.7 | D39: 2647.1 | E39: 1476.4 | F39: 85.1 | H39: 98.2 | K39: =DESPACHO_EJECUTADO!FE43+DESPACHO_EJECUTADO!FF43 -> 61.6 | M39: 53.2 | N39: 7.4 | O39: 581.2 | P39: 667.4 | Q39: =SUM(C39:P39) -> 6637.3 | W39: C.H. ÁNGEL III | X39: 470.4
B40: 17:00 | C40: 958.7 | D40: 3017.7 | E40: 1580.3 | F40: 24.8 | H40: 57.5 | K40: =DESPACHO_EJECUTADO!FE44+DESPACHO_EJECUTADO!FF44 -> 61.2 | M40: 53.8 | N40: 7.4 | O40: 294.6 | P40: 657.7 | Q40: =SUM(C40:P40) -> 6713.7 | W40: C.H. LA JOYA | X40: 167.25
B41: 17:30 | C41: 1063 | D41: 3033.8 | E41: 1761.4 | F41: 25 | H41: 53.8 | K41: =DESPACHO_EJECUTADO!FE45+DESPACHO_EJECUTADO!FF45 -> 61.2 | M41: 53.8 | N41: 7.4 | O41: 42.9 | P41: 666.8 | Q41: =SUM(C41:P41) -> 6769.1 | V41: HIDROCAÑETE S.A. | W41: C.H. IMPERIAL | X41: 84.55
B42: 18:00 | C42: 1111.5 | D42: 3089 | E42: 1966.6 | F42: 25.1 | H42: 0 | K42: =DESPACHO_EJECUTADO!FE46+DESPACHO_EJECUTADO!FF46 -> 60.7 | M42: 53.9 | N42: 7.4 | O42: 0 | P42: 674.1 | Q42: =SUM(C42:P42) -> 6988.3 | V42: HIDROELECTRICA HUANCHOR S.A.C. | W42: C.H. HUANCHOR | X42: 404.65
B43: 18:30 | C43: 1113.2 | D43: 3386.1 | E43: 2163.3 | F43: 24.7 | H43: 0 | K43: =DESPACHO_EJECUTADO!FE47+DESPACHO_EJECUTADO!FF47 -> 61.3 | M43: 53.6 | N43: 7.4 | O43: 0 | P43: 671.6 | Q43: =SUM(C43:P43) -> 7481.2 | V43: HUAURA POWER GROUP S.A. | W43: C.H. YARUCAYA | X43: 446.4
B44: 19:00 | C44: 1115.9 | D44: 3420.2 | E44: 2178.5 | F44: 24.3 | H44: 0 | K44: =DESPACHO_EJECUTADO!FE48+DESPACHO_EJECUTADO!FF48 -> 60.9 | M44: 63.6 | N44: 7.4 | O44: 0 | P44: 662.2 | Q44: =SUM(C44:P44) -> 7533 | V44: HYDRO GLOBAL PERÚ S.A.C. | W44: CH SAN GABAN III | Y44: 4855.05
B45: 19:30 | C45: 1116.5 | D45: 3390.8 | E45: 2265.1 | F45: 24.5 | H45: 0 | K45: =DESPACHO_EJECUTADO!FE49+DESPACHO_EJECUTADO!FF49 -> 61.5 | M45: 57 | N45: 7.4 | O45: 0 | P45: 641.9 | Q45: =SUM(C45:P45) -> 7564.7 | V45: INLAND ENERGY SAC | W45: C.H. SANTA TERESA | X45: 1677.95
B46: 20:00 | C46: 1117.9 | D46: 3403.7 | E46: 2302.6 | F46: 24.8 | H46: 0 | K46: =DESPACHO_EJECUTADO!FE50+DESPACHO_EJECUTADO!FF50 -> 62 | M46: 55.8 | N46: 7.4 | O46: 0 | P46: 620.3 | Q46: =SUM(C46:P46) -> 7594.5 | V46: INVERSIONES SHAQSHA S.A.C. | W46: C.H. PARIAC | X46: 60
B47: 20:30 | C47: 1124.4 | D47: 3453.9 | E47: 2217.9 | F47: 25.1 | H47: 0 | K47: =DESPACHO_EJECUTADO!FE51+DESPACHO_EJECUTADO!FF51 -> 61.5 | M47: 59.8 | N47: 7.4 | O47: 0 | P47: 569 | Q47: =SUM(C47:P47) -> 7519 | V47: KALLPA GENERACION S.A. | W47: C.H. CERRO DEL AGUILA | Y47: 11190.3
B48: 21:00 | C48: 1123 | D48: 3445.9 | E48: 2119.6 | F48: 32.8 | H48: 0 | K48: =DESPACHO_EJECUTADO!FE52+DESPACHO_EJECUTADO!FF52 -> 62.3 | M48: 58.9 | N48: 7.4 | O48: 0 | P48: 536.2 | Q48: =SUM(C48:P48) -> 7386.1 | W48: M.C.H. CERRO DEL AGUILA | X48: 78.15
B49: 21:30 | C49: 1123.1 | D49: 3374 | E49: 2112.4 | F49: 25 | H49: 0 | K49: =DESPACHO_EJECUTADO!FE53+DESPACHO_EJECUTADO!FF53 -> 62.7 | M49: 58.4 | N49: 7.4 | O49: 0 | P49: 529.9 | Q49: =SUM(C49:P49) -> 7292.9 | V49: LA VIRGEN | W49: C.H. LA VIRGEN | Y49: 1184.45
B50: 22:00 | C50: 1122.2 | D50: 3310 | E50: 2056 | F50: 24.8 | H50: 0 | K50: =DESPACHO_EJECUTADO!FE54+DESPACHO_EJECUTADO!FF54 -> 62.3 | M50: 58.2 | N50: 7.4 | O50: 0 | P50: 494 | Q50: =SUM(C50:P50) -> 7134.9 | V50: MAJA ENERGIA S.A.C. | W50: C.H. RONCADOR | X50: 81.6
B51: 22:30 | C51: 1133 | D51: 3311.8 | E51: 2045.3 | F51: 25.3 | H51: 0 | K51: =DESPACHO_EJECUTADO!FE55+DESPACHO_EJECUTADO!FF55 -> 61.5 | M51: 60.3 | N51: 7.4 | O51: 0 | P51: 439.5 | Q51: =SUM(C51:P51) -> 7084.1 | V51: ORAZUL ENERGY PERÚ | W51: C.H. CAÑA BRAVA | X51: 105.2
B52: 23:00 | C52: 1119.1 | D52: 3178.3 | E52: 1919.7 | F52: 25.5 | H52: 0 | K52: =DESPACHO_EJECUTADO!FE56+DESPACHO_EJECUTADO!FF56 -> 61.4 | M52: 59.8 | N52: 7.4 | O52: 0 | P52: 429.9 | Q52: =SUM(C52:P52) -> 6801.1 | W52: C.H. CAÑON DEL PATO | Y52: 3682.6
B53: 23:30 | C53: 1127.2 | D53: 3091.5 | E53: 1937.1 | F53: 25.8 | H53: 0 | K53: =DESPACHO_EJECUTADO!FE57+DESPACHO_EJECUTADO!FF57 -> 61.4 | M53: 61.1 | N53: 7.4 | O53: 0 | P53: 383.1 | Q53: =SUM(C53:P53) -> 6694.6 | W53: C.H. CARHUAQUERO | Y53: 1545.7
B54: 00:00 | C54: 1118.4 | D54: 2993 | E54: 1839.7 | F54: 25.8 | H54: 0 | K54: =DESPACHO_EJECUTADO!FE58+DESPACHO_EJECUTADO!FF58 -> 61.8 | M54: 60.8 | N54: 7.4 | O54: 0 | P54: 347.2 | Q54: =SUM(C54:P54) -> 6454.1 | W54: C.H. CARHUAQUERO IV | X54: 237.9
B55: TOTAL MWh | C55: =SUM(C7:C54)/2 -> 25066.35 | D55: =SUM(D7:D54)/2 -> 67675.95 | E55: =SUM(E7:E54)/2 -> 42651.55 | F55: =SUM(F7:F54)/2 -> 719.1 | G55: =SUM(G7:G54)/2 -> 0 | H55: =SUM(H7:H54)/2 -> 133.75 | I55: =SUM(I7:I54)/2 -> 0 | J55: =SUM(J7:J54)/2 -> 0 | ... Q55: =SUM(Q7:Q54)/2 -> 160046.15 | V55: ORYGEN PERU S.A.A. | W55: C.H. CALLAHUANCA | Y55: 1547.7
B56: % | C56: =C55*100/$Q$55 -> 15.661951 | D56: =D55*100/$Q$55 -> 42.285272 | E56: =E55*100/$Q$55 -> 26.649532 | F56: =F55*100/$Q$55 -> 0.4493079 | G56: =G55*100/$Q$55 -> 0 | H56: =H55*100/$Q$55 -> 0.083569645 | I56: =I55*100/$Q$55 -> 0 | J56: =J55*100/$Q$55 -> 0 | ... Q56: =Q55*100/$Q$55 -> 100 | W56: C.H. HER 1 | X56: 14.4
W57: C.H. HUAMPANI | X57: 717.35
W58: C.H. HUINCO | Y58: 3927.55
W59: C.H. MOYOPAMPA | X59: 1542.65
V60: PERUANA DE INVERSIONES EN ENERGIAS RENOVABLES S.A. | W60: C.H. MANTA I | X60: 449.95
V61: SAN GABAN | W61: C.H. SAN GABAN II | Y61: 2633.25
W62: PCH TUPURI | X62: 22.7
V63: SINERSA | W63: C.H. CHANCAY | X63: 480.15
W64: C.H. POECHOS II | X64: 164.05
V65: STATKRAFT S.A | W65: C.H. ARCATA | X65: 51
W66: C.H. CAHUA | X66: 141.6
W67: C.H. CHEVES | Y67: 1312.85
W68: C.H. GALLITO CIEGO | Y68: 432.5
W69: C.H. MALPASO | Y69: 799.85
W70: C.H. OROYA | X70: 180.65
W71: C.H. PACHACHACA | X71: 214.45
W72: C.H. YAUPI | X72: 2622.3
V73: VARI ENERGIA S.A.C. | W73: C.H. ANASHIRONI | X73: 350.95
V74: TOTAL MWh | X74: 25066.35 | Y74: 67675.95

Sheet GENERACION RER
B3: domingo, 19 de Octubre del 2025
B5: GENERACIÓN ELÉCTRICA DE LAS CENTRALES RER (MW)
B6: HORA | C6: AGRO INDUSTRIAL PARAMONGA S.A. | D6: AGROAURORA S.A.C. | E6: AGROINDUSTRIAS SAN JACINTO S.A.A. | F6: AGROLMOS SOCIEDAD ANONIMA - AGROLMOS S.A. | G6: ANDEAN POWER S.A.C. | H6: ASOCIACIÓN SANTA LUCIA DE CHACAS | I6: ATRIA ENERGIA S.A.C. | J6: BIOENERGIA DEL CHIRA S.A. | K6: COLCA SOLAR S.A.C. | L6: EGEJUNIN | Q6: ELECTRICA YANAPAMPA SAC | R6: EMPRESA DE GENERACION ELECTRICA CANCHAYLLO SAC | S6: EMPRESA DE GENERACION ELECTRICA RIO BAÑOS S.A.C. | T6: EMPRESA DE GENERACION ELECTRICA SANTA ANA S.A.C. | U6: EMPRESA ELECTRICA AGUA AZUL | V6: EMPRESA ELECTRICA RIO DOBLE | W6: ENERGÍA EÓLICA S.A. | Y6: ENERGIA RENOVABLE DEL SUR S.A. | Z6: ENGIE ENERGIA PERU S.A.A. | AE6: GENERACIÓN ANDINA S.A.C. | AG6: GENERADORA DE ENERGÍA DEL PERÚ | AK6: GR CORTARRAMA SOCIEDAD ANONIMA CERRADA | AL6: GR PAINO SOCIEDAD ANONIMA CERRADA | AM6: GR TARUCA SOCIEDAD ANONIMA CERRADA | AN6: HIDROCAÑETE S.A. | AO6: HUAURA POWER GROUP S.A. | AP6: HYDRO PATAPO S.A.C. | AQ6: JOYA SOLAR S.A.C. | AR6: KALLPA GENERACION S.A. | AS6: KONDU SAC | AT6: MAJA ENERGIA S.A.C. | AU6: MAJES ARCUS S.A.C. | AV6: MOQUEGUA FV S.A.C. | AW6: ORAZUL ENERGY PERÚ | AY6: ORYGEN PERU S.A.A. | BD6: PANAMERICANA SOLAR SAC. | BE6: PARQUE EOLICO MARCONA S.A.C. | BF6: PARQUE EOLICO TRES HERMANAS S.A.C. | BG6: PERUANA DE INVERSIONES EN ENERGIAS RENOVABLES S.A. | BH6: PETRAMAS | BL6: REPARTICIÓN ARCUS S.A.C. | BM6: SAN GABAN | BN6: SINERSA | BP6: TACNA SOLAR SAC. | BQ6: VARI ENERGIA S.A.C. | BR6: TOTAL RER
C7: C.T. PARAMONGA | D7: C.T. MAPLE | E7: C.T SAN JACINTO | F7: C.T. AGROLMOS | G7: C.H. CARHUAC | H7: C.H. HUALLIN | I7: C.H. PURMACANA | J7: C.T. CAÑA BRAVA | L7: C.H. HUASAHUASI I | M7: C.H. HUASAHUASI II | N7: C.H. RUNATULLO II | O7: C.H. RUNATULLO III | P7: C.H. STA CRUZ I y II | Q7: C.H. YANAPAMPA | R7: C.H. CANCHAYLLO | S7: C.H. RUCUY | T7: C.H. RENOVANDES H1 | U7: C.H. POTRERO | V7: C.H. LAS PIZARRAS | AE7: C.H. 8 DE AGOSTO | AF7: C.H. EL CARMEN | AG7: C.H. ANGEL I | AH7: C.H. ANGEL II | AI7: C.H. ANGEL III | AJ7: C.H. LA JOYA | AN7: C.H. NUEVAIMPERIAL | AO7: C.H. YARUCAYA | AP7: MCH PATAPO | AT7: C.H. RONCADOR | AW7: C.H. CANA BRAVA | AX7: C.H. CARHUAQUERO4 | BC7: C.H. HER 1 | BG7: C.H. MANTA | BH7: C.T. HUAYCOLORO | BI7: C.T. LA GRINGA V | BJ7: CTB CALLAO | BK7: CTB. DONA CATALINA | BM7: C.H. TUPURI | BN7: C.H. CHANCAY | BO7: C.H. POECHOS2 | BQ7: C.H. ANASHIRONI | BR7: MW
B8: 0:30 | C8: 15.1 | E8: 7.6 | F8: 11.1 | G8: 20.1 | H8: 2.8 | J8: 9.3 | L8: 9.6 | N8: 19.8 | O8: 20.2 | P8: 6.6 | Q8: 3.4 | R8: 5 | S8: 20 | T8: 19.9 | U8: 13.6 | V8: 7.8 | W8: 15.4 | X8: 19.3 | Y8: 37.3 | Z8: 48.8 | AA8: 65.2 | AC8: 5 | AD8: 3.3 | AE8: 10.4 | AF8: 7.5 | AG8: 20.4 | AH8: 20.4 | AI8: 19.6 | AJ8: 7.2 | AL8: 1.1 | AM8: 2 | AN8: 3.6 | AO8: 18.6 | AT8: 3.4 | AW8: 4 | AX8: 9.9 | AY8: 8.7 | BA8: 11.3 | BC8: 0.6 | BE8: 9.7 | BF8: 28 | BG8: 20 | BH8: 2.1 | BI8: 1 | BJ8: 2.3 | BK8: 2 | BM8: 0.7 | BN8: 20 | BO8: 6.9 | BQ8: 18.3 | BR8: 645.9
B9: 1:00 | C9: 14.1 | E9: 8.2 | F9: 11.1 | G9: 20.1 | H9: 2.7 | J9: 9.4 | L9: 9.6 | N9: 19.7 | O9: 20.2 | P9: 6.6 | Q9: 3.5 | R9: 5 | S9: 19.8 | T9: 19.8 | U9: 13.6 | V9: 7.8 | W9: 13.5 | X9: 15.2 | Y9: 32.2 | Z9: 41.3 | AA9: 65.8 | AC9: 4.8 | AD9: 2.7 | AE9: 10.4 | AF9: 7.4 | AG9: 20.4 | AH9: 20.4 | AI9: 19.6 | AJ9: 7.2 | AL9: 1.2 | AM9: 2 | AN9: 3.6 | AO9: 18.6 | AT9: 3.4 | AW9: 1.5 | AX9: 9.8 | AY9: 11.2 | BA9: 16.5 | BC9: 0.6 | BE9: 9.9 | BF9: 29 | BG9: 20 | BH9: 2.1 | BI9: 1 | BJ9: 2.3 | BK9: 2 | BM9: 0.7 | BN9: 19.9 | BO9: 7 | BQ9: 19.1 | BR9: 633.5
B10: 1:30 | C10: 14.5 | E10: 7.1 | F10: 11.1 | G10: 20.2 | H10: 2.7 | J10: 9.1 | L10: 9.6 | N10: 19.2 | O10: 20.2 | P10: 6.6 | Q10: 3.5 | R10: 5.1 | S10: 20 | T10: 20 | U10: 13.6 | V10: 7.8 | W10: 16.1 | X10: 18.5 | Y10: 30.9 | Z10: 42.4 | AA10: 62.4 | AC10: 5 | AD10: 2.7 | AE10: 10.4 | AF10: 7.3 | AG10: 20.4 | AH10: 20.4 | AI10: 19.6 | AJ10: 7.2 | AL10: 3.2 | AM10: 5.7 | AN10: 3.6 | AO10: 18.6 | AT10: 3.4 | AW10: 2 | AX10: 9.9 | AY10: 9.3 | BA10: 14.9 | BC10: 0.6 | BE10: 7.1 | BF10: 24.3 | BG10: 20 | BH10: 2.1 | BI10: 1 | BJ10: 2.3 | BK10: 2 | BM10: 0.6 | BN10: 20 | BO10: 6.8 | BQ10: 17.7 | BR10: 628.7
B11: 2:00 | C11: 14.5 | E11: 7.6 | F11: 11.1 | G11: 20.1 | H11: 2.6 | J11: 9.3 | L11: 9.6 | N11: 19.3 | O11: 20.2 | P11: 6.6 | Q11: 3.5 | R11: 5 | S11: 20 | T11: 20.3 | U11: 13.6 | V11: 7.8 | W11: 17.3 | X11: 16 | Y11: 31.2 | Z11: 48.8 | AA11: 68.1 | AC11: 4.5 | AD11: 3.2 | AE11: 10.4 | AF11: 7.2 | AG11: 20.4 | AH11: 20.4 | AI11: 19.6 | AJ11: 7.2 | AL11: 2.8 | AM11: 4.6 | AN11: 3.6 | AO11: 18.6 | AT11: 3.4 | AW11: 1.9 | AX11: 9.9 | AY11: 6.9 | BA11: 11 | BC11: 0.6 | BE11: 8.2 | BF11: 26.9 | BG11: 20 | BH11: 2.1 | BI11: 1 | BJ11: 2.3 | BK11: 2 | BM11: 0.6 | BN11: 20 | BO11: 6.9 | BQ11: 13 | BR11: 631.7
B12: 2:30 | C12: 14.5 | E12: 7.5 | F12: 11.1 | G12: 20.1 | H12: 2.6 | J12: 9.5 | L12: 9.6 | N12: 19.2 | O12: 20.2 | P12: 6.6 | Q12: 3.5 | R12: 5 | S12: 20 | T12: 9.4 | U12: 13.8 | V12: 7.8 | W12: 17.9 | X12: 16.7 | Y12: 31.8 | Z12: 54.6 | AA12: 72.5 | AC12: 5.8 | AD12: 3 | AE12: 10.4 | AF12: 7 | AG12: 20.4 | AH12: 20.4 | AI12: 19.6 | AJ12: 7.2 | AL12: 5.2 | AM12: 8.2 | AN12: 3.6 | AO12: 18.6 | AT12: 3.4 | AW12: 2 | AX12: 9.9 | AY12: 9 | BA12: 12.3 | BC12: 0.6 | BE12: 8.9 | BF12: 27.3 | BG12: 19.9 | BH12: 2.1 | BI12: 1 | BJ12: 2.3 | BK12: 2 | BM12: 0.6 | BN12: 20 | BO12: 7 | BQ12: 6.8 | BR12: 638.4
B13: 3:00 | C13: 14.7 | E13: 7.5 | F13: 11.1 | G13: 20.2 | H13: 2.5 | J13: 9.5 | L13: 9.6 | N13: 19.1 | O13: 20.3 | P13: 6.6 | Q13: 3.5 | R13: 5.2 | S13: 19.9 | T13: 7.3 | U13: 14.2 | V13: 7.7 | W13: 16.2 | X13: 14.1 | Y13: 31.4 | Z13: 57.2 | AA13: 77.4 | AC13: 5.3 | AD13: 4.1 | AE13: 10.4 | AF13: 7 | AG13: 20.4 | AH13: 20.4 | AI13: 19.6 | AJ13: 6.7 | AL13: 5.8 | AM13: 8.2 | AN13: 3.6 | AO13: 18.6 | AT13: 3.4 | AW13: 1.9 | AX13: 9.9 | AY13: 15.9 | BA13: 19.6 | BC13: 0.6 | BE13: 8 | BF13: 25.5 | BG13: 20 | BH13: 2.1 | BI13: 1 | BJ13: 2.3 | BK13: 2 | BM13: 0.6 | BN13: 20 | BO13: 7 | BQ13: 6.6 | BR13: 651.7
B14: 3:30 | C14: 14.5 | E14: 9 | F14: 11.1 | G14: 20.2 | H14: 2.4 | J14: 9.5 | L14: 9.6 | N14: 18.9 | O14: 20.2 | P14: 6.6 | Q14: 3.3 | R14: 5 | S14: 20 | T14: 6.9 | U14: 14.5 | V14: 8.5 | W14: 23.1 | X14: 11.4 | Y14: 32.2 | Z14: 52 | AA14: 73.4 | AC14: 5.3 | AD14: 1.8 | AE14: 10.4 | AF14: 6.8 | AG14: 20.4 | AH14: 20.4 | AI14: 19.6 | AJ14: 6.7 | AL14: 6.1 | AM14: 7.6 | AN14: 3.6 | AO14: 18.6 | AT14: 3.4 | AW14: 3 | AX14: 9.9 | AY14: 13.9 | BA14: 21.6 | BC14: 0.6 | BE14: 7.1 | BF14: 23.6 | BG14: 20 | BH14: 2.1 | BI14: 1 | BJ14: 2.3 | BK14: 2 | BM14: 0.6 | BN14: 20 | BO14: 6.9 | BQ14: 6.4 | BR14: 644
B15: 4:00 | C15: 14.9 | E15: 7.3 | F15: 11.1 | G15: 20.2 | H15: 2.4 | J15: 9.6 | L15: 9.6 | N15: 18.4 | O15: 20.3 | P15: 6.6 | Q15: 3.4 | R15: 5 | S15: 19.9 | T15: 7.1 | U15: 14.5 | V15: 8.5 | W15: 26.4 | X15: 12.7 | Y15: 26.3 | Z15: 66.1 | AA15: 80.4 | AC15: 7.6 | AD15: 3.7 | AE15: 10.4 | AF15: 6.7 | AG15: 20.4 | AH15: 20.4 | AI15: 19.6 | AJ15: 6.7 | AL15: 4.5 | AM15: 5.6 | AN15: 3.6 | AO15: 18.6 | AT15: 3.4 | AW15: 4.2 | AX15: 9.9 | AY15: 19.3 | BA15: 32.1 | BC15: 0.6 | BE15: 6.4 | BF15: 20.4 | BG15: 20 | BH15: 2.1 | BI15: 1 | BJ15: 2.3 | BK15: 2 | BM15: 0.6 | BN15: 20 | BO15: 6.9 | BQ15: 6.5 | BR15: 676.2
B16: 4:30 | C16: 15.2 | E16: 8.8 | F16: 11.1 | G16: 20.2 | H16: 2.4 | J16: 9.5 | L16: 9.6 | N16: 18.4 | O16: 20.1 | P16: 6.6 | Q16: 3.4 | R16: 5 | S16: 20 | T16: 14.2 | U16: 14.3 | V16: 8.5 | W16: 26.5 | X16: 11.1 | Y16: 29 | Z16: 52 | AA16: 77.4 | AC16: 4.6 | AD16: 2 | AE16: 10.4 | AF16: 6.5 | AG16: 20.4 | AH16: 20.4 | AI16: 19.6 | AJ16: 6.9 | AL16: 4.8 | AM16: 7.3 | AN16: 3.6 | AO16: 18.6 | AT16: 3.4 | AW16: 4.4 | AX16: 9.9 | AY16: 28.9 | BA16: 40.1 | BC16: 0.6 | BE16: 6.2 | BF16: 23 | BG16: 20 | BH16: 2.1 | BI16: 1 | BJ16: 2.3 | BK16: 2 | BM16: 0.6 | BN16: 20 | BO16: 7 | BQ16: 10.1 | BR16: 690
B17: 5:00 | C17: 14.6 | E17: 7.9 | F17: 11.1 | G17: 19.6 | H17: 2.3 | J17: 9.3 | L17: 9.6 | N17: 18.5 | O17: 20.2 | P17: 6.6 | Q17: 3.4 | R17: 5 | S17: 20 | T17: 19.1 | U17: 14.3 | V17: 8.5 | W17: 25.9 | X17: 14 | Y17: 27.3 | Z17: 47.8 | AA17: 77.1 | AC17: 5.1 | AD17: 3.1 | AE17: 10.4 | AF17: 6.4 | AG17: 20.4 | AH17: 20.4 | AI17: 19.6 | AJ17: 6.9 | AL17: 6.3 | AM17: 8.8 | AN17: 3.6 | AO17: 18.6 | AT17: 3.4 | AV17: 0.1 | AW17: 4.3 | AX17: 9.9 | AY17: 35 | BA17: 45.4 | BC17: 0.6 | BE17: 6.3 | BF17: 22.7 | BG17: 20 | BH17: 2.1 | BI17: 1 | BJ17: 2.3 | BK17: 2 | BM17: 0.6 | BN17: 20 | BO17: 7 | BQ17: 8.5 | BR17: 702.9
B18: 5:30 | C18: 15.7 | E18: 8.3 | F18: 11.1 | G18: 15.3 | H18: 2.3 | J18: 9.5 | L18: 9.5 | N18: 19.1 | O18: 20.2 | P18: 6.6 | Q18: 3.5 | R18: 4.9 | S18: 20 | T18: 20 | U18: 14.9 | V18: 8.5 | W18: 23.1 | X18: 17.3 | Y18: 34.5 | Z18: 48.8 | AA18: 70.6 | AB18: 0.5 | AC18: 4.7 | AD18: 1.5 | AE18: 10.4 | AF18: 6.3 | AG18: 20.4 | AH18: 20.4 | AI18: 19.6 | AJ18: 6.9 | AK18: 0.5 | AL18: 10.7 | AM18: 11.3 | AN18: 3.6 | AO18: 18.6 | AQ18: 3.5 | AR18: 2.9 | AT18: 3.4 | AV18: 3.2 | AW18: 4.4 | AX18: 9.9 | AY18: 32.4 | AZ18: 3.2 | BA18: 43.2 | BB18: 2.5 | BC18: 0.6 | BD18: 3.3 | BE18: 10.7 | BF18: 25.2 | BG18: 19.9 | BH18: 2.1 | BI18: 1 | BJ18: 2.3 | BK18: 2 | BM18: 0.6 | BN18: 20 | BO18: 6.9 | BP18: 0.4 | BQ18: 20 | BR18: 742.7
B19: 6:00 | C19: 15.7 | D19: 3.1 | E19: 7 | F19: 11.1 | G19: 15.1 | H19: 2.3 | J19: 9.5 | L19: 9.4 | N19: 19.3 | O19: 20.2 | P19: 6.6 | Q19: 3.3 | R19: 4.9 | S19: 20 | T19: 20.5 | U19: 14.9 | V19: 8.5 | W19: 21 | X19: 19.2 | Y19: 38.9 | Z19: 47.8 | AA19: 70.5 | AB19: 7.5 | AC19: 5.5 | AD19: 2.4 | AE19: 10.4 | AF19: 6.2 | AG19: 20.4 | AH19: 20.4 | AI19: 19.6 | AJ19: 7.1 | AK19: 19.8 | AL19: 6.6 | AM19: 9.6 | AN19: 3.6 | AO19: 18.6 | AQ19: 62 | AR19: 38.5 | AT19: 3.4 | AU19: 0.7 | AV19: 10.3 | AW19: 4.4 | AX19: 9.9 | AY19: 23.7 | AZ19: 36.9 | BA19: 34.1 | BB19: 30.9 | BC19: 0.6 | BD19: 11.3 | BE19: 8.5 | BF19: 22.9 | BG19: 19.9 | BH19: 2.1 | BI19: 1 | BJ19: 2.3 | BK19: 2 | BL19: 0.7 | BM19: 0.6 | BN19: 20 | BO19: 6.6 | BP19: 1 | BQ19: 20.3 | BR19: 921.1
B20: 6:30 | C20: 15 | D20: 4.6 | E20: 8.1 | F20: 11.1 | G20: 14.9 | H20: 2.2 | J20: 9.5 | L20: 9.6 | N20: 19.5 | O20: 20.3 | P20: 6.6 | Q20: 3.4 | R20: 5 | S20: 20 | T20: 20.2 | U20: 14.9 | V20: 8.5 | W20: 20.8 | X20: 18.4 | Y20: 44.6 | Z20: 43.1 | AA20: 61.8 | AB20: 20.3 | AC20: 5 | AD20: 2.1 | AE20: 10.4 | AF20: 6 | AG20: 20.4 | AH20: 20.4 | AI20: 19.6 | AJ20: 7.1 | AK20: 46.4 | AL20: 9.7 | AM20: 11.4 | AN20: 3.6 | AO20: 18.6 | AQ20: 153.9 | AR20: 80.9 | AT20: 3.4 | AU20: 2.6 | AV20: 13.7 | AW20: 4.4 | AX20: 9.9 | AY20: 17.8 | AZ20: 86.3 | BA20: 28.2 | BB20: 70.1 | BC20: 0.6 | BD20: 16.5 | BE20: 10 | BF20: 24.5 | BG20: 19.9 | BH20: 2.1 | BI20: 1 | BJ20: 2.3 | BK20: 2 | BL20: 2.5 | BM20: 0.6 | BN20: 20 | BO20: 6.6 | BP20: 2.7 | BQ20: 20.1 | BR20: 1185.7
B21: 7:00 | C21: 6.3 | D21: 5.1 | E21: 6.6 | F21: 11.1 | G21: 15.1 | H21: 2.2 | J21: 9.5 | K21: 0.1 | L21: 9.8 | N21: 19.4 | O21: 20.3 | P21: 6.4 | Q21: 3.4 | R21: 5 | S21: 19.9 | T21: 20.6 | U21: 14.9 | V21: 8.5 | W21: 24.8 | X21: 22 | Y21: 47.2 | Z21: 43.3 | AA21: 58 | AB21: 30.8 | AC21: 4.9 | AD21: 2.8 | AE21: 10.4 | AF21: 6 | AG21: 20.4 | AH21: 20.4 | AI21: 19.6 | AJ21: 7.1 | AK21: 68.8 | AL21: 11.4 | AM21: 10.9 | AN21: 3.5 | AO21: 18.6 | AQ21: 229.1 | AR21: 181.4 | AT21: 3.4 | AU21: 5.3 | AV21: 14.2 | AW21: 4.5 | AX21: 9.9 | AY21: 10 | AZ21: 129.8 | BA21: 18.6 | BB21: 95.5 | BC21: 0.6 | BD21: 17.4 | BE21: 12.8 | BF21: 28.6 | BG21: 20 | BH21: 2.1 | BI21: 1 | BJ21: 2.3 | BK21: 2 | BL21: 4.9 | BM21: 0.6 | BN21: 20 | BO21: 6.6 | BP21: 12.4 | BQ21: 20.5 | BR21: 1468.6
B22: 7:30 | C22: 6.5 | D22: 5.1 | E22: 8.6 | F22: 11.1 | G22: 15.2 | H22: 2.2 | J22: 9.3 | K22: 0.1 | L22: 10 | N22: 18.9 | O22: 20 | P22: 6.4 | Q22: 3.4 | R22: 4.9 | S22: 20 | T22: 19 | U22: 14.9 | V22: 8.5 | W22: 25.5 | X22: 26.6 | Y22: 55.2 | Z22: 48.5 | AA22: 68.1 | AB22: 35.8 | AC22: 4.4 | AD22: 3.5 | AE22: 10.4 | AF22: 5.9 | AG22: 20.4 | AH22: 20.4 | AI22: 19.6 | AJ22: 7.1 | AK22: 76.5 | AL22: 11.2 | AM22: 9.1 | AN22: 3.5 | AO22: 18.6 | AQ22: 245.7 | AR22: 196.8 | AS22: 0.1 | AT22: 3.4 | AU22: 7.8 | AV22: 14.6 | AW22: 4.3 | AX22: 9.9 | AY22: 7.8 | AZ22: 141.3 | BA22: 10.4 | BB22: 101.3 | BC22: 0.6 | BD22: 18.2 | BE22: 10.2 | BF22: 24.8 | BG22: 19.7 | BH22: 2.1 | BI22: 1 | BJ22: 2.3 | BK22: 2 | BL22: 7.5 | BM22: 0.5 | BN22: 20 | BO22: 6.6 | BP22: 17.1 | BQ22: 19.1 | BR22: 1549.5
B23: 8:00 | C23: 4.9 | D23: 16.3 | E23: 9.4 | F23: 11 | G23: 15.2 | H23: 2.2 | J23: 9.3 | K23: 0.4 | L23: 10 | N23: 18.3 | O23: 20.2 | P23: 6.6 | Q23: 2.9 | R23: 4.9 | S23: 20 | T23: 20.4 | U23: 14.9 | V23: 8.5 | W23: 25.9 | X23: 29.6 | Y23: 69.2 | Z23: 63.2 | AA23: 77.7 | AB23: 36.6 | AC23: 8.3 | AD23: 4.8 | AE23: 10.4 | AF23: 5.9 | AG23: 20.4 | AH23: 20.4 | AI23: 19.6 | AJ23: 7.4 | AK23: 78.4 | AL23: 12.9 | AM23: 11.9 | AN23: 3.5 | AO23: 18.6 | AQ23: 252.9 | AR23: 205.3 | AS23: 0.2 | AT23: 3.4 | AU23: 10.2 | AV23: 14.9 | AW23: 4.3 | AX23: 9.9 | AY23: 9.3 | AZ23: 145.6 | BA23: 8.1 | BB23: 104.7 | BC23: 0.6 | BD23: 18.8 | BE23: 13.2 | BF23: 28.7 | BG23: 19.6 | BH23: 2.1 | BI23: 1 | BJ23: 2.3 | BK23: 2 | BL23: 9.9 | BM23: 0.5 | BN23: 20 | BO23: 6.6 | BP23: 17.4 | BQ23: 20 | BR23: 1651.6
B24: 8:30 | C24: 7 | D24: 17 | E24: 8 | F24: 11.1 | G24: 15.2 | H24: 2.1 | J24: 9.3 | K24: 0.8 | L24: 10 | N24: 18.2 | O24: 20.3 | P24: 6.5 | Q24: 2.5 | R24: 4.8 | S24: 20 | T24: 20.5 | U24: 14.9 | V24: 8.5 | W24: 24.2 | X24: 26.1 | Y24: 79.7 | Z24: 66.7 | AA24: 80.7 | AB24: 37 | AC24: 9.6 | AD24: 4.4 | AE24: 10.4 | AF24: 5.5 | AG24: 20.4 | AH24: 20.4 | AI24: 19.6 | AJ24: 7.3 | AK24: 78.4 | AL24: 9.8 | AM24: 9.7 | AN24: 3.6 | AO24: 18.6 | AQ24: 253 | AR24: 210.8 | AS24: 0.2 | AT24: 3.4 | AU24: 12.4 | AV24: 15.1 | AW24: 5.3 | AX24: 9.9 | AY24: 6.7 | AZ24: 148.5 | BA24: 4 | BB24: 107.1 | BC24: 0.6 | BD24: 19 | BE24: 15.9 | BF24: 38.3 | BG24: 19.5 | BH24: 2.1 | BI24: 1 | BJ24: 2.3 | BK24: 2 | BL24: 12.1 | BM24: 0.5 | BN24: 20 | BO24: 6.6 | BP24: 17.7 | BQ24: 19.1 | BR24: 1681.9
B25: 9:00 | C25: 6.5 | D25: 18 | E25: 8.6 | F25: 11.1 | G25: 15.3 | H25: 2.1 | J25: 8.7 | K25: 1 | L25: 10.1 | N25: 17.8 | O25: 20.2 | P25: 6.3 | Q25: 3.4 | R25: 4.8 | S25: 20 | T25: 20.1 | U25: 14.9 | V25: 8.5 | W25: 20.9 | X25: 35.5 | Y25: 94.7 | Z25: 73.6 | AA25: 87.4 | AB25: 37.4 | AC25: 11 | AD25: 4.6 | AE25: 10.4 | AF25: 5.6 | AG25: 20.4 | AH25: 20.4 | AI25: 19.6 | AJ25: 7.4 | AK25: 79.2 | AL25: 9.2 | AM25: 9.1 | AN25: 3.5 | AO25: 18.6 | AQ25: 253 | AR25: 208.3 | AS25: 0.3 | AT25: 3.4 | AU25: 14 | AV25: 15.2 | AW25: 5.4 | AX25: 9.9 | AY25: 4.2 | AZ25: 150.2 | BA25: 0.3 | BB25: 108.7 | BC25: 0.6 | BD25: 19.2 | BE25: 20.7 | BF25: 50.4 | BG25: 19.4 | BH25: 2.1 | BI25: 1 | BJ25: 2.3 | BK25: 2 | BL25: 13.7 | BM25: 0.5 | BN25: 20.1 | BO25: 6.6 | BP25: 17.9 | BQ25: 19.9 | BR25: 1735.2
B26: 9:30 | C26: 7.6 | D26: 18.6 | E26: 6.7 | F26: 11.1 | G26: 15.3 | J26: 9.5 | K26: 1.1 | L26: 10 | N26: 17.4 | O26: 20.2 | P26: 5.9 | Q26: 3.5 | R26: 4.9 | S26: 20 | T26: 19.9 | U26: 14.7 | V26: 8.5 | W26: 17.1 | X26: 39 | Y26: 100.8 | Z26: 79.6 | AA26: 89.9 | AB26: 37.5 | AC26: 13.3 | AD26: 6.5 | AE26: 10.4 | AF26: 5.6 | AG26: 20.4 | AH26: 20.4 | AI26: 19.6 | AJ26: 6.9 | AK26: 80.4 | AL26: 9.7 | AM26: 9.8 | AN26: 3.6 | AO26: 18.6 | AQ26: 249.8 | AR26: 209.1 | AS26: 0.3 | AT26: 3.4 | AU26: 15.3 | AV26: 15.4 | AW26: 5.4 | AX26: 9.9 | AY26: 3.2 | AZ26: 150.6 | BB26: 109.7 | BC26: 0.6 | BD26: 19.4 | BE26: 21 | BF26: 63.7 | BG26: 19.2 | BH26: 2.1 | BI26: 1 | BJ26: 2.3 | BK26: 2 | BL26: 14.8 | BM26: 0.8 | BN26: 20 | BO26: 6.6 | BP26: 18.9 | BQ26: 20.3 | BR26: 1768.8
B27: 10:00 | C27: 6.8 | D27: 18.7 | E27: 7.5 | F27: 11.1 | G27: 15.3 | J27: 9.1 | K27: 1.1 | L27: 10 | N27: 17.4 | O27: 20.1 | P27: 5.9 | Q27: 3.4 | R27: 4.9 | S27: 20 | T27: 20.1 | U27: 14.4 | V27: 8.5 | W27: 12.2 | X27: 46.1 | Y27: 106.8 | Z27: 86.5 | AA27: 93.2 | AB27: 38 | AC27: 14.4 | AD27: 8.8 | AE27: 10.4 | AF27: 5.9 | AG27: 20.4 | AH27: 20.4 | AI27: 19.6 | AJ27: 6.7 | AK27: 80.7 | AL27: 11.7 | AM27: 10.9 | AN27: 3.5 | AO27: 18.6 | AQ27: 253.3 | AR27: 223.3 | AS27: 0.4 | AT27: 3.4 | AU27: 16.5 | AV27: 15.4 | AW27: 5 | AX27: 9.9 | AY27: 14.4 | AZ27: 150.3 | BB27: 109.9 | BC27: 0.6 | BD27: 19.4 | BE27: 19.7 | BF27: 60.1 | BG27: 19.2 | BH27: 2.1 | BI27: 1 | BJ27: 2.3 | BK27: 2 | BL27: 17.1 | BM27: 1.1 | BN27: 20.1 | BO27: 6.6 | BP27: 19.8 | BQ27: 20.7 | BR27: 1822.7
B28: 10:30 | C28: 7.5 | D28: 19.1 | E28: 8.2 | F28: 11.1 | G28: 15.4 | J28: 9.4 | K28: 1.2 | L28: 10 | N28: 17.5 | O28: 20.2 | P28: 5.9 | Q28: 3.4 | R28: 4.8 | S28: 20 | T28: 20 | U28: 14.5 | V28: 8.5 | W28: 7.9 | X28: 53.4 | Y28: 96.9 | Z28: 99.8 | AA28: 97.3 | AB28: 37.9 | AC28: 15.1 | AD28: 10.3 | AE28: 10.4 | AF28: 6.1 | AG28: 20.4 | AH28: 20.4 | AI28: 19.6 | AJ28: 6.6 | AK28: 80.6 | AL28: 11.3 | AM28: 9.6 | AN28: 3.6 | AO28: 18.6 | AQ28: 252.8 | AR28: 220.9 | AS28: 0.4 | AT28: 3.4 | AU28: 17.9 | AV28: 15.4 | AW28: 4 | AX28: 9.9 | AY28: 13.8 | AZ28: 151.2 | BA28: 0.9 | BB28: 110.4 | BC28: 0.6 | BD28: 19.3 | BE28: 18.4 | BF28: 62.8 | BG28: 19 | BH28: 2.1 | BI28: 1 | BJ28: 2.3 | BK28: 2 | BL28: 17.6 | BM28: 1.1 | BN28: 20.1 | BO28: 6.6 | BP28: 19.8 | BQ28: 20.3 | BR28: 1836.5
B29: 11:00 | C29: 6.3 | D29: 19.1 | E29: 8.7 | F29: 11.1 | G29: 15.3 | H29: 1 | J29: 9.4 | K29: 1.3 | L29: 10 | N29: 17.5 | O29: 20.2 | P29: 5.9 | Q29: 3.4 | R29: 4.7 | S29: 20 | T29: 20.3 | U29: 14 | V29: 8.5 | W29: 12 | X29: 58.6 | Y29: 102 | Z29: 99.5 | AA29: 96.8 | AB29: 38.7 | AC29: 16.3 | AD29: 10.3 | AE29: 10.4 | AF29: 6.7 | AG29: 20.4 | AH29: 20.4 | AI29: 19.6 | AJ29: 6.6 | AK29: 80.6 | AL29: 12.5 | AM29: 10.6 | AN29: 3.6 | AO29: 18.6 | AQ29: 253 | AR29: 218.9 | AS29: 0.4 | AT29: 3.4 | AU29: 18.7 | AV29: 15.6 | AW29: 4.7 | AX29: 9.9 | AY29: 24.6 | AZ29: 147.6 | BA29: 4 | BB29: 107.9 | BC29: 0.6 | BD29: 19 | BE29: 18.4 | BF29: 62.4 | BG29: 19 | BH29: 2.1 | BI29: 1 | BJ29: 2.3 | BK29: 2 | BL29: 18.5 | BM29: 1.1 | BN29: 20.1 | BO29: 6.6 | BP29: 19.7 | BQ29: 20.3 | BR29: 1862.7
B30: 11:30 | C30: 6.7 | D30: 19.1 | E30: 8.6 | F30: 11.1 | G30: 15.2 | H30: 2 | J30: 9.5 | K30: 1.3 | L30: 10 | N30: 17.2 | O30: 20.1 | P30: 6 | Q30: 3.4 | R30: 4.9 | S30: 20 | T30: 19.9 | U30: 14 | V30: 8.5 | W30: 22.1 | X30: 66.4 | Y30: 103.8 | Z30: 104.7 | AA30: 99.9 | AB30: 38.6 | AC30: 16.7 | AD30: 10.9 | AE30: 10.4 | AF30: 7.5 | AG30: 20.4 | AH30: 20.4 | AI30: 19.6 | AJ30: 6.6 | AK30: 80.6 | AL30: 13.4 | AM30: 9.8 | AN30: 3.6 | AO30: 18.6 | AQ30: 252.8 | AR30: 223.1 | AS30: 0.5 | AT30: 3.4 | AU30: 18.6 | AV30: 15.8 | AW30: 4.7 | AX30: 9.9 | AY30: 25 | AZ30: 152.7 | BA30: 5.5 | BB30: 111.9 | BC30: 0.6 | BD30: 18.8 | BE30: 21.6 | BF30: 68.7 | BG30: 19 | BH30: 2.1 | BI30: 1 | BJ30: 2.3 | BK30: 2 | BL30: 18.7 | BM30: 1.1 | BN30: 20 | BO30: 6.6 | BP30: 19.6 | BQ30: 18 | BR30: 1915.5
B31: 12:00 | C31: 6.1 | D31: 19.1 | E31: 7.1 | F31: 11.1 | G31: 15.2 | H31: 2 | J31: 9.5 | K31: 1.3 | L31: 10 | N31: 17.1 | O31: 20 | P31: 6 | Q31: 3.4 | R31: 4.9 | S31: 20 | T31: 20.1 | U31: 13.6 | V31: 8.5 | W31: 18.6 | X31: 59.1 | Y31: 100.9 | Z31: 101.3 | AA31: 100.4 | AB31: 38.6 | AC31: 16.7 | AD31: 10.8 | AE31: 10.4 | AF31: 7.7 | AG31: 20.4 | AH31: 20.4 | AI31: 19.6 | AJ31: 6.6 | AK31: 80.6 | AL31: 13.9 | AM31: 11.8 | AN31: 3.6 | AO31: 18.6 | AQ31: 253 | AR31: 221 | AS31: 0.5 | AT31: 3.4 | AU31: 18.8 | AV31: 16 | AW31: 4.8 | AX31: 10 | AY31: 33.7 | AZ31: 153 | BA31: 13.8 | BB31: 111.7 | BC31: 0.6 | BD31: 19.3 | BE31: 23.3 | BF31: 66.7 | BG31: 19.1 | BH31: 2.1 | BI31: 1 | BJ31: 2.3 | BK31: 2 | BL31: 18.1 | BM31: 1.1 | BN31: 20 | BO31: 6.6 | BP31: 19.7 | BQ31: 17.7 | BR31: 1914.3
B32: 12:30 | C32: 6.4 | D32: 19.1 | E32: 7.5 | F32: 11.1 | G32: 14.8 | H32: 2 | J32: 9.3 | K32: 1.3 | L32: 10 | N32: 17.1 | O32: 20 | P32: 5.7 | Q32: 3.3 | R32: 4.8 | S32: 19.8 | T32: 19.7 | U32: 13.6 | V32: 8.5 | W32: 17.9 | X32: 63.7 | Y32: 95.5 | Z32: 106.7 | AA32: 91.9 | AB32: 38 | AC32: 17.4 | AD32: 11 | AE32: 10.4 | AF32: 8 | AG32: 20.4 | AH32: 20.4 | AI32: 19.6 | AJ32: 6.6 | AK32: 80.7 | AL32: 11.1 | AM32: 9.5 | AN32: 3.6 | AO32: 18.6 | AQ32: 253 | AR32: 223.5 | AS32: 0.5 | AT32: 3.4 | AU32: 18.6 | AV32: 15.8 | AW32: 5.3 | AX32: 10 | AY32: 41.7 | AZ32: 153.6 | BA32: 28.1 | BB32: 111.2 | BC32: 0.6 | BD32: 19.2 | BE32: 21.1 | BF32: 68.9 | BG32: 18.8 | BH32: 2.1 | BI32: 1 | BJ32: 2.3 | BK32: 2 | BL32: 17.9 | BM32: 1.1 | BN32: 19.8 | BO32: 6.6 | BP32: 19.7 | BQ32: 16.8 | BR32: 1927.6
B33: 13:00 | C33: 6.6 | D33: 19.1 | E33: 9 | F33: 11.1 | G33: 14.9 | H33: 2 | J33: 9.3 | K33: 1.3 | L33: 10 | N33: 17.7 | O33: 20.2 | P33: 5.7 | Q33: 3.4 | R33: 4.8 | S33: 20 | T33: 20.5 | U33: 13.2 | V33: 8.4 | W33: 20 | X33: 67.1 | Y33: 93.7 | Z33: 96 | AA33: 93.4 | AB33: 39.2 | AC33: 14.5 | AD33: 10.2 | AE33: 10.4 | AF33: 8.1 | AG33: 20.4 | AH33: 20.4 | AI33: 19.6 | AJ33: 6.6 | AK33: 80.5 | AL33: 12.2 | AM33: 10.6 | AN33: 3.6 | AO33: 18.6 | AQ33: 253.1 | AR33: 223.8 | AS33: 0.4 | AT33: 3.4 | AU33: 18.2 | AV33: 15.7 | AW33: 5.6 | AX33: 10.2 | AY33: 57.6 | AZ33: 154.8 | BA33: 45.8 | BB33: 112.5 | BC33: 0.6 | BD33: 19.1 | BE33: 22.1 | BF33: 67.5 | BG33: 18.5 | BH33: 2.1 | BI33: 1 | BJ33: 2.3 | BK33: 2 | BL33: 18 | BM33: 1.1 | BN33: 20 | BO33: 6.6 | BP33: 19.6 | BQ33: 15.9 | BR33: 1959.8
B34: 13:30 | C34: 6.9 | D34: 19.1 | E34: 8.1 | F34: 11.1 | G34: 15 | H34: 2 | J34: 9.3 | K34: 1.2 | L34: 10 | N34: 18 | O34: 20.2 | P34: 5.6 | Q34: 3.4 | R34: 4.8 | S34: 20 | T34: 20.6 | U34: 13.2 | V34: 8.5 | W34: 17.6 | X34: 67 | Y34: 84.8 | Z34: 96.2 | AA34: 94.5 | AB34: 38.8 | AC34: 14.9 | AD34: 10.2 | AE34: 10.4 | AF34: 8.2 | AG34: 20 | AH34: 20.4 | AI34: 19.6 | AJ34: 6.8 | AK34: 80.7 | AL34: 11.9 | AM34: 9.6 | AN34: 3.6 | AO34: 18.6 | AQ34: 253 | AR34: 222.5 | AS34: 0.4 | AT34: 3.4 | AU34: 17.1 | AV34: 15.9 | AW34: 5.5 | AX34: 9.9 | AY34: 62.2 | AZ34: 154.3 | BA34: 63.8 | BB34: 111.2 | BC34: 0.6 | BD34: 19.3 | BE34: 20.8 | BF34: 67.8 | BG34: 18.5 | BH34: 2.1 | BI34: 1 | BJ34: 2.3 | BK34: 2 | BL34: 17 | BM34: 1.1 | BN34: 20 | BO34: 6.6 | BP34: 19.7 | BQ34: 15.3 | BR34: 1964.1
B35: 14:00 | C35: 5.8 | D35: 19.1 | E35: 8.8 | F35: 11.1 | G35: 15 | H35: 2 | J35: 9.4 | K35: 1.1 | L35: 10 | N35: 18 | O35: 20.2 | P35: 5.6 | Q35: 3.4 | R35: 4.6 | S35: 20 | T35: 20.5 | U35: 13.6 | V35: 8.5 | W35: 16.3 | X35: 65.4 | Y35: 88.6 | Z35: 95.1 | AA35: 92.1 | AB35: 39.2 | AC35: 15 | AD35: 10.5 | AE35: 10.4 | AF35: 8.3 | AG35: 20 | AH35: 20.4 | AI35: 19.6 | AJ35: 6.8 | AK35: 80.6 | AL35: 14.5 | AM35: 11 | AN35: 3.6 | AO35: 18.6 | AQ35: 253.1 | AR35: 219.9 | AS35: 0.4 | AT35: 3.4 | AU35: 15.8 | AV35: 15.7 | AW35: 5.4 | AX35: 9.9 | AY35: 92.3 | AZ35: 151.5 | BA35: 77.9 | BB35: 109.2 | BC35: 0.6 | BD35: 19 | BE35: 21.1 | BF35: 64 | BG35: 18.4 | BH35: 2.1 | BI35: 1 | BJ35: 2.3 | BK35: 2 | BL35: 15.7 | BM35: 1.2 | BN35: 20.2 | BO35: 6.6 | BP35: 19.5 | BQ35: 14.7 | BR35: 1995.6
B36: 14:30 | C36: 6.6 | D36: 19.1 | E36: 6.9 | F36: 11.1 | G36: 15 | H36: 2.1 | J36: 9.4 | K36: 1 | L36: 10 | N36: 19.1 | O36: 20.2 | P36: 5.7 | Q36: 3.4 | R36: 4.6 | S36: 20.1 | T36: 20.3 | U36: 13.8 | V36: 8.5 | W36: 14 | X36: 63.2 | Y36: 85.8 | Z36: 90.1 | AA36: 85.1 | AB36: 38.5 | AC36: 14.1 | AD36: 10.8 | AE36: 10.4 | AF36: 8.2 | AG36: 20 | AH36: 20.4 | AI36: 19.6 | AJ36: 7 | AK36: 80.6 | AL36: 12.9 | AM36: 12 | AN36: 3.6 | AO36: 18.6 | AQ36: 250.2 | AR36: 217.2 | AS36: 0.4 | AT36: 3.4 | AU36: 14.2 | AV36: 15.5 | AW36: 5.4 | AX36: 9.9 | AY36: 106 | AZ36: 152.3 | BA36: 103.9 | BB36: 110 | BC36: 0.6 | BD36: 18.8 | BE36: 19.1 | BF36: 66.4 | BG36: 18.1 | BH36: 2.1 | BI36: 1 | BJ36: 2.3 | BK36: 2 | BL36: 14 | BM36: 1.2 | BN36: 20.2 | BO36: 6.6 | BP36: 19.3 | BQ36: 12.8 | BR36: 2004.7
B37: 15:00 | C37: 8.2 | D37: 19 | E37: 8.1 | F37: 11.1 | G37: 15.1 | H37: 2.2 | J37: 9.4 | K37: 0.9 | L37: 10 | N37: 19.8 | O37: 20.2 | P37: 5.7 | Q37: 3.4 | R37: 4.6 | S37: 20 | T37: 20.4 | U37: 13.8 | V37: 8.5 | W37: 11.7 | X37: 57.9 | Y37: 86.5 | Z37: 88.1 | AA37: 82.2 | AB37: 38.1 | AC37: 12.6 | AD37: 7.1 | AE37: 10.4 | AF37: 8.2 | AG37: 20.4 | AH37: 20.4 | AI37: 19.6 | AJ37: 6.7 | AK37: 80.6 | AL37: 17 | AM37: 11.5 | AN37: 3.5 | AO37: 18.6 | AQ37: 241.4 | AR37: 210.7 | AS37: 0.3 | AT37: 3.4 | AU37: 12.2 | AV37: 15.2 | AW37: 5.3 | AX37: 9.9 | AY37: 120.7 | AZ37: 150.3 | BA37: 125.7 | BB37: 108.1 | BC37: 0.6 | BD37: 18.4 | BE37: 20.6 | BF37: 61.7 | BG37: 18 | BH37: 2.1 | BI37: 1 | BJ37: 2.3 | BK37: 2 | BL37: 12.1 | BM37: 1.2 | BN37: 20 | BO37: 6.6 | BP37: 18.9 | BQ37: 13.2 | BR37: 2003.4
B38: 15:30 | C38: 6.8 | D38: 19 | E38: 6.8 | F38: 11.1 | G38: 15.1 | H38: 2.2 | J38: 9.3 | K38: 0.7 | L38: 10 | N38: 19.8 | O38: 20.2 | P38: 5.5 | Q38: 3.4 | R38: 4.9 | S38: 20 | T38: 20.5 | U38: 13.4 | V38: 8.5 | W38: 9 | X38: 70.7 | Y38: 87.3 | Z38: 78.6 | AA38: 81.7 | AB38: 36.8 | AC38: 12.5 | AD38: 7.5 | AE38: 10.5 | AF38: 8.2 | AG38: 20.4 | AH38: 20.4 | AI38: 19.6 | AJ38: 6.7 | AK38: 80.7 | AL38: 10.3 | AM38: 9.9 | AN38: 3.6 | AO38: 18.6 | AQ38: 222 | AR38: 206.5 | AS38: 0.3 | AT38: 3.4 | AU38: 10.1 | AV38: 14.1 | AW38: 5.4 | AX38: 9.8 | AY38: 126 | AZ38: 137 | BA38: 127.6 | BB38: 98.7 | BC38: 0.6 | BD38: 17 | BE38: 19.4 | BF38: 62.2 | BG38: 17.8 | BH38: 2.1 | BI38: 1 | BJ38: 2.3 | BK38: 2 | BL38: 9.8 | BM38: 1.2 | BN38: 20 | BO38: 6.6 | BP38: 17.6 | BQ38: 13.5 | BR38: 1944.2
B39: 16:00 | C39: 6.6 | D39: 19 | E39: 8.4 | F39: 11.1 | G39: 7.8 | H39: 2.2 | J39: 9.4 | K39: 0.6 | L39: 10 | N39: 19.9 | O39: 19.8 | P39: 5.4 | Q39: 3.3 | R39: 4.9 | S39: 19.8 | T39: 19.5 | U39: 12.8 | V39: 7.7 | W39: 6.1 | X39: 66.5 | Y39: 81.9 | Z39: 74.7 | AA39: 77.5 | AB39: 33 | AC39: 11.3 | AD39: 6.4 | AE39: 10.4 | AF39: 8.3 | AG39: 20.4 | AH39: 20.4 | AI39: 19.6 | AJ39: 6.7 | AK39: 75.3 | AL39: 9.2 | AM39: 6.9 | AN39: 3.6 | AO39: 18.6 | AQ39: 207.5 | AR39: 192.2 | AS39: 0.2 | AT39: 3.4 | AU39: 7.3 | AV39: 12.9 | AW39: 5.3 | AX39: 9.9 | AY39: 127.2 | AZ39: 135.8 | BA39: 127.3 | BB39: 98.4 | BC39: 0.6 | BD39: 15.6 | BE39: 22.5 | BF39: 70.3 | BG39: 17.7 | BH39: 2.1 | BI39: 1 | BJ39: 2.3 | BK39: 2 | BL39: 7.4 | BM39: 1.2 | BN39: 19.9 | BO39: 6.9 | BP39: 16.5 | BQ39: 11.9 | BR39: 1870.3
B40: 16:30 | C40: 6.2 | D40: 19 | E40: 7.5 | F40: 11.1 | G40: 4.8 | H40: 2.3 | J40: 9.4 | K40: 0.3 | L40: 10 | N40: 20.3 | O40: 20.2 | P40: 5.8 | Q40: 3.3 | R40: 4.8 | S40: 19.8 | T40: 20.9 | U40: 12.8 | V40: 7.7 | W40: 3.2 | X40: 62.9 | Y40: 78.6 | Z40: 69.1 | AA40: 77.4 | AB40: 24.1 | AC40: 10.6 | AD40: 5.4 | AE40: 10.4 | AF40: 8.3 | AG40: 20.4 | AH40: 20.4 | AI40: 19.6 | AJ40: 6.7 | AK40: 51.8 | AL40: 1 | AN40: 3.6 | AO40: 18.6 | AQ40: 159.7 | AR40: 138.6 | AS40: 0.2 | AT40: 3.4 | AU40: 4.8 | AV40: 9.9 | AW40: 5.4 | AX40: 9.9 | AY40: 138.5 | AZ40: 92.5 | BA40: 131.5 | BB40: 82.9 | BC40: 0.6 | BD40: 11.6 | BE40: 21.4 | BF40: 67.8 | BG40: 17.8 | BH40: 2.1 | BI40: 1 | BJ40: 2.3 | BK40: 2 | BL40: 4.8 | BM40: 1.2 | BN40: 20 | BO40: 6.8 | BQ40: 12.6 | BR40: 1627.6
B41: 17:00 | C41: 6.4 | D41: 19.1 | E41: 8.8 | F41: 11.1 | G41: 6.8 | H41: 2.4 | J41: 8.4 | K41: 0.2 | L41: 10 | N41: 20 | O41: 20.3 | P41: 5.6 | Q41: 3.3 | R41: 4.7 | S41: 20 | T41: 20.7 | U41: 12.8 | V41: 7.7 | W41: 3.9 | X41: 64 | Y41: 73.9 | Z41: 74 | AA41: 79.6 | AB41: 11.2 | AC41: 10.7 | AD41: 5.8 | AE41: 10.4 | AF41: 8.3 | AG41: 20.4 | AH41: 20.4 | AI41: 19.6 | AJ41: 6.7 | AK41: 21.9 | AL41: 0.5 | AN41: 3.5 | AO41: 18.6 | AQ41: 84.4 | AR41: 76.5 | AS41: 0.1 | AT41: 3.4 | AU41: 2.2 | AV41: 3.7 | AW41: 1.7 | AX41: 9.9 | AY41: 126.3 | AZ41: 44.9 | BA41: 132 | BB41: 43.1 | BC41: 0.6 | BD41: 4.1 | BE41: 19.4 | BF41: 67.6 | BG41: 17.3 | BH41: 2.1 | BI41: 1 | BJ41: 2.3 | BK41: 2 | BL41: 2.3 | BM41: 1.2 | BN41: 20 | BO41: 7.1 | BQ41: 11.8 | BR41: 1328.7
B42: 17:30 | C42: 6.6 | D42: 19 | E42: 7.8 | F42: 11.1 | G42: 16.9 | H42: 2.5 | J42: 9.3 | K42: 0.1 | L42: 10.1 | N42: 20 | O42: 20.2 | P42: 5.7 | Q42: 3.3 | R42: 4.7 | S42: 19.8 | T42: 20.6 | U42: 12.5 | V42: 7.7 | W42: 6.3 | X42: 59.2 | Y42: 87.7 | Z42: 66.4 | AA42: 68.9 | AB42: 1.7 | AC42: 11 | AD42: 5.8 | AE42: 10.4 | AF42: 8.3 | AG42: 20.4 | AH42: 20.4 | AI42: 19.6 | AJ42: 7 | AK42: 3.2 | AL42: 1.4 | AM42: 1 | AN42: 3.5 | AO42: 18.6 | AQ42: 18.8 | AR42: 6.7 | AS42: 0.1 | AT42: 3.4 | AU42: 0.4 | AV42: 0.1 | AW42: 1.9 | AX42: 9.9 | AY42: 128 | AZ42: 4.9 | BA42: 132.1 | BB42: 6.4 | BC42: 0.6 | BE42: 23.8 | BF42: 75.2 | BG42: 17.5 | BH42: 2.1 | BI42: 1 | BJ42: 2.3 | BK42: 2 | BL42: 0.5 | BM42: 1.2 | BN42: 19.8 | BO42: 7.1 | BQ42: 11.7 | BR42: 1096.2
B43: 18:00 | C43: 6.7 | D43: 19.1 | E43: 7.7 | F43: 11.1 | G43: 20.2 | H43: 2.7 | J43: 9.3 | L43: 10.1 | N43: 20.1 | O43: 20.3 | P43: 5.7 | Q43: 3.3 | R43: 4.9 | S43: 19.9 | T43: 20.7 | U43: 12.4 | V43: 7.7 | W43: 7.2 | X43: 50.6 | Y43: 96.6 | Z43: 64.4 | AA43: 73 | AC43: 8.5 | AD43: 4.8 | AE43: 10.4 | AF43: 8.3 | AG43: 20.4 | AH43: 20.4 | AI43: 19.6 | AJ43: 7 | AL43: 4.2 | AM43: 2.5 | AN43: 3.3 | AO43: 18.6 | AT43: 3.4 | AW43: 1.9 | AX43: 9.9 | AY43: 126.8 | BA43: 132.2 | BC43: 0.6 | BE43: 24.9 | BF43: 78.4 | BG43: 17.6 | BH43: 2.1 | BI43: 1 | BJ43: 2.3 | BK43: 2 | BM43: 1.2 | BN43: 20 | BO43: 7 | BQ43: 11.9 | BR43: 1064.9
B44: 18:30 | C44: 5.6 | D44: 19.1 | E44: 8.4 | F44: 11.1 | G44: 20.2 | H44: 2.9 | J44: 9.4 | L44: 10 | N44: 20.1 | O44: 20.2 | P44: 6.2 | Q44: 3.3 | R44: 4.9 | S44: 19.9 | T44: 20.6 | U44: 12.4 | V44: 7.7 | W44: 6.6 | X44: 44.2 | Y44: 90.4 | Z44: 62.3 | AA44: 75.1 | AC44: 7.8 | AD44: 7.4 | AE44: 10.5 | AF44: 8.3 | AG44: 20.4 | AH44: 20.4 | AI44: 19.6 | AJ44: 7 | AL44: 3.8 | AM44: 1.8 | AN44: 3.3 | AO44: 18.6 | AT44: 3.4 | AW44: 1.9 | AX44: 10 | AY44: 136.1 | BA44: 132.1 | BC44: 0.6 | BE44: 25.9 | BF44: 78.1 | BG44: 17.3 | BH44: 2.1 | BI44: 1 | BJ44: 2.3 | BK44: 2 | BM44: 1.2 | BN44: 20.1 | BO44: 7.2 | BQ44: 11.5 | BR44: 1062.3
B45: 19:00 | C45: 15.3 | D45: 19.1 | E45: 8.7 | F45: 11.1 | G45: 20.2 | H45: 3 | J45: 9.4 | L45: 10 | N45: 20.2 | O45: 20.2 | P45: 6.5 | Q45: 3.2 | R45: 4.7 | S45: 19.9 | T45: 20.8 | U45: 12.1 | V45: 7.7 | W45: 7 | X45: 36.6 | Y45: 82.3 | Z45: 68 | AA45: 81.2 | AC45: 10.2 | AD45: 8.1 | AE45: 10.4 | AF45: 8.3 | AG45: 20.4 | AH45: 20.4 | AI45: 19.6 | AJ45: 6.9 | AL45: 1.5 | AM45: 1.1 | AN45: 3.3 | AO45: 18.6 | AT45: 3.4 | AW45: 5.4 | AX45: 9.9 | AY45: 138 | BA45: 128.2 | BC45: 0.6 | BE45: 23.2 | BF45: 76.8 | BG45: 17.5 | BH45: 2.1 | BI45: 1 | BJ45: 2.3 | BK45: 2 | BM45: 1.2 | BN45: 20 | BO45: 7.1 | BQ45: 11.6 | BR45: 1066.3
B46: 19:30 | C46: 15.4 | D46: 19.1 | E46: 7.6 | F46: 5.7 | G46: 20.2 | H46: 3 | J46: 9.2 | L46: 10 | N46: 20.2 | O46: 20.2 | P46: 6.5 | Q46: 3.2 | R46: 4.7 | S46: 19.9 | T46: 20.6 | U46: 12 | V46: 7.7 | W46: 6.8 | X46: 35.1 | Y46: 74.1 | Z46: 70.9 | AA46: 96.3 | AC46: 10.6 | AD46: 9.7 | AE46: 10.4 | AF46: 8.3 | AG46: 20.4 | AH46: 20.4 | AI46: 19.6 | AJ46: 6.8 | AL46: 0.8 | AN46: 3.3 | AO46: 18.6 | AT46: 3.4 | AW46: 5.4 | AX46: 9.9 | AY46: 114.2 | BA46: 131.3 | BC46: 0.6 | BE46: 21.5 | BF46: 70.6 | BG46: 17.9 | BH46: 2.1 | BI46: 1 | BJ46: 2.3 | BK46: 2 | BM46: 1.2 | BN46: 20 | BO46: 7.1 | BQ46: 12.7 | BR46: 1040.5
B47: 20:00 | C47: 15.2 | D47: 17.1 | E47: 8.5 | F47: 6 | G47: 20.2 | H47: 3 | J47: 9 | L47: 10 | N47: 20.2 | O47: 20.2 | P47: 6.4 | Q47: 3.1 | R47: 4.7 | S47: 20 | T47: 20.6 | U47: 12 | V47: 7.8 | W47: 6.3 | X47: 31.1 | Y47: 76.2 | Z47: 91.4 | AA47: 97.8 | AC47: 9 | AD47: 7.2 | AE47: 10.5 | AF47: 8.3 | AG47: 20.4 | AH47: 20.4 | AI47: 19.6 | AJ47: 6.8 | AL47: 0.3 | AN47: 3.4 | AO47: 18.6 | AT47: 3.4 | AW47: 5.5 | AX47: 9.9 | AY47: 100.5 | BA47: 120.2 | BC47: 0.6 | BE47: 20.3 | BF47: 60 | BG47: 18.2 | BH47: 2.1 | BI47: 1 | BJ47: 2.3 | BK47: 2 | BM47: 1.2 | BN47: 20 | BO47: 7.1 | BQ47: 13.2 | BR47: 1018.8
B48: 20:30 | C48: 15 | D48: 16.3 | E48: 8.4 | F48: 11 | G48: 20.2 | H48: 3 | J48: 9.1 | L48: 10 | N48: 20.2 | O48: 20.2 | P48: 6.5 | Q48: 3.1 | R48: 5.1 | S48: 20 | T48: 20.5 | U48: 12 | V48: 7.7 | W48: 6.4 | X48: 26.9 | Y48: 72.3 | Z48: 78.1 | AA48: 89.7 | AC48: 11.1 | AD48: 8.1 | AE48: 10.5 | AF48: 8.3 | AG48: 20.4 | AH48: 20.4 | AI48: 19.6 | AJ48: 7.3 | AN48: 3.4 | AO48: 18.6 | AT48: 3.4 | AW48: 5.4 | AX48: 9.9 | AY48: 88.2 | BA48: 108.7 | BC48: 0.6 | BE48: 19.5 | BF48: 60 | BG48: 17.8 | BH48: 2.1 | BI48: 1 | BJ48: 2.3 | BK48: 2 | BM48: 1.2 | BN48: 20 | BO48: 7.1 | BQ48: 13.3 | BR48: 971.9
B49: 21:00 | C49: 15 | D49: 16.3 | E49: 7.2 | F49: 11 | G49: 20.2 | H49: 3 | J49: 9.4 | L49: 10 | N49: 20.1 | O49: 20.2 | P49: 6.7 | Q49: 3.1 | R49: 5.1 | S49: 20 | T49: 20.4 | U49: 11.6 | V49: 7.7 | W49: 6.6 | X49: 25 | Y49: 66.3 | Z49: 81.1 | AA49: 90.4 | AC49: 13.7 | AD49: 7.4 | AE49: 10.5 | AF49: 8.3 | AG49: 20.4 | AH49: 20.4 | AI49: 19.6 | AJ49: 7.3 | AL49: 0.1 | AM49: 1.3 | AN49: 3.4 | AO49: 18.6 | AT49: 3.4 | AW49: 5.4 | AX49: 10 | AY49: 73.7 | BA49: 107 | BC49: 0.6 | BE49: 16.4 | BF49: 47.2 | BG49: 17.6 | BH49: 2.1 | BI49: 1 | BJ49: 2.3 | BK49: 2 | BM49: 1.2 | BN49: 20 | BO49: 7.1 | BQ49: 12.9 | BR49: 937.3
B50: 21:30 | C50: 14.5 | D50: 16.3 | E50: 7.2 | F50: 11 | G50: 20.2 | H50: 3 | J50: 9.4 | L50: 10 | N50: 20.2 | O50: 20.2 | P50: 6.7 | Q50: 3.2 | R50: 5.2 | S50: 20 | T50: 20.4 | U50: 11.6 | V50: 7.7 | W50: 8.7 | X50: 22.9 | Y50: 61.4 | Z50: 89.7 | AA50: 95.6 | AC50: 11.5 | AD50: 9.2 | AE50: 10.4 | AF50: 8.3 | AG50: 20.4 | AH50: 20.4 | AI50: 19.6 | AJ50: 7.3 | AL50: 0.6 | AM50: 1.6 | AN50: 3.4 | AO50: 18.6 | AT50: 3.4 | AW50: 5.3 | AX50: 9.9 | AY50: 67.2 | BA50: 96.1 | BC50: 0.6 | BE50: 16.9 | BF50: 48.5 | BG50: 17.5 | BH50: 2.1 | BI50: 1 | BJ50: 2.3 | BK50: 2 | BM50: 1.2 | BN50: 20 | BO50: 7 | BQ50: 12.8 | BR50: 930.2
B51: 22:00 | C51: 14.5 | D51: 16.4 | E51: 8 | F51: 11 | G51: 20.2 | H51: 3 | J51: 8.3 | L51: 10 | N51: 20.2 | O51: 20.2 | P51: 6.7 | Q51: 3.1 | R51: 5.2 | S51: 20 | T51: 20.5 | U51: 11.6 | V51: 7.7 | W51: 11.1 | X51: 20.4 | Y51: 53.3 | Z51: 77.4 | AA51: 100.1 | AC51: 13.1 | AD51: 6.7 | AE51: 10.5 | AF51: 8.3 | AG51: 20.4 | AH51: 20.4 | AI51: 19.6 | AJ51: 7.3 | AL51: 4.3 | AM51: 5.2 | AN51: 3.4 | AO51: 18.6 | AT51: 3.4 | AW51: 5.5 | AX51: 9.9 | AY51: 61.9 | BA51: 81.3 | BC51: 0.6 | BE51: 16.1 | BF51: 43.1 | BG51: 17.4 | BH51: 2.1 | BI51: 1 | BJ51: 2.3 | BK51: 2 | BM51: 1.2 | BN51: 20 | BO51: 7.1 | BQ51: 12.9 | BR51: 894.5
B52: 22:30 | C52: 14.3 | D52: 17.9 | E52: 8.9 | F52: 11 | G52: 20.2 | H52: 2.9 | J52: 8.2 | L52: 10 | N52: 20.2 | O52: 20.2 | P52: 6.7 | Q52: 3.1 | R52: 5.2 | S52: 20 | T52: 20.6 | U52: 11.6 | V52: 7.7 | W52: 11.6 | X52: 14.2 | Y52: 47.1 | Z52: 83.5 | AA52: 94.7 | AC52: 11.9 | AD52: 6.2 | AE52: 10.5 | AF52: 8.3 | AG52: 20.4 | AH52: 20.4 | AI52: 19.6 | AJ52: 7.3 | AL52: 4.5 | AM52: 7.9 | AN52: 3.4 | AO52: 18.6 | AT52: 3.4 | AW52: 5.5 | AX52: 9.9 | AY52: 39.6 | BA52: 58.6 | BC52: 0.6 | BE52: 17.2 | BF52: 42.5 | BG52: 17.6 | BH52: 2.1 | BI52: 1 | BJ52: 2.3 | BK52: 2 | BM52: 1.2 | BN52: 20 | BO52: 7 | BQ52: 13 | BR52: 842.3
B53: 23:00 | C53: 14.2 | D53: 19 | E53: 6.2 | F53: 11 | G53: 20.1 | H53: 2.9 | J53: 9.4 | L53: 10 | N53: 20.2 | O53: 20.2 | P53: 6.7 | Q53: 3.1 | R53: 5.2 | S53: 19.8 | T53: 20.2 | U53: 11.6 | V53: 7.7 | W53: 9.6 | X53: 11 | Y53: 46.7 | Z53: 78.1 | AA53: 105.5 | AC53: 13.8 | AD53: 6.2 | AE53: 10.5 | AF53: 8.3 | AG53: 20.4 | AH53: 20.4 | AI53: 19.6 | AJ53: 7.3 | AL53: 8.4 | AM53: 10.7 | AN53: 3.4 | AO53: 18.6 | AT53: 3.4 | AW53: 5.5 | AX53: 9.9 | AY53: 35.6 | BA53: 50.7 | BC53: 0.6 | BE53: 13.8 | BF53: 39.8 | BG53: 17.7 | BH53: 2.1 | BI53: 1 | BJ53: 2.3 | BK53: 2 | BM53: 1.2 | BN53: 20 | BO53: 7.1 | BQ53: 12.2 | BR53: 830.9
B54: 23:30 | C54: 14.1 | D54: 19 | E54: 8.1 | F54: 10.4 | G54: 20.2 | H54: 2.9 | J54: 9.5 | L54: 10 | N54: 20.1 | O54: 20.2 | P54: 6.6 | Q54: 3.1 | R54: 5.1 | S54: 20 | T54: 20.6 | U54: 11.6 | V54: 8.6 | W54: 12.7 | X54: 14 | Y54: 40.5 | Z54: 83.4 | AA54: 100.8 | AC54: 11.1 | AD54: 4.1 | AE54: 10.5 | AF54: 8.3 | AG54: 20.4 | AH54: 20.4 | AI54: 19.6 | AJ54: 7.3 | AL54: 10 | AM54: 9.1 | AN54: 3.4 | AO54: 18.6 | AT54: 3.4 | AW54: 5.5 | AX54: 9.9 | AY54: 20.3 | BA54: 30.7 | BC54: 0.6 | BE54: 11 | BF54: 35.4 | BG54: 17.6 | BH54: 2.1 | BI54: 1 | BJ54: 2.3 | BK54: 2 | BM54: 1.2 | BN54: 20 | BO54: 7 | BQ54: 12.3 | BR54: 786.6
B55: 0:00 | C55: 14.5 | D55: 19.1 | E55: 7.7 | F55: 11 | G55: 20.2 | H55: 2.9 | J55: 8.5 | L55: 10 | N55: 20.1 | O55: 20.1 | P55: 6.6 | Q55: 3.1 | R55: 5.1 | S55: 19.9 | T55: 20.3 | U55: 11.6 | V55: 8.7 | W55: 15.4 | X55: 12.8 | Y55: 38.7 | Z55: 73.2 | AA55: 92.9 | AC55: 8.3 | AD55: 2.6 | AE55: 10.4 | AF55: 8.3 | AG55: 20.4 | AH55: 20.4 | AI55: 19.6 | AJ55: 7.3 | AL55: 9.4 | AM55: 10.1 | AN55: 3.5 | AO55: 18.6 | AT55: 3.4 | AW55: 5.2 | AX55: 10 | AY55: 17.7 | BA55: 29.3 | BC55: 0.6 | BE55: 9.2 | BF55: 27.6 | BG55: 17.5 | BH55: 2.1 | BI55: 1 | BJ55: 2.3 | BK55: 2 | BM55: 1.2 | BN55: 20 | BO55: 7 | BQ55: 12.1 | BR55: 749.5
B56: EJEC MWh | C56: 256.3 | D56: 313.15 | E56: 190.1 | F56: 260.4 | G56: 408.85 | H56: 55.05 | I56: 0 | J56: 222.5 | K56: 9.2 | L56: 237.3 | M56: 0 | N56: 458.45 | O56: 484.45 | P56: 150.05 | Q56: 79.3 | R56: 117.95 | S56: 479.05 | T56: 458.3 | U56: 322 | V56: 196 | W56: 358.2 | X56: 859.35 | Y56: 1587.5 | Z56: 1726.95 | AA56: 1994.7 | AB56: 386.9 | AC56: 242.05 | AD56: 145.85 | AE56: 250.05 | AF56: 177.5 | AG56: 489 | AH56: 489.6 | AI56: 470.4 | AJ56: 167.25 | AK56: 824.05 | AL56: 172.45 | AM56: 169.4 | AN56: 84.55 | AO56: 446.4 | AP56: 0 | AQ56: 2582 | AR56: 2189.65 | AS56: 3.3 | AT56: 81.6 | AU56: 139.85 | AV56: 164.7 | AW56: 105.2 | AX56: 237.9 | AY56: 1265.5 | AZ56: 1539.55 | BA56: 1349 | BB56: 1137 | BC56: 14.4 | BD56: 200.5 | BE56: 384.7 | BF56: 1162.95 | BG56: 449.95 | BH56: 50.4 | BI56: 24 | BJ56: 55.2 | BK56: 48 | BL56: 137.8 | BM56: 22.7 | BN56: 480.15 | BO56: 164.05 | BP56: 177.45 | BQ56: 350.95 | BR56: 30259
L70: TERMOELÉCTRICA | M70: 1420.05 | N70: 4.6929839 | O70: #FFA975
L71: HIDROELÉCTRICA | M71: 7928.4 | N71: 26.201791 | O71: #98D2FF
L72: SOLAR | M72: 9491.95 | N72: 31.369014 | O72: #FFD272
L73: EÓLICA | M73: 11418.6 | N73: 37.736211 | O73: #B9ACFF

Sheet COGENERACIÓN
B3: domingo, 19 de Octubre del 2025
B5: CENTRALES DE COGENERACIÓN DEL SEIN
B6: HORA | C6: AGRO INDUSTRIAL PARAMONGA S.A. | D6: AGROAURORA S.A.C. | E6: AGROINDUSTRIAS SAN JACINTO S.A.A. | F6: AGROLMOS SOCIEDAD ANONIMA - AGROLMOS S.A. | G6: BIOENERGIA DEL CHIRA S.A. | H6: GM OPERACIONES S.A.C. | I6: TOTAL COGENERACION
C7: C.T. PARAMONGA | D7: C.T. MAPLE | E7: C.T SAN JACINTO | F7: C.T. AGROLMOS | G7: C.T. CAÑA BRAVA | H7: C.T. REFINERÍA TALARA | I7: MW
B8: 0:30 | C8: 15.1 | E8: 7.6 | F8: 11.1 | G8: 9.3 | H8: 61.1 | I8: 104.2
B9: 1:00 | C9: 14.1 | E9: 8.2 | F9: 11.1 | G9: 9.4 | H9: 61.6 | I9: 104.4
B10: 1:30 | C10: 14.5 | E10: 7.1 | F10: 11.1 | G10: 9.1 | H10: 61.4 | I10: 103.2
B11: 2:00 | C11: 14.5 | E11: 7.6 | F11: 11.1 | G11: 9.3 | H11: 60.8 | I11: 103.3
B12: 2:30 | C12: 14.5 | E12: 7.5 | F12: 11.1 | G12: 9.5 | H12: 61.5 | I12: 104.1
B13: 3:00 | C13: 14.7 | E13: 7.5 | F13: 11.1 | G13: 9.5 | H13: 61 | I13: 103.8
B14: 3:30 | C14: 14.5 | E14: 9 | F14: 11.1 | G14: 9.5 | H14: 61.7 | I14: 105.8
B15: 4:00 | C15: 14.9 | E15: 7.3 | F15: 11.1 | G15: 9.6 | H15: 61.2 | I15: 104.1
B16: 4:30 | C16: 15.2 | E16: 8.8 | F16: 11.1 | G16: 9.5 | H16: 60.7 | I16: 105.3
B17: 5:00 | C17: 14.6 | E17: 7.9 | F17: 11.1 | G17: 9.3 | H17: 59.8 | I17: 102.7
B18: 5:30 | C18: 15.7 | E18: 8.3 | F18: 11.1 | G18: 9.5 | H18: 60.6 | I18: 105.2
B19: 6:00 | C19: 15.7 | D19: 3.1 | E19: 7 | F19: 11.1 | G19: 9.5 | H19: 60.6 | I19: 107
B20: 6:30 | C20: 15 | D20: 4.6 | E20: 8.1 | F20: 11.1 | G20: 9.5 | H20: 61.2 | I20: 109.5
B21: 7:00 | C21: 6.3 | D21: 5.1 | E21: 6.6 | F21: 11.1 | G21: 9.5 | H21: 61 | I21: 99.6
B22: 7:30 | C22: 6.5 | D22: 5.1 | E22: 8.6 | F22: 11.1 | G22: 9.3 | H22: 61.3 | I22: 101.9
B23: 8:00 | C23: 4.9 | D23: 16.3 | E23: 9.4 | F23: 11 | G23: 9.3 | H23: 60.9 | I23: 111.8
B24: 8:30 | C24: 7 | D24: 17 | E24: 8 | F24: 11.1 | G24: 9.3 | H24: 61.1 | I24: 113.5
B25: 9:00 | C25: 6.5 | D25: 18 | E25: 8.6 | F25: 11.1 | G25: 8.7 | H25: 62.7 | I25: 115.6
B26: 9:30 | C26: 7.6 | D26: 18.6 | E26: 6.7 | F26: 11.1 | G26: 9.5 | H26: 61.7 | I26: 115.2
B27: 10:00 | C27: 6.8 | D27: 18.7 | E27: 7.5 | F27: 11.1 | G27: 9.1 | H27: 59.2 | I27: 112.4
B28: 10:30 | C28: 7.5 | D28: 19.1 | E28: 8.2 | F28: 11.1 | G28: 9.4 | H28: 61.2 | I28: 116.5
B29: 11:00 | C29: 6.3 | D29: 19.1 | E29: 8.7 | F29: 11.1 | G29: 9.4 | H29: 60.6 | I29: 115.2
B30: 11:30 | C30: 6.7 | D30: 19.1 | E30: 8.6 | F30: 11.1 | G30: 9.5 | H30: 60.6 | I30: 115.6
... B56: EJEC MWh | C56: 256.3 | D56: 313.15 | E56: 190.1 | F56: 260.4 | G56: 222.5 | H56: 1468.85 | I56: 2711.3

Sheet EVO_PRO_ENE
B3: miércoles, 1 de Octubre del 2025 - domingo, 19 de Octubre del 2025
B5: EVOLUCIÓN DE LA PRODUCCIÓN DE LA ENERGÍA DIARIA DE LOS INTEGRANTES DEL COES (MWh)
B6: EMPRESA | C6: CENTRAL | D6: UNIDAD | E6: TIPO | F6: Octubre
F7: 1 | G7: 2 | H7: 3 | I7: 4 | J7: 5 | K7: 6 | L7: 7 | M7: 8 | N7: 9 | O7: 10 | P7: 11 | Q7: 12 | R7: 13 | S7: 14 | T7: 15 | U7: 16 | V7: 17 | W7: 18 | X7: 19 | Y7: TOTAL
B8: AGRO INDUSTRIAL PARAMONGA S.A. | C8: C.T. PARAMONGA | D8: TV-01 | E8: TERMOELÉCTRICA | H8: 170.35 | I8: 353.4 | J8: 378.6 | K8: 316.9 | L8: 381.15 | M8: 377 | N8: 377.5 | O8: 351.85 | P8: 356.25 | Q8: 366.45 | R8: 360 | S8: 359.5 | T8: 359.95 | U8: 360.45 | V8: 268.65 | W8: 309.85 | X8: 256.3 | Y8: 5704.15
B9: AGROAURORA S.A.C. | C9: C.T. MAPLE ETANOL | D9: TV | E9: TERMOELÉCTRICA | F9: 450.6 | G9: 441.4 | H9: 362.5 | I9: 292.65 | J9: 440.5 | K9: 431.95 | L9: 406.45 | M9: 448.05 | N9: 445.6 | O9: 441.35 | P9: 441.15 | Q9: 455.8 | R9: 454.8 | S9: 455.45 | T9: 454.55 | U9: 329.7 | V9: 338.55 | W9: 404.3 | X9: 313.15 | Y9: 7808.5
B10: AGROINDUSTRIAS SAN JACINTO S.A.A. | C10: C.T. SAN JACINTO | D10: CENTRAL | E10: TERMOELÉCTRICA | F10: 65 | G10: 182.75 | H10: 189.45 | I10: 192.6 | J10: 192.3 | K10: 195.4 | L10: 190.05 | M10: 191.07 | N10: 188.259 | O10: 188.35 | P10: 163.25 | Q10: 178.45 | R10: 181.2 | S10: 187.6 | T10: 187.63 | U10: 177.1 | V10: 178.9 | W10: 190.9 | X10: 190.1 | Y10: 3410.359
B11: AGROLMOS SOCIEDAD ANONIMA - AGROLMOS S.A. | C11: C.T. AGROLMOS | D11: CENTRAL | E11: TERMOELÉCTRICA | F11: 265.4 | G11: 262.9 | H11: 263.3 | I11: 263.25 | J11: 256.2 | K11: 217.7 | L11: 264.45 | M11: 260.7 | N11: 258.4329 | O11: 259.25 | P11: 247.11025 | Q11: 259.6 | R11: 253.75 | S11: 68.6 | T11: 207.03 | U11: 260.13855 | V11: 264.75 | W11: 263.57 | X11: 260.4 | Y11: 4656.5317
B12: ANDEAN POWER S.A.C. | C12: C.H.CARHUAC | D12: CENTRAL | E12: HIDROELÉCTRICA | F12: 367.55 | G12: 339.7 | H12: 358.95 | I12: 369.8 | J12: 342.05 | K12: 283.65 | L12: 355.65 | M12: 334 | N12: 317.15 | O12: 367.75 | P12: 363.55 | Q12: 369.95 | R12: 370.5 | S12: 389.45 | T12: 393.15 | U12: 412.55 | V12: 450.25 | W12: 456.8 | X12: 408.85 | Y12: 7051.3
B13: ASOCIACIÓN SANTA LUCIA DE CHACAS | C13: C.H. HUALLIN | D13: CENTRAL | E13: HIDROELÉCTRICA | F13: 33.45 | G13: 27.85 | H13: 35 | I13: 44.1 | J13: 33.1 | K13: 29.6 | L13: 31.75 | M13: 29.05 | N13: 27.9 | O13: 38.9 | P13: 42.95 | Q13: 23.2 | R13: 40.25 | S13: 37.5 | T13: 35.45 | U13: 33.45 | V13: 55.35 | W13: 63.55 | X13: 55.05 | Y13: 717.45
B14: ATRIA ENERGIA S.A.C. | C14: C.H. PURMACANA | D14: CENTRAL | E14: HIDROELÉCTRICA | F14: 7.2 | G14: 8.9 | H14: 2.1 | L14: 4.55 | M14: 9.6 | N14: 9.6 | O14: 2.75 | S14: 6.55 | T14: 9.6 | U14: 9.5 | V14: 2.75 | Y14: 73.1
B15: BIOENERGIA DEL CHIRA S.A. | C15: C.T. CAÑA BRAVA | D15: CENTRAL | E15: TERMOELÉCTRICA | F15: 94.65 | G15: 162.7 | H15: 223.25 | I15: 234.55 | J15: 223.85 | K15: 164.3 | L15: 217 | M15: 224.35 | N15: 224.45 | O15: 223.65 | P15: 225.85 | Q15: 222.95 | R15: 213.05 | S15: 221.7 | T15: 199.4 | U15: 222.25 | V15: 222.2 | W15: 223.6 | X15: 222.5 | Y15: 3966.25
B16: CELEPSA | C16: C.H. EL PLATANAL | D16: CENTRAL | E16: HIDROELÉCTRICA | F16: 2674.85 | G16: 2542.3 | H16: 2536.1 | I16: 2631.65 | J16: 3175.4 | K16: 3261.8 | L16: 3113.4 | M16: 2920.2 | N16: 2747.55 | O16: 3272.3 | P16: 3714.2 | Q16: 3457 | R16: 3345.7 | S16: 3113.5 | T16: 3094.6 | U16: 2890 | V16: 3289.6 | W16: 3519.55 | X16: 3544.5 | Y16: 58844.2
B17: CELEPSA RENOVABLES S.R.L. | C17: C.H. MARAÑON | D17: CENTRAL | E17: HIDROELÉCTRICA | F17: 300.85 | G17: 290.1 | H17: 293.45 | I17: 292.8 | J17: 112.9 | K17: 292.8 | L17: 292.75 | M17: 286.1 | N17: 292.8 | O17: 292.8 | P17: 292.8 | Q17: 292.8 | R17: 292.8 | S17: 319.45 | T17: 372.05 | U17: 147.55 | V17: 290.4 | W17: 290.4 | X17: 344.95 | Y17: 5390.55
B18: CENTRALES SANTA ROSA S.A.C. | C18: C.H. SANTA ROSA I | D18: CENTRAL | E18: HIDROELÉCTRICA | Y18: 0
B19: CENTRALES SANTA ROSA S.A.C. | C19: C.H. SANTA ROSA II | D19: CENTRAL | E19: HIDROELÉCTRICA | Y19: 0
B20: CHINANGO S.A.C. | C20: C.H. CHIMAY | D20: CENTRAL | E20: HIDROELÉCTRICA | F20: 2784.45 | G20: 3406 | H20: 3550.95 | I20: 3331.35 | J20: 2767.95 | K20: 2249.75 | L20: 2232.975 | M20: 2605.55 | N20: 2207.1 | O20: 3315.95 | P20: 3202.35 | Q20: 3425.15 | R20: 2994.25 | S20: 3124.3 | T20: 2816.7 | U20: 3615.9 | V20: 3619.85 | W20: 3631.8 | X20: 3407.25 | Y20: 58289.575
B21: CHINANGO S.A.C. | C21: C.H. YANANGO | D21: CENTRAL | E21: HIDROELÉCTRICA | F21: 540.45 | G21: 351.05 | H21: 750 | I21: 684.9 | J21: 580.5 | K21: 433.2 | L21: 520.13 | M21: 575.35 | N21: 532.8 | O21: 737.35 | P21: 721.45 | Q21: 707.95 | R21: 658.4 | S21: 636.5 | T21: 458.7 | U21: 752.8 | V21: 710.65 | W21: 660.95 | X21: 742.5 | Y21: 11755.63
B22: COLCA SOLAR S.A.C. | C22: C.S. YARUCAYA | D22: CENTRAL | E22: SOLAR | F22: 7.5 | G22: 8.65 | H22: 6 | I22: 8.45 | J22: 7.85 | K22: 6.4 | L22: 9.35 | M22: 8.25 | N22: 7.35 | O22: 8.4 | P22: 8.4 | Q22: 9.5 | R22: 8.5 | S22: 9.2 | T22: 8.95 | U22: 9.1 | V22: 9.4 | W22: 8 | X22: 9.2 | Y22: 158.45
B23: EGASA | C23: C.H. CHARCANI III | D23: CENTRAL | E23: HIDROELÉCTRICA | F23: 166.35 | G23: 166.25 | H23: 165.95 | I23: 164.85 | J23: 163.65 | K23: 164.5 | L23: 163.55 | M23: 162.75 | N23: 163.2 | O23: 162.85 | P23: 162.1 | Q23: 160.7 | R23: 163.65 | S23: 164.65 | T23: 164.8 | U23: 164.3 | V23: 163.65 | W23: 164.3 | X23: 163.15 | Y23: 3115.2
B24: EGASA | C24: C.H. CHARCANI IV | D24: CENTRAL | E24: HIDROELÉCTRICA | F24: 297.2 | G24: 297 | H24: 288 | I24: 283.1 | J24: 301.6 | K24: 293.75 | L24: 290.85 | M24: 298.05 | N24: 298.9 | O24: 283 | P24: 281.3 | Q24: 277.6 | R24: 287.85 | S24: 290.3 | T24: 296.05 | U24: 297.45 | V24: 279 | W24: 290.3 | X24: 290.6 | Y24: 5521.9
B25: EGASA | C25: C.H. CHARCANI V | D25: CENTRAL | E25: HIDROELÉCTRICA | F25: 1889.7 | G25: 1892.05 | H25: 1906.2 | I25: 1888.55 | J25: 1905.7 | K25: 1892.1 | L25: 1891.8 | M25: 1893 | N25: 1899.65 | O25: 1897.45 | P25: 1885.9 | Q25: 1908.35 | R25: 1885.5 | S25: 1886.4 | T25: 1903.9 | U25: 1913.8 | V25: 1902.55 | W25: 1906.3 | X25: 1890.15 | Y25: 36039.05
B26: EGASA | C26: C.H. CHARCANI VI | D26: CENTRAL | E26: HIDROELÉCTRICA | Y26: 0
B27: EGASA | C27: C.T. CHILINA DIESEL | D27: CENTRAL | E27: TERMOELÉCTRICA | Y27: 0
B28: EGASA | C28: C.T. CHILINA DIESEL | D28: TG | E28: TERMOELÉCTRICA | Y28: 0
B29: EGASA | C29: C.T. MOLLENDO DIESEL | D29: CENTRAL | E29: TERMOELÉCTRICA | Y29: 0
B30: EGEJUNIN | C30: C.H. HUASAHUASI I | D30: CENTRAL | E30: HIDROELÉCTRICA | F30: 200.95 | G30: 190.45 | H30: 229.25 | I30: 237.9 | J30: 219.9 | K30: 189 | L30: 192.2 | M30: 232 | N30: 220.95 | O30: 249.95 | P30: 328.45 | Q30: 179.45 | R30: 277.65 | S30: 257.75 | T30: 259.2 | U30: 257.35 | V30: 251.5 | W30: 236.55 | X30: 237.3 | Y30: 4447.75
B31: EGEJUNIN | C31: C.H. RUNATULLO II | D31: CENTRAL | E31: HIDROELÉCTRICA | F31: 233.8 | G31: 279 | H31: 381.25 | I31: 422.5 | J31: 384.7 | K31: 376.2 | L31: 373.6 | M31: 361.4 | N31: 364.05 | O31: 403 | P31: 405.25 | Q31: 409.85 | R31: 423.65 | S31: 419.05 | T31: 418.9 | U31: 441.85 | V31: 441.1 | W31: 419.05 | X31: 458.45 | Y31: 7416.65
B32: EGEJUNIN | C32: C.H. RUNATULLO III | D32: CENTRAL | E32: HIDROELÉCTRICA | F32: 322.25 | G32: 377.25 | H32: 475.75 | I32: 484.55 | J32: 486.9 | K32: 475.7 | L32: 475.95 | M32: 474.7 | N32: 461.4 | O32: 486.1 | P32: 487.3 | Q32: 487.4 | R32: 487.1 | S32: 482.5 | T32: 484.95 | U32: 484.9 | V32: 485 | W32: 485 | X32: 484.45 | Y32: 8889.15
B33: EGEJUNIN | C33: C.H. SANTA CRUZ I | D33: CENTRAL | E33: HIDROELÉCTRICA | F33: 71.55 | G33: 62.5 | H33: 119.1 | I33: 154.75 | J33: 124.1 | K33: 112.55 | L33: 115.95 | M33: 118 | N33: 107.75 | O33: 112 | P33: 152.4 | Q33: 164.15 | R33: 178.05 | S33: 177.3 | T33: 144.55 | U33: 133.95 | V33: 133.65 | W33: 156 | X33: 150.05 | Y33: 2488.35
B34: EGEMSA | C34: C.H. MACHUPICCHU | D34: CENTRAL | E34: HIDROELÉCTRICA | F34: 3704.95 | G34: 3919.4 | H34: 3970.1 | I34: 3953.25 | J34: 628.3 | K34: 3894.2 | L34: 3968.15 | M34: 3978.5 | N34: 4006.65 | O34: 4003.25 | P34: 3883.65 | Q34: 3996.1 | R34: 3999 | S34: 3932.35 | T34: 3956.35 | U34: 4008.25 | V34: 3993.85 | W34: 3896.35 | X34: 2989.35 | Y34: 70682
B35: EGESUR | C35: C.H. ARICOTA I | D35: CENTRAL | E35: HIDROELÉCTRICA | F35: 183.05 | G35: 182.85 | H35: 183.8 | I35: 183.3 | J35: 187.5 | K35: 183.6 | L35: 183.3 | M35: 185.1 | N35: 184.3 | O35: 183.35 | P35: 185 | Q35: 183.95 | R35: 182.85 | S35: 180.5 | T35: 182.65 | U35: 182.95 | V35: 183.05 | W35: 184.1 | X35: 184.85 | Y35: 3490.05
B36: EGESUR | C36: C.H. ARICOTA II | D36: CENTRAL | E36: HIDROELÉCTRICA | F36: 144.9 | G36: 149.3 | H36: 150.45 | I36: 148.9 | J36: 149.75 | K36: 148.55 | L36: 147.05 | M36: 148.6 | N36: 148.5 | O36: 145.65 | P36: 143.4 | Q36: 143.6 | R36: 139.65 | S36: 137.5 | T36: 140 | U36: 141.85 | V36: 144.15 | W36: 146.95 | X36: 146.75 | Y36: 2765.5
B37: EGESUR | C37: C.T. INDEPENDENCIA | D37: CENTRAL | E37: TERMOELÉCTRICA | Y37: 0
B38: ELECTRICA YANAPAMPA SAC | C38: C.H. YANAPAMPA | D38: CENTRAL | E38: HIDROELÉCTRICA | F38: 59.75 | G38: 59.1 | H38: 60 | I38: 71.8 | J38: 79.85 | K38: 77.35 | L38: 77.45 | M38: 81.25 | N38: 81.35 | O38: 80.75 | P38: 81.8 | Q38: 81.7 | R38: 81.6 | S38: 82.7 | T38: 80 | U38: 74.1 | V38: 73.8 | W38: 80.2 | X38: 79.3 | Y38: 1443.85
B39: ELECTROPERU | C39: C.H. MANTARO | D39: CENTRAL | E39: HIDROELÉCTRICA | F39: 13007.55 | G39: 14243.5 | H39: 15012.5 | I39: 14590 | J39: 15187.5 | K39: 15165.05 | L39: 15203.2 | M39: 14963.6 | N39: 15205.3 | O39: 15163.3 | P39: 15080.2 | Q39: 15174.4 | R39: 15081.7 | S39: 14208.2 | T39: 15130.95 | U39: 14750.9 | V39: 15140.85 | W39: 15122.4 | X39: 14832.6 | Y39: 282263.7
B40: ELECTROPERU | C40: C.H. RESTITUCION | D40: CENTRAL | E40: HIDROELÉCTRICA | F40: 4287.8 | G40: 4844 | H40: 5148.95 | I40: 4446.1 | J40: 5214.05 | K40: 5222.9 | L40: 5197.2 | M40: 5124.4 | N40: 5217.1 | O40: 5195.2 | P40: 5153.75 | Q40: 5184.9 | R40: 5165.65 | S40: 4813.8 | T40: 5182.75 | U40: 5059.1 | V40: 5174.25 | W40: 5172.55 | X40: 5051.45 | Y40: 95855.9
B41: ELECTROPERU | C41: C.T. TUMBES | D41: MAK1 | E41: TERMOELÉCTRICA | M41: 10.9 | Y41: 10.9
B42: ELECTROPERU | C42: C.T. TUMBES | D42: MAK2 | E42: TERMOELÉCTRICA | Y42: 0
B43: EMPRESA DE GENERACION ELECTRICA CANCHAYLLO SAC | C43: C.H. CANCHAYLLO | D43: CENTRAL | E43: HIDROELÉCTRICA | F43: 109.6 | G43: 113.3 | H43: 111.3 | I43: 110.35 | J43: 109.95 | K43: 110.5 | L43: 112.15 | M43: 113.55 | N43: 114.605 | O43: 113.7 | P43: 116.65 | Q43: 113.75 | R43: 113.65 | S43: 111.05 | T43: 107.05 | U43: 109.2 | V43: 111.6 | W43: 117.45 | X43: 117.95 | Y43: 2137.355
B44: EMPRESA DE GENERACION ELECTRICA RIO BAÑOS S.A.C. | C44: C.H. RUCUY | D44: CENTRAL | E44: HIDROELÉCTRICA | F44: 355.2 | G44: 412.3 | H44: 457.5 | I44: 479.75 | J44: 479.8 | K44: 480.05 | L44: 479.85 | M44: 478.85 | N44: 479.95 | O44: 479.25 | P44: 479.35 | Q44: 479.25 | R44: 479.7 | S44: 479.8 | T44: 479.6 | U44: 477.5 | V44: 479.3 | W44: 480 | X44: 479.05 | Y44: 8896.05
B45: EMPRESA DE GENERACION ELECTRICA SANTA ANA S.A.C. | C45: C.H. RENOVANDES H1 | D45: CENTRAL | E45: HIDROELÉCTRICA | F45: 487.35 | G45: 487.6 | H45: 426.15 | I45: 488.35 | J45: 243.9 | K45: 12.65 | L45: 191.2 | M45: 362.8 | N45: 488 | O45: 482.5 | P45: 487.6 | Q45: 487.4 | R45: 486.3 | S45: 485.05 | T45: 487.75 | U45: 482.2 | V45: 488.3 | W45: 488.6 | X45: 458.3 | Y45: 8022
B46: EMPRESA DE GENERACION HUALLAGA | C46: C.H. CHAGLLA | D46: CENTRAL | E46: HIDROELÉCTRICA | F46: 2225.6 | G46: 2934.8 | H46: 4180.5 | I46: 4222.3 | J46: 3993.35 | K46: 2341.45 | L46: 3109.95 | M46: 4648.1 | N46: 3408.1 | O46: 3319.2 | P46: 4170.35 | Q46: 3169.6 | R46: 4433 | S46: 4329.4 | T46: 3057.15 | U46: 4117.05 | V46: 10353.55 | W46: 5885.75 | X46: 5561 | Y46: 79460.2
B47: EMPRESA DE GENERACION HUALLAGA | C47: P.C.H. CHAGLLA | D47: CENTRAL | E47: HIDROELÉCTRICA | F47: 156 | G47: 156 | H47: 156 | I47: 156 | J47: 156 | K47: 156 | L47: 156 | M47: 156 | N47: 50 | V47: 32.35 | W47: 155.75 | X47: 155.8 | Y47: 1641.9
B48: EMPRESA DE GENERACION HUANZA | C48: C.H. HUANZA | D48: CENTRAL | E48: HIDROELÉCTRICA | F48: 1564.15 | G48: 1467.25 | H48: 1459.9 | I48: 1541.65 | J48: 1327.45 | K48: 1180 | L48: 1422 | M48: 1324.05 | N48: 1331.45 | O48: 1468.9 | P48: 1411 | Q48: 1427.5 | R48: 1414.3 | S48: 1567.65 | T48: 1651.45 | U48: 1801.35 | V48: 1883.55 | W48: 1958.3 | X48: 1778.25 | Y48: 28980.15
B49: EMPRESA ELECTRICA AGUA AZUL | C49: C.H. POTRERO | D49: CENTRAL | E49: HIDROELÉCTRICA | F49: 126.05 | G49: 119.3 | H49: 134.3 | I49: 214.35 | J49: 232.8 | K49: 187.2 | L49: 167.4 | M49: 175.2 | N49: 233.45 | O49: 241.25 | P49: 421.26535 | Q49: 418.05 | R49: 479.95 | S49: 480 | T49: 450.9 | U49: 384.45 | V49: 399.45 | W49: 354.85 | X49: 322 | Y49: 5542.2154
B50: EMPRESA ELECTRICA RIO DOBLE | C50: C.H. LAS PIZARRAS | D50: CENTRAL | E50: HIDROELÉCTRICA | F50: 108.6 | G50: 124.75 | H50: 141.25 | I50: 178.2 | J50: 223.85 | K50: 158.2 | L50: 139.1 | M50: 123.65 | N50: 145.25 | O50: 196.75 | P50: 370.95 | Q50: 405.5 | R50: 374.7 | S50: 323.95 | T50: 292.905 | U50: 246.25 | V50: 234 | W50: 222.95 | X50: 196 | Y50: 4206.805
B51: ENEL GENERACION PIURA S.A. | C51: C.T. MALACAS 1 | D51: TG6 | E51: TERMOELÉCTRICA | G51: 534.7845 | K51: 750.05 | L51: 790.85 | M51: 321.55 | N51: 820 | O51: 59.85 | Q51: 703.3 | R51: 375.1 | S51: 547.8 | T51: 732.95 | U51: 544.1 | V51: 352.9 | W51: 277.3 | Y51: 6810.5345
B52: ENEL GENERACION PIURA S.A. | C52: C.T. MALACAS 2 | D52: TG4 | E52: TERMOELÉCTRICA | F52: 24.95 | G52: 24.7 | H52: 31.15 | I52: 25.55 | J52: 38.35 | K52: 125.8 | T52: 305.45 | X52: 719.1 | Y52: 1295.05
B53: ENEL GENERACION PIURA S.A. | C53: C.T. RF DE GENERACION TALARA | D53: TG5 | E53: TERMOELÉCTRICA | V53: 120.3 | Y53: 120.3
B54: ENERGÍA EÓLICA S.A. | C54: C.E. CUPISNIQUE | D54: CENTRAL | E54: EÓLICA | F54: 995.5 | G54: 507.95 | H54: 866.8 | I54: 1435.85 | J54: 1410.3 | K54: 1230.85 | L54: 1251.6 | M54: 1322.35 | N54: 1418.95 | O54: 1017.75 | P54: 1120.85 | Q54: 834.45 | R54: 892.7 | S54: 1071.65 | T54: 1014.9 | U54: 686.35 | V54: 839.3 | W54: 857.05 | X54: 859.35 | Y54: 19634.5
B55: ENERGÍA EÓLICA S.A. | C55: C.E. TALARA | D55: CENTRAL | E55: EÓLICA | F55: 407.75 | G55: 93.5 | H55: 181.5 | I55: 434.75 | J55: 598.75 | K55: 501.35 | L55: 572.7 | M55: 557.15 | N55: 520.3 | O55: 341.3 | P55: 336.1 | Q55: 226.35 | R55: 208.2 | S55: 560.45 | T55: 535.4 | U55: 562.65 | V55: 558.3 | W55: 370.6 | X55: 358.2 | Y55: 7925.3
B56: ENERGIA RENOVABLE DEL SUR S.A. | C56: C.E. SAN JUAN | D56: CENTRAL | E56: EÓLICA | F56: 2501.15 | G56: 2088 | H56: 782.85 | I56: 2304.35 | J56: 2676.75 | K56: 2067.6 | L56: 2130.95 | M56: 2539.95 | N56: 2276 | O56: 2227.35 | P56: 1989.2 | Q56: 1801.45 | R56: 1366.85 | S56: 1493.15 | T56: 990.25 | U56: 1113.8 | V56: 1051.95 | W56: 1560.3 | X56: 1587.5 | Y56: 34549.4
B57: ENGIE ENERGIA PERU S.A.A. | C57: C.E. PUNTA LOMITAS | D57: PL-BL1 | E57: EÓLICA | F57: 1971.85 | G57: 1753.75 | H57: 509.2 | I57: 2268.6 | J57: 2392.65 | K57: 2328.65 | L57: 2154.4 | N57: 1268.45 | O57: 1281.95 | P57: 1419.65 | Q57: 939.6 | R57: 806.2 | S57: 1123.8 | T57: 919.05 | U57: 1241.25 | V57: 1068.7 | X57: 1726.95 | Y57: 25174.7
B58: ENGIE ENERGIA PERU S.A.A. | C58: C.E. PUNTA LOMITAS | D58: PL-BL2 | E58: EÓLICA | F58: 1975.25 | G58: 2014.7 | H58: 725.95 | I58: 2304.25 | J58: 2419.1 | K58: 2470.1 | L58: 2429.1 | N58: 1646.1 | O58: 1736.2 | P58: 1937.25 | Q58: 1434 | R58: 1216.05 | S58: 1511.25 | T58: 1163.95 | U58: 1393.4 | V58: 1223.1 | X58: 1994.7 | Y58: 29594.45
B59: ENGIE ENERGIA PERU S.A.A. | C59: C.E. PUNTA LOMITAS_EXP | D59: PUN LOM_EXP-BL1 | E59: EÓLICA | F59: 266.3 | G59: 248.8 | H59: 63.8 | I59: 362.8 | J59: 434.75 | K59: 412.55 | L59: 348.5 | M59: 243.9 | N59: 204 | O59: 197.8 | P59: 231.3 | Q59: 153.15 | R59: 140.7 | S59: 169.65 | T59: 129.05 | U59: 166.15 | V59: 148.25 | W59: 163.25 | X59: 242.05 | Y59: 4326.75
B60: ENGIE ENERGIA PERU S.A.A. | C60: C.E. PUNTA LOMITAS_EXP | D60: PUN LOM_EXP-BL2 | E60: EÓLICA | F60: 115.85 | G60: 97.6 | H60: 30.2 | I60: 245.2 | J60: 254.15 | K60: 237.4 | L60: 163.1 | M60: 104.25 | N60: 100.6 | O60: 110.7 | P60: 146.75 | Q60: 88.45 | R60: 79.35 | S60: 100.1 | T60: 94.4 | U60: 127.65 | V60: 96.25 | W60: 109.2 | X60: 145.85 | Y60: 2447.05
B61: ENGIE ENERGIA PERU S.A.A. | C61: C.H. QUITARACSA | D61: CENTRAL | E61: HIDROELÉCTRICA | W61: 0.3 | Y61: 0.3
B62: ENGIE ENERGIA PERU S.A.A. | C62: C.H. YUNCAN | D62: CENTRAL | E62: HIDROELÉCTRICA | F62: 1618.15 | G62: 2173.25 | H62: 2895.2 | I62: 2464.8 | J62: 2530.05 | K62: 2109.1 | L62: 1422.7 | M62: 2525 | N62: 1940 | O62: 2321.2 | P62: 2678.2 | Q62: 2794.7 | R62: 2214.9 | S62: 2281.45 | T62: 2303.35 | U62: 2157.9 | V62: 2993.4 | W62: 2672.35 | X62: 2928.2 | Y62: 45023.9
B63: ENGIE ENERGIA PERU S.A.A. | C63: C.S. INTIPAMPA | D63: CENTRAL | E63: SOLAR | F63: 332.45 | G63: 370.3 | H63: 375.95 | I63: 375.35 | J63: 372.65 | K63: 360.6 | L63: 343.15 | M63: 360 | N63: 372.9 | O63: 378.1 | P63: 384.6 | Q63: 385.55 | R63: 366.65 | S63: 375.05 | T63: 352.4 | U63: 366.45 | V63: 375.35 | W63: 382.15 | X63: 386.9 | Y63: 7016.55
B64: ENGIE ENERGIA PERU S.A.A. | C64: C.T. CHILCA 1 | D64: TG1 | E64: TERMOELÉCTRICA | F64: 3795.8 | G64: 2734.05 | H64: 2867 | I64: 3935.1 | J64: 3821.35 | K64: 4237.75 | L64: 3930.85 | M64: 3098.6 | N64: 4065.25 | O64: 3623.75 | P64: 2804.15 | Q64: 2461.5 | R64: 2976.65 | S64: 855.4 | Y64: 45207.2
B65: ENGIE ENERGIA PERU S.A.A. | C65: C.T. CHILCA 1 | D65: TG2 | E65: TERMOELÉCTRICA | F65: 3764.25 | G65: 2724.4 | H65: 2691.65 | K65: 1347.8 | L65: 3682.2 | M65: 3080.55 | N65: 4025.75 | O65: 3592.2 | P65: 2798.55 | Q65: 2456.45 | R65: 2976.35 | S65: 3871.4 | T65: 4177.4 | U65: 4054.05 | V65: 173.35 | W65: 740.5 | Y65: 46156.85
B66: ENGIE ENERGIA PERU S.A.A. | C66: C.T. CHILCA 1 | D66: TG3 | E66: TERMOELÉCTRICA | F66: 4235.9 | G66: 2845.8 | H66: 2955.4 | I66: 1025.5 | J66: 1546.6 | K66: 4800 | L66: 4385.9 | M66: 3351 | N66: 4472.2 | O66: 4046.25 | P66: 2856.2 | Q66: 2479.15 | R66: 2974.85 | S66: 4461.55 | T66: 4800 | U66: 4788.05 | V66: 4752.7 | W66: 4971.75 | X66: 660.85 | Y66: 66409.65
B67: ENGIE ENERGIA PERU S.A.A. | C67: C.T. CHILCA 1 | D67: TV | E67: TERMOELÉCTRICA | F67: 5984.15 | G67: 4862.6 | H67: 4905.15 | I67: 2242.45 | J67: 2526.4 | K67: 4492.9 | L67: 5976.8 | M67: 5216.85 | N67: 6215.2 | O67: 5780.7 | P67: 4907.05 | Q67: 4485.65 | R67: 5011.3 | S67: 4568.75 | T67: 4435.5 | U67: 4329.7 | V67: 2193.6 | W67: 2149.45 | X67: 90.25 | Y67: 80374.45
B68: ENGIE ENERGIA PERU S.A.A. | C68: C.T. CHILCA 2 | D68: TG41 | E68: TERMOELÉCTRICA | N68: 119.65 | Y68: 119.65
B69: ENGIE ENERGIA PERU S.A.A. | C69: C.T. CHILCA 2 | D69: TV42 | E69: TERMOELÉCTRICA | V69: 0.6 | Y69: 0.6
B70: ENGIE ENERGIA PERU S.A.A. | C70: C.T. NEPI | D70: TG41 | E70: TERMOELÉCTRICA | Y70: 0
B71: ENGIE ENERGIA PERU S.A.A. | C71: C.T. NEPI | D71: TG42 | E71: TERMOELÉCTRICA | Y71: 0
B72: ENGIE ENERGIA PERU S.A.A. | C72: C.T. NEPI | D72: TG43 | E72: TERMOELÉCTRICA | M72: 450.4 | Y72: 450.4
B73: ENGIE ENERGIA PERU S.A.A. | C73: C.T. RF PLANTA ILO | D73: TG1 | E73: TERMOELÉCTRICA | Y73: 0
B74: ENGIE ENERGIA PERU S.A.A. | C74: C.T. RF PLANTA ILO | D74: TG2 | E74: TERMOELÉCTRICA | Y74: 0
B75: ENGIE ENERGIA PERU S.A.A. | C75: C.T. RF PLANTA ILO | D75: TG3 | E75: TERMOELÉCTRICA | Y75: 0
B76: FENIX POWER PERÚ | C76: C.T. FENIX | D76: GT11 | E76: TERMOELÉCTRICA | F76: 3580.25 | G76: 3739.25 | H76: 3994.05 | I76: 4117 | J76: 3214.1 | K76: 4063.1 | L76: 4203.7 | M76: 3414.6 | N76: 4370.9 | O76: 4246.9 | P76: 3317.25 | Q76: 80.55 | R76: 3333.5 | S76: 4086.2 | T76: 4338.5 | U76: 3748.2 | V76: 3884.85 | W76: 4050.35 | X76: 3647.2 | Y76: 69430.45
B77: FENIX POWER PERÚ | C77: C.T. FENIX | D77: GT12 | E77: TERMOELÉCTRICA | F77: 3588.25 | G77: 3744.6 | H77: 4002.35 | I77: 4127.4 | J77: 3222.6 | K77: 4071.45 | L77: 4213.25 | M77: 3422.9 | N77: 4382.25 | O77: 4256.9 | P77: 3324 | Q77: 3418.8 | R77: 3895.15 | S77: 4095.1 | T77: 4349.75 | U77: 3758.6 | V77: 3894.75 | W77: 4061.5 | X77: 3655.1 | Y77: 73484.7
B78: FENIX POWER PERÚ | C78: C.T. FENIX | D78: TV10 | E78: TERMOELÉCTRICA | F78: 4000.55 | G78: 4085.1 | H78: 4222.7 | I78: 4287.7 | J78: 3803.6 | K78: 4254.2 | L78: 4339.35 | M78: 3930.85 | N78: 4421.15 | O78: 4349.3 | P78: 3873.1 | Q78: 2004.55 | R78: 3727.55 | S78: 4266.95 | T78: 4403.75 | U78: 4090.95 | V78: 4173.2 | W78: 4254.15 | X78: 4036.25 | Y78: 76524.95
B79: GENERACIÓN ANDINA S.A.C. | C79: C.H. 8 DE AGOSTO | D79: CENTRAL | E79: HIDROELÉCTRICA | F79: 252 | G79: 252 | H79: 252 | I79: 251.85 | J79: 260.55 | K79: 252 | L79: 293.8 | M79: 313.2 | N79: 251.05 | O79: 354.3 | P79: 503.8 | Q79: 419.95 | R79: 455.75 | S79: 385.15 | T79: 356.05 | U79: 488.55 | V79: 502.3 | W79: 294.3 | X79: 250.05 | Y79: 6388.65
B80: GENERACIÓN ANDINA S.A.C. | C80: C.H. EL CARMEN | D80: CENTRAL | E80: HIDROELÉCTRICA | F80: 148.2 | G80: 144.2 | H80: 183.95 | I80: 119.5 | J80: 79.4 | K80: 67.7 | L80: 69.4 | M80: 85.5 | N80: 65.85 | O80: 162.55 | P80: 158.2 | Q80: 124.7 | R80: 145.25 | S80: 115.75 | T80: 85.9 | U80: 140.85 | V80: 161.5 | W80: 147.3 | X80: 177.5 | Y80: 2383.2
B81: GENERADORA DE ENERGÍA DEL PERÚ | C81: C.H. ÁNGEL I | D81: CENTRAL | E81: HIDROELÉCTRICA | F81: 124.4 | G81: 274.25 | H81: 424.65 | I81: 422 | J81: 345.9 | K81: 247.25 | L81: 244.95 | M81: 328.45 | N81: 397.45 | O81: 374.05 | P81: 316.05 | Q81: 263.5 | R81: 230.6 | S81: 226.8 | T81: 426.05 | U81: 487.4 | V81: 489.6 | W81: 488 | X81: 489 | Y81: 6600.35
B82: GENERADORA DE ENERGÍA DEL PERÚ | C82: C.H. ÁNGEL II | D82: CENTRAL | E82: HIDROELÉCTRICA | F82: 136.6 | G82: 183.35 | H82: 326.4 | I82: 429.45 | J82: 360.95 | K82: 259 | L82: 254.9 | M82: 337.7 | N82: 403.45 | O82: 388.75 | P82: 328.65 | Q82: 277.15 | R82: 241.5 | S82: 237.55 | T82: 433.65 | U82: 489.6 | V82: 489.6 | W82: 489.6 | X82: 489.6 | Y82: 6557.45
B83: GENERADORA DE ENERGÍA DEL PERÚ | C83: C.H. ÁNGEL III | D83: CENTRAL | E83: HIDROELÉCTRICA | F83: 140.05 | G83: 179.4 | H83: 286.9 | I83: 414.15 | J83: 364.45 | K83: 262.55 | L83: 250.35 | M83: 331.45 | N83: 397.2 | O83: 387.6 | P83: 334.15 | Q83: 282.05 | R83: 246.15 | S83: 240.1 | T83: 398.5 | U83: 470.4 | V83: 470.4 | W83: 468.15 | X83: 470.4 | Y83: 6394.4
B84: GENERADORA DE ENERGÍA DEL PERÚ | C84: C.H. LA JOYA | D84: CENTRAL | E84: HIDROELÉCTRICA | F84: 174.85 | G84: 176.2 | H84: 174.05 | I84: 174.85 | J84: 167.9 | K84: 174 | L84: 175.25 | M84: 171.5 | N84: 174.9 | O84: 177.45 | P84: 169.7 | Q84: 165.35 | R84: 172.2 | S84: 165.5 | T84: 185.4 | U84: 182.15 | V84: 173.35 | W84: 169.4 | X84: 167.25 | Y84: 3291.25
B85: GM OPERACIONES S.A.C. | C85: CT REFINERIA TALARA | D85: TV1 REF TALARA | E85: TERMOELÉCTRICA | F85: 697.05 | G85: 675.25 | H85: 670.7 | I85: 677.25 | J85: 690.95 | K85: 700.05 | L85: 678.55 | M85: 670.3 | N85: 667.5 | O85: 674.15 | P85: 383.75 | V85: 224.7 | W85: 642.85 | X85: 657.9 | Y85: 8710.95
B86: GM OPERACIONES S.A.C. | C86: CT REFINERIA TALARA | D86: TV2 REF TALARA | E86: TERMOELÉCTRICA | F86: 788.65 | G86: 783.15 | H86: 768.75 | I86: 777.4 | J86: 778.05 | K86: 766.9 | L86: 767.1 | M86: 768.45 | N86: 783.95 | O86: 790.05 | P86: 444.45 | S86: 2.45 | T86: 374.375 | U86: 761.4 | V86: 789.85 | W86: 779.15 | X86: 810.95 | Y86: 11735.075
B87: GR CORTARRAMA SOCIEDAD ANONIMA CERRADA | C87: C.S. MATARANI | D87: C.S. MATARANI | E87: SOLAR | F87: 793.15 | G87: 790.5 | H87: 812.4 | I87: 819.3 | J87: 812.65 | K87: 784.7 | L87: 702.55 | M87: 777.25 | N87: 787.8 | O87: 798.65 | P87: 812.85 | Q87: 776 | R87: 792.1 | S87: 797.9 | T87: 765.15 | U87: 803.1 | V87: 741.15 | W87: 802.55 | X87: 824.05 | Y87: 14993.8
B88: GR PAINO SOCIEDAD ANONIMA CERRADA | C88: C.E. HUAMBOS | D88: CENTRAL | E88: EÓLICA | F88: 169.2 | G88: 237.4 | H88: 130.9 | I88: 169.35 | J88: 193.8 | K88: 168.05 | L88: 228.85 | M88: 198.1 | N88: 60.15 | O88: 20.1 | P88: 57.1 | Q88: 29.1 | R88: 35.1 | S88: 60.05 | T88: 84.05 | U88: 118.05 | V88: 198.15 | W88: 225.05 | X88: 172.45 | Y88: 2555
B89: GR TARUCA SOCIEDAD ANONIMA CERRADA | C89: C.E. DUNA | D89: CENTRAL | E89: EÓLICA | F89: 203.5 | G89: 301.35 | H89: 164.1 | I89: 195.75 | J89: 213.25 | K89: 208.75 | L89: 242.9 | M89: 186.9 | N89: 54.25 | O89: 16.3 | P89: 60.9 | Q89: 25.3 | R89: 27.45 | S89: 61.45 | T89: 75.9 | U89: 135.85 | V89: 207.95 | W89: 241.45 | X89: 169.4 | Y89: 2792.7
B90: HIDROCAÑETE S.A. | C90: C.H. IMPERIAL | D90: CENTRAL | E90: HIDROELÉCTRICA | F90: 83.75 | G90: 44.3 | H90: 84.65 | I90: 84.75 | J90: 84.8 | K90: 84.15 | L90: 84.25 | M90: 84.15 | N90: 84.55 | O90: 83.85 | P90: 86.05 | Q90: 84.45 | R90: 84.1 | S90: 84 | T90: 86.15 | U90: 84.55 | V90: 85.7 | W90: 85.75 | X90: 84.55 | Y90: 1568.5
B91: HIDROELECTRICA HUANCHOR S.A.C. | C91: C.H. HUANCHOR | D91: CENTRAL | E91: HIDROELÉCTRICA | F91: 438.65 | G91: 436.75 | H91: 440.5 | I91: 442.2 | J91: 430.95 | K91: 431.1 | L91: 440.5 | M91: 435.3 | N91: 438.3 | O91: 439.65 | P91: 418.3966 | Q91: 218.6 | R91: 223.7595 | S91: 247.35 | T91: 340.55 | U91: 402.15 | V91: 424.25 | W91: 409.2 | X91: 404.65 | Y91: 7462.8061
B92: HUAURA POWER GROUP S.A. | C92: C.H. YARUCAYA | D92: CENTRAL | E92: HIDROELÉCTRICA | F92: 444 | G92: 444 | H92: 443.95 | I92: 443.95 | J92: 444 | K92: 444 | L92: 444 | M92: 444 | N92: 443.95 | O92: 444 | P92: 444 | Q92: 444 | R92: 444 | S92: 424.85 | T92: 446.4 | U92: 436.8 | V92: 444.2 | W92: 446.3 | X92: 446.4 | Y92: 8416.8
B93: HYDRO GLOBAL PERÚ S.A.C. | C93: CH SAN GABAN III | D93: CENTRAL | E93: HIDROELÉCTRICA | F93: 2447.4 | G93: 2383.75 | H93: 3446.9 | I93: 3471.9 | J93: 3494.05 | K93: 2787.35 | L93: 2615.05 | M93: 2724.1 | N93: 3215.3 | O93: 3482.1 | P93: 3487.55 | Q93: 3471.35 | R93: 2833.9 | S93: 2878.9 | T93: 3271.95 | U93: 4236.65 | V93: 4788.4 | W93: 4853.05 | X93: 4855.05 | Y93: 64744.7
B94: INFRAESTRUCTURAS Y ENERGIAS DEL PERU S.A.C. | C94: C.T. RF PTO MALDONADO | D94: CENTRAL | E94: TERMOELÉCTRICA | V94: 0.7 | Y94: 0.7
B95: INFRAESTRUCTURAS Y ENERGIAS DEL PERU S.A.C. | C95: C.T. RF PUCALLPA | D95: CENTRAL | E95: TERMOELÉCTRICA | K95: 1.65 | Y95: 1.65
B96: INLAND ENERGY SAC | C96: C.H. SANTA TERESA | D96: CENTRAL | E96: HIDROELÉCTRICA | F96: 1968.2 | G96: 2129.7 | H96: 2165.95 | I96: 2141.25 | J96: 66.35 | K96: 2111.6 | L96: 2160.65 | M96: 2159.75 | N96: 2172.3 | O96: 2173.1 | P96: 2097.95 | Q96: 2174.6 | R96: 2164.9 | S96: 2118.5 | T96: 2113.25 | U96: 2188.55 | V96: 2166.5 | W96: 2090.7 | X96: 1677.95 | Y96: 38041.75
B97: INVERSIONES SHAQSHA S.A.C. | C97: C.H. PARIAC | D97: CENTRAL | E97: HIDROELÉCTRICA | L97: 12.8 | M97: 58.25 | N97: 51.4 | O97: 54.8 | P97: 60 | Q97: 58.75 | R97: 60 | S97: 57.75 | T97: 45.65 | U97: 36.365 | V97: 48.5 | W97: 60 | X97: 60 | Y97: 664.265
B98: JOYA SOLAR S.A.C. | C98: C.S. SAN MARTIN SOLAR | D98: CENTRAL | E98: SOLAR | F98: 2569.3 | G98: 2598.1 | H98: 2600 | I98: 2608.25 | J98: 2599.45 | K98: 2602.25 | L98: 2354.95 | M98: 2503.9 | N98: 2562 | O98: 2591.25 | P98: 2598.2 | Q98: 2616.95 | R98: 2576.7 | S98: 2540.9 | T98: 2435.2 | U98: 2602.65 | V98: 2424.05 | W98: 2550.35 | X98: 2582 | Y98: 48516.45
B99: KALLPA GENERACION S.A. | C99: C.H. CERRO DEL AGUILA | D99: CENTRAL | E99: HIDROELÉCTRICA | F99: 4751.1 | G99: 6923.3 | H99: 7251.35 | I99: 6078.25 | J99: 7618.65 | K99: 7072.95 | L99: 7359.7 | M99: 6757.35 | N99: 7180.1 | O99: 7995.55 | P99: 8674 | Q99: 9434.3 | R99: 10385.75 | S99: 11732.9 | T99: 9360.75 | U99: 9476.75 | V99: 11978.65 | W99: 9513.85 | X99: 11190.3 | Y99: 160735.55
B100: KALLPA GENERACION S.A. | C100: C.S. SUNNY | D100: CENTRAL | E100: SOLAR | F100: 1919.2 | G100: 1953.5 | H100: 2020.1 | I100: 2035.3 | J100: 2146.2 | K100: 2164.25 | L100: 1264.2 | M100: 1750.6 | N100: 2039.45 | O100: 2141.1 | P100: 2166.8 | Q100: 2176.95 | R100: 2208.65 | S100: 2078 | T100: 1947.15 | U100: 2151.19 | V100: 1996.63 | W100: 2092.38 | X100: 2189.65 | Y100: 38441.3
B101: KALLPA GENERACION S.A. | C101: C.T. KALLPA | D101: TG1 | E101: TERMOELÉCTRICA | F101: 3356.05 | G101: 3095.7 | H101: 3106.45 | I101: 3571.4 | J101: 187.8 | S101: 2849.8 | T101: 3766.6 | U101: 3119.8 | V101: 3305.3 | W101: 3399.6 | X101: 3140.85 | Y101: 32899.35
B102: KALLPA GENERACION S.A. | C102: C.T. KALLPA | D102: TG2 | E102: TERMOELÉCTRICA | F102: 3378 | G102: 3093.25 | H102: 3091.9 | I102: 3661.05 | J102: 3660.05 | K102: 4916.6 | L102: 4952.45 | M102: 4699.35 | N102: 4948.15 | O102: 4947.7 | P102: 4847.35 | Q102: 4138.9 | R102: 4925.35 | S102: 3874.85 | T102: 3783.2 | U102: 3119.95 | V102: 3299.35 | W102: 3399.95 | X102: 3142.55 | Y102: 75879.95
B103: KALLPA GENERACION S.A. | C103: C.T. KALLPA | D103: TG3 | E103: TERMOELÉCTRICA | F103: 3378.15 | G103: 3094.9 | H103: 3096 | I103: 3675 | J103: 3676.25 | K103: 4977.55 | L103: 5006.7 | M103: 4740.1 | N103: 5018.4 | O103: 5015.1 | P103: 4898.45 | Q103: 4184.85 | R103: 4995.85 | S103: 3890.25 | T103: 3782.35 | U103: 3116.9 | V103: 3299.1 | W103: 3399.05 | X103: 3141.4 | Y103: 76386.35
...

Sheet G_AREAS
B3: domingo, 19 de Octubre del 2025
B5: HORA | C5: RESUMEN DE GENERACIÓN POR ÁREAS DEL SEIN | D5: RESUMEN DE GENERACIÓN POR ÁREAS DEL SEIN | E5: RESUMEN DE GENERACIÓN POR ÁREAS DEL SEIN | F5: RESUMEN DE GENERACIÓN POR ÁREAS DEL SEIN | G5: RESUMEN DE GENERACIÓN POR ÁREAS DEL SEIN | H5: RESUMEN DE GENERACIÓN POR ÁREAS DEL SEIN | I5: RESUMEN DE GENERACIÓN POR ÁREAS DEL SEIN | J5: RESUMEN DE GENERACIÓN POR ÁREAS DEL SEIN | K5: RESUMEN DE GENERACIÓN POR ÁREAS DEL SEIN | L5: RESUMEN DE GENERACIÓN POR ÁREAS DEL SEIN | M5: RESUMEN DE GENERACIÓN POR ÁREAS DEL SEIN | N5: RESUMEN DE GENERACIÓN POR ÁREAS DEL SEIN | O5: RESUMEN DE GENERACIÓN POR ÁREAS DEL SEIN | P5: RESUMEN DE GENERACIÓN POR ÁREAS DEL SEIN | Q5: RESUMEN DE GENERACIÓN POR ÁREAS DEL SEIN | R5: RESUMEN DE GENERACIÓN POR ÁREAS DEL SEIN | S5: HORA | T5: GENERACIÓN POR TIPO DE GENERACIÓN | U5: GENERACIÓN POR TIPO DE GENERACIÓN | V5: GENERACIÓN POR TIPO DE GENERACIÓN | W5: GENERACIÓN POR TIPO DE GENERACIÓN | X5: GENERACIÓN POR TIPO DE GENERACIÓN | Y5: HORA | Z5: GENERACIÓN POR TIPO DE GENERACIÓN | AA5: GENERACIÓN POR TIPO DE GENERACIÓN | AB5: GENERACIÓN POR TIPO DE GENERACIÓN | AC5: GENERACIÓN POR TIPO DE GENERACIÓN | AD5: GENERACIÓN POR TIPO DE GENERACIÓN
C6: NORTE | D6: NORTE | E6: NORTE | F6: NORTE | G6: CENTRO | H6: CENTRO | I6: CENTRO | J6: CENTRO | K6: SUR | L6: SUR | M6: SUR | N6: SUR | O6: GENERACIÓN INTEGRANTES COES | P6: GENERACIÓN INTEGRANTES COES | Q6: GENERACIÓN INTEGRANTES COES | R6: GENERACIÓN INTEGRANTES COES | T6: INTEGRANTES COES | U6: INTEGRANTES COES | V6: INTEGRANTES COES | W6: INTEGRANTES COES | X6: INTEGRANTES COES | Z6: INTEGRANTES COES RER | AA6: INTEGRANTES COES RER | AB6: INTEGRANTES COES RER | AC6: INTEGRANTES COES RER | AD6: INTEGRANTES COES RER
C7: GENERACIÓN HIDROELÉCTRICA NORTE | D7: GENERACIÓN TERMOELÉCTRICA NORTE | E7: GENERACIÓN SOLAR NORTE | F7: GENERACIÓN EÓLICA NORTE | G7: GENERACIÓN HIDROELÉCTRICA CENTRO | H7: GENERACIÓN TERMOELÉCTRICA CENTRO | I7: GENERACIÓN SOLAR CENTRO | J7: GENERACIÓN EÓLICA CENTRO | K7: GENERACIÓN HIDROELÉCTRICA SUR | L7: GENERACIÓN TERMOELÉCTRICA SUR | M7: GENERACIÓN SOLAR SUR | N7: GENERACIÓN EÓLICA SUR | O7: GENERACIÓN COES NORTE | P7: GENERACIÓN COES CENTRO | Q7: GENERACIÓN COES SUR | R7: TOTAL GENERACION | T7: HIDROELÉCTRICA | U7: TERMOELÉCTRICA | V7: SOLAR | W7: EÓLICA | X7: TOTAL GENERACION | Z7: HIDROELÉCTRICA RER | AA7: TERMOELÉCTRICA RER | AB7: SOLAR RER | AC7: EÓLICA RER | AD7: TOTAL RER
B8: 00:30 | C8: 253 | D8: 89.1 | E8: 0 | F8: 37.8 | G8: 3159.1 | H8: 2247.2 | I8: 0 | J8: 217.3 | K8: 743.6 | L8: 0 | M8: 0 | N8: 0 | O8: 379.9 | P8: 5623.6 | Q8: 743.6 | R8: 6747.1 | S8: 00:30 | T8: 4155.7 | U8: 2336.3 | V8: 0 | W8: 255.1 | X8: 6747.1 | Y8: 00:30 | Z8: 340.3 | AA8: 50.5 | AB8: 0 | AC8: 255.1 | AD8: 645.9
B9: 01:00 | C9: 250.5 | D9: 90.3 | E9: 0 | F9: 31.9 | G9: 3045.3 | H9: 2238.5 | I9: 0 | J9: 213.4 | K9: 747.4 | L9: 0 | M9: 0 | N9: 0 | O9: 372.7 | P9: 5497.2 | Q9: 747.4 | R9: 6617.3 | S9: 01:00 | T9: 4043.2 | U9: 2328.8 | V9: 0 | W9: 245.3 | X9: 6617.3 | Y9: 01:00 | Z9: 338 | AA9: 50.2 | AB9: 0 | AC9: 245.3 | AD9: 633.5
B10: 01:30 | C10: 252.5 | D10: 88.7 | E10: 0 | F10: 43.5 | G10: 3090.4 | H10: 2110.9 | I10: 0 | J10: 199 | K10: 742.5 | L10: 0 | M10: 0 | N10: 0 | O10: 384.7 | P10: 5400.3 | Q10: 742.5 | R10: 6527.5 | S10: 01:30 | T10: 4085.4 | U10: 2199.6 | V10: 0 | W10: 242.5 | X10: 6527.5 | Y10: 01:30 | Z10: 337 | AA10: 49.2 | AB10: 0 | AC10: 242.5 | AD10: 628.7
B11: 02:00 | C11: 259.4 | D11: 88.8 | E11: 0 | F11: 40.7 | G11: 3015.6 | H11: 1975.3 | I11: 0 | J11: 208.8 | K11: 752.6 | L11: 0 | M11: 0 | N11: 0 | O11: 388.9 | P11: 5199.7 | Q11: 752.6 | R11: 6341.2 | S11: 02:00 | T11: 4027.6 | U11: 2064.1 | V11: 0 | W11: 249.5 | X11: 6341.2 | Y11: 02:00 | Z11: 332.3 | AA11: 49.9 | AB11: 0 | AC11: 249.5 | AD11: 631.7
B12: 02:30 | C12: 257.3 | D12: 89.6 | E12: 0 | F12: 48 | G12: 3019.1 | H12: 2011.6 | I12: 0 | J12: 225.2 | K12: 748.2 | L12: 0 | M12: 0 | N12: 0 | O12: 394.9 | P12: 5255.9 | Q12: 748.2 | R12: 6399 | S12: 02:30 | T12: 4024.6 | U12: 2101.2 | V12: 0 | W12: 273.2 | X12: 6399 | Y12: 02:30 | Z12: 315.2 | AA12: 50 | AB12: 0 | AC12: 273.2 | AD12: 638.4
B13: 03:00 | C13: 249.6 | D13: 89.1 | E13: 0 | F13: 44.3 | G13: 3040.4 | H13: 1907.3 | I13: 0 | J13: 244.4 | K13: 744.6 | L13: 0 | M13: 0 | N13: 0 | O13: 383 | P13: 5192.1 | Q13: 744.6 | R13: 6319.7 | S13: 03:00 | T13: 4034.6 | U13: 1996.4 | V13: 0 | W13: 288.7 | X13: 6319.7 | Y13: 03:00 | Z13: 312.8 | AA13: 50.2 | AB13: 0 | AC13: 288.7 | AD13: 651.7
B14: 03:30 | C14: 283.2 | D14: 91.3 | E14: 0 | F14: 48.2 | G14: 2998.9 | H14: 1860.1 | I14: 0 | J14: 230.9 | K14: 747.2 | L14: 0 | M14: 0 | N14: 0 | O14: 422.7 | P14: 5089.9 | Q14: 747.2 | R14: 6259.8 | S14: 03:30 | T14: 4029.3 | U14: 1951.4 | V14: 0 | W14: 279.1 | X14: 6259.8 | Y14: 03:30 | Z14: 313.4 | AA14: 51.5 | AB14: 0 | AC14: 279.1 | AD14: 644
B15: 04:00 | C15: 285.2 | D15: 89.2 | E15: 0 | F15: 49.2 | G15: 2995.4 | H15: 1844.6 | I15: 0 | J15: 262.3 | K15: 755.9 | L15: 0 | M15: 0 | N15: 0 | O15: 423.6 | P15: 5102.3 | Q15: 755.9 | R15: 6281.8 | S15: 04:00 | T15: 4036.5 | U15: 1933.8 | V15: 0 | W15: 311.5 | X15: 6281.8 | Y15: 04:00 | Z15: 314.4 | AA15: 50.3 | AB15: 0 | AC15: 311.5 | AD15: 676.2
B16: 04:30 | C16: 283.5 | D16: 90.1 | E16: 0 | F16: 49.7 | G16: 3002.4 | H16: 1743.6 | I16: 0 | J16: 263.2 | K16: 738.1 | L16: 0 | M16: 0 | N16: 0 | O16: 423.3 | P16: 5009.2 | Q16: 738.1 | R16: 6170.6 | S16: 04:30 | T16: 4024 | U16: 1833.7 | V16: 0 | W16: 312.9 | X16: 6170.6 | Y16: 04:30 | Z16: 325.1 | AA16: 52 | AB16: 0 | AC16: 312.9 | AD16: 690
B17: 05:00 | C17: 284.3 | D17: 88.1 | E17: 0 | F17: 55 | G17: 3031.2 | H17: 1899.6 | I17: 0 | J17: 269.8 | K17: 689.6 | L17: 0 | M17: 0.1 | N17: 0 | O17: 427.4 | P17: 5200.6 | Q17: 689.7 | R17: 6317.7 | S17: 05:00 | T17: 4005.1 | U17: 1987.7 | V17: 0.1 | W17: 324.8 | X17: 6317.7 | Y17: 05:00 | Z17: 327.7 | AA17: 50.3 | AB17: 0.1 | AC17: 324.8 | AD17: 702.9
B18: 05:30 | C18: 288.6 | D18: 89.5 | E18: 0 | F18: 62.4 | G18: 3103.6 | H18: 1818 | I18: 0 | J18: 271.6 | K18: 639.3 | L18: 0 | M18: 20 | N18: 0 | O18: 440.5 | P18: 5193.2 | Q18: 659.3 | R18: 6293 | S18: 05:30 | T18: 4031.5 | U18: 1907.5 | V18: 20 | W18: 334 | X18: 6293 | Y18: 05:30 | Z18: 336.7 | AA18: 52 | AB18: 20 | AC18: 334 | AD18: 742.7
B19: 06:00 | C19: 291 | D19: 91.3 | E19: 0 | F19: 56.4 | G19: 2764.1 | H19: 1778.5 | I19: 0 | J19: 254.3 | K19: 623.1 | L19: 0 | M19: 219.6 | N19: 0 | O19: 438.7 | P19: 4796.9 | Q19: 842.7 | R19: 6078.3 | S19: 06:00 | T19: 3678.2 | U19: 1869.8 | V19: 219.6 | W19: 310.7 | X19: 6078.3 | Y19: 06:00 | Z19: 337 | AA19: 53.8 | AB19: 219.6 | AC19: 310.7 | AD19: 921.1
... B56: TOTAL MWh | C56: 7401 | D56: 3307.85 | E56: 3.3 | F56: 1559.4 | G56: 68820.25 | H56: 43085.45 | I56: 9.2 | J56: 9859.2 | K56: 16521.05 | L56: 0 | M56: 9479.45 | N56: 0 | O56: 12271.55 | P56: 121774.1 | Q56: 26000.5 | R56: 160046.15 | S56: TOTAL MWh | T56: 92742.3 | U56: 46393.3 | V56: 9491.95 | W56: 11418.6 | X56: 160046.15 | Y56: TOTAL MWh | Z56: 7928.4 | AA56: 1420.05 | AB56: 9491.95 | AC56: 11418.6 | AD56: 30259

Sheet HOP
B3: domingo, 19 de Octubre del 2025
B5: Reporte de Horas de Operación
B6: Empresa | C6: Central | D6: Grupo | E6: Modo de Operación | F6: Inicio | G6: Final | H6: O. Arranque | I6: O. Parada | J6: Tipo Operación | K6: Ensayo de Potencia Efectiva | L6: Ensayo de Potencia Mínima | M6: Sistema | N6: Lim. Transm. | O6: Causa | P6: Observación
B7: AGRO INDUSTRIAL PARAMONGA S.A. | C7: C.T. PARAMONGA | D7: CENTRAL | E7: PARAMONGA - BAGAZO | F7: 19/10/2025 00:00:00 | G7: 20/10/2025 00:00:00 | J7: POR COGENERACION | O7: ...
B8: AGROAURORA S.A.C. | C8: C.T. MAPLE ETANOL | D8: CENTRAL | E8: MAPLE- BAGAZO | F8: 19/10/2025 05:40:00 | G8: 20/10/2025 00:00:00 | J8: POR COGENERACION | O8: ...
B9: AGROINDUSTRIAS SAN JACINTO S.A.A. | C9: C.T. SAN JACINTO | D9: CENTRAL | E9: SAN_JACINTO - BAGAZO | F9: 19/10/2025 00:00:00 | G9: 20/10/2025 00:00:00 | J9: POR COGENERACION | O9: ...
B10: AGROLMOS SOCIEDAD ANONIMA - AGROLMOS S.A. | C10: C.T. AGROLMOS | D10: CENTRAL | E10: AGROLMOS TV1 & TV2 - BAGAZO | F10: 19/10/2025 00:00:00 | G10: 19/10/2025 19:23:00 | J10: POR COGENERACION | O10: ...
B11: AGROLMOS SOCIEDAD ANONIMA - AGROLMOS S.A. | C11: C.T. AGROLMOS | D11: CENTRAL | E11: AGROLMOS TV1 & TV2 - BAGAZO | F11: 19/10/2025 19:38:00 | G11: 20/10/2025 00:00:00 | J11: POR COGENERACION | O11: ...
B12: BIOENERGIA DEL CHIRA S.A. | C12: C.T. CAÑA BRAVA | D12: G-1 | E12: CANA BRAVA TV1 - BAGAZO | F12: 19/10/2025 00:00:00 | G12: 20/10/2025 00:00:00 | J12: POR COGENERACION | O12: ...
B13: ENEL GENERACION PIURA S.A. | C13: C.T. MALACAS 2 | D13: CENTRAL | E13: MALACAS2 TG4 - GAS | F13: 19/10/2025 07:25:00 | G13: 19/10/2025 09:56:00 | H13: 19/10/2025 07:04:00 | J13: A MINIMA CARGA | O13: ...
B14: ENEL GENERACION PIURA S.A. | C14: C.T. MALACAS 2 | D14: CENTRAL | E14: MALACAS2 TG4 - GAS | F14: 19/10/2025 09:56:00 | G14: 19/10/2025 16:24:00 | J14: POR POTENCIA O ENERGIA | N14: xLT | O14: ... | P14: A las 09:56 h, S/C generar a 50 MW. A las 12:34 h, S/C generar a 80 MW. A las 15:42 h, S/C generar a 90 MW.
B15: ENEL GENERACION PIURA S.A. | C15: C.T. MALACAS 2 | D15: CENTRAL | E15: MALACAS2 TG4 - GAS | F15: 19/10/2025 16:24:00 | G15: 19/10/2025 18:52:00 | J15: A MINIMA CARGA | O15: ...
B16: ENEL GENERACION PIURA S.A. | C16: C.T. MALACAS 2 | D16: CENTRAL | E16: MALACAS2 TG4 - GAS | F16: 19/10/2025 18:52:00 | G16: 19/10/2025 21:16:00 | J16: POR POTENCIA O ENERGIA | O16: ... | P16: Operó a mínima generación por falta de gas.
B17: ENEL GENERACION PIURA S.A. | C17: C.T. MALACAS 2 | D17: CENTRAL | E17: MALACAS2 TG4 - GAS | F17: 19/10/2025 21:16:00 | G17: 20/10/2025 00:00:00 | J17: A MINIMA CARGA | O17: ...
B18: ENGIE ENERGIA PERU S.A.A. | C18: C.T. CHILCA 1 | D18: CENTRAL | E18: CHILCA1 CCOMB TG3 - GAS | F18: 19/10/2025 00:00:00 | G18: 19/10/2025 01:18:00 | I18: 19/10/2025 00:40:00 | J18: POR POTENCIA O ENERGIA | O18: ...
B19: ENGIE ENERGIA PERU S.A.A. | C19: C.T. CHILCA 1 | D19: TG3 | E19: CHILCA1 TG3 - GAS | F19: 19/10/2025 01:18:00 | G19: 19/10/2025 01:32:00 | J19: A MINIMA CARGA | O19: ...
B20: ENGIE ENERGIA PERU S.A.A. | C20: C.T. CHILCA 1 | D20: TG3 | E20: CHILCA1 TG3 - GAS | F20: 19/10/2025 18:52:00 | G20: 19/10/2025 21:00:00 | H20: 19/10/2025 18:24:00 | J20: POR POTENCIA O ENERGIA | O20: ...
B21: ENGIE ENERGIA PERU S.A.A. | C21: C.T. CHILCA 1 | D21: TG3 | E21: CHILCA1 TG3 - GAS | F21: 19/10/2025 21:00:00 | G21: 19/10/2025 21:59:00 | I21: 19/10/2025 21:47:00 | J21: A MINIMA CARGA | O21: ...
B22: FENIX POWER PERÚ | C22: C.T. FENIX | D22: CENTRAL | E22: FENIX CCOMB GT11 & GT12 - GAS | F22: 19/10/2025 00:00:00 | G22: 19/10/2025 04:10:00 | J22: POR POTENCIA O ENERGIA | O22: ...
B23: FENIX POWER PERÚ | C23: C.T. FENIX | D23: CENTRAL | E23: FENIX CCOMB GT11 & GT12 - GAS | F23: 19/10/2025 04:10:00 | G23: 19/10/2025 05:00:00 | J23: A MINIMA CARGA | O23: ...
B24: FENIX POWER PERÚ | C24: C.T. FENIX | D24: CENTRAL | E24: FENIX CCOMB GT11 & GT12 - GAS | F24: 19/10/2025 05:00:00 | G24: 19/10/2025 05:30:00 | J24: POR RSF | O24: ...
B25: FENIX POWER PERÚ | C25: C.T. FENIX | D25: CENTRAL | E25: FENIX CCOMB GT11 & GT12 - GAS | F25: 19/10/2025 05:30:00 | G25: 19/10/2025 06:00:00 | J25: A MINIMA CARGA | O25: ...
B26: FENIX POWER PERÚ | C26: C.T. FENIX | D26: CENTRAL | E26: FENIX CCOMB GT11 & GT12 - GAS | F26: 19/10/2025 06:00:00 | G26: 19/10/2025 07:30:00 | J26: POR RSF | O26: ...
B27: FENIX POWER PERÚ | C27: C.T. FENIX | D27: CENTRAL | E27: FENIX CCOMB GT11 & GT12 - GAS | F27: 19/10/2025 07:30:00 | G27: 19/10/2025 08:08:00 | J27: A MINIMA CARGA | O27: ...
B28: FENIX POWER PERÚ | C28: C.T. FENIX | D28: CENTRAL | E28: FENIX CCOMB GT11 & GT12 - GAS | F28: 19/10/2025 08:08:00 | G28: 19/10/2025 14:14:00 | J28: POR PRUEBAS | O28: ...
B29: FENIX POWER PERÚ | C29: C.T. FENIX | D29: CENTRAL | E29: FENIX CCOMB GT11 & GT12 - GAS | F29: 19/10/2025 14:14:00 | G29: 19/10/2025 16:30:00 | J29: A MINIMA CARGA | O29: ...
B30: FENIX POWER PERÚ | C30: C.T. FENIX | D30: CENTRAL | E30: FENIX CCOMB GT11 & GT12 - GAS | F30: 19/10/2025 16:30:00 | G30: 19/10/2025 17:14:00 | J30: POR RSF | O30: ...
B31: FENIX POWER PERÚ | C31: C.T. FENIX | D31: CENTRAL | E31: FENIX CCOMB GT11 & GT12 - GAS | F31: 19/10/2025 17:14:00 | G31: 20/10/2025 00:00:00 | J31: POR POTENCIA O ENERGIA | O31: ...
B32: GM OPERACIONES S.A.C. | C32: CT REFINERIA TALARA | D32: TV1 REF TALARA | E32: REF_TALARA TV1 - NLH_RFG | F32: 19/10/2025 00:00:00 | G32: 20/10/2025 00:00:00 | J32: POR COGENERACION | O32: ...
B33: GM OPERACIONES S.A.C. | C33: CT REFINERIA TALARA | D33: TV2 REF TALARA | E33: REF_TALARA TV2 - NLH_RFG | F33: 19/10/2025 00:00:00 | G33: 20/10/2025 00:00:00 | J33: POR COGENERACION | O33: ...
... B39: KALLPA GENERACION S.A. | C39: C.T. LAS FLORES | D39: CENTRAL | E39: LAS FLORES CCOMB TG1 - GAS | F39: 19/10/2025 17:01:00 | G39: 20/10/2025 00:00:00 | J39: POR POTENCIA O ENERGIA | O39: ...
B40: MINERA CERRO VERDE | C40: C.T. RECKA | D40: CENTRAL | E40: RECKA TG1 - D2 | F40: 19/10/2025 15:54:00 | G40: 19/10/2025 17:58:00 | H40: 19/10/2025 15:37:00 | I40: 19/10/2025 17:54:00 | J40: A MINIMA CARGA | O40: ... | P40: A las 16:14 h, S/C generar a máxima para la maniobra de conexión de la línea L-5006. A las 16:24 h, S/C generar a mínima.
B41: ORYGEN PERU S.A.A. | C41: C.T. VENTANILLA | D41: CENTRAL | E41: VENTANILLA CCOMB TG3 & TG4 - GAS | F41: 19/10/2025 00:00:00 | G41: 19/10/2025 06:02:00 | J41: POR POTENCIA O ENERGIA | O41: ...
B42: ORYGEN PERU S.A.A. | C42: C.T. VENTANILLA | D42: CENTRAL | E42: VENTANILLA CCOMB TG3 & TG4 - GAS | F42: 19/10/2025 06:02:00 | G42: 19/10/2025 17:02:00 | J42: A MINIMA CARGA | O42: ...
B43: ORYGEN PERU S.A.A. | C43: C.T. VENTANILLA | D43: CENTRAL | E43: VENTANILLA CCOMB TG3 & TG4 - GAS | F43: 19/10/2025 17:02:00 | G43: 20/10/2025 00:00:00 | J43: POR POTENCIA O ENERGIA | O43: ...
B44: PETRAMAS | C44: C.T. HUAYCOLORO | D44: CENTRAL | E44: HUAYCOLORO - BIOGAS | F44: 19/10/2025 00:00:00 | G44: 20/10/2025 00:00:00 | J44: POR POTENCIA O ENERGIA | O44: ...
B45: PETRAMAS | C45: C.T. LA GRINGA | D45: G2 | E45: LA GRINGA V - BIOGAS | F45: 19/10/2025 00:00:00 | G45: 20/10/2025 00:00:00 | J45: POR POTENCIA O ENERGIA | O45: ...
B46: PETRAMAS | C46: C.T.B DOÑA CATALINA | D46: CENTRAL | E46: DONA CATALINA - BIOGAS | F46: 19/10/2025 00:00:00 | G46: 20/10/2025 00:00:00 | J46: POR POTENCIA O ENERGIA | O46: ...
B47: PETRAMAS | C47: C.T.B. CALLAO | D47: CENTRAL | E47: CALLAO - BIOGAS | F47: 19/10/2025 00:00:00 | G47: 20/10/2025 00:00:00 | J47: POR POTENCIA O ENERGIA | O47: ...

Sheet INDISP
B3: domingo, 19 de Octubre del 2025
B5: Hora Inicio y Fin de Indisponibilidades de las Unidades de Generación SEIN
