Workbook

Sheet EVENTOS
B3: sábado, 15 de Marzo del 2025
B5: INFORMACIÓN DE EVENTOS PRINCIPALES EN SUS INSTALACIONES
B6: TIPO DE EVENTO | C6: EMPRESA | D6: UBICACIÓN | E6: TIPO DE EQUIPO | F6: EQUIPO | G6: INICIO | H6: FINAL | I6: DESCRIPCIÓN | J6: MW INDISP. | K6: INTERRUPCIÓN (SI/NO) | L6: TENSIÓN DE FALLA (kV)
B7: EVENTO | C7: CONELSUR LT SAC | D7: PORTILLO | E7: SUBESTACION | F7: SS.EE. | G7: 15/03/2025 00:00:00 | H7: 16/03/2025 00:00:00 | I7: DECLARACIÓN DE SITUACIÓN EXCEPCIONAL EN LA S.E. PORTILLO DE 60 kV | K7: NO
B8: EVENTO | C8: RED DE ENERGIA DEL PERU S.A. | D8: TINGO MARÍA - AUCAYACU | E8: LINEA DE TRANSMISION | F8: L-1122 | G8: 15/03/2025 18:31:00 | H8: 16/03/2025 00:00:00 | I8: DECLARACIÓN DE SITUACIÓN EXCEPCIONAL EN LA LÍNEA L-1122 (TINGO MARÍA - AUCAYACU) DE 138 kV | K8: NO
B9: FALLA | C9: TRANSMISORA ELECTRICA DEL SUR S.A.C | D9: TINTAYA NUEVA - SOCABAYA | E9: LINEA DE TRANSMISION | F9: L-2023 | G9: 15/03/2025 15:44:00 | H9: 15/03/2025 15:57:00 | I9: DESCONEXIÓN DE LA LÍNEA L-2023 (SOCABAYA - TINTAYA NUEVA) DE 220 KV | J9: 0.8 | K9: SI | L9: 220

Sheet RESTRIC_OPE
B3: sábado, 15 de Marzo del 2025
B5: RESTRICCIONES OPERATIVAS
B6: FECHA | C6: HORA INICIO | D6: HORA FINAL | E6: EMPRESA | F6: UBICACIÓN | G6: T.Eq. | H6: EQUIPO | I6: DESCRIPCIÓN
B7: 15/03/2025 | C7: 00:00 | D7: 24:00 | E7: CELEPSA | F7: C.H. EL PLATANAL | G7: CH | H7: CENTRAL | I7: Debido al incremento del caudal del rio cañete y establecimiento de la temporada de avenida, se declara la C.H. El Platanal como CENTRAL HIDRÁULICA DE PASADA (correo 03/01/2025).
B8: 15/03/2025 | C8: 00:00 | D8: 24:00 | E8: EGASA | F8: C.H. CHARCANI II | G8: GH | H8: G2 | I8: El Grupo N°02 esta operando con una potencia no mayor a 0.07MW en referencia a 0.18MW de su potencia efectiva, con el fin de no generar daños mayores hasta la reparación de su cojinete.
B9: 15/03/2025 | C9: 00:00 | D9: 24:00 | E9: EGASA | F9: S.E. CONVERTIDOR | G9: BARRA | H9: BARRA138KV | I9: EGASA limitó la capacidad del transformador 138 kV/33 kV a 50 MVA por deterioro del aislamiento.
B10: 15/03/2025 | C10: 00:00 | D10: 24:00 | E10: ENEL GENERACION PIURA S.A. | F10: C.T. MALACAS | G10: CT | H10: CENTRAL | I10: De acuerdo con la comunicación vía correo del día 24.10.2024. ENEL GENERACIÓN PIURA informa una restricción de potencia para alcanzar 105 MW en simultaneo (TG6+TGN4).
B11: 15/03/2025 | C11: 00:00 | D11: 24:00 | E11: ENGIE | F11: C.E. PUNTA LOMITAS | G11: CE | H11: CENTRAL | I11: De acuerdo a la carta ENG/737-2024 (Exp:202400007555). Limitación de cables de media tensión a 100 MW de los transformadores PLT1 y PLT2 de la CE Punta Lomitas. Quedan limitados a 200 MW la generación de CE Punta Lomitas y Punta Lomitas Extensión.
B12: 15/03/2025 | C12: 00:00 | D12: 24:00 | E12: ENGIE | F12: C.H. QUITARACSA | G12: CH | H12: CENTRAL | I12: De acuerdo con el correo del 23.04 se considera la operación continua de la CH Quitaracsa debido a que el sistema de refrigeración de la CH Cañón del Pato se alimenta desde la descarga del caudal turbinado por la CH Quitaracsa.
B13: 15/03/2025 | C13: 00:00 | D13: 24:00 | E13: ENGIE | F13: C.H. YUNCÁN | G13: GH | H13: G3 | I13: Según la carta N° ENG/ 198-2024 enviada por su representada, se opera de forma continua el G3 de la CH Yuncán, debido a la ejecución de mantenimientos necesarios para evitar daños en los sellos de seguridad de la válvula esférica del grupo.
B14: 15/03/2025 | C14: 00:00 | D14: 24:00 | E14: ENGIE | F14: C.T. CHILCA 1 | G14: CT | H14: CENTRAL | I14: Restricción de temperatura de la C.T Chilca, ver valor en el modelo de despacho.
B15: 15/03/2025 | C15: 00:00 | D15: 24:00 | E15: ENGIE | F15: C.T. CHILCA 1 | G15: CT | H15: CENTRAL | I15: Con carta ENG/971-2023, indica que no puede cumplir con las IO considerada en el PDO_17122023 dado que vulneran la seguridad de sus activos. Indican que se debe tomar TMO=168h.
B16: 15/03/2025 | C16: 00:00 | D16: 24:00 | E16: ENGIE | F16: C.T. CHILCA 2 | G16: CT | H16: CENTRAL | I16: Con carta ENG/971-2023, indica que no puede cumplir con las IO considerada en el PDO_17122023 dado que vulneran la seguridad de sus activos. Indican que se debe tomar TMO=168h.
B17: 15/03/2025 | C17: 00:00 | D17: 24:00 | E17: ENGIE | F17: C.T. CHILCA 2 | G17: CT | H17: CENTRAL | I17: Restricción de temperatura de la C.T Chilca2, ver valor en el modelo de despacho.
... B50: 15/03/2025 | C50: 00:00 | D50: 24:00 | E50: TRANSMANTARO | F50: S.E. SOCABAYA | G50: SSEE | H50: S.E. | I50: Opera en simple barra en 220 kV por indisponibilidad de la protección diferencial de barras por alarma.

Sheet MANTENIMIENTO EJECUTADOS
B3: sábado, 15 de Marzo del 2025
B5: Mantenimiento Ejecutado
B6: Empresa | C6: Ubicación | D6: Equipo | E6: Inicio | F6: Final | G6: Descripción | H6: MW Indisp. | I6: Prog. | J6: Dispon | K6: Interrupc. | L6: Tipo | M6: CodEq | N6: TipoEq_Osinerg
B7: AGRO INDUSTRIAL PARAMONGA S.A. | C7: PARAMONGA | D7: TV-01 | E7: 15/03/2025 00:00 | F7: 15/03/2025 18:44 | G7: LIMPIEZA E INSPECCION DE LA CALDERA CBS Y MANTENIMIENTO A SUS PERIFERICOS (CONDUCTORES, VENTILADORES, BOMBAS, MOTORES, ETC) | H7: 14 | I7: P | J7: F/S | K7: N | L7: PREV. | M7: 12664 | N7: G
B8: ATLANTICA TRANSMISION SUR S.A. | C8: CHILCA-CTM | D8: INT-5261 | E8: 15/03/2025 00:00 | F8: 16/03/2025 00:00 | G8: Seccionador SBB-5261 fase S indisponible para maniobras de apertura y cierre por anomalia en tapa de tanque de compresion, el seccionador permanece cerrado y bloqueado. | H8: 0 | I8: P | J8: E/S | K8: N | L8: OTROS | M8: 13854 | N8: T
B9: ATLANTICA TRANSMISION SUR S.A. | C9: MONTALVO | D9: ACOPLE 220 | E9: 15/03/2025 00:00 | F9: 16/03/2025 00:00 | G9: Proyecto Refuerzos: Reemplazo del HMI existente, Pruebas y Configuracion. No se contara con nivel 1 de operacion. | H9: 0 | I9: P | J9: E/S | K9: N | L9: P.ENERG | M9: 14767 | N9: T
B10: ATLANTICA TRANSMISION SUR S.A. | C10: MONTALVO | D10: CL-2057 | E10: 15/03/2025 00:00 | F10: 16/03/2025 00:00 | G10: Proyecto Refuerzos: Reemplazo del HMI existente, Pruebas y Configuracion. No se contara con nivel 1 de operacion. | H10: 0 | I10: P | J10: E/S | K10: N | L10: P.ENERG | M10: 13812 | N10: T
B11: ATLANTICA TRANSMISION SUR S.A. | C11: MONTALVO | D11: CL-AUT-5671_500 | E11: 15/03/2025 00:00 | F11: 16/03/2025 00:00 | G11: Proyecto Refuerzos: Reemplazo del HMI existente, Pruebas y Configuracion. No se contara con nivel 1 de operacion en INT-5671, INT-5652 y SAT-5671. | H11: 0 | I11: P | J11: E/S | K11: N | L11: P.ENERG | M11: 13809 | N11: T
B12: ATLANTICA TRANSMISION SUR S.A. | C12: MONTALVO | D12: INT-5652 | E12: 15/03/2025 00:00 | F12: 16/03/2025 00:00 | G12: Proyecto Refuerzos:Indisponible por Implementacion de conexion de corrientes, disparos, posiciones, enclavamientos hacia los nuevos equipos del transformador. Pruebas y Puesta en servicio. AUT-5671 en servicio solo por Barra A 500kV. | H12: 0 | I12: P | J12: F/S | K12: N | L12: P.ENERG | M12: 13765 | N12: T
B13: ATLANTICA TRANSMISION SUR S.A. | C13: OCONA | D13: INT-5450 | E13: 15/03/2025 00:00 | F13: 16/03/2025 00:00 | G13: RESTRICCION OPERATIVA EN INTERRUPTOR INT-5450, POSICION CERRADA, REB-5450 EN SERVICIO SUMINISTRANDO LOS SS.AA. DE S.E. OCO?A | H13: 0 | I13: P | J13: E/S | K13: N | L13: OTROS | M13: 13761 | N13: T
B14: ATLANTICA TRANSMISION SUR S.A. | C14: OCONA | D14: INT-5462 | E14: 15/03/2025 00:00 | F14: 16/03/2025 00:00 | G14: Seccionador SBA-5462 fase T indisponible por problemas mecanicos, el seccionador permanece cerrado y bloqueado | H14: 0 | I14: P | J14: E/S | K14: N | L14: OTROS | M14: 13758 | N14: T
B15: ATLANTICA TRANSMISION SUR S.A. | C15: POROMA | D15: ACOPLE 220 | E15: 15/03/2025 00:00 | F15: 16/03/2025 00:00 | G15: Proyecto Refuerzos: Reemplazo del HMI existente, Pruebas y Configuracion. No se contara con nivel 1 de operacion. | H15: 0 | I15: P | J15: E/S | K15: N | L15: P.ENERG | M15: 13797 | N15: T
B16: ATLANTICA TRANSMISION SUR S.A. | C16: POROMA | D16: CL-2292 | E16: 15/03/2025 00:00 | F16: 16/03/2025 00:00 | G16: Proyecto Refuerzos: Reemplazo del HMI existente, Pruebas y Configuracion. No se contara con nivel 1 de operacion. | H16: 0 | I16: P | J16: E/S | K16: N | L16: P.ENERG | M16: 13798 | N16: T
B17: ATLANTICA TRANSMISION SUR S.A. | C17: POROMA | D17: CL-2293 | E17: 15/03/2025 00:00 | F17: 16/03/2025 00:00 | G17: Proyecto Refuerzos: Reemplazo del HMI existente, Pruebas y Configuracion. No se contara con nivel 1 de operacion. | H17: 0 | I17: P | J17: E/S | K17: N | L17: P.ENERG | M17: 13799 | N17: T
B18: ATLANTICA TRANSMISION SUR S.A. | C18: POROMA | D18: CL-AUT5371_220 | E18: 15/03/2025 00:00 | F18: 16/03/2025 00:00 | G18: Proyecto Refuerzos: Reemplazo del HMI existente, Pruebas y Configuracion. No se contara con nivel 1 de operacion. | H18: 0 | I18: P | J18: E/S | K18: N | L18: P.ENERG | M18: 13796 | N18: T
... B113: TRANSMANTARO | C113: YARABAMBA | D113: IN-5120 | E113: 15/03/2025 00:00 | F113: 16/03/2025 00:00 | G113: INTERRUPTOR INDISPONIBLE POR FALLA EN LOS MANDOS DE CONTROL DE N1, N2 Y N3. | H113: 0 | I113: P | J113: F/S | K113: N | L113: OTROS | M113: 17437 | N113: T

Sheet INGRESO OC
A3: sábado, 15 de Marzo del 2025
A5: INGRESO A OPERACIÓN COMERCIAL
A6: EMPRESA | B6: TIPO DE EQUIPO | C6: UBICACIÓN | D6: EQUIPO | E6: Fecha y hora de Ingreso a Operación Comercial

Sheet DESPACHO_EJECUTADO
B3: sábado, 15 de Marzo del 2025
A5: POTENCIA ACTIVA EJECUTADA DE LAS UNIDADES DE GENERACIÓN DEL SEIN (MW) | FJ5: CENTRALES NO INTEGRANTES COES
A6: FECHA | B6: HORA | C6: 337 | D6: 338 | E6: 101 | F6: 102 | G6: 42667 | H6: 42668 | I6: 126 | J6: 127 | K6: 138 | L6: 139 | M6: 197 | N6: 203 | O6: 204 | P6: 230 | Q6: 209 | R6: 56677 | S6: 796 | T6: 2146 | U6: 142 | V6: 143 | W6: 125 | X6: 187 | Y6: 163 | Z6: 298 | AA6: 299 | AB6: 219 | AC6: 151 | AD6: 152 | AE6: 153 | AF6: 154 | AG6: 756 | AH6: 156 | AI6: 155 | AJ6: 182 | AK6: 212 | AL6: 758 | AM6: 263 | AN6: 265 | AO6: 775 | AP6: 777 | AQ6: 2154 | AR6: 150 | AS6: 149 | AT6: 188 | AU6: 2131 | AV6: 755 | AW6: 252 | AX6: 249 | AY6: 250 | AZ6: 117 | BA6: 267 | BB6: 268 | BC6: 119 | BD6: 120 | BE6: 189 | BF6: 122 | BG6: 266 | BH6: 251 | BI6: 115 | BJ6: 239 | BK6: 288 | BL6: 240 | BM6: 241 | BN6: 242 | BO6: 191 | BP6: 194 | BQ6: 196 | BR6: 207 | BS6: 236 | BT6: 795 | BU6: 285 | BV6: 995 | BW6: 996 | BX6: 997 | BY6: 766 | BZ6: 926 | CA6: 924 | CB6: 121 | CC6: 103 | CD6: 104 | CE6: 106 | CF6: 105 | CG6: 107 | CH6: 110 | CI6: 109 | CJ6: 144 | CK6: 113 | CL6: 114 | CM6: 193 | CN6: 208 | CO6: 786 | CP6: 787 | CQ6: 788 | CR6: 789 | CS6: 248 | CT6: 2159 | CU6: 303 | CV6: 59715 | CW6: 62255 | CX6: 1263 | CY6: 61800 | CZ6: 2194 | DA6: 216 | DB6: 198 | DC6: 49607 | DD6: 214 | DE6: 260 | DF6: 2152 | DG6: 2128 | DH6: 247 | DI6: 228 | DJ6: 2135 | DK6: 261 | DL6: 237 | DM6: 253 | DN6: 770 | DO6: 225 | DP6: 2201 | DQ6: 2171 | DR6: 760 | DS6: 235 | DT6: 238 | DU6: 2184 | DV6: 61855 | DW6: 223 | DX6: 226 | DY6: 201 | DZ6: 258 | EA6: 259 | EB6: 920 | EC6: 257 | ED6: 256 | EE6: 2148 | EF6: 58288 | EG6: 58289 | EH6: 58839 | EI6: 58840 | EJ6: 296 | EK6: 297 | EL6: 211 | EM6: 2175 | EN6: 2178 | EO6: 2181 | EP6: 1262 | EQ6: 233 | ER6: 2150 | ES6: 2165 | ET6: 2161 | EU6: 61197 | EV6: 58851 | EW6: 234 | EX6: 215 | EY6: 917 | EZ6: 289 | FA6: 58333 | FB6: 58336 | FC6: 202 | FD6: 58487 | FE6: 213 | FF6: 232 | FG6: 2190 | FH6: TOTAL COES | FJ6: 221 | FK6: 222 | FL6: 224 | FM6: 2187 | FN6: 227 | FO6: 49400 | FP6: 199 | FQ6: 200 | FR6: TOTAL NO COES
C7: CENTRO | D7: CENTRO | E7: CENTRO | F7: CENTRO | G7: NORTE | H7: NORTE | I7: NORTE | J7: NORTE | K7: CENTRO | L7: CENTRO | M7: CENTRO | N7: CENTRO | O7: CENTRO | P7: CENTRO | Q7: CENTRO | R7: CENTRO | S7: CENTRO | T7: CENTRO | U7: CENTRO | V7: CENTRO | W7: CENTRO | X7: CENTRO | Y7: SUR | Z7: SUR | AA7: SUR | AB7: CENTRO | AC7: SUR | AD7: SUR | AE7: SUR | AF7: SUR | AG7: SUR | AH7: SUR | AI7: SUR | AJ7: SUR | AK7: CENTRO | AL7: NORTE | AM7: NORTE | AN7: NORTE | AO7: CENTRO | AP7: CENTRO | AQ7: CENTRO | AR7: CENTRO | AS7: CENTRO | AT7: CENTRO | AU7: CENTRO | AV7: SUR | AW7: CENTRO | AX7: CENTRO | AY7: CENTRO | AZ7: CENTRO | BA7: CENTRO | BB7: CENTRO | BC7: CENTRO | BD7: CENTRO | BE7: SUR | BF7: NORTE | BG7: CENTRO | BH7: CENTRO | BI7: NORTE | BJ7: NORTE | BK7: NORTE | BL7: SUR | BM7: SUR | BN7: SUR | BO7: CENTRO | BP7: CENTRO | BQ7: CENTRO | BR7: CENTRO | BS7: CENTRO | BT7: CENTRO | BU7: CENTRO | BV7: SUR | BW7: SUR | BX7: SUR | BY7: NORTE | BZ7: SUR | CA7: CENTRO | CB7: NORTE | CC7: CENTRO | CD7: CENTRO | CE7: CENTRO | CF7: CENTRO | CG7: CENTRO | CH7: CENTRO | CI7: CENTRO | CJ7: CENTRO | CK7: CENTRO | CL7: CENTRO | CM7: CENTRO | CN7: CENTRO | CO7: SUR | CP7: SUR | CQ7: SUR | CR7: SUR | CS7: CENTRO | CT7: CENTRO | CU7: CENTRO | CV7: CENTRO | CW7: SUR | CX7: NORTE | CY7: NORTE | CZ7: NORTE | DA7: NORTE | DB7: NORTE | DC7: SUR | DD7: CENTRO | DE7: CENTRO | DF7: CENTRO | DG7: NORTE | DH7: NORTE | DI7: CENTRO | DJ7: CENTRO | DK7: SUR | DL7: SUR | DM7: CENTRO | DN7: CENTRO | DO7: CENTRO | DP7: CENTRO | DQ7: CENTRO | DR7: CENTRO | DS7: SUR | DT7: CENTRO | DU7: CENTRO | DV7: NORTE | DW7: CENTRO | DX7: CENTRO | DY7: NORTE | DZ7: CENTRO | EA7: CENTRO | EB7: CENTRO | EC7: NORTE | ED7: NORTE | EE7: SUR | EF7: CENTRO | EG7: CENTRO | EH7: CENTRO | EI7: CENTRO | EJ7: CENTRO | EK7: CENTRO | EL7: SUR | EM7: SUR | EN7: SUR | EO7: SUR | EP7: NORTE | EQ7: SUR | ER7: SUR | ES7: CENTRO | ET7: CENTRO | EU7: CENTRO | EV7: SUR | EW7: SUR | EX7: NORTE | EY7: CENTRO | EZ7: NORTE | FA7: NORTE | FB7: NORTE | FC7: CENTRO | FD7: CENTRO | FE7: CENTRO | FF7: NORTE | FG7: NORTE | FJ7: NORTE | FK7: CENTRO | FL7: NORTE | FM7: NORTE | FN7: NORTE | FO7: NORTE | FP7: NORTE | FQ7: NORTE
C8: HIDROELÉCTRICA | D8: HIDROELÉCTRICA | E8: HIDROELÉCTRICA | F8: HIDROELÉCTRICA | G8: TERMOELÉCTRICA | H8: TERMOELÉCTRICA | I8: HIDROELÉCTRICA | J8: HIDROELÉCTRICA | K8: TERMOELÉCTRICA | L8: TERMOELÉCTRICA | M8: TERMOELÉCTRICA | N8: TERMOELÉCTRICA | O8: TERMOELÉCTRICA | P8: TERMOELÉCTRICA | Q8: TERMOELÉCTRICA | R8: TERMOELÉCTRICA | S8: HIDROELÉCTRICA | T8: HIDROELÉCTRICA | U8: TERMOELÉCTRICA | V8: TERMOELÉCTRICA | W8: TERMOELÉCTRICA | X8: TERMOELÉCTRICA | Y8: HIDROELÉCTRICA | Z8: HIDROELÉCTRICA | AA8: HIDROELÉCTRICA | AB8: TERMOELÉCTRICA | AC8: HIDROELÉCTRICA | AD8: HIDROELÉCTRICA | AE8: HIDROELÉCTRICA | AF8: HIDROELÉCTRICA | AG8: TERMOELÉCTRICA | AH8: TERMOELÉCTRICA | AI8: TERMOELÉCTRICA | AJ8: HIDROELÉCTRICA | AK8: HIDROELÉCTRICA | AL8: TERMOELÉCTRICA | AM8: TERMOELÉCTRICA | AN8: TERMOELÉCTRICA | AO8: HIDROELÉCTRICA | AP8: HIDROELÉCTRICA | AQ8: HIDROELÉCTRICA | AR8: HIDROELÉCTRICA | AS8: HIDROELÉCTRICA | AT8: HIDROELÉCTRICA | AU8: HIDROELÉCTRICA | AV8: HIDROELÉCTRICA | AW8: TERMOELÉCTRICA | AX8: TERMOELÉCTRICA | AY8: TERMOELÉCTRICA | AZ8: HIDROELÉCTRICA | BA8: HIDROELÉCTRICA | BB8: HIDROELÉCTRICA | BC8: HIDROELÉCTRICA | BD8: HIDROELÉCTRICA | BE8: HIDROELÉCTRICA | BF8: HIDROELÉCTRICA | BG8: HIDROELÉCTRICA | BH8: HIDROELÉCTRICA | BI8: TERMOELÉCTRICA | BJ8: TERMOELÉCTRICA | BK8: TERMOELÉCTRICA | BL8: TERMOELÉCTRICA | BM8: TERMOELÉCTRICA | BN8: TERMOELÉCTRICA | BO8: HIDROELÉCTRICA | BP8: TERMOELÉCTRICA | BQ8: TERMOELÉCTRICA | BR8: TERMOELÉCTRICA | BS8: TERMOELÉCTRICA | BT8: TERMOELÉCTRICA | BU8: TERMOELÉCTRICA | BV8: TERMOELÉCTRICA | BW8: TERMOELÉCTRICA | BX8: TERMOELÉCTRICA | BY8: HIDROELÉCTRICA | BZ8: TERMOELÉCTRICA | CA8: TERMOELÉCTRICA | CB8: HIDROELÉCTRICA | CC8: HIDROELÉCTRICA | CD8: HIDROELÉCTRICA | CE8: HIDROELÉCTRICA | CF8: HIDROELÉCTRICA | CG8: HIDROELÉCTRICA | CH8: TERMOELÉCTRICA | CI8: TERMOELÉCTRICA | CJ8: TERMOELÉCTRICA | CK8: TERMOELÉCTRICA | CL8: TERMOELÉCTRICA | CM8: TERMOELÉCTRICA | CN8: TERMOELÉCTRICA | CO8: TERMOELÉCTRICA | CP8: TERMOELÉCTRICA | CQ8: TERMOELÉCTRICA | CR8: TERMOELÉCTRICA | CS8: TERMOELÉCTRICA | CT8: TERMOELÉCTRICA | CU8: SOLAR | CV8: EÓLICA | CW8: SOLAR | CX8: EÓLICA | CY8: SOLAR | CZ8: HIDROELÉCTRICA | DA8: HIDROELÉCTRICA | DB8: HIDROELÉCTRICA | DC8: HIDROELÉCTRICA | DD8: HIDROELÉCTRICA | DE8: HIDROELÉCTRICA | DF8: HIDROELÉCTRICA | DG8: HIDROELÉCTRICA | DH8: HIDROELÉCTRICA | DI8: HIDROELÉCTRICA | DJ8: HIDROELÉCTRICA | DK8: SOLAR | DL8: SOLAR | DM8: EÓLICA | DN8: EÓLICA | DO8: TERMOELÉCTRICA | DP8: TERMOELÉCTRICA | DQ8: TERMOELÉCTRICA | DR8: TERMOELÉCTRICA | DS8: SOLAR | DT8: HIDROELÉCTRICA | DU8: HIDROELÉCTRICA | DV8: HIDROELÉCTRICA | DW8: HIDROELÉCTRICA | DX8: HIDROELÉCTRICA | DY8: HIDROELÉCTRICA | DZ8: HIDROELÉCTRICA | EA8: HIDROELÉCTRICA | EB8: HIDROELÉCTRICA | EC8: EÓLICA | ED8: EÓLICA | EE8: SOLAR | EF8: EÓLICA | EG8: EÓLICA | EH8: EÓLICA | EI8: EÓLICA | EJ8: HIDROELÉCTRICA | EK8: HIDROELÉCTRICA | EL8: HIDROELÉCTRICA | EM8: HIDROELÉCTRICA | EN8: HIDROELÉCTRICA | EO8: HIDROELÉCTRICA | EP8: EÓLICA | EQ8: SOLAR | ER8: SOLAR | ES8: HIDROELÉCTRICA | ET8: EÓLICA | EU8: EÓLICA | EV8: SOLAR | EW8: SOLAR | EX8: HIDROELÉCTRICA | EY8: HIDROELÉCTRICA | EZ8: TERMOELÉCTRICA | FA8: TERMOELÉCTRICA | FB8: TERMOELÉCTRICA | FC8: TERMOELÉCTRICA | FD8: TERMOELÉCTRICA | FE8: TERMOELÉCTRICA | FF8: TERMOELÉCTRICA | FG8: TERMOELÉCTRICA | FJ8: HIDROELÉCTRICA | FK8: HIDROELÉCTRICA | FL8: HIDROELÉCTRICA | FM8: HIDROELÉCTRICA | FN8: TERMOELÉCTRICA | FO8: TERMOELÉCTRICA | FP8: HIDROELÉCTRICA | FQ8: HIDROELÉCTRICA
C9: CENTRALES SANTA ROSA S.A.C. | D9: CENTRALES SANTA ROSA S.A.C. | E9: ELECTROPERU | F9: ELECTROPERU | G9: ELECTROPERU | H9: ELECTROPERU | I9: ORAZUL ENERGY PERÚ | J9: ORAZUL ENERGY PERÚ | K9: TERMOSELVA | L9: TERMOSELVA | M9: KALLPA GENERACION S.A. | N9: KALLPA GENERACION S.A. | O9: KALLPA GENERACION S.A. | P9: KALLPA GENERACION S.A. | Q9: KALLPA GENERACION S.A. | R9: KALLPA GENERACION S.A. | S9: KALLPA GENERACION S.A. | T9: KALLPA GENERACION S.A. | U9: SHOUGESA | V9: SHOUGESA | W9: SHOUGESA | X9: SHOUGESA | Y9: EGEMSA | Z9: EGESUR | AA9: EGESUR | AB9: EGESUR | AC9: EGASA | AD9: EGASA | AE9: EGASA | AF9: EGASA | AG9: EGASA | AH9: EGASA | AI9: EGASA | AJ9: SAN GABAN | AK9: CELEPSA | AL9: MINERA CERRO VERDE | AM9: PLANTA DE RESERVA FRIA DE GENERACION DE ETEN S.A. | AN9: PLANTA DE RESERVA FRIA DE GENERACION DE ETEN S.A. | AO9: EMPRESA DE GENERACION HUALLAGA | AP9: EMPRESA DE GENERACION HUALLAGA | AQ9: LA VIRGEN | AR9: CHINANGO S.A.C. | AS9: CHINANGO S.A.C. | AT9: HIDROELECTRICA HUANCHOR S.A.C. | AU9: CELEPSA RENOVABLES S.R.L. | AV9: INLAND ENERGY SAC | AW9: FENIX POWER PERÚ | AX9: FENIX POWER PERÚ | AY9: FENIX POWER PERÚ | AZ9: STATKRAFT S.A | BA9: STATKRAFT S.A | BB9: STATKRAFT S.A | BC9: STATKRAFT S.A | BD9: STATKRAFT S.A | BE9: STATKRAFT S.A | BF9: STATKRAFT S.A | BG9: STATKRAFT S.A | BH9: EMPRESA DE GENERACION HUANZA | BI9: ENEL GENERACION PIURA S.A. | BJ9: ENEL GENERACION PIURA S.A. | BK9: ENEL GENERACION PIURA S.A. | BL9: ENGIE | BM9: ENGIE | BN9: ENGIE | BO9: ENGIE | BP9: ENGIE | BQ9: ENGIE | BR9: ENGIE | BS9: ENGIE | BT9: ENGIE | BU9: ENGIE | BV9: ENGIE | BW9: ENGIE | BX9: ENGIE | BY9: ENGIE | BZ9: INFRAESTRUCTURAS Y ENERGIAS DEL PERU S.A.C. | CA9: INFRAESTRUCTURAS Y ENERGIAS DEL PERU S.A.C. | CB9: INVERSIONES SHAQSHA S.A.C. | CC9: ORYGEN PERU S.A.A. | CD9: ORYGEN PERU S.A.A. | CE9: ORYGEN PERU S.A.A. | CF9: ORYGEN PERU S.A.A. | CG9: ORYGEN PERU S.A.A. | CH9: ORYGEN PERU S.A.A. | CI9: ORYGEN PERU S.A.A. | CJ9: ORYGEN PERU S.A.A. | CK9: ORYGEN PERU S.A.A. | CL9: ORYGEN PERU S.A.A. | CM9: ORYGEN PERU S.A.A. | CN9: ORYGEN PERU S.A.A. | CO9: SAMAY I S.A.C | CP9: SAMAY I S.A.C | CQ9: SAMAY I S.A.C | CR9: SAMAY I S.A.C | CS9: TERMOCHILCA S.A.C. | CT9: TERMOCHILCA S.A.C. | CU9: COLCA SOLAR S.A.C. | CV9: ENERGIA RENOVABLE DEL SUR S.A. | CW9: GR CORTARRAMA SOCIEDAD ANONIMA CERRADA | CX9: GR TARUCA SOCIEDAD ANONIMA CERRADA | CY9: KONDU SAC | CZ9: PERUANA DE INVERSIONES EN ENERGIAS RENOVABLES S.A. | DA9: ORAZUL ENERGY PERÚ | DB9: ORAZUL ENERGY PERÚ | DC9: SAN GABAN | DD9: MAJA ENERGIA S.A.C. | DE9: EMPRESA DE GENERACION ELECTRICA CANCHAYLLO SAC | DF9: EMPRESA DE GENERACION ELECTRICA SANTA ANA S.A.C. | DG9: EMPRESA ELECTRICA AGUA AZUL | DH9: EMPRESA ELECTRICA RIO DOBLE | DI9: HIDROCAÑETE S.A. | DJ9: HUAURA POWER GROUP S.A. | DK9: MOQUEGUA FV S.A.C. | DL9: PANAMERICANA SOLAR SAC. | DM9: PARQUE EOLICO MARCONA S.A.C. | DN9: PARQUE EOLICO TRES HERMANAS S.A.C. | DO9: PETRAMAS | DP9: PETRAMAS | DQ9: PETRAMAS | DR9: PETRAMAS | DS9: TACNA SOLAR SAC. | DT9: ELECTRICA YANAPAMPA SAC | DU9: ANDEAN POWER S.A.C. | DV9: ASOCIACIÓN SANTA LUCIA DE CHACAS | DW9: ATRIA ENERGIA S.A.C. | DX9: EGEJUNIN | DY9: EGEJUNIN | DZ9: EGEJUNIN | EA9: EGEJUNIN | EB9: EMPRESA DE GENERACION ELECTRICA RIO BAÑOS S.A.C. | EC9: ENERGÍA EÓLICA S.A. | ED9: ENERGÍA EÓLICA S.A. | EE9: ENGIE | EF9: ENGIE | EG9: ENGIE | EH9: ENGIE | EI9: ENGIE | EJ9: GENERACIÓN ANDINA S.A.C. | EK9: GENERACIÓN ANDINA S.A.C. | EL9: GENERADORA DE ENERGÍA DEL PERÚ | EM9: GENERADORA DE ENERGÍA DEL PERÚ | EN9: GENERADORA DE ENERGÍA DEL PERÚ | EO9: GENERADORA DE ENERGÍA DEL PERÚ | EP9: GR PAINO SOCIEDAD ANONIMA CERRADA | EQ9: MAJES ARCUS S.A.C. | ER9: ORYGEN PERU S.A.A. | ES9: ORYGEN PERU S.A.A. | ET9: ORYGEN PERU S.A.A. | EU9: ORYGEN PERU S.A.A. | EV9: ORYGEN PERU S.A.A. | EW9: REPARTICIÓN ARCUS S.A.C. | EX9: SINERSA | EY9: SINERSA | EZ9: BIOENERGIA DEL CHIRA S.A. | FA9: GM OPERACIONES S.A.C. | FB9: GM OPERACIONES S.A.C. | FC9: SDF ENERGIA SAC | FD9: SDF ENERGIA SAC | FE9: AGRO INDUSTRIAL PARAMONGA S.A. | FF9: AGROAURORA S.A.C. | FG9: AGROINDUSTRIAS SAN JACINTO S.A.A. | FJ9: UNACEM PERU S.A. | FK9: ELECTRO ORIENTE | FL9: AGUAS Y ENERGIA PERU | FM9: ELECTRO ZAÑA S.A.C. | FN9: ELECTRONOROESTE S.A. | FO9: SDE PIURA | FP9: SINERSA | FQ9: SINERSA
C10: SANTA ROSA 1 | D10: SANTA ROSA 2 | E10: MANTARO | F10: RESTITUCION | G10: TUMBES MAK 1 | H10: TUMBES MAK 2 | I10: CARHUAQUERO | J10: CAÑON DEL PATO | K10: AGUAYTIA TG1 | L10: AGUAYTIA TG2 | M10: KALLPA TG1 | N10: KALLPA TG2 | O10: KALLPA TG3 | P10: KALLPA TV | Q10: LFLORES TG1 | R10: LFLORES TV | S10: CERRO DEL AGUILA | T10: CERRODELAGUILAG4 | U10: SHOUGESA TV1 | V10: SHOUGESA TV2 | W10: SHOUGESA TV3 | X10: SHOUGESA CUMMINS | Y10: MACHUPICCHU | Z10: ARICOTA 1 | AA10: ARICOTA 2 | AB10: INDEPENDENCIA | AC10: CHARCANI I,II,III | AD10: CHARCANI IV | AE10: CHARCANI V | AF10: CHARCANI VI | AG10: CHILINA TG | AH10: MOLLENDO 1, 2, 3 | AI10: CHILINA (SULZ 1,2) | AJ10: SAN GABAN II | AK10: PLATANAL | AL10: RECKA | AM10: RF ETEN TG1 | AN10: RF ETEN TG2 | AO10: CHAGLLA GP1 | AP10: CHAGLLA | AQ10: LA VIRGEN | AR10: CHIMAY | AS10: YANANGO | AT10: HUANCHOR | AU10: MARAÑON | AV10: STA TERESA | AW10: FENIX GT11 | AX10: FENIX GT12 | AY10: FENIX TV10 | AZ10: YAUPI | BA10: OROYA | BB10: PACHACHACA | BC10: MALPASO | BD10: CAHUA | BE10: ARCATA | BF10: GALLITO CIEGO | BG10: CHEVES | BH10: HUANZA | BI10: MALACAS2 TG4 | BJ10: MALACAS3 TG 5 | BK10: MALACAS1 TG6 | BL10: RF ILO2 TG1 | BM10: RF ILO2 TG2 | BN10: RF ILO2 TG3 | BO10: YUNCAN | BP10: CHILCA1 TG1 | BQ10: CHILCA1 TG2 | BR10: CHILCA1 TG3 | BS10: CHILCA-TV | BT10: CHILCA2 TG41 | BU10: CHILCA2-TV | BV10: CTNEPI_TG41 | BW10: CTNEPI_TG42 | BX10: CTNEPI_TG43 | BY10: QUITARACSA | BZ10: RF PTO MALDONADO | CA10: RF PUCALLPA | CB10: PARIAC | CC10: HUINCO | CD10: MATUCANA | CE10: MOYOPAMPA | CF10: CALLAHUANCA | CG10: HUAMPANI | CH10: STA ROSA WEST TG7 | CI10: UTI_5 | CJ10: UTI_6 | CK10: VENTANILLA 3 | CL10: VENTANILLA 4 | CM10: VENTANILLA TV | CN10: STAROSA TG8 | CO10: PTO_BRVO TG1 | CP10: PTO_BRVO TG2 | CQ10: PTO_BRVO TG3 | CR10: PTO_BRVO TG4 | CS10: OLLEROS TG1 | CT10: OLLEROS TV | CU10: CS YARUCAYA | CV10: SAN JUAN | CW10: MATARANI | CX10: DUNA | CY10: CARHUAQUERO (CS) | CZ10: MANTA I | DA10: CARHUAQUERO4 | DB10: CAÑA BRAVA | DC10: TUPURI | DD10: RONCADOR | DE10: CANCHAYLLO | DF10: RENOVANDESH1 | DG10: POTRERO | DH10: PIZARRAS | DI10: NIMPERIAL | DJ10: YARUCAYA | DK10: MOQUEGUA-SOLAR | DL10: PANAMERICANA-SOLAR | DM10: PQE-EOLICO-MARCONA | DN10: PQE-EOLICO-3-HERMANAS | DO10: HUAYCOLORO | DP10: CALLAO | DQ10: DONA_CATALINA | DR10: LAGRINGAV | DS10: TACNA-SOLAR | DT10: YANAPAMPA | DU10: CARHUAC | DV10: HUALLIN | DW10: PURMACANA | DX10: HUASAHUASI | DY10: STACRUZ_1_2 | DZ10: RUNATULLO_II | EA10: RUNATULLO_III | EB10: RUCUY | EC10: PQE-EOLICO-TALARA | ED10: PQE-EOLICO-CUPISNIQUE | EE10: INTIPAMPA | EF10: PUNTA LOMITAS-BL1 | EG10: PUNTA LOMITAS-BL2 | EH10: PUN LOMITAS_EXP-BL1 | EI10: PUN LOMITAS_EXP-BL2 | EJ10: 8AGOSTO | EK10: EL CARMEN | EL10: LA JOYA | EM10: ANGEL_I | EN10: ANGEL_II | EO10: ANGEL_III | EP10: HUAMBOS | EQ10: MAJES | ER10: RUBI | ES10: CH_HER1 | ET10: WAYRA-I | EU10: WAYRA EXTENSION | EV10: CLEMESI | EW10: REPARTICION | EX10: POECHOS2 | EY10: CHANCAY | EZ10: CANA BRAVA | FA10: REFINERIA TALARA TV1 | FB10: REFINERÍA TALARA TV2 | FC10: OQUENDO TG1 | FD10: OQUENDO TV1 | FE10: PARAMONGA | FF10: MAPLE | FG10: SAN_JACINTO | FH10: MW | FJ10: CARPAPATA | FK10: CENTRALES ELOR | FL10: PIAS1 | FM10: ZANA | FN10: TABLAZO | FO10: TALLANCA | FP10: CURUMUY | FQ10: POECHOS1 | FR10: MW
A11: 15/03/2025 | B11: 00:30 | C11: 0.9 | D11: 1.5 | E11: 649.7 | F11: 218.5 | I11: 89.4 | J11: 143.8 | M11: 107.4 | N11: 0 | O11: 107.7 | P11: 137.3 | Q11: 108.1 | R11: 68 | S11: 379 | T11: 10.5 | Y11: 161.1 | Z11: 8.4 | AA11: 3 | AC11: 6.2 | AD11: 8.1 | AE11: 142.3 | AF11: 3.6 | AJ11: 110.4 | AK11: 222.6 | AO11: 6.6 | AP11: 459.5 | AQ11: 81.7 | AR11: 148.4 | AS11: 42.4 | AT11: 18.5 | AU11: 17.8 | AV11: 91 | AW11: 50.7 | AX11: 122.3 | AY11: 137.9 | AZ11: 108.2 | BC11: 45.2 | BD11: 39.6 | BE11: 4 | BF11: 38.4 | BG11: 173.3 | BH11: 94.4 | BI11: 25.2 | BO11: 86.6 | BP11: 137.3 | BQ11: 137.3 | BR11: 138.3 | BS11: 219.3 | CB11: 2.1 | CC11: 267.4 | CD11: 127.7 | CE11: 62.8 | CF11: 79.8 | CG11: 29.9 | CL11: 142 | CM11: 65 | CU11: 0 | CV11: 80.6 | CW11: 0 | CX11: 2.6 | CY11: 0 | DA11: 9.8 | DB11: 0 | DC11: 1.1 | DD11: 1.8 | DE11: 4.8 | DF11: 20.1 | DG11: 20 | DH11: 18.3 | DI11: 0 | DJ11: 18.5 | DK11: 0 | DL11: 0 | DM11: 23.3 | DN11: 53.8 | DO11: 4.8 | DP11: 2.4 | DQ11: 2.4 | DR11: 1 | DS11: 0 | DT11: 3.2 | DU11: 20.3 | DV11: 3 | DW11: 0.3 | DX11: 19.9 | DY11: 12.7 | DZ11: 20.2 | EA11: 20.2 | EB11: 19.9 | EC11: 7.8 | ED11: 25.3 | EE11: 0 | EF11: 21 | EG11: 52.9 | EH11: 1.1 | EI11: 0.4 | EJ11: 21 | EK11: 8.4 | EL11: 4 | EM11: 20.4 | EN11: 20.4 | EO11: 20 | EP11: 2.3 | EQ11: 0 | ER11: 0 | ES11: 0.6 | ET11: 60 | EU11: 51.9 | EV11: 0 | EW11: 0 | EX11: 9.4 | EY11: 20 | FA11: 31.3 | FB11: 34.6 | FC11: 28.9 | FD11: 3.5 | FE11: 0 | FF11: 0 | FG11: 7 | FH11: 6725.3 | FJ11: 24.45946 | FK11: 7.974 | FM11: 13.2 | FO11: 18.92064 | FP11: 10.9 | FQ11: 16 | FR11: 91.4541
A12: 15/03/2025 | B12: 01:00 | C12: 0.9 | D12: 0.7 | E12: 646.3 | F12: 216.9 | I12: 89.6 | J12: 144.3 | M12: 106.4 | N12: 0 | O12: 105.9 | P12: 135.7 | Q12: 108.1 | R12: 68.1 | S12: 374 | T12: 10.4 | Y12: 163.1 | Z12: 7.2 | AA12: 2.5 | AC12: 6.2 | AD12: 8.1 | AE12: 143.2 | AF12: 3.6 | AJ12: 109.8 | AK12: 221.4 | AO12: 6.6 | AP12: 452.1 | AQ12: 81.9 | AR12: 146.4 | AS12: 42.4 | AT12: 18.5 | AU12: 17.8 | AV12: 90.9 | AW12: 0 | AX12: 124 | AY12: 72.4 | AZ12: 105.6 | BC12: 43.8 | BD12: 39.8 | BE12: 4 | BF12: 37.5 | BG12: 174.1 | BH12: 93.7 | BI12: 25.1 | BO12: 86.8 | BP12: 132 | BQ12: 132 | BR12: 134.6 | BS12: 220.1 | CB12: 2.1 | CC12: 266.2 | CD12: 126.8 | CE12: 62.3 | CF12: 79.6 | CG12: 29.9 | CL12: 141.9 | CM12: 65.3 | CU12: 0 | CV12: 78.8 | CW12: 0 | CX12: 1.7 | CY12: 0 | DA12: 9.9 | DB12: 0 | DC12: 1.1 | DD12: 1.8 | DE12: 4.8 | DF12: 19.9 | DG12: 19.6 | DH12: 18.3 | DI12: 0 | DJ12: 18.5 | DK12: 0 | DL12: 0 | DM12: 22.4 | DN12: 57.2 | DO12: 4.8 | DP12: 2.4 | DQ12: 2.4 | DR12: 1 | DS12: 0 | DT12: 3.3 | DU12: 20.3 | DV12: 3 | DW12: 0.3 | DX12: 19.9 | DY12: 12.8 | DZ12: 19.7 | EA12: 20.2 | EB12: 20 | EC12: 9.6 | ED12: 23.7 | EE12: 0 | EF12: 22.7 | EG12: 52.8 | EH12: 1.4 | EI12: 1 | EJ12: 21 | EK12: 8.4 | EL12: 3.8 | EM12: 20.4 | EN12: 20.4 | EO12: 20 | EP12: 1.8 | EQ12: 0 | ER12: 0 | ES12: 0.6 | ET12: 55.3 | EU12: 48.7 | EV12: 0 | EW12: 0 | EX12: 9.2 | EY12: 20 | FA12: 31.3 | FB12: 34.7 | FC12: 28.8 | FD12: 3.4 | FE12: 0 | FF12: 0 | FG12: 7.7 | FH12: 6559.4 | FJ12: 24.47376 | FK12: 7.973 | FM12: 13.2 | FO12: 18.92033 | FP12: 10.9 | FQ12: 16 | FR12: 91.46709
A13: 15/03/2025 | B13: 01:30 | C13: 1.1 | D13: 1.6 | E13: 650.9 | F13: 217.7 | I13: 90.8 | J13: 145.7 | M13: 105.2 | N13: 0 | O13: 104.7 | P13: 135.5 | Q13: 108.8 | R13: 67.6 | S13: 376 | T13: 10.5 | Y13: 166.6 | Z13: 7.2 | AA13: 3.3 | AC13: 6.2 | AD13: 8 | AE13: 143.1 | AF13: 4.2 | AJ13: 111.1 | AK13: 222.3 | AO13: 6.6 | AP13: 463.2 | AQ13: 82 | AR13: 146.9 | AS13: 42.5 | AT13: 18.5 | AU13: 17.7 | AV13: 92.1 | AW13: 0 | AX13: 125.9 | AY13: 73.9 | AZ13: 108.9 | BC13: 46.2 | BD13: 40.5 | BE13: 4 | BF13: 39.2 | BG13: 175.6 | BH13: 95.6 | BI13: 24.2 | BO13: 87.4 | BP13: 119.1 | BQ13: 118.9 | BR13: 118 | BS13: 212.1 | CB13: 2.1 | CC13: 261.4 | CD13: 126.5 | CE13: 63.8 | CF13: 80.2 | CG13: 30.5 | CL13: 142.4 | CM13: 65.1 | CU13: 0 | CV13: 81.7 | CW13: 0 | CX13: 1 | CY13: 0 | DA13: 9.9 | DB13: 0 | DC13: 1.1 | DD13: 1.8 | DE13: 5.1 | DF13: 20.5 | DG13: 19.4 | DH13: 18.4 | DI13: 0 | DJ13: 18.5 | DK13: 0 | DL13: 0 | DM13: 19.5 | DN13: 55.6 | DO13: 4.8 | DP13: 2.4 | DQ13: 2.4 | DR13: 1 | DS13: 0 | DT13: 3.3 | DU13: 20.3 | DV13: 3 | DW13: 0.3 | DX13: 19.9 | DY13: 12.9 | DZ13: 19.8 | EA13: 20.3 | EB13: 20 | EC13: 10.5 | ED13: 27.2 | EE13: 0 | EF13: 16.7 | EG13: 44.1 | EH13: 1.7 | EI13: 1.1 | EJ13: 21 | EK13: 8.4 | EL13: 3.7 | EM13: 20.4 | EN13: 20.4 | EO13: 20 | EP13: 0.8 | EQ13: 0 | ER13: 0 | ES13: 0.6 | ET13: 44.2 | EU13: 41 | EV13: 0 | EW13: 0 | EX13: 9.2 | EY13: 20 | FA13: 31.5 | FB13: 35.4 | FC13: 28.7 | FD13: 3.4 | FE13: 0 | FF13: 0 | FG13: 7.5 | FH13: 6519.5 | FJ13: 24.48969 | FK13: 7.974 | FM13: 13.2 | FO13: 18.92022 | FP13: 10.9 | FQ13: 16 | FR13: 91.48391
A14: 15/03/2025 | B14: 02:00 | C14: 1 | D14: 1.7 | E14: 651.1 | F14: 218.8 | I14: 89.8 | J14: 144.5 | M14: 106.2 | N14: 42 | O14: 105.8 | P14: 133.4 | Q14: 110.2 | R14: 68.3 | S14: 378.9 | T14: 10.5 | Y14: 162 | Z14: 7 | AA14: 2.9 | AC14: 6.2 | AD14: 8.1 | AE14: 142.9 | AF14: 3.7 | AJ14: 110.9 | AK14: 220.5 | AO14: 6.6 | AP14: 460.9 | AQ14: 81.8 | AR14: 148.7 | AS14: 42.5 | AT14: 18.5 | AU14: 17.7 | AV14: 90.8 | AW14: 0 | AX14: 123.2 | AY14: 74.3 | AZ14: 107.9 | BC14: 45.2 | BD14: 40.2 | BE14: 4 | BF14: 38.6 | BG14: 173.5 | BH14: 94.7 | BI14: 24.9 | BO14: 87.1 | BP14: 105.4 | BQ14: 105.3 | BR14: 105.3 | BS14: 189.2 | CB14: 2.1 | CC14: 268.4 | CD14: 128.5 | CE14: 63 | CF14: 80 | CG14: 30.1 | CL14: 143.4 | CM14: 65.3 | CU14: 0 | CV14: 81.2 | CW14: 0 | CX14: 0.6 | CY14: 0 | DA14: 9.9 | DB14: 0 | DC14: 1.1 | DD14: 1.8 | DE14: 5.1 | DF14: 20.3 | DG14: 20 | DH14: 18.2 | DI14: 0 | DJ14: 18.5 | DK14: 0 | DL14: 0 | DM14: 21.2 | DN14: 55.9 | DO14: 4.8 | DP14: 2.4 | DQ14: 2.4 | DR14: 1.1 | DS14: 0 | DT14: 3.3 | DU14: 20.3 | DV14: 3 | DW14: 0.3 | DX14: 19.9 | DY14: 12.9 | DZ14: 19.5 | EA14: 20.3 | EB14: 20 | EC14: 9 | ED14: 26.5 | EE14: 0 | EF14: 16.7 | EG14: 45.8 | EH14: 1.8 | EI14: 1.6 | EJ14: 21 | EK14: 8.4 | EL14: 4.1 | EM14: 20.4 | EN14: 20.4 | EO14: 20 | EP14: 0.9 | EQ14: 0 | ER14: 0 | ES14: 0.6 | ET14: 41.3 | EU14: 28.9 | EV14: 0 | EW14: 0 | EX14: 9.2 | EY14: 20 | FA14: 31.6 | FB14: 34.4 | FC14: 28.9 | FD14: 3.4 | FE14: 0 | FF14: 0 | FG14: 6.5 | FH14: 6478.9 | FJ14: 24.44552 | FK14: 7.975 | FM14: 13.2 | FO14: 18.92014 | FP14: 10.9 | FQ14: 16.1 | FR14: 91.54066
A15: 15/03/2025 | B15: 02:30 | C15: 1 | D15: 1.7 | E15: 659.1 | F15: 219.1 | I15: 90.2 | J15: 146.5 | M15: 103.5 | N15: 56.8 | O15: 101.6 | P15: 126 | Q15: 108.5 | R15: 67.5 | S15: 388.2 | T15: 10.6 | Y15: 171.5 | Z15: 8.5 | AA15: 3.2 | AC15: 6.2 | AD15: 8 | AE15: 143.3 | AF15: 3.3 | AJ15: 111.1 | AK15: 220.9 | AO15: 6.6 | AP15: 447.8 | AQ15: 81.8 | AR15: 150.9 | AS15: 42.4 | AT15: 18.5 | AU15: 17.8 | AV15: 92.5 | AW15: 0 | AX15: 125.5 | AY15: 73 | AZ15: 108.8 | BC15: 45.6 | BD15: 40.7 | BE15: 4 | BF15: 39.5 | BG15: 177.4 | BH15: 95.8 | BI15: 0 | BO15: 88.2 | BP15: 69.5 | BQ15: 69.2 | BR15: 68.6 | BS15: 173.7 | CB15: 2.1 | CC15: 276.2 | CD15: 132.2 | CE15: 64.9 | CF15: 80.4 | CG15: 30.8 | CL15: 141.2 | CM15: 63.8 | CU15: 0 | CV15: 76.3 | CW15: 0 | CX15: 0.5 | CY15: 0 | DA15: 9.9 | DB15: 0 | DC15: 1.1 | DD15: 1.8 | DE15: 5.1 | DF15: 20.8 | DG15: 19.2 | DH15: 18.4 | DI15: 0 | DJ15: 18.5 | DK15: 0 | DL15: 0 | DM15: 18 | DN15: 49.3 | DO15: 4.8 | DP15: 2.4 | DQ15: 2.4 | DR15: 1 | DS15: 0 | DT15: 3.3 | DU15: 20.3 | DV15: 3 | DW15: 0.3 | DX15: 19.9 | DY15: 12.9 | DZ15: 19.3 | EA15: 20.3 | EB15: 19.9 | EC15: 8.4 | ED15: 25.8 | EE15: 0 | EF15: 21.9 | EG15: 58.5 | EH15: 1.9 | EI15: 1.5 | EJ15: 21 | EK15: 8.4 | EL15: 4.1 | EM15: 20.4 | EN15: 20.4 | EO15: 20 | EP15: 0.3 | EQ15: 0 | ER15: 0 | ES15: 0.6 | ET15: 29.4 | EU15: 23.6 | EV15: 0 | EW15: 0 | EX15: 9.2 | EY15: 19.9 | FA15: 31.4 | FB15: 34.4 | FC15: 28.6 | FD15: 3.5 | FE15: 0 | FF15: 0 | FG15: 6.9 | FH15: 6354.5 | FJ15: 24.48968 | FK15: 7.973 | FM15: 13.2 | FO15: 18.92002 | FP15: 10.8 | FQ15: 16 | FR15: 91.3827
A16: 15/03/2025 | B16: 03:00 | C16: 1 | D16: 1.7 | E16: 642.4 | F16: 215.7 | I16: 86.4 | J16: 144 | M16: 105 | N16: 105 | O16: 105 | P16: 196.9 | Q16: 108.5 | R16: 68.5 | S16: 367.1 | T16: 10.4 | Y16: 161.5 | Z16: 7.2 | AA16: 2.9 | AC16: 6 | AD16: 8 | AE16: 143.7 | AF16: 3.6 | AJ16: 109.5 | AK16: 220.3 | AO16: 6.6 | AP16: 446.5 | AQ16: 81.9 | AR16: 133.9 | AS16: 42.2 | AT16: 18.4 | AU16: 17.7 | AV16: 90.7 | AW16: 0 | AX16: 122.3 | AY16: 73.1 | AZ16: 107.2 | BC16: 44.8 | BD16: 31.4 | BE16: 4 | BF16: 38.6 | BG16: 171.7 | BH16: 94 | BI16: 0 | BO16: 86.5 | BP16: 64 | BQ16: 63.7 | BR16: 63.9 | BS16: 154.8 | CB16: 2.1 | CC16: 240.5 | CD16: 117.9 | CE16: 62 | CF16: 79.3 | CG16: 29.7 | CL16: 141.6 | CM16: 65.4 | CU16: 0 | CV16: 67.9 | CW16: 0 | CX16: 0.2 | CY16: 0 | DA16: 9.9 | DB16: 0 | DC16: 1.1 | DD16: 1.8 | DE16: 5 | DF16: 19.9 | DG16: 19.3 | DH16: 18.4 | DI16: 0 | DJ16: 18.5 | DK16: 0 | DL16: 0 | DM16: 19.5 | DN16: 45.9 | DO16: 4.8 | DP16: 2.3 | DQ16: 2.4 | DR16: 1 | DS16: 0 | DT16: 3.3 | DU16: 20.3 | DV16: 3 | DW16: 0.3 | DX16: 19.8 | DY16: 12.8 | DZ16: 19 | EA16: 20.2 | EB16: 19.9 | EC16: 12.5 | ED16: 25.7 | EE16: 0 | EF16: 28.9 | EG16: 63 | EH16: 2.3 | EI16: 1.5 | EJ16: 21 | EK16: 8.4 | EL16: 3.9 | EM16: 20.4 | EN16: 20.4 | EO16: 20 | EP16: 0.3 | EQ16: 0 | ER16: 0 | ES16: 0.6 | ET16: 21.1 | EU16: 20.6 | EV16: 0 | EW16: 0 | EX16: 9.3 | EY16: 20 | FA16: 31.5 | FB16: 35 | FC16: 28.8 | FD16: 3.5 | FE16: 0 | FF16: 0 | FG16: 7.5 | FH16: 6279.4 | FJ16: 24.44556 | FK16: 7.974 | FM16: 13.2 | FO16: 18.91997 | FP16: 10.7 | FQ16: 16.1 | FR16: 91.33953
A17: 15/03/2025 | B17: 03:30 | C17: 1 | D17: 1.7 | E17: 650.1 | F17: 217.2 | I17: 83.9 | J17: 145.3 | M17: 150.6 | N17: 150.3 | O17: 150.3 | P17: 244.7 | Q17: 108.7 | R17: 67.5 | S17: 370.5 | T17: 10.4 | Y17: 165.5 | Z17: 7.6 | AA17: 3.1 | AC17: 6 | AD17: 8 | AE17: 142.2 | AF17: 3.7 | AJ17: 111 | AK17: 183.1 | AO17: 6.6 | AP17: 434.7 | AQ17: 81.7 | AR17: 125.8 | AS17: 42.5 | AT17: 18.3 | AU17: 17.7 | AV17: 89.4 | AW17: 0 | AX17: 123.8 | AY17: 74.1 | AZ17: 107.9 | BC17: 45.4 | BD17: 21 | BE17: 4 | BF17: 39.5 | BG17: 173.2 | BH17: 94.9 | BI17: 0 | BO17: 87.2 | BP17: 68.8 | BQ17: 68.5 | BR17: 68.4 | BS17: 145.2 | CB17: 2.1 | CC17: 224.1 | CD17: 112.7 | CE17: 63.2 | CF17: 80.1 | CG17: 30.1 | CL17: 122.3 | CM17: 58 | CU17: 0 | CV17: 82.4 | CW17: 0 | CX17: 0.1 | CY17: 0 | DA17: 9.9 | DB17: 0 | DC17: 1.2 | DD17: 1.8 | DE17: 5 | DF17: 20.3 | DG17: 20 | DH17: 18.5 | DI17: 0 | DJ17: 18.5 | DK17: 0 | DL17: 0 | DM17: 23.3 | DN17: 46 | DO17: 4.8 | DP17: 2.3 | DQ17: 2.4 | DR17: 1 | DS17: 0 | DT17: 3.2 | DU17: 20.3 | DV17: 3 | DW17: 0.3 | DX17: 19.8 | DY17: 12.9 | DZ17: 19 | EA17: 20.3 | EB17: 19.8 | EC17: 10 | ED17: 17.5 | EE17: 0 | EF17: 36.5 | EG17: 76.1 | EH17: 2.9 | EI17: 2.5 | EJ17: 21 | EK17: 8.4 | EL17: 3.8 | EM17: 20.4 | EN17: 20.4 | EO17: 20 | EP17: 0 | EQ17: 0 | ER17: 0 | ES17: 0.6 | ET17: 21.3 | EU17: 21.7 | EV17: 0 | EW17: 0 | EX17: 9.1 | EY17: 19.9 | FA17: 30.9 | FB17: 34.9 | FC17: 28.8 | FD17: 3.4 | FE17: 0 | FF17: 0 | FG17: 7.1 | FH17: 6406.9 | FJ17: 24.4691 | FK17: 7.974 | FM17: 13.2 | FO17: 18.91891 | FP17: 10.9 | FQ17: 15.7 | FR17: 91.16201
A18: 15/03/2025 | B18: 04:00 | C18: 1 | D18: 1.7 | E18: 650.6 | F18: 218.5 | I18: 83.7 | J18: 145.3 | M18: 149.5 | N18: 150 | O18: 148.7 | P18: 246.8 | Q18: 109.5 | R18: 68.7 | S18: 375 | T18: 10.5 | Y18: 162.6 | Z18: 7.8 | AA18: 3.2 | AC18: 6 | AD18: 8.1 | AE18: 142.7 | AF18: 3.7 | AJ18: 110.5 | AK18: 140.5 | AO18: 6.6 | AP18: 373.5 | AQ18: 81.7 | AR18: 124.4 | AS18: 42.5 | AT18: 18.5 | AU18: 17.7 | AV18: 91.8 | AW18: 0 | AX18: 126 | AY18: 74.3 | AZ18: 107.9 | BC18: 45.4 | BD18: 10 | BE18: 4 | BF18: 38.8 | BG18: 173.4 | BH18: 94.9 | BI18: 0 | BO18: 87.4 | BP18: 68.2 | BQ18: 68.2 | BR18: 68.1 | BS18: 145.8 | CB18: 2.1 | CC18: 224.1 | CD18: 112.4 | CE18: 63.2 | CF18: 79.9 | CG18: 30.1 | CL18: 121.6 | CM18: 57.9 | CU18: 0 | CV18: 98.2 | CW18: 0 | CX18: 0.6 | CY18: 0 | DA18: 9.9 | DB18: 0 | DC18: 1.2 | DD18: 1.8 | DE18: 5.1 | DF18: 20.1 | DG18: 19.6 | DH18: 18.5 | DI18: 0 | DJ18: 18.5 | DK18: 0 | DL18: 0 | DM18: 26.9 | DN18: 55.2 | DO18: 4.8 | DP18: 2.4 | DQ18: 2.4 | DR18: 1 | DS18: 0 | DT18: 2.9 | DU18: 20.3 | DV18: 3 | DW18: 0.3 | DX18: 19.8 | DY18: 12.7 | DZ18: 19 | EA18: 20.2 | EB18: 19.8 | EC18: 8.7 | ED18: 14.1 | EE18: 0 | EF18: 36.8 | EG18: 79 | EH18: 3.7 | EI18: 2.6 | EJ18: 21 | EK18: 8.4 | EL18: 4.2 | EM18: 20.4 | EN18: 20.4 | EO18: 20 | EP18: 0.4 | EQ18: 0 | ER18: 0 | ES18: 0.6 | ET18: 18 | EU18: 21.8 | EV18: 0 | EW18: 0 | EX18: 9.2 | EY18: 19.8 | FA18: 30.8 | FB18: 34.4 | FC18: 28.7 | FD18: 3.4 | FE18: 0 | FF18: 0 | FG18: 7.4 | FH18: 6323 | FJ18: 24.40248 | FK18: 7.976 | FM18: 13.2 | FO18: 18.91861 | FP18: 10.8 | FQ18: 15.7 | FR18: 90.99709
A19: 15/03/2025 | B19: 04:30 | C19: 1 | D19: 1.7 | E19: 645.2 | F19: 217.3 | I19: 88 | J19: 144.5 | M19: 108.8 | N19: 108 | O19: 107.6 | P19: 209.3 | Q19: 107.7 | R19: 67.7 | S19: 376.3 | T19: 10.4 | Y19: 162.1 | Z19: 7.8 | AA19: 3 | AC19: 6 | AD19: 8.1 | AE19: 143.3 | AF19: 3.7 | AJ19: 110.2 | AK19: 171.5 | AO19: 6.6 | AP19: 419 | AQ19: 81.9 | AR19: 143.8 | AS19: 42.3 | AT19: 18.5 | AU19: 17.6 | AV19: 88.5 | AW19: 0 | AX19: 121.5 | AY19: 73.5 | AZ19: 108 | BC19: 45.3 | BD19: 0 | BE19: 4 | BF19: 39 | BG19: 172.3 | BH19: 94.5 | BI19: 0 | BO19: 86.7 | BP19: 68.4 | BQ19: 68.3 | BR19: 69.1 | BS19: 146.6 | CB19: 2.1 | CC19: 257.5 | CD19: 128 | CE19: 62.8 | CF19: 79.9 | CG19: 30.1 | CL19: 119.6 | CM19: 56.7 | CU19: 0 | CV19: 97.4 | CW19: 0 | CX19: 0.8 | CY19: 0 | DA19: 9.9 | DB19: 0 | DC19: 1.2 | DD19: 1.8 | DE19: 5.1 | DF19: 20.2 | DG19: 20 | DH19: 18.5 | DI19: 1.5 | DJ19: 18.5 | DK19: 0 | DL19: 0 | DM19: 27.3 | DN19: 53.8 | DO19: 4.8 | DP19: 2.4 | DQ19: 2.4 | DR19: 1.1 | DS19: 0 | DT19: 2.9 | DU19: 20.3 | DV19: 3 | DW19: 0.3 | DX19: 19.9 | DY19: 12.7 | DZ19: 19.1 | EA19: 20.2 | EB19: 20 | EC19: 10.1 | ED19: 14 | EE19: 0 | EF19: 37.3 | EG19: 83.8 | EH19: 2.7 | EI19: 3.3 | EJ19: 21 | EK19: 8.4 | EL19: 4.6 | EM19: 20.4 | EN19: 20.4 | EO19: 20 | EP19: 0.4 | EQ19: 0 | ER19: 0 | ES19: 0.6 | ET19: 20.1 | EU19: 22.4 | EV19: 0 | EW19: 0 | EX19: 9.2 | EY19: 20 | FA19: 30.6 | FB19: 33.9 | FC19: 28.7 | FD19: 3.4 | FE19: 0 | FF19: 0 | FG19: 7.4 | FH19: 6289.1 | FJ19: 24.42988 | FK19: 7.974 | FM19: 13.2 | FO19: 18.91818 | FP19: 10.7 | FQ19: 15.6 | FR19: 90.82206
A20: 15/03/2025 | B20: 05:00 | C20: 1 | D20: 1.7 | E20: 655.8 | F20: 219 | I20: 87.2 | J20: 145.3 | M20: 106.5 | N20: 106.2 | O20: 107.5 | P20: 206.8 | Q20: 109.9 | R20: 67.6 | S20: 380.5 | T20: 10.5 | Y20: 167.5 | Z20: 8.6 | AA20: 3.1 | AC20: 5.8 | AD20: 8 | AE20: 143.4 | AF20: 3.6 | AJ20: 111.3 | AK20: 182.7 | AO20: 6.6 | AP20: 453.1 | AQ20: 81.9 | AR20: 143 | AS20: 42.5 | AT20: 18.5 | AU20: 17.6 | AV20: 90 | AW20: 0 | AX20: 125.1 | AY20: 74.2 | AZ20: 109.1 | BC20: 45.5 | BD20: 0 | BE20: 4 | BF20: 39 | BG20: 176.1 | BH20: 95.1 | BI20: 0 | BO20: 87.2 | BP20: 70.8 | BQ20: 70.6 | BR20: 70.1 | BS20: 145 | CB20: 2.1 | CC20: 257.5 | CD20: 126.1 | CE20: 63.5 | CF20: 80 | CG20: 30.4 | CL20: 120.4 | CM20: 57.4 | CU20: 0 | CV20: 106.4 | CW20: 0 | CX20: 1.3 | CY20: 0 | DA20: 9.9 | DB20: 0 | DC20: 1.2 | DD20: 1.8 | DE20: 5 | DF20: 20.6 | DG20: 20 | DH20: 18.5 | DI20: 3.9 | DJ20: 18.5 | DK20: 0 | DL20: 0 | DM20: 27 | DN20: 56.4 | DO20: 4.8 | DP20: 2.4 | DQ20: 2.4 | DR20: 1 | DS20: 0 | DT20: 3 | DU20: 20.3 | DV20: 3 | DW20: 0.3 | DX20: 19.9 | DY20: 12.7 | DZ20: 19.6 | EA20: 20.3 | EB20: 20 | EC20: 13.5 | ED20: 13.5 | EE20: 0 | EF20: 42.6 | EG20: 89.4 | EH20: 2.1 | EI20: 0.8 | EJ20: 21 | EK20: 8.4 | EL20: 4.8 | EM20: 20.4 | EN20: 20.4 | EO20: 20 | EP20: 1.2 | EQ20: 0 | ER20: 0 | ES20: 0.6 | ET20: 21.2 | EU20: 21 | EV20: 0 | EW20: 0 | EX20: 9.2 | EY20: 20 | FA20: 31 | FB20: 34.2 | FC20: 28.5 | FD20: 3.4 | FE20: 0 | FF20: 0 | FG20: 7.3 | FH20: 6396.6 | FJ20: 24.38957 | FK20: 7.974 | FM20: 13.2 | FO20: 18.91792 | FP20: 10.7 | FQ20: 15.7 | FR20: 90.88149
A21: 15/03/2025 | B21: 05:30 | C21: 1 | D21: 1.6 | E21: 647.4 | F21: 218.2 | I21: 87.1 | J21: 144.9 | M21: 106.7 | N21: 106.7 | O21: 106.7 | P21: 206.6 | Q21: 109.3 | R21: 68.1 | S21: 372.9 | T21: 10.3 | Y21: 165.1 | Z21: 6.9 | AA21: 3.2 | AC21: 5.9 | AD21: 8 | AE21: 143.7 | AF21: 2.9 | AJ21: 110.6 | AK21: 220.7 | AO21: 6.6 | AP21: 457.8 | AQ21: 81.9 | AR21: 142.5 | AS21: 42.5 | AT21: 17.9 | AU21: 17.6 | AV21: 89.2 | AW21: 0 | AX21: 123 | AY21: 73.9 | AZ21: 108.1 | BC21: 44.9 | BD21: 0 | BE21: 4 | BF21: 38.7 | BG21: 172.9 | BH21: 94.6 | BI21: 0 | BO21: 86.9 | BP21: 66.5 | BQ21: 66.6 | BR21: 70.5 | BS21: 156.1 | CB21: 2.1 | CC21: 253.1 | CD21: 127.2 | CE21: 62.8 | CF21: 78 | CG21: 30.1 | CL21: 121.5 | CM21: 58.3 | CU21: 0 | CV21: 95.8 | CW21: 0 | CX21: 0.8 | CY21: 0 | DA21: 9.9 | DB21: 0 | DC21: 1.2 | DD21: 1.8 | DE21: 5 | DF21: 20.2 | DG21: 20 | DH21: 18.5 | DI21: 3.9 | DJ21: 18.5 | DK21: 0 | DL21: 0 | DM21: 27.3 | DN21: 53.1 | DO21: 4.8 | DP21: 2.4 | DQ21: 2.4 | DR21: 1 | DS21: 0 | DT21: 3.2 | DU21: 20.3 | DV21: 2.9 | DW21: 0.3 | DX21: 19.8 | DY21: 12.8 | DZ21: 19.5 | EA21: 20.2 | EB21: 20 | EC21: 14.8 | ED21: 15.3 | EE21: 0 | EF21: 29.8 | EG21: 71.1 | EH21: 1.3 | EI21: 0.9 | EJ21: 21 | EK21: 8.4 | EL21: 4.8 | EM21: 0.3 | EN21: 0 | EO21: 7.4 | EP21: 0.7 | EQ21: 0 | ER21: 0 | ES21: 0.6 | ET21: 19.9 | EU21: 20.4 | EV21: 0 | EW21: 0 | EX21: 9.2 | EY21: 20 | FA21: 30.9 | FB21: 34.5 | FC21: 28.3 | FD21: 3.4 | FE21: 0 | FF21: 0 | FG21: 6.6 | FH21: 6305.5 | FJ21: 24.39852 | FK21: 7.971 | FM21: 13.2 | FO21: 18.91777 | FP21: 10.7 | FQ21: 15.8 | FR21: 90.98729
A22: 15/03/2025 | B22: 06:00 | C22: 1 | D22: 1.6 | E22: 651.8 | F22: 219.1 | I22: 88.9 | J22: 145.2 | M22: 106.5 | N22: 107.2 | O22: 106.8 | P22: 206.6 | Q22: 109.4 | R22: 68 | S22: 380.4 | T22: 10.5 | Y22: 165.3 | Z22: 7.1 | AA22: 2.9 | AC22: 5.5 | AD22: 8.1 | AE22: 142.4 | AF22: 2.9 | AJ22: 43.4 | AK22: 221.8 | AO22: 6.6 | AP22: 461.7 | AQ22: 81.9 | AR22: 149.6 | AS22: 42.5 | AT22: 18.5 | AU22: 17.7 | AV22: 90.7 | AW22: 0 | AX22: 123.5 | AY22: 74.3 | AZ22: 108.7 | BC22: 45.1 | BD22: 0 | BE22: 4 | BF22: 38.7 | BG22: 174.8 | BH22: 94.9 | BI22: 0 | BO22: 87.4 | BP22: 110 | BQ22: 109.9 | BR22: 109.9 | BS22: 192.3 | CB22: 2.1 | CC22: 269 | CD22: 133 | CE22: 63.5 | CF22: 78.2 | CG22: 30.3 | CL22: 121.6 | CM22: 58.2 | CU22: 0 | CV22: 84.8 | CW22: 0.1 | CX22: 0.7 | CY22: 0 | DA22: 9.9 | DB22: 0 | DC22: 0.4 | DD22: 1.8 | DE22: 5 | DF22: 20.5 | DG22: 19.4 | DH22: 18.5 | DI22: 3.9 | DJ22: 18.5 | DK22: 1.9 | DL22: 2 | DM22: 26.3 | DN22: 53.6 | DO22: 4.8 | DP22: 2.4 | DQ22: 2.4 | DR22: 1 | DS22: 2.3 | DT22: 3.2 | DU22: 20.3 | DV22: 3 | DW22: 0.3 | DX22: 19.8 | DY22: 12.9 | DZ22: 20 | EA22: 20.3 | EB22: 20 | EC22: 13.6 | ED22: 15.1 | EE22: 0.3 | EF22: 33.5 | EG22: 65.2 | EH22: 2.2 | EI22: 1.4 | EJ22: 21 | EK22: 8.4 | EL22: 4.7 | EM22: 0 | EN22: 0 | EO22: 0 | EP22: 1.2 | EQ22: 0 | ER22: 1.6 | ES22: 0.6 | ET22: 19 | EU22: 21 | EV22: 1.4 | EW22: 0 | EX22: 9.3 | EY22: 20 | FA22: 30.9 | FB22: 34.4 | FC22: 28.3 | FD22: 3.4 | FE22: 0 | FF22: 0 | FG22: 7.7 | FH22: 6445.2 | FJ22: 24.46983 | FK22: 7.95 | FM22: 13.2 | FO22: 18.9175 | FP22: 10.7 | FQ22: 15.6 | FR22: 90.83733
... A58: 16/03/2025 | B58: 00:00 | C58: 0.9 | D58: 1.6 | E58: 642.8 | F58: 216 | I58: 59.3 | J58: 145.6 | M58: 152.9 | N58: 105.9 | O58: 153.9 | P58: 234.1 | Q58: 202.4 | R58: 107.2 | S58: 371.6 | T58: 10.4 | Y58: 167.3 | Z58: 7.5 | AA58: 2.7 | AC58: 6.6 | AD58: 8.6 | AE58: 143.1 | AF58: 8.3 | AJ58: 110 | AK58: 148.8 | AO58: 6.5 | AP58: 455.9 | AQ58: 81.7 | AR58: 122.4 | AS58: 42.2 | AT58: 18.3 | AU58: 17.1 | AV58: 88.8 | AW58: 0 | AX58: 0 | AY58: 0 | AZ58: 107.4 | BC58: 45.7 | BD58: 45.6 | BE58: 4 | BF58: 37.9 | BG58: 109.5 | BH58: 94.4 | BI58: 0 | BO58: 86.1 | BP58: 170.5 | BQ58: 162.7 | BR58: 200 | BS58: 261.7 | CB58: 2.1 | CC58: 210.4 | CD58: 107.9 | CE58: 64.2 | CF58: 78.4 | CG58: 30 | CL58: 141.1 | CM58: 64.7 | CU58: 0 | CV58: 76.2 | CW58: 0 | CX58: 0.7 | CY58: 0 | DA58: 9.9 | DB58: 2.9 | DC58: 1.1 | DD58: 1.8 | DE58: 5.1 | DF58: 20.1 | DG58: 20 | DH58: 18.9 | DI58: 3.6 | DJ58: 18.5 | DK58: 0 | DL58: 0 | DM58: 26.1 | DN58: 75.9 | DO58: 4.8 | DP58: 2.4 | DQ58: 2.4 | DR58: 1 | DS58: 0 | DT58: 2.6 | DU58: 20.3 | DV58: 3 | DW58: 0 | DX58: 19.8 | DY58: 12.9 | DZ58: 20.2 | EA58: 20.2 | EB58: 19.8 | EC58: 9.1 | ED58: 50.2 | EE58: 0 | EF58: 80.5 | EG58: 94.5 | EH58: 7.4 | EI58: 7.2 | EJ58: 12.6 | EK58: 8.4 | EL58: 6.4 | EM58: 20.4 | EN58: 20.4 | EO58: 20 | EP58: 0.6 | EQ58: 0 | ER58: 0 | ES58: 0.6 | ET58: 37.2 | EU58: 42.6 | EV58: 0 | EW58: 0 | EX58: 9.3 | EY58: 19.8 | FA58: 30.9 | FB58: 35.3 | FC58: 28.7 | FD58: 3.4 | FE58: 15 | FF58: 9.6 | FG58: 5.7 | FH58: 6850.7 | FJ58: 24.37069 | FK58: 7.897 | FM58: 13.2 | FO58: 18.91712 | FP58: 10.2 | FQ58: 16.1 | FR58: 90.68481
A59: EJEC | C59: 23.65 | D59: 37.25 | E59: 15592.6 | F59: 5227.6 | G59: 0 | H59: 0 | I59: 2085.6 | J59: 3482.5 | K59: 0 | L59: 0 | M59: 2961.1 | N59: 2849.35 | O59: 2972.8 | P59: 5140 | Q59: 3633.05 | R59: 2047.15 | S59: 9053.65 | T59: 250.9 | U59: 0 | V59: 0 | W59: 0 | X59: 0 | Y59: 3952.4 | Z59: 182.6 | AA59: 70.7 | AB59: 0 | AC59: 148.95 | AD59: 166.45 | AE59: 3434.05 | AF59: 97.55 | AG59: 0 | AH59: 0 | AI59: 0 | AJ59: 1978.7 | AK59: 4829.15 | AL59: 0 | AM59: 0 | AN59: 0 | AO59: 98.3 | AP59: 10924.9 | AQ59: 1965.1 | AR59: 3415.65 | AS59: 1017.35 | AT59: 442.65 | AU59: 373.4 | AV59: 2158.9 | AW59: 25.35 | AX59: 3224.7 | AY59: 1834.5 | AZ59: 2596.45 | BA59: 0 | BB59: 0 | BC59: 1089.15 | BD59: 397.6 | BE59: 96 | BF59: 935.1 | BG59: 4106.95 | BH59: 2275.7 | BI59: 49.7 | BJ59: 0 | BK59: 0 | BL59: 0 | BM59: 0 | BN59: 0 | BO59: 2087.7 | BP59: 3263 | BQ59: 3172.85 | BR59: 3611.95 | BS59: 5308.6 | BT59: 0 | BU59: 0 | BV59: 0 | BW59: 0 | BX59: 0 | BY59: 0 | BZ59: 0 | CA59: 0 | CB59: 50.3 | CC59: 6063.85 | CD59: 3078.5 | CE59: 1530.65 | CF59: 1898 | CG59: 722.95 | CH59: 0 | CI59: 0 | CJ59: 0 | CK59: 0 | CL59: 3273.95 | CM59: 1523.2 | CN59: 0 | CO59: 0 | CP59: 0 | CQ59: 0 | CR59: 0 | CS59: 0 | CT59: 0 | CU59: 5 | CV59: 2307.8 | CW59: 730.8 | CX59: 14.1 | CY59: 1.95 | CZ59: 0 | DA59: 237.65 | DB59: 49.75 | DC59: 13.4 | DD59: 43.55 | DE59: 122.25 | DF59: 485.7 | DG59: 476.05 | DH59: 447.7 | DI59: 71.8 | DJ59: 444 | DK59: 150.8 | DL59: 180.05 | DM59: 608.3 | DN59: 1732.6 | DO59: 112.2 | DP59: 57.5 | DQ59: 57.6 | DR59: 24.15 | DS59: 184.7 | DT59: 66.85 | DU59: 487.5 | DV59: 71.7 | DW59: 4.35 | DX59: 475.6 | DY59: 308.4 | DZ59: 480.25 | EA59: 486.5 | EB59: 479.35 | EC59: 260.15 | ED59: 990.85 | EE59: 328.95 | EF59: 1607.2 | EG59: 1943.3 | EH59: 142.45 | EI59: 171.5 | EJ59: 374.25 | EK59: 201.6 | EL59: 141.65 | EM59: 234.75 | EN59: 214.7 | EO59: 158.7 | EP59: 10.5 | EQ59: 135.25 | ER59: 1403.55 | ES59: 14.4 | ET59: 1789.3 | EU59: 1784.05 | EV59: 1044.5 | EW59: 137.1 | EX59: 223.05 | EY59: 479.5 | EZ59: 0 | FA59: 737.85 | FB59: 844.65 | FC59: 678.55 | FD59: 78.05 | FE59: 82.25 | FF59: 123.75 | FG59: 167.85 | FH59: 170754.8 | FJ59: 585.40248 | FK59: 190.765 | FL59: 0 | FM59: 316.6 | FN59: 0 | FO59: 454.08565 | FP59: 244.8 | FQ59: 383.1 | FR59: 2174.7531

Sheet REACTIVA
B3: sábado, 15 de Marzo del 2025
A5: POTENCIA REACTIVA EJECUTADA DE LAS UNIDADES DE GENERACIÓN DEL COES (MVAR) | FI5: CENTRALES NO INTEGRANTES COES
A6: FECHA | B6: HORA | C6: 337 | D6: 338 | E6: 101 | F6: 102 | G6: 42667 | H6: 42668 | I6: 126 | J6: 127 | K6: 138 | L6: 139 | M6: 197 | N6: 203 | O6: 204 | P6: 230 | Q6: 209 | R6: 56677 | S6: 796 | T6: 2146 | U6: 142 | V6: 143 | W6: 125 | X6: 187 | Y6: 163 | Z6: 298 | AA6: 219 | AB6: 151 | AC6: 152 | AD6: 153 | AE6: 154 | AF6: 756 | AG6: 156 | AH6: 155 | AI6: 182 | AJ6: 212 | AK6: 758 | AL6: 263 | AM6: 265 | AN6: 775 | AO6: 777 | AP6: 2154 | AQ6: 150 | AR6: 149 | AS6: 188 | AT6: 2131 | AU6: 755 | AV6: 252 | AW6: 249 | AX6: 250 | AY6: 117 | AZ6: 267 | BA6: 268 | BB6: 119 | BC6: 120 | BD6: 189 | BE6: 122 | BF6: 266 | BG6: 251 | BH6: 115 | BI6: 239 | BJ6: 288 | BK6: 240 | BL6: 241 | BM6: 242 | BN6: 191 | BO6: 194 | BP6: 196 | BQ6: 207 | BR6: 236 | BS6: 795 | BT6: 285 | BU6: 995 | BV6: 996 | BW6: 997 | BX6: 766 | BY6: 926 | BZ6: 924 | CA6: 121 | CB6: 103 | CC6: 104 | CD6: 106 | CE6: 105 | CF6: 107 | CG6: 110 | CH6: 109 | CI6: 144 | CJ6: 113 | CK6: 114 | CL6: 193 | CM6: 208 | CN6: 786 | CO6: 787 | CP6: 788 | CQ6: 789 | CR6: 248 | CS6: 2159 | CT6: 303 | CU6: 59715 | CV6: 62255 | CW6: 1263 | CX6: 61800 | CY6: 2194 | CZ6: 216 | DA6: 198 | DB6: 49607 | DC6: 214 | DD6: 260 | DE6: 2152 | DF6: 2128 | DG6: 247 | DH6: 228 | DI6: 2135 | DJ6: 261 | DK6: 237 | DL6: 253 | DM6: 770 | DN6: 225 | DO6: 2201 | DP6: 2171 | DQ6: 760 | DR6: 235 | DS6: 238 | DT6: 2184 | DU6: 61855 | DV6: 223 | DW6: 226 | DX6: 201 | DY6: 258 | DZ6: 259 | EA6: 920 | EB6: 257 | EC6: 256 | ED6: 2148 | EE6: 58288 | EF6: 58289 | EG6: 58839 | EH6: 58840 | EI6: 296 | EJ6: 297 | EK6: 211 | EL6: 2175 | EM6: 2178 | EN6: 2181 | EO6: 1262 | EP6: 233 | EQ6: 2150 | ER6: 2165 | ES6: 2161 | ET6: 61197 | EU6: 58851 | EV6: 234 | EW6: 215 | EX6: 917 | EY6: 289 | EZ6: 58333 | FA6: 58336 | FB6: 202 | FC6: 58487 | FD6: 213 | FE6: 232 | FF6: 2190 | FG6: TOTAL COES | FI6: 221 | FJ6: 222 | FK6: 224 | FL6: 2187 | FM6: 227 | FN6: 49400 | FO6: 199 | FP6: 200 | FQ6: TOTAL NO COES
C7: CENTRO | D7: CENTRO | E7: CENTRO | F7: CENTRO | G7: NORTE | H7: NORTE | I7: NORTE | J7: NORTE | K7: CENTRO | L7: CENTRO | M7: CENTRO | N7: CENTRO | O7: CENTRO | P7: CENTRO | Q7: CENTRO | R7: CENTRO | S7: CENTRO | T7: CENTRO | U7: CENTRO | V7: CENTRO | W7: CENTRO | X7: CENTRO | Y7: SUR | Z7: SUR | AA7: CENTRO | AB7: SUR | AC7: SUR | AD7: SUR | AE7: SUR | AF7: SUR | AG7: SUR | AH7: SUR | AI7: SUR | AJ7: CENTRO | AK7: NORTE | AL7: NORTE | AM7: NORTE | AN7: CENTRO | AO7: CENTRO | AP7: CENTRO | AQ7: CENTRO | AR7: CENTRO | AS7: CENTRO | AT7: CENTRO | AU7: SUR | AV7: CENTRO | AW7: CENTRO | AX7: CENTRO | AY7: CENTRO | AZ7: CENTRO | BA7: CENTRO | BB7: CENTRO | BC7: CENTRO | BD7: SUR | BE7: NORTE | BF7: CENTRO | BG7: CENTRO | BH7: NORTE | BI7: NORTE | BJ7: NORTE | BK7: SUR | BL7: SUR | BM7: SUR | BN7: CENTRO | BO7: CENTRO | BP7: CENTRO | BQ7: CENTRO | BR7: CENTRO | BS7: CENTRO | BT7: CENTRO | BU7: SUR | BV7: SUR | BW7: SUR | BX7: NORTE | BY7: SUR | BZ7: CENTRO | CA7: NORTE | CB7: CENTRO | CC7: CENTRO | CD7: CENTRO | CE7: CENTRO | CF7: CENTRO | CG7: CENTRO | CH7: CENTRO | CI7: CENTRO | CJ7: CENTRO | CK7: CENTRO | CL7: CENTRO | CM7: CENTRO | CN7: SUR | CO7: SUR | CP7: SUR | CQ7: SUR | CR7: CENTRO | CS7: CENTRO | CT7: CENTRO | CU7: CENTRO | CV7: SUR | CW7: NORTE | CX7: NORTE | CY7: NORTE | CZ7: NORTE | DA7: NORTE | DB7: SUR | DC7: CENTRO | DD7: CENTRO | DE7: CENTRO | DF7: NORTE | DG7: NORTE | DH7: CENTRO | DI7: CENTRO | DJ7: SUR | DK7: SUR | DL7: CENTRO | DM7: CENTRO | DN7: CENTRO | DO7: CENTRO | DP7: CENTRO | DQ7: CENTRO | DR7: SUR | DS7: CENTRO | DT7: CENTRO | DU7: NORTE | DV7: CENTRO | DW7: CENTRO | DX7: NORTE | DY7: CENTRO | DZ7: CENTRO | EA7: CENTRO | EB7: NORTE | EC7: NORTE | ED7: SUR | EE7: CENTRO | EF7: CENTRO | EG7: CENTRO | EH7: CENTRO | EI7: CENTRO | EJ7: CENTRO | EK7: SUR | EL7: SUR | EM7: SUR | EN7: SUR | EO7: NORTE | EP7: SUR | EQ7: SUR | ER7: CENTRO | ES7: CENTRO | ET7: CENTRO | EU7: SUR | EV7: SUR | EW7: NORTE | EX7: CENTRO | EY7: NORTE | EZ7: NORTE | FA7: NORTE | FB7: CENTRO | FC7: CENTRO | FD7: CENTRO | FE7: NORTE | FF7: NORTE | FI7: NORTE | FJ7: CENTRO | FK7: NORTE | FL7: NORTE | FM7: NORTE | FN7: NORTE | FO7: NORTE | FP7: NORTE
C8: HIDROELÉCTRICA | D8: HIDROELÉCTRICA | E8: HIDROELÉCTRICA | F8: HIDROELÉCTRICA | G8: TERMOELÉCTRICA | H8: TERMOELÉCTRICA | I8: HIDROELÉCTRICA | J8: HIDROELÉCTRICA | K8: TERMOELÉCTRICA | L8: TERMOELÉCTRICA | M8: TERMOELÉCTRICA | N8: TERMOELÉCTRICA | O8: TERMOELÉCTRICA | P8: TERMOELÉCTRICA | Q8: TERMOELÉCTRICA | R8: TERMOELÉCTRICA | S8: HIDROELÉCTRICA | T8: HIDROELÉCTRICA | U8: TERMOELÉCTRICA | V8: TERMOELÉCTRICA | W8: TERMOELÉCTRICA | X8: TERMOELÉCTRICA | Y8: HIDROELÉCTRICA | Z8: HIDROELÉCTRICA | AA8: TERMOELÉCTRICA | AB8: HIDROELÉCTRICA | AC8: HIDROELÉCTRICA | AD8: HIDROELÉCTRICA | AE8: HIDROELÉCTRICA | AF8: TERMOELÉCTRICA | AG8: TERMOELÉCTRICA | AH8: TERMOELÉCTRICA | AI8: HIDROELÉCTRICA | AJ8: HIDROELÉCTRICA | AK8: TERMOELÉCTRICA | AL8: TERMOELÉCTRICA | AM8: TERMOELÉCTRICA | AN8: HIDROELÉCTRICA | AO8: HIDROELÉCTRICA | AP8: HIDROELÉCTRICA | AQ8: HIDROELÉCTRICA | AR8: HIDROELÉCTRICA | AS8: HIDROELÉCTRICA | AT8: HIDROELÉCTRICA | AU8: HIDROELÉCTRICA | AV8: TERMOELÉCTRICA | AW8: TERMOELÉCTRICA | AX8: TERMOELÉCTRICA | AY8: HIDROELÉCTRICA | AZ8: HIDROELÉCTRICA | BA8: HIDROELÉCTRICA | BB8: HIDROELÉCTRICA | BC8: HIDROELÉCTRICA | BD8: HIDROELÉCTRICA | BE8: HIDROELÉCTRICA | BF8: HIDROELÉCTRICA | BG8: HIDROELÉCTRICA | BH8: TERMOELÉCTRICA | BI8: TERMOELÉCTRICA | BJ8: TERMOELÉCTRICA | BK8: TERMOELÉCTRICA | BL8: TERMOELÉCTRICA | BM8: TERMOELÉCTRICA | BN8: HIDROELÉCTRICA | BO8: TERMOELÉCTRICA | BP8: TERMOELÉCTRICA | BQ8: TERMOELÉCTRICA | BR8: TERMOELÉCTRICA | BS8: TERMOELÉCTRICA | BT8: TERMOELÉCTRICA | BU8: TERMOELÉCTRICA | BV8: TERMOELÉCTRICA | BW8: TERMOELÉCTRICA | BX8: HIDROELÉCTRICA | BY8: TERMOELÉCTRICA | BZ8: TERMOELÉCTRICA | CA8: HIDROELÉCTRICA | CB8: HIDROELÉCTRICA | CC8: HIDROELÉCTRICA | CD8: HIDROELÉCTRICA | CE8: HIDROELÉCTRICA | CF8: HIDROELÉCTRICA | CG8: TERMOELÉCTRICA | CH8: TERMOELÉCTRICA | CI8: TERMOELÉCTRICA | CJ8: TERMOELÉCTRICA | CK8: TERMOELÉCTRICA | CL8: TERMOELÉCTRICA | CM8: TERMOELÉCTRICA | CN8: TERMOELÉCTRICA | CO8: TERMOELÉCTRICA | CP8: TERMOELÉCTRICA | CQ8: TERMOELÉCTRICA | CR8: TERMOELÉCTRICA | CS8: TERMOELÉCTRICA | CT8: SOLAR | CU8: EÓLICA | CV8: SOLAR | CW8: EÓLICA | CX8: SOLAR | CY8: HIDROELÉCTRICA | CZ8: HIDROELÉCTRICA | DA8: HIDROELÉCTRICA | DB8: HIDROELÉCTRICA | DC8: HIDROELÉCTRICA | DD8: HIDROELÉCTRICA | DE8: HIDROELÉCTRICA | DF8: HIDROELÉCTRICA | DG8: HIDROELÉCTRICA | DH8: HIDROELÉCTRICA | DI8: HIDROELÉCTRICA | DJ8: SOLAR | DK8: SOLAR | DL8: EÓLICA | DM8: EÓLICA | DN8: TERMOELÉCTRICA | DO8: TERMOELÉCTRICA | DP8: TERMOELÉCTRICA | DQ8: TERMOELÉCTRICA | DR8: SOLAR | DS8: HIDROELÉCTRICA | DT8: HIDROELÉCTRICA | DU8: HIDROELÉCTRICA | DV8: HIDROELÉCTRICA | DW8: HIDROELÉCTRICA | DX8: HIDROELÉCTRICA | DY8: HIDROELÉCTRICA | DZ8: HIDROELÉCTRICA | EA8: HIDROELÉCTRICA | EB8: EÓLICA | EC8: EÓLICA | ED8: SOLAR | EE8: EÓLICA | EF8: EÓLICA | EG8: EÓLICA | EH8: EÓLICA | EI8: HIDROELÉCTRICA | EJ8: HIDROELÉCTRICA | EK8: HIDROELÉCTRICA | EL8: HIDROELÉCTRICA | EM8: HIDROELÉCTRICA | EN8: HIDROELÉCTRICA | EO8: EÓLICA | EP8: SOLAR | EQ8: SOLAR | ER8: HIDROELÉCTRICA | ES8: EÓLICA | ET8: EÓLICA | EU8: SOLAR | EV8: SOLAR | EW8: HIDROELÉCTRICA | EX8: HIDROELÉCTRICA | EY8: TERMOELÉCTRICA | EZ8: TERMOELÉCTRICA | FA8: TERMOELÉCTRICA | FB8: TERMOELÉCTRICA | FC8: TERMOELÉCTRICA | FD8: TERMOELÉCTRICA | FE8: TERMOELÉCTRICA | FF8: TERMOELÉCTRICA | FI8: HIDROELÉCTRICA | FJ8: HIDROELÉCTRICA | FK8: HIDROELÉCTRICA | FL8: HIDROELÉCTRICA | FM8: TERMOELÉCTRICA | FN8: TERMOELÉCTRICA | FO8: HIDROELÉCTRICA | FP8: HIDROELÉCTRICA
C9: CENTRALES SANTA ROSA S.A.C. | D9: CENTRALES SANTA ROSA S.A.C. | E9: ELECTROPERU | F9: ELECTROPERU | G9: ELECTROPERU | H9: ELECTROPERU | I9: ORAZUL ENERGY PERÚ | J9: ORAZUL ENERGY PERÚ | K9: TERMOSELVA | L9: TERMOSELVA | M9: KALLPA GENERACION S.A. | N9: KALLPA GENERACION S.A. | O9: KALLPA GENERACION S.A. | P9: KALLPA GENERACION S.A. | Q9: KALLPA GENERACION S.A. | R9: KALLPA GENERACION S.A. | S9: KALLPA GENERACION S.A. | T9: KALLPA GENERACION S.A. | U9: SHOUGESA | V9: SHOUGESA | W9: SHOUGESA | X9: SHOUGESA | Y9: EGEMSA | Z9: EGESUR | AA9: EGESUR | AB9: EGASA | AC9: EGASA | AD9: EGASA | AE9: EGASA | AF9: EGASA | AG9: EGASA | AH9: EGASA | AI9: SAN GABAN | AJ9: CELEPSA | AK9: MINERA CERRO VERDE | AL9: PLANTA DE RESERVA FRIA DE GENERACION DE ETEN S.A. | AM9: PLANTA DE RESERVA FRIA DE GENERACION DE ETEN S.A. | AN9: EMPRESA DE GENERACION HUALLAGA | AO9: EMPRESA DE GENERACION HUALLAGA | AP9: LA VIRGEN | AQ9: CHINANGO S.A.C. | AR9: CHINANGO S.A.C. | AS9: HIDROELECTRICA HUANCHOR S.A.C. | AT9: CELEPSA RENOVABLES S.R.L. | AU9: INLAND ENERGY SAC | AV9: FENIX POWER PERÚ | AW9: FENIX POWER PERÚ | AX9: FENIX POWER PERÚ | AY9: STATKRAFT S.A | AZ9: STATKRAFT S.A | BA9: STATKRAFT S.A | BB9: STATKRAFT S.A | BC9: STATKRAFT S.A | BD9: STATKRAFT S.A | BE9: STATKRAFT S.A | BF9: STATKRAFT S.A | BG9: EMPRESA DE GENERACION HUANZA | BH9: ENEL GENERACION PIURA S.A. | BI9: ENEL GENERACION PIURA S.A. | BJ9: ENEL GENERACION PIURA S.A. | BK9: ENGIE | BL9: ENGIE | BM9: ENGIE | BN9: ENGIE | BO9: ENGIE | BP9: ENGIE | BQ9: ENGIE | BR9: ENGIE | BS9: ENGIE | BT9: ENGIE | BU9: ENGIE | BV9: ENGIE | BW9: ENGIE | BX9: ENGIE | BY9: INFRAESTRUCTURAS Y ENERGIAS DEL PERU S.A.C. | BZ9: INFRAESTRUCTURAS Y ENERGIAS DEL PERU S.A.C. | CA9: INVERSIONES SHAQSHA S.A.C. | CB9: ORYGEN PERU S.A.A. | CC9: ORYGEN PERU S.A.A. | CD9: ORYGEN PERU S.A.A. | CE9: ORYGEN PERU S.A.A. | CF9: ORYGEN PERU S.A.A. | CG9: ORYGEN PERU S.A.A. | CH9: ORYGEN PERU S.A.A. | CI9: ORYGEN PERU S.A.A. | CJ9: ORYGEN PERU S.A.A. | CK9: ORYGEN PERU S.A.A. | CL9: ORYGEN PERU S.A.A. | CM9: ORYGEN PERU S.A.A. | CN9: SAMAY I S.A.C | CO9: SAMAY I S.A.C | CP9: SAMAY I S.A.C | CQ9: SAMAY I S.A.C | CR9: TERMOCHILCA S.A.C. | CS9: TERMOCHILCA S.A.C. | CT9: COLCA SOLAR S.A.C. | CU9: ENERGIA RENOVABLE DEL SUR S.A. | CV9: GR CORTARRAMA SOCIEDAD ANONIMA CERRADA | CW9: GR TARUCA SOCIEDAD ANONIMA CERRADA | CX9: KONDU SAC | CY9: PERUANA DE INVERSIONES EN ENERGIAS RENOVABLES S.A. | CZ9: ORAZUL ENERGY PERÚ | DA9: ORAZUL ENERGY PERÚ | DB9: SAN GABAN | DC9: MAJA ENERGIA S.A.C. | DD9: EMPRESA DE GENERACION ELECTRICA CANCHAYLLO SAC | DE9: EMPRESA DE GENERACION ELECTRICA SANTA ANA S.A.C. | DF9: EMPRESA ELECTRICA AGUA AZUL | DG9: EMPRESA ELECTRICA RIO DOBLE | DH9: HIDROCAÑETE S.A. | DI9: HUAURA POWER GROUP S.A. | DJ9: MOQUEGUA FV S.A.C. | DK9: PANAMERICANA SOLAR SAC. | DL9: PARQUE EOLICO MARCONA S.A.C. | DM9: PARQUE EOLICO TRES HERMANAS S.A.C. | DN9: PETRAMAS | DO9: PETRAMAS | DP9: PETRAMAS | DQ9: PETRAMAS | DR9: TACNA SOLAR SAC. | DS9: ELECTRICA YANAPAMPA SAC | DT9: ANDEAN POWER S.A.C. | DU9: ASOCIACIÓN SANTA LUCIA DE CHACAS | DV9: ATRIA ENERGIA S.A.C. | DW9: EGEJUNIN | DX9: EGEJUNIN | DY9: EGEJUNIN | DZ9: EGEJUNIN | EA9: EMPRESA DE GENERACION ELECTRICA RIO BAÑOS S.A.C. | EB9: ENERGÍA EÓLICA S.A. | EC9: ENERGÍA EÓLICA S.A. | ED9: ENGIE | EE9: ENGIE | EF9: ENGIE | EG9: ENGIE | EH9: ENGIE | EI9: GENERACIÓN ANDINA S.A.C. | EJ9: GENERACIÓN ANDINA S.A.C. | EK9: GENERADORA DE ENERGÍA DEL PERÚ | EL9: GENERADORA DE ENERGÍA DEL PERÚ | EM9: GENERADORA DE ENERGÍA DEL PERÚ | EN9: GENERADORA DE ENERGÍA DEL PERÚ | EO9: GR PAINO SOCIEDAD ANONIMA CERRADA | EP9: MAJES ARCUS S.A.C. | EQ9: ORYGEN PERU S.A.A. | ER9: ORYGEN PERU S.A.A. | ES9: ORYGEN PERU S.A.A. | ET9: ORYGEN PERU S.A.A. | EU9: ORYGEN PERU S.A.A. | EV9: REPARTICIÓN ARCUS S.A.C. | EW9: SINERSA | EX9: SINERSA | EY9: BIOENERGIA DEL CHIRA S.A. | EZ9: GM OPERACIONES S.A.C. | FA9: GM OPERACIONES S.A.C. | FB9: SDF ENERGIA SAC | FC9: SDF ENERGIA SAC | FD9: AGRO INDUSTRIAL PARAMONGA S.A. | FE9: AGROAURORA S.A.C. | FF9: AGROINDUSTRIAS SAN JACINTO S.A.A. | FI9: UNACEM PERU S.A. | FJ9: ELECTRO ORIENTE | FK9: AGUAS Y ENERGIA PERU | FL9: ELECTRO ZAÑA S.A.C. | FM9: ELECTRONOROESTE S.A. | FN9: SDE PIURA | FO9: SINERSA | FP9: SINERSA
C10: SANTA ROSA 1 | D10: SANTA ROSA 2 | E10: MANTARO | F10: RESTITUCION | G10: TUMBES MAK 1 | H10: TUMBES MAK 2 | I10: CARHUAQUERO | J10: CAÑON DEL PATO | K10: AGUAYTIA TG1 | L10: AGUAYTIA TG2 | M10: KALLPA TG1 | N10: KALLPA TG2 | O10: KALLPA TG3 | P10: KALLPA TV | Q10: LFLORES TG1 | R10: LFLORES TV | S10: CERRO DEL AGUILA | T10: CERRODELAGUILAG4 | U10: SHOUGESA TV1 | V10: SHOUGESA TV2 | W10: SHOUGESA TV3 | X10: SHOUGESA CUMMINS | Y10: MACHUPICCHU | Z10: ARICOTA 1 | AA10: INDEPENDENCIA | AB10: CHARCANI I,II,III | AC10: CHARCANI IV | AD10: CHARCANI V | AE10: CHARCANI VI | AF10: CHILINA TG | AG10: MOLLENDO 1, 2, 3 | AH10: CHILINA (SULZ 1,2) | AI10: SAN GABAN II | AJ10: PLATANAL | AK10: RECKA | AL10: RF ETEN TG1 | AM10: RF ETEN TG2 | AN10: CHAGLLA GP1 | AO10: CHAGLLA | AP10: LA VIRGEN | AQ10: CHIMAY | AR10: YANANGO | AS10: HUANCHOR | AT10: MARAÑON | AU10: STA TERESA | AV10: FENIX GT11 | AW10: FENIX GT12 | AX10: FENIX TV10 | AY10: YAUPI | AZ10: OROYA | BA10: PACHACHACA | BB10: MALPASO | BC10: CAHUA | BD10: ARCATA | BE10: GALLITO CIEGO | BF10: CHEVES | BG10: HUANZA | BH10: MALACAS2 TG4 | BI10: MALACAS3 TG 5 | BJ10: MALACAS1 TG6 | BK10: RF ILO2 TG1 | BL10: RF ILO2 TG2 | BM10: RF ILO2 TG3 | BN10: YUNCAN | BO10: CHILCA1 TG1 | BP10: CHILCA1 TG2 | BQ10: CHILCA1 TG3 | BR10: CHILCA-TV | BS10: CHILCA2 TG41 | BT10: CHILCA2-TV | BU10: CTNEPI_TG41 | BV10: CTNEPI_TG42 | BW10: CTNEPI_TG43 | BX10: QUITARACSA | BY10: RF PTO MALDONADO | BZ10: RF PUCALLPA | CA10: PARIAC | CB10: HUINCO | CC10: MATUCANA | CD10: MOYOPAMPA | CE10: CALLAHUANCA | CF10: HUAMPANI | CG10: STA ROSA WEST TG7 | CH10: UTI_5 | CI10: UTI_6 | CJ10: VENTANILLA 3 | CK10: VENTANILLA 4 | CL10: VENTANILLA TV | CM10: STAROSA TG8 | CN10: PTO_BRVO TG1 | CO10: PTO_BRVO TG2 | CP10: PTO_BRVO TG3 | CQ10: PTO_BRVO TG4 | CR10: OLLEROS TG1 | CS10: OLLEROS TV | CT10: CS YARUCAYA | CU10: SAN JUAN | CV10: MATARANI | CW10: DUNA | CX10: CARHUAQUERO (CS) | CY10: MANTA I | CZ10: CARHUAQUERO4 | DA10: CAÑA BRAVA | DB10: TUPURI | DC10: RONCADOR | DD10: CANCHAYLLO | DE10: RENOVANDESH1 | DF10: POTRERO | DG10: PIZARRAS | DH10: NIMPERIAL | DI10: YARUCAYA | DJ10: MOQUEGUA-SOLAR | DK10: PANAMERICANA-SOLAR | DL10: PQE-EOLICO-MARCONA | DM10: PQE-EOLICO-3-HERMANAS | DN10: HUAYCOLORO | DO10: CALLAO | DP10: DONA_CATALINA | DQ10: LAGRINGAV | DR10: TACNA-SOLAR | DS10: YANAPAMPA | DT10: CARHUAC | DU10: HUALLIN | DV10: PURMACANA | DW10: HUASAHUASI | DX10: STACRUZ_1_2 | DY10: RUNATULLO_II | DZ10: RUNATULLO_III | EA10: RUCUY | EB10: PQE-EOLICO-TALARA | EC10: PQE-EOLICO-CUPISNIQUE | ED10: INTIPAMPA | EE10: PUNTA LOMITAS-BL1 | EF10: PUNTA LOMITAS-BL2 | EG10: PUN LOMITAS_EXP-BL1 | EH10: PUN LOMITAS_EXP-BL2 | EI10: 8AGOSTO | EJ10: EL CARMEN | EK10: LA JOYA | EL10: ANGEL_I | EM10: ANGEL_II | EN10: ANGEL_III | EO10: HUAMBOS | EP10: MAJES | EQ10: RUBI | ER10: CH_HER1 | ES10: WAYRA-I | ET10: WAYRA EXTENSION | EU10: CLEMESI | EV10: REPARTICION | EW10: POECHOS2 | EX10: CHANCAY | EY10: CANA BRAVA | EZ10: REFINERIA TALARA TV1 | FA10: REFINERÍA TALARA TV2 | FB10: OQUENDO TG1 | FC10: OQUENDO TV1 | FD10: PARAMONGA | FE10: MAPLE | FF10: SAN_JACINTO | FG10: MVAR | FI10: CARPAPATA | FJ10: CENTRALES ELOR | FK10: PIAS1 | FL10: ZANA | FM10: TABLAZO | FN10: TALLANCA | FO10: CURUMUY | FP10: POECHOS1 | FQ10: MVAR
A11: 15/03/2025 | B11: 00:30 | C11: 0.2 | D11: 0.1 | E11: 42.6 | F11: 34.3 | I11: -21.6 | J11: 15.6 | M11: -23.7 | N11: 0 | O11: -19.8 | P11: 17.6 | Q11: 24.9 | R11: 22.2 | S11: 47.8 | T11: 0 | Y11: 2.3 | Z11: 1.2 | AB11: -3.1 | AC11: 2.9 | AD11: 3.2 | AE11: 1.7 | AI11: 15.9 | AJ11: 17.4 | AN11: -0.9 | AO11: 53.3 | AP11: 11 | AQ11: 18.7 | AR11: 2.7 | AS11: 2.2 | AT11: 2.4 | AU11: 0.6 | AV11: 31.7 | AW11: -9.3 | AX11: -36.5 | AY11: 10.6 | BB11: -0.7 | BC11: 6.9 | BD11: 1.1 | BE11: 0.1 | BF11: -9.8 | BG11: 6.6 | BH11: 1.8 | BN11: 10.9 | BO11: -27.2 | BP11: -28.6 | BQ11: -24 | BR11: -26.5 | CA11: 0.2 | CB11: 33.4 | CC11: 25.6 | CD11: -0.6 | CE11: 5.9 | CF11: -2.1 | CK11: 21.4 | CL11: -31.8 | CR11: 0 | CU11: 4.3 | CV11: 0 | CW11: 0 | CZ11: -0.1 | DA11: 0 | DC11: 0.2 | DD11: 1.4 | DE11: 2.6 | DF11: -1.3 | DG11: 0.1 | DH11: 0 | DI11: 0 | DJ11: 0 | DK11: 0 | DL11: -1.9 | DM11: 4.7 | DN11: 1.6 | DO11: 0.5 | DP11: 0.74 | DQ11: 0.3 | DR11: 0 | DS11: 0.2 | DT11: 0.2 | DU11: 0.3 | DW11: -4.8 | DX11: 0.8 | DY11: 2.8 | DZ11: 2.8 | EA11: 1.7 | EB11: 0.8 | EC11: 4 | ED11: 0 | EE11: -6.2 | EF11: -7.1 | EG11: 0 | EH11: 0 | EI11: 2.5 | EJ11: -0.1 | EK11: 0.7 | EL11: 0.2 | EM11: 0.2 | EN11: 0.2 | EP11: 0 | EQ11: 0 | ER11: -0.2 | ES11: 2.8 | ET11: 3 | EU11: 0 | EV11: 0 | EW11: 0.4 | EX11: 2 | EZ11: 5.6 | FA11: 7.2 | FB11: 1.2 | FC11: 2.3 | FD11: 0 | FE11: 0 | FF11: 2.5 | FG11: 269.94 | FI11: 3.08745 | FJ11: 0.627 | FL11: 1.7 | FN11: 2.71321 | FO11: 0 | FP11: 0.9 | FQ11: 9.02766
A12: 15/03/2025 | B12: 01:00 | C12: 0.2 | D12: 0 | E12: 36.8 | F12: 30.9 | I12: -22.2 | J12: 10.9 | M12: -23.7 | N12: 0 | O12: -29.1 | P12: 16.3 | Q12: 23.7 | R12: 22.8 | S12: 43.9 | T12: -0.2 | Y12: 4.4 | Z12: 1.5 | AB12: -3.1 | AC12: 2.9 | AD12: 3 | AE12: 1.7 | AI12: 16 | AJ12: 16.1 | AN12: -0.9 | AO12: 51.8 | AP12: 10.9 | AQ12: 22.2 | AR12: 2.8 | AS12: 2.2 | AT12: 2.4 | AU12: 0.8 | AV12: 0 | AW12: -11 | AX12: -41.3 | AY12: 3.5 | BB12: -4.2 | BC12: 5.6 | BD12: 1.1 | BE12: -0.1 | BF12: -16.1 | BG12: 5.1 | BH12: -5.2 | BN12: 10.4 | BO12: -29.1 | BP12: -30.6 | BQ12: -25.4 | BR12: -26.3 | CA12: 0.2 | CB12: 34 | CC12: 29.9 | CD12: 2.1 | CE12: 5.5 | CF12: -2.3 | CK12: 18 | CL12: -37.3 | CR12: 0 | CU12: 4.5 | CV12: 0 | CW12: 0 | CZ12: -0.1 | DA12: 0 | DC12: 0.1 | DD12: 1.5 | DE12: 2.6 | DF12: -1.5 | DG12: 0.1 | DH12: 0 | DI12: 0 | DJ12: 0 | DK12: 0 | DL12: -1.9 | DM12: 4.2 | DN12: 1.6 | DO12: 0.5 | DP12: 0.74 | DQ12: 0.3 | DR12: 0 | DS12: 0.2 | DT12: 0.3 | DU12: 0.3 | DW12: -4.9 | DX12: 0.9 | DY12: 2.7 | DZ12: 2.8 | EA12: 1.5 | EB12: 0.8 | EC12: 4 | ED12: 0 | EE12: -6.6 | EF12: -7.2 | EG12: 0 | EH12: 0 | EI12: 2.5 | EJ12: -0.1 | EK12: 0.7 | EL12: 0.2 | EM12: 0.2 | EN12: 0.2 | EP12: 0 | EQ12: 0 | ER12: -0.2 | ES12: 3.1 | ET12: 2.8 | EU12: 0 | EV12: 0 | EW12: 0.4 | EX12: 1.8 | EZ12: 8.7 | FA12: 10.3 | FB12: 1.1 | FC12: 2.1 | FD12: 0 | FE12: 0 | FF12: 2.8 | FG12: 175.54 | FI12: 3.20497 | FJ12: 0.535 | FL12: 1.8 | FN12: 2.69241 | FO12: -0.4 | FP12: 0.3 | FQ12: 8.13238
A13: 15/03/2025 | B13: 01:30 | C13: 0.3 | D13: 0.1 | E13: 48.7 | F13: 35.1 | I13: -24.4 | J13: 11.1 | M13: -27 | N13: 0 | O13: -19 | P13: 13.5 | Q13: 23.4 | R13: 20.4 | S13: 47.8 | T13: 0.1 | Y13: 5.1 | Z13: 1 | AB13: -3.1 | AC13: 2.8 | AD13: 4 | AE13: 1.5 | AI13: 18.8 | AJ13: 15.9 | AN13: -1 | AO13: 50.9 | AP13: 10.7 | AQ13: 19.4 | AR13: 3.2 | AS13: 2.2 | AT13: 2.4 | AU13: 0.8 | AV13: 0 | AW13: -11.3 | AX13: -42.4 | AY13: 10.6 | BB13: 0.5 | BC13: 7 | BD13: 1.1 | BE13: -0.2 | BF13: -5.9 | BG13: 4.8 | BH13: -5.7 | BN13: 9.6 | BO13: -30.9 | BP13: -32.3 | BQ13: -27.6 | BR13: -29.1 | CA13: 0.2 | CB13: 33.2 | CC13: 27 | CD13: -0.5 | CE13: 4.5 | CF13: -2.1 | CK13: 16.3 | CL13: -38.9 | CR13: 0 | CU13: 4.5 | CV13: 0 | CW13: 0 | CZ13: -0.1 | DA13: 0 | DC13: 0 | DD13: 1.3 | DE13: 2.6 | DF13: -1.3 | DG13: 0.1 | DH13: 0 | DI13: 0 | DJ13: 0 | DK13: 0 | DL13: -1.7 | DM13: 4.4 | DN13: 1.6 | DO13: 0.5 | DP13: 0.74 | DQ13: 0.3 | DR13: 0 | DS13: 0.1 | DT13: 0.3 | DU13: 0.3 | DW13: -4.8 | DX13: 0.8 | DY13: 2.7 | DZ13: 2.7 | EA13: 1.5 | EB13: 0.8 | EC13: 4 | ED13: 0 | EE13: -6 | EF13: -6.4 | EG13: 0 | EH13: 0 | EI13: 2.5 | EJ13: -0.1 | EK13: 0.7 | EL13: 0.2 | EM13: 0.2 | EN13: 0.2 | EP13: 0 | EQ13: 0 | ER13: -0.2 | ES13: 3.7 | ET13: 3 | EU13: 0 | EV13: 0 | EW13: 0.4 | EX13: 1.8 | EZ13: 9.1 | FA13: 10.8 | FB13: 1.1 | FC13: 1.9 | FD13: 0 | FE13: 0 | FF13: 2.5 | FG13: 199.34 | FI13: 3.06691 | FJ13: 0.408 | FL13: 1.8 | FN13: 2.69868 | FO13: -0.6 | FP13: 0.3 | FQ13: 7.67359
A14: 15/03/2025 | B14: 02:00 | C14: 0.3 | D14: 0.1 | E14: 37.1 | F14: 33 | I14: -27.4 | J14: 11.6 | M14: -29.7 | N14: 1 | O14: -25.4 | P14: 11.3 | Q14: 19.9 | R14: 19.5 | S14: 49.2 | T14: -0.1 | Y14: 4.3 | Z14: 0.6 | AB14: -3.1 | AC14: 2.8 | AD14: 4.5 | AE14: 1.7 | AI14: 17.6 | AJ14: 13.7 | AN14: -1.1 | AO14: 49.8 | AP14: 10.6 | AQ14: 18.5 | AR14: 3.2 | AS14: 2.4 | AT14: 2.4 | AU14: 0.7 | AV14: 0 | AW14: -13.4 | AX14: -44.2 | AY14: 10.1 | BB14: -1.4 | BC14: 6.3 | BD14: 1.1 | BE14: 0 | BF14: -10.8 | BG14: 4.2 | BH14: -7.2 | BN14: 11.1 | BO14: -33.4 | BP14: -34.7 | BQ14: -30.5 | BR14: -34.4 | CA14: 0.2 | CB14: 33.5 | CC14: 26.7 | CD14: 0.3 | CE14: 4.8 | CF14: -2.1 | CK14: 14.3 | CL14: -42.3 | CR14: 0 | CU14: 4.4 | CV14: 0 | CW14: 0 | CZ14: -0.1 | DA14: 0 | DC14: 0 | DD14: 1.3 | DE14: 2.7 | DF14: -1.8 | DG14: 0.1 | DH14: 0 | DI14: 0 | DJ14: 0 | DK14: 0 | DL14: -1.9 | DM14: 3.9 | DN14: 1.6 | DO14: 0.5 | DP14: 0.74 | DQ14: 0.3 | DR14: 0 | DS14: 0 | DT14: 0.3 | DU14: 0.3 | DW14: -4.7 | DX14: 0.8 | DY14: 2.8 | DZ14: 2.3 | EA14: 1.3 | EB14: 0.8 | EC14: 4 | ED14: 0 | EE14: -6.9 | EF14: -7.8 | EG14: 0 | EH14: 0 | EI14: 2.5 | EJ14: -0.1 | EK14: 0.7 | EL14: 0.2 | EM14: 0.2 | EN14: 0.2 | EP14: 0 | EQ14: 0 | ER14: -0.2 | ES14: 3.8 | ET14: 3.3 | EU14: 0 | EV14: 0 | EW14: 0.4 | EX14: 1.6 | EZ14: 8.1 | FA14: 9.7 | FB14: 1.1 | FC14: 1.6 | FD14: 0 | FE14: 0 | FF14: 2.2 | FG14: 127.44 | FI14: 3.05449 | FJ14: 0.27 | FL14: 1.8 | FN14: 2.69812 | FO14: -0.7 | FP14: 0.6 | FQ14: 7.72261
A15: 15/03/2025 | B15: 02:30 | C15: 0.2 | D15: 0.1 | E15: 42.5 | F15: 33 | I15: -25.2 | J15: 12.2 | M15: -31.3 | N15: 0.5 | O15: -27.6 | P15: 9 | Q15: 18.4 | R15: 17.8 | S15: 48.4 | T15: -0.2 | Y15: 6.5 | Z15: 0.7 | AB15: -3.1 | AC15: 2.7 | AD15: 3.5 | AE15: 1.8 | AI15: 17.8 | AJ15: 13.2 | AN15: -1.1 | AO15: 41 | AP15: 10.1 | AQ15: 19.5 | AR15: 3.2 | AS15: 2.1 | AT15: 2.4 | AU15: 1.3 | AV15: 0 | AW15: -16.7 | AX15: -47.5 | AY15: 11.2 | BB15: -1.9 | BC15: 6.3 | BD15: 1.1 | BE15: -0.1 | BF15: -12.4 | BG15: 4.3 | BH15: 0 | BN15: 7.6 | BO15: -38.6 | BP15: -40 | BQ15: -35.3 | BR15: -37.1 | CA15: 0.2 | CB15: 32.9 | CC15: 25.7 | CD15: 0.7 | CE15: 4.2 | CF15: -2.2 | CK15: 11.8 | CL15: -46.6 | CR15: 0 | CU15: 4.6 | CV15: 0 | CW15: 0 | CZ15: 0 | DA15: 0 | DC15: 0.1 | DD15: 1.3 | DE15: 2.7 | DF15: -1.1 | DG15: 0.1 | DH15: 0 | DI15: 0 | DJ15: 0 | DK15: 0 | DL15: -2 | DM15: 3.6 | DN15: 1.6 | DO15: 0.5 | DP15: 0.74 | DQ15: 0.3 | DR15: 0 | DS15: 0 | DT15: 0.3 | DU15: 0.3 | DW15: -4.8 | DX15: 0.8 | DY15: 2.9 | DZ15: 2.2 | EA15: 1.2 | EB15: 0.8 | EC15: 4 | ED15: 0 | EE15: -7.5 | EF15: -8.1 | EG15: 0 | EH15: 0 | EI15: 2.5 | EJ15: -0.1 | EK15: 0.7 | EL15: 0.2 | EM15: 0.2 | EN15: 0.2 | EP15: 0 | EQ15: 0 | ER15: -0.2 | ES15: 4.3 | ET15: 3.4 | EU15: 0 | EV15: 0 | EW15: 0.4 | EX15: 1.4 | EZ15: 7.8 | FA15: 9.4 | FB15: 1.1 | FC15: 1.4 | FD15: 0 | FE15: 0 | FF15: 2.1 | FG15: 86.34 | FI15: 2.85255 | FJ15: 0.673 | FL15: 1.6 | FN15: 2.69072 | FO15: -0.6 | FP15: 0.5 | FQ15: 7.71627
A16: 15/03/2025 | B16: 03:00 | C16: 0.2 | D16: 0.1 | E16: 27.9 | F16: 30.1 | I16: -25.8 | J16: 12.5 | M16: -32.1 | N16: -4 | O16: -34.1 | P16: 11.9 | Q16: 16 | R16: 17.2 | S16: 42.2 | T16: -0.1 | Y16: 1.5 | Z16: 1 | AB16: -3.1 | AC16: 2.8 | AD16: 4.6 | AE16: 1.7 | AI16: 16.3 | AJ16: 13 | AN16: -1.1 | AO16: 44.5 | AP16: 10.2 | AQ16: 21.6 | AR16: 2.8 | AS16: 2.1 | AT16: 2.4 | AU16: 0.7 | AV16: 0 | AW16: -18.9 | AX16: -49.3 | AY16: 9.8 | BB16: -2.8 | BC16: 5.6 | BD16: 1.1 | BE16: -0.1 | BF16: -11.4 | BG16: 2.8 | BH16: 0 | BN16: 7.6 | BO16: -39.3 | BP16: -40.7 | BQ16: -36.5 | BR16: -41 | CA16: 0.2 | CB16: 32.8 | CC16: 27.3 | CD16: 1 | CE16: 4.4 | CF16: -2 | CK16: 9.1 | CL16: -50.1 | CR16: 0 | CU16: 5 | CV16: 0 | CW16: 0 | CZ16: -0.1 | DA16: 0 | DC16: 0 | DD16: 1.3 | DE16: 2.6 | DF16: -1 | DG16: 0.1 | DH16: 0 | DI16: 0 | DJ16: 0 | DK16: 0 | DL16: -2.1 | DM16: 4 | DN16: 1.6 | DO16: 0.5 | DP16: 0.74 | DQ16: 0.3 | DR16: 0 | DS16: -0.1 | DT16: 0.3 | DU16: 0.3 | DW16: -4.7 | DX16: 0.7 | DY16: 2.7 | DZ16: 2.1 | EA16: 1.1 | EB16: 0.8 | EC16: 4 | ED16: 0 | EE16: -10.1 | EF16: -11 | EG16: 0 | EH16: 0 | EI16: 2.5 | EJ16: -0.1 | EK16: 0.7 | EL16: 0.2 | EM16: 0.2 | EN16: 0.2 | EP16: 0 | EQ16: 0 | ER16: -0.2 | ES16: 4.6 | ET16: 3.4 | EU16: 0 | EV16: 0 | EW16: 0.4 | EX16: 1.4 | EZ16: 8.9 | FA16: 10.6 | FB16: 1.2 | FC16: 1.4 | FD16: 0 | FE16: 0 | FF16: 3.3 | FG16: 30.34 | FI16: 2.85577 | FJ16: 0.629 | FL16: 1.9 | FN16: 2.67522 | FO16: -1 | FP16: 0.3 | FQ16: 7.35999
A17: 15/03/2025 | B17: 03:30 | C17: 0.2 | D17: 0.1 | E17: 36.2 | F17: 32.3 | I17: -24.9 | J17: 9.4 | M17: -29.1 | N17: 0.1 | O17: -28.2 | P17: 18.3 | Q17: 17.1 | R17: 16.8 | S17: 47.5 | T17: -0.1 | Y17: 4.4 | Z17: 0.8 | AB17: -3.1 | AC17: 2.6 | AD17: 4 | AE17: 1.6 | AI17: 17.3 | AJ17: 4.1 | AN17: -1.2 | AO17: 35.6 | AP17: 10 | AQ17: 14 | AR17: 3.2 | AS17: 2.3 | AT17: 2.4 | AU17: 1.1 | AV17: 0 | AW17: -17 | AX17: -47.6 | AY17: 8.4 | BB17: -3.1 | BC17: 5.8 | BD17: 1.1 | BE17: -0.1 | BF17: -9.7 | BG17: 3.1 | BH17: 0 | BN17: 7.2 | BO17: -38.1 | BP17: -39.4 | BQ17: -35.4 | BR17: -42.2 | CA17: 0.2 | CB17: 34 | CC17: 25.4 | CD17: 0.2 | CE17: 4.5 | CF17: -1.9 | CK17: 8.1 | CL17: -48.6 | CR17: 0 | CU17: 4.3 | CV17: 0 | CW17: 0 | CZ17: 0 | DA17: 0 | DC17: 0 | DD17: 1.3 | DE17: 2.6 | DF17: -1.3 | DG17: 0.1 | DH17: 0 | DI17: 0 | DJ17: 0 | DK17: 0 | DL17: -2 | DM17: 5.2 | DN17: 1.6 | DO17: 0.5 | DP17: 0.74 | DQ17: 0.3 | DR17: 0 | DS17: -0.2 | DT17: 0.3 | DU17: 0.3 | DW17: -4.8 | DX17: 0.6 | DY17: 2.7 | DZ17: 2.1 | EA17: 1.1 | EB17: 0.8 | EC17: 4 | ED17: 0 | EE17: -6.9 | EF17: -8 | EG17: 0 | EH17: 0 | EI17: 2.6 | EJ17: -0.1 | EK17: 0.8 | EL17: 0.2 | EM17: 0.2 | EN17: 0.2 | EP17: 0 | EQ17: 0 | ER17: -0.2 | ES17: 4.5 | ET17: 3.3 | EU17: 0 | EV17: 0 | EW17: 0.4 | EX17: 1.4 | EZ17: 12.3 | FA17: 13.9 | FB17: 1.2 | FC17: 2.1 | FD17: 0 | FE17: 0 | FF17: 3.1 | FG17: 60.94 | FI17: 2.94126 | FJ17: 0.632 | FL17: 1.9 | FN17: 2.67421 | FO17: 0.6 | FP17: 1.7 | FQ17: 10.44747
A18: 15/03/2025 | B18: 04:00 | C18: 0.2 | D18: 0.1 | E18: 33.5 | F18: 31.5 | I18: -24.6 | J18: 3.1 | M18: -31.3 | N18: -2.7 | O18: -34.1 | P18: 19 | Q18: 17.2 | R18: 17.1 | S18: 48.6 | T18: -0.1 | Y18: 5.7 | Z18: 1.2 | AB18: -3.1 | AC18: 2.8 | AD18: 4.3 | AE18: 1.7 | AI18: 16.2 | AJ18: -2.5 | AN18: -1.2 | AO18: 24.5 | AP18: 9.1 | AQ18: 14.4 | AR18: 3.2 | AS18: 2.4 | AT18: 2.4 | AU18: 0.8 | AV18: 0 | AW18: -17.7 | AX18: -48.4 | AY18: 6.6 | BB18: -4.4 | BC18: 6.4 | BD18: 1.1 | BE18: -0.1 | BF18: -11.7 | BG18: 3 | BH18: 0 | BN18: 3.4 | BO18: -38.6 | BP18: -39.9 | BQ18: -35.7 | BR18: -42.7 | CA18: 0.2 | CB18: 32.8 | CC18: 27 | CD18: 0.1 | CE18: 4.5 | CF18: -1.9 | CK18: 7.2 | CL18: -49.9 | CR18: 0 | CU18: 3.7 | CV18: 0 | CW18: 0 | CZ18: 0 | DA18: 0 | DC18: 0 | DD18: 1.3 | DE18: 2.6 | DF18: -1.5 | DG18: 0.1 | DH18: 0 | DI18: 0 | DJ18: 0 | DK18: 0 | DL18: -2 | DM18: 5.7 | DN18: 1.6 | DO18: 0.5 | DP18: 0.74 | DQ18: 0.3 | DR18: 0 | DS18: -0.3 | DT18: 0.3 | DU18: 0.3 | DW18: -4.6 | DX18: 0.9 | DY18: 2.7 | DZ18: 2.1 | EA18: 1.1 | EB18: 0.8 | EC18: 4 | ED18: 0 | EE18: -7.4 | EF18: -7.6 | EG18: 0 | EH18: 0 | EI18: 2.6 | EJ18: -0.1 | EK18: 0.8 | EL18: 0.2 | EM18: 0.2 | EN18: 0.2 | EP18: 0 | EQ18: 0 | ER18: -0.2 | ES18: 4.6 | ET18: 3.3 | EU18: 0 | EV18: 0 | EW18: 0.4 | EX18: 1.4 | EZ18: 12.1 | FA18: 13.7 | FB18: 1.2 | FC18: 2 | FD18: 0 | FE18: 0 | FF18: 3 | FG18: 11.44 | FI18: 2.09753 | FJ18: 0.641 | FL18: 1.8 | FN18: 2.6698 | FO18: 0.5 | FP18: 1.8 | FQ18: 9.50833
A19: 15/03/2025 | B19: 04:30 | C19: 0.2 | D19: 0.1 | E19: 43.5 | F19: 33.4 | I19: -22.4 | J19: 3.5 | M19: -34 | N19: 6.8 | O19: -24.4 | P19: 10.7 | Q19: 17.3 | R19: 16.3 | S19: 42.8 | T19: 0.3 | Y19: 6.3 | Z19: 1.1 | AB19: -3.1 | AC19: 2.8 | AD19: 5.1 | AE19: 1.7 | AI19: 18 | AJ19: 2.1 | AN19: -1.2 | AO19: 20.1 | AP19: 9 | AQ19: 14.5 | AR19: 2.6 | AS19: 2.2 | AT19: 2.4 | AU19: 1.6 | AV19: 0 | AW19: -19.5 | AX19: -49.8 | AY19: 5.6 | BB19: -1.1 | BC19: 0 | BD19: 1.1 | BE19: -0.2 | BF19: -7.2 | BG19: 3.3 | BH19: 0 | BN19: 3.1 | BO19: -39.8 | BP19: -41.2 | BQ19: -36.2 | BR19: -42.9 | CA19: 0.2 | CB19: 30.3 | CC19: 26.7 | CD19: -0.1 | CE19: 4.4 | CF19: -2.1 | CK19: 6.7 | CL19: -51.3 | CR19: 0 | CU19: 3.1 | CV19: 0 | CW19: 0 | CZ19: -0.1 | DA19: 0 | DC19: 0.1 | DD19: 1.3 | DE19: 2.5 | DF19: -1.7 | DG19: 0.1 | DH19: 0.3 | DI19: 0 | DJ19: 0 | DK19: 0 | DL19: -2.5 | DM19: 4.1 | DN19: 1.6 | DO19: 0.5 | DP19: 0.74 | DQ19: 0.3 | DR19: 0 | DS19: 0 | DT19: 0.4 | DU19: 0.3 | DW19: -4.7 | DX19: 0.6 | DY19: 2.7 | DZ19: 2.3 | EA19: 1.3 | EB19: 0.8 | EC19: 4 | ED19: 0 | EE19: -6.6 | EF19: -7.7 | EG19: 0 | EH19: 0 | EI19: 2.6 | EJ19: -0.1 | EK19: 0.9 | EL19: 0.2 | EM19: 0.2 | EN19: 0.2 | EP19: 0 | EQ19: 0 | ER19: -0.2 | ES19: 4.7 | ET19: 3.3 | EU19: 0 | EV19: 0 | EW19: 0.4 | EX19: 1.6 | EZ19: 13 | FA19: 14.5 | FB19: 1.2 | FC19: 2.1 | FD19: 0 | FE19: 0 | FF19: 2.5 | FG19: 20.14 | FI19: 2.25825 | FJ19: 0.718 | FL19: 1.7 | FN19: 2.66121 | FO19: 0.4 | FP19: 1.3 | FQ19: 9.03746
A20: 15/03/2025 | B20: 05:00 | C20: 0.2 | D20: 0.1 | E20: 40.3 | F20: 33.6 | I20: -21.7 | J20: 11.2 | M20: -31.7 | N20: -0.4 | O20: -28.5 | P20: 15 | Q20: 18.3 | R20: 17.3 | S20: 51.3 | T20: 0 | Y20: 6.5 | Z20: 1 | AB20: -3.1 | AC20: 2.8 | AD20: 5.3 | AE20: 1.7 | AI20: 17.8 | AJ20: 4.2 | AN20: -1.1 | AO20: 44.4 | AP20: 10.2 | AQ20: 12.2 | AR20: 2.7 | AS20: 1.6 | AT20: 2.4 | AU20: 1.3 | AV20: 0 | AW20: -14.5 | AX20: -45.5 | AY20: 7.9 | BB20: -2.3 | BC20: 0 | BD20: 1.2 | BE20: -0.1 | BF20: -12.2 | BG20: 4.3 | BH20: 0 | BN20: 8.7 | BO20: -37.7 | BP20: -39.1 | BQ20: -34.7 | BR20: -42.9 | CA20: 0.2 | CB20: 33.4 | CC20: 25.5 | CD20: -0.1 | CE20: 4.4 | CF20: -2 | CK20: 10.8 | CL20: -44.5 | CR20: 0 | CU20: 3.8 | CV20: 0 | CW20: 0 | CZ20: -0.1 | DA20: 0 | DC20: 0.2 | DD20: 1.3 | DE20: 2.7 | DF20: -1.5 | DG20: 0.1 | DH20: 0.6 | DI20: 0 | DJ20: 0 | DK20: 0 | DL20: -1.8 | DM20: 5.9 | DN20: 1.6 | DO20: 0.5 | DP20: 0.74 | DQ20: 0.3 | DR20: 0.2 | DS20: 0.1 | DT20: 0.4 | DU20: 0.3 | DW20: -4.7 | DX20: 0.8 | DY20: 2.9 | DZ20: 2.3 | EA20: 1.3 | EB20: 0.8 | EC20: 4 | ED20: 0.4 | EE20: -7.1 | EF20: -7.2 | EG20: 0 | EH20: 0 | EI20: 2.6 | EJ20: -0.1 | EK20: 0.9 | EL20: 0.2 | EM20: 0.2 | EN20: 0.2 | EP20: 0 | EQ20: 0 | ER20: -0.2 | ES20: 4.5 | ET20: 3.3 | EU20: 0 | EV20: 0 | EW20: 0.4 | EX20: 1.6 | EZ20: 12.2 | FA20: 13.9 | FB20: 1.2 | FC20: 2.1 | FD20: 0 | FE20: 0 | FF20: 2.9 | FG20: 90.44 | FI20: 2.53442 | FJ20: 0.849 | FL20: 1.8 | FN20: 2.65526 | FO20: 0.8 | FP20: 1.7 | FQ20: 10.33868
A21: 15/03/2025 | B21: 05:30 | C21: 0.2 | D21: 0.1 | E21: 32.8 | F21: 32.5 | I21: -23.2 | J21: 0.2 | M21: -32.7 | N21: 0.8 | O21: -26.8 | P21: 13.4 | Q21: 18.2 | R21: 17.3 | S21: 49.2 | T21: 0.1 | Y21: 4.8 | Z21: 1.1 | AB21: -3.1 | AC21: 3 | AD21: 5.1 | AE21: 1.9 | AI21: 3.4 | AJ21: 14 | AN21: -1 | AO21: 47.4 | AP21: 10 | AQ21: 11.6 | AR21: 3.2 | AS21: 0.2 | AT21: 2.4 | AU21: 0.9 | AV21: 0 | AW21: -15 | AX21: -45.8 | AY21: 7.2 | BB21: -2.3 | BC21: 0 | BD21: 1.2 | BE21: -0.1 | BF21: -10.7 | BG21: 3.8 | BH21: 0 | BN21: 8.1 | BO21: -37.5 | BP21: -38.8 | BQ21: -34.4 | BR21: -39.6 | CA21: 0.2 | CB21: 32.7 | CC21: 24.8 | CD21: -0.8 | CE21: 4.4 | CF21: -2 | CK21: 10.7 | CL21: -44.4 | CR21: 0 | CU21: 4.3 | CV21: 0 | CW21: 0 | CZ21: -0.1 | DA21: 0 | DC21: 0.1 | DD21: 1.3 | DE21: 2.7 | DF21: -1.3 | DG21: 0.1 | DH21: 0.6 | DI21: 0 | DJ21: 0 | DK21: 0 | DL21: -2.3 | DM21: 5.1 | DN21: 1.6 | DO21: 0.5 | DP21: 0.74 | DQ21: 0.3 | DR21: 0.4 | DS21: 0.1 | DT21: 0.4 | DU21: 0.3 | DW21: -4.7 | DX21: 0.8 | DY21: 2.8 | DZ21: 2.3 | EA21: 1.3 | EB21: 0.8 | EC21: 4 | ED21: 0.4 | EE21: -9.5 | EF21: -10.1 | EG21: 0 | EH21: 0 | EI21: 2.6 | EJ21: -0.1 | EK21: 0.9 | EL21: 0.2 | EM21: 0 | EN21: 0.2 | EP21: 0 | EQ21: 0 | ER21: -0.2 | ES21: 4.6 | ET21: 3.4 | EU21: 0 | EV21: 0 | EW21: 0.4 | EX21: 1.6 | EZ21: 13.4 | FA21: 15.1 | FB21: 1.2 | FC21: 2.3 | FD21: 0 | FE21: 0 | FF21: 2.4 | FG21: 59.64 | FI21: 2.87448 | FJ21: 0.877 | FL21: 1.8 | FN21: 2.66795 | FO21: 0.9 | FP21: 1.6 | FQ21: 10.71943
A22: 15/03/2025 | B22: 06:00 | C22: 0.2 | D22: 0.1 | E22: 49.6 | F22: 36.1 | I22: -20.1 | J22: 13.5 | M22: -25.8 | N22: 8.2 | O22: -19.5 | P22: 20.7 | Q22: 24.3 | R22: 21.7 | S22: 55.7 | T22: 0 | Y22: 8.5 | Z22: 1.3 | AB22: -3 | AC22: 3 | AD22: 4.1 | AE22: 1.9 | AI22: 4.7 | AJ22: 15.5 | AN22: -1 | AO22: 49.4 | AP22: 9.9 | AQ22: 11.3 | AR22: 3.4 | AS22: -0.3 | AT22: 2.4 | AU22: 1 | AV22: 0 | AW22: -6.8 | AX22: -37.8 | AY22: 10.4 | BB22: -2.6 | BC22: 0 | BD22: 1.1 | BE22: -0.1 | BF22: -9.1 | BG22: 6 | BH22: 0 | BN22: 9.9 | BO22: -30.1 | BP22: -31.2 | BQ22: -26.7 | BR22: -29.2 | CA22: 0.2 | CB22: 34.9 | CC22: 23.8 | CD22: -0.8 | CE22: 4.7 | CF22: -2 | CK22: 17 | CL22: -35.2 | CR22: 0 | CU22: 5 | CV22: 2.4 | CW22: 0 | CZ22: 0 | DA22: 0 | DC22: 0.1 | DD22: 1.2 | DE22: 2.7 | DF22: -1.2 | DG22: 0.1 | DH22: 0.6 | DI22: 0 | DJ22: -0.1 | DK22: 0 | DL22: -1.9 | DM22: 6 | DN22: 1.6 | DO22: 0.5 | DP22: 0.74 | DQ22: 0.3 | DR22: 0.2 | DS22: 0.3 | DT22: 0.3 | DU22: 0.3 | DW22: -4.9 | DX22: 0.7 | DY22: 3.1 | DZ22: 2.4 | EA22: 1.5 | EB22: 0.8 | EC22: 4 | ED22: 0.3 | EE22: -6.2 | EF22: -6.6 | EG22: 0 | EH22: 0 | EI22: 2.6 | EJ22: -0.1 | EK22: 0.7 | EL22: 0 | EM22: 0 | EN22: 0 | EP22: 0 | EQ22: -0.5 | ER22: -0.2 | ES22: 4.6 | ET22: 3.4 | EU22: 0 | EV22: 0 | EW22: 0.4 | EX22: 1.8 | EZ22: 14.7 | FA22: 16.4 | FB22: 1.2 | FC22: 1.8 | FD22: 0 | FE22: 0 | FF22: 2.2 | FG22: 236.44 | FI22: 2.68714 | FJ22: 0.66 | FL22: 1.8 | FN22: 2.67171 | FO22: 1.6 | FP22: 1.9 | FQ22: 11.31885
... A58: 16/03/2025 | B58: 00:00 | C58: 0.2 | D58: 0.1 | E58: 42.1 | F58: 22.7 | I58: -16.2 | J58: 1.8 | M58: -17.5 | N58: -1.7 | O58: 4.8 | P58: 8 | Q58: 5.5 | R58: -1 | S58: 23.2 | T58: 0.4 | Y58: 4.2 | Z58: 0.8 | AB58: -3.3 | AC58: 2.7 | AD58: 6.6 | AE58: 2.5 | AI58: 17.9 | AJ58: -1.9 | AN58: -0.9 | AO58: 54.5 | AP58: 11.1 | AQ58: 17.5 | AR58: -1 | AS58: 2.6 | AT58: 2.4 | AU58: 0.7 | AV58: 0 | AW58: 0 | AX58: 0 | AY58: 9.5 | BB58: 3.8 | BC58: 6.7 | BD58: 1.1 | BE58: -0.1 | BF58: 13.6 | BG58: 0.7 | BH58: 0 | BN58: 7.2 | BO58: -32 | BP58: -33.9 | BQ58: -10 | BR58: -18.6 | CA58: 0.2 | CB58: 19.1 | CC58: 31.7 | CD58: -1.2 | CE58: 1.8 | CF58: 0.1 | CK58: 14.7 | CL58: -25.7 | CR58: 0 | CU58: 3.5 | CV58: 0 | CW58: 0 | CZ58: -0.1 | DA58: 0 | DC58: 0.1 | DD58: 1.3 | DE58: 2.5 | DF58: -1.3 | DG58: 0.8 | DH58: 0.7 | DI58: 0 | DJ58: 0 | DK58: 0 | DL58: 0 | DM58: 0 | DN58: 1.7 | DO58: 0.5 | DP58: 0.73 | DQ58: 0.4 | DR58: 0 | DS58: 0 | DT58: 0.3 | DU58: 0.3 | DW58: -4.7 | DX58: 0 | DY58: 2.8 | DZ58: 2.3 | EA58: 1.1 | EB58: 0.8 | EC58: 4 | ED58: 0 | EE58: -10.4 | EF58: -10.1 | EG58: 0 | EH58: 0 | EI58: 1.6 | EJ58: -0.1 | EK58: 1.2 | EL58: 0.2 | EM58: 0.2 | EN58: 0.2 | EP58: 0 | EQ58: 0 | ER58: -0.2 | ES58: 3.9 | ET58: 2.6 | EU58: 0 | EV58: 0 | EW58: 0.4 | EX58: 1.4 | EZ58: 8.1 | FA58: 9.7 | FB58: 1.2 | FC58: 1.4 | FD58: 1.7 | FE58: 0 | FF58: 1.2 | FG58: 209.43 | FI58: 2.89713 | FJ58: 0.347 | FL58: 1.6 | FN58: 4.73793 | FO58: -0.2 | FP58: 0.3 | FQ58: 9.68206
A59: EJEC | C59: 4.9 | D59: 2.05 | E59: 1846.25 | F59: 676.4 | G59: 0 | H59: 0 | I59: -456.3 | J59: 342.35 | K59: 0 | L59: 0 | M59: 133.8 | N59: 391.3 | O59: 15.45 | P59: 549.4 | Q59: 314.2 | R59: 290.7 | S59: 818.05 | T59: 2.25 | U59: 0 | V59: 0 | W59: 0 | X59: 0 | Y59: 77.35 | Z59: 29.35 | AA59: 0 | AB59: -74.9 | AC59: 61.4 | AD59: 238.95 | AE59: 30.8 | AF59: 0 | AG59: 0 | AH59: 0 | AI59: 336.8 | AJ59: 272 | AK59: 0 | AL59: 0 | AM59: 0 | AN59: -15.5 | AO59: 1262.4 | AP59: 250.3 | AQ59: 395.3 | AR59: 81.65 | AS59: 22.3 | AT59: 50.9 | AU59: 21.45 | AV59: 15.85 | AW59: -22.15 | AX59: 477.15 | AY59: 221.2 | AZ59: 0 | BA59: 0 | BB59: -11.4 | BC59: 48.15 | BD59: 26.3 | BE59: -0.45 | BF59: 30.4 | BG59: 81.2 | BH59: -8.15 | BI59: 0 | BJ59: 0 | BK59: 0 | BL59: 0 | BM59: 0 | BN59: 239.45 | BO59: -331.05 | BP59: -345.6 | BQ59: -394.4 | BR59: 248.5 | BS59: 0 | BT59: 0 | BU59: 0 | BV59: 0 | BW59: 0 | BX59: 0 | BY59: 0 | BZ59: 0 | CA59: 5.8 | CB59: 1435.55 | CC59: 840.5 | CD59: 89.35 | CE59: 174.45 | CF59: 12.4 | CG59: 0 | CH59: 0 | CI59: 0 | CJ59: 0 | CK59: 981.7 | CL59: -436.9 | CM59: 0 | CN59: 0 | CO59: 0 | CP59: 0 | CQ59: 0 | CR59: 0.4 | CS59: 0 | CT59: 0 | CU59: 83 | CV59: 72 | CW59: 0.05 | CX59: 0 | CY59: 0 | CZ59: -1.65 | DA59: -4.85 | DB59: 0 | DC59: -1.1 | DD59: 31.4 | DE59: 62.3 | DF59: -13.95 | DG59: 16.4 | DH59: 11.95 | DI59: 0.6 | DJ59: -7.9 | DK59: -19.65 | DL59: -34.35 | DM59: 62.9 | DN59: 39.1 | DO59: 12 | DP59: 17.29 | DQ59: 7.95 | DR59: -33.65 | DS59: 2.05 | DT59: 9.8 | DU59: 7.35 | DV59: 0 | DW59: -113.6 | DX59: 17.2 | DY59: 68.4 | DZ59: 66.95 | EA59: 34.9 | EB59: 19.2 | EC59: 96 | ED59: 25.6 | EE59: -160.8 | EF59: -163.05 | EG59: 1.9 | EH59: 0.4 | EI59: 47.7 | EJ59: -2.3 | EK59: 28.3 | EL59: 2.4 | EM59: 2.15 | EN59: 1.65 | EO59: 0 | EP59: 17.35 | EQ59: 166.9 | ER59: -4.8 | ES59: 21.6 | ET59: 40.1 | EU59: 108.7 | EV59: 17.35 | EW59: 9.55 | EX59: 42.25 | EY59: 0 | EZ59: 183.95 | FA59: 225.85 | FB59: 28.3 | FC59: 42.2 | FD59: 12.8 | FE59: 0.8 | FF59: 62.45 | FG59: 12616.99 | FI59: 68.20669 | FJ59: -2.8515 | FK59: 0 | FL59: 41.55 | FM59: 0 | FN59: 91.77829 | FO59: 9.35 | FP59: 51.05 | FQ59: 259.08348

Sheet DEMANDA_AREAS
B3: sábado, 15 de Marzo del 2025
B5: REPORTE DE LA DEMANDA POR ÁREAS Y SUBAREAS OPERATIVAS (MW)
B6: FECHA HORA | C6: DEMANDA | E6: AREA | H6: SUBAREAS
C7: INTERCAMBIOS INTERNACIONALES | D7: SEIN | E7: NORTE | F7: CENTRO | G7: SUR | H7: ELECTROANDES
B8: 00:30 | C8: 0 | D8: 6725.3 | E8: 1022.486 | F8: 3969.024 | G8: 1733.79 | H8: 232.159
B9: 01:00 | C9: 0 | D9: 6559.4 | E9: 953.751 | F9: 3876.849 | G9: 1728.8 | H9: 226.747
B10: 01:30 | C10: 0 | D10: 6519.5 | E10: 975.339 | F10: 3801.951 | G10: 1742.21 | H10: 225.503
B11: 02:00 | C11: 0 | D11: 6478.9 | E11: 974.943 | F11: 3766.057 | G11: 1737.9 | H11: 232.498
B12: 02:30 | C12: 0 | D12: 6354.5 | E12: 950.545 | F12: 3655.495 | G12: 1748.46 | H12: 222.033
B13: 03:00 | C13: 0 | D13: 6279.4 | E13: 956.872 | F13: 3572.988 | G13: 1749.54 | H13: 229.522
B14: 03:30 | C14: 0 | D14: 6406.9 | E14: 933.709 | F14: 3718.601 | G14: 1754.59 | H14: 225.4905
B15: 04:00 | C15: 0 | D15: 6323 | E15: 907.023 | F15: 3667.2345 | G15: 1748.7425 | H15: 224.78188
B16: 04:30 | C16: 0 | D16: 6289.1 | E16: 912.467 | F16: 3642.4499 | G16: 1734.1831 | H16: 223.23734
B17: 05:00 | C17: 0 | D17: 6396.6 | E17: 952.313 | F17: 3706.4656 | G17: 1737.8214 | H17: 221.81105
B18: 05:30 | C18: 0 | D18: 6305.5 | E18: 923.082 | F18: 3688.2462 | G18: 1694.1718 | H18: 221.7281
B19: 06:00 | C19: 0 | D19: 6445.2 | E19: 971.48 | F19: 3814.0184 | G19: 1659.7016 | H19: 206.90854
... B59: ENERGÍA | C59: 0 | D59: 170754.8 | E59: 26388.717 | F59: 100679.59 | G59: 43686.493 | H59: 5648.2957
B61: LEYENDA:
D63: Potencia recibida del Ecuador
D64: Potencia entregada al Ecuador

Sheet DEMANDA_UL
B3: sábado, 15 de Marzo del 2025
B5: POTENCIA DE LOS GRANDES USUARIOS LIBRES (MW)
B6: FECHA HORA | C6: GRANDES USUARIOS LIBRES DEL ÁREA NORTE | X6: GRANDES USUARIOS LIBRES DEL ÁREA CENTRO | BP6: GRANDES USUARIOS LIBRES DEL ÁREA SUR
C7: ARCA CONTINENTAL LINDLEY S.A. | D7: AUSTRAL GROUP S.A.A | E7: CEMENTOS PACASMAYO | F7: CORPORACIÓN PESQUERA INCA S.A.C. | G7: CREDITEX: CIA IND.TEXTIL CREDISA | H7: HIPERMERCADOS TOTTUS S.A | I7: INDUSTRIA TEXTIL PIURA | J7: MINERA BOROO MISQUICHILCA S.A. | K7: MINERA GOLD FIELDS | L7: MINERA HORIZONTE | M7: MINERA MARSA | N7: MINERA MISKY MAYO | O7: MINERA YANACOCHA | P7: OPEN PLAZA | Q7: PESQUERA DIAMANTE | R7: PETROPERU | S7: REAL PLAZA S.R.L. | T7: SIDER PERU | U7: SUPERMERCADOS PERUANOS S.A. | V7: TRUPAL S.A. | W7: UNIÓN DE CERVECERÍAS PERUANAS BACKUS Y JOHNSTON S. | X7: ACEROS AREQUIPA | Y7: ADMINISTRADORA JOCKEY PLAZA SHOPPING CENTER S.A. | Z7: ALICORP | AA7: ARCA CONTINENTAL LINDLEY S.A. | AB7: AUSTRAL GROUP S.A.A | AC7: COMPAÑIA MINERA CONDESTABLE | AD7: CORPORACIÓN PESQUERA INCA S.A.C. | AE7: CREDITEX: CIA IND.TEXTIL CREDISA | AF7: FUNDICION CHILCA S.A. | AG7: HIPERMERCADOS TOTTUS S.A | AH7: INMOBILIARIA KANPU S.A. | AI7: INMUEBLES PANAMERICANA S.A. | AJ7: KIMBERLY-CLARK PERU | AK7: LECHE GLORIA S.A. | AL7: MALL AVENTURA S.A. | AM7: MARCOBRE S.A.C. | AN7: MINERA ANTAMINA | AO7: MINERA ARES | AP7: MINERA BUENAVENTURA | AQ7: MINERA CHINALCO PERÚ S.A. | AR7: MINERA SHOUXIN PERU S.A. | AS7: MINERA VOLCAN | AT7: MINSUR | AU7: MOLYCOP-ADESUR | AV7: NEXA RESOURCES CAJAMARQUILLA S.A. | AW7: NEXA RESOURCES PERÚ S.A.A. | AX7: OPEN PLAZA | AY7: OPP FILM | AZ7: OWENS-ILLINOIS PERÚ S.A. | BA7: PAPELERA NACIONAL S.A. | BB7: PESQUERA DIAMANTE | BC7: QUIMPAC S.A. | BD7: REAL PLAZA S.R.L. | BE7: REFINERIA LA PAMPILLA S.A.A | BF7: SAGA FALABELLA | BG7: SAN MIGUEL INDUSTRIAS PET S.A. | BH7: SHOUGANG HIERRO PERU | BI7: SOFTYS PERU S.A.C. | BJ7: SUPERMERCADOS PERUANOS S.A. | BK7: TEJIDOS SAN JACINTO | BL7: TREN URBANO DE LIMA S.A. | BM7: TRUPAL S.A. | BN7: UNACEM PERU S.A. | BO7: UNIÓN DE CERVECERÍAS PERUANAS BACKUS Y JOHNSTON S. | BP7: ANGLO AMERICAN QUELLAVECO S.A. | BQ7: ARCA CONTINENTAL LINDLEY S.A. | BR7: CAL & CEMENTO SUR S.A. | BS7: COMPAÑIA MINERA ANTAPACCAY S.A. | BT7: COMPAÑÍA MINERA CHUNGAR SAC | BU7: COMPAÑIA MINERA SAN IGNACIO DE MOROCOCHA S.A.A. | BV7: EL BROCAL .S.A. | BW7: EMPRESA ADMINISTRADORA CERRO S.A.C. | BX7: EMPRESA MINERA LOS QUENUALES S.A.C. | BY7: HIPERMERCADOS TOTTUS S.A | BZ7: HUDBAY PERU S.A.C. | CA7: INDUSTRIA CACHIMAYO | CB7: MALL AVENTURA S.A. | CC7: MINERA ARES | CD7: MINERA BUENAVENTURA | CE7: MINERA CERRO VERDE | CF7: MINERA CORONA | CG7: MINERA LAS BAMBAS S.A. | CH7: MINERA VOLCAN | CI7: MINSUR | CJ7: MOLYCOP-ADESUR | CK7: NEXA RESOURCES PERÚ S.A.A. | CL7: OXIDOS DE PASCO S.A.C. | CM7: PESQUERA DIAMANTE | CN7: REAL PLAZA S.R.L. | CO7: SOBREANDES S.A.C. | CP7: SOUTHERN PERU CC | CQ7: SUPERMERCADOS PERUANOS S.A. | CR7: UNACEM PERU S.A. | CS7: UNIÓN DE CERVECERÍAS PERUANAS BACKUS Y JOHNSTON S. | CT7: YURA
B8: 00:30 | E8: 35.6243 | J8: 19.8946 | K8: 26.27211 | L8: 12.877 | M8: 15.1941 | N8: 13.67 | O8: 35.108 | R8: 51.774 | T8: 43.5144 | V8: 9.3 | X8: 156.74286 | Z8: 8.50097 | AF8: 2.1 | AJ8: 5.33786 | AK8: 0 | AL8: 1.1144 | AM8: 47.2979 | AN8: 129.94954 | AO8: 26.98697 | AP8: 0.81 | AQ8: 9.83 | AS8: 37.44593 | AT8: 34.87235 | AW8: 31.3685 | BA8: 1 | BC8: 71.85314 | BE8: 19.9 | BK8: 5.80677 | BO8: 2.15 | BP8: 150.01915 | BR8: 5.14654 | BS8: 131.1127 | BT8: 8.22815 | BV8: 33.1605 | BW8: 3.99012 | BZ8: 54.2573 | CA8: 22.40095 | CB8: 0.3291 | CC8: 0.7 | CD8: 30.0311 | CE8: 448.12736 | CF8: 11.1197 | CG8: 151.8426 | CH8: 18.63197 | CK8: 14.6995 | CL8: 5.32828 | CO8: 15.95037 | CP8: 256.82 | CR8: 37.131 | CT8: 14.37573
B9: 01:00 | E9: 34.9366 | J9: 20.1584 | K9: 26.37476 | L9: 13.042 | M9: 15.224 | N9: 13.68 | O9: 35.002 | R9: 51.596 | T9: 31.3253 | V9: 9.5 | X9: 133.38344 | Z9: 8.86495 | AF9: 3.3 | AJ9: 5.33431 | AK9: 0 | AL9: 1.0337 | AM9: 47.543 | AN9: 135.54549 | AO9: 26.53155 | AP9: 0.7 | AQ9: 10.16 | AS9: 37.61905 | AT9: 34.37548 | AW9: 30.3886 | BA9: 1.1 | BC9: 72.01969 | BE9: 19.9 | BK9: 5.77238 | BO9: 2.14 | BP9: 151.782 | BR9: 5.10766 | BS9: 132.37738 | BT9: 7.95506 | BV9: 32.0551 | BW9: 4.01347 | BZ9: 56.6009 | CA9: 22.39985 | CB9: 0.3142 | CC9: 0.693 | CD9: 29.85295 | CE9: 452.35972 | CF9: 11.3148 | CG9: 150.0147 | CH9: 18.94074 | CK9: 14.7213 | CL9: 5.13223 | CO9: 16.02957 | CP9: 263.36 | CR9: 36.37 | CT9: 14.72903
B10: 01:30 | E10: 33.321 | J10: 20.3352 | K10: 26.19809 | L10: 12.305 | M10: 14.6229 | N10: 12.91 | O10: 35.18 | R10: 51.659 | T10: 42.7944 | V10: 9.7 | X10: 136.31241 | Z10: 8.53142 | AF10: 4.1 | AJ10: 5.31128 | AK10: 0 | AL10: 0.9507 | AM10: 46.4568 | AN10: 137.30925 | AO10: 26.85295 | AP10: 0.64 | AQ10: 10.67 | AS10: 38.63051 | AT10: 35.24186 | AW10: 31.0344 | BA10: 1.5 | BC10: 71.54142 | BE10: 19.9 | BK10: 5.74576 | BO10: 2.03 | BP10: 152.28862 | BR10: 5.09891 | BS10: 133.47907 | BT10: 8.12933 | BV10: 32.6414 | BW10: 4.02097 | BZ10: 90.5729 | CA10: 22.4056 | CB10: 0.3015 | CC10: 0.705 | CD10: 28.66493 | CE10: 446.30661 | CF10: 11.2799 | CG10: 150.1988 | CH10: 19.10084 | CK10: 14.4806 | CL10: 5.16333 | CO10: 15.43642 | CP10: 261.35 | CR10: 35.249 | CT10: 15.33679
B11: 02:00 | E11: 32.7427 | J11: 20.1757 | K11: 26.13153 | L11: 12.466 | M11: 14.6784 | N11: 13.33 | O11: 34.896 | R11: 52.038 | T11: 47.5791 | V11: 9.8 | X11: 103.32458 | Z11: 8.79188 | AF11: 4.5 | AJ11: 5.27359 | AK11: 0 | AL11: 0.9127 | AM11: 47.889 | AN11: 137.19565 | AO11: 26.64117 | AP11: 0.44 | AQ11: 9.62 | AS11: 37.92388 | AT11: 34.69277 | AW11: 30.3775 | BA11: 1.8 | BC11: 71.97937 | BE11: 19.9 | BK11: 5.71977 | BO11: 1.99 | BP11: 150.61138 | BR11: 5.03583 | BS11: 132.21674 | BT11: 8.36717 | BV11: 33.1916 | BW11: 3.90452 | BZ11: 91.5839 | CA11: 22.41629 | CB11: 0.2887 | CC11: 0.692 | CD11: 28.42548 | CE11: 448.311 | CF11: 10.9033 | CG11: 154.9044 | CH11: 19.04518 | CK11: 14.5174 | CL11: 4.85333 | CO11: 15.98631 | CP11: 252.12 | CR11: 36.051 | CT11: 15.43634
B12: 02:30 | E12: 31.8765 | J12: 20.2511 | K12: 25.77265 | L12: 12.05 | M12: 15.1374 | N12: 13.2 | O12: 34.712 | R12: 52.306 | T12: 39.8787 | V12: 9.7 | X12: 106.85008 | Z12: 8.83334 | AF12: 5 | AJ12: 5.22184 | AK12: 0 | AL12: 0.89 | AM12: 48.9756 | AN12: 133.93971 | AO12: 27.38932 | AP12: 0.41 | AQ12: 9.71 | AS12: 37.76459 | AT12: 34.9036 | AW12: 31.5775 | BA12: 1.8 | BC12: 72.12832 | BE12: 19.9 | BK12: 5.57512 | BO12: 2.01 | BP12: 149.97682 | BR12: 5.09611 | BS12: 130.60941 | BT12: 8.07568 | BV12: 31.6223 | BW12: 3.78482 | BZ12: 90.9197 | CA12: 22.44097 | CB12: 0.2806 | CC12: 0.7 | CD12: 29.11755 | CE12: 463.01634 | CF12: 11.0402 | CG12: 149.9422 | CH12: 18.93804 | CK12: 15.0406 | CL12: 4.5628 | CO12: 15.88036 | CP12: 247.19 | CR12: 31.153 | CT12: 15.45628
B13: 03:00 | E13: 32.3412 | J13: 20.1027 | K13: 25.88602 | L13: 13.491 | M13: 15.0753 | N13: 13.6 | O13: 34.43 | R13: 52.279 | T13: 43.4292 | V13: 9.6 | X13: 142.57388 | Z13: 8.8057 | AF13: 4 | AJ13: 4.81592 | AK13: 0 | AL13: 0.8687 | AM13: 48.8629 | AN13: 131.62098 | AO13: 27.46585 | AP13: 0.67 | AQ13: 9.42 | AS13: 37.82235 | AT13: 34.90237 | AW13: 31.6255 | BA13: 1.8 | BC13: 71.97323 | BE13: 19.9 | BK13: 5.66963 | BO13: 1.96 | BP13: 149.16892 | BR13: 4.92582 | BS13: 128.70443 | BT13: 7.58594 | BV13: 31.9519 | BW13: 3.70321 | BZ13: 90.851 | CA13: 22.53756 | CB13: 0.2726 | CC13: 0.69 | CD13: 29.3342 | CE13: 459.86194 | CF13: 10.9887 | CG13: 146.5967 | CH13: 19.00703 | CK13: 14.8803 | CL13: 4.54163 | CO13: 15.93529 | CP13: 256.82 | CR13: 36.284 | CT13: 15.28845
B14: 03:30 | E14: 31.0672 | J14: 20.0343 | K14: 25.68938 | L14: 13.235 | M14: 15.2828 | N14: 13.46 | O14: 34.222 | R14: 52.03 | T14: 34.6069 | V14: 9.6 | X14: 135.20177 | Z14: 8.41227 | AF14: 1.9 | AJ14: 5.05719 | AK14: 0 | AL14: 0.8591 | AM14: 47.8657 | AN14: 133.39049 | AO14: 27.09866 | AP14: 0.48 | AQ14: 9.67 | AS14: 38.36674 | AT14: 34.02901 | AW14: 31.2326 | BA14: 1.8 | BC14: 72.0364 | BE14: 19.9 | BK14: 5.81615 | BO14: 2.2 | BP14: 152.94678 | BR14: 5.08689 | BS14: 130.11022 | BT14: 7.3249 | BV14: 32.5008 | BW14: 3.72163 | BZ14: 89.8584 | CA14: 22.7149 | CB14: 0.2689 | CC14: 0.716 | CD14: 29.82391 | CE14: 468.81686 | CF14: 11.0977 | CG14: 153.939 | CH14: 19.01574 | CK14: 15.1517 | CL14: 4.54829 | CO14: 16.06107 | CP14: 252.75 | CR14: 36.921 | CT14: 15.26526
B15: 04:00 | E15: 29.5314 | J15: 19.1721 | K15: 26.38943 | L15: 13.355 | M15: 15.3774 | N15: 13.48 | O15: 34.74 | R15: 52.424 | T15: 47.3381 | V15: 9.5 | X15: 139.96298 | Z15: 8.27277 | AF15: 1.8 | AJ15: 5.19055 | AK15: 0 | AL15: 0.8556 | AM15: 48.4866 | AN15: 133.75124 | AO15: 27.7262 | AP15: 0.18 | AQ15: 9.19 | AS15: 38.27071 | AT15: 33.11154 | AW15: 30.5354 | BA15: 1.9 | BC15: 72.02334 | BE15: 19.9 | BK15: 5.78017 | BO15: 2.14 | BP15: 153.91138 | BR15: 5.00629 | BS15: 131.25958 | BT15: 7.57597 | BV15: 32.7692 | BW15: 3.73441 | BZ15: 91.3078 | CA15: 22.74224 | CB15: 0.2619 | CC15: 0.688 | CD15: 28.74933 | CE15: 465.48603 | CF15: 11.1084 | CG15: 157.9154 | CH15: 18.65635 | CK15: 14.696 | CL15: 4.75755 | CO15: 16.2097 | CP15: 255.43 | CR15: 30.881 | CT15: 15.43985
B16: 04:30 | E16: 32.0894 | J16: 18.7533 | K16: 26.87635 | L16: 12.736 | M16: 15.5978 | N16: 13.59 | O16: 35.806 | R16: 52.384 | T16: 42.918 | V16: 9.3 | X16: 111.67165 | Z16: 8.36412 | AF16: 1.8 | AJ16: 5.28152 | AK16: 0 | AL16: 0.8379 | AM16: 48.5573 | AN16: 135.20038 | AO16: 27.0009 | AP16: 1.65 | AQ16: 8.83 | AS16: 37.89447 | AT16: 32.86643 | AW16: 30.5402 | BA16: 1.9 | BC16: 71.99054 | BE16: 19.9 | BK16: 5.87565 | BO16: 2.11 | BP16: 152.63288 | BR16: 5.07911 | BS16: 130.71159 | BT16: 7.43186 | BV16: 33.3144 | BW16: 3.76614 | BZ16: 91.3674 | CA16: 22.74017 | CB16: 0.2524 | CC16: 0.72 | CD16: 28.68062 | CE16: 465.11265 | CF16: 11.3768 | CG16: 153.1435 | CH16: 19.21364 | CK16: 14.7274 | CL16: 4.81202 | CO16: 15.62825 | CP16: 259.31 | CR16: 30.966 | CT16: 15.51272
B17: 05:00 | E17: 32.0498 | J17: 18.4668 | K17: 27.20903 | L17: 12.3 | M17: 14.7978 | N17: 13.57 | O17: 35.758 | R17: 51.878 | T17: 44.6594 | V17: 9.1 | X17: 112.3085 | Z17: 8.96555 | AF17: 0.9 | AJ17: 5.03627 | AK17: 0 | AL17: 0.8237 | AM17: 48.9187 | AN17: 134.22837 | AO17: 27.20928 | AP17: 2.1 | AQ17: 9.74 | AS17: 36.55682 | AT17: 32.0961 | AW17: 30.1067 | BA17: 1.8 | BC17: 71.65567 | BE17: 19.9 | BK17: 5.81621 | BO17: 2.15 | BP17: 153.75413 | BR17: 5.17891 | BS17: 131.32129 | BT17: 5.40038 | BV17: 32.6665 | BW17: 3.82145 | BZ17: 91.5987 | CA17: 22.73751 | CB17: 0.2489 | CC17: 0.688 | CD17: 28.11726 | CE17: 465.8168 | CF17: 11.3768 | CG17: 157.5102 | CH17: 18.98967 | CK17: 14.2286 | CL17: 4.81998 | CO17: 15.17887 | CP17: 259.21 | CR17: 36.947 | CT17: 14.99035
B18: 05:30 | E18: 31.928 | J18: 20.1371 | K18: 27.65036 | L18: 11.159 | M18: 14.7356 | N18: 13.66 | O18: 35.702 | R18: 51.783 | T18: 28.6999 | V18: 8.8 | X18: 136.41028 | Z18: 8.9301 | AF18: 1.8 | AJ18: 5.08865 | AK18: 0 | AL18: 0.8306 | AM18: 47.395 | AN18: 131.60849 | AO18: 26.92027 | AP18: 1.93 | AQ18: 10.16 | AS18: 36.09592 | AT18: 32.11328 | AW18: 29.2345 | BA18: 1.7 | BC18: 71.40299 | BE18: 19.9 | BK18: 5.72244 | BO18: 2.17 | BP18: 152.82524 | BR18: 5.17438 | BS18: 131.00982 | BT18: 7.09735 | BV18: 32.1916 | BW18: 3.9366 | BZ18: 91.9254 | CA18: 22.71961 | CB18: 0.2439 | CC18: 0.636 | CD18: 28.94093 | CE18: 468.69313 | CF18: 10.8566 | CG18: 152.4749 | CH18: 18.95654 | CK18: 14.2629 | CL18: 4.70584 | CO18: 14.11775 | CP18: 259.04 | CR18: 37.244 | CT18: 14.55692
B19: 06:00 | E19: 31.9353 | J19: 19.7527 | K19: 27.80741 | L19: 10.302 | M19: 14.3648 | N19: 13.35 | O19: 35.74 | R19: 51.997 | T19: 38.9679 | V19: 8.6 | X19: 146.77641 | Z19: 8.72031 | AF19: 0.9 | AJ19: 5.10208 | AK19: 0 | AL19: 0.8452 | AM19: 50.1315 | AN19: 135.70607 | AO19: 26.49886 | AP19: 1.54 | AQ19: 11.16 | AS19: 35.40868 | AT19: 32.22522 | AW19: 28.9797 | BA19: 1.8 | BC19: 71.51033 | BE19: 19.9 | BK19: 5.5867 | BO19: 2.05 | BP19: 152.54388 | BR19: 4.59699 | BS19: 132.32252 | BT19: 6.84629 | BV19: 31.3738 | BW19: 4.01761 | BZ19: 92.9947 | CA19: 22.72049 | CB19: 0.2428 | CC19: 0.713 | CD19: 28.34623 | CE19: 462.89432 | CF19: 10.3397 | CG19: 148.9059 | CH19: 18.93178 | CK19: 13.6749 | CL19: 4.59137 | CO19: 13.48593 | CP19: 259.3 | CR19: 31.66 | CT19: 14.01238
... B54: 23:30 | E54: 36.889 | J54: 20.4872 | K54: 26.65671 | L54: 12.531 | M54: 12.8839 | N54: 12.64 | O54: 35.048 | R54: 52.023 | T54: 31.2582 | V54: 9.2 | X54: 104.4285 | Z54: 8.99613 | AF54: 0.5 | AJ54: 4.5418 | AK54: 0 | AL54: 1.4597 | AM54: 50.0865 | AN54: 133.54275 | AO54: 28.81031 | AP54: 1.2 | AQ54: 10.09 | AS54: 37.98949 | AT54: 34.30687 | AW54: 30.6346 | BA54: 1.9 | BC54: 73.53103 | BE54: 19.8 | BK54: 5.68558 | BO54: 1.87 | BP54: 152.69225 | BR54: 5.23856 | BS54: 132.63734 | BT54: 9.03818 | BV54: 35.6817 | BW54: 3.85644 | BZ54: 93.045 | CA54: 22.43349 | CB54: 0.4979 | CC54: 0.586 | CD54: 30.92837 | CE54: 468.55229 | CF54: 11.7205 | CG54: 154.2841 | CH54: 19.24681 | CK54: 17.1691 | CL54: 4.90028 | CO54: 15.69096 | CP54: 276.28 | CR54: 37.404 | CT54: 15.62106
B55: 00:00 | E55: 38.5364 | J55: 20.1069 | K55: 26.21133 | L55: 12.315 | M55: 14.1109 | N55: 12.71 | O55: 35.464 | R55: 51.883 | T55: 27.9565 | V55: 9 | X55: 129.41913 | Z55: 8.91339 | AF55: 0.6 | AJ55: 5.27586 | AK55: 0 | AL55: 1.3277 | AM55: 50.3901 | AN55: 132.70472 | AO55: 29.24447 | AP55: 0.83 | AQ55: 9.92 | AS55: 38.40595 | AT55: 34.39065 | AW55: 30.3788 | BA55: 2.1 | BC55: 73.85066 | BE55: 19.8 | BK55: 5.72348 | BO55: 1.79 | BP55: 154.99573 | BR55: 5.2178 | BS55: 134.55255 | BT55: 8.19209 | BV55: 34.5154 | BW55: 3.83695 | BZ55: 93.0492 | CB55: 0.4391 | CC55: 0.651 | CD55: 29.27958 | CE55: 468.00488 | CF55: 11.4951 | CG55: 153.903 | CH55: 19.13643 | CK55: 17.1729 | CL55: 4.87482 | CO55: 15.3441 | CP55: 280.54 | CR55: 37.262 | CT55: 17.26333
B56: MWh | C56: 0 | D56: 0 | E56: 738.71305 | F56: 0 | G56: 0 | H56: 0 | I56: 0 | J56: 482.83405 | K56: 643.54835 | L56: 286.0555 | M56: 288.20435 | N56: 319.205 | O56: 837.111 | P56: 0 | Q56: 0 | R56: 1242.008 | S56: 0 | T56: 872.9878 | U56: 0 | V56: 215.35 | W56: 0 | X56: 2509.4255 | Y56: 0 | Z56: 208.10435 | AA56: 0 | AB56: 0 | AC56: 0 | AD56: 0 | AE56: 0 | AF56: 26.55 | AG56: 0 | AH56: 0 | AI56: 0 | AJ56: 118.96792 | AK56: 0 | AL56: 71.59425 | AM56: 1103.1255 | AN56: 3203.8676 | AO56: 647.74105 | AP56: 18.01 | AQ56: 224.13 | AR56: 0 | AS56: 850.9661 | AT56: 782.31213 | AU56: 0 | AV56: 0 | AW56: 683.38345 | AX56: 0 | AY56: 0 | AZ56: 0 | BA56: 39.4 | BB56: 0 | BC56: 1587.6491 | BD56: 0 | BE56: 489.45 | BF56: 0 | BG56: 0 | BH56: 0 | BI56: 0 | BJ56: 0 | BK56: 135.19792 | BL56: 0 | BM56: 0 | BN56: 0 | BO56: 48.22 | BP56: 3604.6868 | BQ56: 0 | BR56: 125.16024 | BS56: 3144.3792 | BT56: 167.84075 | BU56: 0 | BV56: 756.17665 | BW56: 93.50564 | BX56: 0 | BY56: 0 | BZ56: 2158.1051 | CA56: 488.87009 | CB56: 19.30505 | CC56: 15.7335 | CD56: 698.22846 | CE56: 11097.853 | CF56: 260.1544 | CG56: 3633.0804 | CH56: 439.43407 | CI56: 0 | CJ56: 0 | CK56: 356.47605 | CL56: 112.89521 | CM56: 0 | CN56: 0 | CO56: 354.39109 | CP56: 6302.23 | CQ56: 0 | CR56: 812.63 | CS56: 0 | CT56: 252.29753
B59: Nota :
B60: Información proporcionada por la empresas
C62: DATOS ESTIMADOS
C64: SIN DATOS

Sheet TIPO_RECURSO
B3: sábado, 15 de Marzo del 2025
B5: REPORTE POTENCIA GENERADA POR TIPO DE RECURSO
B6: HORA | C6: H. PASADA | D6: H. REGULACION | E6: GAS DE CAMISEA | F6: GAS DE MALACAS | G6: GAS DE AGUAYTIA | H6: DIESEL | I6: RESIDUAL | J6: NAFTA+GAS DE REFINERIA | K6: FLEXIGAS+GAS DE REFINERIA | L6: BAGAZO | M6: BIOGAS | N6: SOLAR | O6: EOLICA | P6: TOTAL | U6: EMPRESA | V6: CENTRAL | W6: HIDROELECTRICA DE PASADA | X6: HIDROELECTRICA DE REGULACION
B7: 00:30 | C7: 1159.9 | D7: 3362.7 | E7: 1711 | F7: 25.2 | J7: =DESPACHO_EJECUTADO!FA11+DESPACHO_EJECUTADO!FB11 -> 65.9 | L7: 7 | M7: 10.6 | N7: 0 | O7: 383 | P7: =SUM(C7:O7) -> 6725.3 | U7: ANDEAN POWER S.A.C. | V7: C.H. CARHUAC | W7: 487.5
B8: 01:00 | C8: 1155.3 | D8: 3338.9 | E8: 1578.7 | F8: 25.1 | J8: =DESPACHO_EJECUTADO!FA12+DESPACHO_EJECUTADO!FB12 -> 66 | L8: 7.7 | M8: 10.6 | N8: 0 | O8: 377.1 | P8: =SUM(C8:O8) -> 6559.4 | U8: ASOCIACIÓN SANTA LUCIA DE CHACAS | V8: C.H. HUALLIN | W8: 71.7
B9: 01:30 | C9: 1169.1 | D9: 3366.8 | E9: 1529.3 | F9: 24.2 | J9: =DESPACHO_EJECUTADO!FA13+DESPACHO_EJECUTADO!FB13 -> 66.9 | L9: 7.5 | M9: 10.6 | N9: 0 | O9: 345.1 | P9: =SUM(C9:O9) -> 6519.5 | U9: ATRIA ENERGIA S.A.C. | V9: C.H. PURMACANA | W9: 4.35
B10: 02:00 | C10: 1162.1 | D10: 3367.7 | E10: 1509.6 | F10: 24.9 | J10: =DESPACHO_EJECUTADO!FA14+DESPACHO_EJECUTADO!FB14 -> 66 | L10: 6.5 | M10: 10.7 | N10: 0 | O10: 331.4 | P10: =SUM(C10:O10) -> 6478.9 | U10: CELEPSA | V10: C.H. EL PLATANAL | X10: 4829.15
B11: 02:30 | C11: 1177.2 | D11: 3398.1 | E11: 1380.5 | F11: 0 | J11: =DESPACHO_EJECUTADO!FA15+DESPACHO_EJECUTADO!FB15 -> 65.8 | L11: 6.9 | M11: 10.6 | N11: 0 | O11: 315.4 | P11: =SUM(C11:O11) -> 6354.5 | U11: CELEPSA RENOVABLES S.R.L. | V11: C.H. MARAÑON | W11: 373.4
B12: 03:00 | C12: 1144.8 | D12: 3270.7 | E12: 1470 | F12: 0 | J12: =DESPACHO_EJECUTADO!FA16+DESPACHO_EJECUTADO!FB16 -> 66.5 | L12: 7.5 | M12: 10.5 | N12: 0 | O12: 309.4 | P12: =SUM(C12:O12) -> 6279.4 | U12: CENTRALES SANTA ROSA S.A.C. | V12: C.H. SANTA ROSA I | W12: 23.65
B13: 03:30 | C13: 1142 | D13: 3207.8 | E13: 1633.4 | F13: 0 | J13: =DESPACHO_EJECUTADO!FA17+DESPACHO_EJECUTADO!FB17 -> 65.8 | L13: 7.1 | M13: 10.5 | N13: 0 | O13: 340.3 | P13: =SUM(C13:O13) -> 6406.9 | V13: C.H. SANTA ROSA II | W13: 37.25
B14: 04:00 | C14: 1131.4 | D14: 3107 | E14: 1635.4 | F14: 0 | J14: =DESPACHO_EJECUTADO!FA18+DESPACHO_EJECUTADO!FB18 -> 65.2 | L14: 7.4 | M14: 10.6 | N14: 0 | O14: 366 | P14: =SUM(C14:O14) -> 6323 | U14: CHINANGO S.A.C. | V14: C.H. CHIMAY | X14: 3415.65
B15: 04:30 | C15: 1118.7 | D15: 3249.5 | E15: 1464.9 | F15: 0 | J15: =DESPACHO_EJECUTADO!FA19+DESPACHO_EJECUTADO!FB19 -> 64.5 | L15: 7.4 | M15: 10.7 | N15: 0 | O15: 373.4 | P15: =SUM(C15:O15) -> 6289.1 | V15: C.H. YANANGO | W15: 1017.35
B16: 05:00 | C16: 1133.1 | D16: 3314 | E16: 1470 | F16: 0 | J16: =DESPACHO_EJECUTADO!FA20+DESPACHO_EJECUTADO!FB20 -> 65.2 | L16: 7.3 | M16: 10.6 | N16: 0 | O16: 396.4 | P16: =SUM(C16:O16) -> 6396.6 | U16: EGASA | V16: C.H. CHARCANI III | W16: 148.95
B17: 05:30 | C17: 1072.7 | D17: 3326.8 | E17: 1472.2 | F17: 0 | J17: =DESPACHO_EJECUTADO!FA21+DESPACHO_EJECUTADO!FB21 -> 65.4 | L17: 6.6 | M17: 10.6 | N17: 0 | O17: 351.2 | P17: =SUM(C17:O17) -> 6305.5 | V17: C.H. CHARCANI IV | X17: 166.45
B18: 06:00 | C18: 1069.3 | D18: 3309.2 | E18: 1635.9 | F18: 0 | J18: =DESPACHO_EJECUTADO!FA22+DESPACHO_EJECUTADO!FB22 -> 65.3 | L18: 7.7 | M18: 10.6 | N18: 9.6 | O18: 337.6 | P18: =SUM(C18:O18) -> 6445.2 | V18: C.H. CHARCANI V | X18: 3434.05
B19: 06:30 | C19: 1059.1 | D19: 3286.4 | E19: 1524.5 | F19: 0 | J19: =DESPACHO_EJECUTADO!FA23+DESPACHO_EJECUTADO!FB23 -> 65.6 | L19: 6.7 | M19: 10.6 | N19: 90.5 | O19: 286.6 | P19: =SUM(C19:O19) -> 6330 | V19: C.H. CHARCANI VI | X19: 97.55
B20: 07:00 | C20: 1065.4 | D20: 3245 | E20: 1482.1 | F20: 0 | J20: =DESPACHO_EJECUTADO!FA24+DESPACHO_EJECUTADO!FB24 -> 66 | L20: 6 | M20: 10.6 | N20: 230.8 | O20: 289 | P20: =SUM(C20:O20) -> 6394.9 | U20: EGEJUNIN | V20: C.H. HUASAHUASI I | W20: 475.6
B21: 07:30 | C21: 1064.3 | D21: 3302.6 | E21: 1503.2 | F21: 0 | J21: =DESPACHO_EJECUTADO!FA25+DESPACHO_EJECUTADO!FB25 -> 64.8 | L21: 7.4 | M21: 10.6 | N21: 345.7 | O21: 318.8 | P21: =SUM(C21:O21) -> 6617.4 | V21: C.H. RUNATULLO II | W21: 480.25
B22: 08:00 | C22: 1060 | D22: 3245.2 | E22: 1627.7 | F22: 0 | J22: =DESPACHO_EJECUTADO!FA26+DESPACHO_EJECUTADO!FB26 -> 65.8 | L22: 7.3 | M22: 10.6 | N22: 397.1 | O22: 368.2 | P22: =SUM(C22:O22) -> 6781.9 | V22: C.H. RUNATULLO III | W22: 486.5
B23: 08:30 | C23: 1055.2 | D23: 3319 | E23: 1839.6 | F23: 0 | J23: =DESPACHO_EJECUTADO!FA27+DESPACHO_EJECUTADO!FB27 -> 65.5 | L23: 7.4 | M23: 10.6 | N23: 417.6 | O23: 421.5 | P23: =SUM(C23:O23) -> 7136.4 | V23: C.H. SANTA CRUZ I | W23: 308.4
B24: 09:00 | C24: 1055 | D24: 3285.8 | E24: 1944.6 | F24: 0 | J24: =DESPACHO_EJECUTADO!FA28+DESPACHO_EJECUTADO!FB28 -> 65.4 | L24: 6.1 | M24: 10.5 | N24: 425.5 | O24: 494.8 | P24: =SUM(C24:O24) -> 7287.7 | U24: EGEMSA | V24: C.H. MACHUPICCHU | W24: 3952.4
B25: 09:30 | C25: 1055.8 | D25: 3255.4 | E25: 2098.6 | F25: 0 | J25: =DESPACHO_EJECUTADO!FA29+DESPACHO_EJECUTADO!FB29 -> 65.5 | L25: 7.4 | M25: 10.5 | N25: 433.8 | O25: 531.6 | P25: =SUM(C25:O25) -> 7458.6 | U25: EGESUR | V25: C.H. ARICOTA I | X25: 182.6
B26: 10:00 | C26: 1064.9 | D26: 3328.2 | E26: 2117 | F26: 0 | J26: =DESPACHO_EJECUTADO!FA30+DESPACHO_EJECUTADO!FB30 -> 65.5 | L26: 7.3 | M26: 10.4 | N26: 439.2 | O26: 548.4 | P26: =SUM(C26:O26) -> 7580.9 | V26: C.H. ARICOTA II | X26: 70.7
B27: 10:30 | C27: 1045.4 | D27: 3282.7 | E27: 2173.7 | F27: 0 | J27: =DESPACHO_EJECUTADO!FA31+DESPACHO_EJECUTADO!FB31 -> 67.9 | L27: 10.6 | M27: 10.4 | N27: 443.5 | O27: 559.5 | P27: =SUM(C27:O27) -> 7593.7 | U27: ELECTRICA YANAPAMPA SAC | V27: C.H. YANAPAMPA | W27: 66.85
B28: 11:00 | C28: 1055.5 | D28: 3335.4 | E28: 2272.9 | F28: 0 | J28: =DESPACHO_EJECUTADO!FA32+DESPACHO_EJECUTADO!FB32 -> 65.8 | L28: 11.7 | M28: 10.4 | N28: 449.8 | O28: 581.3 | P28: =SUM(C28:O28) -> 7782.8 | U28: ELECTROPERU | V28: C.H. MANTARO | X28: 15592.6
B29: 11:30 | C29: 1049 | D29: 3328.3 | E29: 2281.9 | F29: 0 | J29: =DESPACHO_EJECUTADO!FA33+DESPACHO_EJECUTADO!FB33 -> 66.2 | L29: 12 | M29: 10.3 | N29: 453.4 | O29: 602.4 | P29: =SUM(C29:O29) -> 7803.5 | V29: C.H. RESTITUCION | W29: 5227.6
B30: 12:00 | C30: 1044.8 | D30: 3287.3 | E30: 2218.9 | F30: 0 | J30: =DESPACHO_EJECUTADO!FA34+DESPACHO_EJECUTADO!FB34 -> 67.2 | L30: 16.8 | M30: 10.3 | N30: 455.8 | O30: 649.5 | P30: =SUM(C30:O30) -> 7750.6 | U30: EMPRESA DE GENERACION ELECTRICA CANCHAYLLO SAC | V30: C.H. CANCHAYLLO | W30: 122.25
B31: 12:30 | C31: 1041.2 | D31: 3223.6 | E31: 2256.4 | F31: 0 | J31: =DESPACHO_EJECUTADO!FA35+DESPACHO_EJECUTADO!FB35 -> 65.9 | L31: 16.8 | M31: 10.1 | N31: 450 | O31: 694.9 | P31: =SUM(C31:O31) -> 7758.9 | U31: EMPRESA DE GENERACION ELECTRICA RIO BAÑOS S.A.C. | V31: C.H. RUCUY | W31: 479.35
B32: 13:00 | C32: 1050.7 | D32: 3248.4 | E32: 2135 | F32: 0 | J32: =DESPACHO_EJECUTADO!FA36+DESPACHO_EJECUTADO!FB36 -> 65.8 | L32: 16.6 | M32: 10.1 | N32: 455.5 | O32: 719.1 | P32: =SUM(C32:O32) -> 7701.2 | U32: EMPRESA DE GENERACION ELECTRICA SANTA ANA S.A.C. | V32: C.H. RENOVANDES H1 | W32: 485.7
B33: 13:30 | C33: 1051.4 | D33: 3292.1 | E33: 1983.4 | F33: 0 | J33: =DESPACHO_EJECUTADO!FA37+DESPACHO_EJECUTADO!FB37 -> 66.3 | L33: 16.9 | M33: 10.1 | N33: 453.3 | O33: 723.3 | P33: =SUM(C33:O33) -> 7596.8 | U33: EMPRESA DE GENERACION HUALLAGA | V33: C.H. CHAGLLA | X33: 10924.9
B34: 14:00 | C34: 1051 | D34: 3260.4 | E34: 1944.9 | F34: 0 | J34: =DESPACHO_EJECUTADO!FA38+DESPACHO_EJECUTADO!FB38 -> 65.1 | L34: 16.8 | M34: 10.1 | N34: 449.1 | O34: 746 | P34: =SUM(C34:O34) -> 7543.4 | V34: P.C.H. CHAGLLA | W34: 98.3
B35: 14:30 | C35: 1041.7 | D35: 3303.8 | E35: 1866.2 | F35: 0 | J35: =DESPACHO_EJECUTADO!FA39+DESPACHO_EJECUTADO!FB39 -> 65.6 | L35: 16.9 | M35: 10.1 | N35: 443.2 | O35: 757.8 | P35: =SUM(C35:O35) -> 7505.3 | U35: EMPRESA DE GENERACION HUANZA | V35: C.H. HUANZA | X35: 2275.7
B36: 15:00 | C36: 1016.6 | D36: 3238 | E36: 2043.8 | F36: 0 | J36: =DESPACHO_EJECUTADO!FA40+DESPACHO_EJECUTADO!FB40 -> 65.8 | L36: 15.6 | M36: 10.1 | N36: 434.9 | O36: 755.5 | P36: =SUM(C36:O36) -> 7580.3 | U36: EMPRESA ELECTRICA AGUA AZUL | V36: C.H. POTRERO | W36: 476.05
B37: 15:30 | C37: 1052.3 | D37: 3151.6 | E37: 2030.5 | F37: 0 | J37: =DESPACHO_EJECUTADO!FA41+DESPACHO_EJECUTADO!FB41 -> 66.1 | L37: 16.3 | M37: 10.1 | N37: 420.2 | O37: 769.5 | P37: =SUM(C37:O37) -> 7516.6 | U37: EMPRESA ELECTRICA RIO DOBLE | V37: C.H. LAS PIZARRAS | W37: 447.7
B38: 16:00 | C38: 1054.4 | D38: 3119.6 | E38: 1989.9 | F38: 0 | J38: =DESPACHO_EJECUTADO!FA42+DESPACHO_EJECUTADO!FB42 -> 65.8 | L38: 15 | M38: 10.1 | N38: 389.7 | O38: 766 | P38: =SUM(C38:O38) -> 7410.5 | U38: ENGIE | V38: C.H. YUNCAN | X38: 2087.7
B39: 16:30 | C39: 1064.6 | D39: 3308.5 | E39: 1791.4 | F39: 0 | J39: =DESPACHO_EJECUTADO!FA43+DESPACHO_EJECUTADO!FB43 -> 65.9 | L39: 16.5 | M39: 10.1 | N39: 267.5 | O39: 784.4 | P39: =SUM(C39:O39) -> 7308.9 | U39: GENERACIÓN ANDINA S.A.C. | V39: C.H. 8 DE AGOSTO | W39: 374.25
B40: 17:00 | C40: 1053.5 | D40: 3244.1 | E40: 1793.8 | F40: 0 | J40: =DESPACHO_EJECUTADO!FA44+DESPACHO_EJECUTADO!FB44 -> 66 | L40: 16.4 | M40: 10.5 | N40: 191.4 | O40: 785.9 | P40: =SUM(C40:O40) -> 7161.6 | V40: C.H. EL CARMEN | W40: 201.6
B41: 17:30 | C41: 1066.2 | D41: 3328.6 | E41: 1830.9 | F41: 0 | J41: =DESPACHO_EJECUTADO!FA45+DESPACHO_EJECUTADO!FB45 -> 66.4 | L41: 14.8 | M41: 10.6 | N41: 56.8 | O41: 789.2 | P41: =SUM(C41:O41) -> 7163.5 | U41: GENERADORA DE ENERGÍA DEL PERÚ | V41: C.H. ÁNGEL I | W41: 234.75
B42: 18:00 | C42: 1083.3 | D42: 3382.8 | E42: 1847.9 | F42: 0 | J42: =DESPACHO_EJECUTADO!FA46+DESPACHO_EJECUTADO!FB46 -> 66.3 | L42: 16.7 | M42: 10.6 | N42: 1.4 | O42: 785.4 | P42: =SUM(C42:O42) -> 7194.4 | V42: C.H. ÁNGEL II | W42: 214.7
B43: 18:30 | C43: 1114.3 | D43: 3349.8 | E43: 2120.9 | F43: 0 | J43: =DESPACHO_EJECUTADO!FA47+DESPACHO_EJECUTADO!FB47 -> 66.4 | L43: 16.8 | M43: 10.6 | N43: 0 | O43: 772.6 | P43: =SUM(C43:O43) -> 7451.4 | V43: C.H. ÁNGEL III | W43: 158.7
B44: 19:00 | C44: 1143.4 | D44: 3272 | E44: 2309 | F44: 0 | J44: =DESPACHO_EJECUTADO!FA48+DESPACHO_EJECUTADO!FB48 -> 66.3 | L44: 31.1 | M44: 10.7 | N44: 0 | O44: 745.6 | P44: =SUM(C44:O44) -> 7578.1 | V44: C.H. LA JOYA | W44: 141.65
B45: 19:30 | C45: 1151.3 | D45: 3361.2 | E45: 2262.6 | F45: 0 | J45: =DESPACHO_EJECUTADO!FA49+DESPACHO_EJECUTADO!FB49 -> 66.1 | L45: 30.2 | M45: 10.6 | N45: 0 | O45: 738.7 | P45: =SUM(C45:O45) -> 7620.7 | U45: HIDROCAÑETE S.A. | V45: C.H. IMPERIAL | W45: 71.8
B46: 20:00 | C46: 1160.2 | D46: 3380.9 | E46: 2269.2 | F46: 0 | J46: =DESPACHO_EJECUTADO!FA50+DESPACHO_EJECUTADO!FB50 -> 66.7 | L46: 30.4 | M46: 10.6 | N46: 0 | O46: 695.6 | P46: =SUM(C46:O46) -> 7613.6 | U46: HIDROELECTRICA HUANCHOR S.A.C. | V46: C.H. HUANCHOR | W46: 442.65
B47: 20:30 | C47: 1156.5 | D47: 3372.7 | E47: 2265.9 | F47: 0 | J47: =DESPACHO_EJECUTADO!FA51+DESPACHO_EJECUTADO!FB51 -> 66.4 | L47: 31.1 | M47: 10.6 | N47: 0 | O47: 662.9 | P47: =SUM(C47:O47) -> 7566.1 | U47: HUAURA POWER GROUP S.A. | V47: C.H. YARUCAYA | W47: 444
B48: 21:00 | C48: 1159.4 | D48: 3286.3 | E48: 2255.8 | F48: 0 | J48: =DESPACHO_EJECUTADO!FA52+DESPACHO_EJECUTADO!FB52 -> 66.6 | L48: 30.5 | M48: 10.6 | N48: 0 | O48: 666.7 | P48: =SUM(C48:O48) -> 7475.9 | U48: INLAND ENERGY SAC | V48: C.H. SANTA TERESA | W48: 2158.9
B49: 21:30 | C49: 1172 | D49: 3250.2 | E49: 2264.1 | F49: 0 | J49: =DESPACHO_EJECUTADO!FA53+DESPACHO_EJECUTADO!FB53 -> 66.1 | L49: 32 | M49: 10.6 | N49: 0 | O49: 617.8 | P49: =SUM(C49:O49) -> 7412.8 | U49: INVERSIONES SHAQSHA S.A.C. | V49: C.H. PARIAC | W49: 50.3
B50: 22:00 | C50: 1171.4 | D50: 3243.2 | E50: 2263.3 | F50: 0 | J50: =DESPACHO_EJECUTADO!FA54+DESPACHO_EJECUTADO!FB54 -> 66.1 | L50: 31.9 | M50: 10.6 | N50: 0 | O50: 640.1 | P50: =SUM(C50:O50) -> 7426.6 | U50: KALLPA GENERACION S.A. | V50: C.H. CERRO DEL AGUILA | X50: 9053.65
B51: 22:30 | C51: 1176.2 | D51: 3297.7 | E51: 2137.4 | F51: 0 | J51: =DESPACHO_EJECUTADO!FA55+DESPACHO_EJECUTADO!FB55 -> 65.8 | L51: 31.4 | M51: 10.6 | N51: 0 | O51: 624 | P51: =SUM(C51:O51) -> 7343.1 | V51: M.C.H. CERRO DEL AGUILA | W51: 250.9
B52: 23:00 | C52: 1173.7 | D52: 3252.2 | E52: 2088.3 | F52: 0 | J52: =DESPACHO_EJECUTADO!FA56+DESPACHO_EJECUTADO!FB56 -> 65.9 | L52: 32.3 | M52: 10.6 | N52: 0 | O52: 566.7 | P52: =SUM(C52:O52) -> 7189.7 | U52: LA VIRGEN | V52: C.H. LA VIRGEN | X52: 1965.1
B53: 23:30 | C53: 1157.6 | D53: 3261.5 | E53: 1880.9 | F53: 0 | J53: =DESPACHO_EJECUTADO!FA57+DESPACHO_EJECUTADO!FB57 -> 65.7 | L53: 31.1 | M53: 10.6 | N53: 0 | O53: 530.4 | P53: =SUM(C53:O53) -> 6937.8 | U53: MAJA ENERGIA S.A.C. | V53: C.H. RONCADOR | W53: 43.55
B54: 00:00 | C54: 1167.6 | D54: 3078.6 | E54: 1989.2 | F54: 0 | J54: =DESPACHO_EJECUTADO!FA58+DESPACHO_EJECUTADO!FB58 -> 66.2 | L54: 30.3 | M54: 10.6 | N54: 0 | O54: 508.2 | P54: =SUM(C54:O54) -> 6850.7 | U54: ORAZUL ENERGY PERÚ | V54: C.H. CAÑA BRAVA | W54: 49.75
B55: TOTAL MWh | C55: =+SUM(C7:C54)/2 -> 26420.25 | D55: =+SUM(D7:D54)/2 -> 78814.15 | E55: =+SUM(E7:E54)/2 -> 45598.15 | F55: =+SUM(F7:F54)/2 -> 49.7 | G55: =+SUM(G7:G54)/2 -> 0 | H55: =+SUM(H7:H54)/2 -> 0 | I55: =+SUM(I7:I54)/2 -> 0 | J55: =+SUM(J7:J54)/2 -> 1582.5 | ... P55: =+SUM(P7:P54)/2 -> 170754.8 | V55: C.H. CAÑON DEL PATO | X55: 3482.5
B56: % | C56: =+C55/$P$55*100 -> 15.472625 | D56: =+D55/$P$55*100 -> 46.156331 | E56: =+E55/$P$55*100 -> 26.703876 | F56: =+F55/$P$55*100 -> 0.029106063 | G56: =+G55/$P$55*100 -> 0 | H56: =+H55/$P$55*100 -> 0 | I56: =+I55/$P$55*100 -> 0 | J56: =+J55/$P$55*100 -> 0.92676751 | ... P56: =+P55/$P$55*100 -> 100 | V56: C.H. CARHUAQUERO | X56: 2085.6
V57: C.H. CARHUAQUERO IV | W57: 237.65
U58: ORYGEN PERU S.A.A. | V58: C.H. CALLAHUANCA | X58: 1898
V59: C.H. HER 1 | W59: 14.4
V60: C.H. HUAMPANI | W60: 722.95
V61: C.H. HUINCO | X61: 6063.85
V62: C.H. MATUCANA | X62: 3078.5
V63: C.H. MOYOPAMPA | W63: 1530.65
U64: SAN GABAN | V64: C.H. SAN GABAN II | X64: 1978.7
V65: MCH TUPURI | W65: 13.4
U66: SINERSA | V66: C.H. CHANCAY | W66: 479.5
V67: C.H. POECHOS II | W67: 223.05
U68: STATKRAFT S.A | V68: C.H. ARCATA | W68: 96
V69: C.H. CAHUA | W69: 397.6
V70: C.H. CHEVES | X70: 4106.95
V71: C.H. GALLITO CIEGO | X71: 935.1
V72: C.H. MALPASO | X72: 1089.15
V73: C.H. YAUPI | W73: 2596.45
U74: TOTAL MWh | W74: 26420.25 | X74: 78814.15

Sheet GENERACION RER
B3: sábado, 15 de Marzo del 2025
B5: GENERACIÓN ELÉCTRICA DE LAS CENTRALES RER (MW)
B6: HORA | C6: AGRO INDUSTRIAL PARAMONGA S.A. | D6: AGROAURORA S.A.C. | E6: AGROINDUSTRIAS SAN JACINTO S.A.A. | F6: ANDEAN POWER S.A.C. | G6: ASOCIACIÓN SANTA LUCIA DE CHACAS | H6: ATRIA ENERGIA S.A.C. | I6: BIOENERGIA DEL CHIRA S.A. | J6: COLCA SOLAR S.A.C. | K6: EGEJUNIN | P6: ELECTRICA YANAPAMPA SAC | Q6: EMPRESA DE GENERACION ELECTRICA CANCHAYLLO SAC | R6: EMPRESA DE GENERACION ELECTRICA RIO BAÑOS S.A.C. | S6: EMPRESA DE GENERACION ELECTRICA SANTA ANA S.A.C. | T6: EMPRESA ELECTRICA AGUA AZUL | U6: EMPRESA ELECTRICA RIO DOBLE | V6: ENERGÍA EÓLICA S.A. | X6: ENERGIA RENOVABLE DEL SUR S.A. | Y6: ENGIE | AD6: GENERACIÓN ANDINA S.A.C. | AF6: GENERADORA DE ENERGÍA DEL PERÚ | AJ6: GR CORTARRAMA SOCIEDAD ANONIMA CERRADA | AK6: GR PAINO SOCIEDAD ANONIMA CERRADA | AL6: GR TARUCA SOCIEDAD ANONIMA CERRADA | AM6: HIDROCAÑETE S.A. | AN6: HUAURA POWER GROUP S.A. | AO6: HYDRO PATAPO S.A.C. | AP6: KONDU SAC | AQ6: MAJA ENERGIA S.A.C. | AR6: MAJES ARCUS S.A.C. | AS6: MOQUEGUA FV S.A.C. | AT6: ORAZUL ENERGY PERÚ | AV6: ORYGEN PERU S.A.A. | BA6: PANAMERICANA SOLAR SAC. | BB6: PARQUE EOLICO MARCONA S.A.C. | BC6: PARQUE EOLICO TRES HERMANAS S.A.C. | BD6: PERUANA DE INVERSIONES EN ENERGIAS RENOVABLES S.A. | BE6: PETRAMAS | BI6: REPARTICIÓN ARCUS S.A.C. | BJ6: SAN GABAN | BK6: SDF ENERGIA SAC | BL6: SINERSA | BN6: TACNA SOLAR SAC. | BO6: TOTAL RER
C7: C.T. PARAMONGA | D7: C.T. MAPLE | E7: C.T SAN JACINTO | F7: C.H. CARHUAC | G7: C.H. HUALLIN | H7: C.H. PURMACANA | I7: C.T. CAÑA BRAVA | K7: C.H. HUASAHUASI I | L7: C.H. HUASAHUASI II | M7: C.H. RUNATULLO II | N7: C.H. RUNATULLO III | O7: C.H. STA CRUZ I y II | P7: C.H. YANAPAMPA | Q7: C.H. CANCHAYLLO | R7: C.H. RUCUY | S7: C.H. RENOVANDES H1 | T7: C.H. POTRERO | U7: C.H. LAS PIZARRAS | AD7: C.H. 8 DE AGOSTO | AE7: C.H. EL CARMEN | AF7: C.H. ANGEL I | AG7: C.H. ANGEL II | AH7: C.H. ANGEL III | AI7: C.H. LA JOYA | AM7: C.H. NUEVAIMPERIAL | AN7: C.H. YARUCAYA | AO7: MCH PATAPO | AQ7: C.H. RONCADOR | AT7: C.H. CANA BRAVA | AU7: C.H. CARHUAQUERO4 | AZ7: C.H. HER 1 | BD7: C.H. MANTA | BE7: C.T. HUAYCOLORO | BF7: C.T. LA GRINGA V | BG7: CTB CALLAO | BH7: CTB. DONA CATALINA | BJ7: C.H. TUPURI | BK7: C.T. OQUENDO | BL7: C.H. CHANCAY | BM7: C.H. POECHOS2 | BO7: MW
B8: 0:30 | E8: 7 | F8: 20.3 | G8: 3 | H8: 0.3 | K8: 19.9 | M8: 20.2 | N8: 20.2 | O8: 12.7 | P8: 3.2 | Q8: 4.8 | R8: 19.9 | S8: 20.1 | T8: 20 | U8: 18.3 | V8: 7.8 | W8: 25.3 | X8: 80.6 | Y8: 21 | Z8: 52.9 | AB8: 1.1 | AC8: 0.4 | AD8: 21 | AE8: 8.4 | AF8: 20.4 | AG8: 20.4 | AH8: 20 | AI8: 4 | AK8: 2.3 | AL8: 2.6 | AN8: 18.5 | AQ8: 1.8 | AU8: 9.8 | AV8: 51.9 | AX8: 60 | AZ8: 0.6 | BB8: 23.3 | BC8: 53.8 | BE8: 4.8 | BF8: 1 | BG8: 2.4 | BH8: 2.4 | BJ8: 1.1 | BL8: 20 | BM8: 9.4 | BO8: 738.9
B9: 1:00 | E9: 7.7 | F9: 20.3 | G9: 3 | H9: 0.3 | K9: 19.9 | M9: 19.7 | N9: 20.2 | O9: 12.8 | P9: 3.3 | Q9: 4.8 | R9: 20 | S9: 19.9 | T9: 19.6 | U9: 18.3 | V9: 9.6 | W9: 23.7 | X9: 78.8 | Y9: 22.7 | Z9: 52.8 | AB9: 1.4 | AC9: 1 | AD9: 21 | AE9: 8.4 | AF9: 20.4 | AG9: 20.4 | AH9: 20 | AI9: 3.8 | AK9: 1.8 | AL9: 1.7 | AN9: 18.5 | AQ9: 1.8 | AU9: 9.9 | AV9: 48.7 | AX9: 55.3 | AZ9: 0.6 | BB9: 22.4 | BC9: 57.2 | BE9: 4.8 | BF9: 1 | BG9: 2.4 | BH9: 2.4 | BJ9: 1.1 | BL9: 20 | BM9: 9.2 | BO9: 732.6
B10: 1:30 | E10: 7.5 | F10: 20.3 | G10: 3 | H10: 0.3 | K10: 19.9 | M10: 19.8 | N10: 20.3 | O10: 12.9 | P10: 3.3 | Q10: 5.1 | R10: 20 | S10: 20.5 | T10: 19.4 | U10: 18.4 | V10: 10.5 | W10: 27.2 | X10: 81.7 | Y10: 16.7 | Z10: 44.1 | AB10: 1.7 | AC10: 1.1 | AD10: 21 | AE10: 8.4 | AF10: 20.4 | AG10: 20.4 | AH10: 20 | AI10: 3.7 | AK10: 0.8 | AL10: 1 | AN10: 18.5 | AQ10: 1.8 | AU10: 9.9 | AV10: 41 | AX10: 44.2 | AZ10: 0.6 | BB10: 19.5 | BC10: 55.6 | BE10: 4.8 | BF10: 1 | BG10: 2.4 | BH10: 2.4 | BJ10: 1.1 | BL10: 20 | BM10: 9.2 | BO10: 701.4
B11: 2:00 | E11: 6.5 | F11: 20.3 | G11: 3 | H11: 0.3 | K11: 19.9 | M11: 19.5 | N11: 20.3 | O11: 12.9 | P11: 3.3 | Q11: 5.1 | R11: 20 | S11: 20.3 | T11: 20 | U11: 18.2 | V11: 9 | W11: 26.5 | X11: 81.2 | Y11: 16.7 | Z11: 45.8 | AB11: 1.8 | AC11: 1.6 | AD11: 21 | AE11: 8.4 | AF11: 20.4 | AG11: 20.4 | AH11: 20 | AI11: 4.1 | AK11: 0.9 | AL11: 0.6 | AN11: 18.5 | AQ11: 1.8 | AU11: 9.9 | AV11: 28.9 | AX11: 41.3 | AZ11: 0.6 | BB11: 21.2 | BC11: 55.9 | BE11: 4.8 | BF11: 1.1 | BG11: 2.4 | BH11: 2.4 | BJ11: 1.1 | BL11: 20 | BM11: 9.2 | BO11: 687.1
B12: 2:30 | E12: 6.9 | F12: 20.3 | G12: 3 | H12: 0.3 | K12: 19.9 | M12: 19.3 | N12: 20.3 | O12: 12.9 | P12: 3.3 | Q12: 5.1 | R12: 19.9 | S12: 20.8 | T12: 19.2 | U12: 18.4 | V12: 8.4 | W12: 25.8 | X12: 76.3 | Y12: 21.9 | Z12: 58.5 | AB12: 1.9 | AC12: 1.5 | AD12: 21 | AE12: 8.4 | AF12: 20.4 | AG12: 20.4 | AH12: 20 | AI12: 4.1 | AK12: 0.3 | AL12: 0.5 | AN12: 18.5 | AQ12: 1.8 | AU12: 9.9 | AV12: 23.6 | AX12: 29.4 | AZ12: 0.6 | BB12: 18 | BC12: 49.3 | BE12: 4.8 | BF12: 1 | BG12: 2.4 | BH12: 2.4 | BJ12: 1.1 | BL12: 19.9 | BM12: 9.2 | BO12: 670.9
B13: 3:00 | E13: 7.5 | F13: 20.3 | G13: 3 | H13: 0.3 | K13: 19.8 | M13: 19 | N13: 20.2 | O13: 12.8 | P13: 3.3 | Q13: 5 | R13: 19.9 | S13: 19.9 | T13: 19.3 | U13: 18.4 | V13: 12.5 | W13: 25.7 | X13: 67.9 | Y13: 28.9 | Z13: 63 | AB13: 2.3 | AC13: 1.5 | AD13: 21 | AE13: 8.4 | AF13: 20.4 | AG13: 20.4 | AH13: 20 | AI13: 3.9 | AK13: 0.3 | AL13: 0.2 | AN13: 18.5 | AQ13: 1.8 | AU13: 9.9 | AV13: 20.6 | AX13: 21.1 | AZ13: 0.6 | BB13: 19.5 | BC13: 45.9 | BE13: 4.8 | BF13: 1 | BG13: 2.3 | BH13: 2.4 | BJ13: 1.1 | BL13: 20 | BM13: 9.3 | BO13: 663.9
B14: 3:30 | E14: 7.1 | F14: 20.3 | G14: 3 | H14: 0.3 | K14: 19.8 | M14: 19 | N14: 20.3 | O14: 12.9 | P14: 3.2 | Q14: 5 | R14: 19.8 | S14: 20.3 | T14: 20 | U14: 18.5 | V14: 10 | W14: 17.5 | X14: 82.4 | Y14: 36.5 | Z14: 76.1 | AB14: 2.9 | AC14: 2.5 | AD14: 21 | AE14: 8.4 | AF14: 20.4 | AG14: 20.4 | AH14: 20 | AI14: 3.8 | AL14: 0.1 | AN14: 18.5 | AQ14: 1.8 | AU14: 9.9 | AV14: 21.7 | AX14: 21.3 | AZ14: 0.6 | BB14: 23.3 | BC14: 46 | BE14: 4.8 | BF14: 1 | BG14: 2.3 | BH14: 2.4 | BJ14: 1.2 | BL14: 19.9 | BM14: 9.1 | BO14: 695.3
B15: 4:00 | E15: 7.4 | F15: 20.3 | G15: 3 | H15: 0.3 | K15: 19.8 | M15: 19 | N15: 20.2 | O15: 12.7 | P15: 2.9 | Q15: 5.1 | R15: 19.8 | S15: 20.1 | T15: 19.6 | U15: 18.5 | V15: 8.7 | W15: 14.1 | X15: 98.2 | Y15: 36.8 | Z15: 79 | AB15: 3.7 | AC15: 2.6 | AD15: 21 | AE15: 8.4 | AF15: 20.4 | AG15: 20.4 | AH15: 20 | AI15: 4.2 | AK15: 0.4 | AL15: 0.6 | AN15: 18.5 | AQ15: 1.8 | AU15: 9.9 | AV15: 21.8 | AX15: 18 | AZ15: 0.6 | BB15: 26.9 | BC15: 55.2 | BE15: 4.8 | BF15: 1 | BG15: 2.4 | BH15: 2.4 | BJ15: 1.2 | BL15: 19.8 | BM15: 9.2 | BO15: 720.7
B16: 4:30 | E16: 7.4 | F16: 20.3 | G16: 3 | H16: 0.3 | K16: 19.9 | M16: 19.1 | N16: 20.2 | O16: 12.7 | P16: 2.9 | Q16: 5.1 | R16: 20 | S16: 20.2 | T16: 20 | U16: 18.5 | V16: 10.1 | W16: 14 | X16: 97.4 | Y16: 37.3 | Z16: 83.8 | AB16: 2.7 | AC16: 3.3 | AD16: 21 | AE16: 8.4 | AF16: 20.4 | AG16: 20.4 | AH16: 20 | AI16: 4.6 | AK16: 0.4 | AL16: 0.8 | AM16: 1.5 | AN16: 18.5 | AQ16: 1.8 | AU16: 9.9 | AV16: 22.4 | AX16: 20.1 | AZ16: 0.6 | BB16: 27.3 | BC16: 53.8 | BE16: 4.8 | BF16: 1.1 | BG16: 2.4 | BH16: 2.4 | BJ16: 1.2 | BL16: 20 | BM16: 9.2 | BO16: 731.2
B17: 5:00 | E17: 7.3 | F17: 20.3 | G17: 3 | H17: 0.3 | K17: 19.9 | M17: 19.6 | N17: 20.3 | O17: 12.7 | P17: 3 | Q17: 5 | R17: 20 | S17: 20.6 | T17: 20 | U17: 18.5 | V17: 13.5 | W17: 13.5 | X17: 106.4 | Y17: 42.6 | Z17: 89.4 | AB17: 2.1 | AC17: 0.8 | AD17: 21 | AE17: 8.4 | AF17: 20.4 | AG17: 20.4 | AH17: 20 | AI17: 4.8 | AK17: 1.2 | AL17: 1.3 | AM17: 3.9 | AN17: 18.5 | AQ17: 1.8 | AU17: 9.9 | AV17: 21 | AX17: 21.2 | AZ17: 0.6 | BB17: 27 | BC17: 56.4 | BE17: 4.8 | BF17: 1 | BG17: 2.4 | BH17: 2.4 | BJ17: 1.2 | BL17: 20 | BM17: 9.2 | BO17: 757.6
B18: 5:30 | E18: 6.6 | F18: 20.3 | G18: 2.9 | H18: 0.3 | K18: 19.8 | M18: 19.5 | N18: 20.2 | O18: 12.8 | P18: 3.2 | Q18: 5 | R18: 20 | S18: 20.2 | T18: 20 | U18: 18.5 | V18: 14.8 | W18: 15.3 | X18: 95.8 | Y18: 29.8 | Z18: 71.1 | AB18: 1.3 | AC18: 0.9 | AD18: 21 | AE18: 8.4 | AF18: 0.3 | AH18: 7.4 | AI18: 4.8 | AK18: 0.7 | AL18: 0.8 | AM18: 3.9 | AN18: 18.5 | AQ18: 1.8 | AU18: 9.9 | AV18: 20.4 | AX18: 19.9 | AZ18: 0.6 | BB18: 27.3 | BC18: 53.1 | BE18: 4.8 | BF18: 1 | BG18: 2.4 | BH18: 2.4 | BJ18: 1.2 | BL18: 20 | BM18: 9.2 | BO18: 658.1
B19: 6:00 | E19: 7.7 | F19: 20.3 | G19: 3 | H19: 0.3 | K19: 19.8 | M19: 20 | N19: 20.3 | O19: 12.9 | P19: 3.2 | Q19: 5 | R19: 20 | S19: 20.5 | T19: 19.4 | U19: 18.5 | V19: 13.6 | W19: 15.1 | X19: 84.8 | Y19: 33.5 | Z19: 65.2 | AA19: 0.3 | AB19: 2.2 | AC19: 1.4 | AD19: 21 | AE19: 8.4 | AI19: 4.7 | AJ19: 0.1 | AK19: 1.2 | AL19: 0.7 | AM19: 3.9 | AN19: 18.5 | AQ19: 1.8 | AS19: 1.9 | AU19: 9.9 | AV19: 21 | AW19: 1.6 | AX19: 19 | AY19: 1.4 | AZ19: 0.6 | BA19: 2 | BB19: 26.3 | BC19: 53.6 | BE19: 4.8 | BF19: 1 | BG19: 2.4 | BH19: 2.4 | BJ19: 0.4 | BL19: 20 | BM19: 9.3 | BN19: 2.3 | BO19: 647.2
B20: 6:30 | E20: 6.7 | F20: 20.3 | G20: 3 | H20: 0.3 | K20: 19.8 | M20: 19.8 | N20: 20.2 | O20: 12.9 | P20: 3.2 | Q20: 5.1 | R20: 20 | S20: 20.2 | T20: 20 | U20: 18.5 | V20: 11.7 | W20: 14.2 | X20: 72.5 | Y20: 22.5 | Z20: 45.6 | AA20: 5.8 | AB20: 0.9 | AC20: 0.2 | AD20: 21 | AE20: 8.4 | AI20: 4.6 | AJ20: 10.5 | AK20: 0.1 | AL20: 0.2 | AM20: 3.9 | AN20: 18.5 | AQ20: 1.8 | AR20: 0.7 | AS20: 8.4 | AU20: 9.9 | AV20: 15.9 | AW20: 26.1 | AX20: 15.8 | AY20: 20.4 | AZ20: 0.6 | BA20: 9.1 | BB20: 27.7 | BC20: 59.3 | BE20: 4.8 | BF20: 1 | BG20: 2.4 | BH20: 2.4 | BI20: 0.6 | BL20: 20 | BM20: 9.2 | BN20: 8.9 | BO20: 675.6
B21: 7:00 | E21: 6 | F21: 20.3 | G21: 3 | H21: 0.3 | J21: 0.1 | K21: 19.8 | M21: 20 | N21: 20.3 | O21: 13 | P21: 3.2 | Q21: 5 | R21: 20 | S21: 20.3 | T21: 19.1 | U21: 18.5 | V21: 11.5 | W21: 8.9 | X21: 80.5 | Y21: 23.8 | Z21: 46.2 | AA21: 16.4 | AB21: 2 | AC21: 1.1 | AD21: 21 | AE21: 8.4 | AI21: 4.7 | AJ21: 34.5 | AK21: 0.6 | AL21: 0.7 | AM21: 3.9 | AN21: 18.5 | AQ21: 1.8 | AR21: 2.5 | AS21: 12.6 | AU21: 9.9 | AV21: 12.8 | AW21: 74.5 | AX21: 14.1 | AY21: 58.6 | AZ21: 0.6 | BA21: 15.1 | BB21: 26.9 | BC21: 59.9 | BE21: 4.8 | BF21: 1 | BG21: 2.4 | BH21: 2.4 | BI21: 2.5 | BL21: 20 | BM21: 9.3 | BN21: 14 | BO21: 817.3
B22: 7:30 | E22: 7.4 | F22: 20.3 | G22: 3 | H22: 0.3 | J22: 0.2 | K22: 19.8 | M22: 20.1 | N22: 20.3 | O22: 12.9 | P22: 3.2 | Q22: 5 | R22: 20 | S22: 20.5 | T22: 20 | U22: 18.5 | V22: 11.6 | W22: 5.5 | X22: 73.6 | Y22: 27.5 | Z22: 68.2 | AA22: 27.3 | AB22: 1.7 | AC22: 1.7 | AD22: 20.9 | AE22: 8.4 | AI22: 4.7 | AJ22: 56.8 | AK22: 0.6 | AL22: 0.6 | AM22: 3.8 | AN22: 18.5 | AQ22: 1.8 | AR22: 4.9 | AS22: 13.6 | AU22: 9.9 | AV22: 19.8 | AW22: 117.2 | AX22: 18.8 | AY22: 88.4 | AZ22: 0.6 | BA22: 16.5 | BB22: 26.3 | BC22: 62.9 | BE22: 4.8 | BF22: 1 | BG22: 2.4 | BH22: 2.4 | BI22: 5.1 | BL22: 20 | BM22: 9.2 | BN22: 15.7 | BO22: 964.2
B23: 8:00 | E23: 7.3 | F23: 20.3 | G23: 3 | H23: 0.3 | J23: 0.3 | K23: 19.8 | M23: 20 | N23: 20.2 | O23: 12.9 | P23: 3.2 | Q23: 5 | R23: 20 | S23: 20.3 | T23: 20 | U23: 18.5 | V23: 12.6 | W23: 7.2 | X23: 77.3 | Y23: 42.2 | Z23: 66.8 | AA23: 33.1 | AB23: 3.3 | AC23: 3.1 | AD23: 20.9 | AE23: 8.4 | AI23: 4.7 | AJ23: 67.8 | AK23: 0.2 | AM23: 3.7 | AN23: 18.5 | AP23: 0.1 | AQ23: 1.8 | AR23: 7.5 | AS23: 14.1 | AU23: 9.8 | AV23: 30.3 | AW23: 135.1 | AX23: 28.1 | AY23: 97.2 | AZ23: 0.6 | BA23: 17.3 | BB23: 23.5 | BC23: 73.6 | BE23: 4.8 | BF23: 1 | BG23: 2.4 | BH23: 2.4 | BI23: 7.9 | BL23: 20 | BM23: 9.3 | BN23: 16.7 | BO23: 1064.4
B24: 8:30 | E24: 7.4 | F24: 20.3 | G24: 3 | H24: 0.3 | J24: 0.4 | K24: 19.8 | M24: 20.1 | N24: 20.3 | O24: 12.9 | P24: 3 | Q24: 5 | R24: 20 | S24: 20.6 | T24: 20 | U24: 18.5 | V24: 16.8 | W24: 6.1 | X24: 78.9 | Y24: 62.6 | Z24: 83.4 | AA24: 34.2 | AB24: 4.7 | AC24: 6 | AD24: 21 | AE24: 8.4 | AI24: 4.7 | AJ24: 71.9 | AK24: 0.2 | AM24: 3.6 | AN24: 18.5 | AP24: 0.2 | AQ24: 1.8 | AR24: 9.9 | AS24: 14.3 | AU24: 9.9 | AV24: 38.5 | AW24: 140.2 | AX24: 28.5 | AY24: 101.4 | AZ24: 0.6 | BA24: 17.8 | BB24: 21.9 | BC24: 73.9 | BE24: 4.8 | BF24: 1 | BG24: 2.4 | BH24: 2.4 | BI24: 10.2 | BL24: 20 | BM24: 9.4 | BN24: 17.1 | BO24: 1138.8
B25: 9:00 | E25: 6.1 | F25: 20.2 | G25: 3 | H25: 0.3 | J25: 0.7 | K25: 19.8 | M25: 19.9 | N25: 20.2 | O25: 12.8 | P25: 3.2 | Q25: 5.1 | R25: 20 | S25: 19.7 | T25: 19.4 | U25: 18.5 | V25: 9.6 | W25: 5.9 | X25: 95.9 | Y25: 79.2 | Z25: 92.7 | AA25: 33.1 | AB25: 7.7 | AC25: 7.9 | AD25: 21 | AE25: 8.4 | AI25: 4.8 | AJ25: 73.5 | AK25: 0.5 | AL25: 0.1 | AM25: 3.6 | AN25: 18.5 | AP25: 0.2 | AQ25: 1.8 | AR25: 11.9 | AS25: 14.5 | AU25: 9.9 | AV25: 50.9 | AW25: 141.4 | AX25: 48.6 | AY25: 102.6 | AZ25: 0.6 | BA25: 17.9 | BB25: 23.1 | BC25: 72.7 | BE25: 4.7 | BF25: 1 | BG25: 2.4 | BH25: 2.4 | BI25: 12.4 | BL25: 20 | BM25: 9.2 | BN25: 17.3 | BO25: 1216.8
B26: 9:30 | E26: 7.4 | F26: 20.3 | G26: 3 | H26: 0.3 | J26: 1 | K26: 19.8 | M26: 20.3 | N26: 20.3 | O26: 12.8 | P26: 3.2 | Q26: 5.1 | R26: 20 | S26: 20.4 | T26: 20 | U26: 18.6 | V26: 6 | W26: 5.8 | X26: 112.4 | Y26: 91.5 | Z26: 90.2 | AA26: 33.5 | AB26: 8.9 | AC26: 10 | AD26: 21 | AE26: 8.4 | AI26: 4.9 | AJ26: 74.3 | AM26: 3.6 | AN26: 18.5 | AP26: 0.2 | AQ26: 1.8 | AR26: 13.6 | AS26: 14.8 | AU26: 9.9 | AV26: 59.2 | AW26: 142.7 | AX26: 48.7 | AY26: 104 | AZ26: 0.6 | BA26: 18.1 | BB26: 24.7 | BC26: 74.2 | BE26: 4.7 | BF26: 1 | BG26: 2.4 | BH26: 2.4 | BI26: 14.3 | BL26: 20 | BM26: 9.4 | BN26: 17.3 | BO26: 1265.5
B27: 10:00 | E27: 7.3 | F27: 20.3 | G27: 3 | H27: 0.3 | J27: 1.1 | K27: 19.8 | M27: 20.3 | N27: 20.3 | O27: 12.8 | P27: 3.2 | Q27: 5.1 | R27: 20 | S27: 20.5 | T27: 20 | U27: 18.7 | V27: 5.9 | W27: 8.3 | X27: 116 | Y27: 91.9 | Z27: 89.1 | AA27: 33.9 | AB27: 8.5 | AC27: 11.1 | AD27: 19 | AE27: 8.4 | AI27: 4.5 | AJ27: 75 | AM27: 3.6 | AN27: 18.5 | AP27: 0.2 | AQ27: 1.8 | AR27: 15.1 | AS27: 14.8 | AU27: 9.9 | AV27: 59.4 | AW27: 143.1 | AX27: 50.6 | AY27: 104.8 | AZ27: 0.6 | BA27: 17.9 | BB27: 28.3 | BC27: 79.3 | BE27: 4.6 | BF27: 1 | BG27: 2.4 | BH27: 2.4 | BI27: 15.8 | BL27: 20 | BM27: 9.3 | BN27: 17.5 | BO27: 1285.2
B28: 10:30 | D28: 3.2 | E28: 7.4 | F28: 20.3 | G28: 3 | H28: 0.3 | J28: 0.9 | K28: 19.8 | M28: 20.2 | N28: 20.2 | O28: 12.8 | P28: 3.2 | Q28: 5.2 | R28: 20 | S28: 20 | T28: 20 | U28: 18.6 | V28: 3.3 | W28: 14.2 | X28: 116.5 | Y28: 91.6 | Z28: 88.6 | AA28: 34.5 | AB28: 8.4 | AC28: 11.6 | AD28: 10.5 | AE28: 8.4 | AI28: 7 | AJ28: 75.7 | AM28: 3.6 | AN28: 18.5 | AP28: 0.2 | AQ28: 1.8 | AR28: 16.3 | AS28: 14.8 | AU28: 10 | AV28: 56.6 | AW28: 143 | AX28: 60.5 | AY28: 105.2 | AZ28: 0.6 | BA28: 17 | BB28: 28.7 | BC28: 79.5 | BE28: 4.6 | BF28: 1 | BG28: 2.4 | BH28: 2.4 | BI28: 17.1 | BL28: 20 | BM28: 9.2 | BN28: 18.8 | BO28: 1297.2
B29: 11:00 | D29: 4.2 | E29: 7.5 | F29: 20.2 | G29: 3 | H29: 0.3 | J29: 1.2 | K29: 19.8 | M29: 20.3 | N29: 20.2 | O29: 12.8 | P29: 3.2 | Q29: 5.2 | R29: 20 | S29: 20.3 | T29: 20 | U29: 18.6 | V29: 1.9 | W29: 25.8 | X29: 109.6 | Y29: 91.3 | Z29: 88.4 | AA29: 34.4 | AB29: 8.4 | AC29: 11.6 | AD29: 10.5 | AE29: 8.4 | AI29: 7 | AJ29: 77.8 | AK29: 0.3 | AM29: 3.6 | AN29: 18.5 | AP29: 0.3 | AQ29: 1.8 | AR29: 17.5 | AS29: 14.8 | AU29: 10 | AV29: 67.1 | AW29: 144.5 | AX29: 68.1 | AY29: 105.8 | AZ29: 0.6 | BA29: 16.4 | BB29: 28.3 | BC29: 80.5 | BE29: 4.6 | BF29: 1 | BG29: 2.4 | BH29: 2.4 | BI29: 18 | BL29: 20 | BM29: 9.2 | BN29: 19.1 | BO29: 1326.7
B30: 11:30 | D30: 4.6 | E30: 7.4 | F30: 20.2 | G30: 3 | H30: 0.3 | J30: 1.3 | K30: 19.8 | M30: 20.3 | N30: 20.3 | O30: 12.8 | P30: 2.4 | Q30: 5.1 | R30: 20 | S30: 20.2 | T30: 19.6 | U30: 18.6 | V30: 1.3 | W30: 41.1 | X30: 108.2 | Y30: 91.9 | Z30: 88.7 | AA30: 34.6 | AB30: 8.4 | AC30: 11.8 | AD30: 10.5 | AE30: 8.4 | AI30: 7.5 | AJ30: 78.6 | AM30: 3.6 | AN30: 18.5 | AP30: 0.4 | AQ30: 1.8 | AR30: 18.1 | AS30: 14.6 | AU30: 10 | AV30: 71.9 | AW30: 144 | AX30: 73.6 | AY30: 107.4 | AZ30: 0.6 | BA30: 16.7 | BB30: 25.2 | BC30: 80.3 | BE30: 4.5 | BF30: 1 | BG30: 2.4 | BH30: 2.4 | BI30: 18.6 | BL30: 20 | BM30: 9.3 | BN30: 19.1 | BO30: 1350.9
B31: 12:00 | D31: 9.6 | E31: 7.2 | F31: 20.2 | G31: 3 | H31: 0.3 | J31: 1.3 | K31: 19.8 | M31: 20.4 | N31: 20.3 | O31: 12.9 | P31: 3.1 | Q31: 5.1 | R31: 20 | S31: 20.1 | T31: 20 | U31: 18.6 | V31: 3 | W31: 54.6 | X31: 111.9 | Y31: 92 | Z31: 88.6 | AA31: 34.8 | AB31: 8.5 | AC31: 11.6 | AD31: 10.5 | AE31: 8.4 | AI31: 7.6 | AJ31: 79.3 | AM31: 3.5 | AN31: 18.5 | AP31: 0.3 | AQ31: 1.8 | AR31: 18.3 | AS31: 14.8 | AU31: 9.9 | AV31: 82.4 | AW31: 144.9 | AX31: 89.9 | AY31: 107 | AZ31: 0.6 | BA31: 17.1 | BB31: 28 | BC31: 79 | BE31: 4.5 | BF31: 1 | BG31: 2.4 | BH31: 2.4 | BI31: 18.9 | BL31: 20 | BM31: 9.3 | BN31: 19.1 | BO31: 1406.3
B32: 12:30 | D32: 9.6 | E32: 7.2 | F32: 20.2 | G32: 3 | H32: 0.3 | J32: 0.4 | K32: 19.8 | M32: 20.2 | N32: 20.3 | O32: 12.8 | P32: 3.1 | Q32: 5.2 | R32: 20 | S32: 20.1 | T32: 20 | U32: 18.7 | V32: 8.1 | W32: 64.5 | X32: 111.6 | Y32: 92.1 | Z32: 89 | AA32: 34.9 | AB32: 8.6 | AC32: 11.9 | AD32: 10.5 | AE32: 8.4 | AI32: 7.8 | AJ32: 79.7 | AM32: 3.6 | AN32: 18.5 | AP32: 0.4 | AQ32: 1.8 | AR32: 18.4 | AS32: 14.8 | AT32: 3.5 | AU32: 9.9 | AV32: 95.3 | AW32: 137.1 | AX32: 107.6 | AY32: 107.8 | AZ32: 0.6 | BA32: 18.2 | BB32: 27 | BC32: 79.2 | BE32: 4.3 | BF32: 1 | BG32: 2.4 | BH32: 2.4 | BI32: 19.1 | BL32: 20 | BM32: 9.4 | BN32: 19.2 | BO32: 1449.5
B33: 13:00 | D33: 9.5 | E33: 7.1 | F33: 20.2 | G33: 3 | H33: 0.3 | J33: 0.2 | K33: 19.8 | M33: 20.2 | N33: 20.3 | O33: 12.8 | P33: 3 | Q33: 5.2 | R33: 20 | S33: 20.2 | T33: 19.6 | U33: 18.8 | V33: 9.9 | W33: 65.7 | X33: 102.9 | Y33: 91.9 | Z33: 89.3 | AA33: 34.9 | AB33: 8.5 | AC33: 11.7 | AD33: 10.5 | AE33: 8.4 | AI33: 8.2 | AJ33: 79.4 | AK33: 3.3 | AL33: 3.6 | AM33: 3.6 | AN33: 18.5 | AP33: 0.4 | AQ33: 1.8 | AR33: 18.3 | AS33: 14.7 | AT33: 2.9 | AU33: 9.8 | AV33: 104.4 | AW33: 144.9 | AX33: 122.4 | AY33: 106.8 | AZ33: 0.6 | BA33: 18.3 | BB33: 26.4 | BC33: 79.1 | BE33: 4.3 | BF33: 1 | BG33: 2.4 | BH33: 2.4 | BI33: 18.4 | BL33: 20 | BM33: 9.4 | BN33: 19.2 | BO33: 1478.4
B34: 13:30 | D34: 9.2 | E34: 7.7 | F34: 20.3 | G34: 3 | H34: 0.3 | J34: 0.1 | K34: 19.8 | M34: 20.3 | N34: 20.3 | O34: 12.8 | P34: 3.1 | Q34: 5.1 | R34: 20 | S34: 20.2 | T34: 20 | U34: 18.7 | V34: 11.7 | W34: 66.2 | X34: 102.9 | Y34: 91.8 | Z34: 88.5 | AA34: 34.5 | AB34: 8.6 | AC34: 11.6 | AD34: 10.5 | AE34: 8.4 | AI34: 3.4 | AJ34: 79.6 | AK34: 0.5 | AL34: 0.2 | AM34: 3.6 | AN34: 18.5 | AP34: 0.4 | AQ34: 1.8 | AR34: 17.7 | AS34: 14.4 | AT34: 3.3 | AU34: 10 | AV34: 121.4 | AW34: 145.2 | AX34: 120.4 | AY34: 106.1 | AZ34: 0.6 | BA34: 18.2 | BB34: 21.1 | BC34: 78.4 | BE34: 4.3 | BF34: 1 | BG34: 2.4 | BH34: 2.4 | BI34: 17.8 | BL34: 20 | BM34: 9.4 | BN34: 19.3 | BO34: 1477
B35: 14:00 | D35: 9.4 | E35: 7.4 | F35: 20.3 | G35: 3 | H35: 0.3 | J35: 0.1 | K35: 19.8 | M35: 20.2 | N35: 20.3 | O35: 12.8 | P35: 2.7 | Q35: 5.1 | R35: 20 | S35: 20.5 | T35: 20 | U35: 18.7 | V35: 13.3 | W35: 66.9 | X35: 100.2 | Y35: 91.2 | Z35: 88.9 | AA35: 34.8 | AB35: 9 | AC35: 11.7 | AD35: 10.5 | AE35: 8.4 | AI35: 3.3 | AJ35: 78 | AL35: 0.8 | AM35: 3.6 | AN35: 18.5 | AP35: 0.3 | AQ35: 1.9 | AR35: 16.5 | AS35: 14.8 | AT35: 3.3 | AU35: 9.9 | AV35: 132.1 | AW35: 144.7 | AX35: 128.1 | AY35: 106.1 | AZ35: 0.6 | BA35: 17.9 | BB35: 25.4 | BC35: 78.4 | BE35: 4.3 | BF35: 1 | BG35: 2.4 | BH35: 2.4 | BI35: 16.7 | BL35: 20 | BM35: 9.4 | BN35: 19.2 | BO35: 1495.1
B36: 14:30 | D36: 9.4 | E36: 7.5 | F36: 20.3 | G36: 3 | H36: 0.3 | J36: 0.2 | K36: 19.8 | M36: 20.2 | N36: 20.2 | O36: 12.8 | P36: 2.7 | Q36: 5.1 | R36: 20 | S36: 20.3 | T36: 20 | U36: 18.6 | V36: 16.4 | W36: 59.2 | X36: 109 | Y36: 92 | Z36: 88.8 | AA36: 34.7 | AB36: 8.9 | AC36: 11.6 | AD36: 10.5 | AE36: 8.4 | AI36: 7.1 | AJ36: 78 | AM36: 3.6 | AN36: 18.5 | AP36: 0.2 | AQ36: 1.8 | AR36: 15 | AS36: 14.8 | AT36: 3.3 | AU36: 9.8 | AV36: 139.1 | AW36: 143.3 | AX36: 126 | AY36: 104.8 | AZ36: 0.6 | BA36: 17.6 | BB36: 26.4 | BC36: 80.4 | BE36: 4.3 | BF36: 1 | BG36: 2.4 | BH36: 2.4 | BI36: 15.7 | BL36: 20 | BM36: 9.4 | BN36: 18.9 | BO36: 1504.3
B37: 15:00 | D37: 9.4 | E37: 6.2 | F37: 20.3 | G37: 3 | J37: 0.1 | K37: 19.8 | M37: 20.1 | N37: 20.2 | O37: 12.9 | P37: 2.7 | Q37: 5.2 | R37: 20.2 | S37: 19.8 | T37: 20 | U37: 18.7 | V37: 18.7 | W37: 51.5 | X37: 107.4 | Y37: 92 | Z37: 88.7 | AA37: 34.2 | AB37: 8.4 | AC37: 11.6 | AD37: 10.5 | AE37: 8.4 | AI37: 7.5 | AJ37: 75.9 | AM37: 3.6 | AN37: 18.5 | AP37: 0.1 | AQ37: 1.8 | AR37: 13.4 | AS37: 14.7 | AT37: 3.4 | AU37: 9.8 | AV37: 137.5 | AW37: 142 | AX37: 131.6 | AY37: 103.5 | AZ37: 0.6 | BA37: 17.5 | BB37: 26.4 | BC37: 81.7 | BE37: 4.3 | BF37: 1 | BG37: 2.4 | BH37: 2.4 | BI37: 15.1 | BL37: 20.2 | BM37: 9.4 | BN37: 18.4 | BO37: 1492.7
B38: 15:30 | D38: 9.4 | E38: 6.9 | F38: 20 | G38: 3 | J38: 0.2 | K38: 19.8 | M38: 20.2 | N38: 20.3 | O38: 12.8 | P38: 2.4 | Q38: 5.2 | R38: 19.8 | S38: 20.4 | T38: 20 | U38: 18.7 | V38: 21.2 | W38: 57.3 | X38: 112.4 | Y38: 92 | Z38: 88.7 | AA38: 32.7 | AB38: 8.5 | AC38: 11.7 | AD38: 10.5 | AE38: 8.4 | AI38: 7.9 | AJ38: 73.4 | AL38: 1.1 | AM38: 3.6 | AN38: 18.5 | AQ38: 1.8 | AR38: 11.1 | AS38: 14.2 | AT38: 3.1 | AU38: 9.9 | AV38: 135.4 | AW38: 139.5 | AX38: 132.5 | AY38: 101.5 | AZ38: 0.6 | BA38: 16.9 | BB38: 25 | BC38: 83.7 | BE38: 4.3 | BF38: 1 | BG38: 2.4 | BH38: 2.4 | BI38: 13.2 | BL38: 19.8 | BM38: 9.4 | BN38: 17.5 | BO38: 1492.2
B39: 16:00 | D39: 9.3 | E39: 5.7 | F39: 20.3 | G39: 3 | J39: 0.1 | K39: 19.8 | M39: 20.2 | N39: 20.3 | O39: 12.8 | P39: 1.7 | Q39: 5.1 | R39: 19.8 | S39: 20.2 | T39: 20 | U39: 19.4 | V39: 20.5 | W39: 54 | X39: 113.5 | Y39: 92 | Z39: 88.7 | AA39: 30.5 | AB39: 8.4 | AC39: 11.7 | AD39: 10.4 | AE39: 8.4 | AI39: 7.9 | AJ39: 67.2 | AK39: 0.8 | AL39: 1.1 | AM39: 3.6 | AN39: 18.5 | AQ39: 1.8 | AR39: 10.7 | AS39: 13.2 | AT39: 3.2 | AU39: 9.9 | AV39: 133.7 | AW39: 131.5 | AX39: 132.5 | AY39: 95.6 | AZ39: 0.6 | BA39: 15.8 | BB39: 25.1 | BC39: 84 | BE39: 4.3 | BF39: 1 | BG39: 2.4 | BH39: 2.4 | BI39: 9.1 | BL39: 19.8 | BM39: 9.3 | BN39: 16 | BO39: 1456.8
B40: 16:30 | D40: 9.3 | E40: 7.2 | F40: 20.3 | G40: 3 | J40: 0.1 | K40: 19.8 | M40: 20.2 | N40: 20.3 | O40: 12.8 | P40: 2.5 | Q40: 5.2 | R40: 20 | S40: 20.5 | T40: 20 | U40: 19 | V40: 23.1 | W40: 59.9 | X40: 113.5 | Y40: 92.3 | Z40: 89.9 | AA40: 13.3 | AB40: 8.6 | AC40: 10.7 | AD40: 10.4 | AE40: 8.4 | AI40: 8.1 | AJ40: 28.9 | AK40: 0.2 | AL40: 0.9 | AM40: 3.6 | AN40: 18.5 | AQ40: 1.8 | AR40: 6.8 | AS40: 11.3 | AT40: 5 | AU40: 9.9 | AV40: 143.2 | AW40: 98.4 | AX40: 132.5 | AY40: 77.8 | AZ40: 0.6 | BA40: 13.3 | BB40: 25.3 | BC40: 84.3 | BE40: 4.3 | BF40: 1 | BG40: 2.4 | BH40: 2.4 | BI40: 4.8 | BL40: 20 | BM40: 9.3 | BN40: 12.8 | BO40: 1357.7
B41: 17:00 | D41: 9.4 | E41: 7 | F41: 20.3 | G41: 2.9 | K41: 19.8 | M41: 20.2 | N41: 20.3 | O41: 12.8 | P41: 2.1 | Q41: 5.2 | R41: 20 | S41: 19.9 | T41: 20 | U41: 18.8 | V41: 14.3 | W41: 69.7 | X41: 111.5 | Y41: 92.3 | Z41: 88.6 | AA41: 14.5 | AB41: 8.9 | AC41: 10.6 | AD41: 10.4 | AE41: 8.4 | AI41: 8.1 | AJ41: 32.9 | AK41: 0.6 | AL41: 1.7 | AM41: 3.6 | AN41: 18.5 | AQ41: 1.9 | AR41: 4.4 | AS41: 5.8 | AT41: 5.2 | AU41: 9.9 | AV41: 145 | AW41: 63.8 | AX41: 132.5 | AY41: 56.2 | AZ41: 0.6 | BA41: 6.6 | BB41: 25.6 | BC41: 84.6 | BE41: 4.7 | BF41: 1 | BG41: 2.4 | BH41: 2.4 | BI41: 1.7 | BL41: 20 | BM41: 9.4 | BN41: 5.5 | BO41: 1282.5
B42: 17:30 | D42: 9.3 | E42: 5.5 | F42: 20.5 | G42: 2.9 | K42: 19.8 | M42: 20.3 | N42: 20.3 | O42: 13 | P42: 2.2 | Q42: 5.2 | R42: 20 | S42: 20.3 | T42: 20 | U42: 18.8 | V42: 14.6 | W42: 76.4 | X42: 111.5 | Y42: 91.7 | Z42: 88.7 | AA42: 3 | AB42: 7.4 | AC42: 10.8 | AD42: 10.4 | AE42: 8.4 | AI42: 8.1 | AJ42: 12.8 | AK42: 0.4 | AL42: 1.1 | AM42: 3.6 | AN42: 18.5 | AQ42: 1.9 | AR42: 1.7 | AS42: 0.9 | AT42: 5.2 | AU42: 10 | AV42: 146.7 | AW42: 18 | AX42: 129.4 | AY42: 18 | AZ42: 0.6 | BA42: 0.9 | BB42: 25.8 | BC42: 84.7 | BE42: 4.8 | BF42: 1 | BG42: 2.4 | BH42: 2.4 | BI42: 1 | BL42: 20 | BM42: 9.4 | BN42: 0.5 | BO42: 1150.8
B43: 18:00 | D43: 9.4 | E43: 7.3 | F43: 20.5 | G43: 2.9 | K43: 19.8 | M43: 20.2 | N43: 20.3 | O43: 13 | P43: 2 | Q43: 5.2 | R43: 20 | S43: 20.2 | T43: 20 | U43: 18.8 | V43: 17.5 | W43: 76.5 | X43: 108 | Y43: 90.4 | Z43: 89.8 | AB43: 9.2 | AC43: 10.5 | AD43: 10.4 | AE43: 8.4 | AF43: 20.4 | AI43: 8.1 | AK43: 0.3 | AL43: 0.5 | AM43: 3.6 | AN43: 18.5 | AQ43: 1.8 | AR43: 0.2 | AT43: 5.2 | AU43: 10 | AV43: 143.9 | AW43: 0.4 | AX43: 128.2 | AY43: 0.6 | AZ43: 0.6 | BB43: 25.9 | BC43: 84.7 | BE43: 4.8 | BF43: 1 | BG43: 2.4 | BH43: 2.4 | BI43: 0.2 | BJ43: 0.3 | BL43: 20 | BM43: 9.3 | BO43: 1113.6
B44: 18:30 | D44: 9.4 | E44: 7.4 | F44: 20.3 | G44: 2.9 | K44: 19.8 | M44: 20.2 | N44: 20.3 | O44: 12.9 | P44: 2.2 | Q44: 5.2 | R44: 20 | S44: 20.1 | T44: 20 | U44: 18.8 | V44: 18.8 | W44: 73.7 | X44: 108 | Y44: 92 | Z44: 91 | AB44: 8 | AC44: 10.4 | AD44: 10.4 | AE44: 8.4 | AF44: 20.4 | AG44: 10.2 | AI44: 8.1 | AM44: 3.6 | AN44: 18.5 | AQ44: 1.9 | AT44: 5.4 | AU44: 9.9 | AV44: 131.7 | AX44: 128.8 | AZ44: 0.6 | BB44: 25.9 | BC44: 84.3 | BE44: 4.8 | BF44: 1 | BG44: 2.4 | BH44: 2.4 | BJ44: 1.1 | BL44: 20 | BM44: 9.4 | BO44: 1110.6
B45: 19:00 | C45: 14.5 | D45: 9.4 | E45: 7.2 | F45: 20.2 | G45: 3 | K45: 19.8 | M45: 20.3 | N45: 20.3 | O45: 12.8 | P45: 2.2 | Q45: 5.2 | R45: 20 | S45: 20.2 | T45: 20 | U45: 18.9 | V45: 14.7 | W45: 64.6 | X45: 103.5 | Y45: 92 | Z45: 92.8 | AB45: 7.8 | AC45: 7.5 | AD45: 10.5 | AE45: 8.4 | AF45: 20.4 | AG45: 11.2 | AI45: 8.1 | AM45: 3.6 | AN45: 18.5 | AQ45: 1.9 | AT45: 5.4 | AU45: 9.9 | AV45: 128.2 | AX45: 125.1 | AZ45: 0.6 | BB45: 25.9 | BC45: 83.5 | BE45: 4.8 | BF45: 1.1 | BG45: 2.4 | BH45: 2.4 | BJ45: 1.1 | BL45: 20 | BM45: 9.3 | BO45: 1099.2
B46: 19:30 | C46: 15 | D46: 9.5 | E46: 5.7 | F46: 20.5 | G46: 3 | K46: 19.8 | M46: 20.3 | N46: 20.3 | O46: 12.8 | P46: 2.2 | Q46: 5.1 | R46: 20 | S46: 20 | T46: 20 | U46: 18.8 | V46: 10.5 | W46: 66.8 | X46: 103.5 | Y46: 83 | Z46: 94.2 | AB46: 8.3 | AC46: 7.7 | AD46: 10.5 | AE46: 8.4 | AF46: 20.4 | AG46: 20.4 | AI46: 6.2 | AM46: 3.6 | AN46: 18.5 | AQ46: 1.8 | AT46: 5.1 | AU46: 10 | AV46: 126.2 | AX46: 129.6 | AZ46: 0.6 | BB46: 26 | BC46: 82.9 | BE46: 4.8 | BF46: 1 | BG46: 2.4 | BH46: 2.4 | BJ46: 1.1 | BL46: 20 | BM46: 9.3 | BO46: 1098.2
B47: 20:00 | C47: 15.2 | D47: 9.4 | E47: 5.8 | F47: 20.5 | G47: 3 | K47: 19.8 | M47: 20.2 | N47: 20.3 | O47: 12.8 | P47: 2.2 | Q47: 5.1 | R47: 20 | S47: 20.3 | T47: 20 | U47: 18.7 | V47: 10.6 | W47: 68 | X47: 99.5 | Y47: 82.7 | Z47: 89.2 | AB47: 7.3 | AC47: 10 | AD47: 17.4 | AE47: 8.4 | AF47: 20.4 | AG47: 20.4 | AI47: 6.2 | AK47: 0.2 | AL47: 0.9 | AM47: 3.6 | AN47: 18.5 | AQ47: 1.9 | AT47: 5.1 | AU47: 9.9 | AV47: 100.5 | AX47: 118.1 | AZ47: 0.6 | BB47: 26.2 | BC47: 82.4 | BE47: 4.8 | BF47: 1 | BG47: 2.4 | BH47: 2.4 | BJ47: 1.2 | BL47: 20 | BM47: 9.3 | BO47: 1062.4
B48: 20:30 | C48: 15 | D48: 9.3 | E48: 6.8 | F48: 20.5 | G48: 3 | K48: 19.8 | M48: 20.2 | N48: 20.3 | O48: 12.8 | P48: 2.4 | Q48: 5.1 | R48: 20 | S48: 20.2 | T48: 19.5 | U48: 18.7 | V48: 10.9 | W48: 64.7 | X48: 99.5 | Y48: 74.4 | Z48: 92.1 | AB48: 6.7 | AC48: 9.3 | AD48: 21 | AE48: 8.4 | AF48: 20.4 | AG48: 20.4 | AI48: 6.8 | AK48: 0.6 | AL48: 1.3 | AM48: 3.6 | AN48: 18.5 | AQ48: 1.8 | AT48: 5.1 | AU48: 9.9 | AV48: 84.9 | AX48: 110.2 | AZ48: 0.6 | BB48: 26.4 | BC48: 81.9 | BE48: 4.8 | BF48: 1 | BG48: 2.4 | BH48: 2.4 | BJ48: 1.1 | BL48: 20 | BM48: 9.4 | BO48: 1034.1
B49: 21:00 | C49: 15 | D49: 9.1 | E49: 6.4 | F49: 20.5 | G49: 3 | K49: 19.9 | M49: 20.2 | N49: 20.3 | O49: 12.9 | P49: 2.6 | Q49: 5.1 | R49: 20 | S49: 20.2 | T49: 20 | U49: 18.8 | V49: 7.1 | W49: 67.6 | X49: 96.2 | Y49: 75.9 | Z49: 90.2 | AB49: 7 | AC49: 8.5 | AD49: 21 | AE49: 8.4 | AF49: 20.4 | AG49: 20.4 | AI49: 6.8 | AK49: 0.2 | AL49: 0.7 | AM49: 3.6 | AN49: 18.5 | AQ49: 1.8 | AT49: 5 | AU49: 9.8 | AV49: 94.7 | AX49: 110.5 | AZ49: 0.6 | BB49: 26.6 | BC49: 81.5 | BE49: 4.8 | BF49: 1 | BG49: 2.4 | BH49: 2.4 | BJ49: 1.1 | BL49: 20 | BM49: 9.4 | BO49: 1038.1
B50: 21:30 | C50: 14.9 | D50: 9.7 | E50: 7.4 | F50: 20.5 | G50: 2.9 | K50: 19.8 | M50: 20.2 | N50: 20.3 | O50: 13 | P50: 1.6 | Q50: 5.1 | R50: 20 | S50: 20.5 | T50: 19.5 | U50: 18.8 | V50: 6.3 | W50: 71.6 | X50: 96.2 | Y50: 69.2 | Z50: 89.6 | AB50: 6.5 | AC50: 8 | AD50: 19 | AE50: 8.4 | AF50: 20.4 | AG50: 20.4 | AH50: 10 | AI50: 6.4 | AK50: 0.5 | AL50: 1 | AM50: 3.6 | AN50: 18.5 | AQ50: 1.8 | AT50: 5.1 | AU50: 9.9 | AV50: 78.7 | AX50: 82.5 | AZ50: 0.6 | BB50: 26.7 | BC50: 81 | BE50: 4.8 | BF50: 1 | BG50: 2.4 | BH50: 2.4 | BJ50: 1.1 | BL50: 20 | BM50: 9.4 | BO50: 997.2
B51: 22:00 | C51: 15 | D51: 9.4 | E51: 7.5 | F51: 20.5 | G51: 3 | K51: 19.8 | M51: 20.2 | N51: 20.3 | O51: 13 | P51: 2.4 | Q51: 5.1 | R51: 20 | S51: 20.2 | T51: 20 | U51: 18.9 | V51: 5.1 | W51: 71.6 | X51: 89.7 | Y51: 84.6 | Z51: 90 | AB51: 7.4 | AC51: 9.3 | AD51: 9.2 | AE51: 8.4 | AF51: 20.4 | AG51: 20.4 | AH51: 20 | AI51: 6.4 | AL51: 0.1 | AM51: 3.6 | AN51: 18.5 | AQ51: 1.8 | AT51: 5.1 | AU51: 10 | AV51: 90 | AX51: 84.9 | AZ51: 0.6 | BB51: 26.8 | BC51: 80.6 | BE51: 4.8 | BF51: 1 | BG51: 2.4 | BH51: 2.4 | BJ51: 1.2 | BL51: 20 | BM51: 9.2 | BO51: 1020.8
B52: 22:30 | C52: 14.9 | D52: 9.3 | E52: 7.2 | F52: 20.3 | G52: 3 | K52: 19.8 | M52: 20.2 | N52: 20.3 | O52: 12.9 | P52: 2.5 | Q52: 5.1 | R52: 20 | S52: 20.1 | T52: 19.2 | U52: 18.9 | V52: 3.3 | W52: 70.6 | X52: 89.7 | Y52: 78.3 | Z52: 91.5 | AB52: 6.4 | AC52: 8.5 | AD52: 10.4 | AE52: 8.4 | AF52: 20.4 | AG52: 20.4 | AH52: 20 | AI52: 6.4 | AM52: 3.6 | AN52: 18.5 | AQ52: 1.8 | AT52: 3 | AU52: 9.8 | AV52: 87.5 | AX52: 81.4 | AZ52: 0.6 | BB52: 26.8 | BC52: 80 | BE52: 4.8 | BF52: 1 | BG52: 2.4 | BH52: 2.4 | BJ52: 1.1 | BL52: 20 | BM52: 9.2 | BO52: 1001.9
B53: 23:00 | C53: 15 | D53: 9.5 | E53: 7.8 | F53: 20.3 | G53: 3 | K53: 19.8 | M53: 20.2 | N53: 20.3 | O53: 13 | P53: 2.6 | Q53: 5.1 | R53: 20 | S53: 20.1 | T53: 19.7 | U53: 18.9 | V53: 3.6 | W53: 57.3 | X53: 82.2 | Y53: 68.3 | Z53: 92.7 | AB53: 7.1 | AC53: 7 | AD53: 12.5 | AE53: 8.4 | AF53: 20.4 | AG53: 20.4 | AH53: 20 | AI53: 6.4 | AM53: 3.6 | AN53: 18.5 | AQ53: 1.9 | AT53: 2.9 | AU53: 9.9 | AV53: 68.5 | AX53: 74.1 | AZ53: 0.6 | BB53: 26.7 | BC53: 79.2 | BE53: 4.8 | BF53: 1 | BG53: 2.4 | BH53: 2.4 | BJ53: 1.1 | BL53: 20 | BM53: 9.2 | BO53: 948.4
B54: 23:30 | C54: 15 | D54: 9.7 | E54: 6.4 | F54: 20.3 | G54: 3 | K54: 19.8 | M54: 20.2 | N54: 20.3 | O54: 12.9 | P54: 2.6 | Q54: 5.1 | R54: 19.8 | S54: 20.3 | T54: 20 | U54: 18.9 | V54: 7.3 | W54: 45.9 | X54: 82.2 | Y54: 79.4 | Z54: 93 | AB54: 5.5 | AC54: 7.2 | AD54: 8.7 | AE54: 8.4 | AF54: 20.4 | AG54: 20.4 | AH54: 20 | AI54: 6.4 | AM54: 3.6 | AN54: 18.5 | AQ54: 1.8 | AT54: 2.8 | AU54: 9.9 | AV54: 49.1 | AX54: 56.4 | AZ54: 0.6 | BB54: 26.5 | BC54: 77.9 | BE54: 4.8 | BF54: 1 | BG54: 2.4 | BH54: 2.4 | BJ54: 1.2 | BL54: 19.8 | BM54: 9.2 | BO54: 907
B55: 0:00 | C55: 15 | D55: 9.6 | E55: 5.7 | F55: 20.3 | G55: 3 | K55: 19.8 | M55: 20.2 | N55: 20.2 | O55: 12.9 | P55: 2.6 | Q55: 5.1 | R55: 19.8 | S55: 20.1 | T55: 20 | U55: 18.9 | V55: 9.1 | W55: 50.2 | X55: 76.2 | Y55: 80.5 | Z55: 94.5 | AB55: 7.4 | AC55: 7.2 | AD55: 12.6 | AE55: 8.4 | AF55: 20.4 | AG55: 20.4 | AH55: 20 | AI55: 6.4 | AK55: 0.6 | AL55: 0.7 | AM55: 3.6 | AN55: 18.5 | AQ55: 1.8 | AT55: 2.9 | AU55: 9.9 | AV55: 42.6 | AX55: 37.2 | AZ55: 0.6 | BB55: 26.1 | BC55: 75.9 | BE55: 4.8 | BF55: 1 | BG55: 2.4 | BH55: 2.4 | BJ55: 1.1 | BL55: 19.8 | BM55: 9.3 | BO55: 887.7
B56: EJEC MWh | C56: 82.25 | D56: 123.75 | E56: 167.85 | F56: 487.5 | G56: 71.7 | H56: 4.35 | I56: 0 | J56: 5 | K56: 475.6 | L56: 0 | M56: 480.25 | N56: 486.5 | O56: 308.4 | P56: 66.85 | Q56: 122.25 | R56: 479.35 | S56: 485.7 | T56: 476.05 | U56: 447.7 | V56: 260.15 | W56: 990.85 | X56: 2307.8 | Y56: 1607.2 | Z56: 1943.3 | AA56: 328.95 | AB56: 142.45 | AC56: 171.5 | AD56: 374.25 | AE56: 201.6 | AF56: 234.75 | AG56: 214.7 | AH56: 158.7 | AI56: 141.65 | AJ56: 730.8 | AK56: 10.5 | AL56: 14.1 | AM56: 71.8 | AN56: 444 | AO56: 0 | AP56: 1.95 | AQ56: 43.55 | AR56: 135.25 | AS56: 150.8 | AT56: 49.75 | AU56: 237.65 | AV56: 1784.05 | AW56: 1403.55 | AX56: 1789.3 | AY56: 1044.5 | AZ56: 14.4 | BA56: 180.05 | BB56: 608.3 | BC56: 1732.6 | BD56: 0 | BE56: 112.2 | BF56: 24.15 | BG56: 57.5 | BH56: 57.6 | BI56: 137.1 | BJ56: 13.4 | BK56: 0 | BL56: 479.5 | BM56: 223.05 | BN56: 184.7 | BO56: 25585
L70: TERMOELÉCTRICA | M70: 625.3 | N70: 2.4440102 | O70: #FF0000
L71: SOLAR | M71: 4302.65 | N71: 16.81708 | O71: #FBFB00
L72: HIDROELÉCTRICA | M72: 7294.95 | N72: 28.512605 | O72: #00B0F0
L73: EÓLICA | M73: 13362.1 | N73: 52.226304 | O73: #FBBD00

Sheet COGENERACIÓN
B3: sábado, 15 de Marzo del 2025
B5: CENTRALES DE COGENERACIÓN DEL SEIN
B6: HORA | C6: AGRO INDUSTRIAL PARAMONGA S.A. | D6: AGROAURORA S.A.C. | E6: AGROINDUSTRIAS SAN JACINTO S.A.A. | F6: BIOENERGIA DEL CHIRA S.A. | G6: GM OPERACIONES S.A.C. | H6: SDF ENERGIA SAC | I6: TOTAL COGENERACION
C7: C.T. PARAMONGA | D7: C.T. MAPLE | E7: C.T SAN JACINTO | F7: C.T. CAÑA BRAVA | G7: C.T. REFINERÍA TALARA | H7: C.T. OQUENDO | I7: MW
B8: 0:30 | E8: 7 | G8: 65.9 | H8: 32.4 | I8: 105.3
B9: 1:00 | E9: 7.7 | G9: 66 | H9: 32.2 | I9: 105.9
B10: 1:30 | E10: 7.5 | G10: 66.9 | H10: 32.1 | I10: 106.5
B11: 2:00 | E11: 6.5 | G11: 66 | H11: 32.3 | I11: 104.8
B12: 2:30 | E12: 6.9 | G12: 65.8 | H12: 32.1 | I12: 104.8
B13: 3:00 | E13: 7.5 | G13: 66.5 | H13: 32.3 | I13: 106.3
B14: 3:30 | E14: 7.1 | G14: 65.8 | H14: 32.2 | I14: 105.1
B15: 4:00 | E15: 7.4 | G15: 65.2 | H15: 32.1 | I15: 104.7
B16: 4:30 | E16: 7.4 | G16: 64.5 | H16: 32.1 | I16: 104
B17: 5:00 | E17: 7.3 | G17: 65.2 | H17: 31.9 | I17: 104.4
B18: 5:30 | E18: 6.6 | G18: 65.4 | H18: 31.7 | I18: 103.7
B19: 6:00 | E19: 7.7 | G19: 65.3 | H19: 31.7 | I19: 104.7
... B27: 10:00 | E27: 7.3 | G27: 65.5 | H27: 31.5 | I27: 104.3
B28: 10:30 | D28: 3.2 | E28: 7.4 | G28: 67.9 | H28: 31.2 | I28: 109.7
B29: 11:00 | D29: 4.2 | E29: 7.5 | G29: 65.8 | H29: 30.9 | I29: 108.4
B30: 11:30 | D30: 4.6 | E30: 7.4 | G30: 66.2 | H30: 30.5 | I30: 108.7
B31: 12:00 | D31: 9.6 | E31: 7.2 | G31: 67.2 | H31: 30.4 | I31: 114.4
B32: 12:30 | D32: 9.6 | E32: 7.2 | G32: 65.9 | H32: 30.6 | I32: 113.3
B33: 13:00 | D33: 9.5 | E33: 7.1 | G33: 65.8 | H33: 30.5 | I33: 112.9
B34: 13:30 | D34: 9.2 | E34: 7.7 | G34: 66.3 | H34: 30.3 | I34: 113.5
B35: 14:00 | D35: 9.4 | E35: 7.4 | G35: 65.1 | H35: 30.5 | I35: 112.4
B36: 14:30 | D36: 9.4 | E36: 7.5 | G36: 65.6 | H36: 30.4 | I36: 112.9
B37: 15:00 | D37: 9.4 | E37: 6.2 | G37: 65.8 | H37: 30.4 | I37: 111.8
B38: 15:30 | D38: 9.4 | E38: 6.9 | G38: 66.1 | H38: 30.8 | I38: 113.2
B39: 16:00 | D39: 9.3 | E39: 5.7 | G39: 65.8 | H39: 31 | I39: 111.8
... B44: 18:30 | D44: 9.4 | E44: 7.4 | G44: 66.4 | H44: 31.4 | I44: 114.6
B45: 19:00 | C45: 14.5 | D45: 9.4 | E45: 7.2 | G45: 66.3 | H45: 31.4 | I45: 128.8
B46: 19:30 | C46: 15 | D46: 9.5 | E46: 5.7 | G46: 66.1 | H46: 31.6 | I46: 127.9
B47: 20:00 | C47: 15.2 | D47: 9.4 | E47: 5.8 | G47: 66.7 | H47: 31.6 | I47: 128.7
B48: 20:30 | C48: 15 | D48: 9.3 | E48: 6.8 | G48: 66.4 | H48: 31.5 | I48: 129
B49: 21:00 | C49: 15 | D49: 9.1 | E49: 6.4 | G49: 66.6 | H49: 31.6 | I49: 128.7
B50: 21:30 | C50: 14.9 | D50: 9.7 | E50: 7.4 | G50: 66.1 | H50: 31.7 | I50: 129.8
B51: 22:00 | C51: 15 | D51: 9.4 | E51: 7.5 | G51: 66.1 | H51: 31.7 | I51: 129.7
B52: 22:30 | C52: 14.9 | D52: 9.3 | E52: 7.2 | G52: 65.8 | H52: 32 | I52: 129.2
B53: 23:00 | C53: 15 | D53: 9.5 | E53: 7.8 | G53: 65.9 | H53: 32 | I53: 130.2
B54: 23:30 | C54: 15 | D54: 9.7 | E54: 6.4 | G54: 65.7 | H54: 32.1 | I54: 128.9
B55: 0:00 | C55: 15 | D55: 9.6 | E55: 5.7 | G55: 66.2 | H55: 32.1 | I55: 128.6
B56: EJEC MWh | C56: 82.25 | D56: 123.75 | E56: 167.85 | F56: 0 | G56: 1582.5 | H56: 756.6 | I56: 2712.95

Sheet EVO_PRO_ENE
B3: sábado, 1 de Marzo del 2025 - sábado, 15 de Marzo del 2025
B5: EVOLUCIÓN DE LA PRODUCCIÓN DE LA ENERGÍA DIARIA DE LOS INTEGRANTES DEL COES (MWh)
B6: EMPRESA | C6: CENTRAL | D6: UNIDAD | E6: TIPO | F6: Marzo
F7: 1 | G7: 2 | H7: 3 | I7: 4 | J7: 5 | K7: 6 | L7: 7 | M7: 8 | N7: 9 | O7: 10 | P7: 11 | Q7: 12 | R7: 13 | S7: 14 | T7: 15 | U7: TOTAL
B8: AGRO INDUSTRIAL PARAMONGA S.A. | C8: C.T. PARAMONGA | D8: TV-01 | E8: TERMOELÉCTRICA | T8: 82.25 | U8: 82.25
B9: AGROAURORA S.A.C. | C9: C.T. MAPLE ETANOL | D9: TV | E9: TERMOELÉCTRICA | F9: 248 | G9: 283.07 | H9: 247.43 | I9: 287.315 | J9: 291.3 | K9: 307.1 | L9: 294.95 | M9: 188.3 | N9: 194.25 | O9: 229.85 | P9: 227 | Q9: 108.25 | T9: 123.75 | U9: 3030.565
B10: AGROINDUSTRIAS SAN JACINTO S.A.A. | C10: C.T. SAN JACINTO | D10: CENTRAL | E10: TERMOELÉCTRICA | F10: 164.55 | G10: 162.075 | H10: 155.435 | I10: 156.885 | J10: 153.6 | K10: 142.2 | L10: 152.8 | M10: 152.8 | N10: 112.85 | O10: 152 | P10: 162.1 | Q10: 170.35 | R10: 173.4 | S10: 168.65 | T10: 167.85 | U10: 2347.545
B11: ANDEAN POWER S.A.C. | C11: C.H. CARHUAC | D11: CENTRAL | E11: HIDROELÉCTRICA | F11: 478.15 | G11: 481.675 | H11: 485.209 | I11: 486.023 | J11: 409.85 | K11: 486.85 | L11: 488.3 | M11: 487.7 | N11: 486.15 | O11: 487.5 | P11: 487.3 | Q11: 488.7 | R11: 488 | S11: 487.95 | T11: 487.5 | U11: 7216.857
B12: ASOCIACIÓN SANTA LUCIA DE CHACAS | C12: C.H. HUALLIN | D12: CENTRAL | E12: HIDROELÉCTRICA | F12: 34 | G12: 47.44 | H12: 32.698 | I12: 38.556 | J12: 39.65 | K12: 29.25 | L12: 27.55 | M12: 32.35 | N12: 49.4 | O12: 57.15 | P12: 50.35 | Q12: 52.2 | R12: 70.4 | S12: 71.5 | T12: 71.7 | U12: 704.194
B13: ATRIA ENERGIA S.A.C. | C13: C.H. PURMACANA | D13: CENTRAL | E13: HIDROELÉCTRICA | F13: 7.2 | G13: 3.25 | I13: 1.1045 | J13: 2.3 | L13: 2.05 | M13: 0.1 | O13: 0.85 | S13: 3.3 | T13: 4.35 | U13: 24.5045
B14: BIOENERGIA DEL CHIRA S.A. | C14: C.T. CAÑA BRAVA | D14: CENTRAL | E14: TERMOELÉCTRICA | U14: 0
B15: CELEPSA | C15: C.H. EL PLATANAL | D15: CENTRAL | E15: HIDROELÉCTRICA | F15: 5202.15 | G15: 5150.6494 | H15: 5193.4355 | I15: 4494.7598 | J15: 3066.7 | K15: 5091.6 | L15: 4440.85 | M15: 5339.05 | N15: 5258.85 | O15: 4801.8 | P15: 4972.45 | Q15: 4841.95 | R15: 4786.4 | S15: 4964.05 | T15: 4829.15 | U15: 72433.845
B16: CELEPSA RENOVABLES S.R.L. | C16: C.H. MARAÑON | D16: CENTRAL | E16: HIDROELÉCTRICA | F16: 17.65 | G16: 170.67622 | H16: 416.9567 | L16: 62.25 | M16: 472.8 | N16: 472.8 | O16: 472.9 | P16: 470.35 | Q16: 472.8 | R16: 469.65 | S16: 382.35 | T16: 373.4 | U16: 4254.5829
B17: CENTRALES SANTA ROSA S.A.C. | C17: C.H. SANTA ROSA I | D17: CENTRAL | E17: HIDROELÉCTRICA | F17: 23.45 | G17: 21.818685 | H17: 24.70173 | I17: 25.127895 | J17: 25.2 | K17: 23.45 | L17: 21.8 | M17: 22 | N17: 22.9 | O17: 23.7 | P17: 24.4 | Q17: 25.05 | R17: 23.2 | S17: 23.4 | T17: 23.65 | U17: 353.84831
B18: CENTRALES SANTA ROSA S.A.C. | C18: C.H. SANTA ROSA II | D18: CENTRAL | E18: HIDROELÉCTRICA | F18: 37 | G18: 38.079535 | H18: 37.97834 | I18: 38.746845 | J18: 38.45 | K18: 35.65 | L18: 34.65 | M18: 34.4 | N18: 33.5 | O18: 36.95 | P18: 36.25 | Q18: 15.9 | R18: 34.35 | S18: 36.8 | T18: 37.25 | U18: 525.95472
B19: CHINANGO S.A.C. | C19: C.H. CHIMAY | D19: CENTRAL | E19: HIDROELÉCTRICA | F19: 3492.5 | G19: 3496.9515 | H19: 3533.8086 | I19: 3514.6025 | J19: 3473.8 | K19: 3549.4 | L19: 3335.25 | M19: 3417.2 | N19: 3420.1 | O19: 1744 | P19: 3447.8 | Q19: 3405.2 | R19: 3368.35 | S19: 1564.35 | T19: 3415.65 | U19: 48178.963
B20: CHINANGO S.A.C. | C20: C.H. YANANGO | D20: CENTRAL | E20: HIDROELÉCTRICA | F20: 1014.75 | G20: 1014.6382 | H20: 997.45541 | I20: 1013.5946 | J20: 561.5 | K20: 358.45 | N20: 212.15 | P20: 45.3 | Q20: 339.9 | R20: 994.55 | S20: 524.4 | T20: 1017.35 | U20: 8094.0382
B21: COLCA SOLAR S.A.C. | C21: C.S. YARUCAYA | D21: CENTRAL | E21: SOLAR | F21: 5.85 | G21: 4.23 | H21: 4.03 | I21: 5.56 | J21: 4.95 | K21: 4.35 | L21: 7.2 | M21: 4.65 | N21: 6.75 | O21: 7.55 | P21: 6.65 | Q21: 7.45 | R21: 6.2 | S21: 6.5 | T21: 5 | U21: 86.92
B22: EGASA | C22: C.H. CHARCANI III | D22: CENTRAL | E22: HIDROELÉCTRICA | F22: 153.4 | G22: 145.4 | H22: 152.59 | I22: 153.095 | J22: 145.05 | K22: 152.6 | L22: 136.15 | M22: 101.85 | N22: 152.845 | O22: 107.35 | P22: 109.7 | Q22: 151.9 | R22: 159.9 | S22: 153.7 | T22: 148.95 | U22: 2124.48
B23: EGASA | C23: C.H. CHARCANI IV | D23: CENTRAL | E23: HIDROELÉCTRICA | O23: 30.2 | P23: 160.15 | Q23: 177 | R23: 182.3 | S23: 190.5 | T23: 166.45 | U23: 906.6
B24: EGASA | C24: C.H. CHARCANI V | D24: CENTRAL | E24: HIDROELÉCTRICA | F24: 3441.6 | G24: 3441.145 | H24: 3291.375 | I24: 3290.875 | J24: 3400.15 | K24: 3440.25 | L24: 3441.15 | M24: 2960.8 | N24: 3433.535 | O24: 3430.35 | P24: 3436.45 | Q24: 3437.55 | R24: 3431.9 | S24: 3437.4 | T24: 3434.05 | U24: 50748.58
B25: EGASA | C25: C.H. CHARCANI VI | D25: CENTRAL | E25: HIDROELÉCTRICA | F25: 164.4 | G25: 161.315 | H25: 166.855 | I25: 122.535 | J25: 171.6 | K25: 189.65 | L25: 121.1 | M25: 41.35 | N25: 99.37 | O25: 99.8 | P25: 114.8 | Q25: 105.5 | R25: 109.55 | S25: 100.8 | T25: 97.55 | U25: 1866.175
B26: EGASA | C26: C.T. CHILINA DIESEL | D26: CENTRAL | E26: TERMOELÉCTRICA | U26: 0
B27: EGASA | C27: C.T. CHILINA DIESEL | D27: TG | E27: TERMOELÉCTRICA | U27: 0
B28: EGASA | C28: C.T. MOLLENDO DIESEL | D28: CENTRAL | E28: TERMOELÉCTRICA | K28: 18.45 | R28: 21.25 | U28: 39.7
B29: EGEJUNIN | C29: C.H. HUASAHUASI I | D29: CENTRAL | E29: HIDROELÉCTRICA | F29: 475.45 | G29: 476.6105 | H29: 476.5165 | I29: 476.589 | J29: 476.8 | K29: 386.65 | L29: 451.15 | M29: 475.45 | N29: 475.6 | O29: 475.45 | P29: 475.55 | Q29: 475.5 | R29: 475.6 | S29: 475.95 | T29: 475.6 | U29: 7024.466
B30: EGEJUNIN | C30: C.H. RUNATULLO II | D30: CENTRAL | E30: HIDROELÉCTRICA | F30: 478.3 | G30: 478.82 | H30: 479.35 | I30: 480.04 | J30: 480.05 | K30: 432.7 | L30: 479.45 | M30: 479.25 | N30: 371.55 | O30: 479.85 | P30: 480.8 | Q30: 480.05 | R30: 480.4 | S30: 482.35 | T30: 480.25 | U30: 7043.21
B31: EGEJUNIN | C31: C.H. RUNATULLO III | D31: CENTRAL | E31: HIDROELÉCTRICA | F31: 487.45 | G31: 487.64 | H31: 487.09 | I31: 487.025 | J31: 486.4 | K31: 441.15 | L31: 487.3 | M31: 487.2 | N31: 412.75 | O31: 486.65 | P31: 486.25 | Q31: 486.85 | R31: 486.6 | S31: 486.25 | T31: 486.5 | U31: 7183.105
B32: EGEJUNIN | C32: C.H. SANTA CRUZ I | D32: CENTRAL | E32: HIDROELÉCTRICA | F32: 295.15 | G32: 232.5675 | L32: 25.6 | M32: 253.8 | N32: 309.2 | O32: 248.85 | P32: 310 | Q32: 311.9 | R32: 287.95 | S32: 260.5 | T32: 308.4 | U32: 2843.9175
B33: EGEMSA | C33: C.H. MACHUPICCHU | D33: CENTRAL | E33: HIDROELÉCTRICA | F33: 3964.55 | G33: 3798.3184 | H33: 3756.9495 | I33: 3888.3744 | J33: 3971.4 | K33: 3939.6 | L33: 3968.7 | M33: 4037.7 | N33: 3995.15 | O33: 3976.25 | P33: 3970.5 | Q33: 3961.5 | R33: 3952.05 | S33: 3889.5 | T33: 3952.4 | U33: 59022.942
B34: EGESUR | C34: C.H. ARICOTA I | D34: CENTRAL | E34: HIDROELÉCTRICA | F34: 179.35 | G34: 179.6695 | H34: 178.3585 | I34: 180.8635 | J34: 179.4 | K34: 177.95 | L34: 179.55 | M34: 181.5 | N34: 182.4 | O34: 179.45 | P34: 179.7 | Q34: 180.2 | R34: 180.2 | S34: 179.05 | T34: 182.6 | U34: 2700.2415
B35: EGESUR | C35: C.H. ARICOTA II | D35: CENTRAL | E35: HIDROELÉCTRICA | F35: 56.2 | G35: 63.505 | H35: 64.4495 | I35: 66.3065 | J35: 67.501 | K35: 67.5 | L35: 68.25 | M35: 70.95 | N35: 72.45 | O35: 72.45 | P35: 71.55 | Q35: 72.9 | R35: 72.85 | S35: 71.9 | T35: 70.7 | U35: 1029.462
B36: EGESUR | C36: C.T. INDEPENDENCIA | D36: CENTRAL | E36: TERMOELÉCTRICA | F36: 287.9 | G36: 270.4815 | H36: 295.579 | I36: 228.8855 | J36: 275.7 | K36: 293.4 | L36: 215.35 | M36: 84 | N36: 25.85 | O36: 56.5 | P36: 88 | Q36: 28.4 | R36: 11.95 | S36: 71 | U36: 2232.996
B37: ELECTRICA YANAPAMPA SAC | C37: C.H. YANAPAMPA | D37: CENTRAL | E37: HIDROELÉCTRICA | F37: 76.55 | G37: 76.297 | H37: 72.5515 | I37: 57.187 | J37: 55.35 | K37: 62.05 | L37: 69.4 | M37: 64.4 | N37: 67.95 | O37: 62.55 | P37: 30.35 | Q37: 56.75 | R37: 67.35 | S37: 75.05 | T37: 66.85 | U37: 960.6355
B38: ELECTROPERU | C38: C.H. MANTARO | D38: CENTRAL | E38: HIDROELÉCTRICA | F38: 197.4 | G38: 38.2 | I38: 7.24 | K38: 24.6 | L38: 1961.1 | M38: 11064.2 | N38: 15276.45 | O38: 14809.9 | P38: 15171.35 | Q38: 15606.9 | R38: 15371.45 | S38: 15582.3 | T38: 15592.6 | U38: 120703.69
B39: ELECTROPERU | C39: C.H. RESTITUCION | D39: CENTRAL | E39: HIDROELÉCTRICA | F39: 72.1 | G39: 12.29 | L39: 287.05 | M39: 3536.3 | N39: 5081.55 | O39: 4931.15 | P39: 4633.95 | Q39: 5104.45 | R39: 5089.7 | S39: 4544.8 | T39: 5227.6 | U39: 38520.94
B40: ELECTROPERU | C40: C.T. TUMBES | D40: MAK1 | E40: TERMOELÉCTRICA | H40: 17.535 | K40: 18.945 | L40: 36.955 | N40: 10.5 | U40: 83.935
B41: ELECTROPERU | C41: C.T. TUMBES | D41: MAK2 | E41: TERMOELÉCTRICA | H41: 17.45 | K41: 36.92 | U41: 54.37
B42: EMPRESA DE GENERACION ELECTRICA CANCHAYLLO SAC | C42: C.H. CANCHAYLLO | D42: CENTRAL | E42: HIDROELÉCTRICA | F42: 122.6 | G42: 118.814 | H42: 107.897 | I42: 104.2105 | J42: 74.55 | K42: 89.8 | L42: 66.75 | M42: 53.1 | N42: 79.15 | O42: 114.35 | P42: 103.25 | Q42: 104.2 | R42: 100.05 | S42: 99.95 | T42: 122.25 | U42: 1460.9215
B43: EMPRESA DE GENERACION ELECTRICA RIO BAÑOS S.A.C. | C43: C.H. RUCUY | D43: CENTRAL | E43: HIDROELÉCTRICA | F43: 479.95 | G43: 480.30641 | H43: 479.72303 | I43: 479.53348 | J43: 479.4 | K43: 479.95 | L43: 480.05 | M43: 479.1 | N43: 479.55 | O43: 479.2 | P43: 479.25 | Q43: 479.75 | R43: 479.7 | S43: 479.75 | T43: 479.35 | U43: 7194.5629
B44: EMPRESA DE GENERACION ELECTRICA SANTA ANA S.A.C. | C44: C.H. RENOVANDES H1 | D44: CENTRAL | E44: HIDROELÉCTRICA | F44: 405.15 | G44: 487.25 | H44: 484.16 | I44: 485.585 | J44: 484.35 | K44: 420.4 | L44: 485.1 | M44: 314.25 | N44: 422.45 | O44: 480.8 | P44: 485.95 | Q44: 385.05 | R44: 486.5 | S44: 485.85 | T44: 485.7 | U44: 6798.545
B45: EMPRESA DE GENERACION HUALLAGA | C45: C.H. CHAGLLA | D45: CENTRAL | E45: HIDROELÉCTRICA | F45: 10738.25 | G45: 10686.699 | H45: 11141.905 | I45: 10819.019 | J45: 11035.45 | K45: 11113.25 | L45: 11033.5 | M45: 10867.85 | N45: 11032 | O45: 10887.65 | P45: 11064.7 | Q45: 11044.75 | R45: 10843.15 | S45: 11045.05 | T45: 10924.9 | U45: 164278.12
B46: EMPRESA DE GENERACION HUALLAGA | C46: P.C.H. CHAGLLA | D46: CENTRAL | E46: HIDROELÉCTRICA | F46: 156 | G46: 156.37672 | H46: 156.33116 | I46: 156.36868 | J46: 156 | K46: 156 | L46: 156 | M46: 53.1 | N46: 41.45 | O46: 158.4 | P46: 158.35 | Q46: 158.4 | R46: 158.4 | S46: 158.4 | T46: 98.3 | U46: 2077.8766
B47: EMPRESA DE GENERACION HUANZA | C47: C.H. HUANZA | D47: CENTRAL | E47: HIDROELÉCTRICA | F47: 1961.4 | G47: 2049.705 | H47: 2281.335 | I47: 2293.63 | J47: 2290.35 | K47: 2284.4 | L47: 2285.8 | M47: 2282.3 | N47: 2275.9 | O47: 2275.65 | P47: 2277.15 | Q47: 2281.115 | R47: 2275.05 | S47: 2271.2 | T47: 2275.7 | U47: 33660.685
B48: EMPRESA ELECTRICA AGUA AZUL | C48: C.H. POTRERO | D48: CENTRAL | E48: HIDROELÉCTRICA | F48: 415.2 | G48: 255.962 | H48: 172.3435 | I48: 326.1015 | J48: 369.1 | K48: 414.25 | L48: 375.15 | M48: 395.7 | N48: 478.65 | O48: 480 | P48: 479.9 | Q48: 479.6 | R48: 437.05 | S48: 467.25 | T48: 476.05 | U48: 6022.307
B49: EMPRESA ELECTRICA RIO DOBLE | C49: C.H. LAS PIZARRAS | D49: CENTRAL | E49: HIDROELÉCTRICA | F49: 445.45 | G49: 445.745 | H49: 448.68 | I49: 401.74 | J49: 428.6 | K49: 458 | L49: 453.35 | M49: 453.45 | N49: 453.65 | O49: 454.95 | P49: 455.95 | Q49: 456.75 | R49: 453.65 | S49: 443.65 | T49: 447.7 | U49: 6701.315
B50: ENEL GENERACION PIURA S.A. | C50: C.T. MALACAS 1 | D50: TG6 | E50: TERMOELÉCTRICA | F50: 757.75 | G50: 589.6265 | H50: 812.884 | I50: 558.9085 | J50: 721.7 | K50: 662.7 | L50: 630.3 | M50: 1095.5 | N50: 777.2 | O50: 744.15 | P50: 782.3 | Q50: 796.5 | R50: 753.9 | U50: 9683.419
B51: ENEL GENERACION PIURA S.A. | C51: C.T. MALACAS 2 | D51: TG4 | E51: TERMOELÉCTRICA | G51: 700.3035 | H51: 87.8185 | I51: 564.608 | J51: 352.7 | K51: 682.85 | L51: 485 | N51: 458.6 | O51: 330.6 | S51: 629.55 | T51: 49.7 | U51: 4341.73
B52: ENEL GENERACION PIURA S.A. | C52: C.T. RF DE GENERACION TALARA | D52: TG5 | E52: TERMOELÉCTRICA | U52: 0
B53: ENERGÍA EÓLICA S.A. | C53: C.E. CUPISNIQUE | D53: CENTRAL | E53: EÓLICA | F53: 492.4 | G53: 234.21632 | H53: 573.41678 | I53: 829.4876 | J53: 693.1 | K53: 784.65 | L53: 1130.35 | M53: 732.65 | N53: 489.55 | O53: 893.55 | P53: 920.05 | Q53: 978.3 | R53: 674.75 | S53: 673.5 | T53: 990.85 | U53: 11090.821
B54: ENERGÍA EÓLICA S.A. | C54: C.E. TALARA | D54: CENTRAL | E54: EÓLICA | F54: 126.35 | G54: 72.805165 | H54: 99.786865 | I54: 119.53852 | J54: 97.4 | K54: 28.15 | L54: 104.5 | M54: 118.8 | N54: 43.85 | O54: 130.3 | P54: 113.1 | Q54: 370.8 | R54: 191.9 | S54: 69.55 | T54: 260.15 | U54: 1946.9805
B55: ENERGIA RENOVABLE DEL SUR S.A. | C55: C.E. SAN JUAN | D55: CENTRAL | E55: EÓLICA | F55: 1476.15 | G55: 2410.149 | H55: 2215.8275 | I55: 1834.392 | J55: 1267.4 | K55: 1121.7 | L55: 2566.25 | M55: 2061.45 | N55: 2112.2 | O55: 2161.25 | P55: 876.65 | Q55: 802.45 | R55: 1505.3 | S55: 1240.75 | T55: 2307.8 | U55: 25959.718
B56: ENGIE | C56: C.E. PUNTA LOMITAS | D56: PL-BL1 | E56: EÓLICA | F56: 674.7 | G56: 1264.1088 | H56: 1969.2187 | I56: 1769.0911 | J56: 813.75 | K56: 487.1 | L56: 1355.4 | M56: 1565.3616 | N56: 1622.25 | O56: 1644.95 | P56: 958.6 | Q56: 541.2 | R56: 894.1 | S56: 635.05 | T56: 1607.2 | U56: 17802.08
B57: ENGIE | C57: C.E. PUNTA LOMITAS | D57: PL-BL2 | E57: EÓLICA | F57: 765.7 | G57: 1453.6883 | H57: 1920.3587 | I57: 1827.2767 | J57: 973.65 | K57: 732.8 | L57: 1533.7 | M57: 2060.2078 | N57: 1916.75 | O57: 1998.8 | P57: 1153.8 | Q57: 938.9 | R57: 1223.7 | S57: 1046.5 | T57: 1943.3 | U57: 21489.132
B58: ENGIE | C58: C.E. PUNTA LOMITAS_EXP | D58: PUN LOM_EXP-BL1 | E58: EÓLICA | F58: 43.1 | G58: 65.92504 | H58: 137.81323 | I58: 122.02934 | J58: 58.05 | K58: 25.6 | L58: 104.95 | M58: 128.15 | N58: 165.3 | O58: 168.3 | P58: 96.4 | Q58: 43.25 | R58: 66.9 | S58: 48.3 | T58: 142.45 | U58: 1416.5176
B59: ENGIE | C59: C.E. PUNTA LOMITAS_EXP | D59: PUN LOM_EXP-BL2 | E59: EÓLICA | F59: 12.05 | G59: 93.158995 | H59: 228.80567 | I59: 207.60234 | J59: 67.45 | K59: 27.5 | L59: 139.75 | M59: 121.3 | N59: 134.85 | O59: 150.85 | P59: 104.4 | Q59: 51.45 | R59: 71.1 | S59: 42.8 | T59: 171.5 | U59: 1624.567
B60: ENGIE | C60: C.H. QUITARACSA | D60: CENTRAL | E60: HIDROELÉCTRICA | F60: 2731.65 | G60: 2741.6212 | H60: 2118.2061 | I60: 2367.8402 | J60: 2517.45 | K60: 202.65 | U60: 12679.417
B61: ENGIE | C61: C.H. YUNCAN | D61: CENTRAL | E61: HIDROELÉCTRICA | F61: 2086.95 | G61: 2082.6452 | H61: 2080.9741 | I61: 2087.1043 | J61: 2084.1 | K61: 2081.6 | L61: 2071.75 | M61: 2073.25 | N61: 2001.45 | O61: 1780.55 | P61: 2086.5 | Q61: 2088.1 | R61: 2084.75 | S61: 2085.7 | T61: 2087.7 | U61: 30863.124
B62: ENGIE | C62: C.S. INTIPAMPA | D62: CENTRAL | E62: SOLAR | F62: 189.1 | G62: 199.38369 | H62: 162.58559 | I62: 155.53618 | J62: 311.35 | K62: 89.1 | L62: 252.9 | M62: 250.75 | N62: 219.25 | O62: 140.4 | P62: 324.65 | Q62: 343.25 | R62: 337.8 | S62: 294.25 | T62: 328.95 | U62: 3599.2555
B63: ENGIE | C63: C.T. CHILCA 1 | D63: TG1 | E63: TERMOELÉCTRICA | F63: 3993.45 | G63: 3934.7808 | H63: 4015.2463 | I63: 3840.5846 | J63: 3981.15 | K63: 4065.6 | L63: 4060.6 | M63: 3084.3 | N63: 3109.8 | O63: 2889.35 | P63: 2980.2 | Q63: 2960 | R63: 2934.6 | S63: 3019.75 | T63: 3263 | U63: 52132.412
B64: ENGIE | C64: C.T. CHILCA 1 | D64: TG2 | E64: TERMOELÉCTRICA | F64: 3813.85 | G64: 3757.0858 | H64: 3829.2164 | I64: 3678.231 | J64: 3813.4 | K64: 3873.55 | L64: 3872.4 | M64: 3025.75 | N64: 3065.85 | O64: 2866.55 | P64: 2962.2 | Q64: 2956.6 | R64: 2927.15 | S64: 3015.65 | T64: 3172.85 | U64: 50630.333
B65: ENGIE | C65: C.T. CHILCA 1 | D65: TG3 | E65: TERMOELÉCTRICA | F65: 4701.75 | G65: 4625.8253 | H65: 4766.0346 | I65: 4437.1885 | J65: 4653.65 | K65: 4792.4 | L65: 4735.45 | M65: 3296.95 | N65: 3211.05 | O65: 2942.45 | P65: 2993.05 | Q65: 2955.7 | R65: 2949.25 | S65: 3016.85 | T65: 3611.95 | U65: 57689.548
B66: ENGIE | C66: C.T. CHILCA 1 | D66: TV | E66: TERMOELÉCTRICA | F66: 6174.35 | G66: 6051.7682 | H66: 6167.3929 | I66: 5988.3888 | J66: 6157.7 | K66: 6221.3 | L66: 6206.7 | M66: 5254.8 | N66: 5179.3 | O66: 4960 | P66: 5004.9 | Q66: 5005.4 | R66: 5024.5 | S66: 5038 | T66: 5308.6 | U66: 83743.1
B67: ENGIE | C67: C.T. CHILCA 2 | D67: TG41 | E67: TERMOELÉCTRICA | F67: 200.55 | G67: 326.31458 | H67: 1225.8121 | I67: 1295.9138 | J67: 1525.2 | K67: 1580.05 | L67: 1477.25 | M67: 1171.9 | N67: 1112.8 | O67: 1074.75 | P67: 594 | Q67: 371.55 | R67: 84.7 | S67: 227.15 | U67: 12267.941
B68: ENGIE | C68: C.T. CHILCA 2 | D68: TV42 | E68: TERMOELÉCTRICA | H68: 524.739 | I68: 645.85564 | J68: 779.2 | K68: 793.95 | L68: 769.15 | M68: 701.3 | N68: 679.85 | O68: 674.75 | U68: 5568.7946
B69: ENGIE | C69: C.T. NEPI | D69: TG41 | E69: TERMOELÉCTRICA | H69: 1277.7673 | I69: 241.04592 | K69: 1181.45 | L69: 1058.7 | U69: 3758.9633
B70: ENGIE | C70: C.T. NEPI | D70: TG42 | E70: TERMOELÉCTRICA | U70: 0
B71: ENGIE | C71: C.T. NEPI | D71: TG43 | E71: TERMOELÉCTRICA | N71: 471.65 | U71: 471.65
B72: ENGIE | C72: C.T. RF PLANTA ILO | D72: TG1 | E72: TERMOELÉCTRICA | U72: 0
B73: ENGIE | C73: C.T. RF PLANTA ILO | D73: TG2 | E73: TERMOELÉCTRICA | U73: 0
B74: ENGIE | C74: C.T. RF PLANTA ILO | D74: TG3 | E74: TERMOELÉCTRICA | U74: 0
B75: FENIX POWER PERÚ | C75: C.T. FENIX | D75: GT11 | E75: TERMOELÉCTRICA | F75: 3665.9 | G75: 1305.8552 | H75: 4013.905 | I75: 3902.759 | J75: 3939.1 | K75: 4134.25 | L75: 3659.45 | M75: 3875.25 | N75: 1684.45 | O75: 3558.75 | P75: 3869.65 | Q75: 3980.2 | R75: 3625.45 | S75: 3700.5 | T75: 25.35 | U75: 48940.819
B76: FENIX POWER PERÚ | C76: C.T. FENIX | D76: GT12 | E76: TERMOELÉCTRICA | F76: 3683.3 | G76: 2328.6156 | H76: 4029.2245 | I76: 3910.078 | J76: 3948.95 | K76: 4144.35 | L76: 3665.9 | M76: 3883.3 | N76: 1677.6 | O76: 3565.35 | P76: 3878.6 | Q76: 3991.05 | R76: 3633.65 | S76: 3706.15 | T76: 3224.7 | U76: 53270.818
B77: FENIX POWER PERÚ | C77: C.T. FENIX | D77: TV10 | E77: TERMOELÉCTRICA | F77: 4080.1 | G77: 1775.6855 | H77: 4282.333 | I77: 4202.2535 | J77: 4217.15 | K77: 4345.05 | L77: 4052.75 | M77: 4172 | N77: 1572 | O77: 3975.4 | P77: 4156.45 | Q77: 4242.35 | R77: 4031.05 | S77: 4089.2 | T77: 1834.5 | U77: 55028.272
B78: GENERACIÓN ANDINA S.A.C. | C78: C.H. 8 DE AGOSTO | D78: CENTRAL | E78: HIDROELÉCTRICA | F78: 504.05 | G78: 399.7495 | H78: 503.8515 | I78: 502.1525 | J78: 395.7 | K78: 0.1 | L78: 18.45 | M78: 250.1 | N78: 252 | O78: 252 | P78: 252 | Q78: 355.1 | R78: 357.65 | S78: 463.85 | T78: 374.25 | U78: 4881.0035
B79: GENERACIÓN ANDINA S.A.C. | C79: C.H. EL CARMEN | D79: CENTRAL | E79: HIDROELÉCTRICA | F79: 170.8 | G79: 174.774 | H79: 201.9495 | I79: 201.6775 | J79: 186.85 | K79: 203.55 | L79: 203.85 | M79: 202.8 | N79: 200.9 | O79: 203.55 | P79: 200.45 | Q79: 201.8 | R79: 201.6 | S79: 200.15 | T79: 201.6 | U79: 2956.301
B80: GENERADORA DE ENERGÍA DEL PERÚ | C80: C.H. ÁNGEL I | D80: CENTRAL | E80: HIDROELÉCTRICA | F80: 489.6 | G80: 489.6 | H80: 489.6 | I80: 489.6 | J80: 489.6 | K80: 489.6 | L80: 489.6 | M80: 234.6 | N80: 235.6 | O80: 244.8 | P80: 489.6 | Q80: 489.6 | R80: 489.6 | S80: 227.9 | T80: 234.75 | U80: 6073.65
B81: GENERADORA DE ENERGÍA DEL PERÚ | C81: C.H. ÁNGEL II | D81: CENTRAL | E81: HIDROELÉCTRICA | F81: 489.6 | G81: 489.6 | H81: 489.6 | I81: 489.6 | J81: 489.6 | K81: 489.6 | L81: 489.6 | M81: 214.2 | N81: 229.75 | O81: 239.7 | P81: 489.6 | Q81: 489.6 | R81: 489.6 | S81: 227.15 | T81: 214.7 | U81: 6021.5
B82: GENERADORA DE ENERGÍA DEL PERÚ | C82: C.H. ÁNGEL III | D82: CENTRAL | E82: HIDROELÉCTRICA | F82: 480 | G82: 480 | H82: 480 | I82: 480 | J82: 480 | K82: 480 | L82: 480 | M82: 186 | N82: 187.5 | O82: 227 | P82: 480 | Q82: 480 | R82: 480 | S82: 222 | T82: 158.7 | U82: 5781.2
B83: GENERADORA DE ENERGÍA DEL PERÚ | C83: C.H. LA JOYA | D83: CENTRAL | E83: HIDROELÉCTRICA | L83: 22 | M83: 78.7 | N83: 89.8 | O83: 33.35 | Q83: 33.15 | R83: 107.15 | S83: 115.55 | T83: 141.65 | U83: 621.35
B84: GM OPERACIONES S.A.C. | C84: CT REFINERIA TALARA | D84: TV1 REF TALARA | E84: TERMOELÉCTRICA | O84: 2.55 | P84: 382.38 | Q84: 444.95 | R84: 196.55 | S84: 414.1 | T84: 737.85 | U84: 2178.38
B85: GM OPERACIONES S.A.C. | C85: CT REFINERIA TALARA | D85: TV2 REF TALARA | E85: TERMOELÉCTRICA | F85: 869.55 | G85: 872.48 | H85: 874.555 | I85: 870.815 | J85: 879.35 | K85: 880.565 | L85: 870.95 | M85: 854.65 | N85: 844.55 | O85: 795.9 | P85: 789.205 | Q85: 82.935 | S85: 281.75 | T85: 844.65 | U85: 10611.905
B86: GR CORTARRAMA SOCIEDAD ANONIMA CERRADA | C86: C.S. MATARANI | D86: C.S. MATARANI | E86: SOLAR | F86: 732.6 | G86: 610.685 | H86: 729.91 | I86: 482.955 | J86: 607.45 | K86: 522.6 | L86: 733.55 | M86: 656.95 | N86: 538.15 | O86: 544.6 | P86: 718 | Q86: 717.9 | R86: 718.2 | S86: 729 | T86: 730.8 | U86: 9773.35
B87: GR PAINO SOCIEDAD ANONIMA CERRADA | C87: C.E. HUAMBOS | D87: CENTRAL | E87: EÓLICA | F87: 51.65 | G87: 32.58597 | H87: 23.62121 | I87: 31.77664 | J87: 41.9 | K87: 70.9 | L87: 41.1 | M87: 47.85 | N87: 22.7 | O87: 78.2 | P87: 76.8 | Q87: 62.7 | R87: 84.95 | S87: 50.25 | T87: 10.5 | U87: 727.48382
B88: GR TARUCA SOCIEDAD ANONIMA CERRADA | C88: C.E. DUNA | D88: CENTRAL | E88: EÓLICA | F88: 47.25 | G88: 42.391385 | H88: 31.94139 | I88: 25.49812 | J88: 27.3 | K88: 52 | L88: 26.8 | M88: 53.35 | N88: 16.05 | O88: 76.15 | P88: 63.95 | Q88: 109.9 | R88: 119.35 | S88: 55.55 | T88: 14.1 | U88: 761.5809
B89: HIDROCAÑETE S.A. | C89: C.H. IMPERIAL | D89: CENTRAL | E89: HIDROELÉCTRICA | F89: 85.65 | G89: 85.692 | H89: 83.4875 | I89: 84.5665 | J89: 84.55 | K89: 83.2 | L89: 81.95 | M89: 82.95 | N89: 82.5 | O89: 82.15 | P89: 83.85 | Q89: 84.8 | R89: 84.75 | S89: 84.45 | T89: 71.8 | U89: 1246.346
B90: HIDROELECTRICA HUANCHOR S.A.C. | C90: C.H. HUANCHOR | D90: CENTRAL | E90: HIDROELÉCTRICA | F90: 441.55 | G90: 441.72442 | H90: 441.4533 | I90: 439.11521 | J90: 440.2 | K90: 440.9 | L90: 439.55 | M90: 441.5 | N90: 441.25 | O90: 440.75 | P90: 442.55 | Q90: 442.15 | R90: 441.9 | S90: 442.85 | T90: 442.65 | U90: 6620.0929
B91: HUAURA POWER GROUP S.A. | C91: C.H. YARUCAYA | D91: CENTRAL | E91: HIDROELÉCTRICA | F91: 449.7 | G91: 448.935 | H91: 448.6 | I91: 448.255 | J91: 446.05 | K91: 176.2 | L91: 229.95 | M91: 343.85 | N91: 444.6 | O91: 444.2 | P91: 444.1 | Q91: 444.05 | R91: 444.45 | S91: 444.15 | T91: 444 | U91: 6101.09
B92: INFRAESTRUCTURAS Y ENERGIAS DEL PERU S.A.C. | C92: C.T. RF PTO MALDONADO | D92: CENTRAL | E92: TERMOELÉCTRICA | G92: 87.975 | U92: 87.975
B93: INFRAESTRUCTURAS Y ENERGIAS DEL PERU S.A.C. | C93: C.T. RF PUCALLPA | D93: CENTRAL | E93: TERMOELÉCTRICA | U93: 0
B94: INLAND ENERGY SAC | C94: C.H. SANTA TERESA | D94: CENTRAL | E94: HIDROELÉCTRICA | F94: 2172.25 | G94: 2066.7676 | H94: 2036.195 | I94: 2111.575 | J94: 2170.7 | K94: 2157.45 | L94: 2160.4 | M94: 2167.15 | N94: 2173 | O94: 2173 | P94: 2170.65 | Q94: 2161.4 | R94: 2160.8 | S94: 2118.85 | T94: 2158.9 | U94: 32159.088
B95: INVERSIONES SHAQSHA S.A.C. | C95: C.H. PARIAC | D95: CENTRAL | E95: HIDROELÉCTRICA | J95: 32.9 | K95: 54.5 | L95: 82.65 | M95: 73.8 | N95: 59.15 | O95: 48.9 | P95: 50.45 | Q95: 50.25 | R95: 50.4 | S95: 50.35 | T95: 50.3 | U95: 603.65
B96: KALLPA GENERACION S.A. | C96: C.H. CERRO DEL AGUILA | D96: CENTRAL | E96: HIDROELÉCTRICA | F96: 13450.75 | G96: 11195.95 | H96: 1672.29 | I96: 13405.74 | J96: 13385.35 | K96: 13395.8 | L96: 5973.9 | M96: 929.5 | O96: 5953.05 | P96: 9064.7 | Q96: 9077.95 | R96: 8976.55 | S96: 9043.1 | T96: 9053.65 | U96: 124578.28
B97: KALLPA GENERACION S.A. | C97: C.T. KALLPA | D97: TG1 | E97: TERMOELÉCTRICA | F97: 3231.4 | G97: 3230.39 | H97: 3268.245 | I97: 2988.66 | J97: 3168.65 | K97: 3581.95 | L97: 3771.95 | M97: 3596.7 | N97: 3396.05 | O97: 3100.9 | P97: 3215.75 | Q97: 3584.8 | R97: 3299.8 | S97: 3341.3 | T97: 2961.1 | U97: 49737.645
B98: KALLPA GENERACION S.A. | C98: C.T. KALLPA | D98: TG2 | E98: TERMOELÉCTRICA | F98: 3255.7 | G98: 3265.37 | H98: 3271.86 | I98: 2990.33 | J98: 3167.35 | K98: 3608.15 | L98: 4018.15 | M98: 3791.75 | N98: 3520.8 | O98: 3205.95 | P98: 2861.75 | T98: 2849.35 | U98: 39806.51
B99: KALLPA GENERACION S.A. | C99: C.T. KALLPA | D99: TG3 | E99: TERMOELÉCTRICA | F99: 3251.05 | G99: 3267.43 | H99: 3273.555 | I99: 2994.04 | J99: 3168.8 | K99: 3607.9 | L99: 4022.5 | M99: 3804.25 | N99: 3037.55 | O99: 3211.8 | P99: 3283.4 | Q99: 3858.75 | R99: 3455.7 | S99: 3517.35 | T99: 2972.8 | U99: 50726.875
B100: KALLPA GENERACION S.A. | C100: C.T. KALLPA | D100: TV | E100: TERMOELÉCTRICA | F100: 5592.5 | G100: 5571.865 | H100: 5622.475 | I100: 5390.81 | J100: 5538.25 | K100: 5879.15 | L100: 6211.85 | M100: 6053.8 | N100: 5551.1 | O100: 5536.25 | P100: 5372.6 | Q100: 4024.65 | R100: 3783.5 | S100: 3821.95 | T100: 5140 | U100: 79090.75
B101: KALLPA GENERACION S.A. | C101: C.T. LAS FLORES | D101: TG1 | E101: TERMOELÉCTRICA | F101: 4439.3 | G101: 4629.825 | H101: 4641.86 | I101: 4326.075 | J101: 4577.3 | K101: 4870.95 | L101: 4718 | M101: 4672.85 | N101: 4449.5 | O101: 3917.15 | P101: 4161.05 | Q101: 4568 | R101: 4201.75 | S101: 4558.65 | T101: 3633.05 | U101: 66365.31
B102: KALLPA GENERACION S.A. | C102: C.T. LAS FLORES | D102: TV | E102: TERMOELÉCTRICA | F102: 2384.2 | G102: 2455.11 | H102: 2476.415 | I102: 2347.8 | J102: 2457.3 | K102: 2561.15 | L102: 2502.95 | M102: 2484.8 | N102: 2396.7 | O102: 2167.3 | P102: 2269.45 | Q102: 2443.25 | R102: 2293.8 | S102: 2441.75 | T102: 2047.15 | U102: 35729.125
B103: KALLPA GENERACION S.A. | C103: M.C.H. CERRO DEL AGUILA | D103: CENTRAL | E103: HIDROELÉCTRICA | F103: 251.1 | G103: 229.035 | H103: 46.745 | I103: 252.15 | J103: 251.75 | K103: 253.75 | L103: 115.7 | M103: 57.4 | O103: 173.05 | P103: 252.15 | Q103: 210.1 | S103: 109.45 | T103: 250.9 | U103: 2453.28
...

Sheet G_AREAS
B3: sábado, 15 de Marzo del 2025
B5: HORA | C5: RESUMEN DE GENERACIÓN POR ÁREAS DEL SEIN | D5: RESUMEN DE GENERACIÓN POR ÁREAS DEL SEIN | E5: RESUMEN DE GENERACIÓN POR ÁREAS DEL SEIN | F5: RESUMEN DE GENERACIÓN POR ÁREAS DEL SEIN | G5: RESUMEN DE GENERACIÓN POR ÁREAS DEL SEIN | H5: RESUMEN DE GENERACIÓN POR ÁREAS DEL SEIN | I5: RESUMEN DE GENERACIÓN POR ÁREAS DEL SEIN | J5: RESUMEN DE GENERACIÓN POR ÁREAS DEL SEIN | K5: RESUMEN DE GENERACIÓN POR ÁREAS DEL SEIN | L5: RESUMEN DE GENERACIÓN POR ÁREAS DEL SEIN | M5: RESUMEN DE GENERACIÓN POR ÁREAS DEL SEIN | N5: RESUMEN DE GENERACIÓN POR ÁREAS DEL SEIN | O5: RESUMEN DE GENERACIÓN POR ÁREAS DEL SEIN | P5: RESUMEN DE GENERACIÓN POR ÁREAS DEL SEIN | Q5: RESUMEN DE GENERACIÓN POR ÁREAS DEL SEIN | R5: RESUMEN DE GENERACIÓN POR ÁREAS DEL SEIN | S5: HORA | T5: GENERACIÓN POR TIPO DE GENERACIÓN | U5: GENERACIÓN POR TIPO DE GENERACIÓN | V5: GENERACIÓN POR TIPO DE GENERACIÓN | W5: GENERACIÓN POR TIPO DE GENERACIÓN | X5: GENERACIÓN POR TIPO DE GENERACIÓN | Y5: HORA | Z5: GENERACIÓN POR TIPO DE GENERACIÓN | AA5: GENERACIÓN POR TIPO DE GENERACIÓN | AB5: GENERACIÓN POR TIPO DE GENERACIÓN | AC5: GENERACIÓN POR TIPO DE GENERACIÓN | AD5: GENERACIÓN POR TIPO DE GENERACIÓN
C6: NORTE | D6: NORTE | E6: NORTE | F6: NORTE | G6: CENTRO | H6: CENTRO | I6: CENTRO | J6: CENTRO | K6: SUR | L6: SUR | M6: SUR | N6: SUR | O6: GENERACIÓN INTEGRANTES COES | P6: GENERACIÓN INTEGRANTES COES | Q6: GENERACIÓN INTEGRANTES COES | R6: GENERACIÓN INTEGRANTES COES | T6: INTEGRANTES COES | U6: INTEGRANTES COES | V6: INTEGRANTES COES | W6: INTEGRANTES COES | X6: INTEGRANTES COES | Z6: INTEGRANTES COES RER | AA6: INTEGRANTES COES RER | AB6: INTEGRANTES COES RER | AC6: INTEGRANTES COES RER | AD6: INTEGRANTES COES RER
C7: GENERACIÓN HIDROELÉCTRICA NORTE | D7: GENERACIÓN TERMOELÉCTRICA NORTE | E7: GENERACIÓN SOLAR NORTE | F7: GENERACIÓN EÓLICA NORTE | G7: GENERACIÓN HIDROELÉCTRICA CENTRO | H7: GENERACIÓN TERMOELÉCTRICA CENTRO | I7: GENERACIÓN SOLAR CENTRO | J7: GENERACIÓN EÓLICA CENTRO | K7: GENERACIÓN HIDROELÉCTRICA SUR | L7: GENERACIÓN TERMOELÉCTRICA SUR | M7: GENERACIÓN SOLAR SUR | N7: GENERACIÓN EÓLICA SUR | O7: GENERACIÓN COES NORTE | P7: GENERACIÓN COES CENTRO | Q7: GENERACIÓN COES SUR | R7: TOTAL GENERACION | T7: HIDROELÉCTRICA | U7: TERMOELÉCTRICA | V7: SOLAR | W7: EÓLICA | X7: TOTAL GENERACION | Z7: HIDROELÉCTRICA RER | AA7: TERMOELÉCTRICA RER | AB7: SOLAR RER | AC7: EÓLICA RER | AD7: TOTAL RER
B8: 00:30 | C8: 346.9 | D8: 98.1 | E8: 0 | F8: 38 | G8: 3571.7 | H8: 1721.6 | I8: 0 | J8: 345 | K8: 604 | L8: 0 | M8: 0 | N8: 0 | O8: 483 | P8: 5638.3 | Q8: 604 | R8: 6725.3 | S8: 00:30 | T8: 4522.6 | U8: 1819.7 | V8: 0 | W8: 383 | X8: 6725.3 | Y8: 00:30 | Z8: 338.3 | AA8: 17.6 | AB8: 0 | AC8: 383 | AD8: 738.9
B9: 01:00 | C9: 346.3 | D9: 98.8 | E9: 0 | F9: 36.8 | G9: 3543.6 | H9: 1589.3 | I9: 0 | J9: 340.3 | K9: 604.3 | L9: 0 | M9: 0 | N9: 0 | O9: 481.9 | P9: 5473.2 | Q9: 604.3 | R9: 6559.4 | S9: 01:00 | T9: 4494.2 | U9: 1688.1 | V9: 0 | W9: 377.1 | X9: 6559.4 | Y9: 01:00 | Z9: 337.2 | AA9: 18.3 | AB9: 0 | AC9: 377.1 | AD9: 732.6
B10: 01:30 | C10: 350.6 | D10: 98.6 | E10: 0 | F10: 39.5 | G10: 3573.9 | H10: 1539.9 | I10: 0 | J10: 305.6 | K10: 611.4 | L10: 0 | M10: 0 | N10: 0 | O10: 488.7 | P10: 5419.4 | Q10: 611.4 | R10: 6519.5 | S10: 01:30 | T10: 4535.9 | U10: 1638.5 | V10: 0 | W10: 345.1 | X10: 6519.5 | Y10: 01:30 | Z10: 338.2 | AA10: 18.1 | AB10: 0 | AC10: 345.1 | AD10: 701.4
B11: 02:00 | C11: 348.2 | D11: 97.4 | E11: 0 | F11: 37 | G11: 3577.1 | H11: 1520.3 | I11: 0 | J11: 294.4 | K11: 604.5 | L11: 0 | M11: 0 | N11: 0 | O11: 482.6 | P11: 5391.8 | Q11: 604.5 | R11: 6478.9 | S11: 02:00 | T11: 4529.8 | U11: 1617.7 | V11: 0 | W11: 331.4 | X11: 6478.9 | Y11: 02:00 | Z11: 338.5 | AA11: 17.2 | AB11: 0 | AC11: 331.4 | AD11: 687.1
B12: 02:30 | C12: 350.9 | D12: 72.7 | E12: 0 | F12: 35 | G12: 3606.8 | H12: 1391.1 | I12: 0 | J12: 280.4 | K12: 617.6 | L12: 0 | M12: 0 | N12: 0 | O12: 458.6 | P12: 5278.3 | Q12: 617.6 | R12: 6354.5 | S12: 02:30 | T12: 4575.3 | U12: 1463.8 | V12: 0 | W12: 315.4 | X12: 6354.5 | Y12: 02:30 | Z12: 338 | AA12: 17.5 | AB12: 0 | AC12: 315.4 | AD12: 670.9
B13: 03:00 | C13: 343.8 | D13: 74 | E13: 0 | F13: 38.7 | G13: 3468.8 | H13: 1480.5 | I13: 0 | J13: 270.7 | K13: 602.9 | L13: 0 | M13: 0 | N13: 0 | O13: 456.5 | P13: 5220 | Q13: 602.9 | R13: 6279.4 | S13: 03:00 | T13: 4415.5 | U13: 1554.5 | V13: 0 | W13: 309.4 | X13: 6279.4 | Y13: 03:00 | Z13: 336.5 | AA13: 18 | AB13: 0 | AC13: 309.4 | AD13: 663.9
B14: 03:30 | C14: 344.2 | D14: 72.9 | E14: 0 | F14: 27.6 | G14: 3399.3 | H14: 1643.9 | I14: 0 | J14: 312.7 | K14: 606.3 | L14: 0 | M14: 0 | N14: 0 | O14: 444.7 | P14: 5355.9 | Q14: 606.3 | R14: 6406.9 | S14: 03:30 | T14: 4349.8 | U14: 1716.8 | V14: 0 | W14: 340.3 | X14: 6406.9 | Y14: 03:30 | Z14: 337.4 | AA14: 17.6 | AB14: 0 | AC14: 340.3 | AD14: 695.3
B15: 04:00 | C15: 342.8 | D15: 72.6 | E15: 0 | F15: 23.8 | G15: 3289 | H15: 1646 | I15: 0 | J15: 342.2 | K15: 606.6 | L15: 0 | M15: 0 | N15: 0 | O15: 439.2 | P15: 5277.2 | Q15: 606.6 | R15: 6323 | S15: 04:00 | T15: 4238.4 | U15: 1718.6 | V15: 0 | W15: 366 | X15: 6323 | Y15: 04:00 | Z15: 336.7 | AA15: 18 | AB15: 0 | AC15: 366 | AD15: 720.7
B16: 04:30 | C16: 346.9 | D16: 71.9 | E16: 0 | F16: 25.3 | G16: 3418 | H16: 1475.6 | I16: 0 | J16: 348.1 | K16: 603.3 | L16: 0 | M16: 0 | N16: 0 | O16: 444.1 | P16: 5241.7 | Q16: 603.3 | R16: 6289.1 | S16: 04:30 | T16: 4368.2 | U16: 1547.5 | V16: 0 | W16: 373.4 | X16: 6289.1 | Y16: 04:30 | Z16: 339.7 | AA16: 18.1 | AB16: 0 | AC16: 373.4 | AD16: 731.2
B17: 05:00 | C17: 346.9 | D17: 72.5 | E17: 0 | F17: 29.5 | G17: 3488.1 | H17: 1480.6 | I17: 0 | J17: 366.9 | K17: 612.1 | L17: 0 | M17: 0 | N17: 0 | O17: 448.9 | P17: 5335.6 | Q17: 612.1 | R17: 6396.6 | S17: 05:00 | T17: 4447.1 | U17: 1553.1 | V17: 0 | W17: 396.4 | X17: 6396.6 | Y17: 05:00 | Z17: 343.3 | AA17: 17.9 | AB17: 0 | AC17: 396.4 | AD17: 757.6
B18: 05:30 | C18: 346.1 | D18: 72 | E18: 0 | F18: 31.6 | G18: 3500.2 | H18: 1482.8 | I18: 0 | J18: 319.6 | K18: 553.2 | L18: 0 | M18: 0 | N18: 0 | O18: 449.7 | P18: 5302.6 | Q18: 553.2 | R18: 6305.5 | S18: 05:30 | T18: 4399.5 | U18: 1554.8 | V18: 0 | W18: 351.2 | X18: 6305.5 | Y18: 05:30 | Z18: 289.7 | AA18: 17.2 | AB18: 0 | AC18: 351.2 | AD18: 658.1
B19: 06:00 | C19: 347.9 | D19: 73 | E19: 0 | F19: 30.6 | G19: 3553.2 | H19: 1646.5 | I19: 0 | J19: 307 | K19: 477.4 | L19: 0 | M19: 9.6 | N19: 0 | O19: 451.5 | P19: 5506.7 | Q19: 487 | R19: 6445.2 | S19: 06:00 | T19: 4378.5 | U19: 1719.5 | V19: 9.6 | W19: 337.6 | X19: 6445.2 | Y19: 06:00 | Z19: 281.7 | AA19: 18.3 | AB19: 9.6 | AC19: 337.6 | AD19: 647.2
... B56: TOTAL MWh | C56: 8367.8 | D56: 1923.8 | E56: 1.95 | F56: 1275.6 | G56: 83817.1 | H56: 45931.85 | I56: 5 | J56: 12086.5 | K56: 13049.5 | L56: 0 | M56: 4295.7 | N56: 0 | O56: 11569.15 | P56: 141840.45 | Q56: 17345.2 | R56: 170754.8 | S56: TOTAL MWh | T56: 105234.4 | U56: 47855.65 | V56: 4302.65 | W56: 13362.1 | X56: 170754.8 | Y56: TOTAL MWh | Z56: 7294.95 | AA56: 625.3 | AB56: 4302.65 | AC56: 13362.1 | AD56: 25585

Sheet HOP
B3: sábado, 15 de Marzo del 2025
B5: Reporte de Horas de Operación
B6: Empresa | C6: Central | D6: Grupo | E6: Modo de Operación | F6: Inicio | G6: Final | H6: O. Arranque | I6: O. Parada | J6: Tipo Operación | K6: Ensayo de Potencia Efectiva | L6: Ensayo de Potencia Mínima | M6: Sistema | N6: Lim. Transm. | O6: Causa | P6: Observación
B7: AGRO INDUSTRIAL PARAMONGA S.A. | C7: C.T. PARAMONGA | D7: CENTRAL | E7: PARAMONGA - BAGAZO | F7: 15/03/2025 18:47:00 | G7: 16/03/2025 00:00:00 | H7: 15/03/2025 18:44:00 | J7: POR COGENERACION | O7: ...
B8: AGROAURORA S.A.C. | C8: C.T. MAPLE ETANOL | D8: CENTRAL | E8: MAPLE- BAGAZO | F8: 15/03/2025 10:11:00 | G8: 16/03/2025 00:00:00 | J8: POR COGENERACION | O8: ...
B9: AGROINDUSTRIAS SAN JACINTO S.A.A. | C9: C.T. SAN JACINTO | D9: CENTRAL | E9: SAN_JACINTO - BAGAZO | F9: 15/03/2025 00:00:00 | G9: 16/03/2025 00:00:00 | J9: POR COGENERACION | O9: ...
B10: ENEL GENERACION PIURA S.A. | C10: C.T. MALACAS 2 | D10: CENTRAL | E10: MALACAS2 TG4 - GAS | F10: 15/03/2025 00:00:00 | G10: 15/03/2025 02:15:00 | I10: 15/03/2025 02:10:00 | J10: A MINIMA CARGA | O10: ...
B11: ENGIE | C11: C.T. CHILCA 1 | D11: CENTRAL | E11: CHILCA1 CCOMB TG1 & TG2 & TG3 - GAS | F11: 15/03/2025 00:00:00 | G11: 15/03/2025 02:00:00 | J11: POR POTENCIA O ENERGIA | O11: ...
B12: ENGIE | C12: C.T. CHILCA 1 | D12: CENTRAL | E12: CHILCA1 CCOMB TG1 & TG2 & TG3 - GAS | F12: 15/03/2025 02:00:00 | G12: 15/03/2025 08:00:00 | J12: POR RSF | O12: ...
B13: ENGIE | C13: C.T. CHILCA 1 | D13: CENTRAL | E13: CHILCA1 CCOMB TG1 & TG2 & TG3 - GAS | F13: 15/03/2025 08:00:00 | G13: 16/03/2025 00:00:00 | J13: POR POTENCIA O ENERGIA | O13: ... | P13: A las 16:01 h, S/C generar a 650 MW
B14: FENIX POWER PERÚ | C14: C.T. FENIX | D14: CENTRAL | E14: FENIX CCOMB GT11 & GT12 - GAS | F14: 15/03/2025 00:00:00 | G14: 15/03/2025 00:41:00 | I14: 15/03/2025 00:01:00 | J14: A MINIMA CARGA | O14: ...
B15: FENIX POWER PERÚ | C15: C.T. FENIX | D15: CENTRAL | E15: FENIX CCOMB GT12 - GAS | F15: 15/03/2025 00:41:00 | G15: 15/03/2025 10:29:00 | J15: A MINIMA CARGA | O15: ...
B16: FENIX POWER PERÚ | C16: C.T. FENIX | D16: GT11 | E16: FENIX GT11 - GAS | F16: 15/03/2025 00:41:00 | G16: 15/03/2025 00:42:00 | J16: A MINIMA CARGA | O16: ...
B17: FENIX POWER PERÚ | C17: C.T. FENIX | D17: CENTRAL | E17: FENIX CCOMB GT12 - GAS | F17: 15/03/2025 10:29:00 | G17: 15/03/2025 13:07:00 | J17: POR POTENCIA O ENERGIA | O17: ...
B18: FENIX POWER PERÚ | C18: C.T. FENIX | D18: CENTRAL | E18: FENIX CCOMB GT12 - GAS | F18: 15/03/2025 13:07:00 | G18: 15/03/2025 18:14:00 | J18: A MINIMA CARGA | O18: ...
B19: FENIX POWER PERÚ | C19: C.T. FENIX | D19: CENTRAL | E19: FENIX CCOMB GT12 - GAS | F19: 15/03/2025 18:14:00 | G19: 15/03/2025 22:36:00 | J19: POR POTENCIA O ENERGIA | O19: ...
B20: FENIX POWER PERÚ | C20: C.T. FENIX | D20: CENTRAL | E20: FENIX CCOMB GT12 - GAS | F20: 15/03/2025 22:36:00 | G20: 15/03/2025 23:23:00 | J20: A MINIMA CARGA | O20: ...
B21: FENIX POWER PERÚ | C21: C.T. FENIX | D21: GT12 | E21: FENIX GT12 - GAS | F21: 15/03/2025 23:23:00 | G21: 15/03/2025 23:26:00 | J21: A MINIMA CARGA | O21: ... | P21: En proceso de parada
B22: GM OPERACIONES S.A.C. | C22: CT REFINERIA TALARA | D22: TV1 REF TALARA | E22: REF_TALARA TV1 - NLH_RFG | F22: 15/03/2025 00:00:00 | G22: 16/03/2025 00:00:00 | J22: POR COGENERACION | O22: ...
B23: GM OPERACIONES S.A.C. | C23: CT REFINERIA TALARA | D23: TV2 REF TALARA | E23: REF_TALARA TV2 - NLH_RFG | F23: 15/03/2025 00:00:00 | G23: 16/03/2025 00:00:00 | J23: POR COGENERACION | O23: ...
B24: KALLPA GENERACION S.A. | C24: C.T. KALLPA | D24: CENTRAL | E24: KALLPA CCOMB TG1 & TG3 - GAS | F24: 15/03/2025 00:00:00 | G24: 15/03/2025 02:37:00 | J24: A MINIMA CARGA | O24: ...
B25: KALLPA GENERACION S.A. | C25: C.T. KALLPA | D25: TG2 | E25: KALLPA TG2 - GAS | F25: 15/03/2025 01:31:00 | G25: 15/03/2025 02:37:00 | H25: 15/03/2025 00:45:00 | J25: POR PRUEBAS | O25: REQ. PROPIO
B26: KALLPA GENERACION S.A. | C26: C.T. KALLPA | D26: CENTRAL | E26: KALLPA CCOMB TG1 & TG2 & TG3 - GAS | F26: 15/03/2025 02:37:00 | G26: 15/03/2025 04:10:00 | J26: POR PRUEBAS | O26: REQ. PROPIO
B27: KALLPA GENERACION S.A. | C27: C.T. KALLPA | D27: CENTRAL | E27: KALLPA CCOMB TG1 & TG2 & TG3 - GAS | F27: 15/03/2025 04:10:00 | G27: 15/03/2025 08:00:00 | J27: A MINIMA CARGA | O27: ...
B28: KALLPA GENERACION S.A. | C28: C.T. KALLPA | D28: CENTRAL | E28: KALLPA CCOMB TG1 & TG2 & TG3 - GAS | F28: 15/03/2025 08:00:00 | G28: 15/03/2025 11:30:00 | J28: POR RSF | O28: ...
B29: KALLPA GENERACION S.A. | C29: C.T. KALLPA | D29: CENTRAL | E29: KALLPA CCOMB TG1 & TG2 & TG3 - GAS | F29: 15/03/2025 11:30:00 | G29: 15/03/2025 12:45:00 | J29: POR POTENCIA O ENERGIA | O29: ...
B30: KALLPA GENERACION S.A. | C30: C.T. KALLPA | D30: CENTRAL | E30: KALLPA CCOMB TG1 & TG2 & TG3 - GAS | F30: 15/03/2025 12:45:00 | G30: 15/03/2025 18:23:00 | J30: POR RSF | O30: ...
B31: KALLPA GENERACION S.A. | C31: C.T. KALLPA | D31: CENTRAL | E31: KALLPA CCOMB TG1 & TG2 & TG3 - GAS | F31: 15/03/2025 18:23:00 | G31: 15/03/2025 22:00:00 | J31: POR POTENCIA O ENERGIA | O31: ...
B32: KALLPA GENERACION S.A. | C32: C.T. KALLPA | D32: CENTRAL | E32: KALLPA CCOMB TG1 & TG2 & TG3 - GAS | F32: 15/03/2025 22:00:00 | G32: 16/03/2025 00:00:00 | J32: POR RSF | O32: ...
B33: KALLPA GENERACION S.A. | C33: C.T. LAS FLORES | D33: CENTRAL | E33: LAS FLORES CCOMB TG1 - GAS | F33: 15/03/2025 00:00:00 | G33: 15/03/2025 08:54:00 | J33: A MINIMA CARGA | O33: ...
B34: KALLPA GENERACION S.A. | C34: C.T. LAS FLORES | D34: CENTRAL | E34: LAS FLORES CCOMB TG1 - GAS | F34: 15/03/2025 08:54:00 | G34: 15/03/2025 13:09:00 | J34: POR POTENCIA O ENERGIA | O34: ...
B35: KALLPA GENERACION S.A. | C35: C.T. LAS FLORES | D35: CENTRAL | E35: LAS FLORES CCOMB TG1 - GAS | F35: 15/03/2025 13:09:00 | G35: 15/03/2025 14:53:00 | J35: A MINIMA CARGA | O35: ...
B36: KALLPA GENERACION S.A. | C36: C.T. LAS FLORES | D36: CENTRAL | E36: LAS FLORES CCOMB TG1 - GAS | F36: 15/03/2025 14:53:00 | G36: 15/03/2025 15:37:00 | J36: POR POTENCIA O ENERGIA | O36: ...
B37: KALLPA GENERACION S.A. | C37: C.T. LAS FLORES | D37: CENTRAL | E37: LAS FLORES CCOMB TG1 - GAS | F37: 15/03/2025 15:37:00 | G37: 15/03/2025 18:12:00 | J37: A MINIMA CARGA | O37: ...
... B47: SDF ENERGIA SAC | C47: C.T. OQUENDO | D47: CENTRAL | E47: OQUENDO CCOMB TG1 - GAS | F47: 15/03/2025 00:00:00 | G47: 16/03/2025 00:00:00 | J47: POR COGENERACION | O47: ...
B48: TERMOSELVA | C48: C.T. AGUAYTIA | D48: TG1 | E48: AGUAYTIA TG1 - GAS | F48: 15/03/2025 00:00:00 | G48: 15/03/2025 00:06:00 | I48: 15/03/2025 00:01:00 | J48: A MINIMA CARGA | O48: ...

Sheet INDISP
B3: sábado, 15 de Marzo del 2025
B5: Hora Inicio y Fin de Indisponibilidades de las Unidades de Generación SEIN
B6: Empresa | C6: Ubicación | D6: Equipo | E6: Inicio | F6: Final | G6: Descripción | H6: MW Indisp. | I6: Prog. | J6: Dispon | K6: Interrupc. | L6: Tipo | M6: CodEq | N6: TipoEq_Osinerg
B7: AGRO INDUSTRIAL PARAMONGA S.A. | C7: PARAMONGA | D7: TV-01 | E7: 15/03/2025 00:00 | F7: 15/03/2025 18:44 | G7: LIMPIEZA E INSPECCIÓN DE LA CALDERA CBS Y MANTENIMIENTO A SUS PERIFÉRICOS (CONDUCTORES, VENTILADORES, BOMBAS, MOTORES, ETC) | H7: 14 | I7: P | J7: F/S | K7: N | L7: PREV. | M7: 12664 | N7: G
B8: BIOENERGIA DEL CHIRA S.A. | C8: CAÑA BRAVA | D8: CENTRAL | E8: 15/03/2025 00:00 | F8: 16/03/2025 00:00 | G8: Para Central Caña Brava debido a mantenimiento anual preventivo | H8: 12 | I8: P | J8: F/S | K8: N | L8: PREV. | M8: 20510 | N8: G
B9: CELEPSA RENOVABLES S.R.L. | C9: MARAÑON | D9: G3 | E9: 15/03/2025 06:47 | F9: 15/03/2025 17:49 | G9: Mantenimiento semestral | H9: 6.6 | I9: P | J9: F/S | K9: N | L9: PREV. | M9: 17495 | N9: G
B10: EGASA | C10: CHARCANI IV | D10: G2 | E10: 15/03/2025 00:00 | F10: 16/03/2025 00:00 | G10: Mantenimiento Generador | H10: 5.1 | I10: P | J10: F/S | K10: N | L10: PREV. | M10: 119 | N10: G
B11: EGASA | C11: CHARCANI IV | D11: CENTRAL | E11: 15/03/2025 09:36 | F11: 15/03/2025 12:44 | G11: Descolmatación desarenador Charcani VI | H11: 8 | I11: P | J11: F/S | K11: N | L11: PREV. | M11: 1198 | N11: G
B12: EGASA | C12: CHARCANI VI | D12: CENTRAL | E12: 15/03/2025 06:43 | F12: 15/03/2025 13:17 | G12: Descolmatación desarenador Charcani VI | H12: 8.9 | I12: P | J12: F/S | K12: N | L12: PREV. | M12: 1200 | N12: G
B13: EGESUR | C13: INDEPENDENCIA | D13: INDEP_G4 | E13: 15/03/2025 00:00 | F13: 16/03/2025 00:00 | G13: Mantenimiento Correctivo por fatiga en la leva del cilindro A8 - 1ra ampliación | H13: 5.732 | I13: P | J13: F/S | K13: N | L13: CORR. | M13: 12780 | N13: G
B14: EMPRESA DE GENERACION HUALLAGA | C14: PCH CHAGLLA | D14: GP1 | E14: 15/03/2025 08:05 | F14: 15/03/2025 17:00 | G14: F/S POR MANTENIMIENTO PARARAYOS EN L-1054 | H14: 0 | I14: P | J14: F/S | K14: N | L14: PREV. | M14: 15564 | N14: G
B15: ENGIE | C15: QUITARACSA | D15: CENTRAL | E15: 15/03/2025 00:00 | F15: 16/03/2025 00:00 | G15: FUERA DE SERVICIO DEBIDO A INDISPONIBILIDAD BOCATOMA QUITARACSA Y SAN MATEO POR CAIDA DE ROCAS EN LA ZONA. NO SE PUEDE CAPTAR AGUA EN LA CONDICION PRESENTADA | H15: 110 | I15: P | J15: F/S | K15: N | L15: OTROS | M15: 14448 | N15: G
B16: ENGIE | C16: YUNCÁN | D16: G2 | E16: 15/03/2025 00:00 | F16: 16/03/2025 00:00 | G16: MANTENIMIENTO CORRECTIVO DEL GENERADOR | H16: 45.5 | I16: P | J16: F/S | K16: N | L16: CORR. | M16: 200 | N16: G
B17: GM OPERACIONES S.A.C. | C17: REFINERIA TALARA | D17: CENTRAL | E17: 15/03/2025 00:00 | F17: 16/03/2025 00:00 | G17: INDISPONIBLE POR FALTA DE SUMINISTRO DE AGUA DE MAR EN LA REFINERÍA TALARA A CARGO DE PETROPERU. | H17: 0 | I17: P | J17: F/S | K17: N | L17: OTROS | M17: 22187 | N17: G
B18: KALLPA GENERACION S.A. | C18: CERRO DEL AGUILA | D18: G1 | E18: 15/03/2025 00:00 | F18: 16/03/2025 00:00 | G18: Unidad indisponible por fuga de agua en los bujes de la turbina. | H18: 0 | I18: P | J18: F/S | K18: N | L18: CORR. | M18: 15211 | N18: G
... B28: SHOUGESA | C28: SAN NICOLÁS | D28: TV3 | E28: 15/03/2025 00:00 | F28: 16/03/2025 00:00 | G28: Por mantenimiento anual | H28: 24.425 | I28: P | J28: F/S | K28: N | L28: PREV. | M28: 60 | N28: G

Sheet RESERVA_FRÍA
B3: 15/03/2025 | E3: EJECUTADO | L3: Sábado 15 de Marzo del 2025 / SEM N° 11 | V3: EJECUTADO | AC3: Sábado 15 de Marzo del 2025 / SEM N° 11 | ED3: ENERGIA RENOVABLES | GN3: COGENERACION | GW3: NO INTEGRANTES
B4: Sábado | C4: STARO | E4: ELECTROPERU | I4: ORAZU | K4: TER | M4: KALLPA GENERACION S.A. | U4: SHOUGESA | Y4: EGM | Z4: EGESUR | AC4: EGASA | AJ4: SGB | AK4: CELEP | AL4: MINCVE | AM4: ETEN | AO4: HUALLA | AQ4: LAVI | AR4: CHIN | AT4: HUANCH | AU4: CELER | AV4: INLD | AW4: FENIX POWER PERÚ | AZ4: STATKRAFT S.A | BH4: HUANZA | BI4: ENEL GENERACION PIURA S.A. | BL4: ENGIE | BZ4: IYEP | CB4: SHAQSH | CC4: ORYGEN PERU S.A.A. | CO4: SAMAY I S.A.C | CS4: TCHILC | CU4: GENERACION | CX4: SALIDAS YUPANA | DB4: FLUJO EN LINEAS | DN4: COSTOS MARGINALES | DR4: RESERVA | DW4: DEMANDA POR AREAS | ED4: ACHI | EE4: COLCA | EF4: ERSUR | EG4: GRCOR | EH4: TARU | EI4: KONDU | EJ4: PIEREN | EK4: ORAZU | EM4: SGB | EN4: AIPSA | EO4: MAJA | EP4: EGECSA | EQ4: STANA | ER4: AGUAA | ES4: RDOBLE | ET4: HIDRO | EU4: HUARA | EV4: MOQUE | EW4: PANAM | EX4: PARQU | EY4: PE3HER | EZ4: PETRAMAS | FD4: TACNA | FE4: EYSAC | FF4: AURORA | FG4: AGROIN | FH4: ANDEA | FI4: ASLC | FJ4: ATRIA | FK4: EGEJUNIN | FO4: EGERBA | FP4: EOL | FR4: ENGIE | FW4: GENE | FY4: GENERADORA DE ENERGÍA DEL PERÚ | GC4: PAINO | GD4: SARCUS | GE4: ORYGEN PERU S.A.A. | GJ4: RARCUS | GK4: SINERS | GN4: ACHI | GO4: GM OP | GQ4: SDF | GS4: AIPSA | GT4: AURORA | GU4: AGROIN | GW4: UNACEM | GX4: EOR | GY4: AYEP | GZ4: ELZANA | HA4: ENOSA | HB4: SDE | HC4: SINERS | HF4: RESERVA
C5: 337 | D5: 338 | E5: 101 | F5: 102 | G5: 42667 | H5: 42668 | I5: 126 | J5: 127 | K5: 138 | L5: 139 | M5: 197 | N5: 203 | O5: 204 | P5: 230 | Q5: 209 | R5: 56677 | S5: 796 | T5: 2146 | U5: 142 | V5: 143 | W5: 125 | X5: 187 | Y5: 163 | Z5: 298 | AA5: 299 | AB5: 219 | AC5: 151 | AD5: 152 | AE5: 153 | AF5: 154 | AG5: 756 | AH5: 156 | AI5: 155 | AJ5: 182 | AK5: 212 | AL5: 758 | AM5: 263 | AN5: 265 | AO5: 775 | AP5: 777 | AQ5: 2154 | AR5: 150 | AS5: 149 | AT5: 188 | AU5: 2131 | AV5: 755 | AW5: 252 | AX5: 249 | AY5: 250 | AZ5: 117 | BA5: 267 | BB5: 268 | BC5: 119 | BD5: 120 | BE5: 189 | BF5: 122 | BG5: 266 | BH5: 251 | BI5: 115 | BJ5: 239 | BK5: 288 | BL5: 240 | BM5: 241 | BN5: 242 | BO5: 191 | BP5: 194 | BQ5: 196 | BR5: 207 | BS5: 236 | BT5: 795 | BU5: 285 | BV5: 995 | BW5: 996 | BX5: 997 | BY5: 766 | BZ5: 926 | CA5: 924 | CB5: 121 | CC5: 103 | CD5: 104 | CE5: 106 | CF5: 105 | CG5: 107 | CH5: 110 | CI5: 109 | CJ5: 144 | CK5: 113 | CL5: 114 | CM5: 193 | CN5: 208 | CO5: 786 | CP5: 787 | CQ5: 788 | CR5: 789 | CS5: 248 | CT5: 2159 | CU5: -1222 | CV5: -1223 | CW5: -1224 | CX5: 1221 | CY5: 1222 | CZ5: 1223 | DA5: 1224 | DB5: 1250 | DC5: 1251 | DD5: 1252 | DE5: 1253 | DF5: 1254 | DG5: 1255 | DH5: 1256 | DI5: 1257 | DJ5: 1258 | DK5: 1259 | DL5: 1260 | DM5: 1261 | DN5: 1226 | DO5: 1219 | DP5: 1220 | DQ5: -1203 | DR5: 1227 | DS5: 1205 | DT5: 1207 | DU5: 1206 | DV5: 1218 | DW5: 1211 | DX5: 1212 | DY5: 1213 | DZ5: 1214 | EA5: 1229 | EB5: -1221 | ED5: 289 | EE5: 303 | EF5: 59715 | EG5: 62255 | EH5: 1263 | EI5: 61800 | EJ5: 2194 | EK5: 216 | EL5: 198 | EM5: 49607 | EN5: 213 | EO5: 214 | EP5: 260 | EQ5: 2152 | ER5: 2128 | ES5: 247 | ET5: 228 | EU5: 2135 | EV5: 261 | EW5: 237 | EX5: 253 | EY5: 770 | EZ5: 225 | FA5: 2201 | FB5: 2171 | FC5: 760 | FD5: 235 | FE5: 238 | FF5: 232 | FG5: 2190 | FH5: 2184 | FI5: 61855 | FJ5: 223 | FK5: 226 | FL5: 201 | FM5: 258 | FN5: 259 | FO5: 920 | FP5: 257 | FQ5: 256 | FR5: 2148 | FS5: 58288 | FT5: 58289 | FU5: 58839 | FV5: 58840 | FW5: 296 | FX5: 297 | FY5: 211 | FZ5: 2175 | GA5: 2178 | GB5: 2181 | GC5: 1262 | GD5: 233 | GE5: 2150 | GF5: 2165 | GG5: 2161 | GH5: 61197 | GI5: 58851 | GJ5: 234 | GK5: 215 | GL5: 917 | GN5: 289 | GO5: 58333 | GP5: 58336 | GQ5: 202 | GR5: 58487 | GS5: 213 | GT5: 232 | GU5: 2190 | GW5: 221 | GX5: 222 | GY5: 224 | GZ5: 2187 | HA5: 227 | HB5: 49400 | HC5: 199 | HD5: 200 | HF5: 7000 | HG5: 7001 | HH5: 7002
