Workbook

Sheet EVENTOS
B3: sábado, 25 de Enero del 2025
B5: INFORMACIÓN DE EVENTOS PRINCIPALES EN SUS INSTALACIONES
B6: TIPO DE EVENTO | C6: EMPRESA | D6: UBICACIÓN | E6: TIPO DE EQUIPO | F6: EQUIPO | G6: INICIO | H6: FINAL | I6: DESCRIPCIÓN | J6: MW INDISP. | K6: INTERRUPCIÓN (SI/NO) | L6: TENSIÓN DE FALLA (kV)
B7: EVENTO | C7: CONELSUR LT SAC | D7: PORTILLO | E7: SUBESTACION | F7: SS.EE. | G7: 25/01/2025 00:00:00 | H7: 26/01/2025 00:00:00 | I7: DECLARACIÓN DE SITUACIÓN EXCEPCIONAL EN LA S.E. PORTILLO DE 60 kV | K7: NO
B8: FALLA | C8: EMPRESA ELECTRICA AGUA AZUL | D8: POTRERO | E8: CENTRAL HIDROELÉCTRICA | F8: CENTRAL | G8: 25/01/2025 21:05:00 | H8: 25/01/2025 21:22:00 | I8: DESCONEXIÓN DEL GENERADOR G1 DE LA C.H. POTRERO POR FALLA | K8: NO | L8: 10
B9: FALLA | C9: HUAURA POWER GROUP S.A. | D9: YARUCAYA | E9: CENTRAL HIDROELÉCTRICA | F9: CENTRAL | G9: 25/01/2025 10:10:00 | H9: 25/01/2025 11:18:00 | I9: DESCONEXIÓN DEL GENERADOR G1 DE LA C.H. YARUCAYA POR FALLA | K9: NO | L9: 13.8
B10: EVENTO | C10: RED DE ENERGIA DEL PERU S.A. | D10: TINGO MARÍA - AUCAYACU | E10: LINEA DE TRANSMISION | F10: L-1122 | G10: 25/01/2025 19:05:00 | H10: 25/01/2025 20:30:00 | I10: DECLARACIÓN DE SITUACIÓN EXCEPCIONAL EN LA LÍNEA L-1122 (TINGO MARÍA - AUCAYACU) DE 138 KV | K10: NO
B11: FALLA | C11: RED DE ENERGIA DEL PERU S.A. | D11: TRUJILLO NORTE - CHIMBOTE 1 | E11: LINEA DE TRANSMISION | F11: L-2233 | G11: 25/01/2025 10:48:00 | H11: 26/01/2025 00:00:00 | I11: DESCONEXIÓN DE LA LÍNEA L-2233 (CHIMBOTE 1 - TRUJILLO NORTE) DE 220 kV POR FALLA | K11: NO | L11: 220
B12: FALLA | C12: RED DE ENERGIA DEL PERU S.A. | D12: TRUJILLO NORTE | E12: SVC | F12: SVC-1 | G12: 25/01/2025 21:08:00 | H12: 25/01/2025 22:51:00 | I12: DESCONEXIÓN DEL SVC-1 DE LA S.E. TRUJILLO NORTE POR FALLA | K12: NO | L12: 0
B13: FALLA | C13: TRANSMANTARO | D13: COTARUSE | E13: BANCO DE CONDENSADORES SERIE | F13: CAPAC XC1 | G13: 25/01/2025 15:15:00 | H13: 25/01/2025 17:33:00 | I13: DESCONEXIÓN DEL BANCO SERIE XC1 DE LA S.E. COTARUSE POR FALLA | K13: NO | L13: 0

Sheet RESTRIC_OPE
B3: sábado, 25 de Enero del 2025
B5: RESTRICCIONES OPERATIVAS
B6: FECHA | C6: HORA INICIO | D6: HORA FINAL | E6: EMPRESA | F6: UBICACIÓN | G6: T.Eq. | H6: EQUIPO | I6: DESCRIPCIÓN
B7: 25/01/2025 | C7: 00:00 | D7: 24:00 | E7: CELEPSA | F7: C.H. EL PLATANAL | G7: CH | H7: CENTRAL | I7: Debido al incremento del caudal del rio cañete y establecimiento de la temporada de avenida, se declara la C.H. El Platanal como CENTRAL HIDRÁULICA DE PASADA (correo 03/01/2025).
B8: 25/01/2025 | C8: 00:00 | D8: 24:00 | E8: EGASA | F8: S.E. CONVERTIDOR | G8: BARRA | H8: BARRA138KV | I8: EGASA limitó la capacidad del transformador 138 kV/33 kV a 50 MVA por deterioro del aislamiento.
B9: 25/01/2025 | C9: 00:00 | D9: 24:00 | E9: ENEL GENERACION PIURA S.A. | F9: C.T. MALACAS | G9: CT | H9: CENTRAL | I9: De acuerdo con la comunicación vía correo del día 24.10.2024. ENEL GENERACIÓN PIURA informa una restricción de potencia para alcanzar 105 MW en simultaneo (TG6+TGN4).
B10: 25/01/2025 | C10: 00:00 | D10: 24:00 | E10: ENGIE | F10: C.E. PUNTA LOMITAS | G10: CE | H10: CENTRAL | I10: De acuerdo a la carta ENG/737-2024 (Exp:202400007555). Limitación de cables de media tensión a 100 MW de los transformadores PLT1 y PLT2 de la CE Punta Lomitas. Quedan limitados a 200 MW la generación de CE Punta Lomitas y Punta Lomitas Extensión.
B11: 25/01/2025 | C11: 00:00 | D11: 24:00 | E11: ENGIE | F11: C.H. QUITARACSA | G11: CH | H11: CENTRAL | I11: De acuerdo con el correo del 23.04 se considera la operación continua de la CH Quitaracsa debido a que el sistema de refrigeración de la CH Cañón del Pato se alimenta desde la descarga del caudal turbinado por la CH Quitaracsa.
B12: 25/01/2025 | C12: 00:00 | D12: 24:00 | E12: ENGIE | F12: C.H. YUNCÁN | G12: GH | H12: G3 | I12: Según la carta N° ENG/ 198-2024 enviada por su representada, se opera de forma continua el G3 de la CH Yuncán, debido a la ejecución de mantenimientos necesarios para evitar daños en los sellos de seguridad de la válvula esférica del grupo.
B13: 25/01/2025 | C13: 00:00 | D13: 24:00 | E13: ENGIE | F13: C.T. CHILCA 1 | G13: CT | H13: CENTRAL | I13: Restricción de temperatura de la C.T Chilca, ver valor en el modelo de despacho.
B14: 25/01/2025 | C14: 00:00 | D14: 24:00 | E14: ENGIE | F14: C.T. CHILCA 1 | G14: CT | H14: CENTRAL | I14: Con carta ENG/971-2023, indica que no puede cumplir con las IO considerada en el PDO_17122023 dado que vulneran la seguridad de sus activos. Indican que se debe tomar TMO=168h.
B15: 25/01/2025 | C15: 00:00 | D15: 24:00 | E15: ENGIE | F15: C.T. CHILCA 2 | G15: CT | H15: CENTRAL | I15: Restricción de temperatura de la C.T Chilca2, ver valor en el modelo de despacho.
B16: 25/01/2025 | C16: 00:00 | D16: 24:00 | E16: ENGIE | F16: C.T. CHILCA 2 | G16: CT | H16: CENTRAL | I16: Con carta ENG/971-2023, indica que no puede cumplir con las IO considerada en el PDO_17122023 dado que vulneran la seguridad de sus activos. Indican que se debe tomar TMO=168h.
B17: 25/01/2025 | C17: 00:00 | D17: 24:00 | E17: FENIX POWER PERÚ | F17: C.T. FENIX | G17: CT | H17: CENTRAL | I17: Restricción de temperatura de la CT FENIX, ver valor en el modelo de despacho
... B41: 25/01/2025 | C41: 00:00 | D41: 24:00 | E41: TRANSMANTARO | F41: S.E. SOCABAYA | G41: SSEE | H41: S.E. | I41: Opera en simple barra en 220 kV por indisponibilidad de la protección diferencial de barras por alarma.

Sheet MANTENIMIENTO EJECUTADOS
B3: sábado, 25 de Enero del 2025
B5: Mantenimiento Ejecutado
B6: Empresa | C6: Ubicación | D6: Equipo | E6: Inicio | F6: Final | G6: Descripción | H6: MW Indisp. | I6: Prog. | J6: Dispon | K6: Interrupc. | L6: Tipo | M6: CodEq | N6: TipoEq_Osinerg
B7: ATLANTICA TRANSMISION SUR S.A. | C7: CHILCA-CTM | D7: INT-5261 | E7: 25/01/2025 00:00 | F7: 26/01/2025 00:00 | G7: Seccionador SBB-5261 fase S indisponible para maniobras de apertura y cierre por anomalia en tapa de tanque de compresion, el seccionador permanece cerrado y bloqueado. | H7: 0 | I7: P | J7: E/S | K7: N | L7: OTROS | M7: 13854 | N7: T
B8: ATLANTICA TRANSMISION SUR S.A. | C8: OCONA | D8: INT-5450 | E8: 25/01/2025 00:00 | F8: 26/01/2025 00:00 | G8: RESTRICCION OPERATIVA EN INTERRUPTOR INT-5450, POSICION CERRADA, REB-5450 EN SERVICIO SUMINISTRANDO LOS SS.AA. DE S.E. OCO?A | H8: 0 | I8: P | J8: E/S | K8: N | L8: OTROS | M8: 13761 | N8: T
B9: ATLANTICA TRANSMISION SUR S.A. | C9: OCONA | D9: INT-5462 | E9: 25/01/2025 00:00 | F9: 26/01/2025 00:00 | G9: Seccionador SBA-5462 fase T indisponible por problemas mecanicos, el seccionador permanece cerrado y bloqueado | H9: 0 | I9: P | J9: E/S | K9: N | L9: OTROS | M9: 13758 | N9: T
B10: ATLANTICA TRANSMISION SUR S.A. | C10: OCONA | D10: CL- 5034 | E10: 25/01/2025 08:00 | F10: 25/01/2025 16:00 | G10: Pruebas de mando de los equipos del BCS-5482, REL-5481 y otros por cambio de RTU. | H10: 0 | I10: P | J10: F/S | K10: N | L10: PREV. | M10: 13800 | N10: T
B11: ATLANTICA TRANSMISION SUR S.A. | C11: OCONA | D11: CL-REB-5450 | E11: 25/01/2025 08:00 | F11: 25/01/2025 16:00 | G11: Pruebas de mando de los equipos SBA-5450 e INT-5450 por cambio de RTU. | H11: 0 | I11: P | J11: F/S | K11: N | L11: PREV. | M11: 13803 | N11: T
B12: ATLANTICA TRANSMISION SUR S.A. | C12: OCONA | D12: CL- 5034 | E12: 25/01/2025 08:22 | F12: 25/01/2025 17:25 | G12: MANTENIMIENTO PREVENTIVO EN EQUIPOS DE CELDA | H12: 0 | I12: P | J12: F/S | K12: N | L12: PREV. | M12: 13800 | N12: T
B13: ATLANTICA TRANSMISION SUR S.A. | C13: OCONA | D13: CL-5036 | E13: 25/01/2025 10:00 | F13: 25/01/2025 13:00 | G13: Pruebas de mando de los equipos del BCS-5484, REL-5483 y otros por cambio de RTU. | H13: 0 | I13: P | J13: F/S | K13: N | L13: PREV. | M13: 13802 | N13: T
B14: ATLANTICA TRANSMISION SUR S.A. | C14: OCONA - SAN JOSE | D14: L-5036 | E14: 25/01/2025 08:22 | F14: 25/01/2025 17:25 | G14: INDISPONIBLE POR MANTENIMIENTO EN LA LINEA L-5034 | H14: 0 | I14: P | J14: F/S | K14: N | L14: OTROS | M14: 14961 | N14: T
B15: ATLANTICA TRANSMISION SUR S.A. | C15: POROMA | D15: INT-5361 | E15: 25/01/2025 00:00 | F15: 26/01/2025 00:00 | G15: Seccionador SBA-5361 fase R indisponible por problemas mecanicos, el seccionador permanece cerrado y bloqueado | H15: 0 | I15: P | J15: E/S | K15: N | L15: OTROS | M15: 13746 | N15: T
B16: ATLANTICA TRANSMISION SUR S.A. | C16: POROMA | D16: REB-5350 | E16: 25/01/2025 00:00 | F16: 26/01/2025 00:00 | G16: FUERA DE SERVICIO POR FALLA EN EL EQUIPO. | H16: 0 | I16: P | J16: F/S | K16: N | L16: OTROS | M16: 13771 | N16: T
B17: ATLANTICA TRANSMISION SUR S.A. | C17: POROMA | D17: CL-5034 | E17: 25/01/2025 08:22 | F17: 25/01/2025 17:25 | G17: MANTENIMIENTO PREVENTIVO EN EQUIPOS DE CELDA | H17: 0 | I17: P | J17: F/S | K17: N | L17: PREV. | M17: 13790 | N17: T
B18: ATLANTICA TRANSMISION SUR S.A. | C18: POROMA - OCONA | D18: L-5034 | E18: 25/01/2025 08:22 | F18: 25/01/2025 17:25 | G18: LIMPIEZA DE AISLAMIENTO | H18: 0 | I18: P | J18: F/S | K18: N | L18: PREV. | M18: 13743 | N18: T
... B109: TRANSMANTARO | C109: YARABAMBA | D109: AT-104 523 | E109: 25/01/2025 00:00 | F109: 26/01/2025 00:00 | G109: NO SE TIENE MANDO REMOTO PARA CONTROLAR LOS TAPS DEL AUTOTRANSFORMADOR POR PROBLEMAS EN EL TRANSDUCTOR. LA MANIOBRA ES LOCAL Y REQUIERE AL ASISTENTE EN LA SUBESTACION PARA LAS MANIOBRAS. | H109: 0 | I109: P | J109: E/S | K109: N | L109: OTROS | M109: 17433 | N109: T

Sheet INGRESO OC
A3: sábado, 25 de Enero del 2025
A5: INGRESO A OPERACIÓN COMERCIAL
A6: EMPRESA | B6: TIPO DE EQUIPO | C6: UBICACIÓN | D6: EQUIPO | E6: Fecha y hora de Ingreso a Operación Comercial

Sheet DESPACHO_EJECUTADO
B3: sábado, 25 de Enero del 2025
A5: POTENCIA ACTIVA EJECUTADA DE LAS UNIDADES DE GENERACIÓN DEL SEIN (MW) | FI5: CENTRALES NO INTEGRANTES COES
A6: FECHA | B6: HORA | C6: 337 | D6: 338 | E6: 121 | F6: 101 | G6: 102 | H6: 42667 | I6: 42668 | J6: 126 | K6: 127 | L6: 138 | M6: 139 | N6: 197 | O6: 203 | P6: 204 | Q6: 230 | R6: 209 | S6: 56677 | T6: 796 | U6: 2146 | V6: 142 | W6: 143 | X6: 125 | Y6: 187 | Z6: 163 | AA6: 298 | AB6: 299 | AC6: 219 | AD6: 151 | AE6: 152 | AF6: 153 | AG6: 154 | AH6: 756 | AI6: 156 | AJ6: 155 | AK6: 182 | AL6: 212 | AM6: 758 | AN6: 263 | AO6: 265 | AP6: 775 | AQ6: 777 | AR6: 2154 | AS6: 150 | AT6: 149 | AU6: 188 | AV6: 2131 | AW6: 755 | AX6: 252 | AY6: 249 | AZ6: 250 | BA6: 117 | BB6: 267 | BC6: 268 | BD6: 119 | BE6: 120 | BF6: 189 | BG6: 122 | BH6: 266 | BI6: 251 | BJ6: 115 | BK6: 239 | BL6: 288 | BM6: 240 | BN6: 241 | BO6: 242 | BP6: 191 | BQ6: 194 | BR6: 196 | BS6: 207 | BT6: 236 | BU6: 795 | BV6: 285 | BW6: 995 | BX6: 996 | BY6: 997 | BZ6: 766 | CA6: 926 | CB6: 924 | CC6: 103 | CD6: 104 | CE6: 106 | CF6: 105 | CG6: 107 | CH6: 110 | CI6: 109 | CJ6: 144 | CK6: 113 | CL6: 114 | CM6: 193 | CN6: 208 | CO6: 786 | CP6: 787 | CQ6: 788 | CR6: 789 | CS6: 248 | CT6: 2159 | CU6: 303 | CV6: 59715 | CW6: 62255 | CX6: 1263 | CY6: 61800 | CZ6: 2194 | DA6: 216 | DB6: 198 | DC6: 214 | DD6: 260 | DE6: 2152 | DF6: 2128 | DG6: 247 | DH6: 228 | DI6: 2135 | DJ6: 261 | DK6: 237 | DL6: 253 | DM6: 770 | DN6: 225 | DO6: 2201 | DP6: 2171 | DQ6: 760 | DR6: 235 | DS6: 238 | DT6: 2184 | DU6: 61855 | DV6: 223 | DW6: 226 | DX6: 201 | DY6: 258 | DZ6: 259 | EA6: 920 | EB6: 257 | EC6: 256 | ED6: 2148 | EE6: 58288 | EF6: 58289 | EG6: 58839 | EH6: 58840 | EI6: 296 | EJ6: 297 | EK6: 211 | EL6: 2175 | EM6: 2178 | EN6: 2181 | EO6: 1262 | EP6: 233 | EQ6: 2150 | ER6: 2165 | ES6: 2161 | ET6: 61197 | EU6: 58851 | EV6: 234 | EW6: 215 | EX6: 917 | EY6: 289 | EZ6: 58333 | FA6: 58336 | FB6: 202 | FC6: 58487 | FD6: 213 | FE6: 232 | FF6: 2190 | FG6: TOTAL COES | FI6: 221 | FJ6: 49607 | FK6: 222 | FL6: 224 | FM6: 2187 | FN6: 227 | FO6: 49400 | FP6: 199 | FQ6: 200 | FR6: TOTAL NO COES
C7: CENTRO | D7: CENTRO | E7: NORTE | F7: CENTRO | G7: CENTRO | H7: NORTE | I7: NORTE | J7: NORTE | K7: NORTE | L7: CENTRO | M7: CENTRO | N7: CENTRO | O7: CENTRO | P7: CENTRO | Q7: CENTRO | R7: CENTRO | S7: CENTRO | T7: CENTRO | U7: CENTRO | V7: CENTRO | W7: CENTRO | X7: CENTRO | Y7: CENTRO | Z7: SUR | AA7: SUR | AB7: SUR | AC7: CENTRO | AD7: SUR | AE7: SUR | AF7: SUR | AG7: SUR | AH7: SUR | AI7: SUR | AJ7: SUR | AK7: SUR | AL7: CENTRO | AM7: NORTE | AN7: NORTE | AO7: NORTE | AP7: CENTRO | AQ7: CENTRO | AR7: CENTRO | AS7: CENTRO | AT7: CENTRO | AU7: CENTRO | AV7: CENTRO | AW7: SUR | AX7: CENTRO | AY7: CENTRO | AZ7: CENTRO | BA7: CENTRO | BB7: CENTRO | BC7: CENTRO | BD7: CENTRO | BE7: CENTRO | BF7: SUR | BG7: NORTE | BH7: CENTRO | BI7: CENTRO | BJ7: NORTE | BK7: NORTE | BL7: NORTE | BM7: SUR | BN7: SUR | BO7: SUR | BP7: CENTRO | BQ7: CENTRO | BR7: CENTRO | BS7: CENTRO | BT7: CENTRO | BU7: CENTRO | BV7: CENTRO | BW7: SUR | BX7: SUR | BY7: SUR | BZ7: NORTE | CA7: SUR | CB7: CENTRO | CC7: CENTRO | CD7: CENTRO | CE7: CENTRO | CF7: CENTRO | CG7: CENTRO | CH7: CENTRO | CI7: CENTRO | CJ7: CENTRO | CK7: CENTRO | CL7: CENTRO | CM7: CENTRO | CN7: CENTRO | CO7: SUR | CP7: SUR | CQ7: SUR | CR7: SUR | CS7: CENTRO | CT7: CENTRO | CU7: CENTRO | CV7: CENTRO | CW7: SUR | CX7: NORTE | CY7: NORTE | CZ7: NORTE | DA7: NORTE | DB7: NORTE | DC7: CENTRO | DD7: CENTRO | DE7: CENTRO | DF7: NORTE | DG7: NORTE | DH7: CENTRO | DI7: CENTRO | DJ7: SUR | DK7: SUR | DL7: CENTRO | DM7: CENTRO | DN7: CENTRO | DO7: CENTRO | DP7: CENTRO | DQ7: CENTRO | DR7: SUR | DS7: CENTRO | DT7: CENTRO | DU7: NORTE | DV7: CENTRO | DW7: CENTRO | DX7: NORTE | DY7: CENTRO | DZ7: CENTRO | EA7: CENTRO | EB7: NORTE | EC7: NORTE | ED7: SUR | EE7: CENTRO | EF7: CENTRO | EG7: CENTRO | EH7: CENTRO | EI7: CENTRO | EJ7: CENTRO | EK7: SUR | EL7: SUR | EM7: SUR | EN7: SUR | EO7: NORTE | EP7: SUR | EQ7: SUR | ER7: CENTRO | ES7: CENTRO | ET7: CENTRO | EU7: SUR | EV7: SUR | EW7: NORTE | EX7: CENTRO | EY7: NORTE | EZ7: NORTE | FA7: NORTE | FB7: CENTRO | FC7: CENTRO | FD7: CENTRO | FE7: NORTE | FF7: NORTE | FI7: NORTE | FJ7: SUR | FK7: CENTRO | FL7: NORTE | FM7: NORTE | FN7: NORTE | FO7: NORTE | FP7: NORTE | FQ7: NORTE
C8: HIDROELÉCTRICA | D8: HIDROELÉCTRICA | E8: HIDROELÉCTRICA | F8: HIDROELÉCTRICA | G8: HIDROELÉCTRICA | H8: TERMOELÉCTRICA | I8: TERMOELÉCTRICA | J8: HIDROELÉCTRICA | K8: HIDROELÉCTRICA | L8: TERMOELÉCTRICA | M8: TERMOELÉCTRICA | N8: TERMOELÉCTRICA | O8: TERMOELÉCTRICA | P8: TERMOELÉCTRICA | Q8: TERMOELÉCTRICA | R8: TERMOELÉCTRICA | S8: TERMOELÉCTRICA | T8: HIDROELÉCTRICA | U8: HIDROELÉCTRICA | V8: TERMOELÉCTRICA | W8: TERMOELÉCTRICA | X8: TERMOELÉCTRICA | Y8: TERMOELÉCTRICA | Z8: HIDROELÉCTRICA | AA8: HIDROELÉCTRICA | AB8: HIDROELÉCTRICA | AC8: TERMOELÉCTRICA | AD8: HIDROELÉCTRICA | AE8: HIDROELÉCTRICA | AF8: HIDROELÉCTRICA | AG8: HIDROELÉCTRICA | AH8: TERMOELÉCTRICA | AI8: TERMOELÉCTRICA | AJ8: TERMOELÉCTRICA | AK8: HIDROELÉCTRICA | AL8: HIDROELÉCTRICA | AM8: TERMOELÉCTRICA | AN8: TERMOELÉCTRICA | AO8: TERMOELÉCTRICA | AP8: HIDROELÉCTRICA | AQ8: HIDROELÉCTRICA | AR8: HIDROELÉCTRICA | AS8: HIDROELÉCTRICA | AT8: HIDROELÉCTRICA | AU8: HIDROELÉCTRICA | AV8: HIDROELÉCTRICA | AW8: HIDROELÉCTRICA | AX8: TERMOELÉCTRICA | AY8: TERMOELÉCTRICA | AZ8: TERMOELÉCTRICA | BA8: HIDROELÉCTRICA | BB8: HIDROELÉCTRICA | BC8: HIDROELÉCTRICA | BD8: HIDROELÉCTRICA | BE8: HIDROELÉCTRICA | BF8: HIDROELÉCTRICA | BG8: HIDROELÉCTRICA | BH8: HIDROELÉCTRICA | BI8: HIDROELÉCTRICA | BJ8: TERMOELÉCTRICA | BK8: TERMOELÉCTRICA | BL8: TERMOELÉCTRICA | BM8: TERMOELÉCTRICA | BN8: TERMOELÉCTRICA | BO8: TERMOELÉCTRICA | BP8: HIDROELÉCTRICA | BQ8: TERMOELÉCTRICA | BR8: TERMOELÉCTRICA | BS8: TERMOELÉCTRICA | BT8: TERMOELÉCTRICA | BU8: TERMOELÉCTRICA | BV8: TERMOELÉCTRICA | BW8: TERMOELÉCTRICA | BX8: TERMOELÉCTRICA | BY8: TERMOELÉCTRICA | BZ8: HIDROELÉCTRICA | CA8: TERMOELÉCTRICA | CB8: TERMOELÉCTRICA | CC8: HIDROELÉCTRICA | CD8: HIDROELÉCTRICA | CE8: HIDROELÉCTRICA | CF8: HIDROELÉCTRICA | CG8: HIDROELÉCTRICA | CH8: TERMOELÉCTRICA | CI8: TERMOELÉCTRICA | CJ8: TERMOELÉCTRICA | CK8: TERMOELÉCTRICA | CL8: TERMOELÉCTRICA | CM8: TERMOELÉCTRICA | CN8: TERMOELÉCTRICA | CO8: TERMOELÉCTRICA | CP8: TERMOELÉCTRICA | CQ8: TERMOELÉCTRICA | CR8: TERMOELÉCTRICA | CS8: TERMOELÉCTRICA | CT8: TERMOELÉCTRICA | CU8: SOLAR | CV8: EÓLICA | CW8: SOLAR | CX8: EÓLICA | CY8: SOLAR | CZ8: HIDROELÉCTRICA | DA8: HIDROELÉCTRICA | DB8: HIDROELÉCTRICA | DC8: HIDROELÉCTRICA | DD8: HIDROELÉCTRICA | DE8: HIDROELÉCTRICA | DF8: HIDROELÉCTRICA | DG8: HIDROELÉCTRICA | DH8: HIDROELÉCTRICA | DI8: HIDROELÉCTRICA | DJ8: SOLAR | DK8: SOLAR | DL8: EÓLICA | DM8: EÓLICA | DN8: TERMOELÉCTRICA | DO8: TERMOELÉCTRICA | DP8: TERMOELÉCTRICA | DQ8: TERMOELÉCTRICA | DR8: SOLAR | DS8: HIDROELÉCTRICA | DT8: HIDROELÉCTRICA | DU8: HIDROELÉCTRICA | DV8: HIDROELÉCTRICA | DW8: HIDROELÉCTRICA | DX8: HIDROELÉCTRICA | DY8: HIDROELÉCTRICA | DZ8: HIDROELÉCTRICA | EA8: HIDROELÉCTRICA | EB8: EÓLICA | EC8: EÓLICA | ED8: SOLAR | EE8: EÓLICA | EF8: EÓLICA | EG8: EÓLICA | EH8: EÓLICA | EI8: HIDROELÉCTRICA | EJ8: HIDROELÉCTRICA | EK8: HIDROELÉCTRICA | EL8: HIDROELÉCTRICA | EM8: HIDROELÉCTRICA | EN8: HIDROELÉCTRICA | EO8: EÓLICA | EP8: SOLAR | EQ8: SOLAR | ER8: HIDROELÉCTRICA | ES8: EÓLICA | ET8: EÓLICA | EU8: SOLAR | EV8: SOLAR | EW8: HIDROELÉCTRICA | EX8: HIDROELÉCTRICA | EY8: TERMOELÉCTRICA | EZ8: TERMOELÉCTRICA | FA8: TERMOELÉCTRICA | FB8: TERMOELÉCTRICA | FC8: TERMOELÉCTRICA | FD8: TERMOELÉCTRICA | FE8: TERMOELÉCTRICA | FF8: TERMOELÉCTRICA | FI8: HIDROELÉCTRICA | FJ8: HIDROELÉCTRICA | FK8: HIDROELÉCTRICA | FL8: HIDROELÉCTRICA | FM8: HIDROELÉCTRICA | FN8: TERMOELÉCTRICA | FO8: TERMOELÉCTRICA | FP8: HIDROELÉCTRICA | FQ8: HIDROELÉCTRICA
C9: CENTRALES SANTA ROSA S.A.C. | D9: CENTRALES SANTA ROSA S.A.C. | E9: INVERSIONES SHAQSHA S.A.C. | F9: ELECTROPERU | G9: ELECTROPERU | H9: ELECTROPERU | I9: ELECTROPERU | J9: ORAZUL ENERGY PERÚ | K9: ORAZUL ENERGY PERÚ | L9: TERMOSELVA | M9: TERMOSELVA | N9: KALLPA GENERACION S.A. | O9: KALLPA GENERACION S.A. | P9: KALLPA GENERACION S.A. | Q9: KALLPA GENERACION S.A. | R9: KALLPA GENERACION S.A. | S9: KALLPA GENERACION S.A. | T9: KALLPA GENERACION S.A. | U9: KALLPA GENERACION S.A. | V9: SHOUGESA | W9: SHOUGESA | X9: SHOUGESA | Y9: SHOUGESA | Z9: EGEMSA | AA9: EGESUR | AB9: EGESUR | AC9: EGESUR | AD9: EGASA | AE9: EGASA | AF9: EGASA | AG9: EGASA | AH9: EGASA | AI9: EGASA | AJ9: EGASA | AK9: SAN GABAN | AL9: CELEPSA | AM9: MINERA CERRO VERDE | AN9: PLANTA DE RESERVA FRIA DE GENERACION DE ETEN S.A. | AO9: PLANTA DE RESERVA FRIA DE GENERACION DE ETEN S.A. | AP9: EMPRESA DE GENERACION HUALLAGA | AQ9: EMPRESA DE GENERACION HUALLAGA | AR9: LA VIRGEN | AS9: CHINANGO S.A.C. | AT9: CHINANGO S.A.C. | AU9: HIDROELECTRICA HUANCHOR S.A.C. | AV9: CELEPSA RENOVABLES S.R.L. | AW9: INLAND ENERGY SAC | AX9: FENIX POWER PERÚ | AY9: FENIX POWER PERÚ | AZ9: FENIX POWER PERÚ | BA9: STATKRAFT S.A | BB9: STATKRAFT S.A | BC9: STATKRAFT S.A | BD9: STATKRAFT S.A | BE9: STATKRAFT S.A | BF9: STATKRAFT S.A | BG9: STATKRAFT S.A | BH9: STATKRAFT S.A | BI9: EMPRESA DE GENERACION HUANZA | BJ9: ENEL GENERACION PIURA S.A. | BK9: ENEL GENERACION PIURA S.A. | BL9: ENEL GENERACION PIURA S.A. | BM9: ENGIE | BN9: ENGIE | BO9: ENGIE | BP9: ENGIE | BQ9: ENGIE | BR9: ENGIE | BS9: ENGIE | BT9: ENGIE | BU9: ENGIE | BV9: ENGIE | BW9: ENGIE | BX9: ENGIE | BY9: ENGIE | BZ9: ENGIE | CA9: INFRAESTRUCTURAS Y ENERGIAS DEL PERU S.A.C. | CB9: INFRAESTRUCTURAS Y ENERGIAS DEL PERU S.A.C. | CC9: ORYGEN PERU S.A.A. | CD9: ORYGEN PERU S.A.A. | CE9: ORYGEN PERU S.A.A. | CF9: ORYGEN PERU S.A.A. | CG9: ORYGEN PERU S.A.A. | CH9: ORYGEN PERU S.A.A. | CI9: ORYGEN PERU S.A.A. | CJ9: ORYGEN PERU S.A.A. | CK9: ORYGEN PERU S.A.A. | CL9: ORYGEN PERU S.A.A. | CM9: ORYGEN PERU S.A.A. | CN9: ORYGEN PERU S.A.A. | CO9: SAMAY I S.A.C | CP9: SAMAY I S.A.C | CQ9: SAMAY I S.A.C | CR9: SAMAY I S.A.C | CS9: TERMOCHILCA S.A.C. | CT9: TERMOCHILCA S.A.C. | CU9: COLCA SOLAR S.A.C. | CV9: ENERGIA RENOVABLE DEL SUR S.A. | CW9: GR CORTARRAMA SOCIEDAD ANONIMA CERRADA | CX9: GR TARUCA SOCIEDAD ANONIMA CERRADA | CY9: KONDU SAC | CZ9: PERUANA DE INVERSIONES EN ENERGIAS RENOVABLES S.A. | DA9: ORAZUL ENERGY PERÚ | DB9: ORAZUL ENERGY PERÚ | DC9: MAJA ENERGIA S.A.C. | DD9: EMPRESA DE GENERACION ELECTRICA CANCHAYLLO SAC | DE9: EMPRESA DE GENERACION ELECTRICA SANTA ANA S.A.C. | DF9: EMPRESA ELECTRICA AGUA AZUL | DG9: EMPRESA ELECTRICA RIO DOBLE | DH9: HIDROCAÑETE S.A. | DI9: HUAURA POWER GROUP S.A. | DJ9: MOQUEGUA FV S.A.C. | DK9: PANAMERICANA SOLAR SAC. | DL9: PARQUE EOLICO MARCONA S.A.C. | DM9: PARQUE EOLICO TRES HERMANAS S.A.C. | DN9: PETRAMAS | DO9: PETRAMAS | DP9: PETRAMAS | DQ9: PETRAMAS | DR9: TACNA SOLAR SAC. | DS9: ELECTRICA YANAPAMPA SAC | DT9: ANDEAN POWER S.A.C. | DU9: ASOCIACIÓN SANTA LUCIA DE CHACAS | DV9: ATRIA ENERGIA S.A.C. | DW9: EGEJUNIN | DX9: EGEJUNIN | DY9: EGEJUNIN | DZ9: EGEJUNIN | EA9: EMPRESA DE GENERACION ELECTRICA RIO BAÑOS S.A.C. | EB9: ENERGÍA EÓLICA S.A. | EC9: ENERGÍA EÓLICA S.A. | ED9: ENGIE | EE9: ENGIE | EF9: ENGIE | EG9: ENGIE | EH9: ENGIE | EI9: GENERACIÓN ANDINA S.A.C. | EJ9: GENERACIÓN ANDINA S.A.C. | EK9: GENERADORA DE ENERGÍA DEL PERÚ | EL9: GENERADORA DE ENERGÍA DEL PERÚ | EM9: GENERADORA DE ENERGÍA DEL PERÚ | EN9: GENERADORA DE ENERGÍA DEL PERÚ | EO9: GR PAINO SOCIEDAD ANONIMA CERRADA | EP9: MAJES ARCUS S.A.C. | EQ9: ORYGEN PERU S.A.A. | ER9: ORYGEN PERU S.A.A. | ES9: ORYGEN PERU S.A.A. | ET9: ORYGEN PERU S.A.A. | EU9: ORYGEN PERU S.A.A. | EV9: REPARTICIÓN ARCUS S.A.C. | EW9: SINERSA | EX9: SINERSA | EY9: BIOENERGIA DEL CHIRA S.A. | EZ9: GM OPERACIONES S.A.C. | FA9: GM OPERACIONES S.A.C. | FB9: SDF ENERGIA SAC | FC9: SDF ENERGIA SAC | FD9: AGRO INDUSTRIAL PARAMONGA S.A. | FE9: AGROAURORA S.A.C. | FF9: AGROINDUSTRIAS SAN JACINTO S.A.A. | FI9: UNACEM PERU S.A. | FJ9: SAN GABAN | FK9: ELECTRO ORIENTE | FL9: AGUAS Y ENERGIA PERU | FM9: ELECTRO ZAÑA S.A.C. | FN9: ELECTRONOROESTE S.A. | FO9: SDE PIURA | FP9: SINERSA | FQ9: SINERSA
C10: SANTA ROSA 1 | D10: SANTA ROSA 2 | E10: PARIAC | F10: MANTARO | G10: RESTITUCION | H10: TUMBES MAK 1 | I10: TUMBES MAK 2 | J10: CARHUAQUERO | K10: CAÑON DEL PATO | L10: AGUAYTIA TG1 | M10: AGUAYTIA TG2 | N10: KALLPA TG1 | O10: KALLPA TG2 | P10: KALLPA TG3 | Q10: KALLPA TV | R10: LFLORES TG1 | S10: LFLORES TV | T10: CERRO DEL AGUILA | U10: CERRODELAGUILAG4 | V10: SHOUGESA TV1 | W10: SHOUGESA TV2 | X10: SHOUGESA TV3 | Y10: SHOUGESA CUMMINS | Z10: MACHUPICCHU | AA10: ARICOTA 1 | AB10: ARICOTA 2 | AC10: INDEPENDENCIA | AD10: CHARCANI I,II,III | AE10: CHARCANI IV | AF10: CHARCANI V | AG10: CHARCANI VI | AH10: CHILINA TG | AI10: MOLLENDO 1, 2, 3 | AJ10: CHILINA (SULZ 1,2) | AK10: SAN GABAN II | AL10: PLATANAL | AM10: RECKA | AN10: RF ETEN TG1 | AO10: RF ETEN TG2 | AP10: CHAGLLA GP1 | AQ10: CHAGLLA | AR10: LA VIRGEN | AS10: CHIMAY | AT10: YANANGO | AU10: HUANCHOR | AV10: MARAÑON | AW10: STA TERESA | AX10: FENIX GT11 | AY10: FENIX GT12 | AZ10: FENIX TV10 | BA10: YAUPI | BB10: OROYA | BC10: PACHACHACA | BD10: MALPASO | BE10: CAHUA | BF10: ARCATA | BG10: GALLITO CIEGO | BH10: CHEVES | BI10: HUANZA | BJ10: MALACAS2 TG4 | BK10: MALACAS3 TG 5 | BL10: MALACAS1 TG6 | BM10: RF ILO2 TG1 | BN10: RF ILO2 TG2 | BO10: RF ILO2 TG3 | BP10: YUNCAN | BQ10: CHILCA1 TG1 | BR10: CHILCA1 TG2 | BS10: CHILCA1 TG3 | BT10: CHILCA-TV | BU10: CHILCA2 TG41 | BV10: CHILCA2-TV | BW10: CTNEPI_TG41 | BX10: CTNEPI_TG42 | BY10: CTNEPI_TG43 | BZ10: QUITARACSA | CA10: RF PTO MALDONADO | CB10: RF PUCALLPA | CC10: HUINCO | CD10: MATUCANA | CE10: MOYOPAMPA | CF10: CALLAHUANCA | CG10: HUAMPANI | CH10: STA ROSA WEST TG7 | CI10: UTI_5 | CJ10: UTI_6 | CK10: VENTANILLA 3 | CL10: VENTANILLA 4 | CM10: VENTANILLA TV | CN10: STAROSA TG8 | CO10: PTO_BRVO TG1 | CP10: PTO_BRVO TG2 | CQ10: PTO_BRVO TG3 | CR10: PTO_BRVO TG4 | CS10: OLLEROS TG1 | CT10: OLLEROS TV | CU10: CS YARUCAYA | CV10: SAN JUAN | CW10: MATARANI | CX10: DUNA | CY10: CARHUAQUERO (CS) | CZ10: MANTA I | DA10: CARHUAQUERO4 | DB10: CAÑA BRAVA | DC10: RONCADOR | DD10: CANCHAYLLO | DE10: RENOVANDESH1 | DF10: POTRERO | DG10: PIZARRAS | DH10: NIMPERIAL | DI10: YARUCAYA | DJ10: MOQUEGUA-SOLAR | DK10: PANAMERICANA-SOLAR | DL10: PQE-EOLICO-MARCONA | DM10: PQE-EOLICO-3-HERMANAS | DN10: HUAYCOLORO | DO10: CALLAO | DP10: DONA_CATALINA | DQ10: LAGRINGAV | DR10: TACNA-SOLAR | DS10: YANAPAMPA | DT10: CARHUAC | DU10: HUALLIN | DV10: PURMACANA | DW10: HUASAHUASI | DX10: STACRUZ_1_2 | DY10: RUNATULLO_II | DZ10: RUNATULLO_III | EA10: RUCUY | EB10: PQE-EOLICO-TALARA | EC10: PQE-EOLICO-CUPISNIQUE | ED10: INTIPAMPA | EE10: PUNTA LOMITAS-BL1 | EF10: PUNTA LOMITAS-BL2 | EG10: PUN LOMITAS_EXP-BL1 | EH10: PUN LOMITAS_EXP-BL2 | EI10: 8AGOSTO | EJ10: EL CARMEN | EK10: LA JOYA | EL10: ANGEL_I | EM10: ANGEL_II | EN10: ANGEL_III | EO10: HUAMBOS | EP10: MAJES | EQ10: RUBI | ER10: CH_HER1 | ES10: WAYRA-I | ET10: WAYRA EXTENSION | EU10: CLEMESI | EV10: REPARTICION | EW10: POECHOS2 | EX10: CHANCAY | EY10: CANA BRAVA | EZ10: REFINERIA TALARA TV1 | FA10: REFINERÍA TALARA TV2 | FB10: OQUENDO TG1 | FC10: OQUENDO TV1 | FD10: PARAMONGA | FE10: MAPLE | FF10: SAN_JACINTO | FG10: MW | FI10: CARPAPATA | FJ10: TUPURI | FK10: CENTRALES ELOR | FL10: PIAS1 | FM10: ZANA | FN10: TABLAZO | FO10: TALLANCA | FP10: CURUMUY | FQ10: POECHOS1 | FR10: MW
A11: 25/01/2025 | B11: 00:30 | C11: 1.1 | D11: 1.6 | E11: 4.3 | F11: 648.3 | G11: 218 | J11: 60 | K11: 237 | N11: 121 | O11: 120.9 | P11: 120.6 | Q11: 217.3 | R11: 205.5 | S11: 108 | T11: 564.2 | U11: 10.6 | Z11: 168 | AA11: 7.629 | AB11: 2.563 | AC11: 0 | AD11: 6.5 | AF11: 32.5 | AG11: 6.2 | AH11: 0 | AK11: 110.9 | AL11: 221.8 | AP11: 6.5 | AQ11: 460.1 | AR11: 70.2 | AS11: 142.8 | AT11: 42.1 | AU11: 18.3 | AV11: 19.5 | AW11: 90.1 | AY11: 0 | AZ11: 0 | BA11: 108.9 | BB11: 8 | BC11: 2.2 | BD11: 45.8 | BE11: 47.5 | BF11: 3.5 | BG11: 31.1 | BH11: 174 | BI11: 45.3 | BL11: 47.1 | BP11: 130.8 | BR11: 0 | BZ11: 114.2 | CC11: 222.9 | CD11: 128.5 | CE11: 63.9 | CF11: 81 | CG11: 30.2 | CK11: 142.9 | CL11: 142.4 | CM11: 146.4 | CS11: 188.3 | CT11: 101 | CU11: 0 | CV11: 42.7 | CW11: 0 | CX11: 14.4 | CY11: 0 | CZ11: 20 | DA11: 9.9 | DB11: 4.9 | DC11: 3.6 | DD11: 5.1 | DE11: 20.1 | DF11: 20 | DG11: 15.6 | DH11: 3.5 | DI11: 18.7 | DJ11: 0 | DK11: 0 | DL11: 8.5 | DM11: 23.5 | DN11: 4.7 | DO11: 2.3 | DP11: 2.4 | DQ11: 1.4 | DR11: 0 | DS11: 3.5 | DT11: 17.5 | DU11: 2 | DW11: 19.4 | DX11: 9.6 | DY11: 19.6 | DZ11: 20.3 | EA11: 20 | EB11: 18.3 | EC11: 55.3 | ED11: 0 | EE11: 23.8 | EF11: 50.5 | EG11: 1.1 | EH11: 0.7 | EI11: 21 | EJ11: 7.8 | EK11: 9.5 | EL11: 20 | EM11: 20 | EN11: 19 | EO11: 8.3 | EP11: 0 | EQ11: 0 | ER11: 0.6 | ES11: 13.4 | ET11: 15.7 | EU11: 0 | EV11: 0 | EW11: 6 | EX11: 20 | EY11: 10.9 | EZ11: 17.2 | FA11: 37.4 | FB11: 28.8 | FC11: 3.2 | FD11: 14.2 | FE11: 11.3 | FF11: 8.2 | FG11: 6825.392 | FI11: 23.93035 | FJ11: 1.3 | FK11: 0 | FL11: 6.0435 | FM11: 7.1 | FO11: 18.92246 | FP11: 4.9 | FQ11: 15.9 | FR11: 78.09631
A12: 25/01/2025 | B12: 01:00 | C12: 1.1 | D12: 1.6 | E12: 4.3 | F12: 645.5 | G12: 217.9 | J12: 59.4 | K12: 236.3 | N12: 108 | O12: 108.1 | P12: 108 | Q12: 208 | R12: 204.4 | S12: 108.3 | T12: 558.1 | U12: 10.4 | Z12: 167.2 | AA12: 7.638 | AB12: 2.657 | AC12: 0 | AD12: 6.5 | AF12: 31.4 | AG12: 3.7 | AH12: 0 | AK12: 110.5 | AL12: 179.8 | AP12: 6.5 | AQ12: 457.3 | AR12: 69.5 | AS12: 138.6 | AT12: 41.7 | AU12: 18.3 | AV12: 19.5 | AW12: 87.4 | AY12: 0 | AZ12: 0 | BA12: 109.1 | BB12: 7.9 | BC12: 2.3 | BD12: 45.8 | BE12: 46.8 | BF12: 3.5 | BG12: 31.4 | BH12: 173.7 | BI12: 45.2 | BL12: 47.1 | BP12: 130.2 | BR12: 0 | BZ12: 114.3 | CC12: 185.6 | CD12: 124.2 | CE12: 63.3 | CF12: 80.9 | CG12: 30 | CK12: 142.9 | CL12: 143.2 | CM12: 147.3 | CS12: 187.7 | CT12: 101 | CU12: 0 | CV12: 33.9 | CW12: 0 | CX12: 15.1 | CY12: 0 | CZ12: 20 | DA12: 9.9 | DB12: 4.7 | DC12: 3.6 | DD12: 5.1 | DE12: 20.2 | DF12: 20 | DG12: 15 | DH12: 3.5 | DI12: 18.7 | DJ12: 0 | DK12: 0 | DL12: 9.6 | DM12: 26.8 | DN12: 4.7 | DO12: 2.3 | DP12: 2.4 | DQ12: 1.4 | DR12: 0 | DS12: 3.7 | DT12: 16.4 | DU12: 2 | DW12: 18.4 | DX12: 9.5 | DY12: 19.3 | DZ12: 20.3 | EA12: 19.8 | EB12: 19.3 | EC12: 57.1 | ED12: 0 | EE12: 28.3 | EF12: 58.4 | EG12: 1.8 | EH12: 1.2 | EI12: 21 | EJ12: 7.7 | EK12: 2 | EL12: 20 | EM12: 20 | EN12: 19 | EO12: 9.7 | EP12: 0 | EQ12: 0 | ER12: 0.6 | ES12: 26.9 | ET12: 24.8 | EU12: 0 | EV12: 0 | EW12: 6 | EX12: 19.8 | EY12: 9.8 | EZ12: 16.8 | FA12: 36.7 | FB12: 28.9 | FC12: 3.2 | FD12: 14 | FE12: 13.3 | FF12: 8.1 | FG12: 6691.695 | FI12: 23.93041 | FJ12: 1.3 | FK12: 0 | FL12: 6.0455 | FM12: 7.1 | FO12: 18.92274 | FP12: 4.9 | FQ12: 15.9 | FR12: 78.09865
A13: 25/01/2025 | B13: 01:30 | C13: 1.1 | D13: 1.6 | E13: 4.3 | F13: 648.1 | G13: 217.7 | J13: 60.1 | K13: 238.7 | N13: 108.1 | O13: 107.5 | P13: 108.6 | Q13: 206.1 | R13: 205.5 | S13: 107.5 | T13: 554.6 | U13: 10.6 | Z13: 171.7 | AA13: 7.78 | AB13: 2.7 | AC13: 0 | AD13: 6.5 | AF13: 31.3 | AG13: 5.7 | AH13: 0 | AK13: 111 | AL13: 147.4 | AP13: 6.5 | AQ13: 460.5 | AR13: 69.7 | AS13: 126.2 | AT13: 42 | AU13: 18.3 | AV13: 19.5 | AW13: 90.3 | AY13: 0 | AZ13: 0 | BA13: 110.6 | BB13: 8 | BC13: 2.3 | BD13: 46.9 | BE13: 47.8 | BF13: 3.5 | BG13: 31.5 | BH13: 174.5 | BI13: 46.2 | BL13: 47 | BP13: 131.3 | BR13: 0 | BZ13: 115.2 | CC13: 170.5 | CD13: 115.6 | CE13: 64.2 | CF13: 81.4 | CG13: 30.4 | CK13: 107.5 | CL13: 107.2 | CM13: 123.7 | CS13: 186.4 | CT13: 101.2 | CU13: 0 | CV13: 33.2 | CW13: 0 | CX13: 14.2 | CY13: 0 | CZ13: 20 | DA13: 9.8 | DB13: 4.7 | DC13: 3.6 | DD13: 5.2 | DE13: 20.3 | DF13: 20 | DG13: 15 | DH13: 3.5 | DI13: 18.7 | DJ13: 0 | DK13: 0 | DL13: 8.2 | DM13: 24.5 | DN13: 4.7 | DO13: 2.3 | DP13: 2.4 | DQ13: 1.4 | DR13: 0 | DS13: 3.7 | DT13: 16.4 | DU13: 2 | DW13: 18.3 | DX13: 9.5 | DY13: 19.1 | DZ13: 20.3 | EA13: 19.8 | EB13: 21.1 | EC13: 61.4 | ED13: 0 | EE13: 28.9 | EF13: 51.2 | EG13: 1.4 | EH13: 2.3 | EI13: 21 | EJ13: 7.6 | EK13: 1.4 | EL13: 20 | EM13: 20 | EN13: 19.5 | EO13: 9.5 | EP13: 0 | EQ13: 0 | ER13: 0.6 | ES13: 34.2 | ET13: 29.5 | EU13: 0 | EV13: 0 | EW13: 6 | EX13: 19.8 | EY13: 9.8 | EZ13: 16.5 | FA13: 36.7 | FB13: 28.9 | FC13: 3.2 | FD13: 14.4 | FE13: 15 | FF13: 7.5 | FG13: 6558.28 | FI13: 23.92699 | FJ13: 1.3 | FK13: 0 | FL13: 6.045 | FM13: 7.1 | FO13: 18.92284 | FP13: 4.8 | FQ13: 15.9 | FR13: 77.99483
A14: 25/01/2025 | B14: 02:00 | C14: 1.1 | D14: 1.6 | E14: 4.2 | F14: 650.8 | G14: 218.8 | J14: 60.5 | K14: 239.8 | N14: 116.8 | O14: 117.6 | P14: 116.5 | Q14: 217.6 | R14: 112.6 | S14: 76.1 | T14: 562.4 | U14: 10.6 | Z14: 170.5 | AA14: 8.113 | AB14: 2.718 | AC14: 0 | AD14: 6.5 | AF14: 32.3 | AG14: 5.6 | AH14: 0 | AK14: 111.3 | AL14: 222.1 | AP14: 6.5 | AQ14: 460.4 | AR14: 70 | AS14: 149.4 | AT14: 42.2 | AU14: 18.4 | AV14: 19.5 | AW14: 91.3 | AY14: 0 | AZ14: 0 | BA14: 108.9 | BB14: 8 | BC14: 2.3 | BD14: 46.4 | BE14: 47.5 | BF14: 3.5 | BG14: 31.8 | BH14: 174.9 | BI14: 46.2 | BL14: 47.5 | BP14: 131.5 | BR14: 0 | BZ14: 115.5 | CC14: 214.1 | CD14: 133.8 | CE14: 64.5 | CF14: 81.2 | CG14: 30.5 | CK14: 107.7 | CL14: 108.7 | CM14: 122.5 | CS14: 136.5 | CT14: 79.8 | CU14: 0 | CV14: 31.7 | CW14: 0 | CX14: 12.5 | CY14: 0 | CZ14: 20 | DA14: 9.9 | DB14: 4.8 | DC14: 3.7 | DD14: 5.2 | DE14: 20.6 | DF14: 20 | DG14: 15 | DH14: 3.5 | DI14: 18.7 | DJ14: 0 | DK14: 0 | DL14: 7.3 | DM14: 23.7 | DN14: 4.7 | DO14: 2.3 | DP14: 2.4 | DQ14: 1.4 | DR14: 0 | DS14: 3.5 | DT14: 16.1 | DU14: 2 | DW14: 18.3 | DX14: 9.5 | DY14: 19.2 | DZ14: 20.4 | EA14: 20 | EB14: 22.5 | EC14: 46 | ED14: 0 | EE14: 23.4 | EF14: 44.9 | EG14: 1.4 | EH14: 3.2 | EI14: 21 | EJ14: 7.6 | EK14: 0 | EL14: 20 | EM14: 20 | EN14: 19.8 | EO14: 10.3 | EP14: 0 | EQ14: 0 | ER14: 0.6 | ES14: 29.9 | ET14: 29.2 | EU14: 0 | EV14: 0 | EW14: 6 | EX14: 20 | EY14: 11.3 | EZ14: 16.8 | FA14: 36.4 | FB14: 28.9 | FC14: 3.2 | FD14: 14 | FE14: 14.1 | FF14: 8 | FG14: 6542.031 | FI14: 23.92521 | FJ14: 1.3 | FK14: 0 | FL14: 6.045 | FM14: 7.1 | FO14: 18.92349 | FP14: 4.8 | FQ14: 15.9 | FR14: 77.9937
A15: 25/01/2025 | B15: 02:30 | C15: 1.1 | D15: 1.7 | E15: 4.2 | F15: 632 | G15: 213.6 | J15: 59.6 | K15: 232.3 | N15: 155.3 | O15: 154.1 | P15: 154 | Q15: 259.6 | R15: 108.8 | S15: 67.4 | T15: 531.4 | U15: 10.4 | Z15: 160.2 | AA15: 6.473 | AB15: 2.328 | AC15: 0 | AD15: 6.5 | AF15: 30.2 | AG15: 5.6 | AH15: 0 | AK15: 108.5 | AL15: 222.3 | AP15: 6.5 | AQ15: 451.1 | AR15: 70.6 | AS15: 141.2 | AT15: 40.4 | AU15: 18.3 | AV15: 19.5 | AW15: 89.5 | AY15: 0 | AZ15: 0 | BA15: 105.3 | BB15: 8 | BC15: 2.2 | BD15: 43 | BE15: 46 | BF15: 3.5 | BG15: 30.2 | BH15: 170.2 | BI15: 0 | BL15: 47.3 | BP15: 129.1 | BR15: 0 | BZ15: 111.2 | CC15: 164.4 | CD15: 126.1 | CE15: 61.9 | CF15: 80 | CG15: 29.3 | CK15: 102.9 | CL15: 103.1 | CM15: 119.3 | CS15: 136.8 | CT15: 78.8 | CU15: 0 | CV15: 28.7 | CW15: 0 | CX15: 13.4 | CY15: 0 | CZ15: 20 | DA15: 10 | DB15: 4.7 | DC15: 3.6 | DD15: 5.2 | DE15: 19.7 | DF15: 20 | DG15: 15 | DH15: 3.5 | DI15: 18.7 | DJ15: 0 | DK15: 0 | DL15: 5.4 | DM15: 17.2 | DN15: 4.7 | DO15: 2.3 | DP15: 2.4 | DQ15: 1.4 | DR15: 0 | DS15: 3.6 | DT15: 14.9 | DU15: 2 | DW15: 17.7 | DX15: 9.5 | DY15: 18.7 | DZ15: 20.2 | EA15: 20 | EB15: 17 | EC15: 37.2 | ED15: 0 | EE15: 24.7 | EF15: 50.5 | EG15: 2 | EH15: 1.2 | EI15: 21 | EJ15: 7.5 | EK15: 0 | EL15: 20 | EM15: 20 | EN15: 19.8 | EO15: 9.9 | EP15: 0 | EQ15: 0 | ER15: 0.6 | ES15: 22.2 | ET15: 19.7 | EU15: 0 | EV15: 0 | EW15: 6 | EX15: 20 | EY15: 10.7 | EZ15: 16.5 | FA15: 36.4 | FB15: 28.9 | FC15: 3.2 | FD15: 14 | FE15: 15.1 | FF15: 7.7 | FG15: 6397.601 | FI15: 23.92496 | FJ15: 1.3 | FK15: 0 | FL15: 6.0455 | FM15: 7.1 | FO15: 18.92297 | FP15: 4.8 | FQ15: 15.9 | FR15: 77.99343
A16: 25/01/2025 | B16: 03:00 | C16: 1.1 | D16: 1.7 | E16: 4.3 | F16: 653.8 | G16: 219.5 | J16: 61 | K16: 240.6 | N16: 123.7 | O16: 122.3 | P16: 123.8 | Q16: 235.6 | R16: 109 | S16: 67.5 | T16: 562.1 | U16: 10.5 | Z16: 173.8 | AA16: 8.017 | AB16: 2.66 | AC16: 0 | AD16: 6.6 | AF16: 32.3 | AG16: 6 | AH16: 0 | AK16: 111.5 | AL16: 221.6 | AP16: 6.5 | AQ16: 464.7 | AR16: 70.4 | AS16: 141.9 | AT16: 42.4 | AU16: 18.3 | AV16: 19.5 | AW16: 91.4 | AY16: 0 | AZ16: 0 | BA16: 109.7 | BB16: 8.1 | BC16: 2.3 | BD16: 46 | BE16: 47.8 | BF16: 3.5 | BG16: 31.7 | BH16: 176.6 | BI16: 0 | BL16: 47.3 | BP16: 132.1 | BR16: 0 | BZ16: 115.7 | CC16: 146.5 | CD16: 128.1 | CE16: 65.6 | CF16: 81.7 | CG16: 30.7 | CK16: 104.3 | CL16: 104.3 | CM16: 120.7 | CS16: 137.2 | CT16: 79.8 | CU16: 0 | CV16: 34.7 | CW16: 0 | CX16: 15.1 | CY16: 0 | CZ16: 20 | DA16: 9.9 | DB16: 4.7 | DC16: 3.6 | DD16: 5.2 | DE16: 20.8 | DF16: 20 | DG16: 15.1 | DH16: 3.5 | DI16: 18.7 | DJ16: 0 | DK16: 0 | DL16: 6.9 | DM16: 18.3 | DN16: 4.7 | DO16: 2.3 | DP16: 2.4 | DQ16: 1.4 | DR16: 0 | DS16: 3.6 | DT16: 4.9 | DU16: 2 | DW16: 17.1 | DX16: 9.5 | DY16: 19 | DZ16: 20.4 | EA16: 19.8 | EB16: 15.6 | EC16: 34.8 | ED16: 0 | EE16: 31.4 | EF16: 63.4 | EG16: 1.8 | EH16: 1.6 | EI16: 21 | EJ16: 7.4 | EK16: 0 | EL16: 20 | EM16: 20 | EN16: 19.8 | EO16: 7.9 | EP16: 0 | EQ16: 0 | ER16: 0.6 | ES16: 27.4 | ET16: 25.6 | EU16: 0 | EV16: 0 | EW16: 6 | EX16: 19.8 | EY16: 10.1 | EZ16: 16.6 | FA16: 35.9 | FB16: 28.9 | FC16: 3.3 | FD16: 14.4 | FE16: 16.2 | FF16: 7.9 | FG16: 6434.777 | FI16: 23.92046 | FJ16: 1.3 | FK16: 0 | FL16: 6.044 | FM16: 7.1 | FO16: 18.92306 | FP16: 4.9 | FQ16: 15.9 | FR16: 78.08752
A17: 25/01/2025 | B17: 03:30 | C17: 1.1 | D17: 1.7 | E17: 4.2 | F17: 646.5 | G17: 218.3 | J17: 60.2 | K17: 238.1 | N17: 121.5 | O17: 122 | P17: 121.9 | Q17: 215 | R17: 109.3 | S17: 66.9 | T17: 560.8 | U17: 10.6 | Z17: 158.8 | AA17: 7.577 | AB17: 2.665 | AC17: 0 | AD17: 6.6 | AF17: 32.4 | AG17: 6 | AH17: 0 | AK17: 111 | AL17: 221.4 | AP17: 6.5 | AQ17: 461.5 | AR17: 69.1 | AS17: 148.1 | AT17: 42 | AU17: 18.4 | AV17: 19.5 | AW17: 91.2 | AY17: 0 | AZ17: 0 | BA17: 108.8 | BB17: 8 | BC17: 2.3 | BD17: 45.9 | BE17: 46.9 | BF17: 3.5 | BG17: 31.3 | BH17: 173.9 | BI17: 0 | BL17: 47.4 | BP17: 130.8 | BR17: 0 | BZ17: 114.2 | CC17: 208 | CD17: 132.2 | CE17: 63.9 | CF17: 81 | CG17: 30.2 | CK17: 102.9 | CL17: 102.7 | CM17: 120.1 | CS17: 136.2 | CT17: 78.7 | CU17: 0 | CV17: 39.3 | CW17: 0 | CX17: 14.5 | CY17: 0 | CZ17: 20 | DA17: 9.9 | DB17: 4.8 | DC17: 3.6 | DD17: 5.2 | DE17: 20.3 | DF17: 20 | DG17: 15 | DH17: 3.5 | DI17: 18.7 | DJ17: 0 | DK17: 0 | DL17: 7 | DM17: 20 | DN17: 4.7 | DO17: 2.3 | DP17: 2.4 | DQ17: 1.4 | DR17: 0 | DS17: 3.5 | DT17: 5.4 | DU17: 2 | DW17: 17.1 | DX17: 9.5 | DY17: 18.8 | DZ17: 20.3 | EA17: 20 | EB17: 15.6 | EC17: 28.8 | ED17: 0 | EE17: 25 | EF17: 53.9 | EG17: 1.1 | EH17: 1.8 | EI17: 21 | EJ17: 7.3 | EK17: 0 | EL17: 20 | EM17: 20 | EN17: 20 | EO17: 10.5 | EP17: 0 | EQ17: 0 | ER17: 0.6 | ES17: 29.2 | ET17: 24.5 | EU17: 0 | EV17: 0 | EW17: 6 | EX17: 20 | EY17: 9.8 | EZ17: 16.4 | FA17: 35.9 | FB17: 29 | FC17: 3.2 | FD17: 14.5 | FE17: 16.3 | FF17: 7.8 | FG17: 6417.142 | FI17: 24.07807 | FJ17: 1.3 | FK17: 0 | FL17: 6.0445 | FM17: 7.1 | FO17: 18.92316 | FP17: 4.8 | FQ17: 15.9 | FR17: 78.14573
A18: 25/01/2025 | B18: 04:00 | C18: 1.1 | D18: 1.7 | E18: 4.3 | F18: 637.8 | G18: 215.1 | J18: 59.9 | K18: 234.7 | N18: 107.3 | O18: 108 | P18: 107.6 | Q18: 207.5 | R18: 198.7 | S18: 94.3 | T18: 546.8 | U18: 10.5 | Z18: 165.2 | AA18: 6.93 | AB18: 2.455 | AC18: 0 | AD18: 6.7 | AF18: 31.4 | AG18: 6 | AH18: 0 | AK18: 109.8 | AL18: 222.6 | AP18: 6.5 | AQ18: 351.1 | AR18: 68.9 | AS18: 129.4 | AT18: 41.1 | AU18: 18.3 | AV18: 19.5 | AW18: 89.3 | AY18: 0 | AZ18: 0 | BA18: 108.1 | BB18: 8 | BC18: 2.3 | BD18: 45.2 | BE18: 46.3 | BF18: 3.5 | BG18: 31 | BH18: 168.4 | BI18: 0 | BL18: 47.4 | BP18: 130 | BR18: 0 | BZ18: 112.7 | CC18: 221.9 | CD18: 118.7 | CE18: 62.8 | CF18: 80.6 | CG18: 29.7 | CK18: 103.2 | CL18: 103.7 | CM18: 120 | CS18: 136.3 | CT18: 79.5 | CU18: 0 | CV18: 48.4 | CW18: 0 | CX18: 15.4 | CY18: 0 | CZ18: 20 | DA18: 9.9 | DB18: 4.7 | DC18: 3.6 | DD18: 5.2 | DE18: 19.9 | DF18: 20 | DG18: 15 | DH18: 3.6 | DI18: 18.7 | DJ18: 0 | DK18: 0 | DL18: 8.2 | DM18: 23.1 | DN18: 4.7 | DO18: 2.3 | DP18: 2.4 | DQ18: 1.4 | DR18: 0 | DS18: 3.6 | DT18: 5.5 | DU18: 2 | DW18: 17.2 | DX18: 9.5 | DY18: 18.6 | DZ18: 20.3 | EA18: 19.8 | EB18: 20.2 | EC18: 22.8 | ED18: 0 | EE18: 15.9 | EF18: 38.6 | EG18: 1.9 | EH18: 1.7 | EI18: 21 | EJ18: 7.2 | EK18: 0 | EL18: 20 | EM18: 20 | EN18: 20 | EO18: 10.8 | EP18: 0 | EQ18: 0 | ER18: 0.6 | ES18: 35.8 | ET18: 39.9 | EU18: 0 | EV18: 0 | EW18: 6 | EX18: 19.9 | EY18: 9.3 | EZ18: 16.3 | FA18: 35.4 | FB18: 29 | FC18: 3.2 | FD18: 14.4 | FE18: 14.6 | FF18: 8 | FG18: 6325.285 | FI18: 24.07355 | FJ18: 1.3 | FK18: 0 | FL18: 6.0435 | FM18: 6.9 | FO18: 18.92289 | FP18: 4.9 | FQ18: 15.9 | FR18: 78.03994
A19: 25/01/2025 | B19: 04:30 | C19: 1.1 | D19: 1.7 | E19: 4.3 | F19: 655.5 | G19: 220.6 | J19: 60.4 | K19: 240.8 | N19: 109.8 | O19: 109.6 | P19: 109.9 | Q19: 209.4 | R19: 206.8 | S19: 107.6 | T19: 567.9 | U19: 10.5 | Z19: 170.8 | AA19: 8.006 | AB19: 2.758 | AC19: 0 | AD19: 6.5 | AF19: 32.9 | AG19: 5.9 | AH19: 0 | AK19: 111.7 | AL19: 223 | AP19: 6.5 | AQ19: 470.7 | AR19: 69.6 | AS19: 148.9 | AT19: 42.3 | AU19: 18.4 | AV19: 19.5 | AW19: 94.9 | AY19: 0 | AZ19: 0 | BA19: 110.4 | BB19: 8.1 | BC19: 2.3 | BD19: 45.9 | BE19: 47.6 | BF19: 3.5 | BG19: 31.5 | BH19: 171.8 | BI19: 0 | BL19: 47.1 | BP19: 131.8 | BR19: 0 | BZ19: 115.5 | CC19: 72.1 | CD19: 134.4 | CE19: 64.8 | CF19: 81.5 | CG19: 30.6 | CK19: 104.3 | CL19: 103.7 | CM19: 121.1 | CS19: 137.4 | CT19: 79.7 | CU19: 0 | CV19: 56.4 | CW19: 0 | CX19: 13 | CY19: 0 | CZ19: 20 | DA19: 9.9 | DB19: 4.6 | DC19: 3.6 | DD19: 5.1 | DE19: 20.7 | DF19: 20 | DG19: 15 | DH19: 3.5 | DI19: 18.7 | DJ19: 0 | DK19: 0 | DL19: 10.4 | DM19: 27.3 | DN19: 4.7 | DO19: 2.3 | DP19: 2.4 | DQ19: 1.4 | DR19: 0 | DS19: 3.5 | DT19: 5.3 | DU19: 2 | DW19: 17.4 | DX19: 9.5 | DY19: 18.9 | DZ19: 20.5 | EA19: 19.9 | EB19: 21.1 | EC19: 15.2 | ED19: 0 | EE19: 14.5 | EF19: 34.1 | EG19: 0.9 | EH19: 1.2 | EI19: 21 | EJ19: 7.1 | EK19: 0 | EL19: 20 | EM19: 20 | EN19: 20 | EO19: 9.8 | EP19: 0 | EQ19: 0 | ER19: 0.6 | ES19: 44 | ET19: 38.9 | EU19: 0 | EV19: 0 | EW19: 6.1 | EX19: 20 | EY19: 10.2 | EZ19: 16.9 | FA19: 35.9 | FB19: 29 | FC19: 3.3 | FD19: 14.3 | FE19: 16.3 | FF19: 8 | FG19: 6457.764 | FI19: 24.07229 | FJ19: 1.3 | FK19: 0 | FL19: 6.0425 | FM19: 6.9 | FO19: 18.92223 | FP19: 5 | FQ19: 15.9 | FR19: 78.13702
A20: 25/01/2025 | B20: 05:00 | C20: 1.1 | D20: 1.7 | E20: 4.3 | F20: 641.3 | G20: 216 | J20: 59.2 | K20: 235.1 | N20: 108.1 | O20: 109 | P20: 108.4 | Q20: 223 | R20: 204.8 | S20: 108.2 | T20: 551.8 | U20: 10.3 | Z20: 162.9 | AA20: 7.015 | AB20: 2.46 | AC20: 0 | AD20: 6.7 | AF20: 30.6 | AG20: 5.9 | AH20: 0 | AK20: 110 | AL20: 221.7 | AP20: 6.5 | AQ20: 464.1 | AR20: 68.9 | AS20: 137 | AT20: 41.2 | AU20: 18.4 | AV20: 19.5 | AW20: 89.8 | AY20: 0 | AZ20: 0 | BA20: 108.6 | BB20: 8 | BC20: 2.3 | BD20: 44.7 | BE20: 46.5 | BF20: 3.5 | BG20: 31 | BH20: 168.5 | BI20: 0 | BL20: 47 | BP20: 129.7 | BR20: 0 | BZ20: 113.4 | CC20: 72.2 | CD20: 125.1 | CE20: 63.1 | CF20: 78.8 | CG20: 29.9 | CK20: 104.1 | CL20: 104.4 | CM20: 120.7 | CS20: 136.3 | CT20: 79.7 | CU20: 0 | CV20: 59.3 | CW20: 0 | CX20: 14.2 | CY20: 0 | CZ20: 20 | DA20: 9.9 | DB20: 4.7 | DC20: 3.6 | DD20: 5.1 | DE20: 20 | DF20: 20 | DG20: 15.1 | DH20: 3.5 | DI20: 18.7 | DJ20: 0 | DK20: 0 | DL20: 12.6 | DM20: 28.4 | DN20: 4.6 | DO20: 2.3 | DP20: 2.4 | DQ20: 1.3 | DR20: 0 | DS20: 3.5 | DT20: 5.1 | DU20: 2 | DW20: 17.6 | DX20: 9.4 | DY20: 18.7 | DZ20: 20.3 | EA20: 20 | EB20: 22.6 | EC20: 11.6 | ED20: 0 | EE20: 9.1 | EF20: 25.1 | EG20: 1 | EH20: 0.7 | EI20: 21 | EJ20: 7 | EK20: 0 | EL20: 20 | EM20: 20 | EN20: 20 | EO20: 12.3 | EP20: 0 | EQ20: 0 | ER20: 0.6 | ES20: 41.9 | ET20: 31 | EU20: 0 | EV20: 0 | EW20: 6 | EX20: 20 | EY20: 9.5 | EZ20: 16.3 | FA20: 35.4 | FB20: 28.9 | FC20: 3.3 | FD20: 14.5 | FE20: 14.6 | FF20: 7.4 | FG20: 6334.575 | FI20: 24.07335 | FJ20: 1.3 | FK20: 0 | FL20: 6.0435 | FM20: 6.9 | FO20: 18.92209 | FP20: 5 | FQ20: 15.7 | FR20: 77.93894
A21: 25/01/2025 | B21: 05:30 | C21: 1.1 | D21: 1.7 | E21: 4.3 | F21: 647.1 | G21: 218.3 | J21: 60 | K21: 206.5 | N21: 145.9 | O21: 145.3 | P21: 145.5 | Q21: 240.7 | R21: 206 | S21: 108.3 | T21: 559.8 | U21: 10.5 | Z21: 164.9 | AA21: 7.302 | AB21: 2.57 | AC21: 0 | AD21: 6.7 | AF21: 32.1 | AG21: 5.6 | AH21: 0 | AK21: 110.7 | AL21: 223.1 | AP21: 6.5 | AQ21: 463.7 | AR21: 69 | AS21: 146.6 | AT21: 41.9 | AU21: 18.4 | AV21: 19.5 | AW21: 91.4 | AY21: 0 | AZ21: 0 | BA21: 107.3 | BB21: 8 | BC21: 2.3 | BD21: 44.5 | BE21: 46.5 | BF21: 3.5 | BG21: 31 | BH21: 170 | BI21: 0 | BL21: 47.2 | BP21: 130.5 | BR21: 0 | BZ21: 113.8 | CC21: 92.7 | CD21: 131.2 | CE21: 63.6 | CF21: 79 | CG21: 30 | CK21: 103.9 | CL21: 103.6 | CM21: 120.1 | CS21: 137.3 | CT21: 79.7 | CU21: 0 | CV21: 58.5 | CW21: 0 | CX21: 16.9 | CY21: 0 | CZ21: 20 | DA21: 9.9 | DB21: 4.7 | DC21: 3.6 | DD21: 5.1 | DE21: 20.2 | DF21: 20 | DG21: 15 | DH21: 3.5 | DI21: 18.8 | DJ21: 0.1 | DK21: 0 | DL21: 15.2 | DM21: 27.4 | DN21: 3.8 | DO21: 2.3 | DP21: 2.4 | DQ21: 2.3 | DR21: 0.7 | DS21: 3.6 | DT21: 5.2 | DU21: 2 | DW21: 17.6 | DX21: 9.4 | DY21: 18.9 | DZ21: 20.4 | EA21: 20 | EB21: 18.3 | EC21: 18 | ED21: 0 | EE21: 5.4 | EF21: 12.2 | EG21: 0.8 | EH21: 0 | EI21: 21 | EJ21: 6.9 | EK21: 0 | EL21: 20 | EM21: 20 | EN21: 20 | EO21: 12.6 | EP21: 0 | EQ21: 0 | ER21: 0.6 | ES21: 29.7 | ET21: 26.4 | EU21: 0.2 | EV21: 0 | EW21: 6.1 | EX21: 20 | EY21: 10 | EZ21: 16.6 | FA21: 36 | FB21: 28.9 | FC21: 3.2 | FD21: 14 | FE21: 12.6 | FF21: 7.5 | FG21: 6471.172 | FI21: 24.07693 | FJ21: 1.3 | FK21: 0 | FL21: 6.0455 | FM21: 6.9 | FO21: 18.92197 | FP21: 5 | FQ21: 15.9 | FR21: 78.1444
A22: 25/01/2025 | B22: 06:00 | C22: 1.1 | D22: 1.7 | E22: 4.3 | F22: 643.6 | G22: 216.8 | J22: 58.3 | K22: 204.4 | N22: 140.8 | O22: 140.3 | P22: 140.1 | Q22: 239 | R22: 207.9 | S22: 108.1 | T22: 551.2 | U22: 10.3 | Z22: 164.6 | AA22: 7.062 | AB22: 2.562 | AC22: 0 | AD22: 6.7 | AF22: 30.8 | AG22: 4.9 | AH22: 0 | AK22: 110 | AL22: 222.6 | AP22: 6.5 | AQ22: 464.7 | AR22: 65.9 | AS22: 146.2 | AT22: 41.5 | AU22: 18.4 | AV22: 19.5 | AW22: 90.1 | AY22: 0 | AZ22: 0 | BA22: 109 | BB22: 8 | BC22: 2.3 | BD22: 45.5 | BE22: 46.3 | BF22: 3.5 | BG22: 31.1 | BH22: 168.9 | BI22: 0 | BL22: 47 | BP22: 129.1 | BR22: 0 | BZ22: 113.2 | CC22: 88.9 | CD22: 129.2 | CE22: 62.6 | CF22: 78.3 | CG22: 29.7 | CK22: 104.2 | CL22: 104.5 | CM22: 120.5 | CS22: 135.9 | CT22: 79.2 | CU22: 0 | CV22: 46.3 | CW22: 6.7 | CX22: 14.2 | CY22: 0 | CZ22: 20 | DA22: 9.9 | DB22: 4.7 | DC22: 3.6 | DD22: 5.1 | DE22: 19.9 | DF22: 20 | DG22: 15 | DH22: 3.5 | DI22: 18.8 | DJ22: 0.6 | DK22: 0.6 | DL22: 9.8 | DM22: 18.5 | DN22: 3.7 | DO22: 2.3 | DP22: 2.4 | DQ22: 2.4 | DR22: 3.1 | DS22: 3.5 | DT22: 5.2 | DU22: 2 | DW22: 17.1 | DX22: 9.5 | DY22: 19 | DZ22: 20.3 | EA22: 19.9 | EB22: 19.2 | EC22: 25.6 | ED22: 2.9 | EE22: 3 | EF22: 6.1 | EG22: 0 | EH22: 0.1 | EI22: 21 | EJ22: 6.8 | EK22: 0 | EL22: 20 | EM22: 20 | EN22: 20 | EO22: 7.8 | EP22: 0.5 | EQ22: 9.6 | ER22: 0.6 | ES22: 20.9 | ET22: 20.7 | EU22: 8.1 | EV22: 0.5 | EW22: 6 | EX22: 19.8 | EY22: 9.8 | EZ22: 16.7 | FA22: 35.8 | FB22: 28.8 | FC22: 3.2 | FD22: 12.8 | FE22: 14.9 | FF22: 7.6 | FG22: 6403.224 | FI22: 24.07498 | FJ22: 1.3 | FK22: 0 | FL22: 6.0455 | FM22: 6.9 | FO22: 18.92278 | FP22: 5 | FQ22: 15.9 | FR22: 78.14326
... A58: 26/01/2025 | B58: 00:00 | C58: 1.1 | D58: 1.6 | E58: 4.3 | F58: 648.6 | G58: 218.7 | J58: 89.6 | K58: 238.2 | N58: 145.2 | O58: 147.1 | P58: 146.9 | Q58: 240.9 | R58: 210.1 | S58: 108.7 | T58: 563.7 | U58: 10.3 | Z58: 163.3 | AA58: 7.446 | AB58: 2.727 | AC58: 0 | AD58: 6.6 | AF58: 85.3 | AG58: 6 | AH58: 0 | AK58: 110.6 | AL58: 211.3 | AP58: 6.5 | AQ58: 459.3 | AR58: 59 | AS58: 146.7 | AT58: 41.9 | AU58: 18.4 | AV58: 19.6 | AW58: 90.8 | AY58: 0 | AZ58: 0 | BA58: 106.7 | BB58: 8.1 | BC58: 2.5 | BD58: 46.8 | BE58: 47 | BF58: 3.6 | BG58: 31.6 | BH58: 166.7 | BI58: 19.6 | BL58: 47.4 | BP58: 129.7 | BR58: 0 | BZ58: 115.4 | CC58: 228.8 | CD58: 131.6 | CE58: 62.9 | CF58: 81 | CG58: 29.9 | CK58: 145.4 | CL58: 145.6 | CM58: 149.2 | CS58: 136.8 | CT58: 84.3 | CU58: 0 | CV58: 24.8 | CW58: 0 | CX58: 5.3 | CY58: 0 | CZ58: 20 | DA58: 10 | DB58: 5.3 | DC58: 3.6 | DD58: 5.2 | DE58: 20.3 | DF58: 20 | DG58: 13.5 | DH58: 3.4 | DI58: 18.8 | DJ58: 0 | DK58: 0 | DL58: 4.5 | DM58: 11.6 | DN58: 4.6 | DO58: 2.3 | DP58: 2.4 | DQ58: 3.1 | DR58: 0 | DS58: 3.6 | DT58: 11 | DU58: 2 | DW58: 15 | DX58: 9 | DY58: 20 | DZ58: 20.4 | EA58: 19.9 | EB58: 19.8 | EC58: 64.2 | ED58: 0 | EE58: 10.8 | EF58: 19.2 | EG58: 0.2 | EH58: 0.1 | EI58: 21 | EJ58: 5.3 | EK58: 6.6 | EL58: 20 | EM58: 20 | EN58: 20 | EO58: 3.7 | EP58: 0 | EQ58: 0 | ER58: 0.6 | ES58: 21.6 | ET58: 19.4 | EU58: 0 | EV58: 0 | EW58: 6 | EX58: 20 | EY58: 10.3 | EZ58: 16.6 | FA58: 36.2 | FB58: 29.2 | FC58: 3.4 | FD58: 13 | FE58: 12 | FF58: 8.6 | FG58: 6818.473 | FI58: 23.96457 | FJ58: 1.2 | FK58: 0.536 | FL58: 6.122 | FM58: 13.2 | FO58: 18.92216 | FP58: 4.7 | FQ58: 15.8 | FR58: 84.44473
A59: EJEC | C59: 26.4 | D59: 40.15 | E59: 103.05 | F59: 15521 | G59: 5222.6 | H59: 0 | I59: 0 | J59: 1905.95 | K59: 5583.95 | L59: 0 | M59: 0 | N59: 3075.8 | O59: 3075.55 | P59: 3073.5 | Q59: 5461.45 | R59: 4715.05 | S59: 2507.3 | T59: 13388.7 | U59: 252.35 | V59: 0 | W59: 0 | X59: 0 | Y59: 0 | Z59: 3979.55 | AA59: 181.154 | AB59: 62.7405 | AC59: 97.056 | AD59: 158.7 | AE59: 0 | AF59: 1548.95 | AG59: 138.15 | AH59: 4.25 | AI59: 0 | AJ59: 0 | AK59: 2655.9 | AL59: 5063.2 | AM59: 0 | AN59: 0 | AO59: 0 | AP59: 156 | AQ59: 10957.85 | AR59: 1557.6 | AS59: 3397.55 | AT59: 1002.7 | AU59: 440.85 | AV59: 466.95 | AW59: 2166.25 | AX59: 0 | AY59: 2285.3 | AZ59: 1127.95 | BA59: 2610.25 | BB59: 192.7 | BC59: 57.25 | BD59: 1094.7 | BE59: 1126 | BF59: 84.45 | BG59: 750.2 | BH59: 3502.05 | BI59: 1035.05 | BJ59: 0 | BK59: 0 | BL59: 1118.85 | BM59: 0 | BN59: 0 | BO59: 0 | BP59: 3136.85 | BQ59: 0 | BR59: 233.85 | BS59: 0 | BT59: 0 | BU59: 0 | BV59: 0 | BW59: 0 | BX59: 0 | BY59: 0 | BZ59: 2067.8 | CA59: 0 | CB59: 0 | CC59: 3472.15 | CD59: 3058 | CE59: 1529.5 | CF59: 1941.6 | CG59: 722.2 | CH59: 0 | CI59: 0 | CJ59: 0 | CK59: 3158.35 | CL59: 3147.8 | CM59: 3341.85 | CN59: 0 | CO59: 0 | CP59: 0 | CQ59: 0 | CR59: 0 | CS59: 4221.55 | CT59: 2295.05 | CU59: 8.1 | CV59: 1151.9 | CW59: 645.3 | CX59: 290.3 | CY59: 2.1 | CZ59: 479.6 | DA59: 238.1 | DB59: 122.5 | DC59: 86.45 | DD59: 124.1 | DE59: 484.25 | DF59: 476.95 | DG59: 355.35 | DH59: 82.15 | DI59: 431.75 | DJ59: 115.25 | DK59: 140.45 | DL59: 253.05 | DM59: 731.7 | DN59: 98 | DO59: 54.9 | DP59: 57.6 | DQ59: 54.9 | DR59: 158.3 | DS59: 84.75 | DT59: 331.05 | DU59: 48 | DV59: 0 | DW59: 383.65 | DX59: 212.7 | DY59: 475.25 | DZ59: 487.8 | EA59: 478.4 | EB59: 384.9 | EC59: 1193.4 | ED59: 266.5 | EE59: 599.35 | EF59: 907.35 | EG59: 53.8 | EH59: 53.15 | EI59: 504 | EJ59: 148 | EK59: 114.45 | EL59: 480 | EM59: 480 | EN59: 478.45 | EO59: 230.9 | EP59: 121.45 | EQ59: 1112.45 | ER59: 14.4 | ES59: 1093.05 | ET59: 1084.2 | EU59: 904.85 | EV59: 120.15 | EW59: 144.25 | EX59: 478.65 | EY59: 210.35 | EZ59: 395.35 | FA59: 852.7 | FB59: 683.65 | FC59: 77.25 | FD59: 328.6 | FE59: 334.4 | FF59: 185 | FG59: 168479.15 | FI59: 572.31946 | FJ59: 31.15 | FK59: 78.0955 | FL59: 145.75775 | FM59: 193.55 | FN59: 0 | FO59: 454.12627 | FP59: 105.95 | FQ59: 380.55 | FR59: 1961.499

Sheet REACTIVA
B3: sábado, 25 de Enero del 2025
A5: POTENCIA REACTIVA EJECUTADA DE LAS UNIDADES DE GENERACIÓN DEL COES (MVAR) | FH5: CENTRALES NO INTEGRANTES COES
A6: FECHA | B6: HORA | C6: 337 | D6: 338 | E6: 121 | F6: 101 | G6: 102 | H6: 42667 | I6: 42668 | J6: 126 | K6: 127 | L6: 138 | M6: 139 | N6: 197 | O6: 203 | P6: 204 | Q6: 230 | R6: 209 | S6: 56677 | T6: 796 | U6: 2146 | V6: 142 | W6: 143 | X6: 125 | Y6: 187 | Z6: 163 | AA6: 298 | AB6: 219 | AC6: 151 | AD6: 152 | AE6: 153 | AF6: 154 | AG6: 756 | AH6: 156 | AI6: 155 | AJ6: 182 | AK6: 212 | AL6: 758 | AM6: 263 | AN6: 265 | AO6: 775 | AP6: 777 | AQ6: 2154 | AR6: 150 | AS6: 149 | AT6: 188 | AU6: 2131 | AV6: 755 | AW6: 252 | AX6: 249 | AY6: 250 | AZ6: 117 | BA6: 267 | BB6: 268 | BC6: 119 | BD6: 120 | BE6: 189 | BF6: 122 | BG6: 266 | BH6: 251 | BI6: 115 | BJ6: 239 | BK6: 288 | BL6: 240 | BM6: 241 | BN6: 242 | BO6: 191 | BP6: 194 | BQ6: 196 | BR6: 207 | BS6: 236 | BT6: 795 | BU6: 285 | BV6: 995 | BW6: 996 | BX6: 997 | BY6: 766 | BZ6: 926 | CA6: 924 | CB6: 103 | CC6: 104 | CD6: 106 | CE6: 105 | CF6: 107 | CG6: 110 | CH6: 109 | CI6: 144 | CJ6: 113 | CK6: 114 | CL6: 193 | CM6: 208 | CN6: 786 | CO6: 787 | CP6: 788 | CQ6: 789 | CR6: 248 | CS6: 2159 | CT6: 303 | CU6: 59715 | CV6: 62255 | CW6: 1263 | CX6: 61800 | CY6: 2194 | CZ6: 216 | DA6: 198 | DB6: 214 | DC6: 260 | DD6: 2152 | DE6: 2128 | DF6: 247 | DG6: 228 | DH6: 2135 | DI6: 261 | DJ6: 237 | DK6: 253 | DL6: 770 | DM6: 225 | DN6: 2201 | DO6: 2171 | DP6: 760 | DQ6: 235 | DR6: 238 | DS6: 2184 | DT6: 61855 | DU6: 223 | DV6: 226 | DW6: 201 | DX6: 258 | DY6: 259 | DZ6: 920 | EA6: 257 | EB6: 256 | EC6: 2148 | ED6: 58288 | EE6: 58289 | EF6: 58839 | EG6: 58840 | EH6: 296 | EI6: 297 | EJ6: 211 | EK6: 2175 | EL6: 2178 | EM6: 2181 | EN6: 1262 | EO6: 233 | EP6: 2150 | EQ6: 2165 | ER6: 2161 | ES6: 61197 | ET6: 58851 | EU6: 234 | EV6: 215 | EW6: 917 | EX6: 289 | EY6: 58333 | EZ6: 58336 | FA6: 202 | FB6: 58487 | FC6: 213 | FD6: 232 | FE6: 2190 | FF6: TOTAL COES | FH6: 221 | FI6: 49607 | FJ6: 222 | FK6: 224 | FL6: 2187 | FM6: 227 | FN6: 49400 | FO6: 199 | FP6: 200 | FQ6: TOTAL NO COES
C7: CENTRO | D7: CENTRO | E7: NORTE | F7: CENTRO | G7: CENTRO | H7: NORTE | I7: NORTE | J7: NORTE | K7: NORTE | L7: CENTRO | M7: CENTRO | N7: CENTRO | O7: CENTRO | P7: CENTRO | Q7: CENTRO | R7: CENTRO | S7: CENTRO | T7: CENTRO | U7: CENTRO | V7: CENTRO | W7: CENTRO | X7: CENTRO | Y7: CENTRO | Z7: SUR | AA7: SUR | AB7: CENTRO | AC7: SUR | AD7: SUR | AE7: SUR | AF7: SUR | AG7: SUR | AH7: SUR | AI7: SUR | AJ7: SUR | AK7: CENTRO | AL7: NORTE | AM7: NORTE | AN7: NORTE | AO7: CENTRO | AP7: CENTRO | AQ7: CENTRO | AR7: CENTRO | AS7: CENTRO | AT7: CENTRO | AU7: CENTRO | AV7: SUR | AW7: CENTRO | AX7: CENTRO | AY7: CENTRO | AZ7: CENTRO | BA7: CENTRO | BB7: CENTRO | BC7: CENTRO | BD7: CENTRO | BE7: SUR | BF7: NORTE | BG7: CENTRO | BH7: CENTRO | BI7: NORTE | BJ7: NORTE | BK7: NORTE | BL7: SUR | BM7: SUR | BN7: SUR | BO7: CENTRO | BP7: CENTRO | BQ7: CENTRO | BR7: CENTRO | BS7: CENTRO | BT7: CENTRO | BU7: CENTRO | BV7: SUR | BW7: SUR | BX7: SUR | BY7: NORTE | BZ7: SUR | CA7: CENTRO | CB7: CENTRO | CC7: CENTRO | CD7: CENTRO | CE7: CENTRO | CF7: CENTRO | CG7: CENTRO | CH7: CENTRO | CI7: CENTRO | CJ7: CENTRO | CK7: CENTRO | CL7: CENTRO | CM7: CENTRO | CN7: SUR | CO7: SUR | CP7: SUR | CQ7: SUR | CR7: CENTRO | CS7: CENTRO | CT7: CENTRO | CU7: CENTRO | CV7: SUR | CW7: NORTE | CX7: NORTE | CY7: NORTE | CZ7: NORTE | DA7: NORTE | DB7: CENTRO | DC7: CENTRO | DD7: CENTRO | DE7: NORTE | DF7: NORTE | DG7: CENTRO | DH7: CENTRO | DI7: SUR | DJ7: SUR | DK7: CENTRO | DL7: CENTRO | DM7: CENTRO | DN7: CENTRO | DO7: CENTRO | DP7: CENTRO | DQ7: SUR | DR7: CENTRO | DS7: CENTRO | DT7: NORTE | DU7: CENTRO | DV7: CENTRO | DW7: NORTE | DX7: CENTRO | DY7: CENTRO | DZ7: CENTRO | EA7: NORTE | EB7: NORTE | EC7: SUR | ED7: CENTRO | EE7: CENTRO | EF7: CENTRO | EG7: CENTRO | EH7: CENTRO | EI7: CENTRO | EJ7: SUR | EK7: SUR | EL7: SUR | EM7: SUR | EN7: NORTE | EO7: SUR | EP7: SUR | EQ7: CENTRO | ER7: CENTRO | ES7: CENTRO | ET7: SUR | EU7: SUR | EV7: NORTE | EW7: CENTRO | EX7: NORTE | EY7: NORTE | EZ7: NORTE | FA7: CENTRO | FB7: CENTRO | FC7: CENTRO | FD7: NORTE | FE7: NORTE | FH7: NORTE | FI7: SUR | FJ7: CENTRO | FK7: NORTE | FL7: NORTE | FM7: NORTE | FN7: NORTE | FO7: NORTE | FP7: NORTE
C8: HIDROELÉCTRICA | D8: HIDROELÉCTRICA | E8: HIDROELÉCTRICA | F8: HIDROELÉCTRICA | G8: HIDROELÉCTRICA | H8: TERMOELÉCTRICA | I8: TERMOELÉCTRICA | J8: HIDROELÉCTRICA | K8: HIDROELÉCTRICA | L8: TERMOELÉCTRICA | M8: TERMOELÉCTRICA | N8: TERMOELÉCTRICA | O8: TERMOELÉCTRICA | P8: TERMOELÉCTRICA | Q8: TERMOELÉCTRICA | R8: TERMOELÉCTRICA | S8: TERMOELÉCTRICA | T8: HIDROELÉCTRICA | U8: HIDROELÉCTRICA | V8: TERMOELÉCTRICA | W8: TERMOELÉCTRICA | X8: TERMOELÉCTRICA | Y8: TERMOELÉCTRICA | Z8: HIDROELÉCTRICA | AA8: HIDROELÉCTRICA | AB8: TERMOELÉCTRICA | AC8: HIDROELÉCTRICA | AD8: HIDROELÉCTRICA | AE8: HIDROELÉCTRICA | AF8: HIDROELÉCTRICA | AG8: TERMOELÉCTRICA | AH8: TERMOELÉCTRICA | AI8: TERMOELÉCTRICA | AJ8: HIDROELÉCTRICA | AK8: HIDROELÉCTRICA | AL8: TERMOELÉCTRICA | AM8: TERMOELÉCTRICA | AN8: TERMOELÉCTRICA | AO8: HIDROELÉCTRICA | AP8: HIDROELÉCTRICA | AQ8: HIDROELÉCTRICA | AR8: HIDROELÉCTRICA | AS8: HIDROELÉCTRICA | AT8: HIDROELÉCTRICA | AU8: HIDROELÉCTRICA | AV8: HIDROELÉCTRICA | AW8: TERMOELÉCTRICA | AX8: TERMOELÉCTRICA | AY8: TERMOELÉCTRICA | AZ8: HIDROELÉCTRICA | BA8: HIDROELÉCTRICA | BB8: HIDROELÉCTRICA | BC8: HIDROELÉCTRICA | BD8: HIDROELÉCTRICA | BE8: HIDROELÉCTRICA | BF8: HIDROELÉCTRICA | BG8: HIDROELÉCTRICA | BH8: HIDROELÉCTRICA | BI8: TERMOELÉCTRICA | BJ8: TERMOELÉCTRICA | BK8: TERMOELÉCTRICA | BL8: TERMOELÉCTRICA | BM8: TERMOELÉCTRICA | BN8: TERMOELÉCTRICA | BO8: HIDROELÉCTRICA | BP8: TERMOELÉCTRICA | BQ8: TERMOELÉCTRICA | BR8: TERMOELÉCTRICA | BS8: TERMOELÉCTRICA | BT8: TERMOELÉCTRICA | BU8: TERMOELÉCTRICA | BV8: TERMOELÉCTRICA | BW8: TERMOELÉCTRICA | BX8: TERMOELÉCTRICA | BY8: HIDROELÉCTRICA | BZ8: TERMOELÉCTRICA | CA8: TERMOELÉCTRICA | CB8: HIDROELÉCTRICA | CC8: HIDROELÉCTRICA | CD8: HIDROELÉCTRICA | CE8: HIDROELÉCTRICA | CF8: HIDROELÉCTRICA | CG8: TERMOELÉCTRICA | CH8: TERMOELÉCTRICA | CI8: TERMOELÉCTRICA | CJ8: TERMOELÉCTRICA | CK8: TERMOELÉCTRICA | CL8: TERMOELÉCTRICA | CM8: TERMOELÉCTRICA | CN8: TERMOELÉCTRICA | CO8: TERMOELÉCTRICA | CP8: TERMOELÉCTRICA | CQ8: TERMOELÉCTRICA | CR8: TERMOELÉCTRICA | CS8: TERMOELÉCTRICA | CT8: SOLAR | CU8: EÓLICA | CV8: SOLAR | CW8: EÓLICA | CX8: SOLAR | CY8: HIDROELÉCTRICA | CZ8: HIDROELÉCTRICA | DA8: HIDROELÉCTRICA | DB8: HIDROELÉCTRICA | DC8: HIDROELÉCTRICA | DD8: HIDROELÉCTRICA | DE8: HIDROELÉCTRICA | DF8: HIDROELÉCTRICA | DG8: HIDROELÉCTRICA | DH8: HIDROELÉCTRICA | DI8: SOLAR | DJ8: SOLAR | DK8: EÓLICA | DL8: EÓLICA | DM8: TERMOELÉCTRICA | DN8: TERMOELÉCTRICA | DO8: TERMOELÉCTRICA | DP8: TERMOELÉCTRICA | DQ8: SOLAR | DR8: HIDROELÉCTRICA | DS8: HIDROELÉCTRICA | DT8: HIDROELÉCTRICA | DU8: HIDROELÉCTRICA | DV8: HIDROELÉCTRICA | DW8: HIDROELÉCTRICA | DX8: HIDROELÉCTRICA | DY8: HIDROELÉCTRICA | DZ8: HIDROELÉCTRICA | EA8: EÓLICA | EB8: EÓLICA | EC8: SOLAR | ED8: EÓLICA | EE8: EÓLICA | EF8: EÓLICA | EG8: EÓLICA | EH8: HIDROELÉCTRICA | EI8: HIDROELÉCTRICA | EJ8: HIDROELÉCTRICA | EK8: HIDROELÉCTRICA | EL8: HIDROELÉCTRICA | EM8: HIDROELÉCTRICA | EN8: EÓLICA | EO8: SOLAR | EP8: SOLAR | EQ8: HIDROELÉCTRICA | ER8: EÓLICA | ES8: EÓLICA | ET8: SOLAR | EU8: SOLAR | EV8: HIDROELÉCTRICA | EW8: HIDROELÉCTRICA | EX8: TERMOELÉCTRICA | EY8: TERMOELÉCTRICA | EZ8: TERMOELÉCTRICA | FA8: TERMOELÉCTRICA | FB8: TERMOELÉCTRICA | FC8: TERMOELÉCTRICA | FD8: TERMOELÉCTRICA | FE8: TERMOELÉCTRICA | FH8: HIDROELÉCTRICA | FI8: HIDROELÉCTRICA | FJ8: HIDROELÉCTRICA | FK8: HIDROELÉCTRICA | FL8: HIDROELÉCTRICA | FM8: TERMOELÉCTRICA | FN8: TERMOELÉCTRICA | FO8: HIDROELÉCTRICA | FP8: HIDROELÉCTRICA
C9: CENTRALES SANTA ROSA S.A.C. | D9: CENTRALES SANTA ROSA S.A.C. | E9: INVERSIONES SHAQSHA S.A.C. | F9: ELECTROPERU | G9: ELECTROPERU | H9: ELECTROPERU | I9: ELECTROPERU | J9: ORAZUL ENERGY PERÚ | K9: ORAZUL ENERGY PERÚ | L9: TERMOSELVA | M9: TERMOSELVA | N9: KALLPA GENERACION S.A. | O9: KALLPA GENERACION S.A. | P9: KALLPA GENERACION S.A. | Q9: KALLPA GENERACION S.A. | R9: KALLPA GENERACION S.A. | S9: KALLPA GENERACION S.A. | T9: KALLPA GENERACION S.A. | U9: KALLPA GENERACION S.A. | V9: SHOUGESA | W9: SHOUGESA | X9: SHOUGESA | Y9: SHOUGESA | Z9: EGEMSA | AA9: EGESUR | AB9: EGESUR | AC9: EGASA | AD9: EGASA | AE9: EGASA | AF9: EGASA | AG9: EGASA | AH9: EGASA | AI9: EGASA | AJ9: SAN GABAN | AK9: CELEPSA | AL9: MINERA CERRO VERDE | AM9: PLANTA DE RESERVA FRIA DE GENERACION DE ETEN S.A. | AN9: PLANTA DE RESERVA FRIA DE GENERACION DE ETEN S.A. | AO9: EMPRESA DE GENERACION HUALLAGA | AP9: EMPRESA DE GENERACION HUALLAGA | AQ9: LA VIRGEN | AR9: CHINANGO S.A.C. | AS9: CHINANGO S.A.C. | AT9: HIDROELECTRICA HUANCHOR S.A.C. | AU9: CELEPSA RENOVABLES S.R.L. | AV9: INLAND ENERGY SAC | AW9: FENIX POWER PERÚ | AX9: FENIX POWER PERÚ | AY9: FENIX POWER PERÚ | AZ9: STATKRAFT S.A | BA9: STATKRAFT S.A | BB9: STATKRAFT S.A | BC9: STATKRAFT S.A | BD9: STATKRAFT S.A | BE9: STATKRAFT S.A | BF9: STATKRAFT S.A | BG9: STATKRAFT S.A | BH9: EMPRESA DE GENERACION HUANZA | BI9: ENEL GENERACION PIURA S.A. | BJ9: ENEL GENERACION PIURA S.A. | BK9: ENEL GENERACION PIURA S.A. | BL9: ENGIE | BM9: ENGIE | BN9: ENGIE | BO9: ENGIE | BP9: ENGIE | BQ9: ENGIE | BR9: ENGIE | BS9: ENGIE | BT9: ENGIE | BU9: ENGIE | BV9: ENGIE | BW9: ENGIE | BX9: ENGIE | BY9: ENGIE | BZ9: INFRAESTRUCTURAS Y ENERGIAS DEL PERU S.A.C. | CA9: INFRAESTRUCTURAS Y ENERGIAS DEL PERU S.A.C. | CB9: ORYGEN PERU S.A.A. | CC9: ORYGEN PERU S.A.A. | CD9: ORYGEN PERU S.A.A. | CE9: ORYGEN PERU S.A.A. | CF9: ORYGEN PERU S.A.A. | CG9: ORYGEN PERU S.A.A. | CH9: ORYGEN PERU S.A.A. | CI9: ORYGEN PERU S.A.A. | CJ9: ORYGEN PERU S.A.A. | CK9: ORYGEN PERU S.A.A. | CL9: ORYGEN PERU S.A.A. | CM9: ORYGEN PERU S.A.A. | CN9: SAMAY I S.A.C | CO9: SAMAY I S.A.C | CP9: SAMAY I S.A.C | CQ9: SAMAY I S.A.C | CR9: TERMOCHILCA S.A.C. | CS9: TERMOCHILCA S.A.C. | CT9: COLCA SOLAR S.A.C. | CU9: ENERGIA RENOVABLE DEL SUR S.A. | CV9: GR CORTARRAMA SOCIEDAD ANONIMA CERRADA | CW9: GR TARUCA SOCIEDAD ANONIMA CERRADA | CX9: KONDU SAC | CY9: PERUANA DE INVERSIONES EN ENERGIAS RENOVABLES S.A. | CZ9: ORAZUL ENERGY PERÚ | DA9: ORAZUL ENERGY PERÚ | DB9: MAJA ENERGIA S.A.C. | DC9: EMPRESA DE GENERACION ELECTRICA CANCHAYLLO SAC | DD9: EMPRESA DE GENERACION ELECTRICA SANTA ANA S.A.C. | DE9: EMPRESA ELECTRICA AGUA AZUL | DF9: EMPRESA ELECTRICA RIO DOBLE | DG9: HIDROCAÑETE S.A. | DH9: HUAURA POWER GROUP S.A. | DI9: MOQUEGUA FV S.A.C. | DJ9: PANAMERICANA SOLAR SAC. | DK9: PARQUE EOLICO MARCONA S.A.C. | DL9: PARQUE EOLICO TRES HERMANAS S.A.C. | DM9: PETRAMAS | DN9: PETRAMAS | DO9: PETRAMAS | DP9: PETRAMAS | DQ9: TACNA SOLAR SAC. | DR9: ELECTRICA YANAPAMPA SAC | DS9: ANDEAN POWER S.A.C. | DT9: ASOCIACIÓN SANTA LUCIA DE CHACAS | DU9: ATRIA ENERGIA S.A.C. | DV9: EGEJUNIN | DW9: EGEJUNIN | DX9: EGEJUNIN | DY9: EGEJUNIN | DZ9: EMPRESA DE GENERACION ELECTRICA RIO BAÑOS S.A.C. | EA9: ENERGÍA EÓLICA S.A. | EB9: ENERGÍA EÓLICA S.A. | EC9: ENGIE | ED9: ENGIE | EE9: ENGIE | EF9: ENGIE | EG9: ENGIE | EH9: GENERACIÓN ANDINA S.A.C. | EI9: GENERACIÓN ANDINA S.A.C. | EJ9: GENERADORA DE ENERGÍA DEL PERÚ | EK9: GENERADORA DE ENERGÍA DEL PERÚ | EL9: GENERADORA DE ENERGÍA DEL PERÚ | EM9: GENERADORA DE ENERGÍA DEL PERÚ | EN9: GR PAINO SOCIEDAD ANONIMA CERRADA | EO9: MAJES ARCUS S.A.C. | EP9: ORYGEN PERU S.A.A. | EQ9: ORYGEN PERU S.A.A. | ER9: ORYGEN PERU S.A.A. | ES9: ORYGEN PERU S.A.A. | ET9: ORYGEN PERU S.A.A. | EU9: REPARTICIÓN ARCUS S.A.C. | EV9: SINERSA | EW9: SINERSA | EX9: BIOENERGIA DEL CHIRA S.A. | EY9: GM OPERACIONES S.A.C. | EZ9: GM OPERACIONES S.A.C. | FA9: SDF ENERGIA SAC | FB9: SDF ENERGIA SAC | FC9: AGRO INDUSTRIAL PARAMONGA S.A. | FD9: AGROAURORA S.A.C. | FE9: AGROINDUSTRIAS SAN JACINTO S.A.A. | FH9: UNACEM PERU S.A. | FI9: SAN GABAN | FJ9: ELECTRO ORIENTE | FK9: AGUAS Y ENERGIA PERU | FL9: ELECTRO ZAÑA S.A.C. | FM9: ELECTRONOROESTE S.A. | FN9: SDE PIURA | FO9: SINERSA | FP9: SINERSA
C10: SANTA ROSA 1 | D10: SANTA ROSA 2 | E10: PARIAC | F10: MANTARO | G10: RESTITUCION | H10: TUMBES MAK 1 | I10: TUMBES MAK 2 | J10: CARHUAQUERO | K10: CAÑON DEL PATO | L10: AGUAYTIA TG1 | M10: AGUAYTIA TG2 | N10: KALLPA TG1 | O10: KALLPA TG2 | P10: KALLPA TG3 | Q10: KALLPA TV | R10: LFLORES TG1 | S10: LFLORES TV | T10: CERRO DEL AGUILA | U10: CERRODELAGUILAG4 | V10: SHOUGESA TV1 | W10: SHOUGESA TV2 | X10: SHOUGESA TV3 | Y10: SHOUGESA CUMMINS | Z10: MACHUPICCHU | AA10: ARICOTA 1 | AB10: INDEPENDENCIA | AC10: CHARCANI I,II,III | AD10: CHARCANI IV | AE10: CHARCANI V | AF10: CHARCANI VI | AG10: CHILINA TG | AH10: MOLLENDO 1, 2, 3 | AI10: CHILINA (SULZ 1,2) | AJ10: SAN GABAN II | AK10: PLATANAL | AL10: RECKA | AM10: RF ETEN TG1 | AN10: RF ETEN TG2 | AO10: CHAGLLA GP1 | AP10: CHAGLLA | AQ10: LA VIRGEN | AR10: CHIMAY | AS10: YANANGO | AT10: HUANCHOR | AU10: MARAÑON | AV10: STA TERESA | AW10: FENIX GT11 | AX10: FENIX GT12 | AY10: FENIX TV10 | AZ10: YAUPI | BA10: OROYA | BB10: PACHACHACA | BC10: MALPASO | BD10: CAHUA | BE10: ARCATA | BF10: GALLITO CIEGO | BG10: CHEVES | BH10: HUANZA | BI10: MALACAS2 TG4 | BJ10: MALACAS3 TG 5 | BK10: MALACAS1 TG6 | BL10: RF ILO2 TG1 | BM10: RF ILO2 TG2 | BN10: RF ILO2 TG3 | BO10: YUNCAN | BP10: CHILCA1 TG1 | BQ10: CHILCA1 TG2 | BR10: CHILCA1 TG3 | BS10: CHILCA-TV | BT10: CHILCA2 TG41 | BU10: CHILCA2-TV | BV10: CTNEPI_TG41 | BW10: CTNEPI_TG42 | BX10: CTNEPI_TG43 | BY10: QUITARACSA | BZ10: RF PTO MALDONADO | CA10: RF PUCALLPA | CB10: HUINCO | CC10: MATUCANA | CD10: MOYOPAMPA | CE10: CALLAHUANCA | CF10: HUAMPANI | CG10: STA ROSA WEST TG7 | CH10: UTI_5 | CI10: UTI_6 | CJ10: VENTANILLA 3 | CK10: VENTANILLA 4 | CL10: VENTANILLA TV | CM10: STAROSA TG8 | CN10: PTO_BRVO TG1 | CO10: PTO_BRVO TG2 | CP10: PTO_BRVO TG3 | CQ10: PTO_BRVO TG4 | CR10: OLLEROS TG1 | CS10: OLLEROS TV | CT10: CS YARUCAYA | CU10: SAN JUAN | CV10: MATARANI | CW10: DUNA | CX10: CARHUAQUERO (CS) | CY10: MANTA I | CZ10: CARHUAQUERO4 | DA10: CAÑA BRAVA | DB10: RONCADOR | DC10: CANCHAYLLO | DD10: RENOVANDESH1 | DE10: POTRERO | DF10: PIZARRAS | DG10: NIMPERIAL | DH10: YARUCAYA | DI10: MOQUEGUA-SOLAR | DJ10: PANAMERICANA-SOLAR | DK10: PQE-EOLICO-MARCONA | DL10: PQE-EOLICO-3-HERMANAS | DM10: HUAYCOLORO | DN10: CALLAO | DO10: DONA_CATALINA | DP10: LAGRINGAV | DQ10: TACNA-SOLAR | DR10: YANAPAMPA | DS10: CARHUAC | DT10: HUALLIN | DU10: PURMACANA | DV10: HUASAHUASI | DW10: STACRUZ_1_2 | DX10: RUNATULLO_II | DY10: RUNATULLO_III | DZ10: RUCUY | EA10: PQE-EOLICO-TALARA | EB10: PQE-EOLICO-CUPISNIQUE | EC10: INTIPAMPA | ED10: PUNTA LOMITAS-BL1 | EE10: PUNTA LOMITAS-BL2 | EF10: PUN LOMITAS_EXP-BL1 | EG10: PUN LOMITAS_EXP-BL2 | EH10: 8AGOSTO | EI10: EL CARMEN | EJ10: LA JOYA | EK10: ANGEL_I | EL10: ANGEL_II | EM10: ANGEL_III | EN10: HUAMBOS | EO10: MAJES | EP10: RUBI | EQ10: CH_HER1 | ER10: WAYRA-I | ES10: WAYRA EXTENSION | ET10: CLEMESI | EU10: REPARTICION | EV10: POECHOS2 | EW10: CHANCAY | EX10: CANA BRAVA | EY10: REFINERIA TALARA TV1 | EZ10: REFINERÍA TALARA TV2 | FA10: OQUENDO TG1 | FB10: OQUENDO TV1 | FC10: PARAMONGA | FD10: MAPLE | FE10: SAN_JACINTO | FF10: MVAR | FH10: CARPAPATA | FI10: TUPURI | FJ10: CENTRALES ELOR | FK10: PIAS1 | FL10: ZANA | FM10: TABLAZO | FN10: TALLANCA | FO10: CURUMUY | FP10: POECHOS1 | FQ10: MVAR
A11: 25/01/2025 | B11: 00:30 | C11: 0.2 | D11: 0.1 | E11: 0 | F11: 38.1 | G11: 15.3 | J11: -6.4 | K11: 18.1 | N11: -21 | O11: -32.1 | P11: -11.8 | Q11: 19.8 | R11: -14.4 | S11: -23.1 | T11: 90.4 | U11: 0 | Z11: 14 | AA11: 1.8 | AB11: 0 | AC11: -3.2 | AE11: 8.8 | AF11: 1.8 | AG11: 0 | AJ11: 12.5 | AK11: 18 | AO11: -1.2 | AP11: 50 | AQ11: 9.7 | AR11: 12.1 | AS11: -0.6 | AT11: 0.1 | AU11: 2.7 | AV11: 0.5 | AX11: 0 | AY11: 0 | AZ11: 10.7 | BA11: -1.1 | BB11: 0.2 | BC11: -4.1 | BD11: 2.5 | BE11: 0.9 | BF11: -0.1 | BG11: 15.2 | BH11: 3 | BK11: 1.2 | BO11: 14.8 | BQ11: 0 | BY11: -2.6 | CB11: 40 | CC11: 31.7 | CD11: 9.4 | CE11: 8.2 | CF11: 1.9 | CJ11: 12.1 | CK11: 12.2 | CL11: -21.7 | CR11: -15.6 | CS11: -8.9 | CU11: -5.4 | CV11: 0 | CY11: 1.2 | CZ11: -0.1 | DA11: -0.4 | DB11: 0 | DC11: 0.7 | DD11: 1.8 | DE11: -0.1 | DF11: 2.1 | DG11: 0.6 | DH11: 0 | DI11: 0 | DJ11: 0 | DK11: -2.3 | DL11: -5.8 | DM11: 1.8 | DN11: 0.5 | DO11: 0.6 | DP11: 0.6 | DQ11: 0 | DR11: -0.3 | DS11: 0.6 | DT11: 0.5 | DV11: -4.6 | DW11: 0.7 | DX11: 2.4 | DY11: 2.9 | DZ11: 1.1 | EA11: 0.8 | EB11: 4 | EC11: 0 | ED11: -6.3 | EE11: -7.5 | EF11: 6.4 | EG11: 8.7 | EH11: 2.6 | EI11: -0.1 | EJ11: 1.7 | EK11: 0.2 | EL11: 0.2 | EM11: 0.2 | EO11: 0 | EP11: 0 | EQ11: -0.2 | ER11: -8 | ES11: 3.5 | ET11: 0 | EU11: 0 | EV11: 0.8 | EW11: 1.4 | EX11: 2.7 | EY11: 6.4 | EZ11: 8.7 | FA11: 0.8 | FB11: 1.7 | FC11: 3.1 | FD11: 0.1 | FE11: 3.3 | FF11: 344.4 | FH11: 2.88807 | FJ11: 0 | FK11: 1.508 | FL11: 0.9 | FN11: 1.58882 | FO11: 0 | FP11: 2.9 | FQ11: 9.78489
A12: 25/01/2025 | B12: 01:00 | C12: 0.2 | D12: 0.1 | E12: 0 | F12: 35.3 | G12: 16.1 | J12: -8.1 | K12: 5.2 | N12: -26.7 | O12: -31.2 | P12: -10.4 | Q12: 12.9 | R12: -17.9 | S12: -26.8 | T12: 86.7 | U12: 0.1 | Z12: 15.4 | AA12: 1.8 | AB12: 0 | AC12: -3.2 | AE12: 9.1 | AF12: 2.1 | AG12: 0 | AJ12: 13.9 | AK12: 6.3 | AO12: -1.3 | AP12: 48.2 | AQ12: 9.2 | AR12: 10.3 | AS12: 0.3 | AT12: 0.4 | AU12: 2.7 | AV12: 1.5 | AX12: 0 | AY12: 0 | AZ12: 8.3 | BA12: -1.1 | BB12: 0.2 | BC12: -1.6 | BD12: 3.1 | BE12: 0.9 | BF12: -0.1 | BG12: 20.9 | BH12: 2.1 | BK12: -0.4 | BO12: 12.3 | BQ12: 0 | BY12: 1.9 | CB12: 41.3 | CC12: 24.9 | CD12: -0.4 | CE12: 5.6 | CF12: -2.1 | CJ12: 3.2 | CK12: 3.7 | CL12: -25 | CR12: -15.7 | CS12: -12.6 | CU12: -5.6 | CV12: 0 | CY12: 1.2 | CZ12: -0.1 | DA12: -0.3 | DB12: 0.2 | DC12: 0.7 | DD12: 1.7 | DE12: 0 | DF12: 2.1 | DG12: 0.6 | DH12: 0 | DI12: 0 | DJ12: 0 | DK12: -2.5 | DL12: -6.6 | DM12: 1.8 | DN12: 0.5 | DO12: 0.6 | DP12: 0.6 | DQ12: 0 | DR12: 0 | DS12: 0.6 | DT12: 0.5 | DV12: -4.3 | DW12: 0.6 | DX12: 1.9 | DY12: 2.9 | DZ12: 1 | EA12: 0.8 | EB12: 4 | EC12: 0 | ED12: -7.9 | EE12: -8.9 | EF12: 6.4 | EG12: 8.1 | EH12: 2.6 | EI12: -0.1 | EJ12: 0.3 | EK12: 0.2 | EL12: 0.2 | EM12: 0.2 | EO12: 0 | EP12: 0 | EQ12: -0.2 | ER12: -8.7 | ES12: 3.4 | ET12: 0 | EU12: 0 | EV12: 0.8 | EW12: 1.2 | EX12: 2.5 | EY12: 6.4 | EZ12: 8.1 | FA12: 0.8 | FB12: 1.5 | FC12: 2.6 | FD12: 0 | FE12: 3.2 | FF12: 247.2 | FH12: 2.73792 | FJ12: 0 | FK12: 1.162 | FL12: 0.9 | FN12: 1.59214 | FO12: -0.1 | FP12: 2.9 | FQ12: 9.19206
A13: 25/01/2025 | B13: 01:30 | C13: 0.2 | D13: 0.1 | E13: 0 | F13: 36.3 | G13: 15.5 | J13: -8.6 | K13: 4.5 | N13: -31.6 | O13: -35.3 | P13: -11 | Q13: 8.7 | R13: -21.3 | S13: -28.3 | T13: 82.9 | U13: 0.1 | Z13: 14 | AA13: 2 | AB13: 0 | AC13: -3.2 | AE13: 9.1 | AF13: 1.8 | AG13: 0 | AJ13: 16.5 | AK13: 0.7 | AO13: -1.4 | AP13: 47.1 | AQ13: 9 | AR13: 10.3 | AS13: 0.3 | AT13: 0.6 | AU13: 2.7 | AV13: 2.8 | AX13: 0 | AY13: 0 | AZ13: 4.1 | BA13: -1.2 | BB13: 0.2 | BC13: -0.7 | BD13: 4.9 | BE13: 0.9 | BF13: -0.1 | BG13: 21.9 | BH13: 1.4 | BK13: -1 | BO13: 10.3 | BQ13: 0 | BY13: 0.5 | CB13: 38.6 | CC13: 24 | CD13: -0.6 | CE13: 5.4 | CF13: -2 | CJ13: -2.7 | CK13: -1.8 | CL13: -30 | CR13: -18.9 | CS13: -14.8 | CU13: -5.7 | CV13: 0 | CY13: 1.3 | CZ13: 0 | DA13: -0.3 | DB13: 0.1 | DC13: 0.7 | DD13: 1.7 | DE13: -0.1 | DF13: 2.1 | DG13: 0.6 | DH13: 0 | DI13: 0 | DJ13: 0 | DK13: -2.8 | DL13: -6.9 | DM13: 1.8 | DN13: 0.5 | DO13: 0.6 | DP13: 0.6 | DQ13: 0 | DR13: -0.1 | DS13: 0.6 | DT13: 0.5 | DV13: -4.3 | DW13: 0.8 | DX13: 1.8 | DY13: 3.1 | DZ13: 1.1 | EA13: 0.8 | EB13: 4 | EC13: 0 | ED13: -9.4 | EE13: -9.6 | EF13: 6.3 | EG13: 7 | EH13: 2.6 | EI13: -0.1 | EJ13: 0.3 | EK13: 0.2 | EL13: 0.2 | EM13: 0.2 | EO13: 0 | EP13: 0 | EQ13: -0.2 | ER13: -9.2 | ES13: 3.3 | ET13: 0 | EU13: 0 | EV13: 0.8 | EW13: 1.4 | EX13: 2.5 | EY13: 6.3 | EZ13: 7 | FA13: 0.8 | FB13: 1.3 | FC13: 2 | FD13: 0 | FE13: 3.2 | FF13: 182.3 | FH13: 2.67304 | FJ13: 0 | FK13: 1.238 | FL13: 0.9 | FN13: 1.56936 | FO13: -0.3 | FP13: 2.9 | FQ13: 8.9804
A14: 25/01/2025 | B14: 02:00 | C14: 0.2 | D14: 0.1 | E14: 0 | F14: 37.1 | G14: 15.8 | J14: -7.6 | K14: 19.8 | N14: -25.3 | O14: -32.8 | P14: -11.5 | Q14: 15.4 | R14: -28 | S14: -30.2 | T14: 87.3 | U14: 0.1 | Z14: 18.5 | AA14: 1.7 | AB14: 0 | AC14: -3.2 | AE14: 8.9 | AF14: 1.7 | AG14: 0 | AJ14: 14.4 | AK14: 16.7 | AO14: -1.4 | AP14: 47.5 | AQ14: 9.2 | AR14: 10.8 | AS14: 0.3 | AT14: 0.1 | AU14: 2.7 | AV14: 1.5 | AX14: 0 | AY14: 0 | AZ14: 8.3 | BA14: -1.1 | BB14: 0.2 | BC14: -2.5 | BD14: 2.7 | BE14: 0.9 | BF14: -0.1 | BG14: 18 | BH14: 1.8 | BK14: -1.4 | BO14: 13 | BQ14: 0 | BY14: -0.6 | CB14: 40.1 | CC14: 25.1 | CD14: 0.2 | CE14: 6.9 | CF14: -2.1 | CJ14: -1.5 | CK14: -1.1 | CL14: -28.7 | CR14: -23 | CS14: -14.9 | CU14: -5.7 | CV14: 0 | CY14: 1.3 | CZ14: -0.1 | DA14: -0.3 | DB14: 0.2 | DC14: 0.7 | DD14: 1.8 | DE14: 0.8 | DF14: 2.2 | DG14: 0.6 | DH14: 0 | DI14: 0 | DJ14: 0 | DK14: -2.6 | DL14: -7.4 | DM14: 1.8 | DN14: 0.5 | DO14: 0.6 | DP14: 0.6 | DQ14: 0 | DR14: 0.1 | DS14: 0.6 | DT14: 0.5 | DV14: -4.3 | DW14: 0.6 | DX14: 1.9 | DY14: 3.1 | DZ14: 1.1 | EA14: 0.8 | EB14: 4 | EC14: 0 | ED14: -8.4 | EE14: -8.9 | EF14: 6.3 | EG14: 6.5 | EH14: 2.6 | EI14: -0.1 | EJ14: 0 | EK14: 0.2 | EL14: 0.2 | EM14: 0.2 | EO14: 0 | EP14: 0 | EQ14: -0.2 | ER14: -9.2 | ES14: 3.3 | ET14: 0 | EU14: 0 | EV14: 0.8 | EW14: 1.4 | EX14: 2.8 | EY14: 6.3 | EZ14: 6.5 | FA14: 0.8 | FB14: 1.3 | FC14: 3.6 | FD14: 0 | FE14: 3.1 | FF14: 232.5 | FH14: 2.71653 | FJ14: 0 | FK14: 1.334 | FL14: 0.9 | FN14: 1.57328 | FO14: -0.3 | FP14: 3 | FQ14: 9.22381
A15: 25/01/2025 | B15: 02:30 | C15: 0.2 | D15: 0.1 | E15: -0.2 | F15: 18.9 | G15: 11.2 | J15: -7.7 | K15: 5.7 | N15: -21.7 | O15: -35.4 | P15: -15.8 | Q15: 21 | R15: -29.7 | S15: -30.3 | T15: 76.9 | U15: 0 | Z15: 14.4 | AA15: 2.3 | AB15: 0 | AC15: -3.2 | AE15: 8.5 | AF15: 1.7 | AG15: 0 | AJ15: 11.4 | AK15: 17.5 | AO15: -1.5 | AP15: 48.6 | AQ15: 9.5 | AR15: 12.9 | AS15: -0.3 | AT15: 0.3 | AU15: 2.7 | AV15: 0.9 | AX15: 0 | AY15: 0 | AZ15: 6.4 | BA15: -1 | BB15: 0.2 | BC15: -6.8 | BD15: 0.8 | BE15: 0.9 | BF15: -0.1 | BG15: 12.4 | BH15: 0 | BK15: -2.4 | BO15: 11.7 | BQ15: 0 | BY15: -6.8 | CB15: 41 | CC15: 24.2 | CD15: 2 | CE15: 3.4 | CF15: -0.1 | CJ15: -3.9 | CK15: -3.8 | CL15: -32.7 | CR15: -28.8 | CS15: -15.4 | CU15: -5.7 | CV15: 0 | CY15: 1.2 | CZ15: -0.1 | DA15: -0.2 | DB15: 0.2 | DC15: 0.7 | DD15: 1.7 | DE15: -0.2 | DF15: 2 | DG15: 0.5 | DH15: 0 | DI15: 0 | DJ15: 0 | DK15: -2.6 | DL15: -7.2 | DM15: 1.8 | DN15: 0.5 | DO15: 0.6 | DP15: 0.6 | DQ15: 0 | DR15: 0 | DS15: 0.6 | DT15: 0.5 | DV15: -4.3 | DW15: 0.8 | DX15: 1.7 | DY15: 2.9 | DZ15: 1.1 | EA15: 0.8 | EB15: 4 | EC15: 0 | ED15: -9.4 | EE15: -10.3 | EF15: 6.4 | EG15: 6.4 | EH15: 2.6 | EI15: 0 | EJ15: 0 | EK15: 0.2 | EL15: 0.2 | EM15: 0.2 | EO15: 0 | EP15: 0 | EQ15: -0.2 | ER15: -9.6 | ES15: 3.5 | ET15: 0 | EU15: 0 | EV15: 0.8 | EW15: 1.4 | EX15: 2.6 | EY15: 6.4 | EZ15: 6.4 | FA15: 0.8 | FB15: 1.9 | FC15: 1.1 | FD15: 0 | FE15: 3.4 | FF15: 136.8 | FH15: 2.78294 | FJ15: 0 | FK15: 1.152 | FL15: 0.9 | FN15: 0.81016 | FO15: -0.4 | FP15: 2.9 | FQ15: 8.1451
A16: 25/01/2025 | B16: 03:00 | C16: 0.2 | D16: 0.1 | E16: -0.1 | F16: 30.7 | G16: 14.7 | J16: -8.2 | K16: 19.8 | N16: -25.7 | O16: -37.1 | P16: -14.9 | Q16: 19.4 | R16: -29 | S16: -31.7 | T16: 90.8 | U16: 0 | Z16: 17.3 | AA16: 2.5 | AB16: 0 | AC16: -3.2 | AE16: 8.9 | AF16: 1.7 | AG16: 0 | AJ16: 13.5 | AK16: 16 | AO16: -1.5 | AP16: 46.6 | AQ16: 9.2 | AR16: 10.7 | AS16: -0.1 | AT16: 0.3 | AU16: 2.7 | AV16: 1.1 | AX16: 0 | AY16: 0 | AZ16: 9.2 | BA16: -1.1 | BB16: 0.2 | BC16: -4.1 | BD16: 1 | BE16: 0.9 | BF16: -0.1 | BG16: 14.3 | BH16: 0 | BK16: -3 | BO16: 16.2 | BQ16: 0 | BY16: -5.9 | CB16: 41.6 | CC16: 23.5 | CD16: 0.6 | CE16: 3.6 | CF16: 0.1 | CJ16: -2.6 | CK16: -1.7 | CL16: -29.4 | CR16: -24.7 | CS16: -14.7 | CU16: -5.6 | CV16: 0 | CY16: 1.3 | CZ16: -0.1 | DA16: -0.3 | DB16: 0.2 | DC16: 0.7 | DD16: 1.9 | DE16: -1.2 | DF16: 2.2 | DG16: 0.6 | DH16: 0 | DI16: 0 | DJ16: 0 | DK16: -2.4 | DL16: -6.3 | DM16: 1.8 | DN16: 0.5 | DO16: 0.6 | DP16: 0.6 | DQ16: 0 | DR16: -0.1 | DS16: 0.3 | DT16: 0.5 | DV16: -4.1 | DW16: 0.6 | DX16: 1.8 | DY16: 3 | DZ16: 1 | EA16: 0.8 | EB16: 4 | EC16: 0 | ED16: -9.4 | EE16: -9.9 | EF16: 6.3 | EG16: 6.5 | EH16: 2.6 | EI16: 0 | EJ16: 0 | EK16: 0.2 | EL16: 0.2 | EM16: 0.2 | EO16: 0 | EP16: 0 | EQ16: -0.2 | ER16: -8.4 | ES16: 3.4 | ET16: 0 | EU16: 0 | EV16: 0.8 | EW16: 1.2 | EX16: 2.5 | EY16: 6.3 | EZ16: 6.5 | FA16: 0.8 | FB16: 1.8 | FC16: 2.1 | FD16: 0 | FE16: 2.9 | FF16: 197.3 | FH16: 2.64738 | FJ16: 0 | FK16: 1.204 | FL16: 0.9 | FN16: 0.23418 | FO16: -0.3 | FP16: 3.2 | FQ16: 7.88556
A17: 25/01/2025 | B17: 03:30 | C17: 0.2 | D17: 0.1 | E17: 0 | F17: 36.3 | G17: 14.3 | J17: -7.9 | K17: 7.6 | N17: -26 | O17: -34.5 | P17: -14.5 | Q17: 13.9 | R17: -29.8 | S17: -31.4 | T17: 83.9 | U17: 0.1 | Z17: 16 | AA17: 2.5 | AB17: 0 | AC17: -3.2 | AE17: 8.7 | AF17: 1.6 | AG17: 0 | AJ17: 13.6 | AK17: 15.5 | AO17: -1.5 | AP17: 48.7 | AQ17: 8.9 | AR17: 11.9 | AS17: -0.1 | AT17: 0.2 | AU17: 2.7 | AV17: 1.4 | AX17: 0 | AY17: 0 | AZ17: 8.4 | BA17: -1.1 | BB17: 0.2 | BC17: -4 | BD17: 2 | BE17: 0.9 | BF17: -0.1 | BG17: 15.7 | BH17: 0 | BK17: -3.4 | BO17: 13.4 | BQ17: 0 | BY17: -4.2 | CB17: 40.5 | CC17: 25.5 | CD17: 1.5 | CE17: 3.6 | CF17: 0 | CJ17: -4.8 | CK17: -4.3 | CL17: -33.1 | CR17: -27.1 | CS17: -15.5 | CU17: -5.5 | CV17: 0 | CY17: 1.3 | CZ17: -0.1 | DA17: -0.3 | DB17: 0.2 | DC17: 0.7 | DD17: 1.8 | DE17: -1.1 | DF17: 2.2 | DG17: 0.5 | DH17: 0 | DI17: 0 | DJ17: 0 | DK17: -2.8 | DL17: -7.4 | DM17: 1.8 | DN17: 0.5 | DO17: 0.6 | DP17: 0.6 | DQ17: 0 | DR17: -0.1 | DS17: 0.3 | DT17: 0.5 | DV17: -4.1 | DW17: 0.6 | DX17: 1.7 | DY17: 2.9 | DZ17: 1.1 | EA17: 0.8 | EB17: 4 | EC17: 0 | ED17: -8.5 | EE17: -9.7 | EF17: 6.3 | EG17: 6 | EH17: 2.6 | EI17: 0 | EJ17: 0 | EK17: 0.2 | EL17: 0.2 | EM17: 0.2 | EO17: 0 | EP17: 0 | EQ17: -0.2 | ER17: -9 | ES17: 3.4 | ET17: 0 | EU17: 0 | EV17: 0.4 | EW17: 1.4 | EX17: 2.5 | EY17: 6.3 | EZ17: 6 | FA17: 0.8 | FB17: 1.8 | FC17: 3 | FD17: 0 | FE17: 2.8 | FF17: 170.5 | FH17: 2.65999 | FJ17: 0 | FK17: 1.266 | FL17: 0.9 | FN17: 0.15073 | FO17: -0.7 | FP17: 2.9 | FQ17: 7.17672
A18: 25/01/2025 | B18: 04:00 | C18: 0.2 | D18: 0.1 | E18: 0 | F18: 15 | G18: 10.8 | J18: -7.8 | K18: 12.3 | N18: -31.6 | O18: -42.2 | P18: -22.3 | Q18: 7.5 | R18: -24.9 | S18: -31.4 | T18: 73.7 | U18: 0 | Z18: 15.9 | AA18: 2.3 | AB18: 0 | AC18: -3.2 | AE18: 8.5 | AF18: 1.6 | AG18: 0 | AJ18: 13.2 | AK18: 15.1 | AO18: -1.6 | AP18: 25 | AQ18: 8 | AR18: 12.7 | AS18: 0 | AT18: 0 | AU18: 2.7 | AV18: 1.5 | AX18: 0 | AY18: 0 | AZ18: 7.9 | BA18: -1.3 | BB18: 0.1 | BC18: -6.6 | BD18: 1.7 | BE18: 0.9 | BF18: -0.1 | BG18: 13 | BH18: 0 | BK18: -3.5 | BO18: 0.8 | BQ18: 0 | BY18: -5 | CB18: 39.2 | CC18: 24.8 | CD18: 1.5 | CE18: 3.7 | CF18: 0 | CJ18: -8.6 | CK18: -8.4 | CL18: -39.4 | CR18: -30.5 | CS18: -17.9 | CU18: -5.3 | CV18: 0 | CY18: 1.3 | CZ18: 0 | DA18: -0.3 | DB18: 0 | DC18: 0.7 | DD18: 1.8 | DE18: -1.2 | DF18: 2.2 | DG18: 0.5 | DH18: 0 | DI18: 0 | DJ18: 0 | DK18: -2.9 | DL18: -8 | DM18: 1.8 | DN18: 0.5 | DO18: 0.6 | DP18: 0.6 | DQ18: 0 | DR18: 0.3 | DS18: 0.3 | DT18: 0.5 | DV18: -4.1 | DW18: 0.6 | DX18: 1.7 | DY18: 2.9 | DZ18: 1 | EA18: 0.8 | EB18: 4 | EC18: 0 | ED18: -9.9 | EE18: -11.3 | EF18: 6.4 | EG18: 5.5 | EH18: 2.6 | EI18: 0 | EJ18: 0 | EK18: 0.2 | EL18: 0.2 | EM18: 0.2 | EO18: 0 | EP18: 0 | EQ18: -0.2 | ER18: -9.1 | ES18: 3.2 | ET18: 0 | EU18: 0 | EV18: 0.4 | EW18: 1.2 | EX18: 2.3 | EY18: 6.4 | EZ18: 5.5 | FA18: 0.8 | FB18: 1.6 | FC18: 0.8 | FD18: 0 | FE18: 3.3 | FF18: 43.8 | FH18: 2.31418 | FJ18: 0 | FK18: 1.39 | FL18: 0.9 | FN18: 0.16821 | FO18: -0.7 | FP18: 3 | FQ18: 7.07239
A19: 25/01/2025 | B19: 04:30 | C19: 0.2 | D19: 0.1 | E19: -0.2 | F19: 36.2 | G19: 15.7 | J19: -7.8 | K19: 18 | N19: -27.4 | O19: -37.1 | P19: -14.6 | Q19: 17.7 | R19: -18.7 | S19: -27.7 | T19: 93.1 | U19: 0.1 | Z19: 17.9 | AA19: 2.3 | AB19: 0 | AC19: -3.2 | AE19: 9.1 | AF19: 1.8 | AG19: 0 | AJ19: 13.5 | AK19: 15.2 | AO19: -1.5 | AP19: 38.3 | AQ19: 8.3 | AR19: 10.4 | AS19: 0.1 | AT19: 0 | AU19: 2.7 | AV19: 0.8 | AX19: 0 | AY19: 0 | AZ19: 9.9 | BA19: -1 | BB19: 0.2 | BC19: -4.7 | BD19: 0.9 | BE19: 0.9 | BF19: -0.1 | BG19: 14.5 | BH19: 0 | BK19: 1.5 | BO19: 16.7 | BQ19: 0 | BY19: -6.3 | CB19: 29.7 | CC19: 22.3 | CD19: 0.6 | CE19: 3.8 | CF19: 0 | CJ19: -2.3 | CK19: -1.8 | CL19: -28.7 | CR19: -23 | CS19: -13.7 | CU19: -5.1 | CV19: 0 | CY19: 1.3 | CZ19: -0.1 | DA19: -0.2 | DB19: 0.2 | DC19: 0.6 | DD19: 1.9 | DE19: -1.4 | DF19: 2.2 | DG19: 0.6 | DH19: 0 | DI19: 0 | DJ19: 0 | DK19: -2.7 | DL19: -6.8 | DM19: 1.8 | DN19: 0.5 | DO19: 0.6 | DP19: 0.6 | DQ19: 0 | DR19: 0.3 | DS19: 0.3 | DT19: 0.5 | DV19: -4.2 | DW19: 0.4 | DX19: 1.8 | DY19: 3 | DZ19: 0.9 | EA19: 0.8 | EB19: 4 | EC19: 0 | ED19: -5.7 | EE19: -6.6 | EF19: 6.4 | EG19: 9.7 | EH19: 2.6 | EI19: 0 | EJ19: 0 | EK19: 0.2 | EL19: 0.2 | EM19: 0.2 | EO19: 0 | EP19: 0 | EQ19: -0.2 | ER19: -7.7 | ES19: 3.2 | ET19: 0 | EU19: 0 | EV19: 0.4 | EW19: 1.2 | EX19: 2.6 | EY19: 6.4 | EZ19: 9.7 | FA19: 0.8 | FB19: 1.6 | FC19: 2.8 | FD19: 0 | FE19: 2.9 | FF19: 215.2 | FH19: 2.52036 | FJ19: 0 | FK19: 1.568 | FL19: 0.9 | FN19: 0.18943 | FO19: -0.1 | FP19: 3 | FQ19: 8.07779
A20: 25/01/2025 | B20: 05:00 | C20: 0.2 | D20: 0.1 | E20: -0.2 | F20: 24 | G20: 12.9 | J20: -8.2 | K20: 3.7 | N20: -29.6 | O20: -37.9 | P20: -16.7 | Q20: 12.3 | R20: -21.2 | S20: -28.7 | T20: 81.1 | U20: 0.1 | Z20: 15.1 | AA20: 2.4 | AB20: 0 | AC20: -3.2 | AE20: 8.9 | AF20: 1.7 | AG20: 0 | AJ20: 12.2 | AK20: 16.4 | AO20: -1.4 | AP20: 50.2 | AQ20: 8.9 | AR20: 10.9 | AS20: -0.2 | AT20: -0.2 | AU20: 2.7 | AV20: 0.7 | AX20: 0 | AY20: 0 | AZ20: 11.1 | BA20: -1.1 | BB20: 0.2 | BC20: -3.7 | BD20: 1.8 | BE20: 0.9 | BF20: -0.1 | BG20: 16 | BH20: 0 | BK20: 1.6 | BO20: 12.8 | BQ20: 0 | BY20: -2.8 | CB20: 16.8 | CC20: 23.2 | CD20: 0.7 | CE20: 3.7 | CF20: 0.1 | CJ20: -4.5 | CK20: -3.9 | CL20: -32.4 | CR20: -25.5 | CS20: -16.4 | CU20: -5 | CV20: 0 | CY20: 1.3 | CZ20: -0.1 | DA20: -0.2 | DB20: 0.2 | DC20: 0.6 | DD20: 1.8 | DE20: -1.2 | DF20: 2.2 | DG20: 0.6 | DH20: 0 | DI20: 0 | DJ20: 0 | DK20: -3.5 | DL20: -8.8 | DM20: 1.9 | DN20: 0.5 | DO20: 0.6 | DP20: 0.5 | DQ20: 0.3 | DR20: 0.2 | DS20: 0.3 | DT20: 0.5 | DV20: -4.2 | DW20: 0.7 | DX20: 1.8 | DY20: 2.9 | DZ20: 1.1 | EA20: 0.8 | EB20: 4 | EC20: 0.4 | ED20: -10.6 | EE20: -11.6 | EF20: 6.3 | EG20: 10.1 | EH20: 2.6 | EI20: 0 | EJ20: 0 | EK20: 0.2 | EL20: 0.2 | EM20: 0.2 | EO20: 0 | EP20: 0 | EQ20: -0.2 | ER20: -9.1 | ES20: 3.4 | ET20: 0 | EU20: 0 | EV20: 0.4 | EW20: 1.4 | EX20: 2.4 | EY20: 6.3 | EZ20: 10.1 | FA20: 0.8 | FB20: 1.8 | FC20: 2.6 | FD20: 0 | FE20: 2.8 | FF20: 135.8 | FH20: 2.67577 | FJ20: 0 | FK20: 1.334 | FL20: 0.9 | FN20: 0.20591 | FO20: -0.3 | FP20: 3 | FQ20: 7.81568
A21: 25/01/2025 | B21: 05:30 | C21: 0.2 | D21: 0.1 | E21: -0.3 | F21: 31.1 | G21: 14.6 | J21: -7.5 | K21: 2.2 | N21: -20.1 | O21: -30.7 | P21: -10.3 | Q21: 23.2 | R21: -16.8 | S21: -24.7 | T21: 87.6 | U21: 0 | Z21: 16.1 | AA21: 2.4 | AB21: 0 | AC21: -3.2 | AE21: 8.6 | AF21: 1.8 | AG21: 0 | AJ21: 12.9 | AK21: 17.8 | AO21: -1.4 | AP21: 50.7 | AQ21: 8.9 | AR21: 11.3 | AS21: -0.4 | AT21: -0.3 | AU21: 2.7 | AV21: 0.9 | AX21: 0 | AY21: 0 | AZ21: 10.6 | BA21: -1.1 | BB21: 0.1 | BC21: -5 | BD21: 1 | BE21: 0.9 | BF21: -0.1 | BG21: 13.5 | BH21: 0 | BK21: 2.3 | BO21: 14.2 | BQ21: 0 | BY21: -5.3 | CB21: 17.2 | CC21: 24.4 | CD21: 1.2 | CE21: 3.7 | CF21: -0.1 | CJ21: -1 | CK21: -0.9 | CL21: -27.8 | CR21: -23 | CS21: -14.1 | CU21: -5 | CV21: 0 | CY21: 1.3 | CZ21: -0.1 | DA21: -0.2 | DB21: 0.2 | DC21: 0.6 | DD21: 1.8 | DE21: -1.1 | DF21: 2.2 | DG21: 0.5 | DH21: 0 | DI21: 0 | DJ21: 0 | DK21: -3.4 | DL21: -7.6 | DM21: 1.4 | DN21: 0.5 | DO21: 0.6 | DP21: 1.1 | DQ21: 0.3 | DR21: 0.1 | DS21: 0.3 | DT21: 0.5 | DV21: -4.1 | DW21: 0.6 | DX21: 1.9 | DY21: 3 | DZ21: 1.2 | EA21: 0.8 | EB21: 4 | EC21: 0.3 | ED21: -6.1 | EE21: -7.2 | EF21: 6.3 | EG21: 10.4 | EH21: 2.6 | EI21: 0 | EJ21: 0 | EK21: 0.2 | EL21: 0.2 | EM21: 0.2 | EO21: 0 | EP21: 2.2 | EQ21: -0.2 | ER21: -9.5 | ES21: 3.4 | ET21: 1.2 | EU21: 0 | EV21: 0.4 | EW21: 1.4 | EX21: 2.5 | EY21: 6.3 | EZ21: 10.4 | FA21: 0.8 | FB21: 1.9 | FC21: 1 | FD21: 0.1 | FE21: 3.1 | FF21: 221.4 | FH21: 2.67856 | FJ21: 0 | FK21: 1.152 | FL21: 0.9 | FN21: 0.22884 | FO21: -0.1 | FP21: 2.8 | FQ21: 7.6594
A22: 25/01/2025 | B22: 06:00 | C22: 0.2 | D22: 0.1 | E22: -0.3 | F22: 31.1 | G22: 14.5 | J22: -8.5 | K22: -2.6 | N22: -24.8 | O22: -30.9 | P22: -10.7 | Q22: 17.6 | R22: -12.4 | S22: -28.3 | T22: 79.5 | U22: 0.1 | Z22: 12.1 | AA22: 2.4 | AB22: 0 | AC22: -3.3 | AE22: 6.9 | AF22: 1.7 | AG22: 0 | AJ22: 12.4 | AK22: 17.2 | AO22: -1.5 | AP22: 48.9 | AQ22: 8 | AR22: 10.1 | AS22: 0.1 | AT22: -0.4 | AU22: 2.7 | AV22: 1.5 | AX22: 0 | AY22: 0 | AZ22: 9.7 | BA22: -1.1 | BB22: 0.2 | BC22: -3 | BD22: 2.6 | BE22: 0.9 | BF22: -0.1 | BG22: 18.6 | BH22: 0 | BK22: 2 | BO22: 10.3 | BQ22: 0 | BY22: -1 | CB22: 15.5 | CC22: 21.9 | CD22: -0.5 | CE22: 5.2 | CF22: -0.2 | CJ22: -4.9 | CK22: -4.7 | CL22: -33.7 | CR22: -23 | CS22: -16.5 | CU22: -5.4 | CV22: 0.1 | CY22: 1.2 | CZ22: 0 | DA22: -0.2 | DB22: 0.2 | DC22: 0.5 | DD22: 1.7 | DE22: -1.3 | DF22: 2.2 | DG22: 0.6 | DH22: 0 | DI22: 0 | DJ22: 0 | DK22: -3.1 | DL22: -7.7 | DM22: 1.4 | DN22: 0.5 | DO22: 0.6 | DP22: 1.1 | DQ22: 0.2 | DR22: 0.1 | DS22: 0.3 | DT22: 0.5 | DV22: -4.1 | DW22: 0.7 | DX22: 1.9 | DY22: 2.9 | DZ22: 1.1 | EA22: 0.8 | EB22: 4 | EC22: -0.3 | ED22: -2.5 | EE22: -3 | EF22: 6.3 | EG22: 9 | EH22: 2.6 | EI22: 0 | EJ22: 0 | EK22: 0.2 | EL22: 0.2 | EM22: 0.2 | EO22: 0 | EP22: 0.2 | EQ22: -0.2 | ER22: -11.9 | ES22: 3.5 | ET22: 1.2 | EU22: 0 | EV22: 0.4 | EW22: 1.4 | EX22: 2.6 | EY22: 6.3 | EZ22: 9 | FA22: 0.9 | FB22: 1.8 | FC22: 2 | FD22: 0 | FE22: 3.2 | FF22: 175.5 | FH22: 2.57551 | FJ22: 0 | FK22: 1.116 | FL22: 0.9 | FN22: 0.22492 | FO22: -0.2 | FP22: 2.8 | FQ22: 7.41643
... A58: 26/01/2025 | B58: 00:00 | C58: 0.2 | D58: 0.1 | E58: 0 | F58: 21.9 | G58: 30.1 | J58: -11.9 | K58: 16.5 | N58: 7.4 | O58: 10.8 | P58: 9.2 | Q58: 12.2 | R58: -23.1 | S58: -44.9 | T58: 91.7 | U58: 0.2 | Z58: 8 | AA58: 0 | AB58: 0 | AC58: -3.2 | AE58: 5.9 | AF58: 1.9 | AG58: 0 | AJ58: 15.5 | AK58: 3.6 | AO58: -1.7 | AP58: 46.6 | AQ58: 4.9 | AR58: 12.1 | AS58: 2.9 | AT58: -0.1 | AU58: 2.7 | AV58: 2.4 | AX58: 0 | AY58: 0 | AZ58: 9.3 | BA58: -1.5 | BB58: 0.1 | BC58: 0.4 | BD58: 11.3 | BE58: 1 | BF58: -0.1 | BG58: 10.2 | BH58: 5 | BK58: 1.4 | BO58: 9.6 | BQ58: 0 | BY58: -0.3 | CB58: 11.3 | CC58: 20 | CD58: -2.6 | CE58: 1.1 | CF58: 0.1 | CJ58: 17.3 | CK58: 18.6 | CL58: -21.3 | CR58: -13.9 | CS58: -13.8 | CU58: -5.8 | CV58: 0 | CY58: 1.3 | CZ58: -0.1 | DA58: -0.8 | DB58: 0 | DC58: 0.7 | DD58: 1.8 | DE58: 0 | DF58: 2.1 | DG58: 0.6 | DH58: 0 | DI58: 0 | DJ58: 0 | DK58: -3 | DL58: -2.4 | DM58: 1.8 | DN58: 0.5 | DO58: 0.6 | DP58: 1.3 | DQ58: 0 | DR58: 0 | DS58: -0.5 | DT58: 0.2 | DV58: -3.8 | DW58: 0.1 | DX58: 2.7 | DY58: 2.7 | DZ58: 1.3 | EA58: 0.8 | EB58: 4 | EC58: 0 | ED58: -5.5 | EE58: -8.5 | EF58: 6.3 | EG58: 7.5 | EH58: 2.6 | EI58: -0.1 | EJ58: 1.4 | EK58: 0.2 | EL58: 0.2 | EM58: 0.2 | EO58: 0 | EP58: 0 | EQ58: -0.2 | ER58: -7.3 | ES58: 3.5 | ET58: 0 | EU58: 0 | EV58: 0.2 | EW58: 1.6 | EX58: 2.6 | EY58: 6.3 | EZ58: 7.5 | FA58: 0.8 | FB58: 1.6 | FC58: 4.1 | FD58: 0.7 | FE58: 2.9 | FF58: 319.8 | FH58: 2.43647 | FJ58: 0.128 | FK58: 1.64 | FL58: 1.7 | FN58: 0.19154 | FO58: 0 | FP58: 3.8 | FQ58: 9.89601
A59: EJEC | C59: 4.8 | D59: 1.3 | E59: 0.15 | F59: 1451.45 | G59: 604.7 | H59: 0 | I59: 0 | J59: -141.05 | K59: 301.5 | L59: 0 | M59: 0 | N59: 44.85 | O59: -106.5 | P59: 53.05 | Q59: 520.25 | R59: -376.75 | S59: -753.45 | T59: 1727.9 | U59: 1 | V59: 0 | W59: 0 | X59: 0 | Y59: 0 | Z59: 249.9 | AA59: 29.45 | AB59: 12.15 | AC59: -75.75 | AD59: 0 | AE59: 242.05 | AF59: 52.55 | AG59: 3.4 | AH59: 0 | AI59: 0 | AJ59: 384.3 | AK59: 249.25 | AL59: 0 | AM59: 0 | AN59: 0 | AO59: -33.1 | AP59: 1088.65 | AQ59: 163.1 | AR59: 301.65 | AS59: 28.65 | AT59: 0.3 | AU59: 64.55 | AV59: 28.95 | AW59: 0 | AX59: 417.95 | AY59: -593.95 | AZ59: 237.25 | BA59: -30.15 | BB59: 3.8 | BC59: -79.4 | BD59: 101.05 | BE59: 21.95 | BF59: -1 | BG59: 263.8 | BH59: 50.45 | BI59: 0 | BJ59: 0 | BK59: 22.6 | BL59: 0 | BM59: 0 | BN59: 0 | BO59: 241.55 | BP59: 0 | BQ59: -22.75 | BR59: 0 | BS59: 0 | BT59: 0 | BU59: 0 | BV59: 0 | BW59: 0 | BX59: 0 | BY59: -99 | BZ59: 0 | CA59: 0 | CB59: 983.2 | CC59: 831.45 | CD59: 151.5 | CE59: 233.15 | CF59: 4.45 | CG59: 0 | CH59: 0 | CI59: 0 | CJ59: 745 | CK59: 764.15 | CL59: -510.3 | CM59: 0 | CN59: 0 | CO59: 0 | CP59: 0 | CQ59: 0 | CR59: -144.05 | CS59: -117.5 | CT59: 0 | CU59: -124.15 | CV59: 58.9 | CW59: 0 | CX59: 0 | CY59: 29.85 | CZ59: -1.55 | DA59: -14.25 | DB59: -1.4 | DC59: 15.6 | DD59: 42.8 | DE59: -6.95 | DF59: 45.95 | DG59: 13.45 | DH59: 0.05 | DI59: -5.9 | DJ59: -15.3 | DK59: -85.4 | DL59: -133.3 | DM59: 37.8 | DN59: 12 | DO59: 13.95 | DP59: 23.9 | DQ59: -27.15 | DR59: 0.1 | DS59: 5.35 | DT59: 11.85 | DU59: 0 | DV59: -90.7 | DW59: 14.05 | DX59: 57.25 | DY59: 71.75 | DZ59: 31.85 | EA59: 19.2 | EB59: 95.6 | EC59: 21.5 | ED59: -220.75 | EE59: -238.8 | EF59: 152.6 | EG59: 183.95 | EH59: 62.3 | EI59: -1.05 | EJ59: 23.45 | EK59: 4.8 | EL59: 4.8 | EM59: 4.8 | EN59: 0 | EO59: 14.75 | EP59: 117.15 | EQ59: -4.8 | ER59: -107.2 | ES59: 64.1 | ET59: -40.55 | EU59: 13.65 | EV59: 10.3 | EW59: 39.4 | EX59: 54.35 | EY59: 152.6 | EZ59: 183.95 | FA59: 20.25 | FB59: 40.1 | FC59: 65.7 | FD59: 21.1 | FE59: 77.2 | FF59: 10413.3 | FH59: 58.014995 | FI59: 0 | FJ59: -2.73 | FK59: 32.491 | FL59: 25.1 | FM59: 0 | FN59: 41.418335 | FO59: 3.7 | FP59: 89.15 | FQ59: 247.14433

Sheet DEMANDA_AREAS
B3: sábado, 25 de Enero del 2025
B5: REPORTE DE LA DEMANDA POR ÁREAS Y SUBAREAS OPERATIVAS (MW)
B6: FECHA HORA | C6: DEMANDA | E6: AREA | H6: SUBAREAS
C7: INTERCAMBIOS INTERNACIONALES | D7: SEIN | E7: NORTE | F7: CENTRO | G7: SUR | H7: ELECTROANDES
B8: 00:30 | C8: 0 | D8: 6825.392 | E8: 1040.636 | F8: 4068.854 | G8: 1715.902 | H8: 217.798
B9: 01:00 | C9: 0 | D9: 6691.695 | E9: 972.715 | F9: 3979.735 | G9: 1739.245 | H9: 213.431
B10: 01:30 | C10: 0 | D10: 6558.28 | E10: 956.354 | F10: 3869.856 | G10: 1732.07 | H10: 218.593
B11: 02:00 | C11: 0 | D11: 6542.031 | E11: 989.413 | F11: 3822.017 | G11: 1730.601 | H11: 212.524
B12: 02:30 | C12: 0 | D12: 6397.601 | E12: 942.962 | F12: 3721.288 | G12: 1733.351 | H12: 215.917
B13: 03:00 | C13: 0 | D13: 6434.777 | E13: 965.704 | F13: 3730.826 | G13: 1738.247 | H13: 210.33
B14: 03:30 | C14: 0 | D14: 6417.142 | E14: 915.962 | F14: 3763.478 | G14: 1737.702 | H14: 217.471
B15: 04:00 | C15: 0 | D15: 6325.285 | E15: 963.54 | F15: 3626.43 | G15: 1735.315 | H15: 219.53
B16: 04:30 | C16: 0 | D16: 6457.764 | E16: 959.453 | F16: 3746.877 | G16: 1751.434 | H16: 208.958
B17: 05:00 | C17: 0 | D17: 6334.575 | E17: 925.943 | F17: 3668.357 | G17: 1740.275 | H17: 211.955
B18: 05:30 | C18: 0 | D18: 6471.172 | E18: 930.966 | F18: 3794.764 | G18: 1745.442 | H18: 205.189
B19: 06:00 | C19: 0 | D19: 6403.224 | E19: 940.964 | F19: 3749.806 | G19: 1712.454 | H19: 195.669
... B59: ENERGÍA | C59: 0 | D59: 168479.15 | E59: 25960.68 | F59: 98036.845 | G59: 44481.624 | H59: 4892.1005
B61: LEYENDA:
D63: Potencia recibida del Ecuador
D64: Potencia entregada al Ecuador

Sheet DEMANDA_UL
B3: sábado, 25 de Enero del 2025
B5: POTENCIA DE LOS GRANDES USUARIOS LIBRES (MW)
B6: FECHA HORA | C6: GRANDES USUARIOS LIBRES DEL ÁREA NORTE | X6: GRANDES USUARIOS LIBRES DEL ÁREA CENTRO | BP6: GRANDES USUARIOS LIBRES DEL ÁREA SUR
C7: ARCA CONTINENTAL LINDLEY S.A. | D7: AUSTRAL GROUP S.A.A | E7: CEMENTOS PACASMAYO | F7: CORPORACIÓN PESQUERA INCA S.A.C. | G7: CREDITEX: CIA IND.TEXTIL CREDISA | H7: HIPERMERCADOS TOTTUS S.A | I7: INDUSTRIA TEXTIL PIURA | J7: MINERA BOROO MISQUICHILCA S.A. | K7: MINERA GOLD FIELDS | L7: MINERA HORIZONTE | M7: MINERA MARSA | N7: MINERA MISKY MAYO | O7: MINERA YANACOCHA | P7: OPEN PLAZA | Q7: PESQUERA DIAMANTE | R7: PETROPERU | S7: REAL PLAZA S.R.L. | T7: SIDER PERU | U7: SUPERMERCADOS PERUANOS S.A. | V7: TRUPAL S.A. | W7: UNIÓN DE CERVECERÍAS PERUANAS BACKUS Y JOHNSTON S. | X7: ACEROS AREQUIPA | Y7: ADMINISTRADORA JOCKEY PLAZA SHOPPING CENTER S.A. | Z7: ALICORP | AA7: ARCA CONTINENTAL LINDLEY S.A. | AB7: AUSTRAL GROUP S.A.A | AC7: COMPAÑIA MINERA CONDESTABLE | AD7: CORPORACIÓN PESQUERA INCA S.A.C. | AE7: CREDITEX: CIA IND.TEXTIL CREDISA | AF7: FUNDICION CHILCA S.A. | AG7: HIPERMERCADOS TOTTUS S.A | AH7: INMOBILIARIA KANPU S.A. | AI7: INMUEBLES PANAMERICANA S.A. | AJ7: KIMBERLY-CLARK PERU | AK7: LECHE GLORIA S.A. | AL7: MALL AVENTURA S.A. | AM7: MARCOBRE S.A.C. | AN7: MINERA ANTAMINA | AO7: MINERA ARES | AP7: MINERA BUENAVENTURA | AQ7: MINERA CHINALCO PERÚ S.A. | AR7: MINERA SHOUXIN PERU S.A. | AS7: MINERA VOLCAN | AT7: MINSUR | AU7: MOLYCOP-ADESUR | AV7: NEXA RESOURCES CAJAMARQUILLA S.A. | AW7: NEXA RESOURCES PERÚ S.A.A. | AX7: OPEN PLAZA | AY7: OPP FILM | AZ7: OWENS-ILLINOIS PERÚ S.A. | BA7: PAPELERA NACIONAL S.A. | BB7: PESQUERA DIAMANTE | BC7: QUIMPAC S.A. | BD7: REAL PLAZA S.R.L. | BE7: REFINERIA LA PAMPILLA S.A.A | BF7: SAGA FALABELLA | BG7: SAN MIGUEL INDUSTRIAS PET S.A. | BH7: SHOUGANG HIERRO PERU | BI7: SOFTYS PERU S.A.C. | BJ7: SUPERMERCADOS PERUANOS S.A. | BK7: TEJIDOS SAN JACINTO | BL7: TREN URBANO DE LIMA S.A. | BM7: TRUPAL S.A. | BN7: UNACEM PERU S.A. | BO7: UNIÓN DE CERVECERÍAS PERUANAS BACKUS Y JOHNSTON S. | BP7: ANGLO AMERICAN QUELLAVECO S.A. | BQ7: ARCA CONTINENTAL LINDLEY S.A. | BR7: CAL & CEMENTO SUR S.A. | BS7: COMPAÑIA MINERA ANTAPACCAY S.A. | BT7: COMPAÑÍA MINERA CHUNGAR SAC | BU7: COMPAÑIA MINERA SAN IGNACIO DE MOROCOCHA S.A.A. | BV7: EL BROCAL .S.A. | BW7: EMPRESA ADMINISTRADORA CERRO S.A.C. | BX7: EMPRESA MINERA LOS QUENUALES S.A.C. | BY7: HIPERMERCADOS TOTTUS S.A | BZ7: HUDBAY PERU S.A.C. | CA7: INDUSTRIA CACHIMAYO | CB7: MALL AVENTURA S.A. | CC7: MINERA ARES | CD7: MINERA BUENAVENTURA | CE7: MINERA CERRO VERDE | CF7: MINERA CORONA | CG7: MINERA LAS BAMBAS S.A. | CH7: MINERA VOLCAN | CI7: MINSUR | CJ7: MOLYCOP-ADESUR | CK7: NEXA RESOURCES PERÚ S.A.A. | CL7: OXIDOS DE PASCO S.A.C. | CM7: PESQUERA DIAMANTE | CN7: REAL PLAZA S.R.L. | CO7: SOBREANDES S.A.C. | CP7: SOUTHERN PERU CC | CQ7: SUPERMERCADOS PERUANOS S.A. | CR7: UNACEM PERU S.A. | CS7: UNIÓN DE CERVECERÍAS PERUANAS BACKUS Y JOHNSTON S. | CT7: YURA
B8: 00:30 | E8: 39.02487 | K8: 26.5057 | L8: 13.308 | M8: 14.154 | N8: 9.08 | O8: 33.088 | R8: 41.522 | T8: 47.0536 | X8: 99.22425 | AC8: 14.99 | AF8: 2.4 | AK8: 0 | AL8: 1.026 | AM8: 46.77613 | AN8: 129.06156 | AO8: 24.65669 | AP8: 0.81 | AQ8: 147.4269 | AS8: 35.67473 | AT8: 32.13 | AV8: 192.3019 | AW8: 36.576 | AY8: 0.28725 | BA8: 5.3 | BC8: 73.18587 | BE8: 19.4 | BI8: 16.89454 | BP8: 140.34055 | BR8: 4.2301 | BS8: 129.29928 | BT8: 11.21516 | BV8: 33.3796 | BW8: 3.85819 | BZ8: 88.03488 | CA8: 22.43377 | CB8: 0.3041 | CC8: 0.772 | CD8: 27.6711 | CE8: 453.36701 | CF8: 11.6639 | CG8: 122.54124 | CH8: 18.24259 | CL8: 4.96742 | CO8: 13.42323 | CP8: 245.46 | CR8: 37.019 | CT8: 27.36942
B9: 01:00 | E9: 38.63355 | K9: 26.6291 | L9: 13.088 | M9: 13.32 | N9: 9.03 | O9: 33.158 | R9: 41.68 | T9: 46.6878 | X9: 91.4635 | AC9: 15.65 | AF9: 3.7 | AK9: 0 | AL9: 1.0264 | AM9: 46.80855 | AN9: 128.88474 | AO9: 25.09874 | AP9: 0.7 | AQ9: 149.8069 | AS9: 35.64949 | AT9: 33.32 | AV9: 192.993 | AW9: 36.6041 | AY9: 0.3102 | BA9: 5.3 | BC9: 73.28095 | BE9: 19.4 | BI9: 16.35456 | BP9: 140.02938 | BR9: 4.2531 | BS9: 126.61747 | BT9: 10.48245 | BV9: 34.4427 | BW9: 3.96348 | BZ9: 89.1323 | CA9: 22.43531 | CB9: 0.2868 | CC9: 0.742 | CD9: 26.65295 | CE9: 448.23368 | CF9: 11.6124 | CG9: 145.8069 | CH9: 18.34923 | CL9: 4.88825 | CO9: 13.22549 | CP9: 241.49 | CR9: 36.636 | CT9: 30.3007
B10: 01:30 | E10: 38.85563 | K10: 26.6763 | L10: 13.206 | M10: 13.644 | N10: 8.88 | O10: 32.976 | R10: 41.809 | T10: 42.1573 | X10: 111.36418 | AC10: 15.67 | AF10: 6.1 | AK10: 0 | AL10: 0.9913 | AM10: 46.49433 | AN10: 125.63815 | AO10: 25.43486 | AP10: 0.64 | AQ10: 149.175 | AS10: 35.89092 | AT10: 33.45 | AV10: 190.079 | AW10: 36.9844 | AY10: 0.295 | BA10: 5.3 | BC10: 73.26585 | BE10: 19.4 | BI10: 16.64737 | BP10: 141.3035 | BR10: 4.0439 | BS10: 128.86699 | BT10: 11.09612 | BV10: 33.4257 | BW10: 4.0073 | BZ10: 89.29503 | CA10: 22.43875 | CB10: 0.2873 | CC10: 0.769 | CD10: 26.44493 | CE10: 446.05487 | CF10: 11.6505 | CG10: 148.47593 | CH10: 18.45024 | CL10: 4.86123 | CO10: 13.16571 | CP10: 241.68 | CR10: 36.357 | CT10: 30.37599
B11: 02:00 | E11: 38.53411 | K11: 26.5855 | L11: 13.251 | M11: 14.085 | N11: 10.81 | O11: 32.964 | R11: 41.558 | T11: 27.7417 | X11: 155.25419 | AC11: 15.96 | AF11: 7.8 | AK11: 0 | AL11: 0.9717 | AM11: 45.75154 | AN11: 126.18346 | AO11: 26.34009 | AP11: 0.44 | AQ11: 145.0516 | AS11: 35.42522 | AT11: 32.69 | AV11: 189.1592 | AW11: 37.267 | AY11: 0.30276 | BA11: 5.2 | BC11: 73.30453 | BE11: 19.4 | BI11: 16.73056 | BP11: 140.50164 | BR11: 4.1238 | BS11: 126.77488 | BT11: 10.48518 | BV11: 33.62 | BW11: 3.7307 | BZ11: 89.58722 | CA11: 22.44193 | CB11: 0.2884 | CC11: 0.729 | CD11: 25.73548 | CE11: 449.21509 | CF11: 11.7813 | CG11: 147.48283 | CH11: 17.98455 | CL11: 4.93227 | CO11: 13.45413 | CP11: 247.21 | CR11: 36.557 | CT11: 30.53397
B12: 02:30 | E12: 37.93524 | K12: 26.3264 | L12: 12.81 | M12: 13.592 | N12: 11.59 | O12: 32.818 | R12: 41.527 | T12: 48.4181 | X12: 125.67664 | AC12: 15.45 | AF12: 3.4 | AK12: 0 | AL12: 0.9787 | AM12: 45.27745 | AN12: 127.89829 | AO12: 25.79679 | AP12: 0.41 | AQ12: 144.45 | AS12: 37.26763 | AT12: 31.68 | AV12: 186.5775 | AW12: 37.7466 | AY12: 0.29102 | BA12: 4.9 | BC12: 73.28969 | BE12: 19.4 | BI12: 16.81477 | BP12: 140.89165 | BR12: 3.936 | BS12: 125.77757 | BT12: 12.05463 | BV12: 32.511 | BW12: 3.87202 | BZ12: 89.8411 | CA12: 22.46532 | CB12: 0.2884 | CC12: 0.708 | CD12: 26.24755 | CE12: 453.08799 | CF12: 11.7609 | CG12: 142.99677 | CH12: 17.8052 | CL12: 4.65131 | CO12: 13.2883 | CP12: 251.99 | CR12: 36.861 | CT12: 30.32278
B13: 03:00 | E13: 37.80981 | K13: 26.3459 | L13: 12.791 | M13: 13.779 | N13: 11.72 | O13: 33.266 | R13: 41.377 | T13: 42.0991 | X13: 93.66512 | AC13: 15.01 | AF13: 3.5 | AK13: 0 | AL13: 0.961 | AM13: 46.1277 | AN13: 127.22074 | AO13: 26.11814 | AP13: 0.67 | AQ13: 144.7128 | AS13: 35.77132 | AT13: 32.25 | AV13: 192.0722 | AW13: 36.506 | AY13: 0.36603 | BA13: 5.3 | BC13: 73.35144 | BE13: 19.4 | BI13: 17.03871 | BP13: 136.02519 | BR13: 3.8811 | BS13: 122.88373 | BT13: 11.59673 | BV13: 33.7823 | BW13: 3.96593 | BZ13: 89.9379 | CA13: 22.48597 | CB13: 0.2883 | CC13: 0.749 | CD13: 26.4942 | CE13: 460.25733 | CF13: 11.8798 | CG13: 146.87157 | CH13: 18.17567 | CL13: 4.65475 | CO13: 13.90014 | CP13: 263.39 | CR13: 36.85 | CT13: 30.3007
B14: 03:30 | E14: 35.84948 | K14: 26.2088 | L14: 13.011 | M14: 13.651 | N14: 11.79 | O14: 33.22 | R14: 41.052 | T14: 45.4887 | X14: 90.89295 | AC14: 15.13 | AF14: 2.2 | AK14: 0 | AL14: 0.9575 | AM14: 44.21182 | AN14: 128.44919 | AO14: 26.0669 | AP14: 0.48 | AQ14: 139.6404 | AS14: 35.9196 | AT14: 32.84 | AV14: 192.339 | AW14: 36.4386 | AY14: 0.36992 | BA14: 5.4 | BC14: 73.35247 | BE14: 19.4 | BI14: 19.35711 | BP14: 131.56728 | BR14: 3.8753 | BS14: 125.55714 | BT14: 12.15875 | BV14: 33.9418 | BW14: 4.02736 | BZ14: 90.11173 | CA14: 22.49354 | CB14: 0.279 | CC14: 0.769 | CD14: 25.69391 | CE14: 461.06902 | CF14: 12.1931 | CG14: 139.88632 | CH14: 17.97225 | CL14: 4.94758 | CO14: 13.80585 | CP14: 263.82 | CR14: 36.512 | CT14: 30.13726
B15: 04:00 | E15: 38.16393 | K15: 26.2884 | L15: 12.917 | M15: 14.225 | N15: 12.17 | O15: 34.056 | R15: 41.326 | T15: 38.264 | X15: 130.55278 | AC15: 15.41 | AF15: 3.6 | AK15: 0 | AL15: 0.9501 | AM15: 46.28654 | AN15: 127.50944 | AO15: 25.37023 | AP15: 0.18 | AQ15: 133.1453 | AS15: 35.20134 | AT15: 31.86 | AV15: 190.0334 | AW15: 36.4038 | AY15: 0.36659 | BA15: 5.3 | BC15: 73.19488 | BE15: 19.4 | BI15: 22.93123 | BP15: 131.32097 | BR15: 3.8973 | BS15: 129.24171 | BT15: 11.43967 | BV15: 33.779 | BW15: 3.88656 | BZ15: 90.0335 | CA15: 22.50392 | CB15: 0.2717 | CC15: 0.739 | CD15: 26.73933 | CE15: 463.75196 | CF15: 12.1333 | CG15: 151.27904 | CH15: 17.81351 | CL15: 4.911 | CO15: 13.88996 | CP15: 260.28 | CR15: 36.558 | CT15: 30.58587
B16: 04:30 | E16: 38.26032 | K16: 26.1528 | L16: 12.882 | M16: 14.543 | N16: 12.23 | O16: 34.068 | R16: 41.534 | T16: 42.0657 | X16: 92.25244 | AC16: 14.43 | AF16: 3.6 | AK16: 0 | AL16: 0.8868 | AM16: 45.85228 | AN16: 124.58385 | AO16: 25.95441 | AP16: 1.65 | AQ16: 136.7503 | AS16: 34.77468 | AT16: 31.48 | AV16: 189.6194 | AW16: 36.2275 | AY16: 0.37161 | BA16: 5.2 | BC16: 73.35367 | BE16: 19.4 | BI16: 22.99325 | BP16: 130.89799 | BR16: 3.9518 | BS16: 128.50454 | BT16: 11.03536 | BV16: 31.8515 | BW16: 3.90366 | BZ16: 88.97128 | CA16: 22.51386 | CB16: 0.2649 | CC16: 0.741 | CD16: 27.74062 | CE16: 462.46287 | CF16: 12.034 | CG16: 145.44714 | CH16: 17.69695 | CL16: 4.90793 | CO16: 13.33441 | CP16: 266.89 | CR16: 36.728 | CT16: 30.63903
B17: 05:00 | E17: 38.30962 | K17: 27.0252 | L17: 12.058 | M17: 14.436 | N17: 12.26 | O17: 34.298 | R17: 41.336 | T17: 38.4613 | X17: 144.68644 | AC17: 14.46 | AF17: 3.4 | AK17: 0 | AL17: 0.8663 | AM17: 46.36895 | AN17: 127.73572 | AO17: 26.01838 | AP17: 2.1 | AQ17: 138.9717 | AS17: 33.31322 | AT17: 30.6 | AV17: 191.8815 | AW17: 35.85 | AY17: 0.34555 | BA17: 5.2 | BC17: 73.27955 | BE17: 19.4 | BI17: 22.90004 | BP17: 132.26237 | BR17: 3.9215 | BS17: 130.33992 | BT17: 11.42995 | BV17: 33.3893 | BW17: 4.37541 | BZ17: 89.14399 | CA17: 22.52094 | CB17: 0.264 | CC17: 0.758 | CD17: 27.38726 | CE17: 454.26106 | CF17: 11.6162 | CG17: 147.18933 | CH17: 17.61841 | CL17: 4.90847 | CO17: 12.93122 | CP17: 261.96 | CR17: 37.143 | CT17: 30.38481
B18: 05:30 | E18: 37.93298 | K18: 26.9446 | L18: 11.729 | M18: 14.75 | N18: 12.46 | O18: 34.014 | R18: 41.201 | T18: 46.8054 | X18: 137.316 | AC18: 14.89 | AF18: 1.3 | AK18: 0 | AL18: 0.8616 | AM18: 46.19465 | AN18: 130.75886 | AO18: 25.79008 | AP18: 1.93 | AQ18: 138.4431 | AS18: 33.16526 | AT18: 31.16 | AV18: 191.053 | AW18: 35.2218 | AY18: 0.31535 | BA18: 5.2 | BC18: 73.32698 | BE18: 19.4 | BI18: 22.90178 | BP18: 132.2775 | BR18: 3.8938 | BS18: 129.09685 | BT18: 10.73209 | BV18: 32.9558 | BW18: 3.85894 | BZ18: 90.07457 | CA18: 22.51886 | CB18: 0.2606 | CC18: 0.777 | CD18: 26.28093 | CE18: 457.05031 | CF18: 11.8695 | CG18: 146.84571 | CH18: 17.94176 | CL18: 4.94279 | CO18: 12.2079 | CP18: 263.36 | CR18: 37.412 | CT18: 30.54378
B19: 06:00 | E19: 38.62436 | K19: 26.9951 | L19: 10.486 | M19: 14.86 | N19: 12.28 | O19: 34.472 | R19: 41.261 | T19: 49.8232 | X19: 133.85144 | AC19: 15.47 | AF19: 0.9 | AK19: 0 | AL19: 0.8555 | AM19: 47.08659 | AN19: 130.2497 | AO19: 25.15483 | AP19: 1.54 | AQ19: 138.7295 | AS19: 31.77326 | AT19: 31.18 | AV19: 189.5736 | AW19: 34.8991 | AY19: 0.29123 | BA19: 5.1 | BC19: 73.61256 | BE19: 19.4 | BI19: 22.84308 | BP19: 134.88268 | BR19: 3.7958 | BS19: 124.75838 | BT19: 10.67038 | BV19: 32.5699 | BW19: 3.65085 | BZ19: 90.09561 | CA19: 22.5317 | CB19: 0.2589 | CC19: 0.698 | CD19: 24.65623 | CE19: 452.73062 | CF19: 10.97 | CG19: 149.26579 | CH19: 17.89677 | CL19: 4.67585 | CO19: 11.73335 | CP19: 265.32 | CR19: 37.54 | CT19: 30.41913
... B55: 00:00 | E55: 38.51697 | K55: 26.4176 | L55: 13.108 | M55: 13.877 | N55: 12.87 | O55: 33.314 | R55: 42.959 | T55: 43.5624 | X55: 135.2638 | AC55: 14.28 | AF55: 1.4 | AK55: 0 | AL55: 1.3252 | AM55: 45.49071 | AN55: 126.71471 | AO55: 26.8506 | AP55: 0.83 | AQ55: 76.4963 | AS55: 35.92291 | AT55: 32.49 | AV55: 191.5581 | AW55: 35.5721 | AY55: 0.46514 | BA55: 4.7 | BC55: 72.48874 | BE55: 19.44 | BI55: 20.13655 | BP55: 144.07706 | BR55: 4.2813 | BS55: 126.44156 | BT55: 11.99038 | BV55: 0 | BW55: 3.83695 | BZ55: 89.46078 | CA55: 22.54365 | CB55: 0.3875 | CC55: 0.743 | CD55: 25.73958 | CE55: 452.11555 | CF55: 11.8794 | CG55: 148.13625 | CH55: 18.34485 | CL55: 5.30091 | CO55: 14.87394 | CP55: 275.53 | CR55: 34.703 | CT55: 33.19931
B56: MWh | C56: 0 | D56: 0 | E56: 827.36382 | F56: 0 | G56: 0 | H56: 0 | I56: 0 | J56: 0 | K56: 634.96605 | L56: 289.219 | M56: 312.8505 | N56: 291.835 | O56: 794.418 | P56: 0 | Q56: 0 | R56: 989.22 | S56: 0 | T56: 832.3394 | U56: 0 | V56: 0 | W56: 0 | X56: 2281.6045 | Y56: 0 | Z56: 0 | AA56: 0 | AB56: 0 | AC56: 370.855 | AD56: 0 | AE56: 0 | AF56: 38.75 | AG56: 0 | AH56: 0 | AI56: 0 | AJ56: 0 | AK56: 0 | AL56: 47.78475 | AM56: 987.39405 | AN56: 2846.3883 | AO56: 623.47819 | AP56: 18.01 | AQ56: 2455.5365 | AR56: 0 | AS56: 809.28344 | AT56: 747.3 | AU56: 0 | AV56: 3765.5293 | AW56: 851.00435 | AX56: 0 | AY56: 8.702885 | AZ56: 0 | BA56: 100.55 | BB56: 0 | BC56: 1594.142 | BD56: 0 | BE56: 461.18 | BF56: 0 | BG56: 0 | BH56: 0 | BI56: 513.92661 | BJ56: 0 | BK56: 0 | BL56: 0 | BM56: 0 | BN56: 0 | BO56: 0 | BP56: 3302.5505 | BQ56: 0 | BR56: 103.6712 | BS56: 3013.095 | BT56: 241.97948 | BU56: 0 | BV56: 749.98215 | BW56: 93.604915 | BX56: 0 | BY56: 0 | BZ56: 2147.4493 | CA56: 473.44633 | CB56: 16.56395 | CC56: 18.0125 | CD56: 609.49346 | CE56: 10875.254 | CF56: 272.39615 | CG56: 3538.3639 | CH56: 420.97895 | CI56: 0 | CJ56: 0 | CK56: 0 | CL56: 116.99258 | CM56: 0 | CN56: 0 | CO56: 312.45801 | CP56: 6342.215 | CQ56: 0 | CR56: 840.42 | CS56: 0 | CT56: 764.29574
B59: Nota :
B60: Información proporcionada por la empresas
C62: DATOS ESTIMADOS
C64: SIN DATOS

Sheet TIPO_RECURSO
B3: sábado, 25 de Enero del 2025
B5: REPORTE POTENCIA GENERADA POR TIPO DE RECURSO
B6: HORA | C6: H. PASADA | D6: H. REGULACION | E6: GAS DE CAMISEA | F6: GAS DE MALACAS | G6: GAS DE AGUAYTÍA | H6: RESIDUAL R500 | I6: DIESEL | J6: NAFTA+GAS DE REFINERIA | K6: FLEXIGAS+GAS DE REFINERIA | L6: BAGAZO | M6: BIOGAS | N6: SOLAR | O6: EOLICA | P6: TOTAL | U6: EMPRESA | V6: CENTRAL | W6: HIDROELECTRICA DE PASADA | X6: HIDROELECTRICA DE REGULACION
B7: 00:30 | C7: 1208 | D7: 3537.792 | E7: 1646.3 | F7: 47.1 | I7: 0 | J7: =+DESPACHO_EJECUTADO!EZ11+DESPACHO_EJECUTADO!FA11 -> 54.6 | L7: 44.6 | M7: 10.8 | N7: 0 | O7: 276.2 | P7: =+SUM(C7:O7) -> 6825.392 | U7: ANDEAN POWER S.A.C. | V7: C.H. CARHUAC | W7: 331.05
B8: 01:00 | C8: 1191.5 | D8: 3431.695 | E8: 1599 | F8: 47.1 | I8: 0 | J8: =+DESPACHO_EJECUTADO!EZ12+DESPACHO_EJECUTADO!FA12 -> 53.5 | L8: 45.2 | M8: 10.8 | N8: 0 | O8: 312.9 | P8: =+SUM(C8:O8) -> 6691.695 | U8: ASOCIACIÓN SANTA LUCIA DE CHACAS | V8: C.H. HUALLIN | W8: 48
B9: 01:30 | C9: 1202.7 | D9: 3376.88 | E9: 1501.4 | F9: 47 | I9: 0 | J9: =+DESPACHO_EJECUTADO!EZ13+DESPACHO_EJECUTADO!FA13 -> 53.2 | L9: 46.7 | M9: 10.8 | N9: 0 | O9: 319.6 | P9: =+SUM(C9:O9) -> 6558.28 | U9: CELEPSA | V9: C.H. EL PLATANAL | X9: 5063.2
B10: 02:00 | C10: 1201.8 | D10: 3550.831 | E10: 1344.5 | F10: 47.5 | I10: 0 | J10: =+DESPACHO_EJECUTADO!EZ14+DESPACHO_EJECUTADO!FA14 -> 53.2 | L10: 47.4 | M10: 10.8 | N10: 0 | O10: 286 | P10: =+SUM(C10:O10) -> 6542.031 | U10: CELEPSA RENOVABLES S.R.L. | V10: C.H. MARAÑON | W10: 466.95
B11: 02:30 | C11: 1170 | D11: 3347.801 | E11: 1472.2 | F11: 47.3 | I11: 0 | J11: =+DESPACHO_EJECUTADO!EZ15+DESPACHO_EJECUTADO!FA15 -> 52.9 | L11: 47.5 | M11: 10.8 | N11: 0 | O11: 249.1 | P11: =+SUM(C11:O11) -> 6397.601 | U11: CENTRALES SANTA ROSA S.A.C. | V11: C.H. SANTA ROSA I | W11: 26.4
B12: 03:00 | C12: 1195.7 | D12: 3434.977 | E12: 1360.4 | F12: 47.3 | I12: 0 | J12: =+DESPACHO_EJECUTADO!EZ16+DESPACHO_EJECUTADO!FA16 -> 52.5 | L12: 48.6 | M12: 10.8 | N12: 0 | O12: 284.5 | P12: =+SUM(C12:O12) -> 6434.777 | V12: C.H. SANTA ROSA II | W12: 40.15
B13: 03:30 | C13: 1175 | D13: 3482.642 | E13: 1329.4 | F13: 47.4 | I13: 0 | J13: =+DESPACHO_EJECUTADO!EZ17+DESPACHO_EJECUTADO!FA17 -> 52.3 | L13: 48.4 | M13: 10.8 | N13: 0 | O13: 271.2 | P13: =+SUM(C13:O13) -> 6417.142 | U13: CHINANGO S.A.C. | V13: C.H. CHIMAY | X13: 3397.55
B14: 04:00 | C14: 1171.8 | D14: 3316.285 | E14: 1398.3 | F14: 47.4 | I14: 0 | J14: =+DESPACHO_EJECUTADO!EZ18+DESPACHO_EJECUTADO!FA18 -> 51.7 | L14: 46.3 | M14: 10.8 | N14: 0 | O14: 282.7 | P14: =+SUM(C14:O14) -> 6325.285 | V14: C.H. YANANGO | W14: 1002.7
B15: 04:30 | C15: 1197.3 | D15: 3382.564 | E15: 1431.6 | F15: 47.1 | I15: 0 | J15: =+DESPACHO_EJECUTADO!EZ19+DESPACHO_EJECUTADO!FA19 -> 52.8 | L15: 48.8 | M15: 10.8 | N15: 0 | O15: 286.8 | P15: =+SUM(C15:O15) -> 6457.764 | U15: EGASA | V15: C.H. CHARCANI III | W15: 158.7
B16: 05:00 | C16: 1172.1 | D16: 3298.475 | E16: 1438.9 | F16: 47 | I16: 0 | J16: =+DESPACHO_EJECUTADO!EZ20+DESPACHO_EJECUTADO!FA20 -> 51.7 | L16: 46 | M16: 10.6 | N16: 0 | O16: 269.8 | P16: =+SUM(C16:O16) -> 6334.575 | V16: C.H. CHARCANI V | X16: 1548.95
B17: 05:30 | C17: 1178.9 | D17: 3326.772 | E17: 1568.4 | F17: 47.2 | I17: 0 | J17: =+DESPACHO_EJECUTADO!EZ21+DESPACHO_EJECUTADO!FA21 -> 52.6 | L17: 44.1 | M17: 10.8 | N17: 1 | O17: 241.4 | P17: =+SUM(C17:O17) -> 6471.172 | V17: C.H. CHARCANI VI | X17: 138.15
B18: 06:00 | C18: 1174.1 | D18: 3296.424 | E18: 1552.5 | F18: 47 | I18: 0 | J18: =+DESPACHO_EJECUTADO!EZ22+DESPACHO_EJECUTADO!FA22 -> 52.5 | L18: 45.1 | M18: 10.8 | N18: 32.6 | O18: 192.2 | P18: =+SUM(C18:O18) -> 6403.224 | U18: EGEJUNIN | V18: C.H. HUASAHUASI I | W18: 383.65
B19: 06:30 | C19: 1186.1 | D19: 3198.2 | E19: 1527.1 | F19: 47.7 | I19: 0 | J19: =+DESPACHO_EJECUTADO!EZ23+DESPACHO_EJECUTADO!FA23 -> 52 | L19: 46.8 | M19: 10.8 | N19: 109.3 | O19: 184.8 | P19: =+SUM(C19:O19) -> 6362.8 | V19: C.H. RUNATULLO II | W19: 475.25
B20: 07:00 | C20: 1176.6 | D20: 3070.743 | E20: 1594.4 | F20: 47.3 | I20: 0 | J20: =+DESPACHO_EJECUTADO!EZ24+DESPACHO_EJECUTADO!FA24 -> 51.9 | L20: 44.6 | M20: 10.8 | N20: 218.1 | O20: 170.5 | P20: =+SUM(C20:O20) -> 6384.943 | V20: C.H. RUNATULLO III | W20: 487.8
B21: 07:30 | C21: 1182.4 | D21: 3175.815 | E21: 1624 | F21: 46.9 | I21: 0 | J21: =+DESPACHO_EJECUTADO!EZ25+DESPACHO_EJECUTADO!FA25 -> 52.1 | L21: 46.9 | M21: 10.8 | N21: 331.3 | O21: 155 | P21: =+SUM(C21:O21) -> 6625.215 | V21: C.H. SANTA CRUZ I | W21: 212.7
B22: 08:00 | C22: 1189.5 | D22: 3239.12 | E22: 1688.7 | F22: 47 | I22: 0 | J22: =+DESPACHO_EJECUTADO!EZ26+DESPACHO_EJECUTADO!FA26 -> 52.1 | L22: 46.2 | M22: 10.8 | N22: 382.9 | O22: 157.1 | P22: =+SUM(C22:O22) -> 6813.42 | U22: EGEMSA | V22: C.H. MACHUPICCHU | W22: 3979.55
B23: 08:30 | C23: 1209.4 | D23: 3365.408 | E23: 1746.4 | F23: 46.6 | I23: 0 | J23: =+DESPACHO_EJECUTADO!EZ27+DESPACHO_EJECUTADO!FA27 -> 51.8 | L23: 45.9 | M23: 10.8 | N23: 418.4 | O23: 181.1 | P23: =+SUM(C23:O23) -> 7075.808 | U23: EGESUR | V23: C.H. ARICOTA I | X23: 181.154
B24: 09:00 | C24: 1208.2 | D24: 3454.838 | E24: 1868.979 | F24: 46.6 | I24: 0 | J24: =+DESPACHO_EJECUTADO!EZ28+DESPACHO_EJECUTADO!FA28 -> 52 | L24: 41.7 | M24: 10.8 | N24: 434.3 | O24: 179.7 | P24: =+SUM(C24:O24) -> 7297.117 | V24: C.H. ARICOTA II | X24: 62.7405
B25: 09:30 | C25: 1197 | D25: 3482.469 | E25: 1886.431 | F25: 45.8 | I25: 0 | J25: =+DESPACHO_EJECUTADO!EZ29+DESPACHO_EJECUTADO!FA29 -> 52 | L25: 40.5 | M25: 10.8 | N25: 441 | O25: 193.5 | P25: =+SUM(C25:O25) -> 7349.5 | U25: ELECTRICA YANAPAMPA SAC | V25: C.H. YANAPAMPA | W25: 84.75
B26: 10:00 | C26: 1193.1 | D26: 3461.559 | E26: 2040.685 | F26: 45.7 | I26: 0 | J26: =+DESPACHO_EJECUTADO!EZ30+DESPACHO_EJECUTADO!FA30 -> 51.2 | L26: 38.3 | M26: 10.8 | N26: 447.9 | O26: 229.8 | P26: =+SUM(C26:O26) -> 7519.044 | U26: ELECTROPERU | V26: C.H. MANTARO | X26: 15521
B27: 10:30 | C27: 1174.4 | D27: 3419.295 | E27: 2068.762 | F27: 45 | I27: 0 | J27: =+DESPACHO_EJECUTADO!EZ31+DESPACHO_EJECUTADO!FA31 -> 51.9 | L27: 40 | M27: 10.8 | N27: 448.3 | O27: 281.2 | P27: =+SUM(C27:O27) -> 7539.657 | V27: C.H. RESTITUCION | W27: 5222.6
B28: 11:00 | C28: 1200.3 | D28: 3470.457 | E28: 1936.341 | F28: 44.6 | I28: 0 | J28: =+DESPACHO_EJECUTADO!EZ32+DESPACHO_EJECUTADO!FA32 -> 51 | L28: 40.8 | M28: 10.8 | N28: 463.2 | O28: 304.7 | P28: =+SUM(C28:O28) -> 7522.198 | U28: EMPRESA DE GENERACION ELECTRICA CANCHAYLLO SAC | V28: C.H. CANCHAYLLO | W28: 124.1
B29: 11:30 | C29: 1195.7 | D29: 3441.467 | E29: 2012.466 | F29: 44.8 | I29: 5.4 | J29: =+DESPACHO_EJECUTADO!EZ33+DESPACHO_EJECUTADO!FA33 -> 51.7 | L29: 38.2 | M29: 10.7 | N29: 467.9 | O29: 358.4 | P29: =+SUM(C29:O29) -> 7626.733 | U29: EMPRESA DE GENERACION ELECTRICA RIO BAÑOS S.A.C. | V29: C.H. RUCUY | W29: 478.4
B30: 12:00 | C30: 1192.9 | D30: 3451.839 | E30: 1985.245 | F30: 46 | I30: 3.1 | J30: =+DESPACHO_EJECUTADO!EZ34+DESPACHO_EJECUTADO!FA34 -> 51.3 | L30: 38.7 | M30: 10.7 | N30: 469.5 | O30: 379.5 | P30: =+SUM(C30:O30) -> 7628.784 | U30: EMPRESA DE GENERACION ELECTRICA SANTA ANA S.A.C. | V30: C.H. RENOVANDES H1 | W30: 484.25
B31: 12:30 | C31: 1199.7 | D31: 3407.269 | E31: 2004.349 | F31: 45.5 | I31: 0 | J31: =+DESPACHO_EJECUTADO!EZ35+DESPACHO_EJECUTADO!FA35 -> 51.5 | L31: 38.9 | M31: 10.7 | N31: 466.9 | O31: 412.8 | P31: =+SUM(C31:O31) -> 7637.618 | U31: EMPRESA DE GENERACION HUALLAGA | V31: C.H. CHAGLLA | X31: 10957.85
B32: 13:00 | C32: 1191.6 | D32: 3302.082 | E32: 2025.3 | F32: 45.5 | I32: 0 | J32: =+DESPACHO_EJECUTADO!EZ36+DESPACHO_EJECUTADO!FA36 -> 51.4 | L32: 39.8 | M32: 10.7 | N32: 460.4 | O32: 446.8 | P32: =+SUM(C32:O32) -> 7573.582 | V32: P.C.H. CHAGLLA | W32: 156
B33: 13:30 | C33: 1199.5 | D33: 3341.399 | E33: 1879.869 | F33: 45.2 | I33: 0 | J33: =+DESPACHO_EJECUTADO!EZ37+DESPACHO_EJECUTADO!FA37 -> 51.5 | L33: 40.9 | M33: 10.5 | N33: 422.9 | O33: 476.1 | P33: =+SUM(C33:O33) -> 7467.868 | U33: EMPRESA DE GENERACION HUANZA | V33: C.H. HUANZA | X33: 1035.05
B34: 14:00 | C34: 1189.9 | D34: 3365.271 | E34: 1884.132 | F34: 45.9 | I34: 0 | J34: =+DESPACHO_EJECUTADO!EZ38+DESPACHO_EJECUTADO!FA38 -> 51.6 | L34: 40.8 | M34: 10.5 | N34: 240.7 | O34: 567.5 | P34: =+SUM(C34:O34) -> 7396.303 | U34: EMPRESA ELECTRICA AGUA AZUL | V34: C.H. POTRERO | W34: 476.95
B35: 14:30 | C35: 1196.8 | D35: 3371.23 | E35: 1911.211 | F35: 45.8 | I35: 0 | J35: =+DESPACHO_EJECUTADO!EZ39+DESPACHO_EJECUTADO!FA39 -> 51.2 | L35: 44.4 | M35: 10.4 | N35: 159.8 | O35: 610.1 | P35: =+SUM(C35:O35) -> 7400.941 | U35: EMPRESA ELECTRICA RIO DOBLE | V35: C.H. LAS PIZARRAS | W35: 355.35
B36: 15:00 | C36: 1192.6 | D36: 3339.347 | E36: 1998.132 | F36: 46.2 | I36: 0 | J36: =+DESPACHO_EJECUTADO!EZ40+DESPACHO_EJECUTADO!FA40 -> 51.4 | L36: 46.6 | M36: 10.4 | N36: 141.1 | O36: 619.4 | P36: =+SUM(C36:O36) -> 7445.179 | U36: ENGIE | V36: C.H. QUITARACSA | X36: 2067.8
B37: 15:30 | C37: 1193.4 | D37: 3476.265 | E37: 1945.02 | F37: 46.2 | I37: 0 | J37: =+DESPACHO_EJECUTADO!EZ41+DESPACHO_EJECUTADO!FA41 -> 51.2 | L37: 45.1 | M37: 10.4 | N37: 101 | O37: 566.8 | P37: =+SUM(C37:O37) -> 7435.385 | V37: C.H. YUNCAN | X37: 3136.85
B38: 16:00 | C38: 1188.7 | D38: 3459.464 | E38: 1870.99 | F38: 45.6 | I38: 0 | J38: =+DESPACHO_EJECUTADO!EZ42+DESPACHO_EJECUTADO!FA42 -> 51.2 | L38: 46 | M38: 10.4 | N38: 105.6 | O38: 593.1 | P38: =+SUM(C38:O38) -> 7371.054 | U38: GENERACIÓN ANDINA S.A.C. | V38: C.H. 8 DE AGOSTO | W38: 504
B39: 16:30 | C39: 1177.8 | D39: 3331.616 | E39: 1842.8 | F39: 46.1 | I39: 0 | J39: =+DESPACHO_EJECUTADO!EZ43+DESPACHO_EJECUTADO!FA43 -> 51.9 | L39: 45.1 | M39: 10.4 | N39: 144.4 | O39: 572.8 | P39: =+SUM(C39:O39) -> 7222.916 | V39: C.H. EL CARMEN | W39: 148
B40: 17:00 | C40: 1167.3 | D40: 3125.617 | E40: 1836.1 | F40: 46 | I40: 0 | J40: =+DESPACHO_EJECUTADO!EZ44+DESPACHO_EJECUTADO!FA44 -> 51.8 | L40: 48 | M40: 10.4 | N40: 198.9 | O40: 534.4 | P40: =+SUM(C40:O40) -> 7018.517 | U40: GENERADORA DE ENERGÍA DEL PERÚ | V40: C.H. ÁNGEL I | W40: 480
B41: 17:30 | C41: 1183.9 | D41: 3307.785 | E41: 1698.7 | F41: 46.3 | I41: 0 | J41: =+DESPACHO_EJECUTADO!EZ45+DESPACHO_EJECUTADO!FA45 -> 51.6 | L41: 47.7 | M41: 10.7 | N41: 68.8 | O41: 500 | P41: =+SUM(C41:O41) -> 6915.485 | V41: C.H. ÁNGEL II | W41: 480
B42: 18:00 | C42: 1184.2 | D42: 3297.641 | E42: 1708.3 | F42: 46.4 | I42: 0 | J42: =+DESPACHO_EJECUTADO!EZ46+DESPACHO_EJECUTADO!FA46 -> 51.8 | L42: 46 | M42: 10.7 | N42: 13.6 | O42: 481.9 | P42: =+SUM(C42:O42) -> 6840.541 | V42: C.H. ÁNGEL III | W42: 478.45
B43: 18:30 | C43: 1189.6 | D43: 3494.816 | E43: 1696.8 | F43: 47.1 | I43: 0 | J43: =+DESPACHO_EJECUTADO!EZ47+DESPACHO_EJECUTADO!FA47 -> 51.7 | L43: 46 | M43: 10.7 | N43: 0 | O43: 456.5 | P43: =+SUM(C43:O43) -> 6993.216 | V43: C.H. LA JOYA | W43: 114.45
B44: 19:00 | C44: 1194.1 | D44: 3578.294 | E44: 1891.3 | F44: 46.9 | I44: 0 | J44: =+DESPACHO_EJECUTADO!EZ48+DESPACHO_EJECUTADO!FA48 -> 51.7 | L44: 44.3 | M44: 12.1 | N44: 0 | O44: 438.1 | P44: =+SUM(C44:O44) -> 7256.794 | U44: HIDROCAÑETE S.A. | V44: C.H. IMPERIAL | W44: 82.15
B45: 19:30 | C45: 1195 | D45: 3634.106 | E45: 2090.6 | F45: 47.4 | I45: 0 | J45: =+DESPACHO_EJECUTADO!EZ49+DESPACHO_EJECUTADO!FA49 -> 52.3 | L45: 45.1 | M45: 12.2 | N45: 0 | O45: 354.3 | P45: =+SUM(C45:O45) -> 7431.006 | U45: HIDROELECTRICA HUANCHOR S.A.C. | V45: C.H. HUANCHOR | W45: 440.85
B46: 20:00 | C46: 1198.1 | D46: 3660.061 | E46: 2085.6 | F46: 47.3 | I46: 0 | J46: =+DESPACHO_EJECUTADO!EZ50+DESPACHO_EJECUTADO!FA50 -> 51.7 | L46: 44.1 | M46: 12.2 | N46: 0 | O46: 310.8 | P46: =+SUM(C46:O46) -> 7409.861 | U46: HUAURA POWER GROUP S.A. | V46: C.H. YARUCAYA | W46: 431.75
B47: 20:30 | C47: 1196.2 | D47: 3701.298 | E47: 2008.8 | F47: 47.3 | I47: 0 | J47: =+DESPACHO_EJECUTADO!EZ51+DESPACHO_EJECUTADO!FA51 -> 52.1 | L47: 44.1 | M47: 12.2 | N47: 0 | O47: 291.6 | P47: =+SUM(C47:O47) -> 7353.598 | U47: INLAND ENERGY SAC | V47: C.H. SANTA TERESA | W47: 2166.25
B48: 21:00 | C48: 1196.2 | D48: 3685.359 | E48: 1972.8 | F48: 47.3 | I48: 0 | J48: =+DESPACHO_EJECUTADO!EZ52+DESPACHO_EJECUTADO!FA52 -> 52 | L48: 43.2 | M48: 12.2 | N48: 0 | O48: 279 | P48: =+SUM(C48:O48) -> 7288.059 | U48: INVERSIONES SHAQSHA S.A.C. | V48: C.H. PARIAC | W48: 103.05
B49: 21:30 | C49: 1188.7 | D49: 3640.874 | E49: 1978.2 | F49: 47.4 | I49: 0 | J49: =+DESPACHO_EJECUTADO!EZ53+DESPACHO_EJECUTADO!FA53 -> 52 | L49: 42.9 | M49: 12.2 | N49: 0 | O49: 279.5 | P49: =+SUM(C49:O49) -> 7241.774 | U49: KALLPA GENERACION S.A. | V49: C.H. CERRO DEL AGUILA | X49: 13388.7
B50: 22:00 | C50: 1192.1 | D50: 3540.948 | E50: 1958 | F50: 47.2 | I50: 0 | J50: =+DESPACHO_EJECUTADO!EZ54+DESPACHO_EJECUTADO!FA54 -> 50.8 | L50: 41 | M50: 12.4 | N50: 0 | O50: 268.3 | P50: =+SUM(C50:O50) -> 7110.748 | V50: M.C.H. CERRO DEL AGUILA | W50: 252.35
B51: 22:30 | C51: 1193.8 | D51: 3512.875 | E51: 1912.2 | F51: 47.4 | I51: 0 | J51: =+DESPACHO_EJECUTADO!EZ55+DESPACHO_EJECUTADO!FA55 -> 52.1 | L51: 41.1 | M51: 12.4 | N51: 0 | O51: 258.7 | P51: =+SUM(C51:O51) -> 7030.575 | U51: LA VIRGEN | V51: C.H. LA VIRGEN | X51: 1557.6
B52: 23:00 | C52: 1192.5 | D52: 3391.779 | E52: 1850.9 | F52: 47.1 | I52: 0 | J52: =+DESPACHO_EJECUTADO!EZ56+DESPACHO_EJECUTADO!FA56 -> 52.1 | L52: 41.8 | M52: 12.4 | N52: 0 | O52: 253.7 | P52: =+SUM(C52:O52) -> 6842.279 | U52: MAJA ENERGIA S.A.C. | V52: C.H. RONCADOR | W52: 86.45
B53: 23:30 | C53: 1195.3 | D53: 3482.772 | E53: 1791.3 | F53: 46.8 | I53: 0 | J53: =+DESPACHO_EJECUTADO!EZ57+DESPACHO_EJECUTADO!FA57 -> 52.2 | L53: 42.6 | M53: 12.4 | N53: 0 | O53: 229 | P53: =+SUM(C53:O53) -> 6852.372 | U53: ORAZUL ENERGY PERÚ | V53: C.H. CAÑA BRAVA | W53: 122.5
B54: 00:00 | C54: 1184.3 | D54: 3579.673 | E54: 1692.8 | F54: 47.4 | I54: 0 | J54: =+DESPACHO_EJECUTADO!EZ58+DESPACHO_EJECUTADO!FA58 -> 52.8 | L54: 43.9 | M54: 12.4 | N54: 0 | O54: 205.2 | P54: =+SUM(C54:O54) -> 6818.473 | V54: C.H. CAÑON DEL PATO | X54: 5583.95
B55: TOTAL MWh | C55: =+SUM(C7:C54)/2 -> 28562.9 | D55: =+SUM(D7:D54)/2 -> 82021.095 | E55: =+SUM(E7:E54)/2 -> 42578.306 | F55: =+SUM(F7:F54)/2 -> 1118.85 | G55: =+SUM(G7:G54)/2 -> 0 | H55: =+SUM(H7:H54)/2 -> 0 | I55: =+SUM(I7:I54)/2 -> 4.25 | J55: =+SUM(J7:J54)/2 -> 1248.05 | ... P55: =+SUM(P7:P54)/2 -> 168479.15 | V55: C.H. CARHUAQUERO | X55: 1905.95
B56: % | C56: =+C55/$P$55*100 -> 16.953374 | D56: =+D55/$P$55*100 -> 48.683231 | E56: =+E55/$P$55*100 -> 25.272151 | F56: =+F55/$P$55*100 -> 0.66408811 | G56: =+G55/$P$55*100 -> 0 | H56: =+H55/$P$55*100 -> 0 | I56: =+I55/$P$55*100 -> 0.0025225673 | J56: =+J55/$P$55*100 -> 0.74077415 | ... P56: =+P55/$P$55*100 -> 100 | V56: C.H. CARHUAQUERO IV | W56: 238.1
U57: ORYGEN PERU S.A.A. | V57: C.H. CALLAHUANCA | X57: 1941.6
V58: C.H. HER 1 | W58: 14.4
V59: C.H. HUAMPANI | W59: 722.2
V60: C.H. HUINCO | X60: 3472.15
V61: C.H. MATUCANA | X61: 3058
V62: C.H. MOYOPAMPA | W62: 1529.5
U63: PERUANA DE INVERSIONES EN ENERGIAS RENOVABLES S.A. | V63: C.H. MANTA I | W63: 479.6
U64: SAN GABAN | V64: C.H. SAN GABAN II | X64: 2655.9
U65: SINERSA | V65: C.H. CHANCAY | W65: 478.65
V66: C.H. POECHOS II | W66: 144.25
U67: STATKRAFT S.A | V67: C.H. ARCATA | W67: 84.45
V68: C.H. CAHUA | W68: 1126
V69: C.H. CHEVES | X69: 3502.05
V70: C.H. GALLITO CIEGO | X70: 750.2
V71: C.H. MALPASO | X71: 1094.7
V72: C.H. OROYA | W72: 192.7
V73: C.H. PACHACHACA | W73: 57.25
V74: C.H. YAUPI | W74: 2610.25
U75: TOTAL MWh | W75: 28562.9 | X75: 82021.095

Sheet GENERACION RER
B3: sábado, 25 de Enero del 2025
B5: GENERACIÓN ELÉCTRICA DE LAS CENTRALES RER (MW)
B6: HORA | C6: AGRO INDUSTRIAL PARAMONGA S.A. | D6: AGROAURORA S.A.C. | E6: AGROINDUSTRIAS SAN JACINTO S.A.A. | F6: ANDEAN POWER S.A.C. | G6: ASOCIACIÓN SANTA LUCIA DE CHACAS | H6: ATRIA ENERGIA S.A.C. | I6: BIOENERGIA DEL CHIRA S.A. | J6: COLCA SOLAR S.A.C. | K6: EGEJUNIN | P6: ELECTRICA YANAPAMPA SAC | Q6: EMPRESA DE GENERACION ELECTRICA CANCHAYLLO SAC | R6: EMPRESA DE GENERACION ELECTRICA RIO BAÑOS S.A.C. | S6: EMPRESA DE GENERACION ELECTRICA SANTA ANA S.A.C. | T6: EMPRESA ELECTRICA AGUA AZUL | U6: EMPRESA ELECTRICA RIO DOBLE | V6: ENERGÍA EÓLICA S.A. | X6: ENERGIA RENOVABLE DEL SUR S.A. | Y6: ENGIE | AD6: GENERACIÓN ANDINA S.A.C. | AF6: GENERADORA DE ENERGÍA DEL PERÚ | AJ6: GR CORTARRAMA SOCIEDAD ANONIMA CERRADA | AK6: GR PAINO SOCIEDAD ANONIMA CERRADA | AL6: GR TARUCA SOCIEDAD ANONIMA CERRADA | AM6: HIDROCAÑETE S.A. | AN6: HUAURA POWER GROUP S.A. | AO6: HYDRO PATAPO S.A.C. | AP6: KONDU SAC | AQ6: MAJA ENERGIA S.A.C. | AR6: MAJES ARCUS S.A.C. | AS6: MOQUEGUA FV S.A.C. | AT6: ORAZUL ENERGY PERÚ | AV6: ORYGEN PERU S.A.A. | BA6: PANAMERICANA SOLAR SAC. | BB6: PARQUE EOLICO MARCONA S.A.C. | BC6: PARQUE EOLICO TRES HERMANAS S.A.C. | BD6: PERUANA DE INVERSIONES EN ENERGIAS RENOVABLES S.A. | BE6: PETRAMAS | BI6: REPARTICIÓN ARCUS S.A.C. | BJ6: SDF ENERGIA SAC | BK6: SINERSA | BM6: TACNA SOLAR SAC. | BN6: TOTAL RER
C7: C.T. PARAMONGA | D7: C.T. MAPLE | E7: C.T SAN JACINTO | F7: C.H. CARHUAC | G7: C.H. HUALLIN | H7: C.H. PURMACANA | I7: C.T. CAÑA BRAVA | K7: C.H. HUASAHUASI I | L7: C.H. HUASAHUASI II | M7: C.H. RUNATULLO II | N7: C.H. RUNATULLO III | O7: C.H. STA CRUZ I y II | P7: C.H. YANAPAMPA | Q7: C.H. CANCHAYLLO | R7: C.H. RUCUY | S7: C.H. RENOVANDES H1 | T7: C.H. POTRERO | U7: C.H. LAS PIZARRAS | AD7: C.H. 8 DE AGOSTO | AE7: C.H. EL CARMEN | AF7: C.H. ANGEL I | AG7: C.H. ANGEL II | AH7: C.H. ANGEL III | AI7: C.H. LA JOYA | AM7: C.H. NUEVAIMPERIAL | AN7: C.H. YARUCAYA | AO7: MCH PATAPO | AQ7: C.H. RONCADOR | AT7: C.H. CANA BRAVA | AU7: C.H. CARHUAQUERO4 | AZ7: C.H. HER 1 | BD7: C.H. MANTA | BE7: C.T. HUAYCOLORO | BF7: C.T. LA GRINGA V | BG7: CTB CALLAO | BH7: CTB. DONA CATALINA | BJ7: C.T. OQUENDO | BK7: C.H. CHANCAY | BL7: C.H. POECHOS2 | BN7: MW
B8: 0:30 | C8: 14.2 | D8: 11.3 | E8: 8.2 | F8: 17.5 | G8: 2 | I8: 10.9 | K8: 19.4 | M8: 19.6 | N8: 20.3 | O8: 9.6 | P8: 3.5 | Q8: 5.1 | R8: 20 | S8: 20.1 | T8: 20 | U8: 15.6 | V8: 18.3 | W8: 55.3 | X8: 42.7 | Y8: 23.8 | Z8: 50.5 | AB8: 1.1 | AC8: 0.7 | AD8: 21 | AE8: 7.8 | AF8: 20 | AG8: 20 | AH8: 19 | AI8: 9.5 | AK8: 8.3 | AL8: 14.4 | AM8: 3.5 | AN8: 18.7 | AQ8: 3.6 | AT8: 4.9 | AU8: 9.9 | AV8: 15.7 | AX8: 13.4 | AZ8: 0.6 | BB8: 8.5 | BC8: 23.5 | BD8: 20 | BE8: 4.7 | BF8: 1.4 | BG8: 2.3 | BH8: 2.4 | BK8: 20 | BL8: 6 | BN8: 688.8
B9: 1:00 | C9: 14 | D9: 13.3 | E9: 8.1 | F9: 16.4 | G9: 2 | I9: 9.8 | K9: 18.4 | M9: 19.3 | N9: 20.3 | O9: 9.5 | P9: 3.7 | Q9: 5.1 | R9: 19.8 | S9: 20.2 | T9: 20 | U9: 15 | V9: 19.3 | W9: 57.1 | X9: 33.9 | Y9: 28.3 | Z9: 58.4 | AB9: 1.8 | AC9: 1.2 | AD9: 21 | AE9: 7.7 | AF9: 20 | AG9: 20 | AH9: 19 | AI9: 2 | AK9: 9.7 | AL9: 15.1 | AM9: 3.5 | AN9: 18.7 | AQ9: 3.6 | AT9: 4.7 | AU9: 9.9 | AV9: 24.8 | AX9: 26.9 | AZ9: 0.6 | BB9: 9.6 | BC9: 26.8 | BD9: 20 | BE9: 4.7 | BF9: 1.4 | BG9: 2.3 | BH9: 2.4 | BK9: 19.8 | BL9: 6 | BN9: 715.1
B10: 1:30 | C10: 14.4 | D10: 15 | E10: 7.5 | F10: 16.4 | G10: 2 | I10: 9.8 | K10: 18.3 | M10: 19.1 | N10: 20.3 | O10: 9.5 | P10: 3.7 | Q10: 5.2 | R10: 19.8 | S10: 20.3 | T10: 20 | U10: 15 | V10: 21.1 | W10: 61.4 | X10: 33.2 | Y10: 28.9 | Z10: 51.2 | AB10: 1.4 | AC10: 2.3 | AD10: 21 | AE10: 7.6 | AF10: 20 | AG10: 20 | AH10: 19.5 | AI10: 1.4 | AK10: 9.5 | AL10: 14.2 | AM10: 3.5 | AN10: 18.7 | AQ10: 3.6 | AT10: 4.7 | AU10: 9.8 | AV10: 29.5 | AX10: 34.2 | AZ10: 0.6 | BB10: 8.2 | BC10: 24.5 | BD10: 20 | BE10: 4.7 | BF10: 1.4 | BG10: 2.3 | BH10: 2.4 | BK10: 19.8 | BL10: 6 | BN10: 722.9
B11: 2:00 | C11: 14 | D11: 14.1 | E11: 8 | F11: 16.1 | G11: 2 | I11: 11.3 | K11: 18.3 | M11: 19.2 | N11: 20.4 | O11: 9.5 | P11: 3.5 | Q11: 5.2 | R11: 20 | S11: 20.6 | T11: 20 | U11: 15 | V11: 22.5 | W11: 46 | X11: 31.7 | Y11: 23.4 | Z11: 44.9 | AB11: 1.4 | AC11: 3.2 | AD11: 21 | AE11: 7.6 | AF11: 20 | AG11: 20 | AH11: 19.8 | AK11: 10.3 | AL11: 12.5 | AM11: 3.5 | AN11: 18.7 | AQ11: 3.7 | AT11: 4.8 | AU11: 9.9 | AV11: 29.2 | AX11: 29.9 | AZ11: 0.6 | BB11: 7.3 | BC11: 23.7 | BD11: 20 | BE11: 4.7 | BF11: 1.4 | BG11: 2.3 | BH11: 2.4 | BK11: 20 | BL11: 6 | BN11: 689.6
B12: 2:30 | C12: 14 | D12: 15.1 | E12: 7.7 | F12: 14.9 | G12: 2 | I12: 10.7 | K12: 17.7 | M12: 18.7 | N12: 20.2 | O12: 9.5 | P12: 3.6 | Q12: 5.2 | R12: 20 | S12: 19.7 | T12: 20 | U12: 15 | V12: 17 | W12: 37.2 | X12: 28.7 | Y12: 24.7 | Z12: 50.5 | AB12: 2 | AC12: 1.2 | AD12: 21 | AE12: 7.5 | AF12: 20 | AG12: 20 | AH12: 19.8 | AK12: 9.9 | AL12: 13.4 | AM12: 3.5 | AN12: 18.7 | AQ12: 3.6 | AT12: 4.7 | AU12: 10 | AV12: 19.7 | AX12: 22.2 | AZ12: 0.6 | BB12: 5.4 | BC12: 17.2 | BD12: 20 | BE12: 4.7 | BF12: 1.4 | BG12: 2.3 | BH12: 2.4 | BK12: 20 | BL12: 6 | BN12: 649.3
B13: 3:00 | C13: 14.4 | D13: 16.2 | E13: 7.9 | F13: 4.9 | G13: 2 | I13: 10.1 | K13: 17.1 | M13: 19 | N13: 20.4 | O13: 9.5 | P13: 3.6 | Q13: 5.2 | R13: 19.8 | S13: 20.8 | T13: 20 | U13: 15.1 | V13: 15.6 | W13: 34.8 | X13: 34.7 | Y13: 31.4 | Z13: 63.4 | AB13: 1.8 | AC13: 1.6 | AD13: 21 | AE13: 7.4 | AF13: 20 | AG13: 20 | AH13: 19.8 | AK13: 7.9 | AL13: 15.1 | AM13: 3.5 | AN13: 18.7 | AQ13: 3.6 | AT13: 4.7 | AU13: 9.9 | AV13: 25.6 | AX13: 27.4 | AZ13: 0.6 | BB13: 6.9 | BC13: 18.3 | BD13: 20 | BE13: 4.7 | BF13: 1.4 | BG13: 2.3 | BH13: 2.4 | BK13: 19.8 | BL13: 6 | BN13: 676.3
B14: 3:30 | C14: 14.5 | D14: 16.3 | E14: 7.8 | F14: 5.4 | G14: 2 | I14: 9.8 | K14: 17.1 | M14: 18.8 | N14: 20.3 | O14: 9.5 | P14: 3.5 | Q14: 5.2 | R14: 20 | S14: 20.3 | T14: 20 | U14: 15 | V14: 15.6 | W14: 28.8 | X14: 39.3 | Y14: 25 | Z14: 53.9 | AB14: 1.1 | AC14: 1.8 | AD14: 21 | AE14: 7.3 | AF14: 20 | AG14: 20 | AH14: 20 | AK14: 10.5 | AL14: 14.5 | AM14: 3.5 | AN14: 18.7 | AQ14: 3.6 | AT14: 4.8 | AU14: 9.9 | AV14: 24.5 | AX14: 29.2 | AZ14: 0.6 | BB14: 7 | BC14: 20 | BD14: 20 | BE14: 4.7 | BF14: 1.4 | BG14: 2.3 | BH14: 2.4 | BK14: 20 | BL14: 6 | BN14: 662.9
B15: 4:00 | C15: 14.4 | D15: 14.6 | E15: 8 | F15: 5.5 | G15: 2 | I15: 9.3 | K15: 17.2 | M15: 18.6 | N15: 20.3 | O15: 9.5 | P15: 3.6 | Q15: 5.2 | R15: 19.8 | S15: 19.9 | T15: 20 | U15: 15 | V15: 20.2 | W15: 22.8 | X15: 48.4 | Y15: 15.9 | Z15: 38.6 | AB15: 1.9 | AC15: 1.7 | AD15: 21 | AE15: 7.2 | AF15: 20 | AG15: 20 | AH15: 20 | AK15: 10.8 | AL15: 15.4 | AM15: 3.6 | AN15: 18.7 | AQ15: 3.6 | AT15: 4.7 | AU15: 9.9 | AV15: 39.9 | AX15: 35.8 | AZ15: 0.6 | BB15: 8.2 | BC15: 23.1 | BD15: 20 | BE15: 4.7 | BF15: 1.4 | BG15: 2.3 | BH15: 2.4 | BK15: 19.9 | BL15: 6 | BN15: 671.6
B16: 4:30 | C16: 14.3 | D16: 16.3 | E16: 8 | F16: 5.3 | G16: 2 | I16: 10.2 | K16: 17.4 | M16: 18.9 | N16: 20.5 | O16: 9.5 | P16: 3.5 | Q16: 5.1 | R16: 19.9 | S16: 20.7 | T16: 20 | U16: 15 | V16: 21.1 | W16: 15.2 | X16: 56.4 | Y16: 14.5 | Z16: 34.1 | AB16: 0.9 | AC16: 1.2 | AD16: 21 | AE16: 7.1 | AF16: 20 | AG16: 20 | AH16: 20 | AK16: 9.8 | AL16: 13 | AM16: 3.5 | AN16: 18.7 | AQ16: 3.6 | AT16: 4.6 | AU16: 9.9 | AV16: 38.9 | AX16: 44 | AZ16: 0.6 | BB16: 10.4 | BC16: 27.3 | BD16: 20 | BE16: 4.7 | BF16: 1.4 | BG16: 2.3 | BH16: 2.4 | BK16: 20 | BL16: 6.1 | BN16: 679.3
B17: 5:00 | C17: 14.5 | D17: 14.6 | E17: 7.4 | F17: 5.1 | G17: 2 | I17: 9.5 | K17: 17.6 | M17: 18.7 | N17: 20.3 | O17: 9.4 | P17: 3.5 | Q17: 5.1 | R17: 20 | S17: 20 | T17: 20 | U17: 15.1 | V17: 22.6 | W17: 11.6 | X17: 59.3 | Y17: 9.1 | Z17: 25.1 | AB17: 1 | AC17: 0.7 | AD17: 21 | AE17: 7 | AF17: 20 | AG17: 20 | AH17: 20 | AK17: 12.3 | AL17: 14.2 | AM17: 3.5 | AN17: 18.7 | AQ17: 3.6 | AT17: 4.7 | AU17: 9.9 | AV17: 31 | AX17: 41.9 | AZ17: 0.6 | BB17: 12.6 | BC17: 28.4 | BD17: 20 | BE17: 4.6 | BF17: 1.3 | BG17: 2.3 | BH17: 2.4 | BK17: 20 | BL17: 6 | BN17: 658.2
B18: 5:30 | C18: 14 | D18: 12.6 | E18: 7.5 | F18: 5.2 | G18: 2 | I18: 10 | K18: 17.6 | M18: 18.9 | N18: 20.4 | O18: 9.4 | P18: 3.6 | Q18: 5.1 | R18: 20 | S18: 20.2 | T18: 20 | U18: 15 | V18: 18.3 | W18: 18 | X18: 58.5 | Y18: 5.4 | Z18: 12.2 | AB18: 0.8 | AD18: 21 | AE18: 6.9 | AF18: 20 | AG18: 20 | AH18: 20 | AK18: 12.6 | AL18: 16.9 | AM18: 3.5 | AN18: 18.8 | AQ18: 3.6 | AS18: 0.1 | AT18: 4.7 | AU18: 9.9 | AV18: 26.4 | AX18: 29.7 | AY18: 0.2 | AZ18: 0.6 | BB18: 15.2 | BC18: 27.4 | BD18: 20 | BE18: 3.8 | BF18: 2.3 | BG18: 2.3 | BH18: 2.4 | BK18: 20 | BL18: 6.1 | BM18: 0.7 | BN18: 629.8
B19: 6:00 | C19: 12.8 | D19: 14.9 | E19: 7.6 | F19: 5.2 | G19: 2 | I19: 9.8 | K19: 17.1 | M19: 19 | N19: 20.3 | O19: 9.5 | P19: 3.5 | Q19: 5.1 | R19: 19.9 | S19: 19.9 | T19: 20 | U19: 15 | V19: 19.2 | W19: 25.6 | X19: 46.3 | Y19: 3 | Z19: 6.1 | AA19: 2.9 | AC19: 0.1 | AD19: 21 | AE19: 6.8 | AF19: 20 | AG19: 20 | AH19: 20 | AJ19: 6.7 | AK19: 7.8 | AL19: 14.2 | AM19: 3.5 | AN19: 18.8 | AQ19: 3.6 | AR19: 0.5 | AS19: 0.6 | AT19: 4.7 | AU19: 9.9 | AV19: 20.7 | AW19: 9.6 | AX19: 20.9 | AY19: 8.1 | AZ19: 0.6 | BA19: 0.6 | BB19: 9.8 | BC19: 18.5 | BD19: 20 | BE19: 3.7 | BF19: 2.4 | BG19: 2.3 | BH19: 2.4 | BI19: 0.5 | BK19: 19.8 | BL19: 6 | BM19: 3.1 | BN19: 611.9
B20: 6:30 | C20: 13.9 | D20: 15.5 | E20: 8 | F20: 5.2 | G20: 2 | I20: 9.4 | K20: 17.1 | M20: 18.9 | N20: 20.3 | O20: 9.5 | P20: 3.5 | Q20: 5.1 | R20: 19.8 | S20: 20 | T20: 20 | U20: 15 | V20: 24.5 | W20: 18.1 | X20: 45.8 | Y20: 2.5 | Z20: 5 | AA20: 12.3 | AC20: 0.1 | AD20: 21 | AE20: 6.7 | AF20: 20 | AG20: 20 | AH20: 20 | AI20: 3.3 | AJ20: 15 | AK20: 5.5 | AL20: 11.7 | AM20: 3.4 | AN20: 18.7 | AQ20: 3.6 | AR20: 1.1 | AS20: 1.4 | AT20: 4.8 | AU20: 10 | AV20: 17 | AW20: 36.7 | AX20: 18.1 | AY20: 35 | AZ20: 0.6 | BA20: 1.1 | BB20: 12.3 | BC20: 24.2 | BD20: 20 | BE20: 3.7 | BF20: 2.4 | BG20: 2.3 | BH20: 2.4 | BI20: 1.9 | BK20: 19.8 | BL20: 6.1 | BM20: 4.8 | BN20: 686.1
B21: 7:00 | C21: 14 | D21: 13.5 | E21: 7.4 | F21: 5 | G21: 2 | I21: 9.7 | K21: 16.7 | M21: 19.1 | N21: 20.3 | O21: 9.5 | P21: 3.5 | Q21: 5.2 | R21: 19.8 | S21: 19.8 | T21: 20 | U21: 15 | V21: 21.9 | W21: 14.5 | X21: 44.2 | Y21: 2.7 | Z21: 5.6 | AA21: 22 | AB21: 0.3 | AC21: 0.3 | AD21: 21 | AE21: 6.6 | AF21: 20 | AG21: 20 | AH21: 20 | AI21: 3.7 | AJ21: 12.2 | AK21: 10.9 | AL21: 15.5 | AM21: 3.4 | AN21: 18.7 | AQ21: 3.6 | AR21: 3.3 | AS21: 2.5 | AT21: 4.6 | AU21: 10 | AV21: 13.8 | AW21: 88.4 | AX21: 13.4 | AY21: 79 | AZ21: 0.6 | BA21: 2.2 | BB21: 6.2 | BC21: 21.2 | BD21: 20 | BE21: 3.7 | BF21: 2.4 | BG21: 2.3 | BH21: 2.4 | BI21: 1.5 | BK21: 19.9 | BL21: 6.1 | BM21: 7 | BN21: 778.1
B22: 7:30 | C22: 13.8 | D22: 14.9 | E22: 8.6 | F22: 5 | G22: 2 | I22: 9.6 | J22: 0.1 | K22: 16.7 | M22: 19.8 | N22: 20.3 | O22: 9.5 | P22: 3.5 | Q22: 5.2 | R22: 20 | S22: 20.2 | T22: 20 | U22: 15 | V22: 20.9 | W22: 14.9 | X22: 43 | Y22: 2.9 | Z22: 6.5 | AA22: 36.5 | AB22: 0.1 | AC22: 0.1 | AD22: 21 | AE22: 6.6 | AF22: 20 | AG22: 20 | AH22: 20 | AI22: 4.5 | AJ22: 35.2 | AK22: 11.4 | AL22: 15.4 | AM22: 3.4 | AN22: 18.7 | AQ22: 3.6 | AR22: 5.5 | AS22: 7.2 | AT22: 4.7 | AU22: 10 | AV22: 6.2 | AW22: 122.2 | AX22: 6.8 | AY22: 96.9 | AZ22: 0.6 | BA22: 12.8 | BB22: 8.3 | BC22: 18.5 | BD22: 20 | BE22: 3.7 | BF22: 2.4 | BG22: 2.3 | BH22: 2.4 | BI22: 5.2 | BK22: 20 | BL22: 6 | BM22: 9.7 | BN22: 880.3
B23: 8:00 | C23: 13.2 | D23: 14.1 | E23: 8.1 | F23: 7 | G23: 2 | I23: 10.8 | J23: 0.1 | K23: 16.7 | M23: 20 | N23: 20.4 | O23: 9.4 | P23: 3.5 | Q23: 5.2 | R23: 20 | S23: 20.3 | T23: 20 | U23: 15 | V23: 19.5 | W23: 10.9 | X23: 45.7 | Y23: 4.7 | Z23: 12.1 | AA23: 14.4 | AB23: 0.5 | AC23: 0.7 | AD23: 21 | AE23: 6.4 | AF23: 20 | AG23: 20 | AH23: 20 | AI23: 4.4 | AJ23: 68.1 | AK23: 9.9 | AL23: 13.7 | AM23: 3.4 | AN23: 18.7 | AP23: 0.1 | AQ23: 3.6 | AR23: 8 | AS23: 14.7 | AT23: 4.8 | AU23: 9.9 | AV23: 4.9 | AW23: 130.4 | AY23: 104 | AZ23: 0.6 | BA23: 17.3 | BB23: 10.3 | BC23: 24.2 | BD23: 19.9 | BE23: 3.7 | BF23: 2.4 | BG23: 2.3 | BH23: 2.4 | BI23: 8 | BK23: 20 | BL23: 6 | BM23: 17.8 | BN23: 935.2
B24: 8:30 | C24: 14 | D24: 14 | E24: 7.4 | F24: 19.2 | G24: 2 | I24: 10.5 | J24: 0.6 | K24: 16.4 | M24: 20.1 | N24: 20.4 | O24: 9.4 | P24: 3.6 | Q24: 5.1 | R24: 20 | S24: 20.7 | T24: 20 | U24: 15.1 | V24: 19.5 | W24: 9 | X24: 43.5 | Y24: 7.6 | Z24: 16.5 | AA24: 36.3 | AB24: 0.5 | AC24: 0.7 | AD24: 21 | AE24: 6.4 | AF24: 20 | AG24: 20 | AH24: 20 | AI24: 4.3 | AJ24: 71.4 | AK24: 12.5 | AL24: 15.8 | AM24: 3.4 | AN24: 18.7 | AP24: 0.1 | AQ24: 3.6 | AR24: 10.2 | AS24: 15.1 | AT24: 4.9 | AU24: 9.9 | AV24: 8.4 | AW24: 132.1 | AX24: 0.4 | AY24: 105.2 | AZ24: 0.6 | BA24: 18.1 | BB24: 13 | BC24: 33.7 | BD24: 20 | BE24: 3.7 | BF24: 2.4 | BG24: 2.3 | BH24: 2.4 | BI24: 10.2 | BK24: 20 | BL24: 6 | BM24: 19.1 | BN24: 1007
B25: 9:00 | C25: 13.9 | D25: 13 | E25: 8.9 | F25: 19.6 | G25: 2 | I25: 5.9 | J25: 0.8 | K25: 16.4 | M25: 20.2 | N25: 20.4 | O25: 9.4 | P25: 3.6 | Q25: 5.2 | R25: 20 | S25: 20.5 | T25: 20 | U25: 15 | V25: 16 | W25: 8 | X25: 40.9 | Y25: 18.8 | Z25: 20.8 | AA25: 38 | AB25: 1.6 | AC25: 2.5 | AD25: 21 | AE25: 6.3 | AF25: 20 | AG25: 20 | AH25: 20 | AI25: 4.3 | AJ25: 73.5 | AK25: 14 | AL25: 16.5 | AM25: 3.3 | AN25: 18.7 | AP25: 0.1 | AQ25: 3.6 | AR25: 12.3 | AS25: 14.8 | AT25: 5.4 | AU25: 10 | AV25: 5.4 | AW25: 136.3 | AY25: 108.8 | AZ25: 0.6 | BA25: 18.3 | BB25: 10.7 | BC25: 24.5 | BD25: 20 | BE25: 3.7 | BF25: 2.4 | BG25: 2.3 | BH25: 2.4 | BI25: 12.2 | BK25: 20 | BL25: 6.1 | BM25: 19.2 | BN25: 1018.1
B26: 9:30 | C26: 13.9 | D26: 13 | E26: 8.8 | F26: 20.2 | G26: 2 | I26: 4.8 | J26: 0.9 | K26: 16.4 | M26: 20.1 | N26: 20.3 | O26: 7.3 | P26: 3.5 | Q26: 5.2 | R26: 19.8 | S26: 20.2 | T26: 20 | U26: 15.1 | V26: 10.9 | W26: 8.6 | X26: 52.9 | Y26: 21.2 | Z26: 25.7 | AA26: 37.2 | AB26: 2.1 | AC26: 2.1 | AD26: 21 | AE26: 6.2 | AF26: 20 | AG26: 20 | AH26: 20 | AI26: 5.7 | AJ26: 75.1 | AK26: 13 | AL26: 15.3 | AM26: 3.4 | AN26: 18.7 | AP26: 0.3 | AQ26: 3.6 | AR26: 14 | AS26: 15.5 | AT26: 5.2 | AU26: 10 | AV26: 6.2 | AW26: 136.5 | AY26: 109.2 | AZ26: 0.6 | BA26: 18.8 | BB26: 12.6 | BC26: 22.9 | BD26: 20 | BE26: 3.7 | BF26: 2.4 | BG26: 2.3 | BH26: 2.4 | BI26: 14.1 | BK26: 20 | BL26: 6 | BM26: 19.4 | BN26: 1036.3
B27: 10:00 | C27: 13.9 | D27: 13 | E27: 6.9 | F27: 20.2 | G27: 2 | I27: 4.5 | J27: 1 | K27: 11.2 | M27: 20.1 | N27: 20.3 | O27: 6.9 | P27: 3.5 | Q27: 5.2 | R27: 20 | S27: 20.2 | T27: 20 | U27: 15.1 | V27: 8.5 | W27: 18 | X27: 75.5 | Y27: 18.2 | Z27: 24.7 | AA27: 39.7 | AB27: 1.2 | AC27: 1.8 | AD27: 21 | AE27: 6.2 | AF27: 20 | AG27: 20 | AH27: 20 | AI27: 6 | AJ27: 76.3 | AK27: 14.1 | AL27: 16.1 | AM27: 3.4 | AN27: 18.7 | AP27: 0.3 | AQ27: 3.6 | AR27: 15.4 | AS27: 15.5 | AT27: 5.2 | AU27: 10.1 | AV27: 7.7 | AW27: 137.8 | AX27: 0.8 | AY27: 107.9 | AZ27: 0.6 | BA27: 18.9 | BB27: 14.4 | BC27: 28.8 | BD27: 19.9 | BE27: 3.7 | BF27: 2.4 | BG27: 2.3 | BH27: 2.4 | BI27: 15.6 | BK27: 20 | BL27: 6 | BM27: 19.5 | BN27: 1072.2
B28: 10:30 | C28: 14 | D28: 13 | E28: 8.6 | F28: 20.2 | G28: 2 | I28: 4.4 | J28: 1.2 | K28: 13.4 | M28: 20.1 | N28: 20.3 | O28: 6.9 | P28: 3.5 | Q28: 5.2 | R28: 20 | S28: 19.9 | T28: 20 | U28: 15 | V28: 9.2 | W28: 33.8 | X28: 74.3 | Y28: 26 | Z28: 39.2 | AA28: 39.5 | AB28: 3 | AC28: 1.7 | AD28: 21 | AE28: 6.2 | AF28: 20 | AG28: 20 | AH28: 20 | AI28: 6 | AJ28: 78.5 | AK28: 11.6 | AL28: 14.1 | AM28: 3.4 | AP28: 0.4 | AQ28: 3.6 | AR28: 16.7 | AS28: 15.3 | AT28: 5.2 | AU28: 9.9 | AV28: 8.4 | AW28: 134.5 | AX28: 0.3 | AY28: 107 | AZ28: 0.6 | BA28: 18.7 | BB28: 17.5 | BC28: 42.1 | BD28: 20 | BE28: 3.7 | BF28: 2.4 | BG28: 2.3 | BH28: 2.4 | BI28: 16.9 | BK28: 19.9 | BL28: 6 | BM28: 19.6 | BN28: 1108.6
B29: 11:00 | C29: 14 | D29: 13 | E29: 9.4 | F29: 20.3 | G29: 2 | I29: 4.4 | J29: 1.2 | K29: 16 | M29: 20.2 | N29: 20.4 | O29: 6.9 | P29: 3.5 | Q29: 5.2 | R29: 20 | S29: 20.6 | T29: 20 | U29: 15 | V29: 6.6 | W29: 43.9 | X29: 76.9 | Y29: 26.8 | Z29: 37.4 | AA29: 38.9 | AB29: 2.4 | AC29: 2.1 | AD29: 21 | AE29: 6.1 | AF29: 20 | AG29: 20 | AH29: 20 | AI29: 6.3 | AJ29: 80.5 | AK29: 9.2 | AL29: 11.3 | AM29: 3.4 | AN29: 8.9 | AP29: 0.4 | AQ29: 3.6 | AR29: 17.9 | AS29: 15 | AT29: 5.4 | AU29: 9.9 | AV29: 13.4 | AW29: 141 | AX29: 3.2 | AY29: 112.5 | AZ29: 0.6 | BA29: 18.2 | BB29: 16.1 | BC29: 55.4 | BD29: 20 | BE29: 3.7 | BF29: 2.4 | BG29: 2.3 | BH29: 2.4 | BI29: 17.8 | BK29: 19.9 | BL29: 6 | BM29: 19.8 | BN29: 1160.7
B30: 11:30 | C30: 13.6 | D30: 13 | E30: 7.2 | F30: 20.3 | G30: 2 | I30: 4.4 | J30: 1.3 | K30: 16.1 | M30: 20.2 | N30: 20.4 | O30: 6.9 | P30: 3.6 | Q30: 5.2 | R30: 20 | S30: 20.4 | T30: 20 | U30: 15.1 | V30: 3.5 | W30: 62.4 | X30: 74.6 | Y30: 27 | Z30: 42.2 | AA30: 40.4 | AB30: 2.8 | AC30: 3.5 | AD30: 21 | AE30: 6 | AF30: 20 | AG30: 20 | AH30: 20 | AI30: 6.3 | AJ30: 80.5 | AK30: 13.6 | AL30: 11.8 | AM30: 3.4 | AN30: 10.7 | AP30: 0.4 | AQ30: 3.5 | AR30: 18.6 | AS30: 15.3 | AT30: 5.2 | AU30: 9.9 | AV30: 31.8 | AW30: 141.5 | AX30: 13.1 | AY30: 112.9 | AZ30: 0.6 | BA30: 18.6 | BB30: 19.1 | BC30: 53 | BD30: 20 | BE30: 3.7 | BF30: 2.3 | BG30: 2.3 | BH30: 2.4 | BI30: 18.6 | BK30: 20 | BL30: 6 | BM30: 19.8 | BN30: 1218
B31: 12:00 | C31: 13 | D31: 13 | E31: 8.1 | F31: 20.3 | G31: 2 | I31: 4.6 | J31: 1.3 | K31: 16.1 | M31: 20.1 | N31: 20.3 | O31: 6.9 | P31: 3.5 | Q31: 5.2 | R31: 20 | S31: 20.2 | T31: 20 | U31: 15.1 | V31: 4.5 | W31: 61.2 | X31: 64.8 | Y31: 32.4 | Z31: 40 | AA31: 40.1 | AB31: 3.6 | AC31: 4.2 | AD31: 21 | AE31: 6 | AF31: 20 | AG31: 20 | AH31: 20 | AI31: 6.3 | AJ31: 80.5 | AK31: 13.8 | AL31: 15.6 | AM31: 3.4 | AN31: 18.7 | AP31: 0.4 | AQ31: 3.5 | AR31: 18.9 | AS31: 15.7 | AT31: 5.5 | AU31: 10 | AV31: 38 | AW31: 141.6 | AX31: 24.3 | AY31: 113.1 | AZ31: 0.6 | BA31: 18.9 | BB31: 16 | BC31: 61.1 | BD31: 20 | BE31: 3.7 | BF31: 2.3 | BG31: 2.3 | BH31: 2.4 | BI31: 19 | BK31: 20 | BL31: 6 | BM31: 20 | BN31: 1249.1
B32: 12:30 | C32: 14.5 | D32: 13.5 | E32: 6.4 | F32: 20.3 | G32: 2 | I32: 4.5 | J32: 1.3 | K32: 16 | M32: 20.2 | N32: 20.3 | O32: 6.8 | P32: 3.5 | Q32: 5.2 | R32: 20 | S32: 20.1 | T32: 20 | U32: 15 | V32: 9.1 | W32: 54.9 | X32: 66.7 | Y32: 38 | Z32: 38.5 | AA32: 40.1 | AB32: 2.6 | AC32: 4.3 | AD32: 21 | AE32: 5.9 | AF32: 20 | AG32: 20 | AH32: 20 | AI32: 6.2 | AJ32: 80.5 | AK32: 15.9 | AL32: 15.8 | AM32: 3.4 | AN32: 18.8 | AP32: 0.4 | AQ32: 3.6 | AR32: 19 | AS32: 15.6 | AT32: 5.3 | AU32: 9.9 | AV32: 57.4 | AW32: 140.8 | AX32: 47 | AY32: 112.5 | AZ32: 0.6 | BA32: 18.9 | BB32: 15.7 | BC32: 46.9 | BD32: 20 | BE32: 3.7 | BF32: 2.3 | BG32: 2.3 | BH32: 2.4 | BI32: 19 | BK32: 20 | BL32: 6 | BM32: 18.8 | BN32: 1279.4
B33: 13:00 | C33: 12.2 | D33: 15.7 | E33: 7.5 | F33: 20.3 | G33: 2 | I33: 4.4 | J33: 1.3 | K33: 16 | M33: 20.1 | N33: 20.3 | O33: 9.1 | P33: 3.5 | Q33: 5.2 | R33: 20 | S33: 19.9 | T33: 20 | U33: 15 | V33: 11.4 | W33: 50.7 | X33: 72.4 | Y33: 35.3 | Z33: 52.1 | AA33: 39.2 | AB33: 6 | AC33: 1.7 | AD33: 21 | AE33: 5.9 | AF33: 20 | AG33: 20 | AH33: 20 | AI33: 6.2 | AJ33: 80.4 | AK33: 13.3 | AL33: 15.7 | AM33: 3.4 | AN33: 18.8 | AP33: 0.5 | AQ33: 3.6 | AR33: 19.2 | AS33: 15.5 | AT33: 5.2 | AU33: 9.9 | AV33: 61.9 | AW33: 138.8 | AX33: 54.7 | AY33: 111.5 | AZ33: 0.6 | BA33: 19.3 | BB33: 15.7 | BC33: 55.9 | BD33: 19.9 | BE33: 3.7 | BF33: 2.3 | BG33: 2.3 | BH33: 2.4 | BI33: 15.5 | BK33: 20 | BL33: 6 | BM33: 19.2 | BN33: 1309.6
B34: 13:30 | C34: 13.7 | D34: 16.9 | E34: 6.7 | F34: 15 | G34: 2 | I34: 3.6 | J34: 1 | K34: 15.8 | M34: 20.1 | N34: 20.4 | O34: 9.1 | P34: 3.5 | Q34: 5.1 | R34: 19.8 | S34: 20.5 | T34: 20 | U34: 15 | V34: 10.5 | W34: 59.2 | X34: 80.2 | Y34: 39.3 | Z34: 48.7 | AA34: 8.4 | AB34: 3.2 | AC34: 2.6 | AD34: 21 | AE34: 5.8 | AF34: 20 | AG34: 20 | AH34: 20 | AI34: 6.2 | AJ34: 80.5 | AK34: 13.5 | AL34: 14.4 | AM34: 3.4 | AN34: 18.8 | AP34: 0.4 | AQ34: 3.6 | AR34: 18 | AS34: 11.4 | AT34: 5.2 | AU34: 9.9 | AV34: 73.2 | AW34: 140.3 | AX34: 58.1 | AY34: 112.5 | AZ34: 0.6 | BA34: 14.6 | BB34: 17.1 | BC34: 56.1 | BD34: 20 | BE34: 3.6 | BF34: 2.2 | BG34: 2.3 | BH34: 2.4 | BI34: 15.9 | BK34: 19.8 | BL34: 6 | BM34: 19.9 | BN34: 1297
B35: 14:00 | C35: 14 | D35: 15.6 | E35: 7.1 | F35: 11.1 | G35: 2 | I35: 4.1 | J35: 1.3 | K35: 15.6 | M35: 20.2 | N35: 20.3 | O35: 9.1 | P35: 3.6 | Q35: 5.1 | R35: 19.9 | S35: 20.1 | T35: 20 | U35: 15 | V35: 10.8 | W35: 60.7 | X35: 83.7 | Y35: 48 | Z35: 54.3 | AA35: 5 | AB35: 6.2 | AC35: 6.3 | AD35: 21 | AE35: 5.8 | AF35: 20 | AG35: 20 | AH35: 20 | AI35: 6.4 | AJ35: 61.1 | AK35: 16.8 | AL35: 17.8 | AM35: 3.4 | AN35: 18.8 | AP35: 0.2 | AQ35: 3.6 | AR35: 10.4 | AS35: 14.6 | AT35: 5.2 | AU35: 9.9 | AV35: 96.2 | AW35: 55 | AX35: 86.9 | AY35: 48.1 | AZ35: 0.6 | BA35: 17.6 | BB35: 20.2 | BC35: 59.6 | BD35: 20 | BE35: 3.6 | BF35: 2.2 | BG35: 2.3 | BH35: 2.4 | BI35: 7.7 | BK35: 20 | BL35: 6 | BM35: 19.7 | BN35: 1202.2
B36: 14:30 | C36: 13.9 | D36: 16.3 | E36: 6.8 | F36: 10.8 | G36: 2 | I36: 7.4 | J36: 0.3 | K36: 15.4 | M36: 20.2 | N36: 20.4 | O36: 9 | P36: 3.5 | Q36: 5.2 | R36: 20 | S36: 20.3 | T36: 20 | U36: 14.5 | V36: 11.6 | W36: 64.9 | X36: 86 | Y36: 55.8 | Z36: 56.3 | AA36: 4.2 | AB36: 5.8 | AC36: 8 | AD36: 21 | AE36: 5.8 | AF36: 20 | AG36: 20 | AH36: 20 | AI36: 6.4 | AJ36: 43.8 | AK36: 15.1 | AL36: 16.2 | AM36: 3.4 | AN36: 18.8 | AP36: 0.1 | AQ36: 3.6 | AR36: 8 | AS36: 9.8 | AT36: 5.5 | AU36: 9.9 | AV36: 109.2 | AW36: 28.7 | AX36: 103.7 | AY36: 25.5 | AZ36: 0.6 | BA36: 12.3 | BB36: 20.1 | BC36: 57.4 | BD36: 20 | BE36: 3.6 | BF36: 2.2 | BG36: 2.2 | BH36: 2.4 | BI36: 10.3 | BK36: 20 | BL36: 6 | BM36: 16.8 | BN36: 1167
B37: 15:00 | C37: 14 | D37: 16.3 | E37: 6.4 | F37: 10.8 | G37: 2 | I37: 9.9 | J37: 0.1 | K37: 15.2 | M37: 20.1 | N37: 20.3 | O37: 9 | P37: 3.5 | Q37: 5.2 | R37: 20 | S37: 20.4 | T37: 20 | U37: 14.5 | V37: 12.1 | W37: 73.2 | X37: 76.8 | Y37: 60.9 | Z37: 63.5 | AA37: 4.3 | AB37: 8.6 | AC37: 4.6 | AD37: 21 | AE37: 5.8 | AF37: 20 | AG37: 20 | AH37: 20 | AI37: 6.5 | AJ37: 62.8 | AK37: 14.9 | AL37: 15.5 | AM37: 3.4 | AN37: 18.8 | AP37: 0.1 | AQ37: 3.6 | AR37: 6.7 | AS37: 5.4 | AT37: 5.3 | AU37: 9.8 | AV37: 115.6 | AW37: 19.1 | AX37: 106.9 | AY37: 17.9 | AZ37: 0.6 | BA37: 6.1 | BB37: 17.9 | BC37: 48.9 | BD37: 19.8 | BE37: 3.6 | BF37: 2.2 | BG37: 2.2 | BH37: 2.4 | BI37: 10.6 | BK37: 20 | BL37: 6 | BM37: 8 | BN37: 1159.1
B38: 15:30 | C38: 13.9 | D38: 16.3 | E38: 5.7 | F38: 10.1 | G38: 2 | I38: 9.2 | J38: 0.9 | K38: 15.2 | M38: 20.2 | N38: 20.4 | O38: 8.9 | P38: 3.5 | Q38: 5.2 | R38: 20 | S38: 20.2 | T38: 20 | U38: 14.6 | V38: 13.5 | W38: 74.8 | X38: 61.5 | Y38: 55.7 | Z38: 74.9 | AA38: 5.4 | AB38: 4.8 | AC38: 5.3 | AD38: 21 | AE38: 5.7 | AF38: 20 | AG38: 20 | AH38: 20 | AI38: 6.5 | AJ38: 28.2 | AK38: 14.7 | AL38: 15.7 | AM38: 3.4 | AN38: 18.8 | AQ38: 3.7 | AR38: 5.7 | AS38: 3.4 | AT38: 5.3 | AU38: 9.9 | AV38: 93 | AW38: 22.1 | AX38: 93.6 | AY38: 21.1 | AZ38: 0.6 | BA38: 3.6 | BB38: 16.4 | BC38: 42.9 | BD38: 20 | BE38: 3.6 | BF38: 2.2 | BG38: 2.2 | BH38: 2.4 | BI38: 5.3 | BK38: 20 | BL38: 6 | BM38: 5.3 | BN38: 1064.5
B39: 16:00 | C39: 14 | D39: 16 | E39: 7 | F39: 10.6 | G39: 2 | I39: 9 | J39: 0.4 | K39: 15.3 | M39: 20.2 | N39: 20.3 | O39: 8.9 | P39: 3.5 | Q39: 5.2 | R39: 20 | S39: 20.2 | T39: 20 | U39: 14.6 | V39: 16.7 | W39: 75.9 | X39: 60.1 | Y39: 59.4 | Z39: 71.3 | AA39: 6.2 | AB39: 6.3 | AC39: 6.1 | AD39: 21 | AE39: 5.6 | AF39: 20 | AG39: 20 | AH39: 20 | AI39: 6.3 | AJ39: 27.3 | AK39: 14.4 | AL39: 16 | AM39: 3.4 | AN39: 18.8 | AQ39: 3.6 | AR39: 4.4 | AS39: 2.3 | AT39: 5.3 | AU39: 9.9 | AV39: 106.7 | AW39: 28.3 | AX39: 109.5 | AY39: 26.5 | AZ39: 0.6 | BA39: 2.4 | BB39: 12.5 | BC39: 38.2 | BD39: 20 | BE39: 3.6 | BF39: 2.2 | BG39: 2.2 | BH39: 2.4 | BI39: 3.3 | BK39: 20 | BL39: 6 | BM39: 4.5 | BN39: 1096.4
B40: 16:30 | C40: 14 | D40: 15.6 | E40: 6.5 | F40: 10.3 | G40: 2 | I40: 9 | J40: 0.6 | K40: 15.3 | M40: 20.1 | N40: 20.3 | O40: 8.8 | P40: 3.3 | Q40: 5.2 | R40: 19.9 | S40: 19.9 | T40: 20 | U40: 14.5 | V40: 18.2 | W40: 77.1 | X40: 55.3 | Y40: 51.7 | Z40: 63.3 | AA40: 6.1 | AB40: 6.2 | AC40: 8.2 | AD40: 21 | AE40: 5.6 | AF40: 20 | AG40: 20 | AH40: 20 | AI40: 6.6 | AJ40: 27.1 | AK40: 16.4 | AL40: 14.9 | AM40: 3.4 | AN40: 18.8 | AQ40: 3.6 | AR40: 3.8 | AS40: 1.4 | AT40: 5.3 | AU40: 10.1 | AV40: 100.2 | AW40: 59.8 | AX40: 112.9 | AY40: 37.7 | AZ40: 0.6 | BA40: 1.7 | BB40: 11.5 | BC40: 36.9 | BD40: 19.8 | BE40: 3.6 | BF40: 2.2 | BG40: 2.2 | BH40: 2.4 | BI40: 3.4 | BK40: 20 | BL40: 6 | BM40: 2.8 | BN40: 1113.1
B41: 17:00 | C41: 13.9 | D41: 16.3 | E41: 8.3 | F41: 10.1 | G41: 2 | I41: 9.5 | J41: 0.2 | K41: 15.5 | M41: 20.1 | N41: 20.2 | O41: 8.8 | P41: 3.1 | Q41: 5.2 | R41: 19.8 | S41: 19.7 | T41: 20 | U41: 14.6 | V41: 20 | W41: 80.3 | X41: 36.5 | Y41: 43.8 | Z41: 57.2 | AA41: 10.2 | AB41: 4.2 | AC41: 5.8 | AD41: 21 | AE41: 5.6 | AF41: 20 | AG41: 20 | AH41: 20 | AI41: 6.8 | AJ41: 28.2 | AK41: 13.4 | AL41: 14.8 | AM41: 3.4 | AN41: 18.8 | AQ41: 3.6 | AR41: 2.7 | AS41: 1.3 | AT41: 5.3 | AU41: 9.9 | AV41: 103.1 | AW41: 76 | AX41: 118.9 | AY41: 74.3 | AZ41: 0.6 | BA41: 1 | BB41: 9.1 | BC41: 27.3 | BD41: 20 | BE41: 3.6 | BF41: 2.2 | BG41: 2.2 | BH41: 2.4 | BI41: 3.5 | BK41: 19.8 | BL41: 6 | BM41: 1.5 | BN41: 1131.6
B42: 17:30 | C42: 13.5 | D42: 15.8 | E42: 7.8 | F42: 9.9 | G42: 2 | I42: 10.6 | J42: 0.3 | K42: 15.4 | M42: 20.1 | N42: 20.3 | O42: 8.8 | P42: 3.1 | Q42: 5.2 | R42: 19.8 | S42: 20.3 | T42: 20 | U42: 14.6 | V42: 20.9 | W42: 80 | X42: 34.8 | Y42: 37.2 | Z42: 58.1 | AA42: 4.2 | AB42: 4.7 | AC42: 2.9 | AD42: 21 | AE42: 5.6 | AF42: 20 | AG42: 20 | AH42: 20 | AI42: 6 | AJ42: 13.5 | AK42: 9.6 | AL42: 9.8 | AM42: 3.4 | AN42: 18.8 | AQ42: 3.6 | AR42: 1.8 | AS42: 0.9 | AT42: 5.4 | AU42: 9.9 | AV42: 101.7 | AW42: 24.3 | AX42: 110.4 | AY42: 19.1 | AZ42: 0.6 | BA42: 0.8 | BB42: 5.8 | BC42: 24.1 | BD42: 20 | BE42: 3.7 | BF42: 2.3 | BG42: 2.3 | BH42: 2.4 | BI42: 3.3 | BK42: 19.8 | BL42: 6 | BM42: 0.6 | BN42: 966.8
B43: 18:00 | C43: 13.9 | D43: 12.7 | E43: 8.4 | F43: 10.7 | G43: 2 | I43: 11 | K43: 15.2 | M43: 20.1 | N43: 20.3 | O43: 8.8 | P43: 3.6 | Q43: 5.2 | R43: 20 | S43: 20.1 | T43: 20 | U43: 14.6 | V43: 20.5 | W43: 80 | X43: 36.6 | Y43: 27.3 | Z43: 38.8 | AA43: 1.5 | AB43: 3.2 | AC43: 2.5 | AD43: 21 | AE43: 5.5 | AF43: 20 | AG43: 20 | AH43: 20 | AI43: 5.7 | AJ43: 3.7 | AK43: 6.5 | AL43: 7.6 | AM43: 3.4 | AN43: 18.8 | AQ43: 3.6 | AR43: 0.8 | AS43: 0.2 | AT43: 5.5 | AU43: 9.9 | AV43: 104.8 | AW43: 3.1 | AX43: 116 | AY43: 3.2 | AZ43: 0.6 | BA43: 0.1 | BB43: 6.4 | BC43: 31.7 | BD43: 20 | BE43: 3.7 | BF43: 2.3 | BG43: 2.3 | BH43: 2.4 | BI43: 1 | BK43: 20 | BL43: 6 | BN43: 892.8
B44: 18:30 | C44: 13.9 | D44: 12 | E44: 8.5 | F44: 11 | G44: 2 | I44: 11.6 | K44: 14.8 | M44: 20.1 | N44: 20.3 | O44: 8.9 | P44: 3.6 | Q44: 5.2 | R44: 20 | S44: 20.1 | T44: 20 | U44: 14.6 | V44: 20.5 | W44: 80.3 | X44: 39.3 | Y44: 25.5 | Z44: 35.2 | AB44: 2.4 | AC44: 2.2 | AD44: 21 | AE44: 5.5 | AF44: 20 | AG44: 20 | AH44: 20 | AI44: 6.3 | AK44: 4.1 | AL44: 4.3 | AM44: 3.3 | AN44: 18.8 | AQ44: 3.6 | AT44: 5.4 | AU44: 9.8 | AV44: 94.7 | AX44: 106.3 | AZ44: 0.6 | BB44: 8.2 | BC44: 33.5 | BD44: 20 | BE44: 3.7 | BF44: 2.3 | BG44: 2.3 | BH44: 2.4 | BK44: 20 | BL44: 6 | BN44: 854.1
B45: 19:00 | C45: 13.3 | D45: 12.1 | E45: 7.5 | F45: 14.4 | G45: 2 | I45: 11.4 | K45: 14.6 | M45: 20.2 | N45: 20.3 | O45: 9 | P45: 3.6 | Q45: 5.1 | R45: 20 | S45: 20.1 | T45: 20 | U45: 14.5 | V45: 17.2 | W45: 79.7 | X45: 36.2 | Y45: 20.9 | Z45: 36.7 | AB45: 1.8 | AC45: 2 | AD45: 21 | AE45: 5.5 | AF45: 20 | AG45: 20 | AH45: 20 | AI45: 6.2 | AL45: 0.4 | AM45: 3.4 | AN45: 18.8 | AQ45: 3.7 | AT45: 5.2 | AU45: 9.9 | AV45: 92.6 | AX45: 111.5 | AZ45: 0.6 | BB45: 8.8 | BC45: 30.3 | BD45: 20 | BE45: 4.4 | BF45: 3 | BG45: 2.3 | BH45: 2.4 | BK45: 20 | BL45: 6 | BN45: 838.6
B46: 19:30 | C46: 13.9 | D46: 12.2 | E46: 8.3 | F46: 20.5 | G46: 2 | I46: 10.7 | K46: 14.6 | M46: 20.2 | N46: 20.3 | O46: 9 | P46: 3.6 | Q46: 5.2 | R46: 20 | S46: 19.9 | T46: 20 | U46: 14.5 | V46: 18.7 | W46: 76.8 | X46: 29.5 | Y46: 23.4 | Z46: 31.1 | AB46: 2.6 | AC46: 2.1 | AD46: 21 | AE46: 5.4 | AF46: 20 | AG46: 20 | AH46: 20 | AI46: 6.9 | AM46: 3.4 | AN46: 18.7 | AQ46: 3.6 | AT46: 5.2 | AU46: 9.9 | AV46: 64.1 | AX46: 79.2 | AZ46: 0.6 | BB46: 5.6 | BC46: 21.2 | BD46: 20 | BE46: 4.5 | BF46: 3 | BG46: 2.3 | BH46: 2.4 | BK46: 20 | BL46: 6 | BN46: 762.1
B47: 20:00 | C47: 13.5 | D47: 12.1 | E47: 7.9 | F47: 20.4 | G47: 2 | I47: 10.6 | K47: 14.6 | M47: 20.2 | N47: 20.3 | O47: 9 | P47: 3.6 | Q47: 5.2 | R47: 20 | S47: 20 | T47: 20 | U47: 14.6 | V47: 19.9 | W47: 73.6 | X47: 36.9 | Y47: 18.3 | Z47: 29 | AB47: 1.4 | AC47: 1.4 | AD47: 21 | AE47: 5.4 | AF47: 20 | AG47: 20 | AH47: 20 | AI47: 7 | AL47: 0.3 | AM47: 3.4 | AN47: 18.7 | AQ47: 3.6 | AT47: 5.2 | AU47: 9.9 | AV47: 49.8 | AX47: 52.5 | AZ47: 0.6 | BB47: 5.5 | BC47: 22.2 | BD47: 20 | BE47: 4.5 | BF47: 3 | BG47: 2.3 | BH47: 2.4 | BK47: 20 | BL47: 6 | BN47: 717.8
B48: 20:30 | C48: 13.2 | D48: 12.1 | E48: 8.2 | F48: 20.4 | G48: 2 | I48: 10.6 | K48: 15 | M48: 20.2 | N48: 20.3 | O48: 9 | P48: 3.6 | Q48: 5.2 | R48: 20 | S48: 20.1 | T48: 20 | U48: 14.5 | V48: 12.5 | W48: 69.1 | X48: 34.2 | Y48: 18.6 | Z48: 32.9 | AB48: 1.4 | AC48: 1.8 | AD48: 21 | AE48: 5.3 | AF48: 20 | AG48: 20 | AH48: 20 | AI48: 6.4 | AK48: 0.3 | AL48: 1.7 | AM48: 3.4 | AN48: 18.8 | AQ48: 3.6 | AT48: 5.4 | AU48: 10 | AV48: 37.4 | AX48: 52.1 | AZ48: 0.6 | BB48: 6.7 | BC48: 22.9 | BD48: 20 | BE48: 4.5 | BF48: 3 | BG48: 2.3 | BH48: 2.4 | BK48: 20 | BL48: 6 | BN48: 698.7
B49: 21:00 | C49: 14 | D49: 12 | E49: 6.7 | F49: 20.5 | G49: 2 | I49: 10.5 | K49: 15 | M49: 20.2 | N49: 20.3 | O49: 9 | P49: 3.6 | Q49: 5.1 | R49: 20 | S49: 20 | T49: 20 | U49: 14.6 | V49: 12.7 | W49: 68.3 | X49: 25.8 | Y49: 15.9 | Z49: 34.7 | AB49: 0.6 | AC49: 0.9 | AD49: 21 | AE49: 5.2 | AF49: 20 | AG49: 20 | AH49: 20 | AI49: 6.5 | AK49: 1.4 | AL49: 3.2 | AM49: 3.4 | AN49: 18.8 | AQ49: 3.6 | AT49: 5.2 | AU49: 9.9 | AV49: 37.3 | AX49: 46.6 | AZ49: 0.6 | BB49: 6.8 | BC49: 24.8 | BD49: 20 | BE49: 4.5 | BF49: 3 | BG49: 2.3 | BH49: 2.4 | BK49: 20 | BL49: 6 | BN49: 684.9
B50: 21:30 | C50: 13.5 | D50: 12 | E50: 7.6 | F50: 20.5 | G50: 2 | I50: 9.8 | K50: 15.1 | M50: 20.2 | N50: 20.3 | O50: 9 | P50: 3.6 | Q50: 5.1 | R50: 20 | S50: 20.1 | T50: 13.9 | U50: 14.5 | V50: 12.1 | W50: 69.4 | X50: 24 | Y50: 15.6 | Z50: 36.8 | AB50: 0.9 | AC50: 0.9 | AD50: 21 | AE50: 5.3 | AF50: 20 | AG50: 20 | AH50: 20 | AI50: 6.6 | AK50: 1.2 | AL50: 3.3 | AM50: 3.4 | AN50: 18.8 | AQ50: 3.6 | AT50: 5.4 | AU50: 9.9 | AV50: 50 | AX50: 45.7 | AZ50: 0.6 | BB50: 4.4 | BC50: 15.2 | BD50: 20 | BE50: 4.5 | BF50: 3 | BG50: 2.3 | BH50: 2.4 | BK50: 20 | BL50: 6 | BN50: 679.5
B51: 22:00 | C51: 12 | D51: 12 | E51: 7.5 | F51: 20.3 | G51: 2 | I51: 9.5 | K51: 15.1 | M51: 20.2 | N51: 20.3 | O51: 9 | P51: 3.6 | Q51: 5.1 | R51: 20 | S51: 20 | T51: 20 | U51: 14.5 | V51: 13.6 | W51: 66.3 | X51: 24 | Y51: 19.2 | Z51: 34.8 | AB51: 0.5 | AC51: 0.6 | AD51: 21 | AE51: 5.2 | AF51: 20 | AG51: 20 | AH51: 20 | AI51: 6.6 | AK51: 2.1 | AL51: 4.4 | AM51: 3.4 | AN51: 18.8 | AQ51: 3.6 | AT51: 5.4 | AU51: 9.9 | AV51: 43.7 | AX51: 37 | AZ51: 0.6 | BB51: 4.3 | BC51: 17.8 | BD51: 20 | BE51: 4.6 | BF51: 3.1 | BG51: 2.3 | BH51: 2.4 | BK51: 20 | BL51: 6 | BN51: 672.3
B52: 22:30 | C52: 12 | D52: 12 | E52: 7.1 | F52: 20.3 | G52: 2 | I52: 10 | K52: 15.1 | M52: 20.2 | N52: 20.3 | O52: 9 | P52: 3.6 | Q52: 5.2 | R52: 20 | S52: 20.1 | T52: 20 | U52: 14.6 | V52: 13.9 | W52: 63.6 | X52: 29.9 | Y52: 21.4 | Z52: 32.2 | AD52: 21 | AE52: 5.2 | AF52: 20 | AG52: 20 | AH52: 20 | AI52: 6.8 | AK52: 11 | AL52: 14.1 | AM52: 3.4 | AN52: 18.8 | AQ52: 3.6 | AT52: 5.3 | AU52: 9.9 | AV52: 23.6 | AX52: 25.8 | AZ52: 0.6 | BB52: 5.9 | BC52: 17.3 | BD52: 19.9 | BE52: 4.6 | BF52: 3.1 | BG52: 2.3 | BH52: 2.4 | BK52: 20 | BL52: 6 | BN52: 663.1
B53: 23:00 | C53: 12 | D53: 12 | E53: 8.3 | F53: 20 | G53: 2 | I53: 9.5 | K53: 15.1 | M53: 20.2 | N53: 20.3 | O53: 9 | P53: 3.6 | Q53: 5.2 | R53: 19.4 | S53: 19.9 | T53: 20 | U53: 14.5 | V53: 17.3 | W53: 62.4 | X53: 31.9 | Y53: 20.2 | Z53: 29.4 | AB53: 0.4 | AC53: 0.2 | AD53: 21 | AE53: 5.2 | AF53: 20 | AG53: 20 | AH53: 20 | AI53: 6.6 | AK53: 6.9 | AL53: 12 | AM53: 3.4 | AN53: 18.8 | AQ53: 3.6 | AT53: 5.2 | AU53: 9.9 | AV53: 26.4 | AX53: 25.5 | AZ53: 0.6 | BB53: 5.1 | BC53: 16 | BD53: 20 | BE53: 4.6 | BF53: 3.1 | BG53: 2.3 | BH53: 2.4 | BK53: 19.4 | BL53: 6 | BN53: 656.8
B54: 23:30 | C54: 12.7 | D54: 12 | E54: 8.1 | F54: 12.4 | G54: 2 | I54: 9.8 | K54: 15 | M54: 20.2 | N54: 20.3 | O54: 9 | P54: 3.6 | Q54: 5.2 | R54: 19.9 | S54: 20.5 | T54: 20 | U54: 14 | V54: 20 | W54: 64.3 | X54: 21.5 | Y54: 12.3 | Z54: 21.1 | AB54: 0.3 | AC54: 0.3 | AD54: 21 | AE54: 5.3 | AF54: 20 | AG54: 20 | AH54: 20 | AI54: 6.6 | AK54: 7.7 | AL54: 11.7 | AM54: 3.4 | AN54: 18.8 | AQ54: 3.6 | AT54: 5.4 | AU54: 9.9 | AV54: 19.3 | AX54: 27.8 | AZ54: 0.6 | BB54: 6.3 | BC54: 16.4 | BD54: 20 | BE54: 4.6 | BF54: 3.1 | BG54: 2.3 | BH54: 2.4 | BK54: 19.9 | BL54: 6 | BN54: 626.6
B55: 0:00 | C55: 13 | D55: 12 | E55: 8.6 | F55: 11 | G55: 2 | I55: 10.3 | K55: 15 | M55: 20 | N55: 20.4 | O55: 9 | P55: 3.6 | Q55: 5.2 | R55: 19.9 | S55: 20.3 | T55: 20 | U55: 13.5 | V55: 19.8 | W55: 64.2 | X55: 24.8 | Y55: 10.8 | Z55: 19.2 | AB55: 0.2 | AC55: 0.1 | AD55: 21 | AE55: 5.3 | AF55: 20 | AG55: 20 | AH55: 20 | AI55: 6.6 | AK55: 3.7 | AL55: 5.3 | AM55: 3.4 | AN55: 18.8 | AQ55: 3.6 | AT55: 5.3 | AU55: 10 | AV55: 19.4 | AX55: 21.6 | AZ55: 0.6 | BB55: 4.5 | BC55: 11.6 | BD55: 20 | BE55: 4.6 | BF55: 3.1 | BG55: 2.3 | BH55: 2.4 | BK55: 20 | BL55: 6 | BN55: 602
B56: EJEC MWh | C56: 328.6 | D56: 334.4 | E56: 185 | F56: 331.05 | G56: 48 | H56: 0 | I56: 210.35 | J56: 8.1 | K56: 383.65 | L56: 0 | M56: 475.25 | N56: 487.8 | O56: 212.7 | P56: 84.75 | Q56: 124.1 | R56: 478.4 | S56: 484.25 | T56: 476.95 | U56: 355.35 | V56: 384.9 | W56: 1193.4 | X56: 1151.9 | Y56: 599.35 | Z56: 907.35 | AA56: 266.5 | AB56: 53.8 | AC56: 53.15 | AD56: 504 | AE56: 148 | AF56: 480 | AG56: 480 | AH56: 478.45 | AI56: 114.45 | AJ56: 645.3 | AK56: 230.9 | AL56: 290.3 | AM56: 82.15 | AN56: 431.75 | AO56: 0 | AP56: 2.1 | AQ56: 86.45 | AR56: 121.45 | AS56: 115.25 | AT56: 122.5 | AU56: 238.1 | AV56: 1084.2 | AW56: 1112.45 | AX56: 1093.05 | AY56: 904.85 | AZ56: 14.4 | BA56: 140.45 | BB56: 253.05 | BC56: 731.7 | BD56: 479.6 | BE56: 98 | BF56: 54.9 | BG56: 54.9 | BH56: 57.6 | BI56: 120.15 | BJ56: 0 | BK56: 478.65 | BL56: 144.25 | BM56: 158.3 | BN56: 21170.7
L70: TERMOELÉCTRICA | M70: 1323.75 | N70: 6.2527455 | O70: #FF0000
L71: SOLAR | M71: 3594.9 | N71: 16.980544 | O71: #FBFB00
L72: EÓLICA | M72: 8027.05 | N72: 37.915846 | O72: #FBBD00
L73: HIDROELÉCTRICA | M73: 8225 | N73: 38.850865 | O73: #00B0F0

Sheet COGENERACIÓN
B3: sábado, 25 de Enero del 2025
B5: CENTRALES DE COGENERACIÓN DEL SEIN
B6: HORA | C6: AGRO INDUSTRIAL PARAMONGA S.A. | D6: AGROAURORA S.A.C. | E6: AGROINDUSTRIAS SAN JACINTO S.A.A. | F6: BIOENERGIA DEL CHIRA S.A. | G6: GM OPERACIONES S.A.C. | H6: SDF ENERGIA SAC | I6: TOTAL COGENERACION
C7: C.T. PARAMONGA | D7: C.T. MAPLE | E7: C.T SAN JACINTO | F7: C.T. CAÑA BRAVA | G7: C.T. REFINERÍA TALARA | H7: C.T. OQUENDO | I7: MW
B8: 0:30 | C8: 14.2 | D8: 11.3 | E8: 8.2 | F8: 10.9 | G8: 54.6 | H8: 32 | I8: 131.2
B9: 1:00 | C9: 14 | D9: 13.3 | E9: 8.1 | F9: 9.8 | G9: 53.5 | H9: 32.1 | I9: 130.8
B10: 1:30 | C10: 14.4 | D10: 15 | E10: 7.5 | F10: 9.8 | G10: 53.2 | H10: 32.1 | I10: 132
B11: 2:00 | C11: 14 | D11: 14.1 | E11: 8 | F11: 11.3 | G11: 53.2 | H11: 32.1 | I11: 132.7
B12: 2:30 | C12: 14 | D12: 15.1 | E12: 7.7 | F12: 10.7 | G12: 52.9 | H12: 32.1 | I12: 132.5
B13: 3:00 | C13: 14.4 | D13: 16.2 | E13: 7.9 | F13: 10.1 | G13: 52.5 | H13: 32.2 | I13: 133.3
B14: 3:30 | C14: 14.5 | D14: 16.3 | E14: 7.8 | F14: 9.8 | G14: 52.3 | H14: 32.2 | I14: 132.9
B15: 4:00 | C15: 14.4 | D15: 14.6 | E15: 8 | F15: 9.3 | G15: 51.7 | H15: 32.2 | I15: 130.2
B16: 4:30 | C16: 14.3 | D16: 16.3 | E16: 8 | F16: 10.2 | G16: 52.8 | H16: 32.3 | I16: 133.9
B17: 5:00 | C17: 14.5 | D17: 14.6 | E17: 7.4 | F17: 9.5 | G17: 51.7 | H17: 32.2 | I17: 129.9
B18: 5:30 | C18: 14 | D18: 12.6 | E18: 7.5 | F18: 10 | G18: 52.6 | H18: 32.1 | I18: 128.8
B19: 6:00 | C19: 12.8 | D19: 14.9 | E19: 7.6 | F19: 9.8 | G19: 52.5 | H19: 32 | I19: 129.6
... B56: EJEC MWh | C56: 328.6 | D56: 334.4 | E56: 185 | F56: 210.35 | G56: 1248.05 | H56: 760.9 | I56: 3067.3

Sheet EVO_PRO_ENE
B3: miércoles, 1 de Enero del 2025 - sábado, 25 de Enero del 2025
B5: EVOLUCIÓN DE LA PRODUCCIÓN DE LA ENERGÍA DIARIA DE LOS INTEGRANTES DEL COES (MWh)
B6: EMPRESA | C6: CENTRAL | D6: UNIDAD | E6: TIPO | F6: Enero
F7: 1 | G7: 2 | H7: 3 | I7: 4 | J7: 5 | K7: 6 | L7: 7 | M7: 8 | N7: 9 | O7: 10 | P7: 11 | Q7: 12 | R7: 13 | S7: 14 | T7: 15 | U7: 16 | V7: 17 | W7: 18 | X7: 19 | Y7: 20 | Z7: 21 | AA7: 22 | AB7: 23 | AC7: 24 | AD7: 25 | AE7: TOTAL
B8: AGRO INDUSTRIAL PARAMONGA S.A. | C8: C.T. PARAMONGA | D8: TV-01 | E8: TERMOELÉCTRICA | L8: 224.55 | M8: 388.3 | N8: 387.45 | O8: 389.1 | P8: 389.05 | Q8: 381.85 | R8: 353.1 | S8: 355.3 | T8: 354.05 | U8: 346.3 | V8: 315.55 | W8: 319.35 | X8: 312.65 | Y8: 309.55 | Z8: 331.15 | AA8: 333.25 | AB8: 324.9 | AC8: 330.55 | AD8: 328.6 | AE8: 6474.6
B9: AGROAURORA S.A.C. | C9: C.T. MAPLE ETANOL | D9: TV | E9: TERMOELÉCTRICA | F9: 360 | H9: 179.75 | I9: 379.5 | J9: 393.65 | K9: 392.45 | L9: 383.75 | M9: 362.8 | N9: 358.2 | O9: 362.8 | P9: 359.2 | Q9: 375.75 | R9: 354.95 | S9: 349.4 | T9: 325.2 | U9: 355.95 | V9: 340.75 | W9: 305.8 | X9: 409.85 | Y9: 412.35 | Z9: 408.2 | AA9: 379.6 | AB9: 386.1 | AC9: 352.75 | AD9: 334.4 | AE9: 8623.15
B10: AGROINDUSTRIAS SAN JACINTO S.A.A. | C10: C.T. SAN JACINTO | D10: CENTRAL | E10: TERMOELÉCTRICA | K10: 58.45 | L10: 96.65 | M10: 161.7 | N10: 175.7 | O10: 179.9 | P10: 182.405 | Q10: 177.25 | R10: 172.8 | S10: 188.05 | T10: 187.3 | U10: 186.2334 | V10: 186.05 | W10: 187.85 | X10: 197.1 | Y10: 193 | Z10: 159.85 | AA10: 185.4 | AB10: 176.35 | AC10: 182.95 | AD10: 185 | AE10: 3419.9884
B11: ANDEAN POWER S.A.C. | C11: C.H. CARHUAC | D11: CENTRAL | E11: HIDROELÉCTRICA | F11: 436.45 | G11: 447.15 | H11: 484.25 | I11: 484.6 | J11: 483.35 | K11: 484 | L11: 450.25 | M11: 439.95 | N11: 429.3 | O11: 414.6 | P11: 437.75 | Q11: 418.5 | R11: 384.05 | S11: 410.75 | T11: 360.5 | U11: 432.65 | V11: 420.55 | W11: 384.55 | X11: 413.3 | Y11: 306.8 | Z11: 285.4 | AA11: 277.45 | AB11: 309 | AC11: 288.3 | AD11: 331.05 | AE11: 10014.5
B12: ASOCIACIÓN SANTA LUCIA DE CHACAS | C12: C.H. HUALLIN | D12: CENTRAL | E12: HIDROELÉCTRICA | F12: 48 | G12: 45.85 | H12: 48 | I12: 48 | J12: 48 | K12: 48 | L12: 48 | M12: 48 | N12: 48 | O12: 48 | P12: 29.55 | Q12: 48 | R12: 46.9 | S12: 48 | T12: 48 | U12: 48 | V12: 48 | W12: 48 | X12: 48 | Y12: 46.15 | Z12: 46.25 | AA12: 48 | AB12: 48 | AC12: 48 | AD12: 48 | AE12: 1174.7
B13: ATRIA ENERGIA S.A.C. | C13: C.H. PURMACANA | D13: CENTRAL | E13: HIDROELÉCTRICA | AE13: 0
B14: BIOENERGIA DEL CHIRA S.A. | C14: C.T. CAÑA BRAVA | D14: CENTRAL | E14: TERMOELÉCTRICA | F14: 230.05 | G14: 4.15 | H14: 207.1 | I14: 231.25 | J14: 226.25 | K14: 229.1 | L14: 220.25 | M14: 242.55 | N14: 215 | O14: 246.75 | P14: 247.3 | Q14: 230.9 | R14: 230.2 | S14: 243 | T14: 240.05 | U14: 241.5 | V14: 213.8 | W14: 244.1 | X14: 238 | Y14: 244.65 | Z14: 240.15 | AA14: 250.3 | AB14: 256.05 | AC14: 255.25 | AD14: 210.35 | AE14: 5638.05
B15: CELEPSA | C15: C.H. EL PLATANAL | D15: CENTRAL | E15: HIDROELÉCTRICA | F15: 4523.65 | G15: 4474.1 | H15: 4762.5 | I15: 5166.1 | J15: 5163.45 | K15: 5266.75 | L15: 5280.35 | M15: 5023.05 | N15: 5010.85 | O15: 5120.1 | P15: 5245 | Q15: 5145.95 | R15: 5180.55 | S15: 5298.45 | T15: 5167.65 | U15: 5203.4 | V15: 5292.25 | W15: 5062.05 | X15: 5063.7 | Y15: 5258.25 | Z15: 5275.15 | AA15: 5301.65 | AB15: 5356.7 | AC15: 5250.1 | AD15: 5063.2 | AE15: 127954.95
B16: CELEPSA RENOVABLES S.R.L. | C16: C.H. MARAÑON | D16: CENTRAL | E16: HIDROELÉCTRICA | F16: 473.65 | G16: 473.1 | H16: 415.2 | I16: 360.25 | J16: 431.7 | K16: 469.85 | L16: 472.8 | M16: 472.8 | N16: 473.1415 | O16: 472.8 | P16: 472.8 | Q16: 472.8 | R16: 472.8 | S16: 472.8 | T16: 472.8 | U16: 472.8 | V16: 472.8 | W16: 472.8 | X16: 472.8 | Y16: 453.45 | Z16: 475.45 | AA16: 473.55 | AB16: 448.05 | AC16: 464.95 | AD16: 466.95 | AE16: 11552.891
B17: CENTRALES SANTA ROSA S.A.C. | C17: C.H. SANTA ROSA I | D17: CENTRAL | E17: HIDROELÉCTRICA | F17: 25.45 | G17: 25.95 | H17: 19.75 | I17: 13.4 | J17: 18.1 | K17: 20.2 | L17: 22.1 | M17: 23.3 | N17: 24.3 | O17: 24.45 | P17: 25.2 | Q17: 25.2 | R17: 25.35 | S17: 23.95 | T17: 14.65 | U17: 25.4 | V17: 25.75 | W17: 26.2 | X17: 26.3 | Y17: 24.8 | Z17: 24.55 | AA17: 23.7 | AB17: 26.3 | AC17: 26.4 | AD17: 26.4 | AE17: 587.15
B18: CENTRALES SANTA ROSA S.A.C. | C18: C.H. SANTA ROSA II | D18: CENTRAL | E18: HIDROELÉCTRICA | F18: 37.7 | G18: 37.1 | H18: 31.9 | I18: 24.55 | J18: 31.45 | K18: 35.3 | L18: 35.95 | M18: 36.35 | N18: 37.05 | O18: 37.2 | P18: 38.45 | Q18: 38.2 | R18: 37.9 | S18: 36.25 | T18: 22.3 | U18: 36.7 | V18: 37.15 | W18: 39.2 | X18: 38.45 | Y18: 36.85 | Z18: 38.1 | AA18: 37.05 | AB18: 39.65 | AC18: 38.3 | AD18: 40.15 | AE18: 899.25
B19: CHINANGO S.A.C. | C19: C.H. CHIMAY | D19: CENTRAL | E19: HIDROELÉCTRICA | F19: 3094.35 | G19: 3340.85 | H19: 3399.5 | I19: 3452.55 | J19: 3481.7 | K19: 3446.85 | L19: 2227.35 | M19: 3331.064 | N19: 2748.9 | O19: 3452.7 | P19: 2273.8 | Q19: 3314.15 | R19: 3434.2 | S19: 3445.75 | T19: 3447 | U19: 3516.65 | V19: 3387.15 | W19: 3459.45 | X19: 3425.5 | Y19: 851.55 | Z19: 1126.4 | AA19: 1758.95 | AB19: 1615.9 | AC19: 2847.55 | AD19: 3397.55 | AE19: 73277.364
B20: CHINANGO S.A.C. | C20: C.H. YANANGO | D20: CENTRAL | E20: HIDROELÉCTRICA | F20: 816.75 | G20: 970.5 | H20: 1005.45 | I20: 1002.9 | J20: 1005 | K20: 1004.55 | L20: 1004.4 | M20: 1004.0105 | N20: 1004.4 | O20: 993.6 | P20: 999.4 | Q20: 1004.85 | R20: 993.1 | S20: 929.1 | T20: 853.8 | U20: 785.6 | V20: 742.25 | W20: 738.7 | X20: 823.5 | Y20: 510.57261 | Z20: 1000.85 | AA20: 1004.8 | AB20: 1000.3 | AC20: 1001.05 | AD20: 1002.7 | AE20: 23202.133
B21: COLCA SOLAR S.A.C. | C21: C.S. YARUCAYA | D21: CENTRAL | E21: SOLAR | F21: 4.85 | G21: 4.35 | H21: 6.75 | I21: 6.6 | J21: 7.6 | K21: 4.8 | L21: 5.35 | M21: 7.05 | N21: 7.3 | O21: 4.7 | P21: 6.9 | Q21: 7.95 | R21: 6.7 | S21: 6.95 | T21: 8.85 | U21: 6.85 | V21: 6.9 | W21: 6.7 | X21: 6.7 | Y21: 9 | Z21: 5.05 | AA21: 5.6 | AB21: 7.05 | AC21: 6.65 | AD21: 8.1 | AE21: 165.3
B22: EGASA | C22: C.H. CHARCANI III | D22: CENTRAL | E22: HIDROELÉCTRICA | F22: 144.4 | G22: 148.8 | H22: 151.3 | I22: 151.2 | J22: 154.25 | K22: 151.25 | L22: 151.15 | M22: 151.2 | N22: 151.2 | O22: 153.1 | P22: 156.51 | Q22: 156.7 | R22: 156.15 | S22: 155.05 | T22: 154.45 | U22: 158.35 | V22: 164.1 | W22: 163.65 | X22: 90.85 | Y22: 163.2 | Z22: 163.9 | AA22: 154.65 | AB22: 153.6 | AC22: 157.3 | AD22: 158.7 | AE22: 3815.01
B23: EGASA | C23: C.H. CHARCANI IV | D23: CENTRAL | E23: HIDROELÉCTRICA | F23: 239.55 | G23: 234.3 | H23: 245.4 | I23: 241.3 | J23: 241.65 | K23: 239.15 | L23: 234.75 | M23: 231.05 | N23: 231.35 | O23: 235.64 | P23: 230.91 | Q23: 236.25 | R23: 236.1 | S23: 231.15 | T23: 229.7 | U23: 233.5 | V23: 238.6 | W23: 172.1 | X23: 73.1 | Y23: 120 | Z23: 121.15 | AA23: 46.8 | AE23: 4543.5
B24: EGASA | C24: C.H. CHARCANI V | D24: CENTRAL | E24: HIDROELÉCTRICA | F24: 1540.9 | G24: 1524 | H24: 1529.2 | I24: 1526.8 | J24: 1554.35 | K24: 1503.95 | L24: 1515 | M24: 1511.6 | N24: 1504.7 | O24: 1496.02 | P24: 1512.455 | Q24: 1528 | R24: 1503.7 | S24: 1525.2 | T24: 1515.85 | U24: 1768.05 | V24: 1786.1 | W24: 1782.85 | X24: 1808.75 | Y24: 1817.45 | Z24: 1801.45 | AA24: 1525.8 | AB24: 1552.7 | AC24: 1510.45 | AD24: 1548.95 | AE24: 39694.275
B25: EGASA | C25: C.H. CHARCANI VI | D25: CENTRAL | E25: HIDROELÉCTRICA | F25: 134.95 | G25: 136.9 | H25: 144.1 | I25: 126 | J25: 140.8 | K25: 138.75 | L25: 141.85 | M25: 137.65 | N25: 139.9 | O25: 138.645 | P25: 139.425 | Q25: 141.25 | R25: 140.55 | S25: 137.7 | T25: 137.25 | U25: 139.15 | V25: 162.8 | W25: 168.9 | X25: 157.05 | Y25: 165.5 | Z25: 170.8 | AA25: 131.7 | AB25: 135.4 | AC25: 132.45 | AD25: 138.15 | AE25: 3577.62
B26: EGASA | C26: C.T. CHILINA DIESEL | D26: CENTRAL | E26: TERMOELÉCTRICA | G26: 4.25 | AE26: 4.25
B27: EGASA | C27: C.T. CHILINA DIESEL | D27: TG | E27: TERMOELÉCTRICA | AD27: 4.25 | AE27: 4.25
B28: EGASA | C28: C.T. MOLLENDO DIESEL | D28: CENTRAL | E28: TERMOELÉCTRICA | AE28: 0
B29: EGEJUNIN | C29: C.H. HUASAHUASI I | D29: CENTRAL | E29: HIDROELÉCTRICA | F29: 247.6 | G29: 430.95 | H29: 474.25 | I29: 475.2 | J29: 473.2 | K29: 475.2 | L29: 470.1 | M29: 472.65 | N29: 445.9 | O29: 414.8 | P29: 412.6 | Q29: 475.2 | R29: 464.3 | S29: 382.85 | T29: 325.1 | U29: 275.75 | V29: 261.35 | W29: 249.35 | X29: 248.6 | Y29: 402.3 | Z29: 360.7 | AA29: 453.4 | AB29: 433.3 | AC29: 414.3 | AD29: 383.65 | AE29: 9922.6
B30: EGEJUNIN | C30: C.H. RUNATULLO II | D30: CENTRAL | E30: HIDROELÉCTRICA | F30: 349.2 | G30: 426.2 | H30: 478.5 | I30: 478.35 | J30: 477.55 | K30: 477 | L30: 477.65 | M30: 478.6 | N30: 481.25 | O30: 481.2 | P30: 480 | Q30: 473.45 | R30: 475.35 | S30: 476.6 | T30: 478.8 | U30: 475.5 | V30: 464.45 | W30: 437.05 | X30: 467.85 | Y30: 474.8 | Z30: 476.9 | AA30: 475.75 | AB30: 475.6 | AC30: 474.45 | AD30: 475.25 | AE30: 11687.3
B31: EGEJUNIN | C31: C.H. RUNATULLO III | D31: CENTRAL | E31: HIDROELÉCTRICA | F31: 450.65 | G31: 490.95 | H31: 491.2 | I31: 490.75 | J31: 489.65 | K31: 490.05 | L31: 489.75 | M31: 489.8 | N31: 490.05 | O31: 490.15 | P31: 490.1 | Q31: 489.25 | R31: 489.35 | S31: 489.4 | T31: 489.05 | U31: 489.3 | V31: 489.4 | W31: 488.65 | X31: 488.4 | Y31: 485.75 | Z31: 485.45 | AA31: 486.15 | AB31: 487.75 | AC31: 488.1 | AD31: 487.8 | AE31: 12186.9
B32: EGEJUNIN | C32: C.H. SANTA CRUZ I | D32: CENTRAL | E32: HIDROELÉCTRICA | F32: 279.3 | G32: 256 | H32: 177.35 | I32: 234.2 | J32: 290.3 | K32: 280.9 | L32: 289.2 | M32: 288 | N32: 289.8 | O32: 276.3 | P32: 279.6 | Q32: 288.5 | R32: 287.6 | S32: 289.3 | T32: 289.7 | U32: 289.9 | V32: 250.4 | W32: 222.45 | X32: 143.4 | Y32: 216 | Z32: 206.35 | AA32: 191.6 | AB32: 197 | AC32: 223.8 | AD32: 212.7 | AE32: 6249.65
B33: EGEMSA | C33: C.H. MACHUPICCHU | D33: CENTRAL | E33: HIDROELÉCTRICA | F33: 4014.15 | G33: 3890.05 | H33: 4014.9 | I33: 3957.7 | J33: 3526.95 | K33: 4017.5 | L33: 4007.85 | M33: 3997.65 | N33: 3976.3 | O33: 4001.35 | P33: 3995.1 | Q33: 3227.3 | R33: 4003.9 | S33: 3993.295 | T33: 3981.75 | U33: 3999.55 | V33: 4000 | W33: 3980.55 | X33: 4005.15 | Y33: 3997 | Z33: 3984.45 | AA33: 3999.35 | AB33: 3957.35 | AC33: 3952.3 | AD33: 3979.55 | AE33: 98460.995
B34: EGESUR | C34: C.H. ARICOTA I | D34: CENTRAL | E34: HIDROELÉCTRICA | F34: 172.05 | G34: 172.05 | H34: 172.25 | I34: 171 | J34: 171.45 | K34: 170.85 | L34: 169.05 | M34: 169.55 | N34: 172.1 | O34: 179.4 | P34: 176.65 | Q34: 179.65 | R34: 200.4 | S34: 186.25 | T34: 187.3 | U34: 172.25 | V34: 183.85 | W34: 181.6 | X34: 182.65 | Y34: 184.05 | Z34: 183.15 | AA34: 186.45 | AB34: 180.45 | AC34: 177.8 | AD34: 181.154 | AE34: 4463.404
B35: EGESUR | C35: C.H. ARICOTA II | D35: CENTRAL | E35: HIDROELÉCTRICA | AC35: 61.75 | AD35: 62.7405 | AE35: 124.4905
B36: EGESUR | C36: C.T. INDEPENDENCIA | D36: CENTRAL | E36: TERMOELÉCTRICA | G36: 48.3 | H36: 166.35 | I36: 140.45 | J36: 64.7 | K36: 212.35 | L36: 95 | M36: 108.5 | N36: 162.35 | O36: 129.65 | P36: 74.3 | Q36: 24.3 | R36: 122.15 | S36: 125.5 | T36: 123.85 | U36: 147.9 | V36: 221.9 | W36: 265.15 | X36: 89.45 | Y36: 142.55 | Z36: 240.85 | AA36: 145.5 | AB36: 160.3 | AC36: 63.2 | AD36: 97.056 | AE36: 3171.606
B37: ELECTRICA YANAPAMPA SAC | C37: C.H. YANAPAMPA | D37: CENTRAL | E37: HIDROELÉCTRICA | F37: 76.35 | G37: 78.35 | H37: 67.15 | I37: 71.6 | J37: 75.8 | K37: 79.4 | L37: 74.05 | M37: 82.95 | N37: 81.65 | O37: 83.5 | P37: 84 | Q37: 83.9 | R37: 85.8 | S37: 81.9 | T37: 85.9 | U37: 86.4 | V37: 82.45 | W37: 86.7 | X37: 86.55 | Y37: 84.35 | Z37: 85.15 | AA37: 85.15 | AB37: 84.45 | AC37: 84.55 | AD37: 84.75 | AE37: 2042.8
B38: ELECTROPERU | C38: C.H. MANTARO | D38: CENTRAL | E38: HIDROELÉCTRICA | F38: 15545.15 | G38: 15118.55 | H38: 15559.05 | I38: 14563.895 | J38: 15542.75 | K38: 15304.6 | L38: 15533.6 | M38: 15528.8 | N38: 14996.7 | O38: 15556.6 | P38: 15559.7 | Q38: 15542 | R38: 15555.85 | S38: 15532.55 | T38: 15518.25 | U38: 15549.2 | V38: 15546.15 | W38: 15533.25 | X38: 15023 | Y38: 15525.8 | Z38: 15205.1 | AA38: 15550.165 | AB38: 15518.65 | AC38: 14942.8 | AD38: 15521 | AE38: 384873.16
B39: ELECTROPERU | C39: C.H. RESTITUCION | D39: CENTRAL | E39: HIDROELÉCTRICA | F39: 5257.75 | G39: 5067.3 | H39: 5237.45 | I39: 4858.585 | J39: 5248.6 | K39: 5140.55 | L39: 5236.45 | M39: 5237.55 | N39: 5048.15 | O39: 5256.95 | P39: 3516.65 | Q39: 3595.4 | R39: 5258.55 | S39: 5249.2 | T39: 5260.2 | U39: 5268.25 | V39: 5268.85 | W39: 5273.25 | X39: 5069.5 | Y39: 5268.8 | Z39: 5134.35 | AA39: 5270.26 | AB39: 5254.85 | AC39: 5008.2 | AD39: 5222.6 | AE39: 126508.24
B40: ELECTROPERU | C40: C.T. TUMBES | D40: MAK1 | E40: TERMOELÉCTRICA | H40: 31.13 | I40: 14.71 | U40: 95.025 | V40: 138.045 | W40: 15.9 | AE40: 294.81
B41: ELECTROPERU | C41: C.T. TUMBES | D41: MAK2 | E41: TERMOELÉCTRICA | H41: 29.09 | I41: 14.83 | U41: 96.38 | V41: 137.56 | W41: 15.93 | AE41: 293.79
B42: EMPRESA DE GENERACION ELECTRICA CANCHAYLLO SAC | C42: C.H. CANCHAYLLO | D42: CENTRAL | E42: HIDROELÉCTRICA | F42: 114.5 | G42: 103.6 | H42: 121.4 | I42: 119.45 | J42: 115.45 | K42: 97.35 | L42: 122.9 | M42: 123.75 | N42: 123.75 | O42: 123 | P42: 123.65 | Q42: 123.35 | R42: 123.35 | S42: 121.85 | T42: 114.7 | U42: 108.15 | V42: 102.45 | W42: 101.2 | X42: 117 | Y42: 122.25 | Z42: 124.05 | AA42: 123.95 | AB42: 121.6 | AC42: 119.6 | AD42: 124.1 | AE42: 2936.4
B43: EMPRESA DE GENERACION ELECTRICA RIO BAÑOS S.A.C. | C43: C.H. RUCUY | D43: CENTRAL | E43: HIDROELÉCTRICA | F43: 479.95 | G43: 479.15 | H43: 479.65 | I43: 474 | J43: 479.15 | K43: 479.3 | L43: 479.45 | M43: 479.25 | N43: 479 | O43: 478.95 | P43: 479.25 | Q43: 479 | R43: 479.45 | S43: 478.9 | T43: 477.7 | U43: 478.65 | V43: 479.1 | W43: 479.7 | X43: 479.25 | Y43: 478.6 | Z43: 478.85 | AA43: 479 | AB43: 478.6 | AC43: 478.55 | AD43: 478.4 | AE43: 11970.85
B44: EMPRESA DE GENERACION ELECTRICA SANTA ANA S.A.C. | C44: C.H. RENOVANDES H1 | D44: CENTRAL | E44: HIDROELÉCTRICA | F44: 485 | G44: 423.7 | H44: 485.75 | I44: 484.65 | J44: 485.9 | K44: 465 | L44: 483.85 | M44: 484.4 | N44: 484.8 | O44: 486 | P44: 385.15 | Q44: 485.4 | R44: 486.5 | S44: 484.965 | T44: 464.4 | U44: 485.9 | V44: 486 | W44: 484.85 | X44: 486.5 | Y44: 484.95 | Z44: 484.55 | AA44: 485.15 | AB44: 483.65 | AC44: 483.8 | AD44: 484.25 | AE44: 11925.065
B45: EMPRESA DE GENERACION HUALLAGA | C45: C.H. CHAGLLA | D45: CENTRAL | E45: HIDROELÉCTRICA | F45: 3199.75 | G45: 7586.7 | H45: 10939.2 | I45: 8710.6 | J45: 10473.2 | K45: 10518.25 | L45: 10829.2 | M45: 10647.45 | N45: 10225.1 | O45: 10768.1 | P45: 10912.65 | Q45: 10121 | R45: 10631.6 | S45: 10732 | T45: 10715.3 | U45: 11168.8 | V45: 11387.7 | W45: 7963.15 | X45: 3828 | Y45: 9914.7 | Z45: 10536.25 | AA45: 10815.95 | AB45: 10882.25 | AC45: 11012.55 | AD45: 10957.85 | AE45: 245477.3
B46: EMPRESA DE GENERACION HUALLAGA | C46: P.C.H. CHAGLLA | D46: CENTRAL | E46: HIDROELÉCTRICA | F46: 156 | G46: 156 | H46: 156 | I46: 155.3 | J46: 156 | K46: 156 | L46: 156 | M46: 156 | N46: 156 | O46: 155.95 | P46: 156 | Q46: 156 | R46: 155.95 | S46: 156 | T46: 156 | U46: 156 | V46: 156 | W46: 156 | X46: 156 | Y46: 156 | Z46: 156 | AA46: 156 | AB46: 156 | AC46: 156 | AD46: 156 | AE46: 3899.2
B47: EMPRESA DE GENERACION HUANZA | C47: C.H. HUANZA | D47: CENTRAL | E47: HIDROELÉCTRICA | F47: 1305.9 | G47: 1930.85 | H47: 2249.7 | I47: 2277.7 | J47: 2270.7 | K47: 2002.5 | L47: 1713.8 | M47: 1676.2 | N47: 1549.45 | O47: 1463.3 | P47: 1644.65 | Q47: 1485.8 | R47: 1510.35 | S47: 1604.5 | T47: 1343.3 | U47: 1666.95 | V47: 1601.9 | W47: 1567.7 | X47: 1687.05 | Y47: 1223.6 | Z47: 1069.2 | AA47: 1054.65 | AB47: 1121.5 | AC47: 937.9 | AD47: 1035.05 | AE47: 38994.2
B48: EMPRESA ELECTRICA AGUA AZUL | C48: C.H. POTRERO | D48: CENTRAL | E48: HIDROELÉCTRICA | F48: 476.9 | G48: 478.3 | H48: 471.8 | I48: 476.45 | J48: 475.2 | K48: 477.75 | L48: 474.7 | M48: 399.25 | N48: 425.5 | O48: 479.95 | P48: 478.8 | Q48: 477.1 | R48: 479.25 | S48: 469.8 | T48: 477.65 | U48: 478.55 | V48: 473.45 | W48: 479.75 | X48: 480 | Y48: 480 | Z48: 479.95 | AA48: 480 | AB48: 480 | AC48: 480 | AD48: 476.95 | AE48: 11807.05
B49: EMPRESA ELECTRICA RIO DOBLE | C49: C.H. LAS PIZARRAS | D49: CENTRAL | E49: HIDROELÉCTRICA | F49: 450.2 | G49: 451.5 | H49: 442.55 | I49: 428.7 | J49: 452.7 | K49: 454.2 | L49: 455.15 | M49: 454.15 | N49: 453.645 | O49: 453.2 | P49: 453.92 | Q49: 453.85 | R49: 453.5 | S49: 453.95 | T49: 453.3 | U49: 452 | V49: 451.705 | W49: 452.58 | X49: 452.55 | Y49: 453.215 | Z49: 437.035 | AA49: 432.15 | AB49: 428.1 | AC49: 387.95 | AD49: 355.35 | AE49: 11067.15
B50: ENEL GENERACION PIURA S.A. | C50: C.T. MALACAS 1 | D50: TG6 | E50: TERMOELÉCTRICA | F50: 355.85 | G50: 457.5 | H50: 359.15 | J50: 727.05 | L50: 441.55 | M50: 752.4 | N50: 738.3 | O50: 816.85 | P50: 771.75 | Q50: 766.15 | R50: 1105.15 | S50: 805.45 | T50: 816.45 | U50: 1131.85 | V50: 1135.25 | W50: 1118.5 | X50: 1129.65 | Y50: 1138.7 | Z50: 1126.05 | AA50: 1124 | AB50: 1100 | AC50: 813.05 | AD50: 1118.85 | AE50: 19849.5
B51: ENEL GENERACION PIURA S.A. | C51: C.T. MALACAS 2 | D51: TG4 | E51: TERMOELÉCTRICA | H51: 663.05 | I51: 894.45 | J51: 44.65 | K51: 914.15 | L51: 74.85 | W51: 60.4 | AE51: 2651.55
B52: ENEL GENERACION PIURA S.A. | C52: C.T. RF DE GENERACION TALARA | D52: TG5 | E52: TERMOELÉCTRICA | H52: 407 | AE52: 407
B53: ENERGÍA EÓLICA S.A. | C53: C.E. CUPISNIQUE | D53: CENTRAL | E53: EÓLICA | F53: 826 | G53: 637.1 | H53: 565.05 | I53: 483.8 | J53: 446.9 | K53: 946.35 | L53: 1252.6 | M53: 1412.8 | N53: 1299.5 | O53: 1060.15 | P53: 721.65 | Q53: 1086.1 | R53: 1006 | S53: 1036.9 | T53: 845.9 | U53: 488.95 | V53: 523.6 | W53: 1059 | X53: 1452.95 | Y53: 1228.95 | Z53: 1002.6 | AA53: 1077.35 | AB53: 1381.8 | AC53: 1266.45 | AD53: 1193.4 | AE53: 24301.85
B54: ENERGÍA EÓLICA S.A. | C54: C.E. TALARA | D54: CENTRAL | E54: EÓLICA | F54: 344.35 | G54: 395.75 | H54: 384.4 | I54: 141.95 | J54: 94.85 | K54: 161.95 | L54: 465.35 | M54: 531.8 | N54: 530.7 | O54: 329.8 | P54: 230.45 | Q54: 302.4 | R54: 354.85 | S54: 305.55 | T54: 349.75 | U54: 151.05 | V54: 203.55 | W54: 391.2 | X54: 580.95 | Y54: 528.2 | Z54: 443.55 | AA54: 420.2 | AB54: 561.55 | AC54: 540.7 | AD54: 384.9 | AE54: 9129.75
B55: ENERGIA RENOVABLE DEL SUR S.A. | C55: C.E. SAN JUAN | D55: CENTRAL | E55: EÓLICA | F55: 2667.35 | G55: 1888.4 | H55: 1031.8 | I55: 1510.75 | J55: 862.7 | K55: 715 | L55: 1712.65 | M55: 1729.05 | N55: 1633.15 | O55: 1758.3 | P55: 2050.7 | Q55: 1899.4 | R55: 1355.45 | S55: 1224.5 | T55: 1889.8 | U55: 1369.1 | V55: 1364.4 | W55: 2019.15 | X55: 2070.8 | Y55: 1645.1 | Z55: 2080.4 | AA55: 2344.45 | AB55: 2169 | AC55: 1534 | AD55: 1151.9 | AE55: 41677.3
B56: ENGIE | C56: C.E. PUNTA LOMITAS | D56: PL-BL1 | E56: EÓLICA | F56: 1416 | G56: 1294.2 | H56: 490.05 | I56: 910.85 | J56: 885.7 | K56: 777.2 | L56: 1793.85 | M56: 1777.65 | N56: 1646.2 | O56: 1640.35 | P56: 1225.1 | Q56: 1266.85 | R56: 1046.65 | S56: 1040.35 | T56: 1134.95 | U56: 715.35 | V56: 819.45 | W56: 1316 | X56: 1883.9 | Y56: 1525.95 | Z56: 1457.65 | AA56: 1454.1 | AB56: 1530.45 | AC56: 1137.8 | AD56: 599.35 | AE56: 30785.95
B57: ENGIE | C57: C.E. PUNTA LOMITAS | D57: PL-BL2 | E57: EÓLICA | F57: 1675.05 | G57: 1567.65 | H57: 664.2 | I57: 1146.85 | J57: 995.45 | K57: 964.6 | L57: 1911.45 | M57: 1824.7 | N57: 1813.75 | O57: 1862.9 | P57: 1474.45 | Q57: 1526 | R57: 1347.1 | S57: 1347.25 | T57: 1469.25 | U57: 1069.55 | V57: 1271.05 | W57: 1161.7 | X57: 1830.85 | Y57: 1690.2 | Z57: 1766.25 | AA57: 1814.45 | AB57: 1914.05 | AC57: 1531.8 | AD57: 907.35 | AE57: 36547.9
B58: ENGIE | C58: C.E. PUNTA LOMITAS_EXP | D58: PUN LOM_EXP-BL1 | E58: EÓLICA | F58: 74.35 | G58: 61.95 | H58: 36.6 | I58: 85.7 | J58: 74.9 | K58: 54.35 | L58: 161.2 | M58: 173 | N58: 163.95 | O58: 163.25 | P58: 110.5 | Q58: 103.95 | R58: 99.75 | S58: 102.05 | T58: 110.1 | U58: 55.9 | V58: 63.7 | W58: 113.3 | X58: 165.05 | Y58: 159.2 | Z58: 147.15 | AA58: 137.65 | AB58: 119.85 | AC58: 101.65 | AD58: 53.8 | AE58: 2692.85
B59: ENGIE | C59: C.E. PUNTA LOMITAS_EXP | D59: PUN LOM_EXP-BL2 | E59: EÓLICA | F59: 98.4 | G59: 84.15 | H59: 33.8 | I59: 60.6 | J59: 70.6 | K59: 58.2 | L59: 158.1 | M59: 184.75 | N59: 174.55 | O59: 149.95 | P59: 94.75 | Q59: 89.05 | R59: 92.45 | S59: 89.7 | T59: 90.25 | U59: 60.6 | V59: 66.85 | W59: 90.8 | X59: 210.65 | Y59: 153.65 | Z59: 129.35 | AA59: 127.55 | AB59: 128.5 | AC59: 106.5 | AD59: 53.15 | AE59: 2656.9
B60: ENGIE | C60: C.H. QUITARACSA | D60: CENTRAL | E60: HIDROELÉCTRICA | F60: 1800.35 | G60: 2646.35 | H60: 2696.9 | I60: 2692.95 | J60: 2048.55 | K60: 2695.4 | L60: 2693 | M60: 2690.65 | N60: 2689.7 | O60: 2696.7 | P60: 2277.3 | Q60: 2005.8 | R60: 2068.5 | S60: 2671.3 | T60: 2690.35 | U60: 2661.4 | V60: 1839.15 | W60: 1972.35 | X60: 1967.15 | Y60: 1658.8 | Z60: 1733.2 | AA60: 1581.55 | AB60: 1450 | AC60: 1650.7 | AD60: 2067.8 | AE60: 55645.9
B61: ENGIE | C61: C.H. YUNCAN | D61: CENTRAL | E61: HIDROELÉCTRICA | F61: 2668.75 | G61: 3146.2 | H61: 3160.15 | I61: 3169.95 | J61: 3162.05 | K61: 3086.9 | L61: 2896.45 | M61: 3154.05 | N61: 3147.05 | O61: 3136.45 | P61: 2823.6 | Q61: 2843.2 | R61: 3128.7 | S61: 3147.75 | T61: 2892.7 | U61: 2920.1 | V61: 2776.2 | W61: 2584.85 | X61: 2461.85 | Y61: 2968.8 | Z61: 3070.9 | AA61: 3140.6 | AB61: 3127.35 | AC61: 3133.05 | AD61: 3136.85 | AE61: 74884.5
B62: ENGIE | C62: C.S. INTIPAMPA | D62: CENTRAL | E62: SOLAR | F62: 276.8 | G62: 239.4 | H62: 187.95 | I62: 218.3 | J62: 239.15 | K62: 174.4 | L62: 248.2 | M62: 341 | N62: 337.4 | O62: 395.5 | P62: 384.95 | Q62: 390.7 | R62: 385.5 | S62: 375.45 | T62: 363.05 | U62: 358.7 | V62: 176.2 | W62: 325.05 | X62: 322.5 | Y62: 281.6 | Z62: 240 | AA62: 185.25 | AB62: 273 | AC62: 257.15 | AD62: 266.5 | AE62: 7243.7
B63: ENGIE | C63: C.T. CHILCA 1 | D63: TG1 | E63: TERMOELÉCTRICA | F63: 2419.9 | G63: 3695.6 | N63: 354.9 | O63: 277.95 | R63: 475.3 | S63: 483.45 | W63: 1518.3 | X63: 394.35 | AE63: 9619.75
B64: ENGIE | C64: C.T. CHILCA 1 | D64: TG2 | E64: TERMOELÉCTRICA | F64: 2390.45 | G64: 82.1 | H64: 1769.5 | I64: 568.3 | J64: 704.45 | K64: 1146.55 | L64: 312.65 | N64: 504.15 | O64: 282.05 | R64: 1185.6 | S64: 1266.75 | T64: 525.55 | U64: 645.05 | V64: 2276.95 | W64: 1864.45 | X64: 821 | Y64: 623.8 | Z64: 1818.95 | AA64: 554.75 | AD64: 233.85 | AE64: 19576.9
B65: ENGIE | C65: C.T. CHILCA 1 | D65: TG3 | E65: TERMOELÉCTRICA | H65: 1835.4 | I65: 574.55 | J65: 598.85 | K65: 808.7 | O65: 1047 | R65: 1313.45 | AE65: 6177.95
B66: ENGIE | C66: C.T. CHILCA 1 | D66: TV | E66: TERMOELÉCTRICA | F66: 2850.4 | G66: 1646 | AE66: 4496.4
B67: ENGIE | C67: C.T. CHILCA 2 | D67: TG41 | E67: TERMOELÉCTRICA | J67: 182.9 | P67: 145.15 | Q67: 214.1 | W67: 150.2 | Z67: 164.9 | AA67: 468.55 | AB67: 129.85 | AE67: 1455.65
B68: ENGIE | C68: C.T. CHILCA 2 | D68: TV42 | E68: TERMOELÉCTRICA | AE68: 0
B69: ENGIE | C69: C.T. NEPI | D69: TG41 | E69: TERMOELÉCTRICA | U69: 838.7 | V69: 2363.7 | W69: 391.65 | AE69: 3594.05
B70: ENGIE | C70: C.T. NEPI | D70: TG42 | E70: TERMOELÉCTRICA | AE70: 0
B71: ENGIE | C71: C.T. NEPI | D71: TG43 | E71: TERMOELÉCTRICA | AE71: 0
B72: ENGIE | C72: C.T. RF PLANTA ILO | D72: TG1 | E72: TERMOELÉCTRICA | H72: 367.5 | AE72: 367.5
B73: ENGIE | C73: C.T. RF PLANTA ILO | D73: TG2 | E73: TERMOELÉCTRICA | AC73: 361.5 | AE73: 361.5
B74: ENGIE | C74: C.T. RF PLANTA ILO | D74: TG3 | E74: TERMOELÉCTRICA | J74: 403.7 | AE74: 403.7
B75: FENIX POWER PERÚ | C75: C.T. FENIX | D75: GT11 | E75: TERMOELÉCTRICA | F75: 3326.015 | G75: 3251.75 | H75: 3326.1 | I75: 3474.85 | J75: 646.2 | K75: 3160.05 | L75: 3562.15 | O75: 252 | P75: 2747.3 | Q75: 1428.6 | R75: 3722.45 | S75: 3961.8 | T75: 3804.9 | Y75: 2585.65 | Z75: 4003.8 | AA75: 4018.35 | AB75: 3927.1 | AC75: 3105.1392 | AE75: 54304.204
B76: FENIX POWER PERÚ | C76: C.T. FENIX | D76: GT12 | E76: TERMOELÉCTRICA | F76: 3332.585 | G76: 3258.15 | H76: 3332.05 | I76: 3542.65 | J76: 1382.55 | K76: 3910.85 | L76: 3686.2 | M76: 3731.8985 | N76: 3661.85 | O76: 3940.25 | P76: 3722.85 | Q76: 1294.4 | R76: 3728.8 | S76: 3970.45 | T76: 3866.3 | U76: 2470.7 | Y76: 3053.05 | Z76: 3690.9 | AA76: 4026.4 | AB76: 3936.25 | AC76: 3453.7755 | AD76: 2285.3 | AE76: 73278.209
B77: FENIX POWER PERÚ | C77: C.T. FENIX | D77: TV10 | E77: TERMOELÉCTRICA | F77: 3823.35 | G77: 3823.75 | H77: 3872 | I77: 3959.9 | J77: 596.15 | K77: 3672.25 | L77: 4004 | M77: 1994.0565 | N77: 1966.1 | O77: 2035.45 | P77: 3442.95 | Q77: 1211.8 | R77: 4080.15 | S77: 4224.3 | T77: 4122.1 | U77: 1199.75 | Y77: 2804.3 | Z77: 3372 | AA77: 4260.85 | AB77: 4217.15 | AC77: 3698.694 | AD77: 1127.95 | AE77: 67509.001
B78: GENERACIÓN ANDINA S.A.C. | C78: C.H. 8 DE AGOSTO | D78: CENTRAL | E78: HIDROELÉCTRICA | F78: 485.75 | G78: 428.15 | H78: 474.45 | I78: 501.2 | J78: 499.85 | K78: 501.3 | L78: 502.2 | M78: 502.8 | N78: 501.6 | O78: 502.65 | P78: 499.6 | Q78: 497.8 | R78: 497.9 | S78: 497.45 | T78: 467.65 | U78: 487.5 | V78: 484.9 | W78: 441.59429 | X78: 362.1 | Y78: 447.1 | Z78: 503.9 | AA78: 504 | AB78: 504 | AC78: 504 | AD78: 504 | AE78: 12103.444
B79: GENERACIÓN ANDINA S.A.C. | C79: C.H. EL CARMEN | D79: CENTRAL | E79: HIDROELÉCTRICA | F79: 177.2 | G79: 190.15 | H79: 200.05 | I79: 180.2 | J79: 195.1 | K79: 184.55 | L79: 193.8 | M79: 192.85 | N79: 191.5 | O79: 145.6 | P79: 45.75 | Q79: 200 | R79: 173.45 | S79: 149.35 | T79: 136.05 | U79: 140.8 | V79: 133.45 | W79: 118.7288 | X79: 115.95 | Y79: 120.25 | Z79: 160.6 | AA79: 129.55 | AB79: 166.85 | AC79: 171.6 | AD79: 148 | AE79: 3961.3788
B80: GENERADORA DE ENERGÍA DEL PERÚ | C80: C.H. ÁNGEL I | D80: CENTRAL | E80: HIDROELÉCTRICA | F80: 329.25 | G80: 489.6 | H80: 489.6 | I80: 489.6 | J80: 489.6 | K80: 489.6 | L80: 489.6 | M80: 489.6 | N80: 489.6 | O80: 469.2 | P80: 489.6 | Q80: 489.6 | R80: 489.6 | S80: 489.6 | T80: 489.6 | U80: 484.4 | V80: 489.6 | W80: 480 | X80: 240 | Y80: 480 | Z80: 450 | AA80: 480 | AB80: 480 | AC80: 480 | AD80: 480 | AE80: 11707.25
B81: GENERADORA DE ENERGÍA DEL PERÚ | C81: C.H. ÁNGEL II | D81: CENTRAL | E81: HIDROELÉCTRICA | F81: 331.75 | G81: 489.6 | H81: 489.6 | I81: 489.6 | J81: 489.6 | K81: 489.6 | L81: 489.6 | M81: 489.6 | N81: 478.3 | O81: 462.5 | P81: 489.6 | Q81: 489.6 | R81: 484.5 | S81: 489.6 | T81: 489.6 | U81: 484.4 | V81: 489.6 | W81: 475 | X81: 235 | Y81: 480 | Z81: 437.5 | AA81: 470 | AB81: 480 | AC81: 470.6 | AD81: 480 | AE81: 11644.75
B82: GENERADORA DE ENERGÍA DEL PERÚ | C82: C.H. ÁNGEL III | D82: CENTRAL | E82: HIDROELÉCTRICA | F82: 229.4 | G82: 244.8 | H82: 244.8 | I82: 244.8 | J82: 244.8 | K82: 244.8 | L82: 244.8 | M82: 244.8 | N82: 241.1 | O82: 142.8 | T82: 122.4 | U82: 244.8 | V82: 239.7 | W82: 240 | X82: 110.5 | Y82: 240 | Z82: 222.25 | AA82: 239 | AB82: 239.4 | AC82: 339.5 | AD82: 478.45 | AE82: 5042.9
B83: GENERADORA DE ENERGÍA DEL PERÚ | C83: C.H. LA JOYA | D83: CENTRAL | E83: HIDROELÉCTRICA | F83: 144.45 | G83: 141.75 | H83: 176.25 | I83: 174.1 | J83: 167.05 | K83: 181.15 | L83: 183.2 | M83: 157.05 | N83: 148.3 | O83: 149.1 | P83: 152.85 | Q83: 145.5 | R83: 142.95 | S83: 142.05 | T83: 140.45 | U83: 138.9 | V83: 173.7 | W83: 179.1 | X83: 175.55 | Y83: 184.75 | Z83: 192.4 | AA83: 168.1 | AB83: 150 | AC83: 165.4 | AD83: 114.45 | AE83: 3988.55
B84: GM OPERACIONES S.A.C. | C84: CT REFINERIA TALARA | D84: TV1 REF TALARA | E84: TERMOELÉCTRICA | K84: 65.7 | L84: 465.35 | M84: 328.55 | N84: 364.25 | O84: 471.9 | P84: 514.3 | Q84: 564.54 | R84: 595.2 | S84: 609.25 | T84: 606.3 | U84: 611.25 | V84: 624.95 | W84: 641.5 | X84: 510.25 | Y84: 351.95 | Z84: 359.15 | AA84: 359.7 | AB84: 360.2 | AC84: 372.95 | AD84: 395.35 | AE84: 9172.59
B85: GM OPERACIONES S.A.C. | C85: CT REFINERIA TALARA | D85: TV2 REF TALARA | E85: TERMOELÉCTRICA | F85: 796.2 | G85: 802.5 | H85: 837.05 | I85: 909.62 | J85: 904.05 | K85: 862.1 | L85: 722.75 | M85: 925.4 | N85: 926.5 | O85: 917.35 | P85: 887.2 | Q85: 871.88 | R85: 852.3 | S85: 835.1 | T85: 830.8 | U85: 831.65 | V85: 858.25 | W85: 847.5 | X85: 853 | Y85: 855.45 | Z85: 857.2 | AA85: 865.35 | AB85: 867.8 | AC85: 876.5 | AD85: 852.7 | AE85: 21446.2
B86: GR CORTARRAMA SOCIEDAD ANONIMA CERRADA | C86: C.S. MATARANI | D86: C.S. MATARANI | E86: SOLAR | F86: 538.8 | G86: 418.65 | H86: 457.4 | I86: 457.85 | J86: 742.5 | K86: 640.35 | L86: 688.7 | M86: 789.4 | N86: 775.45 | O86: 774.2 | P86: 806.2 | Q86: 783.65 | R86: 757.65 | S86: 799.4 | T86: 802.55 | U86: 813.3 | V86: 714.25 | W86: 609.75 | X86: 620.75 | Y86: 665.55 | Z86: 503.9 | AA86: 671.55 | AB86: 536.75 | AC86: 686.85 | AD86: 645.3 | AE86: 16700.7
B87: GR PAINO SOCIEDAD ANONIMA CERRADA | C87: C.E. HUAMBOS | D87: CENTRAL | E87: EÓLICA | F87: 61.9 | G87: 35.15 | H87: 23.85 | I87: 54.9 | J87: 127 | K87: 84.3 | L87: 43.3 | M87: 38.6 | N87: 74.3 | O87: 47.65 | P87: 163.55 | Q87: 161.9 | R87: 31.85 | S87: 93.25 | T87: 160.25 | U87: 124.15 | V87: 82.75 | W87: 54.85 | X87: 69.7 | Y87: 59.45 | Z87: 42.55 | AA87: 214.15 | AB87: 290.2 | AC87: 274.05 | AD87: 230.9 | AE87: 2644.5
B88: GR TARUCA SOCIEDAD ANONIMA CERRADA | C88: C.E. DUNA | D88: CENTRAL | E88: EÓLICA | F88: 56.9 | G88: 33.1 | H88: 39.4 | I88: 111.35 | J88: 188.4 | K88: 139.65 | L88: 63.4 | M88: 38.45 | N88: 49.65 | O88: 41.5 | P88: 225.7 | Q88: 205.2 | R88: 34.65 | S88: 70.05 | T88: 141.35 | U88: 89.75 | V88: 72.25 | W88: 56.5 | X88: 55.75 | Y88: 45.3 | Z88: 59.75 | AA88: 282.3 | AB88: 341.15 | AC88: 339.65 | AD88: 290.3 | AE88: 3071.45
B89: HIDROCAÑETE S.A. | C89: C.H. IMPERIAL | D89: CENTRAL | E89: HIDROELÉCTRICA | F89: 73.65 | G89: 81.05 | H89: 78.8 | I89: 79.95 | J89: 75.95 | K89: 80.5 | L89: 83.35 | M89: 83.4 | N89: 84.35 | O89: 84.25 | P89: 84.6 | Q89: 83.85 | R89: 84.45 | S89: 83.65 | T89: 85.3 | U89: 84.5 | V89: 83.55 | W89: 82.75 | X89: 82.3 | Y89: 83 | Z89: 82.6 | AA89: 81.9 | AB89: 79.65 | AC89: 81.95 | AD89: 82.15 | AE89: 2051.45
B90: HIDROELECTRICA HUANCHOR S.A.C. | C90: C.H. HUANCHOR | D90: CENTRAL | E90: HIDROELÉCTRICA | F90: 437 | G90: 438.4 | H90: 431.6 | I90: 432.55 | J90: 435.15 | K90: 439.7 | L90: 440.1 | M90: 440.4 | N90: 439.6 | O90: 440.45 | P90: 440.4 | Q90: 439.15 | R90: 440.5 | S90: 441 | T90: 439.25 | U90: 440.8 | V90: 441.25 | W90: 441.25 | X90: 440.6 | Y90: 441.05 | Z90: 440.75 | AA90: 440.7 | AB90: 438.75 | AC90: 439.85 | AD90: 440.85 | AE90: 10981.1
B91: HUAURA POWER GROUP S.A. | C91: C.H. YARUCAYA | D91: CENTRAL | E91: HIDROELÉCTRICA | F91: 451.15 | G91: 450.5 | H91: 425.05 | I91: 127.2 | J91: 250.7 | K91: 451.2 | L91: 451.1 | M91: 450.45 | N91: 451.2 | O91: 451.05 | P91: 449.74 | Q91: 450.85 | R91: 450.9 | S91: 408.735 | T91: 448.8 | U91: 428.05 | V91: 451.2 | W91: 451.2 | X91: 421 | Y91: 450.65 | Z91: 448.8 | AA91: 415.05 | AB91: 450.7 | AC91: 449.2 | AD91: 431.75 | AE91: 10566.225
B92: INFRAESTRUCTURAS Y ENERGIAS DEL PERU S.A.C. | C92: C.T. RF PTO MALDONADO | D92: CENTRAL | E92: TERMOELÉCTRICA | AE92: 0
B93: INFRAESTRUCTURAS Y ENERGIAS DEL PERU S.A.C. | C93: C.T. RF PUCALLPA | D93: CENTRAL | E93: TERMOELÉCTRICA | AE93: 0
B94: INLAND ENERGY SAC | C94: C.H. SANTA TERESA | D94: CENTRAL | E94: HIDROELÉCTRICA | F94: 2173 | G94: 1849.5 | H94: 2179.65 | I94: 1920.05 | J94: 1893.3 | K94: 2162.5 | L94: 2164.2 | M94: 2169.3 | N94: 2173.3 | O94: 2164.15 | P94: 2172.75 | Q94: 1768.4 | R94: 2162.75 | S94: 2173.095 | T94: 2069 | U94: 2173.3 | V94: 2171.55 | W94: 2186 | X94: 2179.3 | Y94: 2182.35 | Z94: 2176.85 | AA94: 2156.45 | AB94: 2152.9 | AC94: 2160.8 | AD94: 2166.25 | AE94: 52900.695
B95: INVERSIONES SHAQSHA S.A.C. | C95: C.H. PARIAC | D95: CENTRAL | E95: HIDROELÉCTRICA | N95: 17.55 | O95: 83.6 | P95: 98.75 | Q95: 99.25 | R95: 102 | S95: 100.75 | T95: 101.2 | U95: 101.7 | V95: 101.25 | W95: 101.15 | X95: 101.15 | Y95: 103.15 | Z95: 103.2 | AA95: 102.85 | AB95: 103 | AC95: 103.15 | AD95: 103.05 | AE95: 1626.75
B96: KALLPA GENERACION S.A. | C96: C.H. CERRO DEL AGUILA | D96: CENTRAL | E96: HIDROELÉCTRICA | F96: 10008.95 | G96: 13509.65 | H96: 13475.45 | I96: 13406.25 | J96: 13426.15 | K96: 13440.05 | L96: 13427.6 | M96: 13408.95 | N96: 13425.7 | O96: 13273.25 | P96: 13413.7 | Q96: 13404.15 | R96: 12851.8 | S96: 13407.95 | T96: 13388.45 | U96: 13737.95 | V96: 13760.7 | W96: 13519.6 | X96: 11115.5 | Y96: 13398.2 | Z96: 13401.7 | AA96: 13439.5 | AB96: 13387.9 | AC96: 13373.55 | AD96: 13388.7 | AE96: 329791.35
B97: KALLPA GENERACION S.A. | C97: C.T. KALLPA | D97: TG1 | E97: TERMOELÉCTRICA | I97: 2346.15 | J97: 3078.3 | K97: 3219.7 | L97: 3035.85 | M97: 2982.7 | N97: 3067.85 | O97: 3322.05 | P97: 3056.95 | Q97: 3063.4 | R97: 3222.65 | S97: 3400.75 | T97: 3131.8 | U97: 3359.65 | V97: 3706.3 | W97: 3682.5 | X97: 3629 | Y97: 3531.75 | Z97: 3614.3 | AA97: 3337.95 | AB97: 3307.9 | AC97: 2941.6 | AD97: 3075.8 | AE97: 71114.9
B98: KALLPA GENERACION S.A. | C98: C.T. KALLPA | D98: TG2 | E98: TERMOELÉCTRICA | G98: 1165.5 | H98: 4076 | I98: 3216.25 | J98: 3091.45 | K98: 3217.3 | L98: 3026.8 | M98: 2977.8 | N98: 3073 | O98: 3370.8 | P98: 3064.1 | Q98: 3067.15 | R98: 3236.6 | S98: 3454 | T98: 3135.95 | U98: 3401.15 | V98: 3753.6 | W98: 3820.75 | X98: 3714.65 | Y98: 3636.9 | Z98: 3653.5 | AA98: 3370.95 | AB98: 3355.6 | AC98: 2932.75 | AD98: 3075.55 | AE98: 77888.1
B99: KALLPA GENERACION S.A. | C99: C.T. KALLPA | D99: TG3 | E99: TERMOELÉCTRICA | G99: 3573.15 | H99: 4104.95 | I99: 3226.3 | J99: 3094.85 | K99: 3219.05 | L99: 3029.6 | M99: 2974.85 | N99: 3071.7 | O99: 2956.1 | P99: 3066.1 | Q99: 3067.1 | R99: 3238.95 | S99: 3453.1 | T99: 3138 | U99: 3401.55 | V99: 3754.45 | W99: 3823.65 | X99: 3713.6 | Y99: 3578.8 | Z99: 3657.35 | AA99: 3369.4 | AB99: 3355.85 | AC99: 2936.45 | AD99: 3073.5 | AE99: 79878.4
B100: KALLPA GENERACION S.A. | C100: C.T. KALLPA | D100: TV | E100: TERMOELÉCTRICA | G100: 2135.75 | H100: 4227.75 | I100: 5016.8 | J100: 5432.85 | K100: 5552.2 | L100: 5405.7 | M100: 5333.9 | N100: 5439.7 | O100: 5450.95 | P100: 5405.4 | Q100: 5429.3 | R100: 5614.6 | S100: 5780.95 | T100: 5514.1 | U100: 5758.35 | V100: 6036.9 | W100: 5996.7 | X100: 5988.6 | Y100: 5890.85 | Z100: 5958.9 | AA100: 5654.2 | AB100: 5659.4 | AC100: 5338.4 | AD100: 5461.45 | AE100: 129483.7
B101: KALLPA GENERACION S.A. | C101: C.T. LAS FLORES | D101: TG1 | E101: TERMOELÉCTRICA | F101: 454.1 | G101: 3712.5 | H101: 4774.05 | I101: 4599.6 | J101: 4401.6 | K101: 3835.95 | L101: 4318.35 | M101: 4046.45 | N101: 4041.85 | O101: 4524.3 | P101: 4427.85 | Q101: 4195.75 | R101: 4222.4 | S101: 4905.55 | T101: 4816.85 | U101: 4240.45 | V101: 4298.55 | W101: 4401.8 | X101: 4738.65 | Y101: 4887.5 | Z101: 4897.25 | AA101: 4762.05 | AB101: 4448.25 | AC101: 3970.35 | AD101: 4715.05 | AE101: 106637.05
B102: KALLPA GENERACION S.A. | C102: C.T. LAS FLORES | D102: TV | E102: TERMOELÉCTRICA | F102: 262.75 | G102: 1823.75 | H102: 2503.5 | I102: 2442.5 | J102: 2377.45 | K102: 1992.5 | L102: 2337.85 | M102: 2234.95 | N102: 2213.8 | O102: 2422.8 | P102: 2387.8 | Q102: 2292.2 | R102: 2298.6 | S102: 2588 | T102: 2567.7 | U102: 2313.05 | V102: 2352.05 | W102: 2383.35 | X102: 2533.45 | Y102: 2580.5 | Z102: 2597 | AA102: 2528.6 | AB102: 2404.8 | AC102: 2208.7 | AD102: 2507.3 | AE102: 57154.95
B103: KALLPA GENERACION S.A. | C103: M.C.H. CERRO DEL AGUILA | D103: CENTRAL | E103: HIDROELÉCTRICA | F103: 246.85 | G103: 251.7 | H103: 251.3 | I103: 252 | J103: 251.45 | K103: 245.85 | L103: 250.65 | M103: 251.6 | N103: 251.2 | O103: 252 | P103: 251.1 | Q103: 250.85 | R103: 221.05 | S103: 252.45 | T103: 251.7 | U103: 252.1 | V103: 252.1 | W103: 252.4 | X103: 252.5 | Y103: 252.7 | Z103: 252.05 | AA103: 253.1 | AB103: 251.55 | AC103: 251.5 | AD103: 252.35 | AE103: 6254.1
...

Sheet G_AREAS
B3: sábado, 25 de Enero del 2025
B5: HORA | C5: RESUMEN DE GENERACIÓN POR ÁREAS DEL SEIN | D5: RESUMEN DE GENERACIÓN POR ÁREAS DEL SEIN | E5: RESUMEN DE GENERACIÓN POR ÁREAS DEL SEIN | F5: RESUMEN DE GENERACIÓN POR ÁREAS DEL SEIN | G5: RESUMEN DE GENERACIÓN POR ÁREAS DEL SEIN | H5: RESUMEN DE GENERACIÓN POR ÁREAS DEL SEIN | I5: RESUMEN DE GENERACIÓN POR ÁREAS DEL SEIN | J5: RESUMEN DE GENERACIÓN POR ÁREAS DEL SEIN | K5: RESUMEN DE GENERACIÓN POR ÁREAS DEL SEIN | L5: RESUMEN DE GENERACIÓN POR ÁREAS DEL SEIN | M5: RESUMEN DE GENERACIÓN POR ÁREAS DEL SEIN | N5: RESUMEN DE GENERACIÓN POR ÁREAS DEL SEIN | O5: RESUMEN DE GENERACIÓN POR ÁREAS DEL SEIN | P5: RESUMEN DE GENERACIÓN POR ÁREAS DEL SEIN | Q5: RESUMEN DE GENERACIÓN POR ÁREAS DEL SEIN | R5: RESUMEN DE GENERACIÓN POR ÁREAS DEL SEIN | S5: HORA | T5: GENERACIÓN POR TIPO DE GENERACIÓN | U5: GENERACIÓN POR TIPO DE GENERACIÓN | V5: GENERACIÓN POR TIPO DE GENERACIÓN | W5: GENERACIÓN POR TIPO DE GENERACIÓN | X5: GENERACIÓN POR TIPO DE GENERACIÓN | Y5: HORA | Z5: GENERACIÓN POR TIPO DE GENERACIÓN | AA5: GENERACIÓN POR TIPO DE GENERACIÓN | AB5: GENERACIÓN POR TIPO DE GENERACIÓN | AC5: GENERACIÓN POR TIPO DE GENERACIÓN | AD5: GENERACIÓN POR TIPO DE GENERACIÓN
C6: NORTE | D6: NORTE | E6: NORTE | F6: NORTE | G6: CENTRO | H6: CENTRO | I6: CENTRO | J6: CENTRO | K6: SUR | L6: SUR | M6: SUR | N6: SUR | O6: GENERACIÓN INTEGRANTES COES | P6: GENERACIÓN INTEGRANTES COES | Q6: GENERACIÓN INTEGRANTES COES | R6: GENERACIÓN INTEGRANTES COES | T6: INTEGRANTES COES | U6: INTEGRANTES COES | V6: INTEGRANTES COES | W6: INTEGRANTES COES | X6: INTEGRANTES COES | Z6: INTEGRANTES COES RER | AA6: INTEGRANTES COES RER | AB6: INTEGRANTES COES RER | AC6: INTEGRANTES COES RER | AD6: INTEGRANTES COES RER
C7: GENERACIÓN HIDROELÉCTRICA NORTE | D7: GENERACIÓN TERMOELÉCTRICA NORTE | E7: GENERACIÓN SOLAR NORTE | F7: GENERACIÓN EÓLICA NORTE | G7: GENERACIÓN HIDROELÉCTRICA CENTRO | H7: GENERACIÓN TERMOELÉCTRICA CENTRO | I7: GENERACIÓN SOLAR CENTRO | J7: GENERACIÓN EÓLICA CENTRO | K7: GENERACIÓN HIDROELÉCTRICA SUR | L7: GENERACIÓN TERMOELÉCTRICA SUR | M7: GENERACIÓN SOLAR SUR | N7: GENERACIÓN EÓLICA SUR | O7: GENERACIÓN COES NORTE | P7: GENERACIÓN COES CENTRO | Q7: GENERACIÓN COES SUR | R7: TOTAL GENERACION | T7: HIDROELÉCTRICA | U7: TERMOELÉCTRICA | V7: SOLAR | W7: EÓLICA | X7: TOTAL GENERACION | Z7: HIDROELÉCTRICA RER | AA7: TERMOELÉCTRICA RER | AB7: SOLAR RER | AC7: EÓLICA RER | AD7: TOTAL RER
B8: 00:30 | C8: 534.6 | D8: 132.1 | E8: 0 | F8: 96.3 | G8: 3714.8 | H8: 1671.3 | I8: 0 | J8: 179.9 | K8: 496.392 | L8: 0 | M8: 0 | N8: 0 | O8: 763 | P8: 5566 | Q8: 496.392 | R8: 6825.392 | S8: 00:30 | T8: 4745.792 | U8: 1803.4 | V8: 0 | W8: 276.2 | X8: 6825.392 | Y8: 00:30 | Z8: 357.2 | AA8: 55.4 | AB8: 0 | AC8: 276.2 | AD8: 688.8
B9: 01:00 | C9: 532.8 | D9: 131.8 | E9: 0 | F9: 101.2 | G9: 3608.9 | H9: 1623.8 | I9: 0 | J9: 211.7 | K9: 481.495 | L9: 0 | M9: 0 | N9: 0 | O9: 765.8 | P9: 5444.4 | Q9: 481.495 | R9: 6691.695 | S9: 01:00 | T9: 4623.195 | U9: 1755.6 | V9: 0 | W9: 312.9 | X9: 6691.695 | Y9: 01:00 | Z9: 346.2 | AA9: 56 | AB9: 0 | AC9: 312.9 | AD9: 715.1
B10: 01:30 | C10: 536.8 | D10: 132.5 | E10: 0 | F10: 106.2 | G10: 3551.4 | H10: 1526.6 | I10: 0 | J10: 213.4 | K10: 491.38 | L10: 0 | M10: 0 | N10: 0 | O10: 775.5 | P10: 5291.4 | Q10: 491.38 | R10: 6558.28 | S10: 01:30 | T10: 4579.58 | U10: 1659.1 | V10: 0 | W10: 319.6 | X10: 6558.28 | Y10: 01:30 | Z10: 345.8 | AA10: 57.5 | AB10: 0 | AC10: 319.6 | AD10: 722.9
B11: 02:00 | C11: 539 | D11: 134.1 | E11: 0 | F11: 91.3 | G11: 3722 | H11: 1369.3 | I11: 0 | J11: 194.7 | K11: 491.631 | L11: 0 | M11: 0 | N11: 0 | O11: 764.4 | P11: 5286 | Q11: 491.631 | R11: 6542.031 | S11: 02:00 | T11: 4752.631 | U11: 1503.4 | V11: 0 | W11: 286 | X11: 6542.031 | Y11: 02:00 | Z11: 345.4 | AA11: 58.2 | AB11: 0 | AC11: 286 | AD11: 689.6
B12: 02:30 | C12: 524.7 | D12: 133.7 | E12: 0 | F12: 77.5 | G12: 3520.5 | H12: 1497 | I12: 0 | J12: 171.6 | K12: 472.601 | L12: 0 | M12: 0 | N12: 0 | O12: 735.9 | P12: 5189.1 | Q12: 472.601 | R12: 6397.601 | S12: 02:30 | T12: 4517.801 | U12: 1630.7 | V12: 0 | W12: 249.1 | X12: 6397.601 | Y12: 02:30 | Z12: 341.9 | AA12: 58.3 | AB12: 0 | AC12: 249.1 | AD12: 649.3
B13: 03:00 | C13: 540.5 | D13: 134 | E13: 0 | F13: 73.4 | G13: 3594.6 | H13: 1385.6 | I13: 0 | J13: 211.1 | K13: 495.577 | L13: 0 | M13: 0 | N13: 0 | O13: 747.9 | P13: 5191.3 | Q13: 495.577 | R13: 6434.777 | S13: 03:00 | T13: 4630.677 | U13: 1519.6 | V13: 0 | W13: 284.5 | X13: 6434.777 | Y13: 03:00 | Z13: 332.4 | AA13: 59.4 | AB13: 0 | AC13: 284.5 | AD13: 676.3
B14: 03:30 | C14: 535.2 | D14: 133.6 | E14: 0 | F14: 69.4 | G14: 3642.7 | H14: 1354.7 | I14: 0 | J14: 201.8 | K14: 479.742 | L14: 0 | M14: 0 | N14: 0 | O14: 738.2 | P14: 5199.2 | Q14: 479.742 | R14: 6417.142 | S14: 03:30 | T14: 4657.642 | U14: 1488.3 | V14: 0 | W14: 271.2 | X14: 6417.142 | Y14: 03:30 | Z14: 332.5 | AA14: 59.2 | AB14: 0 | AC14: 271.2 | AD14: 662.9
B15: 04:00 | C15: 529.7 | D15: 131 | E15: 0 | F15: 69.2 | G15: 3477.1 | H15: 1423.5 | I15: 0 | J15: 213.5 | K15: 481.285 | L15: 0 | M15: 0 | N15: 0 | O15: 729.9 | P15: 5114.1 | Q15: 481.285 | R15: 6325.285 | S15: 04:00 | T15: 4488.085 | U15: 1554.5 | V15: 0 | W15: 282.7 | X15: 6325.285 | Y15: 04:00 | Z15: 331.8 | AA15: 57.1 | AB15: 0 | AC15: 282.7 | AD15: 671.6
B16: 04:30 | C16: 539.6 | D16: 134.4 | E16: 0 | F16: 59.1 | G16: 3543.3 | H16: 1456.7 | I16: 0 | J16: 227.7 | K16: 496.964 | L16: 0 | M16: 0 | N16: 0 | O16: 733.1 | P16: 5227.7 | Q16: 496.964 | R16: 6457.764 | S16: 04:30 | T16: 4579.864 | U16: 1591.1 | V16: 0 | W16: 286.8 | X16: 6457.764 | Y16: 04:30 | Z16: 332.9 | AA16: 59.6 | AB16: 0 | AC16: 286.8 | AD16: 679.3
B17: 05:00 | C17: 530.1 | D17: 130.2 | E17: 0 | F17: 60.7 | G17: 3461.6 | H17: 1464 | I17: 0 | J17: 209.1 | K17: 478.875 | L17: 0 | M17: 0 | N17: 0 | O17: 721 | P17: 5134.7 | Q17: 478.875 | R17: 6334.575 | S17: 05:00 | T17: 4470.575 | U17: 1594.2 | V17: 0 | W17: 269.8 | X17: 6334.575 | Y17: 05:00 | Z17: 331.8 | AA17: 56.6 | AB17: 0 | AC17: 269.8 | AD17: 658.2
B18: 05:30 | C18: 502.7 | D18: 129.9 | E18: 0 | F18: 65.8 | G18: 3518.2 | H18: 1593.2 | I18: 0 | J18: 175.6 | K18: 484.772 | L18: 0 | M18: 1 | N18: 0 | O18: 698.4 | P18: 5287 | Q18: 485.772 | R18: 6471.172 | S18: 05:30 | T18: 4505.672 | U18: 1723.1 | V18: 1 | W18: 241.4 | X18: 6471.172 | Y18: 05:30 | Z18: 332.5 | AA18: 54.9 | AB18: 1 | AC18: 241.4 | AD18: 629.8
B19: 06:00 | C19: 498.4 | D19: 131.8 | E19: 0 | F19: 66.8 | G19: 3491.9 | H19: 1576.1 | I19: 0 | J19: 125.4 | K19: 480.224 | L19: 0 | M19: 32.6 | N19: 0 | O19: 697 | P19: 5193.4 | Q19: 512.824 | R19: 6403.224 | S19: 06:00 | T19: 4470.524 | U19: 1707.9 | V19: 32.6 | W19: 192.2 | X19: 6403.224 | Y19: 06:00 | Z19: 331.2 | AA19: 55.9 | AB19: 32.6 | AC19: 192.2 | AD19: 611.9
... B56: TOTAL MWh | C56: 12488.4 | D56: 3096.65 | E56: 2.1 | F56: 2099.5 | G56: 85566.85 | H56: 43172.306 | I56: 8.1 | J56: 5927.55 | K56: 12528.745 | L56: 4.25 | M56: 3584.7 | N56: 0 | O56: 17686.65 | P56: 134674.81 | Q56: 16117.694 | R56: 168479.15 | S56: TOTAL MWh | T56: 110583.99 | U56: 46273.206 | V56: 3594.9 | W56: 8027.05 | X56: 168479.15 | Y56: TOTAL MWh | Z56: 8225 | AA56: 1323.75 | AB56: 3594.9 | AC56: 8027.05 | AD56: 21170.7

Sheet HOP
B3: sábado, 25 de Enero del 2025
B5: Reporte de Horas de Operación
B6: Empresa | C6: Central | D6: Grupo | E6: Modo de Operación | F6: Inicio | G6: Final | H6: O. Arranque | I6: O. Parada | J6: Tipo Operación | K6: Ensayo de Potencia Efectiva | L6: Ensayo de Potencia Mínima | M6: Sistema | N6: Lim. Transm. | O6: Causa | P6: Observación
B7: AGRO INDUSTRIAL PARAMONGA S.A. | C7: C.T. PARAMONGA | D7: CENTRAL | E7: PARAMONGA - BAGAZO | F7: 25/01/2025 00:00:00 | G7: 26/01/2025 00:00:00 | J7: NO IDENTIFICADO | O7: ...
B8: AGROAURORA S.A.C. | C8: C.T. MAPLE ETANOL | D8: CENTRAL | E8: MAPLE- BAGAZO | F8: 25/01/2025 00:00:00 | G8: 26/01/2025 00:00:00 | J8: NO IDENTIFICADO | O8: ...
B9: AGROINDUSTRIAS SAN JACINTO S.A.A. | C9: C.T. SAN JACINTO | D9: CENTRAL | E9: SAN_JACINTO - BAGAZO | F9: 25/01/2025 00:00:00 | G9: 26/01/2025 00:00:00 | J9: NO IDENTIFICADO | O9: ...
B10: BIOENERGIA DEL CHIRA S.A. | C10: C.T. CAÑA BRAVA | D10: CENTRAL | E10: CANA BRAVA TV1 & TV2 - BAGAZO | F10: 25/01/2025 00:00:00 | G10: 26/01/2025 00:00:00 | J10: NO IDENTIFICADO | O10: ...
B11: EGASA | C11: C.T. CHILINA DIESEL | D11: TG | E11: CHILINA TG - D2 | F11: 25/01/2025 11:13:00 | G11: 25/01/2025 12:12:00 | H11: 25/01/2025 11:00:00 | I11: 25/01/2025 12:10:00 | J11: A MINIMA CARGA | O11: ... | P11: Operó para evitar sobrecarga L-3060/3061 y L-3080/3081 por mantto L-1126.
B12: EGESUR | C12: C.T. INDEPENDENCIA | D12: CENTRAL | E12: INDEPENDENCIA GAS | F12: 25/01/2025 08:52:00 | G12: 25/01/2025 13:05:00 | H12: 25/01/2025 08:49:00 | J12: POR POTENCIA O ENERGIA | O12: ...
B13: EGESUR | C13: C.T. INDEPENDENCIA | D13: CENTRAL | E13: INDEPENDENCIA GAS | F13: 25/01/2025 13:05:00 | G13: 25/01/2025 16:05:00 | I13: 25/01/2025 15:54:00 | J13: POR POTENCIA O ENERGIA | N13: xLT | O13: ...
B14: ENEL GENERACION PIURA S.A. | C14: C.T. MALACAS 1 | D14: CENTRAL | E14: MALACAS1 TG6 - GAS | F14: 25/01/2025 00:00:00 | G14: 26/01/2025 00:00:00 | J14: POR POTENCIA O ENERGIA | O14: ...
B15: ENGIE | C15: C.T. CHILCA 1 | D15: TG2 | E15: CHILCA1 TG2 - GAS | F15: 25/01/2025 09:24:00 | G15: 25/01/2025 10:49:00 | H15: 25/01/2025 09:06:00 | J15: POR POTENCIA O ENERGIA | O15: ...
B16: ENGIE | C16: C.T. CHILCA 1 | D16: TG2 | E16: CHILCA1 TG2 - GAS | F16: 25/01/2025 10:49:00 | G16: 25/01/2025 11:36:00 | I16: 25/01/2025 11:24:00 | J16: A MINIMA CARGA | O16: ...
B17: FENIX POWER PERÚ | C17: C.T. FENIX | D17: GT12 | E17: FENIX GT12 - GAS | F17: 25/01/2025 07:38:00 | G17: 25/01/2025 09:24:00 | H17: 25/01/2025 05:56:00 | J17: A MINIMA CARGA | O17: ... | P17: En proceso de acople.
B18: FENIX POWER PERÚ | C18: C.T. FENIX | D18: GT12 | E18: FENIX GT12 - GAS | F18: 25/01/2025 09:24:00 | G18: 25/01/2025 09:46:00 | J18: POR POTENCIA O ENERGIA | O18: ...
B19: FENIX POWER PERÚ | C19: C.T. FENIX | D19: CENTRAL | E19: FENIX CCOMB GT12 - GAS | F19: 25/01/2025 09:46:00 | G19: 25/01/2025 16:58:00 | J19: POR POTENCIA O ENERGIA | O19: ...
B20: FENIX POWER PERÚ | C20: C.T. FENIX | D20: CENTRAL | E20: FENIX CCOMB GT12 - GAS | F20: 25/01/2025 16:58:00 | G20: 25/01/2025 18:42:00 | J20: A MINIMA CARGA | O20: ...
B21: FENIX POWER PERÚ | C21: C.T. FENIX | D21: CENTRAL | E21: FENIX CCOMB GT12 - GAS | F21: 25/01/2025 18:42:00 | G21: 25/01/2025 23:17:00 | I21: 25/01/2025 22:55:00 | J21: POR POTENCIA O ENERGIA | O21: ...
B22: FENIX POWER PERÚ | C22: C.T. FENIX | D22: GT12 | E22: FENIX GT12 - GAS | F22: 25/01/2025 23:17:00 | G22: 25/01/2025 23:22:00 | J22: A MINIMA CARGA | O22: ...
B23: GM OPERACIONES S.A.C. | C23: CT REFINERIA TALARA | D23: TV1 REF TALARA | E23: REF_TALARA TV1 - NLH_RFG | F23: 25/01/2025 00:00:00 | G23: 26/01/2025 00:00:00 | J23: POR COGENERACION | O23: ...
B24: GM OPERACIONES S.A.C. | C24: CT REFINERIA TALARA | D24: TV2 REF TALARA | E24: REF_TALARA TV2 - NLH_RFG | F24: 25/01/2025 00:00:00 | G24: 26/01/2025 00:00:00 | J24: POR COGENERACION | O24: ...
B25: KALLPA GENERACION S.A. | C25: C.T. KALLPA | D25: CENTRAL | E25: KALLPA CCOMB TG1 & TG2 & TG3 - GAS | F25: 25/01/2025 00:00:00 | G25: 25/01/2025 06:30:00 | J25: POR RSF | O25: ...
B26: KALLPA GENERACION S.A. | C26: C.T. KALLPA | D26: CENTRAL | E26: KALLPA CCOMB TG1 & TG2 & TG3 - GAS | F26: 25/01/2025 06:30:00 | G26: 25/01/2025 06:53:00 | J26: POR POTENCIA O ENERGIA | O26: ...
B27: KALLPA GENERACION S.A. | C27: C.T. KALLPA | D27: CENTRAL | E27: KALLPA CCOMB TG1 & TG2 & TG3 - GAS | F27: 25/01/2025 06:53:00 | G27: 25/01/2025 08:00:00 | J27: POR RSF | O27: ...
B28: KALLPA GENERACION S.A. | C28: C.T. KALLPA | D28: CENTRAL | E28: KALLPA CCOMB TG1 & TG2 & TG3 - GAS | F28: 25/01/2025 08:00:00 | G28: 25/01/2025 13:05:00 | J28: POR POTENCIA O ENERGIA | O28: ...
B29: KALLPA GENERACION S.A. | C29: C.T. KALLPA | D29: CENTRAL | E29: KALLPA CCOMB TG1 & TG2 & TG3 - GAS | F29: 25/01/2025 13:05:00 | G29: 25/01/2025 19:00:00 | J29: POR RSF | O29: ...
B30: KALLPA GENERACION S.A. | C30: C.T. KALLPA | D30: CENTRAL | E30: KALLPA CCOMB TG1 & TG2 & TG3 - GAS | F30: 25/01/2025 19:00:00 | G30: 25/01/2025 21:00:00 | J30: POR POTENCIA O ENERGIA | O30: ...
B31: KALLPA GENERACION S.A. | C31: C.T. KALLPA | D31: CENTRAL | E31: KALLPA CCOMB TG1 & TG2 & TG3 - GAS | F31: 25/01/2025 21:00:00 | G31: 25/01/2025 22:30:00 | J31: POR RSF | O31: ...
