Workbook

Sheet EVENTOS
B3: jueves, 19 de Junio del 2025
B5: INFORMACIÓN DE EVENTOS PRINCIPALES EN SUS INSTALACIONES
B6: TIPO DE EVENTO | C6: EMPRESA | D6: UBICACIÓN | E6: TIPO DE EQUIPO | F6: EQUIPO | G6: INICIO | H6: FINAL | I6: DESCRIPCIÓN | J6: MW INDISP. | K6: INTERRUPCIÓN (SI/NO) | L6: TENSIÓN DE FALLA (kV)
B7: EVENTO | C7: CONELSUR LT SAC | D7: PORTILLO | E7: SUBESTACION | F7: SS.EE. | G7: 19/06/2025 00:00:00 | H7: 20/06/2025 00:00:00 | I7: DECLARACIÓN DE SITUACIÓN EXCEPCIONAL EN LA S.E. PORTILLO DE 60 kV | K7: NO
B8: EVENTO | C8: RED DE ENERGIA DEL PERU S.A. | D8: TINGO MARÍA - AUCAYACU | E8: LINEA DE TRANSMISION | F8: L-1122 | G8: 19/06/2025 18:42:00 | H8: 19/06/2025 20:11:00 | I8: DECLARACIÓN DE SITUACIÓN EXCEPCIONAL EN LA LINEA L-1122 (TINGO MARIA - AUCAYACU) DE 138 KV | K8: NO

Sheet RESTRIC_OPE
B3: jueves, 19 de Junio del 2025
B5: RESTRICCIONES OPERATIVAS
B6: FECHA | C6: HORA INICIO | D6: HORA FINAL | E6: EMPRESA | F6: UBICACIÓN | G6: T.Eq. | H6: EQUIPO | I6: DESCRIPCIÓN
B7: 19/06/2025 | C7: 00:00 | D7: 24:00 | E7: EGASA | F7: C.H. CHARCANI II | G7: GH | H7: G2 | I7: El Grupo N°02 esta operando con una potencia no mayor a 0.07MW en referencia a 0.18MW de su potencia efectiva, con el fin de no generar daños mayores hasta la reparación de su cojinete.
B8: 19/06/2025 | C8: 00:00 | D8: 24:00 | E8: EGASA | F8: S.E. CONVERTIDOR | G8: BARRA | H8: BARRA138KV | I8: EGASA limitó la capacidad del transformador 138 kV/33 kV a 50 MVA por deterioro del aislamiento.
B9: 19/06/2025 | C9: 00:00 | D9: 24:00 | E9: ENEL GENERACION PIURA S.A. | F9: C.T. MALACAS | G9: CT | H9: CENTRAL | I9: De acuerdo con la comunicación vía correo del día 24.10.2024. ENEL GENERACIÓN PIURA informa una restricción de potencia para alcanzar 105 MW en simultaneo (TG6+TGN4).
B10: 19/06/2025 | C10: 00:00 | D10: 24:00 | E10: ENEL GENERACION PIURA S.A. | F10: C.T. MALACAS | G10: GT | H10: TG4 | I10: De acuerdo a lo informado mediante correo electronico el día 19.05, la TG4 solo puede operar a máxima generación dos horas y el resto a carga a mínima carga.
B11: 19/06/2025 | C11: 00:00 | D11: 24:00 | E11: ENGIE | F11: C.E. PUNTA LOMITAS | G11: CE | H11: CENTRAL | I11: De acuerdo a la carta ENG/737-2024 (Exp:202400007555). Limitación de cables de media tensión a 100 MW de los transformadores PLT1 y PLT2 de la CE Punta Lomitas. Quedan limitados a 200 MW la generación de CE Punta Lomitas y Punta Lomitas Extensión.
B12: 19/06/2025 | C12: 00:00 | D12: 24:00 | E12: ENGIE | F12: C.H. YUNCÁN | G12: GH | H12: G3 | I12: Según la carta N° ENG/ 198-2024 enviada por su representada, se opera de forma continua el G3 de la CH Yuncán, debido a la ejecución de mantenimientos necesarios para evitar daños en los sellos de seguridad de la válvula esférica del grupo.
B13: 19/06/2025 | C13: 00:00 | D13: 24:00 | E13: ENGIE | F13: C.T. CHILCA 1 | G13: CT | H13: CENTRAL | I13: Restricción de temperatura de la C.T Chilca, ver valor en el modelo de despacho.
B14: 19/06/2025 | C14: 00:00 | D14: 24:00 | E14: ENGIE | F14: C.T. CHILCA 1 | G14: CT | H14: CENTRAL | I14: Con carta ENG/971-2023, indica que no puede cumplir con las IO considerada en el PDO_17122023 dado que vulneran la seguridad de sus activos. Indican que se debe tomar TMO=168h.
B15: 19/06/2025 | C15: 00:00 | D15: 24:00 | E15: ENGIE | F15: C.T. CHILCA 2 | G15: CT | H15: CENTRAL | I15: Restricción de temperatura de la C.T Chilca2, ver valor en el modelo de despacho.
B16: 19/06/2025 | C16: 00:00 | D16: 24:00 | E16: ENGIE | F16: C.T. CHILCA 2 | G16: CT | H16: CENTRAL | I16: Con carta ENG/971-2023, indica que no puede cumplir con las IO considerada en el PDO_17122023 dado que vulneran la seguridad de sus activos. Indican que se debe tomar TMO=168h.
B17: 19/06/2025 | C17: 00:00 | D17: 24:00 | E17: FENIX POWER PERÚ | F17: C.T. FENIX | G17: CT | H17: CENTRAL | I17: De acuerdo con lo comunicado en el correo del día 06.05.2024, la CT Fenix cuenta con TMO de 168 hrs en todos su modos de operación.
... B42: 19/06/2025 | C42: 00:00 | D42: 24:00 | E42: TERMOSELVA | F42: C.T. AGUAYTÍA | G42: CT | H42: CENTRAL | I42: Disponibilidad de 12 MMSCF para la CT Aguaytía.

Sheet MANTENIMIENTO EJECUTADOS
B3: jueves, 19 de Junio del 2025
B5: Mantenimiento Ejecutado
B6: Empresa | C6: Ubicación | D6: Equipo | E6: Inicio | F6: Final | G6: Descripción | H6: MW Indisp. | I6: Prog. | J6: Dispon | K6: Interrupc. | L6: Tipo | M6: CodEq | N6: TipoEq_Osinerg
B7: AGROAURORA S.A.C. | C7: MAPLE ETANOL | D7: CENTRAL | E7: 19/06/2025 00:00 | F7: 20/06/2025 00:00 | G7: CENTRAL TERMOELECTRICA FUERA DE SERVICIO POR FALTA DE MATERIA PRIMA PARA LOS REQUERIMIENTOS DE CALOR UTIL EN FABRICA. | H7: 17 | I7: P | J7: F/S | K7: N | L7: OTROS | M7: 13417 | N7: G
B8: ATLANTICA TRANSMISION SUR S.A. | C8: MONTALVO | D8: ACOPLE 220 | E8: 19/06/2025 00:00 | F8: 20/06/2025 00:00 | G8: Proyecto Refuerzos: Reemplazo del HMI existente, Pruebas y Configuracion. No se contara con nivel 1 de operacion. | H8: 0 | I8: P | J8: E/S | K8: N | L8: P.ENERG | M8: 14767 | N8: T
B9: ATLANTICA TRANSMISION SUR S.A. | C9: MONTALVO | D9: BARRA A_220KV | E9: 19/06/2025 00:00 | F9: 20/06/2025 00:00 | G9: Proyecto Refuerzos: Indisponibilidad de la proteccion diferencial de barras 220 kV por Conexion de la nueva UB-87B hacia la UC existente,Configuracion y Pruebas. | H9: 0 | I9: P | J9: E/S | K9: N | L9: P.ENERG | M9: 13869 | N9: T
B10: ATLANTICA TRANSMISION SUR S.A. | C10: MONTALVO | D10: BARRA A_500KV | E10: 19/06/2025 00:00 | F10: 20/06/2025 00:00 | G10: Proyecto Refuerzos: Indisponibilidad de la proteccion diferencial de barras 500kV por conexion de nueva UB-87B hacia la UC existente, Configuracion y Pruebas. | H10: 0 | I10: P | J10: E/S | K10: N | L10: P.ENERG | M10: 13870 | N10: T
B11: ATLANTICA TRANSMISION SUR S.A. | C11: MONTALVO | D11: BARRA B_220kV | E11: 19/06/2025 00:00 | F11: 20/06/2025 00:00 | G11: Proyecto Refuerzos: Indisponibilidad de la proteccion diferencial de barras 220 kV por Conexion de la nueva UB-87B hacia la UC existente,Configuracion y Pruebas. | H11: 0 | I11: P | J11: E/S | K11: N | L11: P.ENERG | M11: 14765 | N11: T
B12: ATLANTICA TRANSMISION SUR S.A. | C12: MONTALVO | D12: BARRA B_500KV | E12: 19/06/2025 00:00 | F12: 20/06/2025 00:00 | G12: Proyecto Refuerzos: Indisponibilidad de la proteccion diferencial de barras 500kV por conexion de nueva UB-87B hacia la UC existente, Configuracion y Pruebas. | H12: 0 | I12: P | J12: E/S | K12: N | L12: P.ENERG | M12: 13871 | N12: T
B13: ATLANTICA TRANSMISION SUR S.A. | C13: MONTALVO | D13: CL-2057 | E13: 19/06/2025 00:00 | F13: 20/06/2025 00:00 | G13: Proyecto Refuerzos: Reemplazo del HMI existente, Pruebas y Configuracion. No se contara con nivel 1 de operacion. | H13: 0 | I13: P | J13: E/S | K13: N | L13: P.ENERG | M13: 13812 | N13: T
B14: ATLANTICA TRANSMISION SUR S.A. | C14: MONTALVO | D14: CL-AUT-5671_500 | E14: 19/06/2025 00:00 | F14: 20/06/2025 00:00 | G14: Proyecto Refuerzos: Reemplazo del HMI existente, Pruebas y Configuracion. No se contara con nivel 1 de operacion en INT-5671, INT-5652 y SAT-5671. | H14: 0 | I14: P | J14: E/S | K14: N | L14: P.ENERG | M14: 13809 | N14: T
B15: ATLANTICA TRANSMISION SUR S.A. | C15: MONTALVO | D15: INT-5652 | E15: 19/06/2025 00:00 | F15: 20/06/2025 00:00 | G15: Proyecto Refuerzos: Indisponible por Implementacion de Conexion de corrientes, disparos, posiciones, enclavamientos hacia los equipos del nuevo Autotransformador. AUT-5671 en servicio solo por Barra A 500kV. | H15: 0 | I15: P | J15: F/S | K15: N | L15: P.ENERG | M15: 13765 | N15: T
B16: ATLANTICA TRANSMISION SUR S.A. | C16: OCONA | D16: INT-5450 | E16: 19/06/2025 00:00 | F16: 20/06/2025 00:00 | G16: Interruptor INT-5450 cerrado con restriccion operativa, REB-5450 en servicio y suministrando los SS.AA. de la S.E. Oco?a. | H16: 0 | I16: P | J16: E/S | K16: N | L16: OTROS | M16: 13761 | N16: T
B17: ATLANTICA TRANSMISION SUR S.A. | C17: OCONA | D17: INT-5462 | E17: 19/06/2025 00:00 | F17: 20/06/2025 00:00 | G17: Seccionador SBA-5462 fase T indisponible por problemas mecanicos, el seccionador permanece cerrado y bloqueado | H17: 0 | I17: P | J17: E/S | K17: N | L17: OTROS | M17: 13758 | N17: T
B18: ATLANTICA TRANSMISION SUR S.A. | C18: OCONA | D18: CL-BCS-5484 | E18: 19/06/2025 08:11 | F18: 19/06/2025 14:50 | G18: LIMPIEZA DE AISLAMIENTO | H18: 0 | I18: P | J18: F/S | K18: N | L18: PREV. | M18: 13868 | N18: T
... B168: TRANSMANTARO | C168: YARABAMBA | D168: BARRA A_220 kV | E168: 19/06/2025 14:37 | F168: 19/06/2025 16:25 | G168: FUERA DE SERVICIO DEBIDO A TRABAJOS DE CL-2066. (R0114238) | H168: 0 | I168: P | J168: F/S | K168: N | L168: OTROS | M168: 17444 | N168: T

Sheet INGRESO OC
A3: jueves, 19 de Junio del 2025
A5: INGRESO A OPERACIÓN COMERCIAL
A6: EMPRESA | B6: TIPO DE EQUIPO | C6: UBICACIÓN | D6: EQUIPO | E6: Fecha y hora de Ingreso a Operación Comercial

Sheet DESPACHO_EJECUTADO
B3: jueves, 19 de Junio del 2025
A5: POTENCIA ACTIVA EJECUTADA DE LAS UNIDADES DE GENERACIÓN DEL SEIN (MW) | FL5: CENTRALES NO INTEGRANTES COES
A6: FECHA | B6: HORA | C6: 65333 | D6: 101 | E6: 102 | F6: 42667 | G6: 42668 | H6: 126 | I6: 127 | J6: 138 | K6: 139 | L6: 197 | M6: 203 | N6: 204 | O6: 230 | P6: 209 | Q6: 56677 | R6: 796 | S6: 2146 | T6: 142 | U6: 143 | V6: 125 | W6: 187 | X6: 163 | Y6: 298 | Z6: 299 | AA6: 219 | AB6: 151 | AC6: 152 | AD6: 153 | AE6: 154 | AF6: 756 | AG6: 156 | AH6: 155 | AI6: 182 | AJ6: 212 | AK6: 758 | AL6: 263 | AM6: 265 | AN6: 775 | AO6: 777 | AP6: 2154 | AQ6: 150 | AR6: 149 | AS6: 188 | AT6: 2131 | AU6: 755 | AV6: 252 | AW6: 249 | AX6: 250 | AY6: 117 | AZ6: 267 | BA6: 268 | BB6: 119 | BC6: 120 | BD6: 189 | BE6: 122 | BF6: 266 | BG6: 337 | BH6: 338 | BI6: 251 | BJ6: 115 | BK6: 239 | BL6: 288 | BM6: 240 | BN6: 241 | BO6: 242 | BP6: 191 | BQ6: 194 | BR6: 196 | BS6: 207 | BT6: 236 | BU6: 795 | BV6: 285 | BW6: 995 | BX6: 996 | BY6: 997 | BZ6: 766 | CA6: 926 | CB6: 924 | CC6: 121 | CD6: 103 | CE6: 104 | CF6: 106 | CG6: 105 | CH6: 107 | CI6: 110 | CJ6: 109 | CK6: 144 | CL6: 113 | CM6: 114 | CN6: 193 | CO6: 208 | CP6: 786 | CQ6: 787 | CR6: 788 | CS6: 789 | CT6: 248 | CU6: 2159 | CV6: 303 | CW6: 59715 | CX6: 62255 | CY6: 1263 | CZ6: 61800 | DA6: 2194 | DB6: 216 | DC6: 198 | DD6: 49607 | DE6: 214 | DF6: 260 | DG6: 2152 | DH6: 2128 | DI6: 247 | DJ6: 228 | DK6: 2135 | DL6: 261 | DM6: 237 | DN6: 253 | DO6: 770 | DP6: 225 | DQ6: 2201 | DR6: 2171 | DS6: 760 | DT6: 235 | DU6: 238 | DV6: 2184 | DW6: 61855 | DX6: 223 | DY6: 226 | DZ6: 201 | EA6: 258 | EB6: 259 | EC6: 920 | ED6: 257 | EE6: 256 | EF6: 2148 | EG6: 58288 | EH6: 58289 | EI6: 58839 | EJ6: 58840 | EK6: 296 | EL6: 297 | EM6: 211 | EN6: 2175 | EO6: 2178 | EP6: 2181 | EQ6: 1262 | ER6: 63425 | ES6: 233 | ET6: 2150 | EU6: 2165 | EV6: 2161 | EW6: 61197 | EX6: 58851 | EY6: 234 | EZ6: 215 | FA6: 917 | FB6: 289 | FC6: 58333 | FD6: 58336 | FE6: 213 | FF6: 232 | FG6: 2190 | FH6: 202 | FI6: 58487 | FJ6: TOTAL COES | FL6: 221 | FM6: 222 | FN6: 224 | FO6: 2187 | FP6: 227 | FQ6: 49400 | FR6: 199 | FS6: 200 | FT6: TOTAL NO COES
C7: SUR | D7: CENTRO | E7: CENTRO | F7: NORTE | G7: NORTE | H7: NORTE | I7: NORTE | J7: CENTRO | K7: CENTRO | L7: CENTRO | M7: CENTRO | N7: CENTRO | O7: CENTRO | P7: CENTRO | Q7: CENTRO | R7: CENTRO | S7: CENTRO | T7: CENTRO | U7: CENTRO | V7: CENTRO | W7: CENTRO | X7: SUR | Y7: SUR | Z7: SUR | AA7: CENTRO | AB7: SUR | AC7: SUR | AD7: SUR | AE7: SUR | AF7: SUR | AG7: SUR | AH7: SUR | AI7: SUR | AJ7: CENTRO | AK7: NORTE | AL7: NORTE | AM7: NORTE | AN7: CENTRO | AO7: CENTRO | AP7: CENTRO | AQ7: CENTRO | AR7: CENTRO | AS7: CENTRO | AT7: CENTRO | AU7: SUR | AV7: CENTRO | AW7: CENTRO | AX7: CENTRO | AY7: CENTRO | AZ7: CENTRO | BA7: CENTRO | BB7: CENTRO | BC7: CENTRO | BD7: SUR | BE7: NORTE | BF7: CENTRO | BG7: CENTRO | BH7: CENTRO | BI7: CENTRO | BJ7: NORTE | BK7: NORTE | BL7: NORTE | BM7: SUR | BN7: SUR | BO7: SUR | BP7: CENTRO | BQ7: CENTRO | BR7: CENTRO | BS7: CENTRO | BT7: CENTRO | BU7: CENTRO | BV7: CENTRO | BW7: SUR | BX7: SUR | BY7: SUR | BZ7: NORTE | CA7: SUR | CB7: CENTRO | CC7: NORTE | CD7: CENTRO | CE7: CENTRO | CF7: CENTRO | CG7: CENTRO | CH7: CENTRO | CI7: CENTRO | CJ7: CENTRO | CK7: CENTRO | CL7: CENTRO | CM7: CENTRO | CN7: CENTRO | CO7: CENTRO | CP7: SUR | CQ7: SUR | CR7: SUR | CS7: SUR | CT7: CENTRO | CU7: CENTRO | CV7: CENTRO | CW7: CENTRO | CX7: SUR | CY7: NORTE | CZ7: NORTE | DA7: NORTE | DB7: NORTE | DC7: NORTE | DD7: SUR | DE7: CENTRO | DF7: CENTRO | DG7: CENTRO | DH7: NORTE | DI7: NORTE | DJ7: CENTRO | DK7: CENTRO | DL7: SUR | DM7: SUR | DN7: CENTRO | DO7: CENTRO | DP7: CENTRO | DQ7: CENTRO | DR7: CENTRO | DS7: CENTRO | DT7: SUR | DU7: CENTRO | DV7: CENTRO | DW7: NORTE | DX7: CENTRO | DY7: CENTRO | DZ7: NORTE | EA7: CENTRO | EB7: CENTRO | EC7: CENTRO | ED7: NORTE | EE7: NORTE | EF7: SUR | EG7: CENTRO | EH7: CENTRO | EI7: CENTRO | EJ7: CENTRO | EK7: CENTRO | EL7: CENTRO | EM7: SUR | EN7: SUR | EO7: SUR | EP7: SUR | EQ7: NORTE | ER7: SUR | ES7: SUR | ET7: SUR | EU7: CENTRO | EV7: CENTRO | EW7: CENTRO | EX7: SUR | EY7: SUR | EZ7: NORTE | FA7: CENTRO | FB7: NORTE | FC7: NORTE | FD7: NORTE | FE7: CENTRO | FF7: NORTE | FG7: NORTE | FH7: CENTRO | FI7: CENTRO | FL7: NORTE | FM7: CENTRO | FN7: NORTE | FO7: NORTE | FP7: NORTE | FQ7: NORTE | FR7: NORTE | FS7: NORTE
C8: HIDROELÉCTRICA | D8: HIDROELÉCTRICA | E8: HIDROELÉCTRICA | F8: TERMOELÉCTRICA | G8: TERMOELÉCTRICA | H8: HIDROELÉCTRICA | I8: HIDROELÉCTRICA | J8: TERMOELÉCTRICA | K8: TERMOELÉCTRICA | L8: TERMOELÉCTRICA | M8: TERMOELÉCTRICA | N8: TERMOELÉCTRICA | O8: TERMOELÉCTRICA | P8: TERMOELÉCTRICA | Q8: TERMOELÉCTRICA | R8: HIDROELÉCTRICA | S8: HIDROELÉCTRICA | T8: TERMOELÉCTRICA | U8: TERMOELÉCTRICA | V8: TERMOELÉCTRICA | W8: TERMOELÉCTRICA | X8: HIDROELÉCTRICA | Y8: HIDROELÉCTRICA | Z8: HIDROELÉCTRICA | AA8: TERMOELÉCTRICA | AB8: HIDROELÉCTRICA | AC8: HIDROELÉCTRICA | AD8: HIDROELÉCTRICA | AE8: HIDROELÉCTRICA | AF8: TERMOELÉCTRICA | AG8: TERMOELÉCTRICA | AH8: TERMOELÉCTRICA | AI8: HIDROELÉCTRICA | AJ8: HIDROELÉCTRICA | AK8: TERMOELÉCTRICA | AL8: TERMOELÉCTRICA | AM8: TERMOELÉCTRICA | AN8: HIDROELÉCTRICA | AO8: HIDROELÉCTRICA | AP8: HIDROELÉCTRICA | AQ8: HIDROELÉCTRICA | AR8: HIDROELÉCTRICA | AS8: HIDROELÉCTRICA | AT8: HIDROELÉCTRICA | AU8: HIDROELÉCTRICA | AV8: TERMOELÉCTRICA | AW8: TERMOELÉCTRICA | AX8: TERMOELÉCTRICA | AY8: HIDROELÉCTRICA | AZ8: HIDROELÉCTRICA | BA8: HIDROELÉCTRICA | BB8: HIDROELÉCTRICA | BC8: HIDROELÉCTRICA | BD8: HIDROELÉCTRICA | BE8: HIDROELÉCTRICA | BF8: HIDROELÉCTRICA | BG8: HIDROELÉCTRICA | BH8: HIDROELÉCTRICA | BI8: HIDROELÉCTRICA | BJ8: TERMOELÉCTRICA | BK8: TERMOELÉCTRICA | BL8: TERMOELÉCTRICA | BM8: TERMOELÉCTRICA | BN8: TERMOELÉCTRICA | BO8: TERMOELÉCTRICA | BP8: HIDROELÉCTRICA | BQ8: TERMOELÉCTRICA | BR8: TERMOELÉCTRICA | BS8: TERMOELÉCTRICA | BT8: TERMOELÉCTRICA | BU8: TERMOELÉCTRICA | BV8: TERMOELÉCTRICA | BW8: TERMOELÉCTRICA | BX8: TERMOELÉCTRICA | BY8: TERMOELÉCTRICA | BZ8: HIDROELÉCTRICA | CA8: TERMOELÉCTRICA | CB8: TERMOELÉCTRICA | CC8: HIDROELÉCTRICA | CD8: HIDROELÉCTRICA | CE8: HIDROELÉCTRICA | CF8: HIDROELÉCTRICA | CG8: HIDROELÉCTRICA | CH8: HIDROELÉCTRICA | CI8: TERMOELÉCTRICA | CJ8: TERMOELÉCTRICA | CK8: TERMOELÉCTRICA | CL8: TERMOELÉCTRICA | CM8: TERMOELÉCTRICA | CN8: TERMOELÉCTRICA | CO8: TERMOELÉCTRICA | CP8: TERMOELÉCTRICA | CQ8: TERMOELÉCTRICA | CR8: TERMOELÉCTRICA | CS8: TERMOELÉCTRICA | CT8: TERMOELÉCTRICA | CU8: TERMOELÉCTRICA | CV8: SOLAR | CW8: EÓLICA | CX8: SOLAR | CY8: EÓLICA | CZ8: SOLAR | DA8: HIDROELÉCTRICA | DB8: HIDROELÉCTRICA | DC8: HIDROELÉCTRICA | DD8: HIDROELÉCTRICA | DE8: HIDROELÉCTRICA | DF8: HIDROELÉCTRICA | DG8: HIDROELÉCTRICA | DH8: HIDROELÉCTRICA | DI8: HIDROELÉCTRICA | DJ8: HIDROELÉCTRICA | DK8: HIDROELÉCTRICA | DL8: SOLAR | DM8: SOLAR | DN8: EÓLICA | DO8: EÓLICA | DP8: TERMOELÉCTRICA | DQ8: TERMOELÉCTRICA | DR8: TERMOELÉCTRICA | DS8: TERMOELÉCTRICA | DT8: SOLAR | DU8: HIDROELÉCTRICA | DV8: HIDROELÉCTRICA | DW8: HIDROELÉCTRICA | DX8: HIDROELÉCTRICA | DY8: HIDROELÉCTRICA | DZ8: HIDROELÉCTRICA | EA8: HIDROELÉCTRICA | EB8: HIDROELÉCTRICA | EC8: HIDROELÉCTRICA | ED8: EÓLICA | EE8: EÓLICA | EF8: SOLAR | EG8: EÓLICA | EH8: EÓLICA | EI8: EÓLICA | EJ8: EÓLICA | EK8: HIDROELÉCTRICA | EL8: HIDROELÉCTRICA | EM8: HIDROELÉCTRICA | EN8: HIDROELÉCTRICA | EO8: HIDROELÉCTRICA | EP8: HIDROELÉCTRICA | EQ8: EÓLICA | ER8: SOLAR | ES8: SOLAR | ET8: SOLAR | EU8: HIDROELÉCTRICA | EV8: EÓLICA | EW8: EÓLICA | EX8: SOLAR | EY8: SOLAR | EZ8: HIDROELÉCTRICA | FA8: HIDROELÉCTRICA | FB8: TERMOELÉCTRICA | FC8: TERMOELÉCTRICA | FD8: TERMOELÉCTRICA | FE8: TERMOELÉCTRICA | FF8: TERMOELÉCTRICA | FG8: TERMOELÉCTRICA | FH8: TERMOELÉCTRICA | FI8: TERMOELÉCTRICA | FL8: HIDROELÉCTRICA | FM8: HIDROELÉCTRICA | FN8: HIDROELÉCTRICA | FO8: HIDROELÉCTRICA | FP8: TERMOELÉCTRICA | FQ8: TERMOELÉCTRICA | FR8: HIDROELÉCTRICA | FS8: HIDROELÉCTRICA
C9: HYDRO GLOBAL PERÚ S.A.C. | D9: ELECTROPERU | E9: ELECTROPERU | F9: ELECTROPERU | G9: ELECTROPERU | H9: ORAZUL ENERGY PERÚ | I9: ORAZUL ENERGY PERÚ | J9: TERMOSELVA | K9: TERMOSELVA | L9: KALLPA GENERACION S.A. | M9: KALLPA GENERACION S.A. | N9: KALLPA GENERACION S.A. | O9: KALLPA GENERACION S.A. | P9: KALLPA GENERACION S.A. | Q9: KALLPA GENERACION S.A. | R9: KALLPA GENERACION S.A. | S9: KALLPA GENERACION S.A. | T9: SHOUGESA | U9: SHOUGESA | V9: SHOUGESA | W9: SHOUGESA | X9: EGEMSA | Y9: EGESUR | Z9: EGESUR | AA9: EGESUR | AB9: EGASA | AC9: EGASA | AD9: EGASA | AE9: EGASA | AF9: EGASA | AG9: EGASA | AH9: EGASA | AI9: SAN GABAN | AJ9: CELEPSA | AK9: MINERA CERRO VERDE | AL9: PLANTA DE RESERVA FRIA DE GENERACION DE ETEN S.A. | AM9: PLANTA DE RESERVA FRIA DE GENERACION DE ETEN S.A. | AN9: EMPRESA DE GENERACION HUALLAGA | AO9: EMPRESA DE GENERACION HUALLAGA | AP9: LA VIRGEN | AQ9: CHINANGO S.A.C. | AR9: CHINANGO S.A.C. | AS9: HIDROELECTRICA HUANCHOR S.A.C. | AT9: CELEPSA RENOVABLES S.R.L. | AU9: INLAND ENERGY SAC | AV9: FENIX POWER PERÚ | AW9: FENIX POWER PERÚ | AX9: FENIX POWER PERÚ | AY9: STATKRAFT S.A | AZ9: STATKRAFT S.A | BA9: STATKRAFT S.A | BB9: STATKRAFT S.A | BC9: STATKRAFT S.A | BD9: STATKRAFT S.A | BE9: STATKRAFT S.A | BF9: STATKRAFT S.A | BG9: CENTRALES SANTA ROSA S.A.C. | BH9: CENTRALES SANTA ROSA S.A.C. | BI9: EMPRESA DE GENERACION HUANZA | BJ9: ENEL GENERACION PIURA S.A. | BK9: ENEL GENERACION PIURA S.A. | BL9: ENEL GENERACION PIURA S.A. | BM9: ENGIE | BN9: ENGIE | BO9: ENGIE | BP9: ENGIE | BQ9: ENGIE | BR9: ENGIE | BS9: ENGIE | BT9: ENGIE | BU9: ENGIE | BV9: ENGIE | BW9: ENGIE | BX9: ENGIE | BY9: ENGIE | BZ9: ENGIE | CA9: INFRAESTRUCTURAS Y ENERGIAS DEL PERU S.A.C. | CB9: INFRAESTRUCTURAS Y ENERGIAS DEL PERU S.A.C. | CC9: INVERSIONES SHAQSHA S.A.C. | CD9: ORYGEN PERU S.A.A. | CE9: ORYGEN PERU S.A.A. | CF9: ORYGEN PERU S.A.A. | CG9: ORYGEN PERU S.A.A. | CH9: ORYGEN PERU S.A.A. | CI9: ORYGEN PERU S.A.A. | CJ9: ORYGEN PERU S.A.A. | CK9: ORYGEN PERU S.A.A. | CL9: ORYGEN PERU S.A.A. | CM9: ORYGEN PERU S.A.A. | CN9: ORYGEN PERU S.A.A. | CO9: ORYGEN PERU S.A.A. | CP9: SAMAY I S.A.C | CQ9: SAMAY I S.A.C | CR9: SAMAY I S.A.C | CS9: SAMAY I S.A.C | CT9: TERMOCHILCA S.A.C. | CU9: TERMOCHILCA S.A.C. | CV9: COLCA SOLAR S.A.C. | CW9: ENERGIA RENOVABLE DEL SUR S.A. | CX9: GR CORTARRAMA SOCIEDAD ANONIMA CERRADA | CY9: GR TARUCA SOCIEDAD ANONIMA CERRADA | CZ9: KONDU SAC | DA9: PERUANA DE INVERSIONES EN ENERGIAS RENOVABLES S.A. | DB9: ORAZUL ENERGY PERÚ | DC9: ORAZUL ENERGY PERÚ | DD9: SAN GABAN | DE9: MAJA ENERGIA S.A.C. | DF9: EMPRESA DE GENERACION ELECTRICA CANCHAYLLO SAC | DG9: EMPRESA DE GENERACION ELECTRICA SANTA ANA S.A.C. | DH9: EMPRESA ELECTRICA AGUA AZUL | DI9: EMPRESA ELECTRICA RIO DOBLE | DJ9: HIDROCAÑETE S.A. | DK9: HUAURA POWER GROUP S.A. | DL9: MOQUEGUA FV S.A.C. | DM9: PANAMERICANA SOLAR SAC. | DN9: PARQUE EOLICO MARCONA S.A.C. | DO9: PARQUE EOLICO TRES HERMANAS S.A.C. | DP9: PETRAMAS | DQ9: PETRAMAS | DR9: PETRAMAS | DS9: PETRAMAS | DT9: TACNA SOLAR SAC. | DU9: ELECTRICA YANAPAMPA SAC | DV9: ANDEAN POWER S.A.C. | DW9: ASOCIACIÓN SANTA LUCIA DE CHACAS | DX9: ATRIA ENERGIA S.A.C. | DY9: EGEJUNIN | DZ9: EGEJUNIN | EA9: EGEJUNIN | EB9: EGEJUNIN | EC9: EMPRESA DE GENERACION ELECTRICA RIO BAÑOS S.A.C. | ED9: ENERGÍA EÓLICA S.A. | EE9: ENERGÍA EÓLICA S.A. | EF9: ENGIE | EG9: ENGIE | EH9: ENGIE | EI9: ENGIE | EJ9: ENGIE | EK9: GENERACIÓN ANDINA S.A.C. | EL9: GENERACIÓN ANDINA S.A.C. | EM9: GENERADORA DE ENERGÍA DEL PERÚ | EN9: GENERADORA DE ENERGÍA DEL PERÚ | EO9: GENERADORA DE ENERGÍA DEL PERÚ | EP9: GENERADORA DE ENERGÍA DEL PERÚ | EQ9: GR PAINO SOCIEDAD ANONIMA CERRADA | ER9: JOYA SOLAR S.A.C. | ES9: MAJES ARCUS S.A.C. | ET9: ORYGEN PERU S.A.A. | EU9: ORYGEN PERU S.A.A. | EV9: ORYGEN PERU S.A.A. | EW9: ORYGEN PERU S.A.A. | EX9: ORYGEN PERU S.A.A. | EY9: REPARTICIÓN ARCUS S.A.C. | EZ9: SINERSA | FA9: SINERSA | FB9: BIOENERGIA DEL CHIRA S.A. | FC9: GM OPERACIONES S.A.C. | FD9: GM OPERACIONES S.A.C. | FE9: AGRO INDUSTRIAL PARAMONGA S.A. | FF9: AGROAURORA S.A.C. | FG9: AGROINDUSTRIAS SAN JACINTO S.A.A. | FH9: SDF ENERGIA SAC | FI9: SDF ENERGIA SAC | FL9: UNACEM PERU S.A. | FM9: ELECTRO ORIENTE | FN9: AGUAS Y ENERGIA PERU | FO9: ELECTRO ZAÑA S.A.C. | FP9: ELECTRONOROESTE S.A. | FQ9: SDE PIURA | FR9: SINERSA | FS9: SINERSA
C10: SAN GABAN III | D10: MANTARO | E10: RESTITUCION | F10: TUMBES MAK 1 | G10: TUMBES MAK 2 | H10: CARHUAQUERO | I10: CAÑON DEL PATO | J10: AGUAYTIA TG1 | K10: AGUAYTIA TG2 | L10: KALLPA TG1 | M10: KALLPA TG2 | N10: KALLPA TG3 | O10: KALLPA TV | P10: LFLORES TG1 | Q10: LFLORES TV | R10: CERRO DEL AGUILA | S10: CERRODELAGUILAG4 | T10: SHOUGESA TV1 | U10: SHOUGESA TV2 | V10: SHOUGESA TV3 | W10: SHOUGESA CUMMINS | X10: MACHUPICCHU | Y10: ARICOTA 1 | Z10: ARICOTA 2 | AA10: INDEPENDENCIA | AB10: CHARCANI I,II,III | AC10: CHARCANI IV | AD10: CHARCANI V | AE10: CHARCANI VI | AF10: CHILINA TG | AG10: MOLLENDO 1, 2, 3 | AH10: CHILINA (SULZ 1,2) | AI10: SAN GABAN II | AJ10: PLATANAL | AK10: RECKA | AL10: RF ETEN TG1 | AM10: RF ETEN TG2 | AN10: CHAGLLA GP1 | AO10: CHAGLLA | AP10: LA VIRGEN | AQ10: CHIMAY | AR10: YANANGO | AS10: HUANCHOR | AT10: MARAÑON | AU10: STA TERESA | AV10: FENIX GT11 | AW10: FENIX GT12 | AX10: FENIX TV10 | AY10: YAUPI | AZ10: OROYA | BA10: PACHACHACA | BB10: MALPASO | BC10: CAHUA | BD10: ARCATA | BE10: GALLITO CIEGO | BF10: CHEVES | BG10: SANTA ROSA 1 | BH10: SANTA ROSA 2 | BI10: HUANZA | BJ10: MALACAS2 TG4 | BK10: MALACAS3 TG 5 | BL10: MALACAS1 TG6 | BM10: RF ILO2 TG1 | BN10: RF ILO2 TG2 | BO10: RF ILO2 TG3 | BP10: YUNCAN | BQ10: CHILCA1 TG1 | BR10: CHILCA1 TG2 | BS10: CHILCA1 TG3 | BT10: CHILCA-TV | BU10: CHILCA2 TG41 | BV10: CHILCA2-TV | BW10: CTNEPI_TG41 | BX10: CTNEPI_TG42 | BY10: CTNEPI_TG43 | BZ10: QUITARACSA | CA10: RF PTO MALDONADO | CB10: RF PUCALLPA | CC10: PARIAC | CD10: HUINCO | CE10: MATUCANA | CF10: MOYOPAMPA | CG10: CALLAHUANCA | CH10: HUAMPANI | CI10: STA ROSA WEST TG7 | CJ10: UTI_5 | CK10: UTI_6 | CL10: VENTANILLA 3 | CM10: VENTANILLA 4 | CN10: VENTANILLA TV | CO10: STAROSA TG8 | CP10: PTO_BRVO TG1 | CQ10: PTO_BRVO TG2 | CR10: PTO_BRVO TG3 | CS10: PTO_BRVO TG4 | CT10: OLLEROS TG1 | CU10: OLLEROS TV | CV10: CS YARUCAYA | CW10: SAN JUAN | CX10: MATARANI | CY10: DUNA | CZ10: CARHUAQUERO (CS) | DA10: MANTA I | DB10: CARHUAQUERO4 | DC10: CAÑA BRAVA | DD10: TUPURI | DE10: RONCADOR | DF10: CANCHAYLLO | DG10: RENOVANDESH1 | DH10: POTRERO | DI10: PIZARRAS | DJ10: NIMPERIAL | DK10: YARUCAYA | DL10: MOQUEGUA-SOLAR | DM10: PANAMERICANA-SOLAR | DN10: PQE-EOLICO-MARCONA | DO10: PQE-EOLICO-3-HERMANAS | DP10: HUAYCOLORO | DQ10: CALLAO | DR10: DONA_CATALINA | DS10: LAGRINGAV | DT10: TACNA-SOLAR | DU10: YANAPAMPA | DV10: CARHUAC | DW10: HUALLIN | DX10: PURMACANA | DY10: HUASAHUASI | DZ10: STACRUZ_1_2 | EA10: RUNATULLO_II | EB10: RUNATULLO_III | EC10: RUCUY | ED10: PQE-EOLICO-TALARA | EE10: PQE-EOLICO-CUPISNIQUE | EF10: INTIPAMPA | EG10: PUNTA LOMITAS-BL1 | EH10: PUNTA LOMITAS-BL2 | EI10: PUN LOMITAS_EXP-BL1 | EJ10: PUN LOMITAS_EXP-BL2 | EK10: 8AGOSTO | EL10: EL CARMEN | EM10: LA JOYA | EN10: ANGEL_I | EO10: ANGEL_II | EP10: ANGEL_III | EQ10: HUAMBOS | ER10: SAN MARTIN SOLAR | ES10: MAJES | ET10: RUBI | EU10: CH_HER1 | EV10: WAYRA-I | EW10: WAYRA EXTENSION | EX10: CLEMESI | EY10: REPARTICION | EZ10: POECHOS2 | FA10: CHANCAY | FB10: CANA BRAVA | FC10: REFINERIA TALARA TV1 | FD10: REFINERÍA TALARA TV2 | FE10: PARAMONGA | FF10: MAPLE | FG10: SAN_JACINTO | FH10: OQUENDO TG1 | FI10: OQUENDO TV1 | FJ10: MW | FL10: CARPAPATA | FM10: CENTRALES ELOR | FN10: PIAS1 | FO10: ZANA | FP10: TABLAZO | FQ10: TALLANCA | FR10: CURUMUY | FS10: POECHOS1 | FT10: MW
A11: 19/06/2025 | B11: 00:30 | C11: 97.8 | D11: 600.8 | E11: 198.6 | H11: 89.8 | I11: 113.9 | J11: 25.9 | L11: 176.2 | M11: 176.4 | N11: 175.4 | O11: 265 | R11: 393.4 | S11: 4.9 | X11: 162.9 | Y11: 7 | Z11: 5.3 | AA11: 0 | AB11: 6.08 | AC11: 8.64 | AD11: 66.66 | AH11: 0 | AI11: 69.6 | AJ11: 199.6 | AN11: 6.5 | AO11: 226.5 | AP11: 74.3 | AQ11: 138.4 | AR11: 42 | AS11: 18.6 | AT11: 19.8 | AU11: 88.9 | AV11: 180.2 | AW11: 180.3 | AX11: 183.2 | AY11: 109.3 | AZ11: 8.2 | BA11: 2.4 | BB11: 33.9 | BC11: 40.3 | BD11: 4 | BE11: 0 | BF11: 37.9 | BI11: 48 | BL11: 0 | BP11: 86.6 | BQ11: 157.1 | BR11: 0 | BS11: 0 | BT11: 69.1 | BY11: 0 | CB11: 0 | CC11: 1.8 | CD11: 52.4 | CE11: 98.8 | CF11: 61.8 | CG11: 70.8 | CH11: 29.7 | CL11: 145.2 | CM11: 146.5 | CN11: 147.8 | CV11: 0 | CW11: 113.1 | CX11: 0 | CY11: 15.6 | CZ11: 0 | DA11: 17.7 | DB11: 9.9 | DC11: 5.6 | DD11: 0.8 | DE11: 1.5 | DF11: 2.6 | DG11: 20 | DH11: 20 | DI11: 15.6 | DJ11: 3.5 | DK11: 18.4 | DL11: 0 | DM11: 0 | DN11: 32 | DO11: 85.4 | DP11: 4.5 | DQ11: 2.2 | DR11: 2.1 | DS11: 1.4 | DT11: 0 | DU11: 2.9 | DV11: 13.1 | DW11: 2.3 | DY11: 19.7 | DZ11: 5.4 | EA11: 10.3 | EB11: 15.9 | EC11: 18.2 | ED11: 15.6 | EE11: 23.2 | EF11: 0 | EG11: 96.2 | EH11: 84.6 | EI11: 16.8 | EJ11: 8.2 | EK11: 16.4 | EL11: 6.6 | EN11: 9.2 | EO11: 9.8 | EP11: 10 | EQ11: 13.2 | ER11: 0 | ES11: 0 | ET11: 0 | EU11: 0.6 | EV11: 91.6 | EW11: 103.9 | EX11: 0 | EY11: 0 | EZ11: 5.5 | FA11: 19.3 | FB11: 9 | FC11: 43.1 | FD11: 13.3 | FE11: 17.1 | FG11: 7.5 | FJ11: 6434.58 | FL11: 24.2 | FM11: 7.944 | FO11: 12 | FP11: 27.24329 | FQ11: 18.91946 | FR11: 4.6 | FS11: 16 | FT11: 110.90675
A12: 19/06/2025 | B12: 01:00 | C12: 93.7 | D12: 602.1 | E12: 202.3 | H12: 89.9 | I12: 116.1 | J12: 25.7 | L12: 130.9 | M12: 129.6 | N12: 131.1 | O12: 224.6 | R12: 393.9 | S12: 4.9 | X12: 160.5 | Y12: 7.4 | Z12: 5.3 | AA12: 0 | AB12: 6.09 | AC12: 8.62 | AD12: 66.86 | AH12: 0 | AI12: 70 | AJ12: 149.4 | AN12: 6.5 | AO12: 291.2 | AP12: 74 | AQ12: 136.1 | AR12: 42.1 | AS12: 18.8 | AT12: 19.8 | AU12: 86.6 | AV12: 181.9 | AW12: 181.6 | AX12: 183.1 | AY12: 108.9 | AZ12: 8.2 | BA12: 2.4 | BB12: 31.6 | BC12: 41.5 | BD12: 4 | BE12: 0 | BF12: 64.6 | BI12: 47.7 | BL12: 0 | BP12: 86.6 | BQ12: 156.9 | BR12: 0 | BS12: 0 | BT12: 68.8 | BY12: 0 | CB12: 0 | CC12: 1.8 | CD12: 44.3 | CE12: 97.9 | CF12: 61.8 | CG12: 70.5 | CH12: 29.8 | CL12: 145.3 | CM12: 146.6 | CN12: 148.2 | CV12: 0 | CW12: 109.7 | CX12: 0 | CY12: 17.1 | CZ12: 0 | DA12: 18 | DB12: 10 | DC12: 5.6 | DD12: 0.8 | DE12: 1.5 | DF12: 2.6 | DG12: 20.3 | DH12: 20 | DI12: 15.6 | DJ12: 3.5 | DK12: 18.4 | DL12: 0 | DM12: 0 | DN12: 31.9 | DO12: 85.3 | DP12: 4.5 | DQ12: 2.2 | DR12: 2.1 | DS12: 1.4 | DT12: 0 | DU12: 3 | DV12: 13 | DW12: 2.2 | DY12: 19.7 | DZ12: 5.4 | EA12: 10.4 | EB12: 16.1 | EC12: 18 | ED12: 16.6 | EE12: 28 | EF12: 0 | EG12: 99.6 | EH12: 91 | EI12: 17.1 | EJ12: 8.6 | EK12: 16.4 | EL12: 6.5 | EN12: 9.2 | EO12: 9.8 | EP12: 10 | EQ12: 16.3 | ER12: 0 | ES12: 0 | ET12: 0 | EU12: 0.6 | EV12: 83.9 | EW12: 97.3 | EX12: 0 | EY12: 0 | EZ12: 5.6 | FA12: 19.2 | FB12: 8.9 | FC12: 43 | FD12: 14.5 | FE12: 17.6 | FG12: 7.3 | FJ12: 6293.37 | FL12: 24.2 | FM12: 7.945 | FO12: 12 | FP12: 27.11197 | FQ12: 18.91869 | FR12: 4.5 | FS12: 16.1 | FT12: 110.77566
A13: 19/06/2025 | B13: 01:30 | C13: 93.9 | D13: 599.4 | E13: 201.7 | H13: 89.1 | I13: 100 | J13: 25.9 | L13: 123.9 | M13: 123.1 | N13: 123.5 | O13: 223.4 | R13: 391.6 | S13: 4.9 | X13: 157.2 | Y13: 6.9 | Z13: 5.4 | AA13: 0 | AB13: 6.1 | AC13: 8.63 | AD13: 49.71 | AH13: 0 | AI13: 69.4 | AJ13: 79.9 | AN13: 6.5 | AO13: 294.8 | AP13: 74 | AQ13: 143.3 | AR13: 42.1 | AS13: 18.8 | AT13: 19.8 | AU13: 89.7 | AV13: 179.3 | AW13: 180 | AX13: 183.4 | AY13: 108.9 | AZ13: 8.2 | BA13: 2.5 | BB13: 29.1 | BC13: 40.5 | BD13: 4 | BE13: 0 | BF13: 67 | BI13: 47.7 | BL13: 0 | BP13: 86.3 | BQ13: 158 | BR13: 0 | BS13: 0 | BT13: 70.2 | BY13: 0 | CB13: 0 | CC13: 1.8 | CD13: 57.6 | CE13: 109.3 | CF13: 61.5 | CG13: 72.6 | CH13: 29.7 | CL13: 111.4 | CM13: 111.2 | CN13: 130.3 | CV13: 0 | CW13: 110.1 | CX13: 0 | CY13: 14 | CZ13: 0 | DA13: 18.1 | DB13: 9.9 | DC13: 5.4 | DD13: 0.7 | DE13: 1.5 | DF13: 2.6 | DG13: 20.1 | DH13: 20 | DI13: 15.6 | DJ13: 3.5 | DK13: 18.4 | DL13: 0 | DM13: 0 | DN13: 31.8 | DO13: 83.9 | DP13: 4.5 | DQ13: 2.2 | DR13: 2.1 | DS13: 1.4 | DT13: 0 | DU13: 2.9 | DV13: 13 | DW13: 2.2 | DY13: 19.7 | DZ13: 5.4 | EA13: 10.1 | EB13: 15.9 | EC13: 18 | ED13: 16.5 | EE13: 31.6 | EF13: 0 | EG13: 100.3 | EH13: 92 | EI13: 16.6 | EJ13: 7.2 | EK13: 16.4 | EL13: 6.4 | EN13: 9.2 | EO13: 9.8 | EP13: 10 | EQ13: 12.7 | ER13: 0 | ES13: 0 | ET13: 0 | EU13: 0.6 | EV13: 90 | EW13: 122.8 | EX13: 0 | EY13: 0 | EZ13: 5.6 | FA13: 19.2 | FB13: 9.3 | FC13: 42.9 | FD13: 14.5 | FE13: 17.6 | FG13: 7.7 | FJ13: 6135.04 | FL13: 24.2 | FM13: 7.94 | FO13: 12 | FP13: 27.14776 | FQ13: 18.91807 | FR13: 4.6 | FS13: 16 | FT13: 110.80583
A14: 19/06/2025 | B14: 02:00 | C14: 96 | D14: 604.7 | E14: 201.7 | H14: 90.2 | I14: 99.3 | J14: 26.2 | L14: 141.3 | M14: 139.8 | N14: 140.5 | O14: 223.5 | R14: 336 | S14: 4.9 | X14: 163 | Y14: 7.3 | Z14: 5.4 | AA14: 0 | AB14: 6.1 | AC14: 8.64 | AD14: 50.89 | AH14: 0 | AI14: 70.2 | AJ14: 95.5 | AN14: 6.5 | AO14: 355.8 | AP14: 74 | AQ14: 143.5 | AR14: 42.1 | AS14: 18.8 | AT14: 19.8 | AU14: 90.8 | AV14: 181.1 | AW14: 181.7 | AX14: 184.1 | AY14: 109.7 | AZ14: 8.2 | BA14: 2.7 | BB14: 34.1 | BC14: 41.3 | BD14: 4 | BE14: 0 | BF14: 63.4 | BI14: 47.9 | BL14: 0 | BP14: 86.7 | BQ14: 158 | BR14: 0 | BS14: 0 | BT14: 70.3 | BY14: 0 | CB14: 0 | CC14: 1.8 | CD14: 45.2 | CE14: 114.6 | CF14: 62.1 | CG14: 73.9 | CH14: 29.8 | CL14: 102.7 | CM14: 102.6 | CN14: 121.5 | CV14: 0 | CW14: 103.2 | CX14: 0 | CY14: 15 | CZ14: 0 | DA14: 18 | DB14: 10 | DC14: 5.6 | DD14: 0.7 | DE14: 1.5 | DF14: 2.6 | DG14: 20.3 | DH14: 20 | DI14: 15.5 | DJ14: 3.4 | DK14: 18.4 | DL14: 0 | DM14: 0 | DN14: 31.8 | DO14: 84.9 | DP14: 4.5 | DQ14: 2.2 | DR14: 2.1 | DS14: 1.4 | DT14: 0 | DU14: 2.9 | DV14: 13 | DW14: 2.2 | DY14: 19.7 | DZ14: 5.5 | EA14: 10.5 | EB14: 16.1 | EC14: 18 | ED14: 13.1 | EE14: 23.6 | EF14: 0 | EG14: 90 | EH14: 86.3 | EI14: 15.7 | EJ14: 6.2 | EK14: 16.4 | EL14: 6.2 | EN14: 9 | EO14: 9.8 | EP14: 10 | EQ14: 13.8 | ER14: 0 | ES14: 0 | ET14: 0 | EU14: 0.6 | EV14: 96.5 | EW14: 123.4 | EX14: 0 | EY14: 0 | EZ14: 5.6 | FA14: 19.2 | FB14: 9.6 | FC14: 42.8 | FD14: 14.5 | FE14: 16.8 | FG14: 7.8 | FJ14: 6175.73 | FL14: 24.3 | FM14: 7.941 | FO14: 12 | FP14: 27.0868 | FQ14: 18.91769 | FR14: 4.6 | FS14: 16 | FT14: 110.84549
A15: 19/06/2025 | B15: 02:30 | C15: 101.2 | D15: 602.9 | E15: 201.5 | H15: 90.4 | I15: 106.4 | J15: 25.9 | L15: 114.9 | M15: 114.5 | N15: 113.9 | O15: 224.7 | R15: 327.1 | S15: 5 | X15: 165.6 | Y15: 7.5 | Z15: 5.4 | AA15: 0 | AB15: 6.09 | AC15: 8.63 | AD15: 49.97 | AH15: 0 | AI15: 70.7 | AJ15: 4.4 | AN15: 6.5 | AO15: 408.2 | AP15: 73.8 | AQ15: 144.8 | AR15: 42.1 | AS15: 18.7 | AT15: 19.8 | AU15: 90.3 | AV15: 183.9 | AW15: 183.7 | AX15: 182.3 | AY15: 109.6 | AZ15: 8.1 | BA15: 2.6 | BB15: 23.7 | BC15: 42.2 | BD15: 4 | BE15: 0 | BF15: 54.6 | BI15: 48.3 | BL15: 0 | BP15: 86.9 | BQ15: 157.6 | BR15: 0 | BS15: 0 | BT15: 69.7 | BY15: 0 | CB15: 0 | CC15: 1.8 | CD15: 52 | CE15: 105 | CF15: 62.4 | CG15: 73.9 | CH15: 30.1 | CL15: 102.8 | CM15: 102.6 | CN15: 120.8 | CV15: 0 | CW15: 110.3 | CX15: 0 | CY15: 17.3 | CZ15: 0 | DA15: 17.9 | DB15: 9.9 | DC15: 5.4 | DD15: 0.7 | DE15: 1.5 | DF15: 2.6 | DG15: 20.5 | DH15: 20 | DI15: 15.5 | DJ15: 3.5 | DK15: 18.4 | DL15: 0 | DM15: 0 | DN15: 32 | DO15: 82.6 | DP15: 4.5 | DQ15: 2.2 | DR15: 2.1 | DS15: 1.4 | DT15: 0 | DU15: 3 | DV15: 13 | DW15: 2.2 | DY15: 19.7 | DZ15: 5.8 | EA15: 10.5 | EB15: 13.9 | EC15: 17.9 | ED15: 11.4 | EE15: 21.3 | EF15: 0 | EG15: 84.3 | EH15: 78.8 | EI15: 11.6 | EJ15: 6.4 | EK15: 16.5 | EL15: 6.2 | EN15: 8.2 | EO15: 9.5 | EP15: 9.7 | EQ15: 14.6 | ER15: 0 | ES15: 0 | ET15: 0 | EU15: 0.6 | EV15: 108.7 | EW15: 128.6 | EX15: 0 | EY15: 0 | EZ15: 5.6 | FA15: 19.2 | FB15: 9.6 | FC15: 43 | FD15: 14.6 | FE15: 16.9 | FG15: 6.9 | FJ15: 6045.99 | FL15: 24.2 | FM15: 7.94 | FO15: 12 | FP15: 27.18328 | FQ15: 18.91742 | FR15: 4.5 | FS15: 16 | FT15: 110.7407
A16: 19/06/2025 | B16: 03:00 | C16: 42.6 | D16: 595 | E16: 198.7 | H16: 89.8 | I16: 102.2 | J16: 26.2 | L16: 150.9 | M16: 150.1 | N16: 150.3 | O16: 246.7 | R16: 299.9 | S16: 4.8 | X16: 160.1 | Y16: 6.5 | Z16: 5.2 | AA16: 0 | AB16: 6.09 | AC16: 8.61 | AD16: 49.2 | AH16: 0 | AI16: 68.1 | AJ16: 0 | AN16: 6.5 | AO16: 451.3 | AP16: 74.1 | AQ16: 143.5 | AR16: 41.9 | AS16: 18.7 | AT16: 19.8 | AU16: 88.2 | AV16: 175.8 | AW16: 178.2 | AX16: 182.2 | AY16: 107.3 | AZ16: 8 | BA16: 2.7 | BB16: 30.2 | BC16: 43.7 | BD16: 4 | BE16: 0 | BF16: 60.3 | BI16: 47.5 | BL16: 0 | BP16: 85.8 | BQ16: 156.6 | BR16: 0 | BS16: 0 | BT16: 69.6 | BY16: 0 | CB16: 0 | CC16: 1.8 | CD16: 35.5 | CE16: 105.4 | CF16: 60.6 | CG16: 73.2 | CH16: 29.3 | CL16: 102 | CM16: 101.6 | CN16: 120.7 | CV16: 0 | CW16: 101.7 | CX16: 0 | CY16: 15 | CZ16: 0 | DA16: 17.8 | DB16: 10 | DC16: 5.6 | DD16: 0.7 | DE16: 1.5 | DF16: 2.6 | DG16: 19.7 | DH16: 20 | DI16: 15.5 | DJ16: 3.5 | DK16: 18.4 | DL16: 0 | DM16: 0 | DN16: 31.6 | DO16: 83.5 | DP16: 4.5 | DQ16: 2.2 | DR16: 2.1 | DS16: 1.4 | DT16: 0 | DU16: 3 | DV16: 13.2 | DW16: 2.2 | DY16: 19.7 | DZ16: 5.8 | EA16: 9.8 | EB16: 12.9 | EC16: 18 | ED16: 17.2 | EE16: 17 | EF16: 0 | EG16: 89.2 | EH16: 87.5 | EI16: 11.2 | EJ16: 8.1 | EK16: 16.5 | EL16: 6 | EN16: 8.2 | EO16: 9 | EP16: 9.5 | EQ16: 14.1 | ER16: 0 | ES16: 0 | ET16: 0 | EU16: 0.6 | EV16: 99.7 | EW16: 108.9 | EX16: 0 | EY16: 0 | EZ16: 5.4 | FA16: 19.2 | FB16: 9.5 | FC16: 42.8 | FD16: 14.7 | FE16: 17.8 | FG16: 7.7 | FJ16: 6048.7 | FL16: 24.4 | FM16: 7.939 | FO16: 12 | FP16: 27.21647 | FQ16: 18.91675 | FR16: 4.6 | FS16: 15.9 | FT16: 110.97222
A17: 19/06/2025 | B17: 03:30 | C17: 53.6 | D17: 603.6 | E17: 202.4 | H17: 91 | I17: 108.8 | J17: 26.5 | L17: 126.1 | M17: 126 | N17: 125.8 | O17: 225.8 | R17: 309.6 | S17: 5 | X17: 165.3 | Y17: 7.5 | Z17: 5.5 | AA17: 0 | AB17: 6.09 | AC17: 8.64 | AD17: 50.48 | AH17: 0 | AI17: 70.7 | AJ17: 0 | AN17: 6.5 | AO17: 457.1 | AP17: 72.4 | AQ17: 146.3 | AR17: 42.1 | AS17: 18.8 | AT17: 19.8 | AU17: 91.4 | AV17: 183.2 | AW17: 183.7 | AX17: 183 | AY17: 109.9 | AZ17: 8.1 | BA17: 2.7 | BB17: 31.8 | BC17: 44.6 | BD17: 4 | BE17: 0 | BF17: 95.9 | BI17: 48.3 | BL17: 0 | BP17: 87 | BQ17: 157.1 | BR17: 0 | BS17: 0 | BT17: 68.1 | BY17: 0 | CB17: 0 | CC17: 1.8 | CD17: 58.6 | CE17: 113.3 | CF17: 62.4 | CG17: 73.8 | CH17: 30.2 | CL17: 102.6 | CM17: 102.4 | CN17: 121.2 | CV17: 0 | CW17: 104.3 | CX17: 0 | CY17: 13.2 | CZ17: 0 | DA17: 17.8 | DB17: 9.9 | DC17: 5.5 | DD17: 0.7 | DE17: 1.6 | DF17: 2.6 | DG17: 20.4 | DH17: 20 | DI17: 15.5 | DJ17: 3.5 | DK17: 18.4 | DL17: 0 | DM17: 0 | DN17: 31.7 | DO17: 82.8 | DP17: 4.5 | DQ17: 2.2 | DR17: 2.1 | DS17: 1.4 | DT17: 0 | DU17: 3 | DV17: 13 | DW17: 2.2 | DY17: 19.7 | DZ17: 5.8 | EA17: 10 | EB17: 13.7 | EC17: 17.9 | ED17: 16.4 | EE17: 15 | EF17: 0 | EG17: 104 | EH17: 90.1 | EI17: 13.8 | EJ17: 9.8 | EK17: 16.5 | EL17: 6 | EN17: 8.2 | EO17: 9 | EP17: 9.5 | EQ17: 13.5 | ER17: 0 | ES17: 0 | ET17: 0 | EU17: 0.6 | EV17: 103.7 | EW17: 136.6 | EX17: 0 | EY17: 0 | EZ17: 5.4 | FA17: 19.2 | FB17: 9.8 | FC17: 43 | FD17: 14.7 | FE17: 17.8 | FG17: 7.2 | FJ17: 6159.71 | FL17: 24.4 | FM17: 7.937 | FO17: 12 | FP17: 27.29215 | FQ17: 18.91647 | FR17: 4.6 | FS17: 15.9 | FT17: 111.04562
A18: 19/06/2025 | B18: 04:00 | C18: 53.2 | D18: 605.3 | E18: 202.4 | H18: 90.5 | I18: 116.4 | J18: 26.6 | L18: 113.2 | M18: 113.6 | N18: 112.5 | O18: 212 | R18: 310.8 | S18: 5 | X18: 166.3 | Y18: 7.5 | Z18: 5.5 | AA18: 0 | AB18: 6.1 | AC18: 8.64 | AD18: 50.45 | AH18: 0 | AI18: 70.9 | AJ18: 0 | AN18: 6.5 | AO18: 460 | AP18: 72 | AQ18: 140.7 | AR18: 42.2 | AS18: 18.8 | AT18: 19.8 | AU18: 90.1 | AV18: 182.9 | AW18: 183.7 | AX18: 183.7 | AY18: 109.6 | AZ18: 8 | BA18: 2.7 | BB18: 27.2 | BC18: 43.5 | BD18: 4 | BE18: 0 | BF18: 65 | BI18: 48.4 | BL18: 0 | BP18: 87.1 | BQ18: 158.1 | BR18: 0 | BS18: 0 | BT18: 68.4 | BY18: 0 | CB18: 0 | CC18: 1.8 | CD18: 70.5 | CE18: 108.5 | CF18: 62.6 | CG18: 74 | CH18: 30.3 | CL18: 103.5 | CM18: 103 | CN18: 122 | CV18: 0 | CW18: 111.8 | CX18: 0 | CY18: 16.9 | CZ18: 0 | DA18: 17.8 | DB18: 9.9 | DC18: 5.6 | DD18: 0.7 | DE18: 1.6 | DF18: 2.6 | DG18: 20.3 | DH18: 20 | DI18: 13.4 | DJ18: 3.5 | DK18: 18.4 | DL18: 0 | DM18: 0 | DN18: 31.7 | DO18: 84.9 | DP18: 4.5 | DQ18: 2.2 | DR18: 2.1 | DS18: 1.4 | DT18: 0 | DU18: 3 | DV18: 13 | DW18: 2.1 | DY18: 19.7 | DZ18: 5.8 | EA18: 10.2 | EB18: 13.7 | EC18: 17.8 | ED18: 18.9 | EE18: 9.9 | EF18: 0 | EG18: 101.9 | EH18: 95.5 | EI18: 19 | EJ18: 8.9 | EK18: 16.5 | EL18: 5.9 | EN18: 8 | EO18: 8.5 | EP18: 9 | EQ18: 14.5 | ER18: 0 | ES18: 0 | ET18: 0 | EU18: 0.6 | EV18: 121.5 | EW18: 130.6 | EX18: 0 | EY18: 0 | EZ18: 5.5 | FA18: 19.2 | FB18: 9.7 | FC18: 43 | FD18: 14.6 | FE18: 17.4 | FG18: 8.1 | FJ18: 6116.79 | FL18: 24.5 | FM18: 7.94 | FO18: 12 | FP18: 27.25449 | FQ18: 18.91668 | FR18: 4.6 | FS18: 16.2 | FT18: 111.41117
A19: 19/06/2025 | B19: 04:30 | C19: 50.9 | D19: 605.3 | E19: 202.7 | H19: 91 | I19: 116.9 | J19: 24.7 | L19: 117.6 | M19: 116.1 | N19: 116.5 | O19: 209.3 | R19: 311.9 | S19: 5.1 | X19: 162.6 | Y19: 7.5 | Z19: 5.4 | AA19: 0 | AB19: 6.08 | AC19: 8.73 | AD19: 51.31 | AH19: 0 | AI19: 70.6 | AJ19: 0 | AN19: 6.5 | AO19: 458.4 | AP19: 72 | AQ19: 150 | AR19: 42 | AS19: 18.8 | AT19: 19.8 | AU19: 90.2 | AV19: 181.7 | AW19: 184 | AX19: 183.1 | AY19: 109.8 | AZ19: 8.1 | BA19: 2.7 | BB19: 34.2 | BC19: 43.4 | BD19: 4 | BE19: 0 | BF19: 83.2 | BI19: 48.2 | BL19: 0 | BP19: 87.4 | BQ19: 156.9 | BR19: 0 | BS19: 0 | BT19: 69 | BY19: 0 | CB19: 0 | CC19: 1.8 | CD19: 115.4 | CE19: 117.2 | CF19: 64.7 | CG19: 75.9 | CH19: 30.1 | CL19: 101.9 | CM19: 101.9 | CN19: 120.7 | CV19: 0 | CW19: 115.5 | CX19: 0 | CY19: 16.6 | CZ19: 0 | DA19: 17.7 | DB19: 9.9 | DC19: 5.4 | DD19: 0.7 | DE19: 1.6 | DF19: 2.6 | DG19: 20.3 | DH19: 20 | DI19: 13.5 | DJ19: 3.5 | DK19: 18.4 | DL19: 0 | DM19: 0 | DN19: 31.8 | DO19: 85.6 | DP19: 4.5 | DQ19: 2.2 | DR19: 2.1 | DS19: 1.4 | DT19: 0 | DU19: 3.2 | DV19: 13 | DW19: 2.1 | DY19: 19.7 | DZ19: 5.7 | EA19: 10.2 | EB19: 13.8 | EC19: 17.8 | ED19: 18.5 | EE19: 5.4 | EF19: 0 | EG19: 100 | EH19: 94.3 | EI19: 15.8 | EJ19: 6.8 | EK19: 16.5 | EL19: 5.8 | EN19: 8 | EO19: 8.5 | EP19: 8.7 | EQ19: 13.8 | ER19: 0 | ES19: 0 | ET19: 0 | EU19: 0.6 | EV19: 97.7 | EW19: 104.6 | EX19: 0 | EY19: 0 | EZ19: 5.6 | FA19: 19.2 | FB19: 9.7 | FC19: 43.3 | FD19: 14.7 | FE19: 17.7 | FG19: 7.9 | FJ19: 6145.12 | FL19: 24.4 | FM19: 7.939 | FO19: 12 | FP19: 27.26415 | FQ19: 18.91644 | FR19: 4.5 | FS19: 16 | FT19: 111.01959
A20: 19/06/2025 | B20: 05:00 | C20: 44.5 | D20: 603 | E20: 202.1 | H20: 89.6 | I20: 115.8 | J20: 25.9 | L20: 116.9 | M20: 117.2 | N20: 115.8 | O20: 211.3 | R20: 313.1 | S20: 5 | X20: 160.9 | Y20: 7.1 | Z20: 5.1 | AA20: 0 | AB20: 6.13 | AC20: 8.73 | AD20: 50.31 | AH20: 0 | AI20: 69.9 | AJ20: 1.3 | AN20: 6.5 | AO20: 455.2 | AP20: 72 | AQ20: 148.3 | AR20: 42 | AS20: 18.6 | AT20: 19.8 | AU20: 90 | AV20: 181.6 | AW20: 181 | AX20: 183.5 | AY20: 109.5 | AZ20: 8.1 | BA20: 2.8 | BB20: 32.9 | BC20: 43.7 | BD20: 4 | BE20: 0 | BF20: 85.4 | BI20: 47.9 | BL20: 0 | BP20: 86.5 | BQ20: 157.6 | BR20: 0 | BS20: 0 | BT20: 68.1 | BY20: 0 | CB20: 0 | CC20: 1.8 | CD20: 110.6 | CE20: 112.2 | CF20: 64 | CG20: 76.8 | CH20: 29.9 | CL20: 102.8 | CM20: 102.6 | CN20: 121.6 | CV20: 0 | CW20: 114.5 | CX20: 0 | CY20: 17.8 | CZ20: 0 | DA20: 17.3 | DB20: 9.9 | DC20: 5.5 | DD20: 0.7 | DE20: 1.6 | DF20: 2.6 | DG20: 20.1 | DH20: 20 | DI20: 13.5 | DJ20: 3.5 | DK20: 18.4 | DL20: 0 | DM20: 0 | DN20: 31.7 | DO20: 85.9 | DP20: 4.5 | DQ20: 2.2 | DR20: 2.1 | DS20: 1.4 | DT20: 0 | DU20: 3.2 | DV20: 13 | DW20: 2 | DY20: 19.7 | DZ20: 5.2 | EA20: 10 | EB20: 13.9 | EC20: 17.8 | ED20: 18.2 | EE20: 5 | EF20: 0 | EG20: 100.3 | EH20: 93.3 | EI20: 17.5 | EJ20: 7.6 | EK20: 16.5 | EL20: 5.7 | EN20: 7.5 | EO20: 8.5 | EP20: 8.7 | EQ20: 15.7 | ER20: 0 | ES20: 0 | ET20: 0 | EU20: 0.6 | EV20: 103.5 | EW20: 128.4 | EX20: 0 | EY20: 0 | EZ20: 5.5 | FA20: 19.2 | FB20: 9.7 | FC20: 42.9 | FD20: 14.8 | FE20: 17.8 | FG20: 8.3 | FJ20: 6150.17 | FL20: 24.5 | FM20: 7.937 | FO20: 12 | FP20: 27.33902 | FQ20: 18.91628 | FR20: 4.4 | FS20: 16.1 | FT20: 111.1923
A21: 19/06/2025 | B21: 05:30 | C21: 49.8 | D21: 601.4 | E21: 202.8 | H21: 90.5 | I21: 118.9 | J21: 26 | L21: 119.5 | M21: 119.4 | N21: 119.2 | O21: 224.4 | R21: 305.4 | S21: 5 | X21: 165.9 | Y21: 7.3 | Z21: 5.2 | AA21: 0 | AB21: 6.15 | AC21: 8.81 | AD21: 50.3 | AH21: 0 | AI21: 70.2 | AJ21: 62.1 | AN21: 6.5 | AO21: 455.9 | AP21: 72.7 | AQ21: 150 | AR21: 42 | AS21: 18.8 | AT21: 19.8 | AU21: 89.3 | AV21: 182.2 | AW21: 183.1 | AX21: 182.6 | AY21: 109.4 | AZ21: 8.1 | BA21: 2.7 | BB21: 34.6 | BC21: 44.3 | BD21: 4 | BE21: 0 | BF21: 83.4 | BI21: 48.1 | BL21: 0 | BP21: 86.8 | BQ21: 157.2 | BR21: 0 | BS21: 0 | BT21: 68.7 | BY21: 0 | CB21: 0 | CC21: 1.8 | CD21: 134.5 | CE21: 102.5 | CF21: 64.2 | CG21: 76.8 | CH21: 30.1 | CL21: 102.3 | CM21: 102.2 | CN21: 120.9 | CV21: 0 | CW21: 94.7 | CX21: 0 | CY21: 17.6 | CZ21: 0 | DA21: 17 | DB21: 9.9 | DC21: 5.5 | DD21: 0.7 | DE21: 1.5 | DF21: 2.6 | DG21: 20.2 | DH21: 20 | DI21: 13.5 | DJ21: 3.5 | DK21: 18.4 | DL21: 0 | DM21: 0 | DN21: 31.9 | DO21: 85.2 | DP21: 4.5 | DQ21: 2.2 | DR21: 2.1 | DS21: 1.4 | DT21: 0 | DU21: 3.2 | DV21: 13.1 | DW21: 2 | DY21: 19.7 | DZ21: 5 | EA21: 10 | EB21: 13.7 | EC21: 18 | ED21: 22.7 | EE21: 5.6 | EF21: 0 | EG21: 87.4 | EH21: 77.1 | EI21: 13.5 | EJ21: 9 | EK21: 16.5 | EL21: 5.6 | EN21: 7.5 | EO21: 8.5 | EP21: 8.7 | EQ21: 15.9 | ER21: 0 | ES21: 0 | ET21: 0 | EU21: 0.6 | EV21: 109.9 | EW21: 133.2 | EX21: 0 | EY21: 0 | EZ21: 5.5 | FA21: 19.2 | FB21: 9 | FC21: 42.8 | FD21: 14.7 | FE21: 17 | FG21: 8.4 | FJ21: 6219.16 | FL21: 24.4 | FM21: 7.939 | FO21: 12 | FP21: 27.35864 | FQ21: 18.91623 | FR21: 4.3 | FS21: 16 | FT21: 110.91387
A22: 19/06/2025 | B22: 06:00 | C22: 47.7 | D22: 602.2 | E22: 200.2 | H22: 90 | I22: 116 | J22: 25.4 | L22: 137.1 | M22: 136.8 | N22: 136.2 | O22: 241.6 | R22: 471.8 | S22: 5 | X22: 164.1 | Y22: 6.9 | Z22: 5.3 | AA22: 0 | AB22: 6.13 | AC22: 8.81 | AD22: 50.04 | AH22: 0 | AI22: 69.9 | AJ22: 82.1 | AN22: 6.5 | AO22: 458.5 | AP22: 72.3 | AQ22: 149.6 | AR22: 42.1 | AS22: 18.8 | AT22: 19.8 | AU22: 91.2 | AV22: 180.9 | AW22: 181.7 | AX22: 182.6 | AY22: 109.2 | AZ22: 8.1 | BA22: 2.7 | BB22: 34.1 | BC22: 43.9 | BD22: 4 | BE22: 0 | BF22: 57.8 | BI22: 48.1 | BL22: 0 | BP22: 86.7 | BQ22: 157.7 | BR22: 0 | BS22: 0 | BT22: 69.4 | BY22: 0 | CB22: 0 | CC22: 1.8 | CD22: 87.7 | CE22: 104.3 | CF22: 64.1 | CG22: 76.9 | CH22: 29.9 | CL22: 145 | CM22: 146.2 | CN22: 145.9 | CV22: 0 | CW22: 100.4 | CX22: 0 | CY22: 16.6 | CZ22: 0 | DA22: 16.9 | DB22: 9.9 | DC22: 5.6 | DD22: 0.7 | DE22: 1.5 | DF22: 2.6 | DG22: 20.1 | DH22: 20 | DI22: 13.6 | DJ22: 3.4 | DK22: 18.4 | DL22: 0.1 | DM22: 0 | DN22: 31.2 | DO22: 79.9 | DP22: 4.5 | DQ22: 2.2 | DR22: 2.1 | DS22: 1.4 | DT22: 0 | DU22: 3.2 | DV22: 13.2 | DW22: 2.1 | DY22: 19.7 | DZ22: 5 | EA22: 9.9 | EB22: 14 | EC22: 18 | ED22: 20 | EE22: 11 | EF22: 0 | EG22: 79.5 | EH22: 63.7 | EI22: 16.7 | EJ22: 7.8 | EK22: 16.5 | EL22: 5.5 | EN22: 7.5 | EO22: 8.5 | EP22: 8.7 | EQ22: 15.2 | ER22: 0 | ES22: 0 | ET22: 0 | EU22: 0.6 | EV22: 99.7 | EW22: 107.3 | EX22: 0 | EY22: 0 | EZ22: 5.5 | FA22: 19.3 | FB22: 9.8 | FC22: 42.9 | FD22: 15.8 | FE22: 17.1 | FG22: 8.7 | FJ22: 6454.28 | FL22: 24.4 | FM22: 7.944 | FO22: 12 | FP22: 27.33817 | FQ22: 18.91569 | FR22: 4.3 | FS22: 16.1 | FT22: 110.99786
... A58: 20/06/2025 | B58: 00:00 | C58: 51.1 | D58: 605.6 | E58: 202.5 | H58: 91.8 | I58: 114.9 | J58: 0 | L58: 186.9 | M58: 205.9 | N58: 208 | O58: 290.5 | R58: 447.4 | S58: 5.1 | X58: 166.9 | Y58: 7.5 | Z58: 5.3 | AA58: 22.1 | AB58: 6.89 | AC58: 14.27 | AD58: 93.84 | AH58: 0 | AI58: 61.4 | AJ58: 29.5 | AN58: 6.5 | AO58: 298.6 | AP58: 60 | AQ58: 125.3 | AR58: 38.8 | AS58: 18.8 | AT58: 19.8 | AU58: 91 | AV58: 182.6 | AW58: 184.4 | AX58: 183.4 | AY58: 110.6 | AZ58: 8.1 | BA58: 1.8 | BB58: 20.5 | BC58: 40 | BD58: 4 | BE58: 0 | BF58: 72 | BI58: 48.3 | BL58: 47.2 | BP58: 87.3 | BQ58: 176.8 | BR58: 174.5 | BS58: 200 | BT58: 174.9 | BY58: 0 | CB58: 0 | CC58: 1.8 | CD58: 70.4 | CE58: 83.1 | CF58: 65.3 | CG58: 73.3 | CH58: 30.4 | CL58: 145.9 | CM58: 147 | CN58: 149.4 | CV58: 0 | CW58: 52.8 | CX58: 0 | CY58: 10.9 | CZ58: 0 | DA58: 15.9 | DB58: 10 | DC58: 5.5 | DD58: 0.6 | DE58: 1.5 | DF58: 2.6 | DG58: 20.4 | DH58: 20 | DI58: 13.6 | DJ58: 3.5 | DK58: 18.4 | DL58: 0 | DM58: 0 | DN58: 18.5 | DO58: 34.1 | DP58: 4.5 | DQ58: 1.2 | DR58: 2.2 | DS58: 2.9 | DT58: 0 | DU58: 2.9 | DV58: 13.5 | DW58: 2 | DY58: 17.2 | DZ58: 4.7 | EA58: 8.5 | EB58: 11.5 | EC58: 17.3 | ED58: 29.7 | EE58: 8.5 | EF58: 0 | EG58: 3.2 | EH58: 8.8 | EI58: 0.4 | EJ58: 0 | EK58: 16.5 | EL58: 5.1 | EN58: 7.2 | EO58: 8 | EP58: 8.2 | EQ58: 7.6 | ER58: 0 | ES58: 0 | ET58: 0 | EU58: 0.6 | EV58: 17.5 | EW58: 13.7 | EX58: 0 | EY58: 0 | EZ58: 5.5 | FA58: 19 | FB58: 9.7 | FC58: 43.2 | FD58: 17.6 | FE58: 17.6 | FG58: 7.8 | FJ58: 6531.3 | FL58: 24.4 | FM58: 7.788 | FO58: 11.6 | FP58: 27.21171 | FQ58: 18.91574 | FR58: 4.5 | FS58: 16 | FT58: 110.41545
A59: EJEC | C59: 2695.5 | D59: 14475.6 | E59: 4850 | F59: 0 | G59: 0 | H59: 2162.65 | I59: 3560.75 | J59: 403.85 | K59: 0 | L59: 3820.6 | M59: 3887.25 | N59: 3897.1 | O59: 6102.5 | P59: 0 | Q59: 0 | R59: 10716.25 | S59: 119.25 | T59: 0 | U59: 0 | V59: 0 | W59: 0 | X59: 3908.05 | Y59: 173.9 | Z59: 127.7 | AA59: 297.85 | AB59: 154.29 | AC59: 255.51 | AD59: 1666.04 | AE59: 0 | AF59: 0 | AG59: 0 | AH59: 3.625 | AI59: 1893 | AJ59: 3009.85 | AK59: 0 | AL59: 0 | AM59: 0 | AN59: 156 | AO59: 8995.2 | AP59: 1619.7 | AQ59: 2969.55 | AR59: 976.7 | AS59: 450.15 | AT59: 475.2 | AU59: 2142.25 | AV59: 4368.45 | AW59: 4375.8 | AX59: 4406.3 | AY59: 2620.8 | AZ59: 194.5 | BA59: 59.9 | BB59: 738.2 | BC59: 1008.15 | BD59: 96 | BE59: 193.85 | BF59: 2271.05 | BG59: 0 | BH59: 0 | BI59: 970 | BJ59: 0 | BK59: 0 | BL59: 759.1 | BM59: 0 | BN59: 0 | BO59: 0 | BP59: 2080.8 | BQ59: 4032.75 | BR59: 2275 | BS59: 489 | BT59: 3008.6 | BU59: 0 | BV59: 0 | BW59: 0 | BX59: 0 | BY59: 455.6 | BZ59: 0 | CA59: 0 | CB59: 199.3 | CC59: 42.15 | CD59: 2670.65 | CE59: 2385.6 | CF59: 1528.25 | CG59: 1767.55 | CH59: 720.15 | CI59: 0 | CJ59: 0 | CK59: 0 | CL59: 3300.05 | CM59: 3321.45 | CN59: 3450.75 | CO59: 0 | CP59: 0 | CQ59: 0 | CR59: 0 | CS59: 0 | CT59: 0 | CU59: 0 | CV59: 7.95 | CW59: 1971.75 | CX59: 564.25 | CY59: 370.75 | CZ59: 1.45 | DA59: 400.95 | DB59: 238.35 | DC59: 132.3 | DD59: 15.2 | DE59: 36.35 | DF59: 62.4 | DG59: 485.85 | DH59: 480 | DI59: 338.3 | DJ59: 82.3 | DK59: 441.6 | DL59: 116.6 | DM59: 138.7 | DN59: 631.25 | DO59: 1691.7 | DP59: 108 | DQ59: 36.8 | DR59: 52.5 | DS59: 27.45 | DT59: 99.15 | DU59: 73.9 | DV59: 278.55 | DW59: 49.1 | DX59: 0 | DY59: 454.95 | DZ59: 113.9 | EA59: 220.9 | EB59: 316.2 | EC59: 425.9 | ED59: 520.95 | EE59: 239.25 | EF59: 240.4 | EG59: 1558.65 | EH59: 1721.45 | EI59: 238.05 | EJ59: 152.75 | EK59: 395.8 | EL59: 124.35 | EM59: 0 | EN59: 186.5 | EO59: 202 | EP59: 207.2 | EQ59: 315.15 | ER59: 1845.35 | ES59: 117.05 | ET59: 1019.85 | EU59: 14.4 | EV59: 1958.15 | EW59: 1923.7 | EX59: 757.7 | EY59: 113.15 | EZ59: 132.35 | FA59: 459.45 | FB59: 229.7 | FC59: 1034.2 | FD59: 386.95 | FE59: 413 | FF59: 0 | FG59: 180.45 | FH59: 0 | FI59: 0 | FJ59: 166908.86 | FL59: 578.45 | FM59: 183.572 | FN59: 0 | FO59: 277.1 | FP59: 648.20629 | FQ59: 410.3 | FR59: 99.6 | FS59: 385.3 | FT59: 2582.5283

Sheet REACTIVA
B3: jueves, 19 de Junio del 2025
A5: POTENCIA REACTIVA EJECUTADA DE LAS UNIDADES DE GENERACIÓN DEL COES (MVAR) | FK5: CENTRALES NO INTEGRANTES COES
A6: FECHA | B6: HORA | C6: 65333 | D6: 101 | E6: 102 | F6: 42667 | G6: 42668 | H6: 126 | I6: 127 | J6: 138 | K6: 139 | L6: 197 | M6: 203 | N6: 204 | O6: 230 | P6: 209 | Q6: 56677 | R6: 796 | S6: 2146 | T6: 142 | U6: 143 | V6: 125 | W6: 187 | X6: 163 | Y6: 298 | Z6: 219 | AA6: 151 | AB6: 152 | AC6: 153 | AD6: 154 | AE6: 756 | AF6: 156 | AG6: 155 | AH6: 182 | AI6: 212 | AJ6: 758 | AK6: 263 | AL6: 265 | AM6: 775 | AN6: 777 | AO6: 2154 | AP6: 150 | AQ6: 149 | AR6: 188 | AS6: 2131 | AT6: 755 | AU6: 252 | AV6: 249 | AW6: 250 | AX6: 117 | AY6: 267 | AZ6: 268 | BA6: 119 | BB6: 120 | BC6: 189 | BD6: 122 | BE6: 266 | BF6: 337 | BG6: 338 | BH6: 251 | BI6: 115 | BJ6: 239 | BK6: 288 | BL6: 240 | BM6: 241 | BN6: 242 | BO6: 191 | BP6: 194 | BQ6: 196 | BR6: 207 | BS6: 236 | BT6: 795 | BU6: 285 | BV6: 995 | BW6: 996 | BX6: 997 | BY6: 766 | BZ6: 926 | CA6: 924 | CB6: 121 | CC6: 103 | CD6: 104 | CE6: 106 | CF6: 105 | CG6: 107 | CH6: 110 | CI6: 109 | CJ6: 144 | CK6: 113 | CL6: 114 | CM6: 193 | CN6: 208 | CO6: 786 | CP6: 787 | CQ6: 788 | CR6: 789 | CS6: 248 | CT6: 2159 | CU6: 303 | CV6: 59715 | CW6: 62255 | CX6: 1263 | CY6: 61800 | CZ6: 2194 | DA6: 216 | DB6: 198 | DC6: 49607 | DD6: 214 | DE6: 260 | DF6: 2152 | DG6: 2128 | DH6: 247 | DI6: 228 | DJ6: 2135 | DK6: 261 | DL6: 237 | DM6: 253 | DN6: 770 | DO6: 225 | DP6: 2201 | DQ6: 2171 | DR6: 760 | DS6: 235 | DT6: 238 | DU6: 2184 | DV6: 61855 | DW6: 223 | DX6: 226 | DY6: 201 | DZ6: 258 | EA6: 259 | EB6: 920 | EC6: 257 | ED6: 256 | EE6: 2148 | EF6: 58288 | EG6: 58289 | EH6: 58839 | EI6: 58840 | EJ6: 296 | EK6: 297 | EL6: 211 | EM6: 2175 | EN6: 2178 | EO6: 2181 | EP6: 1262 | EQ6: 63425 | ER6: 233 | ES6: 2150 | ET6: 2165 | EU6: 2161 | EV6: 61197 | EW6: 58851 | EX6: 234 | EY6: 215 | EZ6: 917 | FA6: 289 | FB6: 58333 | FC6: 58336 | FD6: 213 | FE6: 232 | FF6: 2190 | FG6: 202 | FH6: 58487 | FI6: TOTAL COES | FK6: 221 | FL6: 222 | FM6: 224 | FN6: 2187 | FO6: 227 | FP6: 49400 | FQ6: 199 | FR6: 200 | FS6: TOTAL NO COES
C7: SUR | D7: CENTRO | E7: CENTRO | F7: NORTE | G7: NORTE | H7: NORTE | I7: NORTE | J7: CENTRO | K7: CENTRO | L7: CENTRO | M7: CENTRO | N7: CENTRO | O7: CENTRO | P7: CENTRO | Q7: CENTRO | R7: CENTRO | S7: CENTRO | T7: CENTRO | U7: CENTRO | V7: CENTRO | W7: CENTRO | X7: SUR | Y7: SUR | Z7: CENTRO | AA7: SUR | AB7: SUR | AC7: SUR | AD7: SUR | AE7: SUR | AF7: SUR | AG7: SUR | AH7: SUR | AI7: CENTRO | AJ7: NORTE | AK7: NORTE | AL7: NORTE | AM7: CENTRO | AN7: CENTRO | AO7: CENTRO | AP7: CENTRO | AQ7: CENTRO | AR7: CENTRO | AS7: CENTRO | AT7: SUR | AU7: CENTRO | AV7: CENTRO | AW7: CENTRO | AX7: CENTRO | AY7: CENTRO | AZ7: CENTRO | BA7: CENTRO | BB7: CENTRO | BC7: SUR | BD7: NORTE | BE7: CENTRO | BF7: CENTRO | BG7: CENTRO | BH7: CENTRO | BI7: NORTE | BJ7: NORTE | BK7: NORTE | BL7: SUR | BM7: SUR | BN7: SUR | BO7: CENTRO | BP7: CENTRO | BQ7: CENTRO | BR7: CENTRO | BS7: CENTRO | BT7: CENTRO | BU7: CENTRO | BV7: SUR | BW7: SUR | BX7: SUR | BY7: NORTE | BZ7: SUR | CA7: CENTRO | CB7: NORTE | CC7: CENTRO | CD7: CENTRO | CE7: CENTRO | CF7: CENTRO | CG7: CENTRO | CH7: CENTRO | CI7: CENTRO | CJ7: CENTRO | CK7: CENTRO | CL7: CENTRO | CM7: CENTRO | CN7: CENTRO | CO7: SUR | CP7: SUR | CQ7: SUR | CR7: SUR | CS7: CENTRO | CT7: CENTRO | CU7: CENTRO | CV7: CENTRO | CW7: SUR | CX7: NORTE | CY7: NORTE | CZ7: NORTE | DA7: NORTE | DB7: NORTE | DC7: SUR | DD7: CENTRO | DE7: CENTRO | DF7: CENTRO | DG7: NORTE | DH7: NORTE | DI7: CENTRO | DJ7: CENTRO | DK7: SUR | DL7: SUR | DM7: CENTRO | DN7: CENTRO | DO7: CENTRO | DP7: CENTRO | DQ7: CENTRO | DR7: CENTRO | DS7: SUR | DT7: CENTRO | DU7: CENTRO | DV7: NORTE | DW7: CENTRO | DX7: CENTRO | DY7: NORTE | DZ7: CENTRO | EA7: CENTRO | EB7: CENTRO | EC7: NORTE | ED7: NORTE | EE7: SUR | EF7: CENTRO | EG7: CENTRO | EH7: CENTRO | EI7: CENTRO | EJ7: CENTRO | EK7: CENTRO | EL7: SUR | EM7: SUR | EN7: SUR | EO7: SUR | EP7: NORTE | EQ7: SUR | ER7: SUR | ES7: SUR | ET7: CENTRO | EU7: CENTRO | EV7: CENTRO | EW7: SUR | EX7: SUR | EY7: NORTE | EZ7: CENTRO | FA7: NORTE | FB7: NORTE | FC7: NORTE | FD7: CENTRO | FE7: NORTE | FF7: NORTE | FG7: CENTRO | FH7: CENTRO | FK7: NORTE | FL7: CENTRO | FM7: NORTE | FN7: NORTE | FO7: NORTE | FP7: NORTE | FQ7: NORTE | FR7: NORTE
C8: HIDROELÉCTRICA | D8: HIDROELÉCTRICA | E8: HIDROELÉCTRICA | F8: TERMOELÉCTRICA | G8: TERMOELÉCTRICA | H8: HIDROELÉCTRICA | I8: HIDROELÉCTRICA | J8: TERMOELÉCTRICA | K8: TERMOELÉCTRICA | L8: TERMOELÉCTRICA | M8: TERMOELÉCTRICA | N8: TERMOELÉCTRICA | O8: TERMOELÉCTRICA | P8: TERMOELÉCTRICA | Q8: TERMOELÉCTRICA | R8: HIDROELÉCTRICA | S8: HIDROELÉCTRICA | T8: TERMOELÉCTRICA | U8: TERMOELÉCTRICA | V8: TERMOELÉCTRICA | W8: TERMOELÉCTRICA | X8: HIDROELÉCTRICA | Y8: HIDROELÉCTRICA | Z8: TERMOELÉCTRICA | AA8: HIDROELÉCTRICA | AB8: HIDROELÉCTRICA | AC8: HIDROELÉCTRICA | AD8: HIDROELÉCTRICA | AE8: TERMOELÉCTRICA | AF8: TERMOELÉCTRICA | AG8: TERMOELÉCTRICA | AH8: HIDROELÉCTRICA | AI8: HIDROELÉCTRICA | AJ8: TERMOELÉCTRICA | AK8: TERMOELÉCTRICA | AL8: TERMOELÉCTRICA | AM8: HIDROELÉCTRICA | AN8: HIDROELÉCTRICA | AO8: HIDROELÉCTRICA | AP8: HIDROELÉCTRICA | AQ8: HIDROELÉCTRICA | AR8: HIDROELÉCTRICA | AS8: HIDROELÉCTRICA | AT8: HIDROELÉCTRICA | AU8: TERMOELÉCTRICA | AV8: TERMOELÉCTRICA | AW8: TERMOELÉCTRICA | AX8: HIDROELÉCTRICA | AY8: HIDROELÉCTRICA | AZ8: HIDROELÉCTRICA | BA8: HIDROELÉCTRICA | BB8: HIDROELÉCTRICA | BC8: HIDROELÉCTRICA | BD8: HIDROELÉCTRICA | BE8: HIDROELÉCTRICA | BF8: HIDROELÉCTRICA | BG8: HIDROELÉCTRICA | BH8: HIDROELÉCTRICA | BI8: TERMOELÉCTRICA | BJ8: TERMOELÉCTRICA | BK8: TERMOELÉCTRICA | BL8: TERMOELÉCTRICA | BM8: TERMOELÉCTRICA | BN8: TERMOELÉCTRICA | BO8: HIDROELÉCTRICA | BP8: TERMOELÉCTRICA | BQ8: TERMOELÉCTRICA | BR8: TERMOELÉCTRICA | BS8: TERMOELÉCTRICA | BT8: TERMOELÉCTRICA | BU8: TERMOELÉCTRICA | BV8: TERMOELÉCTRICA | BW8: TERMOELÉCTRICA | BX8: TERMOELÉCTRICA | BY8: HIDROELÉCTRICA | BZ8: TERMOELÉCTRICA | CA8: TERMOELÉCTRICA | CB8: HIDROELÉCTRICA | CC8: HIDROELÉCTRICA | CD8: HIDROELÉCTRICA | CE8: HIDROELÉCTRICA | CF8: HIDROELÉCTRICA | CG8: HIDROELÉCTRICA | CH8: TERMOELÉCTRICA | CI8: TERMOELÉCTRICA | CJ8: TERMOELÉCTRICA | CK8: TERMOELÉCTRICA | CL8: TERMOELÉCTRICA | CM8: TERMOELÉCTRICA | CN8: TERMOELÉCTRICA | CO8: TERMOELÉCTRICA | CP8: TERMOELÉCTRICA | CQ8: TERMOELÉCTRICA | CR8: TERMOELÉCTRICA | CS8: TERMOELÉCTRICA | CT8: TERMOELÉCTRICA | CU8: SOLAR | CV8: EÓLICA | CW8: SOLAR | CX8: EÓLICA | CY8: SOLAR | CZ8: HIDROELÉCTRICA | DA8: HIDROELÉCTRICA | DB8: HIDROELÉCTRICA | DC8: HIDROELÉCTRICA | DD8: HIDROELÉCTRICA | DE8: HIDROELÉCTRICA | DF8: HIDROELÉCTRICA | DG8: HIDROELÉCTRICA | DH8: HIDROELÉCTRICA | DI8: HIDROELÉCTRICA | DJ8: HIDROELÉCTRICA | DK8: SOLAR | DL8: SOLAR | DM8: EÓLICA | DN8: EÓLICA | DO8: TERMOELÉCTRICA | DP8: TERMOELÉCTRICA | DQ8: TERMOELÉCTRICA | DR8: TERMOELÉCTRICA | DS8: SOLAR | DT8: HIDROELÉCTRICA | DU8: HIDROELÉCTRICA | DV8: HIDROELÉCTRICA | DW8: HIDROELÉCTRICA | DX8: HIDROELÉCTRICA | DY8: HIDROELÉCTRICA | DZ8: HIDROELÉCTRICA | EA8: HIDROELÉCTRICA | EB8: HIDROELÉCTRICA | EC8: EÓLICA | ED8: EÓLICA | EE8: SOLAR | EF8: EÓLICA | EG8: EÓLICA | EH8: EÓLICA | EI8: EÓLICA | EJ8: HIDROELÉCTRICA | EK8: HIDROELÉCTRICA | EL8: HIDROELÉCTRICA | EM8: HIDROELÉCTRICA | EN8: HIDROELÉCTRICA | EO8: HIDROELÉCTRICA | EP8: EÓLICA | EQ8: SOLAR | ER8: SOLAR | ES8: SOLAR | ET8: HIDROELÉCTRICA | EU8: EÓLICA | EV8: EÓLICA | EW8: SOLAR | EX8: SOLAR | EY8: HIDROELÉCTRICA | EZ8: HIDROELÉCTRICA | FA8: TERMOELÉCTRICA | FB8: TERMOELÉCTRICA | FC8: TERMOELÉCTRICA | FD8: TERMOELÉCTRICA | FE8: TERMOELÉCTRICA | FF8: TERMOELÉCTRICA | FG8: TERMOELÉCTRICA | FH8: TERMOELÉCTRICA | FK8: HIDROELÉCTRICA | FL8: HIDROELÉCTRICA | FM8: HIDROELÉCTRICA | FN8: HIDROELÉCTRICA | FO8: TERMOELÉCTRICA | FP8: TERMOELÉCTRICA | FQ8: HIDROELÉCTRICA | FR8: HIDROELÉCTRICA
C9: HYDRO GLOBAL PERÚ S.A.C. | D9: ELECTROPERU | E9: ELECTROPERU | F9: ELECTROPERU | G9: ELECTROPERU | H9: ORAZUL ENERGY PERÚ | I9: ORAZUL ENERGY PERÚ | J9: TERMOSELVA | K9: TERMOSELVA | L9: KALLPA GENERACION S.A. | M9: KALLPA GENERACION S.A. | N9: KALLPA GENERACION S.A. | O9: KALLPA GENERACION S.A. | P9: KALLPA GENERACION S.A. | Q9: KALLPA GENERACION S.A. | R9: KALLPA GENERACION S.A. | S9: KALLPA GENERACION S.A. | T9: SHOUGESA | U9: SHOUGESA | V9: SHOUGESA | W9: SHOUGESA | X9: EGEMSA | Y9: EGESUR | Z9: EGESUR | AA9: EGASA | AB9: EGASA | AC9: EGASA | AD9: EGASA | AE9: EGASA | AF9: EGASA | AG9: EGASA | AH9: SAN GABAN | AI9: CELEPSA | AJ9: MINERA CERRO VERDE | AK9: PLANTA DE RESERVA FRIA DE GENERACION DE ETEN S.A. | AL9: PLANTA DE RESERVA FRIA DE GENERACION DE ETEN S.A. | AM9: EMPRESA DE GENERACION HUALLAGA | AN9: EMPRESA DE GENERACION HUALLAGA | AO9: LA VIRGEN | AP9: CHINANGO S.A.C. | AQ9: CHINANGO S.A.C. | AR9: HIDROELECTRICA HUANCHOR S.A.C. | AS9: CELEPSA RENOVABLES S.R.L. | AT9: INLAND ENERGY SAC | AU9: FENIX POWER PERÚ | AV9: FENIX POWER PERÚ | AW9: FENIX POWER PERÚ | AX9: STATKRAFT S.A | AY9: STATKRAFT S.A | AZ9: STATKRAFT S.A | BA9: STATKRAFT S.A | BB9: STATKRAFT S.A | BC9: STATKRAFT S.A | BD9: STATKRAFT S.A | BE9: STATKRAFT S.A | BF9: CENTRALES SANTA ROSA S.A.C. | BG9: CENTRALES SANTA ROSA S.A.C. | BH9: EMPRESA DE GENERACION HUANZA | BI9: ENEL GENERACION PIURA S.A. | BJ9: ENEL GENERACION PIURA S.A. | BK9: ENEL GENERACION PIURA S.A. | BL9: ENGIE | BM9: ENGIE | BN9: ENGIE | BO9: ENGIE | BP9: ENGIE | BQ9: ENGIE | BR9: ENGIE | BS9: ENGIE | BT9: ENGIE | BU9: ENGIE | BV9: ENGIE | BW9: ENGIE | BX9: ENGIE | BY9: ENGIE | BZ9: INFRAESTRUCTURAS Y ENERGIAS DEL PERU S.A.C. | CA9: INFRAESTRUCTURAS Y ENERGIAS DEL PERU S.A.C. | CB9: INVERSIONES SHAQSHA S.A.C. | CC9: ORYGEN PERU S.A.A. | CD9: ORYGEN PERU S.A.A. | CE9: ORYGEN PERU S.A.A. | CF9: ORYGEN PERU S.A.A. | CG9: ORYGEN PERU S.A.A. | CH9: ORYGEN PERU S.A.A. | CI9: ORYGEN PERU S.A.A. | CJ9: ORYGEN PERU S.A.A. | CK9: ORYGEN PERU S.A.A. | CL9: ORYGEN PERU S.A.A. | CM9: ORYGEN PERU S.A.A. | CN9: ORYGEN PERU S.A.A. | CO9: SAMAY I S.A.C | CP9: SAMAY I S.A.C | CQ9: SAMAY I S.A.C | CR9: SAMAY I S.A.C | CS9: TERMOCHILCA S.A.C. | CT9: TERMOCHILCA S.A.C. | CU9: COLCA SOLAR S.A.C. | CV9: ENERGIA RENOVABLE DEL SUR S.A. | CW9: GR CORTARRAMA SOCIEDAD ANONIMA CERRADA | CX9: GR TARUCA SOCIEDAD ANONIMA CERRADA | CY9: KONDU SAC | CZ9: PERUANA DE INVERSIONES EN ENERGIAS RENOVABLES S.A. | DA9: ORAZUL ENERGY PERÚ | DB9: ORAZUL ENERGY PERÚ | DC9: SAN GABAN | DD9: MAJA ENERGIA S.A.C. | DE9: EMPRESA DE GENERACION ELECTRICA CANCHAYLLO SAC | DF9: EMPRESA DE GENERACION ELECTRICA SANTA ANA S.A.C. | DG9: EMPRESA ELECTRICA AGUA AZUL | DH9: EMPRESA ELECTRICA RIO DOBLE | DI9: HIDROCAÑETE S.A. | DJ9: HUAURA POWER GROUP S.A. | DK9: MOQUEGUA FV S.A.C. | DL9: PANAMERICANA SOLAR SAC. | DM9: PARQUE EOLICO MARCONA S.A.C. | DN9: PARQUE EOLICO TRES HERMANAS S.A.C. | DO9: PETRAMAS | DP9: PETRAMAS | DQ9: PETRAMAS | DR9: PETRAMAS | DS9: TACNA SOLAR SAC. | DT9: ELECTRICA YANAPAMPA SAC | DU9: ANDEAN POWER S.A.C. | DV9: ASOCIACIÓN SANTA LUCIA DE CHACAS | DW9: ATRIA ENERGIA S.A.C. | DX9: EGEJUNIN | DY9: EGEJUNIN | DZ9: EGEJUNIN | EA9: EGEJUNIN | EB9: EMPRESA DE GENERACION ELECTRICA RIO BAÑOS S.A.C. | EC9: ENERGÍA EÓLICA S.A. | ED9: ENERGÍA EÓLICA S.A. | EE9: ENGIE | EF9: ENGIE | EG9: ENGIE | EH9: ENGIE | EI9: ENGIE | EJ9: GENERACIÓN ANDINA S.A.C. | EK9: GENERACIÓN ANDINA S.A.C. | EL9: GENERADORA DE ENERGÍA DEL PERÚ | EM9: GENERADORA DE ENERGÍA DEL PERÚ | EN9: GENERADORA DE ENERGÍA DEL PERÚ | EO9: GENERADORA DE ENERGÍA DEL PERÚ | EP9: GR PAINO SOCIEDAD ANONIMA CERRADA | EQ9: JOYA SOLAR S.A.C. | ER9: MAJES ARCUS S.A.C. | ES9: ORYGEN PERU S.A.A. | ET9: ORYGEN PERU S.A.A. | EU9: ORYGEN PERU S.A.A. | EV9: ORYGEN PERU S.A.A. | EW9: ORYGEN PERU S.A.A. | EX9: REPARTICIÓN ARCUS S.A.C. | EY9: SINERSA | EZ9: SINERSA | FA9: BIOENERGIA DEL CHIRA S.A. | FB9: GM OPERACIONES S.A.C. | FC9: GM OPERACIONES S.A.C. | FD9: AGRO INDUSTRIAL PARAMONGA S.A. | FE9: AGROAURORA S.A.C. | FF9: AGROINDUSTRIAS SAN JACINTO S.A.A. | FG9: SDF ENERGIA SAC | FH9: SDF ENERGIA SAC | FK9: UNACEM PERU S.A. | FL9: ELECTRO ORIENTE | FM9: AGUAS Y ENERGIA PERU | FN9: ELECTRO ZAÑA S.A.C. | FO9: ELECTRONOROESTE S.A. | FP9: SDE PIURA | FQ9: SINERSA | FR9: SINERSA
C10: SAN GABAN III | D10: MANTARO | E10: RESTITUCION | F10: TUMBES MAK 1 | G10: TUMBES MAK 2 | H10: CARHUAQUERO | I10: CAÑON DEL PATO | J10: AGUAYTIA TG1 | K10: AGUAYTIA TG2 | L10: KALLPA TG1 | M10: KALLPA TG2 | N10: KALLPA TG3 | O10: KALLPA TV | P10: LFLORES TG1 | Q10: LFLORES TV | R10: CERRO DEL AGUILA | S10: CERRODELAGUILAG4 | T10: SHOUGESA TV1 | U10: SHOUGESA TV2 | V10: SHOUGESA TV3 | W10: SHOUGESA CUMMINS | X10: MACHUPICCHU | Y10: ARICOTA 1 | Z10: INDEPENDENCIA | AA10: CHARCANI I,II,III | AB10: CHARCANI IV | AC10: CHARCANI V | AD10: CHARCANI VI | AE10: CHILINA TG | AF10: MOLLENDO 1, 2, 3 | AG10: CHILINA (SULZ 1,2) | AH10: SAN GABAN II | AI10: PLATANAL | AJ10: RECKA | AK10: RF ETEN TG1 | AL10: RF ETEN TG2 | AM10: CHAGLLA GP1 | AN10: CHAGLLA | AO10: LA VIRGEN | AP10: CHIMAY | AQ10: YANANGO | AR10: HUANCHOR | AS10: MARAÑON | AT10: STA TERESA | AU10: FENIX GT11 | AV10: FENIX GT12 | AW10: FENIX TV10 | AX10: YAUPI | AY10: OROYA | AZ10: PACHACHACA | BA10: MALPASO | BB10: CAHUA | BC10: ARCATA | BD10: GALLITO CIEGO | BE10: CHEVES | BF10: SANTA ROSA 1 | BG10: SANTA ROSA 2 | BH10: HUANZA | BI10: MALACAS2 TG4 | BJ10: MALACAS3 TG 5 | BK10: MALACAS1 TG6 | BL10: RF ILO2 TG1 | BM10: RF ILO2 TG2 | BN10: RF ILO2 TG3 | BO10: YUNCAN | BP10: CHILCA1 TG1 | BQ10: CHILCA1 TG2 | BR10: CHILCA1 TG3 | BS10: CHILCA-TV | BT10: CHILCA2 TG41 | BU10: CHILCA2-TV | BV10: CTNEPI_TG41 | BW10: CTNEPI_TG42 | BX10: CTNEPI_TG43 | BY10: QUITARACSA | BZ10: RF PTO MALDONADO | CA10: RF PUCALLPA | CB10: PARIAC | CC10: HUINCO | CD10: MATUCANA | CE10: MOYOPAMPA | CF10: CALLAHUANCA | CG10: HUAMPANI | CH10: STA ROSA WEST TG7 | CI10: UTI_5 | CJ10: UTI_6 | CK10: VENTANILLA 3 | CL10: VENTANILLA 4 | CM10: VENTANILLA TV | CN10: STAROSA TG8 | CO10: PTO_BRVO TG1 | CP10: PTO_BRVO TG2 | CQ10: PTO_BRVO TG3 | CR10: PTO_BRVO TG4 | CS10: OLLEROS TG1 | CT10: OLLEROS TV | CU10: CS YARUCAYA | CV10: SAN JUAN | CW10: MATARANI | CX10: DUNA | CY10: CARHUAQUERO (CS) | CZ10: MANTA I | DA10: CARHUAQUERO4 | DB10: CAÑA BRAVA | DC10: TUPURI | DD10: RONCADOR | DE10: CANCHAYLLO | DF10: RENOVANDESH1 | DG10: POTRERO | DH10: PIZARRAS | DI10: NIMPERIAL | DJ10: YARUCAYA | DK10: MOQUEGUA-SOLAR | DL10: PANAMERICANA-SOLAR | DM10: PQE-EOLICO-MARCONA | DN10: PQE-EOLICO-3-HERMANAS | DO10: HUAYCOLORO | DP10: CALLAO | DQ10: DONA_CATALINA | DR10: LAGRINGAV | DS10: TACNA-SOLAR | DT10: YANAPAMPA | DU10: CARHUAC | DV10: HUALLIN | DW10: PURMACANA | DX10: HUASAHUASI | DY10: STACRUZ_1_2 | DZ10: RUNATULLO_II | EA10: RUNATULLO_III | EB10: RUCUY | EC10: PQE-EOLICO-TALARA | ED10: PQE-EOLICO-CUPISNIQUE | EE10: INTIPAMPA | EF10: PUNTA LOMITAS-BL1 | EG10: PUNTA LOMITAS-BL2 | EH10: PUN LOMITAS_EXP-BL1 | EI10: PUN LOMITAS_EXP-BL2 | EJ10: 8AGOSTO | EK10: EL CARMEN | EL10: LA JOYA | EM10: ANGEL_I | EN10: ANGEL_II | EO10: ANGEL_III | EP10: HUAMBOS | EQ10: SAN MARTIN SOLAR | ER10: MAJES | ES10: RUBI | ET10: CH_HER1 | EU10: WAYRA-I | EV10: WAYRA EXTENSION | EW10: CLEMESI | EX10: REPARTICION | EY10: POECHOS2 | EZ10: CHANCAY | FA10: CANA BRAVA | FB10: REFINERIA TALARA TV1 | FC10: REFINERÍA TALARA TV2 | FD10: PARAMONGA | FE10: MAPLE | FF10: SAN_JACINTO | FG10: OQUENDO TG1 | FH10: OQUENDO TV1 | FI10: MVAR | FK10: CARPAPATA | FL10: CENTRALES ELOR | FM10: PIAS1 | FN10: ZANA | FO10: TABLAZO | FP10: TALLANCA | FQ10: CURUMUY | FR10: POECHOS1 | FS10: MVAR
A11: 19/06/2025 | B11: 00:30 | C11: -4.9 | D11: 17.4 | E11: 15.1 | H11: -12.6 | I11: -25.1 | L11: -27.1 | M11: -41.8 | N11: -10.7 | O11: 20.4 | R11: 30 | S11: 0.1 | X11: 5.1 | Y11: 0.8 | Z11: 0 | AA11: -2.92 | AB11: 3.45 | AC11: 3.73 | AG11: 0 | AH11: -0.3 | AI11: 2.7 | AM11: -1.8 | AN11: -7.1 | AO11: 5.6 | AP11: 24.1 | AQ11: 8.9 | AR11: -0.5 | AS11: 2.7 | AT11: 1.1 | AU11: -38.4 | AV11: -44.6 | AW11: -46.7 | AX11: 4.7 | AY11: -0.7 | AZ11: 0.2 | BA11: -0.5 | BB11: -2.9 | BC11: 1 | BD11: 0 | BE11: -12.6 | BH11: -9 | BK11: 0 | BO11: -7.4 | BP11: -46.8 | BQ11: 0 | BR11: 0 | BS11: -51.7 | BX11: 0 | CA11: 0 | CB11: -0.4 | CC11: 16.3 | CD11: 21.1 | CE11: 4.2 | CF11: 5.7 | CG11: 1.8 | CK11: 2.4 | CL11: 4.3 | CM11: -45.1 | CS11: 0 | CV11: -1.6 | CW11: 0 | CZ11: 1.2 | DA11: 0 | DB11: -1 | DD11: 0.1 | DE11: 0.9 | DF11: 1.4 | DG11: -1.2 | DH11: 1.3 | DI11: 0.6 | DK11: 0 | DL11: 0 | DM11: -3.1 | DN11: 4.2 | DO11: 1.4 | DP11: 0.7 | DQ11: 0.7 | DR11: 0.5 | DS11: 0 | DT11: -0.1 | DU11: 0.1 | DV11: 0.7 | DX11: -4.7 | DY11: 0.3 | DZ11: 0.1 | EA11: -0.5 | EB11: 0.7 | EC11: 0.8 | ED11: 4 | EE11: 0 | EF11: -5.7 | EG11: -7.1 | EJ11: 2.7 | EK11: 0 | EM11: 0.2 | EN11: 0.2 | EO11: 0.2 | EQ11: 0 | ER11: 0 | ES11: 0 | ET11: -0.2 | EU11: 7.9 | EV11: 3 | EW11: 0 | EX11: 0 | EY11: 0.4 | EZ11: 1 | FA11: 2.3 | FB11: 13.3 | FC11: 5.8 | FD11: 1.5 | FF11: 3.1 | FI11: -202.64 | FK11: 1.7 | FL11: 0.458 | FN11: 1.5 | FO11: 1.30917 | FP11: 0.22056 | FQ11: -0.6 | FR11: 1.8 | FS11: 6.38773
A12: 19/06/2025 | B12: 01:00 | C12: -5.7 | D12: 11.4 | E12: 13.8 | H12: -13.2 | I12: -25.7 | L12: -34 | M12: -53.1 | N12: -21.1 | O12: 10.9 | R12: 29.2 | S12: -0.2 | X12: 4.6 | Y12: 0.7 | Z12: 0 | AA12: -2.94 | AB12: 3.4 | AC12: 3.95 | AG12: 0 | AH12: -2.1 | AI12: -10.1 | AM12: -1.8 | AN12: -11.1 | AO12: 5.5 | AP12: 24.7 | AQ12: 8.6 | AR12: -0.3 | AS12: 2.7 | AT12: -0.6 | AU12: -46.2 | AV12: -46 | AW12: -46.6 | AX12: 4.2 | AY12: -0.5 | AZ12: 0.2 | BA12: -3.9 | BB12: -6 | BC12: 1 | BD12: 0 | BE12: -15.1 | BH12: -9 | BK12: 0 | BO12: -3.6 | BP12: -50.3 | BQ12: 0 | BR12: 0 | BS12: -56.1 | BX12: 0 | CA12: 0 | CB12: -0.4 | CC12: 16.3 | CD12: 22.3 | CE12: 4.6 | CF12: 5.5 | CG12: 1.7 | CK12: -1.4 | CL12: 0.2 | CM12: -51.1 | CS12: 0 | CV12: -1.8 | CW12: 0 | CZ12: 1.2 | DA12: -0.1 | DB12: -1 | DD12: 0.1 | DE12: 0.9 | DF12: 1.4 | DG12: -1.2 | DH12: 1.5 | DI12: 0.5 | DK12: 0 | DL12: 0 | DM12: -2.9 | DN12: 4.4 | DO12: 1.4 | DP12: 0.7 | DQ12: 0.7 | DR12: 0.5 | DS12: 0 | DT12: -0.1 | DU12: 0.1 | DV12: 0.7 | DX12: -4.7 | DY12: 0.3 | DZ12: 0.5 | EA12: -1.8 | EB12: 0.7 | EC12: 0.8 | ED12: 4 | EE12: 0 | EF12: -4.5 | EG12: -5.9 | EJ12: 2.8 | EK12: 0 | EM12: 0.2 | EN12: 0.2 | EO12: 0.2 | EQ12: 0 | ER12: 0 | ES12: 0 | ET12: -0.2 | EU12: 6.4 | EV12: 2.4 | EW12: 0 | EX12: 0 | EY12: 0.4 | EZ12: 1 | FA12: 2.3 | FB12: 12.6 | FC12: 4.7 | FD12: 2.8 | FF12: 2.6 | FI12: -307.89 | FK12: 1.5 | FL12: 0.438 | FN12: 1.5 | FO12: 1.10679 | FP12: 0.25865 | FQ12: -1 | FR12: 1.8 | FS12: 5.60344
A13: 19/06/2025 | B13: 01:30 | C13: -6.7 | D13: 5.5 | E13: 13 | H13: -14.8 | I13: -24.8 | L13: -41.5 | M13: -57.8 | N13: -26.7 | O13: 3.8 | R13: 29.1 | S13: 0 | X13: 3.6 | Y13: 1 | Z13: 0 | AA13: -2.96 | AB13: 3.21 | AC13: 3.35 | AG13: 0 | AH13: -1.7 | AI13: -13.5 | AM13: -1.8 | AN13: -13.1 | AO13: 5.7 | AP13: 23.2 | AQ13: 8.6 | AR13: 0 | AS13: 2.7 | AT13: 0 | AU13: -43.9 | AV13: -46.9 | AW13: -41.3 | AX13: 2.6 | AY13: -0.6 | AZ13: 0.3 | BA13: -1.6 | BB13: -5.2 | BC13: 1 | BD13: 0 | BE13: -13.9 | BH13: -9 | BK13: 0 | BO13: -5.1 | BP13: -54.3 | BQ13: 0 | BR13: 0 | BS13: -59 | BX13: 0 | CA13: 0 | CB13: -0.4 | CC13: 16.6 | CD13: 20.2 | CE13: 2.9 | CF13: 8.6 | CG13: 0.4 | CK13: -9.3 | CL13: -7.6 | CM13: -47.5 | CS13: 0 | CV13: -1.8 | CW13: 0 | CZ13: 1.2 | DA13: 0 | DB13: -0.9 | DD13: 0 | DE13: 0.8 | DF13: 1.4 | DG13: -1.6 | DH13: 1.3 | DI13: 0.5 | DK13: 0 | DL13: 0 | DM13: -2.7 | DN13: -0.1 | DO13: 1.4 | DP13: 0.7 | DQ13: 0.7 | DR13: 0.5 | DS13: 0 | DT13: -0.1 | DU13: 0.1 | DV13: 0.7 | DX13: -4.7 | DY13: 0.3 | DZ13: -0.4 | EA13: -1.8 | EB13: 0.7 | EC13: 0.8 | ED13: 4.9 | EE13: 0 | EF13: -8 | EG13: -10 | EJ13: 2.8 | EK13: 0 | EM13: 0.2 | EN13: 0.2 | EO13: 0.2 | EQ13: 0 | ER13: 0 | ES13: 0 | ET13: -0.2 | EU13: 7.6 | EV13: 4.8 | EW13: 0 | EX13: 0 | EY13: 0.4 | EZ13: 0.8 | FA13: 2.4 | FB13: 15.1 | FC13: 4.6 | FD13: 2 | FF13: 3 | FI13: -367.8 | FK13: 2.2 | FL13: 0.853 | FN13: 1.6 | FO13: 0.30678 | FP13: 0.26081 | FQ13: -0.5 | FR13: 2 | FS13: 6.72059
A14: 19/06/2025 | B14: 02:00 | C14: -5.1 | D14: 10.8 | E14: 13.7 | H14: -12.8 | I14: -11.5 | L14: -34.4 | M14: -55.1 | N14: -24.2 | O14: 9.1 | R14: 22.4 | S14: -0.1 | X14: 4.9 | Y14: 0.7 | Z14: 0 | AA14: -2.94 | AB14: 3.58 | AC14: 3.41 | AG14: 0 | AH14: -1.5 | AI14: -11.2 | AM14: -1.7 | AN14: 4.5 | AO14: 6.7 | AP14: 23.8 | AQ14: 8.7 | AR14: 0.1 | AS14: 2.7 | AT14: 0.2 | AU14: -41.6 | AV14: -42.4 | AW14: -37.9 | AX14: 1.7 | AY14: -0.5 | AZ14: 0.2 | BA14: -2.1 | BB14: -5.1 | BC14: 1 | BD14: 0 | BE14: -13.9 | BH14: -9 | BK14: 0 | BO14: 0.4 | BP14: -50.7 | BQ14: 0 | BR14: 0 | BS14: -58.5 | BX14: 0 | CA14: 0 | CB14: -0.4 | CC14: 9 | CD14: 9 | CE14: 2.6 | CF14: 1.1 | CG14: -0.1 | CK14: -5.8 | CL14: -4.2 | CM14: -41.6 | CS14: 0 | CV14: -2.3 | CW14: 0 | CZ14: 1.2 | DA14: -0.1 | DB14: -0.9 | DD14: 0.1 | DE14: 0.9 | DF14: 1.5 | DG14: -1.6 | DH14: 1.3 | DI14: 0.5 | DK14: 0 | DL14: 0 | DM14: -2.8 | DN14: -0.3 | DO14: 1.4 | DP14: 0.7 | DQ14: 0.7 | DR14: 0.5 | DS14: 0 | DT14: 0.2 | DU14: 0.1 | DV14: 0.6 | DX14: -4.7 | DY14: 0.6 | DZ14: -0.4 | EA14: -1.8 | EB14: 0.6 | EC14: 0.8 | ED14: 10.1 | EE14: 0 | EF14: -7.7 | EG14: -9 | EJ14: 2.8 | EK14: 0 | EM14: 0.2 | EN14: 0.2 | EO14: 0.2 | EQ14: 0 | ER14: 0 | ES14: 0 | ET14: -0.2 | EU14: 8.6 | EV14: 4.3 | EW14: 0 | EX14: 0 | EY14: 0.4 | EZ14: 0.8 | FA14: 2.5 | FB14: 14.7 | FC14: 4.7 | FD14: 1.1 | FF14: 2.7 | FI14: -300.85 | FK14: 2.3 | FL14: 0.925 | FN14: 1.7 | FO14: 0.31938 | FP14: 0.23008 | FQ14: -0.3 | FR14: 2 | FS14: 7.17446
A15: 19/06/2025 | B15: 02:30 | C15: -5.9 | D15: 8 | E15: 13.2 | H15: -12.8 | I15: -14.1 | L15: -45.4 | M15: -59.7 | N15: -28.4 | O15: 0.3 | R15: 19.2 | S15: 0.1 | X15: 3.4 | Y15: 0.4 | Z15: 0 | AA15: -2.95 | AB15: 3.54 | AC15: 2.73 | AG15: 0 | AH15: -1.4 | AI15: -4.1 | AM15: -1.7 | AN15: 19.8 | AO15: 7.4 | AP15: 23.1 | AQ15: 8.8 | AR15: -0.3 | AS15: 2.7 | AT15: 1.1 | AU15: -42.4 | AV15: -46.1 | AW15: -42.2 | AX15: 6.5 | AY15: -0.5 | AZ15: 0.3 | BA15: 1.7 | BB15: -3.5 | BC15: 0.9 | BD15: 0 | BE15: -11.7 | BH15: -8.6 | BK15: 0 | BO15: 0.6 | BP15: -55.3 | BQ15: 0 | BR15: 0 | BS15: -60.2 | BX15: 0 | CA15: 0 | CB15: -0.5 | CC15: 7.8 | CD15: 8.5 | CE15: 1.7 | CF15: 1.1 | CG15: -0.1 | CK15: -9.7 | CL15: -8 | CM15: -47.1 | CS15: 0 | CV15: -1.8 | CW15: 0 | CZ15: 1.2 | DA15: 0 | DB15: -0.8 | DD15: 0.1 | DE15: 0.9 | DF15: 1.5 | DG15: -1.2 | DH15: 1.3 | DI15: 0.5 | DK15: 0 | DL15: 0 | DM15: -3.1 | DN15: -0.9 | DO15: 1.4 | DP15: 0.7 | DQ15: 0.7 | DR15: 0.5 | DS15: 0 | DT15: 0.1 | DU15: 0.1 | DV15: 0.6 | DX15: -4.7 | DY15: 0.5 | DZ15: -0.5 | EA15: -1.5 | EB15: 0.5 | EC15: 0.8 | ED15: 10.2 | EE15: 0 | EF15: -10.3 | EG15: -11.7 | EJ15: 2.8 | EK15: 0 | EM15: 0.2 | EN15: 0.2 | EO15: 0.2 | EQ15: 0 | ER15: 0 | ES15: 0 | ET15: -0.2 | EU15: 10.2 | EV15: 4 | EW15: 0 | EX15: 0 | EY15: 0.4 | EZ15: 0.8 | FA15: 2.5 | FB15: 15.7 | FC15: 6 | FD15: 1.4 | FF15: 2.6 | FI15: -337.88 | FK15: 2.5 | FL15: 0.866 | FN15: 1.6 | FO15: 0.32582 | FP15: 0.23272 | FQ15: -0.6 | FR15: 2.1 | FS15: 7.02454
A16: 19/06/2025 | B16: 03:00 | C16: -10.9 | D16: 12.1 | E16: 13.3 | H16: -11.7 | I16: -21.5 | L16: -40.1 | M16: -57.4 | N16: -26.2 | O16: 4.6 | R16: 10.9 | S16: 0.1 | X16: 5.4 | Y16: 1.2 | Z16: 0 | AA16: -2.92 | AB16: 3.63 | AC16: 4.21 | AG16: 0 | AH16: -3.2 | AI16: 0 | AM16: -1.6 | AN16: 40.2 | AO16: 8.1 | AP16: 25.4 | AQ16: 8.4 | AR16: 0.4 | AS16: 2.7 | AT16: 2.3 | AU16: -43.9 | AV16: -47.7 | AW16: -43.2 | AX16: 4.7 | AY16: -0.3 | AZ16: 0.3 | BA16: 0 | BB16: -4.9 | BC16: 1 | BD16: 0 | BE16: -12.8 | BH16: -9 | BK16: 0 | BO16: 3 | BP16: -55.4 | BQ16: 0 | BR16: 0 | BS16: -60 | BX16: 0 | CA16: 0 | CB16: -0.4 | CC16: 7.7 | CD16: 9.9 | CE16: 2.8 | CF16: 0.9 | CG16: -0.2 | CK16: -10.8 | CL16: -9.4 | CM16: -49.3 | CS16: 0 | CV16: -2.3 | CW16: 0 | CZ16: 1.2 | DA16: 0 | DB16: -1 | DD16: 0 | DE16: 1 | DF16: 1.4 | DG16: -1.2 | DH16: 1.3 | DI16: 0.6 | DK16: 0 | DL16: 0 | DM16: -2.8 | DN16: -0.1 | DO16: 1.4 | DP16: 0.7 | DQ16: 0.7 | DR16: 0.5 | DS16: 0 | DT16: -0.1 | DU16: 0.1 | DV16: 0.6 | DX16: -4.7 | DY16: 0.3 | DZ16: -0.7 | EA16: -1.4 | EB16: 0.7 | EC16: 0.8 | ED16: 9.4 | EE16: 0 | EF16: -8.8 | EG16: -9.4 | EJ16: 2.8 | EK16: -0.1 | EM16: 0.2 | EN16: 0.2 | EO16: 0.2 | EQ16: 0 | ER16: 0 | ES16: 0 | ET16: -0.2 | EU16: 10.2 | EV16: 3.6 | EW16: 0 | EX16: 0 | EY16: 0.4 | EZ16: 1 | FA16: 2.5 | FB16: 15.6 | FC16: 5.4 | FD16: 2.5 | FF16: 3.3 | FI16: -313.78 | FK16: 2.3 | FL16: 0.879 | FN16: 1.6 | FO16: 0.32002 | FP16: 0.31025 | FQ16: -0.7 | FR16: 2 | FS16: 6.70927
A17: 19/06/2025 | B17: 03:30 | C17: -10.9 | D17: 19 | E17: 15.7 | H17: -12.1 | I17: -10.4 | L17: -41.8 | M17: -55.6 | N17: -24.4 | O17: 3.4 | R17: 14.9 | S17: 0.1 | X17: 4.8 | Y17: 0.7 | Z17: 0 | AA17: -2.93 | AB17: 3.55 | AC17: 3.16 | AG17: 0 | AH17: -1.8 | AI17: 0 | AM17: -1.7 | AN17: 39.9 | AO17: 7.6 | AP17: 19.6 | AQ17: 6.4 | AR17: -0.1 | AS17: 2.7 | AT17: 1.6 | AU17: -41.3 | AV17: -45.2 | AW17: -41.2 | AX17: 7.1 | AY17: -0.4 | AZ17: 0.2 | BA17: 1.8 | BB17: -4.2 | BC17: 1 | BD17: 0 | BE17: -10.4 | BH17: -8.6 | BK17: 0 | BO17: 4.1 | BP17: -54.2 | BQ17: 0 | BR17: 0 | BS17: -60.5 | BX17: 0 | CA17: 0 | CB17: -0.4 | CC17: 7.8 | CD17: 8.3 | CE17: 1.7 | CF17: 2.3 | CG17: -0.1 | CK17: -9.1 | CL17: -7.4 | CM17: -46.5 | CS17: 0 | CV17: -2.2 | CW17: 0 | CZ17: 1.2 | DA17: 0.1 | DB17: -1 | DD17: 0.1 | DE17: 0.9 | DF17: 1.4 | DG17: -1.2 | DH17: 1.3 | DI17: 0.6 | DK17: 0 | DL17: 0 | DM17: -2.6 | DN17: 0.2 | DO17: 1.4 | DP17: 0.7 | DQ17: 0.7 | DR17: 0.5 | DS17: 0 | DT17: 0 | DU17: -0.1 | DV17: 0.6 | DX17: -4.7 | DY17: 0.4 | DZ17: -0.4 | EA17: -1.3 | EB17: 0.7 | EC17: 0.8 | ED17: 9.1 | EE17: 0 | EF17: -5.1 | EG17: -5.5 | EJ17: 2.8 | EK17: -0.1 | EM17: 0.2 | EN17: 0.2 | EO17: 0.2 | EQ17: 0 | ER17: 0 | ES17: 0 | ET17: -0.2 | EU17: 10.7 | EV17: 6.7 | EW17: 0 | EX17: 0 | EY17: 0.4 | EZ17: 1 | FA17: 2.6 | FB17: 15.2 | FC17: 4.9 | FD17: 3.1 | FF17: 2.9 | FI17: -266.62 | FK17: 2.3 | FL17: 0.848 | FN17: 1.6 | FO17: 0.32334 | FP17: 0.28032 | FQ17: -0.7 | FR17: 2 | FS17: 6.65166
A18: 19/06/2025 | B18: 04:00 | C18: -11.4 | D18: 19.4 | E18: 16.1 | H18: -13.2 | I18: -11 | L18: -44.4 | M18: -56.8 | N18: -25.6 | O18: 0.4 | R18: 16 | S18: 0.1 | X18: 3.9 | Y18: 0.6 | Z18: 0 | AA18: -2.93 | AB18: 3.54 | AC18: 3.13 | AG18: 0 | AH18: -1.6 | AI18: 0 | AM18: -1.6 | AN18: 40.1 | AO18: 7.4 | AP18: 18.9 | AQ18: 7 | AR18: 0.2 | AS18: 2.7 | AT18: 1.6 | AU18: -42.2 | AV18: -46.4 | AW18: -42.6 | AX18: 8.5 | AY18: -0.5 | AZ18: 0.2 | BA18: 3.5 | BB18: -1.8 | BC18: 1 | BD18: 0 | BE18: -9.5 | BH18: -8.3 | BK18: 0 | BO18: 4.5 | BP18: -55 | BQ18: 0 | BR18: 0 | BS18: -60.6 | BX18: 0 | CA18: 0 | CB18: -0.4 | CC18: 7.8 | CD18: 7.8 | CE18: 1.2 | CF18: 1.2 | CG18: 0.2 | CK18: -6.2 | CL18: -4.6 | CM18: -41.8 | CS18: 0 | CV18: -1.7 | CW18: 0 | CZ18: 1.2 | DA18: 0.1 | DB18: -1 | DD18: 0.1 | DE18: 0.9 | DF18: 1.5 | DG18: -1.2 | DH18: 1.4 | DI18: 0.6 | DK18: 0 | DL18: 0 | DM18: -2.6 | DN18: 0.1 | DO18: 1.4 | DP18: 0.7 | DQ18: 0.7 | DR18: 0.5 | DS18: 0 | DT18: 0.2 | DU18: 0.1 | DV18: 0.6 | DX18: -4.7 | DY18: 0.4 | DZ18: -0.5 | EA18: -1.3 | EB18: 0.7 | EC18: 0.8 | ED18: 7.8 | EE18: 0 | EF18: -4.2 | EG18: -6.8 | EJ18: 2.8 | EK18: -0.1 | EM18: 0.2 | EN18: 0.2 | EO18: 0.2 | EQ18: 0 | ER18: 0 | ES18: 0 | ET18: -0.2 | EU18: 14.8 | EV18: 6.6 | EW18: 0 | EX18: 0 | EY18: 0.4 | EZ18: 1 | FA18: 2.6 | FB18: 15.8 | FC18: 5.6 | FD18: 4 | FF18: 2.8 | FI18: -258.96 | FK18: 2.3 | FL18: 0.899 | FN18: 1.6 | FO18: 0.32219 | FP18: 0.25515 | FQ18: -0.5 | FR18: 1.9 | FS18: 6.77634
A19: 19/06/2025 | B19: 04:30 | C19: -10.3 | D19: 17.9 | E19: 15.2 | H19: -11.9 | I19: -7.2 | L19: -40.7 | M19: -61.8 | N19: -32 | O19: 3.9 | R19: 18.1 | S19: -0.1 | X19: 4.4 | Y19: 1.2 | Z19: 0 | AA19: -2.94 | AB19: 3.72 | AC19: 3.81 | AG19: 0 | AH19: -2.8 | AI19: 0 | AM19: -1.6 | AN19: 41.2 | AO19: 7.6 | AP19: 20.3 | AQ19: 6.9 | AR19: 0.7 | AS19: 2.7 | AT19: -0.2 | AU19: -42.5 | AV19: -43.7 | AW19: -39.3 | AX19: 9.7 | AY19: -0.4 | AZ19: 0.1 | BA19: -1.1 | BB19: -3.9 | BC19: 1 | BD19: 0 | BE19: -14.2 | BH19: -8.6 | BK19: 0 | BO19: 6 | BP19: -52.8 | BQ19: 0 | BR19: 0 | BS19: -60.1 | BX19: 0 | CA19: 0 | CB19: -0.4 | CC19: 12.1 | CD19: 10 | CE19: 2.2 | CF19: 1.1 | CG19: 0 | CK19: -3.4 | CL19: -1.8 | CM19: -38 | CS19: 0 | CV19: -1.4 | CW19: 0 | CZ19: 1.2 | DA19: 0 | DB19: -0.9 | DD19: 0.1 | DE19: 0.9 | DF19: 1.5 | DG19: -1.4 | DH19: 1.2 | DI19: 0.5 | DK19: 0 | DL19: 0 | DM19: -2.4 | DN19: 0.6 | DO19: 1.4 | DP19: 0.7 | DQ19: 0.7 | DR19: 0.5 | DS19: 0 | DT19: 0.1 | DU19: 0.1 | DV19: 0.6 | DX19: -4.7 | DY19: 0.4 | DZ19: -0.2 | EA19: -0.9 | EB19: 0.9 | EC19: 0.8 | ED19: 0 | EE19: 0 | EF19: -6.3 | EG19: -8 | EJ19: 2.8 | EK19: -0.1 | EM19: 0.2 | EN19: 0.2 | EO19: 0.2 | EQ19: 0 | ER19: 0 | ES19: 0 | ET19: -0.2 | EU19: 10.3 | EV19: 3.6 | EW19: 0 | EX19: 0 | EY19: 0.4 | EZ19: 1.2 | FA19: 2.5 | FB19: 15.6 | FC19: 5.5 | FD19: 3 | FF19: 3 | FI19: -257.71 | FK19: 2.4 | FL19: 0.982 | FN19: 1.6 | FO19: 0.32027 | FP19: 0.19858 | FQ19: -0.3 | FR19: 0.4 | FS19: 5.60085
A20: 19/06/2025 | B20: 05:00 | C20: -11.3 | D20: 14.5 | E20: 14.6 | H20: -10.8 | I20: -8.6 | L20: -41.6 | M20: -56.9 | N20: -26.2 | O20: 2.8 | R20: 15.5 | S20: 0 | X20: 3.8 | Y20: 0.9 | Z20: 0 | AA20: -2.95 | AB20: 3.79 | AC20: 3.81 | AG20: 0 | AH20: -2.9 | AI20: -1 | AM20: -1.6 | AN20: 40.7 | AO20: 7.4 | AP20: 19.4 | AQ20: 6.6 | AR20: -0.7 | AS20: 2.7 | AT20: 0.4 | AU20: -41.4 | AV20: -44.8 | AW20: -40.5 | AX20: 7.4 | AY20: -0.4 | AZ20: 0.2 | BA20: 0.2 | BB20: -3 | BC20: 0.9 | BD20: 0 | BE20: -12 | BH20: -9 | BK20: 0 | BO20: 4.7 | BP20: -53.6 | BQ20: 0 | BR20: 0 | BS20: -60.6 | BX20: 0 | CA20: 0 | CB20: -0.4 | CC20: 11.2 | CD20: 8.9 | CE20: 2.2 | CF20: 1.1 | CG20: 0.1 | CK20: -4 | CL20: -2.5 | CM20: -38.7 | CS20: 0 | CV20: -1.4 | CW20: 0 | CZ20: 1.2 | DA20: 0 | DB20: -0.9 | DD20: 0.1 | DE20: 0.9 | DF20: 1.5 | DG20: -1.4 | DH20: 1.2 | DI20: 0.5 | DK20: 0 | DL20: 0 | DM20: -2.5 | DN20: 0.2 | DO20: 1.4 | DP20: 0.7 | DQ20: 0.7 | DR20: 0.5 | DS20: 0.2 | DT20: 0.2 | DU20: 0.1 | DV20: 0.6 | DX20: -4.7 | DY20: 0.3 | DZ20: -0.3 | EA20: -1.4 | EB20: 0.9 | EC20: 0.8 | ED20: 0.4 | EE20: 0.4 | EF20: -6.5 | EG20: -8.8 | EJ20: 2.8 | EK20: -0.1 | EM20: 0.2 | EN20: 0.2 | EO20: 0.2 | EQ20: 0 | ER20: 0 | ES20: 0 | ET20: -0.2 | EU20: 11 | EV20: 6 | EW20: 0 | EX20: 0 | EY20: 0.4 | EZ20: 1.2 | FA20: 2.6 | FB20: 15.9 | FC20: 5.8 | FD20: 3.1 | FF20: 2.9 | FI20: -264.75 | FK20: 2.4 | FL20: 1.115 | FN20: 1.6 | FO20: 0.31808 | FP20: 0.15631 | FQ20: -0.3 | FR20: 0.4 | FS20: 5.68939
A21: 19/06/2025 | B21: 05:30 | C21: -9.5 | D21: 19.5 | E21: 15.2 | H21: -8.6 | I21: -3.5 | L21: -37.8 | M21: -55.4 | N21: -24.2 | O21: 8 | R21: 16.6 | S21: 0 | X21: 6.7 | Y21: 1.4 | Z21: 0 | AA21: -2.95 | AB21: 3.79 | AC21: 5.4 | AG21: 0 | AH21: -1.9 | AI21: -5.8 | AM21: -1.4 | AN21: 41.3 | AO21: 7.8 | AP21: 20.1 | AQ21: 6.3 | AR21: -0.3 | AS21: 2.7 | AT21: 0.5 | AU21: -38.6 | AV21: -42 | AW21: -37.8 | AX21: 9.2 | AY21: -0.4 | AZ21: 0 | BA21: 0.2 | BB21: -2.2 | BC21: 0.9 | BD21: 0 | BE21: -11.7 | BH21: -8.6 | BK21: 0 | BO21: 5.1 | BP21: -51.5 | BQ21: 0 | BR21: 0 | BS21: -57.7 | BX21: 0 | CA21: 0 | CB21: -0.4 | CC21: 11.1 | CD21: 9.3 | CE21: 1.9 | CF21: 1.1 | CG21: -0.1 | CK21: -0.7 | CL21: 1 | CM21: -34.2 | CS21: 0 | CV21: -2.7 | CW21: 0 | CZ21: 1.2 | DA21: 0 | DB21: -1 | DD21: 0.1 | DE21: 0.8 | DF21: 1.4 | DG21: -1.5 | DH21: 1.3 | DI21: 0.5 | DK21: 0 | DL21: 0 | DM21: -2.5 | DN21: 0.3 | DO21: 1.4 | DP21: 0.7 | DQ21: 0.7 | DR21: 0.5 | DS21: 0.2 | DT21: 0.2 | DU21: 0.1 | DV21: 0.5 | DX21: -4.7 | DY21: 0.4 | DZ21: -0.3 | EA21: -1.1 | EB21: 1.1 | EC21: 0.8 | ED21: 4 | EE21: 0.4 | EF21: -9.3 | EG21: -10.7 | EJ21: 2.8 | EK21: -0.1 | EM21: 0.2 | EN21: 0.2 | EO21: 0.2 | EQ21: 0 | ER21: 0 | ES21: 0 | ET21: -0.2 | EU21: 13.4 | EV21: 7.2 | EW21: 0 | EX21: 0 | EY21: 0.4 | EZ21: 1.4 | FA21: 2.3 | FB21: 17 | FC21: 6.8 | FD21: 3 | FF21: 2.8 | FI21: -201.96 | FK21: 2.6 | FL21: 0.713 | FN21: 1.6 | FO21: 0.31502 | FP21: 0.11741 | FQ21: 0.2 | FR21: -0.1 | FS21: 5.44543
A22: 19/06/2025 | B22: 06:00 | C22: -10.1 | D22: 31.2 | E22: 17.5 | H22: -8 | I22: 2.4 | L22: -33.9 | M22: -49.7 | N22: -18.5 | O22: 13.7 | R22: 50.1 | S22: 0 | X22: 7.2 | Y22: 1.1 | Z22: 0 | AA22: -3.01 | AB22: 4.29 | AC22: 7.91 | AG22: 0 | AH22: -1.9 | AI22: -2.9 | AM22: -1.4 | AN22: 42.1 | AO22: 8.2 | AP22: 18.9 | AQ22: 6.9 | AR22: -1.1 | AS22: 2.7 | AT22: 0.9 | AU22: -35.1 | AV22: -38.6 | AW22: -34.3 | AX22: 6.9 | AY22: -0.4 | AZ22: 0 | BA22: 0 | BB22: -1.6 | BC22: 0.9 | BD22: 0 | BE22: -10.5 | BH22: -7.2 | BK22: 0 | BO22: 5.7 | BP22: -48.8 | BQ22: 0 | BR22: 0 | BS22: -56.7 | BX22: 0 | CA22: 0 | CB22: -0.4 | CC22: 10.8 | CD22: 13.2 | CE22: 1.5 | CF22: 1.1 | CG22: 0 | CK22: 6.1 | CL22: 7.9 | CM22: -28.3 | CS22: 0 | CV22: -2.4 | CW22: 0 | CZ22: 1.2 | DA22: 0 | DB22: -1 | DD22: 0.1 | DE22: 0.8 | DF22: 1.5 | DG22: -0.8 | DH22: 1.3 | DI22: 0.5 | DK22: 0 | DL22: 0 | DM22: -2.7 | DN22: 0.2 | DO22: 1.4 | DP22: 0.7 | DQ22: 0.7 | DR22: 0.5 | DS22: 0.3 | DT22: 0.1 | DU22: -0.1 | DV22: 0.6 | DX22: -4.8 | DY22: 0.3 | DZ22: -0.5 | EA22: -0.6 | EB22: 1.2 | EC22: 0.8 | ED22: 4 | EE22: 0.3 | EF22: -8.5 | EG22: -10.2 | EJ22: 2.8 | EK22: -0.1 | EM22: 0.2 | EN22: 0.2 | EO22: 0.2 | EQ22: 0 | ER22: 0 | ES22: 0 | ET22: -0.2 | EU22: 9.9 | EV22: 4.2 | EW22: 0 | EX22: 0 | EY22: 0.4 | EZ22: 1.4 | FA22: 2.5 | FB22: 18.7 | FC22: 8.4 | FD22: 1.8 | FF22: 2.8 | FI22: -85.11 | FK22: 2.4 | FL22: 0.139 | FN22: 1.6 | FO22: 0.32939 | FP22: 0.11912 | FQ22: 0.4 | FR22: 0.4 | FS22: 5.38751
... A58: 20/06/2025 | B58: 00:00 | C58: -7.7 | D58: 26.6 | E58: 20.2 | H58: -9.7 | I58: -9.3 | L58: -26.2 | M58: -29.4 | N58: 1.3 | O58: 25.7 | R58: 47.9 | S58: 0.1 | X58: 7.9 | Y58: 0.7 | Z58: 2.6 | AA58: -3.4 | AB58: 1.77 | AC58: -2.08 | AG58: 0 | AH58: -1.2 | AI58: -9.7 | AM58: -1.6 | AN58: -10.3 | AO58: 2.8 | AP58: 26.2 | AQ58: 7.1 | AR58: -0.3 | AS58: 2.7 | AT58: 1.2 | AU58: -18.1 | AV58: -38.2 | AW58: -48.3 | AX58: 2.3 | AY58: -1 | AZ58: 0.3 | BA58: -2.6 | BB58: 2.7 | BC58: 0.9 | BD58: 0 | BE58: 3.6 | BH58: -5.8 | BK58: 3.9 | BO58: -3.3 | BP58: -31 | BQ58: 0 | BR58: -3 | BS58: -16.1 | BX58: 0 | CA58: 0 | CB58: -0.4 | CC58: 8.7 | CD58: 20.4 | CE58: 3.2 | CF58: 1.7 | CG58: -3 | CK58: -11 | CL58: -9 | CM58: -46.8 | CS58: 0 | CV58: -4.8 | CW58: 0 | CZ58: 1.1 | DA58: 0 | DB58: -0.9 | DD58: 0.2 | DE58: 0.7 | DF58: 1.5 | DG58: -1.2 | DH58: 0.5 | DI58: 0.5 | DK58: 0 | DL58: 0 | DM58: -2.4 | DN58: -3.7 | DO58: 1.4 | DP58: 0.4 | DQ58: 0.7 | DR58: 1.1 | DS58: 0 | DT58: 0.2 | DU58: 0.3 | DV58: 0.5 | DX58: -4.2 | DY58: 0 | DZ58: -0.5 | EA58: -0.8 | EB58: 0.5 | EC58: 0.8 | ED58: 4 | EE58: 0 | EF58: -3.6 | EG58: -7.3 | EJ58: 2.8 | EK58: -0.1 | EM58: 0.2 | EN58: 0.2 | EO58: 0.2 | EQ58: 0 | ER58: 0 | ES58: 0 | ET58: -0.2 | EU58: -4.1 | EV58: -0.8 | EW58: 0 | EX58: 0 | EY58: 0.4 | EZ58: 0.8 | FA58: 2.1 | FB58: 0 | FC58: 0 | FD58: 2.8 | FF58: 0 | FI58: -136.71 | FK58: 1.8 | FL58: 0.123 | FN58: 1.6 | FO58: 0.27424 | FP58: 0.3031 | FQ58: -0.1 | FR58: 1 | FS58: 5.00034
A59: EJEC | C59: 98.4 | D59: 638.5 | E59: 469.25 | F59: 0 | G59: 0 | H59: -145.8 | I59: -117.15 | J59: 0 | K59: 0 | L59: 96.55 | M59: -148.2 | N59: 85.15 | O59: 780.2 | P59: 0 | Q59: 0 | R59: 1019.4 | S59: 0.95 | T59: 0 | U59: 0 | V59: 0 | W59: 0 | X59: 189.2 | Y59: 21.35 | Z59: 35.35 | AA59: -76.16 | AB59: 75.475 | AC59: 178.23 | AD59: 0 | AE59: 0 | AF59: 0 | AG59: 1.715 | AH59: 91.3 | AI59: 32.6 | AJ59: 0 | AK59: 0 | AL59: 0 | AM59: -30.75 | AN59: 539.5 | AO59: 145.75 | AP59: 632.65 | AQ59: 214 | AR59: -0.2 | AS59: 64.8 | AT59: 23.4 | AU59: -435.65 | AV59: -633.95 | AW59: -1016.1 | AX59: 202.35 | AY59: -15.8 | AZ59: 3.8 | BA59: -10.35 | BB59: -43.7 | BC59: 23.25 | BD59: 6.75 | BE59: -174.95 | BF59: 0 | BG59: 0 | BH59: -142.35 | BI59: 0 | BJ59: 0 | BK59: 53.7 | BL59: 0 | BM59: 0 | BN59: 0 | BO59: 109.8 | BP59: -874.35 | BQ59: -1.6 | BR59: -1.5 | BS59: -895.05 | BT59: 0 | BU59: 0 | BV59: 0 | BW59: 0 | BX59: 1.85 | BY59: 0 | BZ59: 0 | CA59: 25.8 | CB59: -9.75 | CC59: 914.1 | CD59: 651.35 | CE59: 208.3 | CF59: 212.55 | CG59: 57.95 | CH59: 0 | CI59: 0 | CJ59: 0 | CK59: 276.4 | CL59: 318.05 | CM59: -518.6 | CN59: 0 | CO59: 0 | CP59: 0 | CQ59: 0 | CR59: 0 | CS59: 0.1 | CT59: 0 | CU59: 0 | CV59: -80.35 | CW59: 53.4 | CX59: 0 | CY59: 0 | CZ59: 27.7 | DA59: -0.45 | DB59: -22.3 | DC59: 0 | DD59: 1.25 | DE59: 20.55 | DF59: 34.55 | DG59: 6.5 | DH59: 31.05 | DI59: 13 | DJ59: 0 | DK59: -6.65 | DL59: -12.1 | DM59: -63.8 | DN59: -16.1 | DO59: 33.6 | DP59: 10.85 | DQ59: 17.2 | DR59: 10.25 | DS59: -11.7 | DT59: 1.75 | DU59: 6.15 | DV59: 14.3 | DW59: 0 | DX59: -108.25 | DY59: 4.55 | DZ59: -4.8 | EA59: 6.45 | EB59: 24.7 | EC59: 19.2 | ED59: 105.55 | EE59: 14.7 | EF59: -207.65 | EG59: -227.9 | EH59: 0 | EI59: 0 | EJ59: 66.45 | EK59: -1.25 | EL59: 0 | EM59: 4.8 | EN59: 4.8 | EO59: 4.8 | EP59: 0 | EQ59: 11.45 | ER59: 13.35 | ES59: -7.65 | ET59: -4.8 | EU59: 133.9 | EV59: 27.75 | EW59: -25.5 | EX59: 10.85 | EY59: 12.9 | EZ59: 31.6 | FA59: 59.65 | FB59: 235.5 | FC59: 111.5 | FD59: 61.55 | FE59: 0 | FF59: 59.8 | FG59: 0 | FH59: 0 | FI59: 3714.51 | FK59: 48.7 | FL59: 0.935 | FM59: 0 | FN59: 37.05 | FO59: 8.005135 | FP59: 29.08113 | FQ59: 9.3 | FR59: 47.75 | FS59: 180.82127

Sheet DEMANDA_AREAS
B3: jueves, 19 de Junio del 2025
B5: REPORTE DE LA DEMANDA POR ÁREAS Y SUBAREAS OPERATIVAS (MW)
B6: FECHA HORA | C6: DEMANDA | E6: AREA | H6: SUBAREAS
C7: INTERCAMBIOS INTERNACIONALES | D7: SEIN | E7: NORTE | F7: CENTRO | G7: SUR | H7: ELECTROANDES
B8: 00:30 | C8: 0 | D8: 6434.58 | E8: 868.6538 | F8: 3827.3777 | G8: 1738.5485 | H8: 218.2659
B9: 01:00 | C9: 0 | D9: 6293.37 | E9: 856.3943 | F9: 3710.6637 | G9: 1726.312 | H9: 211.9216
B10: 01:30 | C10: 0 | D10: 6135.04 | E10: 846.6633 | F10: 3559.9668 | G10: 1728.4099 | H10: 225.5737
B11: 02:00 | C11: 0 | D11: 6175.73 | E11: 894.4425 | F11: 3566.6401 | G11: 1714.6474 | H11: 219.2586
B12: 02:30 | C12: 0 | D12: 6045.99 | E12: 864.6245 | F12: 3481.8771 | G12: 1699.4884 | H12: 221.389
B13: 03:00 | C13: 0 | D13: 6048.7 | E13: 841.5924 | F13: 3480.9358 | G13: 1726.1718 | H13: 222.3338
B14: 03:30 | C14: 0 | D14: 6159.71 | E14: 877.9883 | F14: 3577.6657 | G14: 1704.056 | H14: 219.5149
B15: 04:00 | C15: 0 | D15: 6116.79 | E15: 859.092 | F15: 3557.2322 | G15: 1700.4658 | H15: 219.3228
B16: 04:30 | C16: 0 | D16: 6145.12 | E16: 881.4626 | F16: 3541.1311 | G16: 1722.5263 | H16: 213.071
B17: 05:00 | C17: 0 | D17: 6150.17 | E17: 882.3818 | F17: 3562.8313 | G17: 1704.9569 | H17: 212.804
B18: 05:30 | C18: 0 | D18: 6219.16 | E18: 900.3065 | F18: 3568.264 | G18: 1750.5895 | H18: 210.8494
B19: 06:00 | C19: 0 | D19: 6454.28 | E19: 942.595 | F19: 3758.3197 | G19: 1753.3653 | H19: 208.2454
... B59: ENERGÍA | C59: 0 | D59: 166908.86 | E59: 24800.966 | F59: 99255.701 | G59: 42852.197 | H59: 5016.3763
B61: LEYENDA:
D63: Potencia recibida del Ecuador
D64: Potencia entregada al Ecuador

Sheet DEMANDA_UL
B3: jueves, 19 de Junio del 2025
B5: POTENCIA DE LOS GRANDES USUARIOS LIBRES (MW)
B6: FECHA HORA | C6: GRANDES USUARIOS LIBRES DEL ÁREA NORTE | X6: GRANDES USUARIOS LIBRES DEL ÁREA CENTRO | BP6: GRANDES USUARIOS LIBRES DEL ÁREA SUR
C7: ARCA CONTINENTAL LINDLEY S.A. | D7: AUSTRAL GROUP S.A.A | E7: CEMENTOS PACASMAYO | F7: CONSORCIO MINERO HORIZONTE S.R.L. | G7: CORPORACIÓN PESQUERA INCA S.A.C. | H7: CREDITEX: CIA IND.TEXTIL CREDISA | I7: HIPERMERCADOS TOTTUS S.A | J7: INDUSTRIA TEXTIL PIURA | K7: MINERA BOROO MISQUICHILCA S.A. | L7: MINERA GOLD FIELDS | M7: MINERA MARSA | N7: MINERA MISKY MAYO | O7: MINERA YANACOCHA | P7: OPEN PLAZA | Q7: PESQUERA DIAMANTE | R7: PETROPERU | S7: REAL PLAZA S.R.L. | T7: SIDER PERU | U7: SUPERMERCADOS PERUANOS S.A. | V7: TRUPAL S.A. | W7: UNIÓN DE CERVECERÍAS PERUANAS BACKUS Y JOHNSTON S. | X7: ACEROS AREQUIPA | Y7: ADMINISTRADORA JOCKEY PLAZA SHOPPING CENTER S.A. | Z7: ALICORP | AA7: ARCA CONTINENTAL LINDLEY S.A. | AB7: AUSTRAL GROUP S.A.A | AC7: COMPAÑIA MINERA CONDESTABLE | AD7: CORPORACIÓN PESQUERA INCA S.A.C. | AE7: CREDITEX: CIA IND.TEXTIL CREDISA | AF7: FUNDICION CHILCA S.A. | AG7: HIPERMERCADOS TOTTUS S.A | AH7: INMOBILIARIA KANPU S.A. | AI7: INMUEBLES PANAMERICANA S.A. | AJ7: KIMBERLY-CLARK PERU | AK7: LECHE GLORIA S.A. | AL7: MALL AVENTURA S.A. | AM7: MARCOBRE S.A.C. | AN7: MINERA ANTAMINA | AO7: MINERA ARES | AP7: MINERA BUENAVENTURA | AQ7: MINERA CHINALCO PERÚ S.A. | AR7: MINERA SHOUXIN PERU S.A. | AS7: MINERA VOLCAN | AT7: MINSUR | AU7: MOLYCOP-ADESUR | AV7: NEXA RESOURCES CAJAMARQUILLA S.A. | AW7: NEXA RESOURCES PERÚ S.A.A. | AX7: OPEN PLAZA | AY7: OPP FILM | AZ7: OWENS-ILLINOIS PERÚ S.A. | BA7: PAPELERA NACIONAL S.A. | BB7: PESQUERA DIAMANTE | BC7: QUIMPAC S.A. | BD7: REAL PLAZA S.R.L. | BE7: REFINERIA LA PAMPILLA S.A.A | BF7: SAGA FALABELLA | BG7: SAN MIGUEL INDUSTRIAS PET S.A. | BH7: SHOUGANG HIERRO PERU | BI7: SOFTYS PERU S.A.C. | BJ7: SUPERMERCADOS PERUANOS S.A. | BK7: TEJIDOS SAN JACINTO | BL7: TREN URBANO DE LIMA S.A. | BM7: TRUPAL S.A. | BN7: UNACEM PERU S.A. | BO7: UNIÓN DE CERVECERÍAS PERUANAS BACKUS Y JOHNSTON S. | BP7: ANGLO AMERICAN QUELLAVECO S.A. | BQ7: ARCA CONTINENTAL LINDLEY S.A. | BR7: CAL & CEMENTO SUR S.A. | BS7: COMPAÑIA MINERA ANTAPACCAY S.A. | BT7: COMPAÑÍA MINERA CHUNGAR SAC | BU7: COMPAÑIA MINERA SAN IGNACIO DE MOROCOCHA S.A.A. | BV7: EL BROCAL .S.A. | BW7: EMPRESA ADMINISTRADORA CERRO S.A.C. | BX7: EMPRESA MINERA LOS QUENUALES S.A.C. | BY7: HIPERMERCADOS TOTTUS S.A | BZ7: HUDBAY PERU S.A.C. | CA7: INDUSTRIA CACHIMAYO | CB7: MALL AVENTURA S.A. | CC7: MINERA ARES | CD7: MINERA BUENAVENTURA | CE7: MINERA CERRO VERDE | CF7: MINERA CORONA | CG7: MINERA LAS BAMBAS S.A. | CH7: MINERA VOLCAN | CI7: MINSUR | CJ7: MOLYCOP-ADESUR | CK7: NEXA RESOURCES PERÚ S.A.A. | CL7: OXIDOS DE PASCO S.A.C. | CM7: PESQUERA DIAMANTE | CN7: REAL PLAZA S.R.L. | CO7: SOBREANDES S.A.C. | CP7: SOUTHERN PERU CC | CQ7: SUPERMERCADOS PERUANOS S.A. | CR7: UNACEM PERU S.A. | CS7: UNIÓN DE CERVECERÍAS PERUANAS BACKUS Y JOHNSTON S. | CT7: YURA
B8: 00:30 | E8: 24.86961 | F8: 12.283 | L8: 27.0565 | M8: 12.8757 | N8: 5.07 | O8: 32.264 | R8: 48.295 | T8: 39.1162 | V8: 1 | X8: 145.52169 | Z8: 9.09045 | AC8: 15.68 | AF8: 4.1 | AH8: 6.3492 | AJ8: 5.33786 | AM8: 49.17228 | AN8: 133.95682 | AO8: 28.8236 | AP8: 0.81 | AQ8: 156.70551 | AR8: 16.49586 | AS8: 38.88948 | AT8: 32.23 | AV8: 164.2039 | AW8: 36.7032 | BA8: 5 | BC8: 71.1995 | BE8: 12.5 | BH8: 14.2455 | BI8: 16.96505 | BK8: 5.62421 | BM8: 3.987 | BO8: 1.79 | BP8: 136.62382 | BR8: 2.6227 | BS8: 134.27824 | BT8: 14.68522 | BV8: 33.2723 | BW8: 3.85819 | BX8: 11.9 | BZ8: 93.9175 | CA8: 25.08763 | CC8: 0.59 | CD8: 25.5851 | CE8: 454.09418 | CG8: 151.1052 | CH8: 18.75081 | CK8: 15.1594 | CL8: 4.61031 | CO8: 17.08233 | CP8: 232.07 | CR8: 26.854 | CT8: 25.429
B9: 01:00 | E9: 26.44211 | F9: 12.308 | L9: 27.1205 | M9: 12.6263 | N9: 4.81 | O9: 31.832 | R9: 48.051 | T9: 35.0446 | V9: 1 | X9: 144.64788 | Z9: 8.56551 | AC9: 16.18 | AF9: 5.8 | AH9: 4.1339 | AJ9: 5.33431 | AM9: 49.27873 | AN9: 136.32695 | AO9: 28.6345 | AP9: 0.7 | AQ9: 158.5318 | AR9: 16.53446 | AS9: 39.58309 | AT9: 32.07 | AV9: 164.7556 | AW9: 35.9168 | BA9: 4.9 | BC9: 72.99401 | BE9: 12.5 | BH9: 13.51757 | BI9: 16.607 | BK9: 5.61232 | BM9: 3.578 | BO9: 1.79 | BP9: 135.93295 | BR9: 2.5869 | BS9: 133.42865 | BT9: 14.64393 | BV9: 33.3228 | BW9: 3.96348 | BX9: 11.62 | BZ9: 92.0533 | CA9: 25.10255 | CC9: 0.62 | CD9: 24.32195 | CE9: 453.34625 | CG9: 159.1997 | CH9: 18.93986 | CK9: 14.5757 | CL9: 5.02911 | CO9: 16.29093 | CP9: 230.07 | CR9: 21.778 | CT9: 25.232
B10: 01:30 | E10: 33.65113 | F10: 12.624 | L10: 27.0275 | M10: 13.49 | N10: 5.04 | O10: 32.24 | R10: 48.103 | T10: 39.1658 | V10: 1 | X10: 118.82361 | Z10: 9.0312 | AC10: 16.46 | AF10: 5.7 | AH10: 4.6541 | AJ10: 5.31128 | AM10: 49.3703 | AN10: 136.39793 | AO10: 28.5265 | AP10: 0.64 | AQ10: 156.06974 | AR10: 16.37166 | AS10: 39.41374 | AT10: 32.07 | AV10: 162.5274 | AW10: 35.9156 | BA10: 4.6 | BC10: 72.9066 | BE10: 12.5 | BH10: 12.66971 | BI10: 16.70084 | BK10: 5.61857 | BM10: 3.986 | BO10: 1.8 | BP10: 135.60541 | BR10: 2.6384 | BS10: 134.84508 | BT10: 14.20688 | BV10: 32.9804 | BW10: 4.0073 | BX10: 11.53 | BZ10: 91.5715 | CA10: 25.12686 | CC10: 0.58 | CD10: 25.09693 | CE10: 453.12732 | CG10: 159.3498 | CH10: 18.9762 | CK10: 14.5327 | CL10: 4.78936 | CO10: 16.12909 | CP10: 224.3 | CR10: 26.579 | CT10: 25.829
B11: 02:00 | E11: 37.36388 | F11: 12.807 | L11: 27.1947 | M11: 14.3213 | N11: 4.87 | O11: 31.968 | R11: 48.351 | T11: 43.5899 | V11: 1 | X11: 115.18532 | Z11: 9.14069 | AC11: 16.25 | AF11: 2 | AH11: 4.9378 | AJ11: 5.27359 | AM11: 48.30403 | AN11: 136.03471 | AO11: 28.3957 | AP11: 0.44 | AQ11: 157.72994 | AR11: 16.73443 | AS11: 39.43562 | AT11: 31.67 | AV11: 162.3857 | AW11: 36.2048 | BA11: 4.5 | BC11: 73.10712 | BE11: 12.5 | BH11: 14.77178 | BI11: 16.57101 | BK11: 5.60815 | BM11: 3.951 | BO11: 1.97 | BP11: 136.68449 | BR11: 2.6899 | BS11: 134.53686 | BT11: 14.79023 | BV11: 33.3894 | BW11: 3.7307 | BX11: 11.99 | BZ11: 94.0915 | CA11: 25.15407 | CC11: 0.61 | CD11: 25.87948 | CE11: 447.88092 | CG11: 157.6243 | CH11: 18.97997 | CK11: 14.3263 | CL11: 4.81398 | CO11: 15.97144 | CP11: 223.87 | CR11: 26.949 | CT11: 25.611
B12: 02:30 | E12: 37.495 | F12: 12.799 | L12: 27.4694 | M12: 14.5341 | N12: 4.95 | O12: 32.474 | R12: 48.333 | T12: 37.778 | V12: 1 | X12: 126.98111 | Z12: 9.32429 | AC12: 15.5 | AF12: 2.2 | AH12: 3.4607 | AJ12: 5.22184 | AM12: 49.36034 | AN12: 132.80146 | AO12: 27.9614 | AP12: 0.41 | AQ12: 152.97284 | AR12: 16.69336 | AS12: 39.16446 | AT12: 32.32 | AV12: 164.7066 | AW12: 36.5841 | BA12: 4 | BC12: 73.34927 | BE12: 12.5 | BH12: 14.74011 | BI12: 16.74359 | BK12: 5.62327 | BM12: 2.984 | BO12: 1.95 | BP12: 136.77131 | BR12: 2.6754 | BS12: 134.65518 | BT12: 14.2784 | BV12: 33.4171 | BW12: 3.87202 | BX12: 11.98 | BZ12: 91.7378 | CA12: 25.17904 | CC12: 0.59 | CD12: 26.03855 | CE12: 450.51207 | CG12: 156.2064 | CH12: 18.99079 | CK12: 15.6251 | CL12: 4.51674 | CO12: 15.9351 | CP12: 220.19 | CR12: 28.684 | CT12: 25.511
B13: 03:00 | E13: 38.62062 | F13: 12.289 | L13: 27.3895 | M13: 14.5773 | N13: 5.49 | O13: 32.52 | R13: 48.563 | T13: 38.6311 | V13: 1 | X13: 165.79898 | Z13: 9.30832 | AC13: 15.67 | AF13: 4 | AH13: 3.3877 | AJ13: 4.81592 | AM13: 51.33191 | AN13: 134.97491 | AO13: 28.2798 | AP13: 0.67 | AQ13: 153.65363 | AR13: 16.40993 | AS13: 37.85307 | AT13: 33.66 | AV13: 164.9866 | AW13: 36.8483 | BA13: 3 | BC13: 73.25465 | BE13: 12.5 | BH13: 14.76137 | BI13: 16.571 | BK13: 5.54028 | BM13: 4.321 | BO13: 1.9 | BP13: 137.6429 | BR13: 2.6338 | BS13: 133.94684 | BT13: 14.81649 | BV13: 32.2787 | BW13: 3.96593 | BX13: 11.75 | BZ13: 91.6832 | CA13: 25.1936 | CC13: 0.59 | CD13: 26.6572 | CE13: 456.216 | CG13: 157.8767 | CH13: 19.1299 | CK13: 15.4972 | CL13: 4.49738 | CO13: 16.87402 | CP13: 227.5 | CR13: 28.803 | CT13: 25.831
B14: 03:30 | E14: 38.63682 | F14: 12.326 | L14: 27.5909 | M14: 14.3075 | N14: 5.45 | O14: 32.362 | R14: 48.354 | T14: 33.1208 | V14: 1 | X14: 147.60123 | Z14: 9.23241 | AC14: 15.47 | AF14: 5.9 | AH14: 5.195 | AJ14: 5.05719 | AM14: 50.6748 | AN14: 132.85254 | AO14: 28.7214 | AP14: 0.48 | AQ14: 158.73136 | AR14: 16.26838 | AS14: 38.30421 | AT14: 33.74 | AV14: 166.5016 | AW14: 35.1376 | BA14: 2.8 | BC14: 73.19455 | BE14: 12.5 | BH14: 15.42728 | BI14: 16.56631 | BK14: 5.56637 | BM14: 4.321 | BO14: 1.88 | BP14: 138.35836 | BR14: 2.6255 | BS14: 133.69829 | BT14: 14.65805 | BV14: 32.2433 | BW14: 4.02736 | BX14: 11.7 | BZ14: 93.0124 | CA14: 25.22371 | CC14: 0.61 | CD14: 25.96491 | CE14: 461.44594 | CG14: 158.3191 | CH14: 18.8449 | CK14: 15.2476 | CL14: 4.50547 | CO14: 16.86898 | CP14: 218.17 | CR14: 28.58 | CT14: 25.74
B15: 04:00 | E15: 38.80681 | F15: 12.407 | L15: 27.3148 | M15: 13.6053 | N15: 5.49 | O15: 33.136 | R15: 48.671 | T15: 35.918 | V15: 1 | X15: 146.38114 | Z15: 9.17334 | AC15: 15.31 | AF15: 4.7 | AH15: 4.9795 | AJ15: 5.19055 | AM15: 51.04033 | AN15: 128.67821 | AO15: 28.2662 | AP15: 0.18 | AQ15: 158.26238 | AR15: 16.15424 | AS15: 38.1567 | AT15: 33.19 | AV15: 166.0576 | AW15: 36.1244 | BA15: 2.8 | BC15: 73.02775 | BE15: 12.5 | BH15: 15.02035 | BI15: 16.74794 | BK15: 5.52264 | BM15: 3.981 | BO15: 2 | BP15: 132.14083 | BR15: 2.739 | BS15: 133.42041 | BT15: 14.61861 | BV15: 33.0747 | BW15: 3.88656 | BX15: 12 | BZ15: 94.7103 | CA15: 25.24799 | CC15: 0.62 | CD15: 25.65433 | CE15: 463.55358 | CG15: 156.1311 | CH15: 18.92059 | CK15: 15.6175 | CL15: 4.88126 | CO15: 16.65628 | CP15: 222.16 | CR15: 28.353 | CT15: 23.999
B16: 04:30 | E16: 38.64706 | F16: 12.555 | L16: 27.2327 | M16: 14.0921 | N16: 5.09 | O16: 33.108 | R16: 48.56 | T16: 47.8588 | V16: 1 | X16: 126.33157 | Z16: 9.13174 | AC16: 14.87 | AF16: 3.2 | AH16: 3.6994 | AJ16: 5.28152 | AM16: 50.00463 | AN16: 131.8825 | AO16: 27.9912 | AP16: 1.65 | AQ16: 155.71354 | AR16: 16.85146 | AS16: 38.73586 | AT16: 32.39 | AV16: 164.9295 | AW16: 34.8425 | BA16: 3 | BC16: 72.99127 | BE16: 12.5 | BH16: 12.97357 | BI16: 16.70823 | BK16: 5.64583 | BM16: 4.213 | BO16: 2.05 | BP16: 126.43364 | BR16: 2.7343 | BS16: 132.75268 | BT16: 14.45271 | BV16: 33.4291 | BW16: 3.90366 | BX16: 11.37 | BZ16: 94.6664 | CA16: 25.24107 | CC16: 0.6 | CD16: 23.50862 | CE16: 460.45882 | CG16: 156.3014 | CH16: 18.73859 | CK16: 14.719 | CL16: 4.85215 | CO16: 16.76832 | CP16: 230.97 | CR16: 28.4 | CT16: 23.998
B17: 05:00 | E17: 38.6555 | F17: 11.466 | L17: 27.7978 | M17: 15.181 | N17: 4.18 | O17: 33.204 | R17: 48.466 | T17: 48.9529 | V17: 1 | X17: 112.55033 | Z17: 8.85847 | AC17: 15.1 | AF17: 2 | AH17: 4.3319 | AJ17: 5.03627 | AM17: 50.83623 | AN17: 131.85616 | AO17: 29.1013 | AP17: 2.1 | AQ17: 156.03198 | AR17: 16.31289 | AS17: 38.28597 | AT17: 31.8 | AV17: 166.0778 | AW17: 34.1477 | BA17: 3.2 | BC17: 73.22703 | BE17: 12.5 | BH17: 12.94434 | BI17: 16.5576 | BK17: 5.78707 | BM17: 3.981 | BO17: 1.88 | BP17: 130.23847 | BR17: 2.6778 | BS17: 133.84353 | BT17: 13.44069 | BV17: 32.0395 | BW17: 4.37541 | BX17: 10.93 | BZ17: 93.5836 | CA17: 25.22615 | CC17: 0.63 | CD17: 23.24826 | CE17: 463.12265 | CG17: 149.5369 | CH17: 19.11056 | CK17: 14.9016 | CL17: 4.85792 | CO17: 16.12557 | CP17: 230.73 | CR17: 28.732 | CT17: 24.095
B18: 05:30 | E18: 36.1293 | F18: 11.393 | L18: 27.7342 | M18: 15.3621 | N18: 3.66 | O18: 34.268 | R18: 48.709 | T18: 46.5915 | V18: 1 | X18: 142.74381 | Z18: 8.9529 | AC18: 15.11 | AF18: 1.8 | AH18: 5.3918 | AJ18: 5.08865 | AM18: 51.14356 | AN18: 131.46624 | AO18: 27.8142 | AP18: 1.93 | AQ18: 155.5092 | AR18: 16.29229 | AS18: 37.0016 | AT18: 32 | AV18: 166.443 | AW18: 34.1036 | BA18: 2.8 | BC18: 73.20272 | BE18: 12.5 | BH18: 13.22532 | BI18: 16.62795 | BK18: 5.72222 | BM18: 3.987 | BO18: 1.94 | BP18: 134.91553 | BR18: 2.7234 | BS18: 133.21959 | BT18: 12.94538 | BV18: 32.345 | BW18: 3.85894 | BX18: 10.75 | BZ18: 92.7531 | CA18: 25.21291 | CC18: 0.58 | CD18: 22.81093 | CE18: 464.76551 | CG18: 156.4272 | CH18: 18.93332 | CK18: 14.64 | CL18: 4.85608 | CO18: 15.44379 | CP18: 230.49 | CR18: 30.425 | CT18: 26.043
B19: 06:00 | E19: 35.70656 | F19: 10.714 | L19: 27.5749 | M19: 14.6414 | N19: 3.54 | O19: 33.932 | R19: 48.748 | T19: 41.3269 | V19: 1 | X19: 163.93389 | Z19: 9.09992 | AC19: 15.81 | AF19: 1.8 | AH19: 6.2967 | AJ19: 5.10208 | AM19: 49.81861 | AN19: 131.48264 | AO19: 26.9779 | AP19: 1.54 | AQ19: 157.24784 | AR19: 16.28209 | AS19: 36.45354 | AT19: 32.17 | AV19: 166.4792 | AW19: 33.7936 | BA19: 2.8 | BC19: 73.44851 | BE19: 12.5 | BH19: 17.16921 | BI19: 16.54045 | BK19: 5.47533 | BM19: 3.578 | BO19: 2.12 | BP19: 130.67555 | BR19: 2.6231 | BS19: 133.75464 | BT19: 12.37594 | BV19: 32.0199 | BW19: 3.65085 | BX19: 10.31 | BZ19: 91.194 | CA19: 25.23364 | CC19: 0.61 | CD19: 23.11523 | CE19: 461.61763 | CG19: 145.2035 | CH19: 18.69851 | CK19: 14.7082 | CL19: 4.73105 | CO19: 14.12889 | CP19: 230.66 | CR19: 32.474 | CT19: 30.955
... B55: 00:00 | E55: 34.22543 | F55: 12.631 | L55: 26.531 | M55: 13.1312 | N55: 12.46 | O55: 33.612 | R55: 48.092 | T55: 43.0133 | V55: 1 | X55: 125.86944 | Z55: 8.85457 | AC55: 14.42 | AF55: 3.1 | AH55: 6.052 | AJ55: 5.27586 | AM55: 50.65941 | AN55: 98.02992 | AO55: 26.9227 | AP55: 0.83 | AQ55: 155.69509 | AR55: 16.77895 | AS55: 37.66086 | AT55: 32.06 | AV55: 160.2691 | AW55: 36.6041 | BA55: 2.9 | BC55: 73.31267 | BE55: 12.5 | BH55: 13.90938 | BI55: 17.1039 | BK55: 5.49582 | BM55: 6.981 | BO55: 1.94 | BP55: 132.8145 | BR55: 3.1159 | BS55: 133.52998 | BT55: 15.23894 | BV55: 33.5863 | BW55: 3.83695 | BX55: 12.5 | BZ55: 91.0757 | CA55: 25.06972 | CC55: 0.59 | CD55: 24.47458 | CE55: 447.18829 | CG55: 159.4183 | CH55: 18.52361 | CK55: 17.8431 | CL55: 4.88545 | CO55: 16.97662 | CP55: 205.02 | CR55: 30.263 | CT55: 25.534
B56: MWh | C56: 0 | D56: 0 | E56: 804.16559 | F56: 289.77975 | G56: 0 | H56: 0 | I56: 0 | J56: 0 | K56: 0 | L56: 657.59505 | M56: 308.94485 | N56: 136.11 | O56: 777.283 | P56: 0 | Q56: 0 | R56: 1156.23 | S56: 0 | T56: 778.88955 | U56: 0 | V56: 22.7 | W56: 0 | X56: 2535.7747 | Y56: 0 | Z56: 204.85222 | AA56: 0 | AB56: 0 | AC56: 376.075 | AD56: 0 | AE56: 0 | AF56: 71.75 | AG56: 0 | AH56: 76.7081 | AI56: 0 | AJ56: 118.96792 | AK56: 0 | AL56: 0 | AM56: 1096.8991 | AN56: 2916.4992 | AO56: 664.0597 | AP56: 18.01 | AQ56: 3764.9313 | AR56: 397.85728 | AS56: 894.97282 | AT56: 769.355 | AU56: 0 | AV56: 3573.7458 | AW56: 840.4299 | AX56: 0 | AY56: 0 | AZ56: 0 | BA56: 64 | BB56: 0 | BC56: 1591.924 | BD56: 0 | BE56: 300 | BF56: 0 | BG56: 0 | BH56: 340.64366 | BI56: 381.14451 | BJ56: 0 | BK56: 133.98863 | BL56: 0 | BM56: 119.645 | BN56: 0 | BO56: 46.445 | BP56: 3218.2509 | BQ56: 0 | BR56: 70.64545 | BS56: 3164.4862 | BT56: 322.8324 | BU56: 0 | BV56: 751.63115 | BW56: 93.388145 | BX56: 262.81 | BY56: 0 | BZ56: 2128.5194 | CA56: 526.22006 | CB56: 0 | CC56: 14.395 | CD56: 582.78346 | CE56: 10855.18 | CF56: 0 | CG56: 3755.4382 | CH56: 440.94696 | CI56: 0 | CJ56: 0 | CK56: 374.28095 | CL56: 111.32273 | CM56: 0 | CN56: 0 | CO56: 371.67705 | CP56: 5043.825 | CQ56: 0 | CR56: 665.855 | CS56: 0 | CT56: 548.304
B59: Nota :
B60: Información proporcionada por la empresas
C62: DATOS ESTIMADOS
C64: SIN DATOS

Sheet TIPO_RECURSO
B3: jueves, 19 de Junio del 2025
B5: REPORTE POTENCIA GENERADA POR TIPO DE RECURSO
B6: HORA | C6: H. PASADA | D6: H. REGULACION | E6: GAS DE CAMISEA | F6: GAS DE MALACAS | G6: GAS DE AGUAYTIA | H6: DIÉSEL | I6: RESIDUAL | J6: NAFTA+GAS DE REFINERIA | K6: FLEXIGAS+GAS DE REFINERIA | L6: BAGAZO | M6: BIOGÁS | N6: SOLAR | O6: EÓLICA | P6: TOTAL | U6: EMPRESA | V6: CENTRAL | W6: HIDROELECTRICA DE PASADA | X6: HIDROELECTRICA DE REGULACION
B7: 00:30 | C7: 1086.58 | D7: 2520.1 | E7: 2002.4 | F7: 0 | G7: 25.9 | H7: 0 | J7: =DESPACHO_EJECUTADO!FC11+DESPACHO_EJECUTADO!FD11 -> 56.4 | L7: 33.6 | M7: 10.2 | N7: 0 | O7: 699.4 | P7: =SUM(C7:O7) -> 6434.58 | U7: ANDEAN POWER S.A.C. | V7: C.H.CARHUAC | W7: 278.55
B8: 01:00 | C8: 1087.39 | D8: 2547.78 | E8: 1828.6 | F8: 0 | G8: 25.7 | H8: 0 | J8: =DESPACHO_EJECUTADO!FC12+DESPACHO_EJECUTADO!FD12 -> 57.5 | L8: 33.8 | M8: 10.2 | N8: 0 | O8: 702.4 | P8: =SUM(C8:O8) -> 6293.37 | U8: ASOCIACIÓN SANTA LUCIA DE CHACAS | V8: C.H. HUALLIN | W8: 49.1
B9: 01:30 | C9: 1084.1 | D9: 2475.64 | E9: 1717.7 | F9: 0 | G9: 25.9 | H9: 0 | J9: =DESPACHO_EJECUTADO!FC13+DESPACHO_EJECUTADO!FD13 -> 57.4 | L9: 34.6 | M9: 10.2 | N9: 0 | O9: 729.5 | P9: =SUM(C9:O9) -> 6135.04 | U9: CELEPSA | V9: C.H. EL PLATANAL | X9: 3009.85
B10: 02:00 | C10: 1094 | D10: 2503.23 | E10: 1747.1 | F10: 0 | G10: 26.2 | H10: 0 | J10: =DESPACHO_EJECUTADO!FC14+DESPACHO_EJECUTADO!FD14 -> 57.3 | L10: 34.2 | M10: 10.2 | N10: 0 | O10: 703.5 | P10: =SUM(C10:O10) -> 6175.73 | U10: CELEPSA RENOVABLES S.R.L. | V10: C.H. MARAÑON | W10: 475.2
B11: 02:30 | C11: 1093.79 | D11: 2445.8 | E11: 1671.4 | F11: 0 | G11: 25.9 | H11: 0 | J11: =DESPACHO_EJECUTADO!FC15+DESPACHO_EJECUTADO!FD15 -> 57.6 | L11: 33.4 | M11: 10.2 | N11: 0 | O11: 707.9 | P11: =SUM(C11:O11) -> 6045.99 | U11: CHINANGO S.A.C. | V11: C.H. CHIMAY | X11: 2969.55
B12: 03:00 | C12: 1076.49 | D12: 2373.91 | E12: 1784.7 | F12: 0 | G12: 26.2 | H12: 0 | J12: =DESPACHO_EJECUTADO!FC16+DESPACHO_EJECUTADO!FD16 -> 57.5 | L12: 35 | M12: 10.2 | N12: 0 | O12: 684.7 | P12: =SUM(C12:O12) -> 6048.7 | V12: C.H. YANANGO | W12: 976.7
B13: 03:30 | C13: 1096.69 | D13: 2493.92 | E13: 1705 | F13: 0 | G13: 26.5 | H13: 0 | J13: =DESPACHO_EJECUTADO!FC17+DESPACHO_EJECUTADO!FD17 -> 57.7 | L13: 34.8 | M13: 10.2 | N13: 0 | O13: 734.9 | P13: =SUM(C13:O13) -> 6159.71 | U13: EGASA | V13: C.H. CHARCANI III | W13: 154.29
B14: 04:00 | C14: 1092 | D14: 2472.59 | E14: 1656.6 | F14: 0 | G14: 26.6 | H14: 0 | J14: =DESPACHO_EJECUTADO!FC18+DESPACHO_EJECUTADO!FD18 -> 57.6 | L14: 35.2 | M14: 10.2 | N14: 0 | O14: 766 | P14: =SUM(C14:O14) -> 6116.79 | V14: C.H. CHARCANI IV | X14: 255.51
B15: 04:30 | C15: 1090.38 | D15: 2561.44 | E15: 1658.7 | F15: 0 | G15: 24.7 | H15: 0 | J15: =DESPACHO_EJECUTADO!FC19+DESPACHO_EJECUTADO!FD19 -> 58 | L15: 35.3 | M15: 10.2 | N15: 0 | O15: 706.4 | P15: =SUM(C15:O15) -> 6145.12 | V15: C.H. CHARCANI V | X15: 1666.04
B16: 05:00 | C16: 1084.93 | D16: 2536.24 | E16: 1660 | F16: 0 | G16: 25.9 | H16: 0 | J16: =DESPACHO_EJECUTADO!FC20+DESPACHO_EJECUTADO!FD20 -> 57.7 | L16: 35.8 | M16: 10.2 | N16: 0 | O16: 739.4 | P16: =SUM(C16:O16) -> 6150.17 | U16: EGEJUNIN | V16: C.H. HUASAHUASI I | W16: 454.95
B17: 05:30 | C17: 1090.45 | D17: 2615.21 | E17: 1681.7 | F17: 0 | G17: 26 | H17: 0 | J17: =DESPACHO_EJECUTADO!FC21+DESPACHO_EJECUTADO!FD21 -> 57.5 | L17: 34.4 | M17: 10.2 | N17: 0 | O17: 703.7 | P17: =SUM(C17:O17) -> 6219.16 | V17: C.H. RUNATULLO II | W17: 220.9
B18: 06:00 | C18: 1087.43 | D18: 2726.75 | E18: 1861.1 | F18: 0 | G18: 25.4 | H18: 0 | J18: =DESPACHO_EJECUTADO!FC22+DESPACHO_EJECUTADO!FD22 -> 58.7 | L18: 35.6 | M18: 10.2 | N18: 0.1 | O18: 649 | P18: =SUM(C18:O18) -> 6454.28 | V18: C.H. RUNATULLO III | W18: 316.2
B19: 06:30 | C19: 1081.15 | D19: 2962.65 | E19: 1878.4 | F19: 0 | G19: 25.9 | H19: 0 | J19: =DESPACHO_EJECUTADO!FC23+DESPACHO_EJECUTADO!FD23 -> 58.2 | L19: 32.9 | M19: 10.2 | N19: 12.1 | O19: 643 | P19: =SUM(C19:O19) -> 6704.5 | V19: C.H. SANTA CRUZ I | W19: 113.9
B20: 07:00 | C20: 1080.43 | D20: 2896.6 | E20: 1810.3 | F20: 0 | G20: 26.4 | H20: 0 | J20: =DESPACHO_EJECUTADO!FC24+DESPACHO_EJECUTADO!FD24 -> 58.2 | L20: 34.1 | M20: 10.2 | N20: 139.9 | O20: 641 | P20: =SUM(C20:O20) -> 6697.13 | U20: EGEMSA | V20: C.H. MACHUPICCHU | W20: 3908.05
B21: 07:30 | C21: 1083.75 | D21: 2797.31 | E21: 1818.5 | F21: 0 | G21: 25.4 | H21: 0 | J21: =DESPACHO_EJECUTADO!FC25+DESPACHO_EJECUTADO!FD25 -> 57.8 | L21: 34.2 | M21: 10.2 | N21: 343.5 | O21: 632.6 | P21: =SUM(C21:O21) -> 6803.26 | U21: EGESUR | V21: C.H. ARICOTA I | X21: 173.9
B22: 08:00 | C22: 1074.33 | D22: 2641.15 | E22: 1884.2 | F22: 36.4 | G22: 25.9 | H22: 10.9 | J22: =DESPACHO_EJECUTADO!FC26+DESPACHO_EJECUTADO!FD26 -> 58.2 | L22: 32.4 | M22: 10.2 | N22: 496.9 | O22: 560.3 | P22: =SUM(C22:O22) -> 6830.88 | V22: C.H. ARICOTA II | X22: 127.7
B23: 08:30 | C23: 1080.44 | D23: 2810.93 | E23: 1906.7 | F23: 46.7 | G23: 26.2 | H23: 10.9 | J23: =DESPACHO_EJECUTADO!FC27+DESPACHO_EJECUTADO!FD27 -> 58.3 | L23: 35.5 | M23: 7.8 | N23: 529.5 | O23: 572.5 | P23: =SUM(C23:O23) -> 7085.47 | U23: ELECTRICA YANAPAMPA SAC | V23: C.H. YANAPAMPA | W23: 73.9
B24: 09:00 | C24: 1079.85 | D24: 2916.82 | E24: 1922.4 | F24: 46.4 | G24: 26.4 | H24: 17.58 | J24: =DESPACHO_EJECUTADO!FC28+DESPACHO_EJECUTADO!FD28 -> 58.2 | L24: 35.2 | M24: 7.8 | N24: 542.8 | O24: 591.4 | P24: =SUM(C24:O24) -> 7244.85 | U24: ELECTROPERU | V24: C.H. MANTARO | X24: 14475.6
B25: 09:30 | C25: 1068.44 | D25: 2860.91 | E25: 2012.9 | F25: 46.7 | G25: 26.7 | H25: 25.37 | J25: =DESPACHO_EJECUTADO!FC29+DESPACHO_EJECUTADO!FD29 -> 58 | L25: 33.4 | M25: 7.8 | N25: 549 | O25: 539.6 | P25: =SUM(C25:O25) -> 7228.82 | V25: C.H. RESTITUCION | W25: 4850
B26: 10:00 | C26: 1091.4 | D26: 3012.38 | E26: 1912.8 | F26: 46 | G26: 25.8 | H26: 20.3 | J26: =DESPACHO_EJECUTADO!FC30+DESPACHO_EJECUTADO!FD30 -> 58.4 | L26: 32.2 | M26: 7.8 | N26: 554.4 | O26: 553.4 | P26: =SUM(C26:O26) -> 7314.88 | U26: EMPRESA DE GENERACION ELECTRICA CANCHAYLLO SAC | V26: C.H. CANCHAYLLO | W26: 62.4
B27: 10:30 | C27: 1087.08 | D27: 2946.12 | E27: 1944.2 | F27: 46.5 | G27: 25.7 | H27: 25.2 | J27: =DESPACHO_EJECUTADO!FC31+DESPACHO_EJECUTADO!FD31 -> 58.2 | L27: 35.1 | M27: 7.8 | N27: 553.2 | O27: 552.8 | P27: =SUM(C27:O27) -> 7281.9 | U27: EMPRESA DE GENERACION ELECTRICA RIO BAÑOS S.A.C. | V27: C.H. RUCUY | W27: 425.9
B28: 11:00 | C28: 1084.55 | D28: 3015.01 | E28: 2069.9 | F28: 46.2 | G28: 26.1 | H28: 28.3 | J28: =DESPACHO_EJECUTADO!FC32+DESPACHO_EJECUTADO!FD32 -> 58.5 | L28: 33.8 | M28: 7.8 | N28: 553.7 | O28: 539 | P28: =SUM(C28:O28) -> 7462.86 | U28: EMPRESA DE GENERACION ELECTRICA SANTA ANA S.A.C. | V28: C.H. RENOVANDES H1 | W28: 485.85
B29: 11:30 | C29: 1085.43 | D29: 3000.59 | E29: 2111.2 | F29: 46.2 | G29: 26.2 | H29: 30.3 | J29: =DESPACHO_EJECUTADO!FC33+DESPACHO_EJECUTADO!FD33 -> 59 | L29: 34.1 | M29: 7.7 | N29: 561.6 | O29: 515.6 | P29: =SUM(C29:O29) -> 7477.92 | U29: EMPRESA DE GENERACION HUALLAGA | V29: C.H. CHAGLLA | X29: 8995.2
B30: 12:00 | C30: 1077.54 | D30: 2680.15 | E30: 2403.5 | F30: 45.9 | G30: 26.3 | H30: 30.3 | J30: =DESPACHO_EJECUTADO!FC34+DESPACHO_EJECUTADO!FD34 -> 59 | L30: 34.6 | M30: 8 | N30: 565.8 | O30: 555.7 | P30: =SUM(C30:O30) -> 7486.79 | V30: P.C.H. CHAGLLA | W30: 156
B31: 12:30 | C31: 1067.24 | D31: 2534.85 | E31: 2395 | F31: 45.7 | G31: 26.4 | H31: 30.1 | J31: =DESPACHO_EJECUTADO!FC35+DESPACHO_EJECUTADO!FD35 -> 54.5 | L31: 35.6 | M31: 8 | N31: 575 | O31: 513.6 | P31: =SUM(C31:O31) -> 7285.99 | U31: EMPRESA DE GENERACION HUANZA | V31: C.H. HUANZA | X31: 970
B32: 13:00 | C32: 1086.86 | D32: 2619.53 | E32: 2256.1 | F32: 45.6 | G32: 25.8 | H32: 25.3 | J32: =DESPACHO_EJECUTADO!FC36+DESPACHO_EJECUTADO!FD36 -> 57.2 | L32: 32.6 | M32: 8 | N32: 580.2 | O32: 531.4 | P32: =SUM(C32:O32) -> 7268.59 | U32: EMPRESA ELECTRICA AGUA AZUL | V32: C.H. POTRERO | W32: 480
B33: 13:30 | C33: 1058.42 | D33: 2501.71 | E33: 2318.9 | F33: 45.3 | G33: 25.8 | H33: 25.3 | J33: =DESPACHO_EJECUTADO!FC37+DESPACHO_EJECUTADO!FD37 -> 58.2 | L33: 35.1 | M33: 8 | N33: 581.3 | O33: 546.6 | P33: =SUM(C33:O33) -> 7204.63 | U33: EMPRESA ELECTRICA RIO DOBLE | V33: C.H. LAS PIZARRAS | W33: 338.3
B34: 14:00 | C34: 1086.44 | D34: 2529.2 | E34: 2286 | F34: 45.1 | G34: 25.6 | H34: 28.5 | J34: =DESPACHO_EJECUTADO!FC38+DESPACHO_EJECUTADO!FD38 -> 59.9 | L34: 35.6 | M34: 8 | N34: 580.8 | O34: 615.3 | P34: =SUM(C34:O34) -> 7300.44 | U34: ENGIE | V34: C.H. YUNCAN | X34: 2080.8
B35: 14:30 | C35: 1073.99 | D35: 2673.07 | E35: 2271.9 | F35: 45.2 | G35: 26.5 | H35: 31.1 | J35: =DESPACHO_EJECUTADO!FC39+DESPACHO_EJECUTADO!FD39 -> 60 | L35: 35.3 | M35: 8 | N35: 575.6 | O35: 640.3 | P35: =SUM(C35:O35) -> 7440.96 | U35: GENERACIÓN ANDINA S.A.C. | V35: C.H. 8 DE AGOSTO | W35: 395.8
B36: 15:00 | C36: 1064.18 | D36: 2683.65 | E36: 2181.2 | F36: 46 | G36: 26.2 | H36: 33.2 | J36: =DESPACHO_EJECUTADO!FC40+DESPACHO_EJECUTADO!FD40 -> 60 | L36: 33.5 | M36: 8 | N36: 559.3 | O36: 638.6 | P36: =SUM(C36:O36) -> 7333.83 | V36: C.H. EL CARMEN | W36: 124.35
B37: 15:30 | C37: 1073.57 | D37: 2613.7 | E37: 2319.5 | F37: 45.5 | G37: 27.5 | H37: 33.2 | J37: =DESPACHO_EJECUTADO!FC41+DESPACHO_EJECUTADO!FD41 -> 60.8 | L37: 33.5 | M37: 8 | N37: 524.8 | O37: 599 | P37: =SUM(C37:O37) -> 7339.07 | U37: GENERADORA DE ENERGÍA DEL PERÚ | V37: C.H. ÁNGEL I | W37: 186.5
B38: 16:00 | C38: 1078.47 | D38: 2744.23 | E38: 2422.6 | F38: 45.5 | G38: 0 | H38: 0 | J38: =DESPACHO_EJECUTADO!FC42+DESPACHO_EJECUTADO!FD42 -> 60.7 | L38: 34.1 | M38: 8.1 | N38: 412.3 | O38: 605.8 | P38: =SUM(C38:O38) -> 7411.8 | V38: C.H. ÁNGEL II | W38: 202
B39: 16:30 | C39: 1070.16 | D39: 2921.16 | E39: 2418.2 | F39: 45.8 | G39: 0 | H39: 0 | J39: =DESPACHO_EJECUTADO!FC43+DESPACHO_EJECUTADO!FD43 -> 61.6 | L39: 34.6 | M39: 8.1 | N39: 209.5 | O39: 573.9 | P39: =SUM(C39:O39) -> 7343.02 | V39: C.H. ÁNGEL III | W39: 207.2
B40: 17:00 | C40: 1068.06 | D40: 3057.4 | E40: 2423.7 | F40: 46.1 | G40: 0 | H40: 0 | J40: =DESPACHO_EJECUTADO!FC44+DESPACHO_EJECUTADO!FD44 -> 61.3 | L40: 34.7 | M40: 8.7 | N40: 41.9 | O40: 615.9 | P40: =SUM(C40:O40) -> 7357.76 | U40: HIDROCAÑETE S.A. | V40: C.H. IMPERIAL | W40: 82.3
B41: 17:30 | C41: 1068.64 | D41: 3102.98 | E41: 2422.9 | F41: 46.2 | G41: 0 | H41: 68.1 | J41: =DESPACHO_EJECUTADO!FC45+DESPACHO_EJECUTADO!FD45 -> 61.3 | L41: 34.5 | M41: 9.2 | N41: 0 | O41: 572.6 | P41: =SUM(C41:O41) -> 7386.42 | U41: HIDROELECTRICA HUANCHOR S.A.C. | V41: C.H. HUANCHOR | W41: 450.15
B42: 18:00 | C42: 1073.64 | D42: 3039.01 | E42: 2309.9 | F42: 46.5 | G42: 0 | H42: 196.4 | J42: =DESPACHO_EJECUTADO!FC46+DESPACHO_EJECUTADO!FD46 -> 61.4 | L42: 34.8 | M42: 9.2 | N42: 0 | O42: 592.3 | P42: =SUM(C42:O42) -> 7363.15 | U42: HUAURA POWER GROUP S.A. | V42: C.H. YARUCAYA | W42: 441.6
B43: 18:30 | C43: 1072.38 | D43: 3027.32 | E43: 2432.8 | F43: 46.7 | G43: 0 | H43: 197 | J43: =DESPACHO_EJECUTADO!FC47+DESPACHO_EJECUTADO!FD47 -> 61.3 | L43: 35.5 | M43: 9.2 | N43: 0 | O43: 546.2 | P43: =SUM(C43:O43) -> 7428.4 | U43: HYDRO GLOBAL PERÚ S.A.C. | V43: CH SAN GABAN III | X43: 2695.5
B44: 19:00 | C44: 1069.97 | D44: 3096.95 | E44: 2357.6 | F44: 46.9 | G44: 0 | H44: 196.8 | J44: =DESPACHO_EJECUTADO!FC48+DESPACHO_EJECUTADO!FD48 -> 61.3 | L44: 33.5 | M44: 9.2 | N44: 0 | O44: 518 | P44: =SUM(C44:O44) -> 7390.22 | U44: INLAND ENERGY SAC | V44: C.H. SANTA TERESA | W44: 2142.25
B45: 19:30 | C45: 1076.06 | D45: 3104.95 | E45: 2355.7 | F45: 46.7 | G45: 0 | H45: 196.3 | J45: =DESPACHO_EJECUTADO!FC49+DESPACHO_EJECUTADO!FD49 -> 61.6 | L45: 33.9 | M45: 9.5 | N45: 0 | O45: 472.9 | P45: =SUM(C45:O45) -> 7357.61 | U45: INVERSIONES SHAQSHA S.A.C. | V45: C.H. PARIAC | W45: 42.15
B46: 20:00 | C46: 1071.73 | D46: 3294.3 | E46: 2351.8 | F46: 46.9 | G46: 0 | H46: 56.6 | J46: =DESPACHO_EJECUTADO!FC50+DESPACHO_EJECUTADO!FD50 -> 61.5 | L46: 34 | M46: 10.4 | N46: 0 | O46: 431.9 | P46: =SUM(C46:O46) -> 7359.13 | U46: KALLPA GENERACION S.A. | V46: C.H. CERRO DEL AGUILA | X46: 10716.25
B47: 20:30 | C47: 1066.75 | D47: 3381.26 | E47: 2359.2 | F47: 46.9 | G47: 0 | H47: 0 | J47: =DESPACHO_EJECUTADO!FC51+DESPACHO_EJECUTADO!FD51 -> 61.7 | L47: 32.7 | M47: 10.7 | N47: 0 | O47: 397.8 | P47: =SUM(C47:O47) -> 7357.01 | V47: M.C.H. CERRO DEL AGUILA | W47: 119.25
B48: 21:00 | C48: 1069.94 | D48: 3399.6 | E48: 2353.3 | F48: 46.9 | G48: 0 | H48: 0 | J48: =DESPACHO_EJECUTADO!FC52+DESPACHO_EJECUTADO!FD52 -> 60.9 | L48: 33.4 | M48: 10.7 | N48: 0 | O48: 352.4 | P48: =SUM(C48:O48) -> 7327.14 | U48: LA VIRGEN | V48: C.H. LA VIRGEN | X48: 1619.7
B49: 21:30 | C49: 1069.44 | D49: 3405.25 | E49: 2357.6 | F49: 46.7 | G49: 0 | H49: 0 | J49: =DESPACHO_EJECUTADO!FC53+DESPACHO_EJECUTADO!FD53 -> 62.1 | L49: 33.7 | M49: 10.8 | N49: 0 | O49: 272.9 | P49: =SUM(C49:O49) -> 7258.49 | U49: MAJA ENERGIA S.A.C. | V49: C.H. RONCADOR | W49: 36.35
B50: 22:00 | C50: 1063.83 | D50: 3232.02 | E50: 2529.5 | F50: 46.8 | G50: 0 | H50: 0 | J50: =DESPACHO_EJECUTADO!FC54+DESPACHO_EJECUTADO!FD54 -> 60.8 | L50: 34.1 | M50: 10.8 | N50: 0 | O50: 251.2 | P50: =SUM(C50:O50) -> 7229.05 | U50: ORAZUL ENERGY PERÚ | V50: C.H. CAÑA BRAVA | W50: 132.3
B51: 22:30 | C51: 1062.24 | D51: 3054.15 | E51: 2554 | F51: 47 | G51: 0 | H51: 0 | J51: =DESPACHO_EJECUTADO!FC55+DESPACHO_EJECUTADO!FD55 -> 61.2 | L51: 35.1 | M51: 10.8 | N51: 0 | O51: 229.1 | P51: =SUM(C51:O51) -> 7053.59 | V51: C.H. CAÑON DEL PATO | X51: 3560.75
B52: 23:00 | C52: 1064.07 | D52: 2885.45 | E52: 2561.2 | F52: 47.1 | G52: 0 | H52: 0 | J52: =DESPACHO_EJECUTADO!FC56+DESPACHO_EJECUTADO!FD56 -> 61.2 | L52: 33.8 | M52: 10.8 | N52: 0 | O52: 225.4 | P52: =SUM(C52:O52) -> 6889.02 | V52: C.H. CARHUAQUERO | X52: 2162.65
B53: 23:30 | C53: 1068.99 | D53: 2621.42 | E53: 2546 | F53: 46.9 | G53: 0 | H53: 0 | J53: =DESPACHO_EJECUTADO!FC57+DESPACHO_EJECUTADO!FD57 -> 60.1 | L53: 34.4 | M53: 10.8 | N53: 0 | O53: 214.6 | P53: =SUM(C53:O53) -> 6603.21 | V53: C.H. CARHUAQUERO IV | W53: 238.35
B54: 00:00 | C54: 1077.99 | D54: 2461.41 | E54: 2632.3 | F54: 47.2 | G54: 0 | H54: 0 | J54: =DESPACHO_EJECUTADO!FC58+DESPACHO_EJECUTADO!FD58 -> 60.8 | L54: 35.1 | M54: 10.8 | N54: 0 | O54: 205.7 | P54: =SUM(C54:O54) -> 6531.3 | U54: ORYGEN PERU S.A.A. | V54: C.H. CALLAHUANCA | X54: 1767.55
B55: TOTAL MWh | C55: =SUM(C7:C54)/2 -> 25870.84 | D55: =SUM(D7:D54)/2 -> 67398.9 | E55: =SUM(E7:E54)/2 -> 51033.45 | F55: =SUM(F7:F54)/2 -> 759.1 | G55: =SUM(G7:G54)/2 -> 403.85 | H55: =SUM(H7:H54)/2 -> 658.525 | I55: =SUM(I7:I54)/2 -> 0 | J55: =SUM(J7:J54)/2 -> 1421.15 | ... P55: =SUM(P7:P54)/2 -> 166908.87 | V55: C.H. HER 1 | W55: 14.4
B56: % | C56: =C55/$P$55 -> 0.1549998 | D56: =D55/$P$55 -> 0.40380659 | E56: =E55/$P$55 -> 0.30575638 | F56: =F55/$P$55 -> 0.0045479909 | G56: =G55/$P$55 -> 0.0024195839 | H56: =H55/$P$55 -> 0.0039454166 | I56: =I55/$P$55 -> 0 | J56: =J55/$P$55 -> 0.0085145268 | ... P56: =P55/$P$55 -> 1 | V56: C.H. HUAMPANI | W56: 720.15
V57: C.H. HUINCO | X57: 2670.65
V58: C.H. MATUCANA | X58: 2385.6
V59: C.H. MOYOPAMPA | W59: 1528.25
U60: PERUANA DE INVERSIONES EN ENERGIAS RENOVABLES S.A. | V60: C.H. MANTA I | W60: 400.95
U61: SAN GABAN | V61: C.H. SAN GABAN II | X61: 1893
V62: PCH TUPURI | W62: 15.2
U63: SINERSA | V63: C.H. CHANCAY | W63: 459.45
V64: C.H. POECHOS II | W64: 132.35
U65: STATKRAFT S.A | V65: C.H. ARCATA | W65: 96
V66: C.H. CAHUA | W66: 1008.15
V67: C.H. CHEVES | X67: 2271.05
V68: C.H. GALLITO CIEGO | X68: 193.85
V69: C.H. MALPASO | X69: 738.2
V70: C.H. OROYA | W70: 194.5
V71: C.H. PACHACHACA | W71: 59.9
V72: C.H. YAUPI | W72: 2620.8
U73: TOTAL MWh | W73: 25870.84 | X73: 67398.9

Sheet GENERACION RER
B3: jueves, 19 de Junio del 2025
B5: GENERACIÓN ELÉCTRICA DE LAS CENTRALES RER (MW)
B6: HORA | C6: AGRO INDUSTRIAL PARAMONGA S.A. | D6: AGROAURORA S.A.C. | E6: AGROINDUSTRIAS SAN JACINTO S.A.A. | F6: ANDEAN POWER S.A.C. | G6: ASOCIACIÓN SANTA LUCIA DE CHACAS | H6: ATRIA ENERGIA S.A.C. | I6: BIOENERGIA DEL CHIRA S.A. | J6: COLCA SOLAR S.A.C. | K6: EGEJUNIN | P6: ELECTRICA YANAPAMPA SAC | Q6: EMPRESA DE GENERACION ELECTRICA CANCHAYLLO SAC | R6: EMPRESA DE GENERACION ELECTRICA RIO BAÑOS S.A.C. | S6: EMPRESA DE GENERACION ELECTRICA SANTA ANA S.A.C. | T6: EMPRESA ELECTRICA AGUA AZUL | U6: EMPRESA ELECTRICA RIO DOBLE | V6: ENERGÍA EÓLICA S.A. | X6: ENERGIA RENOVABLE DEL SUR S.A. | Y6: ENGIE | AD6: GENERACIÓN ANDINA S.A.C. | AF6: GENERADORA DE ENERGÍA DEL PERÚ | AJ6: GR CORTARRAMA SOCIEDAD ANONIMA CERRADA | AK6: GR PAINO SOCIEDAD ANONIMA CERRADA | AL6: GR TARUCA SOCIEDAD ANONIMA CERRADA | AM6: HIDROCAÑETE S.A. | AN6: HUAURA POWER GROUP S.A. | AO6: HYDRO PATAPO S.A.C. | AP6: JOYA SOLAR S.A.C. | AQ6: KONDU SAC | AR6: MAJA ENERGIA S.A.C. | AS6: MAJES ARCUS S.A.C. | AT6: MOQUEGUA FV S.A.C. | AU6: ORAZUL ENERGY PERÚ | AW6: ORYGEN PERU S.A.A. | BB6: PANAMERICANA SOLAR SAC. | BC6: PARQUE EOLICO MARCONA S.A.C. | BD6: PARQUE EOLICO TRES HERMANAS S.A.C. | BE6: PERUANA DE INVERSIONES EN ENERGIAS RENOVABLES S.A. | BF6: PETRAMAS | BJ6: REPARTICIÓN ARCUS S.A.C. | BK6: SAN GABAN | BL6: SDF ENERGIA SAC | BM6: SINERSA | BO6: TACNA SOLAR SAC. | BP6: TOTAL RER
C7: C.T. PARAMONGA | D7: C.T. MAPLE | E7: C.T SAN JACINTO | F7: C.H. CARHUAC | G7: C.H. HUALLIN | H7: C.H. PURMACANA | I7: C.T. CAÑA BRAVA | K7: C.H. HUASAHUASI I | L7: C.H. HUASAHUASI II | M7: C.H. RUNATULLO II | N7: C.H. RUNATULLO III | O7: C.H. STA CRUZ I y II | P7: C.H. YANAPAMPA | Q7: C.H. CANCHAYLLO | R7: C.H. RUCUY | S7: C.H. RENOVANDES H1 | T7: C.H. POTRERO | U7: C.H. LAS PIZARRAS | AD7: C.H. 8 DE AGOSTO | AE7: C.H. EL CARMEN | AF7: C.H. ANGEL I | AG7: C.H. ANGEL II | AH7: C.H. ANGEL III | AI7: C.H. LA JOYA | AM7: C.H. NUEVAIMPERIAL | AN7: C.H. YARUCAYA | AO7: MCH PATAPO | AR7: C.H. RONCADOR | AU7: C.H. CANA BRAVA | AV7: C.H. CARHUAQUERO4 | BA7: C.H. HER 1 | BE7: C.H. MANTA | BF7: C.T. HUAYCOLORO | BG7: C.T. LA GRINGA V | BH7: CTB CALLAO | BI7: CTB. DONA CATALINA | BK7: C.H. TUPURI | BL7: C.T. OQUENDO | BM7: C.H. CHANCAY | BN7: C.H. POECHOS2 | BP7: MW
B8: 0:30 | C8: 17.1 | E8: 7.5 | F8: 13.1 | G8: 2.3 | I8: 9 | K8: 19.7 | M8: 10.3 | N8: 15.9 | O8: 5.4 | P8: 2.9 | Q8: 2.6 | R8: 18.2 | S8: 20 | T8: 20 | U8: 15.6 | V8: 15.6 | W8: 23.2 | X8: 113.1 | Y8: 96.2 | Z8: 84.6 | AB8: 16.8 | AC8: 8.2 | AD8: 16.4 | AE8: 6.6 | AF8: 9.2 | AG8: 9.8 | AH8: 10 | AK8: 13.2 | AL8: 15.6 | AM8: 3.5 | AN8: 18.4 | AR8: 1.5 | AU8: 5.6 | AV8: 9.9 | AW8: 103.9 | AY8: 91.6 | BA8: 0.6 | BC8: 32 | BD8: 85.4 | BE8: 17.7 | BF8: 4.5 | BG8: 1.4 | BH8: 2.2 | BI8: 2.1 | BK8: 0.8 | BM8: 19.3 | BN8: 5.5 | BP8: 1024
B9: 1:00 | C9: 17.6 | E9: 7.3 | F9: 13 | G9: 2.2 | I9: 8.9 | K9: 19.7 | M9: 10.4 | N9: 16.1 | O9: 5.4 | P9: 3 | Q9: 2.6 | R9: 18 | S9: 20.3 | T9: 20 | U9: 15.6 | V9: 16.6 | W9: 28 | X9: 109.7 | Y9: 99.6 | Z9: 91 | AB9: 17.1 | AC9: 8.6 | AD9: 16.4 | AE9: 6.5 | AF9: 9.2 | AG9: 9.8 | AH9: 10 | AK9: 16.3 | AL9: 17.1 | AM9: 3.5 | AN9: 18.4 | AR9: 1.5 | AU9: 5.6 | AV9: 10 | AW9: 97.3 | AY9: 83.9 | BA9: 0.6 | BC9: 31.9 | BD9: 85.3 | BE9: 18 | BF9: 4.5 | BG9: 1.4 | BH9: 2.2 | BI9: 2.1 | BK9: 0.8 | BM9: 19.2 | BN9: 5.6 | BP9: 1027.8
B10: 1:30 | C10: 17.6 | E10: 7.7 | F10: 13 | G10: 2.2 | I10: 9.3 | K10: 19.7 | M10: 10.1 | N10: 15.9 | O10: 5.4 | P10: 2.9 | Q10: 2.6 | R10: 18 | S10: 20.1 | T10: 20 | U10: 15.6 | V10: 16.5 | W10: 31.6 | X10: 110.1 | Y10: 100.3 | Z10: 92 | AB10: 16.6 | AC10: 7.2 | AD10: 16.4 | AE10: 6.4 | AF10: 9.2 | AG10: 9.8 | AH10: 10 | AK10: 12.7 | AL10: 14 | AM10: 3.5 | AN10: 18.4 | AR10: 1.5 | AU10: 5.4 | AV10: 9.9 | AW10: 122.8 | AY10: 90 | BA10: 0.6 | BC10: 31.8 | BD10: 83.9 | BE10: 18.1 | BF10: 4.5 | BG10: 1.4 | BH10: 2.2 | BI10: 2.1 | BK10: 0.7 | BM10: 19.2 | BN10: 5.6 | BP10: 1054.5
B11: 2:00 | C11: 16.8 | E11: 7.8 | F11: 13 | G11: 2.2 | I11: 9.6 | K11: 19.7 | M11: 10.5 | N11: 16.1 | O11: 5.5 | P11: 2.9 | Q11: 2.6 | R11: 18 | S11: 20.3 | T11: 20 | U11: 15.5 | V11: 13.1 | W11: 23.6 | X11: 103.2 | Y11: 90 | Z11: 86.3 | AB11: 15.7 | AC11: 6.2 | AD11: 16.4 | AE11: 6.2 | AF11: 9 | AG11: 9.8 | AH11: 10 | AK11: 13.8 | AL11: 15 | AM11: 3.4 | AN11: 18.4 | AR11: 1.5 | AU11: 5.6 | AV11: 10 | AW11: 123.4 | AY11: 96.5 | BA11: 0.6 | BC11: 31.8 | BD11: 84.9 | BE11: 18 | BF11: 4.5 | BG11: 1.4 | BH11: 2.2 | BI11: 2.1 | BK11: 0.7 | BM11: 19.2 | BN11: 5.6 | BP11: 1028.6
B12: 2:30 | C12: 16.9 | E12: 6.9 | F12: 13 | G12: 2.2 | I12: 9.6 | K12: 19.7 | M12: 10.5 | N12: 13.9 | O12: 5.8 | P12: 3 | Q12: 2.6 | R12: 17.9 | S12: 20.5 | T12: 20 | U12: 15.5 | V12: 11.4 | W12: 21.3 | X12: 110.3 | Y12: 84.3 | Z12: 78.8 | AB12: 11.6 | AC12: 6.4 | AD12: 16.5 | AE12: 6.2 | AF12: 8.2 | AG12: 9.5 | AH12: 9.7 | AK12: 14.6 | AL12: 17.3 | AM12: 3.5 | AN12: 18.4 | AR12: 1.5 | AU12: 5.4 | AV12: 9.9 | AW12: 128.6 | AY12: 108.7 | BA12: 0.6 | BC12: 32 | BD12: 82.6 | BE12: 17.9 | BF12: 4.5 | BG12: 1.4 | BH12: 2.2 | BI12: 2.1 | BK12: 0.7 | BM12: 19.2 | BN12: 5.6 | BP12: 1028.9
B13: 3:00 | C13: 17.8 | E13: 7.7 | F13: 13.2 | G13: 2.2 | I13: 9.5 | K13: 19.7 | M13: 9.8 | N13: 12.9 | O13: 5.8 | P13: 3 | Q13: 2.6 | R13: 18 | S13: 19.7 | T13: 20 | U13: 15.5 | V13: 17.2 | W13: 17 | X13: 101.7 | Y13: 89.2 | Z13: 87.5 | AB13: 11.2 | AC13: 8.1 | AD13: 16.5 | AE13: 6 | AF13: 8.2 | AG13: 9 | AH13: 9.5 | AK13: 14.1 | AL13: 15 | AM13: 3.5 | AN13: 18.4 | AR13: 1.5 | AU13: 5.6 | AV13: 10 | AW13: 108.9 | AY13: 99.7 | BA13: 0.6 | BC13: 31.6 | BD13: 83.5 | BE13: 17.8 | BF13: 4.5 | BG13: 1.4 | BH13: 2.2 | BI13: 2.1 | BK13: 0.7 | BM13: 19.2 | BN13: 5.4 | BP13: 1004.2
B14: 3:30 | C14: 17.8 | E14: 7.2 | F14: 13 | G14: 2.2 | I14: 9.8 | K14: 19.7 | M14: 10 | N14: 13.7 | O14: 5.8 | P14: 3 | Q14: 2.6 | R14: 17.9 | S14: 20.4 | T14: 20 | U14: 15.5 | V14: 16.4 | W14: 15 | X14: 104.3 | Y14: 104 | Z14: 90.1 | AB14: 13.8 | AC14: 9.8 | AD14: 16.5 | AE14: 6 | AF14: 8.2 | AG14: 9 | AH14: 9.5 | AK14: 13.5 | AL14: 13.2 | AM14: 3.5 | AN14: 18.4 | AR14: 1.6 | AU14: 5.5 | AV14: 9.9 | AW14: 136.6 | AY14: 103.7 | BA14: 0.6 | BC14: 31.7 | BD14: 82.8 | BE14: 17.8 | BF14: 4.5 | BG14: 1.4 | BH14: 2.2 | BI14: 2.1 | BK14: 0.7 | BM14: 19.2 | BN14: 5.4 | BP14: 1055.5
B15: 4:00 | C15: 17.4 | E15: 8.1 | F15: 13 | G15: 2.1 | I15: 9.7 | K15: 19.7 | M15: 10.2 | N15: 13.7 | O15: 5.8 | P15: 3 | Q15: 2.6 | R15: 17.8 | S15: 20.3 | T15: 20 | U15: 13.4 | V15: 18.9 | W15: 9.9 | X15: 111.8 | Y15: 101.9 | Z15: 95.5 | AB15: 19 | AC15: 8.9 | AD15: 16.5 | AE15: 5.9 | AF15: 8 | AG15: 8.5 | AH15: 9 | AK15: 14.5 | AL15: 16.9 | AM15: 3.5 | AN15: 18.4 | AR15: 1.6 | AU15: 5.6 | AV15: 9.9 | AW15: 130.6 | AY15: 121.5 | BA15: 0.6 | BC15: 31.7 | BD15: 84.9 | BE15: 17.8 | BF15: 4.5 | BG15: 1.4 | BH15: 2.2 | BI15: 2.1 | BK15: 0.7 | BM15: 19.2 | BN15: 5.5 | BP15: 1083.7
B16: 4:30 | C16: 17.7 | E16: 7.9 | F16: 13 | G16: 2.1 | I16: 9.7 | K16: 19.7 | M16: 10.2 | N16: 13.8 | O16: 5.7 | P16: 3.2 | Q16: 2.6 | R16: 17.8 | S16: 20.3 | T16: 20 | U16: 13.5 | V16: 18.5 | W16: 5.4 | X16: 115.5 | Y16: 100 | Z16: 94.3 | AB16: 15.8 | AC16: 6.8 | AD16: 16.5 | AE16: 5.8 | AF16: 8 | AG16: 8.5 | AH16: 8.7 | AK16: 13.8 | AL16: 16.6 | AM16: 3.5 | AN16: 18.4 | AR16: 1.6 | AU16: 5.4 | AV16: 9.9 | AW16: 104.6 | AY16: 97.7 | BA16: 0.6 | BC16: 31.8 | BD16: 85.6 | BE16: 17.7 | BF16: 4.5 | BG16: 1.4 | BH16: 2.2 | BI16: 2.1 | BK16: 0.7 | BM16: 19.2 | BN16: 5.6 | BP16: 1023.9
B17: 5:00 | C17: 17.8 | E17: 8.3 | F17: 13 | G17: 2 | I17: 9.7 | K17: 19.7 | M17: 10 | N17: 13.9 | O17: 5.2 | P17: 3.2 | Q17: 2.6 | R17: 17.8 | S17: 20.1 | T17: 20 | U17: 13.5 | V17: 18.2 | W17: 5 | X17: 114.5 | Y17: 100.3 | Z17: 93.3 | AB17: 17.5 | AC17: 7.6 | AD17: 16.5 | AE17: 5.7 | AF17: 7.5 | AG17: 8.5 | AH17: 8.7 | AK17: 15.7 | AL17: 17.8 | AM17: 3.5 | AN17: 18.4 | AR17: 1.6 | AU17: 5.5 | AV17: 9.9 | AW17: 128.4 | AY17: 103.5 | BA17: 0.6 | BC17: 31.7 | BD17: 85.9 | BE17: 17.3 | BF17: 4.5 | BG17: 1.4 | BH17: 2.2 | BI17: 2.1 | BK17: 0.7 | BM17: 19.2 | BN17: 5.5 | BP17: 1055.5
B18: 5:30 | C18: 17 | E18: 8.4 | F18: 13.1 | G18: 2 | I18: 9 | K18: 19.7 | M18: 10 | N18: 13.7 | O18: 5 | P18: 3.2 | Q18: 2.6 | R18: 18 | S18: 20.2 | T18: 20 | U18: 13.5 | V18: 22.7 | W18: 5.6 | X18: 94.7 | Y18: 87.4 | Z18: 77.1 | AB18: 13.5 | AC18: 9 | AD18: 16.5 | AE18: 5.6 | AF18: 7.5 | AG18: 8.5 | AH18: 8.7 | AK18: 15.9 | AL18: 17.6 | AM18: 3.5 | AN18: 18.4 | AR18: 1.5 | AU18: 5.5 | AV18: 9.9 | AW18: 133.2 | AY18: 109.9 | BA18: 0.6 | BC18: 31.9 | BD18: 85.2 | BE18: 17 | BF18: 4.5 | BG18: 1.4 | BH18: 2.2 | BI18: 2.1 | BK18: 0.7 | BM18: 19.2 | BN18: 5.5 | BP18: 1017.9
B19: 6:00 | C19: 17.1 | E19: 8.7 | F19: 13.2 | G19: 2.1 | I19: 9.8 | K19: 19.7 | M19: 9.9 | N19: 14 | O19: 5 | P19: 3.2 | Q19: 2.6 | R19: 18 | S19: 20.1 | T19: 20 | U19: 13.6 | V19: 20 | W19: 11 | X19: 100.4 | Y19: 79.5 | Z19: 63.7 | AB19: 16.7 | AC19: 7.8 | AD19: 16.5 | AE19: 5.5 | AF19: 7.5 | AG19: 8.5 | AH19: 8.7 | AK19: 15.2 | AL19: 16.6 | AM19: 3.4 | AN19: 18.4 | AR19: 1.5 | AT19: 0.1 | AU19: 5.6 | AV19: 9.9 | AW19: 107.3 | AY19: 99.7 | BA19: 0.6 | BC19: 31.2 | BD19: 79.9 | BE19: 16.9 | BF19: 4.5 | BG19: 1.4 | BH19: 2.2 | BI19: 2.1 | BK19: 0.7 | BM19: 19.3 | BN19: 5.5 | BP19: 964.8
B20: 6:30 | C20: 16.5 | E20: 7.7 | F20: 13.2 | G20: 2 | I20: 8.7 | K20: 19.7 | M20: 9.2 | N20: 14.2 | O20: 4.9 | P20: 3.2 | Q20: 2.6 | R20: 18 | S20: 20.2 | T20: 20 | U20: 13.6 | V20: 21.5 | W20: 12.8 | X20: 109.8 | Y20: 64.9 | Z20: 67.2 | AA20: 0.3 | AB20: 11.5 | AC20: 5 | AD20: 16.5 | AE20: 5.5 | AF20: 8 | AG20: 8.2 | AH20: 8.4 | AK20: 14.8 | AL20: 15.4 | AM20: 3.4 | AN20: 18.4 | AP20: 2.8 | AR20: 1.6 | AT20: 2.4 | AU20: 5.5 | AV20: 10 | AW20: 111.1 | AX20: 2.1 | AY20: 93.5 | AZ20: 1.7 | BA20: 0.6 | BB20: 2.7 | BC20: 31.5 | BD20: 84 | BE20: 16.9 | BF20: 4.5 | BG20: 1.4 | BH20: 2.2 | BI20: 2.1 | BK20: 0.7 | BM20: 19.2 | BN20: 5.6 | BO20: 0.1 | BP20: 967.5
B21: 7:00 | C21: 16.6 | E21: 8.2 | F21: 13.3 | G21: 2 | I21: 9.3 | K21: 19.7 | M21: 9.1 | N21: 14 | O21: 4.9 | P21: 3.2 | Q21: 2.6 | R21: 18 | S21: 20.1 | T21: 20 | U21: 13.6 | V21: 24.2 | W21: 15.1 | X21: 109.7 | Y21: 63.7 | Z21: 81.9 | AA21: 5.1 | AB21: 9.6 | AC21: 6.7 | AD21: 16.5 | AE21: 5.4 | AF21: 8.2 | AG21: 8.5 | AH21: 8.7 | AJ21: 16 | AK21: 15.2 | AL21: 17.4 | AM21: 3.4 | AN21: 18.4 | AP21: 44.7 | AR21: 1.6 | AS21: 1.9 | AT21: 8.5 | AU21: 5.4 | AV21: 10 | AW21: 96.8 | AX21: 28.8 | AY21: 84.3 | AZ21: 22.5 | BA21: 0.6 | BB21: 9.6 | BC21: 31.6 | BD21: 84.8 | BE21: 16.9 | BF21: 4.5 | BG21: 1.4 | BH21: 2.2 | BI21: 2.1 | BJ21: 1.8 | BK21: 0.7 | BM21: 19.2 | BN21: 5.5 | BO21: 1 | BP21: 1094.7
B22: 7:30 | C22: 16.4 | E22: 8 | F22: 13.3 | G22: 2 | I22: 9.8 | J22: 0.1 | K22: 19.7 | M22: 9.3 | N22: 14.1 | O22: 4.7 | P22: 3.2 | Q22: 2.6 | R22: 18 | S22: 20.2 | T22: 20 | U22: 13.6 | V22: 24 | W22: 10.4 | X22: 103.5 | Y22: 66.7 | Z22: 88.8 | AA22: 14.4 | AB22: 9.2 | AC22: 4.8 | AD22: 16.5 | AE22: 5.3 | AF22: 8 | AG22: 8.5 | AH22: 8.7 | AJ22: 38 | AK22: 14.4 | AL22: 16.4 | AM22: 3.4 | AN22: 18.4 | AP22: 128.2 | AR22: 1.6 | AS22: 4.5 | AT22: 11.6 | AU22: 5.4 | AV22: 10 | AW22: 86.9 | AX22: 71.2 | AY22: 90.4 | AZ22: 55.4 | BA22: 0.6 | BB22: 13.8 | BC22: 31.9 | BD22: 85.2 | BE22: 16.9 | BF22: 4.5 | BG22: 1.4 | BH22: 2.2 | BI22: 2.1 | BJ22: 4.4 | BK22: 0.6 | BM22: 19.2 | BN22: 5.5 | BO22: 1.9 | BP22: 1289.8
B23: 8:00 | C23: 17.3 | E23: 5.3 | F23: 13.4 | G23: 2 | I23: 9.8 | J23: 0.1 | K23: 19.7 | M23: 8.7 | N23: 13.7 | O23: 4.7 | P23: 3.2 | Q23: 2.6 | R23: 18 | S23: 19.9 | T23: 20 | U23: 13.6 | V23: 21.3 | W23: 12.4 | X23: 95.6 | Y23: 66.6 | Z23: 84 | AA23: 23.2 | AB23: 7.6 | AC23: 4.9 | AD23: 16.5 | AE23: 5.3 | AF23: 8 | AG23: 8.5 | AH23: 8.7 | AJ23: 58.1 | AK23: 16 | AL23: 17.2 | AM23: 3.4 | AN23: 18.4 | AP23: 189 | AR23: 1.5 | AS23: 7.1 | AT23: 12.2 | AU23: 5.6 | AV23: 9.8 | AW23: 54.6 | AX23: 104.6 | AY23: 63.1 | AZ23: 78.3 | BA23: 0.6 | BB23: 14.6 | BC23: 31.9 | BD23: 85.1 | BE23: 16.9 | BF23: 4.5 | BG23: 1.4 | BH23: 2.2 | BI23: 2.1 | BJ23: 6.7 | BK23: 0.6 | BM23: 19.1 | BN23: 5.6 | BO23: 3 | BP23: 1367.8
B24: 8:30 | C24: 17 | E24: 8.8 | F24: 13.5 | G24: 1.9 | I24: 9.7 | J24: 0.2 | K24: 19.7 | M24: 9.2 | N24: 12.9 | O24: 4.7 | P24: 3.1 | Q24: 2.6 | R24: 18 | S24: 20.4 | T24: 20 | U24: 13.6 | V24: 24.2 | W24: 9.6 | X24: 103.1 | Y24: 77.3 | Z24: 83.6 | AA24: 27.2 | AB24: 10 | AC24: 8.5 | AD24: 16.5 | AE24: 5.2 | AF24: 8 | AG24: 8.5 | AH24: 8.7 | AJ24: 60.9 | AK24: 17 | AL24: 17.3 | AM24: 3.4 | AN24: 18.4 | AP24: 197 | AR24: 1.5 | AS24: 9.2 | AT24: 12.4 | AU24: 5.4 | AV24: 9.9 | AW24: 58.9 | AX24: 113.3 | AY24: 47.8 | AZ24: 81.6 | BA24: 0.6 | BB24: 14.8 | BC24: 31.7 | BD24: 83.5 | BE24: 16.9 | BF24: 4.5 | BH24: 1.2 | BI24: 2.1 | BJ24: 8.7 | BK24: 0.6 | BM24: 19.2 | BN24: 5.6 | BO24: 4.2 | BP24: 1413.3
B25: 9:00 | C25: 17 | E25: 8.2 | F25: 12 | G25: 1.9 | I25: 10 | J25: 0.8 | K25: 19.7 | M25: 9.4 | N25: 13.1 | O25: 4.7 | P25: 3.1 | Q25: 2.6 | R25: 18 | S25: 20.5 | T25: 20 | U25: 15.3 | V25: 25.7 | W25: 8 | X25: 100.3 | Y25: 76.6 | Z25: 63.6 | AA25: 27.2 | AB25: 13.2 | AC25: 12.2 | AD25: 16.5 | AE25: 5.1 | AF25: 8 | AG25: 8.7 | AH25: 8.7 | AJ25: 61.5 | AK25: 15.6 | AL25: 17.7 | AM25: 3.4 | AN25: 18.4 | AP25: 200.4 | AR25: 1.5 | AS25: 11 | AT25: 12.5 | AU25: 5.6 | AV25: 9.9 | AW25: 75.5 | AX25: 113.9 | AY25: 65.7 | AZ25: 82.8 | BA25: 0.6 | BB25: 15 | BC25: 32 | BD25: 85.3 | BE25: 16.9 | BF25: 4.5 | BH25: 1.2 | BI25: 2.1 | BJ25: 10.7 | BK25: 0.6 | BM25: 19.2 | BN25: 5.5 | BO25: 7 | BP25: 1446.1
B26: 9:30 | C26: 17.5 | E26: 5.9 | F26: 12 | G26: 2 | I26: 10 | J26: 0.9 | K26: 19.7 | M26: 8.9 | N26: 12.9 | O26: 4.7 | P26: 3.1 | Q26: 2.6 | R26: 18 | S26: 19.6 | T26: 20 | U26: 15.2 | V26: 24.9 | W26: 3.9 | X26: 105.2 | Y26: 52.9 | Z26: 50.9 | AA26: 27.7 | AB26: 8.3 | AC26: 7.6 | AD26: 16.5 | AE26: 5.1 | AF26: 7.9 | AG26: 8.7 | AH26: 8.7 | AJ26: 61.7 | AK26: 14.4 | AL26: 16.3 | AM26: 3.4 | AN26: 18.4 | AP26: 196 | AQ26: 0.1 | AR26: 1.5 | AS26: 12.8 | AT26: 12.7 | AU26: 5.5 | AV26: 10 | AW26: 72.2 | AX26: 113.7 | AY26: 70.9 | AZ26: 83 | BA26: 0.6 | BB26: 15.1 | BC26: 31.4 | BD26: 80.7 | BE26: 17 | BF26: 4.5 | BH26: 1.2 | BI26: 2.1 | BJ26: 12.4 | BK26: 0.6 | BM26: 19.2 | BN26: 5.4 | BO26: 12.9 | BP26: 1397
B27: 10:00 | C27: 18 | E27: 4.6 | F27: 12.5 | G27: 1.9 | I27: 9.6 | J27: 1 | K27: 19.7 | M27: 9.5 | N27: 13.2 | O27: 4.7 | P27: 3.3 | Q27: 2.6 | R27: 18 | S27: 20.4 | T27: 20 | U27: 15.2 | V27: 24.3 | W27: 3.4 | X27: 102.7 | Y27: 56.1 | Z27: 59.6 | AA27: 27.2 | AB27: 9.9 | AC27: 9.4 | AD27: 16.5 | AE27: 5 | AF27: 7.8 | AG27: 8.7 | AH27: 8.7 | AJ27: 61.9 | AK27: 15.1 | AL27: 16.5 | AM27: 3.4 | AN27: 18.4 | AP27: 197.6 | AQ27: 0.1 | AR27: 1.5 | AS27: 14.2 | AT27: 12.6 | AU27: 5.5 | AV27: 9.8 | AW27: 67.6 | AX27: 113.2 | AY27: 72.6 | AZ27: 83 | BA27: 0.6 | BB27: 15.1 | BC27: 31.9 | BD27: 84.3 | BE27: 17 | BF27: 4.5 | BH27: 1.2 | BI27: 2.1 | BJ27: 13.8 | BK27: 0.6 | BM27: 19.2 | BN27: 5.5 | BO27: 14.7 | BP27: 1417
B28: 10:30 | C28: 17.5 | E28: 7.8 | F28: 12.8 | G28: 1.9 | I28: 9.8 | J28: 1.1 | K28: 19.6 | M28: 9 | N28: 13 | O28: 4.7 | P28: 3.1 | Q28: 2.6 | R28: 18 | S28: 20.3 | T28: 20 | U28: 15.2 | V28: 24.2 | W28: 6.7 | X28: 98.1 | Y28: 57.8 | Z28: 65 | AA28: 26.8 | AB28: 7.9 | AC28: 6.3 | AD28: 16.5 | AE28: 4.9 | AF28: 7.7 | AG28: 8.7 | AH28: 8.8 | AJ28: 61.5 | AK28: 12.7 | AL28: 15.9 | AM28: 3.4 | AN28: 18.4 | AP28: 196 | AQ28: 0.3 | AR28: 1.5 | AS28: 15.1 | AT28: 12.4 | AU28: 5.3 | AV28: 9.9 | AW28: 64.8 | AX28: 112.8 | AY28: 76.9 | AZ28: 82.9 | BA28: 0.6 | BB28: 14.8 | BC28: 32.1 | BD28: 84.4 | BE28: 17.1 | BF28: 4.5 | BH28: 1.2 | BI28: 2.1 | BJ28: 14.8 | BK28: 0.6 | BM28: 19.2 | BN28: 5.4 | BO28: 14.7 | BP28: 1417.1
B29: 11:00 | C29: 17.7 | E29: 6.7 | F29: 13 | G29: 1.9 | I29: 9.4 | J29: 1.2 | K29: 19.4 | M29: 9.3 | N29: 13.3 | O29: 4.5 | P29: 3.1 | Q29: 2.6 | R29: 18 | S29: 20.2 | T29: 20 | U29: 15.2 | V29: 25.1 | W29: 7.8 | X29: 91.4 | Y29: 54.8 | Z29: 70.4 | AA29: 26.7 | AB29: 9.7 | AC29: 7 | AD29: 16.5 | AE29: 4.9 | AF29: 7.7 | AG29: 8.5 | AH29: 8.8 | AJ29: 61.9 | AK29: 13.3 | AL29: 16.2 | AM29: 3.4 | AN29: 18.4 | AP29: 196.5 | AQ29: 0.5 | AR29: 1.5 | AS29: 16.1 | AT29: 12.3 | AU29: 5.5 | AV29: 9.9 | AW29: 58 | AX29: 111.6 | AY29: 70.9 | AZ29: 82.3 | BA29: 0.6 | BB29: 14.6 | BC29: 31.8 | BD29: 82.6 | BE29: 17 | BF29: 4.5 | BH29: 1.2 | BI29: 2.1 | BJ29: 15.5 | BK29: 0.6 | BM29: 19.2 | BN29: 5.6 | BO29: 14.5 | BP29: 1402.9
B30: 11:30 | C30: 17.4 | E30: 7 | F30: 12.9 | G30: 1.9 | I30: 9.7 | J30: 1.2 | K30: 19.4 | M30: 9.4 | N30: 13.1 | O30: 4.4 | P30: 3 | Q30: 2.6 | R30: 17.8 | S30: 20.4 | T30: 20 | U30: 15.2 | V30: 26 | W30: 12.5 | X30: 65.1 | Y30: 59.9 | Z30: 62.7 | AA30: 27.1 | AB30: 10.8 | AC30: 10.7 | AD30: 16.5 | AE30: 4.9 | AF30: 7.7 | AG30: 8.5 | AH30: 8.8 | AJ30: 63.2 | AK30: 15.9 | AL30: 17.5 | AM30: 3.4 | AN30: 18.4 | AP30: 201.6 | AQ30: 0.3 | AR30: 1.5 | AS30: 16.8 | AT30: 12.2 | AU30: 5.6 | AV30: 10 | AW30: 56.3 | AX30: 111.8 | AY30: 65.4 | AZ30: 82.5 | BA30: 0.6 | BB30: 14.5 | BC30: 30.2 | BD30: 82.6 | BE30: 17.2 | BF30: 4.5 | BH30: 1.2 | BI30: 2 | BJ30: 15.9 | BK30: 0.6 | BM30: 19.2 | BN30: 5.6 | BO30: 14.5 | BP30: 1387.6
B31: 12:00 | C31: 17.7 | E31: 7.2 | F31: 5.4 | G31: 1.9 | I31: 9.7 | J31: 1.2 | K31: 19.3 | M31: 9.4 | N31: 13.4 | O31: 4.4 | P31: 3 | Q31: 2.6 | R31: 17.8 | S31: 20.4 | T31: 20 | U31: 15.1 | V31: 24.8 | W31: 14.7 | X31: 77.8 | Y31: 70.4 | Z31: 65.7 | AA31: 27.3 | AB31: 14.8 | AC31: 9.5 | AD31: 16.5 | AE31: 4.8 | AF31: 7.7 | AG31: 8.4 | AH31: 8.8 | AJ31: 64.4 | AK31: 14.9 | AL31: 17.6 | AM31: 3.4 | AN31: 18.4 | AP31: 201.8 | AQ31: 0.2 | AR31: 1.5 | AS31: 16.7 | AT31: 12.3 | AU31: 5.5 | AV31: 9.9 | AW31: 63.3 | AX31: 113.2 | AY31: 76.9 | AZ31: 83.3 | BA31: 0.6 | BB31: 14.9 | BC31: 26.9 | BD31: 78.4 | BE31: 17 | BF31: 4.5 | BH31: 1.2 | BI31: 2.3 | BJ31: 16.1 | BK31: 0.6 | BM31: 19.2 | BN31: 5.5 | BO31: 14.4 | BP31: 1424.6
B32: 12:30 | C32: 18 | E32: 7.9 | F32: 5.9 | G32: 1.9 | I32: 9.7 | J32: 1.2 | K32: 18.6 | M32: 9 | N32: 12.8 | O32: 4.5 | P32: 3.2 | Q32: 2.6 | R32: 17.6 | S32: 20 | T32: 20 | U32: 13.5 | V32: 24.7 | W32: 13.8 | X32: 69.4 | Y32: 55 | Z32: 57.6 | AA32: 27.2 | AB32: 12.6 | AC32: 8.6 | AD32: 16.5 | AE32: 4.7 | AF32: 7.7 | AG32: 8.2 | AH32: 8.4 | AJ32: 65.2 | AK32: 15.1 | AL32: 15.7 | AM32: 3.4 | AN32: 18.4 | AP32: 207.5 | AQ32: 0.2 | AR32: 1.5 | AS32: 16.8 | AT32: 12.4 | AU32: 5.4 | AV32: 10 | AW32: 58.6 | AX32: 114.7 | AY32: 75.1 | AZ32: 84.2 | BA32: 0.6 | BB32: 15 | BC32: 30 | BD32: 77.4 | BE32: 17 | BF32: 4.5 | BH32: 1.2 | BI32: 2.3 | BJ32: 16 | BK32: 0.6 | BM32: 19 | BN32: 5.6 | BO32: 14.6 | BP32: 1388.8
B33: 13:00 | C33: 17.1 | E33: 6.5 | F33: 6.3 | G33: 1.9 | I33: 9 | J33: 1.2 | K33: 18.6 | M33: 9.6 | N33: 13.5 | O33: 4.4 | P33: 3.2 | Q33: 2.6 | R33: 17.7 | S33: 20.5 | T33: 20 | U33: 13.5 | V33: 25.1 | W33: 11.8 | X33: 54.7 | Y33: 74.2 | Z33: 62.9 | AA33: 27.4 | AB33: 9.3 | AC33: 7.5 | AD33: 16.5 | AE33: 4.7 | AF33: 7.5 | AG33: 8.2 | AH33: 8.4 | AJ33: 65.2 | AK33: 12.1 | AL33: 14.4 | AM33: 3.4 | AN33: 18.4 | AP33: 210.1 | AQ33: 0.4 | AR33: 1.5 | AS33: 16.5 | AT33: 12.5 | AU33: 5.5 | AV33: 9.9 | AW33: 70.2 | AX33: 116.5 | AY33: 91.4 | AZ33: 84.9 | BA33: 0.6 | BB33: 15 | BC33: 24.1 | BD33: 73.7 | BE33: 16.8 | BF33: 4.5 | BH33: 1.2 | BI33: 2.3 | BJ33: 15.7 | BK33: 0.6 | BM33: 19.1 | BN33: 5.5 | BO33: 14.8 | BP33: 1410.6
B34: 13:30 | C34: 18 | E34: 7.5 | F34: 6.4 | G34: 1.8 | I34: 9.6 | J34: 1.2 | K34: 18.7 | M34: 9.2 | N34: 12.7 | O34: 4.4 | P34: 3.2 | Q34: 2.6 | R34: 17.8 | S34: 20.1 | T34: 20 | U34: 13.5 | V34: 24.8 | W34: 10.5 | X34: 50.9 | Y34: 66.5 | Z34: 87 | AA34: 27.7 | AB34: 8.9 | AC34: 6.6 | AD34: 16.5 | AE34: 4.6 | AF34: 7.5 | AG34: 8.2 | AH34: 8.4 | AJ34: 65.4 | AK34: 14.6 | AL34: 16.4 | AM34: 3.3 | AN34: 18.4 | AP34: 210.6 | AQ34: 0.3 | AR34: 1.5 | AS34: 15.5 | AT34: 12.7 | AU34: 5.3 | AV34: 9.9 | AW34: 76.3 | AX34: 117.6 | AY34: 95.9 | AZ34: 85.4 | BA34: 0.6 | BB34: 15.1 | BC34: 22.9 | BD34: 65.3 | BE34: 16.7 | BF34: 4.5 | BH34: 1.2 | BI34: 2.3 | BJ34: 14.9 | BK34: 0.6 | BM34: 19.2 | BN34: 5.5 | BO34: 14.9 | BP34: 1427.6
B35: 14:00 | C35: 17.8 | E35: 8.2 | F35: 6.4 | G35: 1.9 | I35: 9.6 | J35: 1.1 | K35: 18.8 | M35: 9.8 | N35: 13 | O35: 4.5 | P35: 3.1 | Q35: 2.6 | R35: 17.8 | S35: 20.7 | T35: 20 | U35: 13.5 | V35: 24 | W35: 11.1 | X35: 46.6 | Y35: 81.6 | Z35: 88.8 | AA35: 27.9 | AB35: 13.5 | AC35: 9.9 | AD35: 16.5 | AE35: 4.6 | AF35: 7.5 | AG35: 8 | AH35: 8.4 | AJ35: 65.4 | AK35: 14.8 | AL35: 16.8 | AM35: 3.3 | AN35: 18.4 | AP35: 211.5 | AQ35: 0.2 | AR35: 1.5 | AS35: 14.5 | AT35: 12.8 | AU35: 5.6 | AV35: 9.9 | AW35: 99.9 | AX35: 117.9 | AY35: 120 | AZ35: 85.5 | BA35: 0.6 | BB35: 15.2 | BC35: 22.2 | BD35: 66.1 | BE35: 16.6 | BF35: 4.5 | BH35: 1.2 | BI35: 2.3 | BJ35: 13.9 | BK35: 0.6 | BM35: 19.2 | BN35: 5.4 | BO35: 14.9 | BP35: 1497.9
B36: 14:30 | C36: 17.5 | E36: 7.9 | F36: 6.6 | G36: 1.8 | I36: 9.9 | J36: 1 | K36: 18.8 | M36: 9.3 | N36: 12.7 | O36: 4.5 | P36: 3.2 | Q36: 2.6 | R36: 17.8 | S36: 20.4 | T36: 20 | U36: 13.5 | V36: 24.2 | W36: 9.4 | X36: 60.4 | Y36: 83.2 | Z36: 82.4 | AA36: 28.1 | AB36: 13.5 | AC36: 10 | AD36: 16.5 | AE36: 4.6 | AF36: 7.5 | AG36: 8 | AH36: 8.2 | AJ36: 65 | AK36: 12.8 | AL36: 15.8 | AM36: 3.3 | AN36: 18.4 | AP36: 211 | AQ36: 0.1 | AR36: 1.5 | AS36: 13 | AT36: 12.7 | AU36: 5.6 | AV36: 10 | AW36: 110.8 | AX36: 117.6 | AY36: 123.5 | AZ36: 84.6 | BA36: 0.6 | BB36: 15.2 | BC36: 25 | BD36: 69.3 | BE36: 16.5 | BF36: 4.5 | BH36: 1.2 | BI36: 2.3 | BJ36: 12.6 | BK36: 0.6 | BM36: 19.2 | BN36: 5.4 | BO36: 14.7 | BP36: 1516.3
B37: 15:00 | C37: 16.2 | E37: 7.4 | F37: 6.4 | G37: 1.8 | I37: 9.9 | J37: 0.9 | K37: 18.8 | M37: 9.4 | N37: 12.7 | O37: 4.5 | P37: 3.2 | Q37: 2.6 | R37: 17.5 | S37: 20.3 | T37: 20 | U37: 13.6 | V37: 22.8 | W37: 8.9 | X37: 56.5 | Y37: 81.7 | Z37: 81.7 | AA37: 27.8 | AB37: 13.9 | AC37: 9.8 | AD37: 16.5 | AE37: 4.6 | AF37: 7.5 | AG37: 8 | AH37: 8.2 | AJ37: 63.6 | AK37: 13.4 | AL37: 16.2 | AM37: 3.3 | AN37: 18.4 | AP37: 207.6 | AQ37: 0.1 | AR37: 1.5 | AS37: 11.2 | AT37: 12.3 | AU37: 5.5 | AV37: 9.9 | AW37: 109.6 | AX37: 115.2 | AY37: 125.4 | AZ37: 82.7 | BA37: 0.6 | BB37: 14.7 | BC37: 23.9 | BD37: 74.8 | BE37: 16.4 | BF37: 4.5 | BH37: 1.2 | BI37: 2.3 | BJ37: 10.9 | BK37: 0.6 | BM37: 19 | BN37: 5.6 | BO37: 12.3 | BP37: 1495.8
B38: 15:30 | C38: 17 | E38: 7.7 | F38: 6.4 | G38: 1.9 | I38: 8.8 | J38: 0.7 | K38: 18.8 | M38: 9.6 | N38: 12.9 | O38: 4.3 | P38: 3.2 | Q38: 2.6 | R38: 17.6 | S38: 20.4 | T38: 20 | U38: 13.6 | V38: 20.9 | W38: 6.1 | X38: 45.3 | Y38: 85.2 | Z38: 81.5 | AA38: 26.1 | AB38: 12.2 | AC38: 10.7 | AD38: 16.5 | AE38: 4.5 | AF38: 7.5 | AG38: 8 | AH38: 8.2 | AJ38: 60.8 | AK38: 9.9 | AL38: 14.3 | AM38: 3.3 | AN38: 18.4 | AP38: 199.1 | AQ38: 0.1 | AR38: 1.5 | AS38: 9 | AT38: 11.4 | AU38: 5.5 | AV38: 10 | AW38: 100.6 | AX38: 109.4 | AY38: 125 | AZ38: 79 | BA38: 0.6 | BB38: 13.6 | BC38: 20.7 | BD38: 66.6 | BE38: 16.3 | BF38: 4.5 | BH38: 1.2 | BI38: 2.3 | BJ38: 8.9 | BK38: 0.6 | BM38: 19.2 | BN38: 5.4 | BO38: 6.7 | BP38: 1422.1
B39: 16:00 | C39: 17.3 | E39: 7.7 | F39: 6.5 | G39: 2 | I39: 9.1 | J39: 0.6 | K39: 18.8 | M39: 9.8 | N39: 13.5 | O39: 4.2 | P39: 3.1 | Q39: 2.6 | R39: 17.4 | S39: 20.6 | T39: 20 | U39: 13.6 | V39: 23 | W39: 4.9 | X39: 51.4 | Y39: 80.8 | Z39: 86.1 | AA39: 18.3 | AB39: 11.9 | AC39: 9.6 | AD39: 16.5 | AE39: 4.2 | AF39: 7.7 | AG39: 8 | AH39: 8.2 | AJ39: 43.3 | AK39: 13.1 | AL39: 16.6 | AM39: 3.3 | AN39: 18.4 | AP39: 170.5 | AR39: 1.5 | AS39: 6.7 | AT39: 8.7 | AU39: 5.5 | AV39: 9.9 | AW39: 107.7 | AX39: 77.5 | AY39: 121.2 | AZ39: 67.5 | BA39: 0.6 | BB39: 10.3 | BC39: 18.2 | BD39: 61.3 | BE39: 16.2 | BF39: 4.5 | BH39: 1.2 | BI39: 2.4 | BJ39: 6.7 | BK39: 0.6 | BM39: 19.1 | BN39: 5.5 | BO39: 2.2 | BP39: 1317.6
B40: 16:30 | C40: 16.8 | E40: 7.9 | F40: 6.6 | G40: 2 | I40: 9.9 | J40: 0.2 | K40: 18.8 | M40: 8.6 | N40: 12.8 | O40: 4.1 | P40: 3 | Q40: 2.6 | R40: 17.4 | S40: 20.3 | T40: 20 | U40: 13.6 | V40: 22.3 | W40: 5.7 | X40: 58.2 | Y40: 61.6 | Z40: 79.1 | AA40: 8.7 | AB40: 7.8 | AC40: 5.9 | AD40: 16.5 | AE40: 4.2 | AF40: 7.7 | AG40: 8 | AH40: 8.2 | AJ40: 21 | AK40: 15.6 | AL40: 17.9 | AM40: 3.4 | AN40: 18.4 | AP40: 91.5 | AR40: 1.5 | AS40: 4.1 | AT40: 3.3 | AU40: 5.6 | AV40: 9.9 | AW40: 100.2 | AX40: 37.2 | AY40: 112.6 | AZ40: 35.3 | BA40: 0.6 | BB40: 3.7 | BC40: 21.7 | BD40: 65.3 | BE40: 16.3 | BF40: 4.5 | BH40: 1.2 | BI40: 2.4 | BJ40: 4.2 | BK40: 0.6 | BM40: 19 | BN40: 5.5 | BO40: 0.3 | BP40: 1081.3
B41: 17:00 | C41: 17.5 | E41: 7.6 | F41: 7.7 | G41: 2.1 | I41: 9.6 | K41: 18.8 | M41: 8.4 | N41: 12.8 | O41: 4.1 | P41: 3.1 | Q41: 2.6 | R41: 17.4 | S41: 20.3 | T41: 20 | U41: 13.6 | V41: 24.1 | W41: 5.9 | X41: 66.9 | Y41: 63.9 | Z41: 86.4 | AA41: 1.4 | AB41: 8.2 | AC41: 6.3 | AD41: 16.5 | AE41: 4.2 | AF41: 7.7 | AG41: 8.4 | AH41: 8.2 | AJ41: 4.5 | AK41: 10.8 | AL41: 14.2 | AM41: 3.4 | AN41: 18.4 | AP41: 19.7 | AR41: 1.5 | AS41: 1.4 | AT41: 0.2 | AU41: 5.5 | AV41: 9.9 | AW41: 120.6 | AX41: 5.9 | AY41: 125.6 | AZ41: 7 | BA41: 0.6 | BB41: 0.1 | BC41: 20.3 | BD41: 62.7 | BE41: 16.2 | BF41: 4.5 | BG41: 0.6 | BH41: 1.2 | BI41: 2.4 | BJ41: 1.7 | BK41: 0.6 | BM41: 19 | BN41: 5.4 | BP41: 957.6
B42: 17:30 | C42: 17.1 | E42: 7.7 | F42: 12.4 | G42: 2.2 | I42: 9.7 | K42: 18.8 | M42: 8.2 | N42: 12.6 | O42: 4.1 | P42: 2.9 | Q42: 2.6 | R42: 17.4 | S42: 20.4 | T42: 20 | U42: 13.6 | V42: 21.4 | W42: 3.4 | X42: 71.3 | Y42: 48.6 | Z42: 80.3 | AB42: 5.2 | AC42: 5.1 | AD42: 16.5 | AE42: 4.2 | AF42: 7.7 | AG42: 8.4 | AH42: 8.6 | AK42: 11.7 | AL42: 15.9 | AM42: 3.4 | AN42: 18.4 | AR42: 1.5 | AU42: 5.6 | AV42: 9.9 | AW42: 104.1 | AY42: 121.9 | BA42: 0.6 | BC42: 22.6 | BD42: 61.1 | BE42: 16 | BF42: 4.5 | BG42: 1.3 | BH42: 1.2 | BI42: 2.2 | BK42: 0.6 | BM42: 19 | BN42: 5.5 | BP42: 877.4
B43: 18:00 | C43: 17.2 | E43: 7.8 | F43: 13.6 | G43: 2.2 | I43: 9.8 | K43: 18.8 | M43: 8.4 | N43: 12.6 | O43: 4.1 | P43: 3.1 | Q43: 2.6 | R43: 17.4 | S43: 20.3 | T43: 20 | U43: 13.6 | V43: 19.9 | W43: 3.6 | X43: 77.4 | Y43: 58.4 | Z43: 89.7 | AB43: 8 | AC43: 3.6 | AD43: 16.5 | AE43: 4.2 | AF43: 7.5 | AG43: 8.4 | AH43: 8.6 | AK43: 9.2 | AL43: 14.1 | AM43: 3.4 | AN43: 18.4 | AR43: 1.5 | AU43: 5.6 | AV43: 9.9 | AW43: 96.9 | AY43: 114.4 | BA43: 0.6 | BC43: 24 | BD43: 73.1 | BE43: 16 | BF43: 4.5 | BG43: 1.3 | BH43: 1.2 | BI43: 2.2 | BK43: 0.6 | BM43: 19 | BN43: 5.5 | BP43: 898.7
B44: 18:30 | C44: 17.5 | E44: 8.1 | F44: 13.5 | G44: 2.2 | I44: 9.9 | K44: 18.7 | M44: 8.2 | N44: 11.4 | O44: 4.1 | P44: 3.1 | Q44: 2.6 | R44: 17.6 | S44: 20.1 | T44: 20 | U44: 13.6 | V44: 17 | W44: 1 | X44: 74.5 | Y44: 65 | Z44: 88.4 | AB44: 8.3 | AC44: 5.3 | AD44: 16.5 | AE44: 4.8 | AF44: 7.3 | AG44: 8.4 | AH44: 8.6 | AK44: 12.8 | AL44: 14.2 | AM44: 3.4 | AN44: 18.4 | AR44: 1.5 | AU44: 5.4 | AV44: 9.9 | AW44: 83.9 | AY44: 89.2 | BA44: 0.6 | BC44: 21.1 | BD44: 65.5 | BE44: 15.8 | BF44: 4.5 | BG44: 1.3 | BH44: 1.2 | BI44: 2.2 | BK44: 0.6 | BM44: 19.2 | BN44: 5.5 | BP44: 851.9
B45: 19:00 | C45: 16.4 | E45: 7.4 | F45: 13.5 | G45: 2.2 | I45: 9.7 | K45: 18.7 | M45: 8.3 | N45: 11.4 | O45: 4.3 | P45: 3.1 | Q45: 2.6 | R45: 17.6 | S45: 20.1 | T45: 20 | U45: 13.6 | V45: 16.4 | W45: 1.8 | X45: 76.7 | Y45: 60.7 | Z45: 92.4 | AB45: 7 | AC45: 6.2 | AD45: 16.5 | AE45: 5.1 | AF45: 7.3 | AG45: 8.2 | AH45: 8.4 | AK45: 8.4 | AL45: 12.6 | AM45: 3.4 | AN45: 18.4 | AR45: 1.5 | AU45: 5.5 | AV45: 10 | AW45: 71.8 | AY45: 78.1 | BA45: 0.6 | BC45: 20.7 | BD45: 65.2 | BE45: 15.9 | BF45: 4.5 | BG45: 1.3 | BH45: 1.2 | BI45: 2.2 | BK45: 0.6 | BM45: 19.1 | BN45: 5.5 | BP45: 822.1
B46: 19:30 | C46: 16.9 | E46: 7.5 | F46: 13.5 | G46: 2.2 | I46: 9.5 | K46: 18.3 | M46: 8.3 | N46: 11.6 | O46: 4.4 | P46: 3.2 | Q46: 2.6 | R46: 17.8 | S46: 20.4 | T46: 20 | U46: 13.6 | V46: 15.2 | W46: 2 | X46: 74 | Y46: 57.7 | Z46: 83.1 | AB46: 6.8 | AC46: 4.2 | AD46: 16.5 | AE46: 5.1 | AF46: 7.1 | AG46: 8 | AH46: 8.2 | AK46: 11.5 | AL46: 12.1 | AM46: 3.5 | AN46: 18.4 | AR46: 1.5 | AU46: 5.5 | AV46: 9.9 | AW46: 61.9 | AY46: 60.6 | BA46: 0.6 | BC46: 24 | BD46: 59.8 | BE46: 15.7 | BF46: 4.5 | BG46: 1.4 | BH46: 1.2 | BI46: 2.4 | BK46: 0.6 | BM46: 19.2 | BN46: 5.5 | BP46: 777.5
B47: 20:00 | C47: 16.7 | E47: 7.6 | F47: 13.5 | G47: 2.3 | I47: 9.7 | K47: 18.3 | M47: 8.4 | N47: 12.2 | O47: 4.4 | P47: 3 | Q47: 2.6 | R47: 17.4 | S47: 20.1 | T47: 20 | U47: 13.6 | V47: 16.3 | W47: 2.1 | X47: 75.1 | Y47: 60.4 | Z47: 79.4 | AB47: 5.9 | AC47: 2.6 | AD47: 16.5 | AE47: 5.2 | AF47: 7.2 | AG47: 8 | AH47: 8.2 | AK47: 6.7 | AL47: 10.7 | AM47: 3.5 | AN47: 18.4 | AR47: 1.5 | AU47: 5.5 | AV47: 9.9 | AW47: 37.2 | AY47: 49.6 | BA47: 0.6 | BC47: 24.7 | BD47: 61.2 | BE47: 15.6 | BF47: 4.5 | BG47: 2.3 | BH47: 1.2 | BI47: 2.4 | BK47: 0.6 | BM47: 19 | BN47: 5.5 | BP47: 737.3
B48: 20:30 | C48: 16.5 | E48: 6.4 | F48: 13.5 | G48: 2.2 | I48: 9.8 | K48: 17.8 | M48: 8.4 | N48: 12.1 | O48: 4.4 | P48: 3.1 | Q48: 2.6 | R48: 17.6 | S48: 20.2 | T48: 20 | U48: 13.6 | V48: 18.8 | W48: 2.9 | X48: 74 | Y48: 43.6 | Z48: 71.2 | AB48: 5 | AC48: 1.7 | AD48: 16.5 | AE48: 5.3 | AF48: 7.3 | AG48: 7.6 | AH48: 8 | AK48: 7.9 | AL48: 13.6 | AM48: 3.5 | AN48: 18.4 | AR48: 1.5 | AU48: 5.5 | AV48: 10 | AW48: 34.9 | AY48: 42.4 | BA48: 0.6 | BC48: 22.7 | BD48: 59.1 | BE48: 15.6 | BF48: 4.5 | BG48: 2.8 | BH48: 1.2 | BI48: 2.2 | BK48: 0.6 | BM48: 19.1 | BN48: 5.5 | BP48: 701.7
B49: 21:00 | C49: 16 | E49: 7.7 | F49: 13.5 | G49: 2.2 | I49: 9.7 | K49: 17.8 | M49: 8.4 | N49: 12.2 | O49: 4.5 | P49: 3.1 | Q49: 2.6 | R49: 17.7 | S49: 20.3 | T49: 20 | U49: 13.6 | V49: 20.4 | W49: 4.5 | X49: 71.7 | Y49: 35.4 | Z49: 55.8 | AB49: 3.3 | AC49: 1.1 | AD49: 16.5 | AE49: 5.3 | AF49: 7.4 | AG49: 7.6 | AH49: 8 | AK49: 11.9 | AL49: 13.6 | AM49: 3.5 | AN49: 18.4 | AR49: 1.5 | AU49: 5.6 | AV49: 10.1 | AW49: 21.3 | AY49: 31.1 | BA49: 0.6 | BC49: 26.4 | BD49: 55.9 | BE49: 15.6 | BF49: 4.5 | BG49: 2.8 | BH49: 1.2 | BI49: 2.2 | BK49: 0.6 | BM49: 19.2 | BN49: 5.5 | BP49: 657.8
B50: 21:30 | C50: 17 | E50: 7.3 | F50: 13.5 | G50: 2.1 | I50: 9.4 | K50: 17.6 | M50: 8.6 | N50: 12.3 | O50: 4.5 | P50: 3.1 | Q50: 2.6 | R50: 17.6 | S50: 20.3 | T50: 20 | U50: 13.6 | V50: 23.3 | W50: 8 | X50: 67.3 | Y50: 20.1 | Z50: 40.1 | AB50: 2 | AC50: 0.9 | AD50: 16.5 | AE50: 5.3 | AF50: 7.4 | AG50: 7.6 | AH50: 7.8 | AK50: 10.4 | AL50: 13.5 | AM50: 3.5 | AN50: 18.4 | AR50: 1.5 | AU50: 5.6 | AV50: 10 | AW50: 12.9 | AY50: 15.9 | BA50: 0.6 | BC50: 16.8 | BD50: 41.7 | BE50: 15.6 | BF50: 4.5 | BG50: 2.9 | BH50: 1.2 | BI50: 2.2 | BK50: 0.6 | BM50: 19.2 | BN50: 5.5 | BP50: 578.3
B51: 22:00 | C51: 16.5 | E51: 7.6 | F51: 13.5 | G51: 2.1 | I51: 10 | K51: 17.1 | M51: 8.3 | N51: 12.2 | O51: 4.6 | P51: 2.9 | Q51: 2.6 | R51: 17.4 | S51: 20.2 | T51: 20 | U51: 13.6 | V51: 26.8 | W51: 6.9 | X51: 60 | Y51: 15.2 | Z51: 25.6 | AB51: 2 | AC51: 1.6 | AD51: 16.5 | AE51: 5.1 | AF51: 7.4 | AG51: 7.6 | AH51: 7.8 | AK51: 13.3 | AL51: 15.8 | AM51: 3.5 | AN51: 18.4 | AR51: 1.5 | AU51: 5.6 | AV51: 9.9 | AW51: 14.4 | AY51: 24.9 | BA51: 0.6 | BC51: 14.2 | BD51: 30.5 | BE51: 15.7 | BF51: 4.5 | BG51: 2.9 | BH51: 1.2 | BI51: 2.2 | BK51: 0.6 | BM51: 19 | BN51: 5.6 | BP51: 555.4
B52: 22:30 | C52: 17.5 | E52: 7.7 | F52: 13.5 | G52: 2.1 | I52: 9.9 | K52: 17.2 | M52: 8.2 | N52: 12.1 | O52: 4.8 | P52: 2.8 | Q52: 2.6 | R52: 17.4 | S52: 20.1 | T52: 20 | U52: 13.6 | V52: 27.6 | W52: 6.5 | X52: 51.5 | Y52: 6.9 | Z52: 21.6 | AB52: 1.1 | AC52: 0.7 | AD52: 16.5 | AE52: 5.1 | AF52: 7.4 | AG52: 7.8 | AH52: 8 | AK52: 11.7 | AL52: 13.8 | AM52: 3.5 | AN52: 18.4 | AR52: 1.5 | AU52: 5.6 | AV52: 9.9 | AW52: 20.5 | AY52: 24.3 | BA52: 0.6 | BC52: 13.8 | BD52: 29.1 | BE52: 15.9 | BF52: 4.5 | BG52: 2.9 | BH52: 1.2 | BI52: 2.2 | BK52: 0.6 | BM52: 19 | BN52: 5.5 | BP52: 534.7
B53: 23:00 | C53: 17.3 | E53: 7.6 | F53: 13.5 | G53: 2 | I53: 8.9 | K53: 17.2 | M53: 8.4 | N53: 12.2 | O53: 4.8 | P53: 3 | Q53: 2.6 | R53: 17.4 | S53: 20.2 | T53: 20 | U53: 13.6 | V53: 28.2 | W53: 10.8 | X53: 53.1 | Y53: 3.9 | Z53: 20.4 | AB53: 1.1 | AC53: 0.4 | AD53: 16.5 | AE53: 5.1 | AF53: 7.4 | AG53: 7.8 | AH53: 8 | AK53: 11.3 | AL53: 13.9 | AM53: 3.5 | AN53: 18.4 | AR53: 1.5 | AU53: 5.6 | AV53: 9.9 | AW53: 16.2 | AY53: 28.2 | BA53: 0.6 | BC53: 13.3 | BD53: 24.6 | BE53: 15.9 | BF53: 4.5 | BG53: 2.9 | BH53: 1.2 | BI53: 2.2 | BK53: 0.6 | BM53: 19 | BN53: 5.6 | BP53: 530.3
B54: 23:30 | C54: 17.4 | E54: 7.5 | F54: 13.5 | G54: 2 | I54: 9.5 | K54: 17.2 | M54: 8.2 | N54: 12.1 | O54: 4.8 | P54: 2.9 | Q54: 2.6 | R54: 17.2 | S54: 20.1 | T54: 20 | U54: 13.6 | V54: 29.7 | W54: 14.5 | X54: 52.2 | Y54: 4.1 | Z54: 15 | AB54: 0.4 | AD54: 16.5 | AE54: 5.1 | AF54: 7.2 | AG54: 8 | AH54: 8.2 | AK54: 11.1 | AL54: 14.4 | AM54: 3.5 | AN54: 18.4 | AR54: 1.5 | AU54: 5.4 | AV54: 9.9 | AW54: 11.6 | AY54: 17.7 | BA54: 0.6 | BC54: 14.7 | BD54: 29.2 | BE54: 16 | BF54: 4.5 | BG54: 2.9 | BH54: 1.2 | BI54: 2.2 | BK54: 0.6 | BM54: 19 | BN54: 5.6 | BP54: 519.5
B55: 0:00 | C55: 17.6 | E55: 7.8 | F55: 13.5 | G55: 2 | I55: 9.7 | K55: 17.2 | M55: 8.5 | N55: 11.5 | O55: 4.7 | P55: 2.9 | Q55: 2.6 | R55: 17.3 | S55: 20.4 | T55: 20 | U55: 13.6 | V55: 29.7 | W55: 8.5 | X55: 52.8 | Y55: 3.2 | Z55: 8.8 | AB55: 0.4 | AD55: 16.5 | AE55: 5.1 | AF55: 7.2 | AG55: 8 | AH55: 8.2 | AK55: 7.6 | AL55: 10.9 | AM55: 3.5 | AN55: 18.4 | AR55: 1.5 | AU55: 5.5 | AV55: 10 | AW55: 13.7 | AY55: 17.5 | BA55: 0.6 | BC55: 18.5 | BD55: 34.1 | BE55: 15.9 | BF55: 4.5 | BG55: 2.9 | BH55: 1.2 | BI55: 2.2 | BK55: 0.6 | BM55: 19 | BN55: 5.5 | BP55: 511.3
B56: EJEC MWh | C56: 413 | D56: 0 | E56: 180.45 | F56: 278.55 | G56: 49.1 | H56: 0 | I56: 229.7 | J56: 7.95 | K56: 454.95 | L56: 0 | M56: 220.9 | N56: 316.2 | O56: 113.9 | P56: 73.9 | Q56: 62.4 | R56: 425.9 | S56: 485.85 | T56: 480 | U56: 338.3 | V56: 520.95 | W56: 239.25 | X56: 1971.75 | Y56: 1558.65 | Z56: 1721.45 | AA56: 240.4 | AB56: 238.05 | AC56: 152.75 | AD56: 395.8 | AE56: 124.35 | AF56: 186.5 | AG56: 202 | AH56: 207.2 | AI56: 0 | AJ56: 564.25 | AK56: 315.15 | AL56: 370.75 | AM56: 82.3 | AN56: 441.6 | AO56: 0 | AP56: 1845.35 | AQ56: 1.45 | AR56: 36.35 | AS56: 117.05 | AT56: 116.6 | AU56: 132.3 | AV56: 238.35 | AW56: 1923.7 | AX56: 1019.85 | AY56: 1958.15 | AZ56: 757.7 | BA56: 14.4 | BB56: 138.7 | BC56: 631.25 | BD56: 1691.7 | BE56: 400.95 | BF56: 108 | BG56: 27.45 | BH56: 36.8 | BI56: 52.5 | BJ56: 113.15 | BK56: 15.2 | BL56: 0 | BM56: 459.45 | BN56: 132.35 | BO56: 99.15 | BP56: 25732.1
L70: TERMOELÉCTRICA | M70: 1047.9 | N70: 4.0723454 | O70: #FFA975
L71: SOLAR | M71: 5021.6 | N71: 19.514925 | O71: #FFD272
L72: HIDROELÉCTRICA | M72: 6369.05 | N72: 24.751381 | O72: #98D2FF
L73: EÓLICA | M73: 13293.55 | N73: 51.661349 | O73: #B9ACFF

Sheet COGENERACIÓN
B3: jueves, 19 de Junio del 2025
B5: CENTRALES DE COGENERACIÓN DEL SEIN
B6: HORA | C6: AGRO INDUSTRIAL PARAMONGA S.A. | D6: AGROAURORA S.A.C. | E6: AGROINDUSTRIAS SAN JACINTO S.A.A. | F6: BIOENERGIA DEL CHIRA S.A. | G6: GM OPERACIONES S.A.C. | H6: SDF ENERGIA SAC | I6: TOTAL COGENERACION
C7: C.T. PARAMONGA | D7: C.T. MAPLE | E7: C.T SAN JACINTO | F7: C.T. CAÑA BRAVA | G7: C.T. REFINERÍA TALARA | H7: C.T. OQUENDO | I7: MW
B8: 0:30 | C8: 17.1 | E8: 7.5 | F8: 9 | G8: 56.4 | I8: 90
B9: 1:00 | C9: 17.6 | E9: 7.3 | F9: 8.9 | G9: 57.5 | I9: 91.3
B10: 1:30 | C10: 17.6 | E10: 7.7 | F10: 9.3 | G10: 57.4 | I10: 92
B11: 2:00 | C11: 16.8 | E11: 7.8 | F11: 9.6 | G11: 57.3 | I11: 91.5
B12: 2:30 | C12: 16.9 | E12: 6.9 | F12: 9.6 | G12: 57.6 | I12: 91
B13: 3:00 | C13: 17.8 | E13: 7.7 | F13: 9.5 | G13: 57.5 | I13: 92.5
B14: 3:30 | C14: 17.8 | E14: 7.2 | F14: 9.8 | G14: 57.7 | I14: 92.5
B15: 4:00 | C15: 17.4 | E15: 8.1 | F15: 9.7 | G15: 57.6 | I15: 92.8
B16: 4:30 | C16: 17.7 | E16: 7.9 | F16: 9.7 | G16: 58 | I16: 93.3
B17: 5:00 | C17: 17.8 | E17: 8.3 | F17: 9.7 | G17: 57.7 | I17: 93.5
B18: 5:30 | C18: 17 | E18: 8.4 | F18: 9 | G18: 57.5 | I18: 91.9
B19: 6:00 | C19: 17.1 | E19: 8.7 | F19: 9.8 | G19: 58.7 | I19: 94.3
... B55: 0:00 | C55: 17.6 | E55: 7.8 | F55: 9.7 | G55: 60.8 | I55: 95.9
B56: EJEC MWh | C56: 413 | D56: 0 | E56: 180.45 | F56: 229.7 | G56: 1421.15 | H56: 0 | I56: 2244.3

Sheet EVO_PRO_ENE
B3: domingo, 1 de Junio del 2025 - jueves, 19 de Junio del 2025
B5: EVOLUCIÓN DE LA PRODUCCIÓN DE LA ENERGÍA DIARIA DE LOS INTEGRANTES DEL COES (MWh)
B6: EMPRESA | C6: CENTRAL | D6: UNIDAD | E6: TIPO | F6: Junio
F7: 1 | G7: 2 | H7: 3 | I7: 4 | J7: 5 | K7: 6 | L7: 7 | M7: 8 | N7: 9 | O7: 10 | P7: 11 | Q7: 12 | R7: 13 | S7: 14 | T7: 15 | U7: 16 | V7: 17 | W7: 18 | X7: 19 | Y7: TOTAL
B8: AGRO INDUSTRIAL PARAMONGA S.A. | C8: C.T. PARAMONGA | D8: TV-01 | E8: TERMOELÉCTRICA | F8: 368.9 | I8: 47.15 | J8: 354.1 | K8: 422.95 | L8: 414.35 | M8: 408.3 | N8: 398.85 | O8: 410.6 | P8: 407.3 | Q8: 407.45 | R8: 404.7 | S8: 400.1 | T8: 398.1 | U8: 384.7 | V8: 403.8 | W8: 391.8 | X8: 413 | Y8: 6436.15
B9: AGROAURORA S.A.C. | C9: C.T. MAPLE ETANOL | D9: TV | E9: TERMOELÉCTRICA | Y9: 0
B10: AGROINDUSTRIAS SAN JACINTO S.A.A. | C10: C.T. SAN JACINTO | D10: CENTRAL | E10: TERMOELÉCTRICA | H10: 54.85 | I10: 141.15 | J10: 152.85 | K10: 150.65 | L10: 154.55 | M10: 159.55 | N10: 177.05 | O10: 178.55 | P10: 176.3 | Q10: 167.5 | R10: 156.05 | S10: 188.785 | T10: 185.65 | U10: 164.9 | V10: 182.6 | W10: 188.45 | X10: 180.45 | Y10: 2759.885
B11: ANDEAN POWER S.A.C. | C11: C.H.CARHUAC | D11: CENTRAL | E11: HIDROELÉCTRICA | F11: 276.6 | G11: 274.7 | H11: 261.15 | I11: 250.45 | J11: 244.5 | K11: 244.05 | L11: 247.65 | M11: 237.5 | N11: 250.25 | O11: 298.6 | P11: 272.8 | Q11: 266.25 | R11: 265.6 | S11: 260.05 | T11: 265.8 | U11: 273.95 | V11: 275.4 | W11: 270 | X11: 278.55 | Y11: 5013.85
B12: ASOCIACIÓN SANTA LUCIA DE CHACAS | C12: C.H. HUALLIN | D12: CENTRAL | E12: HIDROELÉCTRICA | F12: 66.4 | G12: 59.9 | H12: 49.8 | I12: 47.15 | J12: 46.45 | K12: 42.95 | L12: 43.3 | M12: 42.3 | N12: 43.25 | O12: 46.75 | P12: 43.4 | Q12: 40.35 | R12: 40.85 | S12: 43.35 | T12: 47.05 | U12: 60.1 | V12: 59.8 | W12: 53.25 | X12: 49.1 | Y12: 925.5
B13: ATRIA ENERGIA S.A.C. | C13: C.H. PURMACANA | D13: CENTRAL | E13: HIDROELÉCTRICA | F13: 9.6 | G13: 6.75 | K13: 4.75 | L13: 5.45 | S13: 4.65 | T13: 8.3 | U13: 4.3 | Y13: 43.8
B14: BIOENERGIA DEL CHIRA S.A. | C14: C.T. CAÑA BRAVA | D14: CENTRAL | E14: TERMOELÉCTRICA | F14: 239.65 | G14: 205.85 | H14: 231.9 | I14: 225.75 | J14: 220.9 | K14: 221.05 | L14: 214.55 | M14: 215.4 | N14: 204.6 | O14: 190.4 | P14: 213.05 | Q14: 222.45 | R14: 221.65 | S14: 207.35 | T14: 195.05 | U14: 185.85 | V14: 93.3 | W14: 174.95 | X14: 229.7 | Y14: 3913.4
B15: CELEPSA | C15: C.H. EL PLATANAL | D15: CENTRAL | E15: HIDROELÉCTRICA | F15: 3914.5 | G15: 4008.9 | H15: 3906.9 | I15: 3839.5 | J15: 3591.4 | K15: 3553.65 | L15: 3674.15 | M15: 3367.45 | N15: 3293.05 | O15: 3214.35 | P15: 3279.1 | Q15: 3182 | R15: 2800.75 | S15: 2624.85 | T15: 3180.1 | U15: 3699.9 | V15: 3229.65 | W15: 3100.1 | X15: 3009.85 | Y15: 64470.15
B16: CELEPSA RENOVABLES S.R.L. | C16: C.H. MARAÑON | D16: CENTRAL | E16: HIDROELÉCTRICA | F16: 472.8 | G16: 472.8 | H16: 472.8 | I16: 382.2 | J16: 257.65 | K16: 316.8 | L16: 364.7 | M16: 475.2 | N16: 475.2 | O16: 474.4 | P16: 474.95 | Q16: 475.2 | R16: 475.2 | S16: 475.2 | T16: 475.2 | U16: 475 | V16: 475.2 | W16: 475.2 | X16: 475.2 | Y16: 8440.9
B17: CENTRALES SANTA ROSA S.A.C. | C17: C.H. SANTA ROSA I | D17: CENTRAL | E17: HIDROELÉCTRICA | Y17: 0
B18: CENTRALES SANTA ROSA S.A.C. | C18: C.H. SANTA ROSA II | D18: CENTRAL | E18: HIDROELÉCTRICA | Y18: 0
B19: CHINANGO S.A.C. | C19: C.H. CHIMAY | D19: CENTRAL | E19: HIDROELÉCTRICA | F19: 3163.1 | G19: 2553.85 | H19: 2402.4 | I19: 1960.25 | J19: 1810.7 | K19: 2018.15 | L19: 1724.95 | M19: 1706.4 | N19: 1887.55 | O19: 1804.05 | P19: 1822.1 | Q19: 2265.1 | R19: 1780.25 | S19: 1614.35 | T19: 2128.05 | U19: 3468.15 | V19: 3537.8 | W19: 3482.85 | X19: 2969.55 | Y19: 44099.6
B20: CHINANGO S.A.C. | C20: C.H. YANANGO | D20: CENTRAL | E20: HIDROELÉCTRICA | F20: 908.7 | G20: 836.85 | H20: 757.35 | I20: 705.7 | J20: 644.75 | K20: 630 | L20: 625.5 | M20: 617.5 | N20: 572.9 | O20: 656 | P20: 739.1 | Q20: 749.6 | R20: 738.3 | S20: 724.1 | T20: 876.5 | U20: 997.55 | V20: 1009.2 | W20: 1010.7 | X20: 976.7 | Y20: 14777
B21: COLCA SOLAR S.A.C. | C21: C.S. YARUCAYA | D21: CENTRAL | E21: SOLAR | F21: 7.2 | G21: 5.7 | H21: 8.2 | I21: 8.15 | J21: 8.15 | K21: 8.1 | L21: 7.3 | M21: 8.3 | N21: 8.15 | O21: 8.1 | P21: 7.45 | Q21: 7.95 | R21: 8.05 | S21: 7.9 | T21: 6.1 | U21: 7.35 | V21: 6.35 | W21: 5.7 | X21: 7.95 | Y21: 142.15
B22: EGASA | C22: C.H. CHARCANI III | D22: CENTRAL | E22: HIDROELÉCTRICA | F22: 153.75 | G22: 163.65 | H22: 163.85 | I22: 163.55 | J22: 163.65 | K22: 164 | L22: 163.2 | M22: 163.55 | N22: 164.8 | O22: 165.2 | P22: 164.35 | Q22: 165.5 | R22: 165.2 | S22: 166.6 | T22: 166.75 | U22: 165.45 | V22: 158.15 | W22: 147.35 | X22: 154.29 | Y22: 3082.84
B23: EGASA | C23: C.H. CHARCANI IV | D23: CENTRAL | E23: HIDROELÉCTRICA | F23: 256.2 | G23: 304.1 | H23: 312.6 | I23: 302.85 | J23: 310.5 | K23: 305.55 | L23: 298.4 | M23: 279.85 | N23: 281.05 | O23: 282 | P23: 284.05 | Q23: 279.9 | R23: 280.85 | S23: 284.6 | T23: 278.85 | U23: 285.65 | V23: 257.6 | W23: 226.15 | X23: 255.51 | Y23: 5366.26
B24: EGASA | C24: C.H. CHARCANI V | D24: CENTRAL | E24: HIDROELÉCTRICA | F24: 1638.05 | G24: 1930.75 | H24: 1952.75 | I24: 1926.8 | J24: 1981.05 | K24: 1959.25 | L24: 1881.1 | M24: 1793.6 | N24: 1794.9 | O24: 1783.15 | P24: 1804.55 | Q24: 1787.6 | R24: 1813.85 | S24: 1803.05 | T24: 1800.1 | U24: 1803.25 | V24: 1594.4 | W24: 1490.05 | X24: 1666.04 | Y24: 34204.29
B25: EGASA | C25: C.H. CHARCANI VI | D25: CENTRAL | E25: HIDROELÉCTRICA | Y25: 0
B26: EGASA | C26: C.T. CHILINA DIESEL | D26: CENTRAL | E26: TERMOELÉCTRICA | X26: 3.625 | Y26: 3.625
B27: EGASA | C27: C.T. CHILINA DIESEL | D27: TG | E27: TERMOELÉCTRICA | Y27: 0
B28: EGASA | C28: C.T. MOLLENDO DIESEL | D28: CENTRAL | E28: TERMOELÉCTRICA | N28: 19 | Y28: 19
B29: EGEJUNIN | C29: C.H. HUASAHUASI I | D29: CENTRAL | E29: HIDROELÉCTRICA | F29: 433.25 | G29: 400 | H29: 355.25 | I29: 317.6 | J29: 294 | K29: 268.3 | L29: 259.2 | M29: 246.55 | N29: 242.75 | O29: 235.3 | P29: 232.95 | Q29: 233.85 | R29: 225 | S29: 220.35 | T29: 231.8 | U29: 236.95 | V29: 320.45 | W29: 472.8 | X29: 454.95 | Y29: 5681.3
B30: EGEJUNIN | C30: C.H. RUNATULLO II | D30: CENTRAL | E30: HIDROELÉCTRICA | F30: 133.05 | G30: 224.5 | H30: 206.8 | I30: 187.4 | J30: 172.45 | K30: 164.55 | L30: 159.95 | M30: 158.8 | N30: 157.9 | O30: 155.55 | P30: 149.7 | Q30: 151.25 | R30: 143.9 | S30: 138.45 | T30: 173.25 | U30: 270 | V30: 271.35 | W30: 243.85 | X30: 220.9 | Y30: 3483.6
B31: EGEJUNIN | C31: C.H. RUNATULLO III | D31: CENTRAL | E31: HIDROELÉCTRICA | F31: 194.95 | G31: 329.5 | H31: 301.35 | I31: 267.25 | J31: 242.95 | K31: 234.3 | L31: 228.1 | M31: 220.9 | N31: 224.15 | O31: 214.3 | P31: 207.6 | Q31: 209.85 | R31: 201.15 | S31: 193.2 | T31: 243.2 | U31: 383.35 | V31: 383.5 | W31: 343.9 | X31: 316.2 | Y31: 4939.7
B32: EGEJUNIN | C32: C.H. SANTA CRUZ I | D32: CENTRAL | E32: HIDROELÉCTRICA | F32: 152.8 | G32: 143.85 | H32: 123.9 | I32: 130.2 | J32: 126.35 | K32: 119.8 | L32: 110.9 | M32: 111.2 | N32: 105.6 | O32: 106.1 | P32: 111 | Q32: 104.95 | R32: 105.95 | S32: 109.75 | T32: 112.25 | U32: 116.1 | V32: 127.3 | W32: 119.45 | X32: 113.9 | Y32: 2251.35
B33: EGEMSA | C33: C.H. MACHUPICCHU | D33: CENTRAL | E33: HIDROELÉCTRICA | F33: 3969.65 | G33: 3948.7 | H33: 3939.75 | I33: 3945.95 | J33: 3918.4 | K33: 3913.4 | L33: 3915.75 | M33: 3933.55 | N33: 3919.1 | O33: 3922.7 | P33: 3910.3 | Q33: 3897.7 | R33: 3885 | S33: 3835.1 | T33: 3218.45 | U33: 3860.05 | V33: 3900.8 | W33: 3931.45 | X33: 3908.05 | Y33: 73673.85
B34: EGESUR | C34: C.H. ARICOTA I | D34: CENTRAL | E34: HIDROELÉCTRICA | F34: 175.9 | G34: 174.9 | H34: 175.35 | I34: 174.35 | J34: 173.75 | K34: 173.6 | L34: 174.55 | M34: 174.8 | N34: 175.2 | O34: 175.9 | P34: 175.05 | Q34: 175.6 | R34: 174.15 | S34: 175.8 | T34: 172.25 | U34: 173.45 | V34: 173.05 | W34: 174.967 | X34: 173.9 | Y34: 3316.517
B35: EGESUR | C35: C.H. ARICOTA II | D35: CENTRAL | E35: HIDROELÉCTRICA | F35: 100.35 | G35: 131.4 | H35: 130.9 | I35: 129.5 | J35: 127.2 | K35: 126.85 | L35: 128.2 | M35: 131.5 | N35: 129.75 | O35: 130.4 | P35: 130.7 | Q35: 129.25 | R35: 128.55 | S35: 129.45 | T35: 128.7 | U35: 128.8 | V35: 127.75 | W35: 127.798 | X35: 127.7 | Y35: 2424.748
B36: EGESUR | C36: C.T. INDEPENDENCIA | D36: CENTRAL | E36: TERMOELÉCTRICA | F36: 42.85 | G36: 323.8 | H36: 385.75 | I36: 375.15 | M36: 110.95 | O36: 320.15 | P36: 178.35 | V36: 87.6 | X36: 297.85 | Y36: 2122.45
B37: ELECTRICA YANAPAMPA SAC | C37: C.H. YANAPAMPA | D37: CENTRAL | E37: HIDROELÉCTRICA | F37: 76.95 | G37: 78.05 | H37: 77.2 | I37: 76.35 | J37: 75.6 | K37: 76.65 | L37: 78.6 | M37: 78 | N37: 76.55 | O37: 75.8 | P37: 74.25 | Q37: 72.75 | R37: 67.35 | S37: 65.6 | T37: 65.85 | U37: 68.3 | V37: 71.75 | W37: 74 | X37: 73.9 | Y37: 1403.5
B38: ELECTROPERU | C38: C.H. MANTARO | D38: CENTRAL | E38: HIDROELÉCTRICA | F38: 15079.95 | G38: 15544 | H38: 15538.75 | I38: 15327.2 | J38: 15233.7 | K38: 15517.785 | L38: 14359.95 | M38: 14803.3 | N38: 15541.4 | O38: 15571.6 | P38: 15556.3 | Q38: 15530.85 | R38: 15537.85 | S38: 15548.05 | T38: 15532.95 | U38: 15539.05 | V38: 15546.5 | W38: 14480.65 | X38: 14475.6 | Y38: 290265.43
B39: ELECTROPERU | C39: C.H. RESTITUCION | D39: CENTRAL | E39: HIDROELÉCTRICA | F39: 5046.1 | G39: 5216.4 | H39: 4346.85 | I39: 5125.75 | J39: 5110.4 | K39: 5219.67 | L39: 4777.5 | M39: 4920.6 | N39: 5129.4 | O39: 5141.7 | P39: 5136.35 | Q39: 4458.7 | R39: 4499.85 | S39: 3814.95 | T39: 5200.2 | U39: 5198.3 | V39: 5201.9 | W39: 4855.5 | X39: 4850 | Y39: 93250.12
B40: ELECTROPERU | C40: C.T. TUMBES | D40: MAK1 | E40: TERMOELÉCTRICA | Y40: 0
B41: ELECTROPERU | C41: C.T. TUMBES | D41: MAK2 | E41: TERMOELÉCTRICA | Y41: 0
B42: EMPRESA DE GENERACION ELECTRICA CANCHAYLLO SAC | C42: C.H. CANCHAYLLO | D42: CENTRAL | E42: HIDROELÉCTRICA | F42: 108.8 | G42: 108.4 | H42: 105.4 | I42: 104.3 | J42: 102.5 | K42: 101.7 | L42: 99.5 | M42: 100.25 | N42: 84.8 | O42: 98.1 | P42: 96.25 | Q42: 93.05 | R42: 69.7 | S42: 64.85 | T42: 62.4 | U42: 62.4 | V42: 62.4 | W42: 62.4 | X42: 62.4 | Y42: 1649.6
B43: EMPRESA DE GENERACION ELECTRICA RIO BAÑOS S.A.C. | C43: C.H. RUCUY | D43: CENTRAL | E43: HIDROELÉCTRICA | F43: 478.65 | G43: 479.65 | H43: 478.85 | I43: 479.65 | J43: 478.4 | K43: 477.95 | L43: 474.85 | M43: 472.05 | N43: 469.25 | O43: 464.75 | P43: 459.4 | Q43: 452.05 | R43: 447.3 | S43: 436.1 | T43: 430.6 | U43: 426.7 | V43: 433.7 | W43: 441.25 | X43: 425.9 | Y43: 8707.05
B44: EMPRESA DE GENERACION ELECTRICA SANTA ANA S.A.C. | C44: C.H. RENOVANDES H1 | D44: CENTRAL | E44: HIDROELÉCTRICA | F44: 389.9 | G44: 479.65 | H44: 479.9 | I44: 480.3 | J44: 478.35 | K44: 481.25 | L44: 486.9 | M44: 487.6 | N44: 486.65 | O44: 488.3 | P44: 487.65 | Q44: 486.7 | R44: 487 | S44: 486.9 | T44: 475.35 | U44: 485.95 | V44: 486.2 | W44: 486.85 | X44: 485.85 | Y44: 9107.25
B45: EMPRESA DE GENERACION HUALLAGA | C45: C.H. CHAGLLA | D45: CENTRAL | E45: HIDROELÉCTRICA | F45: 10930.4 | G45: 8482.2 | H45: 5342.6 | I45: 4829.4 | J45: 5367.9 | K45: 5562.3 | L45: 5294.25 | M45: 4953.1 | N45: 4972.8 | O45: 5940.5 | P45: 6102.85 | Q45: 2341.05 | R45: 2122.5 | S45: 5010.8 | T45: 7059.4 | U45: 7883.85 | V45: 8025.7 | W45: 8787.9 | X45: 8995.2 | Y45: 118004.7
B46: EMPRESA DE GENERACION HUALLAGA | C46: P.C.H. CHAGLLA | D46: CENTRAL | E46: HIDROELÉCTRICA | F46: 156.05 | G46: 156 | H46: 156 | I46: 156 | J46: 156 | K46: 156 | L46: 156 | M46: 156 | N46: 156 | O46: 156 | P46: 156 | Q46: 156 | R46: 156 | S46: 66.45 | T46: 48.75 | U46: 156 | V46: 156 | W46: 156 | X46: 156 | Y46: 2767.25
B47: EMPRESA DE GENERACION HUANZA | C47: C.H. HUANZA | D47: CENTRAL | E47: HIDROELÉCTRICA | N47: 467.9 | O47: 1121.9 | P47: 1040.45 | Q47: 1002.95 | R47: 1017.95 | S47: 981.6 | T47: 1059.45 | U47: 1036.6 | V47: 1038.35 | W47: 1032.65 | X47: 970 | Y47: 10769.8
B48: EMPRESA ELECTRICA AGUA AZUL | C48: C.H. POTRERO | D48: CENTRAL | E48: HIDROELÉCTRICA | F48: 364.95 | G48: 344.6 | H48: 480 | I48: 480 | J48: 480 | K48: 480 | L48: 475.95 | M48: 463.2 | N48: 453.5 | O48: 419.75 | P48: 460.3 | Q48: 479.285 | R48: 480 | S48: 476.1 | T48: 480 | U48: 480 | V48: 480 | W48: 480 | X48: 480 | Y48: 8737.635
B49: EMPRESA ELECTRICA RIO DOBLE | C49: C.H. LAS PIZARRAS | D49: CENTRAL | E49: HIDROELÉCTRICA | F49: 391.9 | G49: 365.85 | H49: 340.45 | I49: 324.65 | J49: 294.05 | K49: 265.2 | L49: 270.6 | M49: 287.3 | N49: 281.05 | O49: 271 | P49: 282 | Q49: 416.25 | R49: 406.25 | S49: 331.95 | T49: 327.6 | U49: 418.4 | V49: 409.95 | W49: 378.95 | X49: 338.3 | Y49: 6401.7
B50: ENEL GENERACION PIURA S.A. | C50: C.T. MALACAS 1 | D50: TG6 | E50: TERMOELÉCTRICA | F50: 23.65 | Q50: 90 | R50: 200.5 | S50: 527.05 | T50: 93.9 | V50: 634.1 | W50: 695.3 | X50: 759.1 | Y50: 3023.6
B51: ENEL GENERACION PIURA S.A. | C51: C.T. MALACAS 2 | D51: TG4 | E51: TERMOELÉCTRICA | Y51: 0
B52: ENEL GENERACION PIURA S.A. | C52: C.T. RF DE GENERACION TALARA | D52: TG5 | E52: TERMOELÉCTRICA | Y52: 0
B53: ENERGÍA EÓLICA S.A. | C53: C.E. CUPISNIQUE | D53: CENTRAL | E53: EÓLICA | F53: 664.7 | G53: 590.4 | H53: 472.4 | I53: 475.7 | J53: 544.2 | K53: 667.25 | L53: 1173.3 | M53: 677.15 | N53: 260.5 | O53: 217.1 | P53: 816.05 | Q53: 1047.9 | R53: 441.6 | S53: 674.8 | T53: 1053.05 | U53: 1035.85 | V53: 880.6 | W53: 629.35 | X53: 239.25 | Y53: 12561.15
B54: ENERGÍA EÓLICA S.A. | C54: C.E. TALARA | D54: CENTRAL | E54: EÓLICA | F54: 221.6 | G54: 439.4 | H54: 292.3 | I54: 483.05 | J54: 282.4 | K54: 392.4 | L54: 591.9 | M54: 459.55 | N54: 137.55 | O54: 21.65 | P54: 323 | Q54: 546.35 | R54: 399.45 | S54: 476.55 | T54: 645.7 | U54: 627.35 | V54: 554.35 | W54: 541.35 | X54: 520.95 | Y54: 7956.85
B55: ENERGIA RENOVABLE DEL SUR S.A. | C55: C.E. SAN JUAN | D55: CENTRAL | E55: EÓLICA | F55: 1652.9 | G55: 1228.15 | H55: 1006.15 | I55: 621.85 | J55: 1123.05 | K55: 1623.35 | L55: 2448.1 | M55: 1345.7 | N55: 680.1 | O55: 85.35 | P55: 197.9 | Q55: 882.55 | R55: 1427.3 | S55: 2018 | T55: 1324.6 | U55: 1930.6 | V55: 2740.4 | W55: 2839.85 | X55: 1971.75 | Y55: 27147.65
B56: ENGIE | C56: C.E. PUNTA LOMITAS | D56: PL-BL1 | E56: EÓLICA | F56: 486 | G56: 240.75 | H56: 405.05 | I56: 958.7 | J56: 918.9 | K56: 1384.55 | L56: 1616.35 | M56: 1540.95 | N56: 860.4 | O56: 19.65 | P56: 145.3 | Q56: 1076.45 | R56: 1090.4 | S56: 1149.65 | T56: 492.15 | U56: 1895.45 | V56: 1920.25 | W56: 1771.3 | X56: 1558.65 | Y56: 19530.9
B57: ENGIE | C57: C.E. PUNTA LOMITAS | D57: PL-BL2 | E57: EÓLICA | F57: 853.3 | G57: 628.75 | H57: 853.9 | I57: 1130.9 | J57: 1086.3 | K57: 1466.2 | L57: 1654.65 | M57: 898.7 | N57: 871.45 | O57: 37 | P57: 219.9 | Q57: 1392.4 | R57: 1603.55 | S57: 1644.25 | T57: 778.55 | U57: 2104.8 | V57: 1652.6 | W57: 1607.85 | X57: 1721.45 | Y57: 22206.5
B58: ENGIE | C58: C.E. PUNTA LOMITAS_EXP | D58: PUN LOM_EXP-BL1 | E58: EÓLICA | F58: 53.2 | G58: 25.45 | H58: 35.9 | I58: 124.95 | J58: 133.2 | K58: 210.9 | L58: 273.3 | M58: 201.95 | N58: 114.8 | O58: 1.85 | P58: 14.15 | Q58: 112.75 | R58: 89.05 | S58: 137.9 | T58: 64.6 | U58: 293.5 | V58: 307.4 | W58: 299.4 | X58: 238.05 | Y58: 2732.3
B59: ENGIE | C59: C.E. PUNTA LOMITAS_EXP | D59: PUN LOM_EXP-BL2 | E59: EÓLICA | F59: 49.35 | G59: 32.05 | H59: 54.95 | I59: 95.5 | J59: 86.7 | K59: 101.9 | L59: 135.45 | M59: 62.9 | N59: 78.45 | O59: 1.25 | P59: 8.75 | Q59: 82.9 | R59: 69.05 | S59: 103.85 | T59: 39.6 | U59: 207.9 | V59: 219.2 | W59: 147.45 | X59: 152.75 | Y59: 1729.95
B60: ENGIE | C60: C.H. QUITARACSA | D60: CENTRAL | E60: HIDROELÉCTRICA | T60: 142.15 | U60: 224.75 | Y60: 366.9
B61: ENGIE | C61: C.H. YUNCAN | D61: CENTRAL | E61: HIDROELÉCTRICA | F61: 2072.3 | G61: 2075.3 | H61: 2075.5 | I61: 2039.35 | J61: 1965.35 | K61: 1861.65 | L61: 1575.75 | M61: 1843.85 | N61: 1281.1 | O61: 1779.35 | P61: 1673 | Q61: 1606 | R61: 1577.35 | S61: 1301.1 | T61: 1752.05 | U61: 2036.55 | V61: 2079.35 | W61: 2084.75 | X61: 2080.8 | Y61: 34760.45
B62: ENGIE | C62: C.S. INTIPAMPA | D62: CENTRAL | E62: SOLAR | F62: 249 | G62: 255.45 | H62: 252 | I62: 248.65 | J62: 247.4 | K62: 247.6 | L62: 238.5 | M62: 256.6 | N62: 163.3 | P62: 105.75 | Q62: 206.85 | R62: 205.1 | S62: 210.5 | T62: 256.55 | U62: 182.9 | V62: 180.95 | W62: 224.95 | X62: 240.4 | Y62: 3972.45
B63: ENGIE | C63: C.T. CHILCA 1 | D63: TG1 | E63: TERMOELÉCTRICA | F63: 240.9 | G63: 2602.65 | H63: 3644.2 | I63: 4264.25 | J63: 4250.8 | K63: 4250.45 | L63: 3934.05 | M63: 4109.15 | N63: 4228.5 | O63: 4205.1 | P63: 4184.55 | Q63: 4230.1 | R63: 4220.25 | S63: 3579.75 | T63: 1922.25 | U63: 3752 | V63: 3757.6 | W63: 3786.3 | X63: 4032.75 | Y63: 69195.6
B64: ENGIE | C64: C.T. CHILCA 1 | D64: TG2 | E64: TERMOELÉCTRICA | F64: 400.2 | G64: 2538.85 | H64: 4173.2 | I64: 4214.05 | J64: 4200 | K64: 4199.7 | L64: 3901.45 | M64: 4067.6 | N64: 4177.25 | O64: 4165.8 | P64: 4135.3 | Q64: 4183 | R64: 4174.7 | S64: 4135.5 | T64: 3785.6 | U64: 3710.15 | V64: 1764 | X64: 2275 | Y64: 64201.35
B65: ENGIE | C65: C.T. CHILCA 1 | D65: TG3 | E65: TERMOELÉCTRICA | F65: 3642.8 | G65: 3350.4 | H65: 4666.8 | I65: 4800 | J65: 4774.8 | K65: 4800 | L65: 4300.85 | M65: 4649.05 | N65: 4800 | O65: 4776.6 | P65: 4800 | Q65: 4800 | R65: 4800 | S65: 4609.75 | T65: 60.1 | V65: 441.2 | X65: 489 | Y65: 64561.35
B66: ENGIE | C66: C.T. CHILCA 1 | D66: TV | E66: TERMOELÉCTRICA | F66: 1700.9 | G66: 2837.7 | H66: 6150.15 | I66: 6608.9 | J66: 6589.3 | K66: 6606.85 | L66: 6177.6 | M66: 6449.55 | N66: 6562.25 | O66: 6517.95 | P66: 6511.3 | Q66: 6555.95 | R66: 6549.8 | S66: 6131.7 | T66: 2800.7 | U66: 3836.65 | V66: 2700.7 | W66: 1656.45 | X66: 3008.6 | Y66: 95953
B67: ENGIE | C67: C.T. CHILCA 2 | D67: TG41 | E67: TERMOELÉCTRICA | G67: 1280.9 | H67: 371.9 | I67: 315.85 | W67: 154.25 | Y67: 2122.9
B68: ENGIE | C68: C.T. CHILCA 2 | D68: TV42 | E68: TERMOELÉCTRICA | Y68: 0
B69: ENGIE | C69: C.T. NEPI | D69: TG41 | E69: TERMOELÉCTRICA | Y69: 0
B70: ENGIE | C70: C.T. NEPI | D70: TG42 | E70: TERMOELÉCTRICA | P70: 456.15 | Y70: 456.15
B71: ENGIE | C71: C.T. NEPI | D71: TG43 | E71: TERMOELÉCTRICA | X71: 455.6 | Y71: 455.6
B72: ENGIE | C72: C.T. RF PLANTA ILO | D72: TG1 | E72: TERMOELÉCTRICA | Y72: 0
B73: ENGIE | C73: C.T. RF PLANTA ILO | D73: TG2 | E73: TERMOELÉCTRICA | Y73: 0
B74: ENGIE | C74: C.T. RF PLANTA ILO | D74: TG3 | E74: TERMOELÉCTRICA | Y74: 0
B75: FENIX POWER PERÚ | C75: C.T. FENIX | D75: GT11 | E75: TERMOELÉCTRICA | F75: 3488.35 | G75: 4366.65 | H75: 4375.65 | I75: 4374.25 | J75: 3818.75 | K75: 3355.4 | L75: 1083.3 | N75: 2702.51 | O75: 4385.28 | P75: 4377.25 | Q75: 4321.5 | R75: 4373.4 | S75: 4370.9 | T75: 4067.35 | U75: 3617.75 | V75: 3869.2 | W75: 3608.5752 | X75: 4368.45 | Y75: 68924.515
B76: FENIX POWER PERÚ | C76: C.T. FENIX | D76: GT12 | E76: TERMOELÉCTRICA | F76: 3496.7 | G76: 4381.1 | H76: 4389.55 | I76: 4382.65 | J76: 3829.2 | K76: 3365.6 | L76: 3016.3 | M76: 17.15 | N76: 2726.88 | O76: 4395.4 | P76: 4385.75 | Q76: 4329.2 | R76: 4385.85 | S76: 4381.75 | T76: 4071.7 | U76: 3625.05 | V76: 3877.6 | W76: 3619.3755 | X76: 4375.8 | Y76: 71052.606
B77: FENIX POWER PERÚ | C77: C.T. FENIX | D77: TV10 | E77: TERMOELÉCTRICA | F77: 3940.95 | G77: 4412.25 | H77: 4423.7 | I77: 4436.45 | J77: 4133.1 | K77: 3889.35 | L77: 2499.6 | M77: 18.65 | N77: 2478.99 | O77: 4406.6 | P77: 4406.25 | Q77: 4370.95 | R77: 4407.15 | S77: 4431.8 | T77: 4258.15 | U77: 4007 | V77: 4146 | W77: 3990.784 | X77: 4406.3 | Y77: 73064.024
B78: GENERACIÓN ANDINA S.A.C. | C78: C.H. 8 DE AGOSTO | D78: CENTRAL | E78: HIDROELÉCTRICA | F78: 334.2 | G78: 384.4 | H78: 306.4 | I78: 260.7 | J78: 233.05 | K78: 241.35 | L78: 258.2 | M78: 258.95 | N78: 251.85 | O78: 254.1 | P78: 296.8 | Q78: 331.8 | R78: 298.3 | S78: 314.65 | T78: 393.55 | U78: 394.75 | V78: 357.9 | W78: 394.05 | X78: 395.8 | Y78: 5960.8
B79: GENERACIÓN ANDINA S.A.C. | C79: C.H. EL CARMEN | D79: CENTRAL | E79: HIDROELÉCTRICA | F79: 140.25 | G79: 108 | H79: 90.55 | I79: 83.4 | J79: 79.5 | K79: 76.7 | L79: 74.4 | M79: 73.2 | N79: 70.7 | O79: 69.6 | P79: 80.35 | Q79: 91 | R79: 87.1 | S79: 103.2 | T79: 100.95 | U79: 103.15 | V79: 196.65 | W79: 175.05 | X79: 124.35 | Y79: 1928.1
B80: GENERADORA DE ENERGÍA DEL PERÚ | C80: C.H. ÁNGEL I | D80: CENTRAL | E80: HIDROELÉCTRICA | F80: 242.9 | G80: 237.4 | H80: 226.3 | I80: 214.25 | J80: 206.85 | K80: 207.15 | L80: 203.25 | M80: 197.8 | N80: 231.25 | O80: 222.45 | P80: 213.25 | Q80: 200.8 | R80: 183.9 | S80: 176.85 | T80: 173.6 | U80: 186.9 | V80: 194.35 | W80: 195.15 | X80: 186.5 | Y80: 3900.9
B81: GENERADORA DE ENERGÍA DEL PERÚ | C81: C.H. ÁNGEL II | D81: CENTRAL | E81: HIDROELÉCTRICA | F81: 250.1 | G81: 255.4 | H81: 242.85 | I81: 232.1 | J81: 224.8 | K81: 226.9 | L81: 221.3 | M81: 214.2 | N81: 249.7 | O81: 239.1 | P81: 230.05 | Q81: 217.8 | R81: 199.1 | S81: 193.1 | T81: 189 | U81: 203.35 | V81: 210.1 | W81: 210.85 | X81: 202 | Y81: 4211.8
B82: GENERADORA DE ENERGÍA DEL PERÚ | C82: C.H. ÁNGEL III | D82: CENTRAL | E82: HIDROELÉCTRICA | F82: 252.15 | G82: 258.25 | H82: 247.9 | I82: 237.15 | J82: 228.1 | K82: 227.4 | L82: 221.8 | M82: 214.5 | N82: 247.85 | O82: 243.05 | P82: 233.8 | Q82: 222.9 | R82: 204 | S82: 198.65 | T82: 194.55 | U82: 206.8 | V82: 214.55 | W82: 215.05 | X82: 207.2 | Y82: 4275.65
B83: GENERADORA DE ENERGÍA DEL PERÚ | C83: C.H. LA JOYA | D83: CENTRAL | E83: HIDROELÉCTRICA | G83: 157.35 | H83: 204 | I83: 194.25 | J83: 199.45 | K83: 205.45 | L83: 210.55 | M83: 197.55 | N83: 197.15 | O83: 194.55 | P83: 185.85 | Q83: 185.3 | R83: 191.25 | S83: 194.8 | T83: 199.95 | U83: 193.25 | V83: 10.75 | Y83: 2921.45
B84: GM OPERACIONES S.A.C. | C84: CT REFINERIA TALARA | D84: TV1 REF TALARA | E84: TERMOELÉCTRICA | F84: 1044.7 | G84: 1044.4 | H84: 1045.85 | I84: 1057 | J84: 1060.65 | K84: 1051.15 | L84: 985.25 | M84: 969.95 | N84: 904 | O84: 1028.4 | P84: 1010.25 | Q84: 1025.4 | R84: 1034.135 | S84: 1020.5 | T84: 1043.3 | U84: 1030.05 | V84: 1012.695 | W84: 1026.2 | X84: 1034.2 | Y84: 19428.08
B85: GM OPERACIONES S.A.C. | C85: CT REFINERIA TALARA | D85: TV2 REF TALARA | E85: TERMOELÉCTRICA | F85: 358.55 | G85: 379.8 | H85: 384.1 | I85: 394.8 | J85: 348.3 | K85: 381.05 | L85: 383.4 | M85: 347.5 | N85: 315.45 | O85: 285.9 | P85: 276.4 | Q85: 287.7 | R85: 300.745 | S85: 305.35 | T85: 311.5 | U85: 433.6 | V85: 390.909 | W85: 315.8 | X85: 386.95 | Y85: 6587.804
B86: GR CORTARRAMA SOCIEDAD ANONIMA CERRADA | C86: C.S. MATARANI | D86: C.S. MATARANI | E86: SOLAR | F86: 597.4 | G86: 602.7 | H86: 597.35 | I86: 590.45 | J86: 598 | K86: 600.45 | L86: 562.65 | M86: 602.75 | N86: 569.05 | O86: 495.95 | P86: 521.75 | Q86: 569 | R86: 474.35 | S86: 486.25 | T86: 570.35 | U86: 490.2 | V86: 444 | W86: 534 | X86: 564.25 | Y86: 10470.9
B87: GR PAINO SOCIEDAD ANONIMA CERRADA | C87: C.E. HUAMBOS | D87: CENTRAL | E87: EÓLICA | F87: 219.95 | G87: 318.85 | H87: 272.7 | I87: 192.5 | J87: 252.8 | K87: 234.35 | L87: 210 | M87: 204.2 | N87: 265.35 | O87: 148.7 | P87: 137.2 | Q87: 33.4 | R87: 33.1 | S87: 36.2 | T87: 64.7 | U87: 123.05 | V87: 202.2 | W87: 290.75 | X87: 315.15 | Y87: 3555.15
B88: GR TARUCA SOCIEDAD ANONIMA CERRADA | C88: C.E. DUNA | D88: CENTRAL | E88: EÓLICA | F88: 289.15 | G88: 369.05 | H88: 336.2 | I88: 262.5 | J88: 320.85 | K88: 306.25 | L88: 289.4 | M88: 228.1 | N88: 272.4 | O88: 190.65 | P88: 188.6 | Q88: 43.7 | R88: 17.5 | S88: 23.75 | T88: 87.05 | U88: 188.95 | V88: 283.45 | W88: 332.15 | X88: 370.75 | Y88: 4400.45
B89: HIDROCAÑETE S.A. | C89: C.H. IMPERIAL | D89: CENTRAL | E89: HIDROELÉCTRICA | F89: 78.5 | G89: 79.1 | H89: 84.1 | I89: 84.2 | J89: 85 | K89: 79.7 | L89: 84.6 | M89: 85.55 | N89: 85.6 | O89: 83.35 | P89: 81.15 | Q89: 81.4 | R89: 82.25 | S89: 83 | T89: 84.25 | U89: 85.55 | V89: 82.35 | W89: 81.7 | X89: 82.3 | Y89: 1573.65
B90: HIDROELECTRICA HUANCHOR S.A.C. | C90: C.H. HUANCHOR | D90: CENTRAL | E90: HIDROELÉCTRICA | F90: 450.4 | G90: 450.65 | H90: 450.95 | I90: 450.85 | J90: 450.7 | K90: 450.4 | L90: 450.6 | M90: 450.05 | N90: 450.95 | O90: 451.4 | P90: 451.15 | Q90: 450.75 | R90: 451.2 | S90: 451.2 | T90: 451.05 | U90: 451.2 | V90: 450.65 | W90: 449.1 | X90: 450.15 | Y90: 8563.4
B91: HUAURA POWER GROUP S.A. | C91: C.H. YARUCAYA | D91: CENTRAL | E91: HIDROELÉCTRICA | F91: 445.5 | G91: 446.25 | H91: 444.3 | I91: 444 | J91: 444 | K91: 444 | L91: 444 | M91: 444 | N91: 444 | O91: 444 | P91: 442.55 | Q91: 441.6 | R91: 441.6 | S91: 441.6 | T91: 441.6 | U91: 441.6 | V91: 441.6 | W91: 441.6 | X91: 441.6 | Y91: 8419.4
B92: HYDRO GLOBAL PERÚ S.A.C. | C92: CH SAN GABAN III | D92: CENTRAL | E92: HIDROELÉCTRICA | I92: 1325.8 | J92: 3106.9 | K92: 2988.85 | L92: 3053.6 | M92: 2837.95 | N92: 3005.3 | O92: 3251 | P92: 3264.35 | Q92: 2706.1 | R92: 2816.65 | S92: 2779.4 | T92: 2596.05 | U92: 2900.4 | V92: 2828.35 | W92: 2685.05 | X92: 2695.5 | Y92: 44841.25
B93: INFRAESTRUCTURAS Y ENERGIAS DEL PERU S.A.C. | C93: C.T. RF PTO MALDONADO | D93: CENTRAL | E93: TERMOELÉCTRICA | I93: 30.95 | Y93: 30.95
B94: INFRAESTRUCTURAS Y ENERGIAS DEL PERU S.A.C. | C94: C.T. RF PUCALLPA | D94: CENTRAL | E94: TERMOELÉCTRICA | G94: 1.65 | N94: 156.65 | O94: 1.45 | S94: 297.25 | U94: 213.45 | V94: 306.9 | W94: 335.95 | X94: 199.3 | Y94: 1512.6
B95: INLAND ENERGY SAC | C95: C.H. SANTA TERESA | D95: CENTRAL | E95: HIDROELÉCTRICA | F95: 2159.2 | G95: 2154.8 | H95: 2159.3 | I95: 2150.85 | J95: 2139.5 | K95: 2134.95 | L95: 2132.85 | M95: 2128.8 | N95: 2132.55 | O95: 2149.25 | P95: 2147.85 | Q95: 2127.15 | R95: 2106.3 | S95: 2105 | T95: 1786.3 | U95: 2122.35 | V95: 2143.5 | W95: 2133.05 | X95: 2142.25 | Y95: 40255.8
B96: INVERSIONES SHAQSHA S.A.C. | C96: C.H. PARIAC | D96: CENTRAL | E96: HIDROELÉCTRICA | F96: 101.3 | G96: 98.3 | H96: 96.5 | I96: 97.05 | J96: 95.05 | K96: 95.2 | L96: 94.3 | M96: 90.85 | N96: 85.25 | O96: 85.75 | P96: 72.55 | Q96: 51.4 | R96: 49.4 | S96: 27.6 | T96: 43.65 | U96: 46.75 | V96: 49.8 | W96: 44.8 | X96: 42.15 | Y96: 1367.65
B97: JOYA SOLAR S.A.C. | C97: C.S. SAN MARTIN SOLAR | D97: CENTRAL | E97: SOLAR | F97: 2014.6 | G97: 1925.95 | H97: 1913.85 | I97: 1893.85 | J97: 1890.8 | K97: 1883.05 | L97: 1792.6 | M97: 1940.6 | N97: 1843.4 | O97: 1614.8 | P97: 1706.9 | Q97: 1854.5 | R97: 1719.45 | S97: 1621.85 | T97: 1927 | U97: 1669.55 | V97: 1304.2 | W97: 1856.75 | X97: 1845.35 | Y97: 34219.05
B98: KALLPA GENERACION S.A. | C98: C.H. CERRO DEL AGUILA | D98: CENTRAL | E98: HIDROELÉCTRICA | F98: 8853.95 | G98: 12436.3 | H98: 11849.95 | I98: 11353.25 | J98: 12137.1 | K98: 9219.15 | L98: 7532.85 | M98: 8258.9 | N98: 9849.25 | O98: 10707.05 | P98: 9786.65 | Q98: 8836.45 | R98: 9539.55 | S98: 9257.75 | T98: 9291.1 | U98: 8699.65 | V98: 10489.8 | W98: 10537.8 | X98: 10716.25 | Y98: 189352.75
B99: KALLPA GENERACION S.A. | C99: C.T. KALLPA | D99: TG1 | E99: TERMOELÉCTRICA | F99: 36.65 | G99: 1303.9 | H99: 492.6 | M99: 116.3 | N99: 3651.25 | O99: 4425.3 | P99: 4333 | Q99: 3535.25 | R99: 4415.9 | S99: 4205.1 | T99: 3529.1 | U99: 3012.45 | V99: 3787.65 | W99: 3740.5 | X99: 3820.6 | Y99: 44405.55
B100: KALLPA GENERACION S.A. | C100: C.T. KALLPA | D100: TG2 | E100: TERMOELÉCTRICA | F100: 4487 | G100: 4970.8 | H100: 4953.95 | I100: 4964.35 | J100: 4651.2 | K100: 4138.7 | L100: 3307.2 | M100: 4291.4 | N100: 3716.35 | O100: 4847.4 | P100: 4693.9 | Q100: 3699.05 | R100: 4834.4 | S100: 4465.25 | T100: 3616.15 | U100: 3037.45 | V100: 4049.65 | W100: 3838.6 | X100: 3887.25 | Y100: 80450.05
B101: KALLPA GENERACION S.A. | C101: C.T. KALLPA | D101: TG3 | E101: TERMOELÉCTRICA | F101: 4522.8 | G101: 5028.9 | H101: 5029.6 | I101: 5032.7 | J101: 4688.3 | K101: 4173 | L101: 3330.5 | M101: 4311.75 | N101: 3724.5 | O101: 4892.15 | P101: 4720.3 | Q101: 3722.45 | R101: 4872.3 | S101: 4476.65 | T101: 3618.15 | U101: 3034.9 | V101: 4074.9 | W101: 3844.1 | X101: 3897.1 | Y101: 80995.05
B102: KALLPA GENERACION S.A. | C102: C.T. KALLPA | D102: TV | E102: TERMOELÉCTRICA | F102: 4469.85 | G102: 4798.1 | H102: 4775.35 | I102: 4785.6 | J102: 4590.9 | K102: 4221.8 | L102: 3696.45 | M102: 4340.85 | N102: 5965.6 | O102: 6825.05 | P102: 6708.55 | Q102: 5843 | R102: 6824.65 | S102: 6570.4 | T102: 5827.85 | U102: 5320.45 | V102: 6210.6 | W102: 6063.7 | X102: 6102.5 | Y102: 103941.25
B103: KALLPA GENERACION S.A. | C103: C.T. LAS FLORES | D103: TG1 | E103: TERMOELÉCTRICA | F103: 4743.85 | Y103: 4743.85
...

Sheet G_AREAS
B3: jueves, 19 de Junio del 2025
B5: HORA | C5: RESUMEN DE GENERACIÓN POR ÁREAS DEL SEIN | D5: RESUMEN DE GENERACIÓN POR ÁREAS DEL SEIN | E5: RESUMEN DE GENERACIÓN POR ÁREAS DEL SEIN | F5: RESUMEN DE GENERACIÓN POR ÁREAS DEL SEIN | G5: RESUMEN DE GENERACIÓN POR ÁREAS DEL SEIN | H5: RESUMEN DE GENERACIÓN POR ÁREAS DEL SEIN | I5: RESUMEN DE GENERACIÓN POR ÁREAS DEL SEIN | J5: RESUMEN DE GENERACIÓN POR ÁREAS DEL SEIN | K5: RESUMEN DE GENERACIÓN POR ÁREAS DEL SEIN | L5: RESUMEN DE GENERACIÓN POR ÁREAS DEL SEIN | M5: RESUMEN DE GENERACIÓN POR ÁREAS DEL SEIN | N5: RESUMEN DE GENERACIÓN POR ÁREAS DEL SEIN | O5: RESUMEN DE GENERACIÓN POR ÁREAS DEL SEIN | P5: RESUMEN DE GENERACIÓN POR ÁREAS DEL SEIN | Q5: RESUMEN DE GENERACIÓN POR ÁREAS DEL SEIN | R5: RESUMEN DE GENERACIÓN POR ÁREAS DEL SEIN | S5: HORA | T5: GENERACIÓN POR TIPO DE GENERACIÓN | U5: GENERACIÓN POR TIPO DE GENERACIÓN | V5: GENERACIÓN POR TIPO DE GENERACIÓN | W5: GENERACIÓN POR TIPO DE GENERACIÓN | X5: GENERACIÓN POR TIPO DE GENERACIÓN | Y5: HORA | Z5: GENERACIÓN POR TIPO DE GENERACIÓN | AA5: GENERACIÓN POR TIPO DE GENERACIÓN | AB5: GENERACIÓN POR TIPO DE GENERACIÓN | AC5: GENERACIÓN POR TIPO DE GENERACIÓN | AD5: GENERACIÓN POR TIPO DE GENERACIÓN
C6: NORTE | D6: NORTE | E6: NORTE | F6: NORTE | G6: CENTRO | H6: CENTRO | I6: CENTRO | J6: CENTRO | K6: SUR | L6: SUR | M6: SUR | N6: SUR | O6: GENERACIÓN INTEGRANTES COES | P6: GENERACIÓN INTEGRANTES COES | Q6: GENERACIÓN INTEGRANTES COES | R6: GENERACIÓN INTEGRANTES COES | T6: INTEGRANTES COES | U6: INTEGRANTES COES | V6: INTEGRANTES COES | W6: INTEGRANTES COES | X6: INTEGRANTES COES | Z6: INTEGRANTES COES RER | AA6: INTEGRANTES COES RER | AB6: INTEGRANTES COES RER | AC6: INTEGRANTES COES RER | AD6: INTEGRANTES COES RER
C7: GENERACIÓN HIDROELÉCTRICA NORTE | D7: GENERACIÓN TERMOELÉCTRICA NORTE | E7: GENERACIÓN SOLAR NORTE | F7: GENERACIÓN EÓLICA NORTE | G7: GENERACIÓN HIDROELÉCTRICA CENTRO | H7: GENERACIÓN TERMOELÉCTRICA CENTRO | I7: GENERACIÓN SOLAR CENTRO | J7: GENERACIÓN EÓLICA CENTRO | K7: GENERACIÓN HIDROELÉCTRICA SUR | L7: GENERACIÓN TERMOELÉCTRICA SUR | M7: GENERACIÓN SOLAR SUR | N7: GENERACIÓN EÓLICA SUR | O7: GENERACIÓN COES NORTE | P7: GENERACIÓN COES CENTRO | Q7: GENERACIÓN COES SUR | R7: TOTAL GENERACION | T7: HIDROELÉCTRICA | U7: TERMOELÉCTRICA | V7: SOLAR | W7: EÓLICA | X7: TOTAL GENERACION | Z7: HIDROELÉCTRICA RER | AA7: TERMOELÉCTRICA RER | AB7: SOLAR RER | AC7: EÓLICA RER | AD7: TOTAL RER
B8: 00:30 | C8: 287.5 | D8: 72.9 | E8: 0 | F8: 67.6 | G8: 2772.5 | H8: 2055.6 | I8: 0 | J8: 631.8 | K8: 546.68 | L8: 0 | M8: 0 | N8: 0 | O8: 428 | P8: 5459.9 | Q8: 546.68 | R8: 6434.58 | S8: 00:30 | T8: 3606.68 | U8: 2128.5 | V8: 0 | W8: 699.4 | X8: 6434.58 | Y8: 00:30 | Z8: 280.8 | AA8: 43.8 | AB8: 0 | AC8: 699.4 | AD8: 1024
B9: 01:00 | C9: 290.2 | D9: 73.7 | E9: 0 | F9: 78 | G9: 2806.1 | H9: 1882.1 | I9: 0 | J9: 624.4 | K9: 538.87 | L9: 0 | M9: 0 | N9: 0 | O9: 441.9 | P9: 5312.6 | Q9: 538.87 | R9: 6293.37 | S9: 01:00 | T9: 3635.17 | U9: 1955.8 | V9: 0 | W9: 702.4 | X9: 6293.37 | Y9: 01:00 | Z9: 281.4 | AA9: 44 | AB9: 0 | AC9: 702.4 | AD9: 1027.8
B10: 01:30 | C10: 273.1 | D10: 74.4 | E10: 0 | F10: 74.8 | G10: 2766 | H10: 1771.4 | I10: 0 | J10: 654.7 | K10: 520.64 | L10: 0 | M10: 0 | N10: 0 | O10: 422.3 | P10: 5192.1 | Q10: 520.64 | R10: 6135.04 | S10: 01:30 | T10: 3559.74 | U10: 1845.8 | V10: 0 | W10: 729.5 | X10: 6135.04 | Y10: 01:30 | Z10: 280.2 | AA10: 44.8 | AB10: 0 | AC10: 729.5 | AD10: 1054.5
B11: 02:00 | C11: 273.7 | D11: 74.7 | E11: 0 | F11: 65.5 | G11: 2791.7 | H11: 1800.3 | I11: 0 | J11: 638 | K11: 531.83 | L11: 0 | M11: 0 | N11: 0 | O11: 413.9 | P11: 5230 | Q11: 531.83 | R11: 6175.73 | S11: 02:00 | T11: 3597.23 | U11: 1875 | V11: 0 | W11: 703.5 | X11: 6175.73 | Y11: 02:00 | Z11: 280.7 | AA11: 44.4 | AB11: 0 | AC11: 703.5 | AD11: 1028.6
B12: 02:30 | C12: 280.9 | D12: 74.1 | E12: 0 | F12: 64.6 | G12: 2721.2 | H12: 1724.4 | I12: 0 | J12: 643.3 | K12: 537.49 | L12: 0 | M12: 0 | N12: 0 | O12: 419.6 | P12: 5088.9 | Q12: 537.49 | R12: 6045.99 | S12: 02:30 | T12: 3539.59 | U12: 1798.5 | V12: 0 | W12: 707.9 | X12: 6045.99 | Y12: 02:30 | Z12: 277.4 | AA12: 43.6 | AB12: 0 | AC12: 707.9 | AD12: 1028.9
B13: 03:00 | C13: 276.1 | D13: 74.7 | E13: 0 | F13: 63.3 | G13: 2708.3 | H13: 1838.9 | I13: 0 | J13: 621.4 | K13: 466 | L13: 0 | M13: 0 | N13: 0 | O13: 414.1 | P13: 5168.6 | Q13: 466 | R13: 6048.7 | S13: 03:00 | T13: 3450.4 | U13: 1913.6 | V13: 0 | W13: 684.7 | X13: 6048.7 | Y13: 03:00 | Z13: 274.3 | AA13: 45.2 | AB13: 0 | AC13: 684.7 | AD13: 1004.2
B14: 03:30 | C14: 283.7 | D14: 74.7 | E14: 0 | F14: 58.1 | G14: 2816.3 | H14: 1759.5 | I14: 0 | J14: 676.8 | K14: 490.61 | L14: 0 | M14: 0 | N14: 0 | O14: 416.5 | P14: 5252.6 | Q14: 490.61 | R14: 6159.71 | S14: 03:30 | T14: 3590.61 | U14: 1834.2 | V14: 0 | W14: 734.9 | X14: 6159.71 | Y14: 03:30 | Z14: 275.6 | AA14: 45 | AB14: 0 | AC14: 734.9 | AD14: 1055.5
B15: 04:00 | C15: 288.8 | D15: 75.4 | E15: 0 | F15: 60.2 | G15: 2786.9 | H15: 1710.8 | I15: 0 | J15: 705.8 | K15: 488.89 | L15: 0 | M15: 0 | N15: 0 | O15: 424.4 | P15: 5203.5 | Q15: 488.89 | R15: 6116.79 | S15: 04:00 | T15: 3564.59 | U15: 1786.2 | V15: 0 | W15: 766 | X15: 6116.79 | Y15: 04:00 | Z15: 272.3 | AA15: 45.4 | AB15: 0 | AC15: 766 | AD15: 1083.7
B16: 04:30 | C16: 289.6 | D16: 75.6 | E16: 0 | F16: 54.3 | G16: 2879 | H16: 1711.3 | I16: 0 | J16: 652.1 | K16: 483.22 | L16: 0 | M16: 0 | N16: 0 | O16: 419.5 | P16: 5242.4 | Q16: 483.22 | R16: 6145.12 | S16: 04:30 | T16: 3651.82 | U16: 1786.9 | V16: 0 | W16: 706.4 | X16: 6145.12 | Y16: 04:30 | Z16: 272 | AA16: 45.5 | AB16: 0 | AC16: 706.4 | AD16: 1023.9
B17: 05:00 | C17: 286.1 | D17: 75.7 | E17: 0 | F17: 56.7 | G17: 2863 | H17: 1713.9 | I17: 0 | J17: 682.7 | K17: 472.07 | L17: 0 | M17: 0 | N17: 0 | O17: 418.5 | P17: 5259.6 | Q17: 472.07 | R17: 6150.17 | S17: 05:00 | T17: 3621.17 | U17: 1789.6 | V17: 0 | W17: 739.4 | X17: 6150.17 | Y17: 05:00 | Z17: 270.1 | AA17: 46 | AB17: 0 | AC17: 739.4 | AD17: 1055.5
B18: 05:30 | C18: 289.6 | D18: 74.9 | E18: 0 | F18: 61.8 | G18: 2933.7 | H18: 1734.9 | I18: 0 | J18: 641.9 | K18: 482.36 | L18: 0 | M18: 0 | N18: 0 | O18: 426.3 | P18: 5310.5 | Q18: 482.36 | R18: 6219.16 | S18: 05:30 | T18: 3705.66 | U18: 1809.8 | V18: 0 | W18: 703.7 | X18: 6219.16 | Y18: 05:30 | Z18: 269.6 | AA18: 44.6 | AB18: 0 | AC18: 703.7 | AD18: 1017.9
B19: 06:00 | C19: 286.4 | D19: 77.2 | E19: 0 | F19: 62.8 | G19: 3048.3 | H19: 1913.8 | I19: 0 | J19: 586.2 | K19: 479.48 | L19: 0 | M19: 0.1 | N19: 0 | O19: 426.4 | P19: 5548.3 | Q19: 479.58 | R19: 6454.28 | S19: 06:00 | T19: 3814.18 | U19: 1991 | V19: 0.1 | W19: 649 | X19: 6454.28 | Y19: 06:00 | Z19: 269.9 | AA19: 45.8 | AB19: 0.1 | AC19: 649 | AD19: 964.8
... B56: TOTAL MWh | C56: 7844.65 | D56: 2590.4 | E56: 1.45 | F56: 1446.1 | G56: 71701.95 | H56: 52274.35 | I56: 7.95 | J56: 11847.45 | K56: 13723.14 | L56: 459.225 | M56: 5012.2 | N56: 0 | O56: 11882.6 | P56: 135831.7 | Q56: 19194.565 | R56: 166908.86 | S56: TOTAL MWh | T56: 93269.74 | U56: 55323.975 | V56: 5021.6 | W56: 13293.55 | X56: 166908.86 | Y56: TOTAL MWh | Z56: 6369.05 | AA56: 1047.9 | AB56: 5021.6 | AC56: 13293.55 | AD56: 25732.1

Sheet HOP
B3: jueves, 19 de Junio del 2025
B5: Reporte de Horas de Operación
B6: Empresa | C6: Central | D6: Grupo | E6: Modo de Operación | F6: Inicio | G6: Final | H6: O. Arranque | I6: O. Parada | J6: Tipo Operación | K6: Ensayo de Potencia Efectiva | L6: Ensayo de Potencia Mínima | M6: Sistema | N6: Lim. Transm. | O6: Causa | P6: Observación
B7: AGRO INDUSTRIAL PARAMONGA S.A. | C7: C.T. PARAMONGA | D7: CENTRAL | E7: PARAMONGA - BAGAZO | F7: 19/06/2025 00:00:00 | G7: 20/06/2025 00:00:00 | J7: POR COGENERACION | O7: ...
B8: AGROINDUSTRIAS SAN JACINTO S.A.A. | C8: C.T. SAN JACINTO | D8: CENTRAL | E8: SAN_JACINTO - BAGAZO | F8: 19/06/2025 00:00:00 | G8: 20/06/2025 00:00:00 | J8: POR COGENERACION | O8: ...
B9: BIOENERGIA DEL CHIRA S.A. | C9: C.T. CAÑA BRAVA | D9: G-1 | E9: CANA BRAVA TV1 - BAGAZO | F9: 19/06/2025 00:00:00 | G9: 20/06/2025 00:00:00 | J9: POR COGENERACION | O9: ...
B10: EGASA | C10: C.T. CHILINA DIESEL | D10: SLZ1 | E10: CHILINA SULZ 12 - D2 | F10: 19/06/2025 08:48:00 | G10: 19/06/2025 09:53:00 | J10: POR PRUEBAS | O10: ...
B11: EGESUR | C11: C.T. INDEPENDENCIA | D11: INDEP_G4 | E11: INDEPENDENCIA GAS | F11: 19/06/2025 10:11:00 | G11: 19/06/2025 11:00:00 | H11: 19/06/2025 10:10:00 | J11: POR PRUEBAS | O11: ...
B12: EGESUR | C12: C.T. INDEPENDENCIA | D12: CENTRAL | E12: INDEPENDENCIA GAS | F12: 19/06/2025 10:48:00 | G12: 19/06/2025 23:58:00 | H12: 19/06/2025 10:43:00 | J12: POR POTENCIA O ENERGIA | O12: ...
B13: EGESUR | C13: C.T. INDEPENDENCIA | D13: INDEP_G3 | E13: INDEPENDENCIA GAS | F13: 19/06/2025 11:03:00 | G13: 19/06/2025 11:29:00 | J13: POR PRUEBAS | O13: ...
B14: EGESUR | C14: C.T. INDEPENDENCIA | D14: INDEP_G2 | E14: INDEPENDENCIA GAS | F14: 19/06/2025 11:30:00 | G14: 19/06/2025 11:50:00 | J14: POR PRUEBAS | O14: ...
B15: EGESUR | C15: C.T. INDEPENDENCIA | D15: INDEP_G1 | E15: INDEPENDENCIA GAS | F15: 19/06/2025 11:51:00 | G15: 19/06/2025 12:21:00 | J15: POR PRUEBAS | O15: ...
B16: ENEL GENERACION PIURA S.A. | C16: C.T. MALACAS 1 | D16: CENTRAL | E16: MALACAS1 TG6 - GAS | F16: 19/06/2025 07:47:00 | G16: 20/06/2025 00:00:00 | H16: 19/06/2025 07:32:00 | J16: POR POTENCIA O ENERGIA | O16: ...
B17: ENGIE | C17: C.T. CHILCA 1 | D17: CENTRAL | E17: CHILCA1 CCOMB TG1 - GAS | F17: 19/06/2025 00:00:00 | G17: 19/06/2025 10:24:00 | J17: A MINIMA CARGA | O17: ...
B18: ENGIE | C18: C.T. CHILCA 1 | D18: TG2 | E18: CHILCA1 TG2 - GAS | F18: 19/06/2025 09:22:00 | G18: 19/06/2025 10:24:00 | H18: 19/06/2025 09:11:00 | J18: A MINIMA CARGA | O18: ... | P18: proceso de acople en modo 2x1
B19: ENGIE | C19: C.T. CHILCA 1 | D19: CENTRAL | E19: CHILCA1 CCOMB TG1 - GAS | F19: 19/06/2025 10:24:00 | G19: 19/06/2025 11:29:00 | J19: POR POTENCIA O ENERGIA | O19: ...
B20: ENGIE | C20: C.T. CHILCA 1 | D20: TG2 | E20: CHILCA1 TG2 - GAS | F20: 19/06/2025 10:24:00 | G20: 19/06/2025 11:29:00 | J20: POR POTENCIA O ENERGIA | O20: ... | P20: proceso de acople en modo 2x1
B21: ENGIE | C21: C.T. CHILCA 1 | D21: CENTRAL | E21: CHILCA1 CCOMB TG1 & TG2 - GAS | F21: 19/06/2025 11:29:00 | G21: 20/06/2025 00:00:00 | J21: POR POTENCIA O ENERGIA | O21: ...
B22: ENGIE | C22: C.T. CHILCA 1 | D22: TG3 | E22: CHILCA1 TG3 - GAS | F22: 19/06/2025 21:30:00 | G22: 20/06/2025 00:00:00 | H22: 19/06/2025 21:09:00 | J22: POR POTENCIA O ENERGIA | O22: ...
B23: ENGIE | C23: C.T. NEPI | D23: TG43 | E23: CTNEPI TG43 - D2 | F23: 19/06/2025 17:20:00 | G23: 19/06/2025 20:06:00 | H23: 19/06/2025 17:01:00 | I23: 19/06/2025 19:43:00 | J23: POR PRUEBAS ALEATORIAS PR-25 | O23: ... | P23: A las 17:43 h, alcanzó su máxima generación
B24: FENIX POWER PERÚ | C24: C.T. FENIX | D24: CENTRAL | E24: FENIX CCOMB GT11 & GT12 - GAS | F24: 19/06/2025 00:00:00 | G24: 20/06/2025 00:00:00 | J24: POR POTENCIA O ENERGIA | O24: ...
B25: GM OPERACIONES S.A.C. | C25: CT REFINERIA TALARA | D25: TV1 REF TALARA | E25: REF_TALARA TV1 - NLH_RFG | F25: 19/06/2025 00:00:00 | G25: 20/06/2025 00:00:00 | J25: POR COGENERACION | O25: ...
B26: GM OPERACIONES S.A.C. | C26: CT REFINERIA TALARA | D26: TV2 REF TALARA | E26: REF_TALARA TV2 - NLH_RFG | F26: 19/06/2025 00:00:00 | G26: 20/06/2025 00:00:00 | J26: POR COGENERACION | O26: ...
B27: INFRAESTRUCTURAS Y ENERGIAS DEL PERU S.A.C. | C27: C.T. RF PUCALLPA | D27: CENTRAL | E27: RF PUCALLPA - D2 | F27: 19/06/2025 07:38:00 | G27: 19/06/2025 15:33:00 | H27: 19/06/2025 07:35:00 | I27: 19/06/2025 15:29:00 | J27: POR SEGURIDAD | O27: ... | P27: A las 07:38 sincronizó a mínima generación.
B28: KALLPA GENERACION S.A. | C28: C.T. KALLPA | D28: CENTRAL | E28: KALLPA CCOMB TG1 & TG2 & TG3 - GAS | F28: 19/06/2025 00:00:00 | G28: 19/06/2025 00:45:00 | J28: POR POTENCIA O ENERGIA | O28: ...
B29: KALLPA GENERACION S.A. | C29: C.T. KALLPA | D29: CENTRAL | E29: KALLPA CCOMB TG1 & TG2 & TG3 - GAS | F29: 19/06/2025 00:45:00 | G29: 19/06/2025 07:47:00 | J29: POR RSF | O29: ...
B30: KALLPA GENERACION S.A. | C30: C.T. KALLPA | D30: CENTRAL | E30: KALLPA CCOMB TG1 & TG2 & TG3 - GAS | F30: 19/06/2025 07:47:00 | G30: 20/06/2025 00:00:00 | J30: POR POTENCIA O ENERGIA | O30: ...
B31: ORYGEN PERU S.A.A. | C31: C.T. VENTANILLA | D31: CENTRAL | E31: VENTANILLA CCOMB TG3 & TG4 - GAS | F31: 19/06/2025 00:00:00 | G31: 19/06/2025 01:17:00 | J31: POR POTENCIA O ENERGIA | O31: ...
B32: ORYGEN PERU S.A.A. | C32: C.T. VENTANILLA | D32: CENTRAL | E32: VENTANILLA CCOMB TG3 & TG4 - GAS | F32: 19/06/2025 01:17:00 | G32: 19/06/2025 05:35:00 | J32: A MINIMA CARGA | O32: ...
B33: ORYGEN PERU S.A.A. | C33: C.T. VENTANILLA | D33: CENTRAL | E33: VENTANILLA CCOMB TG3 & TG4 - GAS | F33: 19/06/2025 05:35:00 | G33: 20/06/2025 00:00:00 | J33: POR POTENCIA O ENERGIA | O33: ...
B34: PETRAMAS | C34: C.T. HUAYCOLORO | D34: CENTRAL | E34: HUAYCOLORO - BIOGAS | F34: 19/06/2025 00:00:00 | G34: 20/06/2025 00:00:00 | J34: POR POTENCIA O ENERGIA | O34: ...
B35: PETRAMAS | C35: C.T. LA GRINGA | D35: G1 | E35: LA GRINGA V - BIOGAS | F35: 19/06/2025 00:00:00 | G35: 19/06/2025 08:14:00 | I35: 19/06/2025 08:02:00 | J35: POR POTENCIA O ENERGIA | O35: ...
B36: PETRAMAS | C36: C.T. LA GRINGA | D36: CENTRAL | E36: LA GRINGA V - BIOGAS | F36: 19/06/2025 16:52:00 | G36: 20/06/2025 00:00:00 | H36: 19/06/2025 16:48:00 | J36: POR POTENCIA O ENERGIA | O36: ...
B37: PETRAMAS | C37: C.T.B DOÑA CATALINA | D37: CENTRAL | E37: DONA CATALINA - BIOGAS | F37: 19/06/2025 00:00:00 | G37: 20/06/2025 00:00:00 | J37: POR POTENCIA O ENERGIA | O37: ...
B38: PETRAMAS | C38: C.T.B. CALLAO | D38: CENTRAL | E38: CALLAO - BIOGAS | F38: 19/06/2025 00:00:00 | G38: 20/06/2025 00:00:00 | I38: 19/06/2025 08:02:00 | J38: POR POTENCIA O ENERGIA | O38: ...
B39: TERMOSELVA | C39: C.T. AGUAYTIA | D39: TG1 | E39: AGUAYTIA TG1 - GAS | F39: 19/06/2025 00:00:00 | G39: 19/06/2025 10:24:00 | J39: A MINIMA CARGA | O39: ...
B40: TERMOSELVA | C40: C.T. AGUAYTIA | D40: TG1 | E40: AGUAYTIA TG1 - GAS | F40: 19/06/2025 10:24:00 | G40: 19/06/2025 15:35:00 | I40: 19/06/2025 15:31:00 | J40: POR POTENCIA O ENERGIA | O40: ... | P40: A mínima generación por restricción de gas.

Sheet INDISP
B3: jueves, 19 de Junio del 2025
B5: Hora Inicio y Fin de Indisponibilidades de las Unidades de Generación SEIN
B6: Empresa | C6: Ubicación | D6: Equipo | E6: Inicio | F6: Final | G6: Descripción | H6: MW Indisp. | I6: Prog. | J6: Dispon | K6: Interrupc. | L6: Tipo | M6: CodEq | N6: TipoEq_Osinerg
B7: AGROAURORA S.A.C. | C7: MAPLE ETANOL | D7: CENTRAL | E7: 19/06/2025 00:00 | F7: 20/06/2025 00:00 | G7: CENTRAL TERMOELECTRICA FUERA DE SERVICIO POR FALTA DE MATERIA PRIMA PARA LOS REQUERIMIENTOS DE CALOR ÚTIL EN FÁBRICA. | H7: 17 | I7: P | J7: F/S | K7: N | L7: OTROS | M7: 13417 | N7: G
B8: EGASA | C8: CHARCANI VI | D8: G1 | E8: 19/06/2025 00:00 | F8: 20/06/2025 00:00 | G8: Mantenimiento Generador | H8: 8.9 | I8: P | J8: F/S | K8: N | L8: PREV. | M8: 188 | N8: G
B9: EGASA | C9: CHILINA D | D9: SLZ1 | E9: 19/06/2025 08:10 | F9: 19/06/2025 10:55 | G9: Mantenimiento Semestral | H9: 5.1 | I9: P | J9: F/S | K9: N | L9: PREV. | M9: 136 | N9: G
B10: ELECTROPERU | C10: MANTARO | D10: G5 | E10: 19/06/2025 00:00 | F10: 20/06/2025 00:00 | G10: MANTENIMIENTO CORRECTIVO POR INCREMENTO EN LAS VIBRACIONES DEL COJINETE COMBINADO SUPERIOR. CAMBIO RODETE, AJUSTE COJINETE GUÍA TURBINA.ADICIONALMENTE SE REALIZARÁ MANTENIMIENTO PREVENTIVO Y CONTROLES SISTEMÁTICOS. | H10: 100 | I10: P | J10: F/S | K10: N | L10: CORR. | M10: 5 | N10: G
B11: EMPRESA DE GENERACION HUANZA | C11: HUANZA | D11: 1GER | E11: 19/06/2025 00:00 | F11: 20/06/2025 00:00 | G11: CAMBIO DE VÁLVULA ESFERICA EN GRUPO G1 | H11: 47 | I11: P | J11: F/S | K11: N | L11: PREV. | M11: 14006 | N11: G
B12: ENGIE | C12: RESERVA FRIA PLANTA ILO | D12: TG3 | E12: 19/06/2025 00:00 | F12: 20/06/2025 00:00 | G12: TG3 - MANTENIMIENTO ANUAL | H12: 170 | I12: P | J12: F/S | K12: N | L12: PREV. | M12: 13551 | N12: G
B13: ENGIE | C13: YUNCÁN | D13: G2 | E13: 19/06/2025 00:00 | F13: 20/06/2025 00:00 | G13: MANTENIMIENTO CORRECTIVO DEL GENERADOR | H13: 45.5 | I13: P | J13: F/S | K13: N | L13: CORR. | M13: 200 | N13: G
B14: GENERACIÓN ANDINA S.A.C. | C14: EL CARMEN (CH) | D14: G1 | E14: 19/06/2025 08:00 | F14: 20/06/2025 00:00 | G14: MANTENIMIENTO ANUAL DE TURBINA G1 (INSPECCIÓN DE RODETE, INYECTORES). | H14: 4.27 | I14: P | J14: F/S | K14: N | L14: PREV. | M14: 20590 | N14: G
B15: GENERACIÓN ANDINA S.A.C. | C15: EL CARMEN (CH) | D15: G1 | E15: 19/06/2025 08:00 | F15: 20/06/2025 00:00 | G15: MANTENIMIENTO ANUAL Y PRUEBAS ELECTRICAS DE GENERADOR UG1. | H15: 4.27 | I15: P | J15: F/S | K15: N | L15: PREV. | M15: 20590 | N15: G
B16: GENERACIÓN ANDINA S.A.C. | C16: EL CARMEN (CH) | D16: G1 | E16: 19/06/2025 08:00 | F16: 20/06/2025 00:00 | G16: MANTENIMIENTO EQUIPOS AUXILIARES, UNIDAD DE POTENCIA HIDRAULICA, TABLEROS DE CONTROL Y PROTECCIÓN UG1. | H16: 4.27 | I16: P | J16: F/S | K16: N | L16: PREV. | M16: 20590 | N16: G
B17: KALLPA GENERACION S.A. | C17: LAS FLORES | D17: TG1 | E17: 19/06/2025 00:00 | F17: 20/06/2025 00:00 | G17: MANTTO CORRECTIVO TG – INSPECCION DE TURBINA | H17: 0 | I17: P | J17: F/S | K17: N | L17: CORR. | M17: 12726 | N17: G
B18: ORYGEN PERU S.A.A. | C18: SANTA ROSA | D18: TG7 | E18: 19/06/2025 00:00 | F18: 20/06/2025 00:00 | G18: REEMPLAZO DE BATERÍAS UNIDAD TG7 | H18: 0 | I18: P | J18: F/S | K18: N | L18: PREV. | M18: 33 | N18: G
... B26: STATKRAFT S.A | C26: MALPASO | D26: G2 | E26: 19/06/2025 00:00 | F26: 20/06/2025 00:00 | G26: CAMBIO DE NUCLEO + REBOBINADO DE GENERADOR + MANTENIMIENTO MAYOR UG2 | H26: 12.92 | I26: P | J26: F/S | K26: N | L26: PREV. | M26: 40 | N26: G

Sheet RESERVA_FRÍA
B3: 19/06/2025 | E3: EJECUTADO | L3: Jueves 19 de Junio del 2025 / SEM N° 24 | V3: EJECUTADO | AC3: Jueves 19 de Junio del 2025 / SEM N° 24 | EE3: ENERGIA RENOVABLES | GP3: COGENERACION | GY3: NO INTEGRANTES
B4: Jueves | C4: HYDROG | D4: ELECTROPERU | H4: ORAZU | J4: TER | L4: KALLPA GENERACION S.A. | T4: SHOUGESA | X4: EGM | Y4: EGESUR | AB4: EGASA | AI4: SGB | AJ4: CELEP | AK4: MINCVE | AL4: ETEN | AN4: HUALLA | AP4: LAVI | AQ4: CHIN | AS4: HUANCH | AT4: CELER | AU4: INLD | AV4: FENIX POWER PERÚ | AY4: STATKRAFT S.A | BG4: STARO | BI4: HUANZA | BJ4: ENEL GENERACION PIURA S.A. | BM4: ENGIE | CA4: IYEP | CC4: SHAQSH | CD4: ORYGEN PERU S.A.A. | CP4: SAMAY I S.A.C | CT4: TCHILC | CV4: GENERACION | CY4: SALIDAS YUPANA | DC4: FLUJO EN LINEAS | DO4: COSTOS MARGINALES | DS4: RESERVA | DX4: DEMANDA POR AREAS | EE4: ACHI | EF4: COLCA | EG4: ERSUR | EH4: GRCOR | EI4: TARU | EJ4: KONDU | EK4: PIEREN | EL4: ORAZU | EN4: SGB | EO4: AIPSA | EP4: MAJA | EQ4: EGECSA | ER4: STANA | ES4: AGUAA | ET4: RDOBLE | EU4: HIDRO | EV4: HUARA | EW4: MOQUE | EX4: PANAM | EY4: PARQU | EZ4: PE3HER | FA4: PETRAMAS | FE4: TACNA | FF4: EYSAC | FG4: AURORA | FH4: AGROIN | FI4: ANDEA | FJ4: ASLC | FK4: ATRIA | FL4: EGEJUNIN | FP4: EGERBA | FQ4: EOL | FS4: ENGIE | FX4: GENE | FZ4: GENERADORA DE ENERGÍA DEL PERÚ | GD4: PAINO | GE4: JOYAS | GF4: SARCUS | GG4: ORYGEN PERU S.A.A. | GL4: RARCUS | GM4: SINERS | GP4: ACHI | GQ4: GM OP | GS4: AIPSA | GT4: AURORA | GU4: AGROIN | GV4: SDF | GY4: UNACEM | GZ4: EOR | HA4: AYEP | HB4: ELZANA | HC4: ENOSA | HD4: SDE | HE4: SINERS | HH4: RESERVA
