Workbook

Sheet EVENTOS
B3: martes, 10 de Febrero del 2026
B5: INFORMACIÓN DE EVENTOS PRINCIPALES EN SUS INSTALACIONES
B6: TIPO DE EVENTO | C6: EMPRESA | D6: UBICACIÓN | E6: TIPO DE EQUIPO | F6: EQUIPO | G6: INICIO | H6: FINAL | I6: DESCRIPCIÓN | J6: MW INDISP. | K6: INTERRUPCIÓN (SI/NO) | L6: TENSIÓN DE FALLA (kV)
B7: FALLA | C7: ARUNTANI S.A.C. | D7: PUNO - TUCARI | E7: LINEA DE TRANSMISION | F7: L-6007 | G7: 10/02/2026 16:58:20 | H7: 10/02/2026 17:22:00 | I7: DESCONECTÓ LA LÍNEA L-6007 (PUNO – TUCARI) DE 60 KV POR FALLA | J7: 0.11 | K7: SI | L7: 60
B8: FALLA | C8: CELARIS ENERGY S.A. | D8: MANTA I | E8: GENERADOR HIDROELÉCTRICO | F8: G1 | G8: 10/02/2026 19:10:10 | H8: 10/02/2026 19:44:04 | I8: DESCONEXIÓN DEL GENERADOR G1 DE LA C.H. MANTA | K8: NO | L8: 6.3
B9: EVENTO | C9: CONELSUR LT SAC | D9: PORTILLO | E9: SUBESTACION | F9: SS.EE. | G9: 10/02/2026 07:53:00 | H9: 11/02/2026 00:00:00 | I9: DECLARACIÓN DE SITUACIÓN EXCEPCIONAL EN LA S.E. PORTILLO 60 kV | K9: NO
B10: FALLA | C10: ELECTRO DUNAS | D10: NAZCA - PUQUIO | E10: LINEA DE TRANSMISION | F10: L-6630/2 | G10: 10/02/2026 19:03:39 | H10: 10/02/2026 19:03:44 | I10: DESCONEXIÓN DE LA LÍNEA L-6630/2 (NAZCA – PUQUIO) DE 60 KV | K10: NO | L10: 60
B11: EVENTO | C11: ELECTRO ORIENTE | D11: BELAUNDE TERRY - TARAPOTO | E11: LINEA DE TRANSMISION | F11: L-1018 | G11: 10/02/2026 18:25:00 | H11: 10/02/2026 20:49:00 | I11: DECLARACIÓN DE SITUACIÓN EXCEPCIONAL EN LA LÍNEA L-1018 (BELAUNDE TERRY - TARAPOTO) DE 138 kV | K11: NO
B12: FALLA | C12: ELECTRO PUNO | D12: AZÁNGARO - ANTAUTA | E12: LINEA DE TRANSMISION | F12: L-6021 | G12: 10/02/2026 15:18:00 | H12: 10/02/2026 15:19:37 | I12: DESCONEXIÓN DE LA LINEA L-6021 (AZÁNGARO - ANTAUTA) DE 60 KV | J12: 1.85 | K12: SI | L12: 60
B13: EVENTO | C13: HIDRANDINA | D13: CARAZ - HUARAZ | E13: LINEA DE TRANSMISION | F13: L-6684 | G13: 10/02/2026 03:01:23 | H13: 10/02/2026 04:34:00 | I13: DESCONEXIÓN DE LA LÍNEA L-6684 (CARAZ - HUARAZ) DE 66 kV POR FALLA | J13: 10.87 | K13: SI
B14: FALLA | C14: HIDRANDINA | D14: CARAZ - SANTA CRUZ | E14: LINEA DE TRANSMISION | F14: L-6690 | G14: 10/02/2026 16:57:51 | H14: 10/02/2026 17:13:00 | I14: DESCONEXIÓN DE LAS LÍNEAS L-6678 (HUALLANCA - SANTA CRUZ) Y L-6690 (SANTA CRUZ - CARAZ) DE 66 KV | K14: NO | L14: 66
B15: FALLA | C15: HIDRANDINA | D15: HUALLANCA - CARAZ | E15: LINEA DE TRANSMISION | F15: L-6678 | G15: 10/02/2026 17:15:34 | H15: 10/02/2026 17:23:08 | I15: DESCONEXIÓN DE LAS LÍNEAS L-6678 (HUALLANCA - SANTA CRUZ) | K15: NO | L15: 0
B16: FALLA | C16: INVERSIONES SHAQSHA S.A.C. | D16: PARIAC | E16: GENERADOR HIDROELÉCTRICO | F16: CH3 - G1 | G16: 10/02/2026 16:13:52 | H16: 11/02/2026 00:00:00 | I16: DESCONEXIÓN DEL GENERADOR G1 DE LA C.H. 3 PARIAC | K16: NO | L16: 0.44
B17: FALLA | C17: ISA PERU | D17: CHIMBOTE 1 - HUALLANCA | E17: LINEA DE TRANSMISION | F17: L-1105 | G17: 10/02/2026 17:44:16 | H17: 10/02/2026 18:14:47 | I17: DESCONEXIÓN DE LA LÍNEA L-1105 (CHIMBOTE 1 - HUALLANCA) DE 138 KV | J17: 1.5 | K17: SI | L17: 138
B18: EVENTO | C18: RED DE ENERGIA DEL PERU S.A. | D18: CALLALLI - SANTUARIO | E18: LINEA DE TRANSMISION | F18: L-1020 | G18: 10/02/2026 14:40:08 | H18: 10/02/2026 15:21:56 | I18: DESCONEXIÓN DE LA LÍNEA L-1020 (CALLALI - SANTUARIO) DE 138 kV POR FALLA | K18: NO
B19: FALLA | C19: SAN GABAN | D19: PCH TUPURI | E19: CENTRAL HIDROELÉCTRICA | F19: CENTRAL | G19: 10/02/2026 06:48:00 | H19: 10/02/2026 07:49:00 | I19: DESCONEXIÓN DE LA C.H. TUPURI POR FALLA. | K19: NO | L19: 2.4

Sheet RESTRIC_OPE
B3: martes, 10 de Febrero del 2026
B5: RESTRICCIONES OPERATIVAS
B6: FECHA | C6: HORA INICIO | D6: HORA FINAL | E6: EMPRESA | F6: UBICACIÓN | G6: T.Eq. | H6: EQUIPO | I6: DESCRIPCIÓN
B7: 10/02/2026 | C7: 00:00 | D7: 24:00 | E7: CELEPSA | F7: C.H. EL PLATANAL | G7: CH | H7: CENTRAL | I7: De acuerdo con lo informado por CELEPSA mediante correo el dia 17.01, declaran que la CH Platanal se encontrará de pasada.
B8: 10/02/2026 | C8: 00:00 | D8: 24:00 | E8: EGASA | F8: S.E. CONVERTIDOR | G8: BARRA | H8: BARRA138KV | I8: EGASA limitó la capacidad del transformador 138 kV/33 kV a 50 MVA por deterioro del aislamiento.
B9: 10/02/2026 | C9: 00:00 | D9: 24:00 | E9: ELECTROPERU | F9: C.H. MANTARO | G9: CH | H9: CENTRAL | I9: De acuerdo con el correo del día 25.08.2025, la central tiene una limitación de potencia máxima de 650 MW por seguridad de la central.
B10: 10/02/2026 | C10: 00:00 | D10: 24:00 | E10: ENEL GENERACION PIURA S.A. | F10: C.T. MALACAS | G10: CT | H10: CENTRAL | I10: De acuerdo con la comunicación vía correo del día 24.10.2024. ENEL GENERACIÓN PIURA informa una restricción de potencia para alcanzar 105 MW en simultaneo (TG6+TGN4).
B11: 10/02/2026 | C11: 00:00 | D11: 24:00 | E11: ENEL GENERACION PIURA S.A. | F11: C.T. MALACAS | G11: GT | H11: TG4 | I11: De acuerdo a lo informado por correo electrónico el día 16.01, con la disponibilidad de aproximadamente 12 MMPCD (339.8Mm³) la unidad TG4 puede con una generación de 80 MW durante 4 horas, y a potencia mínima durante el resto de los periodos
B12: 10/02/2026 | C12: 00:00 | D12: 24:00 | E12: ENGIE ENERGIA PERU S.A.A. | F12: C.H. YUNCÁN | G12: GH | H12: G3 | I12: Según la carta N° ENG/ 198-2024 enviada por su representada, se opera de forma continua el G3 de la CH Yuncán, debido a la ejecución de mantenimientos necesarios para evitar daños en los sellos de seguridad de la válvula esférica del grupo.
B13: 10/02/2026 | C13: 00:00 | D13: 24:00 | E13: ENGIE ENERGIA PERU S.A.A. | F13: C.T. CHILCA 1 | G13: CT | H13: CENTRAL | I13: Restricción de temperatura de la C.T Chilca, ver valor en el modelo de despacho.
B14: 10/02/2026 | C14: 00:00 | D14: 24:00 | E14: ENGIE ENERGIA PERU S.A.A. | F14: C.T. CHILCA 1 | G14: CT | H14: CENTRAL | I14: Con carta ENG/971-2023, indica que no puede cumplir con las IO considerada en el PDO_17122023 dado que vulneran la seguridad de sus activos. Indican que se debe tomar TMO=168h.
B15: 10/02/2026 | C15: 00:00 | D15: 24:00 | E15: ENGIE ENERGIA PERU S.A.A. | F15: C.T. CHILCA 2 | G15: CT | H15: CENTRAL | I15: Con carta ENG/971-2023, indica que no puede cumplir con las IO considerada en el PDO_17122023 dado que vulneran la seguridad de sus activos. Indican que se debe tomar TMO=168h.
B16: 10/02/2026 | C16: 00:00 | D16: 24:00 | E16: FENIX POWER PERÚ | F16: C.T. FENIX | G16: CT | H16: CENTRAL | I16: De acuerdo con lo comunicado en el correo del día 06.05.2025, la CT Fenix cuenta con TMO de 168 hrs en todos sus modos de operación.
B17: 10/02/2026 | C17: 00:00 | D17: 24:00 | E17: KALLPA GENERACION S.A. | F17: C.H. CERRO DEL AGUILA | G17: GH | H17: G1 | I17: De acuerdo a lo informado el día 17/11 por la empresa KALLPA, el G1 tiene un TA = 15min
... B59: 10/02/2026 | C59: 00:00 | D59: 24:00 | E59: TERMOSELVA | F59: C.T. AGUAYTÍA | G59: CT | H59: CENTRAL | I59: Disponibilidad de 23.5 MMSCF para la CT Aguaytía.

Sheet MANTENIMIENTO EJECUTADOS
B3: martes, 10 de Febrero del 2026
B5: Mantenimiento Ejecutado
B6: Empresa | C6: Ubicación | D6: Equipo | E6: Inicio | F6: Final | G6: Descripción | H6: MW Indisp. | I6: Prog. | J6: Dispon | K6: Interrupc. | L6: Tipo | M6: CodEq | N6: TipoEq_Osinerg
B7: ATLANTICA TRANSMISION SUR S.A. | C7: CHILCA CTM - POROMA | D7: L-5032 | E7: 10/02/2026 07:14 | F7: 10/02/2026 16:35 | G7: Inspeccion Anual en LLTT | H7: 0 | I7: P | J7: E/S | K7: N | L7: PREV. | M7: 13652 | N7: T
B8: ATLANTICA TRANSMISION SUR S.A. | C8: CHILCA-CTM | D8: INT-5261 | E8: 10/02/2026 07:58 | F8: 10/02/2026 13:52 | G8: Mantenimiento Preventivo en Seccionador SBB-5261. Requiere Barra B 500 kV. Fuera de Servicio | H8: 0 | I8: P | J8: F/S | K8: N | L8: PREV. | M8: 13854 | N8: T
B9: ATLANTICA TRANSMISION SUR S.A. | C9: OCONA | D9: INT-5450 | E9: 10/02/2026 00:00 | F9: 11/02/2026 00:00 | G9: Interruptor INT-5450 cerrado con restriccion operativa, REB-5450 en servicio y suministrando los SS.AA. de la S.E. Oco?a. | H9: 0 | I9: P | J9: E/S | K9: N | L9: OTROS | M9: 13761 | N9: T
B10: ATLANTICA TRANSMISION SUR S.A. | C10: OCONA | D10: SE OCOÑA | E10: 10/02/2026 11:37 | F10: 10/02/2026 17:30 | G10: Inspeccion Anual en Subestacion | H10: 0 | I10: P | J10: E/S | K10: N | L10: PREV. | M10: 13741 | N10: T
B11: ATLANTICA TRANSMISION SUR S.A. | C11: POROMA | D11: INT-5371 | E11: 10/02/2026 00:00 | F11: 11/02/2026 00:00 | G11: Seccionador SBB-5371 fase T indisponible por problemas mecanicos, el seccionador permanece cerrado y bloqueado | H11: 0 | I11: P | J11: E/S | K11: N | L11: OTROS | M11: 13751 | N11: T
B12: ATLANTICA TRANSMISION SUR S.A. | C12: POROMA | D12: REB-5350 | E12: 10/02/2026 00:00 | F12: 11/02/2026 00:00 | G12: Fuera de servicio por falla en el equipo. | H12: 0 | I12: P | J12: F/S | K12: N | L12: OTROS | M12: 13771 | N12: T
B13: ATLANTICA TRANSMISION SUR S.A. | C13: POROMA - OCONA | D13: L-5034 | E13: 10/02/2026 09:28 | F13: 10/02/2026 16:50 | G13: Actividad de reparacion de pedestales para la Linea L5034. | H13: 0 | I13: P | J13: F/S | K13: N | L13: PREV. | M13: 13743 | N13: T
B14: ATN S.A. | C14: KIMAN AYLLU | D14: AUT-501 | E14: 10/02/2026 00:00 | F14: 11/02/2026 00:00 | G14: Restriccion Operativa en el circuito de control de cambiador de tap s del AUT-501 | H14: 0 | I14: P | J14: E/S | K14: N | L14: OTROS | M14: 13099 | N14: T
B15: CONELSUR LT SAC | C15: CAJAMARQUILLA | D15: BARRA A 220kV | E15: 10/02/2026 00:00 | F15: 11/02/2026 00:00 | G15: NO SE PUEDE INDISPONER LA BARRA A POR RESTRICCION OPERATIVA DEL SECCIONADOR DE BARRA B DE LA CL-2708 PROPIEDAD DE NEXA. | H15: 0 | I15: P | J15: E/S | K15: N | L15: OTROS | M15: 1103 | N15: T
B16: CONELSUR LT SAC | C16: CAJAMARQUILLA | D16: BARRA A 220kV | E16: 10/02/2026 05:00 | F16: 10/02/2026 19:00 | G16: A SOLICITUD DE NEXA POR CORRECTIVO EN CL-2708 | H16: 0 | I16: P | J16: F/S | K16: N | L16: CORR. | M16: 1103 | N16: T
B17: CONELSUR LT SAC | C17: CALLAHUANCA (CNS) | D17: S.E. | E17: 10/02/2026 00:00 | F17: 11/02/2026 00:00 | G17: RELE DIFERENCIAL DE BARRAS DE CALLAHUANCA 220KV INOPERATIVO | H17: 0 | I17: P | J17: E/S | K17: N | L17: OTROS | M17: 316 | N17: T
B18: CONELSUR LT SAC | C18: HUAMPANI | D18: CL-6040 | E18: 10/02/2026 00:00 | F18: 10/02/2026 19:46 | G18: CONEXIONADO Y PRUEBA DE COLUMNA DE MANDO. (ESTA ACTIVIDAD SOLO INDISPONE UNO DE LOS TRANSFORMADORES DE LA SSEE, RESTRINGE GENERACION) | H18: 0 | I18: P | J18: F/S | K18: N | L18: PREV. | M18: 1590 | N18: T
... B112: TRANSMANTARO | C112: YARABAMBA | D112: IN-5120 | E112: 10/02/2026 00:00 | F112: 11/02/2026 00:00 | G112: SE. YARABAMBA 500KV: INTERRRUPTOR INDISPONIBLE POR PROBLEMAS DE MANDOS. REACTOR R-31 SERA OPERADO CON EL INTERRRUPTOR IN-5116. | H112: 0 | I112: P | J112: F/S | K112: N | L112: OTROS | M112: 17437 | N112: T

Sheet INGRESO OC
A3: martes, 10 de Febrero del 2026
A5: INGRESO A OPERACIÓN COMERCIAL
A6: EMPRESA | B6: TIPO DE EQUIPO | C6: UBICACIÓN | D6: EQUIPO | E6: Fecha y hora de Ingreso a Operación Comercial

Sheet DESPACHO_EJECUTADO
B3: martes, 10 de Febrero del 2026
A5: POTENCIA ACTIVA EJECUTADA DE LAS UNIDADES DE GENERACIÓN DEL SEIN (MW) | FQ5: CENTRALES NO INTEGRANTES COES
A6: FECHA | B6: HORA | C6: 65333 | D6: 101 | E6: 102 | F6: 42667 | G6: 42668 | H6: 126 | I6: 127 | J6: 138 | K6: 139 | L6: 197 | M6: 203 | N6: 204 | O6: 230 | P6: 209 | Q6: 56677 | R6: 796 | S6: 2146 | T6: 142 | U6: 143 | V6: 125 | W6: 187 | X6: 163 | Y6: 298 | Z6: 299 | AA6: 219 | AB6: 151 | AC6: 152 | AD6: 153 | AE6: 154 | AF6: 756 | AG6: 156 | AH6: 155 | AI6: 182 | AJ6: 212 | AK6: 758 | AL6: 263 | AM6: 265 | AN6: 775 | AO6: 777 | AP6: 2154 | AQ6: 150 | AR6: 149 | AS6: 188 | AT6: 2131 | AU6: 755 | AV6: 252 | AW6: 249 | AX6: 250 | AY6: 117 | AZ6: 119 | BA6: 120 | BB6: 189 | BC6: 122 | BD6: 266 | BE6: 337 | BF6: 338 | BG6: 251 | BH6: 115 | BI6: 239 | BJ6: 288 | BK6: 240 | BL6: 241 | BM6: 242 | BN6: 191 | BO6: 194 | BP6: 196 | BQ6: 207 | BR6: 236 | BS6: 795 | BT6: 285 | BU6: 995 | BV6: 996 | BW6: 997 | BX6: 766 | BY6: 926 | BZ6: 924 | CA6: 121 | CB6: 103 | CC6: 104 | CD6: 106 | CE6: 105 | CF6: 107 | CG6: 110 | CH6: 109 | CI6: 144 | CJ6: 113 | CK6: 114 | CL6: 193 | CM6: 208 | CN6: 786 | CO6: 787 | CP6: 788 | CQ6: 789 | CR6: 248 | CS6: 2159 | CT6: 267 | CU6: 268 | CV6: 2194 | CW6: 303 | CX6: 59715 | CY6: 62255 | CZ6: 1263 | DA6: 61800 | DB6: 69125 | DC6: 216 | DD6: 198 | DE6: 70400 | DF6: 76068 | DG6: 49607 | DH6: 214 | DI6: 260 | DJ6: 2152 | DK6: 2128 | DL6: 247 | DM6: 228 | DN6: 2135 | DO6: 261 | DP6: 237 | DQ6: 253 | DR6: 770 | DS6: 235 | DT6: 238 | DU6: 2184 | DV6: 61855 | DW6: 223 | DX6: 75566 | DY6: 226 | DZ6: 201 | EA6: 258 | EB6: 259 | EC6: 257 | ED6: 256 | EE6: 2148 | EF6: 58288 | EG6: 58289 | EH6: 58839 | EI6: 58840 | EJ6: 75260 | EK6: 296 | EL6: 297 | EM6: 211 | EN6: 2175 | EO6: 2178 | EP6: 2181 | EQ6: 1262 | ER6: 63425 | ES6: 233 | ET6: 2150 | EU6: 2165 | EV6: 2161 | EW6: 61197 | EX6: 58851 | EY6: 225 | EZ6: 2201 | FA6: 2171 | FB6: 760 | FC6: 234 | FD6: 215 | FE6: 917 | FF6: 920 | FG6: 289 | FH6: 58333 | FI6: 58336 | FJ6: 213 | FK6: 232 | FL6: 2190 | FM6: 69867 | FN6: 75066 | FO6: TOTAL COES | FQ6: 221 | FR6: 222 | FS6: 224 | FT6: 2187 | FU6: 227 | FV6: 49400 | FW6: 199 | FX6: 200 | FY6: TOTAL NO COES
C7: SUR | D7: CENTRO | E7: CENTRO | F7: NORTE | G7: NORTE | H7: NORTE | I7: NORTE | J7: CENTRO | K7: CENTRO | L7: CENTRO | M7: CENTRO | N7: CENTRO | O7: CENTRO | P7: CENTRO | Q7: CENTRO | R7: CENTRO | S7: CENTRO | T7: CENTRO | U7: CENTRO | V7: CENTRO | W7: CENTRO | X7: SUR | Y7: SUR | Z7: SUR | AA7: CENTRO | AB7: SUR | AC7: SUR | AD7: SUR | AE7: SUR | AF7: SUR | AG7: SUR | AH7: SUR | AI7: SUR | AJ7: CENTRO | AK7: NORTE | AL7: NORTE | AM7: NORTE | AN7: CENTRO | AO7: CENTRO | AP7: CENTRO | AQ7: CENTRO | AR7: CENTRO | AS7: CENTRO | AT7: CENTRO | AU7: SUR | AV7: CENTRO | AW7: CENTRO | AX7: CENTRO | AY7: CENTRO | AZ7: CENTRO | BA7: CENTRO | BB7: SUR | BC7: NORTE | BD7: CENTRO | BE7: CENTRO | BF7: CENTRO | BG7: CENTRO | BH7: NORTE | BI7: NORTE | BJ7: NORTE | BK7: SUR | BL7: SUR | BM7: SUR | BN7: CENTRO | BO7: CENTRO | BP7: CENTRO | BQ7: CENTRO | BR7: CENTRO | BS7: CENTRO | BT7: CENTRO | BU7: SUR | BV7: SUR | BW7: SUR | BX7: NORTE | BY7: SUR | BZ7: CENTRO | CA7: NORTE | CB7: CENTRO | CC7: CENTRO | CD7: CENTRO | CE7: CENTRO | CF7: CENTRO | CG7: CENTRO | CH7: CENTRO | CI7: CENTRO | CJ7: CENTRO | CK7: CENTRO | CL7: CENTRO | CM7: CENTRO | CN7: SUR | CO7: SUR | CP7: SUR | CQ7: SUR | CR7: CENTRO | CS7: CENTRO | CT7: CENTRO | CU7: CENTRO | CV7: NORTE | CW7: CENTRO | CX7: CENTRO | CY7: SUR | CZ7: NORTE | DA7: NORTE | DB7: CENTRO | DC7: NORTE | DD7: NORTE | DE7: SUR | DG7: SUR | DH7: CENTRO | DI7: CENTRO | DJ7: CENTRO | DK7: NORTE | DL7: NORTE | DM7: CENTRO | DN7: CENTRO | DO7: SUR | DP7: SUR | DQ7: CENTRO | DR7: CENTRO | DS7: SUR | DT7: CENTRO | DU7: CENTRO | DV7: NORTE | DW7: CENTRO | DX7: CENTRO | DY7: CENTRO | DZ7: NORTE | EA7: CENTRO | EB7: CENTRO | EC7: NORTE | ED7: NORTE | EE7: SUR | EF7: CENTRO | EG7: CENTRO | EH7: CENTRO | EI7: CENTRO | EJ7: SUR | EK7: CENTRO | EL7: CENTRO | EM7: SUR | EN7: SUR | EO7: SUR | EP7: SUR | EQ7: NORTE | ER7: SUR | ES7: SUR | ET7: SUR | EU7: CENTRO | EV7: CENTRO | EW7: CENTRO | EX7: SUR | EY7: CENTRO | EZ7: CENTRO | FA7: CENTRO | FB7: CENTRO | FC7: SUR | FD7: NORTE | FE7: CENTRO | FF7: CENTRO | FG7: NORTE | FH7: NORTE | FI7: NORTE | FJ7: CENTRO | FK7: NORTE | FL7: NORTE | FM7: NORTE | FN7: NORTE | FQ7: NORTE | FR7: CENTRO | FS7: NORTE | FT7: NORTE | FU7: NORTE | FV7: NORTE | FW7: NORTE | FX7: NORTE
C8: HIDROELÉCTRICA | D8: HIDROELÉCTRICA | E8: HIDROELÉCTRICA | F8: TERMOELÉCTRICA | G8: TERMOELÉCTRICA | H8: HIDROELÉCTRICA | I8: HIDROELÉCTRICA | J8: TERMOELÉCTRICA | K8: TERMOELÉCTRICA | L8: TERMOELÉCTRICA | M8: TERMOELÉCTRICA | N8: TERMOELÉCTRICA | O8: TERMOELÉCTRICA | P8: TERMOELÉCTRICA | Q8: TERMOELÉCTRICA | R8: HIDROELÉCTRICA | S8: HIDROELÉCTRICA | T8: TERMOELÉCTRICA | U8: TERMOELÉCTRICA | V8: TERMOELÉCTRICA | W8: TERMOELÉCTRICA | X8: HIDROELÉCTRICA | Y8: HIDROELÉCTRICA | Z8: HIDROELÉCTRICA | AA8: TERMOELÉCTRICA | AB8: HIDROELÉCTRICA | AC8: HIDROELÉCTRICA | AD8: HIDROELÉCTRICA | AE8: HIDROELÉCTRICA | AF8: TERMOELÉCTRICA | AG8: TERMOELÉCTRICA | AH8: TERMOELÉCTRICA | AI8: HIDROELÉCTRICA | AJ8: HIDROELÉCTRICA | AK8: TERMOELÉCTRICA | AL8: TERMOELÉCTRICA | AM8: TERMOELÉCTRICA | AN8: HIDROELÉCTRICA | AO8: HIDROELÉCTRICA | AP8: HIDROELÉCTRICA | AQ8: HIDROELÉCTRICA | AR8: HIDROELÉCTRICA | AS8: HIDROELÉCTRICA | AT8: HIDROELÉCTRICA | AU8: HIDROELÉCTRICA | AV8: TERMOELÉCTRICA | AW8: TERMOELÉCTRICA | AX8: TERMOELÉCTRICA | AY8: HIDROELÉCTRICA | AZ8: HIDROELÉCTRICA | BA8: HIDROELÉCTRICA | BB8: HIDROELÉCTRICA | BC8: HIDROELÉCTRICA | BD8: HIDROELÉCTRICA | BE8: HIDROELÉCTRICA | BF8: HIDROELÉCTRICA | BG8: HIDROELÉCTRICA | BH8: TERMOELÉCTRICA | BI8: TERMOELÉCTRICA | BJ8: TERMOELÉCTRICA | BK8: TERMOELÉCTRICA | BL8: TERMOELÉCTRICA | BM8: TERMOELÉCTRICA | BN8: HIDROELÉCTRICA | BO8: TERMOELÉCTRICA | BP8: TERMOELÉCTRICA | BQ8: TERMOELÉCTRICA | BR8: TERMOELÉCTRICA | BS8: TERMOELÉCTRICA | BT8: TERMOELÉCTRICA | BU8: TERMOELÉCTRICA | BV8: TERMOELÉCTRICA | BW8: TERMOELÉCTRICA | BX8: HIDROELÉCTRICA | BY8: TERMOELÉCTRICA | BZ8: TERMOELÉCTRICA | CA8: HIDROELÉCTRICA | CB8: HIDROELÉCTRICA | CC8: HIDROELÉCTRICA | CD8: HIDROELÉCTRICA | CE8: HIDROELÉCTRICA | CF8: HIDROELÉCTRICA | CG8: TERMOELÉCTRICA | CH8: TERMOELÉCTRICA | CI8: TERMOELÉCTRICA | CJ8: TERMOELÉCTRICA | CK8: TERMOELÉCTRICA | CL8: TERMOELÉCTRICA | CM8: TERMOELÉCTRICA | CN8: TERMOELÉCTRICA | CO8: TERMOELÉCTRICA | CP8: TERMOELÉCTRICA | CQ8: TERMOELÉCTRICA | CR8: TERMOELÉCTRICA | CS8: TERMOELÉCTRICA | CT8: HIDROELÉCTRICA | CU8: HIDROELÉCTRICA | CV8: HIDROELÉCTRICA | CW8: SOLAR | CX8: EÓLICA | CY8: SOLAR | CZ8: EÓLICA | DA8: SOLAR | DB8: HIDROELÉCTRICA | DC8: HIDROELÉCTRICA | DD8: HIDROELÉCTRICA | DE8: SOLAR | DF8: SOLAR | DG8: HIDROELÉCTRICA | DH8: HIDROELÉCTRICA | DI8: HIDROELÉCTRICA | DJ8: HIDROELÉCTRICA | DK8: HIDROELÉCTRICA | DL8: HIDROELÉCTRICA | DM8: HIDROELÉCTRICA | DN8: HIDROELÉCTRICA | DO8: SOLAR | DP8: SOLAR | DQ8: EÓLICA | DR8: EÓLICA | DS8: SOLAR | DT8: HIDROELÉCTRICA | DU8: HIDROELÉCTRICA | DV8: HIDROELÉCTRICA | DW8: HIDROELÉCTRICA | DX8: SOLAR | DY8: HIDROELÉCTRICA | DZ8: HIDROELÉCTRICA | EA8: HIDROELÉCTRICA | EB8: HIDROELÉCTRICA | EC8: EÓLICA | ED8: EÓLICA | EE8: SOLAR | EF8: EÓLICA | EG8: EÓLICA | EH8: EÓLICA | EI8: EÓLICA | EJ8: SOLAR | EK8: HIDROELÉCTRICA | EL8: HIDROELÉCTRICA | EM8: HIDROELÉCTRICA | EN8: HIDROELÉCTRICA | EO8: HIDROELÉCTRICA | EP8: HIDROELÉCTRICA | EQ8: EÓLICA | ER8: SOLAR | ES8: SOLAR | ET8: SOLAR | EU8: HIDROELÉCTRICA | EV8: EÓLICA | EW8: EÓLICA | EX8: SOLAR | EY8: TERMOELÉCTRICA | EZ8: TERMOELÉCTRICA | FA8: TERMOELÉCTRICA | FB8: TERMOELÉCTRICA | FC8: SOLAR | FD8: HIDROELÉCTRICA | FE8: HIDROELÉCTRICA | FF8: HIDROELÉCTRICA | FG8: TERMOELÉCTRICA | FH8: TERMOELÉCTRICA | FI8: TERMOELÉCTRICA | FJ8: TERMOELÉCTRICA | FK8: TERMOELÉCTRICA | FL8: TERMOELÉCTRICA | FM8: TERMOELÉCTRICA | FN8: TERMOELÉCTRICA | FQ8: HIDROELÉCTRICA | FR8: HIDROELÉCTRICA | FS8: HIDROELÉCTRICA | FT8: HIDROELÉCTRICA | FU8: TERMOELÉCTRICA | FV8: TERMOELÉCTRICA | FW8: HIDROELÉCTRICA | FX8: HIDROELÉCTRICA
C9: HYDRO GLOBAL PERÚ S.A.C. | D9: ELECTROPERU | E9: ELECTROPERU | F9: ELECTROPERU | G9: ELECTROPERU | H9: ORAZUL ENERGY PERÚ | I9: ORAZUL ENERGY PERÚ | J9: TERMOSELVA | K9: TERMOSELVA | L9: KALLPA GENERACION S.A. | M9: KALLPA GENERACION S.A. | N9: KALLPA GENERACION S.A. | O9: KALLPA GENERACION S.A. | P9: KALLPA GENERACION S.A. | Q9: KALLPA GENERACION S.A. | R9: KALLPA GENERACION S.A. | S9: KALLPA GENERACION S.A. | T9: SHOUGESA | U9: SHOUGESA | V9: SHOUGESA | W9: SHOUGESA | X9: EGEMSA | Y9: EGESUR | Z9: EGESUR | AA9: EGESUR | AB9: EGASA | AC9: EGASA | AD9: EGASA | AE9: EGASA | AF9: EGASA | AG9: EGASA | AH9: EGASA | AI9: SAN GABAN | AJ9: CELEPSA | AK9: MINERA CERRO VERDE | AL9: PLANTA DE RESERVA FRIA DE GENERACION DE ETEN S.A. | AM9: PLANTA DE RESERVA FRIA DE GENERACION DE ETEN S.A. | AN9: EMPRESA DE GENERACION HUALLAGA | AO9: EMPRESA DE GENERACION HUALLAGA | AP9: LA VIRGEN | AQ9: CHINANGO S.A.C. | AR9: CHINANGO S.A.C. | AS9: HIDROELECTRICA HUANCHOR S.A.C. | AT9: CELEPSA RENOVABLES S.R.L. | AU9: INLAND ENERGY SAC | AV9: FENIX POWER PERÚ | AW9: FENIX POWER PERÚ | AX9: FENIX POWER PERÚ | AY9: STATKRAFT S.A | AZ9: STATKRAFT S.A | BA9: STATKRAFT S.A | BB9: STATKRAFT S.A | BC9: STATKRAFT S.A | BD9: STATKRAFT S.A | BE9: CENTRALES SANTA ROSA S.A.C. | BF9: CENTRALES SANTA ROSA S.A.C. | BG9: EMPRESA DE GENERACION HUANZA | BH9: ENEL GENERACION PIURA S.A. | BI9: ENEL GENERACION PIURA S.A. | BJ9: ENEL GENERACION PIURA S.A. | BK9: ENGIE ENERGIA PERU S.A.A. | BL9: ENGIE ENERGIA PERU S.A.A. | BM9: ENGIE ENERGIA PERU S.A.A. | BN9: ENGIE ENERGIA PERU S.A.A. | BO9: ENGIE ENERGIA PERU S.A.A. | BP9: ENGIE ENERGIA PERU S.A.A. | BQ9: ENGIE ENERGIA PERU S.A.A. | BR9: ENGIE ENERGIA PERU S.A.A. | BS9: ENGIE ENERGIA PERU S.A.A. | BT9: ENGIE ENERGIA PERU S.A.A. | BU9: ENGIE ENERGIA PERU S.A.A. | BV9: ENGIE ENERGIA PERU S.A.A. | BW9: ENGIE ENERGIA PERU S.A.A. | BX9: ENGIE ENERGIA PERU S.A.A. | BY9: INFRAESTRUCTURAS Y ENERGIAS DEL PERU S.A.C. | BZ9: INFRAESTRUCTURAS Y ENERGIAS DEL PERU S.A.C. | CA9: INVERSIONES SHAQSHA S.A.C. | CB9: ORYGEN PERU S.A.A. | CC9: ORYGEN PERU S.A.A. | CD9: ORYGEN PERU S.A.A. | CE9: ORYGEN PERU S.A.A. | CF9: ORYGEN PERU S.A.A. | CG9: ORYGEN PERU S.A.A. | CH9: ORYGEN PERU S.A.A. | CI9: ORYGEN PERU S.A.A. | CJ9: ORYGEN PERU S.A.A. | CK9: ORYGEN PERU S.A.A. | CL9: ORYGEN PERU S.A.A. | CM9: ORYGEN PERU S.A.A. | CN9: SAMAY I S.A.C | CO9: SAMAY I S.A.C | CP9: SAMAY I S.A.C | CQ9: SAMAY I S.A.C | CR9: TERMOCHILCA S.A.C. | CS9: TERMOCHILCA S.A.C. | CT9: TRANSMISION ANDINA DE GENERACION S.A.C. | CU9: TRANSMISION ANDINA DE GENERACION S.A.C. | CV9: CELARIS ENERGY S.A. | CW9: COLCA SOLAR S.A.C. | CX9: ENERGIA RENOVABLE DEL SUR S.A. | CY9: GR CORTARRAMA SOCIEDAD ANONIMA CERRADA | CZ9: GR TARUCA SOCIEDAD ANONIMA CERRADA | DA9: KONDU SAC | DB9: VARI ENERGIA S.A.C. | DC9: ORAZUL ENERGY PERÚ | DD9: ORAZUL ENERGY PERÚ | DE9: KALLPA GENERACION S.A. | DF9: KALLPA GENERACION S.A. | DG9: SAN GABAN | DH9: MAJA ENERGIA S.A.C. | DI9: EMPRESA DE GENERACION ELECTRICA CANCHAYLLO SAC | DJ9: EMPRESA DE GENERACION ELECTRICA SANTA ANA S.A.C. | DK9: EMPRESA ELECTRICA AGUA AZUL | DL9: EMPRESA ELECTRICA RIO DOBLE | DM9: HIDROCAÑETE S.A. | DN9: HUAURA POWER GROUP S.A. | DO9: MOQUEGUA FV S.A.C. | DP9: PANAMERICANA SOLAR SAC. | DQ9: PARQUE EOLICO MARCONA S.A.C. | DR9: PARQUE EOLICO TRES HERMANAS S.A.C. | DS9: TACNA SOLAR SAC. | DT9: ELECTRICA YANAPAMPA SAC | DU9: ANDEAN POWER S.A.C. | DV9: ASOCIACIÓN SANTA LUCIA DE CHACAS | DW9: ATRIA ENERGIA S.A.C. | DX9: COENERGY S.A.C. | DY9: EGEJUNIN | DZ9: EGEJUNIN | EA9: EGEJUNIN | EB9: EGEJUNIN | EC9: ENERGÍA EÓLICA S.A. | ED9: ENERGÍA EÓLICA S.A. | EE9: ENGIE ENERGIA PERU S.A.A. | EF9: ENGIE ENERGIA PERU S.A.A. | EG9: ENGIE ENERGIA PERU S.A.A. | EH9: ENGIE ENERGIA PERU S.A.A. | EI9: ENGIE ENERGIA PERU S.A.A. | EJ9: ENGIE ENERGIA PERU S.A.A. | EK9: GENERACIÓN ANDINA S.A.C. | EL9: GENERACIÓN ANDINA S.A.C. | EM9: GENERADORA DE ENERGÍA DEL PERÚ | EN9: GENERADORA DE ENERGÍA DEL PERÚ | EO9: GENERADORA DE ENERGÍA DEL PERÚ | EP9: GENERADORA DE ENERGÍA DEL PERÚ | EQ9: GR PAINO SOCIEDAD ANONIMA CERRADA | ER9: JOYA SOLAR S.A.C. | ES9: MAJES ARCUS S.A.C. | ET9: ORYGEN PERU S.A.A. | EU9: ORYGEN PERU S.A.A. | EV9: ORYGEN PERU S.A.A. | EW9: ORYGEN PERU S.A.A. | EX9: ORYGEN PERU S.A.A. | EY9: PETRAMAS | EZ9: PETRAMAS | FA9: PETRAMAS | FB9: PETRAMAS | FC9: REPARTICIÓN ARCUS S.A.C. | FD9: SINERSA | FE9: SINERSA | FF9: SINERSA | FG9: BIOENERGIA DEL CHIRA S.A. | FH9: GM OPERACIONES S.A.C. | FI9: GM OPERACIONES S.A.C. | FJ9: AGRO INDUSTRIAL PARAMONGA S.A. | FK9: AGROAURORA S.A.C. | FL9: AGROINDUSTRIAS SAN JACINTO S.A.A. | FM9: AGROLMOS SOCIEDAD ANONIMA - AGROLMOS S.A. | FN9: CASA GRANDE S.A.A. | FQ9: UNACEM PERU S.A. | FR9: ELECTRO ORIENTE | FS9: AGUAS Y ENERGIA PERU | FT9: ELECTRO ZAÑA S.A.C. | FU9: ELECTRONOROESTE S.A. | FV9: SDE PIURA | FW9: SINERSA | FX9: SINERSA
C10: SAN GABAN III | D10: MANTARO | E10: RESTITUCION | F10: TUMBES MAK 1 | G10: TUMBES MAK 2 | H10: CARHUAQUERO | I10: CAÑON DEL PATO | J10: AGUAYTIA TG1 | K10: AGUAYTIA TG2 | L10: KALLPA TG1 | M10: KALLPA TG2 | N10: KALLPA TG3 | O10: KALLPA TV | P10: LFLORES TG1 | Q10: LFLORES TV | R10: CERRO DEL AGUILA | S10: CERRODELAGUILAG4 | T10: SHOUGESA TV1 | U10: SHOUGESA TV2 | V10: SHOUGESA TV3 | W10: SHOUGESA CUMMINS | X10: MACHUPICCHU | Y10: ARICOTA 1 | Z10: ARICOTA 2 | AA10: INDEPENDENCIA | AB10: CHARCANI I,II,III | AC10: CHARCANI IV | AD10: CHARCANI V | AE10: CHARCANI VI | AF10: CHILINA TG | AG10: MOLLENDO 1, 2, 3 | AH10: CHILINA (SULZ 1,2) | AI10: SAN GABAN II | AJ10: PLATANAL | AK10: RECKA | AL10: RF ETEN TG1 | AM10: RF ETEN TG2 | AN10: CHAGLLA GP1 | AO10: CHAGLLA | AP10: LA VIRGEN | AQ10: CHIMAY | AR10: YANANGO | AS10: HUANCHOR | AT10: MARAÑON | AU10: STA TERESA | AV10: FENIX GT11 | AW10: FENIX GT12 | AX10: FENIX TV10 | AY10: YAUPI | AZ10: MALPASO | BA10: CAHUA | BB10: ARCATA | BC10: GALLITO CIEGO | BD10: CHEVES | BE10: SANTA ROSA 1 | BF10: SANTA ROSA 2 | BG10: HUANZA | BH10: MALACAS2 TG4 | BI10: MALACAS3 TG 5 | BJ10: MALACAS1 TG6 | BK10: RF ILO2 TG1 | BL10: RF ILO2 TG2 | BM10: RF ILO2 TG3 | BN10: YUNCAN | BO10: CHILCA1 TG1 | BP10: CHILCA1 TG2 | BQ10: CHILCA1 TG3 | BR10: CHILCA-TV | BS10: CHILCA2 TG41 | BT10: CHILCA2-TV | BU10: CTNEPI_TG41 | BV10: CTNEPI_TG42 | BW10: CTNEPI_TG43 | BX10: QUITARACSA | BY10: RF PTO MALDONADO | BZ10: RF PUCALLPA | CA10: PARIAC | CB10: HUINCO | CC10: MATUCANA | CD10: MOYOPAMPA | CE10: CALLAHUANCA | CF10: HUAMPANI | CG10: STA ROSA WEST TG7 | CH10: UTI_5 | CI10: UTI_6 | CJ10: VENTANILLA 3 | CK10: VENTANILLA 4 | CL10: VENTANILLA TV | CM10: STAROSA TG8 | CN10: PTO_BRVO TG1 | CO10: PTO_BRVO TG2 | CP10: PTO_BRVO TG3 | CQ10: PTO_BRVO TG4 | CR10: OLLEROS TG1 | CS10: OLLEROS TV | CT10: OROYA | CU10: PACHACHACA | CV10: MANTA I | CW10: CS YARUCAYA | CX10: SAN JUAN | CY10: MATARANI | CZ10: DUNA | DA10: CARHUAQUERO (CS) | DB10: ANASHIRONI | DC10: CARHUAQUERO4 | DD10: CAÑA BRAVA | DE10: SUNNY | DF10: SUNNY EXPANSION | DG10: TUPURI | DH10: RONCADOR | DI10: CANCHAYLLO | DJ10: RENOVANDESH1 | DK10: POTRERO | DL10: PIZARRAS | DM10: NIMPERIAL | DN10: YARUCAYA | DO10: MOQUEGUA-SOLAR | DP10: PANAMERICANA-SOLAR | DQ10: PQE-EOLICO-MARCONA | DR10: PQE-EOLICO-3-HERMANAS | DS10: TACNA-SOLAR | DT10: YANAPAMPA | DU10: CARHUAC | DV10: HUALLIN | DW10: PURMACANA | DX10: COENERGY | DY10: HUASAHUASI | DZ10: STACRUZ_1_2 | EA10: RUNATULLO_II | EB10: RUNATULLO_III | EC10: PQE-EOLICO-TALARA | ED10: PQE-EOLICO-CUPISNIQUE | EE10: INTIPAMPA | EF10: PUNTA LOMITAS-BL1 | EG10: PUNTA LOMITAS-BL2 | EH10: PUN LOMITAS_EXP-BL1 | EI10: PUN LOMITAS_EXP-BL2 | EJ10: EXPANSIÓN INTIPAMPA | EK10: 8AGOSTO | EL10: EL CARMEN | EM10: LA JOYA | EN10: ANGEL_I | EO10: ANGEL_II | EP10: ANGEL_III | EQ10: HUAMBOS | ER10: SAN MARTIN SOLAR | ES10: MAJES | ET10: RUBI | EU10: CH_HER1 | EV10: WAYRA-I | EW10: WAYRA EXTENSION | EX10: CLEMESI | EY10: HUAYCOLORO | EZ10: CALLAO | FA10: DONA_CATALINA | FB10: LAGRINGAV | FC10: REPARTICION | FD10: POECHOS2 | FE10: CHANCAY | FF10: RUCUY | FG10: CANA BRAVA | FH10: REFINERIA TALARA TV1 | FI10: REFINERÍA TALARA TV2 | FJ10: PARAMONGA | FK10: MAPLE | FL10: SAN_JACINTO | FM10: AGROLMOS | FN10: CASA GRANDE | FO10: MW | FQ10: CARPAPATA | FR10: CENTRALES ELOR | FS10: PIAS1 | FT10: ZANA | FU10: TABLAZO | FV10: TALLANCA | FW10: CURUMUY | FX10: POECHOS1 | FY10: MW
A11: 10/02/2026 | B11: 00:30 | C11: 201.8 | D11: 637.8 | E11: 216.4 | H11: 89.2 | I11: 241.9 | L11: 141.2 | M11: 141.5 | N11: 141.3 | O11: 245.2 | P11: 205.9 | Q11: 108.7 | R11: 554.8 | S11: 10.3 | X11: 168.4 | Y11: 7.3 | Z11: 5.4 | AA11: 0 | AB11: 6.7 | AD11: 141.6 | AI11: 110.3 | AJ11: 199 | AN11: 6.5 | AO11: 459.2 | AP11: 80.4 | AQ11: 152.6 | AR11: 42.1 | AS11: 18.4 | AT11: 18.8 | AU11: 92.3 | AY11: 106.2 | AZ11: 0 | BA11: 45.7 | BB11: 4 | BC11: 32.9 | BD11: 160.4 | BG11: 0 | BJ11: 0 | BN11: 127.4 | BP11: 0 | BQ11: 0 | BS11: 38.1 | BT11: 27.6 | CA11: 2.3 | CB11: 46.8 | CC11: 101.9 | CD11: 64 | CE11: 76.6 | CF11: 26 | CJ11: 142.3 | CK11: 143.1 | CL11: 147.9 | CR11: 208.5 | CS11: 100.4 | CT11: 7 | CU11: 4.3 | CV11: 20 | CW11: 0 | CX11: 31.6 | CY11: 0 | CZ11: 0 | DA11: 0 | DB11: 20.3 | DC11: 10 | DD11: 5.5 | DE11: 0 | DG11: 2.1 | DH11: 1.8 | DI11: 5 | DJ11: 20.3 | DK11: 20 | DL11: 18.8 | DM11: 2.7 | DN11: 18.4 | DO11: 0 | DP11: 0 | DQ11: 15.2 | DR11: 29.3 | DS11: 0 | DT11: 3.5 | DU11: 6 | DV11: 2.8 | DW11: 0.4 | DX11: 0 | DY11: 19.8 | DZ11: 8 | EA11: 20.3 | EB11: 20.2 | EC11: 3.2 | ED11: 5.1 | EE11: 0 | EF11: 32.9 | EG11: 73.9 | EH11: 2.6 | EI11: 1.7 | EJ11: 0 | EK11: 21 | EL11: 6.2 | EM11: 7.2 | EN11: 20.4 | EO11: 20.4 | EP11: 20.1 | EQ11: 0.25 | ER11: 0 | ES11: 0 | ET11: 0 | EU11: 0 | EV11: 17.2 | EW11: 14.2 | EX11: 0 | EY11: 3.6 | EZ11: 1.1 | FA11: 2.4 | FB11: 0.9 | FC11: 0 | FD11: 8.4 | FE11: 20 | FF11: 20 | FG11: 9.4 | FH11: 27.6 | FI11: 34.4 | FJ11: 15 | FK11: 15.5 | FL11: 7.9 | FM11: 11.7 | FN11: 22.4 | FO11: 6807.05 | FQ11: 24.6 | FR11: 7.95 | FS11: 11.9 | FT11: 13.2 | FU11: 25.2 | FV11: 18.94327 | FW11: 12.2 | FX11: 15.7 | FY11: 129.69327
A12: 10/02/2026 | B12: 01:00 | C12: 197.4 | D12: 626.9 | E12: 213.1 | H12: 86.6 | I12: 235.9 | L12: 120.8 | M12: 120.3 | N12: 120.2 | O12: 224.2 | P12: 207 | Q12: 109.5 | R12: 549.3 | S12: 9.9 | X12: 154 | Y12: 7.1 | Z12: 5 | AA12: 0 | AB12: 6.7 | AD12: 141.4 | AI12: 108.4 | AJ12: 204.6 | AN12: 6.5 | AO12: 452.4 | AP12: 80.2 | AQ12: 149.9 | AR12: 41.7 | AS12: 18.6 | AT12: 18.8 | AU12: 88.2 | AY12: 100.3 | AZ12: 0 | BA12: 45 | BB12: 4 | BC12: 30.8 | BD12: 151.8 | BG12: 0 | BJ12: 0 | BN12: 123.1 | BP12: 0 | BQ12: 0 | BS12: 39.1 | BT12: 27.8 | CA12: 2.3 | CB12: 56.6 | CC12: 102.6 | CD12: 60.4 | CE12: 74.8 | CF12: 20.8 | CJ12: 141.3 | CK12: 142.3 | CL12: 146.4 | CR12: 208.5 | CS12: 100.5 | CT12: 6.9 | CU12: 4.4 | CV12: 20 | CW12: 0 | CX12: 32.9 | CY12: 0 | CZ12: 0 | DA12: 0 | DB12: 19.6 | DC12: 9.9 | DD12: 5.5 | DE12: 0 | DG12: 2.1 | DH12: 1.8 | DI12: 5 | DJ12: 19.9 | DK12: 20 | DL12: 18.7 | DM12: 2.7 | DN12: 18.4 | DO12: 0 | DP12: 0 | DQ12: 15.9 | DR12: 24 | DS12: 0 | DT12: 3.5 | DU12: 3.2 | DV12: 2.8 | DW12: 0.4 | DX12: 0 | DY12: 19.8 | DZ12: 8 | EA12: 19.9 | EB12: 20.1 | EC12: 2.1 | ED12: 4.2 | EE12: 0 | EF12: 19.1 | EG12: 54.2 | EH12: 1.5 | EI12: 0.8 | EJ12: 0 | EK12: 21 | EL12: 6.2 | EM12: 6.9 | EN12: 20.4 | EO12: 20.4 | EP12: 20.1 | EQ12: 0 | ER12: 0 | ES12: 0 | ET12: 0 | EU12: 0 | EV12: 14.6 | EW12: 7.4 | EX12: 0 | EY12: 3.6 | EZ12: 1.1 | FA12: 2.4 | FB12: 0.9 | FC12: 0 | FD12: 8.4 | FE12: 20 | FF12: 20 | FG12: 9.5 | FH12: 27.4 | FI12: 34.1 | FJ12: 15.1 | FK12: 17.1 | FL12: 8.3 | FM12: 11.7 | FN12: 21.7 | FO12: 6588.6 | FQ12: 24.5 | FR12: 7.96 | FS12: 12 | FT12: 13.2 | FU12: 24.8 | FV12: 18.94314 | FW12: 12 | FX12: 15.7 | FY12: 129.10314
A13: 10/02/2026 | B13: 01:30 | C13: 205.7 | D13: 639.7 | E13: 216.6 | H13: 90.6 | I13: 243.6 | L13: 131.1 | M13: 130.2 | N13: 131.3 | O13: 217.7 | P13: 205.4 | Q13: 108.7 | R13: 568.5 | S13: 10.2 | X13: 165.2 | Y13: 7.6 | Z13: 5.4 | AA13: 0 | AB13: 6.7 | AD13: 143.2 | AI13: 110.3 | AJ13: 170.7 | AN13: 6.5 | AO13: 455 | AP13: 80 | AQ13: 153.9 | AR13: 42.1 | AS13: 18.6 | AT13: 18.8 | AU13: 91.7 | AY13: 106.8 | AZ13: 0 | BA13: 46.4 | BB13: 4 | BC13: 33.9 | BD13: 84.8 | BG13: 0 | BJ13: 0 | BN13: 127.9 | BP13: 0 | BQ13: 0 | BS13: 37.6 | BT13: 27.7 | CA13: 2.3 | CB13: 67.1 | CC13: 105.5 | CD13: 62.9 | CE13: 76.4 | CF13: 30.2 | CJ13: 111 | CK13: 110.8 | CL13: 130.1 | CR13: 208.5 | CS13: 100.5 | CT13: 6.9 | CU13: 4.2 | CV13: 20 | CW13: 0 | CX13: 27.8 | CY13: 0 | CZ13: 0 | DA13: 0 | DB13: 20.4 | DC13: 9.9 | DD13: 5.3 | DE13: 0 | DG13: 2.1 | DH13: 1.8 | DI13: 5.1 | DJ13: 20.4 | DK13: 20 | DL13: 18.7 | DM13: 2.7 | DN13: 18.4 | DO13: 0 | DP13: 0 | DQ13: 14.3 | DR13: 26.3 | DS13: 0 | DT13: 3.4 | DU13: 3.4 | DV13: 2.8 | DW13: 0.4 | DX13: 0 | DY13: 19.8 | DZ13: 8.1 | EA13: 19.9 | EB13: 20.2 | EC13: 1.9 | ED13: 0.5 | EE13: 0 | EF13: 15.9 | EG13: 53.6 | EH13: 1.9 | EI13: 1 | EJ13: 0 | EK13: 21 | EL13: 6.2 | EM13: 0 | EN13: 20.4 | EO13: 20.4 | EP13: 20.1 | EQ13: 0 | ER13: 0 | ES13: 0 | ET13: 0 | EU13: 0 | EV13: 7.4 | EW13: 4.4 | EX13: 0 | EY13: 3.6 | EZ13: 1.1 | FA13: 2.4 | FB13: 0.9 | FC13: 0 | FD13: 8.3 | FE13: 20 | FF13: 20 | FG13: 9.3 | FH13: 27.7 | FI13: 34.5 | FJ13: 14.5 | FK13: 17.1 | FL13: 7.6 | FM13: 11.7 | FN13: 22.3 | FO13: 6527.4 | FQ13: 24.5 | FR13: 7.95 | FS13: 11.9 | FT13: 13.2 | FU13: 25.2 | FV13: 18.94322 | FW13: 12 | FX13: 15.6 | FY13: 129.29322
A14: 10/02/2026 | B14: 02:00 | C14: 203.9 | D14: 641.6 | E14: 217 | H14: 90.7 | I14: 242.4 | L14: 115.9 | M14: 115.7 | N14: 115.1 | O14: 219.5 | P14: 182.2 | Q14: 103.8 | R14: 561.2 | S14: 10.3 | X14: 170 | Y14: 7.7 | Z14: 5.4 | AA14: 0 | AB14: 6.7 | AD14: 142.1 | AI14: 110.5 | AJ14: 173.7 | AN14: 6.5 | AO14: 458.6 | AP14: 80.4 | AQ14: 152.8 | AR14: 42.1 | AS14: 18.6 | AT14: 18.8 | AU14: 94.2 | AY14: 107.2 | AZ14: 0 | BA14: 46.7 | BB14: 4 | BC14: 33.7 | BD14: 93.8 | BG14: 0 | BJ14: 0 | BN14: 128.7 | BP14: 0 | BQ14: 0 | BS14: 38 | BT14: 27.7 | CA14: 2.3 | CB14: 88.7 | CC14: 99.1 | CD14: 64.3 | CE14: 73.1 | CF14: 30.6 | CJ14: 103.6 | CK14: 103.5 | CL14: 121.5 | CR14: 208.6 | CS14: 100.3 | CT14: 6.9 | CU14: 4.3 | CV14: 20 | CW14: 0 | CX14: 31.1 | CY14: 0 | CZ14: 0 | DA14: 0 | DB14: 20.4 | DC14: 9.9 | DD14: 5.4 | DE14: 0 | DG14: 2.1 | DH14: 1.8 | DI14: 5.1 | DJ14: 20.7 | DK14: 20 | DL14: 18.7 | DM14: 2.8 | DN14: 18.4 | DO14: 0 | DP14: 0 | DQ14: 20.8 | DR14: 24.1 | DS14: 0 | DT14: 3.5 | DU14: 3.4 | DV14: 2.7 | DW14: 0.4 | DX14: 0 | DY14: 19.8 | DZ14: 8 | EA14: 20.1 | EB14: 20.2 | EC14: 2.9 | ED14: 0 | EE14: 0 | EF14: 11.6 | EG14: 39.6 | EH14: 0.8 | EI14: 0.3 | EJ14: 0 | EK14: 21 | EL14: 6.2 | EM14: 0 | EN14: 20.4 | EO14: 20.4 | EP14: 20.1 | EQ14: 0 | ER14: 0 | ES14: 0 | ET14: 0 | EU14: 0 | EV14: 1.5 | EW14: 1.4 | EX14: 0 | EY14: 3.6 | EZ14: 1.1 | FA14: 2.4 | FB14: 0.9 | FC14: 0 | FD14: 8.4 | FE14: 20 | FF14: 20 | FG14: 9.3 | FH14: 27.9 | FI14: 34.7 | FJ14: 14.5 | FK14: 17.1 | FL14: 8.3 | FM14: 11.7 | FN14: 22.7 | FO14: 6442.2 | FQ14: 24.6 | FR14: 7.95 | FS14: 11.8 | FT14: 13.2 | FU14: 25.3 | FV14: 18.94335 | FW14: 12 | FX14: 15.7 | FY14: 129.49335
A15: 10/02/2026 | B15: 02:30 | C15: 198.7 | D15: 631.2 | E15: 214.6 | H15: 89.3 | I15: 238.4 | L15: 140.6 | M15: 139.9 | N15: 139.2 | O15: 226.8 | P15: 108.8 | Q15: 72.4 | R15: 551.7 | S15: 9.9 | X15: 155.9 | Y15: 7.1 | Z15: 5.2 | AA15: 0 | AB15: 6.7 | AD15: 141.9 | AI15: 108.5 | AJ15: 223.5 | AN15: 6.5 | AO15: 456.6 | AP15: 79.9 | AQ15: 149.8 | AR15: 41.9 | AS15: 18.6 | AT15: 18.8 | AU15: 87.5 | AY15: 104.1 | AZ15: 0 | BA15: 44.6 | BB15: 4 | BC15: 32.2 | BD15: 85.9 | BG15: 0 | BJ15: 0 | BN15: 128.4 | BP15: 0 | BQ15: 0 | BS15: 38.2 | BT15: 27.8 | CA15: 2.3 | CB15: 101 | CC15: 93.5 | CD15: 60.8 | CE15: 71.2 | CF15: 29 | CJ15: 103.1 | CK15: 103.2 | CL15: 122 | CR15: 192.4 | CS15: 96.9 | CT15: 6.9 | CU15: 4.2 | CV15: 20 | CW15: 0 | CX15: 18.9 | CY15: 0 | CZ15: 0 | DA15: 0 | DB15: 20.1 | DC15: 10 | DD15: 5.5 | DE15: 0 | DG15: 2.1 | DH15: 1.8 | DI15: 5 | DJ15: 19.7 | DK15: 20 | DL15: 18.8 | DM15: 2.8 | DN15: 18.4 | DO15: 0 | DP15: 0 | DQ15: 17.7 | DR15: 22.5 | DS15: 0 | DT15: 3.4 | DU15: 3.4 | DV15: 2.7 | DW15: 0.4 | DX15: 0 | DY15: 19.8 | DZ15: 8.1 | EA15: 19.6 | EB15: 20.1 | EC15: 1.7 | ED15: 0 | EE15: 0 | EF15: 19.7 | EG15: 42.2 | EH15: 1.1 | EI15: 0.6 | EJ15: 0 | EK15: 21 | EL15: 6.2 | EM15: 0 | EN15: 20.4 | EO15: 20.4 | EP15: 20.1 | EQ15: 0 | ER15: 0 | ES15: 0 | ET15: 0 | EU15: 0 | EV15: 0 | EW15: 0 | EX15: 0 | EY15: 3.7 | EZ15: 1.1 | FA15: 2.4 | FB15: 0.9 | FC15: 0 | FD15: 8.4 | FE15: 20 | FF15: 20 | FG15: 9.3 | FH15: 27.7 | FI15: 34.5 | FJ15: 15 | FK15: 17.1 | FL15: 7.7 | FM15: 11.7 | FN15: 21.6 | FO15: 6356.9 | FQ15: 24.6 | FR15: 7.95 | FS15: 11.8 | FT15: 13.2 | FU15: 25.2 | FV15: 18.9434 | FW15: 12 | FX15: 15.6 | FY15: 129.2934
A16: 10/02/2026 | B16: 03:00 | C16: 204.6 | D16: 641.3 | E16: 216.3 | H16: 90.3 | I16: 244.9 | L16: 139.5 | M16: 139 | N16: 139.5 | O16: 224.3 | P16: 107.9 | Q16: 67 | R16: 565.2 | S16: 10.3 | X16: 163.9 | Y16: 7.6 | Z16: 5.4 | AA16: 0 | AB16: 6.7 | AD16: 142.7 | AI16: 110.4 | AJ16: 222.4 | AN16: 6.5 | AO16: 457 | AP16: 74 | AQ16: 153.7 | AR16: 42.1 | AS16: 18.6 | AT16: 18.8 | AU16: 93.5 | AY16: 107.9 | AZ16: 0 | BA16: 46.5 | BB16: 4 | BC16: 34.1 | BD16: 91.4 | BG16: 0 | BJ16: 0 | BN16: 128.4 | BP16: 0 | BQ16: 0 | BS16: 37.9 | BT16: 27.8 | CA16: 2.3 | CB16: 110.6 | CC16: 109.3 | CD16: 63.5 | CE16: 73 | CF16: 30.2 | CJ16: 103.1 | CK16: 103 | CL16: 121.7 | CR16: 137.2 | CS16: 78.2 | CT16: 7 | CU16: 4.3 | CV16: 10 | CW16: 0 | CX16: 15.3 | CY16: 0 | CZ16: 0 | DA16: 0 | DB16: 20.3 | DC16: 9.9 | DD16: 5.4 | DE16: 0 | DG16: 2.1 | DH16: 1.8 | DI16: 5 | DJ16: 20.4 | DK16: 20 | DL16: 18.8 | DM16: 2.8 | DN16: 18.4 | DO16: 0 | DP16: 0 | DQ16: 10.8 | DR16: 27.6 | DS16: 0 | DT16: 3.5 | DU16: 3.4 | DV16: 2.7 | DW16: 0.4 | DX16: 0 | DY16: 19.8 | DZ16: 8.1 | EA16: 19.8 | EB16: 20.2 | EC16: 1.3 | ED16: 0.2 | EE16: 0 | EF16: 19.7 | EG16: 48 | EH16: 1.2 | EI16: 0.9 | EJ16: 0 | EK16: 21 | EL16: 6.2 | EM16: 0 | EN16: 20.4 | EO16: 20.4 | EP16: 20.1 | EQ16: 0 | ER16: 0 | ES16: 0 | ET16: 0 | EU16: 0 | EV16: 2.9 | EW16: 3.1 | EX16: 0 | EY16: 3.7 | EZ16: 1.1 | FA16: 2.4 | FB16: 0.9 | FC16: 0 | FD16: 8.4 | FE16: 20 | FF16: 20 | FG16: 9.2 | FH16: 27.9 | FI16: 34.6 | FJ16: 14.5 | FK16: 17.1 | FL16: 8.6 | FM16: 11.7 | FN16: 22.4 | FO16: 6369.2 | FQ16: 24.5 | FR16: 7.95 | FS16: 11.8 | FT16: 13.2 | FU16: 25.5 | FV16: 18.94298 | FW16: 12 | FX16: 15.4 | FY16: 129.29298
A17: 10/02/2026 | B17: 03:30 | C17: 198.8 | D17: 629.9 | E17: 214.1 | H17: 88.9 | I17: 241.4 | L17: 111.9 | M17: 112.1 | N17: 112.3 | O17: 225.9 | P17: 162 | Q17: 82.8 | R17: 547.9 | S17: 10 | X17: 166.2 | Y17: 7.3 | Z17: 5.1 | AA17: 0 | AB17: 6.7 | AD17: 140.6 | AI17: 110.3 | AJ17: 175.4 | AN17: 6.5 | AO17: 457.6 | AP17: 77 | AQ17: 134.2 | AR17: 42.1 | AS17: 18.4 | AT17: 18.8 | AU17: 93 | AY17: 104.7 | AZ17: 0 | BA17: 45.1 | BB17: 4 | BC17: 32.7 | BD17: 88.2 | BG17: 0 | BJ17: 0 | BN17: 127.4 | BP17: 0 | BQ17: 0 | BS17: 38.3 | BT17: 27.8 | CA17: 0.6 | CB17: 39.6 | CC17: 87.6 | CD17: 62.9 | CE17: 72.6 | CF17: 29.9 | CJ17: 103.1 | CK17: 102.9 | CL17: 121.4 | CR17: 184.1 | CS17: 88.8 | CT17: 6.9 | CU17: 4.2 | CV17: 10 | CW17: 0 | CX17: 17.9 | CY17: 0 | CZ17: 0 | DA17: 0 | DB17: 20.3 | DC17: 9.9 | DD17: 5.4 | DE17: 0 | DG17: 2.1 | DH17: 1.8 | DI17: 5 | DJ17: 20.3 | DK17: 20 | DL17: 18.8 | DM17: 2.8 | DN17: 18.4 | DO17: 0 | DP17: 0 | DQ17: 12.4 | DR17: 25.1 | DS17: 0 | DT17: 3.5 | DU17: 3.4 | DV17: 2.7 | DW17: 0.4 | DX17: 0 | DY17: 19.8 | DZ17: 8.2 | EA17: 19.9 | EB17: 20.1 | EC17: 0.6 | ED17: 0.5 | EE17: 0 | EF17: 22 | EG17: 64.6 | EH17: 2.5 | EI17: 0.9 | EJ17: 0 | EK17: 21 | EL17: 6.2 | EM17: 0 | EN17: 20.4 | EO17: 20.4 | EP17: 20.1 | EQ17: 0 | ER17: 0 | ES17: 0 | ET17: 0 | EU17: 0 | EV17: 10.1 | EW17: 15.4 | EX17: 0 | EY17: 3.7 | EZ17: 1.1 | FA17: 2.4 | FB17: 0.9 | FC17: 0 | FD17: 8.4 | FE17: 19.9 | FF17: 19.9 | FG17: 9.1 | FH17: 27.9 | FI17: 34.8 | FJ17: 14.5 | FK17: 17.1 | FL17: 8.1 | FM17: 11.7 | FN17: 22 | FO17: 6244.4 | FQ17: 24.6 | FR17: 7.95 | FS17: 11.9 | FT17: 13.2 | FU17: 25.4 | FV17: 18.94304 | FW17: 12 | FX17: 15.7 | FY17: 129.69304
A18: 10/02/2026 | B18: 04:00 | C18: 198.2 | D18: 626.3 | E18: 212.3 | H18: 88.4 | I18: 240 | L18: 105.6 | M18: 105.9 | N18: 105.9 | O18: 211.5 | P18: 162.9 | Q18: 91.9 | R18: 541.7 | S18: 10 | X18: 161 | Y18: 7.1 | Z18: 5.1 | AA18: 0 | AB18: 6.7 | AD18: 140.9 | AI18: 109.2 | AJ18: 168.1 | AN18: 6.5 | AO18: 456.9 | AP18: 80.2 | AQ18: 129.2 | AR18: 41.9 | AS18: 18.5 | AT18: 18.8 | AU18: 87.6 | AY18: 104.5 | AZ18: 0 | BA18: 44.6 | BB18: 4 | BC18: 32.3 | BD18: 85.2 | BG18: 0 | BJ18: 0 | BN18: 125.7 | BP18: 0 | BQ18: 0 | BS18: 38.1 | BT18: 27.8 | CA18: 0.6 | CB18: 37.4 | CC18: 81.7 | CD18: 61.7 | CE18: 72 | CF18: 29.3 | CJ18: 102.7 | CK18: 102.5 | CL18: 121.3 | CR18: 208.8 | CS18: 100.3 | CT18: 6.9 | CU18: 4.3 | CV18: 13.5 | CW18: 0 | CX18: 19 | CY18: 0 | CZ18: 0 | DA18: 0 | DB18: 20.1 | DC18: 9.9 | DD18: 5.4 | DE18: 0 | DG18: 2.1 | DH18: 1.8 | DI18: 5 | DJ18: 19.9 | DK18: 20 | DL18: 18.9 | DM18: 2.7 | DN18: 18.4 | DO18: 0 | DP18: 0 | DQ18: 16 | DR18: 27 | DS18: 0 | DT18: 3.5 | DU18: 3.4 | DV18: 2.7 | DW18: 0.4 | DX18: 0 | DY18: 19.8 | DZ18: 8.2 | EA18: 19.8 | EB18: 20.1 | EC18: 0.4 | ED18: 1 | EE18: 0 | EF18: 36.4 | EG18: 79.7 | EH18: 2.3 | EI18: 1.9 | EJ18: 0 | EK18: 21 | EL18: 6.2 | EM18: 0 | EN18: 20.4 | EO18: 20.4 | EP18: 20.1 | EQ18: 0.21 | ER18: 0 | ES18: 0 | ET18: 0 | EU18: 0 | EV18: 21.4 | EW18: 18.2 | EX18: 0 | EY18: 3.7 | EZ18: 1.1 | FA18: 2.4 | FB18: 0.9 | FC18: 0 | FD18: 8.4 | FE18: 20 | FF18: 20 | FG18: 9.3 | FH18: 27.7 | FI18: 34.5 | FJ18: 14.5 | FK18: 17.1 | FL18: 8.1 | FM18: 11.6 | FN18: 21.7 | FO18: 6258.21 | FQ18: 24.5 | FR18: 7.95 | FS18: 11.9 | FT18: 13.2 | FU18: 25.3 | FV18: 18.94285 | FW18: 12 | FX18: 15.7 | FY18: 129.49285
A19: 10/02/2026 | B19: 04:30 | C19: 201.2 | D19: 635.2 | E19: 214.8 | H19: 89.9 | I19: 241.9 | L19: 118.3 | M19: 118.9 | N19: 118.4 | O19: 211.4 | P19: 107.7 | Q19: 71.5 | R19: 558.6 | S19: 10.1 | X19: 156.5 | Y19: 7.5 | Z19: 5.5 | AA19: 0 | AB19: 6.7 | AD19: 142 | AI19: 110.1 | AJ19: 159.4 | AN19: 6.5 | AO19: 458 | AP19: 79.8 | AQ19: 141.4 | AR19: 42.1 | AS19: 18.5 | AT19: 18.8 | AU19: 90.8 | AY19: 105.5 | AZ19: 0 | BA19: 45.5 | BB19: 4 | BC19: 33.1 | BD19: 89 | BG19: 0 | BJ19: 0 | BN19: 127.9 | BP19: 0 | BQ19: 0 | BS19: 37.9 | BT19: 27.7 | CA19: 0.3 | CB19: 45.2 | CC19: 113.8 | CD19: 63.1 | CE19: 70.9 | CF19: 30 | CJ19: 103 | CK19: 102.9 | CL19: 121.2 | CR19: 208.3 | CS19: 100.2 | CT19: 6.9 | CU19: 4.3 | CV19: 19.5 | CW19: 0 | CX19: 13 | CY19: 0 | CZ19: 0 | DA19: 0 | DB19: 20.2 | DC19: 10 | DD19: 5.4 | DE19: 0 | DG19: 2.1 | DH19: 1.8 | DI19: 4.9 | DJ19: 20.1 | DK19: 20 | DL19: 18.7 | DM19: 2.7 | DN19: 18.4 | DO19: 0 | DP19: 0 | DQ19: 14.9 | DR19: 28.5 | DS19: 0 | DT19: 3.5 | DU19: 3.4 | DV19: 2.7 | DW19: 0.4 | DX19: 0 | DY19: 19.8 | DZ19: 8.1 | EA19: 19.8 | EB19: 20.2 | EC19: 1 | ED19: 1.6 | EE19: 0 | EF19: 34 | EG19: 72 | EH19: 4.3 | EI19: 2.2 | EJ19: 0 | EK19: 21 | EL19: 6.2 | EM19: 0 | EN19: 20.4 | EO19: 20.4 | EP19: 20.1 | EQ19: 0.29 | ER19: 0 | ES19: 0 | ET19: 0 | EU19: 0 | EV19: 35.7 | EW19: 42.5 | EX19: 0 | EY19: 3.7 | EZ19: 1.1 | FA19: 2.4 | FB19: 0.9 | FC19: 0 | FD19: 8.4 | FE19: 20 | FF19: 19.9 | FG19: 9.4 | FH19: 27.4 | FI19: 34.1 | FJ19: 15 | FK19: 17.1 | FL19: 8.4 | FM19: 11.7 | FN19: 22 | FO19: 6343.49 | FQ19: 24.6 | FR19: 7.95 | FS19: 11.8 | FT19: 13.2 | FU19: 25.3 | FV19: 18.94279 | FW19: 12 | FX19: 15.6 | FY19: 129.39279
A20: 10/02/2026 | B20: 05:00 | C20: 202.1 | D20: 633.4 | E20: 214.3 | H20: 89.7 | I20: 241.7 | L20: 115.6 | M20: 117 | N20: 117 | O20: 210.7 | P20: 107.1 | Q20: 66.8 | R20: 559.1 | S20: 10.3 | X20: 166.9 | Y20: 7.4 | Z20: 5.5 | AA20: 0 | AB20: 6.7 | AD20: 142.1 | AI20: 110.2 | AJ20: 162.5 | AN20: 6.5 | AO20: 455.1 | AP20: 80.2 | AQ20: 137.9 | AR20: 42.1 | AS20: 18.5 | AT20: 18.8 | AU20: 91.4 | AY20: 105.7 | AZ20: 0 | BA20: 45.7 | BB20: 4 | BC20: 33.2 | BD20: 77.8 | BG20: 0 | BJ20: 0 | BN20: 127.5 | BP20: 0 | BQ20: 0 | BS20: 37.9 | BT20: 27.6 | CA20: 1 | CB20: 44.2 | CC20: 109.8 | CD20: 62.9 | CE20: 70.9 | CF20: 29.8 | CJ20: 102.6 | CK20: 102.5 | CL20: 121.1 | CR20: 208.5 | CS20: 100 | CT20: 6.9 | CU20: 4.2 | CV20: 20 | CW20: 0 | CX20: 20.8 | CY20: 0 | CZ20: 0.15 | DA20: 0 | DB20: 20.2 | DC20: 9.9 | DD20: 5.3 | DE20: 0 | DG20: 2.1 | DH20: 1.8 | DI20: 4.9 | DJ20: 20 | DK20: 20 | DL20: 18.8 | DM20: 2.6 | DN20: 18.4 | DO20: 0 | DP20: 0 | DQ20: 9.9 | DR20: 19.3 | DS20: 0 | DT20: 3.5 | DU20: 3.4 | DV20: 2.7 | DW20: 0.4 | DX20: 0 | DY20: 19.8 | DZ20: 8.2 | EA20: 19.9 | EB20: 20.2 | EC20: 1.1 | ED20: 5.1 | EE20: 0 | EF20: 23.8 | EG20: 49.6 | EH20: 1.8 | EI20: 0.8 | EJ20: 0 | EK20: 21 | EL20: 6.2 | EM20: 0 | EN20: 20.4 | EO20: 20.4 | EP20: 20.1 | EQ20: 0.56 | ER20: 0 | ES20: 0 | ET20: 0 | EU20: 0 | EV20: 63.4 | EW20: 45.2 | EX20: 0 | EY20: 3.7 | EZ20: 1.1 | FA20: 2.4 | FB20: 0.9 | FC20: 0 | FD20: 8.4 | FE20: 19.8 | FF20: 19.8 | FG20: 9.1 | FH20: 26.9 | FI20: 33.4 | FJ20: 15.4 | FK20: 17.1 | FL20: 8.4 | FM20: 11.7 | FN20: 22 | FO20: 6312.21 | FQ20: 24.5 | FR20: 7.95 | FS20: 11.8 | FT20: 13.2 | FU20: 24.8 | FV20: 18.94249 | FW20: 12 | FX20: 15.6 | FY20: 128.79249
A21: 10/02/2026 | B21: 05:30 | C21: 202.1 | D21: 639.2 | E21: 216.3 | H21: 90.1 | I21: 241.8 | L21: 137.2 | M21: 136.2 | N21: 136.1 | O21: 228.8 | P21: 107.9 | Q21: 66.5 | R21: 561 | S21: 10.3 | X21: 165.4 | Y21: 7.6 | Z21: 5.5 | AA21: 0 | AB21: 1.7 | AD21: 142.6 | AI21: 110.2 | AJ21: 208 | AN21: 6.5 | AO21: 460.2 | AP21: 79.5 | AQ21: 152.3 | AR21: 42.1 | AS21: 18.6 | AT21: 18.8 | AU21: 90.5 | AY21: 107 | AZ21: 0 | BA21: 46.4 | BB21: 4 | BC21: 34 | BD21: 92.9 | BG21: 0 | BJ21: 0 | BN21: 128 | BP21: 0 | BQ21: 0 | BS21: 37.6 | BT21: 27.8 | CA21: 2 | CB21: 58.9 | CC21: 124 | CD21: 63.7 | CE21: 71 | CF21: 30.2 | CJ21: 103.7 | CK21: 103.2 | CL21: 122.1 | CR21: 209 | CS21: 100.8 | CT21: 7 | CU21: 4.3 | CV21: 20 | CW21: 0 | CX21: 34.5 | CY21: 0 | CZ21: 0.49 | DA21: 0 | DB21: 20.3 | DC21: 9.9 | DD21: 5.4 | DE21: 0 | DG21: 2.1 | DH21: 1.8 | DI21: 5 | DJ21: 20.3 | DK21: 20 | DL21: 18.9 | DM21: 2.6 | DN21: 18.4 | DO21: 0.1 | DP21: 0 | DQ21: 11.3 | DR21: 31.5 | DS21: 0 | DT21: 3.5 | DU21: 3.4 | DV21: 2.7 | DW21: 0.4 | DX21: 0 | DY21: 19.8 | DZ21: 8.2 | EA21: 19.9 | EB21: 20.2 | EC21: 0.7 | ED21: 3.8 | EE21: 0 | EF21: 14.4 | EG21: 51.7 | EH21: 0.6 | EI21: 0 | EJ21: 0 | EK21: 21 | EL21: 6.2 | EM21: 0 | EN21: 20.4 | EO21: 20.4 | EP21: 20.1 | EQ21: 0.8 | ER21: 0 | ES21: 0 | ET21: 0 | EU21: 0 | EV21: 42.2 | EW21: 27.4 | EX21: 0 | EY21: 3.7 | EZ21: 1.1 | FA21: 2.4 | FB21: 0.9 | FC21: 0 | FD21: 8.4 | FE21: 20 | FF21: 20 | FG21: 8.8 | FH21: 27.1 | FI21: 33.6 | FJ21: 15.4 | FK21: 17.2 | FL21: 6.9 | FM21: 11.7 | FN21: 20.7 | FO21: 6488.89 | FQ21: 24.6 | FR21: 7.96 | FS21: 10.5 | FT21: 13.2 | FU21: 25.2 | FV21: 18.94265 | FW21: 12 | FX21: 15.8 | FY21: 128.20265
A22: 10/02/2026 | B22: 06:00 | C22: 203.7 | D22: 635.1 | E22: 215.3 | H22: 90.6 | I22: 241.3 | L22: 140.6 | M22: 140.5 | N22: 140.6 | O22: 239.8 | P22: 108.5 | Q22: 67.4 | R22: 555.7 | S22: 10.2 | X22: 167.7 | Y22: 7.5 | Z22: 5.4 | AA22: 0 | AB22: 6.5 | AD22: 142.4 | AI22: 110.4 | AJ22: 222.1 | AN22: 6.5 | AO22: 456.5 | AP22: 79.7 | AQ22: 152.2 | AR22: 42.1 | AS22: 18.6 | AT22: 18.8 | AU22: 92.2 | AY22: 106.3 | AZ22: 0 | BA22: 45.8 | BB22: 4 | BC22: 33.4 | BD22: 92 | BG22: 0 | BJ22: 0 | BN22: 127.8 | BP22: 0 | BQ22: 0 | BS22: 38.1 | BT22: 27.8 | CA22: 2.4 | CB22: 73.7 | CC22: 123 | CD22: 63.5 | CE22: 69 | CF22: 30.2 | CJ22: 103.2 | CK22: 103.1 | CL22: 122 | CR22: 209.3 | CS22: 101.1 | CT22: 6.9 | CU22: 4.3 | CV22: 20 | CW22: 0 | CX22: 38.5 | CY22: 0.7 | CZ22: 0 | DA22: 0 | DB22: 20.4 | DC22: 10 | DD22: 5.4 | DE22: 0 | DG22: 2.1 | DH22: 1.8 | DI22: 5.1 | DJ22: 20.5 | DK22: 20 | DL22: 18.9 | DM22: 2.6 | DN22: 18.4 | DO22: 2.4 | DP22: 3 | DQ22: 13.5 | DR22: 39.5 | DS22: 0.8 | DT22: 3.5 | DU22: 3.4 | DV22: 2.7 | DW22: 0.4 | DX22: 0 | DY22: 19.7 | DZ22: 8.1 | EA22: 20.1 | EB22: 20.2 | EC22: 0.3 | ED22: 1.8 | EE22: 0.4 | EF22: 21.5 | EG22: 55.3 | EH22: 1.9 | EI22: 2.1 | EJ22: 0 | EK22: 21 | EL22: 6.2 | EM22: 0 | EN22: 20.4 | EO22: 20.4 | EP22: 20.1 | EQ22: 0 | ER22: 4 | ES22: 0.3 | ET22: 4.7 | EU22: 0 | EV22: 42.1 | EW22: 30.7 | EX22: 3.8 | EY22: 3.7 | EZ22: 1.1 | FA22: 2.4 | FB22: 0.9 | FC22: 0 | FD22: 8.4 | FE22: 20 | FF22: 20 | FG22: 8.8 | FH22: 27.3 | FI22: 34 | FJ22: 15.1 | FK22: 17.2 | FL22: 7.3 | FM22: 11.6 | FN22: 20.7 | FO22: 6582 | FQ22: 24.5 | FR22: 7.96 | FS22: 9.8 | FT22: 13.2 | FU22: 25 | FV22: 18.94243 | FW22: 11.9 | FX22: 15.6 | FY22: 126.90243
... A58: 11/02/2026 | B58: 00:00 | C58: 202.8 | D58: 642.3 | E58: 216.1 | H58: 90.3 | I58: 241.2 | L58: 138 | M58: 136.4 | N58: 138.8 | O58: 241.8 | P58: 204.7 | Q58: 108.3 | R58: 542.6 | S58: 10.5 | X58: 167.7 | Y58: 8.6 | Z58: 6.2 | AA58: 0 | AB58: 6.7 | AD58: 142.5 | AI58: 110.4 | AJ58: 190 | AN58: 6.5 | AO58: 458.2 | AP58: 73.5 | AQ58: 152.5 | AR58: 42 | AS58: 18.4 | AT58: 18.9 | AU58: 91.3 | AY58: 106.3 | AZ58: 15.9 | BA58: 45.1 | BB58: 4 | BC58: 34.2 | BD58: 161.4 | BG58: 0 | BJ58: 0 | BN58: 125.29 | BP58: 0 | BQ58: 0 | BS58: 37.65 | BT58: 27.35 | CA58: 2.1 | CB58: 109.4 | CC58: 101.2 | CD58: 63.1 | CE58: 73.3 | CF58: 30.2 | CJ58: 140.3 | CK58: 141 | CL58: 146.6 | CR58: 207.7 | CS58: 99.8 | CT58: 7 | CU58: 4.4 | CV58: 14 | CW58: 0 | CX58: 58.7 | CY58: 0 | CZ58: 1.15 | DA58: 0 | DB58: 20.3 | DC58: 10 | DD58: 5.5 | DE58: 0 | DG58: 1.7 | DH58: 1.8 | DI58: 5 | DJ58: 20.4 | DK58: 20 | DL58: 18.9 | DM58: 2.6 | DN58: 18.4 | DO58: 0 | DP58: 0 | DQ58: 20.4 | DR58: 60.6 | DS58: 0 | DT58: 3.4 | DU58: 3 | DV58: 2.8 | DW58: 0.3 | DX58: 0 | DY58: 19.7 | DZ58: 8 | EA58: 20.2 | EB58: 20.2 | EC58: 1.7 | ED58: 13.3 | EE58: 0 | EF58: 50.99 | EG58: 99.7 | EH58: 4.4397 | EI58: 2.4206 | EJ58: 0 | EK58: 18.2 | EL58: 5.8 | EM58: 0 | EN58: 20.4 | EO58: 20.4 | EP58: 20 | EQ58: 1.86 | ER58: 0 | ES58: 0 | ET58: 0 | EU58: 0 | EV58: 97.9 | EW58: 78.5 | EX58: 0 | EY58: 3.8 | EZ58: 2.1 | FA58: 2.4 | FB58: 0.9 | FC58: 0 | FD58: 8.1 | FE58: 20 | FF58: 20 | FG58: 8.9 | FH58: 27.2 | FI58: 34 | FJ58: 14.5 | FK58: 14.7 | FL58: 8.3 | FM58: 11.6 | FN58: 23 | FO58: 7082.6503 | FQ58: 24.6 | FR58: 7.91 | FS58: 11.6 | FT58: 13.2 | FU58: 25.5 | FV58: 18.9488 | FW58: 11.8 | FX58: 15.6 | FY58: 129.1588
A59: EJEC | C59: 4846.65 | D59: 15255.75 | E59: 5160.8 | F59: 0 | G59: 0 | H59: 2157.05 | I59: 5790.5 | J59: 0 | K59: 0 | L59: 3284.35 | M59: 3282.8 | N59: 3282.45 | O59: 5601.5 | P59: 4311.15 | Q59: 2345.6 | R59: 13288.35 | S59: 244.65 | T59: 0 | U59: 0 | V59: 0 | W59: 0 | X59: 3963.3 | Y59: 189.25 | Z59: 134.45 | AA59: 162.15 | AB59: 158 | AC59: 0 | AD59: 3410.75 | AE59: 0 | AF59: 0 | AG59: 0 | AH59: 0 | AI59: 2642.85 | AJ59: 4631.6 | AK59: 0 | AL59: 0 | AM59: 0 | AN59: 156 | AO59: 10777.85 | AP59: 1859.9 | AQ59: 3621.75 | AR59: 1008.95 | AS59: 442.7 | AT59: 451.75 | AU59: 2183 | AV59: 0 | AW59: 0 | AX59: 0 | AY59: 2538.85 | AZ59: 436.9 | BA59: 1078.55 | BB59: 96 | BC59: 795.1 | BD59: 3112 | BE59: 0 | BF59: 0 | BG59: 678.15 | BH59: 0 | BI59: 0 | BJ59: 664.75 | BK59: 0 | BL59: 0 | BM59: 0 | BN59: 3052.205 | BO59: 0 | BP59: 696.055 | BQ59: 1811.015 | BR59: 0 | BS59: 1304.675 | BT59: 745.765 | BU59: 0 | BV59: 0 | BW59: 0 | BX59: 0 | BY59: 0 | BZ59: 0 | CA59: 51.25 | CB59: 2511.15 | CC59: 2659.65 | CD59: 1521.25 | CE59: 1786.3 | CF59: 661.5 | CG59: 0 | CH59: 0 | CI59: 0 | CJ59: 3085.3 | CK59: 3095.25 | CL59: 3407.95 | CM59: 0 | CN59: 0 | CO59: 0 | CP59: 0 | CQ59: 0 | CR59: 4382.75 | CS59: 2199.65 | CT59: 166.65 | CU59: 102.7 | CV59: 435.45 | CW59: 7 | CX59: 1538.7 | CY59: 767.95 | CZ59: 39.495 | DA59: 1.45 | DB59: 486.15 | DC59: 238.3 | DD59: 130.1 | DE59: 1902.8 | DF59: 0 | DG59: 42.35 | DH59: 40.5 | DI59: 119.85 | DJ59: 485.2 | DK59: 452.35 | DL59: 451.15 | DM59: 63.3 | DN59: 441.6 | DO59: 148.3 | DP59: 181.5 | DQ59: 448.05 | DR59: 1312.1 | DS59: 143.75 | DT59: 78.5 | DU59: 230.4 | DV59: 64.15 | DW59: 7.75 | DX59: 3.05 | DY59: 474.85 | DZ59: 167.25 | EA59: 483 | EB59: 484.65 | EC59: 65.9 | ED59: 287.15 | EE59: 269.7 | EF59: 1018.925 | EG59: 1675.285 | EH59: 117.64705 | EI59: 110.61245 | EJ59: 347.5 | EK59: 475.8 | EL59: 145.45 | EM59: 7.05 | EN59: 489.6 | EO59: 489.6 | EP59: 481.4 | EQ59: 45.92 | ER59: 2243.65 | ES59: 137.5 | ET59: 1249.15 | EU59: 4.8 | EV59: 1606.85 | EW59: 1745.3 | EX59: 958.35 | EY59: 82.85 | EZ59: 26.95 | FA59: 54.75 | FB59: 21.6 | FC59: 117.35 | FD59: 197.95 | FE59: 479.75 | FF59: 479.45 | FG59: 216.45 | FH59: 658.05 | FI59: 818.25 | FJ59: 358.15 | FK59: 333.35 | FL59: 187 | FM59: 270.05 | FN59: 529.85 | FO59: 177963.15 | FQ59: 589.4 | FR59: 190.565 | FS59: 266.05 | FT59: 316.8 | FU59: 596.55 | FV59: 454.713 | FW59: 277.15 | FX59: 373.95 | FY59: 3065.178

Sheet REACTIVA
B3: martes, 10 de Febrero del 2026
A5: POTENCIA REACTIVA EJECUTADA DE LAS UNIDADES DE GENERACIÓN DEL COES (MVAR) | FQ5: CENTRALES NO INTEGRANTES COES
A6: FECHA | B6: HORA | C6: 65333 | D6: 101 | E6: 102 | F6: 42667 | G6: 42668 | H6: 126 | I6: 127 | J6: 138 | K6: 139 | L6: 197 | M6: 203 | N6: 204 | O6: 230 | P6: 209 | Q6: 56677 | R6: 796 | S6: 2146 | T6: 142 | U6: 143 | V6: 125 | W6: 187 | X6: 163 | Y6: 298 | Z6: 299 | AA6: 219 | AB6: 151 | AC6: 152 | AD6: 153 | AE6: 154 | AF6: 756 | AG6: 156 | AH6: 155 | AI6: 182 | AJ6: 212 | AK6: 758 | AL6: 263 | AM6: 265 | AN6: 775 | AO6: 777 | AP6: 2154 | AQ6: 150 | AR6: 149 | AS6: 188 | AT6: 2131 | AU6: 755 | AV6: 252 | AW6: 249 | AX6: 250 | AY6: 117 | AZ6: 119 | BA6: 120 | BB6: 189 | BC6: 122 | BD6: 266 | BE6: 337 | BF6: 338 | BG6: 251 | BH6: 115 | BI6: 239 | BJ6: 288 | BK6: 240 | BL6: 241 | BM6: 242 | BN6: 191 | BO6: 194 | BP6: 196 | BQ6: 207 | BR6: 236 | BS6: 795 | BT6: 285 | BU6: 995 | BV6: 996 | BW6: 997 | BX6: 766 | BY6: 926 | BZ6: 924 | CA6: 121 | CB6: 103 | CC6: 104 | CD6: 106 | CE6: 105 | CF6: 107 | CG6: 110 | CH6: 109 | CI6: 144 | CJ6: 113 | CK6: 114 | CL6: 193 | CM6: 208 | CN6: 786 | CO6: 787 | CP6: 788 | CQ6: 789 | CR6: 248 | CS6: 2159 | CT6: 267 | CU6: 268 | CV6: 2194 | CW6: 303 | CX6: 59715 | CY6: 62255 | CZ6: 1263 | DA6: 61800 | DB6: 69125 | DC6: 216 | DD6: 198 | DE6: 70400 | DF6: 76068 | DG6: 49607 | DH6: 214 | DI6: 260 | DJ6: 2152 | DK6: 2128 | DL6: 247 | DM6: 228 | DN6: 2135 | DO6: 261 | DP6: 237 | DQ6: 253 | DR6: 770 | DS6: 235 | DT6: 238 | DU6: 2184 | DV6: 61855 | DW6: 223 | DX6: 75566 | DY6: 226 | DZ6: 201 | EA6: 258 | EB6: 259 | EC6: 257 | ED6: 256 | EE6: 2148 | EF6: 58288 | EG6: 58289 | EH6: 58839 | EI6: 58840 | EJ6: 75260 | EK6: 296 | EL6: 297 | EM6: 211 | EN6: 2175 | EO6: 2178 | EP6: 2181 | EQ6: 1262 | ER6: 63425 | ES6: 233 | ET6: 2150 | EU6: 2165 | EV6: 2161 | EW6: 61197 | EX6: 58851 | EY6: 225 | EZ6: 2201 | FA6: 2171 | FB6: 760 | FC6: 234 | FD6: 215 | FE6: 917 | FF6: 920 | FG6: 289 | FH6: 58333 | FI6: 58336 | FJ6: 213 | FK6: 232 | FL6: 2190 | FM6: 69867 | FN6: 75066 | FO6: TOTAL COES | FQ6: 221 | FR6: 222 | FS6: 224 | FT6: 2187 | FU6: 227 | FV6: 49400 | FW6: 199 | FX6: 200 | FY6: TOTAL NO COES
C7: SUR | D7: CENTRO | E7: CENTRO | F7: NORTE | G7: NORTE | H7: NORTE | I7: NORTE | J7: CENTRO | K7: CENTRO | L7: CENTRO | M7: CENTRO | N7: CENTRO | O7: CENTRO | P7: CENTRO | Q7: CENTRO | R7: CENTRO | S7: CENTRO | T7: CENTRO | U7: CENTRO | V7: CENTRO | W7: CENTRO | X7: SUR | Y7: SUR | Z7: SUR | AA7: CENTRO | AB7: SUR | AC7: SUR | AD7: SUR | AE7: SUR | AF7: SUR | AG7: SUR | AH7: SUR | AI7: SUR | AJ7: CENTRO | AK7: NORTE | AL7: NORTE | AM7: NORTE | AN7: CENTRO | AO7: CENTRO | AP7: CENTRO | AQ7: CENTRO | AR7: CENTRO | AS7: CENTRO | AT7: CENTRO | AU7: SUR | AV7: CENTRO | AW7: CENTRO | AX7: CENTRO | AY7: CENTRO | AZ7: CENTRO | BA7: CENTRO | BB7: SUR | BC7: NORTE | BD7: CENTRO | BE7: CENTRO | BF7: CENTRO | BG7: CENTRO | BH7: NORTE | BI7: NORTE | BJ7: NORTE | BK7: SUR | BL7: SUR | BM7: SUR | BN7: CENTRO | BO7: CENTRO | BP7: CENTRO | BQ7: CENTRO | BR7: CENTRO | BS7: CENTRO | BT7: CENTRO | BU7: SUR | BV7: SUR | BW7: SUR | BX7: NORTE | BY7: SUR | BZ7: CENTRO | CA7: NORTE | CB7: CENTRO | CC7: CENTRO | CD7: CENTRO | CE7: CENTRO | CF7: CENTRO | CG7: CENTRO | CH7: CENTRO | CI7: CENTRO | CJ7: CENTRO | CK7: CENTRO | CL7: CENTRO | CM7: CENTRO | CN7: SUR | CO7: SUR | CP7: SUR | CQ7: SUR | CR7: CENTRO | CS7: CENTRO | CT7: CENTRO | CU7: CENTRO | CV7: NORTE | CW7: CENTRO | CX7: CENTRO | CY7: SUR | CZ7: NORTE | DA7: NORTE | DB7: CENTRO | DC7: NORTE | DD7: NORTE | DE7: SUR | DG7: SUR | DH7: CENTRO | DI7: CENTRO | DJ7: CENTRO | DK7: NORTE | DL7: NORTE | DM7: CENTRO | DN7: CENTRO | DO7: SUR | DP7: SUR | DQ7: CENTRO | DR7: CENTRO | DS7: SUR | DT7: CENTRO | DU7: CENTRO | DV7: NORTE | DW7: CENTRO | DX7: CENTRO | DY7: CENTRO | DZ7: NORTE | EA7: CENTRO | EB7: CENTRO | EC7: NORTE | ED7: NORTE | EE7: SUR | EF7: CENTRO | EG7: CENTRO | EH7: CENTRO | EI7: CENTRO | EJ7: SUR | EK7: CENTRO | EL7: CENTRO | EM7: SUR | EN7: SUR | EO7: SUR | EP7: SUR | EQ7: NORTE | ER7: SUR | ES7: SUR | ET7: SUR | EU7: CENTRO | EV7: CENTRO | EW7: CENTRO | EX7: SUR | EY7: CENTRO | EZ7: CENTRO | FA7: CENTRO | FB7: CENTRO | FC7: SUR | FD7: NORTE | FE7: CENTRO | FF7: CENTRO | FG7: NORTE | FH7: NORTE | FI7: NORTE | FJ7: CENTRO | FK7: NORTE | FL7: NORTE | FM7: NORTE | FN7: NORTE | FQ7: NORTE | FR7: CENTRO | FS7: NORTE | FT7: NORTE | FU7: NORTE | FV7: NORTE | FW7: NORTE | FX7: NORTE
C8: HIDROELÉCTRICA | D8: HIDROELÉCTRICA | E8: HIDROELÉCTRICA | F8: TERMOELÉCTRICA | G8: TERMOELÉCTRICA | H8: HIDROELÉCTRICA | I8: HIDROELÉCTRICA | J8: TERMOELÉCTRICA | K8: TERMOELÉCTRICA | L8: TERMOELÉCTRICA | M8: TERMOELÉCTRICA | N8: TERMOELÉCTRICA | O8: TERMOELÉCTRICA | P8: TERMOELÉCTRICA | Q8: TERMOELÉCTRICA | R8: HIDROELÉCTRICA | S8: HIDROELÉCTRICA | T8: TERMOELÉCTRICA | U8: TERMOELÉCTRICA | V8: TERMOELÉCTRICA | W8: TERMOELÉCTRICA | X8: HIDROELÉCTRICA | Y8: HIDROELÉCTRICA | Z8: HIDROELÉCTRICA | AA8: TERMOELÉCTRICA | AB8: HIDROELÉCTRICA | AC8: HIDROELÉCTRICA | AD8: HIDROELÉCTRICA | AE8: HIDROELÉCTRICA | AF8: TERMOELÉCTRICA | AG8: TERMOELÉCTRICA | AH8: TERMOELÉCTRICA | AI8: HIDROELÉCTRICA | AJ8: HIDROELÉCTRICA | AK8: TERMOELÉCTRICA | AL8: TERMOELÉCTRICA | AM8: TERMOELÉCTRICA | AN8: HIDROELÉCTRICA | AO8: HIDROELÉCTRICA | AP8: HIDROELÉCTRICA | AQ8: HIDROELÉCTRICA | AR8: HIDROELÉCTRICA | AS8: HIDROELÉCTRICA | AT8: HIDROELÉCTRICA | AU8: HIDROELÉCTRICA | AV8: TERMOELÉCTRICA | AW8: TERMOELÉCTRICA | AX8: TERMOELÉCTRICA | AY8: HIDROELÉCTRICA | AZ8: HIDROELÉCTRICA | BA8: HIDROELÉCTRICA | BB8: HIDROELÉCTRICA | BC8: HIDROELÉCTRICA | BD8: HIDROELÉCTRICA | BE8: HIDROELÉCTRICA | BF8: HIDROELÉCTRICA | BG8: HIDROELÉCTRICA | BH8: TERMOELÉCTRICA | BI8: TERMOELÉCTRICA | BJ8: TERMOELÉCTRICA | BK8: TERMOELÉCTRICA | BL8: TERMOELÉCTRICA | BM8: TERMOELÉCTRICA | BN8: HIDROELÉCTRICA | BO8: TERMOELÉCTRICA | BP8: TERMOELÉCTRICA | BQ8: TERMOELÉCTRICA | BR8: TERMOELÉCTRICA | BS8: TERMOELÉCTRICA | BT8: TERMOELÉCTRICA | BU8: TERMOELÉCTRICA | BV8: TERMOELÉCTRICA | BW8: TERMOELÉCTRICA | BX8: HIDROELÉCTRICA | BY8: TERMOELÉCTRICA | BZ8: TERMOELÉCTRICA | CA8: HIDROELÉCTRICA | CB8: HIDROELÉCTRICA | CC8: HIDROELÉCTRICA | CD8: HIDROELÉCTRICA | CE8: HIDROELÉCTRICA | CF8: HIDROELÉCTRICA | CG8: TERMOELÉCTRICA | CH8: TERMOELÉCTRICA | CI8: TERMOELÉCTRICA | CJ8: TERMOELÉCTRICA | CK8: TERMOELÉCTRICA | CL8: TERMOELÉCTRICA | CM8: TERMOELÉCTRICA | CN8: TERMOELÉCTRICA | CO8: TERMOELÉCTRICA | CP8: TERMOELÉCTRICA | CQ8: TERMOELÉCTRICA | CR8: TERMOELÉCTRICA | CS8: TERMOELÉCTRICA | CT8: HIDROELÉCTRICA | CU8: HIDROELÉCTRICA | CV8: HIDROELÉCTRICA | CW8: SOLAR | CX8: EÓLICA | CY8: SOLAR | CZ8: EÓLICA | DA8: SOLAR | DB8: HIDROELÉCTRICA | DC8: HIDROELÉCTRICA | DD8: HIDROELÉCTRICA | DE8: SOLAR | DF8: SOLAR | DG8: HIDROELÉCTRICA | DH8: HIDROELÉCTRICA | DI8: HIDROELÉCTRICA | DJ8: HIDROELÉCTRICA | DK8: HIDROELÉCTRICA | DL8: HIDROELÉCTRICA | DM8: HIDROELÉCTRICA | DN8: HIDROELÉCTRICA | DO8: SOLAR | DP8: SOLAR | DQ8: EÓLICA | DR8: EÓLICA | DS8: SOLAR | DT8: HIDROELÉCTRICA | DU8: HIDROELÉCTRICA | DV8: HIDROELÉCTRICA | DW8: HIDROELÉCTRICA | DX8: SOLAR | DY8: HIDROELÉCTRICA | DZ8: HIDROELÉCTRICA | EA8: HIDROELÉCTRICA | EB8: HIDROELÉCTRICA | EC8: EÓLICA | ED8: EÓLICA | EE8: SOLAR | EF8: EÓLICA | EG8: EÓLICA | EH8: EÓLICA | EI8: EÓLICA | EJ8: SOLAR | EK8: HIDROELÉCTRICA | EL8: HIDROELÉCTRICA | EM8: HIDROELÉCTRICA | EN8: HIDROELÉCTRICA | EO8: HIDROELÉCTRICA | EP8: HIDROELÉCTRICA | EQ8: EÓLICA | ER8: SOLAR | ES8: SOLAR | ET8: SOLAR | EU8: HIDROELÉCTRICA | EV8: EÓLICA | EW8: EÓLICA | EX8: SOLAR | EY8: TERMOELÉCTRICA | EZ8: TERMOELÉCTRICA | FA8: TERMOELÉCTRICA | FB8: TERMOELÉCTRICA | FC8: SOLAR | FD8: HIDROELÉCTRICA | FE8: HIDROELÉCTRICA | FF8: HIDROELÉCTRICA | FG8: TERMOELÉCTRICA | FH8: TERMOELÉCTRICA | FI8: TERMOELÉCTRICA | FJ8: TERMOELÉCTRICA | FK8: TERMOELÉCTRICA | FL8: TERMOELÉCTRICA | FM8: TERMOELÉCTRICA | FN8: TERMOELÉCTRICA | FQ8: HIDROELÉCTRICA | FR8: HIDROELÉCTRICA | FS8: HIDROELÉCTRICA | FT8: HIDROELÉCTRICA | FU8: TERMOELÉCTRICA | FV8: TERMOELÉCTRICA | FW8: HIDROELÉCTRICA | FX8: HIDROELÉCTRICA
C9: HYDRO GLOBAL PERÚ S.A.C. | D9: ELECTROPERU | E9: ELECTROPERU | F9: ELECTROPERU | G9: ELECTROPERU | H9: ORAZUL ENERGY PERÚ | I9: ORAZUL ENERGY PERÚ | J9: TERMOSELVA | K9: TERMOSELVA | L9: KALLPA GENERACION S.A. | M9: KALLPA GENERACION S.A. | N9: KALLPA GENERACION S.A. | O9: KALLPA GENERACION S.A. | P9: KALLPA GENERACION S.A. | Q9: KALLPA GENERACION S.A. | R9: KALLPA GENERACION S.A. | S9: KALLPA GENERACION S.A. | T9: SHOUGESA | U9: SHOUGESA | V9: SHOUGESA | W9: SHOUGESA | X9: EGEMSA | Y9: EGESUR | Z9: EGESUR | AA9: EGESUR | AB9: EGASA | AC9: EGASA | AD9: EGASA | AE9: EGASA | AF9: EGASA | AG9: EGASA | AH9: EGASA | AI9: SAN GABAN | AJ9: CELEPSA | AK9: MINERA CERRO VERDE | AL9: PLANTA DE RESERVA FRIA DE GENERACION DE ETEN S.A. | AM9: PLANTA DE RESERVA FRIA DE GENERACION DE ETEN S.A. | AN9: EMPRESA DE GENERACION HUALLAGA | AO9: EMPRESA DE GENERACION HUALLAGA | AP9: LA VIRGEN | AQ9: CHINANGO S.A.C. | AR9: CHINANGO S.A.C. | AS9: HIDROELECTRICA HUANCHOR S.A.C. | AT9: CELEPSA RENOVABLES S.R.L. | AU9: INLAND ENERGY SAC | AV9: FENIX POWER PERÚ | AW9: FENIX POWER PERÚ | AX9: FENIX POWER PERÚ | AY9: STATKRAFT S.A | AZ9: STATKRAFT S.A | BA9: STATKRAFT S.A | BB9: STATKRAFT S.A | BC9: STATKRAFT S.A | BD9: STATKRAFT S.A | BE9: CENTRALES SANTA ROSA S.A.C. | BF9: CENTRALES SANTA ROSA S.A.C. | BG9: EMPRESA DE GENERACION HUANZA | BH9: ENEL GENERACION PIURA S.A. | BI9: ENEL GENERACION PIURA S.A. | BJ9: ENEL GENERACION PIURA S.A. | BK9: ENGIE ENERGIA PERU S.A.A. | BL9: ENGIE ENERGIA PERU S.A.A. | BM9: ENGIE ENERGIA PERU S.A.A. | BN9: ENGIE ENERGIA PERU S.A.A. | BO9: ENGIE ENERGIA PERU S.A.A. | BP9: ENGIE ENERGIA PERU S.A.A. | BQ9: ENGIE ENERGIA PERU S.A.A. | BR9: ENGIE ENERGIA PERU S.A.A. | BS9: ENGIE ENERGIA PERU S.A.A. | BT9: ENGIE ENERGIA PERU S.A.A. | BU9: ENGIE ENERGIA PERU S.A.A. | BV9: ENGIE ENERGIA PERU S.A.A. | BW9: ENGIE ENERGIA PERU S.A.A. | BX9: ENGIE ENERGIA PERU S.A.A. | BY9: INFRAESTRUCTURAS Y ENERGIAS DEL PERU S.A.C. | BZ9: INFRAESTRUCTURAS Y ENERGIAS DEL PERU S.A.C. | CA9: INVERSIONES SHAQSHA S.A.C. | CB9: ORYGEN PERU S.A.A. | CC9: ORYGEN PERU S.A.A. | CD9: ORYGEN PERU S.A.A. | CE9: ORYGEN PERU S.A.A. | CF9: ORYGEN PERU S.A.A. | CG9: ORYGEN PERU S.A.A. | CH9: ORYGEN PERU S.A.A. | CI9: ORYGEN PERU S.A.A. | CJ9: ORYGEN PERU S.A.A. | CK9: ORYGEN PERU S.A.A. | CL9: ORYGEN PERU S.A.A. | CM9: ORYGEN PERU S.A.A. | CN9: SAMAY I S.A.C | CO9: SAMAY I S.A.C | CP9: SAMAY I S.A.C | CQ9: SAMAY I S.A.C | CR9: TERMOCHILCA S.A.C. | CS9: TERMOCHILCA S.A.C. | CT9: TRANSMISION ANDINA DE GENERACION S.A.C. | CU9: TRANSMISION ANDINA DE GENERACION S.A.C. | CV9: CELARIS ENERGY S.A. | CW9: COLCA SOLAR S.A.C. | CX9: ENERGIA RENOVABLE DEL SUR S.A. | CY9: GR CORTARRAMA SOCIEDAD ANONIMA CERRADA | CZ9: GR TARUCA SOCIEDAD ANONIMA CERRADA | DA9: KONDU SAC | DB9: VARI ENERGIA S.A.C. | DC9: ORAZUL ENERGY PERÚ | DD9: ORAZUL ENERGY PERÚ | DE9: KALLPA GENERACION S.A. | DF9: KALLPA GENERACION S.A. | DG9: SAN GABAN | DH9: MAJA ENERGIA S.A.C. | DI9: EMPRESA DE GENERACION ELECTRICA CANCHAYLLO SAC | DJ9: EMPRESA DE GENERACION ELECTRICA SANTA ANA S.A.C. | DK9: EMPRESA ELECTRICA AGUA AZUL | DL9: EMPRESA ELECTRICA RIO DOBLE | DM9: HIDROCAÑETE S.A. | DN9: HUAURA POWER GROUP S.A. | DO9: MOQUEGUA FV S.A.C. | DP9: PANAMERICANA SOLAR SAC. | DQ9: PARQUE EOLICO MARCONA S.A.C. | DR9: PARQUE EOLICO TRES HERMANAS S.A.C. | DS9: TACNA SOLAR SAC. | DT9: ELECTRICA YANAPAMPA SAC | DU9: ANDEAN POWER S.A.C. | DV9: ASOCIACIÓN SANTA LUCIA DE CHACAS | DW9: ATRIA ENERGIA S.A.C. | DX9: COENERGY S.A.C. | DY9: EGEJUNIN | DZ9: EGEJUNIN | EA9: EGEJUNIN | EB9: EGEJUNIN | EC9: ENERGÍA EÓLICA S.A. | ED9: ENERGÍA EÓLICA S.A. | EE9: ENGIE ENERGIA PERU S.A.A. | EF9: ENGIE ENERGIA PERU S.A.A. | EG9: ENGIE ENERGIA PERU S.A.A. | EH9: ENGIE ENERGIA PERU S.A.A. | EI9: ENGIE ENERGIA PERU S.A.A. | EJ9: ENGIE ENERGIA PERU S.A.A. | EK9: GENERACIÓN ANDINA S.A.C. | EL9: GENERACIÓN ANDINA S.A.C. | EM9: GENERADORA DE ENERGÍA DEL PERÚ | EN9: GENERADORA DE ENERGÍA DEL PERÚ | EO9: GENERADORA DE ENERGÍA DEL PERÚ | EP9: GENERADORA DE ENERGÍA DEL PERÚ | EQ9: GR PAINO SOCIEDAD ANONIMA CERRADA | ER9: JOYA SOLAR S.A.C. | ES9: MAJES ARCUS S.A.C. | ET9: ORYGEN PERU S.A.A. | EU9: ORYGEN PERU S.A.A. | EV9: ORYGEN PERU S.A.A. | EW9: ORYGEN PERU S.A.A. | EX9: ORYGEN PERU S.A.A. | EY9: PETRAMAS | EZ9: PETRAMAS | FA9: PETRAMAS | FB9: PETRAMAS | FC9: REPARTICIÓN ARCUS S.A.C. | FD9: SINERSA | FE9: SINERSA | FF9: SINERSA | FG9: BIOENERGIA DEL CHIRA S.A. | FH9: GM OPERACIONES S.A.C. | FI9: GM OPERACIONES S.A.C. | FJ9: AGRO INDUSTRIAL PARAMONGA S.A. | FK9: AGROAURORA S.A.C. | FL9: AGROINDUSTRIAS SAN JACINTO S.A.A. | FM9: AGROLMOS SOCIEDAD ANONIMA - AGROLMOS S.A. | FN9: CASA GRANDE S.A.A. | FQ9: UNACEM PERU S.A. | FR9: ELECTRO ORIENTE | FS9: AGUAS Y ENERGIA PERU | FT9: ELECTRO ZAÑA S.A.C. | FU9: ELECTRONOROESTE S.A. | FV9: SDE PIURA | FW9: SINERSA | FX9: SINERSA
C10: SAN GABAN III | D10: MANTARO | E10: RESTITUCION | F10: TUMBES MAK 1 | G10: TUMBES MAK 2 | H10: CARHUAQUERO | I10: CAÑON DEL PATO | J10: AGUAYTIA TG1 | K10: AGUAYTIA TG2 | L10: KALLPA TG1 | M10: KALLPA TG2 | N10: KALLPA TG3 | O10: KALLPA TV | P10: LFLORES TG1 | Q10: LFLORES TV | R10: CERRO DEL AGUILA | S10: CERRODELAGUILAG4 | T10: SHOUGESA TV1 | U10: SHOUGESA TV2 | V10: SHOUGESA TV3 | W10: SHOUGESA CUMMINS | X10: MACHUPICCHU | Y10: ARICOTA 1 | Z10: ARICOTA 2 | AA10: INDEPENDENCIA | AB10: CHARCANI I,II,III | AC10: CHARCANI IV | AD10: CHARCANI V | AE10: CHARCANI VI | AF10: CHILINA TG | AG10: MOLLENDO 1, 2, 3 | AH10: CHILINA (SULZ 1,2) | AI10: SAN GABAN II | AJ10: PLATANAL | AK10: RECKA | AL10: RF ETEN TG1 | AM10: RF ETEN TG2 | AN10: CHAGLLA GP1 | AO10: CHAGLLA | AP10: LA VIRGEN | AQ10: CHIMAY | AR10: YANANGO | AS10: HUANCHOR | AT10: MARAÑON | AU10: STA TERESA | AV10: FENIX GT11 | AW10: FENIX GT12 | AX10: FENIX TV10 | AY10: YAUPI | AZ10: MALPASO | BA10: CAHUA | BB10: ARCATA | BC10: GALLITO CIEGO | BD10: CHEVES | BE10: SANTA ROSA 1 | BF10: SANTA ROSA 2 | BG10: HUANZA | BH10: MALACAS2 TG4 | BI10: MALACAS3 TG 5 | BJ10: MALACAS1 TG6 | BK10: RF ILO2 TG1 | BL10: RF ILO2 TG2 | BM10: RF ILO2 TG3 | BN10: YUNCAN | BO10: CHILCA1 TG1 | BP10: CHILCA1 TG2 | BQ10: CHILCA1 TG3 | BR10: CHILCA-TV | BS10: CHILCA2 TG41 | BT10: CHILCA2-TV | BU10: CTNEPI_TG41 | BV10: CTNEPI_TG42 | BW10: CTNEPI_TG43 | BX10: QUITARACSA | BY10: RF PTO MALDONADO | BZ10: RF PUCALLPA | CA10: PARIAC | CB10: HUINCO | CC10: MATUCANA | CD10: MOYOPAMPA | CE10: CALLAHUANCA | CF10: HUAMPANI | CG10: STA ROSA WEST TG7 | CH10: UTI_5 | CI10: UTI_6 | CJ10: VENTANILLA 3 | CK10: VENTANILLA 4 | CL10: VENTANILLA TV | CM10: STAROSA TG8 | CN10: PTO_BRVO TG1 | CO10: PTO_BRVO TG2 | CP10: PTO_BRVO TG3 | CQ10: PTO_BRVO TG4 | CR10: OLLEROS TG1 | CS10: OLLEROS TV | CT10: OROYA | CU10: PACHACHACA | CV10: MANTA I | CW10: CS YARUCAYA | CX10: SAN JUAN | CY10: MATARANI | CZ10: DUNA | DA10: CARHUAQUERO (CS) | DB10: ANASHIRONI | DC10: CARHUAQUERO4 | DD10: CAÑA BRAVA | DE10: SUNNY | DF10: SUNNY EXPANSION | DG10: TUPURI | DH10: RONCADOR | DI10: CANCHAYLLO | DJ10: RENOVANDESH1 | DK10: POTRERO | DL10: PIZARRAS | DM10: NIMPERIAL | DN10: YARUCAYA | DO10: MOQUEGUA-SOLAR | DP10: PANAMERICANA-SOLAR | DQ10: PQE-EOLICO-MARCONA | DR10: PQE-EOLICO-3-HERMANAS | DS10: TACNA-SOLAR | DT10: YANAPAMPA | DU10: CARHUAC | DV10: HUALLIN | DW10: PURMACANA | DX10: COENERGY | DY10: HUASAHUASI | DZ10: STACRUZ_1_2 | EA10: RUNATULLO_II | EB10: RUNATULLO_III | EC10: PQE-EOLICO-TALARA | ED10: PQE-EOLICO-CUPISNIQUE | EE10: INTIPAMPA | EF10: PUNTA LOMITAS-BL1 | EG10: PUNTA LOMITAS-BL2 | EH10: PUN LOMITAS_EXP-BL1 | EI10: PUN LOMITAS_EXP-BL2 | EJ10: EXPANSIÓN INTIPAMPA | EK10: 8AGOSTO | EL10: EL CARMEN | EM10: LA JOYA | EN10: ANGEL_I | EO10: ANGEL_II | EP10: ANGEL_III | EQ10: HUAMBOS | ER10: SAN MARTIN SOLAR | ES10: MAJES | ET10: RUBI | EU10: CH_HER1 | EV10: WAYRA-I | EW10: WAYRA EXTENSION | EX10: CLEMESI | EY10: HUAYCOLORO | EZ10: CALLAO | FA10: DONA_CATALINA | FB10: LAGRINGAV | FC10: REPARTICION | FD10: POECHOS2 | FE10: CHANCAY | FF10: RUCUY | FG10: CANA BRAVA | FH10: REFINERIA TALARA TV1 | FI10: REFINERÍA TALARA TV2 | FJ10: PARAMONGA | FK10: MAPLE | FL10: SAN_JACINTO | FM10: AGROLMOS | FN10: CASA GRANDE | FO10: MVAR | FQ10: CARPAPATA | FR10: CENTRALES ELOR | FS10: PIAS1 | FT10: ZANA | FU10: TABLAZO | FV10: TALLANCA | FW10: CURUMUY | FX10: POECHOS1 | FY10: MVAR
A11: 10/02/2026 | B11: 00:30 | C11: 31.4 | D11: 0.2 | E11: 8.1 | H11: -14.7 | I11: 12.4 | L11: -26.4 | M11: -19.2 | N11: -6.2 | O11: 24.8 | P11: -13.4 | Q11: -14.4 | R11: 73 | S11: 0 | X11: -3.2 | Y11: 1 | Z11: 1.1 | AA11: 0 | AB11: -3.2 | AD11: 7.3 | AI11: 11.8 | AJ11: 7.9 | AN11: -1 | AO11: 46.6 | AP11: 7 | AQ11: 29.8 | AR11: 8.6 | AS11: 0.8 | AT11: 2.6 | AU11: 1.5 | AY11: 11.2 | AZ11: 0 | BA11: 1 | BB11: 1.2 | BC11: 0.1 | BD11: 1.6 | BG11: 0 | BJ11: 0 | BN11: 10 | BP11: 0 | BQ11: 0 | BS11: -2.2 | BT11: -1.7 | CA11: -0.2 | CB11: 15.3 | CC11: 24.9 | CD11: 5.1 | CE11: 7.6 | CF11: 3.8 | CJ11: 5.8 | CK11: 8.5 | CL11: -22.3 | CR11: -13 | CS11: -14.4 | CT11: -2.2 | CU11: 0.5 | CV11: 1.4 | CX11: -4.5 | CY11: 0 | CZ11: 0 | DB11: 0.1 | DC11: -0.1 | DD11: -0.9 | DE11: 0 | DH11: 0 | DI11: 1.4 | DJ11: 0.2 | DK11: -1.5 | DL11: 0.2 | DM11: 0.4 | DO11: 0 | DP11: 0 | DQ11: -6.6 | DR11: 6.1 | DS11: 0 | DT11: 0 | DU11: 0.4 | DV11: 0.6 | DW11: 0 | DY11: -4.4 | DZ11: 0.4 | EA11: 3.3 | EB11: 3 | EE11: 0 | EF11: -8.8 | EG11: -7.4 | EH11: -1.3 | EI11: -0.6 | EK11: 2.6 | EL11: -0.1 | EM11: 1.3 | EN11: 0.2 | EO11: 0.2 | EP11: 0.2 | EQ11: -0.75 | ER11: 0 | ES11: 0 | ET11: 0 | EU11: 0 | EV11: 4.6 | EW11: -0.4 | EX11: 0 | EY11: 2 | EZ11: 0.3 | FA11: 0.8 | FB11: 0.5 | FC11: 0 | FD11: 0.2 | FE11: 1.6 | FF11: 1.3 | FG11: 2 | FH11: 11.4 | FI11: 0.4 | FJ11: 3.5 | FK11: 0.9 | FL11: 2.1 | FM11: 3.7 | FN11: 10.64 | FO11: 245.39 | FQ11: 1.9 | FR11: -0.65 | FS11: 2.8 | FT11: 1.7 | FU11: 1.3 | FV11: 2.70232 | FW11: -0.5 | FX11: 2.4 | FY11: 11.65232
A12: 10/02/2026 | B12: 01:00 | C12: 26.5 | D12: -15.6 | E12: 3.4 | H12: -15.9 | I12: 0.5 | L12: -26.3 | M12: -30 | N12: -17.9 | O12: 21.6 | P12: -15.4 | Q12: -13.8 | R12: 60.4 | S12: -0.4 | X12: -7.6 | Y12: 0.9 | Z12: 0.9 | AA12: 0 | AB12: -3.3 | AD12: 7.2 | AI12: 10.9 | AJ12: 7.8 | AN12: -1.1 | AO12: 46.4 | AP12: 6.9 | AQ12: 33.7 | AR12: 7.6 | AS12: 0.3 | AT12: 2.6 | AU12: 1.1 | AY12: 2.4 | AZ12: 0 | BA12: -1.7 | BB12: 1.2 | BC12: 0.1 | BD12: -0.6 | BG12: 0 | BJ12: 0 | BN12: 9.9 | BP12: 0 | BQ12: 0 | BS12: -3.4 | BT12: -2 | CA12: -0.3 | CB12: 14.3 | CC12: 28.7 | CD12: 2 | CE12: 7.3 | CF12: 3.8 | CJ12: 1.4 | CK12: 5.3 | CL12: -29.6 | CR12: -16.6 | CS12: -16.6 | CT12: -2.2 | CU12: 0.5 | CV12: 1.4 | CX12: -3.5 | CY12: 0 | CZ12: 0 | DB12: 0 | DC12: 0 | DD12: -1 | DE12: 0 | DH12: 0 | DI12: 1.3 | DJ12: 0.2 | DK12: -1.7 | DL12: 0.3 | DM12: 0.4 | DO12: 0 | DP12: 0 | DQ12: -5.3 | DR12: 4.4 | DS12: 0 | DT12: 0 | DU12: 0.4 | DV12: 0.6 | DW12: 0 | DY12: -4.4 | DZ12: 0.6 | EA12: 3.1 | EB12: 2.9 | EE12: 0 | EF12: -9 | EG12: -10.1 | EH12: -1.4 | EI12: -0.9 | EK12: 2.6 | EL12: -0.1 | EM12: 1.4 | EN12: 0.2 | EO12: 0.2 | EP12: 0.2 | EQ12: 0 | ER12: 0 | ES12: 0 | ET12: 0 | EU12: 0 | EV12: 4.7 | EW12: 0.3 | EX12: 0 | EY12: 2 | EZ12: 0.3 | FA12: 0.8 | FB12: 0.5 | FC12: 0 | FD12: 0.2 | FE12: 1.5 | FF12: 1.3 | FG12: 2 | FH12: 10.7 | FI12: 0.5 | FJ12: 3.5 | FK12: 0.8 | FL12: 2 | FM12: 4.3 | FN12: 10.8 | FO12: 124.3 | FQ12: 1.9 | FR12: -0.81 | FS12: 2.7 | FT12: 1.6 | FU12: 1.3 | FV12: 2.69984 | FW12: -0.7 | FX12: 2.3 | FY12: 10.98984
A13: 10/02/2026 | B13: 01:30 | C13: 33.2 | D13: 7.3 | E13: 9 | H13: -11.3 | I13: 2.6 | L13: -25.4 | M13: -16 | N13: -2.8 | O13: 20.9 | P13: -16.4 | Q13: -15.9 | R13: 65.4 | S13: 0.2 | X13: -5 | Y13: 0.9 | Z13: 1.1 | AA13: 0 | AB13: -3.2 | AD13: 7.3 | AI13: 11.8 | AJ13: -0.9 | AN13: -1.1 | AO13: 46 | AP13: 6.6 | AQ13: 31 | AR13: 7.9 | AS13: 0.6 | AT13: 2.6 | AU13: 1.4 | AY13: 11.2 | AZ13: 0 | BA13: 1 | BB13: 1.2 | BC13: 0 | BD13: 2.5 | BG13: 0 | BJ13: 0 | BN13: 9.8 | BP13: 0 | BQ13: 0 | BS13: -2.8 | BT13: -2 | CA13: -0.2 | CB13: 13.9 | CC13: 26 | CD13: -0.6 | CE13: 7.4 | CF13: 1.8 | CJ13: -4.3 | CK13: -1.7 | CL13: -34.5 | CR13: -20.3 | CS13: -18.7 | CT13: -2.5 | CU13: 0.5 | CV13: 1.4 | CX13: -4.7 | CY13: 0 | CZ13: 0 | DB13: 0.1 | DC13: -0.1 | DD13: -0.8 | DE13: 0 | DH13: 0 | DI13: 1.3 | DJ13: 0.2 | DK13: -1.2 | DL13: 0.3 | DM13: 0.5 | DO13: 0 | DP13: 0 | DQ13: -5.6 | DR13: 8.3 | DS13: 0 | DT13: -0.1 | DU13: 0.4 | DV13: 0.6 | DW13: 0.1 | DY13: -4.6 | DZ13: 0.7 | EA13: 3.2 | EB13: 2.9 | EE13: 0 | EF13: -4.8 | EG13: -11 | EH13: -0.7 | EI13: -0.5 | EK13: 2.6 | EL13: 0 | EM13: 0 | EN13: 0.2 | EO13: 0.2 | EP13: 0.2 | EQ13: 0 | ER13: 0 | ES13: 0 | ET13: 0 | EU13: 0 | EV13: 4.9 | EW13: 0.7 | EX13: 0 | EY13: 2 | EZ13: 0.3 | FA13: 0.8 | FB13: 0.5 | FC13: 0 | FD13: 0.2 | FE13: 1.4 | FF13: 1.1 | FG13: 2 | FH13: 10.9 | FI13: 0.1 | FJ13: 3 | FK13: 0.7 | FL13: 1.8 | FM13: 4.3 | FN13: 10.76 | FO13: 180.06 | FQ13: 2.1 | FR13: -0.59 | FS13: 2.6 | FT13: 1.7 | FU13: 1.3 | FV13: 2.69502 | FW13: -0.7 | FX13: 2.4 | FY13: 11.50502
A14: 10/02/2026 | B14: 02:00 | C14: 30.6 | D14: 4.2 | E14: 8.2 | H14: -12.6 | I14: 1.3 | L14: -26.7 | M14: -22.4 | N14: -9.4 | O14: 21.5 | P14: -19.1 | Q14: -16.2 | R14: 65.7 | S14: -0.1 | X14: -4.8 | Y14: 0.5 | Z14: 0.4 | AA14: 0 | AB14: -3.3 | AD14: 5.8 | AI14: 10.4 | AJ14: -0.6 | AN14: -1.2 | AO14: 45.6 | AP14: 6.7 | AQ14: 21.7 | AR14: 4.1 | AS14: 0.2 | AT14: 2.6 | AU14: 1.2 | AY14: 9.7 | AZ14: 0 | BA14: 0.4 | BB14: 1.2 | BC14: 0 | BD14: -0.1 | BG14: 0 | BJ14: 0 | BN14: 11.2 | BP14: 0 | BQ14: 0 | BS14: -3.7 | BT14: -2.3 | CA14: -0.3 | CB14: 8.5 | CC14: 10.3 | CD14: -3.5 | CE14: 0.9 | CF14: -0.1 | CJ14: -4.3 | CK14: -1.6 | CL14: -33.8 | CR14: -21.2 | CS14: -19.3 | CT14: -2.2 | CU14: 0.6 | CV14: 1.4 | CX14: -3.3 | CY14: 0 | CZ14: 0 | DB14: 0 | DC14: -0.1 | DD14: -0.9 | DE14: 0 | DH14: 0 | DI14: 1.3 | DJ14: 0.2 | DK14: -0.9 | DL14: 0.3 | DM14: 0.5 | DO14: 0 | DP14: 0 | DQ14: -6.3 | DR14: 8.2 | DS14: 0 | DT14: -0.1 | DU14: 0.4 | DV14: 0.6 | DW14: 0.1 | DY14: -4.6 | DZ14: 0.9 | EA14: 3.2 | EB14: 2.9 | EE14: 0 | EF14: -5.3 | EG14: -6.8 | EH14: -0.8 | EI14: -0.6 | EK14: 2.6 | EL14: 0 | EM14: 0 | EN14: 0.2 | EO14: 0.2 | EP14: 0.2 | EQ14: 0 | ER14: 0 | ES14: 0 | ET14: 0 | EU14: 0 | EV14: 4.9 | EW14: 0 | EX14: 0 | EY14: 2 | EZ14: 0.3 | FA14: 0.8 | FB14: 0.5 | FC14: 0 | FD14: 0.2 | FE14: 1.2 | FF14: 0.9 | FG14: 2 | FH14: 10.3 | FI14: 0.2 | FJ14: 2.2 | FK14: 0.6 | FL14: 2.1 | FM14: 4.3 | FN14: 9.92 | FO14: 100.62 | FQ14: 2.2 | FR14: -0.55 | FS14: 2.4 | FT14: 1.7 | FU14: 1.3 | FV14: 2.69435 | FW14: -0.8 | FX14: 2.4 | FY14: 11.34435
A15: 10/02/2026 | B15: 02:30 | C15: 28.6 | D15: -7.7 | E15: 6.3 | H15: -11.9 | I15: 8.3 | L15: -27.4 | M15: -23.4 | N15: -10.5 | O15: 18.2 | P15: -26.6 | Q15: -20 | R15: 63.8 | S15: 0.1 | X15: -7.1 | Y15: 0.9 | Z15: 1 | AA15: 0 | AB15: -3.2 | AD15: 8.4 | AI15: 9.9 | AJ15: 11.6 | AN15: -1.2 | AO15: 44.7 | AP15: 6.8 | AQ15: 21.6 | AR15: 4.2 | AS15: 0.5 | AT15: 2.6 | AU15: 1 | AY15: 8.8 | AZ15: 0 | BA15: 0.3 | BB15: 1.2 | BC15: 0.2 | BD15: 0.7 | BG15: 0 | BJ15: 0 | BN15: 10.7 | BP15: 0 | BQ15: 0 | BS15: -3.4 | BT15: -2.2 | CA15: -0.3 | CB15: 8.3 | CC15: 10.3 | CD15: -4.2 | CE15: 0.9 | CF15: 0.1 | CJ15: -5.8 | CK15: -2.7 | CL15: -35.6 | CR15: -22.6 | CS15: -19.4 | CT15: -2.4 | CU15: 0.5 | CV15: 1.4 | CX15: -3.1 | CY15: 0 | CZ15: 0 | DB15: 0 | DC15: -0.1 | DD15: -0.9 | DE15: 0 | DH15: 0 | DI15: 1.3 | DJ15: 0.1 | DK15: -1 | DL15: 0.3 | DM15: 0.5 | DO15: 0 | DP15: 0 | DQ15: -5.7 | DR15: 9 | DS15: 0 | DT15: -0.1 | DU15: 0.4 | DV15: 0.6 | DW15: 0.1 | DY15: -4.6 | DZ15: 0.8 | EA15: 3.2 | EB15: 2.8 | EE15: 0 | EF15: -3.6 | EG15: -6.9 | EH15: -0.4 | EI15: -0.4 | EK15: 2.6 | EL15: 0 | EM15: 0 | EN15: 0.2 | EO15: 0.2 | EP15: 0.2 | EQ15: 0 | ER15: 0 | ES15: 0 | ET15: 0 | EU15: 0 | EV15: 4.8 | EW15: 0 | EX15: 0 | EY15: 2 | EZ15: 0.3 | FA15: 0.8 | FB15: 0.5 | FC15: 0 | FD15: 0.2 | FE15: 1.2 | FF15: 1 | FG15: 2 | FH15: 10.2 | FI15: 0.2 | FJ15: 2.6 | FK15: 0.5 | FL15: 1.7 | FM15: 4.3 | FN15: 10.4 | FO15: 82.5 | FQ15: 1.9 | FR15: -0.57 | FS15: 2.5 | FT15: 1.7 | FU15: 1.3 | FV15: 2.6949 | FW15: -0.9 | FX15: 2.4 | FY15: 11.0249
A16: 10/02/2026 | B16: 03:00 | C16: 33.7 | D16: 8.9 | E16: 9 | H16: -11.9 | I16: 12.6 | L16: -25.6 | M16: -18.3 | N16: -5.8 | O16: 20.7 | P16: -25.3 | Q16: -19.6 | R16: 68.3 | S16: 0.1 | X16: -2.8 | Y16: 1.1 | Z16: 1.4 | AA16: 0 | AB16: -3.2 | AD16: 10.1 | AI16: 11.4 | AJ16: 10.6 | AN16: -1.3 | AO16: 43.8 | AP16: 4.8 | AQ16: 21.7 | AR16: 4.2 | AS16: 0.6 | AT16: 2.6 | AU16: 1.5 | AY16: 10.2 | AZ16: 0 | BA16: 1.2 | BB16: 1.2 | BC16: 0 | BD16: 1.2 | BG16: 0 | BJ16: 0 | BN16: 9.8 | BP16: 0 | BQ16: 0 | BS16: -3.9 | BT16: -2.4 | CA16: -0.2 | CB16: 8 | CC16: 10.3 | CD16: -3.5 | CE16: 1 | CF16: 0 | CJ16: -5.4 | CK16: -2.5 | CL16: -35.1 | CR16: -29 | CS16: -21.5 | CT16: -2.4 | CU16: 0.5 | CV16: 0.9 | CX16: -3.5 | CY16: 0 | CZ16: 0 | DB16: 0.1 | DC16: -0.1 | DD16: -0.8 | DE16: 0 | DH16: 0 | DI16: 1.2 | DJ16: 0.2 | DK16: -1.1 | DL16: 0.3 | DM16: 0.4 | DO16: 0 | DP16: 0 | DQ16: -4.6 | DR16: 9.6 | DS16: 0 | DT16: -0.2 | DU16: 0.4 | DV16: 0.6 | DW16: 0.1 | DY16: -4.5 | DZ16: 1.1 | EA16: 3.2 | EB16: 2.9 | EE16: 0 | EF16: -6.5 | EG16: -8.3 | EH16: -1 | EI16: -0.7 | EK16: 2.6 | EL16: 0 | EM16: 0 | EN16: 0.2 | EO16: 0.2 | EP16: 0.2 | EQ16: 0 | ER16: 0 | ES16: 0 | ET16: 0 | EU16: 0 | EV16: 4.7 | EW16: -0.7 | EX16: 0 | EY16: 2 | EZ16: 0.3 | FA16: 0.8 | FB16: 0.5 | FC16: 0 | FD16: 0.2 | FE16: 1.4 | FF16: 1.1 | FG16: 2 | FH16: 10.8 | FI16: 0.4 | FJ16: 2 | FK16: 1.9 | FL16: 2.1 | FM16: 4.3 | FN16: 11.21 | FO16: 128.71 | FQ16: 1.8 | FR16: -0.61 | FS16: 2.6 | FT16: 1.7 | FU16: 1.3 | FV16: 2.69679 | FW16: -0.7 | FX16: 1.7 | FY16: 10.48679
A17: 10/02/2026 | B17: 03:30 | C17: 30.1 | D17: -11.4 | E17: 5.6 | H17: -13.5 | I17: 1.5 | L17: -34.6 | M17: -27.5 | N17: -14.4 | O17: 13.6 | P17: -24.9 | Q17: -20.8 | R17: 59.4 | S17: 0 | X17: -2.9 | Y17: 1.1 | Z17: 1.2 | AA17: 0 | AB17: -3.2 | AD17: 10.5 | AI17: 10.8 | AJ17: 0.4 | AN17: -1.3 | AO17: 43.3 | AP17: 5.6 | AQ17: 22.3 | AR17: 3.9 | AS17: 0.3 | AT17: 2.6 | AU17: -0.2 | AY17: 9.2 | AZ17: 0 | BA17: -0.5 | BB17: 1.2 | BC17: 0 | BD17: -0.8 | BG17: 0 | BJ17: 0 | BN17: 8.1 | BP17: 0 | BQ17: 0 | BS17: -5.7 | BT17: -3.2 | CA17: 0 | CB17: 8.5 | CC17: 10.7 | CD17: -3.5 | CE17: 3.4 | CF17: -0.2 | CJ17: -9.1 | CK17: -6.3 | CL17: -40.5 | CR17: -26 | CS17: -21.5 | CT17: -2.2 | CU17: 0.5 | CV17: 0.9 | CX17: -3.8 | CY17: 0 | CZ17: 0 | DB17: 0.1 | DC17: -0.1 | DD17: -0.9 | DE17: 0 | DH17: 0 | DI17: 1.3 | DJ17: 0.2 | DK17: -0.9 | DL17: 0.2 | DM17: 0.4 | DO17: 0 | DP17: 0 | DQ17: -5.1 | DR17: 9.1 | DS17: 0 | DT17: -0.3 | DU17: 0.4 | DV17: 0.6 | DW17: 0.1 | DY17: -4.6 | DZ17: 1.2 | EA17: 3.2 | EB17: 2.9 | EE17: 0 | EF17: -9.5 | EG17: -11 | EH17: -1.5 | EI17: -1 | EK17: 2.6 | EL17: 0 | EM17: 0 | EN17: 0.2 | EO17: 0.2 | EP17: 0.2 | EQ17: 0 | ER17: 0 | ES17: 0 | ET17: 0 | EU17: 0 | EV17: 4.8 | EW17: -0.3 | EX17: 0 | EY17: 2 | EZ17: 0.3 | FA17: 0.8 | FB17: 0.5 | FC17: 0 | FD17: 0.2 | FE17: 1.4 | FF17: 1.1 | FG17: 2 | FH17: 10.8 | FI17: 0.1 | FJ17: 2.4 | FK17: 2.1 | FL17: 2.1 | FM17: 4.3 | FN17: 10.77 | FO17: 10.07 | FQ17: 1.9 | FR17: -0.68 | FS17: 2.6 | FT17: 1.7 | FU17: 1.3 | FV17: 2.69945 | FW17: -0.7 | FX17: 1.6 | FY17: 10.41945
A18: 10/02/2026 | B18: 04:00 | C18: 29.8 | D18: -12.7 | E18: 4.6 | H18: -13.3 | I18: -7.3 | L18: -35.8 | M18: -29.6 | N18: -16.5 | O18: 10 | P18: -26.2 | Q18: -20.6 | R18: 55.5 | S18: 0.1 | X18: -5.6 | Y18: 1.1 | Z18: 1.3 | AA18: 0 | AB18: -3.3 | AD18: 10.4 | AI18: 10.5 | AJ18: -2.3 | AN18: -1.3 | AO18: 43.8 | AP18: 6.3 | AQ18: 23 | AR18: 3.8 | AS18: 0.3 | AT18: 2.6 | AU18: 1.2 | AY18: 8.4 | AZ18: 0 | BA18: 0 | BB18: 1.2 | BC18: 0.1 | BD18: 0.2 | BG18: 0 | BJ18: 0 | BN18: 8.2 | BP18: 0 | BQ18: 0 | BS18: -6 | BT18: -3.3 | CA18: 0 | CB18: 8 | CC18: 10.9 | CD18: -2.6 | CE18: 1 | CF18: 0.1 | CJ18: -11.2 | CK18: -8.5 | CL18: -43.6 | CR18: -22.7 | CS18: -20.2 | CT18: -2.2 | CU18: 0.7 | CV18: 1.1 | CX18: -4 | CY18: 0 | CZ18: 0 | DB18: -0.1 | DC18: 0 | DD18: -0.9 | DE18: 0 | DH18: 0 | DI18: 1.4 | DJ18: 0.2 | DK18: -1.1 | DL18: 0.3 | DM18: 0.4 | DO18: 0 | DP18: 0 | DQ18: -4.9 | DR18: 4.8 | DS18: 0 | DT18: -0.4 | DU18: 0.4 | DV18: 0.6 | DW18: 0 | DY18: -4.6 | DZ18: 0.6 | EA18: 3.2 | EB18: 2.8 | EE18: 0 | EF18: -8.8 | EG18: -10.5 | EH18: -1.3 | EI18: -0.8 | EK18: 2.6 | EL18: 0 | EM18: 0 | EN18: 0.2 | EO18: 0.2 | EP18: 0.2 | EQ18: -0.99 | ER18: 0 | ES18: 0 | ET18: 0 | EU18: 0 | EV18: 4.5 | EW18: -0.6 | EX18: 0 | EY18: 2 | EZ18: 0.3 | FA18: 0.8 | FB18: 0.5 | FC18: 0 | FD18: 0.2 | FE18: 1.4 | FF18: 1.1 | FG18: 2 | FH18: 10.3 | FI18: 0.6 | FJ18: 2 | FK18: 1.9 | FL18: 2.1 | FM18: 4.3 | FN18: 10.63 | FO18: -27.06 | FQ18: 1.7 | FR18: -0.7 | FS18: 2.6 | FT18: 1.7 | FU18: 1.3 | FV18: 2.68917 | FW18: -0.8 | FX18: 1.5 | FY18: 9.98917
A19: 10/02/2026 | B19: 04:30 | C19: 31.7 | D19: 3.1 | E19: 7.5 | H19: -12.6 | I19: 0.1 | L19: -31.2 | M19: -22.1 | N19: -8.7 | O19: 14.1 | P19: -28.4 | Q19: -20.7 | R19: 62 | S19: 0.2 | X19: -4.6 | Y19: 1.2 | Z19: 1.6 | AA19: 0 | AB19: -3.2 | AD19: 11.1 | AI19: 11.3 | AJ19: -4 | AN19: -1.2 | AO19: 43.5 | AP19: 6 | AQ19: 22.2 | AR19: 3.9 | AS19: 0.5 | AT19: 2.6 | AU19: 1.7 | AY19: 8.3 | AZ19: 0 | BA19: 0.6 | BB19: 1.2 | BC19: 0 | BD19: 3.9 | BG19: 0 | BJ19: 0 | BN19: 8.9 | BP19: 0 | BQ19: 0 | BS19: -4.9 | BT19: -2.9 | CA19: -0.2 | CB19: 8.1 | CC19: 10.9 | CD19: -3.4 | CE19: 0.9 | CF19: -0.1 | CJ19: -9.6 | CK19: -6.8 | CL19: -41.5 | CR19: -23.1 | CS19: -20.4 | CT19: -2.2 | CU19: 0.5 | CV19: 1.3 | CX19: -4.2 | CY19: 0 | CZ19: 0 | DB19: 0.1 | DC19: -0.1 | DD19: -0.9 | DE19: 0 | DH19: 0 | DI19: 1.3 | DJ19: 0.2 | DK19: -1.3 | DL19: 0.3 | DM19: 0.4 | DO19: 0 | DP19: 0 | DQ19: -4.4 | DR19: 5.7 | DS19: 0 | DT19: -0.1 | DU19: 0.4 | DV19: 0.6 | DW19: 0.1 | DY19: -4.6 | DZ19: 0.2 | EA19: 3.2 | EB19: 3 | EE19: 0 | EF19: -5.5 | EG19: -6.2 | EH19: -0.7 | EI19: -0.1 | EK19: 2.7 | EL19: 0 | EM19: 0 | EN19: 0.2 | EO19: 0.2 | EP19: 0.2 | EQ19: -0.86 | ER19: 0 | ES19: 0 | ET19: 0 | EU19: 0 | EV19: 4 | EW19: -4.5 | EX19: 0 | EY19: 2 | EZ19: 0.3 | FA19: 0.8 | FB19: 0.5 | FC19: 0 | FD19: 0.2 | FE19: 1.4 | FF19: 1.1 | FG19: 2.1 | FH19: 10.5 | FI19: 0.4 | FJ19: 2.5 | FK19: 2.2 | FL19: 3.2 | FM19: 4.3 | FN19: 10.87 | FO19: 48.81 | FQ19: 1.9 | FR19: -0.6 | FS19: 2.9 | FT19: 1.6 | FU19: 1.3 | FV19: 2.679 | FW19: -0.7 | FX19: 1.6 | FY19: 10.679
A20: 10/02/2026 | B20: 05:00 | C20: 32.5 | D20: -2.9 | E20: 6.4 | H20: -12.7 | I20: -1.4 | L20: -32.2 | M20: -27.1 | N20: -14.1 | O20: 13.4 | P20: -29.1 | Q20: -21.8 | R20: 62.5 | S20: 0.1 | X20: -3.7 | Y20: 1.2 | Z20: 1.5 | AA20: 0 | AB20: -3.2 | AD20: 12.1 | AI20: 11.4 | AJ20: -3.6 | AN20: -1.2 | AO20: 42.9 | AP20: 6.1 | AQ20: 23.2 | AR20: 3.9 | AS20: 1.2 | AT20: 2.6 | AU20: 0.9 | AY20: 7.7 | AZ20: 0 | BA20: -0.1 | BB20: 1.2 | BC20: 0 | BD20: 0.3 | BG20: 0 | BJ20: 0 | BN20: 11 | BP20: 0 | BQ20: 0 | BS20: -4.5 | BT20: -2.7 | CA20: -0.5 | CB20: 7.7 | CC20: 11.4 | CD20: -2.9 | CE20: 0.9 | CF20: 0 | CJ20: -8.8 | CK20: -6.1 | CL20: -40.1 | CR20: -22.8 | CS20: -20.3 | CT20: -2.2 | CU20: 0.3 | CV20: 1.4 | CX20: -4.2 | CY20: 0 | CZ20: -0.49 | DB20: 0 | DC20: -0.1 | DD20: -0.8 | DE20: 0 | DH20: 0 | DI20: 1.3 | DJ20: 0.2 | DK20: -1.3 | DL20: 0.3 | DM20: 0.4 | DO20: 0 | DP20: 0 | DQ20: -4.1 | DR20: 6.2 | DS20: 0.2 | DT20: -0.1 | DU20: 0.4 | DV20: 0.6 | DW20: 0.1 | DY20: -4.6 | DZ20: 0.5 | EA20: 3.2 | EB20: 3 | EE20: 0 | EF20: -7 | EG20: -8.9 | EH20: -1 | EI20: -0.5 | EK20: 2.7 | EL20: 0 | EM20: 0 | EN20: 0.2 | EO20: 0.2 | EP20: 0.2 | EQ20: -1.94 | ER20: 0 | ES20: 0.3 | ET20: 0 | EU20: 0 | EV20: 2.4 | EW20: -4.5 | EX20: 0 | EY20: 2 | EZ20: 0.3 | FA20: 0.8 | FB20: 0.5 | FC20: 0.3 | FD20: 0.2 | FE20: 1.4 | FF20: 1.1 | FG20: 2 | FH20: 10.5 | FI20: 0 | FJ20: 1.2 | FK20: 1.8 | FL20: 2.8 | FM20: 4.3 | FN20: 10.42 | FO20: 22.29 | FQ20: 1.9 | FR20: -0.11 | FS20: 2.3 | FT20: 1.7 | FU20: 1.3 | FV20: 2.69189 | FW20: -0.6 | FX20: 1.5 | FY20: 10.68189
A21: 10/02/2026 | B21: 05:30 | C21: 31.6 | D21: 10.9 | E21: 9.2 | H21: -11.6 | I21: -0.1 | L21: -25.5 | M21: -16 | N21: -3.6 | O21: 19.6 | P21: -23.8 | Q21: -19.6 | R21: 73.2 | S21: 0.1 | X21: -2.6 | Y21: 1.5 | Z21: 1.9 | AA21: 0 | AB21: -2 | AD21: 14.8 | AI21: 13.3 | AJ21: 7 | AN21: -1.1 | AO21: 43.3 | AP21: 6.2 | AQ21: 21.2 | AR21: 4.4 | AS21: 0.6 | AT21: 2.6 | AU21: 2.1 | AY21: 11.2 | AZ21: 0 | BA21: 1.1 | BB21: 1.2 | BC21: 0 | BD21: 6.4 | BG21: 0 | BJ21: 0 | BN21: 8.2 | BP21: 0 | BQ21: 0 | BS21: -3 | BT21: -2.4 | CA21: 0.1 | CB21: 9 | CC21: 10.7 | CD21: -3.6 | CE21: 1.1 | CF21: 0.1 | CJ21: -4.7 | CK21: -1.9 | CL21: -34.3 | CR21: -18.9 | CS21: -17.9 | CT21: -1.9 | CU21: 0.5 | CV21: 1.4 | CX21: -4 | CY21: 0 | CZ21: -1.71 | DB21: 0 | DC21: 0 | DD21: -0.8 | DE21: 0 | DH21: 0 | DI21: 1.2 | DJ21: 0.3 | DK21: -1.3 | DL21: 0.3 | DM21: 0.5 | DO21: 0 | DP21: 0 | DQ21: -3.8 | DR21: 7 | DS21: 0.5 | DT21: 0 | DU21: 0.4 | DV21: 0.6 | DW21: 0.1 | DY21: -4.6 | DZ21: 0.3 | EA21: 3.3 | EB21: 3 | EE21: 0 | EF21: -5.5 | EG21: -7.2 | EH21: -0.7 | EI21: 0 | EK21: 2.7 | EL21: 0 | EM21: 0 | EN21: 0.2 | EO21: 0.2 | EP21: 0.2 | EQ21: -2.91 | ER21: 0 | ES21: 0.3 | ET21: 0 | EU21: 0 | EV21: 3.7 | EW21: -2.1 | EX21: 0 | EY21: 2 | EZ21: 0.3 | FA21: 0.8 | FB21: 0.5 | FC21: 0.3 | FD21: 0.2 | FE21: 1.6 | FF21: 1.3 | FG21: 1.9 | FH21: 10.6 | FI21: 0.5 | FJ21: 2.7 | FK21: 0.9 | FL21: 2.7 | FM21: 4.3 | FN21: 10.06 | FO21: 150.84 | FQ21: 2.1 | FR21: 0.1 | FS21: 1.9 | FT21: 1.7 | FU21: 1.3 | FV21: 2.69357 | FW21: -0.4 | FX21: 1.6 | FY21: 10.99357
A22: 10/02/2026 | B22: 06:00 | C22: 35.1 | D22: 2.7 | E22: 8.4 | H22: -11.8 | I22: 12.9 | L22: -24.3 | M22: -15.5 | N22: -1.9 | O22: 24.8 | P22: -22.8 | Q22: -17.7 | R22: 71.7 | S22: 0.1 | X22: -3.3 | Y22: 1.3 | Z22: 1 | AA22: 0 | AB22: -3.1 | AD22: 12.9 | AI22: 11.1 | AJ22: 11.9 | AN22: -1.1 | AO22: 44.3 | AP22: 7.4 | AQ22: 21.1 | AR22: 4.2 | AS22: 0.5 | AT22: 2.6 | AU22: 2.1 | AY22: 10.8 | AZ22: 0 | BA22: 0.4 | BB22: 1.2 | BC22: 0.2 | BD22: -1.1 | BG22: 0 | BJ22: 0 | BN22: 8.2 | BP22: 0 | BQ22: 0 | BS22: -3 | BT22: -2 | CA22: -0.3 | CB22: 9 | CC22: 10 | CD22: 4 | CE22: 0.9 | CF22: -0.2 | CJ22: -2.7 | CK22: 0 | CL22: -31 | CR22: -15.9 | CS22: -16.1 | CT22: -1.9 | CU22: 0.5 | CV22: 1.4 | CX22: -3.1 | CY22: 2 | CZ22: 0 | DB22: 0 | DC22: -0.1 | DD22: -0.8 | DE22: 0 | DH22: 0 | DI22: 1.5 | DJ22: 0.2 | DK22: -1.1 | DL22: 0.3 | DM22: 0.4 | DO22: -0.1 | DP22: 0 | DQ22: -3.9 | DR22: 6.1 | DS22: 0.2 | DT22: 0 | DU22: 0.4 | DV22: 0.6 | DW22: 0.1 | DY22: -4.8 | DZ22: 0.1 | EA22: 3.3 | EB22: 3 | EE22: 0.3 | EF22: -5.9 | EG22: -7.4 | EH22: -0.9 | EI22: -0.6 | EK22: 2.7 | EL22: 0 | EM22: 0 | EN22: 0.2 | EO22: 0.2 | EP22: 0.2 | EQ22: 0 | ER22: 1.7 | ES22: 0.4 | ET22: 0.1 | EU22: 0 | EV22: 3.7 | EW22: -2.6 | EX22: 1.9 | EY22: 2 | EZ22: 0.3 | FA22: 0.8 | FB22: 0.5 | FC22: 1.6 | FD22: 0.2 | FE22: 1.6 | FF22: 1.3 | FG22: 1.9 | FH22: 11.1 | FI22: 0.2 | FJ22: 2.5 | FK22: 1.2 | FL22: 2.7 | FM22: 4.3 | FN22: 11.69 | FO22: 189.19 | FQ22: 2.1 | FR22: 0 | FS22: 1.6 | FT22: 1.7 | FU22: 1.3 | FV22: 2.69123 | FW22: -0.4 | FX22: 1.6 | FY22: 10.59123
... A58: 11/02/2026 | B58: 00:00 | C58: 31 | D58: 6.4 | E58: 7.7 | H58: -11.4 | I58: 8.1 | L58: -24 | M58: -34.1 | N58: -12.4 | O58: 25 | P58: -24.8 | Q58: -22 | R58: 77.4 | S58: 0.3 | X58: -1.9 | Y58: 1 | Z58: 0.4 | AA58: 0 | AB58: -3.2 | AD58: 0.2 | AI58: 13.8 | AJ58: -0.5 | AN58: -1.7 | AO58: 50.1 | AP58: 5.3 | AQ58: 35.5 | AR58: 9 | AS58: 0.9 | AT58: 2.6 | AU58: 1.6 | AY58: 10.5 | AZ58: -0.7 | BA58: 1.5 | BB58: 1.2 | BC58: 0.6 | BD58: 0.4 | BG58: 0 | BJ58: 0 | BN58: 0 | BP58: 0 | BQ58: 0 | BS58: 0 | BT58: 0 | CA58: -0.4 | CB58: 32.5 | CC58: 30.9 | CD58: 5.6 | CE58: 11.3 | CF58: 1 | CJ58: 4.7 | CK58: 7.6 | CL58: -23.9 | CR58: -8.4 | CS58: -9.6 | CT58: -2.3 | CU58: 0.6 | CV58: 1.1 | CX58: -3.3 | CY58: 0 | CZ58: -3.92 | DB58: 0.1 | DC58: 0 | DD58: -1 | DE58: 0 | DH58: 0 | DI58: 1.2 | DJ58: 0.2 | DK58: -1.2 | DL58: 0.3 | DM58: 0.4 | DO58: 0 | DP58: 0 | DQ58: -8.7 | DR58: 3.2 | DS58: 0 | DT58: 0.1 | DU58: 0.4 | DV58: 0.6 | DW58: 0 | DY58: -4.7 | DZ58: 0 | EA58: 3.1 | EB58: 3 | EE58: 0 | EF58: 0 | EG58: 0 | EH58: 0 | EI58: 0 | EK58: 2.3 | EL58: -0.2 | EM58: 0 | EN58: 0.2 | EO58: 0.2 | EP58: 0.2 | EQ58: -5.14 | ER58: 0 | ES58: 0 | ET58: 0 | EU58: 0 | EV58: -0.4 | EW58: -9.5 | EX58: 0 | EY58: 2 | EZ58: 0.7 | FA58: 0.7 | FB58: 0.5 | FC58: 0 | FD58: 0.1 | FE58: 1.8 | FF58: 1.5 | FG58: 1.9 | FH58: 8.5 | FI58: 0.1 | FJ58: 2.3 | FK58: 2.1 | FL58: 1.9 | FM58: 4.1 | FN58: 11.3 | FO58: 221.44 | FQ58: 1.7 | FR58: -0.46 | FS58: 1.8 | FT58: 1.9 | FU58: 1.3 | FV58: 0.22426 | FW58: -0.9 | FX58: 3.9 | FY58: 9.46426
A59: EJEC | C59: 784.3 | D59: 1198.75 | E59: 488.65 | F59: 0 | G59: 0 | H59: -180.95 | I59: 218.55 | J59: 0 | K59: 0 | L59: -128.55 | M59: -350 | N59: 19.55 | O59: 1004.25 | P59: 250.45 | Q59: -55.9 | R59: 1738.3 | S59: 1.3 | T59: 0 | U59: 0 | V59: 0 | W59: 0 | X59: -71.25 | Y59: 18.65 | Z59: 13.9 | AA59: 21.15 | AB59: -75.25 | AC59: 0 | AD59: 321.75 | AE59: 0 | AF59: 0 | AG59: 0 | AH59: 0 | AI59: 328.65 | AJ59: 292.9 | AK59: 0 | AL59: 0 | AM59: 0 | AN59: -28.1 | AO59: 1185.85 | AP59: 168.8 | AQ59: 747.1 | AR59: 193.85 | AS59: -2.4 | AT59: 62.4 | AU59: 33.7 | AV59: 0 | AW59: 0 | AX59: 0 | AY59: 271.7 | AZ59: 14.1 | BA59: 35.2 | BB59: 28.5 | BC59: 10.15 | BD59: -70.95 | BE59: 0 | BF59: 0 | BG59: 71.85 | BH59: 0 | BI59: 0 | BJ59: -5.25 | BK59: 0 | BL59: 0 | BM59: 0 | BN59: 303.65 | BO59: 0 | BP59: -323.05 | BQ59: -182.95 | BR59: 0 | BS59: 52.3 | BT59: -26 | BU59: 0 | BV59: 0 | BW59: 0 | BX59: 0 | BY59: 0 | BZ59: 0 | CA59: -6.85 | CB59: 874.2 | CC59: 720.75 | CD59: 242.75 | CE59: 281 | CF59: 81.15 | CG59: 0 | CH59: 0 | CI59: 0 | CJ59: 761.1 | CK59: 831.6 | CL59: -53.3 | CM59: 0 | CN59: 0 | CO59: 0 | CP59: 0 | CQ59: 0 | CR59: 363.85 | CS59: 80.8 | CT59: -50.45 | CU59: 13.5 | CV59: 30.8 | CW59: 0 | CX59: -75.9 | CY59: 83.65 | CZ59: -50.375 | DA59: 0 | DB59: 1.15 | DC59: -1.1 | DD59: -21.6 | DE59: 269.95 | DF59: 0 | DG59: 0 | DH59: 0.4 | DI59: 36.75 | DJ59: 4.5 | DK59: -8.85 | DL59: 7 | DM59: 10.4 | DN59: 0 | DO59: -7.3 | DP59: -18.8 | DQ59: -134.55 | DR59: 147.55 | DS59: -26.1 | DT59: 1.3 | DU59: 11.5 | DV59: 13.75 | DW59: 0.75 | DX59: 0 | DY59: -110.65 | DZ59: 7.75 | EA59: 71.55 | EB59: 70.35 | EC59: 0 | ED59: 0 | EE59: 16.7 | EF59: -121.95 | EG59: -136.75 | EH59: -15.4 | EI59: -9.55 | EJ59: 0 | EK59: 59.5 | EL59: -0.6 | EM59: 1.35 | EN59: 4.8 | EO59: 4.8 | EP59: 4.8 | EQ59: -71.535 | ER59: 112.9 | ES59: 1.65 | ET59: 130 | EU59: -1.2 | EV59: 30.7 | EW59: -29.25 | EX59: 69.2 | EY59: 45.6 | EZ59: 7.65 | FA59: 17.25 | FB59: 12 | FC59: 3.25 | FD59: 4.7 | FE59: 45.95 | FF59: 38.3 | FG59: 46.95 | FH59: 211.1 | FI59: 6.15 | FJ59: 75.25 | FK59: 25.9 | FL59: 69.6 | FM59: 95.6 | FN59: 283.14 | FO59: 13872.18 | FQ59: 49.2 | FR59: -8.005 | FS59: 51.95 | FT59: 42.25 | FU59: 31.2 | FV59: 54.382755 | FW59: -5.45 | FX59: 49.5 | FY59: 265.02776

Sheet DEMANDA_AREAS
B3: martes, 10 de Febrero del 2026
B5: REPORTE DE LA DEMANDA POR ÁREAS Y SUBAREAS OPERATIVAS (MW)
B6: FECHA HORA | C6: DEMANDA | E6: AREA | H6: SUBAREAS
C7: INTERCAMBIOS INTERNACIONALES | D7: SEIN | E7: NORTE | F7: CENTRO | G7: SUR | H7: ELECTROANDES
B8: 00:30 | C8: 0 | D8: 6807.05 | E8: 1075.1756 | F8: 4040.4958 | G8: 1691.3786 | H8: 241.797
B9: 01:00 | C9: 0 | D9: 6588.6 | E9: 1031.8698 | F9: 3946.3234 | G9: 1610.4068 | H9: 245.1996
B10: 01:30 | C10: 0 | D10: 6527.4 | E10: 1009.5208 | F10: 3906.5988 | G10: 1611.2804 | H10: 246.5729
B11: 02:00 | C11: 0 | D11: 6442.2 | E11: 993.5215 | F11: 3857.1852 | G11: 1591.4933 | H11: 244.3871
B12: 02:30 | C12: 0 | D12: 6356.9 | E12: 1010.3924 | F12: 3803.7261 | G12: 1542.7815 | H12: 243.117
B13: 03:00 | C13: 0 | D13: 6369.2 | E13: 1002.5696 | F13: 3816.2583 | G13: 1550.3721 | H13: 239.3984
B14: 03:30 | C14: 0 | D14: 6244.4 | E14: 987.2471 | F14: 3696.5162 | G14: 1560.6367 | H14: 240.2831
B15: 04:00 | C15: 0 | D15: 6258.21 | E15: 956.9533 | F15: 3734.6993 | G15: 1566.5574 | H15: 243.6779
B16: 04:30 | C16: 0 | D16: 6343.49 | E16: 1024.245 | F16: 3764.6531 | G16: 1554.5919 | H16: 238.3331
B17: 05:00 | C17: 0 | D17: 6312.21 | E17: 978.2442 | F17: 3758.7097 | G17: 1575.2561 | H17: 241.1054
B18: 05:30 | C18: 0 | D18: 6488.89 | E18: 1010.1115 | F18: 3808.5991 | G18: 1670.1794 | H18: 236.4918
B19: 06:00 | C19: 0 | D19: 6582 | E19: 1039.2904 | F19: 3875.1378 | G19: 1667.5718 | H19: 229.5193
... B59: ENERGÍA | C59: 0 | D59: 177963.15 | E59: 28186.373 | F59: 109093.21 | G59: 40683.563 | H59: 5670.939
B61: LEYENDA:
D63: Potencia recibida del Ecuador
D64: Potencia entregada al Ecuador

Sheet DEMANDA_UL
B3: martes, 10 de Febrero del 2026
B5: POTENCIA DE LOS GRANDES USUARIOS LIBRES (MW)
B6: FECHA HORA | C6: GRANDES USUARIOS LIBRES DEL ÁREA NORTE | X6: GRANDES USUARIOS LIBRES DEL ÁREA CENTRO | BP6: GRANDES USUARIOS LIBRES DEL ÁREA SUR
C7: ARCA CONTINENTAL LINDLEY S.A. | D7: AUSTRAL GROUP S.A.A | E7: CEMENTOS PACASMAYO | F7: CONSORCIO MINERO HORIZONTE S.R.L. | G7: CORPORACIÓN PESQUERA INCA S.A.C. | H7: CREDITEX: CIA IND.TEXTIL CREDISA | I7: HIPERMERCADOS TOTTUS S.A | J7: INDUSTRIA TEXTIL PIURA | K7: MINERA BOROO MISQUICHILCA S.A. | L7: MINERA GOLD FIELDS | M7: MINERA MARSA | N7: MINERA MISKY MAYO | O7: MINERA YANACOCHA | P7: OPEN PLAZA | Q7: PESQUERA DIAMANTE | R7: PETROPERU | S7: REAL PLAZA S.R.L. | T7: SIDER PERU | U7: SUPERMERCADOS PERUANOS S.A. | V7: TRUPAL S.A. | W7: UNIÓN DE CERVECERÍAS PERUANAS BACKUS Y JOHNSTON S. | X7: ACEROS AREQUIPA | Y7: ADMINISTRADORA JOCKEY PLAZA SHOPPING CENTER S.A. | Z7: ALICORP | AA7: ARCA CONTINENTAL LINDLEY S.A. | AB7: AUSTRAL GROUP S.A.A | AC7: COMPAÑIA MINERA CONDESTABLE | AD7: CORPORACIÓN PESQUERA INCA S.A.C. | AE7: CREDITEX: CIA IND.TEXTIL CREDISA | AF7: FUNDICION CHILCA S.A. | AG7: HIPERMERCADOS TOTTUS S.A | AH7: INMOBILIARIA KANPU S.A. | AI7: INMUEBLES PANAMERICANA S.A. | AJ7: KIMBERLY-CLARK PERU | AK7: LECHE GLORIA S.A. | AL7: MALL AVENTURA S.A. | AM7: MARCOBRE S.A.C. | AN7: MINERA ANTAMINA | AO7: MINERA ARES | AP7: MINERA BUENAVENTURA | AQ7: MINERA CHINALCO PERÚ S.A. | AR7: MINERA SHOUXIN PERU S.A. | AS7: MINERA VOLCAN | AT7: MINSUR | AU7: MOLYCOP-ADESUR | AV7: NEXA RESOURCES CAJAMARQUILLA S.A. | AW7: NEXA RESOURCES PERÚ S.A.A. | AX7: OPEN PLAZA | AY7: OPP FILM | AZ7: OWENS-ILLINOIS PERÚ S.A. | BA7: PAPELERA NACIONAL S.A. | BB7: PESQUERA DIAMANTE | BC7: QUIMPAC S.A. | BD7: REAL PLAZA S.R.L. | BE7: REFINERIA LA PAMPILLA S.A.A | BF7: SAGA FALABELLA | BG7: SAN MIGUEL INDUSTRIAS PET S.A. | BH7: SHOUGANG HIERRO PERU | BI7: SOFTYS PERU S.A.C. | BJ7: SUPERMERCADOS PERUANOS S.A. | BK7: TEJIDOS SAN JACINTO | BL7: TREN URBANO DE LIMA S.A. | BM7: TRUPAL S.A. | BN7: UNACEM PERU S.A. | BO7: UNIÓN DE CERVECERÍAS PERUANAS BACKUS Y JOHNSTON S. | BP7: ANGLO AMERICAN QUELLAVECO S.A. | BQ7: ARCA CONTINENTAL LINDLEY S.A. | BR7: CAL & CEMENTO SUR S.A. | BS7: COMPAÑIA MINERA ANTAPACCAY S.A. | BT7: COMPAÑÍA MINERA CHUNGAR SAC | BU7: COMPAÑIA MINERA SAN IGNACIO DE MOROCOCHA S.A.A. | BV7: EL BROCAL .S.A. | BW7: EMPRESA ADMINISTRADORA CERRO S.A.C. | BX7: EMPRESA MINERA LOS QUENUALES S.A.C. | BY7: HIPERMERCADOS TOTTUS S.A | BZ7: HUDBAY PERU S.A.C. | CA7: INDUSTRIA CACHIMAYO | CB7: MALL AVENTURA S.A. | CC7: MINERA ARES | CD7: MINERA BUENAVENTURA | CE7: MINERA CERRO VERDE | CF7: MINERA CORONA | CG7: MINERA LAS BAMBAS S.A. | CH7: MINERA VOLCAN | CI7: MINSUR | CJ7: MOLYCOP-ADESUR | CK7: NEXA RESOURCES PERÚ S.A.A. | CL7: OXIDOS DE PASCO S.A.C. | CM7: PESQUERA DIAMANTE | CN7: REAL PLAZA S.R.L. | CO7: SOBREANDES S.A.C. | CP7: SOUTHERN PERU CC | CQ7: SUPERMERCADOS PERUANOS S.A. | CR7: UNACEM PERU S.A. | CS7: UNIÓN DE CERVECERÍAS PERUANAS BACKUS Y JOHNSTON S. | CT7: YURA
B8: 00:30 | E8: 37.71192 | F8: 12.23 | K8: 19.9658 | L8: 27.5149 | M8: 14.8956 | N8: 14.21 | O8: 30.928 | R8: 44.04 | T8: 17.7936 | V8: 8.6 | X8: 142.48842 | Z8: 9.72782 | AC8: 15.04 | AF8: 3.8 | AH8: 0.2675 | AK8: 0 | AL8: 1.3955 | AM8: 47.20112 | AN8: 122.88 | AO8: 26.3025 | AP8: 0.81 | AQ8: 74.8834 | AS8: 36.376 | AT8: 31.14 | AV8: 193.1549 | AW8: 30.7758 | BA8: 2.5 | BC8: 70.3257 | BE8: 13 | BI8: 7.95734 | BK8: 4.83208 | BM8: 6.325 | BN8: 55.669 | BO8: 2.24 | BP8: 145.27809 | BR8: 4.08751 | BS8: 131.99 | BT8: 10.72135 | BW8: 3.85819 | BZ8: 92.2089 | CA8: 24.365 | CB8: 0.4307 | CC8: 0.576 | CD8: 30.1211 | CE8: 319.33471 | CG8: 158.414 | CH8: 17.561 | CL8: 4.90337 | CO8: 16.18266 | CP8: 291.25 | CR8: 29.027 | CT8: 23.383
B9: 01:00 | E9: 44.3334 | F9: 12.217 | K9: 20.2435 | L9: 27.4312 | M9: 14.6387 | N9: 14.37 | O9: 30.772 | R9: 43.965 | T9: 45.9392 | V9: 8.6 | X9: 154.68086 | Z9: 9.73658 | AC9: 14.93 | AF9: 2.9 | AH9: 0.2565 | AK9: 0 | AL9: 1.2547 | AM9: 46.8644 | AN9: 123.88 | AO9: 26.9638 | AP9: 0.7 | AQ9: 75.608 | AS9: 35.794 | AT9: 35.01 | AV9: 195.63518 | AW9: 29.8477 | BA9: 2.4 | BC9: 70.08564 | BE9: 13 | BI9: 8.1413 | BK9: 4.6837 | BM9: 6.521 | BN9: 55.597 | BO9: 2.21 | BP9: 147.99427 | BR9: 4.01928 | BS9: 134.55 | BT9: 10.16567 | BW9: 3.96348 | BZ9: 92.4618 | CA9: 24.401 | CB9: 0.4244 | CC9: 0.558 | CD9: 29.73295 | CE9: 250.60377 | CG9: 162.8952 | CH9: 17.265 | CL9: 4.94218 | CO9: 16.70869 | CP9: 289.32 | CR9: 31.197 | CT9: 28.717
B10: 01:30 | E10: 44.45499 | F10: 11.528 | K10: 19.4459 | L10: 27.1082 | M10: 14.3107 | N10: 14.33 | O10: 31.144 | R10: 44.077 | T10: 46.5149 | V10: 8.5 | X10: 105.43509 | Z10: 9.80208 | AC10: 15.72 | AF10: 2.8 | AH10: 0.2558 | AK10: 0 | AL10: 1.1448 | AM10: 44.93549 | AN10: 122.91 | AO10: 27.9533 | AP10: 0.64 | AQ10: 72.1862 | AS10: 36.338 | AT10: 34.51 | AV10: 195.67376 | AW10: 30.757 | BA10: 2.6 | BC10: 69.8209 | BE10: 13 | BI10: 8.07449 | BK10: 4.77364 | BM10: 6.421 | BN10: 55.535 | BO10: 2.19 | BP10: 147.50471 | BR10: 4.16538 | BS10: 133.45 | BT10: 11.08218 | BW10: 4.0073 | BZ10: 92.3209 | CA10: 24.397 | CB10: 0.4046 | CC10: 0.54 | CD10: 30.49493 | CE10: 229.51803 | CG10: 154.9771 | CH10: 17.455 | CL10: 4.76491 | CO10: 16.26474 | CP10: 290.89 | CR10: 32.43 | CT10: 29.042
B11: 02:00 | E11: 43.94072 | F11: 11.747 | K11: 19.2333 | L11: 27.038 | M11: 13.8875 | N11: 14.15 | O11: 31.098 | R11: 43.889 | T11: 21.8543 | V11: 8.8 | X11: 124.74573 | Z11: 9.47561 | AC11: 15.89 | AF11: 1.8 | AH11: 0.2539 | AK11: 0 | AL11: 1.134 | AM11: 45.6975 | AN11: 123.6 | AO11: 28.4931 | AP11: 0.44 | AQ11: 68.5467 | AS11: 36.216 | AT11: 35.16 | AV11: 193.28939 | AW11: 31.3213 | BA11: 2.7 | BC11: 69.48979 | BE11: 13 | BI11: 8.10039 | BK11: 4.76698 | BM11: 6.325 | BN11: 56.894 | BO11: 2.2 | BP11: 146.43645 | BR11: 4.17928 | BS11: 135.66 | BT11: 10.59941 | BW11: 3.7307 | BZ11: 92.1712 | CA11: 24.437 | CB11: 0.3903 | CC11: 0.572 | CD11: 30.12548 | CE11: 224.26189 | CG11: 155.6413 | CH11: 17.099 | CL11: 4.82395 | CO11: 16.62481 | CP11: 281.85 | CR11: 32.091 | CT11: 29.77
B12: 02:30 | E12: 44.16375 | F12: 11.533 | K12: 19.6023 | L12: 27.0901 | M12: 13.5444 | N12: 14.47 | O12: 31.036 | R12: 44.029 | T12: 47.3397 | V12: 8.8 | X12: 119.72494 | Z12: 9.57919 | AC12: 14.99 | AF12: 5.1 | AH12: 0.2709 | AK12: 0 | AL12: 1.1065 | AM12: 44.76324 | AN12: 125.15 | AO12: 28.3545 | AP12: 0.41 | AQ12: 70.4158 | AS12: 36.031 | AT12: 33.88 | AV12: 193.41111 | AW12: 32.4519 | BA12: 2.6 | BC12: 69.2986 | BE12: 13 | BI12: 7.94772 | BK12: 4.7876 | BM12: 6.451 | BN12: 58.563 | BO12: 2.12 | BP12: 144.2579 | BR12: 4.24391 | BS12: 135.33 | BT12: 9.69658 | BW12: 3.87202 | BZ12: 91.5496 | CA12: 24.453 | CB12: 0.3856 | CC12: 0.558 | CD12: 29.62755 | CE12: 204.93662 | CG12: 162.6989 | CH12: 17.237 | CL12: 4.9578 | CO12: 16.39502 | CP12: 280.77 | CR12: 32.332 | CT12: 27.859
B13: 03:00 | E13: 49.20802 | F13: 12.084 | K13: 19.8078 | L13: 27.2485 | M13: 14.1631 | N13: 14.54 | O13: 30.798 | R13: 43.961 | T13: 37.8463 | V13: 8.7 | X13: 95.98715 | Z13: 9.73734 | AC13: 13.34 | AF13: 6.1 | AH13: 0.295 | AK13: 0 | AL13: 1.0837 | AM13: 43.97203 | AN13: 125.68 | AO13: 28.158 | AP13: 0.67 | AQ13: 71.5538 | AS13: 36.463 | AT13: 34.16 | AV13: 193.31835 | AW13: 34.8073 | BA13: 2.5 | BC13: 69.36737 | BE13: 13 | BI13: 8.08988 | BK13: 4.77823 | BM13: 6.6321 | BN13: 58.404 | BO13: 2.16 | BP13: 139.59694 | BR13: 4.2163 | BS13: 134.49 | BT13: 10.77492 | BW13: 3.96593 | BZ13: 91.2361 | CA13: 24.469 | CB13: 0.3841 | CC13: 0.556 | CD13: 29.3742 | CE13: 201.13721 | CG13: 162.4441 | CH13: 17.397 | CL13: 4.88555 | CO13: 15.76986 | CP13: 288.96 | CR13: 32.44 | CT13: 28.814
B14: 03:30 | E14: 50.1221 | F14: 12.447 | K14: 19.5769 | L14: 27.6364 | M14: 14.358 | N14: 14.61 | O14: 30.934 | R14: 44.14 | T14: 41.658 | V14: 8.7 | X14: 124.18215 | Z14: 9.82351 | AC14: 13.1 | AF14: 5.6 | AH14: 0.2815 | AK14: 0 | AL14: 1.061 | AM14: 46.833 | AN14: 123.4 | AO14: 28.0173 | AP14: 0.48 | AQ14: 70.4181 | AS14: 36.147 | AT14: 33.65 | AV14: 195.83224 | AW14: 35.3553 | BA14: 2.6 | BC14: 70.46046 | BE14: 13 | BI14: 8.16673 | BK14: 4.81966 | BM14: 6.213 | BN14: 55.899 | BO14: 1.85 | BP14: 141.88391 | BR14: 4.30713 | BS14: 134.68 | BT14: 11.91778 | BW14: 4.02736 | BZ14: 91.1567 | CA14: 24.491 | CB14: 0.3702 | CC14: 0.584 | CD14: 29.30391 | CE14: 200.86994 | CG14: 167.0113 | CH14: 17.895 | CL14: 4.68308 | CO14: 16.99771 | CP14: 283.34 | CR14: 31.938 | CT14: 33.725
B15: 04:00 | E15: 50.04894 | F15: 11.697 | K15: 20.881 | L15: 27.5951 | M15: 14.3364 | N15: 14.53 | O15: 30.782 | R15: 42.65 | T15: 46.9585 | V15: 8.8 | X15: 161.4643 | Z15: 9.65417 | AC15: 13.07 | AF15: 3.4 | AH15: 0.2864 | AK15: 0 | AL15: 1.0481 | AM15: 46.85849 | AN15: 124.67 | AO15: 28.053 | AP15: 0.18 | AQ15: 70.6357 | AS15: 34.176 | AT15: 33.94 | AV15: 195.70836 | AW15: 35.0111 | BA15: 2.5 | BC15: 70.00866 | BE15: 13 | BI15: 8.04378 | BK15: 4.75589 | BM15: 6.231 | BN15: 51.413 | BO15: 1.92 | BP15: 140.14975 | BR15: 4.35179 | BS15: 134.54 | BT15: 12.2814 | BW15: 3.88656 | BZ15: 91.5817 | CA15: 24.501 | CB15: 0.3591 | CC15: 0.598 | CD15: 30.41933 | CE15: 202.16324 | CG15: 161.8328 | CH15: 17.753 | CL15: 4.59137 | CO15: 17.25623 | CP15: 288.12 | CR15: 31.596 | CT15: 34.002
B16: 04:30 | E16: 50.05333 | F16: 11.557 | K16: 20.8257 | L16: 27.4562 | M16: 15.5291 | N16: 14.67 | O16: 29.612 | R16: 42.292 | T16: 51.0896 | V16: 9.5 | X16: 143.69453 | Z16: 9.6146 | AC16: 13.11 | AF16: 4.2 | AH16: 0.2785 | AK16: 0 | AL16: 1.0243 | AM16: 47.16503 | AN16: 122.38 | AO16: 28.3419 | AP16: 1.65 | AQ16: 69.891 | AS16: 33.272 | AT16: 32.83 | AV16: 195.3401 | AW16: 33.9394 | BA16: 2.48 | BC16: 64.93697 | BE16: 13 | BI16: 8.12275 | BK16: 4.64757 | BM16: 6.521 | BN16: 48.724 | BO16: 1.83 | BP16: 139.38448 | BR16: 4.33392 | BS16: 134.41 | BT16: 11.25964 | BW16: 3.90366 | BZ16: 91.0909 | CA16: 24.501 | CB16: 0.3554 | CC16: 0.554 | CD16: 28.49062 | CE16: 197.3907 | CG16: 161.3188 | CH16: 17.52 | CL16: 4.56161 | CO16: 17.02828 | CP16: 293.29 | CR16: 31.309 | CT16: 34.064
B17: 05:00 | E17: 49.94072 | F17: 11.459 | K17: 21.065 | L17: 24.2548 | M17: 15.6187 | N17: 14.37 | O17: 29.802 | R17: 42.221 | T17: 43.0402 | V17: 9.8 | X17: 142.37195 | Z17: 9.73171 | AC17: 12.98 | AF17: 3.1 | AH17: 0.2655 | AK17: 0 | AL17: 1.0318 | AM17: 48.17759 | AN17: 121.67 | AO17: 29.1004 | AP17: 2.1 | AQ17: 69.7201 | AS17: 31.682 | AT17: 33.1 | AV17: 193.25102 | AW17: 32.8711 | BA17: 2.6 | BC17: 59.38754 | BE17: 13 | BI17: 8.29107 | BK17: 4.77748 | BM17: 6.356 | BN17: 47.842 | BO17: 2.15 | BP17: 135.87123 | BR17: 4.308 | BS17: 133.8 | BT17: 11.22145 | BW17: 4.37541 | BZ17: 91.5941 | CA17: 24.507 | CB17: 0.3436 | CC17: 0.552 | CD17: 28.85726 | CE17: 200.90495 | CG17: 155.7781 | CH17: 18.315 | CL17: 4.5684 | CO17: 16.06113 | CP17: 293.86 | CR17: 32.224 | CT17: 34.068
B18: 05:30 | E18: 49.98913 | F18: 10.027 | K18: 21.1884 | L18: 27.4015 | M18: 15.4597 | N18: 14.44 | O18: 29.62 | R18: 42.186 | T18: 31.8811 | V18: 9.6 | X18: 132.96105 | Z18: 9.64014 | AC18: 13.86 | AF18: 2.4 | AH18: 0.2572 | AK18: 0 | AL18: 1.0157 | AM18: 47.24228 | AN18: 123.58 | AO18: 27.8034 | AP18: 1.93 | AQ18: 69.6218 | AS18: 32.082 | AT18: 32.77 | AV18: 193.40581 | AW18: 32.8377 | BA18: 2.5 | BC18: 55.19415 | BE18: 13 | BI18: 8.24558 | BK18: 4.76439 | BM18: 6.523 | BN18: 47.61 | BO18: 2.19 | BP18: 138.1047 | BR18: 4.46516 | BS18: 135.71 | BT18: 9.39142 | BW18: 3.85894 | BZ18: 91.8139 | CA18: 24.5 | CB18: 0.3459 | CC18: 0.578 | CD18: 29.06093 | CE18: 237.6596 | CG18: 151.6815 | CH18: 18.204 | CL18: 4.62065 | CO18: 14.60313 | CP18: 293.48 | CR18: 32.199 | CT18: 34.174
B19: 06:00 | E19: 49.71354 | F19: 9.466 | K19: 21.1366 | L19: 28.3432 | M19: 14.8944 | N19: 14.5 | O19: 29.766 | R19: 42.182 | T19: 45.374 | V19: 9.2 | X19: 110.78095 | Z19: 9.71344 | AC19: 14.56 | AF19: 3.9 | AH19: 0.2563 | AK19: 0 | AL19: 1.0531 | AM19: 48.91854 | AN19: 123.17 | AO19: 22.0674 | AP19: 1.54 | AQ19: 74.8127 | AS19: 32.181 | AT19: 32.63 | AV19: 193.56245 | AW19: 31.3589 | BA19: 2.5 | BC19: 52.11084 | BE19: 13 | BI19: 7.96506 | BK19: 4.96268 | BM19: 6.3251 | BN19: 47.554 | BO19: 2.18 | BP19: 139.15817 | BR19: 4.20916 | BS19: 134.69 | BT19: 10.62282 | BW19: 3.65085 | BZ19: 91.2045 | CA19: 24.517 | CB19: 0.3445 | CC19: 0.534 | CD19: 28.33623 | CE19: 280.59663 | CG19: 153.962 | CH19: 18.031 | CL19: 4.52554 | CO19: 13.69738 | CP19: 293.25 | CR19: 31.87 | CT19: 33.719
... B55: 00:00 | E55: 41.471 | F55: 11.448 | K55: 18.2012 | L55: 27.0291 | M55: 13.8741 | N55: 14.09 | O55: 31.51 | R55: 43.906 | T55: 11.5933 | V55: 9.9 | X55: 103.97466 | Z55: 9.16138 | AC55: 15.14 | AF55: 2.9 | AH55: 0.2333 | AK55: 0 | AL55: 1.6219 | AM55: 51.70788 | AN55: 121.23 | AO55: 28.2823 | AP55: 0.83 | AQ55: 163.304 | AS55: 37.508 | AT55: 32.75 | AV55: 198.51484 | AW55: 30.7389 | BA55: 1.3 | BC55: 69.01886 | BE55: 13 | BI55: 8.21445 | BK55: 5.31516 | BM55: 6.356 | BN55: 54.29 | BO55: 2.32 | BP55: 129.18645 | BR55: 4.23764 | BS55: 134.51 | BT55: 12.69448 | BW55: 3.83695 | BZ55: 91.6602 | CA55: 24.004 | CB55: 0.5127 | CC55: 0.577 | CD55: 29.40958 | CE55: 309.62167 | CG55: 158.2736 | CH55: 17.817 | CL55: 4.74352 | CO55: 16.55062 | CP55: 291.44 | CR55: 28.828 | CT55: 24.629
B56: MWh | C56: 0 | D56: 0 | E56: 1019.591 | F56: 268.329 | G56: 0 | H56: 0 | I56: 0 | J56: 0 | K56: 469.2861 | L56: 665.64325 | M56: 324.61815 | N56: 333.51 | O56: 733.529 | P56: 0 | Q56: 0 | R56: 1017.734 | S56: 0 | T56: 469.04125 | U56: 0 | V56: 212.55 | W56: 0 | X56: 2379.1409 | Y56: 0 | Z56: 224.33456 | AA56: 0 | AB56: 0 | AC56: 354.65 | AD56: 0 | AE56: 0 | AF56: 81.05 | AG56: 0 | AH56: 5.848 | AI56: 0 | AJ56: 0 | AK56: 0 | AL56: 66.23005 | AM56: 1150.4574 | AN56: 2918.485 | AO56: 657.0426 | AP56: 18.01 | AQ56: 3027.903 | AR56: 0 | AS56: 838.9635 | AT56: 788.275 | AU56: 0 | AV56: 4234.385 | AW56: 742.6444 | AX56: 0 | AY56: 0 | AZ56: 0 | BA56: 42.79 | BB56: 0 | BC56: 1280.8056 | BD56: 0 | BE56: 312 | BF56: 0 | BG56: 0 | BH56: 0 | BI56: 197.72182 | BJ56: 0 | BK56: 116.18364 | BL56: 0 | BM56: 153.89525 | BN56: 1072.5565 | BO56: 55.265 | BP56: 3309.2047 | BQ56: 0 | BR56: 102.41191 | BS56: 3205.005 | BT56: 253.89574 | BU56: 0 | BV56: 0 | BW56: 93.385435 | BX56: 0 | BY56: 0 | BZ56: 2183.7465 | CA56: 485.4925 | CB56: 23.5346 | CC56: 13.7845 | CD56: 716.88346 | CE56: 6329.1262 | CF56: 0 | CG56: 3439.5776 | CH56: 415.934 | CI56: 0 | CJ56: 0 | CK56: 0 | CL56: 112.53897 | CM56: 0 | CN56: 0 | CO56: 370.10402 | CP56: 6749.73 | CQ56: 0 | CR56: 732.99 | CS56: 0 | CT56: 574.85
B59: Nota :
B60: Información proporcionada por la empresas
C62: DATOS ESTIMADOS
C64: SIN DATOS

Sheet TIPO_RECURSO
B3: martes, 10 de Febrero del 2026
B5: REPORTE POTENCIA GENERADA POR TIPO DE RECURSO
B6: HORA | C6: H. PASADA | D6: H. REGULACION | E6: GAS DE CAMISEA | F6: GAS DE MALACAS | G6: GAS DE AGUAYTIA | H6: DIÉSEL | I6: RESIDUAL | J6: NAFTA+GAS DE REFINERIA | K6: FLEXIGAS+GAS DE REFINERIA | L6: BAGAZO | M6: BIOGÁS | N6: SOLAR | O6: EÓLICA | P6: TOTAL | U6: EMPRESA | V6: CENTRAL | W6: HIDROELECTRICA DE PASADA | X6: HIDROELECTRICA DE REGULACION
B7: 00:30 | C7: 1209 | D7: 3427.3 | E7: 1791.7 | F7: 0 | K7: =+DESPACHO_EJECUTADO!FH11+DESPACHO_EJECUTADO!FI11 -> 62 | L7: 81.9 | M7: 8 | N7: 0 | O7: 227.15 | P7: =+SUM(C7:O7) -> 6807.05 | U7: ANDEAN POWER S.A.C. | V7: C.H.CARHUAC | W7: 230.4
B8: 01:00 | C8: 1166.3 | D8: 3384.8 | E8: 1707.9 | F8: 0 | K8: =+DESPACHO_EJECUTADO!FH12+DESPACHO_EJECUTADO!FI12 -> 61.5 | L8: 83.4 | M8: 8 | N8: 0 | O8: 176.7 | P8: =+SUM(C8:O8) -> 6588.6 | U8: ASOCIACIÓN SANTA LUCIA DE CHACAS | V8: C.H. HUALLIN | W8: 64.15
B9: 01:30 | C9: 1199.3 | D9: 3369.8 | E9: 1650.6 | F9: 0 | K9: =+DESPACHO_EJECUTADO!FH13+DESPACHO_EJECUTADO!FI13 -> 62.2 | L9: 82.5 | M9: 8 | N9: 0 | O9: 155 | P9: =+SUM(C9:O9) -> 6527.4 | U9: ATRIA ENERGIA S.A.C. | V9: C.H. PURMACANA | W9: 7.75
B10: 02:00 | C10: 1210.4 | D10: 3388.1 | E10: 1555.4 | F10: 0 | K10: =+DESPACHO_EJECUTADO!FH14+DESPACHO_EJECUTADO!FI14 -> 62.6 | L10: 83.6 | M10: 8 | N10: 0 | O10: 134.1 | P10: =+SUM(C10:O10) -> 6442.2 | U10: CELARIS ENERGY S.A. | V10: C.H. MANTA I | W10: 435.45
B11: 02:30 | C11: 1174.5 | D11: 3394 | E11: 1511.3 | F11: 0 | K11: =+DESPACHO_EJECUTADO!FH15+DESPACHO_EJECUTADO!FI15 -> 62.2 | L11: 82.4 | M11: 8.1 | N11: 0 | O11: 124.4 | P11: =+SUM(C11:O11) -> 6356.9 | U11: CELEPSA | V11: C.H. EL PLATANAL | X11: 4631.6
B12: 03:00 | C12: 1191.7 | D12: 3466.3 | E12: 1426.1 | F12: 0 | K12: =+DESPACHO_EJECUTADO!FH16+DESPACHO_EJECUTADO!FI16 -> 62.5 | L12: 83.5 | M12: 8.1 | N12: 0 | O12: 131 | P12: =+SUM(C12:O12) -> 6369.2 | U12: CELEPSA RENOVABLES S.R.L. | V12: C.H. MARAÑON | W12: 451.75
B13: 03:30 | C13: 1183.2 | D13: 3262.5 | E13: 1473.4 | F13: 0 | K13: =+DESPACHO_EJECUTADO!FH17+DESPACHO_EJECUTADO!FI17 -> 62.7 | L13: 82.5 | M13: 8.1 | N13: 0 | O13: 172 | P13: =+SUM(C13:O13) -> 6244.4 | U13: CHINANGO S.A.C. | V13: C.H. CHIMAY | X13: 3621.75
B14: 04:00 | C14: 1171.3 | D14: 3225.6 | E14: 1485.2 | F14: 0 | K14: =+DESPACHO_EJECUTADO!FH18+DESPACHO_EJECUTADO!FI18 -> 62.2 | L14: 82.3 | M14: 8.1 | N14: 0 | O14: 223.51 | P14: =+SUM(C14:O14) -> 6258.21 | V14: C.H. YANANGO | W14: 1008.95
B15: 04:30 | C15: 1182.5 | D15: 3310.4 | E15: 1447.4 | F15: 0 | K15: =+DESPACHO_EJECUTADO!FH19+DESPACHO_EJECUTADO!FI19 -> 61.5 | L15: 83.6 | M15: 8.1 | N15: 0 | O15: 249.99 | P15: =+SUM(C15:O15) -> 6343.49 | U15: EGASA | V15: C.H. CHARCANI III | W15: 158
B16: 05:00 | C16: 1193.9 | D16: 3290.3 | E16: 1434.4 | F16: 0 | K16: =+DESPACHO_EJECUTADO!FH20+DESPACHO_EJECUTADO!FI20 -> 60.3 | L16: 83.7 | M16: 8.1 | N16: 0 | O16: 241.51 | P16: =+SUM(C16:O16) -> 6312.21 | V16: C.H. CHARCANI V | X16: 3410.75
B17: 05:30 | C17: 1194.1 | D17: 3408.9 | E17: 1516.9 | F17: 0 | K17: =+DESPACHO_EJECUTADO!FH21+DESPACHO_EJECUTADO!FI21 -> 60.7 | L17: 80.7 | M17: 8.1 | N17: 0.1 | O17: 219.39 | P17: =+SUM(C17:O17) -> 6488.89 | U17: EGEJUNIN | V17: C.H. HUASAHUASI I | W17: 474.85
B18: 06:00 | C18: 1201.1 | D18: 3421.5 | E18: 1542 | F18: 0 | K18: =+DESPACHO_EJECUTADO!FH22+DESPACHO_EJECUTADO!FI22 -> 61.3 | L18: 80.7 | M18: 8.1 | N18: 20.1 | O18: 247.2 | P18: =+SUM(C18:O18) -> 6582 | V18: C.H. RUNATULLO II | W18: 483
B19: 06:30 | C19: 1196.8 | D19: 3340.6 | E19: 1432.6 | F19: 0 | K19: =+DESPACHO_EJECUTADO!FH23+DESPACHO_EJECUTADO!FI23 -> 61.5 | L19: 83.8 | M19: 8.1 | N19: 159.6 | O19: 275.3 | P19: =+SUM(C19:O19) -> 6558.3 | V19: C.H. RUNATULLO III | W19: 484.65
B20: 07:00 | C20: 1193.9 | D20: 3092.4 | E20: 1392.5 | F20: 0 | K20: =+DESPACHO_EJECUTADO!FH24+DESPACHO_EJECUTADO!FI24 -> 61.9 | L20: 83 | M20: 8.1 | N20: 456.2 | O20: 247.6 | P20: =+SUM(C20:O20) -> 6535.6 | V20: C.H. SANTA CRUZ I | W20: 167.25
B21: 07:30 | C21: 1196 | D21: 3246.6 | E21: 1391.9 | F21: 0 | K21: =+DESPACHO_EJECUTADO!FH25+DESPACHO_EJECUTADO!FI25 -> 61.7 | L21: 77.8 | M21: 8.1 | N21: 703.8 | O21: 217 | P21: =+SUM(C21:O21) -> 6902.9 | U21: EGEMSA | V21: C.H. MACHUPICCHU | W21: 3963.3
B22: 08:00 | C22: 1199.1 | D22: 3360.6 | E22: 1421.6 | F22: 0 | K22: =+DESPACHO_EJECUTADO!FH26+DESPACHO_EJECUTADO!FI26 -> 61.7 | L22: 74.9 | M22: 8.1 | N22: 826.5 | O22: 202.7 | P22: =+SUM(C22:O22) -> 7155.2 | U22: EGESUR | V22: C.H. ARICOTA I | X22: 189.25
B23: 08:30 | C23: 1204.8 | D23: 3499.1 | E23: 1467.9 | F23: 0 | K23: =+DESPACHO_EJECUTADO!FH27+DESPACHO_EJECUTADO!FI27 -> 61.9 | L23: 75 | M23: 8.1 | N23: 895.8 | O23: 210.4 | P23: =+SUM(C23:O23) -> 7423 | V23: C.H. ARICOTA II | X23: 134.45
B24: 09:00 | C24: 1198.8 | D24: 3394.4 | E24: 1689.1 | F24: 42.6 | K24: =+DESPACHO_EJECUTADO!FH28+DESPACHO_EJECUTADO!FI28 -> 61.9 | L24: 73.1 | M24: 8 | N24: 934.4 | O24: 247.5 | P24: =+SUM(C24:O24) -> 7649.8 | U24: ELECTRICA YANAPAMPA SAC | V24: C.H. YANAPAMPA | W24: 78.5
B25: 09:30 | C25: 1199 | D25: 3407.3 | E25: 1732.7 | F25: 42.8 | K25: =+DESPACHO_EJECUTADO!FH29+DESPACHO_EJECUTADO!FI29 -> 62.1 | L25: 72.6 | M25: 7.2 | N25: 950.9 | O25: 290 | P25: =+SUM(C25:O25) -> 7764.6 | U25: ELECTROPERU | V25: C.H. MANTARO | X25: 15255.75
B26: 10:00 | C26: 1196 | D26: 3459.6 | E26: 1749.9 | F26: 44 | K26: =+DESPACHO_EJECUTADO!FH30+DESPACHO_EJECUTADO!FI30 -> 62.5 | L26: 75.6 | M26: 6.8 | N26: 960.4 | O26: 332 | P26: =+SUM(C26:O26) -> 7886.8 | V26: C.H. RESTITUCION | W26: 5160.8
B27: 10:30 | C27: 1174.9 | D27: 3493.6 | E27: 1788 | F27: 44.3 | K27: =+DESPACHO_EJECUTADO!FH31+DESPACHO_EJECUTADO!FI31 -> 62.3 | L27: 73.6 | M27: 6.9 | N27: 948.7 | O27: 381.6 | P27: =+SUM(C27:O27) -> 7973.9 | U27: EMPRESA DE GENERACION ELECTRICA CANCHAYLLO SAC | V27: C.H. CANCHAYLLO | W27: 119.85
B28: 11:00 | C28: 1195 | D28: 3598.3 | E28: 1814.4 | F28: 43.8 | K28: =+DESPACHO_EJECUTADO!FH32+DESPACHO_EJECUTADO!FI32 -> 62.1 | L28: 72.1 | M28: 6.9 | N28: 933.3 | O28: 464.3 | P28: =+SUM(C28:O28) -> 8190.2 | U28: EMPRESA DE GENERACION ELECTRICA SANTA ANA S.A.C. | V28: C.H. RENOVANDES H1 | W28: 485.2
B29: 11:30 | C29: 1191.7 | D29: 3554.9 | E29: 1841.5 | F29: 44.1 | K29: =+DESPACHO_EJECUTADO!FH33+DESPACHO_EJECUTADO!FI33 -> 62.1 | L29: 71 | M29: 7.9 | N29: 940.1 | O29: 556.96 | P29: =+SUM(C29:O29) -> 8270.26 | U29: EMPRESA DE GENERACION HUALLAGA | V29: C.H. CHAGLLA | X29: 10777.85
B30: 12:00 | C30: 1174.8 | D30: 3448.2 | E30: 1787.1 | F30: 44 | K30: =+DESPACHO_EJECUTADO!FH34+DESPACHO_EJECUTADO!FI34 -> 62.3 | L30: 80.3 | M30: 7.9 | N30: 965.4 | O30: 623.03 | P30: =+SUM(C30:O30) -> 8193.03 | V30: P.C.H. CHAGLLA | W30: 156
B31: 12:30 | C31: 1172.9 | D31: 3349.9 | E31: 1810.8 | F31: 43.7 | K31: =+DESPACHO_EJECUTADO!FH35+DESPACHO_EJECUTADO!FI35 -> 62.7 | L31: 81.9 | M31: 7.8 | N31: 938.8 | O31: 646.82 | P31: =+SUM(C31:O31) -> 8115.32 | U31: EMPRESA DE GENERACION HUANZA | V31: C.H. HUANZA | X31: 678.15
B32: 13:00 | C32: 1174.1 | D32: 3424.3 | E32: 1669 | F32: 44.3 | K32: =+DESPACHO_EJECUTADO!FH36+DESPACHO_EJECUTADO!FI36 -> 62.1 | L32: 77.1 | M32: 7.8 | N32: 913.9 | O32: 666.19 | P32: =+SUM(C32:O32) -> 8038.79 | U32: EMPRESA ELECTRICA AGUA AZUL | V32: C.H. POTRERO | W32: 452.35
B33: 13:30 | C33: 1187.8 | D33: 3480.7 | E33: 1643.1 | F33: 43.7 | K33: =+DESPACHO_EJECUTADO!FH37+DESPACHO_EJECUTADO!FI37 -> 62.1 | L33: 76.1 | M33: 7.8 | N33: 925.3 | O33: 688.5 | P33: =+SUM(C33:O33) -> 8115.1 | U33: EMPRESA ELECTRICA RIO DOBLE | V33: C.H. LAS PIZARRAS | W33: 451.15
B34: 14:00 | C34: 1192.2 | D34: 3493.3 | E34: 1651.2 | F34: 44.2 | K34: =+DESPACHO_EJECUTADO!FH38+DESPACHO_EJECUTADO!FI38 -> 61.7 | L34: 78.7 | M34: 7.8 | N34: 915.1 | O34: 740.83 | P34: =+SUM(C34:O34) -> 8185.03 | U34: ENGIE ENERGIA PERU S.A.A. | V34: C.H. YUNCAN | X34: 3052.205
B35: 14:30 | C35: 1195.3 | D35: 3592 | E35: 1735.4 | F35: 44.1 | K35: =+DESPACHO_EJECUTADO!FH39+DESPACHO_EJECUTADO!FI39 -> 61.4 | L35: 78.1 | M35: 7.8 | N35: 836 | O35: 734.68 | P35: =+SUM(C35:O35) -> 8284.78 | U35: GENERACIÓN ANDINA S.A.C. | V35: C.H. 8 DE AGOSTO | W35: 475.8
B36: 15:00 | C36: 1192.9 | D36: 3598.5 | E36: 1911.9 | F36: 44.1 | K36: =+DESPACHO_EJECUTADO!FH40+DESPACHO_EJECUTADO!FI40 -> 61.1 | L36: 79 | M36: 7.8 | N36: 705.7 | O36: 742.33 | P36: =+SUM(C36:O36) -> 8343.33 | V36: C.H. EL CARMEN | W36: 145.45
B37: 15:30 | C37: 1203.7 | D37: 3548.1 | E37: 1960.4 | F37: 44.1 | K37: =+DESPACHO_EJECUTADO!FH41+DESPACHO_EJECUTADO!FI41 -> 60.4 | L37: 77.1 | M37: 7.7 | N37: 599.8 | O37: 696.19 | P37: =+SUM(C37:O37) -> 8197.49 | U37: GENERADORA DE ENERGÍA DEL PERÚ | V37: C.H. ÁNGEL I | W37: 489.6
B38: 16:00 | C38: 1203.1 | D38: 3511.6 | E38: 2008.7 | F38: 44.4 | K38: =+DESPACHO_EJECUTADO!FH42+DESPACHO_EJECUTADO!FI42 -> 60.8 | L38: 72.9 | M38: 6.6 | N38: 558 | O38: 647.98 | P38: =+SUM(C38:O38) -> 8114.08 | V38: C.H. ÁNGEL II | W38: 489.6
B39: 16:30 | C39: 1187.8 | D39: 3527 | E39: 2048.4 | F39: 44.2 | K39: =+DESPACHO_EJECUTADO!FH43+DESPACHO_EJECUTADO!FI43 -> 60.8 | L39: 75 | M39: 6.6 | N39: 430.1 | O39: 636.54 | P39: =+SUM(C39:O39) -> 8016.44 | V39: C.H. ÁNGEL III | W39: 481.4
B40: 17:00 | C40: 1178.5 | D40: 3596 | E40: 2141 | F40: 44.4 | K40: =+DESPACHO_EJECUTADO!FH44+DESPACHO_EJECUTADO!FI44 -> 61.4 | L40: 78 | M40: 6.6 | N40: 258.4 | O40: 637.03 | P40: =+SUM(C40:O40) -> 8001.33 | V40: C.H. LA JOYA | W40: 7.05
B41: 17:30 | C41: 1177.6 | D41: 3604.2 | E41: 2114.8 | F41: 44.7 | K41: =+DESPACHO_EJECUTADO!FH45+DESPACHO_EJECUTADO!FI45 -> 60.8 | L41: 82 | M41: 6.6 | N41: 145.5 | O41: 622.93 | P41: =+SUM(C41:O41) -> 7859.13 | U41: HIDROCAÑETE S.A. | V41: C.H. IMPERIAL | W41: 63.3
B42: 18:00 | C42: 1196.4 | D42: 3570.2 | E42: 2036.5 | F42: 44.6 | K42: =+DESPACHO_EJECUTADO!FH46+DESPACHO_EJECUTADO!FI46 -> 60.8 | L42: 81.8 | M42: 6.8 | N42: 34.9 | O42: 608 | P42: =+SUM(C42:O42) -> 7640 | U42: HIDROELECTRICA HUANCHOR S.A.C. | V42: C.H. HUANCHOR | W42: 442.7
B43: 18:30 | C43: 1198.2 | D43: 3622.5 | E43: 1949.9 | F43: 44.5 | K43: =+DESPACHO_EJECUTADO!FH47+DESPACHO_EJECUTADO!FI47 -> 60.7 | L43: 80.9 | M43: 7.4 | N43: 1.2 | O43: 646.03 | P43: =+SUM(C43:O43) -> 7611.33 | U43: HUAURA POWER GROUP S.A. | V43: C.H. YARUCAYA | W43: 441.6
B44: 19:00 | C44: 1199.6 | D44: 3713.5 | E44: 2167.3 | F44: 44.9 | K44: =+DESPACHO_EJECUTADO!FH48+DESPACHO_EJECUTADO!FI48 -> 59.8 | L44: 81.5 | M44: 7.5 | N44: 0 | O44: 551.42 | P44: =+SUM(C44:O44) -> 7825.52 | U44: HYDRO GLOBAL PERÚ S.A.C. | V44: CH SAN GABAN III | X44: 4846.65
B45: 19:30 | C45: 1194.2 | D45: 3711.1 | E45: 2235.7 | F45: 44.8 | K45: =+DESPACHO_EJECUTADO!FH49+DESPACHO_EJECUTADO!FI49 -> 60.1 | L45: 81.9 | M45: 7.7 | N45: 0 | O45: 508.48 | P45: =+SUM(C45:O45) -> 7843.98 | U45: INLAND ENERGY SAC | V45: C.H. SANTA TERESA | W45: 2183
B46: 20:00 | C46: 1193.3 | D46: 3707.3 | E46: 2244.5 | F46: 45 | K46: =+DESPACHO_EJECUTADO!FH50+DESPACHO_EJECUTADO!FI50 -> 60.5 | L46: 80.6 | M46: 7.4 | N46: 0 | O46: 484.52 | P46: =+SUM(C46:O46) -> 7823.12 | U46: INVERSIONES SHAQSHA S.A.C. | V46: C.H. PARIAC | W46: 51.25
B47: 20:30 | C47: 1206.9 | D47: 3744.6 | E47: 2175.9 | F47: 44.9 | K47: =+DESPACHO_EJECUTADO!FH51+DESPACHO_EJECUTADO!FI51 -> 61.3 | L47: 81.1 | M47: 7.7 | N47: 0 | O47: 429.8 | P47: =+SUM(C47:O47) -> 7752.2 | U47: KALLPA GENERACION S.A. | V47: C.H. CERRO DEL AGUILA | X47: 13288.35
B48: 21:00 | C48: 1201.2 | D48: 3736.7 | E48: 2230 | F48: 44.8 | K48: =+DESPACHO_EJECUTADO!FH52+DESPACHO_EJECUTADO!FI52 -> 61.2 | L48: 81 | M48: 7.8 | N48: 0 | O48: 371.8 | P48: =+SUM(C48:O48) -> 7734.5 | V48: M.C.H. CERRO DEL AGUILA | W48: 244.65
B49: 21:30 | C49: 1209.5 | D49: 3739 | E49: 2233 | F49: 44.9 | K49: =+DESPACHO_EJECUTADO!FH53+DESPACHO_EJECUTADO!FI53 -> 61.5 | L49: 82.5 | M49: 7.8 | N49: 0 | O49: 370.16 | P49: =+SUM(C49:O49) -> 7748.36 | U49: LA VIRGEN | V49: C.H. LA VIRGEN | X49: 1859.9
B50: 22:00 | C50: 1200.5 | D50: 3708.2 | E50: 2252.9 | F50: 45 | K50: =+DESPACHO_EJECUTADO!FH54+DESPACHO_EJECUTADO!FI54 -> 60.9 | L50: 66.6 | M50: 7.8 | N50: 0 | O50: 380.78 | P50: =+SUM(C50:O50) -> 7722.68 | U50: MAJA ENERGIA S.A.C. | V50: C.H. RONCADOR | W50: 40.5
B51: 22:30 | C51: 1197.5 | D51: 3567.84 | E51: 2229.72 | F51: 44.8 | K51: =+DESPACHO_EJECUTADO!FH55+DESPACHO_EJECUTADO!FI55 -> 61.4 | L51: 69.5 | M51: 8 | N51: 0 | O51: 389.6494 | P51: =+SUM(C51:O51) -> 7568.4094 | U51: ORAZUL ENERGY PERÚ | V51: C.H. CAÑA BRAVA | W51: 130.1
B52: 23:00 | C52: 1193.5 | D52: 3508.59 | E52: 1992.53 | F52: 44.8 | K52: =+DESPACHO_EJECUTADO!FH56+DESPACHO_EJECUTADO!FI56 -> 60.5 | L52: 80.3 | M52: 8.4 | N52: 0 | O52: 494.7527 | P52: =+SUM(C52:O52) -> 7383.3727 | V52: C.H. CAÑON DEL PATO | X52: 5790.5
B53: 23:30 | C53: 1183 | D53: 3494.29 | E53: 1734.27 | F53: 45 | K53: =+DESPACHO_EJECUTADO!FH57+DESPACHO_EJECUTADO!FI57 -> 61.7 | L53: 81.5 | M53: 9 | N53: 0 | O53: 486.4566 | P53: =+SUM(C53:O53) -> 7095.2166 | V53: C.H. CARHUAQUERO | X53: 2157.05
B54: 00:00 | C54: 1189.4 | D54: 3481.79 | E54: 1768.4 | F54: 0 | K54: =+DESPACHO_EJECUTADO!FH58+DESPACHO_EJECUTADO!FI58 -> 61.2 | L54: 81 | M54: 9.2 | N54: 0 | O54: 491.6603 | P54: =+SUM(C54:O54) -> 7082.6503 | V54: C.H. CARHUAQUERO IV | W54: 238.3
B55: TOTAL MWh | C55: =SUM(C7:C54)/2 -> 28613.6 | D55: =SUM(D7:D54)/2 -> 83638.155 | E55: =SUM(E7:E54)/2 -> 42998.41 | F55: =SUM(F7:F54)/2 -> 664.75 | G55: =SUM(G7:G54)/2 -> 0 | H55: =SUM(H7:H54)/2 -> 0 | I55: =SUM(I7:I54)/2 -> 0 | J55: =SUM(J7:J54)/2 -> 0 | ... P55: =SUM(P7:P54)/2 -> 177963.15 | U55: ORYGEN PERU S.A.A. | V55: C.H. CALLAHUANCA | X55: 1786.3
B56: % | C56: =+C55/$P$55 -> 0.16078385 | D56: =+D55/$P$55 -> 0.46997457 | E56: =+E55/$P$55 -> 0.24161412 | F56: =+F55/$P$55 -> 0.0037353239 | G56: =+G55/$P$55 -> 0 | H56: =+H55/$P$55 -> 0 | I56: =+I55/$P$55 -> 0 | J56: =+J55/$P$55 -> 0 | ... P56: =+P55/$P$55 -> 1 | V56: C.H. HER 1 | W56: 4.8
V57: C.H. HUAMPANI | W57: 661.5
V58: C.H. HUINCO | X58: 2511.15
V59: C.H. MATUCANA | X59: 2659.65
V60: C.H. MOYOPAMPA | W60: 1521.25
U61: SAN GABAN | V61: C.H. SAN GABAN II | X61: 2642.85
V62: PCH TUPURI | W62: 42.35
U63: SINERSA | V63: C.H. CHANCAY | W63: 479.75
V64: C.H. POECHOS II | W64: 197.95
V65: C.H. RUCUY | W65: 479.45
U66: STATKRAFT S.A | V66: C.H. ARCATA | W66: 96
V67: C.H. CAHUA | W67: 1078.55
V68: C.H. CHEVES | X68: 3112
V69: C.H. GALLITO CIEGO | X69: 795.1
V70: C.H. MALPASO | X70: 436.9
V71: C.H. YAUPI | W71: 2538.85
U72: TRANSMISION ANDINA DE GENERACION S.A.C. | V72: C.H. OROYA | W72: 166.65
V73: C.H. PACHACHACA | W73: 102.7
U74: VARI ENERGIA S.A.C. | V74: C.H. ANASHIRONI | W74: 486.15
U75: TOTAL MWh | W75: 28613.6 | X75: 83638.155

Sheet GENERACION RER
B3: martes, 10 de Febrero del 2026
B5: GENERACIÓN ELÉCTRICA DE LAS CENTRALES RER (MW)
B6: HORA | C6: AGRO INDUSTRIAL PARAMONGA S.A. | D6: AGROAURORA S.A.C. | E6: AGROINDUSTRIAS SAN JACINTO S.A.A. | F6: AGROLMOS SOCIEDAD ANONIMA - AGROLMOS S.A. | G6: ANDEAN POWER S.A.C. | H6: ASOCIACIÓN SANTA LUCIA DE CHACAS | I6: ATRIA ENERGIA S.A.C. | J6: BIOENERGIA DEL CHIRA S.A. | K6: CASA GRANDE S.A.A. | L6: CELARIS ENERGY S.A. | M6: COENERGY S.A.C. | N6: COLCA SOLAR S.A.C. | O6: EGEJUNIN | T6: ELECTRICA YANAPAMPA SAC | U6: EMPRESA DE GENERACION ELECTRICA CANCHAYLLO SAC | V6: EMPRESA DE GENERACION ELECTRICA SANTA ANA S.A.C. | W6: EMPRESA ELECTRICA AGUA AZUL | X6: EMPRESA ELECTRICA RIO DOBLE | Y6: ENERGÍA EÓLICA S.A. | AA6: ENERGIA RENOVABLE DEL SUR S.A. | AB6: ENERGIA RENOVABLE LA JOYA S.A. | AD6: ENGIE ENERGIA PERU S.A.A. | AH6: GENERACIÓN ANDINA S.A.C. | AJ6: GENERADORA DE ENERGÍA DEL PERÚ | AN6: GR CORTARRAMA SOCIEDAD ANONIMA CERRADA | AO6: GR PAINO SOCIEDAD ANONIMA CERRADA | AP6: GR TARUCA SOCIEDAD ANONIMA CERRADA | AQ6: HIDROCAÑETE S.A. | AR6: HUAURA POWER GROUP S.A. | AS6: HYDRO PATAPO S.A.C. | AT6: JOYA SOLAR S.A.C. | AU6: KALLPA GENERACION S.A. | AW6: KONDU SAC | AX6: MAJA ENERGIA S.A.C. | AY6: MAJES ARCUS S.A.C. | BA6: MOQUEGUA FV S.A.C. | BB6: ORAZUL ENERGY PERÚ | BD6: ORYGEN PERU S.A.A. | BJ6: PANAMERICANA SOLAR SAC. | BK6: PARQUE EOLICO MARCONA S.A.C. | BL6: PARQUE EOLICO TRES HERMANAS S.A.C. | BM6: PETRAMAS | BQ6: REPARTICIÓN ARCUS S.A.C. | BR6: SAN GABAN | BS6: SINERSA | BV6: TACNA SOLAR SAC. | BW6: VARI ENERGIA S.A.C. | BX6: TOTAL RER
C7: C.T. PARAMONGA | D7: C.T. MAPLE | E7: C.T SAN JACINTO | F7: C.T. AGROLMOS | G7: C.H. CARHUAC | H7: C.H. HUALLIN | I7: C.H. PURMACANA | J7: C.T. CAÑA BRAVA | K7: C.T. CASA GRANDE | L7: C.H. MANTA | M7: CS COENERGY | N7: CS YARUCAYA | O7: C.H. HUASAHUASI I | P7: C.H. HUASAHUASI II | Q7: C.H. RUNATULLO II | R7: C.H. RUNATULLO III | S7: C.H. STA CRUZ I y II | T7: C.H. YANAPAMPA | U7: C.H. CANCHAYLLO | V7: C.H. RENOVANDES H1 | W7: C.H. POTRERO | X7: C.H. LAS PIZARRAS | Y7: C.E. CUPISNIQUE | Z7: C.E. TALARA | AA7: CE SAN JUAN | AB7: C.S. ILLA 1 | AC7: C.S. ILLA 2 | AD7: C.E. P LOM EXPANSION | AE7: C.E. PUNTA LOMITAS | AF7: C.S. INTIPAMPA | AG7: CS EXPANSIÓN INTIPAMPA | AH7: C.H. 8 DE AGOSTO | AI7: C.H. EL CARMEN | AJ7: C.H. ANGEL I | AK7: C.H. ANGEL II | AL7: C.H. ANGEL III | AM7: C.H. LA JOYA | AN7: CS MATARANI | AO7: C.E. HUAMBOS | AP7: C.E. DUNA | AQ7: C.H. NUEVAIMPERIAL | AR7: C.H. YARUCAYA | AS7: MCH PATAPO | AT7: CS SAN MARTIN SOLAR | AU7: CS SUNNY | AV7: CS SUNNY EXPANSION | AW7: CARHUAQUERO (CS) | AX7: C.H. RONCADOR | AY7: C.S. MAJES | AZ7: C.S. SOL DE VERANO | BA7: C.S. MOQUEGUA FV | BB7: C.H. CANA BRAVA | BC7: C.H. CARHUAQUERO4 | BD7: C.E. WAYRA EXTENSION | BE7: C.E. WAYRA I | BF7: C.H. HER 1 | BG7: C.S. CLEMESI | BH7: C.S. RUBI | BI7: C.S. Wayra Solar | BJ7: C.S. PANAMERICANA-SOLAR | BK7: C.E. MARCONA | BL7: C.E. 3 HERMANAS | BM7: C.T. HUAYCOLORO | BN7: C.T. LA GRINGA V | BO7: CTB CALLAO | BP7: CTB. DONA CATALINA | BQ7: C.S. REPARTICION | BR7: C.H. TUPURI | BS7: C.H. CHANCAY | BT7: C.H. POECHOS2 | BU7: C.H. RUCUY | BV7: C.S. TACNA-SOLAR | BW7: C.H. ANASHIRONI | BX7: MW
B8: 0:30 | C8: 15 | D8: 15.5 | E8: 7.9 | F8: 11.7 | G8: 6 | H8: 2.8 | I8: 0.4 | J8: 9.4 | K8: 22.4 | L8: 20 | O8: 19.8 | Q8: 20.3 | R8: 20.2 | S8: 8 | T8: 3.5 | U8: 5 | V8: 20.3 | W8: 20 | X8: 18.8 | Y8: 5.1 | Z8: 3.2 | AA8: 31.6 | AD8: 4.3 | AE8: 106.8 | AH8: 21 | AI8: 6.2 | AJ8: 20.4 | AK8: 20.4 | AL8: 20.1 | AM8: 7.2 | AO8: 0.25 | AQ8: 2.7 | AR8: 18.4 | AX8: 1.8 | BB8: 5.5 | BC8: 10 | BD8: 14.2 | BE8: 17.2 | BK8: 15.2 | BL8: 29.3 | BM8: 3.6 | BN8: 0.9 | BO8: 1.1 | BP8: 2.4 | BR8: 2.1 | BS8: 20 | BT8: 8.4 | BU8: 20 | BW8: 20.3 | BX8: 686.65
B9: 1:00 | C9: 15.1 | D9: 17.1 | E9: 8.3 | F9: 11.7 | G9: 3.2 | H9: 2.8 | I9: 0.4 | J9: 9.5 | K9: 21.7 | L9: 20 | O9: 19.8 | Q9: 19.9 | R9: 20.1 | S9: 8 | T9: 3.5 | U9: 5 | V9: 19.9 | W9: 20 | X9: 18.7 | Y9: 4.2 | Z9: 2.1 | AA9: 32.9 | AD9: 2.3 | AE9: 73.3 | AH9: 21 | AI9: 6.2 | AJ9: 20.4 | AK9: 20.4 | AL9: 20.1 | AM9: 6.9 | AQ9: 2.7 | AR9: 18.4 | AX9: 1.8 | BB9: 5.5 | BC9: 9.9 | BD9: 7.4 | BE9: 14.6 | BK9: 15.9 | BL9: 24 | BM9: 3.6 | BN9: 0.9 | BO9: 1.1 | BP9: 2.4 | BR9: 2.1 | BS9: 20 | BT9: 8.4 | BU9: 20 | BW9: 19.6 | BX9: 632.8
B10: 1:30 | C10: 14.5 | D10: 17.1 | E10: 7.6 | F10: 11.7 | G10: 3.4 | H10: 2.8 | I10: 0.4 | J10: 9.3 | K10: 22.3 | L10: 20 | O10: 19.8 | Q10: 19.9 | R10: 20.2 | S10: 8.1 | T10: 3.4 | U10: 5.1 | V10: 20.4 | W10: 20 | X10: 18.7 | Y10: 0.5 | Z10: 1.9 | AA10: 27.8 | AD10: 2.9 | AE10: 69.5 | AH10: 21 | AI10: 6.2 | AJ10: 20.4 | AK10: 20.4 | AL10: 20.1 | AQ10: 2.7 | AR10: 18.4 | AX10: 1.8 | BB10: 5.3 | BC10: 9.9 | BD10: 4.4 | BE10: 7.4 | BK10: 14.3 | BL10: 26.3 | BM10: 3.6 | BN10: 0.9 | BO10: 1.1 | BP10: 2.4 | BR10: 2.1 | BS10: 20 | BT10: 8.3 | BU10: 20 | BW10: 20.4 | BX10: 604.7
B11: 2:00 | C11: 14.5 | D11: 17.1 | E11: 8.3 | F11: 11.7 | G11: 3.4 | H11: 2.7 | I11: 0.4 | J11: 9.3 | K11: 22.7 | L11: 20 | O11: 19.8 | Q11: 20.1 | R11: 20.2 | S11: 8 | T11: 3.5 | U11: 5.1 | V11: 20.7 | W11: 20 | X11: 18.7 | Z11: 2.9 | AA11: 31.1 | AD11: 1.1 | AE11: 51.2 | AH11: 21 | AI11: 6.2 | AJ11: 20.4 | AK11: 20.4 | AL11: 20.1 | AQ11: 2.8 | AR11: 18.4 | AX11: 1.8 | BB11: 5.4 | BC11: 9.9 | BD11: 1.4 | BE11: 1.5 | BK11: 20.8 | BL11: 24.1 | BM11: 3.6 | BN11: 0.9 | BO11: 1.1 | BP11: 2.4 | BR11: 2.1 | BS11: 20 | BT11: 8.4 | BU11: 20 | BW11: 20.4 | BX11: 585.6
B12: 2:30 | C12: 15 | D12: 17.1 | E12: 7.7 | F12: 11.7 | G12: 3.4 | H12: 2.7 | I12: 0.4 | J12: 9.3 | K12: 21.6 | L12: 20 | O12: 19.8 | Q12: 19.6 | R12: 20.1 | S12: 8.1 | T12: 3.4 | U12: 5 | V12: 19.7 | W12: 20 | X12: 18.8 | Z12: 1.7 | AA12: 18.9 | AD12: 1.7 | AE12: 61.9 | AH12: 21 | AI12: 6.2 | AJ12: 20.4 | AK12: 20.4 | AL12: 20.1 | AQ12: 2.8 | AR12: 18.4 | AX12: 1.8 | BB12: 5.5 | BC12: 10 | BK12: 17.7 | BL12: 22.5 | BM12: 3.7 | BN12: 0.9 | BO12: 1.1 | BP12: 2.4 | BR12: 2.1 | BS12: 20 | BT12: 8.4 | BU12: 20 | BW12: 20.1 | BX12: 573.1
B13: 3:00 | C13: 14.5 | D13: 17.1 | E13: 8.6 | F13: 11.7 | G13: 3.4 | H13: 2.7 | I13: 0.4 | J13: 9.2 | K13: 22.4 | L13: 10 | O13: 19.8 | Q13: 19.8 | R13: 20.2 | S13: 8.1 | T13: 3.5 | U13: 5 | V13: 20.4 | W13: 20 | X13: 18.8 | Y13: 0.2 | Z13: 1.3 | AA13: 15.3 | AD13: 2.1 | AE13: 67.7 | AH13: 21 | AI13: 6.2 | AJ13: 20.4 | AK13: 20.4 | AL13: 20.1 | AQ13: 2.8 | AR13: 18.4 | AX13: 1.8 | BB13: 5.4 | BC13: 9.9 | BD13: 3.1 | BE13: 2.9 | BK13: 10.8 | BL13: 27.6 | BM13: 3.7 | BN13: 0.9 | BO13: 1.1 | BP13: 2.4 | BR13: 2.1 | BS13: 20 | BT13: 8.4 | BU13: 20 | BW13: 20.3 | BX13: 571.9
B14: 3:30 | C14: 14.5 | D14: 17.1 | E14: 8.1 | F14: 11.7 | G14: 3.4 | H14: 2.7 | I14: 0.4 | J14: 9.1 | K14: 22 | L14: 10 | O14: 19.8 | Q14: 19.9 | R14: 20.1 | S14: 8.2 | T14: 3.5 | U14: 5 | V14: 20.3 | W14: 20 | X14: 18.8 | Y14: 0.5 | Z14: 0.6 | AA14: 17.9 | AD14: 3.4 | AE14: 86.6 | AH14: 21 | AI14: 6.2 | AJ14: 20.4 | AK14: 20.4 | AL14: 20.1 | AQ14: 2.8 | AR14: 18.4 | AX14: 1.8 | BB14: 5.4 | BC14: 9.9 | BD14: 15.4 | BE14: 10.1 | BK14: 12.4 | BL14: 25.1 | BM14: 3.7 | BN14: 0.9 | BO14: 1.1 | BP14: 2.4 | BR14: 2.1 | BS14: 19.9 | BT14: 8.4 | BU14: 19.9 | BW14: 20.3 | BX14: 611.7
B15: 4:00 | C15: 14.5 | D15: 17.1 | E15: 8.1 | F15: 11.6 | G15: 3.4 | H15: 2.7 | I15: 0.4 | J15: 9.3 | K15: 21.7 | L15: 13.5 | O15: 19.8 | Q15: 19.8 | R15: 20.1 | S15: 8.2 | T15: 3.5 | U15: 5 | V15: 19.9 | W15: 20 | X15: 18.9 | Y15: 1 | Z15: 0.4 | AA15: 19 | AD15: 4.2 | AE15: 116.1 | AH15: 21 | AI15: 6.2 | AJ15: 20.4 | AK15: 20.4 | AL15: 20.1 | AO15: 0.21 | AQ15: 2.7 | AR15: 18.4 | AX15: 1.8 | BB15: 5.4 | BC15: 9.9 | BD15: 18.2 | BE15: 21.4 | BK15: 16 | BL15: 27 | BM15: 3.7 | BN15: 0.9 | BO15: 1.1 | BP15: 2.4 | BR15: 2.1 | BS15: 20 | BT15: 8.4 | BU15: 20 | BW15: 20.1 | BX15: 666.01
B16: 4:30 | C16: 15 | D16: 17.1 | E16: 8.4 | F16: 11.7 | G16: 3.4 | H16: 2.7 | I16: 0.4 | J16: 9.4 | K16: 22 | L16: 19.5 | O16: 19.8 | Q16: 19.8 | R16: 20.2 | S16: 8.1 | T16: 3.5 | U16: 4.9 | V16: 20.1 | W16: 20 | X16: 18.7 | Y16: 1.6 | Z16: 1 | AA16: 13 | AD16: 6.5 | AE16: 106 | AH16: 21 | AI16: 6.2 | AJ16: 20.4 | AK16: 20.4 | AL16: 20.1 | AO16: 0.29 | AQ16: 2.7 | AR16: 18.4 | AX16: 1.8 | BB16: 5.4 | BC16: 10 | BD16: 42.5 | BE16: 35.7 | BK16: 14.9 | BL16: 28.5 | BM16: 3.7 | BN16: 0.9 | BO16: 1.1 | BP16: 2.4 | BR16: 2.1 | BS16: 20 | BT16: 8.4 | BU16: 19.9 | BW16: 20.2 | BX16: 699.79
B17: 5:00 | C17: 15.4 | D17: 17.1 | E17: 8.4 | F17: 11.7 | G17: 3.4 | H17: 2.7 | I17: 0.4 | J17: 9.1 | K17: 22 | L17: 20 | O17: 19.8 | Q17: 19.9 | R17: 20.2 | S17: 8.2 | T17: 3.5 | U17: 4.9 | V17: 20 | W17: 20 | X17: 18.8 | Y17: 5.1 | Z17: 1.1 | AA17: 20.8 | AD17: 2.6 | AE17: 73.4 | AH17: 21 | AI17: 6.2 | AJ17: 20.4 | AK17: 20.4 | AL17: 20.1 | AO17: 0.56 | AP17: 0.15 | AQ17: 2.6 | AR17: 18.4 | AX17: 1.8 | BB17: 5.3 | BC17: 9.9 | BD17: 45.2 | BE17: 63.4 | BK17: 9.9 | BL17: 19.3 | BM17: 3.7 | BN17: 0.9 | BO17: 1.1 | BP17: 2.4 | BR17: 2.1 | BS17: 19.8 | BT17: 8.4 | BU17: 19.8 | BW17: 20.2 | BX17: 691.51
B18: 5:30 | C18: 15.4 | D18: 17.2 | E18: 6.9 | F18: 11.7 | G18: 3.4 | H18: 2.7 | I18: 0.4 | J18: 8.8 | K18: 20.7 | L18: 20 | O18: 19.8 | Q18: 19.9 | R18: 20.2 | S18: 8.2 | T18: 3.5 | U18: 5 | V18: 20.3 | W18: 20 | X18: 18.9 | Y18: 3.8 | Z18: 0.7 | AA18: 34.5 | AD18: 0.6 | AE18: 66.1 | AH18: 21 | AI18: 6.2 | AJ18: 20.4 | AK18: 20.4 | AL18: 20.1 | AO18: 0.8 | AP18: 0.49 | AQ18: 2.6 | AR18: 18.4 | AX18: 1.8 | BA18: 0.1 | BB18: 5.4 | BC18: 9.9 | BD18: 27.4 | BE18: 42.2 | BK18: 11.3 | BL18: 31.5 | BM18: 3.7 | BN18: 0.9 | BO18: 1.1 | BP18: 2.4 | BR18: 2.1 | BS18: 20 | BT18: 8.4 | BU18: 20 | BW18: 20.3 | BX18: 667.59
B19: 6:00 | C19: 15.1 | D19: 17.2 | E19: 7.3 | F19: 11.6 | G19: 3.4 | H19: 2.7 | I19: 0.4 | J19: 8.8 | K19: 20.7 | L19: 20 | O19: 19.7 | Q19: 20.1 | R19: 20.2 | S19: 8.1 | T19: 3.5 | U19: 5.1 | V19: 20.5 | W19: 20 | X19: 18.9 | Y19: 1.8 | Z19: 0.3 | AA19: 38.5 | AD19: 4 | AE19: 76.8 | AF19: 0.4 | AH19: 21 | AI19: 6.2 | AJ19: 20.4 | AK19: 20.4 | AL19: 20.1 | AN19: 0.7 | AQ19: 2.6 | AR19: 18.4 | AT19: 4 | AX19: 1.8 | AY19: 0.3 | BA19: 2.4 | BB19: 5.4 | BC19: 10 | BD19: 30.7 | BE19: 42.1 | BG19: 3.8 | BH19: 4.7 | BJ19: 3 | BK19: 13.5 | BL19: 39.5 | BM19: 3.7 | BN19: 0.9 | BO19: 1.1 | BP19: 2.4 | BR19: 2.1 | BS19: 20 | BT19: 8.4 | BU19: 20 | BV19: 0.8 | BW19: 20.4 | BX19: 715.9
B20: 6:30 | C20: 15.5 | D20: 17.2 | E20: 8.9 | F20: 11.7 | G20: 3.2 | H20: 2.6 | I20: 0.4 | J20: 8.9 | K20: 21.6 | L20: 20 | O20: 19.8 | Q20: 20.1 | R20: 20.2 | S20: 8 | T20: 3.5 | U20: 5.1 | V20: 20 | W20: 20 | X20: 18.8 | Y20: 0.6 | Z20: 0.3 | AA20: 31.5 | AD20: 2.1 | AE20: 72.8 | AF20: 2.4 | AG20: 0.7 | AH20: 21 | AI20: 6.2 | AJ20: 20.4 | AK20: 20.4 | AL20: 20.1 | AN20: 18.4 | AQ20: 2.5 | AR20: 18.4 | AT20: 53.3 | AU20: 1.6 | AX20: 1.8 | AY20: 1.4 | BA20: 8.7 | BB20: 5.3 | BC20: 9.8 | BD20: 56.1 | BE20: 57.1 | BF20: 0.3 | BG20: 25.1 | BH20: 34.8 | BJ20: 10.4 | BK20: 11.9 | BL20: 42.9 | BM20: 3.7 | BN20: 0.9 | BO20: 1.1 | BP20: 2.4 | BQ20: 1.1 | BR20: 1.8 | BS20: 20 | BT20: 8.4 | BU20: 20 | BV20: 1.7 | BW20: 20.2 | BX20: 885.1
B21: 7:00 | C21: 15.8 | D21: 17.2 | E21: 8 | F21: 11.7 | G21: 3.3 | H21: 2.6 | I21: 0.4 | J21: 9.1 | K21: 21.2 | L21: 20 | M21: 0.1 | O21: 19.8 | Q21: 20.2 | R21: 20.2 | S21: 8 | T21: 3.5 | U21: 5 | V21: 20.1 | W21: 20 | X21: 18.7 | Z21: 0.1 | AA21: 29.7 | AD21: 1.8 | AE21: 64.4 | AF21: 9 | AG21: 3.4 | AH21: 21 | AI21: 6.3 | AJ21: 20.4 | AK21: 20.4 | AL21: 20.1 | AN21: 43.1 | AQ21: 2.5 | AR21: 18.4 | AT21: 145.7 | AU21: 79.7 | AX21: 1.8 | AY21: 3.2 | BA21: 11.9 | BB21: 5.5 | BC21: 9.9 | BD21: 55.3 | BE21: 56.8 | BF21: 0.3 | BG21: 58.5 | BH21: 79.2 | BJ21: 14.6 | BK21: 6.9 | BL21: 32.6 | BM21: 3.7 | BN21: 0.9 | BO21: 1.1 | BP21: 2.4 | BQ21: 3.2 | BS21: 20 | BT21: 8.3 | BU21: 20 | BV21: 4.6 | BW21: 20.3 | BX21: 1151.9
B22: 7:30 | C22: 14.6 | D22: 13.8 | E22: 7.6 | F22: 11.2 | G22: 3.3 | H22: 2.6 | I22: 0.4 | J22: 9.2 | K22: 21.4 | L22: 20 | M22: 0.1 | N22: 0.1 | O22: 19.8 | Q22: 20.2 | R22: 20.2 | S22: 8 | T22: 3.6 | U22: 5 | V22: 20.2 | W22: 20 | X22: 18.8 | AA22: 30.1 | AD22: 2.7 | AE22: 62.1 | AF22: 19.6 | AG22: 10.5 | AH22: 20.9 | AI22: 6.3 | AJ22: 20.4 | AK22: 20.4 | AL22: 20.1 | AN22: 67.7 | AQ22: 2.6 | AR22: 18.4 | AT22: 203.6 | AU22: 164.7 | AX22: 1.8 | AY22: 5.7 | BA22: 12.9 | BB22: 5.4 | BC22: 9.9 | BD22: 47.1 | BE22: 51.3 | BF22: 0.6 | BG22: 77.8 | BH22: 112.6 | BJ22: 16.4 | BK22: 5.8 | BL22: 17.9 | BM22: 3.7 | BN22: 0.9 | BO22: 1.1 | BP22: 2.4 | BQ22: 2.7 | BS22: 20 | BT22: 8.3 | BU22: 20 | BV22: 9.4 | BW22: 20.3 | BX22: 1364.2
B23: 8:00 | C23: 16 | D23: 8.4 | E23: 7.5 | F23: 11.2 | G23: 3.3 | H23: 2.6 | I23: 0.4 | J23: 9.2 | K23: 22.6 | L23: 20 | M23: 0.2 | N23: 0.1 | O23: 19.8 | Q23: 20.1 | R23: 20.2 | S23: 8 | T23: 3.5 | U23: 5 | V23: 20.4 | W23: 20 | X23: 18.8 | AA23: 18 | AD23: 4.1 | AE23: 89.2 | AF23: 30.6 | AG23: 26 | AH23: 20.5 | AI23: 6.3 | AJ23: 20.4 | AK23: 20.4 | AL23: 20.1 | AN23: 75.5 | AQ23: 2.7 | AR23: 18.4 | AT23: 226.6 | AU23: 181.1 | AW23: 0.1 | AX23: 1.8 | AY23: 8.1 | BA23: 13.9 | BB23: 5.5 | BC23: 9.9 | BD23: 33.8 | BE23: 35.4 | BF23: 0.6 | BG23: 93.8 | BH23: 128.8 | BJ23: 16.9 | BK23: 6.3 | BL23: 15.9 | BM23: 3.7 | BN23: 0.9 | BO23: 1.1 | BP23: 2.4 | BQ23: 8.8 | BR23: 1.7 | BS23: 20 | BT23: 8.4 | BU23: 20 | BV23: 16 | BW23: 20.3 | BX23: 1471.3
B24: 8:30 | C24: 15.9 | D24: 8.4 | E24: 7.3 | F24: 11.2 | G24: 3.3 | H24: 2.6 | I24: 0.4 | J24: 9.2 | K24: 23 | L24: 20 | M24: 0.2 | N24: 0.5 | O24: 19.8 | Q24: 20.3 | R24: 20.2 | S24: 7.8 | T24: 3.4 | U24: 5 | V24: 20.3 | W24: 20 | X24: 18.8 | AA24: 18.5 | AD24: 4.3 | AE24: 101.7 | AF24: 31.1 | AG24: 45 | AH24: 20.7 | AI24: 6.3 | AJ24: 20.4 | AK24: 20.4 | AL24: 20.1 | AN24: 76.2 | AQ24: 2.7 | AR24: 18.4 | AT24: 242.7 | AU24: 193.4 | AW24: 0.1 | AX24: 1.8 | AY24: 10.6 | BA24: 14.4 | BB24: 5.5 | BC24: 10 | BD24: 28.8 | BE24: 29.2 | BF24: 0.6 | BG24: 99.1 | BH24: 135.5 | BJ24: 17.4 | BK24: 7.2 | BL24: 20.7 | BM24: 3.7 | BN24: 0.9 | BO24: 1.1 | BP24: 2.4 | BQ24: 10.4 | BR24: 1.8 | BS24: 20 | BT24: 8.3 | BU24: 20 | BV24: 19.2 | BW24: 20.3 | BX24: 1548.5
B25: 9:00 | C25: 15.1 | D25: 8.4 | E25: 6.5 | F25: 11.2 | G25: 3.3 | H25: 2.6 | I25: 0.4 | J25: 9.2 | K25: 22.7 | L25: 20 | M25: 0.3 | N25: 0.8 | O25: 19.8 | Q25: 20.3 | R25: 20.2 | S25: 7.8 | T25: 2 | U25: 5 | V25: 20.6 | W25: 20 | X25: 18.8 | AA25: 42.1 | AD25: 10 | AE25: 132.9 | AF25: 34.2 | AG25: 46.7 | AH25: 20.6 | AI25: 6.3 | AJ25: 20.4 | AK25: 20.4 | AL25: 20.1 | AN25: 78.8 | AQ25: 2.7 | AR25: 18.4 | AT25: 253 | AU25: 201.7 | AW25: 0.1 | AX25: 1.8 | AY25: 12.6 | BA25: 14.7 | BB25: 5.4 | BC25: 9.9 | BD25: 14.2 | BE25: 10 | BF25: 0.6 | BG25: 102.3 | BH25: 139.7 | BJ25: 17.9 | BK25: 7.8 | BL25: 30.5 | BM25: 3.6 | BN25: 0.9 | BO25: 1.1 | BP25: 2.4 | BQ25: 12.5 | BR25: 1.8 | BS25: 20 | BT25: 8.4 | BU25: 20 | BV25: 19.1 | BW25: 20.3 | BX25: 1620.9
B26: 9:30 | C26: 15 | D26: 8.4 | E26: 6.8 | F26: 11.1 | G26: 3.3 | H26: 2.6 | I26: 0.4 | J26: 8.8 | K26: 22.5 | L26: 20 | M26: 0.3 | N26: 0.9 | O26: 19.8 | Q26: 20.2 | R26: 20.2 | S26: 7.8 | T26: 2.4 | U26: 5 | V26: 20.3 | W26: 20 | X26: 18.8 | Y26: 0.1 | AA26: 53.3 | AD26: 17.1 | AE26: 142.9 | AF26: 32.8 | AG26: 49.9 | AH26: 20.2 | AI26: 6.3 | AJ26: 20.4 | AK26: 20.4 | AL26: 20.1 | AN26: 80.4 | AQ26: 2.8 | AR26: 18.4 | AT26: 253 | AU26: 209.4 | AW26: 0.2 | AX26: 1.8 | AY26: 14.1 | BA26: 14.6 | BB26: 5.4 | BC26: 9.9 | BD26: 10.5 | BE26: 5.4 | BF26: 0.6 | BG26: 103.3 | BH26: 140.7 | BJ26: 17.8 | BK26: 12.5 | BL26: 48.2 | BM26: 3.4 | BN26: 0.9 | BO26: 1.1 | BP26: 1.8 | BQ26: 14.3 | BR26: 1.8 | BS26: 20 | BT26: 8.4 | BU26: 20 | BV26: 19.2 | BW26: 20.2 | BX26: 1678.2
B27: 10:00 | C27: 15.1 | D27: 8.4 | E27: 9.1 | F27: 11 | G27: 3.4 | H27: 2.6 | I27: 0.3 | J27: 9.5 | K27: 22.5 | L27: 20.2 | M27: 0.3 | N27: 1.1 | O27: 19.8 | Q27: 20.3 | R27: 20.2 | S27: 7.7 | T27: 0.7 | U27: 5 | V27: 20.2 | W27: 20 | X27: 18.8 | Y27: 2.1 | Z27: 1.9 | AA27: 65.6 | AD27: 17.1 | AE27: 163.8 | AF27: 36.3 | AG27: 42.4 | AH27: 20.2 | AI27: 6.2 | AJ27: 20.4 | AK27: 20.4 | AL27: 20.1 | AN27: 80.8 | AQ27: 2.8 | AR27: 18.4 | AT27: 253.1 | AU27: 213.7 | AW27: 0.2 | AY27: 16 | BA27: 14.7 | BB27: 5.3 | BC27: 9.9 | BD27: 16.6 | BE27: 8 | BF27: 0.6 | BG27: 105.4 | BH27: 143.1 | BJ27: 18 | BK27: 12.7 | BL27: 44.2 | BM27: 3 | BN27: 0.9 | BO27: 1.1 | BP27: 1.8 | BQ27: 16.1 | BR27: 1.8 | BS27: 20 | BT27: 8.3 | BU27: 20 | BV27: 19.2 | BW27: 20.3 | BX27: 1728.7
B28: 10:30 | C28: 14.6 | D28: 8.4 | E28: 8.8 | F28: 10.5 | G28: 7.2 | H28: 2.5 | I28: 0.4 | J28: 9.4 | K28: 21.9 | L28: 20 | M28: 0.3 | N28: 1.2 | O28: 19.8 | Q28: 20.2 | R28: 20.1 | S28: 7.7 | T28: 1.9 | U28: 5 | V28: 20.1 | W28: 20 | X28: 18.8 | Y28: 3.6 | Z28: 3.8 | AA28: 82.6 | AD28: 19.3 | AE28: 146.9 | AF28: 15.9 | AG28: 42.4 | AH28: 20.2 | AI28: 6 | AJ28: 20.4 | AK28: 20.4 | AL28: 20.1 | AN28: 80.8 | AQ28: 2.8 | AR28: 18.4 | AT28: 253.1 | AU28: 215.9 | AW28: 0.2 | AY28: 17 | BA28: 14.8 | BB28: 5.5 | BC28: 9.9 | BD28: 32.7 | BE28: 17.4 | BF28: 0.6 | BG28: 107.9 | BH28: 144.3 | BJ28: 18.3 | BK28: 20 | BL28: 55.3 | BM28: 2.9 | BN28: 0.9 | BO28: 1.1 | BP28: 2 | BQ28: 17.3 | BR28: 1.8 | BS28: 20.1 | BT28: 8.3 | BU28: 20 | BV28: 19.3 | BW28: 20.2 | BX28: 1769.2
B29: 11:00 | C29: 14.8 | D29: 8.4 | E29: 6.9 | F29: 11 | G29: 8.9 | H29: 2.5 | I29: 0.2 | J29: 8.5 | K29: 22.5 | L29: 20 | M29: 0.3 | N29: 1.2 | O29: 19.8 | Q29: 20.2 | R29: 20.3 | S29: 7.6 | T29: 3.6 | U29: 5 | V29: 20.4 | W29: 20 | X29: 18.8 | Y29: 7.1 | Z29: 5.9 | AA29: 81.2 | AD29: 21.7 | AE29: 155.8 | AF29: 19.5 | AG29: 23.7 | AH29: 20.2 | AI29: 6.1 | AJ29: 20.4 | AK29: 20.4 | AL29: 20.1 | AN29: 80.8 | AQ29: 2.8 | AR29: 18.4 | AT29: 253 | AU29: 216.3 | AW29: 0.3 | AY29: 18 | BA29: 15 | BB29: 5.5 | BC29: 10 | BD29: 65.6 | BE29: 44.9 | BF29: 0.6 | BG29: 106.3 | BH29: 144.4 | BJ29: 18.5 | BK29: 20.1 | BL29: 62 | BM29: 3 | BN29: 0.9 | BO29: 1.1 | BP29: 1.9 | BQ29: 16.6 | BR29: 1.8 | BS29: 20 | BT29: 8.2 | BU29: 20 | BV29: 19.4 | BW29: 20.3 | BX29: 1838.7
B30: 11:30 | C30: 15 | D30: 9.1 | E30: 7.9 | F30: 11.1 | G30: 10.2 | H30: 2.5 | I30: 0.2 | J30: 8.3 | K30: 19.6 | L30: 20 | M30: 0.3 | N30: 1.3 | O30: 19.8 | Q30: 20.2 | R30: 20.2 | S30: 7.5 | T30: 3.6 | U30: 5 | V30: 20.2 | W30: 20 | X30: 18.8 | Y30: 12.7 | Z30: 4.3 | AA30: 85.3 | AD30: 19.3 | AE30: 170.1 | AF30: 30.6 | AG30: 26.1 | AH30: 19.8 | AI30: 6.2 | AJ30: 20.4 | AK30: 20.4 | AL30: 20.1 | AN30: 80.8 | AO30: 1.9 | AP30: 2.46 | AQ30: 2.6 | AR30: 18.4 | AT30: 253.2 | AU30: 214 | AW30: 0.4 | AX30: 1.8 | AY30: 18.3 | BA30: 15 | BB30: 5.5 | BC30: 10 | BD30: 92.1 | BE30: 77.8 | BF30: 0.6 | BG30: 104.5 | BH30: 140.9 | BJ30: 18.6 | BK30: 21.6 | BL30: 69.4 | BM30: 3.5 | BN30: 0.9 | BO30: 1.1 | BP30: 2.4 | BQ30: 16.9 | BR30: 1.8 | BS30: 20 | BT30: 8.2 | BU30: 20 | BV30: 19.2 | BW30: 20.2 | BX30: 1940.16
B31: 12:00 | C31: 14.8 | D31: 16.3 | E31: 8.2 | F31: 11.1 | G31: 18.7 | H31: 2.5 | I31: 0.2 | J31: 9 | K31: 20.9 | L31: 20 | M31: 0.4 | N31: 1.3 | O31: 19.8 | Q31: 20 | R31: 20.2 | S31: 7.5 | T31: 3.6 | U31: 5 | V31: 19.9 | W31: 20 | X31: 18.8 | Y31: 16.9 | Z31: 3.2 | AA31: 91.9 | AD31: 24.2 | AE31: 190.4 | AF31: 32.3 | AG31: 41.8 | AH31: 19.6 | AI31: 6.2 | AJ31: 20.4 | AK31: 20.4 | AL31: 20.1 | AN31: 80.8 | AO31: 3.45 | AP31: 7.08 | AQ31: 2.6 | AR31: 18.4 | AT31: 253.2 | AU31: 211.9 | AW31: 0.3 | AX31: 1.8 | AY31: 18.5 | BA31: 15 | BB31: 5.3 | BC31: 9.9 | BD31: 96.8 | BE31: 89.1 | BF31: 0.6 | BG31: 111.2 | BH31: 145.6 | BJ31: 18.7 | BK31: 23.2 | BL31: 76.8 | BM31: 3.6 | BN31: 0.9 | BO31: 1.1 | BP31: 2.3 | BQ31: 15.3 | BR31: 1.8 | BS31: 20 | BT31: 8.3 | BU31: 20 | BV31: 19.1 | BW31: 20.2 | BX31: 2048.43
B32: 12:30 | C32: 14.8 | D32: 16.3 | E32: 7.7 | F32: 11 | G32: 12 | H32: 2.5 | I32: 0.2 | J32: 9 | K32: 23.1 | L32: 20 | M32: 0.4 | N32: 0.9 | O32: 19.8 | Q32: 20.1 | R32: 20.2 | S32: 7.5 | T32: 3.6 | U32: 5 | V32: 19.7 | W32: 20 | X32: 18.9 | Y32: 17.5 | Z32: 4.9 | AA32: 84 | AD32: 28.4 | AE32: 190.4 | AF32: 34.5 | AG32: 40.2 | AH32: 19.6 | AI32: 6.2 | AJ32: 20.4 | AK32: 20.4 | AL32: 20.1 | AN32: 80.7 | AO32: 6.71 | AP32: 9.41 | AQ32: 2.6 | AR32: 18.4 | AT32: 253 | AU32: 213.7 | AW32: 0.3 | AX32: 1.8 | AY32: 18.7 | BA32: 15 | BB32: 5.5 | BC32: 9.9 | BD32: 99.8 | BE32: 99.3 | BF32: 0.6 | BG32: 107.8 | BH32: 120.3 | BJ32: 18.3 | BK32: 27.1 | BL32: 79.3 | BM32: 3.5 | BN32: 0.9 | BO32: 1.1 | BP32: 2.3 | BQ32: 16 | BR32: 1.8 | BS32: 19.8 | BT32: 8.3 | BU32: 19.8 | BV32: 19 | BW32: 20 | BX32: 2040.02
B33: 13:00 | C33: 14.9 | D33: 13.1 | E33: 7.4 | F33: 10.4 | G33: 12.6 | H33: 2.5 | I33: 0.2 | J33: 9 | K33: 22.3 | L33: 20 | M33: 0.4 | N33: 1.3 | O33: 19.8 | Q33: 20.2 | R33: 20.2 | S33: 7.4 | T33: 3.6 | U33: 5 | V33: 20 | W33: 20 | X33: 18.9 | Y33: 19.4 | Z33: 6.8 | AA33: 86.5 | AD33: 29.4 | AE33: 195.7 | AF33: 26.5 | AG33: 38 | AH33: 19.6 | AI33: 6 | AJ33: 20.4 | AK33: 20.4 | AL33: 20.1 | AN33: 80.9 | AO33: 9.01 | AP33: 10.18 | AQ33: 2.6 | AR33: 18.4 | AT33: 253 | AU33: 212.9 | AW33: 0.3 | AX33: 1.8 | AY33: 18.5 | BA33: 14.9 | BB33: 5.3 | BC33: 10 | BD33: 103.6 | BE33: 105 | BF33: 0.6 | BG33: 96 | BH33: 121.4 | BJ33: 17.2 | BK33: 24.8 | BL33: 75.8 | BM33: 3.5 | BN33: 0.9 | BO33: 1.1 | BP33: 2.3 | BQ33: 13.7 | BR33: 1.8 | BS33: 20 | BT33: 8.2 | BU33: 19.9 | BV33: 18.9 | BW33: 20.2 | BX33: 2030.69
B34: 13:30 | C34: 14.4 | D34: 13 | E34: 7.4 | F34: 10.8 | G34: 12.7 | H34: 2.5 | I34: 0.2 | J34: 9.4 | K34: 21.1 | L34: 20 | M34: 0.3 | N34: 0.9 | O34: 19.8 | Q34: 20.3 | R34: 20.2 | S34: 7.3 | T34: 3.5 | U34: 5 | V34: 20.2 | W34: 20 | X34: 18.9 | Y34: 20.2 | Z34: 10 | AA34: 97.3 | AD34: 22.6 | AE34: 191.6 | AF34: 31.8 | AG34: 37.8 | AH34: 19.6 | AI34: 6 | AJ34: 20.4 | AK34: 20.4 | AL34: 20.1 | AN34: 80.8 | AO34: 9.9 | AP34: 9.7 | AQ34: 2.6 | AR34: 18.4 | AT34: 253.2 | AU34: 207 | AW34: 0.2 | AX34: 1.8 | AY34: 17.8 | BA34: 14.8 | BB34: 5.5 | BC34: 9.9 | BD34: 109.9 | BE34: 115.4 | BF34: 0.6 | BG34: 104.6 | BH34: 129.1 | BJ34: 16.5 | BK34: 23.5 | BL34: 78.4 | BM34: 3.5 | BN34: 0.9 | BO34: 1.1 | BP34: 2.3 | BQ34: 11.8 | BR34: 1.8 | BS34: 20 | BT34: 8.2 | BU34: 19.8 | BV34: 18.7 | BW34: 20.2 | BX34: 2063.6
B35: 14:00 | C35: 14.7 | D35: 13 | E35: 8.4 | F35: 10.7 | G35: 12.7 | H35: 2.5 | I35: 0.2 | J35: 9.5 | K35: 22.4 | L35: 20 | M35: 0.3 | N35: 0.5 | O35: 19.8 | Q35: 20.3 | R35: 20.2 | S35: 7.3 | T35: 3.5 | U35: 5 | V35: 20.3 | W35: 20 | X35: 18.8 | Y35: 20.7 | Z35: 9.4 | AA35: 105.6 | AD35: 22.8 | AE35: 191.4 | AF35: 18.3 | AG35: 36.7 | AH35: 19.5 | AI35: 6 | AJ35: 20.4 | AK35: 20.4 | AL35: 20.1 | AN35: 80.8 | AO35: 8.17 | AP35: 8.06 | AQ35: 2.6 | AR35: 18.4 | AT35: 253 | AU35: 206.9 | AW35: 0.1 | AX35: 1.8 | AY35: 16.7 | BA35: 14.7 | BB35: 5.4 | BC35: 9.9 | BD35: 149.4 | BE35: 120.9 | BF35: 0.6 | BG35: 103.5 | BH35: 139.4 | BJ35: 17.1 | BK35: 24.4 | BL35: 80 | BM35: 3.5 | BN35: 0.9 | BO35: 1.1 | BP35: 2.3 | BQ35: 11 | BR35: 1.8 | BS35: 19.9 | BT35: 8.2 | BU35: 19.8 | BV35: 16.1 | BW35: 20.3 | BX35: 2108.13
B36: 14:30 | C36: 15 | D36: 13.1 | E36: 7.2 | F36: 11 | G36: 12.8 | H36: 2.5 | I36: 0.2 | J36: 9.4 | K36: 22.4 | L36: 20 | M36: 0.3 | N36: 0.4 | O36: 19.8 | Q36: 20.3 | R36: 20.3 | S36: 7.5 | T36: 3.6 | U36: 5.1 | V36: 20.5 | W36: 20 | X36: 18.9 | Y36: 20.9 | Z36: 8.1 | AA36: 110 | AD36: 19.3 | AE36: 194.4 | AF36: 34.2 | AG36: 26 | AH36: 19.2 | AI36: 6 | AJ36: 20.4 | AK36: 20.4 | AL36: 20 | AN36: 80.8 | AO36: 6.53 | AP36: 8.35 | AQ36: 2.6 | AR36: 18.4 | AT36: 250.7 | AU36: 187.6 | AW36: 0.1 | AX36: 1.8 | AY36: 15.3 | BA36: 14.6 | BB36: 5.5 | BC36: 9.9 | BD36: 141.3 | BE36: 120.3 | BF36: 0.6 | BG36: 89.8 | BH36: 94 | BJ36: 17.6 | BK36: 25.3 | BL36: 80.2 | BM36: 3.5 | BN36: 0.9 | BO36: 1.1 | BP36: 2.3 | BQ36: 11.8 | BR36: 1.8 | BS36: 20 | BT36: 8.2 | BU36: 20 | BV36: 12.8 | BW36: 20.4 | BX36: 2023.28
B37: 15:00 | C37: 15.4 | D37: 13.1 | E37: 9 | F37: 10.3 | G37: 12.9 | H37: 2.5 | I37: 0.2 | J37: 9.2 | K37: 22 | L37: 20 | M37: 0.4 | N37: 0.4 | O37: 19.8 | Q37: 20.2 | R37: 20.2 | S37: 7.6 | T37: 3.6 | U37: 5 | V37: 20 | W37: 20 | X37: 18.9 | Y37: 21.4 | Z37: 8 | AA37: 111 | AD37: 25.6 | AE37: 188.2 | AF37: 16.2 | AG37: 31.1 | AH37: 19.4 | AI37: 6 | AJ37: 20.4 | AK37: 20.4 | AL37: 20 | AN37: 78.2 | AO37: 5.39 | AP37: 5.84 | AQ37: 2.6 | AR37: 18.4 | AT37: 177.6 | AU37: 170.5 | AX37: 1.8 | AY37: 13.1 | BA37: 14.1 | BB37: 5.4 | BC37: 10 | BD37: 146.1 | BE37: 124.5 | BG37: 72.5 | BH37: 92.4 | BJ37: 17.2 | BK37: 25.4 | BL37: 80.9 | BM37: 3.5 | BN37: 0.9 | BO37: 1.1 | BP37: 2.3 | BQ37: 13.1 | BR37: 1.8 | BS37: 20 | BT37: 8.2 | BU37: 20 | BV37: 8.9 | BW37: 20.2 | BX37: 1900.33
B38: 15:30 | C38: 15.5 | D38: 10.7 | E38: 8.7 | F38: 10.4 | G38: 16.9 | H38: 1.9 | I38: 0.3 | J38: 9.5 | K38: 22.3 | L38: 20 | M38: 0.3 | N38: 0.3 | O38: 19.8 | Q38: 20.2 | R38: 20.2 | S38: 7.8 | T38: 2.8 | U38: 5 | V38: 20.4 | W38: 20 | X38: 18.7 | Y38: 26.9 | Z38: 7.3 | AA38: 99.7 | AD38: 18.7 | AE38: 165.7 | AF38: 27 | AG38: 20.7 | AH38: 19.4 | AI38: 6 | AJ38: 20.4 | AK38: 20.4 | AL38: 20 | AN38: 53.7 | AO38: 1.59 | AP38: 1.6 | AQ38: 2.6 | AR38: 18.4 | AT38: 125 | AU38: 165.4 | AX38: 1.8 | AY38: 11.3 | BA38: 13.1 | BB38: 5.5 | BC38: 10 | BD38: 152.5 | BE38: 116.3 | BG38: 66.1 | BH38: 86.8 | BJ38: 16.1 | BK38: 25 | BL38: 80.9 | BM38: 3.4 | BN38: 0.9 | BO38: 1.1 | BP38: 2.3 | BQ38: 7.1 | BR38: 1.8 | BS38: 20 | BT38: 8.2 | BU38: 20 | BV38: 6.9 | BW38: 20.3 | BX38: 1749.59
B39: 16:00 | C39: 15.2 | D39: 8 | E39: 7 | F39: 11.2 | G39: 17.3 | H39: 2.5 | I39: 0.3 | J39: 9.2 | K39: 22.3 | L39: 20.1 | M39: 0.3 | N39: 0.2 | O39: 19.8 | Q39: 20.2 | R39: 20.2 | S39: 7.7 | T39: 2.7 | U39: 5 | V39: 20.1 | W39: 20 | X39: 18.8 | Y39: 23.9 | Z39: 4.2 | AA39: 94.8 | AD39: 12.6 | AE39: 130.2 | AF39: 30.7 | AG39: 29 | AH39: 19.4 | AI39: 6 | AJ39: 20.4 | AK39: 20.4 | AL39: 20 | AN39: 63.4 | AO39: 1.08 | AP39: 0.1 | AQ39: 2.6 | AR39: 18.4 | AT39: 104.1 | AU39: 151 | AX39: 1.8 | AY39: 5.6 | BA39: 11.3 | BB39: 5.5 | BC39: 9.9 | BD39: 159.3 | BE39: 122.2 | BG39: 60.7 | BH39: 78.6 | BJ39: 14.2 | BK39: 26.1 | BL39: 73.5 | BM39: 2.8 | BN39: 0.9 | BO39: 1.1 | BP39: 1.8 | BQ39: 8.9 | BR39: 1.8 | BS39: 20 | BT39: 8.2 | BU39: 20 | BW39: 20.2 | BX39: 1654.78
B40: 16:30 | C40: 15 | D40: 8.9 | E40: 9.1 | F40: 10.8 | G40: 17.3 | H40: 2.7 | I40: 0.3 | J40: 9.1 | K40: 22.1 | L40: 20.1 | M40: 0.2 | N40: 0.2 | O40: 19.8 | Q40: 20.3 | R40: 20.2 | S40: 6.1 | T40: 3.4 | U40: 4.9 | V40: 20.2 | W40: 1.4 | X40: 18.8 | Y40: 29.1 | Z40: 3.7 | AA40: 92.3 | AD40: 11.7 | AE40: 109.7 | AF40: 17.4 | AG40: 42.7 | AH40: 19.4 | AI40: 6 | AJ40: 20.4 | AK40: 20.4 | AL40: 20 | AN40: 41.7 | AO40: 3.58 | AP40: 1.46 | AQ40: 2.6 | AR40: 18.4 | AT40: 73.7 | AU40: 98.3 | AX40: 1.8 | AY40: 6.6 | BA40: 8.5 | BB40: 5.3 | BC40: 10 | BD40: 162.2 | BE40: 121.1 | BG40: 56.1 | BH40: 70.5 | BJ40: 11.3 | BK40: 26.5 | BL40: 75.2 | BM40: 2.8 | BN40: 0.9 | BO40: 1.1 | BP40: 1.8 | BQ40: 2.9 | BR40: 1.7 | BS40: 20 | BT40: 8.1 | BU40: 20 | BW40: 20.3 | BX40: 1498.14
B41: 17:00 | C41: 15 | D41: 14.2 | E41: 7.4 | F41: 10.1 | G41: 17.4 | H41: 2.7 | I41: 0.3 | J41: 9 | K41: 22.3 | L41: 20 | M41: 0.2 | N41: 0.2 | O41: 19.8 | Q41: 20.1 | R41: 20.2 | T41: 3.5 | U41: 4.9 | V41: 20.2 | X41: 18.8 | Y41: 32.7 | Z41: 4.9 | AA41: 97.7 | AD41: 7 | AE41: 104.7 | AF41: 5.2 | AG41: 22.8 | AH41: 19.2 | AI41: 6 | AJ41: 20.4 | AK41: 20.4 | AL41: 20 | AN41: 32.5 | AO41: 2 | AP41: 0.53 | AQ41: 2.6 | AR41: 18.4 | AT41: 41.2 | AU41: 54.8 | AX41: 1.8 | AY41: 4.8 | BA41: 4.8 | BB41: 5.5 | BC41: 9.9 | BD41: 163.3 | BE41: 127.9 | BG41: 36.9 | BH41: 45 | BJ41: 7.9 | BK41: 22.1 | BL41: 74.2 | BM41: 2.8 | BN41: 0.9 | BO41: 1.1 | BP41: 1.8 | BQ41: 2.1 | BR41: 1.7 | BS41: 20 | BT41: 8.2 | BU41: 20 | BW41: 20.2 | BX41: 1322.23
B42: 17:30 | C42: 15.5 | D42: 17.1 | E42: 9.2 | F42: 10 | G42: 17.4 | H42: 2.8 | I42: 0.3 | J42: 8 | K42: 22.2 | L42: 20 | M42: 0.1 | N42: 0.1 | O42: 19.8 | Q42: 20.1 | R42: 20.2 | T42: 3.5 | U42: 4.9 | V42: 20.1 | W42: 3.3 | X42: 18.8 | Y42: 28.7 | Z42: 3.6 | AA42: 87.3 | AD42: 5 | AE42: 114.8 | AF42: 2.4 | AG42: 6.9 | AH42: 19 | AI42: 6 | AJ42: 20.4 | AK42: 20.4 | AL42: 20 | AN42: 13.2 | AO42: 2.08 | AP42: 0.55 | AQ42: 2.6 | AR42: 18.4 | AT42: 46.5 | AU42: 28.6 | AX42: 1.8 | AY42: 2.2 | BA42: 2.5 | BB42: 5.3 | BC42: 10 | BD42: 156.2 | BE42: 127.5 | BG42: 18.3 | BH42: 20.9 | BJ42: 3 | BK42: 21 | BL42: 76.2 | BM42: 2.8 | BN42: 0.9 | BO42: 1.1 | BP42: 1.8 | BQ42: 0.8 | BR42: 1.7 | BS42: 20 | BT42: 8.2 | BU42: 20 | BW42: 20.3 | BX42: 1202.33
B43: 18:00 | C43: 14.5 | D43: 17.1 | E43: 9.2 | F43: 11 | G43: 17.4 | H43: 2.8 | I43: 0.3 | J43: 7.9 | K43: 22.1 | L43: 20 | M43: 0.1 | N43: 0.1 | O43: 19.8 | Q43: 20.2 | R43: 20.2 | T43: 3.5 | U43: 4.8 | V43: 20 | W43: 20 | X43: 18.8 | Y43: 21.8 | Z43: 2.8 | AA43: 92.8 | AD43: 7.6 | AE43: 134.1 | AF43: 0.5 | AG43: 3.7 | AH43: 19 | AI43: 5.9 | AJ43: 20.4 | AK43: 20.4 | AL43: 20 | AN43: 4.4 | AO43: 3.06 | AP43: 0.94 | AQ43: 2.6 | AR43: 18.4 | AT43: 8.8 | AU43: 5.3 | AX43: 1.8 | AY43: 0.6 | BA43: 0.2 | BB43: 5.5 | BC43: 9.9 | BD43: 130.5 | BE43: 122.2 | BG43: 5.2 | BH43: 5.6 | BJ43: 0.1 | BK43: 21.6 | BL43: 70.6 | BM43: 2.8 | BN43: 0.9 | BO43: 1.1 | BP43: 2 | BQ43: 0.3 | BR43: 1.7 | BS43: 20 | BT43: 8.2 | BU43: 20 | BW43: 20.2 | BX43: 1093.3
B44: 18:30 | C44: 14 | D44: 17.1 | E44: 8.5 | F44: 11.1 | G44: 17.4 | H44: 2.9 | I44: 0.3 | J44: 7.9 | K44: 22.3 | L44: 20.1 | O44: 19.8 | Q44: 20.2 | R44: 20.2 | S44: 1.3 | T44: 3.5 | U44: 4.8 | V44: 20.2 | W44: 20 | X44: 18.7 | Y44: 20.4 | Z44: 1.8 | AA44: 95.3 | AD44: 15.3 | AE44: 163.9 | AG44: 0.8 | AH44: 18.8 | AI44: 5.8 | AJ44: 20.4 | AK44: 20.4 | AL44: 20 | AO44: 2.12 | AP44: 0.71 | AQ44: 2.5 | AR44: 18.4 | AU44: 0.2 | AX44: 1.8 | BB44: 5.4 | BC44: 9.8 | BD44: 132.1 | BE44: 116.4 | BG44: 0.2 | BK44: 24.4 | BL44: 73.6 | BM44: 3.2 | BN44: 0.9 | BO44: 0.9 | BP44: 2.4 | BR44: 1.7 | BS44: 20 | BT44: 8.1 | BU44: 20 | BW44: 20.3 | BX44: 1098.33
B45: 19:00 | C45: 15.4 | D45: 17.2 | E45: 6.6 | F45: 11.1 | G45: 17.4 | H45: 2.9 | I45: 0.3 | J45: 8.7 | K45: 22.5 | L45: 12.9 | O45: 19.7 | Q45: 20.2 | R45: 20.2 | S45: 3.5 | T45: 3.5 | U45: 4.7 | V45: 20.4 | W45: 20 | X45: 18.7 | Y45: 20.3 | Z45: 1.2 | AA45: 106.7 | AD45: 6 | AE45: 112.9 | AH45: 18.9 | AI45: 5.8 | AJ45: 20.4 | AK45: 20.4 | AL45: 20 | AO45: 2.48 | AP45: 0.94 | AQ45: 2.5 | AR45: 18.4 | AX45: 1.8 | BB45: 5.3 | BC45: 10 | BD45: 100 | BE45: 96.1 | BK45: 25.5 | BL45: 79.3 | BM45: 3.2 | BN45: 0.9 | BO45: 1 | BP45: 2.4 | BR45: 1.7 | BS45: 20 | BT45: 8.2 | BU45: 20 | BW45: 20.4 | BX45: 998.62
B46: 19:30 | C46: 14.7 | D46: 17.2 | E46: 7.7 | F46: 11.6 | G46: 17.4 | H46: 2.9 | I46: 0.3 | J46: 8.5 | K46: 22.2 | L46: 12.1 | O46: 19.7 | Q46: 20.2 | R46: 20.2 | S46: 4.7 | T46: 3.5 | U46: 5 | V46: 20.3 | W46: 20 | X46: 18.7 | Y46: 24.6 | Z46: 0.3 | AA46: 108.1 | AD46: 2.9 | AE46: 50.6 | AH46: 18.8 | AI46: 5.8 | AJ46: 20.4 | AK46: 20.4 | AL46: 20 | AO46: 2.62 | AP46: 1.36 | AQ46: 2.4 | AR46: 18.4 | AX46: 1.8 | BB46: 5.5 | BC46: 9.9 | BD46: 108.5 | BE46: 105.5 | BK46: 24.7 | BL46: 79.3 | BM46: 3.2 | BN46: 0.9 | BO46: 1.2 | BP46: 2.4 | BR46: 1.7 | BS46: 20 | BT46: 8.2 | BU46: 20 | BW46: 20.3 | BX46: 956.68
B47: 20:00 | C47: 14.7 | D47: 17.2 | E47: 5.8 | F47: 11.6 | G47: 17.4 | H47: 2.9 | I47: 0.3 | J47: 8.9 | K47: 22.4 | L47: 15 | O47: 19.7 | Q47: 20.2 | R47: 20.2 | S47: 4.6 | T47: 3.5 | U47: 5.1 | V47: 20.1 | W47: 20 | X47: 18.8 | Y47: 25.1 | Z47: 0.2 | AA47: 97.3 | AD47: 3.8 | AE47: 33.3 | AH47: 18.4 | AI47: 5.8 | AJ47: 20.4 | AK47: 20.4 | AL47: 20 | AO47: 2.08 | AP47: 0.54 | AQ47: 2.3 | AR47: 18.4 | AX47: 1.8 | BB47: 5.4 | BC47: 9.9 | BD47: 120.1 | BE47: 102.5 | BK47: 22.9 | BL47: 76.7 | BM47: 3.2 | BN47: 0.9 | BO47: 0.9 | BP47: 2.4 | BR47: 1.7 | BS47: 20 | BT47: 8.1 | BU47: 20 | BW47: 20.3 | BX47: 933.22
B48: 20:30 | C48: 14.7 | D48: 17.2 | E48: 6 | F48: 11.6 | G48: 17.4 | H48: 2.9 | I48: 0.3 | J48: 9.3 | K48: 22.3 | L48: 15 | O48: 19.7 | Q48: 20.2 | R48: 20.2 | S48: 7.9 | T48: 3.5 | U48: 5 | V48: 20.5 | W48: 20 | X48: 18.8 | Y48: 25.6 | Z48: 0.1 | AA48: 83.1 | AD48: 3.7 | AE48: 37.4 | AH48: 18.6 | AI48: 5.8 | AJ48: 20.4 | AK48: 20.4 | AL48: 20 | AO48: 2.25 | AP48: 1.05 | AQ48: 2.3 | AR48: 18.4 | AX48: 1.8 | BB48: 5.4 | BC48: 9.9 | BD48: 97.2 | BE48: 82.7 | BK48: 21.1 | BL48: 75.6 | BM48: 3.4 | BN48: 0.9 | BO48: 1 | BP48: 2.4 | BR48: 1.7 | BS48: 20 | BT48: 8 | BU48: 20 | BW48: 20.5 | BX48: 883.2
B49: 21:00 | C49: 14.7 | D49: 17.2 | E49: 6.3 | F49: 11.6 | G49: 17.4 | H49: 2.9 | I49: 0.3 | J49: 8.9 | K49: 22.3 | L49: 15 | O49: 19.7 | Q49: 20.1 | R49: 20.2 | S49: 7.9 | T49: 3.5 | U49: 5 | V49: 20 | W49: 20 | X49: 18.7 | Y49: 20 | Z49: 0.7 | AA49: 74.8 | AD49: 4.3 | AE49: 49 | AH49: 18.6 | AI49: 5.8 | AJ49: 20.4 | AK49: 20.4 | AL49: 20 | AO49: 1.89 | AP49: 1.21 | AQ49: 2.4 | AR49: 18.4 | AX49: 1.8 | BB49: 5.4 | BC49: 9.9 | BD49: 67.6 | BE49: 64.8 | BK49: 20.9 | BL49: 66.6 | BM49: 3.5 | BN49: 0.9 | BO49: 1 | BP49: 2.4 | BR49: 1.7 | BS49: 20 | BT49: 8 | BU49: 20 | BW49: 20.2 | BX49: 824.3
B50: 21:30 | C50: 14.9 | D50: 17.2 | E50: 7 | F50: 11.6 | G50: 17.4 | H50: 2.9 | I50: 0.3 | J50: 9.3 | K50: 22.5 | L50: 15 | O50: 19.8 | Q50: 20.2 | R50: 20.2 | S50: 7.9 | T50: 3 | U50: 5.1 | V50: 20.7 | W50: 20 | X50: 18.8 | Y50: 18 | Z50: 1.2 | AA50: 72.2 | AD50: 3.5 | AE50: 46.7 | AH50: 18.6 | AI50: 5.8 | AJ50: 20.4 | AK50: 20.4 | AL50: 20 | AO50: 2.24 | AP50: 0.92 | AQ50: 2.6 | AR50: 18.4 | AX50: 1.8 | BB50: 5.5 | BC50: 9.9 | BD50: 60 | BE50: 73.8 | BK50: 22.6 | BL50: 69 | BM50: 3.5 | BN50: 0.9 | BO50: 1 | BP50: 2.4 | BR50: 1.7 | BS50: 20 | BT50: 8.1 | BU50: 20 | BW50: 20.4 | BX50: 825.36
B51: 22:00 | C51: 15.2 | D51: 1.2 | E51: 7.7 | F51: 11.6 | G51: 17.4 | H51: 2.9 | I51: 0.3 | J51: 8.6 | K51: 22.3 | L51: 15 | O51: 19.8 | Q51: 20.2 | R51: 20.2 | S51: 7.9 | T51: 2.7 | U51: 5 | V51: 20.2 | W51: 20 | X51: 18.8 | Y51: 10.7 | Z51: 2.3 | AA51: 82.6 | AD51: 4.4 | AE51: 51.86 | AH51: 18.6 | AI51: 5.8 | AJ51: 20.4 | AK51: 20.4 | AL51: 20 | AO51: 1.67 | AP51: 0.75 | AQ51: 2.8 | AR51: 18.4 | AX51: 1.8 | BB51: 5.5 | BC51: 10 | BD51: 63.5 | BE51: 67.6 | BK51: 22.5 | BL51: 72.9 | BM51: 3.5 | BN51: 0.9 | BO51: 1 | BP51: 2.4 | BR51: 1.7 | BS51: 20 | BT51: 8.1 | BU51: 20 | BW51: 20.2 | BX51: 819.28
B52: 22:30 | C52: 14.5 | D52: 5 | E52: 8.5 | F52: 11.6 | G52: 11 | H52: 2.8 | I52: 0.3 | J52: 8.6 | K52: 21.3 | L52: 14.6 | O52: 19.8 | Q52: 20.2 | R52: 20.2 | S52: 8 | T52: 2.2 | U52: 5.1 | V52: 20.5 | W52: 20 | X52: 18.8 | Y52: 10.7 | Z52: 4.2 | AA52: 81.4 | AD52: 5.5994 | AE52: 83.77 | AH52: 18.4 | AI52: 5.9 | AJ52: 20.4 | AK52: 20.4 | AL52: 20 | AO52: 2.09 | AP52: 0.99 | AQ52: 2.8 | AR52: 18.4 | AX52: 1.8 | BB52: 5.2 | BC52: 9.9 | BD52: 50.3 | BE52: 61.3 | BK52: 21.8 | BL52: 67.5 | BM52: 3.7 | BN52: 0.9 | BO52: 1 | BP52: 2.4 | BR52: 1.7 | BS52: 20 | BT52: 8 | BU52: 20 | BW52: 20.3 | BX52: 823.8494
B53: 23:00 | C53: 14.2 | D53: 15.6 | E53: 7.3 | F53: 11.6 | G53: 9 | H53: 2.8 | I53: 0.3 | J53: 9.2 | K53: 22.4 | L53: 14.5 | O53: 19.8 | Q53: 20.1 | R53: 20.2 | S53: 7.9 | T53: 3.4 | U53: 5.1 | V53: 20.1 | W53: 20 | X53: 18.8 | Y53: 16.9 | Z53: 4.3 | AA53: 73.8 | AD53: 4.6227 | AE53: 115.52 | AH53: 18.3 | AI53: 5.8 | AJ53: 20.4 | AK53: 20.4 | AL53: 20 | AO53: 2.13 | AP53: 1.28 | AQ53: 2.8 | AR53: 18.4 | AX53: 1.8 | BB53: 5.5 | BC53: 10 | BD53: 95 | BE53: 89.6 | BK53: 23.5 | BL53: 68.1 | BM53: 3.8 | BN53: 0.9 | BO53: 1.3 | BP53: 2.4 | BR53: 1.7 | BS53: 20 | BT53: 8 | BU53: 20 | BW53: 20.2 | BX53: 938.7527
B54: 23:30 | C54: 14.2 | D54: 16.1 | E54: 7.5 | F54: 11.6 | G54: 4.6 | H54: 2.8 | I54: 0.3 | J54: 9.1 | K54: 23 | L54: 14.3 | O54: 19.8 | Q54: 20.2 | R54: 20.2 | S54: 8 | T54: 3.4 | U54: 5 | V54: 20.1 | W54: 20 | X54: 18.8 | Y54: 18.6 | Z54: 3.4 | AA54: 53.3 | AD54: 5.4366 | AE54: 133.48 | AH54: 18.2 | AI54: 5.8 | AJ54: 20.4 | AK54: 20.4 | AL54: 20 | AO54: 1.85 | AP54: 1.19 | AQ54: 2.8 | AR54: 18.4 | AX54: 1.8 | BB54: 5.4 | BC54: 9.9 | BD54: 84.2 | BE54: 92 | BK54: 24.3 | BL54: 68.7 | BM54: 3.8 | BN54: 0.9 | BO54: 1.9 | BP54: 2.4 | BR54: 1.7 | BS54: 20 | BT54: 8.1 | BU54: 20 | BW54: 20.4 | BX54: 927.7566
B55: 0:00 | C55: 14.5 | D55: 14.7 | E55: 8.3 | F55: 11.6 | G55: 3 | H55: 2.8 | I55: 0.3 | J55: 8.9 | K55: 23 | L55: 14 | O55: 19.7 | Q55: 20.2 | R55: 20.2 | S55: 8 | T55: 3.4 | U55: 5 | V55: 20.4 | W55: 20 | X55: 18.9 | Y55: 13.3 | Z55: 1.7 | AA55: 58.7 | AD55: 6.8603 | AE55: 150.69 | AH55: 18.2 | AI55: 5.8 | AJ55: 20.4 | AK55: 20.4 | AL55: 20 | AO55: 1.86 | AP55: 1.15 | AQ55: 2.6 | AR55: 18.4 | AX55: 1.8 | BB55: 5.5 | BC55: 10 | BD55: 78.5 | BE55: 97.9 | BK55: 20.4 | BL55: 60.6 | BM55: 3.8 | BN55: 0.9 | BO55: 2.1 | BP55: 2.4 | BR55: 1.7 | BS55: 20 | BT55: 8.1 | BU55: 20 | BW55: 20.3 | BX55: 930.9603
B56: EJEC MWh | C56: 358.15 | D56: 333.35 | E56: 187 | F56: 270.05 | G56: 230.4 | H56: 64.15 | I56: 7.75 | J56: 216.45 | K56: 529.85 | L56: 435.45 | M56: 3.05 | N56: 7 | O56: 474.85 | P56: 0 | Q56: 483 | R56: 484.65 | S56: 167.25 | T56: 78.5 | U56: 119.85 | V56: 485.2 | W56: 452.35 | X56: 451.15 | Y56: 287.15 | Z56: 65.9 | AA56: 1538.7 | AB56: 0 | AC56: 0 | AD56: 228.2595 | AE56: 2694.21 | AF56: 269.7 | AG56: 347.5 | AH56: 475.8 | AI56: 145.45 | AJ56: 489.6 | AK56: 489.6 | AL56: 481.4 | AM56: 7.05 | AN56: 767.95 | AO56: 45.92 | AP56: 39.495 | AQ56: 63.3 | AR56: 441.6 | AS56: 0 | AT56: 2243.65 | AU56: 1902.8 | AV56: 0 | AW56: 1.45 | AX56: 40.5 | AY56: 137.5 | AZ56: 0 | BA56: 148.3 | BB56: 130.1 | BC56: 238.3 | BD56: 1745.3 | BE56: 1606.85 | BF56: 4.8 | BG56: 958.35 | BH56: 1249.15 | BI56: 0 | BJ56: 181.5 | BK56: 448.05 | BL56: 1312.1 | BM56: 82.85 | BN56: 21.6 | BO56: 26.95 | BP56: 54.75 | BQ56: 117.35 | BR56: 42.35 | BS56: 479.75 | BT56: 197.95 | BU56: 479.45 | BV56: 143.75 | BW56: 486.15 | BX56: 29199.635
L70: TERMOELÉCTRICA | M70: 2081 | N70: 7.1268015 | O70: #FFA975
L71: SOLAR | M71: 8479 | N71: 29.038035 | O71: #FFD272
L72: HIDROELÉCTRICA | M72: 8627.7 | N72: 29.547288 | O72: #98D2FF
L73: EÓLICA | M73: 10011.934 | N73: 34.287876 | O73: #B9ACFF

Sheet COGENERACIÓN
B3: martes, 10 de Febrero del 2026
B5: CENTRALES DE COGENERACIÓN DEL SEIN
B6: HORA | C6: AGRO INDUSTRIAL PARAMONGA S.A. | D6: AGROAURORA S.A.C. | E6: AGROINDUSTRIAS SAN JACINTO S.A.A. | F6: AGROLMOS SOCIEDAD ANONIMA - AGROLMOS S.A. | G6: BIOENERGIA DEL CHIRA S.A. | H6: CASA GRANDE S.A.A. | I6: GM OPERACIONES S.A.C. | J6: TOTAL COGENERACION
C7: C.T. PARAMONGA | D7: C.T. MAPLE | E7: C.T SAN JACINTO | F7: C.T. AGROLMOS | G7: C.T. CAÑA BRAVA | H7: C.T. CASA GRANDE | I7: C.T. REFINERÍA TALARA | J7: MW
B8: 0:30 | C8: 15 | D8: 15.5 | E8: 7.9 | F8: 11.7 | G8: 9.4 | H8: 22.4 | I8: 62 | J8: 143.9
B9: 1:00 | C9: 15.1 | D9: 17.1 | E9: 8.3 | F9: 11.7 | G9: 9.5 | H9: 21.7 | I9: 61.5 | J9: 144.9
B10: 1:30 | C10: 14.5 | D10: 17.1 | E10: 7.6 | F10: 11.7 | G10: 9.3 | H10: 22.3 | I10: 62.2 | J10: 144.7
B11: 2:00 | C11: 14.5 | D11: 17.1 | E11: 8.3 | F11: 11.7 | G11: 9.3 | H11: 22.7 | I11: 62.6 | J11: 146.2
B12: 2:30 | C12: 15 | D12: 17.1 | E12: 7.7 | F12: 11.7 | G12: 9.3 | H12: 21.6 | I12: 62.2 | J12: 144.6
B13: 3:00 | C13: 14.5 | D13: 17.1 | E13: 8.6 | F13: 11.7 | G13: 9.2 | H13: 22.4 | I13: 62.5 | J13: 146
B14: 3:30 | C14: 14.5 | D14: 17.1 | E14: 8.1 | F14: 11.7 | G14: 9.1 | H14: 22 | I14: 62.7 | J14: 145.2
B15: 4:00 | C15: 14.5 | D15: 17.1 | E15: 8.1 | F15: 11.6 | G15: 9.3 | H15: 21.7 | I15: 62.2 | J15: 144.5
B16: 4:30 | C16: 15 | D16: 17.1 | E16: 8.4 | F16: 11.7 | G16: 9.4 | H16: 22 | I16: 61.5 | J16: 145.1
B17: 5:00 | C17: 15.4 | D17: 17.1 | E17: 8.4 | F17: 11.7 | G17: 9.1 | H17: 22 | I17: 60.3 | J17: 144
B18: 5:30 | C18: 15.4 | D18: 17.2 | E18: 6.9 | F18: 11.7 | G18: 8.8 | H18: 20.7 | I18: 60.7 | J18: 141.4
B19: 6:00 | C19: 15.1 | D19: 17.2 | E19: 7.3 | F19: 11.6 | G19: 8.8 | H19: 20.7 | I19: 61.3 | J19: 142
... B56: EJEC MWh | C56: 358.15 | D56: 333.35 | E56: 187 | F56: 270.05 | G56: 216.45 | H56: 529.85 | I56: 1476.3 | J56: 3371.15

Sheet EVO_PRO_ENE
B3: domingo, 1 de Febrero del 2026 - martes, 10 de Febrero del 2026
B5: EVOLUCIÓN DE LA PRODUCCIÓN DE LA ENERGÍA DIARIA DE LOS INTEGRANTES DEL COES (MWh)
B6: EMPRESA | C6: CENTRAL | D6: UNIDAD | E6: TIPO | F6: Febrero
F7: 1 | G7: 2 | H7: 3 | I7: 4 | J7: 5 | K7: 6 | L7: 7 | M7: 8 | N7: 9 | O7: 10 | P7: TOTAL
B8: AGRO INDUSTRIAL PARAMONGA S.A. | C8: C.T. PARAMONGA | D8: TV-01 | E8: TERMOELÉCTRICA | F8: 92.9 | H8: 156.65 | I8: 345.05 | J8: 344.4 | K8: 351.7 | L8: 348.35 | M8: 344.1 | N8: 355.8 | O8: 358.15 | P8: 2697.1
B9: AGROAURORA S.A.C. | C9: C.T. MAPLE ETANOL | D9: TV | E9: TERMOELÉCTRICA | F9: 110.05 | G9: 117.1 | H9: 78.05 | I9: 116.6 | J9: 112.25 | K9: 175.5 | L9: 405.55 | M9: 393.3 | N9: 419.14 | O9: 333.35 | P9: 2260.89
B10: AGROINDUSTRIAS SAN JACINTO S.A.A. | C10: C.T. SAN JACINTO | D10: CENTRAL | E10: TERMOELÉCTRICA | F10: 192 | G10: 124.86 | J10: 66.05 | K10: 176.1 | L10: 118.65 | M10: 194.1 | N10: 187.821 | O10: 187 | P10: 1246.581
B11: AGROLMOS SOCIEDAD ANONIMA - AGROLMOS S.A. | C11: C.T. AGROLMOS | D11: CENTRAL | E11: TERMOELÉCTRICA | F11: 217.05 | G11: 54.5 | H11: 154.01 | I11: 184.25 | J11: 265.85 | K11: 269.95 | L11: 216.55 | M11: 269.2 | N11: 270.6273 | O11: 270.05 | P11: 2172.0373
B12: ANDEAN POWER S.A.C. | C12: C.H.CARHUAC | D12: CENTRAL | E12: HIDROELÉCTRICA | F12: 358.3 | G12: 451.75 | H12: 464.5 | I12: 443.25 | J12: 354.65 | K12: 312.35 | L12: 297.1 | M12: 254.6 | N12: 218.65 | O12: 230.4 | P12: 3385.55
B13: ASOCIACIÓN SANTA LUCIA DE CHACAS | C13: C.H. HUALLIN | D13: CENTRAL | E13: HIDROELÉCTRICA | F13: 73.55 | G13: 74.4 | H13: 72.05 | I13: 73.5 | J13: 73.8 | K13: 75.7 | L13: 69.4 | M13: 64.4 | N13: 64.45 | O13: 64.15 | P13: 705.4
B14: ATRIA ENERGIA S.A.C. | C14: C.H. PURMACANA | D14: CENTRAL | E14: HIDROELÉCTRICA | F14: 9.6 | G14: 9.4 | H14: 8.5 | I14: 8.1 | J14: 7.3 | K14: 8.65 | L14: 9.6 | M14: 9.6 | N14: 9.6 | O14: 7.75 | P14: 88.1
B15: BIOENERGIA DEL CHIRA S.A. | C15: C.T. CAÑA BRAVA | D15: CENTRAL | E15: TERMOELÉCTRICA | F15: 218.2 | G15: 209.25 | H15: 197.7 | I15: 219.2 | J15: 219.95 | K15: 214.1 | L15: 211.45 | M15: 183.75 | N15: 218.8 | O15: 216.45 | P15: 2108.85
B16: CASA GRANDE S.A.A. | C16: C.T. CASA GRANDE | D16: TV3 | E16: TERMOELÉCTRICA | F16: 500.25 | G16: 273.865 | H16: 509.65 | I16: 507.8 | J16: 509.3 | K16: 506.55 | L16: 509.15 | M16: 494.55 | N16: 487.43705 | O16: 529.85 | P16: 4828.402
B17: CELARIS ENERGY S.A. | C17: C.H. MANTA I | D17: CENTRAL | E17: HIDROELÉCTRICA | F17: 480.2 | G17: 323.8 | H17: 480.4 | I17: 461.1 | J17: 480.05 | K17: 479.9 | L17: 321.75 | M17: 239.1 | N17: 479.85 | O17: 435.45 | P17: 4181.6
B18: CELEPSA | C18: C.H. EL PLATANAL | D18: CENTRAL | E18: HIDROELÉCTRICA | F18: 3920.15 | G18: 4860.55 | H18: 4886.25 | I18: 4890.05 | J18: 4601.45 | K18: 4459.6 | L18: 4787.6 | M18: 4228.75 | N18: 4244.15 | O18: 4631.6 | P18: 45510.15
B19: CELEPSA RENOVABLES S.R.L. | C19: C.H. MARAÑON | D19: CENTRAL | E19: HIDROELÉCTRICA | F19: 451.2 | G19: 443.15 | H19: 446.85 | I19: 451.2 | J19: 446 | K19: 451.2 | L19: 451.2 | M19: 451.2 | N19: 413.8 | O19: 451.75 | P19: 4457.55
B20: CENTRALES SANTA ROSA S.A.C. | C20: C.H. SANTA ROSA I | D20: CENTRAL | E20: HIDROELÉCTRICA | P20: 0
B21: CENTRALES SANTA ROSA S.A.C. | C21: C.H. SANTA ROSA II | D21: CENTRAL | E21: HIDROELÉCTRICA | P21: 0
B22: CHINANGO S.A.C. | C22: C.H. CHIMAY | D22: CENTRAL | E22: HIDROELÉCTRICA | F22: 3261.4 | G22: 3502.8 | H22: 3592.9 | I22: 3595.7 | J22: 3627.85 | K22: 3591.45 | L22: 3559.25 | M22: 2764.85 | N22: 3468.6 | O22: 3621.75 | P22: 34586.55
B23: CHINANGO S.A.C. | C23: C.H. YANANGO | D23: CENTRAL | E23: HIDROELÉCTRICA | F23: 1012.15 | G23: 1008.65 | H23: 1008.6 | I23: 1007.9 | J23: 1008.3 | K23: 1008.7 | L23: 1008.6 | M23: 1008.2 | N23: 1008.75 | O23: 1008.95 | P23: 10088.8
B24: COENERGY S.A.C. | C24: C.S. COENERGY | D24: CENTRAL | E24: SOLAR | F24: 2.55 | G24: 2.65 | H24: 2.55 | I24: 2.75 | J24: 3 | K24: 2.85 | L24: 3.1 | M24: 2.55 | N24: 2.9 | O24: 3.05 | P24: 27.95
B25: COLCA SOLAR S.A.C. | C25: C.S. YARUCAYA | D25: CENTRAL | E25: SOLAR | F25: 4.6 | G25: 3.15 | H25: 4.75 | I25: 6.05 | J25: 7.9 | K25: 4.25 | L25: 3.25 | M25: 8.35 | N25: 7.05 | O25: 7 | P25: 56.35
B26: EGASA | C26: C.H. CHARCANI III | D26: CENTRAL | E26: HIDROELÉCTRICA | F26: 15.6 | G26: 90.55 | H26: 143.75 | I26: 140.8 | J26: 155.7 | K26: 160.25 | L26: 162.2 | M26: 158.45 | N26: 161.1 | O26: 158 | P26: 1346.4
B27: EGASA | C27: C.H. CHARCANI IV | D27: CENTRAL | E27: HIDROELÉCTRICA | P27: 0
B28: EGASA | C28: C.H. CHARCANI V | D28: CENTRAL | E28: HIDROELÉCTRICA | F28: 3416.55 | G28: 3417.7 | H28: 3419.05 | I28: 3413.95 | J28: 3413.2 | K28: 3410.65 | L28: 3416.5 | M28: 3390.17 | N28: 3415.75 | O28: 3410.75 | P28: 34124.27
B29: EGASA | C29: C.H. CHARCANI VI | D29: CENTRAL | E29: HIDROELÉCTRICA | P29: 0
B30: EGASA | C30: C.T. CHILINA DIESEL | D30: CENTRAL | E30: TERMOELÉCTRICA | H30: 1.65 | I30: 1.05 | P30: 2.7
B31: EGASA | C31: C.T. CHILINA DIESEL | D31: TG | E31: TERMOELÉCTRICA | G31: 11.15 | P31: 11.15
B32: EGASA | C32: C.T. MOLLENDO DIESEL | D32: CENTRAL | E32: TERMOELÉCTRICA | P32: 0
B33: EGEJUNIN | C33: C.H. HUASAHUASI I | D33: CENTRAL | E33: HIDROELÉCTRICA | F33: 475.1 | G33: 473.7 | H33: 472.9 | I33: 474.85 | J33: 475.15 | K33: 475.25 | L33: 474.7 | M33: 475.5 | N33: 473.8 | O33: 474.85 | P33: 4745.8
B34: EGEJUNIN | C34: C.H. RUNATULLO II | D34: CENTRAL | E34: HIDROELÉCTRICA | F34: 481.7 | G34: 479 | H34: 480.35 | I34: 480.25 | J34: 480.65 | K34: 481.85 | L34: 475.45 | M34: 479.1 | N34: 482.6 | O34: 483 | P34: 4803.95
B35: EGEJUNIN | C35: C.H. RUNATULLO III | D35: CENTRAL | E35: HIDROELÉCTRICA | F35: 486.05 | G35: 485.95 | H35: 486.25 | I35: 486.25 | J35: 486.35 | K35: 484.75 | L35: 484.7 | M35: 484.6 | N35: 484.6 | O35: 484.65 | P35: 4854.15
B36: EGEJUNIN | C36: C.H. SANTA CRUZ I | D36: CENTRAL | E36: HIDROELÉCTRICA | F36: 310.05 | G36: 306.8 | H36: 306.75 | I36: 263.75 | J36: 274.95 | K36: 266.35 | L36: 244.05 | M36: 217 | N36: 192.1 | O36: 167.25 | P36: 2549.05
B37: EGEMSA | C37: C.H. MACHUPICCHU | D37: CENTRAL | E37: HIDROELÉCTRICA | F37: 3900 | G37: 3964.95 | H37: 3996.95 | I37: 3992.4 | J37: 3993.9 | K37: 3993.15 | L37: 3973.15 | M37: 3554.7 | N37: 3991.2 | O37: 3963.3 | P37: 39323.7
B38: EGESUR | C38: C.H. ARICOTA I | D38: CENTRAL | E38: HIDROELÉCTRICA | F38: 193.15 | G38: 193.75 | H38: 195.55 | I38: 189.75 | J38: 191 | K38: 191.5 | L38: 192.4 | M38: 189.3 | N38: 189.1 | O38: 189.25 | P38: 1914.75
B39: EGESUR | C39: C.H. ARICOTA II | D39: CENTRAL | E39: HIDROELÉCTRICA | F39: 128.65 | G39: 131.75 | H39: 131.25 | I39: 130.8 | J39: 135.7 | K39: 135.3 | L39: 133.75 | M39: 134.55 | N39: 135.95 | O39: 134.45 | P39: 1332.15
B40: EGESUR | C40: C.T. INDEPENDENCIA | D40: CENTRAL | E40: TERMOELÉCTRICA | F40: 100.3 | G40: 270.85 | H40: 77.05 | I40: 99.5 | J40: 99.75 | L40: 207.5 | M40: 190.25 | N40: 264.55 | O40: 162.15 | P40: 1471.9
B41: ELECTRICA YANAPAMPA SAC | C41: C.H. YANAPAMPA | D41: CENTRAL | E41: HIDROELÉCTRICA | F41: 79.85 | G41: 74.5 | H41: 76.35 | I41: 80.15 | J41: 79.6 | K41: 81.35 | L41: 72.5 | M41: 82.2 | N41: 82.95 | O41: 78.5 | P41: 787.95
B42: ELECTROPERU | C42: C.H. MANTARO | D42: CENTRAL | E42: HIDROELÉCTRICA | F42: 15110.1 | G42: 15251.95 | H42: 15325.1 | I42: 15267.6 | J42: 15274 | K42: 15224.9 | L42: 15290.35 | M42: 14854.15 | N42: 15255.1 | O42: 15255.75 | P42: 152109
B43: ELECTROPERU | C43: C.H. RESTITUCION | D43: CENTRAL | E43: HIDROELÉCTRICA | F43: 5096.35 | G43: 5132.8 | H43: 5143.4 | I43: 5124.1 | J43: 5135.15 | K43: 5156.55 | L43: 4693.75 | M43: 5050.4 | N43: 5165 | O43: 5160.8 | P43: 50858.3
B44: ELECTROPERU | C44: C.T. TUMBES | D44: MAK1 | E44: TERMOELÉCTRICA | P44: 0
B45: ELECTROPERU | C45: C.T. TUMBES | D45: MAK2 | E45: TERMOELÉCTRICA | P45: 0
B46: EMPRESA DE GENERACION ELECTRICA CANCHAYLLO SAC | C46: C.H. CANCHAYLLO | D46: CENTRAL | E46: HIDROELÉCTRICA | F46: 112.5 | G46: 100.8 | H46: 124.1 | I46: 103.55 | J46: 113.3 | K46: 123.6 | L46: 123.25 | M46: 116.85 | N46: 114.45 | O46: 119.85 | P46: 1152.25
B47: EMPRESA DE GENERACION ELECTRICA SANTA ANA S.A.C. | C47: C.H. RENOVANDES H1 | D47: CENTRAL | E47: HIDROELÉCTRICA | F47: 387.05 | G47: 388.1 | H47: 377.65 | I47: 489.2 | J47: 487.2 | K47: 486.7 | L47: 488.3 | M47: 486.6 | N47: 486.6 | O47: 485.2 | P47: 4562.6
B48: EMPRESA DE GENERACION HUALLAGA | C48: C.H. CHAGLLA | D48: CENTRAL | E48: HIDROELÉCTRICA | F48: 9464.9 | G48: 10349.55 | H48: 11041.4 | I48: 10527.6 | J48: 11010.7 | K48: 10765.2 | L48: 10480.3 | M48: 10669.45 | N48: 10937.3 | O48: 10777.85 | P48: 106024.25
B49: EMPRESA DE GENERACION HUALLAGA | C49: P.C.H. CHAGLLA | D49: CENTRAL | E49: HIDROELÉCTRICA | F49: 156 | G49: 156 | H49: 156 | I49: 156 | J49: 156 | K49: 155.9 | L49: 155.95 | M49: 156 | N49: 146.15 | O49: 156 | P49: 1550
B50: EMPRESA DE GENERACION HUANZA | C50: C.H. HUANZA | D50: CENTRAL | E50: HIDROELÉCTRICA | F50: 1009.8 | G50: 1357.1 | H50: 1200.6 | I50: 1277.05 | J50: 1010.95 | K50: 898.3 | L50: 855.85 | M50: 762.7 | N50: 571.5 | O50: 678.15 | P50: 9622
B51: EMPRESA ELECTRICA AGUA AZUL | C51: C.H. POTRERO | D51: CENTRAL | E51: HIDROELÉCTRICA | F51: 479.2 | G51: 443.5 | H51: 480 | I51: 480 | J51: 460.55 | K51: 480 | L51: 480 | M51: 480 | N51: 480 | O51: 452.35 | P51: 4715.6
B52: EMPRESA ELECTRICA RIO DOBLE | C52: C.H. LAS PIZARRAS | D52: CENTRAL | E52: HIDROELÉCTRICA | F52: 445.15 | G52: 442.95 | H52: 449.1 | I52: 450.85 | J52: 451.4 | K52: 452.55 | L52: 431.8 | M52: 446.7 | N52: 450.2 | O52: 451.15 | P52: 4471.85
B53: ENEL GENERACION PIURA S.A. | C53: C.T. MALACAS 1 | D53: TG6 | E53: TERMOELÉCTRICA | F53: 528.25 | G53: 146.85 | H53: 466.15 | I53: 778 | J53: 777.4 | K53: 679.35 | L53: 700.15 | M53: 748.75 | N53: 768.25 | O53: 664.75 | P53: 6257.9
B54: ENEL GENERACION PIURA S.A. | C54: C.T. MALACAS 2 | D54: TG4 | E54: TERMOELÉCTRICA | G54: 456.25 | H54: 338.3 | P54: 794.55
B55: ENEL GENERACION PIURA S.A. | C55: C.T. RF DE GENERACION TALARA | D55: TG5 | E55: TERMOELÉCTRICA | P55: 0
B56: ENERGÍA EÓLICA S.A. | C56: C.E. CUPISNIQUE | D56: CENTRAL | E56: EÓLICA | F56: 185.6 | G56: 29.8 | H56: 253.05 | I56: 813.3 | J56: 860.85 | K56: 628.6 | L56: 96.15 | M56: 130.3 | N56: 232.1 | O56: 287.15 | P56: 3516.9
B57: ENERGÍA EÓLICA S.A. | C57: C.E. TALARA | D57: CENTRAL | E57: EÓLICA | F57: 120.85 | G57: 102.7 | H57: 234.7 | I57: 258.65 | J57: 312.6 | K57: 259.5 | L57: 60.45 | M57: 98.7 | N57: 100.9 | O57: 65.9 | P57: 1614.95
B58: ENERGIA RENOVABLE DEL SUR S.A. | C58: C.E. SAN JUAN | D58: CENTRAL | E58: EÓLICA | F58: 872.2 | G58: 357.2 | H58: 934.7 | I58: 1367.05 | J58: 2517.3 | K58: 2802.15 | L58: 1631.05 | M58: 1301.35 | N58: 1741.65 | O58: 1538.7 | P58: 15063.35
B59: ENGIE ENERGIA PERU S.A.A. | C59: C.E. PUNTA LOMITAS | D59: PL-BL1 | E59: EÓLICA | F59: 372.47 | G59: 182.8 | H59: 344.8 | I59: 381.05 | J59: 696.7 | K59: 1768.45 | L59: 1162.7 | M59: 1101.95 | N59: 1248.2 | O59: 1018.925 | P59: 8278.045
B60: ENGIE ENERGIA PERU S.A.A. | C60: C.E. PUNTA LOMITAS | D60: PL-BL2 | E60: EÓLICA | F60: 651.42 | G60: 317.68 | H60: 622.3 | I60: 639.45 | J60: 1032.8 | K60: 2222.835 | L60: 1755 | M60: 1694.7 | N60: 1775.35 | O60: 1675.285 | P60: 12386.82
B61: ENGIE ENERGIA PERU S.A.A. | C61: C.E. PUNTA LOMITAS_EXP | D61: PUN LOM_EXP-BL1 | E61: EÓLICA | F61: 37.72 | G61: 20.85 | H61: 45.95 | I61: 34 | J61: 87.75 | K61: 255.1 | L61: 180.6 | M61: 160.6 | N61: 150.9 | O61: 117.64705 | P61: 1091.1171
B62: ENGIE ENERGIA PERU S.A.A. | C62: C.E. PUNTA LOMITAS_EXP | D62: PUN LOM_EXP-BL2 | E62: EÓLICA | F62: 35.66 | G62: 12.35 | H62: 26.65 | I62: 25.3 | J62: 53.1 | K62: 198.35 | L62: 133.05 | M62: 121.45 | N62: 120.35 | O62: 110.61245 | P62: 836.87245
B63: ENGIE ENERGIA PERU S.A.A. | C63: C.H. QUITARACSA | D63: CENTRAL | E63: HIDROELÉCTRICA | F63: 160.5 | H63: 363.05 | J63: 141.4 | M63: 153.65 | P63: 818.6
B64: ENGIE ENERGIA PERU S.A.A. | C64: C.H. YUNCAN | D64: CENTRAL | E64: HIDROELÉCTRICA | F64: 2509.05 | G64: 3075.25 | H64: 3078.4 | I64: 3064.85 | J64: 3061.75 | K64: 3062.5 | L64: 3064.5 | M64: 3059.5 | N64: 3062.4 | O64: 3052.205 | P64: 30090.405
B65: ENGIE ENERGIA PERU S.A.A. | C65: C.S. EXPANSIÓN INTIPAMPA | D65: CENTRAL | E65: SOLAR | F65: 275.3 | G65: 173.9 | H65: 153.2 | I65: 201.25 | J65: 271 | K65: 387.4 | L65: 347.35 | M65: 152.55 | N65: 219 | O65: 347.5 | P65: 2528.45
B66: ENGIE ENERGIA PERU S.A.A. | C66: C.S. INTIPAMPA | D66: CENTRAL | E66: SOLAR | F66: 169.75 | G66: 118.5 | H66: 170.3 | I66: 153.3 | J66: 231.05 | K66: 288.5 | L66: 252.9 | M66: 107.9 | N66: 167.75 | O66: 269.7 | P66: 1929.65
B67: ENGIE ENERGIA PERU S.A.A. | C67: C.T. CHILCA 1 | D67: TG1 | E67: TERMOELÉCTRICA | K67: 314.05 | L67: 884.6 | M67: 781.7 | N67: 576.15 | P67: 2556.5
B68: ENGIE ENERGIA PERU S.A.A. | C68: C.T. CHILCA 1 | D68: TG2 | E68: TERMOELÉCTRICA | F68: 688.65 | G68: 2238.5 | H68: 1625.8 | I68: 1372.6 | J68: 1318.4 | K68: 518.15 | L68: 776.85 | M68: 1401.15 | N68: 1840.1 | O68: 696.055 | P68: 12476.255
B69: ENGIE ENERGIA PERU S.A.A. | C69: C.T. CHILCA 1 | D69: TG3 | E69: TERMOELÉCTRICA | F69: 1749.05 | G69: 2707.15 | H69: 2345.55 | I69: 2401.55 | J69: 2309 | K69: 1144.35 | L69: 2425.25 | M69: 2387.9 | N69: 3178.6 | O69: 1811.015 | P69: 22459.415
B70: ENGIE ENERGIA PERU S.A.A. | C70: C.T. CHILCA 1 | D70: TV | E70: TERMOELÉCTRICA | P70: 0
B71: ENGIE ENERGIA PERU S.A.A. | C71: C.T. CHILCA 2 | D71: TG41 | E71: TERMOELÉCTRICA | F71: 1342.6 | G71: 1401.6 | H71: 1424.65 | I71: 1410.5 | J71: 1449.55 | K71: 1274.15 | L71: 1377.2 | M71: 176.85 | N71: 1151.4 | O71: 1304.675 | P71: 12313.175
B72: ENGIE ENERGIA PERU S.A.A. | C72: C.T. CHILCA 2 | D72: TV42 | E72: TERMOELÉCTRICA | F72: 764.75 | G72: 772.15 | H72: 773.2 | I72: 769.45 | J72: 785.95 | K72: 736.05 | L72: 755.7 | N72: 508.9 | O72: 745.765 | P72: 6611.915
B73: ENGIE ENERGIA PERU S.A.A. | C73: C.T. NEPI | D73: TG41 | E73: TERMOELÉCTRICA | P73: 0
B74: ENGIE ENERGIA PERU S.A.A. | C74: C.T. NEPI | D74: TG42 | E74: TERMOELÉCTRICA | P74: 0
B75: ENGIE ENERGIA PERU S.A.A. | C75: C.T. NEPI | D75: TG43 | E75: TERMOELÉCTRICA | P75: 0
B76: ENGIE ENERGIA PERU S.A.A. | C76: C.T. RF PLANTA ILO | D76: TG1 | E76: TERMOELÉCTRICA | P76: 0
B77: ENGIE ENERGIA PERU S.A.A. | C77: C.T. RF PLANTA ILO | D77: TG2 | E77: TERMOELÉCTRICA | P77: 0
B78: ENGIE ENERGIA PERU S.A.A. | C78: C.T. RF PLANTA ILO | D78: TG3 | E78: TERMOELÉCTRICA | P78: 0
B79: FENIX POWER PERÚ | C79: C.T. FENIX | D79: GT11 | E79: TERMOELÉCTRICA | F79: 3824.55 | G79: 1322.6 | P79: 5147.15
B80: FENIX POWER PERÚ | C80: C.T. FENIX | D80: GT12 | E80: TERMOELÉCTRICA | F80: 3832.7 | G80: 1262 | P80: 5094.7
B81: FENIX POWER PERÚ | C81: C.T. FENIX | D81: TV10 | E81: TERMOELÉCTRICA | F81: 4132.7 | G81: 1449.3 | P81: 5582
B82: GENERACIÓN ANDINA S.A.C. | C82: C.H. 8 DE AGOSTO | D82: CENTRAL | E82: HIDROELÉCTRICA | F82: 503.2 | G82: 504.5 | H82: 506.9 | I82: 510.9 | J82: 510.65 | K82: 511.25 | L82: 510.5 | M82: 350.25 | N82: 467.2 | O82: 475.8 | P82: 4851.15
B83: GENERACIÓN ANDINA S.A.C. | C83: C.H. EL CARMEN | D83: CENTRAL | E83: HIDROELÉCTRICA | F83: 186.7 | G83: 168.9 | H83: 192.15 | I83: 187.5 | J83: 161.5 | K83: 178.8 | L83: 174.55 | M83: 170.75 | N83: 155.75 | O83: 145.45 | P83: 1722.05
B84: GENERADORA DE ENERGÍA DEL PERÚ | C84: C.H. ÁNGEL I | D84: CENTRAL | E84: HIDROELÉCTRICA | F84: 489.6 | G84: 489.6 | H84: 488.15 | I84: 489.6 | J84: 489.6 | K84: 489.6 | L84: 489.6 | M84: 489.6 | N84: 487.5 | O84: 489.6 | P84: 4892.45
B85: GENERADORA DE ENERGÍA DEL PERÚ | C85: C.H. ÁNGEL II | D85: CENTRAL | E85: HIDROELÉCTRICA | F85: 489.6 | G85: 489.6 | H85: 488.09 | I85: 489.6 | J85: 489.6 | K85: 489.6 | L85: 489.6 | M85: 489.6 | N85: 476.8 | O85: 489.6 | P85: 4881.69
B86: GENERADORA DE ENERGÍA DEL PERÚ | C86: C.H. ÁNGEL III | D86: CENTRAL | E86: HIDROELÉCTRICA | F86: 482.4 | G86: 482.4 | H86: 481.77 | I86: 482.25 | J86: 372.4 | K86: 395.85 | L86: 481.85 | M86: 480 | N86: 464.1 | O86: 481.4 | P86: 4604.42
B87: GENERADORA DE ENERGÍA DEL PERÚ | C87: C.H. LA JOYA | D87: CENTRAL | E87: HIDROELÉCTRICA | H87: 11.35 | I87: 146.85 | J87: 149.25 | K87: 151.7 | L87: 141.35 | M87: 138.6 | N87: 153.8 | O87: 7.05 | P87: 899.95
B88: GM OPERACIONES S.A.C. | C88: CT REFINERIA TALARA | D88: TV1 REF TALARA | E88: TERMOELÉCTRICA | F88: 643.7 | G88: 650.4 | H88: 646.1 | I88: 648.85 | J88: 636.55 | K88: 658.1 | L88: 658.25 | M88: 663.75 | N88: 659 | O88: 658.05 | P88: 6522.75
B89: GM OPERACIONES S.A.C. | C89: CT REFINERIA TALARA | D89: TV2 REF TALARA | E89: TERMOELÉCTRICA | F89: 798.05 | G89: 814.9 | H89: 811.85 | I89: 804.9 | J89: 806.8 | K89: 822.5 | L89: 821.5 | M89: 828.45 | N89: 820.5 | O89: 818.25 | P89: 8147.7
B90: GR CORTARRAMA SOCIEDAD ANONIMA CERRADA | C90: C.S. MATARANI | D90: C.S. MATARANI | E90: SOLAR | F90: 697.55 | G90: 485.55 | H90: 712.35 | I90: 759.6 | J90: 691.2 | K90: 742.8 | L90: 577.85 | M90: 406.85 | N90: 813.65 | O90: 767.95 | P90: 6655.35
B91: GR PAINO SOCIEDAD ANONIMA CERRADA | C91: C.E. HUAMBOS | D91: CENTRAL | E91: EÓLICA | F91: 33.9 | G91: 3.45 | H91: 23.38 | I91: 119.45 | J91: 108.4 | K91: 24.55 | L91: 43.4 | M91: 166.1 | N91: 125.25 | O91: 45.92 | P91: 693.8
B92: GR TARUCA SOCIEDAD ANONIMA CERRADA | C92: C.E. DUNA | D92: CENTRAL | E92: EÓLICA | F92: 20.15 | G92: 1.45 | H92: 22.875 | I92: 122.7 | J92: 120.55 | K92: 13.95 | L92: 47.65 | M92: 195.15 | N92: 136 | O92: 39.495 | P92: 719.97
B93: HIDROCAÑETE S.A. | C93: C.H. IMPERIAL | D93: CENTRAL | E93: HIDROELÉCTRICA | F93: 80.1 | G93: 79.4 | H93: 77.3 | I93: 76.1 | J93: 79.6 | K93: 80.35 | L93: 79.25 | M93: 69 | N93: 57.95 | O93: 63.3 | P93: 742.35
B94: HIDROELECTRICA HUANCHOR S.A.C. | C94: C.H. HUANCHOR | D94: CENTRAL | E94: HIDROELÉCTRICA | F94: 442.35 | G94: 441.85 | H94: 444.25 | I94: 444.05 | J94: 445.45 | K94: 444.65 | L94: 441.75 | M94: 442.55 | N94: 443.2 | O94: 442.7 | P94: 4432.8
B95: HUAURA POWER GROUP S.A. | C95: C.H. YARUCAYA | D95: CENTRAL | E95: HIDROELÉCTRICA | F95: 444.15 | G95: 444.9 | H95: 414 | I95: 444.55 | J95: 444 | K95: 407.95 | L95: 445.85 | M95: 443.25 | N95: 441.6 | O95: 441.6 | P95: 4371.85
B96: HYDRO GLOBAL PERÚ S.A.C. | C96: CH SAN GABAN III | D96: CENTRAL | E96: HIDROELÉCTRICA | F96: 4870.1 | G96: 4860.15 | H96: 4181.5 | I96: 4832.05 | J96: 4836.35 | K96: 4856.5 | L96: 3440.165 | M96: 3481.85 | N96: 4821.6 | O96: 4846.65 | P96: 45026.915
B97: INFRAESTRUCTURAS Y ENERGIAS DEL PERU S.A.C. | C97: C.T. RF PTO MALDONADO | D97: CENTRAL | E97: TERMOELÉCTRICA | F97: 116.15 | P97: 116.15
B98: INFRAESTRUCTURAS Y ENERGIAS DEL PERU S.A.C. | C98: C.T. RF PUCALLPA | D98: CENTRAL | E98: TERMOELÉCTRICA | H98: 1.65 | P98: 1.65
B99: INLAND ENERGY SAC | C99: C.H. SANTA TERESA | D99: CENTRAL | E99: HIDROELÉCTRICA | F99: 2121.8 | G99: 2171.6 | H99: 2181.9 | I99: 2168.6 | J99: 2181.3 | K99: 2178.4 | L99: 2178.1 | M99: 1842.25 | N99: 2182.9 | O99: 2183 | P99: 21389.85
B100: INVERSIONES SHAQSHA S.A.C. | C100: C.H. PARIAC | D100: CENTRAL | E100: HIDROELÉCTRICA | F100: 55.2 | G100: 55.2 | H100: 53.75 | I100: 23.35 | J100: 26.3 | K100: 55.2 | L100: 57.6 | M100: 56.25 | N100: 55.15 | O100: 51.25 | P100: 489.25
B101: JOYA SOLAR S.A.C. | C101: C.S. SAN MARTIN SOLAR | D101: CENTRAL | E101: SOLAR | F101: 2235.75 | G101: 1360.05 | H101: 1920.65 | I101: 2422.6 | J101: 2091.95 | K101: 2507.15 | L101: 1888.9 | M101: 950.75 | N101: 2553.5 | O101: 2243.65 | P101: 20174.95
B102: KALLPA GENERACION S.A. | C102: C.H. CERRO DEL AGUILA | D102: CENTRAL | E102: HIDROELÉCTRICA | F102: 12999.15 | G102: 13385.9 | H102: 13468.165 | I102: 13399.45 | J102: 13384.15 | K102: 13334.9 | L102: 13380.85 | M102: 13180.15 | N102: 13226.95 | O102: 13288.35 | P102: 133048.02
B103: KALLPA GENERACION S.A. | C103: C.S. SUNNY | D103: CENTRAL | E103: SOLAR | F103: 1347.3 | G103: 985.75 | H103: 1702.5 | I103: 1960.45 | J103: 0.6 | K103: 1590.7 | L103: 1529.05 | M103: 732.5 | N103: 2068.1 | O103: 1902.8 | P103: 13819.75
...

Sheet G_AREAS
B3: martes, 10 de Febrero del 2026
B5: HORA | C5: RESUMEN DE GENERACIÓN POR ÁREAS DEL SEIN | D5: RESUMEN DE GENERACIÓN POR ÁREAS DEL SEIN | E5: RESUMEN DE GENERACIÓN POR ÁREAS DEL SEIN | F5: RESUMEN DE GENERACIÓN POR ÁREAS DEL SEIN | G5: RESUMEN DE GENERACIÓN POR ÁREAS DEL SEIN | H5: RESUMEN DE GENERACIÓN POR ÁREAS DEL SEIN | I5: RESUMEN DE GENERACIÓN POR ÁREAS DEL SEIN | J5: RESUMEN DE GENERACIÓN POR ÁREAS DEL SEIN | K5: RESUMEN DE GENERACIÓN POR ÁREAS DEL SEIN | L5: RESUMEN DE GENERACIÓN POR ÁREAS DEL SEIN | M5: RESUMEN DE GENERACIÓN POR ÁREAS DEL SEIN | N5: RESUMEN DE GENERACIÓN POR ÁREAS DEL SEIN | O5: RESUMEN DE GENERACIÓN POR ÁREAS DEL SEIN | P5: RESUMEN DE GENERACIÓN POR ÁREAS DEL SEIN | Q5: RESUMEN DE GENERACIÓN POR ÁREAS DEL SEIN | R5: RESUMEN DE GENERACIÓN POR ÁREAS DEL SEIN | S5: HORA | T5: GENERACIÓN POR TIPO DE GENERACIÓN | U5: GENERACIÓN POR TIPO DE GENERACIÓN | V5: GENERACIÓN POR TIPO DE GENERACIÓN | W5: GENERACIÓN POR TIPO DE GENERACIÓN | X5: GENERACIÓN POR TIPO DE GENERACIÓN | Y5: HORA | Z5: GENERACIÓN POR TIPO DE GENERACIÓN | AA5: GENERACIÓN POR TIPO DE GENERACIÓN | AB5: GENERACIÓN POR TIPO DE GENERACIÓN | AC5: GENERACIÓN POR TIPO DE GENERACIÓN | AD5: GENERACIÓN POR TIPO DE GENERACIÓN
C6: NORTE | D6: NORTE | E6: NORTE | F6: NORTE | G6: CENTRO | H6: CENTRO | I6: CENTRO | J6: CENTRO | K6: SUR | L6: SUR | M6: SUR | N6: SUR | O6: GENERACIÓN INTEGRANTES COES | P6: GENERACIÓN INTEGRANTES COES | Q6: GENERACIÓN INTEGRANTES COES | R6: GENERACIÓN INTEGRANTES COES | T6: INTEGRANTES COES | U6: INTEGRANTES COES | V6: INTEGRANTES COES | W6: INTEGRANTES COES | X6: INTEGRANTES COES | Z6: INTEGRANTES COES RER | AA6: INTEGRANTES COES RER | AB6: INTEGRANTES COES RER | AC6: INTEGRANTES COES RER | AD6: INTEGRANTES COES RER
C7: GENERACIÓN HIDROELÉCTRICA NORTE | D7: GENERACIÓN TERMOELÉCTRICA NORTE | E7: GENERACIÓN SOLAR NORTE | F7: GENERACIÓN EÓLICA NORTE | G7: GENERACIÓN HIDROELÉCTRICA CENTRO | H7: GENERACIÓN TERMOELÉCTRICA CENTRO | I7: GENERACIÓN SOLAR CENTRO | J7: GENERACIÓN EÓLICA CENTRO | K7: GENERACIÓN HIDROELÉCTRICA SUR | L7: GENERACIÓN TERMOELÉCTRICA SUR | M7: GENERACIÓN SOLAR SUR | N7: GENERACIÓN EÓLICA SUR | O7: GENERACIÓN COES NORTE | P7: GENERACIÓN COES CENTRO | Q7: GENERACIÓN COES SUR | R7: TOTAL GENERACION | T7: HIDROELÉCTRICA | U7: TERMOELÉCTRICA | V7: SOLAR | W7: EÓLICA | X7: TOTAL GENERACION | Z7: HIDROELÉCTRICA RER | AA7: TERMOELÉCTRICA RER | AB7: SOLAR RER | AC7: EÓLICA RER | AD7: TOTAL RER
B8: 00:30 | C8: 459.8 | D8: 128.9 | E8: 0 | F8: 8.55 | G8: 3368.5 | H8: 1814.7 | I8: 0 | J8: 218.6 | K8: 808 | L8: 0 | M8: 0 | N8: 0 | O8: 597.25 | P8: 5401.8 | Q8: 808 | R8: 6807.05 | S8: 00:30 | T8: 4636.3 | U8: 1943.6 | V8: 0 | W8: 227.15 | X8: 6807.05 | Y8: 00:30 | Z8: 369.6 | AA8: 89.9 | AB8: 0 | AC8: 227.15 | AD8: 686.65
B9: 01:00 | C9: 448.9 | D9: 129.8 | E9: 0 | F9: 6.3 | G9: 3320.1 | H9: 1731 | I9: 0 | J9: 170.4 | K9: 782.1 | L9: 0 | M9: 0 | N9: 0 | O9: 585 | P9: 5221.5 | Q9: 782.1 | R9: 6588.6 | S9: 01:00 | T9: 4551.1 | U9: 1860.8 | V9: 0 | W9: 176.7 | X9: 6588.6 | Y9: 01:00 | Z9: 364.7 | AA9: 91.4 | AB9: 0 | AC9: 176.7 | AD9: 632.8
B10: 01:30 | C10: 463.5 | D10: 130.2 | E10: 0 | F10: 2.4 | G10: 3302.8 | H10: 1673.1 | I10: 0 | J10: 152.6 | K10: 802.8 | L10: 0 | M10: 0 | N10: 0 | O10: 596.1 | P10: 5128.5 | Q10: 802.8 | R10: 6527.4 | S10: 01:30 | T10: 4569.1 | U10: 1803.3 | V10: 0 | W10: 155 | X10: 6527.4 | Y10: 01:30 | Z10: 359.2 | AA10: 90.5 | AB10: 0 | AC10: 155 | AD10: 604.7
B11: 02:00 | C11: 462.2 | D11: 131.7 | E11: 0 | F11: 2.9 | G11: 3328.8 | H11: 1577.9 | I11: 0 | J11: 131.2 | K11: 807.5 | L11: 0 | M11: 0 | N11: 0 | O11: 596.8 | P11: 5037.9 | Q11: 807.5 | R11: 6442.2 | S11: 02:00 | T11: 4598.5 | U11: 1709.6 | V11: 0 | W11: 134.1 | X11: 6442.2 | Y11: 02:00 | Z11: 359.9 | AA11: 91.6 | AB11: 0 | AC11: 134.1 | AD11: 585.6
B12: 02:30 | C12: 455.7 | D12: 129.6 | E12: 0 | F12: 1.7 | G12: 3334.3 | H12: 1534.4 | I12: 0 | J12: 122.7 | K12: 778.5 | L12: 0 | M12: 0 | N12: 0 | O12: 587 | P12: 4991.4 | Q12: 778.5 | R12: 6356.9 | S12: 02:30 | T12: 4568.5 | U12: 1664 | V12: 0 | W12: 124.4 | X12: 6356.9 | Y12: 02:30 | Z12: 358.2 | AA12: 90.5 | AB12: 0 | AC12: 124.4 | AD12: 573.1
B13: 03:00 | C13: 454.9 | D13: 131.5 | E13: 0 | F13: 1.5 | G13: 3401.3 | H13: 1448.7 | I13: 0 | J13: 129.5 | K13: 801.8 | L13: 0 | M13: 0 | N13: 0 | O13: 587.9 | P13: 4979.5 | Q13: 801.8 | R13: 6369.2 | S13: 03:00 | T13: 4658 | U13: 1580.2 | V13: 0 | W13: 131 | X13: 6369.2 | Y13: 03:00 | Z13: 349.3 | AA13: 91.6 | AB13: 0 | AC13: 131 | AD13: 571.9
B14: 03:30 | C14: 447 | D14: 130.7 | E14: 0 | F14: 1.1 | G14: 3203.7 | H14: 1496 | I14: 0 | J14: 170.9 | K14: 795 | L14: 0 | M14: 0 | N14: 0 | O14: 578.8 | P14: 4870.6 | Q14: 795 | R14: 6244.4 | S14: 03:30 | T14: 4445.7 | U14: 1626.7 | V14: 0 | W14: 172 | X14: 6244.4 | Y14: 03:30 | Z14: 349.1 | AA14: 90.6 | AB14: 0 | AC14: 172 | AD14: 611.7
B15: 04:00 | C15: 448.3 | D15: 130 | E15: 0 | F15: 1.61 | G15: 3165.8 | H15: 1507.8 | I15: 0 | J15: 221.9 | K15: 782.8 | L15: 0 | M15: 0 | N15: 0 | O15: 579.91 | P15: 4895.5 | Q15: 782.8 | R15: 6258.21 | S15: 04:00 | T15: 4396.9 | U15: 1637.8 | V15: 0 | W15: 223.51 | X15: 6258.21 | Y15: 04:00 | Z15: 352.1 | AA15: 90.4 | AB15: 0 | AC15: 223.51 | AD15: 666.01
B16: 04:30 | C16: 458 | D16: 130.1 | E16: 0 | F16: 2.89 | G16: 3247.6 | H16: 1470.5 | I16: 0 | J16: 247.1 | K16: 787.3 | L16: 0 | M16: 0 | N16: 0 | O16: 590.99 | P16: 4965.2 | Q16: 787.3 | R16: 6343.49 | S16: 04:30 | T16: 4492.9 | U16: 1600.6 | V16: 0 | W16: 249.99 | X16: 6343.49 | Y16: 04:30 | Z16: 358.1 | AA16: 91.7 | AB16: 0 | AC16: 249.99 | AD16: 699.79
B17: 05:00 | C17: 458.9 | D17: 128.6 | E17: 0 | F17: 6.91 | G17: 3226 | H17: 1457.9 | I17: 0 | J17: 234.6 | K17: 799.3 | L17: 0 | M17: 0 | N17: 0 | O17: 594.41 | P17: 4918.5 | Q17: 799.3 | R17: 6312.21 | S17: 05:00 | T17: 4484.2 | U17: 1586.5 | V17: 0 | W17: 241.51 | X17: 6312.21 | Y17: 05:00 | Z17: 358.2 | AA17: 91.8 | AB17: 0 | AC17: 241.51 | AD17: 691.51
B18: 05:30 | C18: 461.4 | D18: 126 | E18: 0 | F18: 5.79 | G18: 3349 | H18: 1540.4 | I18: 0 | J18: 213.6 | K18: 792.6 | L18: 0 | M18: 0.1 | N18: 0 | O18: 593.19 | P18: 5103 | Q18: 792.7 | R18: 6488.89 | S18: 05:30 | T18: 4603 | U18: 1666.4 | V18: 0.1 | W18: 219.39 | X18: 6488.89 | Y18: 05:30 | Z18: 359.3 | AA18: 88.8 | AB18: 0.1 | AC18: 219.39 | AD18: 667.59
B19: 06:00 | C19: 461.2 | D19: 126.9 | E19: 0 | F19: 2.1 | G19: 3358.6 | H19: 1565.2 | I19: 0 | J19: 245.1 | K19: 802.8 | L19: 0 | M19: 20.1 | N19: 0 | O19: 590.2 | P19: 5168.9 | Q19: 822.9 | R19: 6582 | S19: 06:00 | T19: 4622.6 | U19: 1692.1 | V19: 20.1 | W19: 247.2 | X19: 6582 | Y19: 06:00 | Z19: 359.8 | AA19: 88.8 | AB19: 20.1 | AC19: 247.2 | AD19: 715.9
... B56: TOTAL MWh | C56: 10930.6 | D56: 3677.75 | E56: 1.45 | F56: 438.465 | G56: 82186.905 | H56: 43542.71 | I56: 10.05 | J56: 9573.4695 | K56: 19134.25 | L56: 0 | M56: 8467.5 | N56: 0 | O56: 15048.265 | P56: 135313.13 | Q56: 27601.75 | R56: 177963.15 | S56: TOTAL MWh | T56: 112251.76 | U56: 47220.46 | V56: 8479 | W56: 10011.934 | X56: 177963.15 | Y56: TOTAL MWh | Z56: 8627.7 | AA56: 2081 | AB56: 8479 | AC56: 10011.934 | AD56: 29199.635

Sheet HOP
B3: martes, 10 de Febrero del 2026
B5: Reporte de Horas de Operación
B6: Empresa | C6: Central | D6: Grupo | E6: Modo de Operación | F6: Inicio | G6: Final | H6: O. Arranque | I6: O. Parada | J6: Tipo Operación | K6: Ensayo de Potencia Efectiva | L6: Ensayo de Potencia Mínima | M6: Sistema | N6: Lim. Transm. | O6: Causa | P6: Observación
B7: AGRO INDUSTRIAL PARAMONGA S.A. | C7: C.T. PARAMONGA | D7: CENTRAL | E7: PARAMONGA - BAGAZO | F7: 10/02/2026 00:00:00 | G7: 11/02/2026 00:00:00 | J7: POR COGENERACION | O7: ...
B8: AGROAURORA S.A.C. | C8: C.T. MAPLE ETANOL | D8: CENTRAL | E8: MAPLE- BAGAZO | F8: 10/02/2026 00:00:00 | G8: 10/02/2026 21:43:00 | J8: POR COGENERACION | O8: ...
B9: AGROAURORA S.A.C. | C9: C.T. MAPLE ETANOL | D9: CENTRAL | E9: MAPLE- BAGAZO | F9: 10/02/2026 21:59:00 | G9: 11/02/2026 00:00:00 | J9: POR COGENERACION | O9: ...
B10: AGROINDUSTRIAS SAN JACINTO S.A.A. | C10: C.T. SAN JACINTO | D10: CENTRAL | E10: SAN_JACINTO - BAGAZO | F10: 10/02/2026 00:00:00 | G10: 11/02/2026 00:00:00 | J10: POR COGENERACION | O10: ...
B11: AGROLMOS SOCIEDAD ANONIMA - AGROLMOS S.A. | C11: C.T. AGROLMOS | D11: CENTRAL | E11: AGROLMOS TV1 & TV2 - BAGAZO | F11: 10/02/2026 00:00:00 | G11: 11/02/2026 00:00:00 | J11: POR COGENERACION | O11: ...
B12: BIOENERGIA DEL CHIRA S.A. | C12: C.T. CAÑA BRAVA | D12: G-1 | E12: CANA BRAVA TV1 - BAGAZO | F12: 10/02/2026 00:00:00 | G12: 11/02/2026 00:00:00 | J12: POR COGENERACION | O12: ...
B13: CASA GRANDE S.A.A. | C13: C.T. CASA GRANDE | D13: CENTRAL | E13: CASA GRANDE TV1 & TV3 - BAGAZO | F13: 10/02/2026 00:00:00 | G13: 11/02/2026 00:00:00 | J13: POR COGENERACION | O13: ...
B14: EGESUR | C14: C.T. INDEPENDENCIA | D14: CENTRAL | E14: INDEPENDENCIA GAS | F14: 10/02/2026 11:22:00 | G14: 10/02/2026 12:29:00 | H14: 10/02/2026 11:16:00 | J14: POR POTENCIA O ENERGIA | O14: ...
B15: EGESUR | C15: C.T. INDEPENDENCIA | D15: CENTRAL | E15: INDEPENDENCIA GAS | F15: 10/02/2026 12:29:00 | G15: 10/02/2026 12:58:00 | I15: 10/02/2026 12:50:00 | J15: A MINIMA CARGA | O15: ...
B16: EGESUR | C16: C.T. INDEPENDENCIA | D16: CENTRAL | E16: INDEPENDENCIA GAS | F16: 10/02/2026 14:59:00 | G16: 10/02/2026 18:04:00 | H16: 10/02/2026 14:55:00 | I16: 10/02/2026 17:54:00 | J16: POR POTENCIA O ENERGIA | O16: ...
B17: EGESUR | C17: C.T. INDEPENDENCIA | D17: CENTRAL | E17: INDEPENDENCIA GAS | F17: 10/02/2026 19:08:00 | G17: 10/02/2026 22:49:00 | H17: 10/02/2026 19:04:00 | I17: 10/02/2026 22:39:00 | J17: POR POTENCIA O ENERGIA | O17: ...
B18: ENEL GENERACION PIURA S.A. | C18: C.T. MALACAS 1 | D18: CENTRAL | E18: MALACAS1 TG6 - GAS | F18: 10/02/2026 08:34:00 | G18: 10/02/2026 23:46:00 | H18: 10/02/2026 08:18:00 | I18: 10/02/2026 23:30:00 | J18: POR POTENCIA O ENERGIA | O18: ...
B19: ENGIE ENERGIA PERU S.A.A. | C19: C.T. CHILCA 1 | D19: TG3 | E19: CHILCA1 TG3 - GAS | F19: 10/02/2026 11:46:00 | G19: 10/02/2026 12:29:00 | H19: 10/02/2026 11:26:00 | J19: POR POTENCIA O ENERGIA | O19: ...
B20: ENGIE ENERGIA PERU S.A.A. | C20: C.T. CHILCA 1 | D20: TG3 | E20: CHILCA1 TG3 - GAS | F20: 10/02/2026 12:29:00 | G20: 10/02/2026 14:53:00 | J20: A MINIMA CARGA | O20: ...
B21: ENGIE ENERGIA PERU S.A.A. | C21: C.T. CHILCA 1 | D21: TG3 | E21: CHILCA1 TG3 - GAS | F21: 10/02/2026 14:53:00 | G21: 10/02/2026 22:44:00 | J21: POR POTENCIA O ENERGIA | O21: ... | P21: A las 18:00 h, S/C generar a 100 MW. A las 18:38 h, S/C generar a máxima generación.
B22: ENGIE ENERGIA PERU S.A.A. | C22: C.T. CHILCA 1 | D22: TG2 | E22: CHILCA1 TG2 - GAS | F22: 10/02/2026 15:28:00 | G22: 10/02/2026 23:13:00 | H22: 10/02/2026 15:12:00 | I22: 10/02/2026 23:02:00 | J22: POR POTENCIA O ENERGIA | O22: ... | P22: A las 15:28 h, S/C generar a 107 MW. A las 16:11 h, S/C generar a mínimo del segundo tramo. A las 20:03 h, S/C generar a mínimo del segundo tramo. A las 22:22 h, S/C generar a mínimo del segundo tramo.
B23: ENGIE ENERGIA PERU S.A.A. | C23: C.T. CHILCA 1 | D23: TG3 | E23: CHILCA1 TG3 - GAS | F23: 10/02/2026 22:44:00 | G23: 10/02/2026 23:25:00 | I23: 10/02/2026 23:11:00 | J23: A MINIMA CARGA | O23: ...
B24: ENGIE ENERGIA PERU S.A.A. | C24: C.T. CHILCA 2 | D24: CENTRAL | E24: CHILCA2 CCOMB TG41 - GAS | F24: 10/02/2026 00:00:00 | G24: 10/02/2026 09:43:00 | J24: A MINIMA CARGA | O24: ...
B25: ENGIE ENERGIA PERU S.A.A. | C25: C.T. CHILCA 2 | D25: CENTRAL | E25: CHILCA2 CCOMB TG41 - GAS | F25: 10/02/2026 09:43:00 | G25: 10/02/2026 12:58:00 | J25: POR POTENCIA O ENERGIA | O25: ...
B26: ENGIE ENERGIA PERU S.A.A. | C26: C.T. CHILCA 2 | D26: CENTRAL | E26: CHILCA2 CCOMB TG41 - GAS | F26: 10/02/2026 12:58:00 | G26: 10/02/2026 14:51:00 | J26: A MINIMA CARGA | O26: ...
B27: ENGIE ENERGIA PERU S.A.A. | C27: C.T. CHILCA 2 | D27: CENTRAL | E27: CHILCA2 CCOMB TG41 - GAS | F27: 10/02/2026 14:51:00 | G27: 10/02/2026 23:11:00 | J27: POR POTENCIA O ENERGIA | O27: ...
B28: ENGIE ENERGIA PERU S.A.A. | C28: C.T. CHILCA 2 | D28: CENTRAL | E28: CHILCA2 CCOMB TG41 - GAS | F28: 10/02/2026 23:11:00 | G28: 11/02/2026 00:00:00 | J28: A MINIMA CARGA | O28: ...
B29: GM OPERACIONES S.A.C. | C29: CT REFINERIA TALARA | D29: TV1 REF TALARA | E29: REF_TALARA TV1 - NLH_RFG | F29: 10/02/2026 00:00:00 | G29: 11/02/2026 00:00:00 | J29: POR COGENERACION | O29: ...
B30: GM OPERACIONES S.A.C. | C30: CT REFINERIA TALARA | D30: TV2 REF TALARA | E30: REF_TALARA TV2 - NLH_RFG | F30: 10/02/2026 00:00:00 | G30: 11/02/2026 00:00:00 | J30: POR COGENERACION | O30: ...
B31: KALLPA GENERACION S.A. | C31: C.T. KALLPA | D31: CENTRAL | E31: KALLPA CCOMB TG1 & TG2 & TG3 - GAS | F31: 10/02/2026 00:00:00 | G31: 10/02/2026 00:16:00 | J31: POR RSF | O31: ...
B32: KALLPA GENERACION S.A. | C32: C.T. KALLPA | D32: CENTRAL | E32: KALLPA CCOMB TG1 & TG2 & TG3 - GAS | F32: 10/02/2026 00:16:00 | G32: 10/02/2026 00:45:00 | J32: POR POTENCIA O ENERGIA | O32: ...
B33: KALLPA GENERACION S.A. | C33: C.T. KALLPA | D33: CENTRAL | E33: KALLPA CCOMB TG1 & TG2 & TG3 - GAS | F33: 10/02/2026 00:45:00 | G33: 10/02/2026 09:00:00 | J33: POR RSF | O33: ...
B34: KALLPA GENERACION S.A. | C34: C.T. KALLPA | D34: CENTRAL | E34: KALLPA CCOMB TG1 & TG2 & TG3 - GAS | F34: 10/02/2026 09:00:00 | G34: 11/02/2026 00:00:00 | J34: POR POTENCIA O ENERGIA | O34: ...
B35: KALLPA GENERACION S.A. | C35: C.T. LAS FLORES | D35: CENTRAL | E35: LAS FLORES CCOMB TG1 - GAS | F35: 10/02/2026 00:00:00 | G35: 10/02/2026 01:49:00 | J35: POR POTENCIA O ENERGIA | O35: ...
... B50: PETRAMAS | C50: C.T.B DOÑA CATALINA | D50: CENTRAL | E50: DONA CATALINA - BIOGAS | F50: 10/02/2026 00:00:00 | G50: 11/02/2026 00:00:00 | J50: POR POTENCIA O ENERGIA | O50: ...
B51: PETRAMAS | C51: C.T.B. CALLAO | D51: CENTRAL | E51: CALLAO - BIOGAS | F51: 10/02/2026 00:00:00 | G51: 11/02/2026 00:00:00 | H51: 10/02/2026 22:56:00 | J51: POR POTENCIA O ENERGIA | O51: ...
B52: TERMOCHILCA S.A.C. | C52: C.T. OLLEROS | D52: CENTRAL | E52: OLLEROS CCOMB TG1 - GAS | F52: 10/02/2026 00:00:00 | G52: 10/02/2026 02:15:00 | J52: POR POTENCIA O ENERGIA | O52: ...
B53: TERMOCHILCA S.A.C. | C53: C.T. OLLEROS | D53: CENTRAL | E53: OLLEROS CCOMB TG1 - GAS | F53: 10/02/2026 02:15:00 | G53: 10/02/2026 03:03:00 | J53: A MINIMA CARGA | O53: ...
B54: TERMOCHILCA S.A.C. | C54: C.T. OLLEROS | D54: CENTRAL | E54: OLLEROS CCOMB TG1 - GAS | F54: 10/02/2026 03:03:00 | G54: 10/02/2026 06:28:00 | J54: POR POTENCIA O ENERGIA | O54: ...
B55: TERMOCHILCA S.A.C. | C55: C.T. OLLEROS | D55: CENTRAL | E55: OLLEROS CCOMB TG1 - GAS | F55: 10/02/2026 06:28:00 | G55: 10/02/2026 08:19:00 | J55: A MINIMA CARGA | O55: ...
B56: TERMOCHILCA S.A.C. | C56: C.T. OLLEROS | D56: CENTRAL | E56: OLLEROS CCOMB TG1 - GAS | F56: 10/02/2026 08:19:00 | G56: 11/02/2026 00:00:00 | J56: POR POTENCIA O ENERGIA | O56: ... | P56: A las 09:59 h solicitó bajar a mínima generación por alarma de protección de mínimo vacío. A las 15:19 h indicaron que tienen condiciones para subir a máxima generación.

Sheet INDISP
B3: martes, 10 de Febrero del 2026
B5: Hora Inicio y Fin de Indisponibilidades de las Unidades de Generación SEIN
B6: Empresa | C6: Ubicación | D6: Equipo | E6: Inicio | F6: Final | G6: Descripción | H6: MW Indisp. | I6: Prog. | J6: Dispon | K6: Interrupc. | L6: Tipo | M6: CodEq | N6: TipoEq_Osinerg
B7: EGASA | C7: CHARCANI IV | D7: CENTRAL | E7: 10/02/2026 00:00 | F7: 11/02/2026 00:00 | G7: FS Fuerza mayor, ingreso de huaico a central | H7: 15 | I7: F | J7: F/S | K7: N | L7: OTROS | M7: 1198 | N7: G
B8: EGESUR | C8: ARICOTA I | D8: G1 | E8: 10/02/2026 00:00 | F8: 11/02/2026 00:00 | G8: MANTENIMIENTO ELECTROMECÁNICO 3 / MODERNIZACIÓN DE EQUIPAMIENTO DE REGULADOR AUTOMÁTICO DE VOLTAJE / SISTEMA DE EXCITACIÓN UNIDAD DE GENERACIÓN 01 - CENTRAL HIDROELÉCTRICA ARICOTA I | H8: 11.091 | I8: P | J8: F/S | K8: N | L8: PREV. | M8: 124 | N8: G
B9: ENGIE ENERGIA PERU S.A.A. | C9: CHILCA 1 | D9: TV | E9: 10/02/2026 00:00 | F9: 11/02/2026 00:00 | G9: MANTENIMIENTO ANUAL DE UNIDAD Y SISTEMAS AUXILIARES | H9: 260 | I9: P | J9: F/S | K9: N | L9: PREV. | M9: 13344 | N9: G
B10: FENIX POWER PERÚ | C10: FENIX | D10: CENTRAL | E10: 10/02/2026 00:00 | F10: 11/02/2026 00:00 | G10: Indisponibilidad de las señales ICCP debido al mantenimiento de la central. | H10: 0 | I10: P | J10: F/S | K10: N | L10: OTROS | M10: 13601 | N10: G
B11: FENIX POWER PERÚ | C11: FENIX | D11: GT11 | E11: 10/02/2026 00:00 | F11: 11/02/2026 00:00 | G11: Anual BOP e inspección boroscopica de turbinas | H11: 0 | I11: P | J11: F/S | K11: N | L11: PREV. | M11: 13604 | N11: G
B12: FENIX POWER PERÚ | C12: FENIX | D12: GT12 | E12: 10/02/2026 00:00 | F12: 11/02/2026 00:00 | G12: Anual BOP e inspección boroscopica de turbinas | H12: 0 | I12: P | J12: F/S | K12: N | L12: PREV. | M12: 13603 | N12: G
B13: FENIX POWER PERÚ | C13: FENIX | D13: TV10 | E13: 10/02/2026 00:00 | F13: 11/02/2026 00:00 | G13: Anual BOP e inspección boroscopica de turbinas | H13: 0 | I13: P | J13: F/S | K13: N | L13: PREV. | M13: 13602 | N13: G
B14: MINERA CERRO VERDE | C14: RECKA | D14: CENTRAL | E14: 10/02/2026 00:00 | F14: 11/02/2026 00:00 | G14: Indisponible debido al mantenimiento en la línea L-2167. | H14: 0 | I14: P | J14: F/S | K14: N | L14: OTROS | M14: 15107 | N14: G
B15: ORYGEN PERU S.A.A. | C15: CH HER 1 | D15: G3 | E15: 10/02/2026 00:00 | F15: 10/02/2026 16:05 | G15: PRUEBAS DE DISPARO EFECTIVO, | H15: 0.35 | I15: P | J15: F/S | K15: N | L15: PREV. | M15: 18792 | N15: G
B16: ORYGEN PERU S.A.A. | C16: CH HER 1 | D16: G4 | E16: 10/02/2026 00:00 | F16: 10/02/2026 15:39 | G16: PRUEBAS DE DISPARO EFECTIVO | H16: 0.35 | I16: P | J16: F/S | K16: N | L16: PREV. | M16: 18793 | N16: G
B17: PARQUE EOLICO TRES HERMANAS S.A.C. | C17: PARQUE EOLICO 3 HERMANAS | D17: CENTRAL | E17: 10/02/2026 00:00 | F17: 10/02/2026 04:37 | G17: TH-33 falla en la bobina en el generador | H17: 3.15 | I17: P | J17: F/S | K17: N | L17: CORR. | M17: 15160 | N17: G
B18: PARQUE EOLICO TRES HERMANAS S.A.C. | C18: PARQUE EOLICO 3 HERMANAS | D18: CENTRAL | E18: 10/02/2026 08:45 | F18: 10/02/2026 17:09 | G18: TH-17 Mantenimiento 10mo anual | H18: 3.15 | I18: P | J18: F/S | K18: N | L18: PREV. | M18: 15160 | N18: G
... B21: SHOUGESA | C21: SAN NICOLÁS | D21: TV3 | E21: 10/02/2026 00:00 | F21: 11/02/2026 00:00 | G21: Indisponible por falla en la celda del auxiliar N°3. | H21: 24.26 | I21: F | J21: F/S | K21: N | L21: CORR. | M21: 60 | N21: G

Sheet RESERVA_FRÍA
B3: 10/02/2026 | E3: EJECUTADO | L3: Martes 10 de Febrero del 2026 / SEM N° 6 | V3: EJECUTADO | AC3: Martes 10 de Febrero del 2026 / SEM N° 6 | EE3: ENERGIA RENOVABLES | GW3: COGENERACION | HF3: NO INTEGRANTES
B4: Martes | C4: HYDROG | D4: ELECTROPERU | H4: ORAZU | J4: TER | L4: KALLPA GENERACION S.A. | T4: SHOUGESA | X4: EGM | Y4: EGESUR | AB4: EGASA | AI4: SGB | AJ4: CELEP | AK4: MINCVE | AL4: ETEN | AN4: HUALLA | AP4: LAVI | AQ4: CHIN | AS4: HUANCH | AT4: CELER | AU4: INLD | AV4: FENIX POWER PERÚ | AY4: STATKRAFT S.A | BE4: STARO | BG4: HUANZA | BH4: ENEL GENERACION PIURA S.A. | BK4: ENGIE ENERGIA PERU S.A.A. | BY4: IYEP | CA4: SHAQSH | CB4: ORYGEN PERU S.A.A. | CN4: SAMAY I S.A.C | CR4: TCHILC | CT4: TADG | CV4: GENERACION | CY4: SALIDAS YUPANA | DC4: FLUJO EN LINEAS | DO4: COSTOS MARGINALES | DS4: RESERVA | DX4: DEMANDA POR AREAS | EE4: ACHI | EF4: PIEREN | EG4: COLCA | EH4: ERSUR | EI4: GRCOR | EJ4: TARU | EK4: KONDU | EL4: VARI | EM4: ORAZU | EO4: KALLPA | EQ4: SGB | ER4: AIPSA | ES4: MAJA | ET4: EGECSA | EU4: STANA | EV4: AGUAA | EW4: RDOBLE | EX4: HIDRO | EY4: HUARA | EZ4: MOQUE | FA4: PANAM | FB4: PARQU | FC4: PE3HER | FD4: TACNA | FE4: EYSAC | FF4: AURORA | FG4: AGROIN | FH4: AGROLM | FI4: ANDEA | FJ4: ASLC | FK4: ATRIA | FL4: CAGR | FM4: COENGY | FN4: EGEJUNIN | FR4: EOL | FT4: ENGIE ENERGIA PERU S.A.A. | FZ4: GENE | GB4: GENERADORA DE ENERGÍA DEL PERÚ | GF4: PAINO | GG4: JOYAS | GH4: SARCUS | GI4: ORYGEN PERU S.A.A. | GN4: PETRAMAS | GR4: RARCUS | GS4: SINERSA | GW4: ACHI | GX4: GM OP | GZ4: AIPSA | HA4: AURORA | HB4: AGROIN | HC4: AGROLM | HD4: CAGR | HF4: UNACEM | HG4: EOR | HH4: AYEP | HI4: ELZANA | HJ4: ENOSA | HK4: SDE | HL4: SINERS
