Workbook

Sheet EVENTOS
B3: jueves, 5 de Junio del 2025
B5: INFORMACIÓN DE EVENTOS PRINCIPALES EN SUS INSTALACIONES
B6: TIPO DE EVENTO | C6: EMPRESA | D6: UBICACIÓN | E6: TIPO DE EQUIPO | F6: EQUIPO | G6: INICIO | H6: FINAL | I6: DESCRIPCIÓN | J6: MW INDISP. | K6: INTERRUPCIÓN (SI/NO) | L6: TENSIÓN DE FALLA (kV)
B7: FALLA | C7: CELEPSA RENOVABLES S.R.L. | D7: MARAÑON | E7: GENERADOR HIDROELÉCTRICO | F7: G1 | G7: 05/06/2025 12:15:00 | H7: 05/06/2025 12:34:00 | I7: DESCONEXIÓN DEL GENERADOR G1 DE LA C.H. MARAÑÓN POR FALLA | K7: NO | L7: 13.8
B8: EVENTO | C8: CONELSUR LT SAC | D8: PORTILLO | E8: SUBESTACION | F8: SS.EE. | G8: 05/06/2025 00:00:00 | H8: 06/06/2025 00:00:00 | I8: DECLARACIÓN DE SITUACIÓN EXCEPCIONAL EN LA S.E. PORTILLO DE 60 kV | K8: NO
B9: FALLA | C9: EMPRESA ELECTRICA RIO DOBLE | D9: LAS PIZARRAS | E9: GENERADOR HIDROELÉCTRICO | F9: G1 | G9: 05/06/2025 11:16:27 | H9: 05/06/2025 11:36:46 | I9: DESCONEXIÓN DEL GENERADOR G1 DE LA C.H. LAS PIZARRAS | K9: NO | L9: 6.6
B10: FALLA | C10: EMPRESA ELECTRICA RIO DOBLE | D10: LAS PIZARRAS | E10: GENERADOR HIDROELÉCTRICO | F10: G1 | G10: 05/06/2025 11:38:41 | H10: 05/06/2025 15:03:03 | I10: DESCONEXIÓN DEL GENERADOR G1 DE LA C.H. LAS PIZARRAS | K10: NO | L10: 6.6

Sheet RESTRIC_OPE
B3: jueves, 5 de Junio del 2025
B5: RESTRICCIONES OPERATIVAS
B6: FECHA | C6: HORA INICIO | D6: HORA FINAL | E6: EMPRESA | F6: UBICACIÓN | G6: T.Eq. | H6: EQUIPO | I6: DESCRIPCIÓN
B7: 05/06/2025 | C7: 00:00 | D7: 24:00 | E7: CELEPSA | F7: C.H. EL PLATANAL | G7: CH | H7: CENTRAL | I7: Debido al incremento del caudal del rio cañete y establecimiento de la temporada de avenida, se declara la C.H. El Platanal como CENTRAL HIDRÁULICA DE PASADA (correo 03/01/2025).
B8: 05/06/2025 | C8: 00:00 | D8: 24:00 | E8: EGASA | F8: C.H. CHARCANI II | G8: GH | H8: G2 | I8: El Grupo N°02 esta operando con una potencia no mayor a 0.07MW en referencia a 0.18MW de su potencia efectiva, con el fin de no generar daños mayores hasta la reparación de su cojinete.
B9: 05/06/2025 | C9: 00:00 | D9: 24:00 | E9: EGASA | F9: S.E. CONVERTIDOR | G9: BARRA | H9: BARRA138KV | I9: EGASA limitó la capacidad del transformador 138 kV/33 kV a 50 MVA por deterioro del aislamiento.
B10: 05/06/2025 | C10: 00:00 | D10: 24:00 | E10: ENEL GENERACION PIURA S.A. | F10: C.T. MALACAS | G10: CT | H10: CENTRAL | I10: De acuerdo con la comunicación vía correo del día 24.10.2024. ENEL GENERACIÓN PIURA informa una restricción de potencia para alcanzar 105 MW en simultaneo (TG6+TGN4).
B11: 05/06/2025 | C11: 00:00 | D11: 24:00 | E11: ENEL GENERACION PIURA S.A. | F11: C.T. MALACAS | G11: GT | H11: TG4 | I11: De acuerdo a lo informado mediante correo electronico el día 19.05, la TG4 solo puede operar a máxima generación dos horas y el resto a carga a mínima carga.
B12: 05/06/2025 | C12: 00:00 | D12: 24:00 | E12: ENGIE | F12: C.E. PUNTA LOMITAS | G12: CE | H12: CENTRAL | I12: De acuerdo a la carta ENG/737-2024 (Exp:202400007555). Limitación de cables de media tensión a 100 MW de los transformadores PLT1 y PLT2 de la CE Punta Lomitas. Quedan limitados a 200 MW la generación de CE Punta Lomitas y Punta Lomitas Extensión.
B13: 05/06/2025 | C13: 00:00 | D13: 24:00 | E13: ENGIE | F13: C.H. QUITARACSA | G13: CH | H13: CENTRAL | I13: De acuerdo con el correo del 23.04 se considera la operación continua de la CH Quitaracsa debido a que el sistema de refrigeración de la CH Cañón del Pato se alimenta desde la descarga del caudal turbinado por la CH Quitaracsa.
B14: 05/06/2025 | C14: 00:00 | D14: 24:00 | E14: ENGIE | F14: C.H. YUNCÁN | G14: GH | H14: G3 | I14: Según la carta N° ENG/ 198-2024 enviada por su representada, se opera de forma continua el G3 de la CH Yuncán, debido a la ejecución de mantenimientos necesarios para evitar daños en los sellos de seguridad de la válvula esférica del grupo.
B15: 05/06/2025 | C15: 00:00 | D15: 24:00 | E15: ENGIE | F15: C.T. CHILCA 1 | G15: CT | H15: CENTRAL | I15: Restricción de temperatura de la C.T Chilca, ver valor en el modelo de despacho.
B16: 05/06/2025 | C16: 00:00 | D16: 24:00 | E16: ENGIE | F16: C.T. CHILCA 1 | G16: CT | H16: CENTRAL | I16: Con carta ENG/971-2023, indica que no puede cumplir con las IO considerada en el PDO_17122023 dado que vulneran la seguridad de sus activos. Indican que se debe tomar TMO=168h.
B17: 05/06/2025 | C17: 00:00 | D17: 24:00 | E17: ENGIE | F17: C.T. CHILCA 2 | G17: CT | H17: CENTRAL | I17: Restricción de temperatura de la C.T Chilca2, ver valor en el modelo de despacho.
... B47: 05/06/2025 | C47: 00:00 | D47: 24:00 | E47: TERMOSELVA | F47: C.T. AGUAYTÍA | G47: CT | H47: CENTRAL | I47: Restricción total de GN para la CT Aguaytía.

Sheet MANTENIMIENTO EJECUTADOS
B3: jueves, 5 de Junio del 2025
B5: Mantenimiento Ejecutado
B6: Empresa | C6: Ubicación | D6: Equipo | E6: Inicio | F6: Final | G6: Descripción | H6: MW Indisp. | I6: Prog. | J6: Dispon | K6: Interrupc. | L6: Tipo | M6: CodEq | N6: TipoEq_Osinerg
B7: AGROAURORA S.A.C. | C7: MAPLE ETANOL | D7: CENTRAL | E7: 05/06/2025 00:00 | F7: 06/06/2025 00:00 | G7: CENTRAL TERMOELECTRICA FUERA DE SERVICIO POR FALTA DE MATERIA PRIMA PARA LOS REQUERIMIENTOS DE CALOR UTIL EN FABRICA. | H7: 17 | I7: P | J7: F/S | K7: N | L7: OTROS | M7: 13417 | N7: G
B8: AGROAURORA S.A.C. | C8: MAPLE ETANOL | D8: CENTRAL | E8: 05/06/2025 00:00 | F8: 06/06/2025 00:00 | G8: MANTENIMIENTO PREVENTIVO PROGRAMADO DE LA CENTRAL TERMOELECTRICA Y EQUIPOS AUXILIARES. | H8: 17 | I8: P | J8: F/S | K8: N | L8: PREV. | M8: 13417 | N8: G
B9: ATLANTICA TRANSMISION SUR S.A. | C9: MONTALVO | D9: ACOPLE 220 | E9: 05/06/2025 00:00 | F9: 06/06/2025 00:00 | G9: Proyecto Refuerzos: Reemplazo del HMI existente, Pruebas y Configuracion. No se contara con nivel 1 de operacion. | H9: 0 | I9: P | J9: E/S | K9: N | L9: P.ENERG | M9: 14767 | N9: T
B10: ATLANTICA TRANSMISION SUR S.A. | C10: MONTALVO | D10: BARRA A_220KV | E10: 05/06/2025 00:00 | F10: 06/06/2025 00:00 | G10: Proyecto Refuerzos: Indisponibilidad de la proteccion diferencial de barras 220 kV por Conexion de la nueva UB-87B hacia la UC existente,Configuracion y Pruebas. | H10: 0 | I10: P | J10: E/S | K10: N | L10: P.ENERG | M10: 13869 | N10: T
B11: ATLANTICA TRANSMISION SUR S.A. | C11: MONTALVO | D11: BARRA A_500KV | E11: 05/06/2025 00:00 | F11: 06/06/2025 00:00 | G11: Proyecto Refuerzos: Indisponibilidad de la proteccion diferencial de barras 500kV por conexion de nueva UB-87B hacia la UC existente, Configuracion y Pruebas. | H11: 0 | I11: P | J11: E/S | K11: N | L11: P.ENERG | M11: 13870 | N11: T
B12: ATLANTICA TRANSMISION SUR S.A. | C12: MONTALVO | D12: BARRA B_220kV | E12: 05/06/2025 00:00 | F12: 06/06/2025 00:00 | G12: Proyecto Refuerzos: Indisponibilidad de la proteccion diferencial de barras 220 kV por Conexion de la nueva UB-87B hacia la UC existente,Configuracion y Pruebas. | H12: 0 | I12: P | J12: E/S | K12: N | L12: P.ENERG | M12: 14765 | N12: T
B13: ATLANTICA TRANSMISION SUR S.A. | C13: MONTALVO | D13: BARRA B_500KV | E13: 05/06/2025 00:00 | F13: 06/06/2025 00:00 | G13: Proyecto Refuerzos: Indisponibilidad de la proteccion diferencial de barras 500kV por conexion de nueva UB-87B hacia la UC existente, Configuracion y Pruebas. | H13: 0 | I13: P | J13: E/S | K13: N | L13: P.ENERG | M13: 13871 | N13: T
B14: ATLANTICA TRANSMISION SUR S.A. | C14: MONTALVO | D14: CL-2057 | E14: 05/06/2025 00:00 | F14: 06/06/2025 00:00 | G14: Proyecto Refuerzos: Reemplazo del HMI existente, Pruebas y Configuracion. No se contara con nivel 1 de operacion. | H14: 0 | I14: P | J14: E/S | K14: N | L14: P.ENERG | M14: 13812 | N14: T
B15: ATLANTICA TRANSMISION SUR S.A. | C15: MONTALVO | D15: CL-AUT-5671_500 | E15: 05/06/2025 00:00 | F15: 06/06/2025 00:00 | G15: Proyecto Refuerzos: Reemplazo del HMI existente, Pruebas y Configuracion. No se contara con nivel 1 de operacion en INT-5671, INT-5652 y SAT-5671. | H15: 0 | I15: P | J15: E/S | K15: N | L15: P.ENERG | M15: 13809 | N15: T
B16: ATLANTICA TRANSMISION SUR S.A. | C16: MONTALVO | D16: INT-5652 | E16: 05/06/2025 00:00 | F16: 06/06/2025 00:00 | G16: Proyecto Refuerzos: Indisponible por Implementacion de Conexion de corrientes, disparos, posiciones, enclavamientos hacia los equipos del nuevo Autotransformador. AUT-5671 en servicio solo por Barra A 500kV. | H16: 0 | I16: P | J16: F/S | K16: N | L16: P.ENERG | M16: 13765 | N16: T
B17: ATLANTICA TRANSMISION SUR S.A. | C17: OCONA | D17: INT-5450 | E17: 05/06/2025 00:00 | F17: 06/06/2025 00:00 | G17: Interruptor INT-5450 cerrado con restriccion operativa, REB-5450 en servicio y suministrando los SS.AA. de la S.E. Oco?a. | H17: 0 | I17: P | J17: E/S | K17: N | L17: OTROS | M17: 13761 | N17: T
B18: ATLANTICA TRANSMISION SUR S.A. | C18: OCONA | D18: INT-5462 | E18: 05/06/2025 00:00 | F18: 06/06/2025 00:00 | G18: Seccionador SBA-5462 fase T indisponible por problemas mecanicos, el seccionador permanece cerrado y bloqueado | H18: 0 | I18: P | J18: E/S | K18: N | L18: OTROS | M18: 13758 | N18: T
... B143: TRANSMANTARO | C143: YARABAMBA | D143: IN-5120 | E143: 05/06/2025 00:00 | F143: 06/06/2025 00:00 | G143: INTERRUPTOR INDISPONIBLE POR FALLA EN LOS MANDOS DE CONTROL DE N1, N2 Y N3. | H143: 0 | I143: P | J143: F/S | K143: N | L143: OTROS | M143: 17437 | N143: T

Sheet INGRESO OC
A3: jueves, 5 de Junio del 2025
A5: INGRESO A OPERACIÓN COMERCIAL
A6: EMPRESA | B6: TIPO DE EQUIPO | C6: UBICACIÓN | D6: EQUIPO | E6: Fecha y hora de Ingreso a Operación Comercial

Sheet DESPACHO_EJECUTADO
B3: jueves, 5 de Junio del 2025
A5: POTENCIA ACTIVA EJECUTADA DE LAS UNIDADES DE GENERACIÓN DEL SEIN (MW) | FL5: CENTRALES NO INTEGRANTES COES
A6: FECHA | B6: HORA | C6: 65333 | D6: 101 | E6: 102 | F6: 42667 | G6: 42668 | H6: 126 | I6: 127 | J6: 138 | K6: 139 | L6: 197 | M6: 203 | N6: 204 | O6: 230 | P6: 209 | Q6: 56677 | R6: 796 | S6: 2146 | T6: 142 | U6: 143 | V6: 125 | W6: 187 | X6: 163 | Y6: 298 | Z6: 299 | AA6: 219 | AB6: 151 | AC6: 152 | AD6: 153 | AE6: 154 | AF6: 756 | AG6: 156 | AH6: 155 | AI6: 182 | AJ6: 212 | AK6: 758 | AL6: 263 | AM6: 265 | AN6: 775 | AO6: 777 | AP6: 2154 | AQ6: 150 | AR6: 149 | AS6: 188 | AT6: 2131 | AU6: 755 | AV6: 252 | AW6: 249 | AX6: 250 | AY6: 117 | AZ6: 267 | BA6: 268 | BB6: 119 | BC6: 120 | BD6: 189 | BE6: 122 | BF6: 266 | BG6: 337 | BH6: 338 | BI6: 251 | BJ6: 115 | BK6: 239 | BL6: 288 | BM6: 240 | BN6: 241 | BO6: 242 | BP6: 191 | BQ6: 194 | BR6: 196 | BS6: 207 | BT6: 236 | BU6: 795 | BV6: 285 | BW6: 995 | BX6: 996 | BY6: 997 | BZ6: 766 | CA6: 926 | CB6: 924 | CC6: 121 | CD6: 103 | CE6: 104 | CF6: 106 | CG6: 105 | CH6: 107 | CI6: 110 | CJ6: 109 | CK6: 144 | CL6: 113 | CM6: 114 | CN6: 193 | CO6: 208 | CP6: 786 | CQ6: 787 | CR6: 788 | CS6: 789 | CT6: 248 | CU6: 2159 | CV6: 303 | CW6: 59715 | CX6: 62255 | CY6: 1263 | CZ6: 61800 | DA6: 2194 | DB6: 216 | DC6: 198 | DD6: 49607 | DE6: 214 | DF6: 260 | DG6: 2152 | DH6: 2128 | DI6: 247 | DJ6: 228 | DK6: 2135 | DL6: 261 | DM6: 237 | DN6: 253 | DO6: 770 | DP6: 225 | DQ6: 2201 | DR6: 2171 | DS6: 760 | DT6: 235 | DU6: 238 | DV6: 2184 | DW6: 61855 | DX6: 223 | DY6: 226 | DZ6: 201 | EA6: 258 | EB6: 259 | EC6: 920 | ED6: 257 | EE6: 256 | EF6: 2148 | EG6: 58288 | EH6: 58289 | EI6: 58839 | EJ6: 58840 | EK6: 296 | EL6: 297 | EM6: 211 | EN6: 2175 | EO6: 2178 | EP6: 2181 | EQ6: 1262 | ER6: 63425 | ES6: 233 | ET6: 2150 | EU6: 2165 | EV6: 2161 | EW6: 61197 | EX6: 58851 | EY6: 234 | EZ6: 215 | FA6: 917 | FB6: 289 | FC6: 58333 | FD6: 58336 | FE6: 202 | FF6: 58487 | FG6: 213 | FH6: 232 | FI6: 2190 | FJ6: TOTAL COES | FL6: 221 | FM6: 222 | FN6: 224 | FO6: 2187 | FP6: 227 | FQ6: 49400 | FR6: 199 | FS6: 200 | FT6: TOTAL NO COES
C7: SUR | D7: CENTRO | E7: CENTRO | F7: NORTE | G7: NORTE | H7: NORTE | I7: NORTE | J7: CENTRO | K7: CENTRO | L7: CENTRO | M7: CENTRO | N7: CENTRO | O7: CENTRO | P7: CENTRO | Q7: CENTRO | R7: CENTRO | S7: CENTRO | T7: CENTRO | U7: CENTRO | V7: CENTRO | W7: CENTRO | X7: SUR | Y7: SUR | Z7: SUR | AA7: CENTRO | AB7: SUR | AC7: SUR | AD7: SUR | AE7: SUR | AF7: SUR | AG7: SUR | AH7: SUR | AI7: SUR | AJ7: CENTRO | AK7: NORTE | AL7: NORTE | AM7: NORTE | AN7: CENTRO | AO7: CENTRO | AP7: CENTRO | AQ7: CENTRO | AR7: CENTRO | AS7: CENTRO | AT7: CENTRO | AU7: SUR | AV7: CENTRO | AW7: CENTRO | AX7: CENTRO | AY7: CENTRO | AZ7: CENTRO | BA7: CENTRO | BB7: CENTRO | BC7: CENTRO | BD7: SUR | BE7: NORTE | BF7: CENTRO | BG7: CENTRO | BH7: CENTRO | BI7: CENTRO | BJ7: NORTE | BK7: NORTE | BL7: NORTE | BM7: SUR | BN7: SUR | BO7: SUR | BP7: CENTRO | BQ7: CENTRO | BR7: CENTRO | BS7: CENTRO | BT7: CENTRO | BU7: CENTRO | BV7: CENTRO | BW7: SUR | BX7: SUR | BY7: SUR | BZ7: NORTE | CA7: SUR | CB7: CENTRO | CC7: NORTE | CD7: CENTRO | CE7: CENTRO | CF7: CENTRO | CG7: CENTRO | CH7: CENTRO | CI7: CENTRO | CJ7: CENTRO | CK7: CENTRO | CL7: CENTRO | CM7: CENTRO | CN7: CENTRO | CO7: CENTRO | CP7: SUR | CQ7: SUR | CR7: SUR | CS7: SUR | CT7: CENTRO | CU7: CENTRO | CV7: CENTRO | CW7: CENTRO | CX7: SUR | CY7: NORTE | CZ7: NORTE | DA7: NORTE | DB7: NORTE | DC7: NORTE | DD7: SUR | DE7: CENTRO | DF7: CENTRO | DG7: CENTRO | DH7: NORTE | DI7: NORTE | DJ7: CENTRO | DK7: CENTRO | DL7: SUR | DM7: SUR | DN7: CENTRO | DO7: CENTRO | DP7: CENTRO | DQ7: CENTRO | DR7: CENTRO | DS7: CENTRO | DT7: SUR | DU7: CENTRO | DV7: CENTRO | DW7: NORTE | DX7: CENTRO | DY7: CENTRO | DZ7: NORTE | EA7: CENTRO | EB7: CENTRO | EC7: CENTRO | ED7: NORTE | EE7: NORTE | EF7: SUR | EG7: CENTRO | EH7: CENTRO | EI7: CENTRO | EJ7: CENTRO | EK7: CENTRO | EL7: CENTRO | EM7: SUR | EN7: SUR | EO7: SUR | EP7: SUR | EQ7: NORTE | ER7: SUR | ES7: SUR | ET7: SUR | EU7: CENTRO | EV7: CENTRO | EW7: CENTRO | EX7: SUR | EY7: SUR | EZ7: NORTE | FA7: CENTRO | FB7: NORTE | FC7: NORTE | FD7: NORTE | FE7: CENTRO | FF7: CENTRO | FG7: CENTRO | FH7: NORTE | FI7: NORTE | FL7: NORTE | FM7: CENTRO | FN7: NORTE | FO7: NORTE | FP7: NORTE | FQ7: NORTE | FR7: NORTE | FS7: NORTE
C8: HIDROELÉCTRICA | D8: HIDROELÉCTRICA | E8: HIDROELÉCTRICA | F8: TERMOELÉCTRICA | G8: TERMOELÉCTRICA | H8: HIDROELÉCTRICA | I8: HIDROELÉCTRICA | J8: TERMOELÉCTRICA | K8: TERMOELÉCTRICA | L8: TERMOELÉCTRICA | M8: TERMOELÉCTRICA | N8: TERMOELÉCTRICA | O8: TERMOELÉCTRICA | P8: TERMOELÉCTRICA | Q8: TERMOELÉCTRICA | R8: HIDROELÉCTRICA | S8: HIDROELÉCTRICA | T8: TERMOELÉCTRICA | U8: TERMOELÉCTRICA | V8: TERMOELÉCTRICA | W8: TERMOELÉCTRICA | X8: HIDROELÉCTRICA | Y8: HIDROELÉCTRICA | Z8: HIDROELÉCTRICA | AA8: TERMOELÉCTRICA | AB8: HIDROELÉCTRICA | AC8: HIDROELÉCTRICA | AD8: HIDROELÉCTRICA | AE8: HIDROELÉCTRICA | AF8: TERMOELÉCTRICA | AG8: TERMOELÉCTRICA | AH8: TERMOELÉCTRICA | AI8: HIDROELÉCTRICA | AJ8: HIDROELÉCTRICA | AK8: TERMOELÉCTRICA | AL8: TERMOELÉCTRICA | AM8: TERMOELÉCTRICA | AN8: HIDROELÉCTRICA | AO8: HIDROELÉCTRICA | AP8: HIDROELÉCTRICA | AQ8: HIDROELÉCTRICA | AR8: HIDROELÉCTRICA | AS8: HIDROELÉCTRICA | AT8: HIDROELÉCTRICA | AU8: HIDROELÉCTRICA | AV8: TERMOELÉCTRICA | AW8: TERMOELÉCTRICA | AX8: TERMOELÉCTRICA | AY8: HIDROELÉCTRICA | AZ8: HIDROELÉCTRICA | BA8: HIDROELÉCTRICA | BB8: HIDROELÉCTRICA | BC8: HIDROELÉCTRICA | BD8: HIDROELÉCTRICA | BE8: HIDROELÉCTRICA | BF8: HIDROELÉCTRICA | BG8: HIDROELÉCTRICA | BH8: HIDROELÉCTRICA | BI8: HIDROELÉCTRICA | BJ8: TERMOELÉCTRICA | BK8: TERMOELÉCTRICA | BL8: TERMOELÉCTRICA | BM8: TERMOELÉCTRICA | BN8: TERMOELÉCTRICA | BO8: TERMOELÉCTRICA | BP8: HIDROELÉCTRICA | BQ8: TERMOELÉCTRICA | BR8: TERMOELÉCTRICA | BS8: TERMOELÉCTRICA | BT8: TERMOELÉCTRICA | BU8: TERMOELÉCTRICA | BV8: TERMOELÉCTRICA | BW8: TERMOELÉCTRICA | BX8: TERMOELÉCTRICA | BY8: TERMOELÉCTRICA | BZ8: HIDROELÉCTRICA | CA8: TERMOELÉCTRICA | CB8: TERMOELÉCTRICA | CC8: HIDROELÉCTRICA | CD8: HIDROELÉCTRICA | CE8: HIDROELÉCTRICA | CF8: HIDROELÉCTRICA | CG8: HIDROELÉCTRICA | CH8: HIDROELÉCTRICA | CI8: TERMOELÉCTRICA | CJ8: TERMOELÉCTRICA | CK8: TERMOELÉCTRICA | CL8: TERMOELÉCTRICA | CM8: TERMOELÉCTRICA | CN8: TERMOELÉCTRICA | CO8: TERMOELÉCTRICA | CP8: TERMOELÉCTRICA | CQ8: TERMOELÉCTRICA | CR8: TERMOELÉCTRICA | CS8: TERMOELÉCTRICA | CT8: TERMOELÉCTRICA | CU8: TERMOELÉCTRICA | CV8: SOLAR | CW8: EÓLICA | CX8: SOLAR | CY8: EÓLICA | CZ8: SOLAR | DA8: HIDROELÉCTRICA | DB8: HIDROELÉCTRICA | DC8: HIDROELÉCTRICA | DD8: HIDROELÉCTRICA | DE8: HIDROELÉCTRICA | DF8: HIDROELÉCTRICA | DG8: HIDROELÉCTRICA | DH8: HIDROELÉCTRICA | DI8: HIDROELÉCTRICA | DJ8: HIDROELÉCTRICA | DK8: HIDROELÉCTRICA | DL8: SOLAR | DM8: SOLAR | DN8: EÓLICA | DO8: EÓLICA | DP8: TERMOELÉCTRICA | DQ8: TERMOELÉCTRICA | DR8: TERMOELÉCTRICA | DS8: TERMOELÉCTRICA | DT8: SOLAR | DU8: HIDROELÉCTRICA | DV8: HIDROELÉCTRICA | DW8: HIDROELÉCTRICA | DX8: HIDROELÉCTRICA | DY8: HIDROELÉCTRICA | DZ8: HIDROELÉCTRICA | EA8: HIDROELÉCTRICA | EB8: HIDROELÉCTRICA | EC8: HIDROELÉCTRICA | ED8: EÓLICA | EE8: EÓLICA | EF8: SOLAR | EG8: EÓLICA | EH8: EÓLICA | EI8: EÓLICA | EJ8: EÓLICA | EK8: HIDROELÉCTRICA | EL8: HIDROELÉCTRICA | EM8: HIDROELÉCTRICA | EN8: HIDROELÉCTRICA | EO8: HIDROELÉCTRICA | EP8: HIDROELÉCTRICA | EQ8: EÓLICA | ER8: SOLAR | ES8: SOLAR | ET8: SOLAR | EU8: HIDROELÉCTRICA | EV8: EÓLICA | EW8: EÓLICA | EX8: SOLAR | EY8: SOLAR | EZ8: HIDROELÉCTRICA | FA8: HIDROELÉCTRICA | FB8: TERMOELÉCTRICA | FC8: TERMOELÉCTRICA | FD8: TERMOELÉCTRICA | FE8: TERMOELÉCTRICA | FF8: TERMOELÉCTRICA | FG8: TERMOELÉCTRICA | FH8: TERMOELÉCTRICA | FI8: TERMOELÉCTRICA | FL8: HIDROELÉCTRICA | FM8: HIDROELÉCTRICA | FN8: HIDROELÉCTRICA | FO8: HIDROELÉCTRICA | FP8: TERMOELÉCTRICA | FQ8: TERMOELÉCTRICA | FR8: HIDROELÉCTRICA | FS8: HIDROELÉCTRICA
C9: HYDRO GLOBAL PERÚ S.A.C. | D9: ELECTROPERU | E9: ELECTROPERU | F9: ELECTROPERU | G9: ELECTROPERU | H9: ORAZUL ENERGY PERÚ | I9: ORAZUL ENERGY PERÚ | J9: TERMOSELVA | K9: TERMOSELVA | L9: KALLPA GENERACION S.A. | M9: KALLPA GENERACION S.A. | N9: KALLPA GENERACION S.A. | O9: KALLPA GENERACION S.A. | P9: KALLPA GENERACION S.A. | Q9: KALLPA GENERACION S.A. | R9: KALLPA GENERACION S.A. | S9: KALLPA GENERACION S.A. | T9: SHOUGESA | U9: SHOUGESA | V9: SHOUGESA | W9: SHOUGESA | X9: EGEMSA | Y9: EGESUR | Z9: EGESUR | AA9: EGESUR | AB9: EGASA | AC9: EGASA | AD9: EGASA | AE9: EGASA | AF9: EGASA | AG9: EGASA | AH9: EGASA | AI9: SAN GABAN | AJ9: CELEPSA | AK9: MINERA CERRO VERDE | AL9: PLANTA DE RESERVA FRIA DE GENERACION DE ETEN S.A. | AM9: PLANTA DE RESERVA FRIA DE GENERACION DE ETEN S.A. | AN9: EMPRESA DE GENERACION HUALLAGA | AO9: EMPRESA DE GENERACION HUALLAGA | AP9: LA VIRGEN | AQ9: CHINANGO S.A.C. | AR9: CHINANGO S.A.C. | AS9: HIDROELECTRICA HUANCHOR S.A.C. | AT9: CELEPSA RENOVABLES S.R.L. | AU9: INLAND ENERGY SAC | AV9: FENIX POWER PERÚ | AW9: FENIX POWER PERÚ | AX9: FENIX POWER PERÚ | AY9: STATKRAFT S.A | AZ9: STATKRAFT S.A | BA9: STATKRAFT S.A | BB9: STATKRAFT S.A | BC9: STATKRAFT S.A | BD9: STATKRAFT S.A | BE9: STATKRAFT S.A | BF9: STATKRAFT S.A | BG9: CENTRALES SANTA ROSA S.A.C. | BH9: CENTRALES SANTA ROSA S.A.C. | BI9: EMPRESA DE GENERACION HUANZA | BJ9: ENEL GENERACION PIURA S.A. | BK9: ENEL GENERACION PIURA S.A. | BL9: ENEL GENERACION PIURA S.A. | BM9: ENGIE | BN9: ENGIE | BO9: ENGIE | BP9: ENGIE | BQ9: ENGIE | BR9: ENGIE | BS9: ENGIE | BT9: ENGIE | BU9: ENGIE | BV9: ENGIE | BW9: ENGIE | BX9: ENGIE | BY9: ENGIE | BZ9: ENGIE | CA9: INFRAESTRUCTURAS Y ENERGIAS DEL PERU S.A.C. | CB9: INFRAESTRUCTURAS Y ENERGIAS DEL PERU S.A.C. | CC9: INVERSIONES SHAQSHA S.A.C. | CD9: ORYGEN PERU S.A.A. | CE9: ORYGEN PERU S.A.A. | CF9: ORYGEN PERU S.A.A. | CG9: ORYGEN PERU S.A.A. | CH9: ORYGEN PERU S.A.A. | CI9: ORYGEN PERU S.A.A. | CJ9: ORYGEN PERU S.A.A. | CK9: ORYGEN PERU S.A.A. | CL9: ORYGEN PERU S.A.A. | CM9: ORYGEN PERU S.A.A. | CN9: ORYGEN PERU S.A.A. | CO9: ORYGEN PERU S.A.A. | CP9: SAMAY I S.A.C | CQ9: SAMAY I S.A.C | CR9: SAMAY I S.A.C | CS9: SAMAY I S.A.C | CT9: TERMOCHILCA S.A.C. | CU9: TERMOCHILCA S.A.C. | CV9: COLCA SOLAR S.A.C. | CW9: ENERGIA RENOVABLE DEL SUR S.A. | CX9: GR CORTARRAMA SOCIEDAD ANONIMA CERRADA | CY9: GR TARUCA SOCIEDAD ANONIMA CERRADA | CZ9: KONDU SAC | DA9: PERUANA DE INVERSIONES EN ENERGIAS RENOVABLES S.A. | DB9: ORAZUL ENERGY PERÚ | DC9: ORAZUL ENERGY PERÚ | DD9: SAN GABAN | DE9: MAJA ENERGIA S.A.C. | DF9: EMPRESA DE GENERACION ELECTRICA CANCHAYLLO SAC | DG9: EMPRESA DE GENERACION ELECTRICA SANTA ANA S.A.C. | DH9: EMPRESA ELECTRICA AGUA AZUL | DI9: EMPRESA ELECTRICA RIO DOBLE | DJ9: HIDROCAÑETE S.A. | DK9: HUAURA POWER GROUP S.A. | DL9: MOQUEGUA FV S.A.C. | DM9: PANAMERICANA SOLAR SAC. | DN9: PARQUE EOLICO MARCONA S.A.C. | DO9: PARQUE EOLICO TRES HERMANAS S.A.C. | DP9: PETRAMAS | DQ9: PETRAMAS | DR9: PETRAMAS | DS9: PETRAMAS | DT9: TACNA SOLAR SAC. | DU9: ELECTRICA YANAPAMPA SAC | DV9: ANDEAN POWER S.A.C. | DW9: ASOCIACIÓN SANTA LUCIA DE CHACAS | DX9: ATRIA ENERGIA S.A.C. | DY9: EGEJUNIN | DZ9: EGEJUNIN | EA9: EGEJUNIN | EB9: EGEJUNIN | EC9: EMPRESA DE GENERACION ELECTRICA RIO BAÑOS S.A.C. | ED9: ENERGÍA EÓLICA S.A. | EE9: ENERGÍA EÓLICA S.A. | EF9: ENGIE | EG9: ENGIE | EH9: ENGIE | EI9: ENGIE | EJ9: ENGIE | EK9: GENERACIÓN ANDINA S.A.C. | EL9: GENERACIÓN ANDINA S.A.C. | EM9: GENERADORA DE ENERGÍA DEL PERÚ | EN9: GENERADORA DE ENERGÍA DEL PERÚ | EO9: GENERADORA DE ENERGÍA DEL PERÚ | EP9: GENERADORA DE ENERGÍA DEL PERÚ | EQ9: GR PAINO SOCIEDAD ANONIMA CERRADA | ER9: JOYA SOLAR S.A.C. | ES9: MAJES ARCUS S.A.C. | ET9: ORYGEN PERU S.A.A. | EU9: ORYGEN PERU S.A.A. | EV9: ORYGEN PERU S.A.A. | EW9: ORYGEN PERU S.A.A. | EX9: ORYGEN PERU S.A.A. | EY9: REPARTICIÓN ARCUS S.A.C. | EZ9: SINERSA | FA9: SINERSA | FB9: BIOENERGIA DEL CHIRA S.A. | FC9: GM OPERACIONES S.A.C. | FD9: GM OPERACIONES S.A.C. | FE9: SDF ENERGIA SAC | FF9: SDF ENERGIA SAC | FG9: AGRO INDUSTRIAL PARAMONGA S.A. | FH9: AGROAURORA S.A.C. | FI9: AGROINDUSTRIAS SAN JACINTO S.A.A. | FL9: UNACEM PERU S.A. | FM9: ELECTRO ORIENTE | FN9: AGUAS Y ENERGIA PERU | FO9: ELECTRO ZAÑA S.A.C. | FP9: ELECTRONOROESTE S.A. | FQ9: SDE PIURA | FR9: SINERSA | FS9: SINERSA
C10: SAN GABAN III | D10: MANTARO | E10: RESTITUCION | F10: TUMBES MAK 1 | G10: TUMBES MAK 2 | H10: CARHUAQUERO | I10: CAÑON DEL PATO | J10: AGUAYTIA TG1 | K10: AGUAYTIA TG2 | L10: KALLPA TG1 | M10: KALLPA TG2 | N10: KALLPA TG3 | O10: KALLPA TV | P10: LFLORES TG1 | Q10: LFLORES TV | R10: CERRO DEL AGUILA | S10: CERRODELAGUILAG4 | T10: SHOUGESA TV1 | U10: SHOUGESA TV2 | V10: SHOUGESA TV3 | W10: SHOUGESA CUMMINS | X10: MACHUPICCHU | Y10: ARICOTA 1 | Z10: ARICOTA 2 | AA10: INDEPENDENCIA | AB10: CHARCANI I,II,III | AC10: CHARCANI IV | AD10: CHARCANI V | AE10: CHARCANI VI | AF10: CHILINA TG | AG10: MOLLENDO 1, 2, 3 | AH10: CHILINA (SULZ 1,2) | AI10: SAN GABAN II | AJ10: PLATANAL | AK10: RECKA | AL10: RF ETEN TG1 | AM10: RF ETEN TG2 | AN10: CHAGLLA GP1 | AO10: CHAGLLA | AP10: LA VIRGEN | AQ10: CHIMAY | AR10: YANANGO | AS10: HUANCHOR | AT10: MARAÑON | AU10: STA TERESA | AV10: FENIX GT11 | AW10: FENIX GT12 | AX10: FENIX TV10 | AY10: YAUPI | AZ10: OROYA | BA10: PACHACHACA | BB10: MALPASO | BC10: CAHUA | BD10: ARCATA | BE10: GALLITO CIEGO | BF10: CHEVES | BG10: SANTA ROSA 1 | BH10: SANTA ROSA 2 | BI10: HUANZA | BJ10: MALACAS2 TG4 | BK10: MALACAS3 TG 5 | BL10: MALACAS1 TG6 | BM10: RF ILO2 TG1 | BN10: RF ILO2 TG2 | BO10: RF ILO2 TG3 | BP10: YUNCAN | BQ10: CHILCA1 TG1 | BR10: CHILCA1 TG2 | BS10: CHILCA1 TG3 | BT10: CHILCA-TV | BU10: CHILCA2 TG41 | BV10: CHILCA2-TV | BW10: CTNEPI_TG41 | BX10: CTNEPI_TG42 | BY10: CTNEPI_TG43 | BZ10: QUITARACSA | CA10: RF PTO MALDONADO | CB10: RF PUCALLPA | CC10: PARIAC | CD10: HUINCO | CE10: MATUCANA | CF10: MOYOPAMPA | CG10: CALLAHUANCA | CH10: HUAMPANI | CI10: STA ROSA WEST TG7 | CJ10: UTI_5 | CK10: UTI_6 | CL10: VENTANILLA 3 | CM10: VENTANILLA 4 | CN10: VENTANILLA TV | CO10: STAROSA TG8 | CP10: PTO_BRVO TG1 | CQ10: PTO_BRVO TG2 | CR10: PTO_BRVO TG3 | CS10: PTO_BRVO TG4 | CT10: OLLEROS TG1 | CU10: OLLEROS TV | CV10: CS YARUCAYA | CW10: SAN JUAN | CX10: MATARANI | CY10: DUNA | CZ10: CARHUAQUERO (CS) | DA10: MANTA I | DB10: CARHUAQUERO4 | DC10: CAÑA BRAVA | DD10: TUPURI | DE10: RONCADOR | DF10: CANCHAYLLO | DG10: RENOVANDESH1 | DH10: POTRERO | DI10: PIZARRAS | DJ10: NIMPERIAL | DK10: YARUCAYA | DL10: MOQUEGUA-SOLAR | DM10: PANAMERICANA-SOLAR | DN10: PQE-EOLICO-MARCONA | DO10: PQE-EOLICO-3-HERMANAS | DP10: HUAYCOLORO | DQ10: CALLAO | DR10: DONA_CATALINA | DS10: LAGRINGAV | DT10: TACNA-SOLAR | DU10: YANAPAMPA | DV10: CARHUAC | DW10: HUALLIN | DX10: PURMACANA | DY10: HUASAHUASI | DZ10: STACRUZ_1_2 | EA10: RUNATULLO_II | EB10: RUNATULLO_III | EC10: RUCUY | ED10: PQE-EOLICO-TALARA | EE10: PQE-EOLICO-CUPISNIQUE | EF10: INTIPAMPA | EG10: PUNTA LOMITAS-BL1 | EH10: PUNTA LOMITAS-BL2 | EI10: PUN LOMITAS_EXP-BL1 | EJ10: PUN LOMITAS_EXP-BL2 | EK10: 8AGOSTO | EL10: EL CARMEN | EM10: LA JOYA | EN10: ANGEL_I | EO10: ANGEL_II | EP10: ANGEL_III | EQ10: HUAMBOS | ER10: SAN MARTIN SOLAR | ES10: MAJES | ET10: RUBI | EU10: CH_HER1 | EV10: WAYRA-I | EW10: WAYRA EXTENSION | EX10: CLEMESI | EY10: REPARTICION | EZ10: POECHOS2 | FA10: CHANCAY | FB10: CANA BRAVA | FC10: REFINERIA TALARA TV1 | FD10: REFINERÍA TALARA TV2 | FE10: OQUENDO TG1 | FF10: OQUENDO TV1 | FG10: PARAMONGA | FH10: MAPLE | FI10: SAN_JACINTO | FJ10: MW | FL10: CARPAPATA | FM10: CENTRALES ELOR | FN10: PIAS1 | FO10: ZANA | FP10: TABLAZO | FQ10: TALLANCA | FR10: CURUMUY | FS10: POECHOS1 | FT10: MW
A11: 05/06/2025 | B11: 00:30 | C11: 141 | D11: 599.9 | E11: 200.3 | H11: 66.3 | I11: 154 | M11: 207.1 | N11: 209.9 | O11: 200.6 | R11: 556.3 | S11: 4.7 | X11: 163.8 | Y11: 6.9 | Z11: 5.3 | AB11: 6.8 | AC11: 14.6 | AD11: 60.8 | AI11: 69.5 | AJ11: 116.4 | AN11: 6.5 | AO11: 162.9 | AP11: 52.4 | AQ11: 53.5 | AR11: 28.1 | AS11: 18.8 | AT11: 13.2 | AU11: 90.1 | AV11: 181.6 | AW11: 179.3 | AX11: 184.8 | AY11: 106.1 | AZ11: 8.4 | BA11: 2.7 | BB11: 16.7 | BC11: 42.9 | BE11: 15.3 | BF11: 136.2 | BP11: 82.4 | BQ11: 179.1 | BR11: 177 | BS11: 200 | BT11: 276.3 | CC11: 4.1 | CD11: 89.1 | CE11: 112.4 | CF11: 63.3 | CG11: 72.5 | CH11: 30.3 | CL11: 147.8 | CM11: 149 | CN11: 150.1 | CT11: 6.1 | CU11: 0 | CV11: 0 | CW11: 43.5 | CX11: 0 | CY11: 9.1 | CZ11: 0 | DA11: 16.5 | DB11: 9.8 | DC11: 5.3 | DD11: 0.7 | DE11: 0 | DF11: 4.2 | DG11: 19.9 | DH11: 20 | DI11: 13.2 | DJ11: 3.5 | DK11: 18.5 | DL11: 0 | DM11: 0 | DN11: 15.2 | DO11: 40.8 | DP11: 3 | DQ11: 1.1 | DR11: 2.4 | DS11: 3.1 | DT11: 0 | DU11: 3.1 | DV11: 10.3 | DW11: 2 | DY11: 13.8 | DZ11: 5.6 | EA11: 7.2 | EB11: 10 | EC11: 19.8 | ED11: 9.4 | EE11: 9.8 | EF11: 0 | EG11: 37.2 | EH11: 49.5 | EI11: 5.7 | EJ11: 3.7 | EK11: 10.2 | EL11: 3.4 | EM11: 8.1 | EN11: 8.5 | EO11: 9.1 | EP11: 9.4 | EQ11: 5.6 | ER11: 0 | ES11: 0 | ET11: 0 | EU11: 0.6 | EV11: 70.5 | EW11: 81.3 | EX11: 0 | EY11: 0 | EZ11: 9.7 | FA11: 20 | FB11: 9.2 | FC11: 44.1 | FD11: 16.4 | FG11: 16.2 | FI11: 6.2 | FJ11: 6568.6 | FL11: 24.10214 | FM11: 0 | FO11: 13.2 | FP11: 3.86452 | FQ11: 18.93516 | FR11: 11.5 | FS11: 16.1 | FT11: 87.70182
A12: 05/06/2025 | B12: 01:00 | C12: 139.7 | D12: 599.5 | E12: 199.7 | H12: 60.2 | I12: 157.3 | M12: 205.5 | N12: 209.8 | O12: 199.8 | R12: 558.3 | S12: 4.9 | X12: 161.8 | Y12: 7.2 | Z12: 5.5 | AB12: 6.8 | AC12: 12 | AD12: 60.2 | AI12: 70.7 | AJ12: 86 | AN12: 6.5 | AO12: 153.2 | AP12: 53.2 | AQ12: 52.3 | AR12: 28.2 | AS12: 18.8 | AT12: 13.2 | AU12: 89.9 | AV12: 182.3 | AW12: 183.7 | AX12: 184.3 | AY12: 107.3 | AZ12: 8.4 | BA12: 2.7 | BB12: 18.2 | BC12: 43.5 | BE12: 16.1 | BF12: 100.2 | BP12: 83.9 | BQ12: 178.5 | BR12: 176.5 | BS12: 200 | BT12: 276.1 | CC12: 4 | CD12: 87.1 | CE12: 109.1 | CF12: 64.2 | CG12: 74.1 | CH12: 30.7 | CL12: 147.1 | CM12: 148.6 | CN12: 149.5 | CT12: 9 | CU12: 0 | CV12: 0 | CW12: 44.8 | CX12: 0 | CY12: 7.1 | CZ12: 0 | DA12: 16.6 | DB12: 9.9 | DC12: 4.7 | DD12: 0.7 | DE12: 0 | DF12: 4.3 | DG12: 20.1 | DH12: 20 | DI12: 13.2 | DJ12: 3.5 | DK12: 18.5 | DL12: 0 | DM12: 0 | DN12: 16.4 | DO12: 42.5 | DP12: 3 | DQ12: 1.1 | DR12: 2.4 | DS12: 3.1 | DT12: 0 | DU12: 3.2 | DV12: 10.3 | DW12: 2 | DY12: 13.8 | DZ12: 5.6 | EA12: 7.3 | EB12: 9.9 | EC12: 19.9 | ED12: 6.9 | EE12: 7.1 | EF12: 0 | EG12: 33.9 | EH12: 46.9 | EI12: 6.6 | EJ12: 3.8 | EK12: 10.2 | EL12: 3.4 | EM12: 8.1 | EN12: 8.5 | EO12: 9.1 | EP12: 9.4 | EQ12: 4 | ER12: 0 | ES12: 0 | ET12: 0 | EU12: 0.6 | EV12: 58.5 | EW12: 83.5 | EX12: 0 | EY12: 0 | EZ12: 9.8 | FA12: 20 | FB12: 9.3 | FC12: 43.8 | FD12: 16.5 | FG12: 16.1 | FI12: 6.7 | FJ12: 6471.9 | FL12: 24.10293 | FM12: 0 | FO12: 13.2 | FP12: 0 | FQ12: 18.93478 | FR12: 11.6 | FS12: 16.1 | FT12: 83.93771
A13: 05/06/2025 | B13: 01:30 | C13: 139.6 | D13: 600.9 | E13: 197.9 | H13: 59.4 | I13: 156 | M13: 206.5 | N13: 209.6 | O13: 200.2 | R13: 559.5 | S13: 4.9 | X13: 165.8 | Y13: 7.3 | Z13: 5.3 | AB13: 6.8 | AC13: 11.8 | AD13: 59.9 | AI13: 70.4 | AJ13: 92.1 | AN13: 6.5 | AO13: 0 | AP13: 54 | AQ13: 53.3 | AR13: 28.5 | AS13: 18.8 | AT13: 13.2 | AU13: 90 | AV13: 188.1 | AW13: 188.1 | AX13: 190.2 | AY13: 107.6 | AZ13: 8.4 | BA13: 2.7 | BB13: 18.3 | BC13: 43.2 | BE13: 16 | BF13: 111.3 | BP13: 84.1 | BQ13: 177.9 | BR13: 175.6 | BS13: 200 | BT13: 275.3 | CC13: 4 | CD13: 92.3 | CE13: 111.1 | CF13: 63.2 | CG13: 74.1 | CH13: 30.7 | CL13: 147.1 | CM13: 148.3 | CN13: 149.1 | CT13: 9.9 | CU13: 0 | CV13: 0 | CW13: 38.4 | CX13: 0 | CY13: 6.2 | CZ13: 0 | DA13: 16.7 | DB13: 9.9 | DC13: 4.8 | DD13: 0.7 | DE13: 0 | DF13: 4.3 | DG13: 20.1 | DH13: 20 | DI13: 13.2 | DJ13: 3.5 | DK13: 18.5 | DL13: 0 | DM13: 0 | DN13: 17.8 | DO13: 43.8 | DP13: 3 | DQ13: 1.1 | DR13: 2.4 | DS13: 3.1 | DT13: 0 | DU13: 3.1 | DV13: 10.3 | DW13: 2 | DY13: 13.8 | DZ13: 5.6 | EA13: 7.2 | EB13: 10 | EC13: 19.9 | ED13: 9.4 | EE13: 9.2 | EF13: 0 | EG13: 20.8 | EH13: 36.8 | EI13: 4.8 | EJ13: 2.8 | EK13: 10.1 | EL13: 3.4 | EM13: 8.1 | EN13: 8.5 | EO13: 9.1 | EP13: 9.4 | EQ13: 4.5 | ER13: 0 | ES13: 0 | ET13: 0 | EU13: 0.6 | EV13: 50.2 | EW13: 60.1 | EX13: 0 | EY13: 0 | EZ13: 9.8 | FA13: 20 | FB13: 9.6 | FC13: 44 | FD13: 16.4 | FG13: 16.2 | FI13: 6.3 | FJ13: 6304.3 | FL13: 24.10124 | FM13: 0 | FO13: 13.2 | FP13: 0 | FQ13: 18.93436 | FR13: 11.5 | FS13: 16.1 | FT13: 83.8356
A14: 05/06/2025 | B14: 02:00 | C14: 139.8 | D14: 592.7 | E14: 197.4 | H14: 59.4 | I14: 153.4 | M14: 205.9 | N14: 208.1 | O14: 199.1 | R14: 548.4 | S14: 4.8 | X14: 160.2 | Y14: 6.7 | Z14: 5.1 | AB14: 6.8 | AC14: 11.8 | AD14: 60.6 | AI14: 68.4 | AJ14: 98.3 | AN14: 6.5 | AO14: 0 | AP14: 53.6 | AQ14: 49.7 | AR14: 28.5 | AS14: 18.8 | AT14: 13.2 | AU14: 86.6 | AV14: 176 | AW14: 178.1 | AX14: 185.8 | AY14: 105.3 | AZ14: 8.3 | BA14: 2.7 | BB14: 17.3 | BC14: 43.7 | BE14: 11.4 | BF14: 81.8 | BP14: 83.1 | BQ14: 177.4 | BR14: 175 | BS14: 200 | BT14: 276 | CC14: 4 | CD14: 69.3 | CE14: 100.3 | CF14: 61.6 | CG14: 71.6 | CH14: 30.2 | CL14: 146.6 | CM14: 147.4 | CN14: 148 | CT14: 48.8 | CU14: 0 | CV14: 0 | CW14: 34.5 | CX14: 0 | CY14: 6.8 | CZ14: 0 | DA14: 16.6 | DB14: 9.9 | DC14: 4.8 | DD14: 0.7 | DE14: 0 | DF14: 4.2 | DG14: 19.4 | DH14: 20 | DI14: 13.2 | DJ14: 3.5 | DK14: 18.5 | DL14: 0 | DM14: 0 | DN14: 17.8 | DO14: 46.2 | DP14: 3 | DQ14: 1.1 | DR14: 2.4 | DS14: 3.1 | DT14: 0 | DU14: 3.1 | DV14: 10.3 | DW14: 2 | DY14: 13.8 | DZ14: 5.6 | EA14: 7 | EB14: 9.5 | EC14: 19.9 | ED14: 10.6 | EE14: 18.5 | EF14: 0 | EG14: 17.2 | EH14: 37.5 | EI14: 2.4 | EJ14: 0.9 | EK14: 10.1 | EL14: 3.4 | EM14: 8.1 | EN14: 8.5 | EO14: 9.1 | EP14: 9.4 | EQ14: 3.9 | ER14: 0 | ES14: 0 | ET14: 0 | EU14: 0.6 | EV14: 49.9 | EW14: 44.8 | EX14: 0 | EY14: 0 | EZ14: 9.8 | FA14: 20 | FB14: 9.4 | FC14: 44.3 | FD14: 16.4 | FG14: 16.3 | FI14: 6.5 | FJ14: 6188 | FL14: 24.10037 | FM14: 0 | FO14: 13.2 | FP14: 0 | FQ14: 18.92767 | FR14: 11.5 | FS14: 16 | FT14: 83.72804
A15: 05/06/2025 | B15: 02:30 | C15: 140.6 | D15: 598.8 | E15: 199.7 | H15: 60 | I15: 159.1 | M15: 206.4 | N15: 208.9 | O15: 199.2 | R15: 555 | S15: 4.9 | X15: 165.8 | Y15: 7.3 | Z15: 5.2 | AB15: 6.8 | AC15: 11.8 | AD15: 91.4 | AI15: 70.3 | AJ15: 81.1 | AN15: 6.5 | AO15: 0 | AP15: 55 | AQ15: 55.6 | AR15: 30.1 | AS15: 18.8 | AT15: 13.2 | AU15: 88.7 | AV15: 182.7 | AW15: 183.8 | AX15: 184.1 | AY15: 106.9 | AZ15: 8.3 | BA15: 2.7 | BB15: 18.2 | BC15: 43.4 | BE15: 11.5 | BF15: 85.9 | BP15: 83.9 | BQ15: 177.8 | BR15: 175.7 | BS15: 200 | BT15: 276 | CC15: 4.1 | CD15: 81.5 | CE15: 106.1 | CF15: 63.1 | CG15: 72.1 | CH15: 30.6 | CL15: 147 | CM15: 148.3 | CN15: 149 | CT15: 50.4 | CU15: 0 | CV15: 0 | CW15: 32 | CX15: 0 | CY15: 6.5 | CZ15: 0 | DA15: 16.7 | DB15: 9.9 | DC15: 4.8 | DD15: 0.7 | DE15: 0 | DF15: 4.2 | DG15: 20 | DH15: 20 | DI15: 12.4 | DJ15: 3.5 | DK15: 18.5 | DL15: 0 | DM15: 0 | DN15: 14.8 | DO15: 37.5 | DP15: 3 | DQ15: 1.1 | DR15: 2.4 | DS15: 3.1 | DT15: 0 | DU15: 3.2 | DV15: 10.3 | DW15: 1.9 | DY15: 13.8 | DZ15: 5.6 | EA15: 7.1 | EB15: 9.7 | EC15: 19.9 | ED15: 12.1 | EE15: 12.5 | EF15: 0 | EG15: 36.3 | EH15: 44.4 | EI15: 3.2 | EJ15: 4.6 | EK15: 10.1 | EL15: 3.4 | EM15: 8.1 | EN15: 8.5 | EO15: 9.1 | EP15: 9.4 | EQ15: 3.7 | ER15: 0 | ES15: 0 | ET15: 0 | EU15: 0.6 | EV15: 37.8 | EW15: 32.4 | EX15: 0 | EY15: 0 | EZ15: 9.8 | FA15: 20 | FB15: 9.7 | FC15: 44.3 | FD15: 16.4 | FG15: 16.4 | FI15: 4.9 | FJ15: 6273.6 | FL15: 24.1029 | FM15: 0 | FO15: 13.2 | FP15: 0 | FQ15: 18.92753 | FR15: 11.5 | FS15: 16 | FT15: 83.73043
A16: 05/06/2025 | B16: 03:00 | C16: 139.7 | D16: 599 | E16: 198.5 | H16: 60.2 | I16: 160.8 | M16: 205.8 | N16: 208.6 | O16: 200.5 | R16: 557.9 | S16: 4.9 | X16: 163.9 | Y16: 7.3 | Z16: 5.2 | AB16: 6.9 | AC16: 11.8 | AD16: 61.1 | AI16: 70.4 | AJ16: 93.6 | AN16: 6.5 | AO16: 0 | AP16: 55 | AQ16: 54.5 | AR16: 29.8 | AS16: 18.8 | AT16: 13.2 | AU16: 89.3 | AV16: 180.9 | AW16: 182.6 | AX16: 184 | AY16: 105.8 | AZ16: 8.4 | BA16: 2.8 | BB16: 18.2 | BC16: 43.3 | BE16: 11.6 | BF16: 124.5 | BP16: 83.9 | BQ16: 177.5 | BR16: 175.5 | BS16: 200 | BT16: 276.5 | CC16: 4 | CD16: 98.7 | CE16: 112.9 | CF16: 63.1 | CG16: 72 | CH16: 30.6 | CL16: 147.5 | CM16: 148.2 | CN16: 149.4 | CT16: 50.5 | CU16: 0 | CV16: 0 | CW16: 27.9 | CX16: 0 | CY16: 4.8 | CZ16: 0 | DA16: 16.7 | DB16: 9.9 | DC16: 4.7 | DD16: 0.7 | DE16: 0 | DF16: 4.1 | DG16: 20 | DH16: 20 | DI16: 12.4 | DJ16: 3.5 | DK16: 18.5 | DL16: 0 | DM16: 0 | DN16: 12.9 | DO16: 36.4 | DP16: 3 | DQ16: 1.1 | DR16: 2.4 | DS16: 3.1 | DT16: 0 | DU16: 3.2 | DV16: 10.3 | DW16: 1.9 | DY16: 13.8 | DZ16: 5.6 | EA16: 7.2 | EB16: 9.8 | EC16: 19.9 | ED16: 14.6 | EE16: 7.3 | EF16: 0 | EG16: 14.4 | EH16: 37 | EI16: 1.2 | EJ16: 0.2 | EK16: 10.1 | EL16: 3.4 | EM16: 8.1 | EN16: 8.5 | EO16: 9.1 | EP16: 9.4 | EQ16: 2.3 | ER16: 0 | ES16: 0 | ET16: 0 | EU16: 0.6 | EV16: 15.9 | EW16: 17.4 | EX16: 0 | EY16: 0 | EZ16: 9.7 | FA16: 20 | FB16: 8.6 | FC16: 44.3 | FD16: 16.5 | FG16: 16.2 | FI16: 6.5 | FJ16: 6230.7 | FL16: 24.09977 | FM16: 0 | FO16: 13.2 | FP16: 0 | FQ16: 18.92741 | FR16: 11.5 | FS16: 16.2 | FT16: 83.92718
A17: 05/06/2025 | B17: 03:30 | C17: 138.9 | D17: 596 | E17: 198.3 | H17: 59.9 | I17: 158.9 | M17: 206.8 | N17: 208.8 | O17: 199.6 | R17: 554.1 | S17: 4.9 | X17: 162.5 | Y17: 6.9 | Z17: 5.1 | AB17: 6.8 | AC17: 11.7 | AD17: 60 | AI17: 69.9 | AJ17: 129 | AN17: 6.5 | AO17: 0 | AP17: 55 | AQ17: 51.7 | AR17: 30.8 | AS17: 18.8 | AT17: 13.2 | AU17: 86.2 | AV17: 181.8 | AW17: 182.4 | AX17: 183.5 | AY17: 106.6 | AZ17: 8.4 | BA17: 2.7 | BB17: 17.7 | BC17: 43.2 | BE17: 11.3 | BF17: 53.9 | BP17: 83.8 | BQ17: 177.4 | BR17: 175.2 | BS17: 200 | BT17: 275.4 | CC17: 4 | CD17: 73.2 | CE17: 105.5 | CF17: 62.9 | CG17: 75 | CH17: 30.6 | CL17: 147.3 | CM17: 148.2 | CN17: 149.2 | CT17: 50.5 | CU17: 0 | CV17: 0 | CW17: 29.3 | CX17: 0 | CY17: 8.5 | CZ17: 0 | DA17: 16.7 | DB17: 9.9 | DC17: 4.8 | DD17: 0.7 | DE17: 0 | DF17: 4.1 | DG17: 19.8 | DH17: 20 | DI17: 12.4 | DJ17: 3.5 | DK17: 18.5 | DL17: 0 | DM17: 0 | DN17: 11.6 | DO17: 30.3 | DP17: 3 | DQ17: 1.1 | DR17: 2.4 | DS17: 3.1 | DT17: 0 | DU17: 3.2 | DV17: 10.3 | DW17: 1.9 | DY17: 12.6 | DZ17: 5.6 | EA17: 7 | EB17: 9.5 | EC17: 20 | ED17: 14.5 | EE17: 6.1 | EF17: 0 | EG17: 13.2 | EH17: 27.6 | EI17: 1.1 | EJ17: 0.5 | EK17: 10.1 | EL17: 3.4 | EM17: 8.1 | EN17: 8.6 | EO17: 9.2 | EP17: 9.5 | EQ17: 3.2 | ER17: 0 | ES17: 0 | ET17: 0 | EU17: 0.6 | EV17: 20.6 | EW17: 13.4 | EX17: 0 | EY17: 0 | EZ17: 9.8 | FA17: 20 | FB17: 9.1 | FC17: 44.4 | FD17: 16.5 | FG17: 16.3 | FI17: 6.3 | FJ17: 6131.9 | FL17: 24.09961 | FM17: 0 | FO17: 13.2 | FP17: 0 | FQ17: 18.92696 | FR17: 11.7 | FS17: 16.1 | FT17: 84.02657
A18: 05/06/2025 | B18: 04:00 | C18: 140 | D18: 602.8 | E18: 198.5 | H18: 34.3 | I18: 162.5 | M18: 206 | N18: 209.4 | O18: 198.9 | R18: 560.4 | S18: 4.9 | X18: 165.7 | Y18: 7.7 | Z18: 5.3 | AB18: 6.8 | AC18: 11.5 | AD18: 61.6 | AI18: 70.7 | AJ18: 78 | AN18: 6.5 | AO18: 152.2 | AP18: 55.8 | AQ18: 53.1 | AR18: 29.7 | AS18: 18.8 | AT18: 13.2 | AU18: 91 | AV18: 183.9 | AW18: 184.4 | AX18: 184.7 | AY18: 107.7 | AZ18: 8.3 | BA18: 2.7 | BB18: 18.9 | BC18: 44 | BE18: 11.6 | BF18: 72.6 | BP18: 84 | BQ18: 177.7 | BR18: 175.6 | BS18: 200 | BT18: 274.8 | CC18: 4 | CD18: 84.8 | CE18: 108.1 | CF18: 63.4 | CG18: 75.1 | CH18: 30.8 | CL18: 147.4 | CM18: 148.3 | CN18: 149.4 | CT18: 50.4 | CU18: 0 | CV18: 0 | CW18: 26.7 | CX18: 0 | CY18: 8.5 | CZ18: 0 | DA18: 16.7 | DB18: 10 | DC18: 2.8 | DD18: 0.7 | DE18: 0 | DF18: 4.4 | DG18: 20.2 | DH18: 20 | DI18: 12.4 | DJ18: 3.5 | DK18: 18.5 | DL18: 0 | DM18: 0 | DN18: 11.6 | DO18: 29.4 | DP18: 3 | DQ18: 1.1 | DR18: 2.4 | DS18: 3.1 | DT18: 0 | DU18: 3.2 | DV18: 10.3 | DW18: 1.9 | DY18: 12.5 | DZ18: 5.6 | EA18: 7.3 | EB18: 10.2 | EC18: 20 | ED18: 15.1 | EE18: 5 | EF18: 0 | EG18: 8.8 | EH18: 13.5 | EI18: 0.7 | EJ18: 1 | EK18: 10 | EL18: 3.4 | EM18: 8.3 | EN18: 8.6 | EO18: 9.2 | EP18: 9.5 | EQ18: 3.4 | ER18: 0 | ES18: 0 | ET18: 0 | EU18: 0.6 | EV18: 11.2 | EW18: 5.9 | EX18: 0 | EY18: 0 | EZ18: 9.8 | FA18: 20 | FB18: 9.3 | FC18: 44.4 | FD18: 16.4 | FG18: 16.2 | FI18: 5.8 | FJ18: 6240 | FL18: 24.09673 | FM18: 0 | FO18: 13.2 | FP18: 0 | FQ18: 18.92648 | FR18: 11.5 | FS18: 16.2 | FT18: 83.92321
A19: 05/06/2025 | B19: 04:30 | C19: 140 | D19: 593.6 | E19: 198 | H19: 32.4 | I19: 159.8 | M19: 207.2 | N19: 209.1 | O19: 200 | R19: 550.7 | S19: 4.7 | X19: 161.1 | Y19: 6.7 | Z19: 5.1 | AB19: 6.8 | AC19: 11.6 | AD19: 59.7 | AI19: 68.4 | AJ19: 55.2 | AN19: 6.5 | AO19: 145.9 | AP19: 54.7 | AQ19: 0 | AR19: 29.5 | AS19: 18.8 | AT19: 13.2 | AU19: 88.7 | AV19: 179.2 | AW19: 179.4 | AX19: 183.5 | AY19: 105.5 | AZ19: 8.4 | BA19: 2.8 | BB19: 16.9 | BC19: 42.5 | BE19: 11.1 | BF19: 72.4 | BP19: 82.7 | BQ19: 178.2 | BR19: 176.1 | BS19: 200 | BT19: 275.4 | CC19: 4 | CD19: 55.3 | CE19: 92 | CF19: 61.8 | CG19: 77.2 | CH19: 30.2 | CL19: 147.3 | CM19: 148.4 | CN19: 149.2 | CT19: 97.2 | CU19: 37.6 | CV19: 0 | CW19: 29 | CX19: 0 | CY19: 8.7 | CZ19: 0 | DA19: 16.8 | DB19: 9.9 | DC19: 2.9 | DD19: 0.7 | DE19: 0 | DF19: 4.4 | DG19: 19.6 | DH19: 20 | DI19: 12.4 | DJ19: 3.5 | DK19: 18.5 | DL19: 0 | DM19: 0 | DN19: 9.5 | DO19: 28.9 | DP19: 3 | DQ19: 1.1 | DR19: 2.4 | DS19: 3.1 | DT19: 0 | DU19: 3.1 | DV19: 10.3 | DW19: 1.9 | DY19: 12.4 | DZ19: 5.6 | EA19: 7 | EB19: 9.4 | EC19: 19.8 | ED19: 16.1 | EE19: 5.6 | EF19: 0 | EG19: 5.7 | EH19: 8.4 | EI19: 0.6 | EJ19: 0.4 | EK19: 10 | EL19: 3.3 | EM19: 8.3 | EN19: 8.6 | EO19: 9.2 | EP19: 9.5 | EQ19: 3 | ER19: 0 | ES19: 0 | ET19: 0 | EU19: 0.6 | EV19: 5.4 | EW19: 3.4 | EX19: 0 | EY19: 0 | EZ19: 9.8 | FA19: 20 | FB19: 9.4 | FC19: 44.4 | FD19: 16.5 | FG19: 16.1 | FI19: 6.4 | FJ19: 6126.3 | FL19: 24.09669 | FM19: 0 | FO19: 13.2 | FP19: 0 | FQ19: 18.92628 | FR19: 11.5 | FS19: 16.2 | FT19: 83.92297
A20: 05/06/2025 | B20: 05:00 | C20: 139.8 | D20: 600.5 | E20: 200.2 | H20: 34.3 | I20: 165.5 | M20: 207.3 | N20: 208.2 | O20: 200.2 | R20: 559.6 | S20: 4.9 | X20: 164 | Y20: 7.5 | Z20: 5.6 | AB20: 6.8 | AC20: 11.6 | AD20: 60.9 | AI20: 70.5 | AJ20: 88.3 | AN20: 6.5 | AO20: 150.4 | AP20: 56 | AQ20: 0 | AR20: 31.2 | AS20: 18.8 | AT20: 13.2 | AU20: 90 | AV20: 182.8 | AW20: 184.5 | AX20: 184.7 | AY20: 106.8 | AZ20: 8.4 | BA20: 2.8 | BB20: 18.4 | BC20: 43.7 | BE20: 11.6 | BF20: 88.4 | BP20: 84 | BQ20: 177.5 | BR20: 175.8 | BS20: 200 | BT20: 274.8 | CC20: 4 | CD20: 96.2 | CE20: 109.5 | CF20: 63.2 | CG20: 78.1 | CH20: 30.7 | CL20: 102.9 | CM20: 101.8 | CN20: 121.4 | CT20: 145.5 | CU20: 74.9 | CV20: 0 | CW20: 26 | CX20: 0 | CY20: 9.5 | CZ20: 0 | DA20: 16.8 | DB20: 9.9 | DC20: 2.9 | DD20: 0.7 | DE20: 0 | DF20: 4.4 | DG20: 20.1 | DH20: 20 | DI20: 12.5 | DJ20: 3.5 | DK20: 18.5 | DL20: 0 | DM20: 0 | DN20: 9.6 | DO20: 18.1 | DP20: 3 | DQ20: 1.1 | DR20: 2.4 | DS20: 3.1 | DT20: 0 | DU20: 3.1 | DV20: 10.3 | DW20: 1.8 | DY20: 12.3 | DZ20: 5.6 | EA20: 7.2 | EB20: 9.7 | EC20: 19.8 | ED20: 21.3 | EE20: 5.2 | EF20: 0 | EG20: 5.6 | EH20: 12.3 | EI20: 1 | EJ20: 0.8 | EK20: 10 | EL20: 3.3 | EM20: 8.2 | EN20: 8.7 | EO20: 9.2 | EP20: 9.6 | EQ20: 4.7 | ER20: 0 | ES20: 0 | ET20: 0 | EU20: 0.6 | EV20: 3.4 | EW20: 4.8 | EX20: 0 | EY20: 0 | EZ20: 9.8 | FA20: 20 | FB20: 9.4 | FC20: 44.5 | FD20: 16.5 | FG20: 16.3 | FI20: 3.6 | FJ20: 6254.9 | FL20: 24.1263 | FM20: 0 | FO20: 13.2 | FP20: 0 | FQ20: 18.92603 | FR20: 11.7 | FS20: 16.2 | FT20: 84.15233
A21: 05/06/2025 | B21: 05:30 | C21: 139.8 | D21: 601.6 | E21: 200.1 | H21: 34.3 | I21: 167.7 | M21: 209.6 | N21: 209 | O21: 200.3 | R21: 561.6 | S21: 4.9 | X21: 162.6 | Y21: 7.5 | Z21: 5.4 | AB21: 6.9 | AC21: 11.6 | AD21: 61.3 | AI21: 90.4 | AJ21: 59.1 | AN21: 6.5 | AO21: 156.7 | AP21: 55 | AQ21: 0 | AR21: 29.6 | AS21: 18.8 | AT21: 13.2 | AU21: 87.9 | AV21: 182.3 | AW21: 183.9 | AX21: 185.3 | AY21: 105.6 | AZ21: 8.3 | BA21: 2.8 | BB21: 18.4 | BC21: 43.7 | BE21: 11.3 | BF21: 133.3 | BP21: 84.1 | BQ21: 178.2 | BR21: 176.5 | BS21: 200 | BT21: 275.3 | CC21: 4.1 | CD21: 110.2 | CE21: 113.5 | CF21: 63.3 | CG21: 78.2 | CH21: 30.6 | CL21: 103.4 | CM21: 102 | CN21: 121.5 | CT21: 213.6 | CU21: 98.4 | CV21: 0 | CW21: 22.8 | CX21: 0 | CY21: 11.9 | CZ21: 0 | DA21: 16.8 | DB21: 9.9 | DC21: 3 | DD21: 0.7 | DE21: 0 | DF21: 4.4 | DG21: 20 | DH21: 20 | DI21: 12.4 | DJ21: 3.5 | DK21: 18.5 | DL21: 0 | DM21: 0 | DN21: 7.7 | DO21: 16.2 | DP21: 3 | DQ21: 1.1 | DR21: 2.4 | DS21: 3.1 | DT21: 0 | DU21: 3.2 | DV21: 10.3 | DW21: 1.8 | DY21: 12.5 | DZ21: 5.6 | EA21: 7.3 | EB21: 9.9 | EC21: 20 | ED21: 17.6 | EE21: 3.4 | EF21: 0 | EG21: 3.7 | EH21: 6.6 | EI21: 1 | EJ21: 0.3 | EK21: 10 | EL21: 3.3 | EM21: 8.1 | EN21: 8.7 | EO21: 9.3 | EP21: 9.6 | EQ21: 6.4 | ER21: 0 | ES21: 0 | ET21: 0 | EU21: 0.6 | EV21: 3.1 | EW21: 8.8 | EX21: 0 | EY21: 0 | EZ21: 9.8 | FA21: 20 | FB21: 9.5 | FC21: 44.4 | FD21: 16.4 | FG21: 16.2 | FI21: 6.3 | FJ21: 6400.3 | FL21: 24.19051 | FM21: 0 | FO21: 13.2 | FP21: 0 | FQ21: 18.92618 | FR21: 11.5 | FS21: 16.2 | FT21: 84.01669
A22: 05/06/2025 | B22: 06:00 | C22: 119.1 | D22: 599.9 | E22: 200.3 | H22: 34.1 | I22: 170.1 | M22: 207.1 | N22: 207.8 | O22: 200 | R22: 558.6 | S22: 5 | X22: 165 | Y22: 7.7 | Z22: 5.5 | AB22: 6.8 | AC22: 11.6 | AD22: 60.7 | AI22: 90.9 | AJ22: 97.1 | AN22: 6.5 | AO22: 164.8 | AP22: 55.6 | AQ22: 0 | AR22: 31.4 | AS22: 18.8 | AT22: 13.2 | AU22: 88.8 | AV22: 184.3 | AW22: 183.5 | AX22: 184.3 | AY22: 105.7 | AZ22: 8.4 | BA22: 2.8 | BB22: 29.9 | BC22: 44 | BE22: 11.5 | BF22: 139.4 | BP22: 84.1 | BQ22: 178.3 | BR22: 175.9 | BS22: 200 | BT22: 275.2 | CC22: 4 | CD22: 171.1 | CE22: 123.4 | CF22: 63.6 | CG22: 78.1 | CH22: 30.8 | CL22: 103.9 | CM22: 101 | CN22: 120.9 | CT22: 217.6 | CU22: 103 | CV22: 0 | CW22: 25.3 | CX22: 0 | CY22: 10.8 | CZ22: 0 | DA22: 16.7 | DB22: 9.9 | DC22: 2.9 | DD22: 0.7 | DE22: 0 | DF22: 4.3 | DG22: 20.3 | DH22: 20 | DI22: 13.2 | DJ22: 3.5 | DK22: 18.5 | DL22: 0.1 | DM22: 0 | DN22: 9.8 | DO22: 15.6 | DP22: 3 | DQ22: 1.1 | DR22: 2.4 | DS22: 3.1 | DT22: 0 | DU22: 3.1 | DV22: 10.3 | DW22: 1.8 | DY22: 12.3 | DZ22: 5.6 | EA22: 7.5 | EB22: 9.9 | EC22: 20 | ED22: 14.2 | EE22: 0.3 | EF22: 0 | EG22: 3 | EH22: 4.6 | EI22: 0.5 | EJ22: 0.1 | EK22: 10 | EL22: 3.3 | EM22: 8.1 | EN22: 8.7 | EO22: 9.3 | EP22: 9.6 | EQ22: 5.6 | ER22: 0 | ES22: 0 | ET22: 0 | EU22: 0.6 | EV22: 8.5 | EW22: 22.3 | EX22: 0 | EY22: 0 | EZ22: 9.8 | FA22: 20 | FB22: 9.2 | FC22: 44.3 | FD22: 16.4 | FG22: 8 | FI22: 6.5 | FJ22: 6525.7 | FL22: 24.28962 | FM22: 0 | FO22: 13.2 | FP22: 0 | FQ22: 18.92581 | FR22: 11.6 | FS22: 16.1 | FT22: 84.11543
... A58: 06/06/2025 | B58: 00:00 | C58: 135.2 | D58: 639.4 | E58: 216.6 | H58: 90.2 | I58: 147.4 | M58: 164.7 | N58: 165 | O58: 169.5 | R58: 544.8 | S58: 4.6 | X58: 162.9 | Y58: 6.8 | Z58: 5 | AB58: 6.8 | AC58: 14.1 | AD58: 60.4 | AI58: 109.1 | AJ58: 136.2 | AN58: 6.5 | AO58: 151.4 | AP58: 48.7 | AQ58: 45.6 | AR58: 26 | AS58: 18.6 | AT58: 13.2 | AU58: 88.4 | AV58: 119.8 | AW58: 120.2 | AX58: 151 | AY58: 103.8 | AZ58: 8.4 | BA58: 2.8 | BB58: 17.4 | BC58: 43.8 | BE58: 10.7 | BF58: 75.4 | BP58: 80.5 | BQ58: 178.6 | BR58: 176 | BS58: 200 | BT58: 276.2 | CC58: 4 | CD58: 57.1 | CE58: 99.5 | CF58: 62.9 | CG58: 75.8 | CH58: 29.5 | CL58: 102.4 | CM58: 101.9 | CN58: 121.4 | CT58: 218.6 | CU58: 104 | CV58: 0 | CW58: 50.3 | CX58: 0 | CY58: 15.5 | CZ58: 0 | DA58: 15.9 | DB58: 9.9 | DC58: 5.4 | DD58: 0.6 | DE58: 1.5 | DF58: 4.2 | DG58: 19.6 | DH58: 20 | DI58: 12.4 | DJ58: 3.6 | DK58: 18.5 | DL58: 0 | DM58: 0 | DN58: 14.2 | DO58: 36.2 | DP58: 4.4 | DQ58: 1 | DR58: 2.2 | DS58: 3 | DT58: 0 | DU58: 3 | DV58: 10.1 | DW58: 1.9 | DY58: 11.5 | DZ58: 5.4 | EA58: 6.8 | EB58: 8.9 | EC58: 19.9 | ED58: 7.5 | EE58: 15.5 | EF58: 0 | EG58: 70.2 | EH58: 84.1 | EI58: 7.7 | EJ58: 5.4 | EK58: 9.3 | EL58: 3.2 | EM58: 8.1 | EN58: 8.3 | EO58: 9.1 | EP58: 9.2 | EQ58: 13.6 | ER58: 0 | ES58: 0 | ET58: 0 | EU58: 0.6 | EV58: 84.1 | EW58: 80.3 | EX58: 0 | EY58: 0 | EZ58: 9.8 | FA58: 20 | FB58: 9.4 | FC58: 44 | FD58: 13.2 | FG58: 17.8 | FI58: 7.3 | FJ58: 6562.4 | FL58: 24.17401 | FM58: 0.642 | FO58: 13.2 | FP58: 27.14595 | FQ58: 18.927 | FR58: 11.5 | FS58: 16.1 | FT58: 111.68896
A59: EJEC | C59: 3106.9 | D59: 15233.7 | E59: 5110.4 | F59: 0 | G59: 0 | H59: 1804.2 | I59: 3801.6 | J59: 0 | K59: 0 | L59: 0 | M59: 4651.2 | N59: 4688.3 | O59: 4590.9 | P59: 0 | Q59: 0 | R59: 12137.1 | S59: 115.75 | T59: 0 | U59: 0 | V59: 0 | W59: 0 | X59: 3918.4 | Y59: 173.75 | Z59: 127.2 | AA59: 0 | AB59: 163.65 | AC59: 310.5 | AD59: 1981.05 | AE59: 0 | AF59: 0 | AG59: 0 | AH59: 0 | AI59: 2194.25 | AJ59: 3591.4 | AK59: 0 | AL59: 0 | AM59: 0 | AN59: 156 | AO59: 5367.9 | AP59: 1238.5 | AQ59: 1810.7 | AR59: 644.75 | AS59: 450.7 | AT59: 257.65 | AU59: 2139.5 | AV59: 3818.75 | AW59: 3829.2 | AX59: 4133.1 | AY59: 2507.05 | AZ59: 199.5 | BA59: 65.5 | BB59: 470 | BC59: 1041.1 | BD59: 0 | BE59: 389.65 | BF59: 2494.9 | BG59: 0 | BH59: 0 | BI59: 0 | BJ59: 0 | BK59: 0 | BL59: 0 | BM59: 0 | BN59: 0 | BO59: 0 | BP59: 1965.35 | BQ59: 4250.8 | BR59: 4200 | BS59: 4774.8 | BT59: 6589.3 | BU59: 0 | BV59: 0 | BW59: 0 | BX59: 0 | BY59: 0 | BZ59: 0 | CA59: 0 | CB59: 0 | CC59: 95.05 | CD59: 2371.75 | CE59: 2613.65 | CF59: 1537.55 | CG59: 1823.15 | CH59: 723.1 | CI59: 0 | CJ59: 0 | CK59: 0 | CL59: 3099.85 | CM59: 3100.75 | CN59: 3318.8 | CO59: 0 | CP59: 0 | CQ59: 0 | CR59: 0 | CS59: 0 | CT59: 4308.95 | CU59: 2014 | CV59: 8.15 | CW59: 1123.05 | CX59: 598 | CY59: 320.85 | CZ59: 2.6 | DA59: 394.1 | DB59: 237.2 | DC59: 120.1 | DD59: 16.4 | DE59: 27 | DF59: 102.5 | DG59: 478.35 | DH59: 480 | DI59: 294.05 | DJ59: 85 | DK59: 444 | DL59: 117 | DM59: 140.7 | DN59: 334.15 | DO59: 1010.45 | DP59: 68.7 | DQ59: 24.8 | DR59: 56 | DS59: 73.1 | DT59: 106.1 | DU59: 75.6 | DV59: 244.5 | DW59: 46.45 | DX59: 0 | DY59: 294 | DZ59: 126.35 | EA59: 172.45 | EB59: 242.95 | EC59: 478.4 | ED59: 282.4 | EE59: 544.2 | EF59: 247.4 | EG59: 918.9 | EH59: 1086.3 | EI59: 133.2 | EJ59: 86.7 | EK59: 233.05 | EL59: 79.5 | EM59: 199.45 | EN59: 206.85 | EO59: 224.8 | EP59: 228.1 | EQ59: 252.8 | ER59: 1890.8 | ES59: 114.2 | ET59: 1029.4 | EU59: 14.4 | EV59: 1306.05 | EW59: 1488.1 | EX59: 766.65 | EY59: 114.25 | EZ59: 234.8 | FA59: 479.4 | FB59: 220.9 | FC59: 1060.65 | FD59: 348.3 | FE59: 0 | FF59: 0 | FG59: 354.1 | FH59: 0 | FI59: 152.85 | FJ59: 168143.1 | FL59: 559.68205 | FM59: 79.4765 | FN59: 0 | FO59: 316.8 | FP59: 471.11372 | FQ59: 454.31721 | FR59: 276.5 | FS59: 387.2 | FT59: 2545.0895
FJ61: 168385.19
FJ63: =+FJ61-FJ59 -> 242.08645

Sheet REACTIVA
B3: jueves, 5 de Junio del 2025
A5: POTENCIA REACTIVA EJECUTADA DE LAS UNIDADES DE GENERACIÓN DEL COES (MVAR) | FK5: CENTRALES NO INTEGRANTES COES
A6: FECHA | B6: HORA | C6: 65333 | D6: 101 | E6: 102 | F6: 42667 | G6: 42668 | H6: 126 | I6: 127 | J6: 138 | K6: 139 | L6: 197 | M6: 203 | N6: 204 | O6: 230 | P6: 209 | Q6: 56677 | R6: 796 | S6: 2146 | T6: 142 | U6: 143 | V6: 125 | W6: 187 | X6: 163 | Y6: 298 | Z6: 219 | AA6: 151 | AB6: 152 | AC6: 153 | AD6: 154 | AE6: 756 | AF6: 156 | AG6: 155 | AH6: 182 | AI6: 212 | AJ6: 758 | AK6: 263 | AL6: 265 | AM6: 775 | AN6: 777 | AO6: 2154 | AP6: 150 | AQ6: 149 | AR6: 188 | AS6: 2131 | AT6: 755 | AU6: 252 | AV6: 249 | AW6: 250 | AX6: 117 | AY6: 267 | AZ6: 268 | BA6: 119 | BB6: 120 | BC6: 189 | BD6: 122 | BE6: 266 | BF6: 337 | BG6: 338 | BH6: 251 | BI6: 115 | BJ6: 239 | BK6: 288 | BL6: 240 | BM6: 241 | BN6: 242 | BO6: 191 | BP6: 194 | BQ6: 196 | BR6: 207 | BS6: 236 | BT6: 795 | BU6: 285 | BV6: 995 | BW6: 996 | BX6: 997 | BY6: 766 | BZ6: 926 | CA6: 924 | CB6: 121 | CC6: 103 | CD6: 104 | CE6: 106 | CF6: 105 | CG6: 107 | CH6: 110 | CI6: 109 | CJ6: 144 | CK6: 113 | CL6: 114 | CM6: 193 | CN6: 208 | CO6: 786 | CP6: 787 | CQ6: 788 | CR6: 789 | CS6: 248 | CT6: 2159 | CU6: 303 | CV6: 59715 | CW6: 62255 | CX6: 1263 | CY6: 61800 | CZ6: 2194 | DA6: 216 | DB6: 198 | DC6: 49607 | DD6: 214 | DE6: 260 | DF6: 2152 | DG6: 2128 | DH6: 247 | DI6: 228 | DJ6: 2135 | DK6: 261 | DL6: 237 | DM6: 253 | DN6: 770 | DO6: 225 | DP6: 2201 | DQ6: 2171 | DR6: 760 | DS6: 235 | DT6: 238 | DU6: 2184 | DV6: 61855 | DW6: 223 | DX6: 226 | DY6: 201 | DZ6: 258 | EA6: 259 | EB6: 920 | EC6: 257 | ED6: 256 | EE6: 2148 | EF6: 58288 | EG6: 58289 | EH6: 58839 | EI6: 58840 | EJ6: 296 | EK6: 297 | EL6: 211 | EM6: 2175 | EN6: 2178 | EO6: 2181 | EP6: 1262 | EQ6: 63425 | ER6: 233 | ES6: 2150 | ET6: 2165 | EU6: 2161 | EV6: 61197 | EW6: 58851 | EX6: 234 | EY6: 215 | EZ6: 917 | FA6: 289 | FB6: 58333 | FC6: 58336 | FD6: 202 | FE6: 58487 | FF6: 213 | FG6: 232 | FH6: 2190 | FI6: TOTAL COES | FK6: 221 | FL6: 222 | FM6: 224 | FN6: 2187 | FO6: 227 | FP6: 49400 | FQ6: 199 | FR6: 200 | FS6: TOTAL NO COES
C7: SUR | D7: CENTRO | E7: CENTRO | F7: NORTE | G7: NORTE | H7: NORTE | I7: NORTE | J7: CENTRO | K7: CENTRO | L7: CENTRO | M7: CENTRO | N7: CENTRO | O7: CENTRO | P7: CENTRO | Q7: CENTRO | R7: CENTRO | S7: CENTRO | T7: CENTRO | U7: CENTRO | V7: CENTRO | W7: CENTRO | X7: SUR | Y7: SUR | Z7: CENTRO | AA7: SUR | AB7: SUR | AC7: SUR | AD7: SUR | AE7: SUR | AF7: SUR | AG7: SUR | AH7: SUR | AI7: CENTRO | AJ7: NORTE | AK7: NORTE | AL7: NORTE | AM7: CENTRO | AN7: CENTRO | AO7: CENTRO | AP7: CENTRO | AQ7: CENTRO | AR7: CENTRO | AS7: CENTRO | AT7: SUR | AU7: CENTRO | AV7: CENTRO | AW7: CENTRO | AX7: CENTRO | AY7: CENTRO | AZ7: CENTRO | BA7: CENTRO | BB7: CENTRO | BC7: SUR | BD7: NORTE | BE7: CENTRO | BF7: CENTRO | BG7: CENTRO | BH7: CENTRO | BI7: NORTE | BJ7: NORTE | BK7: NORTE | BL7: SUR | BM7: SUR | BN7: SUR | BO7: CENTRO | BP7: CENTRO | BQ7: CENTRO | BR7: CENTRO | BS7: CENTRO | BT7: CENTRO | BU7: CENTRO | BV7: SUR | BW7: SUR | BX7: SUR | BY7: NORTE | BZ7: SUR | CA7: CENTRO | CB7: NORTE | CC7: CENTRO | CD7: CENTRO | CE7: CENTRO | CF7: CENTRO | CG7: CENTRO | CH7: CENTRO | CI7: CENTRO | CJ7: CENTRO | CK7: CENTRO | CL7: CENTRO | CM7: CENTRO | CN7: CENTRO | CO7: SUR | CP7: SUR | CQ7: SUR | CR7: SUR | CS7: CENTRO | CT7: CENTRO | CU7: CENTRO | CV7: CENTRO | CW7: SUR | CX7: NORTE | CY7: NORTE | CZ7: NORTE | DA7: NORTE | DB7: NORTE | DC7: SUR | DD7: CENTRO | DE7: CENTRO | DF7: CENTRO | DG7: NORTE | DH7: NORTE | DI7: CENTRO | DJ7: CENTRO | DK7: SUR | DL7: SUR | DM7: CENTRO | DN7: CENTRO | DO7: CENTRO | DP7: CENTRO | DQ7: CENTRO | DR7: CENTRO | DS7: SUR | DT7: CENTRO | DU7: CENTRO | DV7: NORTE | DW7: CENTRO | DX7: CENTRO | DY7: NORTE | DZ7: CENTRO | EA7: CENTRO | EB7: CENTRO | EC7: NORTE | ED7: NORTE | EE7: SUR | EF7: CENTRO | EG7: CENTRO | EH7: CENTRO | EI7: CENTRO | EJ7: CENTRO | EK7: CENTRO | EL7: SUR | EM7: SUR | EN7: SUR | EO7: SUR | EP7: NORTE | EQ7: SUR | ER7: SUR | ES7: SUR | ET7: CENTRO | EU7: CENTRO | EV7: CENTRO | EW7: SUR | EX7: SUR | EY7: NORTE | EZ7: CENTRO | FA7: NORTE | FB7: NORTE | FC7: NORTE | FD7: CENTRO | FE7: CENTRO | FF7: CENTRO | FG7: NORTE | FH7: NORTE | FK7: NORTE | FL7: CENTRO | FM7: NORTE | FN7: NORTE | FO7: NORTE | FP7: NORTE | FQ7: NORTE | FR7: NORTE
C8: HIDROELÉCTRICA | D8: HIDROELÉCTRICA | E8: HIDROELÉCTRICA | F8: TERMOELÉCTRICA | G8: TERMOELÉCTRICA | H8: HIDROELÉCTRICA | I8: HIDROELÉCTRICA | J8: TERMOELÉCTRICA | K8: TERMOELÉCTRICA | L8: TERMOELÉCTRICA | M8: TERMOELÉCTRICA | N8: TERMOELÉCTRICA | O8: TERMOELÉCTRICA | P8: TERMOELÉCTRICA | Q8: TERMOELÉCTRICA | R8: HIDROELÉCTRICA | S8: HIDROELÉCTRICA | T8: TERMOELÉCTRICA | U8: TERMOELÉCTRICA | V8: TERMOELÉCTRICA | W8: TERMOELÉCTRICA | X8: HIDROELÉCTRICA | Y8: HIDROELÉCTRICA | Z8: TERMOELÉCTRICA | AA8: HIDROELÉCTRICA | AB8: HIDROELÉCTRICA | AC8: HIDROELÉCTRICA | AD8: HIDROELÉCTRICA | AE8: TERMOELÉCTRICA | AF8: TERMOELÉCTRICA | AG8: TERMOELÉCTRICA | AH8: HIDROELÉCTRICA | AI8: HIDROELÉCTRICA | AJ8: TERMOELÉCTRICA | AK8: TERMOELÉCTRICA | AL8: TERMOELÉCTRICA | AM8: HIDROELÉCTRICA | AN8: HIDROELÉCTRICA | AO8: HIDROELÉCTRICA | AP8: HIDROELÉCTRICA | AQ8: HIDROELÉCTRICA | AR8: HIDROELÉCTRICA | AS8: HIDROELÉCTRICA | AT8: HIDROELÉCTRICA | AU8: TERMOELÉCTRICA | AV8: TERMOELÉCTRICA | AW8: TERMOELÉCTRICA | AX8: HIDROELÉCTRICA | AY8: HIDROELÉCTRICA | AZ8: HIDROELÉCTRICA | BA8: HIDROELÉCTRICA | BB8: HIDROELÉCTRICA | BC8: HIDROELÉCTRICA | BD8: HIDROELÉCTRICA | BE8: HIDROELÉCTRICA | BF8: HIDROELÉCTRICA | BG8: HIDROELÉCTRICA | BH8: HIDROELÉCTRICA | BI8: TERMOELÉCTRICA | BJ8: TERMOELÉCTRICA | BK8: TERMOELÉCTRICA | BL8: TERMOELÉCTRICA | BM8: TERMOELÉCTRICA | BN8: TERMOELÉCTRICA | BO8: HIDROELÉCTRICA | BP8: TERMOELÉCTRICA | BQ8: TERMOELÉCTRICA | BR8: TERMOELÉCTRICA | BS8: TERMOELÉCTRICA | BT8: TERMOELÉCTRICA | BU8: TERMOELÉCTRICA | BV8: TERMOELÉCTRICA | BW8: TERMOELÉCTRICA | BX8: TERMOELÉCTRICA | BY8: HIDROELÉCTRICA | BZ8: TERMOELÉCTRICA | CA8: TERMOELÉCTRICA | CB8: HIDROELÉCTRICA | CC8: HIDROELÉCTRICA | CD8: HIDROELÉCTRICA | CE8: HIDROELÉCTRICA | CF8: HIDROELÉCTRICA | CG8: HIDROELÉCTRICA | CH8: TERMOELÉCTRICA | CI8: TERMOELÉCTRICA | CJ8: TERMOELÉCTRICA | CK8: TERMOELÉCTRICA | CL8: TERMOELÉCTRICA | CM8: TERMOELÉCTRICA | CN8: TERMOELÉCTRICA | CO8: TERMOELÉCTRICA | CP8: TERMOELÉCTRICA | CQ8: TERMOELÉCTRICA | CR8: TERMOELÉCTRICA | CS8: TERMOELÉCTRICA | CT8: TERMOELÉCTRICA | CU8: SOLAR | CV8: EÓLICA | CW8: SOLAR | CX8: EÓLICA | CY8: SOLAR | CZ8: HIDROELÉCTRICA | DA8: HIDROELÉCTRICA | DB8: HIDROELÉCTRICA | DC8: HIDROELÉCTRICA | DD8: HIDROELÉCTRICA | DE8: HIDROELÉCTRICA | DF8: HIDROELÉCTRICA | DG8: HIDROELÉCTRICA | DH8: HIDROELÉCTRICA | DI8: HIDROELÉCTRICA | DJ8: HIDROELÉCTRICA | DK8: SOLAR | DL8: SOLAR | DM8: EÓLICA | DN8: EÓLICA | DO8: TERMOELÉCTRICA | DP8: TERMOELÉCTRICA | DQ8: TERMOELÉCTRICA | DR8: TERMOELÉCTRICA | DS8: SOLAR | DT8: HIDROELÉCTRICA | DU8: HIDROELÉCTRICA | DV8: HIDROELÉCTRICA | DW8: HIDROELÉCTRICA | DX8: HIDROELÉCTRICA | DY8: HIDROELÉCTRICA | DZ8: HIDROELÉCTRICA | EA8: HIDROELÉCTRICA | EB8: HIDROELÉCTRICA | EC8: EÓLICA | ED8: EÓLICA | EE8: SOLAR | EF8: EÓLICA | EG8: EÓLICA | EH8: EÓLICA | EI8: EÓLICA | EJ8: HIDROELÉCTRICA | EK8: HIDROELÉCTRICA | EL8: HIDROELÉCTRICA | EM8: HIDROELÉCTRICA | EN8: HIDROELÉCTRICA | EO8: HIDROELÉCTRICA | EP8: EÓLICA | EQ8: SOLAR | ER8: SOLAR | ES8: SOLAR | ET8: HIDROELÉCTRICA | EU8: EÓLICA | EV8: EÓLICA | EW8: SOLAR | EX8: SOLAR | EY8: HIDROELÉCTRICA | EZ8: HIDROELÉCTRICA | FA8: TERMOELÉCTRICA | FB8: TERMOELÉCTRICA | FC8: TERMOELÉCTRICA | FD8: TERMOELÉCTRICA | FE8: TERMOELÉCTRICA | FF8: TERMOELÉCTRICA | FG8: TERMOELÉCTRICA | FH8: TERMOELÉCTRICA | FK8: HIDROELÉCTRICA | FL8: HIDROELÉCTRICA | FM8: HIDROELÉCTRICA | FN8: HIDROELÉCTRICA | FO8: TERMOELÉCTRICA | FP8: TERMOELÉCTRICA | FQ8: HIDROELÉCTRICA | FR8: HIDROELÉCTRICA
C9: HYDRO GLOBAL PERÚ S.A.C. | D9: ELECTROPERU | E9: ELECTROPERU | F9: ELECTROPERU | G9: ELECTROPERU | H9: ORAZUL ENERGY PERÚ | I9: ORAZUL ENERGY PERÚ | J9: TERMOSELVA | K9: TERMOSELVA | L9: KALLPA GENERACION S.A. | M9: KALLPA GENERACION S.A. | N9: KALLPA GENERACION S.A. | O9: KALLPA GENERACION S.A. | P9: KALLPA GENERACION S.A. | Q9: KALLPA GENERACION S.A. | R9: KALLPA GENERACION S.A. | S9: KALLPA GENERACION S.A. | T9: SHOUGESA | U9: SHOUGESA | V9: SHOUGESA | W9: SHOUGESA | X9: EGEMSA | Y9: EGESUR | Z9: EGESUR | AA9: EGASA | AB9: EGASA | AC9: EGASA | AD9: EGASA | AE9: EGASA | AF9: EGASA | AG9: EGASA | AH9: SAN GABAN | AI9: CELEPSA | AJ9: MINERA CERRO VERDE | AK9: PLANTA DE RESERVA FRIA DE GENERACION DE ETEN S.A. | AL9: PLANTA DE RESERVA FRIA DE GENERACION DE ETEN S.A. | AM9: EMPRESA DE GENERACION HUALLAGA | AN9: EMPRESA DE GENERACION HUALLAGA | AO9: LA VIRGEN | AP9: CHINANGO S.A.C. | AQ9: CHINANGO S.A.C. | AR9: HIDROELECTRICA HUANCHOR S.A.C. | AS9: CELEPSA RENOVABLES S.R.L. | AT9: INLAND ENERGY SAC | AU9: FENIX POWER PERÚ | AV9: FENIX POWER PERÚ | AW9: FENIX POWER PERÚ | AX9: STATKRAFT S.A | AY9: STATKRAFT S.A | AZ9: STATKRAFT S.A | BA9: STATKRAFT S.A | BB9: STATKRAFT S.A | BC9: STATKRAFT S.A | BD9: STATKRAFT S.A | BE9: STATKRAFT S.A | BF9: CENTRALES SANTA ROSA S.A.C. | BG9: CENTRALES SANTA ROSA S.A.C. | BH9: EMPRESA DE GENERACION HUANZA | BI9: ENEL GENERACION PIURA S.A. | BJ9: ENEL GENERACION PIURA S.A. | BK9: ENEL GENERACION PIURA S.A. | BL9: ENGIE | BM9: ENGIE | BN9: ENGIE | BO9: ENGIE | BP9: ENGIE | BQ9: ENGIE | BR9: ENGIE | BS9: ENGIE | BT9: ENGIE | BU9: ENGIE | BV9: ENGIE | BW9: ENGIE | BX9: ENGIE | BY9: ENGIE | BZ9: INFRAESTRUCTURAS Y ENERGIAS DEL PERU S.A.C. | CA9: INFRAESTRUCTURAS Y ENERGIAS DEL PERU S.A.C. | CB9: INVERSIONES SHAQSHA S.A.C. | CC9: ORYGEN PERU S.A.A. | CD9: ORYGEN PERU S.A.A. | CE9: ORYGEN PERU S.A.A. | CF9: ORYGEN PERU S.A.A. | CG9: ORYGEN PERU S.A.A. | CH9: ORYGEN PERU S.A.A. | CI9: ORYGEN PERU S.A.A. | CJ9: ORYGEN PERU S.A.A. | CK9: ORYGEN PERU S.A.A. | CL9: ORYGEN PERU S.A.A. | CM9: ORYGEN PERU S.A.A. | CN9: ORYGEN PERU S.A.A. | CO9: SAMAY I S.A.C | CP9: SAMAY I S.A.C | CQ9: SAMAY I S.A.C | CR9: SAMAY I S.A.C | CS9: TERMOCHILCA S.A.C. | CT9: TERMOCHILCA S.A.C. | CU9: COLCA SOLAR S.A.C. | CV9: ENERGIA RENOVABLE DEL SUR S.A. | CW9: GR CORTARRAMA SOCIEDAD ANONIMA CERRADA | CX9: GR TARUCA SOCIEDAD ANONIMA CERRADA | CY9: KONDU SAC | CZ9: PERUANA DE INVERSIONES EN ENERGIAS RENOVABLES S.A. | DA9: ORAZUL ENERGY PERÚ | DB9: ORAZUL ENERGY PERÚ | DC9: SAN GABAN | DD9: MAJA ENERGIA S.A.C. | DE9: EMPRESA DE GENERACION ELECTRICA CANCHAYLLO SAC | DF9: EMPRESA DE GENERACION ELECTRICA SANTA ANA S.A.C. | DG9: EMPRESA ELECTRICA AGUA AZUL | DH9: EMPRESA ELECTRICA RIO DOBLE | DI9: HIDROCAÑETE S.A. | DJ9: HUAURA POWER GROUP S.A. | DK9: MOQUEGUA FV S.A.C. | DL9: PANAMERICANA SOLAR SAC. | DM9: PARQUE EOLICO MARCONA S.A.C. | DN9: PARQUE EOLICO TRES HERMANAS S.A.C. | DO9: PETRAMAS | DP9: PETRAMAS | DQ9: PETRAMAS | DR9: PETRAMAS | DS9: TACNA SOLAR SAC. | DT9: ELECTRICA YANAPAMPA SAC | DU9: ANDEAN POWER S.A.C. | DV9: ASOCIACIÓN SANTA LUCIA DE CHACAS | DW9: ATRIA ENERGIA S.A.C. | DX9: EGEJUNIN | DY9: EGEJUNIN | DZ9: EGEJUNIN | EA9: EGEJUNIN | EB9: EMPRESA DE GENERACION ELECTRICA RIO BAÑOS S.A.C. | EC9: ENERGÍA EÓLICA S.A. | ED9: ENERGÍA EÓLICA S.A. | EE9: ENGIE | EF9: ENGIE | EG9: ENGIE | EH9: ENGIE | EI9: ENGIE | EJ9: GENERACIÓN ANDINA S.A.C. | EK9: GENERACIÓN ANDINA S.A.C. | EL9: GENERADORA DE ENERGÍA DEL PERÚ | EM9: GENERADORA DE ENERGÍA DEL PERÚ | EN9: GENERADORA DE ENERGÍA DEL PERÚ | EO9: GENERADORA DE ENERGÍA DEL PERÚ | EP9: GR PAINO SOCIEDAD ANONIMA CERRADA | EQ9: JOYA SOLAR S.A.C. | ER9: MAJES ARCUS S.A.C. | ES9: ORYGEN PERU S.A.A. | ET9: ORYGEN PERU S.A.A. | EU9: ORYGEN PERU S.A.A. | EV9: ORYGEN PERU S.A.A. | EW9: ORYGEN PERU S.A.A. | EX9: REPARTICIÓN ARCUS S.A.C. | EY9: SINERSA | EZ9: SINERSA | FA9: BIOENERGIA DEL CHIRA S.A. | FB9: GM OPERACIONES S.A.C. | FC9: GM OPERACIONES S.A.C. | FD9: SDF ENERGIA SAC | FE9: SDF ENERGIA SAC | FF9: AGRO INDUSTRIAL PARAMONGA S.A. | FG9: AGROAURORA S.A.C. | FH9: AGROINDUSTRIAS SAN JACINTO S.A.A. | FK9: UNACEM PERU S.A. | FL9: ELECTRO ORIENTE | FM9: AGUAS Y ENERGIA PERU | FN9: ELECTRO ZAÑA S.A.C. | FO9: ELECTRONOROESTE S.A. | FP9: SDE PIURA | FQ9: SINERSA | FR9: SINERSA
C10: SAN GABAN III | D10: MANTARO | E10: RESTITUCION | F10: TUMBES MAK 1 | G10: TUMBES MAK 2 | H10: CARHUAQUERO | I10: CAÑON DEL PATO | J10: AGUAYTIA TG1 | K10: AGUAYTIA TG2 | L10: KALLPA TG1 | M10: KALLPA TG2 | N10: KALLPA TG3 | O10: KALLPA TV | P10: LFLORES TG1 | Q10: LFLORES TV | R10: CERRO DEL AGUILA | S10: CERRODELAGUILAG4 | T10: SHOUGESA TV1 | U10: SHOUGESA TV2 | V10: SHOUGESA TV3 | W10: SHOUGESA CUMMINS | X10: MACHUPICCHU | Y10: ARICOTA 1 | Z10: INDEPENDENCIA | AA10: CHARCANI I,II,III | AB10: CHARCANI IV | AC10: CHARCANI V | AD10: CHARCANI VI | AE10: CHILINA TG | AF10: MOLLENDO 1, 2, 3 | AG10: CHILINA (SULZ 1,2) | AH10: SAN GABAN II | AI10: PLATANAL | AJ10: RECKA | AK10: RF ETEN TG1 | AL10: RF ETEN TG2 | AM10: CHAGLLA GP1 | AN10: CHAGLLA | AO10: LA VIRGEN | AP10: CHIMAY | AQ10: YANANGO | AR10: HUANCHOR | AS10: MARAÑON | AT10: STA TERESA | AU10: FENIX GT11 | AV10: FENIX GT12 | AW10: FENIX TV10 | AX10: YAUPI | AY10: OROYA | AZ10: PACHACHACA | BA10: MALPASO | BB10: CAHUA | BC10: ARCATA | BD10: GALLITO CIEGO | BE10: CHEVES | BF10: SANTA ROSA 1 | BG10: SANTA ROSA 2 | BH10: HUANZA | BI10: MALACAS2 TG4 | BJ10: MALACAS3 TG 5 | BK10: MALACAS1 TG6 | BL10: RF ILO2 TG1 | BM10: RF ILO2 TG2 | BN10: RF ILO2 TG3 | BO10: YUNCAN | BP10: CHILCA1 TG1 | BQ10: CHILCA1 TG2 | BR10: CHILCA1 TG3 | BS10: CHILCA-TV | BT10: CHILCA2 TG41 | BU10: CHILCA2-TV | BV10: CTNEPI_TG41 | BW10: CTNEPI_TG42 | BX10: CTNEPI_TG43 | BY10: QUITARACSA | BZ10: RF PTO MALDONADO | CA10: RF PUCALLPA | CB10: PARIAC | CC10: HUINCO | CD10: MATUCANA | CE10: MOYOPAMPA | CF10: CALLAHUANCA | CG10: HUAMPANI | CH10: STA ROSA WEST TG7 | CI10: UTI_5 | CJ10: UTI_6 | CK10: VENTANILLA 3 | CL10: VENTANILLA 4 | CM10: VENTANILLA TV | CN10: STAROSA TG8 | CO10: PTO_BRVO TG1 | CP10: PTO_BRVO TG2 | CQ10: PTO_BRVO TG3 | CR10: PTO_BRVO TG4 | CS10: OLLEROS TG1 | CT10: OLLEROS TV | CU10: CS YARUCAYA | CV10: SAN JUAN | CW10: MATARANI | CX10: DUNA | CY10: CARHUAQUERO (CS) | CZ10: MANTA I | DA10: CARHUAQUERO4 | DB10: CAÑA BRAVA | DC10: TUPURI | DD10: RONCADOR | DE10: CANCHAYLLO | DF10: RENOVANDESH1 | DG10: POTRERO | DH10: PIZARRAS | DI10: NIMPERIAL | DJ10: YARUCAYA | DK10: MOQUEGUA-SOLAR | DL10: PANAMERICANA-SOLAR | DM10: PQE-EOLICO-MARCONA | DN10: PQE-EOLICO-3-HERMANAS | DO10: HUAYCOLORO | DP10: CALLAO | DQ10: DONA_CATALINA | DR10: LAGRINGAV | DS10: TACNA-SOLAR | DT10: YANAPAMPA | DU10: CARHUAC | DV10: HUALLIN | DW10: PURMACANA | DX10: HUASAHUASI | DY10: STACRUZ_1_2 | DZ10: RUNATULLO_II | EA10: RUNATULLO_III | EB10: RUCUY | EC10: PQE-EOLICO-TALARA | ED10: PQE-EOLICO-CUPISNIQUE | EE10: INTIPAMPA | EF10: PUNTA LOMITAS-BL1 | EG10: PUNTA LOMITAS-BL2 | EH10: PUN LOMITAS_EXP-BL1 | EI10: PUN LOMITAS_EXP-BL2 | EJ10: 8AGOSTO | EK10: EL CARMEN | EL10: LA JOYA | EM10: ANGEL_I | EN10: ANGEL_II | EO10: ANGEL_III | EP10: HUAMBOS | EQ10: SAN MARTIN SOLAR | ER10: MAJES | ES10: RUBI | ET10: CH_HER1 | EU10: WAYRA-I | EV10: WAYRA EXTENSION | EW10: CLEMESI | EX10: REPARTICION | EY10: POECHOS2 | EZ10: CHANCAY | FA10: CANA BRAVA | FB10: REFINERIA TALARA TV1 | FC10: REFINERÍA TALARA TV2 | FD10: OQUENDO TG1 | FE10: OQUENDO TV1 | FF10: PARAMONGA | FG10: MAPLE | FH10: SAN_JACINTO | FI10: MVAR | FK10: CARPAPATA | FL10: CENTRALES ELOR | FM10: PIAS1 | FN10: ZANA | FO10: TABLAZO | FP10: TALLANCA | FQ10: CURUMUY | FR10: POECHOS1 | FS10: MVAR
A11: 05/06/2025 | B11: 00:30 | C11: 17.6 | D11: -10.5 | E11: 5.9 | H11: -29.4 | I11: -17.7 | M11: -19.4 | N11: -8.9 | O11: -10.1 | R11: 60.9 | S11: -0.1 | X11: 0.5 | Y11: 1.4 | AA11: -3.5 | AB11: 3 | AC11: 15.3 | AH11: -8 | AI11: -11.8 | AM11: -1.3 | AN11: -23.2 | AO11: -0.2 | AP11: 5.6 | AQ11: 4.3 | AR11: -1.6 | AS11: 1.8 | AT11: 0.9 | AU11: -20.6 | AV11: -36.4 | AW11: -48.1 | AX11: 0.3 | AY11: -1.5 | AZ11: 0 | BA11: -3.9 | BB11: -3.9 | BD11: 0.1 | BE11: -1.9 | BO11: -5.6 | BP11: -40.5 | BQ11: -42 | BR11: 0 | BS11: -18.7 | CB11: -0.3 | CC11: 27.1 | CD11: 15.1 | CE11: 1.5 | CF11: 4.9 | CG11: -0.1 | CK11: -13.5 | CL11: -12.8 | CM11: -38.6 | CS11: -2.5 | CT11: 0 | CV11: -5.1 | CW11: 0 | CZ11: 1.2 | DA11: 0 | DB11: -0.8 | DD11: 0 | DE11: 0.9 | DF11: 0.1 | DG11: -0.6 | DH11: 1.2 | DI11: 0.5 | DK11: 0 | DL11: 0 | DM11: -4.5 | DN11: -11.3 | DO11: 1.4 | DP11: 0.3 | DQ11: 1 | DR11: 1.3 | DS11: 0 | DT11: -0.1 | DU11: 0.5 | DV11: 0.5 | DX11: -3.8 | DY11: 0.5 | DZ11: -0.3 | EA11: 0.5 | EB11: 1.1 | EC11: 0.8 | ED11: 4 | EE11: 0 | EF11: -9.2 | EG11: -9.1 | EH11: 0 | EI11: 0 | EJ11: 1.2 | EK11: -0.2 | EL11: 1.6 | EM11: 0.2 | EN11: 0.2 | EO11: 0.2 | EQ11: 0 | ER11: 0 | ES11: 0 | ET11: -0.2 | EU11: 2.7 | EV11: 0.6 | EW11: 0 | EX11: 0 | EY11: 0.2 | EZ11: 1.2 | FA11: 3.2 | FB11: 15 | FC11: 7.7 | FF11: 3.6 | FH11: 1.6 | FI11: -260.6 | FK11: 2.42904 | FL11: 0 | FN11: 1.5 | FO11: 0.33569 | FP11: 0.39747 | FQ11: -0.7 | FR11: 2.1 | FS11: 6.0622
A12: 05/06/2025 | B12: 01:00 | C12: 28.2 | D12: -1 | E12: 7.9 | H12: -22.7 | I12: 30.6 | M12: -16.2 | N12: -7.6 | O12: -7.5 | R12: 64.3 | S12: 0 | X12: -0.5 | Y12: 1.4 | AA12: -3.3 | AB12: 3.4 | AC12: 17.3 | AH12: -5 | AI12: -17 | AM12: -1.4 | AN12: -24.9 | AO12: 0.1 | AP12: 4.9 | AQ12: 1.6 | AR12: -1.6 | AS12: 1.8 | AT12: 1.9 | AU12: -5.1 | AV12: -20.4 | AW12: -37.4 | AX12: -0.8 | AY12: -1.4 | AZ12: 0.4 | BA12: -0.7 | BB12: -1.7 | BD12: 0 | BE12: -0.7 | BO12: -4.3 | BP12: -46.3 | BQ12: -47.8 | BR12: 0 | BS12: -26.3 | CB12: -0.1 | CC12: 17.5 | CD12: 11.4 | CE12: -2.8 | CF12: 6.1 | CG12: -2.1 | CK12: -4.4 | CL12: -3.8 | CM12: -25.8 | CS12: -0.1 | CT12: 0 | CV12: -5.1 | CW12: 0 | CZ12: 1.2 | DA12: 0 | DB12: -0.3 | DD12: 0 | DE12: 0.9 | DF12: 0.1 | DG12: -0.6 | DH12: 1.2 | DI12: 0.5 | DK12: 0 | DL12: 0 | DM12: -4.2 | DN12: -10.2 | DO12: 1.4 | DP12: 0.3 | DQ12: 1 | DR12: 1.3 | DS12: 0 | DT12: 0.3 | DU12: 0.5 | DV12: 0.5 | DX12: -3.8 | DY12: 0.4 | DZ12: 0 | EA12: -1.1 | EB12: 1.2 | EC12: 0.8 | ED12: 4 | EE12: 0 | EF12: -9 | EG12: -8.9 | EH12: 0 | EI12: 0 | EJ12: 1.2 | EK12: -0.2 | EL12: 1.6 | EM12: 0.2 | EN12: 0.2 | EO12: 0.2 | EQ12: 0 | ER12: 0 | ES12: 0 | ET12: -0.2 | EU12: 2.4 | EV12: 2 | EW12: 0 | EX12: 0 | EY12: 0.2 | EZ12: 1.4 | FA12: 4.2 | FB12: 16.3 | FC12: 9.1 | FF12: 2.9 | FH12: 1.8 | FI12: -126.2 | FK12: 2.60207 | FL12: 0 | FN12: 1.7 | FO12: 0 | FP12: 0.34953 | FQ12: -0.3 | FR12: 2 | FS12: 6.3516
A13: 05/06/2025 | B13: 01:30 | C13: 28.3 | D13: -14.3 | E13: 5.4 | H13: -26.1 | I13: 16 | M13: -20.9 | N13: -5.7 | O13: -15.1 | R13: 60.8 | S13: 0.1 | X13: -1 | Y13: 1.2 | AA13: -3.4 | AB13: 3.5 | AC13: 16.4 | AH13: -5 | AI13: -17.3 | AM13: -1.4 | AN13: 0 | AO13: 0 | AP13: 5 | AQ13: 1.7 | AR13: -1.5 | AS13: 1.8 | AT13: 1.9 | AU13: -8.7 | AV13: -23.9 | AW13: -45.7 | AX13: -3 | AY13: -1.4 | AZ13: 0.4 | BA13: -1.2 | BB13: -2.1 | BD13: 0 | BE13: -1.4 | BO13: -9 | BP13: -49.4 | BQ13: -51 | BR13: -3.3 | BS13: -28.1 | CB13: -0.3 | CC13: 18 | CD13: 11.9 | CE13: -2.4 | CF13: 5.1 | CG13: -2.1 | CK13: -9.5 | CL13: -8.9 | CM13: -33.1 | CS13: -0.3 | CT13: 0 | CV13: -5.3 | CW13: 0 | CZ13: 1.3 | DA13: 0 | DB13: -0.3 | DD13: 0 | DE13: 1 | DF13: 0.1 | DG13: 0 | DH13: 1.2 | DI13: 0.6 | DK13: 0 | DL13: 0 | DM13: -4.5 | DN13: -11.1 | DO13: 1.4 | DP13: 0.3 | DQ13: 1 | DR13: 1.3 | DS13: 0 | DT13: 0 | DU13: 0.5 | DV13: 0.5 | DX13: -3.9 | DY13: 0.5 | DZ13: -0.2 | EA13: -1.2 | EB13: 1.3 | EC13: 0.8 | ED13: 4 | EE13: 0 | EF13: -11 | EG13: -11 | EH13: 0 | EI13: 0 | EJ13: 1.2 | EK13: -0.2 | EL13: 1.7 | EM13: 0.2 | EN13: 0.2 | EO13: 0.2 | EQ13: 0 | ER13: 0 | ES13: 0 | ET13: -0.2 | EU13: 0.7 | EV13: 0 | EW13: 0 | EX13: 0 | EY13: 0.2 | EZ13: 1.3 | FA13: 4.1 | FB13: 15.6 | FC13: 8.3 | FF13: 2.5 | FH13: 2.2 | FI13: -213.7 | FK13: 2.3549 | FL13: 0 | FN13: 1.7 | FO13: 0 | FP13: 0.56596 | FQ13: -0.8 | FR13: 1.8 | FS13: 5.62086
A14: 05/06/2025 | B14: 02:00 | C14: 27.2 | D14: -12.6 | E14: 4.2 | H14: -24.5 | I14: 19.6 | M14: -23.2 | N14: -10 | O14: -16.6 | R14: 53 | S14: 0.1 | X14: -0.2 | Y14: 1 | AA14: -3.4 | AB14: 3.6 | AC14: 17.1 | AH14: -5.3 | AI14: -16.6 | AM14: -0.7 | AN14: 0 | AO14: 2.5 | AP14: 6.3 | AQ14: 1.4 | AR14: -1.5 | AS14: 1.8 | AT14: 1.6 | AU14: -8.3 | AV14: -26.2 | AW14: -47.4 | AX14: -4.4 | AY14: -1.4 | AZ14: 0.4 | BA14: 0.1 | BB14: -0.2 | BD14: 0.1 | BE14: 1.6 | BO14: -3.9 | BP14: -50.4 | BQ14: -52 | BR14: -3.9 | BS14: -29.6 | CB14: -0.2 | CC14: 16.4 | CD14: 13 | CE14: -1.6 | CF14: 4.8 | CG14: -2 | CK14: -10.6 | CL14: -9.9 | CM14: -35.3 | CS14: -5.7 | CT14: 0 | CV14: -5.4 | CW14: 0 | CZ14: 1.3 | DA14: 0 | DB14: -0.3 | DD14: 0 | DE14: 1.1 | DF14: -0.3 | DG14: -0.6 | DH14: 1.2 | DI14: 0.6 | DK14: 0 | DL14: 0 | DM14: -4.7 | DN14: -12 | DO14: 1.4 | DP14: 0.3 | DQ14: 1 | DR14: 1.3 | DS14: 0 | DT14: 0 | DU14: 0.5 | DV14: 0.5 | DX14: -3.9 | DY14: 0.2 | DZ14: -0.3 | EA14: -1.1 | EB14: 1.3 | EC14: 0.8 | ED14: 4 | EE14: 0 | EF14: -12.2 | EG14: -12.5 | EH14: 0 | EI14: 0 | EJ14: 1.2 | EK14: -0.2 | EL14: 1.7 | EM14: 0.2 | EN14: 0.2 | EO14: 0.2 | EQ14: 0 | ER14: 0 | ES14: 0 | ET14: -0.2 | EU14: 0.5 | EV14: 0 | EW14: 0 | EX14: 0 | EY14: 0.2 | EZ14: 1.2 | FA14: 4.2 | FB14: 15.1 | FC14: 7.8 | FF14: 1.8 | FH14: 2 | FI14: -233.7 | FK14: 3.21392 | FL14: 0 | FN14: 1.6 | FO14: 0 | FP14: 3.88975 | FQ14: -1.2 | FR14: 1.9 | FS14: 9.40367
A15: 05/06/2025 | B15: 02:30 | C15: 28.4 | D15: -8.1 | E15: 5.9 | H15: -26.7 | I15: 16.4 | M15: -22.1 | N15: -6.3 | O15: -13 | R15: 61.7 | S15: 0 | X15: -0.8 | Y15: 0.8 | AA15: -3.3 | AB15: 3.6 | AC15: 17.5 | AH15: -5.6 | AI15: -18 | AM15: -0.8 | AN15: 0 | AO15: 3 | AP15: 5.1 | AQ15: 1.6 | AR15: -1.3 | AS15: 1.8 | AT15: 1.8 | AU15: -9.2 | AV15: -25 | AW15: -46.9 | AX15: -0.5 | AY15: -1.4 | AZ15: 0.4 | BA15: -0.5 | BB15: -1.8 | BD15: 0.1 | BE15: -2.1 | BO15: -2.4 | BP15: -49.3 | BQ15: -50.8 | BR15: -3.2 | BS15: -27.9 | CB15: -0.3 | CC15: 17.9 | CD15: 12.3 | CE15: -2.2 | CF15: 4.9 | CG15: -2 | CK15: -10.6 | CL15: -9.8 | CM15: -34.7 | CS15: -9.3 | CT15: 0 | CV15: -5.4 | CW15: 0 | CZ15: 1.3 | DA15: 0 | DB15: -0.3 | DD15: 0 | DE15: 1.1 | DF15: 0.1 | DG15: -0.4 | DH15: 1.2 | DI15: 0.6 | DK15: 0 | DL15: 0 | DM15: -4.1 | DN15: -10.3 | DO15: 1.4 | DP15: 0.3 | DQ15: 1 | DR15: 1.3 | DS15: 0 | DT15: 0.3 | DU15: 0.5 | DV15: 0.5 | DX15: -3.9 | DY15: 0.4 | DZ15: -0.3 | EA15: -1.2 | EB15: 1.3 | EC15: 0.8 | ED15: 4 | EE15: 0 | EF15: -9.7 | EG15: -9.3 | EH15: 0 | EI15: 0 | EJ15: 1.2 | EK15: -0.2 | EL15: 1.7 | EM15: 0.2 | EN15: 0.2 | EO15: 0.2 | EQ15: 0 | ER15: 0 | ES15: 0 | ET15: -0.2 | EU15: 0 | EV15: 0 | EW15: 0 | EX15: 0 | EY15: 0.2 | EZ15: 1.2 | FA15: 4.1 | FB15: 14.6 | FC15: 7.3 | FF15: 2.1 | FH15: 1.7 | FI15: -207.2 | FK15: 3.22575 | FL15: 0 | FN15: 1.8 | FO15: 0 | FP15: 3.90101 | FQ15: -0.8 | FR15: 2.1 | FS15: 10.22676
A16: 05/06/2025 | B16: 03:00 | C16: 27.8 | D16: -7.1 | E16: 4.9 | H16: -26.3 | I16: 26.4 | M16: -22.6 | N16: -7.8 | O16: -10 | R16: 62.1 | S16: -0.1 | X16: -0.4 | Y16: 1.3 | AA16: -3.3 | AB16: 3.6 | AC16: 17.7 | AH16: -6 | AI16: -17.6 | AM16: -0.8 | AN16: 0 | AO16: 2.9 | AP16: 5.8 | AQ16: 1.8 | AR16: -1.7 | AS16: 1.8 | AT16: 0.7 | AU16: -7.7 | AV16: -24.2 | AW16: -45.8 | AX16: -0.1 | AY16: -1.4 | AZ16: 0.4 | BA16: -1.8 | BB16: -1.2 | BD16: 0.1 | BE16: -2.5 | BO16: -2.2 | BP16: -48.4 | BQ16: -49.9 | BR16: -2.1 | BS16: -28.8 | CB16: -0.3 | CC16: 17 | CD16: 14 | CE16: -1.3 | CF16: 4.9 | CG16: -1.9 | CK16: -9.2 | CL16: -8.6 | CM16: -33.1 | CS16: -9.9 | CT16: 0 | CV16: -5.5 | CW16: 0 | CZ16: 1.3 | DA16: 0 | DB16: -0.3 | DD16: 0 | DE16: 1.1 | DF16: 0.1 | DG16: -0.6 | DH16: 1.2 | DI16: 0.5 | DK16: 0 | DL16: 0 | DM16: -4.3 | DN16: -11.1 | DO16: 1.4 | DP16: 0.3 | DQ16: 1 | DR16: 1.3 | DS16: 0 | DT16: 0.2 | DU16: 0.5 | DV16: 0.5 | DX16: -4.1 | DY16: 0.3 | DZ16: -0.3 | EA16: -1.1 | EB16: 1.1 | EC16: 0.8 | ED16: 4 | EE16: 0 | EF16: -9.6 | EG16: -9.7 | EH16: 0 | EI16: 0 | EJ16: 1.2 | EK16: -0.2 | EL16: 1.8 | EM16: 0.2 | EN16: 0.2 | EO16: 0.2 | EQ16: 0 | ER16: 0 | ES16: 0 | ET16: -0.2 | EU16: 4.7 | EV16: 0 | EW16: 0 | EX16: 0 | EY16: 0.2 | EZ16: 1.2 | FA16: 4 | FB16: 15.3 | FC16: 7.9 | FF16: 3 | FH16: 2.1 | FI16: -180.3 | FK16: 3.14212 | FL16: 0 | FN16: 1.7 | FO16: 0 | FP16: 3.90168 | FQ16: -1 | FR16: 1.9 | FS16: 9.6438
A17: 05/06/2025 | B17: 03:30 | C17: 27.6 | D17: -13 | E17: 4.7 | H17: -21.7 | I17: 31.6 | M17: -22.4 | N17: -3 | O17: -15.6 | R17: 57.9 | S17: 0 | X17: -0.6 | Y17: 1.2 | AA17: -3.3 | AB17: 3.5 | AC17: 17.4 | AH17: -5.3 | AI17: -13.2 | AM17: -0.7 | AN17: 0 | AO17: 2.8 | AP17: 5.2 | AQ17: 1.6 | AR17: -1.4 | AS17: 1.8 | AT17: 0.5 | AU17: -7.5 | AV17: -24.3 | AW17: -46.2 | AX17: -0.5 | AY17: -1.3 | AZ17: 0.6 | BA17: 0.3 | BB17: -1.1 | BD17: 0.1 | BE17: -1.9 | BO17: -2.8 | BP17: -49.6 | BQ17: -51 | BR17: -3.4 | BS17: -29.1 | CB17: -0.3 | CC17: 17.5 | CD17: 12.2 | CE17: -2.3 | CF17: 5 | CG17: -2.1 | CK17: -10.3 | CL17: -9.5 | CM17: -34.2 | CS17: -9.4 | CT17: 0 | CV17: -5.5 | CW17: 0 | CZ17: 1.3 | DA17: 0 | DB17: -0.3 | DD17: 0 | DE17: 1.1 | DF17: 0.1 | DG17: -0.6 | DH17: 1.3 | DI17: 0.5 | DK17: 0 | DL17: 0 | DM17: -4.7 | DN17: -12.1 | DO17: 1.4 | DP17: 0.3 | DQ17: 1 | DR17: 1.3 | DS17: 0 | DT17: 0.3 | DU17: 0.4 | DV17: 0.5 | DX17: -3.5 | DY17: 0.3 | DZ17: -0.4 | EA17: -1.1 | EB17: 1.3 | EC17: 0.8 | ED17: 4 | EE17: 0 | EF17: -12.3 | EG17: -11.8 | EH17: 0 | EI17: 0 | EJ17: 1.2 | EK17: -0.2 | EL17: 1.8 | EM17: 0.2 | EN17: 0.2 | EO17: 0.2 | EQ17: 0 | ER17: 0 | ES17: 0 | ET17: -0.2 | EU17: 4.6 | EV17: 3.5 | EW17: 0 | EX17: 0 | EY17: 0.2 | EZ17: 1.2 | FA17: 3.2 | FB17: 10.7 | FC17: 3.5 | FF17: 2.5 | FH17: 1.8 | FI17: -197.5 | FK17: 3.14802 | FL17: 0 | FN17: 1.8 | FO17: 0 | FP17: 3.89037 | FQ17: -1.4 | FR17: 2.1 | FS17: 9.53839
A18: 05/06/2025 | B18: 04:00 | C18: 29 | D18: -0.6 | E18: 6.9 | H18: -20.8 | I18: 31.5 | M18: -21.7 | N18: -1.2 | O18: -13.2 | R18: 64.1 | S18: 0 | X18: 2.2 | Y18: 1.3 | AA18: -3.3 | AB18: 3.6 | AC18: 18.3 | AH18: -5.6 | AI18: -18.1 | AM18: -0.6 | AN18: -26.8 | AO18: 3.4 | AP18: 5.3 | AQ18: 1.7 | AR18: -1.7 | AS18: 1.8 | AT18: 0.9 | AU18: -6.7 | AV18: -23.4 | AW18: -45.3 | AX18: -0.5 | AY18: -1.2 | AZ18: 0.5 | BA18: -0.1 | BB18: -0.9 | BD18: 0.1 | BE18: -2 | BO18: -1.6 | BP18: -48.8 | BQ18: -50.2 | BR18: -2.4 | BS18: -28.8 | CB18: -0.2 | CC18: 17.4 | CD18: 12.6 | CE18: -2.3 | CF18: 4.9 | CG18: -2.1 | CK18: -9.4 | CL18: -8.7 | CM18: -33.3 | CS18: -9.4 | CT18: 0 | CV18: -5.5 | CW18: 0 | CZ18: 1.3 | DA18: 0 | DB18: 0 | DD18: 0 | DE18: 1 | DF18: 0.1 | DG18: 0.6 | DH18: 1.4 | DI18: 0.5 | DK18: 0 | DL18: 0 | DM18: -4.4 | DN18: -11 | DO18: 1.4 | DP18: 0.3 | DQ18: 1 | DR18: 1.3 | DS18: 0 | DT18: 0.2 | DU18: 0.5 | DV18: 0.5 | DX18: -3.5 | DY18: 0.4 | DZ18: -0.3 | EA18: -1.2 | EB18: 1.2 | EC18: 0.8 | ED18: 4 | EE18: 0 | EF18: -9.6 | EG18: -8.6 | EH18: 0 | EI18: 0 | EJ18: 1.2 | EK18: -0.2 | EL18: 1.9 | EM18: 0.2 | EN18: 0.2 | EO18: 0.2 | EQ18: 0 | ER18: 0 | ES18: 0 | ET18: -0.2 | EU18: 4.8 | EV18: 3.5 | EW18: 0 | EX18: 0 | EY18: 0.2 | EZ18: 1.4 | FA18: 4 | FB18: 10 | FC18: 2.8 | FF18: 2.2 | FH18: 2.1 | FI18: -178.7 | FK18: 3.17841 | FL18: 0 | FN18: 1.8 | FO18: 0 | FP18: 3.89034 | FQ18: -1.4 | FR18: 1.2 | FS18: 8.66875
A19: 05/06/2025 | B19: 04:30 | C19: 27.8 | D19: -15 | E19: 4.4 | H19: -21 | I19: 34.2 | M19: -25 | N19: -5.6 | O19: -16.9 | R19: 59.5 | S19: 0.1 | X19: -1.4 | Y19: 1.6 | AA19: -3.3 | AB19: 3.6 | AC19: 18.1 | AH19: -5.9 | AI19: -19.5 | AM19: -0.7 | AN19: -27.8 | AO19: 3.1 | AP19: 0 | AQ19: 1.9 | AR19: -1.6 | AS19: 1.8 | AT19: 1.4 | AU19: -8 | AV19: -24 | AW19: -45.6 | AX19: -1.6 | AY19: -1.1 | AZ19: 0.4 | BA19: -1.2 | BB19: -1.5 | BD19: 0.1 | BE19: -2.5 | BO19: -2.9 | BP19: -49.4 | BQ19: -50.9 | BR19: -3.3 | BS19: -28.4 | CB19: -0.3 | CC19: 17.2 | CD19: 12.9 | CE19: -2.1 | CF19: 4.8 | CG19: -2.2 | CK19: -11.8 | CL19: -10.9 | CM19: -36.7 | CS19: -7.1 | CT19: -8.1 | CV19: -5.5 | CW19: 0 | CZ19: 1.3 | DA19: 0 | DB19: 0 | DD19: 0 | DE19: 0.9 | DF19: 0 | DG19: 0.6 | DH19: 1.3 | DI19: 0.6 | DK19: 0 | DL19: 0 | DM19: -4.5 | DN19: -11.8 | DO19: 1.4 | DP19: 0.3 | DQ19: 1 | DR19: 1.3 | DS19: 0 | DT19: 0.1 | DU19: 0.5 | DV19: 0.5 | DX19: -3.5 | DY19: 0.3 | DZ19: -0.3 | EA19: -1.1 | EB19: 1.1 | EC19: 0.8 | ED19: 4 | EE19: 0 | EF19: -10.2 | EG19: -10.8 | EH19: 0 | EI19: 0 | EJ19: 1.2 | EK19: -0.2 | EL19: 1.9 | EM19: 0.2 | EN19: 0.2 | EO19: 0.2 | EQ19: 0 | ER19: 0 | ES19: 0 | ET19: -0.2 | EU19: 5 | EV19: 3.6 | EW19: 0 | EX19: 0 | EY19: 0.2 | EZ19: 1.4 | FA19: 3.2 | FB19: 10.1 | FC19: 2.9 | FF19: 1.6 | FH19: 1.9 | FI19: -248.9 | FK19: 3.12037 | FL19: 0 | FN19: 1.6 | FO19: 0 | FP19: 3.89187 | FQ19: -1.1 | FR19: 0.2 | FS19: 7.71224
A20: 05/06/2025 | B20: 05:00 | C20: 27.3 | D20: -3 | E20: 7.1 | H20: -20.5 | I20: 22.5 | M20: -19.4 | N20: -0.1 | O20: -9.8 | R20: 67.5 | S20: 0 | X20: 0.4 | Y20: 1.7 | AA20: -3.4 | AB20: 3.5 | AC20: 12.6 | AH20: -5.6 | AI20: -16.3 | AM20: -0.7 | AN20: -27.6 | AO20: 3 | AP20: 0 | AQ20: 1.9 | AR20: 0.6 | AS20: 1.8 | AT20: 2.1 | AU20: -3.4 | AV20: -19.1 | AW20: -41.1 | AX20: -0.9 | AY20: -1.1 | AZ20: 0.6 | BA20: 0.3 | BB20: -1.4 | BD20: 0.1 | BE20: -2 | BO20: -2.6 | BP20: -46.4 | BQ20: -47.8 | BR20: -0.1 | BS20: -27 | CB20: -0.3 | CC20: 17.4 | CD20: 12.3 | CE20: -2 | CF20: 4.9 | CG20: -2.1 | CK20: -12.7 | CL20: -12.4 | CM20: -33.4 | CS20: -7.6 | CT20: -11 | CV20: -5.6 | CW20: 0 | CZ20: 1.3 | DA20: 0 | DB20: 0 | DD20: 0 | DE20: 0.9 | DF20: 0.1 | DG20: 0.4 | DH20: 1.4 | DI20: 0.6 | DK20: 0 | DL20: 0 | DM20: -4 | DN20: -8.9 | DO20: 1.4 | DP20: 0.3 | DQ20: 1 | DR20: 1.3 | DS20: 0.2 | DT20: 0.3 | DU20: 0.5 | DV20: 0.5 | DX20: -3.4 | DY20: 0.5 | DZ20: -0.2 | EA20: -1.1 | EB20: 1.3 | EC20: 0.8 | ED20: 4 | EE20: 0.4 | EF20: -9.8 | EG20: -8.8 | EH20: 0 | EI20: 0 | EJ20: 1.2 | EK20: -0.2 | EL20: 1.7 | EM20: 0.2 | EN20: 0.2 | EO20: 0.2 | EQ20: 0 | ER20: 0 | ES20: 0 | ET20: -0.2 | EU20: 4.9 | EV20: 3.6 | EW20: 0 | EX20: 0 | EY20: 0.2 | EZ20: 1.4 | FA20: 4 | FB20: 12.8 | FC20: 5.5 | FF20: 3 | FH20: 2.1 | FI20: -177.2 | FK20: 3.11264 | FL20: 0 | FN20: 1.8 | FO20: 0 | FP20: 3.89539 | FQ20: -1 | FR20: 0.5 | FS20: 8.30803
A21: 05/06/2025 | B21: 05:30 | C21: 27.3 | D21: -4.3 | E21: 6.7 | H21: -21.4 | I21: 21.7 | M21: -20.7 | N21: -2 | O21: -7.8 | R21: 69.4 | S21: -0.1 | X21: 0.9 | Y21: 1.8 | AA21: -3.3 | AB21: 3.9 | AC21: 14 | AH21: -2.7 | AI21: -17.9 | AM21: -0.6 | AN21: -26.4 | AO21: 3.2 | AP21: 0 | AQ21: 2 | AR21: 1 | AS21: 1.8 | AT21: 0.8 | AU21: -0.8 | AV21: -15.8 | AW21: -42.4 | AX21: -1.5 | AY21: -1.1 | AZ21: 0.6 | BA21: -1.4 | BB21: -1.5 | BD21: 0.1 | BE21: -3.5 | BO21: -1.6 | BP21: -44.4 | BQ21: -45.8 | BR21: 0 | BS21: -24 | CB21: -0.4 | CC21: 18.4 | CD21: 12.3 | CE21: -2.3 | CF21: 7.6 | CG21: -2.2 | CK21: -9.1 | CL21: -8.7 | CM21: -28.1 | CS21: 0 | CT21: -6.8 | CV21: -5.6 | CW21: 0 | CZ21: 1.3 | DA21: 0 | DB21: 0 | DD21: 0 | DE21: 0.9 | DF21: 0.1 | DG21: 0.8 | DH21: 1.4 | DI21: 0.5 | DK21: 0 | DL21: 0 | DM21: -3.9 | DN21: -9.2 | DO21: 1.4 | DP21: 0.3 | DQ21: 1 | DR21: 1.3 | DS21: 0.2 | DT21: 0.3 | DU21: 0.5 | DV21: 0.5 | DX21: -3.4 | DY21: 0.3 | DZ21: 0 | EA21: -1.2 | EB21: 1.3 | EC21: 0.8 | ED21: 4 | EE21: 0.4 | EF21: -9.9 | EG21: -8.7 | EH21: 0 | EI21: 0 | EJ21: 1.2 | EK21: -0.2 | EL21: 1.7 | EM21: 0.2 | EN21: 0.2 | EO21: 0.2 | EQ21: 0 | ER21: 0 | ES21: 0 | ET21: -0.2 | EU21: 4.9 | EV21: 3.5 | EW21: 0 | EX21: 0 | EY21: 0.2 | EZ21: 1.4 | FA21: 4.2 | FB21: 14 | FC21: 6.6 | FF21: 3.9 | FH21: 2.1 | FI21: -135.8 | FK21: 3.22271 | FL21: 0 | FN21: 1.7 | FO21: 0 | FP21: 3.88377 | FQ21: -0.7 | FR21: 0.5 | FS21: 8.60648
A22: 05/06/2025 | B22: 06:00 | C22: 22.9 | D22: 5 | E22: 9.2 | H22: -20.8 | I22: 23.9 | M22: -5.3 | N22: 16.8 | O22: -2.4 | R22: 68.2 | S22: 0.2 | X22: 3.3 | Y22: 1.6 | AA22: -3.3 | AB22: 3.9 | AC22: 15.2 | AH22: -2.8 | AI22: -12.9 | AM22: -0.5 | AN22: -25.2 | AO22: 3.4 | AP22: 0 | AQ22: 1.5 | AR22: 1.2 | AS22: 1.8 | AT22: 1.3 | AU22: 6.3 | AV22: -10.7 | AW22: -37.8 | AX22: 0.1 | AY22: -1.1 | AZ22: 0.4 | BA22: -0.5 | BB22: -0.1 | BD22: 0.1 | BE22: 3.8 | BO22: -3.1 | BP22: -41.4 | BQ22: -42.8 | BR22: 0 | BS22: -19.8 | CB22: -0.3 | CC22: 29 | CD22: 11.7 | CE22: -2.7 | CF22: 6 | CG22: -2.1 | CK22: -5.1 | CL22: -4.7 | CM22: -21.8 | CS22: -4.7 | CT22: -8.9 | CV22: -5.5 | CW22: 0 | CZ22: 1.3 | DA22: 0 | DB22: 0 | DD22: 0 | DE22: 0.9 | DF22: 0.1 | DG22: 1 | DH22: 1.3 | DI22: 0.6 | DK22: 0 | DL22: 0 | DM22: -4 | DN22: -9.3 | DO22: 1.4 | DP22: 0.3 | DQ22: 1 | DR22: 1.3 | DS22: 0.4 | DT22: 0.4 | DU22: 0.4 | DV22: 0.5 | DX22: -3.5 | DY22: 0.3 | DZ22: 0.1 | EA22: -1 | EB22: 1.5 | EC22: 0.8 | ED22: 1.5 | EE22: 0.3 | EF22: -9 | EG22: -7.6 | EH22: 0 | EI22: 0 | EJ22: 1.2 | EK22: -0.2 | EL22: 1.7 | EM22: 0.2 | EN22: 0.2 | EO22: 0.2 | EQ22: 0 | ER22: 0 | ES22: 0 | ET22: -0.2 | EU22: 4.8 | EV22: 3.5 | EW22: 0 | EX22: 0 | EY22: 0.2 | EZ22: 1.4 | FA22: 3.2 | FB22: 14.5 | FC22: 7.1 | FF22: 3.2 | FH22: 2.1 | FI22: -25.4 | FK22: 3.2616 | FL22: 0 | FN22: 1.7 | FO22: 0 | FP22: 3.87807 | FQ22: -0.5 | FR22: 0.5 | FS22: 8.83967
... A58: 06/06/2025 | B58: 00:00 | C58: 16.7 | D58: -6.9 | E58: 6.3 | H58: -19.2 | I58: 19.8 | M58: -39.2 | N58: -7.6 | O58: 7.9 | R58: 58.1 | S58: 0 | X58: -4.5 | Y58: 2.1 | AA58: -3.4 | AB58: 3.4 | AC58: -3.3 | AH58: -3.6 | AI58: -8 | AM58: -0.6 | AN58: -23.4 | AO58: 1.1 | AP58: 13.1 | AQ58: 5.2 | AR58: 0.7 | AS58: 1.8 | AT58: 1.2 | AU58: 4.1 | AV58: -24.7 | AW58: -47.6 | AX58: -1 | AY58: -1.7 | AZ58: 0.3 | BA58: -3.2 | BB58: -6.7 | BD58: 0.1 | BE58: -20.2 | BO58: -5.9 | BP58: -40.9 | BQ58: -42.6 | BR58: 0 | BS58: -22.6 | CB58: -0.3 | CC58: 6.2 | CD58: 10.1 | CE58: 0.5 | CF58: -1.2 | CG58: 0.1 | CK58: -13.4 | CL58: -12.6 | CM58: -45.2 | CS58: -1.6 | CT58: -7.9 | CV58: -4.8 | CW58: 0 | CZ58: 1.1 | DA58: 0 | DB58: -0.8 | DD58: 0.1 | DE58: 0.7 | DF58: 0.1 | DG58: 1 | DH58: 1.2 | DI58: 0.6 | DK58: 0 | DL58: 0 | DM58: -4.9 | DN58: -12.6 | DO58: 1.7 | DP58: 0.3 | DQ58: 0.7 | DR58: 1.2 | DS58: 0 | DT58: -0.1 | DU58: 0.5 | DV58: 0.5 | DX58: -3.1 | DY58: 0.7 | DZ58: 0.1 | EA58: -0.7 | EB58: 1.1 | EC58: 0.8 | ED58: 4 | EE58: 0 | EF58: -7.2 | EG58: -7.5 | EH58: 0 | EI58: 0 | EJ58: 1.2 | EK58: -0.2 | EL58: 1.5 | EM58: 0.2 | EN58: 0.2 | EO58: 0.2 | EQ58: 0 | ER58: 0 | ES58: 0 | ET58: -0.2 | EU58: 6.8 | EV58: 1.9 | EW58: 0 | EX58: 0 | EY58: 0.2 | EZ58: 1.2 | FA58: 4 | FB58: 14.1 | FC58: 6.5 | FF58: 3.8 | FH58: 2.2 | FI58: -241.9 | FK58: 2.06272 | FL58: 0.102 | FN58: 1.7 | FO58: 3.30442 | FP58: 2.68002 | FQ58: -1 | FR58: 0.9 | FS58: 9.74916
A59: EJEC | C59: 561.2 | D59: 229.65 | E59: 233.55 | F59: 0 | G59: 0 | H59: -339.4 | I59: 637.25 | J59: 0 | K59: 0 | L59: 0 | M59: -226.75 | N59: 247.8 | O59: 257.4 | P59: 0 | Q59: 0 | R59: 1237.2 | S59: 0.7 | T59: 0 | U59: 0 | V59: 0 | W59: 0 | X59: -2.95 | Y59: 34.75 | Z59: 0 | AA59: -80.35 | AB59: 105.45 | AC59: 365.6 | AD59: 0 | AE59: 0 | AF59: 0 | AG59: 0 | AH59: 5.4 | AI59: -50.05 | AJ59: 0 | AK59: 0 | AL59: 0 | AM59: -15.8 | AN59: -190.5 | AO59: 75.5 | AP59: 333.5 | AQ59: 156.4 | AR59: -6.95 | AS59: 35.15 | AT59: 25.55 | AU59: 192.9 | AV59: -387.8 | AW59: -974.15 | AX59: 66.75 | AY59: -33.65 | AZ59: 8.85 | BA59: -4.8 | BB59: -75.95 | BC59: 0 | BD59: 3.8 | BE59: -56.3 | BF59: 0 | BG59: 0 | BH59: 0 | BI59: 0 | BJ59: 0 | BK59: 0 | BL59: 0 | BM59: 0 | BN59: 0 | BO59: 24.85 | BP59: -450.45 | BQ59: -465.75 | BR59: -20 | BS59: 309.3 | BT59: 0 | BU59: 0 | BV59: 0 | BW59: 0 | BX59: 0 | BY59: 0 | BZ59: 0 | CA59: 0 | CB59: -6 | CC59: 718.95 | CD59: 493.8 | CE59: 157.35 | CF59: 155.9 | CG59: -3.9 | CH59: 0 | CI59: 0 | CJ59: 0 | CK59: 555 | CL59: 580.35 | CM59: -366 | CN59: 0 | CO59: 0 | CP59: 0 | CQ59: 0 | CR59: 0 | CS59: -40.15 | CT59: -100.65 | CU59: 0 | CV59: -117.85 | CW59: 62.15 | CX59: 0 | CY59: 0 | CZ59: 28.85 | DA59: -0.5 | DB59: -16.15 | DC59: 0 | DD59: 0.05 | DE59: 23.55 | DF59: 2.45 | DG59: 11.35 | DH59: 30.8 | DI59: 13.9 | DJ59: 0 | DK59: -6.35 | DL59: -12.2 | DM59: -139.6 | DN59: -345.9 | DO59: 29.5 | DP59: 7.2 | DQ59: 21.5 | DR59: 30.2 | DS59: -13.6 | DT59: 1.5 | DU59: 11.75 | DV59: 13.15 | DW59: 0 | DX59: -77.55 | DY59: 7.7 | DZ59: 5.5 | EA59: 5.7 | EB59: 33.35 | EC59: 19.2 | ED59: 82.85 | EE59: 15.8 | EF59: -147.8 | EG59: -130.45 | EH59: 0.2 | EI59: 0.65 | EJ59: 28.6 | EK59: -4.8 | EL59: 41.4 | EM59: 4.8 | EN59: 4.8 | EO59: 4.8 | EP59: 0 | EQ59: 17.45 | ER59: 12.6 | ES59: -0.5 | ET59: -4.8 | EU59: 159.1 | EV59: 86.6 | EW59: 1.8 | EX59: 10.95 | EY59: 4.8 | EZ59: 36.6 | FA59: 88.1 | FB59: 316.25 | FC59: 139.05 | FD59: 0 | FE59: 0 | FF59: 52.1 | FG59: 0 | FH59: 51.25 | FI59: 4413.4 | FK59: 69.316325 | FL59: -9.6665 | FM59: 0 | FN59: 42.05 | FO59: 53.349445 | FP59: 77.363215 | FQ59: 8.25 | FR59: 26.25 | FS59: 266.91249

Sheet DEMANDA_AREAS
B3: jueves, 5 de Junio del 2025
B5: REPORTE DE LA DEMANDA POR ÁREAS Y SUBAREAS OPERATIVAS (MW)
B6: FECHA HORA | C6: DEMANDA | E6: AREA | H6: SUBAREAS
C7: INTERCAMBIOS INTERNACIONALES | D7: SEIN | E7: NORTE | F7: CENTRO | G7: SUR | H7: ELECTROANDES
B8: 00:30 | C8: 0 | D8: 6568.6 | E8: 965.323 | F8: 3825.2771 | G8: 1777.9999 | H8: 239.2498
B9: 01:00 | C9: 0 | D9: 6471.9 | E9: 987.6604 | F9: 3716.6339 | G9: 1767.6057 | H9: 240.462
B10: 01:30 | C10: 0 | D10: 6304.3 | E10: 922.4835 | F10: 3622.4859 | G10: 1759.3306 | H10: 244.754
B11: 02:00 | C11: 0 | D11: 6188 | E11: 933.8424 | F11: 3488.4883 | G11: 1765.6693 | H11: 242.8972
B12: 02:30 | C12: 0 | D12: 6273.6 | E12: 912.388 | F12: 3583.2103 | G12: 1778.0017 | H12: 244.863
B13: 03:00 | C13: 0 | D13: 6230.7 | E13: 928.2881 | F13: 3555.0651 | G13: 1747.3468 | H13: 240.3329
B14: 03:30 | C14: 0 | D14: 6131.9 | E14: 937.2543 | F14: 3440.9453 | G14: 1753.7004 | H14: 243.2123
B15: 04:00 | C15: 0 | D15: 6240 | E15: 943.5752 | F15: 3529.2928 | G15: 1767.132 | H15: 241.1758
B16: 04:30 | C16: 0 | D16: 6126.3 | E16: 948.0541 | F16: 3412.3283 | G16: 1765.9176 | H16: 237.252
B17: 05:00 | C17: 0 | D17: 6254.9 | E17: 930.1809 | F17: 3541.9016 | G17: 1782.8175 | H17: 237.3701
B18: 05:30 | C18: 0 | D18: 6400.3 | E18: 962.5039 | F18: 3634.2921 | G18: 1803.504 | H18: 227.8048
B19: 06:00 | C19: 0 | D19: 6525.7 | E19: 992.3606 | F19: 3724.8616 | G19: 1808.4778 | H19: 220.9811
... B59: ENERGÍA | C59: 0 | D59: 168143.1 | E59: 25814.507 | F59: 98810.32 | G59: 43518.273 | H59: 5395.0062
B61: LEYENDA:
D63: Potencia recibida del Ecuador
D64: Potencia entregada al Ecuador

Sheet DEMANDA_UL
B3: jueves, 5 de Junio del 2025
B5: POTENCIA DE LOS GRANDES USUARIOS LIBRES (MW)
B6: FECHA HORA | C6: GRANDES USUARIOS LIBRES DEL ÁREA NORTE | X6: GRANDES USUARIOS LIBRES DEL ÁREA CENTRO | BP6: GRANDES USUARIOS LIBRES DEL ÁREA SUR
C7: ARCA CONTINENTAL LINDLEY S.A. | D7: AUSTRAL GROUP S.A.A | E7: CEMENTOS PACASMAYO | F7: CONSORCIO MINERO HORIZONTE S.R.L. | G7: CORPORACIÓN PESQUERA INCA S.A.C. | H7: CREDITEX: CIA IND.TEXTIL CREDISA | I7: HIPERMERCADOS TOTTUS S.A | J7: INDUSTRIA TEXTIL PIURA | K7: MINERA BOROO MISQUICHILCA S.A. | L7: MINERA GOLD FIELDS | M7: MINERA MARSA | N7: MINERA MISKY MAYO | O7: MINERA YANACOCHA | P7: OPEN PLAZA | Q7: PESQUERA DIAMANTE | R7: PETROPERU | S7: REAL PLAZA S.R.L. | T7: SIDER PERU | U7: SUPERMERCADOS PERUANOS S.A. | V7: TRUPAL S.A. | W7: UNIÓN DE CERVECERÍAS PERUANAS BACKUS Y JOHNSTON S. | X7: ACEROS AREQUIPA | Y7: ADMINISTRADORA JOCKEY PLAZA SHOPPING CENTER S.A. | Z7: ALICORP | AA7: ARCA CONTINENTAL LINDLEY S.A. | AB7: AUSTRAL GROUP S.A.A | AC7: COMPAÑIA MINERA CONDESTABLE | AD7: CORPORACIÓN PESQUERA INCA S.A.C. | AE7: CREDITEX: CIA IND.TEXTIL CREDISA | AF7: FUNDICION CHILCA S.A. | AG7: HIPERMERCADOS TOTTUS S.A | AH7: INMOBILIARIA KANPU S.A. | AI7: INMUEBLES PANAMERICANA S.A. | AJ7: KIMBERLY-CLARK PERU | AK7: LECHE GLORIA S.A. | AL7: MALL AVENTURA S.A. | AM7: MARCOBRE S.A.C. | AN7: MINERA ANTAMINA | AO7: MINERA ARES | AP7: MINERA BUENAVENTURA | AQ7: MINERA CHINALCO PERÚ S.A. | AR7: MINERA SHOUXIN PERU S.A. | AS7: MINERA VOLCAN | AT7: MINSUR | AU7: MOLYCOP-ADESUR | AV7: NEXA RESOURCES CAJAMARQUILLA S.A. | AW7: NEXA RESOURCES PERÚ S.A.A. | AX7: OPEN PLAZA | AY7: OPP FILM | AZ7: OWENS-ILLINOIS PERÚ S.A. | BA7: PAPELERA NACIONAL S.A. | BB7: PESQUERA DIAMANTE | BC7: QUIMPAC S.A. | BD7: REAL PLAZA S.R.L. | BE7: REFINERIA LA PAMPILLA S.A.A | BF7: SAGA FALABELLA | BG7: SAN MIGUEL INDUSTRIAS PET S.A. | BH7: SHOUGANG HIERRO PERU | BI7: SOFTYS PERU S.A.C. | BJ7: SUPERMERCADOS PERUANOS S.A. | BK7: TEJIDOS SAN JACINTO | BL7: TREN URBANO DE LIMA S.A. | BM7: TRUPAL S.A. | BN7: UNACEM PERU S.A. | BO7: UNIÓN DE CERVECERÍAS PERUANAS BACKUS Y JOHNSTON S. | BP7: ANGLO AMERICAN QUELLAVECO S.A. | BQ7: ARCA CONTINENTAL LINDLEY S.A. | BR7: CAL & CEMENTO SUR S.A. | BS7: COMPAÑIA MINERA ANTAPACCAY S.A. | BT7: COMPAÑÍA MINERA CHUNGAR SAC | BU7: COMPAÑIA MINERA SAN IGNACIO DE MOROCOCHA S.A.A. | BV7: EL BROCAL .S.A. | BW7: EMPRESA ADMINISTRADORA CERRO S.A.C. | BX7: EMPRESA MINERA LOS QUENUALES S.A.C. | BY7: HIPERMERCADOS TOTTUS S.A | BZ7: HUDBAY PERU S.A.C. | CA7: INDUSTRIA CACHIMAYO | CB7: MALL AVENTURA S.A. | CC7: MINERA ARES | CD7: MINERA BUENAVENTURA | CE7: MINERA CERRO VERDE | CF7: MINERA CORONA | CG7: MINERA LAS BAMBAS S.A. | CH7: MINERA VOLCAN | CI7: MINSUR | CJ7: MOLYCOP-ADESUR | CK7: NEXA RESOURCES PERÚ S.A.A. | CL7: OXIDOS DE PASCO S.A.C. | CM7: PESQUERA DIAMANTE | CN7: REAL PLAZA S.R.L. | CO7: SOBREANDES S.A.C. | CP7: SOUTHERN PERU CC | CQ7: SUPERMERCADOS PERUANOS S.A. | CR7: UNACEM PERU S.A. | CS7: UNIÓN DE CERVECERÍAS PERUANAS BACKUS Y JOHNSTON S. | CT7: YURA
B8: 00:30 | E8: 44.59327 | F8: 13.116 | K8: 19.9172 | L8: 26.0047 | M8: 13.2839 | N8: 7.98 | O8: 29.654 | R8: 42.66 | T8: 41.3484 | V8: 9.5 | X8: 133.372 | Z8: 8.12894 | AC8: 14.94 | AF8: 3.1 | AH8: 5.0112 | AJ8: 5.33786 | AK8: 0 | AL8: 1.1119 | AM8: 46.85773 | AN8: 118.29779 | AO8: 28.2331 | AP8: 0.81 | AQ8: 157.94 | AR8: 16.67765 | AS8: 37.74358 | AT8: 32.24042 | AV8: 160.39212 | AW8: 29.78464 | BA8: 2.8 | BC8: 73.81262 | BE8: 18.9 | BH8: 9.28925 | BK8: 5.70972 | BM8: 6.998 | BN8: 53.74 | BO8: 1.95 | BP8: 114.24621 | BR8: 2.75829 | BS8: 134.22695 | BT8: 12.8056 | BV8: 32.9539 | BW8: 3.85819 | BZ8: 83.09173 | CA8: 25.10325 | CB8: 0.3161 | CC8: 0.604 | CD8: 23.6911 | CE8: 445.54309 | CF8: 11.5442 | CG8: 158.9952 | CH8: 18.33561 | CK8: 15.8753 | CL8: 5.01655 | CP8: 291.49 | CR8: 39.709 | CT8: 25.19
B9: 01:00 | E9: 43.63264 | F9: 12.888 | K9: 20.2126 | L9: 26.4222 | M9: 13.0571 | N9: 9.88 | O9: 29.14 | R9: 42.598 | T9: 45.5938 | V9: 9.6 | X9: 113.593 | Z9: 8.16426 | AC9: 14.88 | AF9: 2.8 | AH9: 4.2975 | AJ9: 5.33431 | AK9: 0 | AL9: 0.9939 | AM9: 47.33287 | AN9: 118.32087 | AO9: 28.2489 | AP9: 0.7 | AQ9: 158.69 | AR9: 16.9116 | AS9: 37.67398 | AT9: 33.00861 | AV9: 159.18897 | AW9: 29.27895 | AY9: 3.37339 | BA9: 2.7 | BC9: 73.40654 | BE9: 18.9 | BH9: 10.51035 | BK9: 5.87569 | BM9: 6.897 | BN9: 53.5 | BO9: 2.02 | BP9: 114.35218 | BR9: 2.72426 | BS9: 133.09034 | BT9: 13.10152 | BV9: 32.1773 | BW9: 3.96348 | BZ9: 90.06234 | CA9: 25.09916 | CB9: 0.3068 | CC9: 0.577 | CD9: 23.41295 | CE9: 452.75677 | CF9: 11.6113 | CG9: 155.0627 | CH9: 18.09762 | CK9: 15.2529 | CL9: 4.7882 | CP9: 293.09 | CR9: 40.327 | CT9: 24.09
B10: 01:30 | E10: 44.03645 | F10: 13.141 | K10: 20.4714 | L10: 26.3507 | M10: 13.8912 | N10: 10.02 | O10: 29.182 | R10: 42.742 | T10: 39.7784 | V10: 9.7 | X10: 93.937 | Z10: 8.16758 | AC10: 15.16 | AF10: 5 | AH10: 6.1698 | AJ10: 5.31128 | AK10: 0 | AL10: 0.908 | AM10: 46.29351 | AN10: 117.05898 | AO10: 28.7337 | AP10: 0.64 | AQ10: 157.66 | AR10: 16.99108 | AS10: 37.89261 | AT10: 32.87711 | AV10: 161.30603 | AW10: 29.04708 | AY10: 3.28359 | BA10: 2.7 | BC10: 72.65607 | BE10: 18.9 | BH10: 8.98509 | BK10: 5.9344 | BM10: 6.987 | BN10: 56.06 | BO10: 2.1 | BP10: 116.21643 | BR10: 2.86618 | BS10: 131.85493 | BT10: 13.102 | BV10: 32.27 | BW10: 4.0073 | BZ10: 89.96047 | CA10: 25.1238 | CB10: 0.2987 | CC10: 0.582 | CD10: 23.94493 | CE10: 451.75066 | CF10: 11.819 | CG10: 162.555 | CH10: 18.98365 | CK10: 15.2292 | CL10: 4.72071 | CP10: 289.08 | CR10: 40.023 | CT10: 28.096
B11: 02:00 | E11: 43.89984 | F11: 13.102 | K11: 19.9737 | L11: 26.2134 | M11: 14.0266 | N11: 10.02 | O11: 30.154 | R11: 43.586 | T11: 43.6565 | V11: 9.8 | X11: 155.859 | Z11: 8.34997 | AC11: 15.78 | AF11: 7.1 | AH11: 5.7533 | AJ11: 5.27359 | AK11: 0 | AL11: 0.874 | AM11: 47.28083 | AN11: 117.70643 | AO11: 28.8574 | AP11: 0.44 | AQ11: 159.17 | AR11: 17.20122 | AS11: 37.80248 | AT11: 32.70728 | AV11: 163.45938 | AW11: 29.79843 | AY11: 3.33065 | BA11: 2.7 | BC11: 72.70812 | BE11: 18.9 | BH11: 9.54533 | BK11: 5.86001 | BM11: 6.698 | BN11: 54.51 | BO11: 2.09 | BP11: 113.87312 | BR11: 2.8244 | BS11: 134.00895 | BT11: 13.23951 | BV11: 32.1118 | BW11: 3.7307 | BZ11: 88.73587 | CA11: 25.14352 | CB11: 0.2942 | CC11: 0.604 | CD11: 24.18548 | CE11: 452.57434 | CF11: 11.7273 | CG11: 162.9997 | CH11: 18.79079 | CK11: 15.8741 | CL11: 4.70029 | CP11: 282.15 | CR11: 40.109 | CT11: 28.796
B12: 02:30 | E12: 44.01656 | F12: 13.395 | K12: 19.4518 | L12: 26.1173 | M12: 14.4538 | N12: 10.53 | O12: 30.036 | R12: 43.153 | T12: 39.2424 | V12: 9.8 | X12: 146.095 | Z12: 8.43628 | AC12: 15.54 | AF12: 3.6 | AH12: 3.5625 | AJ12: 5.22184 | AK12: 0 | AL12: 0.8678 | AM12: 46.09134 | AN12: 115.93375 | AO12: 28.4141 | AP12: 0.41 | AQ12: 157.39 | AR12: 17.24171 | AS12: 38.10923 | AT12: 32.69279 | AV12: 163.22427 | AW12: 29.46619 | AY12: 3.35841 | BA12: 2.7 | BC12: 72.474 | BE12: 18.9 | BH12: 11.13165 | BK12: 5.8269 | BM12: 7.121 | BN12: 56.76 | BO12: 2.16 | BP12: 112.20673 | BR12: 2.74761 | BS12: 133.42524 | BT12: 13.58717 | BV12: 30.7745 | BW12: 3.87202 | BZ12: 87.79321 | CA12: 25.20154 | CB12: 0.2904 | CC12: 0.549 | CD12: 24.45755 | CE12: 455.8938 | CF12: 12.0038 | CG12: 158.2293 | CH12: 19.06778 | CK12: 16.3145 | CL12: 4.79327 | CP12: 281 | CR12: 40.049 | CT12: 27.857
B13: 03:00 | E13: 44.02437 | F13: 13.251 | K13: 19.2433 | L13: 26.2801 | M13: 15.0366 | N13: 10.83 | O13: 30.304 | R13: 43.234 | T13: 35.7687 | V13: 9.7 | X13: 137.722 | Z13: 8.67004 | AC13: 15.78 | AF13: 4.1 | AH13: 3.1256 | AJ13: 4.81592 | AK13: 0 | AL13: 0.8247 | AM13: 47.18457 | AN13: 116.19343 | AO13: 28.0314 | AP13: 0.67 | AQ13: 159.46 | AR13: 17.1943 | AS13: 38.79956 | AT13: 32.69838 | AV13: 163.17273 | AW13: 30.51627 | AY13: 3.31291 | BA13: 2.8 | BC13: 72.60927 | BE13: 18.9 | BH13: 10.43612 | BK13: 5.59735 | BM13: 7.321 | BN13: 56.9 | BO13: 2.06 | BP13: 113.28631 | BR13: 2.7037 | BS13: 132.40413 | BT13: 12.98972 | BV13: 30.5534 | BW13: 3.96593 | BZ13: 89.59326 | CA13: 25.18732 | CB13: 0.2943 | CC13: 0.603 | CD13: 23.9042 | CE13: 453.27433 | CF13: 12.1378 | CG13: 160.4362 | CH13: 18.97994 | CK13: 16.0127 | CL13: 4.72044 | CP13: 289.51 | CR13: 39.588 | CT13: 27.063
B14: 03:30 | E14: 44.23271 | F14: 13.329 | K14: 19.3695 | L14: 26.5039 | M14: 14.6819 | N14: 11.15 | O14: 29.684 | R14: 43.201 | T14: 35.2961 | V14: 9.6 | X14: 113.051 | Z14: 8.79984 | AC14: 15.63 | AF14: 4.9 | AH14: 6.3759 | AJ14: 5.05719 | AK14: 0 | AL14: 0.8047 | AM14: 45.82639 | AN14: 117.49044 | AO14: 28.4829 | AP14: 0.48 | AQ14: 157.42 | AR14: 16.98134 | AS14: 37.6582 | AT14: 33.05489 | AV14: 162.75343 | AW14: 31.56866 | AY14: 3.28072 | BA14: 2.7 | BC14: 72.62828 | BE14: 18.9 | BH14: 9.5608 | BK14: 5.75422 | BM14: 6.879 | BN14: 56.77 | BO14: 2.06 | BP14: 113.57328 | BR14: 2.76208 | BS14: 135.60706 | BT14: 13.10846 | BV14: 31.756 | BW14: 4.02736 | BZ14: 89.69316 | CA14: 25.2414 | CB14: 0.3017 | CC14: 0.581 | CD14: 23.40391 | CE14: 452.9948 | CF14: 12.227 | CG14: 154.5405 | CH14: 18.82794 | CK14: 15.9771 | CL14: 4.72373 | CP14: 288.71 | CR14: 39.354 | CT14: 27.563
B15: 04:00 | E15: 43.27841 | F15: 13.273 | K15: 19.2568 | L15: 26.667 | M15: 14.4858 | N15: 11.18 | O15: 29.608 | R15: 43.185 | T15: 42.3959 | V15: 9.8 | X15: 115.378 | Z15: 8.90102 | AC15: 15.46 | AF15: 4.8 | AH15: 6.3753 | AJ15: 5.19055 | AK15: 0 | AL15: 0.7893 | AM15: 45.83497 | AN15: 117.52725 | AO15: 27.9132 | AP15: 0.18 | AQ15: 157.15 | AR15: 16.79446 | AS15: 37.40041 | AT15: 31.87714 | AV15: 160.83201 | AW15: 31.4471 | AY15: 3.31128 | BA15: 2.8 | BC15: 72.56512 | BE15: 18.9 | BH15: 10.62817 | BK15: 5.73935 | BM15: 6.998 | BN15: 55.17 | BO15: 1.96 | BP15: 113.46036 | BR15: 2.7958 | BS15: 135.93836 | BT15: 12.68923 | BV15: 32.2904 | BW15: 3.88656 | BZ15: 87.30002 | CA15: 25.26453 | CB15: 0.2935 | CC15: 0.596 | CD15: 23.27933 | CE15: 455.84273 | CF15: 11.9716 | CG15: 159.5035 | CH15: 18.70077 | CK15: 15.3444 | CL15: 4.84273 | CP15: 292.19 | CR15: 39.298 | CT15: 27.701
B16: 04:30 | E16: 43.91326 | F16: 12.493 | K16: 19.2141 | L16: 26.6475 | M16: 15.6976 | N16: 11.19 | O16: 29.812 | R16: 43.421 | T16: 41.2345 | V16: 9.7 | X16: 138.676 | Z16: 8.94519 | AC16: 14.98 | AF16: 5.9 | AH16: 3.2337 | AJ16: 5.28152 | AK16: 0 | AL16: 0.7716 | AM16: 47.1685 | AN16: 118.03308 | AO16: 28.4752 | AP16: 1.65 | AQ16: 157.66 | AR16: 17.35176 | AS16: 37.11325 | AT16: 31.70346 | AV16: 124.45958 | AW16: 34.1648 | AY16: 3.30818 | BA16: 2.8 | BC16: 72.60195 | BE16: 18.9 | BH16: 10.9653 | BK16: 5.83262 | BM16: 6.897 | BN16: 56.9 | BO16: 1.78 | BP16: 113.47562 | BR16: 2.8617 | BS16: 135.39293 | BT16: 12.51349 | BV16: 32.7799 | BW16: 3.90366 | BZ16: 87.06171 | CA16: 25.26403 | CB16: 0.2886 | CC16: 0.599 | CD16: 22.85062 | CE16: 455.46291 | CF16: 11.9942 | CG16: 155.2108 | CH16: 19.01271 | CK16: 15.1519 | CL16: 5.12456 | CP16: 295.87 | CR16: 39.442 | CT16: 28.022
B17: 05:00 | E17: 43.58894 | F17: 12.555 | K17: 19.3878 | L17: 26.6634 | M17: 16.6784 | N17: 11.11 | O17: 29.496 | R17: 43.056 | T17: 39.6698 | V17: 9.8 | X17: 145.952 | Z17: 8.76645 | AC17: 15.08 | AF17: 3.6 | AH17: 2.1013 | AJ17: 5.03627 | AK17: 0 | AL17: 0.7581 | AM17: 48.41834 | AN17: 116.62685 | AO17: 27.8154 | AP17: 2.1 | AQ17: 154.29 | AR17: 16.00682 | AS17: 36.20154 | AT17: 31.17747 | AV17: 125.26296 | AW17: 33.77584 | AY17: 3.39361 | BA17: 2.8 | BC17: 72.46645 | BE17: 18.9 | BH17: 11.2781 | BK17: 5.83123 | BM17: 6.987 | BN17: 66.34 | BO17: 1.83 | BP17: 113.23469 | BR17: 2.92253 | BS17: 130.74047 | BT17: 12.2482 | BV17: 32.1454 | BW17: 4.37541 | BZ17: 87.19018 | CA17: 25.21562 | CB17: 0.27 | CC17: 0.593 | CD17: 22.46726 | CE17: 456.76702 | CF17: 11.6717 | CG17: 153.4645 | CH17: 18.88244 | CK17: 15.4 | CL17: 5.11881 | CP17: 297.63 | CR17: 39.781 | CT17: 27.192
B18: 05:30 | E18: 43.84617 | F18: 11.707 | K18: 19.4822 | L18: 26.7895 | M18: 15.4179 | N18: 9.75 | O18: 30.03 | R18: 43.226 | T18: 39.1051 | V18: 9.9 | X18: 139.488 | Z18: 8.46595 | AC18: 15.3 | AF18: 1.6 | AH18: 3.2369 | AJ18: 5.08865 | AK18: 0 | AL18: 0.7643 | AM18: 46.4625 | AN18: 115.24191 | AO18: 28.1621 | AP18: 1.93 | AQ18: 157.81 | AR18: 16.65132 | AS18: 36.73215 | AT18: 31.19108 | AV18: 121.1868 | AW18: 33.03378 | AY18: 3.38961 | BA18: 2.7 | BC18: 72.42554 | BE18: 18.9 | BH18: 10.2696 | BK18: 5.87754 | BM18: 6.698 | BN18: 65.66 | BO18: 1.76 | BP18: 112.96709 | BR18: 2.87448 | BS18: 132.82668 | BT18: 11.89132 | BV18: 31.0792 | BW18: 3.85894 | BZ18: 87.5232 | CA18: 25.17789 | CB18: 0.2742 | CC18: 0.56 | CD18: 21.90093 | CE18: 458.08908 | CF18: 11.572 | CG18: 151.3336 | CH18: 18.27719 | CK18: 14.6458 | CL18: 4.96352 | CP18: 298.48 | CR18: 39.728 | CT18: 27.248
B19: 06:00 | E19: 43.67937 | F19: 11.085 | K19: 19.0082 | L19: 26.678 | M19: 14.173 | N19: 9.45 | O19: 29.998 | R19: 42.866 | T19: 34.086 | V19: 9.9 | X19: 118.855 | Z19: 8.1026 | AC19: 15.88 | AF19: 0.9 | AH19: 2.7494 | AJ19: 5.10208 | AK19: 0 | AL19: 0.8991 | AM19: 47.59221 | AN19: 115.22003 | AO19: 27.4388 | AP19: 1.54 | AQ19: 153.89 | AR19: 16.67281 | AS19: 34.36719 | AT19: 31.43291 | AV19: 121.29941 | AW19: 31.79438 | AY19: 3.45636 | BA19: 2.9 | BC19: 72.37319 | BE19: 18.9 | BH19: 12.42764 | BK19: 5.89558 | BM19: 7.121 | BN19: 64.44 | BO19: 1.8 | BP19: 112.57426 | BR19: 2.75497 | BS19: 129.14489 | BT19: 11.18895 | BV19: 30.7434 | BW19: 3.65085 | BZ19: 87.95873 | CA19: 25.17739 | CB19: 0.2714 | CC19: 0.643 | CD19: 20.95623 | CE19: 457.71301 | CF19: 11.2524 | CG19: 152.7024 | CH19: 19.03996 | CK19: 14.4914 | CL19: 4.77102 | CP19: 295.36 | CR19: 39.876 | CT19: 30.482
B20: 06:30 | E20: 43.00743 | F20: 9.273 | K20: 19.171 | L20: 27.1618 | M20: 13.7448 | N20: 10.34 | O20: 29.316 | R20: 42.813 | T20: 33.5165 | V20: 9.5 | X20: 108.841 | Z20: 8.10129 | AC20: 16.03 | AF20: 0.9 | AH20: 4.5068 | AJ20: 5.06943 | AK20: 0 | AL20: 1.0731 | AM20: 47.27173 | AN20: 111.07008 | AO20: 26.6396 | AP20: 0.55 | AQ20: 151.9 | AR20: 16.61169 | AS20: 34.43479 | AT20: 32.24975 | AV20: 121.29087 | AW20: 31.10471 | AY20: 3.49345 | BA20: 3 | BC20: 71.8543 | BE20: 18.9 | BH20: 8.02263 | BK20: 5.82871 | BM20: 7.321 | BN20: 64.61 | BO20: 1.7 | BP20: 114.87384 | BR20: 2.71366 | BS20: 127.20115 | BT20: 11.56019 | BV20: 28.1473 | BW20: 3.60756 | BZ20: 87.81787 | CA20: 25.19119 | CB20: 0.3142 | CC20: 0.62 | CD20: 20.71701 | CE20: 429.93799 | CF20: 10.79 | CG20: 156.1243 | CH20: 18.52499 | CK20: 14.7051 | CL20: 4.65805 | CP20: 297.03 | CR20: 39.44 | CT20: 32.598
... B55: 00:00 | E55: 27.9019 | F55: 13.395 | K55: 20.129 | L55: 25.9542 | M55: 13.5944 | N55: 12.25 | O55: 29.402 | R55: 43.388 | T55: 24.7616 | V55: 9 | X55: 131.235 | Z55: 8.71098 | AC55: 14.59 | AF55: 2.2 | AH55: 2.9584 | AJ55: 5.27586 | AK55: 0 | AL55: 1.1631 | AM55: 44.18281 | AN55: 125.66972 | AO55: 27.7913 | AP55: 0.83 | AQ55: 155.95 | AR55: 17.04927 | AS55: 38.56161 | AT55: 30.16729 | AV55: 162.82293 | AW55: 35.59736 | AY55: 3.25538 | BA55: 4.8 | BC55: 65.15483 | BE55: 18.8 | BH55: 10.40142 | BK55: 5.8627 | BM55: 7.321 | BN55: 50.58 | BO55: 2.14 | BP55: 121.24877 | BR55: 2.69718 | BS55: 131.72259 | BT55: 12.75297 | BV55: 30.9507 | BW55: 3.83695 | BZ55: 88.14722 | CA55: 24.71691 | CB55: 0.3198 | CC55: 0.581 | CD55: 23.44958 | CE55: 432.07928 | CF55: 11.6085 | CG55: 154.9169 | CH55: 18.74816 | CK55: 17.1744 | CL55: 5.00302 | CP55: 290.79 | CR55: 26.949 | CT55: 24.528
B56: MWh | C56: 0 | D56: 0 | E56: 853.59452 | F56: 297.828 | G56: 0 | H56: 0 | I56: 0 | J56: 0 | K56: 465.83855 | L56: 639.69845 | M56: 315.9166 | N56: 264.03 | O56: 699.863 | P56: 0 | Q56: 0 | R56: 1012.5975 | S56: 0 | T56: 788.8863 | U56: 0 | V56: 218.95 | W56: 0 | X56: 2673.9435 | Y56: 0 | Z56: 205.93084 | AA56: 0 | AB56: 0 | AC56: 375.695 | AD56: 0 | AE56: 0 | AF56: 76.25 | AG56: 0 | AH56: 56.44775 | AI56: 0 | AJ56: 118.96792 | AK56: 0 | AL56: 69.77525 | AM56: 1119.094 | AN56: 2802.9444 | AO56: 665.53415 | AP56: 18.01 | AQ56: 3615.625 | AR56: 398.65089 | AS56: 870.5901 | AT56: 756.79098 | AU56: 0 | AV56: 3050.8541 | AW56: 784.55357 | AX56: 0 | AY56: 79.747745 | AZ56: 0 | BA56: 93.05 | BB56: 0 | BC56: 1475.918 | BD56: 0 | BE56: 453.45 | BF56: 0 | BG56: 0 | BH56: 254.85251 | BI56: 0 | BJ56: 0 | BK56: 137.91177 | BL56: 0 | BM56: 167.714 | BN56: 1158.83 | BO56: 46.115 | BP56: 2776.3175 | BQ56: 0 | BR56: 72.98836 | BS56: 3068.1506 | BT56: 288.8713 | BU56: 0 | BV56: 726.85625 | BW56: 93.448515 | BX56: 0 | BY56: 0 | BZ56: 2133.3483 | CA56: 482.72055 | CB56: 19.7974 | CC56: 14.2945 | CD56: 549.81845 | CE56: 10114.482 | CF56: 277.2302 | CG56: 3768.0833 | CH56: 430.98348 | CI56: 0 | CJ56: 0 | CK56: 368.98535 | CL56: 114.52788 | CM56: 0 | CN56: 0 | CO56: 0 | CP56: 6689.975 | CQ56: 0 | CR56: 820.9465 | CS56: 0 | CT56: 566.126
B59: Nota :
B60: Información proporcionada por la empresas
C62: DATOS ESTIMADOS
C64: SIN DATOS

Sheet TIPO_RECURSO
B3: jueves, 5 de Junio del 2025
B5: REPORTE POTENCIA GENERADA POR TIPO DE RECURSO
B6: HORA | C6: H. PASADA | D6: H. REGULACION | E6: GAS DE CAMISEA | F6: RESIDUAL | G6: NAFTA+GAS DE REFINERIA | H6: FLEXIGAS+GAS DE REFINERIA | I6: BAGAZO | J6: BIOGÁS | K6: SOLAR | L6: EÓLICA | M6: TOTAL | R6: EMPRESA | S6: CENTRAL | T6: HIDROELECTRICA DE PASADA | U6: HIDROELECTRICA DE REGULACION
B7: 00:30 | C7: 1052.5 | D7: 2584.4 | E7: 2448.7 | G7: =+DESPACHO_EJECUTADO!FC11+DESPACHO_EJECUTADO!FD11 -> 60.5 | I7: 31.6 | J7: 9.6 | K7: 0 | L7: 381.3 | M7: =+SUM(C7:L7) -> 6568.6 | R7: ANDEAN POWER S.A.C. | S7: C.H.CARHUAC | T7: 244.5
B8: 01:00 | C8: 1053.2 | D8: 2504 | E8: 2450.7 | G8: =+DESPACHO_EJECUTADO!FC12+DESPACHO_EJECUTADO!FD12 -> 60.3 | I8: 32.1 | J8: 9.6 | K8: 0 | L8: 362 | M8: =+SUM(C8:L8) -> 6471.9 | R8: ASOCIACIÓN SANTA LUCIA DE CHACAS | S8: C.H. HUALLIN | T8: 46.45
B9: 01:30 | C9: 1054.8 | D9: 2376.7 | E9: 2465.9 | G9: =+DESPACHO_EJECUTADO!FC13+DESPACHO_EJECUTADO!FD13 -> 60.4 | I9: 32.1 | J9: 9.6 | K9: 0 | L9: 304.8 | M9: =+SUM(C9:L9) -> 6304.3 | R9: CELEPSA | S9: C.H. EL PLATANAL | U9: 3591.4
B10: 02:00 | C10: 1039.6 | D10: 2282.7 | E10: 2472.2 | G10: =+DESPACHO_EJECUTADO!FC14+DESPACHO_EJECUTADO!FD14 -> 60.7 | I10: 32.2 | J10: 9.6 | K10: 0 | L10: 291 | M10: =+SUM(C10:L10) -> 6188 | R10: CELEPSA RENOVABLES S.R.L. | S10: C.H. MARAÑON | T10: 257.65
B11: 02:30 | C11: 1054.8 | D11: 2350.4 | E11: 2489.3 | G11: =+DESPACHO_EJECUTADO!FC15+DESPACHO_EJECUTADO!FD15 -> 60.7 | I11: 31 | J11: 9.6 | K11: 0 | L11: 277.8 | M11: =+SUM(C11:L11) -> 6273.6 | R11: CHINANGO S.A.C. | S11: C.H. CHIMAY | U11: 1810.7
B12: 03:00 | C12: 1050.9 | D12: 2398.3 | E12: 2487.5 | G12: =+DESPACHO_EJECUTADO!FC16+DESPACHO_EJECUTADO!FD16 -> 60.8 | I12: 31.3 | J12: 9.6 | K12: 0 | L12: 192.3 | M12: =+SUM(C12:L12) -> 6230.7 | S12: C.H. YANANGO | T12: 644.75
B13: 03:30 | C13: 1046.2 | D13: 2317.5 | E13: 2486.1 | G13: =+DESPACHO_EJECUTADO!FC17+DESPACHO_EJECUTADO!FD17 -> 60.9 | I13: 31.7 | J13: 9.6 | K13: 0 | L13: 179.9 | M13: =+SUM(C13:L13) -> 6131.9 | R13: EGASA | S13: C.H. CHARCANI III | T13: 163.65
B14: 04:00 | C14: 1055.6 | D14: 2451 | E14: 2490.9 | G14: =+DESPACHO_EJECUTADO!FC18+DESPACHO_EJECUTADO!FD18 -> 60.8 | I14: 31.3 | J14: 9.6 | K14: 0 | L14: 140.8 | M14: =+SUM(C14:L14) -> 6240 | S14: C.H. CHARCANI IV | U14: 310.5
B15: 04:30 | C15: 1040 | D15: 2291.4 | E15: 2567.8 | G15: =+DESPACHO_EJECUTADO!FC19+DESPACHO_EJECUTADO!FD19 -> 60.9 | I15: 31.9 | J15: 9.6 | K15: 0 | L15: 124.7 | M15: =+SUM(C15:L15) -> 6126.3 | S15: C.H. CHARCANI V | U15: 1981.05
B16: 05:00 | C16: 1053.7 | D16: 2436.7 | E16: 2542.3 | G16: =+DESPACHO_EJECUTADO!FC20+DESPACHO_EJECUTADO!FD20 -> 61 | I16: 29.3 | J16: 9.6 | K16: 0 | L16: 122.3 | M16: =+SUM(C16:L16) -> 6254.9 | R16: EGEJUNIN | S16: C.H. HUASAHUASI I | T16: 294
B17: 05:30 | C17: 1048.1 | D17: 2501 | E17: 2639.3 | G17: =+DESPACHO_EJECUTADO!FC21+DESPACHO_EJECUTADO!FD21 -> 60.8 | I17: 32 | J17: 9.6 | K17: 0 | L17: 109.5 | M17: =+SUM(C17:L17) -> 6400.3 | S17: C.H. RUNATULLO II | T17: 172.45
B18: 06:00 | C18: 1055 | D18: 2613.2 | E18: 2642.8 | G18: =+DESPACHO_EJECUTADO!FC22+DESPACHO_EJECUTADO!FD22 -> 60.7 | I18: 23.7 | J18: 9.6 | K18: 0.1 | L18: 120.6 | M18: =+SUM(C18:L18) -> 6525.7 | S18: C.H. RUNATULLO III | T18: 242.95
B19: 06:30 | C19: 1070.4 | D19: 2626.4 | E19: 2765 | G19: =+DESPACHO_EJECUTADO!FC23+DESPACHO_EJECUTADO!FD23 -> 60.8 | I19: 23.5 | J19: 9.6 | K19: 21.1 | L19: 177.4 | M19: =+SUM(C19:L19) -> 6754.2 | S19: C.H. SANTA CRUZ I | T19: 126.35
B20: 07:00 | C20: 1065.1 | D20: 2313 | E20: 2752.2 | G20: =+DESPACHO_EJECUTADO!FC24+DESPACHO_EJECUTADO!FD24 -> 60.8 | I20: 15.4 | J20: 9.6 | K20: 164.4 | L20: 209.2 | M20: =+SUM(C20:L20) -> 6589.7 | R20: EGEMSA | S20: C.H. MACHUPICCHU | T20: 3918.4
B21: 07:30 | C21: 1068.3 | D21: 2364.9 | E21: 2759 | G21: =+DESPACHO_EJECUTADO!FC25+DESPACHO_EJECUTADO!FD25 -> 60.7 | I21: 15.9 | J21: 9.6 | K21: 368.4 | L21: 204.2 | M21: =+SUM(C21:L21) -> 6851 | R21: EGESUR | S21: C.H. ARICOTA I | U21: 173.75
B22: 08:00 | C22: 1070.1 | D22: 2412.2 | E22: 2630.7 | G22: =+DESPACHO_EJECUTADO!FC26+DESPACHO_EJECUTADO!FD26 -> 60.9 | I22: 15.2 | J22: 9.6 | K22: 510.7 | L22: 165.4 | M22: =+SUM(C22:L22) -> 6874.8 | S22: C.H. ARICOTA II | U22: 127.2
B23: 08:30 | C23: 1069.5 | D23: 2817 | E23: 2485.5 | G23: =+DESPACHO_EJECUTADO!FC27+DESPACHO_EJECUTADO!FD27 -> 61.2 | I23: 15.5 | J23: 8 | K23: 537.2 | L23: 150.6 | M23: =+SUM(C23:L23) -> 7144.5 | R23: ELECTRICA YANAPAMPA SAC | S23: C.H. YANAPAMPA | T23: 75.6
B24: 09:00 | C24: 1064.5 | D24: 2796.5 | E24: 2471.1 | G24: =+DESPACHO_EJECUTADO!FC28+DESPACHO_EJECUTADO!FD28 -> 61 | I24: 16.7 | J24: 8 | K24: 554.8 | L24: 160.5 | M24: =+SUM(C24:L24) -> 7133.1 | R24: ELECTROPERU | S24: C.H. MANTARO | U24: 15233.7
B25: 09:30 | C25: 1058.6 | D25: 2917.7 | E25: 2469.4 | G25: =+DESPACHO_EJECUTADO!FC29+DESPACHO_EJECUTADO!FD29 -> 60.6 | I25: 31.9 | J25: 8 | K25: 563.2 | L25: 188.8 | M25: =+SUM(C25:L25) -> 7298.2 | S25: C.H. RESTITUCION | T25: 5110.4
B26: 10:00 | C26: 1064 | D26: 2973.7 | E26: 2476.4 | G26: =+DESPACHO_EJECUTADO!FC30+DESPACHO_EJECUTADO!FD30 -> 60.6 | I26: 30.1 | J26: 8 | K26: 570 | L26: 219.3 | M26: =+SUM(C26:L26) -> 7402.1 | R26: EMPRESA DE GENERACION ELECTRICA CANCHAYLLO SAC | S26: C.H. CANCHAYLLO | T26: 102.5
B27: 10:30 | C27: 1063.9 | D27: 2889.3 | E27: 2593.5 | G27: =+DESPACHO_EJECUTADO!FC31+DESPACHO_EJECUTADO!FD31 -> 58.6 | I27: 29.4 | J27: 8 | K27: 571.2 | L27: 233.1 | M27: =+SUM(C27:L27) -> 7447 | R27: EMPRESA DE GENERACION ELECTRICA RIO BAÑOS S.A.C. | S27: C.H. RUCUY | T27: 478.4
B28: 11:00 | C28: 1059.8 | D28: 2917 | E28: 2588.7 | G28: =+DESPACHO_EJECUTADO!FC32+DESPACHO_EJECUTADO!FD32 -> 53.5 | I28: 31.8 | J28: 8 | K28: 570.7 | L28: 255.1 | M28: =+SUM(C28:L28) -> 7484.6 | R28: EMPRESA DE GENERACION ELECTRICA SANTA ANA S.A.C. | S28: C.H. RENOVANDES H1 | T28: 478.35
B29: 11:30 | C29: 1043.3 | D29: 2788.3 | E29: 2589.7 | G29: =+DESPACHO_EJECUTADO!FC33+DESPACHO_EJECUTADO!FD33 -> 53.3 | I29: 32.7 | J29: 8 | K29: 576.9 | L29: 291.6 | M29: =+SUM(C29:L29) -> 7383.8 | R29: EMPRESA DE GENERACION HUALLAGA | S29: C.H. CHAGLLA | U29: 5367.9
B30: 12:00 | C30: 1058.8 | D30: 2742.5 | E30: 2580.3 | G30: =+DESPACHO_EJECUTADO!FC34+DESPACHO_EJECUTADO!FD34 -> 57.6 | I30: 33.1 | J30: 8 | K30: 580.8 | L30: 320.8 | M30: =+SUM(C30:L30) -> 7381.9 | S30: P.C.H. CHAGLLA | T30: 156
B31: 12:30 | C31: 1060.5 | D31: 3006.9 | E31: 2264.5 | G31: =+DESPACHO_EJECUTADO!FC35+DESPACHO_EJECUTADO!FD35 -> 57.8 | I31: 32.5 | J31: 8 | K31: 583.9 | L31: 329.6 | M31: =+SUM(C31:L31) -> 7343.7 | R31: EMPRESA ELECTRICA AGUA AZUL | S31: C.H. POTRERO | T31: 480
B32: 13:00 | C32: 1050.4 | D32: 2763.1 | E32: 2251.4 | G32: =+DESPACHO_EJECUTADO!FC36+DESPACHO_EJECUTADO!FD36 -> 57.7 | I32: 32.5 | J32: 8 | K32: 586.6 | L32: 383.7 | M32: =+SUM(C32:L32) -> 7133.4 | R32: EMPRESA ELECTRICA RIO DOBLE | S32: C.H. LAS PIZARRAS | T32: 294.05
B33: 13:30 | C33: 1063.9 | D33: 2798.4 | E33: 2141.1 | G33: =+DESPACHO_EJECUTADO!FC37+DESPACHO_EJECUTADO!FD37 -> 57.4 | I33: 33.3 | J33: 8 | K33: 587.8 | L33: 477.5 | M33: =+SUM(C33:L33) -> 7167.4 | R33: ENGIE | S33: C.H. YUNCAN | U33: 1965.35
B34: 14:00 | C34: 1066.4 | D34: 2938.7 | E34: 2171.5 | G34: =+DESPACHO_EJECUTADO!FC38+DESPACHO_EJECUTADO!FD38 -> 57.8 | I34: 33.5 | J34: 8 | K34: 588.6 | L34: 523 | M34: =+SUM(C34:L34) -> 7387.5 | R34: GENERACIÓN ANDINA S.A.C. | S34: C.H. 8 DE AGOSTO | T34: 233.05
B35: 14:30 | C35: 1065.8 | D35: 3012.8 | E35: 2199.1 | G35: =+DESPACHO_EJECUTADO!FC39+DESPACHO_EJECUTADO!FD39 -> 57.7 | I35: 31.9 | J35: 8 | K35: 584.3 | L35: 525 | M35: =+SUM(C35:L35) -> 7484.6 | S35: C.H. EL CARMEN | T35: 79.5
B36: 15:00 | C36: 1051.2 | D36: 2668.3 | E36: 2466.9 | G36: =+DESPACHO_EJECUTADO!FC40+DESPACHO_EJECUTADO!FD40 -> 57.4 | I36: 32.5 | J36: 8 | K36: 569.9 | L36: 545.3 | M36: =+SUM(C36:L36) -> 7399.5 | R36: GENERADORA DE ENERGÍA DEL PERÚ | S36: C.H. ÁNGEL I | T36: 206.85
B37: 15:30 | C37: 1055.6 | D37: 2830.4 | E37: 2370.2 | G37: =+DESPACHO_EJECUTADO!FC41+DESPACHO_EJECUTADO!FD41 -> 57.8 | I37: 33 | J37: 8 | K37: 534.7 | L37: 574.2 | M37: =+SUM(C37:L37) -> 7463.9 | S37: C.H. ÁNGEL II | T37: 224.8
B38: 16:00 | C38: 1051.3 | D38: 2804.4 | E38: 2469.3 | G38: =+DESPACHO_EJECUTADO!FC42+DESPACHO_EJECUTADO!FD42 -> 57.9 | I38: 33.9 | J38: 9.1 | K38: 410.9 | L38: 582.3 | M38: =+SUM(C38:L38) -> 7419.1 | S38: C.H. ÁNGEL III | T38: 228.1
B39: 16:30 | C39: 1061.8 | D39: 2742.9 | E39: 2741.1 | G39: =+DESPACHO_EJECUTADO!FC43+DESPACHO_EJECUTADO!FD43 -> 58 | I39: 34.2 | J39: 9.2 | K39: 198.5 | L39: 584.6 | M39: =+SUM(C39:L39) -> 7430.3 | S39: C.H. LA JOYA | T39: 199.45
B40: 17:00 | C40: 1043.8 | D40: 2785.2 | E40: 2757.6 | G40: =+DESPACHO_EJECUTADO!FC44+DESPACHO_EJECUTADO!FD44 -> 57.7 | I40: 33.4 | J40: 9.2 | K40: 35.8 | L40: 592.1 | M40: =+SUM(C40:L40) -> 7314.8 | R40: HIDROCAÑETE S.A. | S40: C.H. IMPERIAL | T40: 85
B41: 17:30 | C41: 1059.8 | D41: 2908.1 | E41: 2776.9 | G41: =+DESPACHO_EJECUTADO!FC45+DESPACHO_EJECUTADO!FD45 -> 58.2 | I41: 33.1 | J41: 9.2 | K41: 0 | L41: 610 | M41: =+SUM(C41:L41) -> 7455.3 | R41: HIDROELECTRICA HUANCHOR S.A.C. | S41: C.H. HUANCHOR | T41: 450.7
B42: 18:00 | C42: 1063 | D42: 2878.9 | E42: 2754.6 | G42: =+DESPACHO_EJECUTADO!FC46+DESPACHO_EJECUTADO!FD46 -> 57.9 | I42: 32.1 | J42: 9.2 | K42: 0 | L42: 617.4 | M42: =+SUM(C42:L42) -> 7413.1 | R42: HUAURA POWER GROUP S.A. | S42: C.H. YARUCAYA | T42: 444
B43: 18:30 | C43: 1061.9 | D43: 2893.6 | E43: 2758.2 | G43: =+DESPACHO_EJECUTADO!FC47+DESPACHO_EJECUTADO!FD47 -> 57.3 | I43: 34.2 | J43: 10.1 | K43: 0 | L43: 626.6 | M43: =+SUM(C43:L43) -> 7441.9 | R43: HYDRO GLOBAL PERÚ S.A.C. | S43: CH SAN GABAN III | U43: 3106.9
B44: 19:00 | C44: 1064.6 | D44: 2897.8 | E44: 2751.5 | G44: =+DESPACHO_EJECUTADO!FC48+DESPACHO_EJECUTADO!FD48 -> 57.5 | I44: 33 | J44: 10.6 | K44: 0 | L44: 646.7 | M44: =+SUM(C44:L44) -> 7461.7 | R44: INLAND ENERGY SAC | S44: C.H. SANTA TERESA | T44: 2139.5
B45: 19:30 | C45: 1062.1 | D45: 2844.4 | E45: 2764 | G45: =+DESPACHO_EJECUTADO!FC49+DESPACHO_EJECUTADO!FD49 -> 56.8 | I45: 32.2 | J45: 10.6 | K45: 0 | L45: 620.5 | M45: =+SUM(C45:L45) -> 7390.6 | R45: INVERSIONES SHAQSHA S.A.C. | S45: C.H. PARIAC | T45: 95.05
B46: 20:00 | C46: 1060.1 | D46: 2886.4 | E46: 2762.3 | G46: =+DESPACHO_EJECUTADO!FC50+DESPACHO_EJECUTADO!FD50 -> 57.4 | I46: 31.9 | J46: 10.6 | K46: 0 | L46: 608.2 | M46: =+SUM(C46:L46) -> 7416.9 | R46: KALLPA GENERACION S.A. | S46: C.H. CERRO DEL AGUILA | U46: 12137.1
B47: 20:30 | C47: 1058.3 | D47: 2898.4 | E47: 2762.1 | G47: =+DESPACHO_EJECUTADO!FC51+DESPACHO_EJECUTADO!FD51 -> 57.3 | I47: 32.7 | J47: 10.6 | K47: 0 | L47: 500.3 | M47: =+SUM(C47:L47) -> 7319.7 | S47: M.C.H. CERRO DEL AGUILA | T47: 115.75
B48: 21:00 | C48: 1062.4 | D48: 3031.6 | E48: 2764.3 | G48: =+DESPACHO_EJECUTADO!FC52+DESPACHO_EJECUTADO!FD52 -> 57 | I48: 32.3 | J48: 10.6 | K48: 0 | L48: 411.3 | M48: =+SUM(C48:L48) -> 7369.5 | R48: LA VIRGEN | S48: C.H. LA VIRGEN | U48: 1238.5
B49: 21:30 | C49: 1051.5 | D49: 3051.6 | E49: 2763.6 | G49: =+DESPACHO_EJECUTADO!FC53+DESPACHO_EJECUTADO!FD53 -> 56.8 | I49: 33.2 | J49: 10.6 | K49: 0 | L49: 377.8 | M49: =+SUM(C49:L49) -> 7345.1 | R49: MAJA ENERGIA S.A.C. | S49: C.H. RONCADOR | T49: 27
B50: 22:00 | C50: 1049.4 | D50: 2845.2 | E50: 2758.1 | G50: =+DESPACHO_EJECUTADO!FC54+DESPACHO_EJECUTADO!FD54 -> 56.4 | I50: 33.1 | J50: 10.6 | K50: 0 | L50: 427.5 | M50: =+SUM(C50:L50) -> 7180.3 | R50: ORAZUL ENERGY PERÚ | S50: C.H. CAÑA BRAVA | T50: 120.1
B51: 22:30 | C51: 1062.7 | D51: 2821.7 | E51: 2732.6 | G51: =+DESPACHO_EJECUTADO!FC55+DESPACHO_EJECUTADO!FD55 -> 57.9 | I51: 33.9 | J51: 10.6 | K51: 0 | L51: 463 | M51: =+SUM(C51:L51) -> 7182.4 | S51: C.H. CAÑON DEL PATO | U51: 3801.6
B52: 23:00 | C52: 1069.2 | D52: 2763.1 | E52: 2464.2 | G52: =+DESPACHO_EJECUTADO!FC56+DESPACHO_EJECUTADO!FD56 -> 57.2 | I52: 34.3 | J52: 10.6 | K52: 0 | L52: 539.8 | M52: =+SUM(C52:L52) -> 6938.4 | S52: C.H. CARHUAQUERO | U52: 1804.2
B53: 23:30 | C53: 1058.9 | D53: 2726 | E53: 2378 | G53: =+DESPACHO_EJECUTADO!FC57+DESPACHO_EJECUTADO!FD57 -> 57.7 | I53: 33.1 | J53: 9.6 | K53: 0 | L53: 540.3 | M53: =+SUM(C53:L53) -> 6803.6 | S53: C.H. CARHUAQUERO IV | T53: 237.2
B54: 00:00 | C54: 1055.5 | D54: 2550.7 | E54: 2369.3 | G54: =+DESPACHO_EJECUTADO!FC58+DESPACHO_EJECUTADO!FD58 -> 57.2 | I54: 34.5 | J54: 10.6 | K54: 0 | L54: 484.6 | M54: =+SUM(C54:L54) -> 6562.4 | R54: ORYGEN PERU S.A.A. | S54: C.H. CALLAHUANCA | U54: 1823.15
B55: TOTAL MWh | C55: =SUM(C7:C54)/2 -> 25385.4 | D55: =SUM(D7:D54)/2 -> 65007.2 | E55: =SUM(E7:E54)/2 -> 61368.7 | F55: =SUM(F7:F54)/2 -> 0 | G55: =SUM(G7:G54)/2 -> 1408.95 | H55: =SUM(H7:H54)/2 -> 0 | I55: =SUM(I7:I54)/2 -> 727.85 | J55: =SUM(J7:J54)/2 -> 222.6 | ... M55: =SUM(M7:M54)/2 -> 168143.1 | S55: C.H. HER 1 | T55: 14.4
B56: % | C56: =+C55/$M$55 -> 0.15097497 | D56: =+D55/$M$55 -> 0.3866183 | E56: =+E55/$M$55 -> 0.364979 | F56: =+F55/$M$55 -> 0 | G56: =+G55/$M$55 -> 0.0083794696 | H56: =+H55/$M$55 -> 0 | I56: =+I55/$M$55 -> 0.0043287533 | J56: =+J55/$M$55 -> 0.0013238723 | ... M56: =+M55/$M$55 -> 1 | S56: C.H. HUAMPANI | T56: 723.1
S57: C.H. HUINCO | U57: 2371.75
S58: C.H. MATUCANA | U58: 2613.65
S59: C.H. MOYOPAMPA | T59: 1537.55
R60: PERUANA DE INVERSIONES EN ENERGIAS RENOVABLES S.A. | S60: C.H. MANTA I | T60: 394.1
R61: SAN GABAN | S61: C.H. SAN GABAN II | U61: 2194.25
S62: PCH TUPURI | T62: 16.4
R63: SINERSA | S63: C.H. CHANCAY | T63: 479.4
S64: C.H. POECHOS II | T64: 234.8
R65: STATKRAFT S.A | S65: C.H. CAHUA | T65: 1041.1
S66: C.H. CHEVES | U66: 2494.9
S67: C.H. GALLITO CIEGO | U67: 389.65
S68: C.H. MALPASO | U68: 470
S69: C.H. OROYA | T69: 199.5
S70: C.H. PACHACHACA | T70: 65.5
S71: C.H. YAUPI | T71: 2507.05
R72: TOTAL MWh | T72: 25385.4 | U72: 65007.2

Sheet GENERACION RER
B3: jueves, 5 de Junio del 2025
B5: GENERACIÓN ELÉCTRICA DE LAS CENTRALES RER (MW)
B6: HORA | C6: AGRO INDUSTRIAL PARAMONGA S.A. | D6: AGROAURORA S.A.C. | E6: AGROINDUSTRIAS SAN JACINTO S.A.A. | F6: ANDEAN POWER S.A.C. | G6: ASOCIACIÓN SANTA LUCIA DE CHACAS | H6: ATRIA ENERGIA S.A.C. | I6: BIOENERGIA DEL CHIRA S.A. | J6: COLCA SOLAR S.A.C. | K6: EGEJUNIN | P6: ELECTRICA YANAPAMPA SAC | Q6: EMPRESA DE GENERACION ELECTRICA CANCHAYLLO SAC | R6: EMPRESA DE GENERACION ELECTRICA RIO BAÑOS S.A.C. | S6: EMPRESA DE GENERACION ELECTRICA SANTA ANA S.A.C. | T6: EMPRESA ELECTRICA AGUA AZUL | U6: EMPRESA ELECTRICA RIO DOBLE | V6: ENERGÍA EÓLICA S.A. | X6: ENERGIA RENOVABLE DEL SUR S.A. | Y6: ENGIE | AD6: GENERACIÓN ANDINA S.A.C. | AF6: GENERADORA DE ENERGÍA DEL PERÚ | AJ6: GR CORTARRAMA SOCIEDAD ANONIMA CERRADA | AK6: GR PAINO SOCIEDAD ANONIMA CERRADA | AL6: GR TARUCA SOCIEDAD ANONIMA CERRADA | AM6: HIDROCAÑETE S.A. | AN6: HUAURA POWER GROUP S.A. | AO6: HYDRO PATAPO S.A.C. | AP6: JOYA SOLAR S.A.C. | AQ6: KONDU SAC | AR6: MAJA ENERGIA S.A.C. | AS6: MAJES ARCUS S.A.C. | AT6: MOQUEGUA FV S.A.C. | AU6: ORAZUL ENERGY PERÚ | AW6: ORYGEN PERU S.A.A. | BB6: PANAMERICANA SOLAR SAC. | BC6: PARQUE EOLICO MARCONA S.A.C. | BD6: PARQUE EOLICO TRES HERMANAS S.A.C. | BE6: PERUANA DE INVERSIONES EN ENERGIAS RENOVABLES S.A. | BF6: PETRAMAS | BJ6: REPARTICIÓN ARCUS S.A.C. | BK6: SAN GABAN | BL6: SDF ENERGIA SAC | BM6: SINERSA | BO6: TACNA SOLAR SAC. | BP6: TOTAL RER
C7: C.T. PARAMONGA | D7: C.T. MAPLE | E7: C.T SAN JACINTO | F7: C.H. CARHUAC | G7: C.H. HUALLIN | H7: C.H. PURMACANA | I7: C.T. CAÑA BRAVA | K7: C.H. HUASAHUASI I | L7: C.H. HUASAHUASI II | M7: C.H. RUNATULLO II | N7: C.H. RUNATULLO III | O7: C.H. STA CRUZ I y II | P7: C.H. YANAPAMPA | Q7: C.H. CANCHAYLLO | R7: C.H. RUCUY | S7: C.H. RENOVANDES H1 | T7: C.H. POTRERO | U7: C.H. LAS PIZARRAS | AD7: C.H. 8 DE AGOSTO | AE7: C.H. EL CARMEN | AF7: C.H. ANGEL I | AG7: C.H. ANGEL II | AH7: C.H. ANGEL III | AI7: C.H. LA JOYA | AM7: C.H. NUEVAIMPERIAL | AN7: C.H. YARUCAYA | AO7: MCH PATAPO | AR7: C.H. RONCADOR | AU7: C.H. CANA BRAVA | AV7: C.H. CARHUAQUERO4 | BA7: C.H. HER 1 | BE7: C.H. MANTA | BF7: C.T. HUAYCOLORO | BG7: C.T. LA GRINGA V | BH7: CTB CALLAO | BI7: CTB. DONA CATALINA | BK7: C.H. TUPURI | BL7: C.T. OQUENDO | BM7: C.H. CHANCAY | BN7: C.H. POECHOS2 | BP7: MW
B8: 0:30 | C8: 16.2 | E8: 6.2 | F8: 10.3 | G8: 2 | I8: 9.2 | K8: 13.8 | M8: 7.2 | N8: 10 | O8: 5.6 | P8: 3.1 | Q8: 4.2 | R8: 19.8 | S8: 19.9 | T8: 20 | U8: 13.2 | V8: 9.4 | W8: 9.8 | X8: 43.5 | Y8: 37.2 | Z8: 49.5 | AB8: 5.7 | AC8: 3.7 | AD8: 10.2 | AE8: 3.4 | AF8: 8.5 | AG8: 9.1 | AH8: 9.4 | AI8: 8.1 | AK8: 5.6 | AL8: 9.1 | AM8: 3.5 | AN8: 18.5 | AU8: 5.3 | AV8: 9.8 | AW8: 81.3 | AY8: 70.5 | BA8: 0.6 | BC8: 15.2 | BD8: 40.8 | BE8: 16.5 | BF8: 3 | BG8: 3.1 | BH8: 1.1 | BI8: 2.4 | BK8: 0.7 | BM8: 20 | BN8: 9.7 | BP8: 684.9
B9: 1:00 | C9: 16.1 | E9: 6.7 | F9: 10.3 | G9: 2 | I9: 9.3 | K9: 13.8 | M9: 7.3 | N9: 9.9 | O9: 5.6 | P9: 3.2 | Q9: 4.3 | R9: 19.9 | S9: 20.1 | T9: 20 | U9: 13.2 | V9: 6.9 | W9: 7.1 | X9: 44.8 | Y9: 33.9 | Z9: 46.9 | AB9: 6.6 | AC9: 3.8 | AD9: 10.2 | AE9: 3.4 | AF9: 8.5 | AG9: 9.1 | AH9: 9.4 | AI9: 8.1 | AK9: 4 | AL9: 7.1 | AM9: 3.5 | AN9: 18.5 | AU9: 4.7 | AV9: 9.9 | AW9: 83.5 | AY9: 58.5 | BA9: 0.6 | BC9: 16.4 | BD9: 42.5 | BE9: 16.6 | BF9: 3 | BG9: 3.1 | BH9: 1.1 | BI9: 2.4 | BK9: 0.7 | BM9: 20 | BN9: 9.8 | BP9: 666.3
B10: 1:30 | C10: 16.2 | E10: 6.3 | F10: 10.3 | G10: 2 | I10: 9.6 | K10: 13.8 | M10: 7.2 | N10: 10 | O10: 5.6 | P10: 3.1 | Q10: 4.3 | R10: 19.9 | S10: 20.1 | T10: 20 | U10: 13.2 | V10: 9.4 | W10: 9.2 | X10: 38.4 | Y10: 20.8 | Z10: 36.8 | AB10: 4.8 | AC10: 2.8 | AD10: 10.1 | AE10: 3.4 | AF10: 8.5 | AG10: 9.1 | AH10: 9.4 | AI10: 8.1 | AK10: 4.5 | AL10: 6.2 | AM10: 3.5 | AN10: 18.5 | AU10: 4.8 | AV10: 9.9 | AW10: 60.1 | AY10: 50.2 | BA10: 0.6 | BC10: 17.8 | BD10: 43.8 | BE10: 16.7 | BF10: 3 | BG10: 3.1 | BH10: 1.1 | BI10: 2.4 | BK10: 0.7 | BM10: 20 | BN10: 9.8 | BP10: 609.1
B11: 2:00 | C11: 16.3 | E11: 6.5 | F11: 10.3 | G11: 2 | I11: 9.4 | K11: 13.8 | M11: 7 | N11: 9.5 | O11: 5.6 | P11: 3.1 | Q11: 4.2 | R11: 19.9 | S11: 19.4 | T11: 20 | U11: 13.2 | V11: 10.6 | W11: 18.5 | X11: 34.5 | Y11: 17.2 | Z11: 37.5 | AB11: 2.4 | AC11: 0.9 | AD11: 10.1 | AE11: 3.4 | AF11: 8.5 | AG11: 9.1 | AH11: 9.4 | AI11: 8.1 | AK11: 3.9 | AL11: 6.8 | AM11: 3.5 | AN11: 18.5 | AU11: 4.8 | AV11: 9.9 | AW11: 44.8 | AY11: 49.9 | BA11: 0.6 | BC11: 17.8 | BD11: 46.2 | BE11: 16.6 | BF11: 3 | BG11: 3.1 | BH11: 1.1 | BI11: 2.4 | BK11: 0.7 | BM11: 20 | BN11: 9.8 | BP11: 593.8
B12: 2:30 | C12: 16.4 | E12: 4.9 | F12: 10.3 | G12: 1.9 | I12: 9.7 | K12: 13.8 | M12: 7.1 | N12: 9.7 | O12: 5.6 | P12: 3.2 | Q12: 4.2 | R12: 19.9 | S12: 20 | T12: 20 | U12: 12.4 | V12: 12.1 | W12: 12.5 | X12: 32 | Y12: 36.3 | Z12: 44.4 | AB12: 3.2 | AC12: 4.6 | AD12: 10.1 | AE12: 3.4 | AF12: 8.5 | AG12: 9.1 | AH12: 9.4 | AI12: 8.1 | AK12: 3.7 | AL12: 6.5 | AM12: 3.5 | AN12: 18.5 | AU12: 4.8 | AV12: 9.9 | AW12: 32.4 | AY12: 37.8 | BA12: 0.6 | BC12: 14.8 | BD12: 37.5 | BE12: 16.7 | BF12: 3 | BG12: 3.1 | BH12: 1.1 | BI12: 2.4 | BK12: 0.7 | BM12: 20 | BN12: 9.8 | BP12: 579.6
B13: 3:00 | C13: 16.2 | E13: 6.5 | F13: 10.3 | G13: 1.9 | I13: 8.6 | K13: 13.8 | M13: 7.2 | N13: 9.8 | O13: 5.6 | P13: 3.2 | Q13: 4.1 | R13: 19.9 | S13: 20 | T13: 20 | U13: 12.4 | V13: 14.6 | W13: 7.3 | X13: 27.9 | Y13: 14.4 | Z13: 37 | AB13: 1.2 | AC13: 0.2 | AD13: 10.1 | AE13: 3.4 | AF13: 8.5 | AG13: 9.1 | AH13: 9.4 | AI13: 8.1 | AK13: 2.3 | AL13: 4.8 | AM13: 3.5 | AN13: 18.5 | AU13: 4.7 | AV13: 9.9 | AW13: 17.4 | AY13: 15.9 | BA13: 0.6 | BC13: 12.9 | BD13: 36.4 | BE13: 16.7 | BF13: 3 | BG13: 3.1 | BH13: 1.1 | BI13: 2.4 | BK13: 0.7 | BM13: 20 | BN13: 9.7 | BP13: 494.3
B14: 3:30 | C14: 16.3 | E14: 6.3 | F14: 10.3 | G14: 1.9 | I14: 9.1 | K14: 12.6 | M14: 7 | N14: 9.5 | O14: 5.6 | P14: 3.2 | Q14: 4.1 | R14: 20 | S14: 19.8 | T14: 20 | U14: 12.4 | V14: 14.5 | W14: 6.1 | X14: 29.3 | Y14: 13.2 | Z14: 27.6 | AB14: 1.1 | AC14: 0.5 | AD14: 10.1 | AE14: 3.4 | AF14: 8.6 | AG14: 9.2 | AH14: 9.5 | AI14: 8.1 | AK14: 3.2 | AL14: 8.5 | AM14: 3.5 | AN14: 18.5 | AU14: 4.8 | AV14: 9.9 | AW14: 13.4 | AY14: 20.6 | BA14: 0.6 | BC14: 11.6 | BD14: 30.3 | BE14: 16.7 | BF14: 3 | BG14: 3.1 | BH14: 1.1 | BI14: 2.4 | BK14: 0.7 | BM14: 20 | BN14: 9.8 | BP14: 481
B15: 4:00 | C15: 16.2 | E15: 5.8 | F15: 10.3 | G15: 1.9 | I15: 9.3 | K15: 12.5 | M15: 7.3 | N15: 10.2 | O15: 5.6 | P15: 3.2 | Q15: 4.4 | R15: 20 | S15: 20.2 | T15: 20 | U15: 12.4 | V15: 15.1 | W15: 5 | X15: 26.7 | Y15: 8.8 | Z15: 13.5 | AB15: 0.7 | AC15: 1 | AD15: 10 | AE15: 3.4 | AF15: 8.6 | AG15: 9.2 | AH15: 9.5 | AI15: 8.3 | AK15: 3.4 | AL15: 8.5 | AM15: 3.5 | AN15: 18.5 | AU15: 2.8 | AV15: 10 | AW15: 5.9 | AY15: 11.2 | BA15: 0.6 | BC15: 11.6 | BD15: 29.4 | BE15: 16.7 | BF15: 3 | BG15: 3.1 | BH15: 1.1 | BI15: 2.4 | BK15: 0.7 | BM15: 20 | BN15: 9.8 | BP15: 441.3
B16: 4:30 | C16: 16.1 | E16: 6.4 | F16: 10.3 | G16: 1.9 | I16: 9.4 | K16: 12.4 | M16: 7 | N16: 9.4 | O16: 5.6 | P16: 3.1 | Q16: 4.4 | R16: 19.8 | S16: 19.6 | T16: 20 | U16: 12.4 | V16: 16.1 | W16: 5.6 | X16: 29 | Y16: 5.7 | Z16: 8.4 | AB16: 0.6 | AC16: 0.4 | AD16: 10 | AE16: 3.3 | AF16: 8.6 | AG16: 9.2 | AH16: 9.5 | AI16: 8.3 | AK16: 3 | AL16: 8.7 | AM16: 3.5 | AN16: 18.5 | AU16: 2.9 | AV16: 9.9 | AW16: 3.4 | AY16: 5.4 | BA16: 0.6 | BC16: 9.5 | BD16: 28.9 | BE16: 16.8 | BF16: 3 | BG16: 3.1 | BH16: 1.1 | BI16: 2.4 | BK16: 0.7 | BM16: 20 | BN16: 9.8 | BP16: 423.7
B17: 5:00 | C17: 16.3 | E17: 3.6 | F17: 10.3 | G17: 1.8 | I17: 9.4 | K17: 12.3 | M17: 7.2 | N17: 9.7 | O17: 5.6 | P17: 3.1 | Q17: 4.4 | R17: 19.8 | S17: 20.1 | T17: 20 | U17: 12.5 | V17: 21.3 | W17: 5.2 | X17: 26 | Y17: 5.6 | Z17: 12.3 | AB17: 1 | AC17: 0.8 | AD17: 10 | AE17: 3.3 | AF17: 8.7 | AG17: 9.2 | AH17: 9.6 | AI17: 8.2 | AK17: 4.7 | AL17: 9.5 | AM17: 3.5 | AN17: 18.5 | AU17: 2.9 | AV17: 9.9 | AW17: 4.8 | AY17: 3.4 | BA17: 0.6 | BC17: 9.6 | BD17: 18.1 | BE17: 16.8 | BF17: 3 | BG17: 3.1 | BH17: 1.1 | BI17: 2.4 | BK17: 0.7 | BM17: 20 | BN17: 9.8 | BP17: 419.7
B18: 5:30 | C18: 16.2 | E18: 6.3 | F18: 10.3 | G18: 1.8 | I18: 9.5 | K18: 12.5 | M18: 7.3 | N18: 9.9 | O18: 5.6 | P18: 3.2 | Q18: 4.4 | R18: 20 | S18: 20 | T18: 20 | U18: 12.4 | V18: 17.6 | W18: 3.4 | X18: 22.8 | Y18: 3.7 | Z18: 6.6 | AB18: 1 | AC18: 0.3 | AD18: 10 | AE18: 3.3 | AF18: 8.7 | AG18: 9.3 | AH18: 9.6 | AI18: 8.1 | AK18: 6.4 | AL18: 11.9 | AM18: 3.5 | AN18: 18.5 | AU18: 3 | AV18: 9.9 | AW18: 8.8 | AY18: 3.1 | BA18: 0.6 | BC18: 7.7 | BD18: 16.2 | BE18: 16.8 | BF18: 3 | BG18: 3.1 | BH18: 1.1 | BI18: 2.4 | BK18: 0.7 | BM18: 20 | BN18: 9.8 | BP18: 410.3
B19: 6:00 | C19: 8 | E19: 6.5 | F19: 10.3 | G19: 1.8 | I19: 9.2 | K19: 12.3 | M19: 7.5 | N19: 9.9 | O19: 5.6 | P19: 3.1 | Q19: 4.3 | R19: 20 | S19: 20.3 | T19: 20 | U19: 13.2 | V19: 14.2 | W19: 0.3 | X19: 25.3 | Y19: 3 | Z19: 4.6 | AB19: 0.5 | AC19: 0.1 | AD19: 10 | AE19: 3.3 | AF19: 8.7 | AG19: 9.3 | AH19: 9.6 | AI19: 8.1 | AK19: 5.6 | AL19: 10.8 | AM19: 3.5 | AN19: 18.5 | AT19: 0.1 | AU19: 2.9 | AV19: 9.9 | AW19: 22.3 | AY19: 8.5 | BA19: 0.6 | BC19: 9.8 | BD19: 15.6 | BE19: 16.7 | BF19: 3 | BG19: 3.1 | BH19: 1.1 | BI19: 2.4 | BK19: 0.7 | BM19: 20 | BN19: 9.8 | BP19: 413.9
B20: 6:30 | C20: 8 | E20: 6.5 | F20: 10.3 | G20: 1.8 | I20: 9 | K20: 12.3 | M20: 7.9 | N20: 9.8 | O20: 5.5 | P20: 3.2 | Q20: 4.3 | R20: 19.8 | S20: 20 | T20: 20 | U20: 13.2 | V20: 16.3 | W20: 0.1 | X20: 28.5 | Y20: 3.1 | Z20: 6 | AA20: 0.4 | AC20: 0.3 | AD20: 10 | AE20: 3.3 | AF20: 8.8 | AG20: 9.8 | AH20: 9.3 | AI20: 8.4 | AJ20: 2.2 | AK20: 5.4 | AL20: 11.2 | AM20: 3.5 | AN20: 18.5 | AP20: 4.6 | AR20: 1.5 | AT20: 3.1 | AU20: 2.9 | AV20: 9.9 | AW20: 48.8 | AX20: 4.1 | AY20: 15.6 | AZ20: 3 | BA20: 0.6 | BB20: 3.5 | BC20: 11.2 | BD20: 30.9 | BE20: 16.8 | BF20: 3 | BG20: 3.1 | BH20: 1.1 | BI20: 2.4 | BK20: 0.7 | BM20: 20 | BN20: 9.8 | BO20: 0.2 | BP20: 493.5
B21: 7:00 | E21: 6.1 | F21: 10.3 | G21: 1.9 | I21: 9.3 | K21: 12.3 | M21: 7.7 | N21: 9.3 | O21: 5.3 | P21: 3.1 | Q21: 4.2 | R21: 19.8 | S21: 19.6 | T21: 20 | U21: 13.2 | V21: 18.8 | W21: 0.1 | X21: 28.5 | Y21: 5.5 | Z21: 6.3 | AA21: 6.6 | AB21: 1.9 | AC21: 1.6 | AD21: 10 | AE21: 3.3 | AF21: 8.8 | AG21: 9.8 | AH21: 9.5 | AI21: 8.4 | AJ21: 18.5 | AK21: 7.9 | AL21: 11.6 | AM21: 3.5 | AN21: 18.5 | AP21: 55.2 | AR21: 1.5 | AS21: 2.1 | AT21: 9.2 | AU21: 3.8 | AV21: 9.8 | AW21: 49.1 | AX21: 33.1 | AY21: 31.4 | AZ21: 26.3 | BA21: 0.6 | BB21: 10.6 | BC21: 10.9 | BD21: 35.6 | BE21: 16.9 | BF21: 3 | BG21: 3.1 | BH21: 1.1 | BI21: 2.4 | BJ21: 2.1 | BK21: 0.7 | BM21: 19.8 | BN21: 9.8 | BO21: 0.7 | BP21: 660
B22: 7:30 | E22: 6.5 | F22: 10.3 | G22: 1.9 | I22: 9.4 | J22: 0.1 | K22: 12.4 | M22: 7.8 | N22: 10.1 | O22: 5.3 | P22: 3.2 | Q22: 4.2 | R22: 19.8 | S22: 19.8 | T22: 20 | U22: 13.2 | V22: 22.2 | W22: 0.1 | X22: 30.9 | Y22: 7.7 | Z22: 7.3 | AA22: 15.9 | AB22: 1.2 | AC22: 1.2 | AD22: 10 | AE22: 3.3 | AF22: 8.8 | AG22: 9.9 | AH22: 9.8 | AI22: 8.3 | AJ22: 43.6 | AK22: 10.1 | AL22: 14.3 | AM22: 3.5 | AN22: 18.5 | AP22: 138 | AR22: 1.5 | AS22: 4.7 | AT22: 11.5 | AU22: 5.4 | AV22: 9.8 | AW22: 40.2 | AX22: 76.4 | AY22: 34.9 | AZ22: 58.8 | BA22: 0.6 | BB22: 13.9 | BC22: 9.4 | BD22: 24.7 | BE22: 16.7 | BF22: 3 | BG22: 3.1 | BH22: 1.1 | BI22: 2.4 | BJ22: 4.5 | BK22: 0.7 | BM22: 20 | BN22: 9.8 | BO22: 1 | BP22: 862.7
B23: 8:00 | E23: 6.6 | F23: 10.1 | G23: 1.8 | I23: 8.6 | J23: 0.3 | K23: 12.3 | M23: 7.9 | N23: 10.4 | O23: 5.3 | P23: 3.2 | Q23: 4.2 | R23: 19.8 | S23: 20.3 | T23: 20 | U23: 13.2 | V23: 19.1 | X23: 33.3 | Y23: 4 | Z23: 8.3 | AA23: 24.5 | AB23: 1 | AC23: 1.1 | AD23: 9.9 | AE23: 3.3 | AF23: 8.8 | AG23: 10 | AH23: 9.9 | AI23: 8.1 | AJ23: 62.5 | AK23: 11.7 | AL23: 14.3 | AM23: 3.5 | AN23: 18.5 | AP23: 191.9 | AR23: 1.5 | AS23: 7.1 | AT23: 12.2 | AU23: 5.5 | AV23: 9.9 | AW23: 21.4 | AX23: 110.3 | AY23: 18.6 | AZ23: 79 | BA23: 0.6 | BB23: 14.6 | BC23: 9.4 | BD23: 23.2 | BE23: 16.9 | BF23: 3 | BG23: 3.1 | BH23: 1.1 | BI23: 2.4 | BJ23: 7 | BK23: 0.7 | BM23: 20 | BN23: 9.8 | BO23: 1.3 | BP23: 966.3
B24: 8:30 | C24: 1 | E24: 5.3 | F24: 10.3 | G24: 1.8 | I24: 9.2 | J24: 0.6 | K24: 12.4 | M24: 7.9 | N24: 11.7 | O24: 5.3 | P24: 3.2 | Q24: 4.1 | R24: 20 | S24: 20.2 | T24: 20 | U24: 13.2 | V24: 18.4 | X24: 36.6 | Y24: 1 | Z24: 5.9 | AA24: 28.2 | AB24: 0.2 | AC24: 0.1 | AD24: 9.7 | AE24: 3.3 | AF24: 8.8 | AG24: 10 | AH24: 9.9 | AI24: 8 | AJ24: 64.6 | AK24: 12.2 | AL24: 15.8 | AM24: 3.4 | AN24: 18.5 | AP24: 199.5 | AQ24: 0.1 | AR24: 1.5 | AS24: 9.2 | AT24: 12.3 | AU24: 5.5 | AV24: 9.8 | AW24: 15.7 | AX24: 113.9 | AY24: 11.6 | AZ24: 82.4 | BA24: 0.6 | BB24: 14.9 | BC24: 10.2 | BD24: 22.9 | BE24: 16.9 | BF24: 1.5 | BG24: 3.1 | BH24: 1 | BI24: 2.4 | BJ24: 9.1 | BK24: 0.7 | BM24: 20 | BN24: 9.8 | BO24: 2.4 | BP24: 977.8
B25: 9:00 | C25: 2 | E25: 5.4 | F25: 10.3 | G25: 1.8 | I25: 9.3 | J25: 0.8 | K25: 12.5 | M25: 7.6 | N25: 11.7 | O25: 5.4 | P25: 3.2 | Q25: 4.2 | R25: 19.8 | S25: 20 | T25: 20 | U25: 13.2 | V25: 16.6 | X25: 56.2 | Y25: 6.5 | Z25: 9.7 | AA25: 28.4 | AB25: 0.2 | AC25: 0.4 | AD25: 9.7 | AE25: 3.3 | AF25: 8.8 | AG25: 9.6 | AH25: 9.9 | AI25: 8.8 | AJ25: 65.3 | AK25: 10.5 | AL25: 12.7 | AM25: 3.5 | AN25: 18.5 | AP25: 206.3 | AQ25: 0.1 | AR25: 1.5 | AS25: 11 | AT25: 12.5 | AU25: 5.4 | AV25: 9.9 | AW25: 3 | AX25: 115.8 | AY25: 1.1 | AZ25: 83.9 | BA25: 0.6 | BB25: 15.1 | BC25: 11.3 | BD25: 32.3 | BE25: 16.9 | BF25: 1.5 | BG25: 3.1 | BH25: 1 | BI25: 2.4 | BJ25: 11 | BK25: 0.7 | BM25: 20 | BN25: 9.8 | BO25: 4.6 | BP25: 1006.6
B26: 9:30 | C26: 17.3 | E26: 5.2 | F26: 10.3 | G26: 1.8 | I26: 9.4 | J26: 0.9 | K26: 12.6 | M26: 7.6 | N26: 11.6 | O26: 5.4 | P26: 3.2 | Q26: 4.4 | R26: 19.9 | S26: 20 | T26: 20 | U26: 13.2 | V26: 13.1 | W26: 0.7 | X26: 66.9 | Y26: 10.6 | Z26: 13.1 | AA26: 28.2 | AB26: 2 | AC26: 1.4 | AD26: 9.9 | AE26: 3.3 | AF26: 8.8 | AG26: 9.4 | AH26: 9.9 | AI26: 8.7 | AJ26: 65.6 | AK26: 13.4 | AL26: 16.5 | AM26: 3.5 | AN26: 18.5 | AP26: 206.8 | AQ26: 0.1 | AR26: 1.5 | AS26: 12.4 | AT26: 12.5 | AU26: 5.4 | AV26: 9.9 | AX26: 115.9 | AZ26: 84.6 | BA26: 0.6 | BB26: 15.1 | BC26: 13.4 | BD26: 37.7 | BE26: 16.9 | BF26: 1.5 | BG26: 3.1 | BH26: 1 | BI26: 2.4 | BJ26: 12.6 | BK26: 0.7 | BM26: 20 | BN26: 9.8 | BO26: 8.5 | BP26: 1058.7
B27: 10:00 | C27: 16.9 | E27: 4.1 | F27: 10.3 | G27: 1.7 | I27: 9.1 | J27: 1 | K27: 12.6 | M27: 7.6 | N27: 11.8 | O27: 5.4 | P27: 3.2 | Q27: 4.4 | R27: 20 | S27: 20 | T27: 20 | U27: 13.2 | V27: 11.5 | W27: 3.1 | X27: 73.1 | Y27: 17.8 | Z27: 22.3 | AA27: 27.7 | AB27: 2.7 | AC27: 2.4 | AD27: 9.9 | AE27: 3.3 | AF27: 8.8 | AG27: 9.4 | AH27: 9.6 | AI27: 8.3 | AJ27: 65.7 | AK27: 15.3 | AL27: 15.8 | AM27: 3.5 | AN27: 18.5 | AP27: 205.4 | AQ27: 0.3 | AR27: 1.5 | AS27: 13.7 | AT27: 12.3 | AU27: 5.3 | AV27: 9.9 | AX27: 115.4 | AZ27: 84.5 | BA27: 0.6 | BB27: 15 | BC27: 14.7 | BD27: 40.6 | BE27: 16.9 | BF27: 1.5 | BG27: 3.1 | BH27: 1 | BI27: 2.4 | BJ27: 13.8 | BK27: 0.7 | BM27: 20 | BN27: 9.7 | BO27: 15.2 | BP27: 1093.5
B28: 10:30 | C28: 16.6 | E28: 4.2 | F28: 10.2 | G28: 1.8 | I28: 8.6 | J28: 1.1 | K28: 12.6 | M28: 7.6 | N28: 11.7 | O28: 5.3 | P28: 3.2 | Q28: 4.4 | R28: 20 | S28: 20.2 | T28: 20 | U28: 13.2 | V28: 10.2 | W28: 6.1 | X28: 65.9 | Y28: 24.3 | Z28: 25.6 | AA28: 27.8 | AB28: 4.4 | AC28: 3.3 | AD28: 9.9 | AE28: 3.3 | AF28: 8.8 | AG28: 9.4 | AH28: 9.6 | AI28: 8.3 | AJ28: 65.9 | AK28: 14.5 | AL28: 16.6 | AM28: 3.5 | AN28: 18.5 | AP28: 206 | AQ28: 0.4 | AR28: 1.5 | AS28: 14.7 | AT28: 12 | AU28: 5.4 | AV28: 9.9 | AW28: 2.9 | AX28: 113.7 | AZ28: 84 | BA28: 0.6 | BB28: 15.2 | BC28: 14.2 | BD28: 45.1 | BE28: 16.9 | BF28: 1.5 | BG28: 3.1 | BH28: 1 | BI28: 2.4 | BJ28: 14.9 | BK28: 0.7 | BM28: 20 | BN28: 9.8 | BO28: 15.5 | BP28: 1108
B29: 11:00 | C29: 16.1 | E29: 6.6 | F29: 10.3 | G29: 1.8 | I29: 9.1 | J29: 1.2 | K29: 12.6 | M29: 7.6 | N29: 11.8 | O29: 5.2 | P29: 3.2 | Q29: 4.4 | R29: 20 | S29: 20.1 | T29: 20 | U29: 13.2 | V29: 11.9 | W29: 8.7 | X29: 58.8 | Y29: 27.1 | Z29: 21.1 | AA29: 27.7 | AB29: 6.4 | AC29: 4.3 | AD29: 9.7 | AE29: 3.3 | AF29: 8.8 | AG29: 9.4 | AH29: 9.6 | AI29: 7.7 | AJ29: 65.5 | AK29: 16.2 | AL29: 16.8 | AM29: 3.6 | AN29: 18.5 | AP29: 205.7 | AQ29: 0.4 | AR29: 1.5 | AS29: 15.4 | AT29: 12.4 | AU29: 5.4 | AV29: 9.9 | AW29: 25.6 | AX29: 113 | AY29: 4.1 | AZ29: 83.1 | BA29: 0.6 | BB29: 15.2 | BC29: 13.9 | BD29: 40.2 | BE29: 16.8 | BF29: 1.5 | BG29: 3.1 | BH29: 1 | BI29: 2.4 | BJ29: 15.6 | BK29: 0.7 | BM29: 20 | BN29: 9.8 | BO29: 15.5 | BP29: 1131.1
B30: 11:30 | C30: 16.8 | E30: 6.9 | F30: 10.3 | G30: 1.8 | I30: 9 | J30: 1.2 | K30: 12.6 | M30: 7.5 | N30: 11.5 | O30: 5.2 | P30: 3.2 | Q30: 4.5 | R30: 20 | S30: 19.8 | T30: 20 | U30: 9.4 | V30: 6.9 | W30: 13.4 | X30: 64.2 | Y30: 24 | Z30: 23.4 | AA30: 27.7 | AB30: 4.8 | AC30: 3.4 | AD30: 9.5 | AE30: 3.3 | AF30: 8.8 | AG30: 9.4 | AH30: 9.5 | AI30: 7.7 | AJ30: 66.8 | AK30: 15.5 | AL30: 17.6 | AM30: 3.5 | AN30: 18.5 | AP30: 208.6 | AQ30: 0.4 | AR30: 1.5 | AS30: 16.2 | AT30: 12.6 | AU30: 5.4 | AV30: 9.9 | AW30: 48.5 | AX30: 112.9 | AY30: 16.3 | AZ30: 83.7 | BA30: 0.6 | BB30: 15.3 | BC30: 13.8 | BD30: 39.8 | BE30: 16.7 | BF30: 1.5 | BG30: 3.1 | BH30: 1 | BI30: 2.4 | BJ30: 16 | BK30: 0.7 | BM30: 20 | BN30: 9.8 | BO30: 15.5 | BP30: 1169.8
B31: 12:00 | C31: 16.8 | E31: 7.1 | F31: 10.3 | G31: 1.8 | I31: 9.2 | J31: 1.2 | K31: 12.6 | M31: 7.6 | N31: 11.1 | O31: 5.2 | P31: 3.2 | Q31: 4.4 | R31: 20 | S31: 19.9 | T31: 20 | U31: 10 | V31: 6.5 | W31: 15.6 | X31: 56.2 | Y31: 25.2 | Z31: 21.6 | AA31: 27.8 | AB31: 5.2 | AC31: 4.3 | AD31: 9.4 | AE31: 3.3 | AF31: 8.8 | AG31: 9.4 | AH31: 9.5 | AI31: 8.6 | AJ31: 68 | AK31: 13.8 | AL31: 16.5 | AM31: 3.5 | AN31: 18.5 | AP31: 211 | AQ31: 0.4 | AR31: 1.5 | AS31: 16.7 | AT31: 12.4 | AU31: 5.4 | AV31: 9.8 | AW31: 70.6 | AX31: 112.9 | AY31: 34.7 | AZ31: 83.8 | BA31: 0.6 | BB31: 15 | BC31: 14.3 | BD31: 36.3 | BE31: 16.7 | BF31: 1.5 | BG31: 3.1 | BH31: 1 | BI31: 2.4 | BJ31: 16.2 | BK31: 0.7 | BM31: 20 | BN31: 9.8 | BO31: 15.4 | BP31: 1204.3
B32: 12:30 | C32: 16.5 | E32: 6.7 | F32: 10.1 | G32: 1.8 | I32: 9.3 | J32: 1.2 | K32: 12.5 | M32: 7.2 | N32: 11.3 | O32: 5.2 | P32: 3.2 | Q32: 4.4 | R32: 20 | S32: 20.2 | T32: 20 | U32: 10 | V32: 6.1 | W32: 23 | X32: 47.2 | Y32: 30.4 | Z32: 34 | AA32: 27.7 | AB32: 6.3 | AC32: 4.2 | AD32: 9.5 | AE32: 3.3 | AF32: 8.6 | AG32: 9.4 | AH32: 9.5 | AI32: 8.8 | AJ32: 68.4 | AK32: 13.9 | AL32: 16.6 | AM32: 3.6 | AN32: 18.5 | AP32: 211.8 | AQ32: 0.4 | AR32: 1.5 | AS32: 16.6 | AT32: 12.7 | AU32: 5.5 | AV32: 9.9 | AW32: 72.9 | AX32: 114 | AY32: 32.5 | AZ32: 84.4 | BA32: 0.6 | BB32: 14.9 | BC32: 7.6 | BD32: 34.9 | BE32: 16.6 | BF32: 1.5 | BG32: 3.1 | BH32: 1 | BI32: 2.4 | BJ32: 16.3 | BK32: 0.7 | BM32: 20 | BN32: 9.8 | BO32: 15.5 | BP32: 1215.7
B33: 13:00 | C33: 17 | E33: 6.3 | F33: 10.1 | G33: 1.8 | I33: 9.2 | J33: 1.2 | K33: 12.5 | M33: 7.1 | N33: 11 | O33: 5.2 | P33: 3.2 | Q33: 4.3 | R33: 20 | S33: 19.6 | T33: 20 | U33: 10 | V33: 8.6 | W33: 28.2 | X33: 48.8 | Y33: 40.5 | Z33: 38.3 | AA33: 28 | AB33: 8.1 | AC33: 5.7 | AD33: 9.6 | AE33: 3.3 | AF33: 8.6 | AG33: 9.4 | AH33: 9.5 | AI33: 8.9 | AJ33: 68.9 | AK33: 13.7 | AL33: 16.4 | AM33: 3.6 | AN33: 18.5 | AP33: 212.2 | AQ33: 0.4 | AR33: 1.5 | AS33: 16.2 | AT33: 12.8 | AU33: 5.5 | AV33: 9.9 | AW33: 77.2 | AX33: 115.2 | AY33: 39.8 | AZ33: 85 | BA33: 0.6 | BB33: 15.1 | BC33: 12.5 | BD33: 45.9 | BE33: 16.6 | BF33: 1.5 | BG33: 3.1 | BH33: 1 | BI33: 2.4 | BJ33: 15.9 | BK33: 0.7 | BM33: 20 | BN33: 9.8 | BO33: 15.7 | BP33: 1271.6
B34: 13:30 | C34: 17.2 | E34: 6.8 | F34: 10.2 | G34: 1.7 | I34: 9.3 | J34: 1.1 | K34: 12.1 | M34: 7.2 | N34: 11 | O34: 5.2 | P34: 3.2 | Q34: 4.3 | R34: 19.8 | S34: 19.8 | T34: 20 | U34: 10 | V34: 15.9 | W34: 33.2 | X34: 67.7 | Y34: 55 | Z34: 57.2 | AA34: 27.9 | AB34: 9.6 | AC34: 8.4 | AD34: 9.6 | AE34: 3.3 | AF34: 8.4 | AG34: 9.4 | AH34: 9.5 | AI34: 8.8 | AJ34: 68.9 | AK34: 14 | AL34: 14 | AM34: 3.6 | AN34: 18.5 | AP34: 214.2 | AQ34: 0.4 | AR34: 1.5 | AS34: 15.4 | AT34: 12.8 | AU34: 5.4 | AV34: 9.8 | AW34: 77 | AX34: 115.9 | AY34: 49.2 | AZ34: 85.2 | BA34: 0.6 | BB34: 15.3 | BC34: 14.6 | BD34: 61.7 | BE34: 16.5 | BF34: 1.5 | BG34: 3.1 | BH34: 1 | BI34: 2.4 | BJ34: 15 | BK34: 0.7 | BM34: 20 | BN34: 9.8 | BO34: 15.7 | BP34: 1366.5
B35: 14:00 | C35: 17.7 | E35: 6.8 | F35: 10.1 | G35: 1.7 | I35: 9 | J35: 1.1 | K35: 12.2 | M35: 7.2 | N35: 11.2 | O35: 5.2 | P35: 3.2 | Q35: 4.2 | R35: 20 | S35: 19.8 | T35: 20 | U35: 10 | V35: 14.5 | W35: 49.4 | X35: 81.2 | Y35: 50.4 | Z35: 60.3 | AA35: 28.7 | AB35: 10.3 | AC35: 6.3 | AD35: 9.6 | AE35: 3.3 | AF35: 8.5 | AG35: 9.4 | AH35: 9.5 | AI35: 8.5 | AJ35: 68.9 | AK35: 14 | AL35: 15.2 | AM35: 3.6 | AN35: 18.5 | AP35: 214.4 | AQ35: 0.4 | AR35: 1.5 | AS35: 14.1 | AT35: 12.7 | AU35: 5.5 | AV35: 9.9 | AW35: 76.4 | AX35: 117.5 | AY35: 58.8 | AZ35: 85.8 | BA35: 0.6 | BB35: 15.2 | BC35: 19.7 | BD35: 66.5 | BE35: 16.4 | BF35: 1.5 | BG35: 3.1 | BH35: 1 | BI35: 2.4 | BJ35: 14.1 | BK35: 0.7 | BM35: 20 | BN35: 9.8 | BO35: 15.7 | BP35: 1413.2
B36: 14:30 | C36: 17.2 | E36: 5.4 | F36: 10.1 | G36: 1.9 | I36: 9.3 | J36: 1 | K36: 11.9 | M36: 7.2 | N36: 11.2 | O36: 4.9 | P36: 3.2 | Q36: 4.1 | R36: 20 | S36: 20.1 | T36: 20 | U36: 10 | V36: 11.1 | W36: 64.2 | X36: 75.4 | Y36: 48.2 | Z36: 59.4 | AA36: 29 | AB36: 8.1 | AC36: 5.8 | AD36: 9.6 | AE36: 3.3 | AF36: 8.7 | AG36: 9.4 | AH36: 9.5 | AI36: 8.4 | AJ36: 68.7 | AK36: 13.8 | AL36: 15.9 | AM36: 3.6 | AN36: 18.5 | AP36: 213.7 | AQ36: 0.4 | AR36: 1.5 | AS36: 12.4 | AT36: 12.6 | AU36: 5.5 | AV36: 9.9 | AW36: 68.5 | AX36: 117.3 | AY36: 54.4 | AZ36: 85.8 | BA36: 0.6 | BB36: 15.2 | BC36: 22.3 | BD36: 77.9 | BE36: 16.3 | BF36: 1.5 | BG36: 3.1 | BH36: 1 | BI36: 2.4 | BJ36: 12.7 | BK36: 0.7 | BM36: 20 | BN36: 9.7 | BO36: 15.5 | BP36: 1409
B37: 15:00 | C37: 17.1 | E37: 6.8 | F37: 10.1 | G37: 1.9 | I37: 8.6 | J37: 0.8 | K37: 11.9 | M37: 6.9 | N37: 11 | O37: 4.7 | P37: 3.2 | Q37: 4.4 | R37: 20 | S37: 19.6 | T37: 20 | U37: 10 | V37: 9.9 | W37: 55.8 | X37: 46.4 | Y37: 59 | Z37: 62 | AA37: 28.8 | AB37: 8.9 | AC37: 8.3 | AD37: 9.6 | AE37: 3.3 | AF37: 8.7 | AG37: 9.4 | AH37: 9.5 | AI37: 8.4 | AJ37: 66.8 | AK37: 15.5 | AL37: 17.1 | AM37: 3.6 | AN37: 18.5 | AP37: 210.2 | AQ37: 0.3 | AR37: 1.5 | AS37: 10.6 | AT37: 12.3 | AU37: 5.4 | AV37: 9.9 | AW37: 106.5 | AX37: 115.7 | AY37: 64.3 | AZ37: 83.8 | BA37: 0.6 | BB37: 14.8 | BC37: 20.7 | BD37: 70.9 | BE37: 16.3 | BF37: 1.5 | BG37: 3.1 | BH37: 1 | BI37: 2.4 | BJ37: 10.9 | BK37: 0.7 | BM37: 19.8 | BN37: 9.8 | BO37: 14.9 | BP37: 1414.4
B38: 15:30 | C38: 17.2 | E38: 6.6 | F38: 10.1 | G38: 2 | I38: 9.2 | J38: 0.7 | K38: 11.9 | M38: 7.1 | N38: 10.1 | O38: 4.7 | P38: 3.2 | Q38: 4.4 | R38: 20 | S38: 19.8 | T38: 20 | U38: 10 | V38: 6.9 | W38: 50 | X38: 43.2 | Y38: 58.3 | Z38: 63.4 | AA38: 26.3 | AB38: 9.4 | AC38: 6 | AD38: 9.6 | AE38: 3.3 | AF38: 8.6 | AG38: 9.4 | AH38: 9.5 | AI38: 8.4 | AJ38: 63.4 | AK38: 15.8 | AL38: 16.4 | AM38: 3.5 | AN38: 18.5 | AP38: 199.9 | AQ38: 0.3 | AR38: 1.5 | AS38: 8.6 | AT38: 11.5 | AU38: 5.5 | AV38: 9.8 | AW38: 120.6 | AX38: 109.4 | AY38: 104.2 | AZ38: 79.4 | BA38: 0.6 | BB38: 13.6 | BC38: 14.2 | BD38: 65.8 | BE38: 16.3 | BF38: 1.5 | BG38: 3.1 | BH38: 1 | BI38: 2.4 | BJ38: 8.8 | BK38: 0.7 | BM38: 20 | BN38: 9.8 | BO38: 12.8 | BP38: 1408.2
B39: 16:00 | C39: 17 | E39: 7.6 | F39: 10.1 | G39: 2 | I39: 9.3 | J39: 0.5 | K39: 11.7 | M39: 7 | N39: 9.1 | O39: 4.7 | P39: 3.2 | Q39: 4.3 | R39: 20 | S39: 19.7 | T39: 20 | U39: 10 | V39: 3.9 | W39: 49.9 | X39: 36.2 | Y39: 51 | Z39: 56 | AA39: 18.3 | AB39: 8.1 | AC39: 6.8 | AD39: 9.6 | AE39: 3.3 | AF39: 8.6 | AG39: 9.4 | AH39: 9.5 | AI39: 8.4 | AJ39: 44.9 | AK39: 15.7 | AL39: 16.1 | AM39: 3.6 | AN39: 18.5 | AP39: 165.1 | AQ39: 0.2 | AR39: 1.5 | AS39: 6.2 | AT39: 8.4 | AU39: 5.5 | AV39: 9.9 | AW39: 131.6 | AX39: 75.5 | AY39: 125.1 | AZ39: 66.4 | BA39: 0.6 | BB39: 10.4 | BC39: 16.7 | BD39: 65.2 | BE39: 16.3 | BF39: 2.6 | BG39: 3.1 | BH39: 1 | BI39: 2.4 | BJ39: 6.5 | BK39: 0.7 | BM39: 19.9 | BN39: 9.8 | BO39: 8.5 | BP39: 1293.1
B40: 16:30 | C40: 17 | E40: 7.8 | F40: 10.1 | G40: 2 | I40: 9.4 | J40: 0.2 | K40: 11.7 | M40: 7.2 | N40: 9.5 | O40: 4.7 | P40: 3.2 | Q40: 4.3 | R40: 20 | S40: 20 | T40: 20 | U40: 13.2 | V40: 4.7 | W40: 50 | X40: 36.5 | Y40: 62.7 | Z40: 61.2 | AA40: 8.1 | AB40: 11.1 | AC40: 7.2 | AD40: 9.6 | AE40: 3.3 | AF40: 8.6 | AG40: 9.4 | AH40: 9.5 | AI40: 8.4 | AJ40: 19.2 | AK40: 15.1 | AL40: 15.9 | AM40: 3.5 | AN40: 18.5 | AP40: 84.5 | AQ40: 0.2 | AR40: 1.5 | AS40: 3.8 | AT40: 3 | AU40: 5.4 | AV40: 10 | AW40: 127.9 | AX40: 35.7 | AY40: 130.3 | AZ40: 34.2 | BA40: 0.6 | BB40: 3.5 | BC40: 12.6 | BD40: 49.4 | BE40: 16.2 | BF40: 3 | BG40: 3 | BH40: 1 | BI40: 2.2 | BJ40: 4 | BK40: 0.7 | BM40: 20 | BN40: 9.8 | BO40: 2.1 | BP40: 1087.4
B41: 17:00 | C41: 17 | E41: 6.9 | F41: 10.1 | G41: 2.1 | I41: 9.5 | J41: 0.1 | K41: 11.7 | M41: 7 | N41: 9.4 | O41: 4.7 | P41: 3.2 | Q41: 4.2 | R41: 20 | S41: 19.3 | T41: 20 | U41: 13.1 | V41: 6 | W41: 51.4 | X41: 35.4 | Y41: 62.4 | Z41: 67.1 | AA41: 1.1 | AB41: 10.6 | AC41: 3.8 | AD41: 9.6 | AE41: 3.3 | AF41: 8.6 | AG41: 9.4 | AH41: 9.5 | AI41: 8.4 | AJ41: 3.7 | AK41: 14.4 | AL41: 15.7 | AM41: 3.5 | AN41: 18.5 | AP41: 16.6 | AR41: 1.5 | AS41: 1.3 | AT41: 0.1 | AU41: 5.5 | AV41: 9.9 | AW41: 136.2 | AX41: 5.2 | AY41: 129.8 | AZ41: 6.2 | BA41: 0.6 | BC41: 11.7 | BD41: 47.6 | BE41: 16 | BF41: 3 | BG41: 3 | BH41: 1 | BI41: 2.2 | BJ41: 1.5 | BK41: 0.7 | BM41: 20 | BN41: 9.8 | BP41: 930.1
B42: 17:30 | C42: 17 | E42: 6.9 | F42: 10.1 | G42: 2.1 | I42: 9.2 | K42: 11.5 | M42: 7.1 | N42: 9.5 | O42: 4.7 | P42: 3.2 | Q42: 4.3 | R42: 20 | S42: 19.9 | T42: 20 | U42: 13.1 | V42: 9.6 | W42: 61 | X42: 37.7 | Y42: 64.1 | Z42: 66.2 | AB42: 8.2 | AC42: 6.3 | AD42: 9.6 | AE42: 3.3 | AF42: 8.6 | AG42: 9.4 | AH42: 9.5 | AI42: 8.4 | AK42: 15.7 | AL42: 17.1 | AM42: 3.6 | AN42: 18.5 | AR42: 1.5 | AU42: 5.5 | AV42: 9.9 | AW42: 141.1 | AY42: 130.7 | BA42: 0.6 | BC42: 11.5 | BD42: 40.8 | BE42: 16 | BF42: 3 | BG42: 3 | BH42: 1 | BI42: 2.2 | BK42: 0.7 | BM42: 20 | BN42: 9.8 | BP42: 912.7
B43: 18:00 | C43: 16.8 | E43: 6 | F43: 10.1 | G43: 2.2 | I43: 9.3 | K43: 11.6 | M43: 7.1 | N43: 9.2 | O43: 4.8 | P43: 3.2 | Q43: 4.4 | R43: 19.9 | S43: 19.9 | T43: 20 | U43: 13.1 | V43: 12.3 | W43: 54.3 | X43: 35.7 | Y43: 67.1 | Z43: 76.7 | AB43: 10.5 | AC43: 6 | AD43: 9.6 | AE43: 3.3 | AF43: 8.6 | AG43: 9.4 | AH43: 9.5 | AI43: 8.5 | AK43: 14.1 | AL43: 16.2 | AM43: 3.5 | AN43: 18.5 | AR43: 1.5 | AU43: 5.3 | AV43: 9.9 | AW43: 139.1 | AY43: 132.1 | BA43: 0.6 | BC43: 12.2 | BD43: 41.1 | BE43: 16 | BF43: 3 | BG43: 3 | BH43: 1 | BI43: 2.2 | BK43: 0.7 | BM43: 20 | BN43: 9.7 | BP43: 918.8
B44: 18:30 | C44: 17.3 | E44: 7.7 | F44: 10.1 | G44: 2.2 | I44: 9.2 | K44: 11.4 | M44: 6.7 | N44: 9.4 | O44: 4.7 | P44: 3.1 | Q44: 4.3 | R44: 19.9 | S44: 20.1 | T44: 20 | U44: 13 | V44: 12.8 | W44: 50.4 | X44: 51.7 | Y44: 68.9 | Z44: 77.6 | AB44: 10.1 | AC44: 3.3 | AD44: 9.3 | AE44: 3.3 | AF44: 8.6 | AG44: 9.4 | AH44: 9.5 | AI44: 8.5 | AK44: 11 | AL44: 15.7 | AM44: 3.6 | AN44: 18.5 | AR44: 1.5 | AU44: 5.3 | AV44: 9.9 | AW44: 132.9 | AY44: 128.4 | BA44: 0.6 | BC44: 13.8 | BD44: 50 | BE44: 16 | BF44: 3.9 | BG44: 3 | BH44: 1 | BI44: 2.2 | BK44: 0.7 | BM44: 19.8 | BN44: 9.7 | BP44: 930
B45: 19:00 | C45: 16.9 | E45: 6.8 | F45: 10 | G45: 2.2 | I45: 9.3 | K45: 11.4 | M45: 6.7 | N45: 9.4 | O45: 4.8 | P45: 3.1 | Q45: 4.3 | R45: 20 | S45: 20.1 | T45: 20 | U45: 13.1 | V45: 10.5 | W45: 45.6 | X45: 62.8 | Y45: 66.1 | Z45: 82.8 | AB45: 7.8 | AC45: 4.2 | AD45: 9.3 | AE45: 3.3 | AF45: 8.6 | AG45: 9.4 | AH45: 9.5 | AI45: 8.6 | AK45: 13.1 | AL45: 16.9 | AM45: 3.6 | AN45: 18.5 | AR45: 1.5 | AU45: 5.5 | AV45: 9.9 | AW45: 125.2 | AY45: 127.8 | BA45: 0.6 | BC45: 18.8 | BD45: 65.1 | BE45: 15.9 | BF45: 4.4 | BG45: 3 | BH45: 1 | BI45: 2.2 | BK45: 0.7 | BM45: 19.8 | BN45: 9.8 | BP45: 949.9
B46: 19:30 | C46: 16.8 | E46: 6.8 | F46: 10 | G46: 2.2 | I46: 8.6 | K46: 11.4 | M46: 6.8 | N46: 9.4 | O46: 4.9 | P46: 3.1 | Q46: 4.2 | R46: 19.9 | S46: 19.9 | T46: 20 | U46: 13 | V46: 8.1 | W46: 45.8 | X46: 63.5 | Y46: 71.2 | Z46: 78.9 | AB46: 10.7 | AC46: 5 | AD46: 9.4 | AE46: 3.3 | AF46: 8.6 | AG46: 9.4 | AH46: 9.5 | AI46: 8.5 | AK46: 13.2 | AL46: 16.7 | AM46: 3.6 | AN46: 18.5 | AR46: 1.5 | AU46: 5.5 | AV46: 9.9 | AW46: 110.6 | AY46: 119.5 | BA46: 0.6 | BC46: 18 | BD46: 59.3 | BE46: 16 | BF46: 4.4 | BG46: 3 | BH46: 1 | BI46: 2.2 | BK46: 0.7 | BM46: 20 | BN46: 9.8 | BP46: 922.9
B47: 20:00 | C47: 16.5 | E47: 6.8 | F47: 10 | G47: 2.2 | I47: 8.6 | K47: 11.4 | M47: 6.7 | N47: 9.5 | O47: 5.1 | P47: 3.1 | Q47: 4.2 | R47: 20 | S47: 20 | T47: 20 | U47: 13 | V47: 9.7 | W47: 42.9 | X47: 61.2 | Y47: 71.5 | Z47: 83.4 | AB47: 7.7 | AC47: 4.7 | AD47: 9.4 | AE47: 3.3 | AF47: 8.6 | AG47: 9.4 | AH47: 9.5 | AI47: 8.5 | AK47: 10.9 | AL47: 15.2 | AM47: 3.6 | AN47: 18.5 | AR47: 1.5 | AU47: 5.5 | AV47: 9.9 | AW47: 104.7 | AY47: 112.7 | BA47: 0.6 | BC47: 20.2 | BD47: 63.4 | BE47: 15.9 | BF47: 4.4 | BG47: 3 | BH47: 1 | BI47: 2.2 | BK47: 0.7 | BM47: 20 | BN47: 9.8 | BP47: 910.6
B48: 20:30 | C48: 17 | E48: 6.6 | F48: 10.1 | G48: 2.2 | I48: 9.1 | K48: 11.5 | M48: 6.7 | N48: 9.3 | O48: 5.4 | P48: 3.1 | Q48: 4.1 | R48: 19.9 | S48: 19.9 | T48: 20 | U48: 13 | V48: 10.4 | W48: 35.9 | X48: 65.4 | Y48: 69.9 | Z48: 80.1 | AB48: 8.9 | AC48: 6.6 | AD48: 9.4 | AE48: 3.3 | AF48: 8.6 | AG48: 9.4 | AH48: 9.5 | AI48: 8.2 | AK48: 9.3 | AL48: 11.9 | AM48: 3.6 | AN48: 18.5 | AR48: 1.5 | AU48: 5.5 | AV48: 9.8 | AW48: 60.3 | AY48: 66.7 | BA48: 0.6 | BC48: 20.6 | BD48: 54.3 | BE48: 15.9 | BF48: 4.4 | BG48: 3 | BH48: 1 | BI48: 2.2 | BK48: 0.6 | BM48: 20 | BN48: 9.8 | BP48: 803
B49: 21:00 | C49: 16.9 | E49: 6.3 | F49: 10 | G49: 2.2 | I49: 9.1 | K49: 11.5 | M49: 6.8 | N49: 9.5 | O49: 5.5 | P49: 3.1 | Q49: 4.1 | R49: 19.9 | S49: 20.1 | T49: 20 | U49: 12.3 | V49: 10.9 | W49: 36.1 | X49: 61.2 | Y49: 67.9 | Z49: 80.4 | AB49: 7.3 | AC49: 4.4 | AD49: 9.4 | AE49: 3.3 | AF49: 8.6 | AG49: 9.2 | AH49: 9.3 | AI49: 8.3 | AK49: 7 | AL49: 11.1 | AM49: 3.6 | AN49: 18.5 | AR49: 1.5 | AU49: 5.5 | AV49: 9.8 | AW49: 38.1 | AY49: 40.8 | BA49: 0.6 | BC49: 12.5 | BD49: 33.6 | BE49: 15.8 | BF49: 4.4 | BG49: 3 | BH49: 1 | BI49: 2.2 | BK49: 0.6 | BM49: 20 | BN49: 9.8 | BP49: 713
B50: 21:30 | C50: 17 | E50: 6.8 | F50: 10.1 | G50: 2.1 | I50: 9.4 | K50: 11.5 | M50: 6.7 | N50: 9.4 | O50: 5.5 | P50: 3.1 | Q50: 4 | R50: 20 | S50: 19.8 | T50: 20 | U50: 12.3 | V50: 7.7 | W50: 27.1 | X50: 61.6 | Y50: 65.4 | Z50: 80.3 | AB50: 5.7 | AC50: 3.8 | AD50: 9.4 | AE50: 3.3 | AF50: 8.6 | AG50: 9.2 | AH50: 9.3 | AI50: 8.2 | AK50: 10.4 | AL50: 12.3 | AM50: 3.6 | AN50: 18.5 | AR50: 1.5 | AU50: 5.5 | AV50: 9.9 | AW50: 29.2 | AY50: 31.1 | BA50: 0.6 | BC50: 12.8 | BD50: 30.4 | BE50: 15.8 | BF50: 4.4 | BG50: 3 | BH50: 1 | BI50: 2.2 | BK50: 0.6 | BM50: 19.8 | BN50: 9.7 | BP50: 679.6
B51: 22:00 | C51: 17 | E51: 6.9 | F51: 10.1 | G51: 2 | I51: 9.2 | K51: 11.5 | M51: 6.7 | N51: 9.2 | O51: 5.5 | P51: 3 | Q51: 4.2 | R51: 20 | S51: 19.8 | T51: 20 | U51: 12.3 | V51: 9.4 | W51: 25.2 | X51: 48.1 | Y51: 72.2 | Z51: 84.1 | AB51: 8.3 | AC51: 4.6 | AD51: 9.4 | AE51: 3.3 | AF51: 8.4 | AG51: 9.2 | AH51: 9.3 | AI51: 8.2 | AK51: 11.1 | AL51: 13 | AM51: 3.6 | AN51: 18.5 | AR51: 1.5 | AU51: 5.5 | AV51: 9.9 | AW51: 50.9 | AY51: 52.8 | BA51: 0.6 | BC51: 15.4 | BD51: 32.4 | BE51: 15.8 | BF51: 4.4 | BG51: 3 | BH51: 1 | BI51: 2.2 | BK51: 0.6 | BM51: 20 | BN51: 9.8 | BP51: 729.1
B52: 22:30 | C52: 17.7 | E52: 6.8 | F52: 10.1 | G52: 2 | I52: 9.4 | K52: 11.5 | M52: 6.7 | N52: 9.4 | O52: 5.4 | P52: 3 | Q52: 4.3 | R52: 20 | S52: 20 | T52: 20 | U52: 12.3 | V52: 11.2 | W52: 22.9 | X52: 42.5 | Y52: 69.2 | Z52: 79.5 | AB52: 6.6 | AC52: 4.3 | AD52: 9.4 | AE52: 3.3 | AF52: 8.4 | AG52: 9.2 | AH52: 9.3 | AI52: 8.2 | AK52: 10.1 | AL52: 13.3 | AM52: 3.6 | AN52: 18.5 | AR52: 1.5 | AU52: 5.5 | AV52: 9.9 | AW52: 65.9 | AY52: 83 | BA52: 0.6 | BC52: 12.3 | BD52: 42.2 | BE52: 15.8 | BF52: 4.4 | BG52: 3 | BH52: 1 | BI52: 2.2 | BK52: 0.6 | BM52: 20 | BN52: 9.8 | BP52: 765.8
B53: 23:00 | C53: 17.6 | E53: 7.3 | F53: 10.1 | G53: 2 | I53: 9.4 | K53: 11.5 | M53: 6.8 | N53: 9.6 | O53: 5.4 | P53: 3 | Q53: 4.3 | R53: 19.9 | S53: 20.2 | T53: 20 | U53: 12.3 | V53: 12.4 | W53: 18.5 | X53: 53.5 | Y53: 69.6 | Z53: 84.4 | AB53: 7.3 | AC53: 4 | AD53: 9.4 | AE53: 3.3 | AF53: 8.4 | AG53: 9.2 | AH53: 9.3 | AI53: 8.2 | AK53: 10.3 | AL53: 14.6 | AM53: 3.6 | AN53: 18.5 | AR53: 1.5 | AU53: 5.3 | AV53: 9.9 | AW53: 99.1 | AY53: 100.4 | BA53: 0.6 | BC53: 19 | BD53: 46.7 | BE53: 15.8 | BF53: 4.4 | BG53: 3 | BH53: 1 | BI53: 2.2 | BK53: 0.6 | BM53: 19.9 | BN53: 9.7 | BP53: 843
... B55: 0:00 | C55: 17.8 | E55: 7.3 | F55: 10.1 | G55: 1.9 | I55: 9.4 | K55: 11.5 | M55: 6.8 | N55: 8.9 | O55: 5.4 | P55: 3 | Q55: 4.2 | R55: 19.9 | S55: 19.6 | T55: 20 | U55: 12.4 | V55: 7.5 | W55: 15.5 | X55: 50.3 | Y55: 70.2 | Z55: 84.1 | AB55: 7.7 | AC55: 5.4 | AD55: 9.3 | AE55: 3.2 | AF55: 8.3 | AG55: 9.1 | AH55: 9.2 | AI55: 8.1 | AK55: 13.6 | AL55: 15.5 | AM55: 3.6 | AN55: 18.5 | AR55: 1.5 | AU55: 5.4 | AV55: 9.9 | AW55: 80.3 | AY55: 84.1 | BA55: 0.6 | BC55: 14.2 | BD55: 36.2 | BE55: 15.9 | BF55: 4.4 | BG55: 3 | BH55: 1 | BI55: 2.2 | BK55: 0.6 | BM55: 20 | BN55: 9.8 | BP55: 786.4
B56: EJEC MWh | C56: 354.1 | D56: 0 | E56: 152.85 | F56: 244.5 | G56: 46.45 | H56: 0 | I56: 220.9 | J56: 8.15 | K56: 294 | L56: 0 | M56: 172.45 | N56: 242.95 | O56: 126.35 | P56: 75.6 | Q56: 102.5 | R56: 478.4 | S56: 478.35 | T56: 480 | U56: 294.05 | V56: 282.4 | W56: 544.2 | X56: 1123.05 | Y56: 918.9 | Z56: 1086.3 | AA56: 247.4 | AB56: 133.2 | AC56: 86.7 | AD56: 233.05 | AE56: 79.5 | AF56: 206.85 | AG56: 224.8 | AH56: 228.1 | AI56: 199.45 | AJ56: 598 | AK56: 252.8 | AL56: 320.85 | AM56: 85 | AN56: 444 | AO56: 0 | AP56: 1890.8 | AQ56: 2.6 | AR56: 27 | AS56: 114.2 | AT56: 117 | AU56: 120.1 | AV56: 237.2 | AW56: 1488.1 | AX56: 1029.4 | AY56: 1306.05 | AZ56: 766.65 | BA56: 14.4 | BB56: 140.7 | BC56: 334.15 | BD56: 1010.45 | BE56: 394.1 | BF56: 68.7 | BG56: 73.1 | BH56: 24.8 | BI56: 56 | BJ56: 114.25 | BK56: 16.4 | BL56: 0 | BM56: 479.4 | BN56: 234.8 | BO56: 106.1 | BP56: 21232.6
L70: TERMOELÉCTRICA | M70: 950.45 | N70: 4.4763712 | O70: #FFA975
L71: SOLAR | M71: 5135.25 | N71: 24.185686 | O71: #FFD272
L72: HIDROELÉCTRICA | M72: 6259.75 | N72: 29.481787 | O72: #98D2FF
L73: EÓLICA | M73: 8887.15 | N73: 41.856155 | O73: #B9ACFF

Sheet COGENERACIÓN
B3: jueves, 5 de Junio del 2025
B5: CENTRALES DE COGENERACIÓN DEL SEIN
B6: HORA | C6: AGRO INDUSTRIAL PARAMONGA S.A. | D6: AGROAURORA S.A.C. | E6: AGROINDUSTRIAS SAN JACINTO S.A.A. | F6: BIOENERGIA DEL CHIRA S.A. | G6: GM OPERACIONES S.A.C. | H6: SDF ENERGIA SAC | I6: TOTAL COGENERACION
C7: C.T. PARAMONGA | D7: C.T. MAPLE | E7: C.T SAN JACINTO | F7: C.T. CAÑA BRAVA | G7: C.T. REFINERÍA TALARA | H7: C.T. OQUENDO | I7: MW
B8: 0:30 | C8: 16.2 | E8: 6.2 | F8: 9.2 | G8: 60.5 | I8: 92.1
B9: 1:00 | C9: 16.1 | E9: 6.7 | F9: 9.3 | G9: 60.3 | I9: 92.4
B10: 1:30 | C10: 16.2 | E10: 6.3 | F10: 9.6 | G10: 60.4 | I10: 92.5
B11: 2:00 | C11: 16.3 | E11: 6.5 | F11: 9.4 | G11: 60.7 | I11: 92.9
B12: 2:30 | C12: 16.4 | E12: 4.9 | F12: 9.7 | G12: 60.7 | I12: 91.7
B13: 3:00 | C13: 16.2 | E13: 6.5 | F13: 8.6 | G13: 60.8 | I13: 92.1
B14: 3:30 | C14: 16.3 | E14: 6.3 | F14: 9.1 | G14: 60.9 | I14: 92.6
B15: 4:00 | C15: 16.2 | E15: 5.8 | F15: 9.3 | G15: 60.8 | I15: 92.1
B16: 4:30 | C16: 16.1 | E16: 6.4 | F16: 9.4 | G16: 60.9 | I16: 92.8
B17: 5:00 | C17: 16.3 | E17: 3.6 | F17: 9.4 | G17: 61 | I17: 90.3
B18: 5:30 | C18: 16.2 | E18: 6.3 | F18: 9.5 | G18: 60.8 | I18: 92.8
B19: 6:00 | C19: 8 | E19: 6.5 | F19: 9.2 | G19: 60.7 | I19: 84.4
B20: 6:30 | C20: 8 | E20: 6.5 | F20: 9 | G20: 60.8 | I20: 84.3
B21: 7:00 | E21: 6.1 | F21: 9.3 | G21: 60.8 | I21: 76.2
B22: 7:30 | E22: 6.5 | F22: 9.4 | G22: 60.7 | I22: 76.6
B23: 8:00 | E23: 6.6 | F23: 8.6 | G23: 60.9 | I23: 76.1
B24: 8:30 | C24: 1 | E24: 5.3 | F24: 9.2 | G24: 61.2 | I24: 76.7
B25: 9:00 | C25: 2 | E25: 5.4 | F25: 9.3 | G25: 61 | I25: 77.7
B26: 9:30 | C26: 17.3 | E26: 5.2 | F26: 9.4 | G26: 60.6 | I26: 92.5
B27: 10:00 | C27: 16.9 | E27: 4.1 | F27: 9.1 | G27: 60.6 | I27: 90.7
B28: 10:30 | C28: 16.6 | E28: 4.2 | F28: 8.6 | G28: 58.6 | I28: 88
B29: 11:00 | C29: 16.1 | E29: 6.6 | F29: 9.1 | G29: 53.5 | I29: 85.3
B30: 11:30 | C30: 16.8 | E30: 6.9 | F30: 9 | G30: 53.3 | I30: 86
B31: 12:00 | C31: 16.8 | E31: 7.1 | F31: 9.2 | G31: 57.6 | I31: 90.7
B32: 12:30 | C32: 16.5 | E32: 6.7 | F32: 9.3 | G32: 57.8 | I32: 90.3
B33: 13:00 | C33: 17 | E33: 6.3 | F33: 9.2 | G33: 57.7 | I33: 90.2
B34: 13:30 | C34: 17.2 | E34: 6.8 | F34: 9.3 | G34: 57.4 | I34: 90.7
B35: 14:00 | C35: 17.7 | E35: 6.8 | F35: 9 | G35: 57.8 | I35: 91.3
... B55: 0:00 | C55: 17.8 | E55: 7.3 | F55: 9.4 | G55: 57.2 | I55: 91.7
B56: EJEC MWh | C56: 354.1 | D56: 0 | E56: 152.85 | F56: 220.9 | G56: 1408.95 | H56: 0 | I56: 2136.8

Sheet EVO_PRO_ENE
B3: domingo, 1 de Junio del 2025 - jueves, 5 de Junio del 2025
B5: EVOLUCIÓN DE LA PRODUCCIÓN DE LA ENERGÍA DIARIA DE LOS INTEGRANTES DEL COES (MWh)
B6: EMPRESA | C6: CENTRAL | D6: UNIDAD | E6: TIPO | F6: Junio
F7: 1 | G7: 2 | H7: 3 | I7: 4 | J7: 5 | K7: TOTAL
B8: AGRO INDUSTRIAL PARAMONGA S.A. | C8: C.T. PARAMONGA | D8: TV-01 | E8: TERMOELÉCTRICA | F8: 368.9 | I8: 47.15 | J8: 354.1 | K8: 770.15
B9: AGROAURORA S.A.C. | C9: C.T. MAPLE ETANOL | D9: TV | E9: TERMOELÉCTRICA | K9: 0
B10: AGROINDUSTRIAS SAN JACINTO S.A.A. | C10: C.T. SAN JACINTO | D10: CENTRAL | E10: TERMOELÉCTRICA | H10: 54.85 | I10: 141.15 | J10: 152.85 | K10: 348.85
B11: ANDEAN POWER S.A.C. | C11: C.H.CARHUAC | D11: CENTRAL | E11: HIDROELÉCTRICA | F11: 276.6 | G11: 274.7 | H11: 261.15 | I11: 250.45 | J11: 244.5 | K11: 1307.4
B12: ASOCIACIÓN SANTA LUCIA DE CHACAS | C12: C.H. HUALLIN | D12: CENTRAL | E12: HIDROELÉCTRICA | F12: 66.4 | G12: 59.9 | H12: 49.8 | I12: 47.15 | J12: 46.45 | K12: 269.7
B13: ATRIA ENERGIA S.A.C. | C13: C.H. PURMACANA | D13: CENTRAL | E13: HIDROELÉCTRICA | F13: 9.6 | G13: 6.75 | K13: 16.35
B14: BIOENERGIA DEL CHIRA S.A. | C14: C.T. CAÑA BRAVA | D14: CENTRAL | E14: TERMOELÉCTRICA | F14: 239.65 | G14: 205.85 | H14: 231.9 | I14: 225.75 | J14: 220.9 | K14: 1124.05
B15: CELEPSA | C15: C.H. EL PLATANAL | D15: CENTRAL | E15: HIDROELÉCTRICA | F15: 3914.5 | G15: 4008.9 | H15: 3906.9 | I15: 3839.5 | J15: 3591.4 | K15: 19261.2
B16: CELEPSA RENOVABLES S.R.L. | C16: C.H. MARAÑON | D16: CENTRAL | E16: HIDROELÉCTRICA | F16: 472.8 | G16: 472.8 | H16: 472.8 | I16: 382.2 | J16: 257.65 | K16: 2058.25
B17: CENTRALES SANTA ROSA S.A.C. | C17: C.H. SANTA ROSA I | D17: CENTRAL | E17: HIDROELÉCTRICA | K17: 0
B18: CENTRALES SANTA ROSA S.A.C. | C18: C.H. SANTA ROSA II | D18: CENTRAL | E18: HIDROELÉCTRICA | K18: 0
B19: CHINANGO S.A.C. | C19: C.H. CHIMAY | D19: CENTRAL | E19: HIDROELÉCTRICA | F19: 3163.1 | G19: 2553.85 | H19: 2402.4 | I19: 1960.25 | J19: 1810.7 | K19: 11890.3
B20: CHINANGO S.A.C. | C20: C.H. YANANGO | D20: CENTRAL | E20: HIDROELÉCTRICA | F20: 908.7 | G20: 836.85 | H20: 757.35 | I20: 705.7 | J20: 644.75 | K20: 3853.35
B21: COLCA SOLAR S.A.C. | C21: C.S. YARUCAYA | D21: CENTRAL | E21: SOLAR | F21: 7.2 | G21: 5.7 | H21: 8.2 | I21: 8.15 | J21: 8.15 | K21: 37.4
B22: EGASA | C22: C.H. CHARCANI III | D22: CENTRAL | E22: HIDROELÉCTRICA | F22: 153.75 | G22: 163.65 | H22: 163.85 | I22: 163.55 | J22: 163.65 | K22: 808.45
B23: EGASA | C23: C.H. CHARCANI IV | D23: CENTRAL | E23: HIDROELÉCTRICA | F23: 256.2 | G23: 304.1 | H23: 312.6 | I23: 302.85 | J23: 310.5 | K23: 1486.25
B24: EGASA | C24: C.H. CHARCANI V | D24: CENTRAL | E24: HIDROELÉCTRICA | F24: 1638.05 | G24: 1930.75 | H24: 1952.75 | I24: 1926.8 | J24: 1981.05 | K24: 9429.4
B25: EGASA | C25: C.H. CHARCANI VI | D25: CENTRAL | E25: HIDROELÉCTRICA | K25: 0
B26: EGASA | C26: C.T. CHILINA DIESEL | D26: CENTRAL | E26: TERMOELÉCTRICA | K26: 0
B27: EGASA | C27: C.T. CHILINA DIESEL | D27: TG | E27: TERMOELÉCTRICA | K27: 0
B28: EGASA | C28: C.T. MOLLENDO DIESEL | D28: CENTRAL | E28: TERMOELÉCTRICA | K28: 0
B29: EGEJUNIN | C29: C.H. HUASAHUASI I | D29: CENTRAL | E29: HIDROELÉCTRICA | F29: 433.25 | G29: 400 | H29: 355.25 | I29: 317.6 | J29: 294 | K29: 1800.1
B30: EGEJUNIN | C30: C.H. RUNATULLO II | D30: CENTRAL | E30: HIDROELÉCTRICA | F30: 133.05 | G30: 224.5 | H30: 206.8 | I30: 187.4 | J30: 172.45 | K30: 924.2
B31: EGEJUNIN | C31: C.H. RUNATULLO III | D31: CENTRAL | E31: HIDROELÉCTRICA | F31: 194.95 | G31: 329.5 | H31: 301.35 | I31: 267.25 | J31: 242.95 | K31: 1336
B32: EGEJUNIN | C32: C.H. SANTA CRUZ I | D32: CENTRAL | E32: HIDROELÉCTRICA | F32: 152.8 | G32: 143.85 | H32: 123.9 | I32: 130.2 | J32: 126.35 | K32: 677.1
B33: EGEMSA | C33: C.H. MACHUPICCHU | D33: CENTRAL | E33: HIDROELÉCTRICA | F33: 3969.65 | G33: 3948.7 | H33: 3939.75 | I33: 3945.95 | J33: 3918.4 | K33: 19722.45
B34: EGESUR | C34: C.H. ARICOTA I | D34: CENTRAL | E34: HIDROELÉCTRICA | F34: 175.9 | G34: 174.9 | H34: 175.35 | I34: 174.35 | J34: 173.75 | K34: 874.25
B35: EGESUR | C35: C.H. ARICOTA II | D35: CENTRAL | E35: HIDROELÉCTRICA | F35: 100.35 | G35: 131.4 | H35: 130.9 | I35: 129.5 | J35: 127.2 | K35: 619.35
B36: EGESUR | C36: C.T. INDEPENDENCIA | D36: CENTRAL | E36: TERMOELÉCTRICA | F36: 42.85 | G36: 323.8 | H36: 385.75 | I36: 375.15 | K36: 1127.55
B37: ELECTRICA YANAPAMPA SAC | C37: C.H. YANAPAMPA | D37: CENTRAL | E37: HIDROELÉCTRICA | F37: 76.95 | G37: 78.05 | H37: 77.2 | I37: 76.35 | J37: 75.6 | K37: 384.15
B38: ELECTROPERU | C38: C.H. MANTARO | D38: CENTRAL | E38: HIDROELÉCTRICA | F38: 15079.95 | G38: 15544 | H38: 15538.75 | I38: 15327.2 | J38: 15233.7 | K38: 76723.6
B39: ELECTROPERU | C39: C.H. RESTITUCION | D39: CENTRAL | E39: HIDROELÉCTRICA | F39: 5046.1 | G39: 5216.4 | H39: 4346.85 | I39: 5125.75 | J39: 5110.4 | K39: 24845.5
B40: ELECTROPERU | C40: C.T. TUMBES | D40: MAK1 | E40: TERMOELÉCTRICA | K40: 0
B41: ELECTROPERU | C41: C.T. TUMBES | D41: MAK2 | E41: TERMOELÉCTRICA | K41: 0
B42: EMPRESA DE GENERACION ELECTRICA CANCHAYLLO SAC | C42: C.H. CANCHAYLLO | D42: CENTRAL | E42: HIDROELÉCTRICA | F42: 108.8 | G42: 108.4 | H42: 105.4 | I42: 104.3 | J42: 102.5 | K42: 529.4
B43: EMPRESA DE GENERACION ELECTRICA RIO BAÑOS S.A.C. | C43: C.H. RUCUY | D43: CENTRAL | E43: HIDROELÉCTRICA | F43: 478.65 | G43: 479.65 | H43: 478.85 | I43: 479.65 | J43: 478.4 | K43: 2395.2
B44: EMPRESA DE GENERACION ELECTRICA SANTA ANA S.A.C. | C44: C.H. RENOVANDES H1 | D44: CENTRAL | E44: HIDROELÉCTRICA | F44: 389.9 | G44: 479.65 | H44: 479.9 | I44: 480.3 | J44: 478.35 | K44: 2308.1
B45: EMPRESA DE GENERACION HUALLAGA | C45: C.H. CHAGLLA | D45: CENTRAL | E45: HIDROELÉCTRICA | F45: 10930.4 | G45: 8482.2 | H45: 5342.6 | I45: 4829.4 | J45: 5367.9 | K45: 34952.5
B46: EMPRESA DE GENERACION HUALLAGA | C46: P.C.H. CHAGLLA | D46: CENTRAL | E46: HIDROELÉCTRICA | F46: 156.05 | G46: 156 | H46: 156 | I46: 156 | J46: 156 | K46: 780.05
B47: EMPRESA DE GENERACION HUANZA | C47: C.H. HUANZA | D47: CENTRAL | E47: HIDROELÉCTRICA | K47: 0
B48: EMPRESA ELECTRICA AGUA AZUL | C48: C.H. POTRERO | D48: CENTRAL | E48: HIDROELÉCTRICA | F48: 364.95 | G48: 344.6 | H48: 480 | I48: 480 | J48: 480 | K48: 2149.55
B49: EMPRESA ELECTRICA RIO DOBLE | C49: C.H. LAS PIZARRAS | D49: CENTRAL | E49: HIDROELÉCTRICA | F49: 391.9 | G49: 365.85 | H49: 340.45 | I49: 324.65 | J49: 294.05 | K49: 1716.9
B50: ENEL GENERACION PIURA S.A. | C50: C.T. MALACAS 1 | D50: TG6 | E50: TERMOELÉCTRICA | F50: 23.65 | K50: 23.65
B51: ENEL GENERACION PIURA S.A. | C51: C.T. MALACAS 2 | D51: TG4 | E51: TERMOELÉCTRICA | K51: 0
B52: ENEL GENERACION PIURA S.A. | C52: C.T. RF DE GENERACION TALARA | D52: TG5 | E52: TERMOELÉCTRICA | K52: 0
B53: ENERGÍA EÓLICA S.A. | C53: C.E. CUPISNIQUE | D53: CENTRAL | E53: EÓLICA | F53: 664.7 | G53: 590.4 | H53: 472.4 | I53: 475.7 | J53: 544.2 | K53: 2747.4
B54: ENERGÍA EÓLICA S.A. | C54: C.E. TALARA | D54: CENTRAL | E54: EÓLICA | F54: 221.6 | G54: 439.4 | H54: 292.3 | I54: 483.05 | J54: 282.4 | K54: 1718.75
B55: ENERGIA RENOVABLE DEL SUR S.A. | C55: C.E. SAN JUAN | D55: CENTRAL | E55: EÓLICA | F55: 1652.9 | G55: 1228.15 | H55: 1006.15 | I55: 621.85 | J55: 1123.05 | K55: 5632.1
B56: ENGIE | C56: C.E. PUNTA LOMITAS | D56: PL-BL1 | E56: EÓLICA | F56: 486 | G56: 240.75 | H56: 405.05 | I56: 958.7 | J56: 918.9 | K56: 3009.4
B57: ENGIE | C57: C.E. PUNTA LOMITAS | D57: PL-BL2 | E57: EÓLICA | F57: 853.3 | G57: 628.75 | H57: 853.9 | I57: 1130.9 | J57: 1086.3 | K57: 4553.15
B58: ENGIE | C58: C.E. PUNTA LOMITAS_EXP | D58: PUN LOM_EXP-BL1 | E58: EÓLICA | F58: 53.2 | G58: 25.45 | H58: 35.9 | I58: 124.95 | J58: 133.2 | K58: 372.7
B59: ENGIE | C59: C.E. PUNTA LOMITAS_EXP | D59: PUN LOM_EXP-BL2 | E59: EÓLICA | F59: 49.35 | G59: 32.05 | H59: 54.95 | I59: 95.5 | J59: 86.7 | K59: 318.55
B60: ENGIE | C60: C.H. QUITARACSA | D60: CENTRAL | E60: HIDROELÉCTRICA | K60: 0
B61: ENGIE | C61: C.H. YUNCAN | D61: CENTRAL | E61: HIDROELÉCTRICA | F61: 2072.3 | G61: 2075.3 | H61: 2075.5 | I61: 2039.35 | J61: 1965.35 | K61: 10227.8
B62: ENGIE | C62: C.S. INTIPAMPA | D62: CENTRAL | E62: SOLAR | F62: 249 | G62: 255.45 | H62: 252 | I62: 248.65 | J62: 247.4 | K62: 1252.5
B63: ENGIE | C63: C.T. CHILCA 1 | D63: TG1 | E63: TERMOELÉCTRICA | F63: 240.9 | G63: 2602.65 | H63: 3644.2 | I63: 4264.25 | J63: 4250.8 | K63: 15002.8
B64: ENGIE | C64: C.T. CHILCA 1 | D64: TG2 | E64: TERMOELÉCTRICA | F64: 400.2 | G64: 2538.85 | H64: 4173.2 | I64: 4214.05 | J64: 4200 | K64: 15526.3
B65: ENGIE | C65: C.T. CHILCA 1 | D65: TG3 | E65: TERMOELÉCTRICA | F65: 3642.8 | G65: 3350.4 | H65: 4666.8 | I65: 4800 | J65: 4774.8 | K65: 21234.8
B66: ENGIE | C66: C.T. CHILCA 1 | D66: TV | E66: TERMOELÉCTRICA | F66: 1700.9 | G66: 2837.7 | H66: 6150.15 | I66: 6608.9 | J66: 6589.3 | K66: 23886.95
B67: ENGIE | C67: C.T. CHILCA 2 | D67: TG41 | E67: TERMOELÉCTRICA | G67: 1280.9 | H67: 371.9 | I67: 315.85 | K67: 1968.65
B68: ENGIE | C68: C.T. CHILCA 2 | D68: TV42 | E68: TERMOELÉCTRICA | K68: 0
B69: ENGIE | C69: C.T. NEPI | D69: TG41 | E69: TERMOELÉCTRICA | K69: 0
B70: ENGIE | C70: C.T. NEPI | D70: TG42 | E70: TERMOELÉCTRICA | K70: 0
B71: ENGIE | C71: C.T. NEPI | D71: TG43 | E71: TERMOELÉCTRICA | K71: 0
B72: ENGIE | C72: C.T. RF PLANTA ILO | D72: TG1 | E72: TERMOELÉCTRICA | K72: 0
B73: ENGIE | C73: C.T. RF PLANTA ILO | D73: TG2 | E73: TERMOELÉCTRICA | K73: 0
B74: ENGIE | C74: C.T. RF PLANTA ILO | D74: TG3 | E74: TERMOELÉCTRICA | K74: 0
B75: FENIX POWER PERÚ | C75: C.T. FENIX | D75: GT11 | E75: TERMOELÉCTRICA | F75: 3488.35 | G75: 4366.65 | H75: 4375.65 | I75: 4374.25 | J75: 3818.75 | K75: 20423.65
B76: FENIX POWER PERÚ | C76: C.T. FENIX | D76: GT12 | E76: TERMOELÉCTRICA | F76: 3496.7 | G76: 4381.1 | H76: 4389.55 | I76: 4382.65 | J76: 3829.2 | K76: 20479.2
B77: FENIX POWER PERÚ | C77: C.T. FENIX | D77: TV10 | E77: TERMOELÉCTRICA | F77: 3940.95 | G77: 4412.25 | H77: 4423.7 | I77: 4436.45 | J77: 4133.1 | K77: 21346.45
B78: GENERACIÓN ANDINA S.A.C. | C78: C.H. 8 DE AGOSTO | D78: CENTRAL | E78: HIDROELÉCTRICA | F78: 334.2 | G78: 384.4 | H78: 306.4 | I78: 260.7 | J78: 233.05 | K78: 1518.75
B79: GENERACIÓN ANDINA S.A.C. | C79: C.H. EL CARMEN | D79: CENTRAL | E79: HIDROELÉCTRICA | F79: 140.25 | G79: 108 | H79: 90.55 | I79: 83.4 | J79: 79.5 | K79: 501.7
B80: GENERADORA DE ENERGÍA DEL PERÚ | C80: C.H. ÁNGEL I | D80: CENTRAL | E80: HIDROELÉCTRICA | F80: 242.9 | G80: 237.4 | H80: 226.3 | I80: 214.25 | J80: 206.85 | K80: 1127.7
B81: GENERADORA DE ENERGÍA DEL PERÚ | C81: C.H. ÁNGEL II | D81: CENTRAL | E81: HIDROELÉCTRICA | F81: 250.1 | G81: 255.4 | H81: 242.85 | I81: 232.1 | J81: 224.8 | K81: 1205.25
B82: GENERADORA DE ENERGÍA DEL PERÚ | C82: C.H. ÁNGEL III | D82: CENTRAL | E82: HIDROELÉCTRICA | F82: 252.15 | G82: 258.25 | H82: 247.9 | I82: 237.15 | J82: 228.1 | K82: 1223.55
B83: GENERADORA DE ENERGÍA DEL PERÚ | C83: C.H. LA JOYA | D83: CENTRAL | E83: HIDROELÉCTRICA | G83: 157.35 | H83: 204 | I83: 194.25 | J83: 199.45 | K83: 755.05
B84: GM OPERACIONES S.A.C. | C84: CT REFINERIA TALARA | D84: TV1 REF TALARA | E84: TERMOELÉCTRICA | F84: 1044.7 | G84: 1044.4 | H84: 1045.85 | I84: 1057 | J84: 1060.65 | K84: 5252.6
B85: GM OPERACIONES S.A.C. | C85: CT REFINERIA TALARA | D85: TV2 REF TALARA | E85: TERMOELÉCTRICA | F85: 358.55 | G85: 379.8 | H85: 384.1 | I85: 394.8 | J85: 348.3 | K85: 1865.55
B86: GR CORTARRAMA SOCIEDAD ANONIMA CERRADA | C86: C.S. MATARANI | D86: C.S. MATARANI | E86: SOLAR | F86: 597.4 | G86: 602.7 | H86: 597.35 | I86: 590.45 | J86: 598 | K86: 2985.9
B87: GR PAINO SOCIEDAD ANONIMA CERRADA | C87: C.E. HUAMBOS | D87: CENTRAL | E87: EÓLICA | F87: 219.95 | G87: 318.85 | H87: 272.7 | I87: 192.5 | J87: 252.8 | K87: 1256.8
B88: GR TARUCA SOCIEDAD ANONIMA CERRADA | C88: C.E. DUNA | D88: CENTRAL | E88: EÓLICA | F88: 289.15 | G88: 369.05 | H88: 336.2 | I88: 262.5 | J88: 320.85 | K88: 1577.75
B89: HIDROCAÑETE S.A. | C89: C.H. IMPERIAL | D89: CENTRAL | E89: HIDROELÉCTRICA | F89: 78.5 | G89: 79.1 | H89: 84.1 | I89: 84.2 | J89: 85 | K89: 410.9
B90: HIDROELECTRICA HUANCHOR S.A.C. | C90: C.H. HUANCHOR | D90: CENTRAL | E90: HIDROELÉCTRICA | F90: 450.4 | G90: 450.65 | H90: 450.95 | I90: 450.85 | J90: 450.7 | K90: 2253.55
B91: HUAURA POWER GROUP S.A. | C91: C.H. YARUCAYA | D91: CENTRAL | E91: HIDROELÉCTRICA | F91: 445.5 | G91: 446.25 | H91: 444.3 | I91: 444 | J91: 444 | K91: 2224.05
B92: HYDRO GLOBAL PERÚ S.A.C. | C92: CH SAN GABAN III | D92: CHSAN GABAN III | E92: HIDROELÉCTRICA | I92: 1325.8 | J92: 3106.9 | K92: 4432.7
B93: INFRAESTRUCTURAS Y ENERGIAS DEL PERU S.A.C. | C93: C.T. RF PTO MALDONADO | D93: CENTRAL | E93: TERMOELÉCTRICA | I93: 30.95 | K93: 30.95
B94: INFRAESTRUCTURAS Y ENERGIAS DEL PERU S.A.C. | C94: C.T. RF PUCALLPA | D94: CENTRAL | E94: TERMOELÉCTRICA | G94: 1.65 | K94: 1.65
B95: INLAND ENERGY SAC | C95: C.H. SANTA TERESA | D95: CENTRAL | E95: HIDROELÉCTRICA | F95: 2159.2 | G95: 2154.8 | H95: 2159.3 | I95: 2150.85 | J95: 2139.5 | K95: 10763.65
B96: INVERSIONES SHAQSHA S.A.C. | C96: C.H. PARIAC | D96: CENTRAL | E96: HIDROELÉCTRICA | F96: 101.3 | G96: 98.3 | H96: 96.5 | I96: 97.05 | J96: 95.05 | K96: 488.2
B97: JOYA SOLAR S.A.C. | C97: C.S. SAN MARTIN SOLAR | D97: CENTRAL | E97: SOLAR | F97: 2014.6 | G97: 1925.95 | H97: 1913.85 | I97: 1893.85 | J97: 1890.8 | K97: 9639.05
B98: KALLPA GENERACION S.A. | C98: C.H. CERRO DEL AGUILA | D98: CENTRAL | E98: HIDROELÉCTRICA | F98: 8853.95 | G98: 12436.3 | H98: 11849.95 | I98: 11353.25 | J98: 12137.1 | K98: 56630.55
B99: KALLPA GENERACION S.A. | C99: C.T. KALLPA | D99: TG1 | E99: TERMOELÉCTRICA | F99: 36.65 | G99: 1303.9 | H99: 492.6 | K99: 1833.15
B100: KALLPA GENERACION S.A. | C100: C.T. KALLPA | D100: TG2 | E100: TERMOELÉCTRICA | F100: 4487 | G100: 4970.8 | H100: 4953.95 | I100: 4964.35 | J100: 4651.2 | K100: 24027.3
B101: KALLPA GENERACION S.A. | C101: C.T. KALLPA | D101: TG3 | E101: TERMOELÉCTRICA | F101: 4522.8 | G101: 5028.9 | H101: 5029.6 | I101: 5032.7 | J101: 4688.3 | K101: 24302.3
B102: KALLPA GENERACION S.A. | C102: C.T. KALLPA | D102: TV | E102: TERMOELÉCTRICA | F102: 4469.85 | G102: 4798.1 | H102: 4775.35 | I102: 4785.6 | J102: 4590.9 | K102: 23419.8
B103: KALLPA GENERACION S.A. | C103: C.T. LAS FLORES | D103: TG1 | E103: TERMOELÉCTRICA | F103: 4743.85 | K103: 4743.85
...

Sheet G_AREAS
B3: jueves, 5 de Junio del 2025
B5: HORA | C5: RESUMEN DE GENERACIÓN POR ÁREAS DEL SEIN | D5: RESUMEN DE GENERACIÓN POR ÁREAS DEL SEIN | E5: RESUMEN DE GENERACIÓN POR ÁREAS DEL SEIN | F5: RESUMEN DE GENERACIÓN POR ÁREAS DEL SEIN | G5: RESUMEN DE GENERACIÓN POR ÁREAS DEL SEIN | H5: RESUMEN DE GENERACIÓN POR ÁREAS DEL SEIN | I5: RESUMEN DE GENERACIÓN POR ÁREAS DEL SEIN | J5: RESUMEN DE GENERACIÓN POR ÁREAS DEL SEIN | K5: RESUMEN DE GENERACIÓN POR ÁREAS DEL SEIN | L5: RESUMEN DE GENERACIÓN POR ÁREAS DEL SEIN | M5: RESUMEN DE GENERACIÓN POR ÁREAS DEL SEIN | N5: RESUMEN DE GENERACIÓN POR ÁREAS DEL SEIN | O5: RESUMEN DE GENERACIÓN POR ÁREAS DEL SEIN | P5: RESUMEN DE GENERACIÓN POR ÁREAS DEL SEIN | Q5: RESUMEN DE GENERACIÓN POR ÁREAS DEL SEIN | R5: RESUMEN DE GENERACIÓN POR ÁREAS DEL SEIN | S5: HORA | T5: GENERACIÓN POR TIPO DE GENERACIÓN | U5: GENERACIÓN POR TIPO DE GENERACIÓN | V5: GENERACIÓN POR TIPO DE GENERACIÓN | W5: GENERACIÓN POR TIPO DE GENERACIÓN | X5: GENERACIÓN POR TIPO DE GENERACIÓN | Y5: HORA | Z5: GENERACIÓN POR TIPO DE GENERACIÓN | AA5: GENERACIÓN POR TIPO DE GENERACIÓN | AB5: GENERACIÓN POR TIPO DE GENERACIÓN | AC5: GENERACIÓN POR TIPO DE GENERACIÓN | AD5: GENERACIÓN POR TIPO DE GENERACIÓN
C6: NORTE | D6: NORTE | E6: NORTE | F6: NORTE | G6: CENTRO | H6: CENTRO | I6: CENTRO | J6: CENTRO | K6: SUR | L6: SUR | M6: SUR | N6: SUR | O6: GENERACIÓN INTEGRANTES COES | P6: GENERACIÓN INTEGRANTES COES | Q6: GENERACIÓN INTEGRANTES COES | R6: GENERACIÓN INTEGRANTES COES | T6: INTEGRANTES COES | U6: INTEGRANTES COES | V6: INTEGRANTES COES | W6: INTEGRANTES COES | X6: INTEGRANTES COES | Z6: INTEGRANTES COES RER | AA6: INTEGRANTES COES RER | AB6: INTEGRANTES COES RER | AC6: INTEGRANTES COES RER | AD6: INTEGRANTES COES RER
C7: GENERACIÓN HIDROELÉCTRICA NORTE | D7: GENERACIÓN TERMOELÉCTRICA NORTE | E7: GENERACIÓN SOLAR NORTE | F7: GENERACIÓN EÓLICA NORTE | G7: GENERACIÓN HIDROELÉCTRICA CENTRO | H7: GENERACIÓN TERMOELÉCTRICA CENTRO | I7: GENERACIÓN SOLAR CENTRO | J7: GENERACIÓN EÓLICA CENTRO | K7: GENERACIÓN HIDROELÉCTRICA SUR | L7: GENERACIÓN TERMOELÉCTRICA SUR | M7: GENERACIÓN SOLAR SUR | N7: GENERACIÓN EÓLICA SUR | O7: GENERACIÓN COES NORTE | P7: GENERACIÓN COES CENTRO | Q7: GENERACIÓN COES SUR | R7: TOTAL GENERACION | T7: HIDROELÉCTRICA | U7: TERMOELÉCTRICA | V7: SOLAR | W7: EÓLICA | X7: TOTAL GENERACION | Z7: HIDROELÉCTRICA RER | AA7: TERMOELÉCTRICA RER | AB7: SOLAR RER | AC7: EÓLICA RER | AD7: TOTAL RER
B8: 00:30 | C8: 321.8 | D8: 75.9 | E8: 0 | F8: 33.9 | G8: 2720.5 | H8: 2474.5 | I8: 0 | J8: 347.4 | K8: 594.6 | L8: 0 | M8: 0 | N8: 0 | O8: 431.6 | P8: 5542.4 | Q8: 594.6 | R8: 6568.6 | S8: 00:30 | T8: 3636.9 | U8: 2550.4 | V8: 0 | W8: 381.3 | X8: 6568.6 | Y8: 00:30 | Z8: 262.4 | AA8: 41.2 | AB8: 0 | AC8: 381.3 | AD8: 684.9
B9: 01:00 | C9: 319.4 | D9: 76.3 | E9: 0 | F9: 25.1 | G9: 2648.2 | H9: 2476.4 | I9: 0 | J9: 336.9 | K9: 589.6 | L9: 0 | M9: 0 | N9: 0 | O9: 420.8 | P9: 5461.5 | Q9: 589.6 | R9: 6471.9 | S9: 01:00 | T9: 3557.2 | U9: 2552.7 | V9: 0 | W9: 362 | X9: 6471.9 | Y9: 01:00 | Z9: 262.6 | AA9: 41.7 | AB9: 0 | AC9: 362 | AD9: 666.3
B10: 01:30 | C10: 317.4 | D10: 76.3 | E10: 0 | F10: 29.3 | G10: 2521.4 | H10: 2491.7 | I10: 0 | J10: 275.5 | K10: 592.7 | L10: 0 | M10: 0 | N10: 0 | O10: 423 | P10: 5288.6 | Q10: 592.7 | R10: 6304.3 | S10: 01:30 | T10: 3431.5 | U10: 2568 | V10: 0 | W10: 304.8 | X10: 6304.3 | Y10: 01:30 | Z10: 262.6 | AA10: 41.7 | AB10: 0 | AC10: 304.8 | AD10: 609.1
B11: 02:00 | C11: 310.1 | D11: 76.6 | E11: 0 | F11: 39.8 | G11: 2430.4 | H11: 2498.1 | I11: 0 | J11: 251.2 | K11: 581.8 | L11: 0 | M11: 0 | N11: 0 | O11: 426.5 | P11: 5179.7 | Q11: 581.8 | R11: 6188 | S11: 02:00 | T11: 3322.3 | U11: 2574.7 | V11: 0 | W11: 291 | X11: 6188 | Y11: 02:00 | Z11: 261 | AA11: 41.8 | AB11: 0 | AC11: 291 | AD11: 593.8
B12: 02:30 | C12: 315.8 | D12: 75.3 | E12: 0 | F12: 34.8 | G12: 2465.7 | H12: 2515.3 | I12: 0 | J12: 243 | K12: 623.7 | L12: 0 | M12: 0 | N12: 0 | O12: 425.9 | P12: 5224 | Q12: 623.7 | R12: 6273.6 | S12: 02:30 | T12: 3405.2 | U12: 2590.6 | V12: 0 | W12: 277.8 | X12: 6273.6 | Y12: 02:30 | Z12: 261.2 | AA12: 40.6 | AB12: 0 | AC12: 277.8 | AD12: 579.6
B13: 03:00 | C13: 317.5 | D13: 75.9 | E13: 0 | F13: 29 | G13: 2540.3 | H13: 2513.3 | I13: 0 | J13: 163.3 | K13: 591.4 | L13: 0 | M13: 0 | N13: 0 | O13: 422.4 | P13: 5216.9 | Q13: 591.4 | R13: 6230.7 | S13: 03:00 | T13: 3449.2 | U13: 2589.2 | V13: 0 | W13: 192.3 | X13: 6230.7 | Y13: 03:00 | Z13: 261.1 | AA13: 40.9 | AB13: 0 | AC13: 192.3 | AD13: 494.3
B14: 03:30 | C14: 315.2 | D14: 76.3 | E14: 0 | F14: 32.3 | G14: 2464.4 | H14: 2512 | I14: 0 | J14: 147.6 | K14: 584.1 | L14: 0 | M14: 0 | N14: 0 | O14: 423.8 | P14: 5124 | Q14: 584.1 | R14: 6131.9 | S14: 03:30 | T14: 3363.7 | U14: 2588.3 | V14: 0 | W14: 179.9 | X14: 6131.9 | Y14: 03:30 | Z14: 259.8 | AA14: 41.3 | AB14: 0 | AC14: 179.9 | AD14: 481
B15: 04:00 | C15: 291.6 | D15: 75.9 | E15: 0 | F15: 32 | G15: 2618.4 | H15: 2516.7 | I15: 0 | J15: 108.8 | K15: 596.6 | L15: 0 | M15: 0 | N15: 0 | O15: 399.5 | P15: 5243.9 | Q15: 596.6 | R15: 6240 | S15: 04:00 | T15: 3506.6 | U15: 2592.6 | V15: 0 | W15: 140.8 | X15: 6240 | Y15: 04:00 | Z15: 259.6 | AA15: 40.9 | AB15: 0 | AC15: 140.8 | AD15: 441.3
B16: 04:30 | C16: 286.6 | D16: 76.7 | E16: 0 | F16: 33.4 | G16: 2460.4 | H16: 2593.5 | I16: 0 | J16: 91.3 | K16: 584.4 | L16: 0 | M16: 0 | N16: 0 | O16: 396.7 | P16: 5145.2 | Q16: 584.4 | R16: 6126.3 | S16: 04:30 | T16: 3331.4 | U16: 2670.2 | V16: 0 | W16: 124.7 | X16: 6126.3 | Y16: 04:30 | Z16: 257.5 | AA16: 41.5 | AB16: 0 | AC16: 124.7 | AD16: 423.7
B17: 05:00 | C17: 294.7 | D17: 74 | E17: 0 | F17: 40.7 | G17: 2602.6 | H17: 2568.2 | I17: 0 | J17: 81.6 | K17: 593.1 | L17: 0 | M17: 0 | N17: 0 | O17: 409.4 | P17: 5252.4 | Q17: 593.1 | R17: 6254.9 | S17: 05:00 | T17: 3490.4 | U17: 2642.2 | V17: 0 | W17: 122.3 | X17: 6254.9 | Y17: 05:00 | Z17: 258.5 | AA17: 38.9 | AB17: 0 | AC17: 122.3 | AD17: 419.7
B18: 05:30 | C18: 296.7 | D18: 76.6 | E18: 0 | F18: 39.3 | G18: 2642.6 | H18: 2665.1 | I18: 0 | J18: 70.2 | K18: 609.8 | L18: 0 | M18: 0 | N18: 0 | O18: 412.6 | P18: 5377.9 | Q18: 609.8 | R18: 6400.3 | S18: 05:30 | T18: 3549.1 | U18: 2741.7 | V18: 0 | W18: 109.5 | X18: 6400.3 | Y18: 05:30 | Z18: 259.2 | AA18: 41.6 | AB18: 0 | AC18: 109.5 | AD18: 410.3
B19: 06:00 | C19: 299.6 | D19: 76.4 | E19: 0 | F19: 30.9 | G19: 2776.1 | H19: 2660.4 | I19: 0 | J19: 89.7 | K19: 592.5 | L19: 0 | M19: 0.1 | N19: 0 | O19: 406.9 | P19: 5526.2 | Q19: 592.6 | R19: 6525.7 | S19: 06:00 | T19: 3668.2 | U19: 2736.8 | V19: 0.1 | W19: 120.6 | X19: 6525.7 | Y19: 06:00 | Z19: 259.9 | AA19: 33.3 | AB19: 0.1 | AC19: 120.6 | AD19: 413.9
... B56: TOTAL MWh | C56: 8023.55 | D56: 1782.7 | E56: 2.6 | F56: 1400.25 | G56: 67378.25 | H56: 61945.4 | I56: 8.15 | J56: 7486.9 | K56: 14990.8 | L56: 0 | M56: 5124.5 | N56: 0 | O56: 11209.1 | P56: 136818.7 | Q56: 20115.3 | R56: 168143.1 | S56: TOTAL MWh | T56: 90392.6 | U56: 63728.1 | V56: 5135.25 | W56: 8887.15 | X56: 168143.1 | Y56: TOTAL MWh | Z56: 6259.75 | AA56: 950.45 | AB56: 5135.25 | AC56: 8887.15 | AD56: 21232.6

Sheet HOP
B3: jueves, 5 de Junio del 2025
B5: Reporte de Horas de Operación
B6: Empresa | C6: Central | D6: Grupo | E6: Modo de Operación | F6: Inicio | G6: Final | H6: O. Arranque | I6: O. Parada | J6: Tipo Operación | K6: Ensayo de Potencia Efectiva | L6: Ensayo de Potencia Mínima | M6: Sistema | N6: Lim. Transm. | O6: Causa | P6: Observación
B7: AGRO INDUSTRIAL PARAMONGA S.A. | C7: C.T. PARAMONGA | D7: CENTRAL | E7: PARAMONGA - BAGAZO | F7: 05/06/2025 00:00:00 | G7: 05/06/2025 06:35:00 | I7: 05/06/2025 05:53:00 | J7: POR COGENERACION | O7: ...
B8: AGRO INDUSTRIAL PARAMONGA S.A. | C8: C.T. PARAMONGA | D8: CENTRAL | E8: PARAMONGA - BAGAZO | F8: 05/06/2025 08:10:00 | G8: 05/06/2025 08:34:00 | H8: 05/06/2025 07:49:00 | I8: 05/06/2025 08:33:00 | J8: POR COGENERACION | O8: ...
B9: AGRO INDUSTRIAL PARAMONGA S.A. | C9: C.T. PARAMONGA | D9: CENTRAL | E9: PARAMONGA - BAGAZO | F9: 05/06/2025 08:56:00 | G9: 06/06/2025 00:00:00 | H9: 05/06/2025 08:52:00 | J9: POR COGENERACION | O9: ...
B10: AGROINDUSTRIAS SAN JACINTO S.A.A. | C10: C.T. SAN JACINTO | D10: CENTRAL | E10: SAN_JACINTO - BAGAZO | F10: 05/06/2025 00:00:00 | G10: 06/06/2025 00:00:00 | J10: POR COGENERACION | O10: ...
B11: BIOENERGIA DEL CHIRA S.A. | C11: C.T. CAÑA BRAVA | D11: G-1 | E11: CANA BRAVA TV1 - BAGAZO | F11: 05/06/2025 00:00:00 | G11: 06/06/2025 00:00:00 | J11: POR COGENERACION | O11: ...
B12: ENGIE | C12: C.T. CHILCA 1 | D12: CENTRAL | E12: CHILCA1 CCOMB TG1 & TG2 & TG3 - GAS | F12: 05/06/2025 00:00:00 | G12: 06/06/2025 00:00:00 | J12: POR POTENCIA O ENERGIA | O12: ... | P12: A las 13:19h, S/C generar a 750 MW. A las 13:50 h, S/C generar a máxima.
B13: FENIX POWER PERÚ | C13: C.T. FENIX | D13: CENTRAL | E13: FENIX CCOMB GT11 & GT12 - GAS | F13: 05/06/2025 00:00:00 | G13: 05/06/2025 07:53:00 | J13: POR POTENCIA O ENERGIA | O13: ...
B14: FENIX POWER PERÚ | C14: C.T. FENIX | D14: CENTRAL | E14: FENIX CCOMB GT11 & GT12 - GAS | F14: 05/06/2025 07:53:00 | G14: 05/06/2025 10:07:00 | J14: A MINIMA CARGA | O14: ...
B15: FENIX POWER PERÚ | C15: C.T. FENIX | D15: CENTRAL | E15: FENIX CCOMB GT11 & GT12 - GAS | F15: 05/06/2025 10:07:00 | G15: 05/06/2025 11:57:00 | J15: POR POTENCIA O ENERGIA | O15: ... | P15: A mínima generación por despacho.
B16: FENIX POWER PERÚ | C16: C.T. FENIX | D16: CENTRAL | E16: FENIX CCOMB GT11 & GT12 - GAS | F16: 05/06/2025 11:57:00 | G16: 05/06/2025 15:54:00 | J16: A MINIMA CARGA | O16: ...
B17: FENIX POWER PERÚ | C17: C.T. FENIX | D17: CENTRAL | E17: FENIX CCOMB GT11 & GT12 - GAS | F17: 05/06/2025 15:54:00 | G17: 05/06/2025 22:32:00 | J17: POR POTENCIA O ENERGIA | O17: ...
B18: FENIX POWER PERÚ | C18: C.T. FENIX | D18: CENTRAL | E18: FENIX CCOMB GT11 & GT12 - GAS | F18: 05/06/2025 22:32:00 | G18: 06/06/2025 00:00:00 | J18: A MINIMA CARGA | O18: ...
B19: GM OPERACIONES S.A.C. | C19: CT REFINERIA TALARA | D19: TV1 REF TALARA | E19: REF_TALARA TV1 - NLH_RFG | F19: 05/06/2025 00:00:00 | G19: 06/06/2025 00:00:00 | J19: POR COGENERACION | O19: ...
B20: GM OPERACIONES S.A.C. | C20: CT REFINERIA TALARA | D20: TV2 REF TALARA | E20: REF_TALARA TV2 - NLH_RFG | F20: 05/06/2025 00:00:00 | G20: 06/06/2025 00:00:00 | J20: POR COGENERACION | O20: ...
B21: KALLPA GENERACION S.A. | C21: C.T. KALLPA | D21: CENTRAL | E21: KALLPA CCOMB TG2 & TG3 - GAS | F21: 05/06/2025 00:00:00 | G21: 05/06/2025 13:11:00 | J21: POR POTENCIA O ENERGIA | O21: ... | P21: A las 11:59h, S/C generar a 400 MW. A las 13:01h, S/C generar a 350 MW.
B22: KALLPA GENERACION S.A. | C22: C.T. KALLPA | D22: CENTRAL | E22: KALLPA CCOMB TG2 & TG3 - GAS | F22: 05/06/2025 13:11:00 | G22: 05/06/2025 14:28:00 | J22: A MINIMA CARGA | O22: ...
B23: KALLPA GENERACION S.A. | C23: C.T. KALLPA | D23: CENTRAL | E23: KALLPA CCOMB TG2 & TG3 - GAS | F23: 05/06/2025 14:28:00 | G23: 06/06/2025 00:00:00 | J23: POR POTENCIA O ENERGIA | O23: ... | P23: A las 14:28 h, S/C generar a 450 MW. A las 14:36 h, S/C generar a máxima. A las 15:15 h, S/C generar a 500 MW. A las 15:53 h, S/C generar a máxima. A las 22:42 h, S/C generar a 515 MW.
B24: ORYGEN PERU S.A.A. | C24: C.T. VENTANILLA | D24: CENTRAL | E24: VENTANILLA CCOMB TG3 & TG4 - GAS | F24: 05/06/2025 00:00:00 | G24: 05/06/2025 04:33:00 | J24: POR POTENCIA O ENERGIA | O24: ...
B25: ORYGEN PERU S.A.A. | C25: C.T. VENTANILLA | D25: CENTRAL | E25: VENTANILLA CCOMB TG3 & TG4 - GAS | F25: 05/06/2025 04:33:00 | G25: 05/06/2025 06:01:00 | J25: A MINIMA CARGA | O25: ...
B26: ORYGEN PERU S.A.A. | C26: C.T. VENTANILLA | D26: CENTRAL | E26: VENTANILLA CCOMB TG3 & TG4 - GAS | F26: 05/06/2025 06:01:00 | G26: 05/06/2025 07:46:00 | J26: POR POTENCIA O ENERGIA | O26: ... | P26: A las 07:40 h, S/C generar a 350 MW.
B27: ORYGEN PERU S.A.A. | C27: C.T. VENTANILLA | D27: CENTRAL | E27: VENTANILLA CCOMB TG3 & TG4 - GAS | F27: 05/06/2025 07:46:00 | G27: 05/06/2025 10:07:00 | J27: A MINIMA CARGA | O27: ...
B28: ORYGEN PERU S.A.A. | C28: C.T. VENTANILLA | D28: CENTRAL | E28: VENTANILLA CCOMB TG3 & TG4 - GAS | F28: 05/06/2025 10:07:00 | G28: 05/06/2025 11:57:00 | J28: POR POTENCIA O ENERGIA | O28: ...
B29: ORYGEN PERU S.A.A. | C29: C.T. VENTANILLA | D29: CENTRAL | E29: VENTANILLA CCOMB TG3 & TG4 - GAS | F29: 05/06/2025 11:57:00 | G29: 05/06/2025 15:57:00 | J29: A MINIMA CARGA | O29: ...
B30: ORYGEN PERU S.A.A. | C30: C.T. VENTANILLA | D30: CENTRAL | E30: VENTANILLA CCOMB TG3 & TG4 - GAS | F30: 05/06/2025 15:57:00 | G30: 05/06/2025 22:24:00 | J30: POR POTENCIA O ENERGIA | O30: ...
B31: ORYGEN PERU S.A.A. | C31: C.T. VENTANILLA | D31: CENTRAL | E31: VENTANILLA CCOMB TG3 & TG4 - GAS | F31: 05/06/2025 22:24:00 | G31: 06/06/2025 00:00:00 | J31: A MINIMA CARGA | O31: ...
B32: PETRAMAS | C32: C.T. HUAYCOLORO | D32: CENTRAL | E32: HUAYCOLORO - BIOGAS | F32: 05/06/2025 00:00:00 | G32: 06/06/2025 00:00:00 | H32: 05/06/2025 18:11:00 | I32: 05/06/2025 08:00:00 | J32: POR POTENCIA O ENERGIA | O32: ...
B33: PETRAMAS | C33: C.T. HUAYCOLORO | D33: G1 | E33: HUAYCOLORO - BIOGAS | F33: 05/06/2025 15:42:00 | G33: 06/06/2025 00:00:00 | H33: 05/06/2025 15:36:00 | J33: POR POTENCIA O ENERGIA | O33: ...
B34: PETRAMAS | C34: C.T. LA GRINGA | D34: CENTRAL | E34: LA GRINGA V - BIOGAS | F34: 05/06/2025 00:00:00 | G34: 06/06/2025 00:00:00 | J34: POR POTENCIA O ENERGIA | O34: ...
B35: PETRAMAS | C35: C.T.B DOÑA CATALINA | D35: CENTRAL | E35: DONA CATALINA - BIOGAS | F35: 05/06/2025 00:00:00 | G35: 06/06/2025 00:00:00 | J35: POR POTENCIA O ENERGIA | O35: ...
B36: PETRAMAS | C36: C.T.B. CALLAO | D36: G1 CALLAO | E36: CALLAO - BIOGAS | F36: 05/06/2025 00:00:00 | G36: 06/06/2025 00:00:00 | J36: POR POTENCIA O ENERGIA | O36: ...
B37: TERMOCHILCA S.A.C. | C37: C.T. OLLEROS | D37: TG1 | E37: OLLEROS TG1 - GAS | F37: 05/06/2025 00:18:00 | G37: 05/06/2025 04:08:00 | J37: POR PRUEBAS | O37: REQ. PROPIO | P37: A las 23:54 h del 04/06/2025 se dio orden de arranque. En proceso de acople para ciclo combinado.
B38: TERMOCHILCA S.A.C. | C38: C.T. OLLEROS | D38: CENTRAL | E38: OLLEROS CCOMB TG1 - GAS | F38: 05/06/2025 04:08:00 | G38: 06/06/2025 00:00:00 | J38: POR PRUEBAS | O38: REQ. PROPIO | P38: A las 04:48 h S/C subir a carga base por pruebas.

Sheet INDISP
B3: jueves, 5 de Junio del 2025
B5: Hora Inicio y Fin de Indisponibilidades de las Unidades de Generación SEIN
B6: Empresa | C6: Ubicación | D6: Equipo | E6: Inicio | F6: Final | G6: Descripción | H6: MW Indisp. | I6: Prog. | J6: Dispon | K6: Interrupc. | L6: Tipo | M6: CodEq | N6: TipoEq_Osinerg
B7: AGROAURORA S.A.C. | C7: MAPLE ETANOL | D7: CENTRAL | E7: 05/06/2025 00:00 | F7: 06/06/2025 00:00 | G7: MANTENIMIENTO PREVENTIVO PROGRAMADO DE LA CENTRAL TERMOELECTRICA Y EQUIPOS AUXILIARES. | H7: 17 | I7: P | J7: F/S | K7: N | L7: PREV. | M7: 13417 | N7: G
B8: AGROAURORA S.A.C. | C8: MAPLE ETANOL | D8: CENTRAL | E8: 05/06/2025 00:00 | F8: 06/06/2025 00:00 | G8: CENTRAL TERMOELECTRICA FUERA DE SERVICIO POR FALTA DE MATERIA PRIMA PARA LOS REQUERIMIENTOS DE CALOR ÚTIL EN FÁBRICA. | H8: 17 | I8: P | J8: F/S | K8: N | L8: OTROS | M8: 13417 | N8: G
B9: CELEPSA RENOVABLES S.R.L. | C9: MARAÑON | D9: CENTRAL | E9: 05/06/2025 08:00 | F9: 05/06/2025 11:07 | G9: Por indisponibilidad de la L6169 | H9: 19.5 | I9: P | J9: F/S | K9: N | L9: OTROS | M9: 17492 | N9: G
B10: EGASA | C10: CHARCANI VI | D10: G1 | E10: 05/06/2025 00:00 | F10: 06/06/2025 00:00 | G10: Mantenimiento Generador | H10: 8.9 | I10: P | J10: F/S | K10: N | L10: PREV. | M10: 188 | N10: G
B11: ELECTROPERU | C11: MANTARO | D11: G6 | E11: 05/06/2025 00:05 | F11: 05/06/2025 06:09 | G11: INSPECCIÓN RODETE | H11: 101 | I11: P | J11: F/S | K11: N | L11: PREV. | M11: 6 | N11: G
B12: EMPRESA DE GENERACION HUANZA | C12: HUANZA | D12: CENTRAL | E12: 05/06/2025 00:00 | F12: 06/06/2025 00:00 | G12: CAMBIO DE VÁLVULA ESFERICA EN GRUPO G1 CON VACIADO Y LLENADO DE TUBERÍA FORZADA | H12: 94 | I12: P | J12: F/S | K12: N | L12: PREV. | M12: 14005 | N12: G
B13: ENEL GENERACION PIURA S.A. | C13: MALACAS 1 | D13: TG6 | E13: 05/06/2025 00:00 | F13: 06/06/2025 00:00 | G13: Inspección y mantenimiento de equipos BOP previo a EPEyR modo diesel. | H13: 0 | I13: P | J13: F/S | K13: N | L13: OTROS | M13: 16925 | N13: G
B14: ENGIE | C14: QUITARACSA | D14: CENTRAL | E14: 05/06/2025 00:00 | F14: 06/06/2025 00:00 | G14: FUERA DE SERVICIO DEBIDO A INDISPONIBILIDAD DE BOCATOMA QUITARACSA Y SAN MATEO POR CAIDA DE ROCAS EN LA ZONA. NO SE PUEDE CAPTAR AGUA. | H14: 110 | I14: P | J14: F/S | K14: N | L14: PREV. | M14: 14448 | N14: G
B15: ENGIE | C15: RESERVA FRIA PLANTA ILO | D15: CENTRAL | E15: 05/06/2025 00:00 | F15: 06/06/2025 00:00 | G15: MANTENIMIENTO BOP/UPS/DC (TODA LA PLANTA F/S) & BOROSCOPIA GENERADOR TG1 Y TG2 | H15: 460 | I15: P | J15: F/S | K15: N | L15: PREV. | M15: 13549 | N15: G
B16: ENGIE | C16: YUNCÁN | D16: G2 | E16: 05/06/2025 00:00 | F16: 06/06/2025 00:00 | G16: MANTENIMIENTO CORRECTIVO DEL GENERADOR | H16: 45.5 | I16: P | J16: F/S | K16: N | L16: CORR. | M16: 200 | N16: G
B17: KALLPA GENERACION S.A. | C17: LAS FLORES | D17: TG1 | E17: 05/06/2025 00:00 | F17: 06/06/2025 00:00 | G17: Unidad indisponible por falla ocurrida el 01/06 | H17: 0 | I17: P | J17: F/S | K17: N | L17: CORR. | M17: 12726 | N17: G
B18: PETRAMAS | C18: CTB CALLAO | D18: G2 CALLAO | E18: 05/06/2025 00:00 | F18: 06/06/2025 00:00 | G18: REACONDICIONAMIENTO GENERAL DEL MOTOR EN EL BASTIDOR/MANTENIMIENTO DE GENERADOR ELECTRICO/MANTENIMIENTO AL ENFRIADOR DE ACEITE DE MOTOR | H18: 1.2 | I18: R | J18: F/S | K18: N | L18: PREV. | M18: 20852 | N18: G
... B23: STATKRAFT S.A | C23: PACHACHACA | D23: G3 | E23: 05/06/2025 00:00 | F23: 06/06/2025 00:00 | G23: REHABILITACIÓN DE RODETES | H23: 3.25 | I23: P | J23: F/S | K23: N | L23: PREV. | M23: 48 | N23: G

Sheet RESERVA_FRÍA
B3: 05/06/2025 | E3: EJECUTADO | L3: Jueves 5 de Junio del 2025 / SEM N° 22 | V3: EJECUTADO | AC3: Jueves 5 de Junio del 2025 / SEM N° 22 | EE3: ENERGIA RENOVABLES | GP3: COGENERACION | GY3: NO INTEGRANTES
B4: Jueves | C4: HYDROG | D4: ELECTROPERU | H4: ORAZU | J4: TER | L4: KALLPA GENERACION S.A. | T4: SHOUGESA | X4: EGM | Y4: EGESUR | AB4: EGASA | AI4: SGB | AJ4: CELEP | AK4: MINCVE | AL4: ETEN | AN4: HUALLA | AP4: LAVI | AQ4: CHIN | AS4: HUANCH | AT4: CELER | AU4: INLD | AV4: FENIX POWER PERÚ | AY4: STATKRAFT S.A | BG4: STARO | BI4: HUANZA | BJ4: ENEL GENERACION PIURA S.A. | BM4: ENGIE | CA4: IYEP | CC4: SHAQSH | CD4: ORYGEN PERU S.A.A. | CP4: SAMAY I S.A.C | CT4: TCHILC | CV4: GENERACION | CY4: SALIDAS YUPANA | DC4: FLUJO EN LINEAS | DO4: COSTOS MARGINALES | DS4: RESERVA | DX4: DEMANDA POR AREAS | EE4: ACHI | EF4: COLCA | EG4: ERSUR | EH4: GRCOR | EI4: TARU | EJ4: KONDU | EK4: PIEREN | EL4: ORAZU | EN4: SGB | EO4: AIPSA | EP4: MAJA | EQ4: EGECSA | ER4: STANA | ES4: AGUAA | ET4: RDOBLE | EU4: HIDRO | EV4: HUARA | EW4: MOQUE | EX4: PANAM | EY4: PARQU | EZ4: PE3HER | FA4: PETRAMAS | FE4: TACNA | FF4: EYSAC | FG4: AURORA | FH4: AGROIN | FI4: ANDEA | FJ4: ASLC | FK4: ATRIA | FL4: EGEJUNIN | FP4: EGERBA | FQ4: EOL | FS4: ENGIE | FX4: GENE | FZ4: GENERADORA DE ENERGÍA DEL PERÚ | GD4: PAINO | GE4: JOYAS | GF4: SARCUS | GG4: ORYGEN PERU S.A.A. | GL4: RARCUS | GM4: SINERS | GP4: ACHI | GQ4: GM OP | GS4: SDF | GU4: AIPSA | GV4: AURORA | GW4: AGROIN | GY4: UNACEM | GZ4: EOR | HA4: AYEP | HB4: ELZANA | HC4: ENOSA | HD4: SDE | HE4: SINERS
C5: 65333 | D5: 101 | E5: 102 | F5: 42667 | G5: 42668 | H5: 126 | I5: 127 | J5: 138 | K5: 139 | L5: 197 | M5: 203 | N5: 204 | O5: 230 | P5: 209 | Q5: 56677 | R5: 796 | S5: 2146 | T5: 142 | U5: 143 | V5: 125 | W5: 187 | X5: 163 | Y5: 298 | Z5: 299 | AA5: 219 | AB5: 151 | AC5: 152 | AD5: 153 | AE5: 154 | AF5: 756 | AG5: 156 | AH5: 155 | AI5: 182 | AJ5: 212 | AK5: 758 | AL5: 263 | AM5: 265 | AN5: 775 | AO5: 777 | AP5: 2154 | AQ5: 150 | AR5: 149 | AS5: 188 | AT5: 2131 | AU5: 755 | AV5: 252 | AW5: 249 | AX5: 250 | AY5: 117 | AZ5: 267 | BA5: 268 | BB5: 119 | BC5: 120 | BD5: 189 | BE5: 122 | BF5: 266 | BG5: 337 | BH5: 338 | BI5: 251 | BJ5: 115 | BK5: 239 | BL5: 288 | BM5: 240 | BN5: 241 | BO5: 242 | BP5: 191 | BQ5: 194 | BR5: 196 | BS5: 207 | BT5: 236 | BU5: 795 | BV5: 285 | BW5: 995 | BX5: 996 | BY5: 997 | BZ5: 766 | CA5: 926 | CB5: 924 | CC5: 121 | CD5: 103 | CE5: 104 | CF5: 106 | CG5: 105 | CH5: 107 | CI5: 110 | CJ5: 109 | CK5: 144 | CL5: 113 | CM5: 114 | CN5: 193 | CO5: 208 | CP5: 786 | CQ5: 787 | CR5: 788 | CS5: 789 | CT5: 248 | CU5: 2159 | CV5: -1222 | CW5: -1223 | CX5: -1224 | CY5: 1221 | CZ5: 1222 | DA5: 1223 | DB5: 1224 | DC5: 1250 | DD5: 1251 | DE5: 1252 | DF5: 1253 | DG5: 1254 | DH5: 1255 | DI5: 1256 | DJ5: 1257 | DK5: 1258 | DL5: 1259 | DM5: 1260 | DN5: 1261 | DO5: 1226 | DP5: 1219 | DQ5: 1220 | DR5: -1203 | DS5: 1227 | DT5: 1205 | DU5: 1207 | DV5: 1206 | DW5: 1218 | DX5: 1211 | DY5: 1212 | DZ5: 1213 | EA5: 1214 | EB5: 1229 | EC5: -1221 | EE5: 289 | EF5: 303 | EG5: 59715 | EH5: 62255 | EI5: 1263 | EJ5: 61800 | EK5: 2194 | EL5: 216 | EM5: 198 | EN5: 49607 | EO5: 213 | EP5: 214 | EQ5: 260 | ER5: 2152 | ES5: 2128 | ET5: 247 | EU5: 228 | EV5: 2135 | EW5: 261 | EX5: 237 | EY5: 253 | EZ5: 770 | FA5: 225 | FB5: 2201 | FC5: 2171 | FD5: 760 | FE5: 235 | FF5: 238 | FG5: 232 | FH5: 2190 | FI5: 2184 | FJ5: 61855 | FK5: 223 | FL5: 226 | FM5: 201 | FN5: 258 | FO5: 259 | FP5: 920 | FQ5: 257 | FR5: 256 | FS5: 2148 | FT5: 58288 | FU5: 58289 | FV5: 58839 | FW5: 58840 | FX5: 296 | FY5: 297 | FZ5: 211 | GA5: 2175 | GB5: 2178 | GC5: 2181 | GD5: 1262 | GE5: 63425 | GF5: 233 | GG5: 2150 | GH5: 2165 | GI5: 2161 | GJ5: 61197 | GK5: 58851 | GL5: 234 | GM5: 215 | GN5: 917 | GP5: 289 | GQ5: 58333 | GR5: 58336 | GS5: 202 | GT5: 58487 | GU5: 213 | GV5: 232 | GW5: 2190 | GY5: 221 | GZ5: 222 | HA5: 224 | HB5: 2187 | HC5: 227 | HD5: 49400 | HE5: 199 | HF5: 200 | HH5: 7000 | HI5: 7001 | HJ5: 7002
B6: Día Hora | C6: SAN GABAN III | D6: MANTARO | E6: RESTITUCION | F6: TUMBES MAK 1 | G6: TUMBES MAK 2 | H6: CARHUAQUERO | I6: CAÑON DEL PATO | J6: AGUAYTIA TG1 | K6: AGUAYTIA TG2 | L6: KALLPA TG1 | M6: KALLPA TG2 | N6: KALLPA TG3 | O6: KALLPA TV | P6: LFLORES TG1 | Q6: LFLORES TV | R6: CERRO DEL AGUILA | S6: CERRODELAGUILAG4 | T6: SHOUGESA TV1 | U6: SHOUGESA TV2 | V6: SHOUGESA TV3 | W6: SHOUGESA CUMMINS | X6: MACHUPICCHU | Y6: ARICOTA 1 | Z6: ARICOTA 2 | AA6: INDEPENDENCIA | AB6: CHARCANI I,II,III | AC6: CHARCANI IV | AD6: CHARCANI V | AE6: CHARCANI VI | AF6: CHILINA TG | AG6: MOLLENDO 1, 2, 3 | AH6: CHILINA (SULZ 1,2) | AI6: SAN GABAN II | AJ6: PLATANAL | AK6: RECKA | AL6: RF ETEN TG1 | AM6: RF ETEN TG2 | AN6: CHAGLLA GP1 | AO6: CHAGLLA | AP6: LA VIRGEN | AQ6: CHIMAY | AR6: YANANGO | AS6: HUANCHOR | AT6: MARAÑON | AU6: STA TERESA | AV6: FENIX GT11 | AW6: FENIX GT12 | AX6: FENIX TV10 | AY6: YAUPI | AZ6: OROYA | BA6: PACHACHACA | BB6: MALPASO | BC6: CAHUA | BD6: ARCATA | BE6: GALLITO CIEGO | BF6: CHEVES | BG6: SANTA ROSA 1 | BH6: SANTA ROSA 2 | BI6: HUANZA | BJ6: MALACAS2 TG4 | BK6: MALACAS3 TG 5 | BL6: MALACAS1 TG6 | BM6: RF ILO2 TG1 | BN6: RF ILO2 TG2 | BO6: RF ILO2 TG3 | BP6: YUNCAN | BQ6: CHILCA1 TG1 | BR6: CHILCA1 TG2 | BS6: CHILCA1 TG3 | BT6: CHILCA-TV | BU6: CHILCA2 TG41 | BV6: CHILCA2-TV | BW6: CTNEPI_TG41 | BX6: CTNEPI_TG42 | BY6: CTNEPI_TG43 | BZ6: QUITARACSA | CA6: RF PTO MALDONADO | CB6: RF PUCALLPA | CC6: PARIAC | CD6: HUINCO | CE6: MATUCANA | CF6: MOYOPAMPA | CG6: CALLAHUANCA | CH6: HUAMPANI | CI6: STA ROSA WEST TG7 | CJ6: UTI_5 | CK6: UTI_6 | CL6: VENTANILLA 3 | CM6: VENTANILLA 4 | CN6: VENTANILLA TV | CO6: STAROSA TG8 | CP6: PTO_BRVO TG1 | CQ6: PTO_BRVO TG2 | CR6: PTO_BRVO TG3 | CS6: PTO_BRVO TG4 | CT6: OLLEROS TG1 | CU6: OLLEROS TV | CV6: Total CoGeneracion | CW6: Total Renovables | CX6: Total Generación COES | CY6: Demanda YUPANA | CZ6: Oferta | DA6: Perdidas YUPANA | DB6: Deficit YUPANA | DC6: FLUJO ENLACE CENTRO - SUR | DD6: FLUJO CHILCA CARAPONGO 500 KV | DE6: FLUJO CARAPONGO CARABAYLLO 500 KV | DF6: FLUJO CHIMBOTE TRUJILLO 500 KV | DG6: FLUJO TRUJILLO LA NIÑA 500 KV | DH6: FLUJO COLCABAMBA POROMA 500 KV | DI6: FLUJO CHILCA POROMA 500 KV | DJ6: FLUJO POROMA YARABAMBA 500 KV | DK6: FLUJO POROMA OCOÑA 500 KV | DL6: FLUJO YARABAMBA MOLTALVO 500 KV | DM6: FLUJO HUANCAVELICA - INDEPENDENCIA 220 KV | DN6: FLUJO CHILCA - SAN JUAN 220 KV | DO6: Cmg Santa Rosa YUPANA(US$/MWh) | DP6: Cmg Trujillo YUPANA(US$/MWh) | DQ6: Cmg Socabaya YUPANA(US$/MWh) | DR6: Nivel de Demanda | DS6: Reserva Fría Térmica | DT6: Reserva Eficiente | DU6: Reserva Eficiente Gas | DV6: Reserva Eficiente Carbón | DW6: Nivel Tablachaca | DX6: Demanda Centro | DY6: Demanda Norte | DZ6: Demanda Sur | EA6: Demanda Electroandes | EB6: Demanda Ecuador | EC6: Demanda COES | EE6: CANA BRAVA | EF6: CS YARUCAYA | EG6: SAN JUAN | EH6: MATARANI | EI6: DUNA | EJ6: CARHUAQUERO (CS) | EK6: MANTA I | EL6: CARHUAQUERO4 | EM6: CAÑA BRAVA | EN6: TUPURI | EO6: PARAMONGA | EP6: RONCADOR | EQ6: CANCHAYLLO | ER6: RENOVANDESH1 | ES6: POTRERO | ET6: PIZARRAS | EU6: NIMPERIAL | EV6: YARUCAYA | EW6: MOQUEGUA-SOLAR | EX6: PANAMERICANA-SOLAR | EY6: PQE-EOLICO-MARCONA | EZ6: PQE-EOLICO-3-HERMANAS | FA6: HUAYCOLORO | FB6: CALLAO | FC6: DONA_CATALINA | FD6: LAGRINGAV | FE6: TACNA-SOLAR | FF6: YANAPAMPA | FG6: MAPLE | FH6: SAN_JACINTO | FI6: CARHUAC | FJ6: HUALLIN | FK6: PURMACANA | FL6: HUASAHUASI | FM6: STACRUZ_1_2 | FN6: RUNATULLO_II | FO6: RUNATULLO_III | FP6: RUCUY | FQ6: PQE-EOLICO-TALARA | FR6: PQE-EOLICO-CUPISNIQUE | FS6: INTIPAMPA | FT6: PUNTA LOMITAS-BL1 | FU6: PUNTA LOMITAS-BL2 | FV6: PUN LOMITAS_EXP-BL1 | FW6: PUN LOMITAS_EXP-BL2 | FX6: 8AGOSTO | FY6: EL CARMEN | FZ6: LA JOYA | GA6: ANGEL_I | GB6: ANGEL_II | GC6: ANGEL_III | GD6: HUAMBOS | GE6: SAN MARTIN SOLAR | GF6: MAJES | GG6: RUBI | GH6: CH_HER1 | GI6: WAYRA-I | GJ6: WAYRA EXTENSION | GK6: CLEMESI | GL6: REPARTICION | GM6: POECHOS2 | GN6: CHANCAY | GP6: CANA BRAVA | GQ6: REFINERIA TALARA TV1 | GR6: REFINERÍA TALARA TV2 | GS6: OQUENDO TG1 | GT6: OQUENDO TV1 | GU6: PARAMONGA | GV6: MAPLE | GW6: SAN_JACINTO | GY6: CARPAPATA | GZ6: CENTRALES ELOR | HA6: PIAS1 | HB6: ZANA | HC6: TABLAZO | HD6: TALLANCA | HE6: CURUMUY | HF6: POECHOS1 | HH6: ReservaFriaTermica | HI6: ReservaFria Rapida Termica | HJ6: ReservaFria Termica xMantenimiento
B7: 00:30 | F7: 8.82587 | G7: 8.51669 | J7: 88.0592 | T7: 18.14123 | U7: 19.19196 | W7: 1.06127 | AA7: 23.06068 | AF7: 12.23925 | AG7: 24.4617 | AH7: 10.27692 | AK7: 179.37322 | AL7: 217.12263 | AM7: 7.93273 | BJ7: 32.327 | BK7: 184.87493 | BW7: 206.49456 | BX7: 206.11549 | BY7: 205.99003 | CA7: 17.41583 | CB7: 44.05367 | CI7: 118.14735 | CJ7: 47.90514 | CK7: 53.71012 | CP7: 180.55348 | CQ7: 180.52451 | CR7: 181.33356 | CS7: 181.02912 | CU7: 99.77333 | HH7: 2558.5115 | HI7: 2521.1783 | HJ7: 1180.7008
B8: 01:00 | F8: 8.82587 | G8: 8.51669 | J8: 88.0592 | T8: 18.14123 | U8: 19.19196 | W8: 1.06127 | AA8: 23.06068 | AF8: 12.23925 | AG8: 24.4617 | AH8: 10.27692 | AK8: 179.37322 | AL8: 217.12263 | AM8: 7.93273 | BJ8: 32.327 | BK8: 184.87493 | BV8: 110.49702 | BW8: 206.49456 | BX8: 206.11549 | BY8: 205.99003 | CA8: 17.41583 | CB8: 44.05367 | CI8: 118.14735 | CJ8: 47.90514 | CK8: 53.71012 | CP8: 180.55348 | CQ8: 180.52451 | CR8: 181.33356 | CS8: 181.02912 | CU8: 99.77333 | HH8: 2669.0085 | HI8: 2631.6753 | HJ8: 1180.7008
B9: 01:30 | F9: 8.82587 | G9: 8.51669 | J9: 88.0592 | T9: 18.14123 | U9: 19.19196 | W9: 1.06127 | AA9: 23.06068 | AF9: 12.23925 | AG9: 24.4617 | AH9: 10.27692 | AK9: 179.37322 | AL9: 217.12263 | AM9: 7.93273 | BJ9: 32.327 | BK9: 184.87493 | BV9: 110.49702 | BW9: 206.49456 | BX9: 206.11549 | BY9: 205.99003 | CA9: 17.41583 | CB9: 44.05367 | CI9: 118.14735 | CJ9: 47.90514 | CK9: 53.71012 | CP9: 180.55348 | CQ9: 180.52451 | CR9: 181.33356 | CS9: 181.02912 | CU9: 99.77333 | HH9: 2669.0085 | HI9: 2631.6753 | HJ9: 1180.7008
B10: 02:00 | F10: 8.82587 | G10: 8.51669 | J10: 88.0592 | T10: 18.14123 | U10: 19.19196 | W10: 1.06127 | AA10: 23.06068 | AF10: 12.23925 | AG10: 24.4617 | AH10: 10.27692 | AK10: 179.37322 | AL10: 217.12263 | AM10: 7.93273 | BJ10: 32.327 | BK10: 184.87493 | BV10: 110.49702 | BW10: 206.49456 | BX10: 206.11549 | BY10: 205.99003 | CA10: 17.41583 | CB10: 44.05367 | CI10: 118.14735 | CJ10: 47.90514 | CK10: 53.71012 | CP10: 180.55348 | CQ10: 180.52451 | CR10: 181.33356 | CS10: 181.02912 | CU10: 99.77333 | HH10: 2669.0085 | HI10: 2631.6753 | HJ10: 1180.7008
B11: 02:30 | F11: 8.82587 | G11: 8.51669 | J11: 88.0592 | T11: 18.14123 | U11: 19.19196 | W11: 1.06127 | AA11: 23.06068 | AF11: 12.23925 | AG11: 24.4617 | AH11: 10.27692 | AK11: 179.37322 | AL11: 217.12263 | AM11: 7.93273 | BJ11: 32.327 | BK11: 184.87493 | BV11: 110.49702 | BW11: 206.49456 | BX11: 206.11549 | BY11: 205.99003 | CA11: 17.41583 | CB11: 44.05367 | CI11: 118.14735 | CJ11: 47.90514 | CK11: 53.71012 | CP11: 180.55348 | CQ11: 180.52451 | CR11: 181.33356 | CS11: 181.02912 | CU11: 99.77333 | HH11: 2669.0085 | HI11: 2631.6753 | HJ11: 1180.7008
B12: 03:00 | F12: 8.82587 | G12: 8.51669 | J12: 88.0592 | T12: 18.14123 | U12: 19.19196 | W12: 1.06127 | AA12: 23.06068 | AF12: 12.23925 | AG12: 24.4617 | AH12: 10.27692 | AK12: 179.37322 | AL12: 217.12263 | AM12: 7.93273 | BJ12: 32.327 | BK12: 184.87493 | BV12: 110.49702 | BW12: 206.49456 | BX12: 206.11549 | BY12: 205.99003 | CA12: 17.41583 | CB12: 44.05367 | CI12: 118.14735 | CJ12: 47.90514 | CK12: 53.71012 | CP12: 180.55348 | CQ12: 180.52451 | CR12: 181.33356 | CS12: 181.02912 | CU12: 99.77333 | HH12: 2669.0085 | HI12: 2631.6753 | HJ12: 1180.7008
B13: 03:30 | F13: 8.82587 | G13: 8.51669 | J13: 88.0592 | T13: 18.14123 | U13: 19.19196 | W13: 1.06127 | AA13: 23.06068 | AF13: 12.23925 | AG13: 24.4617 | AH13: 10.27692 | AK13: 179.37322 | AL13: 217.12263 | AM13: 7.93273 | BJ13: 32.327 | BK13: 184.87493 | BV13: 110.49702 | BW13: 206.49456 | BX13: 206.11549 | BY13: 205.99003 | CA13: 17.41583 | CB13: 44.05367 | CI13: 118.14735 | CJ13: 47.90514 | CK13: 53.71012 | CP13: 180.55348 | CQ13: 180.52451 | CR13: 181.33356 | CS13: 181.02912 | CU13: 99.77333 | HH13: 2669.0085 | HI13: 2631.6753 | HJ13: 1180.7008
B14: 04:00 | F14: 8.82587 | G14: 8.51669 | J14: 88.0592 | T14: 18.14123 | U14: 19.19196 | W14: 1.06127 | AA14: 23.06068 | AF14: 12.23925 | AG14: 24.4617 | AH14: 10.27692 | AK14: 179.37322 | AL14: 217.12263 | AM14: 7.93273 | BJ14: 32.327 | BK14: 184.87493 | BV14: 110.49702 | BW14: 206.49456 | BX14: 206.11549 | BY14: 205.99003 | CA14: 17.41583 | CB14: 44.05367 | CI14: 118.14735 | CJ14: 47.90514 | CK14: 53.71012 | CP14: 180.55348 | CQ14: 180.52451 | CR14: 181.33356 | CS14: 181.02912 | CU14: 99.77333 | HH14: 2669.0085 | HI14: 2631.6753 | HJ14: 1180.7008
B15: 04:30 | F15: 8.82587 | G15: 8.51669 | J15: 88.0592 | T15: 18.14123 | U15: 19.19196 | W15: 1.06127 | AA15: 23.06068 | AF15: 12.23925 | AG15: 24.4617 | AH15: 10.27692 | AK15: 179.37322 | AL15: 217.12263 | AM15: 7.93273 | BJ15: 32.327 | BK15: 184.87493 | BV15: 110.49702 | BW15: 206.49456 | BX15: 206.11549 | BY15: 205.99003 | CA15: 17.41583 | CB15: 44.05367 | CI15: 118.14735 | CJ15: 47.90514 | CK15: 53.71012 | CP15: 180.55348 | CQ15: 180.52451 | CR15: 181.33356 | CS15: 181.02912 | HH15: 2569.2352 | HI15: 2531.902 | HJ15: 1180.7008
B16: 05:00 | F16: 8.82587 | G16: 8.51669 | J16: 88.0592 | T16: 18.14123 | U16: 19.19196 | W16: 1.06127 | AA16: 23.06068 | AF16: 12.23925 | AG16: 24.4617 | AH16: 10.27692 | AK16: 179.37322 | AL16: 217.12263 | AM16: 7.93273 | BJ16: 32.327 | BK16: 184.87493 | BV16: 110.49702 | BW16: 206.49456 | BX16: 206.11549 | BY16: 205.99003 | CA16: 17.41583 | CB16: 44.05367 | CI16: 118.14735 | CJ16: 47.90514 | CK16: 53.71012 | CP16: 180.55348 | CQ16: 180.52451 | CR16: 181.33356 | CS16: 181.02912 | HH16: 2569.2352 | HI16: 2531.902 | HJ16: 1180.7008
B17: 05:30 | F17: 8.82587 | G17: 8.51669 | J17: 88.0592 | T17: 18.14123 | U17: 19.19196 | W17: 1.06127 | AA17: 23.06068 | AF17: 12.23925 | AG17: 24.4617 | AH17: 10.27692 | AK17: 179.37322 | AL17: 217.12263 | AM17: 7.93273 | BJ17: 32.327 | BK17: 184.87493 | BV17: 110.49702 | BW17: 206.49456 | BX17: 206.11549 | BY17: 205.99003 | CA17: 17.41583 | CB17: 44.05367 | CI17: 118.14735 | CJ17: 47.90514 | CK17: 53.71012 | CP17: 180.55348 | CQ17: 180.52451 | CR17: 181.33356 | CS17: 181.02912 | HH17: 2569.2352 | HI17: 2531.902 | HJ17: 1180.7008
B18: 06:00 | F18: 8.82587 | G18: 8.51669 | J18: 88.0592 | T18: 18.14123 | U18: 19.19196 | W18: 1.06127 | AA18: 23.06068 | AF18: 12.23925 | AG18: 24.4617 | AH18: 10.27692 | AK18: 179.37322 | AL18: 217.12263 | AM18: 7.93273 | BJ18: 32.327 | BK18: 184.87493 | BV18: 110.49702 | BW18: 206.49456 | BX18: 206.11549 | BY18: 205.99003 | CA18: 17.41583 | CB18: 44.05367 | CI18: 118.14735 | CJ18: 47.90514 | CK18: 53.71012 | CO18: 191.19621 | CP18: 180.55348 | CQ18: 180.52451 | CR18: 181.33356 | CS18: 181.02912 | HH18: 2760.4314 | HI18: 2723.0982 | HJ18: 1180.7008
B19: 06:30 | F19: 8.82587 | G19: 8.51669 | J19: 88.0592 | T19: 18.14123 | U19: 19.19196 | W19: 1.06127 | AA19: 23.06068 | AF19: 12.23925 | AG19: 24.4617 | AH19: 10.27692 | AK19: 179.37322 | AL19: 217.12263 | AM19: 7.93273 | BJ19: 32.327 | BK19: 184.87493 | BV19: 110.49702 | BW19: 206.49456 | BX19: 206.11549 | BY19: 205.99003 | CA19: 17.41583 | CB19: 44.05367 | CI19: 118.14735 | CJ19: 47.90514 | CK19: 53.71012 | CO19: 191.19621 | CP19: 180.55348 | CQ19: 180.52451 | CR19: 181.33356 | CS19: 181.02912 | HH19: 2760.4314 | HI19: 2723.0982 | HJ19: 1180.7008
B20: 07:00 | F20: 8.82587 | G20: 8.51669 | J20: 88.0592 | T20: 18.14123 | U20: 19.19196 | W20: 1.06127 | AA20: 23.06068 | AF20: 12.23925 | AG20: 24.4617 | AH20: 10.27692 | AK20: 179.37322 | AL20: 217.12263 | AM20: 7.93273 | BJ20: 32.327 | BK20: 184.87493 | BV20: 110.49702 | BW20: 206.49456 | BX20: 206.11549 | BY20: 205.99003 | CA20: 17.41583 | CB20: 44.05367 | CI20: 118.14735 | CJ20: 47.90514 | CK20: 53.71012 | CO20: 191.19621 | CP20: 180.55348 | CQ20: 180.52451 | CR20: 181.33356 | CS20: 181.02912 | HH20: 2760.4314 | HI20: 2723.0982 | HJ20: 1180.7008
