Workbook

Sheet EVENTOS
B3: jueves, 28 de Agosto del 2025
B5: INFORMACIÓN DE EVENTOS PRINCIPALES EN SUS INSTALACIONES
B6: TIPO DE EVENTO | C6: EMPRESA | D6: UBICACIÓN | E6: TIPO DE EQUIPO | F6: EQUIPO | G6: INICIO | H6: FINAL | I6: DESCRIPCIÓN | J6: MW INDISP. | K6: INTERRUPCIÓN (SI/NO) | L6: TENSIÓN DE FALLA (kV)
B7: EVENTO | C7: CONELSUR LT SAC | D7: PORTILLO | E7: SUBESTACION | F7: SS.EE. | G7: 28/08/2025 00:00:00 | H7: 29/08/2025 00:00:00 | I7: DECLARACIÓN DE SITUACIÓN EXCEPCIONAL EN LA S.E. PORTILLO DE 60 kV | K7: NO
B8: FALLA | C8: EGESUR | D8: INDEPENDENCIA | E8: GENERADOR TERMOELÉCTRICO | F8: INDEP_G2 | G8: 28/08/2025 14:39:00 | H8: 28/08/2025 14:45:00 | I8: DESCONECTO EL GENERADOR G2 DE LA C.T. INDEPENDENCIA, POR FALLA. | K8: NO | L8: 0
B9: FALLA | C9: SAN GABAN | D9: PCH TUPURI | E9: CENTRAL HIDROELÉCTRICA | F9: CENTRAL | G9: 28/08/2025 13:12:00 | H9: 28/08/2025 14:50:00 | I9: DESCONEXIÓN DE LA P.C.H. TUPURI | K9: NO | L9: 2.4
B10: EVENTO | C10: STATKRAFT S.A | D10: OROYA NUEVA - ALAMBRÓN | E10: LINEA DE TRANSMISION | F10: L-6513 | G10: 28/08/2025 07:46:00 | H10: 28/08/2025 08:47:00 | I10: DESCONECTÓ LA LÍNEA L-6513 (OROYA NUEVA – ALAMBRÓN) DE 50 KV POR FALLA QUE SE INVESTIGA | J10: 0.98 | K10: SI

Sheet RESTRIC_OPE
B3: jueves, 28 de Agosto del 2025
B5: RESTRICCIONES OPERATIVAS
B6: FECHA | C6: HORA INICIO | D6: HORA FINAL | E6: EMPRESA | F6: UBICACIÓN | G6: T.Eq. | H6: EQUIPO | I6: DESCRIPCIÓN
B7: 28/08/2025 | C7: 00:00 | D7: 24:00 | E7: EGASA | F7: S.E. CONVERTIDOR | G7: BARRA | H7: BARRA138KV | I7: EGASA limitó la capacidad del transformador 138 kV/33 kV a 50 MVA por deterioro del aislamiento.
B8: 28/08/2025 | C8: 00:00 | D8: 24:00 | E8: ELECTROPERU | F8: C.H. MANTARO | G8: CH | H8: CENTRAL | I8: De acuerdo con el correo del día 25.08.2025, la central tiene una limitación de potencia máxima de 650 MW por seguridad de la central.
B9: 28/08/2025 | C9: 00:00 | D9: 24:00 | E9: ENEL GENERACION PIURA S.A. | F9: C.T. MALACAS | G9: CT | H9: CENTRAL | I9: De acuerdo con la comunicación vía correo del día 24.10.2024. ENEL GENERACIÓN PIURA informa una restricción de potencia para alcanzar 105 MW en simultaneo (TG6+TGN4).
B10: 28/08/2025 | C10: 00:00 | D10: 24:00 | E10: ENEL GENERACION PIURA S.A. | F10: C.T. MALACAS | G10: GT | H10: TG4 | I10: De acuerdo a lo informado mediante correo electronico el día 04.07, la uniadTG4 puede operar a potencia efectiva durante 3 horas o con 80MW durante 4 horas, y el resto de los periodos a mínima generación.
B11: 28/08/2025 | C11: 00:00 | D11: 24:00 | E11: ENGIE | F11: C.H. YUNCÁN | G11: GH | H11: G3 | I11: Según la carta N° ENG/ 198-2024 enviada por su representada, se opera de forma continua el G3 de la CH Yuncán, debido a la ejecución de mantenimientos necesarios para evitar daños en los sellos de seguridad de la válvula esférica del grupo.
B12: 28/08/2025 | C12: 00:00 | D12: 24:00 | E12: ENGIE | F12: C.T. CHILCA 1 | G12: CT | H12: CENTRAL | I12: Restricción de temperatura de la C.T Chilca, ver valor en el modelo de despacho.
B13: 28/08/2025 | C13: 00:00 | D13: 24:00 | E13: ENGIE | F13: C.T. CHILCA 1 | G13: CT | H13: CENTRAL | I13: Con carta ENG/971-2023, indica que no puede cumplir con las IO considerada en el PDO_17122023 dado que vulneran la seguridad de sus activos. Indican que se debe tomar TMO=168h.
B14: 28/08/2025 | C14: 00:00 | D14: 24:00 | E14: ENGIE | F14: C.T. CHILCA 2 | G14: CT | H14: CENTRAL | I14: Con carta ENG/971-2023, indica que no puede cumplir con las IO considerada en el PDO_17122023 dado que vulneran la seguridad de sus activos. Indican que se debe tomar TMO=168h.
B15: 28/08/2025 | C15: 00:00 | D15: 24:00 | E15: FENIX POWER PERÚ | F15: C.T. FENIX | G15: CT | H15: CENTRAL | I15: De acuerdo con lo comunicado en el correo del día 06.05.2024, la CT Fenix cuenta con TMO de 168 hrs en todos su modos de operación.
B16: 28/08/2025 | C16: 00:00 | D16: 24:00 | E16: KALLPA GENERACION S.A. | F16: C.H. CERRO DEL AGUILA | G16: CH | H16: CENTRAL | I16: De acuerdo con el correo del 22.08.2025 la central se encuentra indisponible para dar RSF hasta el 29.08.2025.
B17: 28/08/2025 | C17: 00:00 | D17: 24:00 | E17: KALLPA GENERACION S.A. | F17: C.H. MINI CENTRAL CERRO DEL AGUILA | G17: CH | H17: CENTRAL | I17: De acuerdo con lo informado por Kallpa el día 20.08.2025, la MCH Cerro del Águila tiene TA=0.07h, TMO=0.08h, TMA=0.16h.
... B45: 28/08/2025 | C45: 00:00 | D45: 24:00 | E45: TERMOSELVA | F45: C.T. AGUAYTÍA | G45: CT | H45: CENTRAL | I45: Disponibilidad de 23.5 MMSCF para la CT Aguaytía.

Sheet MANTENIMIENTO EJECUTADOS
B3: jueves, 28 de Agosto del 2025
B5: Mantenimiento Ejecutado
B6: Empresa | C6: Ubicación | D6: Equipo | E6: Inicio | F6: Final | G6: Descripción | H6: MW Indisp. | I6: Prog. | J6: Dispon | K6: Interrupc. | L6: Tipo | M6: CodEq | N6: TipoEq_Osinerg
B7: ATLANTICA TRANSMISION SUR S.A. | C7: MONTALVO | D7: AUT-5672 | E7: 28/08/2025 00:00 | F7: 29/08/2025 00:00 | G7: Energizado por pruebas de puesta de servicio previo a su integracion. | H7: 0 | I7: P | J7: E/S | K7: N | L7: PRUEBA | M7: 24276 | N7: T
B8: ATLANTICA TRANSMISION SUR S.A. | C8: MONTALVO | D8: BARRA A_220KV | E8: 28/08/2025 00:00 | F8: 29/08/2025 00:00 | G8: Proyecto Refuerzos: Indisponibilidad de la proteccion diferencial de barras 220 kV por Conexion de la nueva UB-87B hacia la UC existente,Configuracion y Pruebas. | H8: 0 | I8: P | J8: E/S | K8: N | L8: P.ENERG | M8: 13869 | N8: T
B9: ATLANTICA TRANSMISION SUR S.A. | C9: MONTALVO | D9: BARRA A_500KV | E9: 28/08/2025 00:00 | F9: 29/08/2025 00:00 | G9: Proyecto Refuerzos: Indisponibilidad de la proteccion diferencial de barras 500kV por conexion de nueva UB-87B hacia la UC existente, Configuracion y Pruebas. | H9: 0 | I9: P | J9: E/S | K9: N | L9: P.ENERG | M9: 13870 | N9: T
B10: ATLANTICA TRANSMISION SUR S.A. | C10: MONTALVO | D10: BARRA B_220kV | E10: 28/08/2025 00:00 | F10: 29/08/2025 00:00 | G10: Proyecto Refuerzos: Indisponibilidad de la proteccion diferencial de barras 220 kV por Conexion de la nueva UB-87B hacia la UC existente,Configuracion y Pruebas. | H10: 0 | I10: P | J10: E/S | K10: N | L10: P.ENERG | M10: 14765 | N10: T
B11: ATLANTICA TRANSMISION SUR S.A. | C11: MONTALVO | D11: BARRA B_500KV | E11: 28/08/2025 00:00 | F11: 29/08/2025 00:00 | G11: Proyecto Refuerzos: Indisponibilidad de la proteccion diferencial de barras 500kV por conexion de nueva UB-87B hacia la UC existente, Configuracion y Pruebas. | H11: 0 | I11: P | J11: E/S | K11: N | L11: P.ENERG | M11: 13871 | N11: T
B12: ATLANTICA TRANSMISION SUR S.A. | C12: OCONA | D12: INT-5450 | E12: 28/08/2025 00:00 | F12: 29/08/2025 00:00 | G12: Interruptor INT-5450 cerrado con restriccion operativa, REB-5450 en servicio y suministrando los SS.AA. de la S.E. Oco?a. | H12: 0 | I12: P | J12: E/S | K12: N | L12: OTROS | M12: 13761 | N12: T
B13: ATLANTICA TRANSMISION SUR S.A. | C13: OCONA | D13: INT-5462 | E13: 28/08/2025 00:00 | F13: 29/08/2025 00:00 | G13: Seccionador SBA-5462 fase T indisponible por problemas mecanicos, el seccionador permanece cerrado y bloqueado | H13: 0 | I13: P | J13: E/S | K13: N | L13: OTROS | M13: 13758 | N13: T
B14: ATLANTICA TRANSMISION SUR S.A. | C14: POROMA | D14: AUT-5372 | E14: 28/08/2025 00:00 | F14: 29/08/2025 00:00 | G14: Energizado por pruebas de puesta de servicio previo a su integracion. | H14: 0 | I14: P | J14: E/S | K14: N | L14: PRUEBA | M14: 24298 | N14: T
B15: ATLANTICA TRANSMISION SUR S.A. | C15: POROMA | D15: BARRA A_220KV | E15: 28/08/2025 00:00 | F15: 29/08/2025 00:00 | G15: Proyecto Refuerzos: Indisponibilidad de la proteccion diferencial de barras 220 kV por Conexion de la nueva UB-87B hacia la UC existente,Configuracion y Pruebas. | H15: 0 | I15: P | J15: E/S | K15: N | L15: P.ENERG | M15: 13860 | N15: T
B16: ATLANTICA TRANSMISION SUR S.A. | C16: POROMA | D16: BARRA A_500KV | E16: 28/08/2025 00:00 | F16: 29/08/2025 00:00 | G16: Proyecto Refuerzos: Indisponibilidad de la proteccion diferencial de barras 500kV por conexion de nueva UB-87B hacia la UC existente, Configuracion y Pruebas. | H16: 0 | I16: P | J16: E/S | K16: N | L16: P.ENERG | M16: 13862 | N16: T
B17: ATLANTICA TRANSMISION SUR S.A. | C17: POROMA | D17: BARRA B_220KV | E17: 28/08/2025 00:00 | F17: 29/08/2025 00:00 | G17: Proyecto Refuerzos: Indisponibilidad de la proteccion diferencial de barras 220 kV por Conexion de la nueva UB-87B hacia la UC existente,Configuracion y Pruebas. | H17: 0 | I17: P | J17: E/S | K17: N | L17: P.ENERG | M17: 13861 | N17: T
B18: ATLANTICA TRANSMISION SUR S.A. | C18: POROMA | D18: BARRA B_500KV | E18: 28/08/2025 00:00 | F18: 29/08/2025 00:00 | G18: Proyecto Refuerzos: Indisponibilidad de la proteccion diferencial de barras 500kV por conexion de nueva UB-87B hacia la UC existente, Configuracion y Pruebas. | H18: 0 | I18: P | J18: E/S | K18: N | L18: P.ENERG | M18: 13863 | N18: T
... B122: VARI ENERGIA S.A.C. | C122: ANASHIRONI | D122: G1 | E122: 28/08/2025 00:00 | F122: 29/08/2025 00:00 | G122: CH. Anashironi en Servicio 5 MW en modo prueba por mantenimiento correctivo: * Revision de equipo caudalimetro de Sistema de Lubricacion. * Pruebas del sistema de lubricacion con grupo en vacio y con carga de 5 MW. | H122: 0 | I122: P | J122: E/S | K122: N | L122: CORR. | M122: 24348 | N122: G

Sheet INGRESO OC
A3: jueves, 28 de Agosto del 2025
A5: INGRESO A OPERACIÓN COMERCIAL
A6: EMPRESA | B6: TIPO DE EQUIPO | C6: UBICACIÓN | D6: EQUIPO | E6: Fecha y hora de Ingreso a Operación Comercial

Sheet DESPACHO_EJECUTADO
B3: jueves, 28 de Agosto del 2025
A5: POTENCIA ACTIVA EJECUTADA DE LAS UNIDADES DE GENERACIÓN DEL SEIN (MW) | FL5: CENTRALES NO INTEGRANTES COES
A6: FECHA | B6: HORA | C6: 65333 | D6: 101 | E6: 102 | F6: 42667 | G6: 42668 | H6: 126 | I6: 127 | J6: 138 | K6: 139 | L6: 197 | M6: 203 | N6: 204 | O6: 230 | P6: 209 | Q6: 56677 | R6: 796 | S6: 2146 | T6: 142 | U6: 143 | V6: 125 | W6: 187 | X6: 163 | Y6: 298 | Z6: 299 | AA6: 219 | AB6: 151 | AC6: 152 | AD6: 153 | AE6: 154 | AF6: 756 | AG6: 156 | AH6: 155 | AI6: 182 | AJ6: 212 | AK6: 758 | AL6: 263 | AM6: 265 | AN6: 775 | AO6: 777 | AP6: 2154 | AQ6: 150 | AR6: 149 | AS6: 188 | AT6: 2131 | AU6: 755 | AV6: 252 | AW6: 249 | AX6: 250 | AY6: 117 | AZ6: 267 | BA6: 268 | BB6: 119 | BC6: 120 | BD6: 189 | BE6: 122 | BF6: 266 | BG6: 337 | BH6: 338 | BI6: 251 | BJ6: 115 | BK6: 239 | BL6: 288 | BM6: 240 | BN6: 241 | BO6: 242 | BP6: 191 | BQ6: 194 | BR6: 196 | BS6: 207 | BT6: 236 | BU6: 795 | BV6: 285 | BW6: 995 | BX6: 996 | BY6: 997 | BZ6: 766 | CA6: 926 | CB6: 924 | CC6: 121 | CD6: 103 | CE6: 104 | CF6: 106 | CG6: 105 | CH6: 107 | CI6: 110 | CJ6: 109 | CK6: 144 | CL6: 113 | CM6: 114 | CN6: 193 | CO6: 208 | CP6: 786 | CQ6: 787 | CR6: 788 | CS6: 789 | CT6: 248 | CU6: 2159 | CV6: 303 | CW6: 59715 | CX6: 62255 | CY6: 1263 | CZ6: 61800 | DA6: 2194 | DB6: 69125 | DC6: 216 | DD6: 198 | DE6: 49607 | DF6: 214 | DG6: 260 | DH6: 2152 | DI6: 2128 | DJ6: 247 | DK6: 228 | DL6: 2135 | DM6: 261 | DN6: 237 | DO6: 253 | DP6: 770 | DQ6: 225 | DR6: 2201 | DS6: 2171 | DT6: 760 | DU6: 235 | DV6: 238 | DW6: 2184 | DX6: 61855 | DY6: 223 | DZ6: 226 | EA6: 201 | EB6: 258 | EC6: 259 | ED6: 920 | EE6: 257 | EF6: 256 | EG6: 2148 | EH6: 58288 | EI6: 58289 | EJ6: 58839 | EK6: 58840 | EL6: 296 | EM6: 297 | EN6: 211 | EO6: 2175 | EP6: 2178 | EQ6: 2181 | ER6: 1262 | ES6: 63425 | ET6: 233 | EU6: 2150 | EV6: 2165 | EW6: 2161 | EX6: 61197 | EY6: 58851 | EZ6: 234 | FA6: 215 | FB6: 917 | FC6: 289 | FD6: 58333 | FE6: 58336 | FF6: 213 | FG6: 232 | FH6: 2190 | FI6: 69867 | FJ6: TOTAL COES | FL6: 221 | FM6: 222 | FN6: 224 | FO6: 2187 | FP6: 227 | FQ6: 49400 | FR6: 199 | FS6: 200 | FT6: 70400 | FU6: TOTAL NO COES
C7: SUR | D7: CENTRO | E7: CENTRO | F7: NORTE | G7: NORTE | H7: NORTE | I7: NORTE | J7: CENTRO | K7: CENTRO | L7: CENTRO | M7: CENTRO | N7: CENTRO | O7: CENTRO | P7: CENTRO | Q7: CENTRO | R7: CENTRO | S7: CENTRO | T7: CENTRO | U7: CENTRO | V7: CENTRO | W7: CENTRO | X7: SUR | Y7: SUR | Z7: SUR | AA7: CENTRO | AB7: SUR | AC7: SUR | AD7: SUR | AE7: SUR | AF7: SUR | AG7: SUR | AH7: SUR | AI7: SUR | AJ7: CENTRO | AK7: NORTE | AL7: NORTE | AM7: NORTE | AN7: CENTRO | AO7: CENTRO | AP7: CENTRO | AQ7: CENTRO | AR7: CENTRO | AS7: CENTRO | AT7: CENTRO | AU7: SUR | AV7: CENTRO | AW7: CENTRO | AX7: CENTRO | AY7: CENTRO | AZ7: CENTRO | BA7: CENTRO | BB7: CENTRO | BC7: CENTRO | BD7: SUR | BE7: NORTE | BF7: CENTRO | BG7: CENTRO | BH7: CENTRO | BI7: CENTRO | BJ7: NORTE | BK7: NORTE | BL7: NORTE | BM7: SUR | BN7: SUR | BO7: SUR | BP7: CENTRO | BQ7: CENTRO | BR7: CENTRO | BS7: CENTRO | BT7: CENTRO | BU7: CENTRO | BV7: CENTRO | BW7: SUR | BX7: SUR | BY7: SUR | BZ7: NORTE | CA7: SUR | CB7: CENTRO | CC7: NORTE | CD7: CENTRO | CE7: CENTRO | CF7: CENTRO | CG7: CENTRO | CH7: CENTRO | CI7: CENTRO | CJ7: CENTRO | CK7: CENTRO | CL7: CENTRO | CM7: CENTRO | CN7: CENTRO | CO7: CENTRO | CP7: SUR | CQ7: SUR | CR7: SUR | CS7: SUR | CT7: CENTRO | CU7: CENTRO | CV7: CENTRO | CW7: CENTRO | CX7: SUR | CY7: NORTE | CZ7: NORTE | DA7: NORTE | DB7: CENTRO | DC7: NORTE | DD7: NORTE | DE7: SUR | DF7: CENTRO | DG7: CENTRO | DH7: CENTRO | DI7: NORTE | DJ7: NORTE | DK7: CENTRO | DL7: CENTRO | DM7: SUR | DN7: SUR | DO7: CENTRO | DP7: CENTRO | DQ7: CENTRO | DR7: CENTRO | DS7: CENTRO | DT7: CENTRO | DU7: SUR | DV7: CENTRO | DW7: CENTRO | DX7: NORTE | DY7: CENTRO | DZ7: CENTRO | EA7: NORTE | EB7: CENTRO | EC7: CENTRO | ED7: CENTRO | EE7: NORTE | EF7: NORTE | EG7: SUR | EH7: CENTRO | EI7: CENTRO | EJ7: CENTRO | EK7: CENTRO | EL7: CENTRO | EM7: CENTRO | EN7: SUR | EO7: SUR | EP7: SUR | EQ7: SUR | ER7: NORTE | ES7: SUR | ET7: SUR | EU7: SUR | EV7: CENTRO | EW7: CENTRO | EX7: CENTRO | EY7: SUR | EZ7: SUR | FA7: NORTE | FB7: CENTRO | FC7: NORTE | FD7: NORTE | FE7: NORTE | FF7: CENTRO | FG7: NORTE | FH7: NORTE | FI7: NORTE | FL7: NORTE | FM7: CENTRO | FN7: NORTE | FO7: NORTE | FP7: NORTE | FQ7: NORTE | FR7: NORTE | FS7: NORTE | FT7: SUR
C8: HIDROELÉCTRICA | D8: HIDROELÉCTRICA | E8: HIDROELÉCTRICA | F8: TERMOELÉCTRICA | G8: TERMOELÉCTRICA | H8: HIDROELÉCTRICA | I8: HIDROELÉCTRICA | J8: TERMOELÉCTRICA | K8: TERMOELÉCTRICA | L8: TERMOELÉCTRICA | M8: TERMOELÉCTRICA | N8: TERMOELÉCTRICA | O8: TERMOELÉCTRICA | P8: TERMOELÉCTRICA | Q8: TERMOELÉCTRICA | R8: HIDROELÉCTRICA | S8: HIDROELÉCTRICA | T8: TERMOELÉCTRICA | U8: TERMOELÉCTRICA | V8: TERMOELÉCTRICA | W8: TERMOELÉCTRICA | X8: HIDROELÉCTRICA | Y8: HIDROELÉCTRICA | Z8: HIDROELÉCTRICA | AA8: TERMOELÉCTRICA | AB8: HIDROELÉCTRICA | AC8: HIDROELÉCTRICA | AD8: HIDROELÉCTRICA | AE8: HIDROELÉCTRICA | AF8: TERMOELÉCTRICA | AG8: TERMOELÉCTRICA | AH8: TERMOELÉCTRICA | AI8: HIDROELÉCTRICA | AJ8: HIDROELÉCTRICA | AK8: TERMOELÉCTRICA | AL8: TERMOELÉCTRICA | AM8: TERMOELÉCTRICA | AN8: HIDROELÉCTRICA | AO8: HIDROELÉCTRICA | AP8: HIDROELÉCTRICA | AQ8: HIDROELÉCTRICA | AR8: HIDROELÉCTRICA | AS8: HIDROELÉCTRICA | AT8: HIDROELÉCTRICA | AU8: HIDROELÉCTRICA | AV8: TERMOELÉCTRICA | AW8: TERMOELÉCTRICA | AX8: TERMOELÉCTRICA | AY8: HIDROELÉCTRICA | AZ8: HIDROELÉCTRICA | BA8: HIDROELÉCTRICA | BB8: HIDROELÉCTRICA | BC8: HIDROELÉCTRICA | BD8: HIDROELÉCTRICA | BE8: HIDROELÉCTRICA | BF8: HIDROELÉCTRICA | BG8: HIDROELÉCTRICA | BH8: HIDROELÉCTRICA | BI8: HIDROELÉCTRICA | BJ8: TERMOELÉCTRICA | BK8: TERMOELÉCTRICA | BL8: TERMOELÉCTRICA | BM8: TERMOELÉCTRICA | BN8: TERMOELÉCTRICA | BO8: TERMOELÉCTRICA | BP8: HIDROELÉCTRICA | BQ8: TERMOELÉCTRICA | BR8: TERMOELÉCTRICA | BS8: TERMOELÉCTRICA | BT8: TERMOELÉCTRICA | BU8: TERMOELÉCTRICA | BV8: TERMOELÉCTRICA | BW8: TERMOELÉCTRICA | BX8: TERMOELÉCTRICA | BY8: TERMOELÉCTRICA | BZ8: HIDROELÉCTRICA | CA8: TERMOELÉCTRICA | CB8: TERMOELÉCTRICA | CC8: HIDROELÉCTRICA | CD8: HIDROELÉCTRICA | CE8: HIDROELÉCTRICA | CF8: HIDROELÉCTRICA | CG8: HIDROELÉCTRICA | CH8: HIDROELÉCTRICA | CI8: TERMOELÉCTRICA | CJ8: TERMOELÉCTRICA | CK8: TERMOELÉCTRICA | CL8: TERMOELÉCTRICA | CM8: TERMOELÉCTRICA | CN8: TERMOELÉCTRICA | CO8: TERMOELÉCTRICA | CP8: TERMOELÉCTRICA | CQ8: TERMOELÉCTRICA | CR8: TERMOELÉCTRICA | CS8: TERMOELÉCTRICA | CT8: TERMOELÉCTRICA | CU8: TERMOELÉCTRICA | CV8: SOLAR | CW8: EÓLICA | CX8: SOLAR | CY8: EÓLICA | CZ8: SOLAR | DA8: HIDROELÉCTRICA | DB8: HIDROELÉCTRICA | DC8: HIDROELÉCTRICA | DD8: HIDROELÉCTRICA | DE8: HIDROELÉCTRICA | DF8: HIDROELÉCTRICA | DG8: HIDROELÉCTRICA | DH8: HIDROELÉCTRICA | DI8: HIDROELÉCTRICA | DJ8: HIDROELÉCTRICA | DK8: HIDROELÉCTRICA | DL8: HIDROELÉCTRICA | DM8: SOLAR | DN8: SOLAR | DO8: EÓLICA | DP8: EÓLICA | DQ8: TERMOELÉCTRICA | DR8: TERMOELÉCTRICA | DS8: TERMOELÉCTRICA | DT8: TERMOELÉCTRICA | DU8: SOLAR | DV8: HIDROELÉCTRICA | DW8: HIDROELÉCTRICA | DX8: HIDROELÉCTRICA | DY8: HIDROELÉCTRICA | DZ8: HIDROELÉCTRICA | EA8: HIDROELÉCTRICA | EB8: HIDROELÉCTRICA | EC8: HIDROELÉCTRICA | ED8: HIDROELÉCTRICA | EE8: EÓLICA | EF8: EÓLICA | EG8: SOLAR | EH8: EÓLICA | EI8: EÓLICA | EJ8: EÓLICA | EK8: EÓLICA | EL8: HIDROELÉCTRICA | EM8: HIDROELÉCTRICA | EN8: HIDROELÉCTRICA | EO8: HIDROELÉCTRICA | EP8: HIDROELÉCTRICA | EQ8: HIDROELÉCTRICA | ER8: EÓLICA | ES8: SOLAR | ET8: SOLAR | EU8: SOLAR | EV8: HIDROELÉCTRICA | EW8: EÓLICA | EX8: EÓLICA | EY8: SOLAR | EZ8: SOLAR | FA8: HIDROELÉCTRICA | FB8: HIDROELÉCTRICA | FC8: TERMOELÉCTRICA | FD8: TERMOELÉCTRICA | FE8: TERMOELÉCTRICA | FF8: TERMOELÉCTRICA | FG8: TERMOELÉCTRICA | FH8: TERMOELÉCTRICA | FI8: TERMOELÉCTRICA | FL8: HIDROELÉCTRICA | FM8: HIDROELÉCTRICA | FN8: HIDROELÉCTRICA | FO8: HIDROELÉCTRICA | FP8: TERMOELÉCTRICA | FQ8: TERMOELÉCTRICA | FR8: HIDROELÉCTRICA | FS8: HIDROELÉCTRICA | FT8: SOLAR
C9: HYDRO GLOBAL PERÚ S.A.C. | D9: ELECTROPERU | E9: ELECTROPERU | F9: ELECTROPERU | G9: ELECTROPERU | H9: ORAZUL ENERGY PERÚ | I9: ORAZUL ENERGY PERÚ | J9: TERMOSELVA | K9: TERMOSELVA | L9: KALLPA GENERACION S.A. | M9: KALLPA GENERACION S.A. | N9: KALLPA GENERACION S.A. | O9: KALLPA GENERACION S.A. | P9: KALLPA GENERACION S.A. | Q9: KALLPA GENERACION S.A. | R9: KALLPA GENERACION S.A. | S9: KALLPA GENERACION S.A. | T9: SHOUGESA | U9: SHOUGESA | V9: SHOUGESA | W9: SHOUGESA | X9: EGEMSA | Y9: EGESUR | Z9: EGESUR | AA9: EGESUR | AB9: EGASA | AC9: EGASA | AD9: EGASA | AE9: EGASA | AF9: EGASA | AG9: EGASA | AH9: EGASA | AI9: SAN GABAN | AJ9: CELEPSA | AK9: MINERA CERRO VERDE | AL9: PLANTA DE RESERVA FRIA DE GENERACION DE ETEN S.A. | AM9: PLANTA DE RESERVA FRIA DE GENERACION DE ETEN S.A. | AN9: EMPRESA DE GENERACION HUALLAGA | AO9: EMPRESA DE GENERACION HUALLAGA | AP9: LA VIRGEN | AQ9: CHINANGO S.A.C. | AR9: CHINANGO S.A.C. | AS9: HIDROELECTRICA HUANCHOR S.A.C. | AT9: CELEPSA RENOVABLES S.R.L. | AU9: INLAND ENERGY SAC | AV9: FENIX POWER PERÚ | AW9: FENIX POWER PERÚ | AX9: FENIX POWER PERÚ | AY9: STATKRAFT S.A | AZ9: STATKRAFT S.A | BA9: STATKRAFT S.A | BB9: STATKRAFT S.A | BC9: STATKRAFT S.A | BD9: STATKRAFT S.A | BE9: STATKRAFT S.A | BF9: STATKRAFT S.A | BG9: CENTRALES SANTA ROSA S.A.C. | BH9: CENTRALES SANTA ROSA S.A.C. | BI9: EMPRESA DE GENERACION HUANZA | BJ9: ENEL GENERACION PIURA S.A. | BK9: ENEL GENERACION PIURA S.A. | BL9: ENEL GENERACION PIURA S.A. | BM9: ENGIE | BN9: ENGIE | BO9: ENGIE | BP9: ENGIE | BQ9: ENGIE | BR9: ENGIE | BS9: ENGIE | BT9: ENGIE | BU9: ENGIE | BV9: ENGIE | BW9: ENGIE | BX9: ENGIE | BY9: ENGIE | BZ9: ENGIE | CA9: INFRAESTRUCTURAS Y ENERGIAS DEL PERU S.A.C. | CB9: INFRAESTRUCTURAS Y ENERGIAS DEL PERU S.A.C. | CC9: INVERSIONES SHAQSHA S.A.C. | CD9: ORYGEN PERU S.A.A. | CE9: ORYGEN PERU S.A.A. | CF9: ORYGEN PERU S.A.A. | CG9: ORYGEN PERU S.A.A. | CH9: ORYGEN PERU S.A.A. | CI9: ORYGEN PERU S.A.A. | CJ9: ORYGEN PERU S.A.A. | CK9: ORYGEN PERU S.A.A. | CL9: ORYGEN PERU S.A.A. | CM9: ORYGEN PERU S.A.A. | CN9: ORYGEN PERU S.A.A. | CO9: ORYGEN PERU S.A.A. | CP9: SAMAY I S.A.C | CQ9: SAMAY I S.A.C | CR9: SAMAY I S.A.C | CS9: SAMAY I S.A.C | CT9: TERMOCHILCA S.A.C. | CU9: TERMOCHILCA S.A.C. | CV9: COLCA SOLAR S.A.C. | CW9: ENERGIA RENOVABLE DEL SUR S.A. | CX9: GR CORTARRAMA SOCIEDAD ANONIMA CERRADA | CY9: GR TARUCA SOCIEDAD ANONIMA CERRADA | CZ9: KONDU SAC | DA9: PERUANA DE INVERSIONES EN ENERGIAS RENOVABLES S.A. | DB9: VARI ENERGIA S.A.C. | DC9: ORAZUL ENERGY PERÚ | DD9: ORAZUL ENERGY PERÚ | DE9: SAN GABAN | DF9: MAJA ENERGIA S.A.C. | DG9: EMPRESA DE GENERACION ELECTRICA CANCHAYLLO SAC | DH9: EMPRESA DE GENERACION ELECTRICA SANTA ANA S.A.C. | DI9: EMPRESA ELECTRICA AGUA AZUL | DJ9: EMPRESA ELECTRICA RIO DOBLE | DK9: HIDROCAÑETE S.A. | DL9: HUAURA POWER GROUP S.A. | DM9: MOQUEGUA FV S.A.C. | DN9: PANAMERICANA SOLAR SAC. | DO9: PARQUE EOLICO MARCONA S.A.C. | DP9: PARQUE EOLICO TRES HERMANAS S.A.C. | DQ9: PETRAMAS | DR9: PETRAMAS | DS9: PETRAMAS | DT9: PETRAMAS | DU9: TACNA SOLAR SAC. | DV9: ELECTRICA YANAPAMPA SAC | DW9: ANDEAN POWER S.A.C. | DX9: ASOCIACIÓN SANTA LUCIA DE CHACAS | DY9: ATRIA ENERGIA S.A.C. | DZ9: EGEJUNIN | EA9: EGEJUNIN | EB9: EGEJUNIN | EC9: EGEJUNIN | ED9: EMPRESA DE GENERACION ELECTRICA RIO BAÑOS S.A.C. | EE9: ENERGÍA EÓLICA S.A. | EF9: ENERGÍA EÓLICA S.A. | EG9: ENGIE | EH9: ENGIE | EI9: ENGIE | EJ9: ENGIE | EK9: ENGIE | EL9: GENERACIÓN ANDINA S.A.C. | EM9: GENERACIÓN ANDINA S.A.C. | EN9: GENERADORA DE ENERGÍA DEL PERÚ | EO9: GENERADORA DE ENERGÍA DEL PERÚ | EP9: GENERADORA DE ENERGÍA DEL PERÚ | EQ9: GENERADORA DE ENERGÍA DEL PERÚ | ER9: GR PAINO SOCIEDAD ANONIMA CERRADA | ES9: JOYA SOLAR S.A.C. | ET9: MAJES ARCUS S.A.C. | EU9: ORYGEN PERU S.A.A. | EV9: ORYGEN PERU S.A.A. | EW9: ORYGEN PERU S.A.A. | EX9: ORYGEN PERU S.A.A. | EY9: ORYGEN PERU S.A.A. | EZ9: REPARTICIÓN ARCUS S.A.C. | FA9: SINERSA | FB9: SINERSA | FC9: BIOENERGIA DEL CHIRA S.A. | FD9: GM OPERACIONES S.A.C. | FE9: GM OPERACIONES S.A.C. | FF9: AGRO INDUSTRIAL PARAMONGA S.A. | FG9: AGROAURORA S.A.C. | FH9: AGROINDUSTRIAS SAN JACINTO S.A.A. | FI9: AGROLMOS SOCIEDAD ANONIMA - AGROLMOS S.A. | FL9: UNACEM PERU S.A. | FM9: ELECTRO ORIENTE | FN9: AGUAS Y ENERGIA PERU | FO9: ELECTRO ZAÑA S.A.C. | FP9: ELECTRONOROESTE S.A. | FQ9: SDE PIURA | FR9: SINERSA | FS9: SINERSA | FT9: KALLPA GENERACION S.A.
C10: SAN GABAN III | D10: MANTARO | E10: RESTITUCION | F10: TUMBES MAK 1 | G10: TUMBES MAK 2 | H10: CARHUAQUERO | I10: CAÑON DEL PATO | J10: AGUAYTIA TG1 | K10: AGUAYTIA TG2 | L10: KALLPA TG1 | M10: KALLPA TG2 | N10: KALLPA TG3 | O10: KALLPA TV | P10: LFLORES TG1 | Q10: LFLORES TV | R10: CERRO DEL AGUILA | S10: CERRODELAGUILAG4 | T10: SHOUGESA TV1 | U10: SHOUGESA TV2 | V10: SHOUGESA TV3 | W10: SHOUGESA CUMMINS | X10: MACHUPICCHU | Y10: ARICOTA 1 | Z10: ARICOTA 2 | AA10: INDEPENDENCIA | AB10: CHARCANI I,II,III | AC10: CHARCANI IV | AD10: CHARCANI V | AE10: CHARCANI VI | AF10: CHILINA TG | AG10: MOLLENDO 1, 2, 3 | AH10: CHILINA (SULZ 1,2) | AI10: SAN GABAN II | AJ10: PLATANAL | AK10: RECKA | AL10: RF ETEN TG1 | AM10: RF ETEN TG2 | AN10: CHAGLLA GP1 | AO10: CHAGLLA | AP10: LA VIRGEN | AQ10: CHIMAY | AR10: YANANGO | AS10: HUANCHOR | AT10: MARAÑON | AU10: STA TERESA | AV10: FENIX GT11 | AW10: FENIX GT12 | AX10: FENIX TV10 | AY10: YAUPI | AZ10: OROYA | BA10: PACHACHACA | BB10: MALPASO | BC10: CAHUA | BD10: ARCATA | BE10: GALLITO CIEGO | BF10: CHEVES | BG10: SANTA ROSA 1 | BH10: SANTA ROSA 2 | BI10: HUANZA | BJ10: MALACAS2 TG4 | BK10: MALACAS3 TG 5 | BL10: MALACAS1 TG6 | BM10: RF ILO2 TG1 | BN10: RF ILO2 TG2 | BO10: RF ILO2 TG3 | BP10: YUNCAN | BQ10: CHILCA1 TG1 | BR10: CHILCA1 TG2 | BS10: CHILCA1 TG3 | BT10: CHILCA-TV | BU10: CHILCA2 TG41 | BV10: CHILCA2-TV | BW10: CTNEPI_TG41 | BX10: CTNEPI_TG42 | BY10: CTNEPI_TG43 | BZ10: QUITARACSA | CA10: RF PTO MALDONADO | CB10: RF PUCALLPA | CC10: PARIAC | CD10: HUINCO | CE10: MATUCANA | CF10: MOYOPAMPA | CG10: CALLAHUANCA | CH10: HUAMPANI | CI10: STA ROSA WEST TG7 | CJ10: UTI_5 | CK10: UTI_6 | CL10: VENTANILLA 3 | CM10: VENTANILLA 4 | CN10: VENTANILLA TV | CO10: STAROSA TG8 | CP10: PTO_BRVO TG1 | CQ10: PTO_BRVO TG2 | CR10: PTO_BRVO TG3 | CS10: PTO_BRVO TG4 | CT10: OLLEROS TG1 | CU10: OLLEROS TV | CV10: CS YARUCAYA | CW10: SAN JUAN | CX10: MATARANI | CY10: DUNA | CZ10: CARHUAQUERO (CS) | DA10: MANTA I | DB10: ANASHIRONI | DC10: CARHUAQUERO4 | DD10: CAÑA BRAVA | DE10: TUPURI | DF10: RONCADOR | DG10: CANCHAYLLO | DH10: RENOVANDESH1 | DI10: POTRERO | DJ10: PIZARRAS | DK10: NIMPERIAL | DL10: YARUCAYA | DM10: MOQUEGUA-SOLAR | DN10: PANAMERICANA-SOLAR | DO10: PQE-EOLICO-MARCONA | DP10: PQE-EOLICO-3-HERMANAS | DQ10: HUAYCOLORO | DR10: CALLAO | DS10: DONA_CATALINA | DT10: LAGRINGAV | DU10: TACNA-SOLAR | DV10: YANAPAMPA | DW10: CARHUAC | DX10: HUALLIN | DY10: PURMACANA | DZ10: HUASAHUASI | EA10: STACRUZ_1_2 | EB10: RUNATULLO_II | EC10: RUNATULLO_III | ED10: RUCUY | EE10: PQE-EOLICO-TALARA | EF10: PQE-EOLICO-CUPISNIQUE | EG10: INTIPAMPA | EH10: PUNTA LOMITAS-BL1 | EI10: PUNTA LOMITAS-BL2 | EJ10: PUN LOMITAS_EXP-BL1 | EK10: PUN LOMITAS_EXP-BL2 | EL10: 8AGOSTO | EM10: EL CARMEN | EN10: LA JOYA | EO10: ANGEL_I | EP10: ANGEL_II | EQ10: ANGEL_III | ER10: HUAMBOS | ES10: SAN MARTIN SOLAR | ET10: MAJES | EU10: RUBI | EV10: CH_HER1 | EW10: WAYRA-I | EX10: WAYRA EXTENSION | EY10: CLEMESI | EZ10: REPARTICION | FA10: POECHOS2 | FB10: CHANCAY | FC10: CANA BRAVA | FD10: REFINERIA TALARA TV1 | FE10: REFINERÍA TALARA TV2 | FF10: PARAMONGA | FG10: MAPLE | FH10: SAN_JACINTO | FI10: AGROLMOS | FJ10: MW | FL10: CARPAPATA | FM10: CENTRALES ELOR | FN10: PIAS1 | FO10: ZANA | FP10: TABLAZO | FQ10: TALLANCA | FR10: CURUMUY | FS10: POECHOS1 | FT10: SUNNY | FU10: MW
A11: 28/08/2025 | B11: 00:30 | C11: 99.9 | D11: 639.8 | E11: 214.7 | H11: 8.1 | I11: 78.1 | L11: 189.3 | M11: 204.6 | N11: 204.1 | O11: 284.5 | P11: 217.8 | Q11: 111.1 | R11: 198.9 | S11: 3.2 | T11: 0 | X11: 120.5 | Y11: 7.4 | Z11: 3.3 | AA11: 0 | AB11: 6.34 | AC11: 9.66 | AD11: 40.31 | AI11: 60.7 | AJ11: 99.84518 | AN11: 6.5 | AO11: 154 | AP11: 29.5 | AQ11: 55.8 | AR11: 17.2 | AS11: 18.4 | AT11: 10.9 | AU11: 63.3 | AV11: 183 | AW11: 182.9 | AX11: 184.7 | AY11: 66.8 | BA11: 0 | BB11: 15.6 | BC11: 32.9 | BD11: 2 | BE11: 0 | BF11: 85.1 | BI11: 0 | BL11: 47.5 | BP11: 34.1 | BQ11: 179.1 | BR11: 176.7 | BS11: 211.5 | BT11: 274.8 | BU11: 12 | BV11: 0 | CC11: 0.4 | CD11: 143.7 | CE11: 92.2 | CF11: 63 | CG11: 70 | CH11: 29.3 | CL11: 147.5 | CM11: 149.8 | CN11: 150 | CO11: 0 | CT11: 218.3 | CU11: 104.7 | CV11: 0 | CW11: 26.9 | CX11: 0 | CY11: 18.1 | CZ11: 0 | DA11: 4.9 | DB11: 5.1 | DC11: 6.5 | DD11: 2.5 | DE11: 0.3 | DF11: 1.8 | DG11: 4.4 | DH11: 15.9 | DI11: 3.9 | DJ11: 3.1 | DK11: 3.3 | DL11: 18.5 | DM11: 0 | DN11: 0 | DO11: 5 | DP11: 23.7 | DQ11: 3.6 | DR11: 1.1 | DS11: 1.2 | DT11: 2.4 | DU11: 0 | DV11: 2.3 | DW11: 8.8 | DX11: 1.3 | DZ11: 5.5 | EA11: 3 | EB11: 5.1 | EC11: 6.8 | ED11: 10 | EE11: 22.5 | EF11: 9.2 | EG11: 0 | EH11: 34.5 | EI11: 49.1 | EJ11: 3.4 | EK11: 3 | EL11: 8.2 | EM11: 1.8 | EO11: 4 | EP11: 4.5 | EQ11: 5.2 | ER11: 16.7 | ES11: 0 | ET11: 0 | EU11: 0 | EV11: 0.6 | EW11: 22.2 | EX11: 22.1 | EY11: 0 | EZ11: 0 | FA11: 7.6 | FB11: 19.7 | FC11: 9.6 | FD11: 33.8 | FE11: 29.4 | FF11: 14.5 | FG11: 18.3 | FH11: 9.1 | FI11: 11.09 | FJ11: 6570.4452 | FL11: 18.66829 | FM11: 8.07 | FN11: 6.1 | FO11: 6.2 | FP11: 27.5 | FQ11: 18.91854 | FR11: 5 | FS11: 5 | FU11: 95.45683
A12: 28/08/2025 | B12: 01:00 | C12: 99.7 | D12: 638.5 | E12: 214.3 | H12: 0 | I12: 79.3 | L12: 190 | M12: 203.7 | N12: 203.8 | O12: 285 | P12: 216.5 | Q12: 111.4 | R12: 198.9 | S12: 3.3 | T12: 0 | X12: 126.7 | Y12: 7.4 | Z12: 3.4 | AA12: 0 | AB12: 6.38 | AC12: 9.66 | AD12: 41.08 | AI12: 60.5 | AJ12: 109.89748 | AN12: 6.5 | AO12: 154.3 | AP12: 29.2 | AQ12: 53.5 | AR12: 17.9 | AS12: 18.4 | AT12: 10.9 | AU12: 63.7 | AV12: 183.2 | AW12: 184.6 | AX12: 184.2 | AY12: 51.5 | BA12: 0 | BB12: 12.8 | BC12: 33.3 | BD12: 2 | BE12: 0 | BF12: 81.9 | BI12: 0 | BL12: 47 | BP12: 34.9 | BQ12: 179.8 | BR12: 176.9 | BS12: 212 | BT12: 274.9 | BU12: 12.3 | BV12: 0 | CC12: 0.4 | CD12: 137.3 | CE12: 91.5 | CF12: 63.2 | CG12: 69.7 | CH12: 29.2 | CL12: 146.7 | CM12: 149.1 | CN12: 149.8 | CO12: 0 | CT12: 218.4 | CU12: 104.6 | CV12: 0 | CW12: 19.5 | CX12: 0 | CY12: 18.1 | CZ12: 0 | DA12: 4.9 | DB12: 5.1 | DC12: 0 | DD12: 0 | DE12: 0.3 | DF12: 1.8 | DG12: 4.4 | DH12: 15.6 | DI12: 3.9 | DJ12: 3.1 | DK12: 3.3 | DL12: 18.5 | DM12: 0 | DN12: 0 | DO12: 4.7 | DP12: 20.9 | DQ12: 3.7 | DR12: 0.8 | DS12: 1.2 | DT12: 2.4 | DU12: 0 | DV12: 2.4 | DW12: 0.6 | DX12: 1.3 | DZ12: 5.4 | EA12: 3.2 | EB12: 4.8 | EC12: 6.8 | ED12: 10 | EE12: 26.8 | EF12: 7.3 | EG12: 0 | EH12: 28.9 | EI12: 45.5 | EJ12: 3.9 | EK12: 3.1 | EL12: 8 | EM12: 1.8 | EO12: 4 | EP12: 4.5 | EQ12: 4.7 | ER12: 17.4 | ES12: 0 | ET12: 0 | EU12: 0 | EV12: 0.6 | EW12: 21 | EX12: 22.8 | EY12: 0 | EZ12: 0 | FA12: 7.1 | FB12: 19.5 | FC12: 9 | FD12: 33.5 | FE12: 29.2 | FF12: 14.6 | FG12: 18.3 | FH12: 8.6 | FI12: 11.01 | FJ12: 6512.8275 | FL12: 19.03531 | FM12: 0.41 | FN12: 6.1 | FO12: 6.2 | FP12: 27.5 | FQ12: 18.91825 | FR12: 5 | FS12: 5.1 | FU12: 88.26356
A13: 28/08/2025 | B13: 01:30 | C13: 97.1 | D13: 630.4 | E13: 211.5 | H13: 0 | I13: 76.9 | L13: 189.2 | M13: 203.6 | N13: 203.4 | O13: 286.9 | P13: 217.3 | Q13: 110.7 | R13: 191.9 | S13: 2.9 | T13: 0 | X13: 119.6 | Y13: 6.8 | Z13: 3.1 | AA13: 0 | AB13: 6.37 | AC13: 9.65 | AD13: 38.92 | AI13: 58.7 | AJ13: 107.52872 | AN13: 6.5 | AO13: 0 | AP13: 30.4 | AQ13: 58.5 | AR13: 17.5 | AS13: 18.5 | AT13: 10.9 | AU13: 61 | AV13: 178.4 | AW13: 178.3 | AX13: 184.1 | AY13: 52.2 | BA13: 0 | BB13: 3 | BC13: 32.3 | BD13: 2 | BE13: 0 | BF13: 82.8 | BI13: 0 | BL13: 46.9 | BP13: 33.7 | BQ13: 178.8 | BR13: 177.3 | BS13: 211.8 | BT13: 274.9 | BU13: 12 | BV13: 0 | CC13: 0.4 | CD13: 139.6 | CE13: 81.9 | CF13: 61.4 | CG13: 69.3 | CH13: 28.5 | CL13: 147.5 | CM13: 149.8 | CN13: 149.6 | CO13: 0 | CT13: 218.3 | CU13: 104.7 | CV13: 0 | CW13: 22.1 | CX13: 0 | CY13: 17.8 | CZ13: 0 | DA13: 5 | DB13: 4.9 | DC13: 0 | DD13: 0 | DE13: 0.3 | DF13: 1.8 | DG13: 4.8 | DH13: 15.2 | DI13: 4.1 | DJ13: 3.1 | DK13: 3.3 | DL13: 18.5 | DM13: 0 | DN13: 0 | DO13: 6.1 | DP13: 21.8 | DQ13: 4.1 | DR13: 0.7 | DS13: 1.2 | DT13: 3 | DU13: 0 | DV13: 2.5 | DW13: 0 | DX13: 1.3 | DZ13: 5.4 | EA13: 3.2 | EB13: 5 | EC13: 7 | ED13: 10 | EE13: 26.8 | EF13: 6.4 | EG13: 0 | EH13: 23.6 | EI13: 39.1 | EJ13: 2.9 | EK13: 2.8 | EL13: 8 | EM13: 1.8 | EO13: 4.2 | EP13: 4.5 | EQ13: 4.7 | ER13: 16.2 | ES13: 0 | ET13: 0 | EU13: 0 | EV13: 0.6 | EW13: 20.6 | EX13: 17.7 | EY13: 0 | EZ13: 0 | FA13: 7.1 | FB13: 19.2 | FC13: 8.9 | FD13: 33.6 | FE13: 29.5 | FF13: 13.5 | FG13: 18.3 | FH13: 9.4 | FI13: 10.73 | FJ13: 6277.5987 | FL13: 19.19653 | FM13: 0 | FN13: 6.1 | FO13: 6.2 | FP13: 27.5 | FQ13: 18.91818 | FR13: 5.1 | FS13: 5 | FU13: 88.01471
A14: 28/08/2025 | B14: 02:00 | C14: 99.8 | D14: 639.9 | E14: 214.9 | H14: 0 | I14: 78.5 | L14: 189.9 | M14: 205.7 | N14: 203.6 | O14: 283.2 | P14: 216.9 | Q14: 111 | R14: 250.9 | S14: 3.2 | T14: 0 | X14: 120.9 | Y14: 7.6 | Z14: 3.4 | AA14: 0 | AB14: 6.37 | AC14: 9.66 | AD14: 40.4 | AI14: 60.5 | AJ14: 104.20957 | AN14: 6.5 | AO14: 0 | AP14: 28.2 | AQ14: 59.2 | AR14: 18 | AS14: 18.4 | AT14: 10.9 | AU14: 63.7 | AV14: 183.2 | AW14: 183.3 | AX14: 185.1 | AY14: 53.4 | BA14: 0 | BB14: 13.3 | BC14: 34.7 | BD14: 2 | BE14: 0 | BF14: 29.1 | BI14: 0 | BL14: 47.2 | BP14: 34.8 | BQ14: 179.1 | BR14: 176.4 | BS14: 211.3 | BT14: 274.3 | BU14: 12 | BV14: 0 | CC14: 0.4 | CD14: 138.5 | CE14: 87.8 | CF14: 63 | CG14: 66.9 | CH14: 29.3 | CL14: 147.3 | CM14: 149.7 | CN14: 149.9 | CO14: 0 | CT14: 217.8 | CU14: 104.4 | CV14: 0 | CW14: 22.4 | CX14: 0 | CY14: 17.2 | CZ14: 0 | DA14: 5 | DB14: 5.1 | DC14: 0 | DD14: 0 | DE14: 0.3 | DF14: 1.8 | DG14: 4.8 | DH14: 15.9 | DI14: 4.2 | DJ14: 3.1 | DK14: 3.3 | DL14: 18.5 | DM14: 0 | DN14: 0 | DO14: 5.9 | DP14: 20.2 | DQ14: 4.4 | DR14: 1.1 | DS14: 1.2 | DT14: 3 | DU14: 0 | DV14: 2.5 | DW14: 0 | DX14: 1.3 | DZ14: 5.4 | EA14: 3.2 | EB14: 5 | EC14: 7.2 | ED14: 10 | EE14: 27.2 | EF14: 4.7 | EG14: 0 | EH14: 22.3 | EI14: 32.9 | EJ14: 3 | EK14: 2.3 | EL14: 7.8 | EM14: 1.8 | EO14: 4.5 | EP14: 4.5 | EQ14: 4.7 | ER14: 13.9 | ES14: 0 | ET14: 0 | EU14: 0 | EV14: 0.6 | EW14: 19.9 | EX14: 17.3 | EY14: 0 | EZ14: 0 | FA14: 7.1 | FB14: 19.2 | FC14: 9.3 | FD14: 33.7 | FE14: 29.5 | FF14: 13.5 | FG14: 18.3 | FH14: 7.9 | FI14: 11.05 | FJ14: 6318.5896 | FL14: 19.41718 | FM14: 0 | FN14: 6.1 | FO14: 6.2 | FP14: 27.5 | FQ14: 18.91809 | FR14: 5.1 | FS14: 5.1 | FU14: 88.33527
A15: 28/08/2025 | B15: 02:30 | C15: 99.6 | D15: 637.3 | E15: 213.8 | H15: 0 | I15: 79 | L15: 189.4 | M15: 205 | N15: 204 | O15: 282.2 | P15: 217.1 | Q15: 111 | R15: 245.7 | S15: 3.2 | T15: 0 | X15: 119.9 | Y15: 7.2 | Z15: 3.2 | AA15: 0 | AB15: 6.36 | AC15: 9.67 | AD15: 40.02 | AI15: 60.1 | AJ15: 98.42813 | AN15: 6.5 | AO15: 0 | AP15: 31 | AQ15: 48.4 | AR15: 19.3 | AS15: 18.5 | AT15: 10.9 | AU15: 62.4 | AV15: 181.9 | AW15: 182.4 | AX15: 184.1 | AY15: 52.7 | BA15: 0 | BB15: 11.7 | BC15: 19.9 | BD15: 2 | BE15: 0 | BF15: 25.5 | BI15: 0 | BL15: 47.4 | BP15: 34.8 | BQ15: 179.2 | BR15: 176.8 | BS15: 211.4 | BT15: 274.6 | BU15: 12.2 | BV15: 0 | CC15: 0.4 | CD15: 84 | CE15: 79.7 | CF15: 63.9 | CG15: 67.6 | CH15: 29.2 | CL15: 147.6 | CM15: 150.1 | CN15: 150.3 | CO15: 0 | CT15: 218.2 | CU15: 104.8 | CV15: 0 | CW15: 21.2 | CX15: 0 | CY15: 14.6 | CZ15: 0 | DA15: 5.1 | DB15: 5.1 | DC15: 0 | DD15: 0 | DE15: 0.3 | DF15: 1.8 | DG15: 4.8 | DH15: 15.6 | DI15: 4.2 | DJ15: 3.1 | DK15: 3.3 | DL15: 18.5 | DM15: 0 | DN15: 0 | DO15: 5.1 | DP15: 20.6 | DQ15: 4.4 | DR15: 1.1 | DS15: 1.2 | DT15: 3 | DU15: 0 | DV15: 2.3 | DW15: 0 | DX15: 1.2 | DZ15: 5.4 | EA15: 3.2 | EB15: 4.8 | EC15: 7.1 | ED15: 10 | EE15: 26.8 | EF15: 2.3 | EG15: 0 | EH15: 18.9 | EI15: 31.5 | EJ15: 2.1 | EK15: 1.3 | EL15: 7.7 | EM15: 1.8 | EO15: 4.7 | EP15: 4.5 | EQ15: 4.7 | ER15: 11 | ES15: 0 | ET15: 0 | EU15: 0 | EV15: 0.6 | EW15: 14.9 | EX15: 11.4 | EY15: 0 | EZ15: 0 | FA15: 7.1 | FB15: 19.2 | FC15: 9.2 | FD15: 33.6 | FE15: 29.4 | FF15: 14 | FG15: 18.3 | FH15: 7.3 | FI15: 11.05 | FJ15: 6181.9281 | FL15: 20.00964 | FM15: 0 | FN15: 6.1 | FO15: 6.2 | FP15: 27.4 | FQ15: 18.91806 | FR15: 5.2 | FS15: 5.1 | FU15: 88.9277
A16: 28/08/2025 | B16: 03:00 | C16: 99.4 | D16: 639.2 | E16: 214.5 | H16: 0 | I16: 81.9 | L16: 189 | M16: 206.2 | N16: 206.6 | O16: 282 | P16: 217.7 | Q16: 110.9 | R16: 179 | S16: 3.2 | T16: 0 | X16: 122.2 | Y16: 7.4 | Z16: 3.3 | AA16: 0 | AB16: 6.33 | AC16: 9.66 | AD16: 40.68 | AI16: 60.8 | AJ16: 71.31502 | AN16: 6.5 | AO16: 0 | AP16: 29.4 | AQ16: 61.4 | AR16: 19.6 | AS16: 18.6 | AT16: 10.9 | AU16: 62.7 | AV16: 184.2 | AW16: 184.6 | AX16: 184.9 | AY16: 53.4 | BA16: 0 | BB16: 21.7 | BC16: 36.5 | BD16: 2 | BE16: 0 | BF16: 84.5 | BI16: 0 | BL16: 46.8 | BP16: 35 | BQ16: 178.9 | BR16: 176.7 | BS16: 211.4 | BT16: 274.5 | BU16: 13.2 | BV16: 0 | CC16: 0.4 | CD16: 163 | CE16: 96.6 | CF16: 64.1 | CG16: 69.9 | CH16: 29.3 | CL16: 147.7 | CM16: 150.2 | CN16: 150.4 | CO16: 0 | CT16: 217.9 | CU16: 104.6 | CV16: 0 | CW16: 19.2 | CX16: 0 | CY16: 12.5 | CZ16: 0 | DA16: 5 | DB16: 5.2 | DC16: 0 | DD16: 0 | DE16: 0.3 | DF16: 1.8 | DG16: 4.7 | DH16: 15.8 | DI16: 4.3 | DJ16: 3.1 | DK16: 3.3 | DL16: 18.5 | DM16: 0 | DN16: 0 | DO16: 4.4 | DP16: 14.6 | DQ16: 4.4 | DR16: 1.1 | DS16: 1.2 | DT16: 3 | DU16: 0 | DV16: 2.4 | DW16: 0 | DX16: 1.2 | DZ16: 5.5 | EA16: 3.2 | EB16: 4.8 | EC16: 7.2 | ED16: 10 | EE16: 26.1 | EF16: 2.6 | EG16: 0 | EH16: 15.5 | EI16: 26.8 | EJ16: 2.1 | EK16: 1.3 | EL16: 7.6 | EM16: 1.8 | EO16: 4.5 | EP16: 5.2 | EQ16: 5.2 | ER16: 11.6 | ES16: 0 | ET16: 0 | EU16: 0 | EV16: 0.6 | EW16: 14.1 | EX16: 9 | EY16: 0 | EZ16: 0 | FA16: 7.1 | FB16: 19.5 | FC16: 9.5 | FD16: 33.5 | FE16: 29.2 | FF16: 13.7 | FG16: 18.3 | FH16: 8.2 | FI16: 11.06 | FJ16: 6283.545 | FL16: 20.18062 | FM16: 0 | FN16: 6.1 | FO16: 6.2 | FP16: 27.4 | FQ16: 18.91821 | FR16: 5.3 | FS16: 5 | FU16: 89.09883
A17: 28/08/2025 | B17: 03:30 | C17: 99.6 | D17: 642.2 | E17: 215.7 | H17: 0 | I17: 82.4 | L17: 189.3 | M17: 206.6 | N17: 205.7 | O17: 283.4 | P17: 216.2 | Q17: 110.7 | R17: 178.8 | S17: 3.2 | T17: 0 | X17: 122 | Y17: 7.7 | Z17: 3.4 | AA17: 0 | AB17: 6.36 | AC17: 9.63 | AD17: 40.15 | AI17: 61 | AJ17: 52.57629 | AN17: 6.5 | AO17: 0 | AP17: 31.7 | AQ17: 69.5 | AR17: 21.9 | AS17: 18.6 | AT17: 10.9 | AU17: 65.4 | AV17: 183.4 | AW17: 184 | AX17: 184.5 | AY17: 53.5 | BA17: 0 | BB17: 4.7 | BC17: 24.4 | BD17: 2 | BE17: 0 | BF17: 85.2 | BI17: 0 | BL17: 47.8 | BP17: 35.3 | BQ17: 178.4 | BR17: 176 | BS17: 211.1 | BT17: 274.6 | BU17: 14.9 | BV17: 0 | CC17: 0.4 | CD17: 163.3 | CE17: 99 | CF17: 64.5 | CG17: 69.9 | CH17: 29.5 | CL17: 148 | CM17: 150.3 | CN17: 150.8 | CO17: 0 | CT17: 218.2 | CU17: 104.6 | CV17: 0 | CW17: 18.2 | CX17: 0 | CY17: 15.1 | CZ17: 0 | DA17: 5 | DB17: 5.2 | DC17: 0 | DD17: 0 | DE17: 0.3 | DF17: 1.8 | DG17: 4.7 | DH17: 16.1 | DI17: 4.4 | DJ17: 3.1 | DK17: 3.3 | DL17: 18.5 | DM17: 0 | DN17: 0 | DO17: 2.7 | DP17: 10.1 | DQ17: 4.4 | DR17: 1.1 | DS17: 1.2 | DT17: 3 | DU17: 0 | DV17: 2.4 | DW17: 0 | DX17: 1.2 | DZ17: 5.5 | EA17: 3.2 | EB17: 5.1 | EC17: 7.2 | ED17: 10 | EE17: 23 | EF17: 5.7 | EG17: 0 | EH17: 15.1 | EI17: 23.3 | EJ17: 1.6 | EK17: 1.4 | EL17: 7.6 | EM17: 1.8 | EO17: 4.5 | EP17: 5.2 | EQ17: 5.4 | ER17: 10.2 | ES17: 0 | ET17: 0 | EU17: 0 | EV17: 0.6 | EW17: 10.3 | EX17: 5 | EY17: 0 | EZ17: 0 | FA17: 7.1 | FB17: 19.5 | FC17: 8.8 | FD17: 33.4 | FE17: 29.5 | FF17: 13.5 | FG17: 18.3 | FH17: 7.5 | FI17: 11.05 | FJ17: 6241.5663 | FL17: 20.27794 | FM17: 0 | FN17: 6.1 | FO17: 6.2 | FP17: 27.5 | FQ17: 18.91822 | FR17: 5.3 | FS17: 5 | FU17: 89.29616
A18: 28/08/2025 | B18: 04:00 | C18: 99.2 | D18: 640.6 | E18: 214.8 | H18: 0 | I18: 81.8 | L18: 189.4 | M18: 205.2 | N18: 204.3 | O18: 283.2 | P18: 214.8 | Q18: 110.3 | R18: 184.2 | S18: 3.2 | T18: 0 | X18: 120.2 | Y18: 7.6 | Z18: 3.4 | AA18: 0 | AB18: 6.31 | AC18: 7.52 | AD18: 40.9 | AI18: 61.2 | AJ18: 83.22815 | AN18: 6.5 | AO18: 0 | AP18: 32.8 | AQ18: 74.7 | AR18: 20.5 | AS18: 18.6 | AT18: 10.9 | AU18: 63.4 | AV18: 183.2 | AW18: 183.5 | AX18: 184.6 | AY18: 54.1 | BA18: 0 | BB18: 5.4 | BC18: 24.5 | BD18: 2 | BE18: 0 | BF18: 84.7 | BI18: 0 | BL18: 47.1 | BP18: 35.5 | BQ18: 178 | BR18: 175.5 | BS18: 210.5 | BT18: 273.7 | BU18: 29.6 | BV18: 3.6 | CC18: 0.4 | CD18: 196.2 | CE18: 110.8 | CF18: 64.6 | CG18: 70.2 | CH18: 29.5 | CL18: 146.5 | CM18: 149.1 | CN18: 149 | CO18: 0 | CT18: 218 | CU18: 104.6 | CV18: 0 | CW18: 9.4 | CX18: 0 | CY18: 15.7 | CZ18: 0 | DA18: 4.9 | DB18: 5.2 | DC18: 0 | DD18: 0 | DE18: 0.3 | DF18: 1.8 | DG18: 4.6 | DH18: 15 | DI18: 4.4 | DJ18: 3.1 | DK18: 3.3 | DL18: 18.5 | DM18: 0 | DN18: 0 | DO18: 1.1 | DP18: 4.4 | DQ18: 4.4 | DR18: 1.2 | DS18: 1.2 | DT18: 3 | DU18: 0 | DV18: 1.6 | DW18: 0 | DX18: 1.2 | DZ18: 5.4 | EA18: 3.2 | EB18: 4.8 | EC18: 7.2 | ED18: 10 | EE18: 20.6 | EF18: 4.7 | EG18: 0 | EH18: 6.5 | EI18: 18.9 | EJ18: 0.8 | EK18: 0.8 | EL18: 7.6 | EM18: 1.8 | EO18: 4.5 | EP18: 5.2 | EQ18: 5.4 | ER18: 13.5 | ES18: 0 | ET18: 0 | EU18: 0 | EV18: 0.6 | EW18: 2.3 | EX18: 1.1 | EY18: 0 | EZ18: 0 | FA18: 7.1 | FB18: 19.7 | FC18: 7.1 | FD18: 33.3 | FE18: 29.2 | FF18: 13.5 | FG18: 18.3 | FH18: 7.2 | FI18: 11.01 | FJ18: 6278.7681 | FL18: 20.901 | FM18: 0 | FN18: 6.1 | FO18: 6.2 | FP18: 27.5 | FQ18: 18.91841 | FR18: 5.2 | FS18: 5 | FU18: 89.81941
A19: 28/08/2025 | B19: 04:30 | C19: 97.4 | D19: 635.8 | E19: 213.3 | H19: 0 | I19: 80.4 | L19: 190 | M19: 206.7 | N19: 205.7 | O19: 283.1 | P19: 216.4 | Q19: 111.5 | R19: 248.7 | S19: 3.2 | T19: 0 | X19: 115 | Y19: 7 | Z19: 3.2 | AA19: 0 | AB19: 6.29 | AC19: 7.53 | AD19: 40.02 | AI19: 59.1 | AJ19: 81.11302 | AN19: 6.5 | AO19: 0 | AP19: 32.1 | AQ19: 57.5 | AR19: 20.9 | AS19: 18.6 | AT19: 10.9 | AU19: 61.6 | AV19: 179.6 | AW19: 180.6 | AX19: 184.9 | AY19: 52.1 | BA19: 0 | BB19: 11.2 | BC19: 33.6 | BD19: 2 | BE19: 0 | BF19: 81.2 | BI19: 40.4 | BL19: 47.7 | BP19: 34.1 | BQ19: 179.8 | BR19: 176.9 | BS19: 211.6 | BT19: 274.9 | BU19: 30.3 | BV19: 5.6 | CC19: 0.4 | CD19: 103.8 | CE19: 91.8 | CF19: 63.2 | CG19: 69.5 | CH19: 28.8 | CL19: 148 | CM19: 150.3 | CN19: 150.3 | CO19: 0 | CT19: 218.1 | CU19: 104.5 | CV19: 0 | CW19: 12.6 | CX19: 0 | CY19: 15.5 | CZ19: 0 | DA19: 5 | DB19: 5 | DC19: 0 | DD19: 0 | DE19: 0.3 | DF19: 1.8 | DG19: 4.5 | DH19: 14.9 | DI19: 4.5 | DJ19: 3.1 | DK19: 3.3 | DL19: 18.5 | DM19: 0 | DN19: 0 | DO19: 0.8 | DP19: 2.7 | DQ19: 4.4 | DR19: 1.2 | DS19: 1.2 | DT19: 3 | DU19: 0 | DV19: 1.6 | DW19: 2.4 | DX19: 1.2 | DZ19: 5.5 | EA19: 3.2 | EB19: 5 | EC19: 7.1 | ED19: 10 | EE19: 15.6 | EF19: 4.1 | EG19: 0 | EH19: 5 | EI19: 16.8 | EJ19: 0.5 | EK19: 0 | EL19: 7.4 | EM19: 1.8 | EO19: 4.5 | EP19: 5 | EQ19: 5.2 | ER19: 15.2 | ES19: 0 | ET19: 0 | EU19: 0 | EV19: 0.6 | EW19: 0.3 | EX19: 0.2 | EY19: 0 | EZ19: 0 | FA19: 7.1 | FB19: 19.6 | FC19: 9.2 | FD19: 33.6 | FE19: 29.2 | FF19: 13.9 | FG19: 18.3 | FH19: 7 | FI19: 11.08 | FJ19: 6244.233 | FL19: 21.01298 | FM19: 0 | FN19: 6.1 | FO19: 6.2 | FP19: 27.4 | FQ19: 18.91924 | FR19: 5.3 | FS19: 5 | FU19: 89.93222
A20: 28/08/2025 | B20: 05:00 | C20: 99.4 | D20: 641.6 | E20: 215.4 | H20: 0 | I20: 85.9 | L20: 189.1 | M20: 205.5 | N20: 205 | O20: 283.4 | P20: 217.4 | Q20: 111.1 | R20: 251 | S20: 3.2 | T20: 8.8 | X20: 120.7 | Y20: 7.7 | Z20: 3.4 | AA20: 0 | AB20: 6.32 | AC20: 7.69 | AD20: 40.76 | AI20: 60.9 | AJ20: 61.49795 | AN20: 6.5 | AO20: 0 | AP20: 34.5 | AQ20: 71.6 | AR20: 24.1 | AS20: 18.6 | AT20: 10.9 | AU20: 63.1 | AV20: 183.7 | AW20: 183.8 | AX20: 184.9 | AY20: 52.8 | BA20: 0 | BB20: 10.1 | BC20: 32.6 | BD20: 2 | BE20: 0 | BF20: 84.9 | BI20: 41.3 | BL20: 47.1 | BP20: 35.2 | BQ20: 179.1 | BR20: 176.2 | BS20: 211.1 | BT20: 274.8 | BU20: 29.6 | BV20: 13.6 | CC20: 0.4 | CD20: 186.1 | CE20: 100.3 | CF20: 64.4 | CG20: 69.9 | CH20: 29.5 | CL20: 147.6 | CM20: 149.9 | CN20: 149.9 | CO20: 0 | CT20: 218.5 | CU20: 104.7 | CV20: 0 | CW20: 14.5 | CX20: 0 | CY20: 17.1 | CZ20: 0 | DA20: 5 | DB20: 5.1 | DC20: 0 | DD20: 0 | DE20: 0.3 | DF20: 1.8 | DG20: 4.5 | DH20: 15.6 | DI20: 4.9 | DJ20: 3.1 | DK20: 3.3 | DL20: 18.5 | DM20: 0 | DN20: 0 | DO20: 1.7 | DP20: 3.2 | DQ20: 4.4 | DR20: 1.2 | DS20: 1.2 | DT20: 3 | DU20: 0 | DV20: 2 | DW20: 10.4 | DX20: 1.2 | DZ20: 5.6 | EA20: 3.2 | EB20: 5 | EC20: 7.2 | ED20: 10 | EE20: 11.1 | EF20: 5.9 | EG20: 0 | EH20: 4.3 | EI20: 12.3 | EJ20: 0.6 | EK20: 0.1 | EL20: 7.4 | EM20: 1.8 | EO20: 4.5 | EP20: 5 | EQ20: 5.2 | ER20: 15.6 | ES20: 0 | ET20: 0.0777 | EU20: 0 | EV20: 0.6 | EW20: 0 | EX20: 0 | EY20: 0 | EZ20: 0 | FA20: 7.1 | FB20: 19.5 | FC20: 9.3 | FD20: 33.3 | FE20: 29.1 | FF20: 14 | FG20: 18.3 | FH20: 7.9 | FI20: 10.8 | FJ20: 6395.8457 | FL20: 20.43463 | FM20: 0 | FN20: 6.1 | FO20: 6.2 | FP20: 27.4 | FQ20: 18.92075 | FR20: 5.3 | FS20: 5.1 | FU20: 89.45538
A21: 28/08/2025 | B21: 05:30 | C21: 100 | D21: 639.3 | E21: 214.7 | H21: 0 | I21: 85.3 | L21: 189.8 | M21: 203.8 | N21: 203 | O21: 282.4 | P21: 217.8 | Q21: 111.4 | R21: 376.6 | S21: 3.2 | T21: 11.6 | X21: 120.3 | Y21: 7.4 | Z21: 3.3 | AA21: 0 | AB21: 6.32 | AC21: 7.68 | AD21: 40.32 | AI21: 100.2 | AJ21: 41.57422 | AN21: 6.5 | AO21: 0 | AP21: 32.5 | AQ21: 51.7 | AR21: 21.1 | AS21: 18.6 | AT21: 10.9 | AU21: 62.4 | AV21: 181.9 | AW21: 182.6 | AX21: 184.7 | AY21: 78.9 | BA21: 0 | BB21: 9.9 | BC21: 30 | BD21: 2 | BE21: 0 | BF21: 69.7 | BI21: 82.7 | BL21: 47.3 | BP21: 65.8 | BQ21: 180.6 | BR21: 177.9 | BS21: 212.1 | BT21: 275.2 | BU21: 38 | BV21: 26.8 | CC21: 0.4 | CD21: 100.3 | CE21: 90.2 | CF21: 62.9 | CG21: 69.7 | CH21: 29.1 | CL21: 147.8 | CM21: 150.2 | CN21: 150.5 | CO21: 0 | CT21: 218.3 | CU21: 104.7 | CV21: 0 | CW21: 14.7 | CX21: 0 | CY21: 17.3 | CZ21: 0 | DA21: 5.1 | DB21: 5.1 | DC21: 0 | DD21: 0 | DE21: 0.3 | DF21: 1.8 | DG21: 4.5 | DH21: 15.5 | DI21: 5 | DJ21: 3.1 | DK21: 3.3 | DL21: 18.5 | DM21: 0 | DN21: 0 | DO21: 0.9 | DP21: 2.1 | DQ21: 4.4 | DR21: 1.2 | DS21: 1.2 | DT21: 3 | DU21: 0 | DV21: 2.6 | DW21: 14.6 | DX21: 1.2 | DZ21: 5.6 | EA21: 3 | EB21: 4.8 | EC21: 7.2 | ED21: 10 | EE21: 10.1 | EF21: 6.6 | EG21: 0 | EH21: 3.1 | EI21: 12.1 | EJ21: 0.2 | EK21: 0 | EL21: 7.4 | EM21: 1.8 | EO21: 4.5 | EP21: 5 | EQ21: 5.2 | ER21: 16 | ES21: 0 | ET21: 0.0778 | EU21: 0 | EV21: 0.6 | EW21: 0 | EX21: 0.1 | EY21: 0 | EZ21: 0 | FA21: 7.1 | FB21: 19.5 | FC21: 9.1 | FD21: 33.7 | FE21: 29.4 | FF21: 14 | FG21: 18.3 | FH21: 9.1 | FI21: 9.95 | FJ21: 6518.822 | FL21: 20.16783 | FM21: 0 | FN21: 6.1 | FO21: 6.2 | FP21: 27.5 | FQ21: 18.9216 | FR21: 5.3 | FS21: 5.1 | FU21: 89.28943
A22: 28/08/2025 | B22: 06:00 | C22: 99.2 | D22: 644.4 | E22: 216.2 | H22: 0 | I22: 84.6 | L22: 190.3 | M22: 200.9 | N22: 200.1 | O22: 282.1 | P22: 216.6 | Q22: 111.4 | R22: 380.7 | S22: 3.2 | T22: 12.8 | X22: 125.9 | Y22: 7.9 | Z22: 3.4 | AA22: 0 | AB22: 6.35 | AC22: 7.71 | AD22: 40.5 | AI22: 101.4 | AJ22: 30.81606 | AN22: 6.5 | AO22: 0 | AP22: 33.6 | AQ22: 51.9 | AR22: 22.4 | AS22: 18.6 | AT22: 10.9 | AU22: 67 | AV22: 184.1 | AW22: 184.2 | AX22: 184.8 | AY22: 80.8 | BA22: 0 | BB22: 10.8 | BC22: 29.8 | BD22: 2 | BE22: 0 | BF22: 64.1 | BI22: 83.9 | BL22: 47.5 | BP22: 66.3 | BQ22: 179.4 | BR22: 176 | BS22: 210.5 | BT22: 275.1 | BU22: 77 | BV22: 37 | CC22: 0.4 | CD22: 107.8 | CE22: 78.5 | CF22: 66.9 | CG22: 72 | CH22: 29.7 | CL22: 147.9 | CM22: 150.4 | CN22: 150.7 | CO22: 0 | CT22: 218.7 | CU22: 104.8 | CV22: 0 | CW22: 21.8 | CX22: 0 | CY22: 18.1 | CZ22: 0 | DA22: 5.1 | DB22: 5.2 | DC22: 0 | DD22: 0 | DE22: 0.3 | DF22: 1.8 | DG22: 4.5 | DH22: 15.8 | DI22: 5.1 | DJ22: 3.1 | DK22: 3.3 | DL22: 18.5 | DM22: 1.1 | DN22: 1.2 | DO22: 2.6 | DP22: 5.5 | DQ22: 4.4 | DR22: 0.7 | DS22: 1.2 | DT22: 3 | DU22: 0 | DV22: 2.6 | DW22: 20.1 | DX22: 1.2 | DZ22: 5.6 | EA22: 2.9 | EB22: 4.8 | EC22: 7.3 | ED22: 10 | EE22: 9.5 | EF22: 10.6 | EG22: 0 | EH22: 7.8 | EI22: 16 | EJ22: 0.6 | EK22: 1.1 | EL22: 7.4 | EM22: 1.8 | EO22: 4.5 | EP22: 5 | EQ22: 5.2 | ER22: 17.2 | ES22: 1.4 | ET22: 0.1278 | EU22: 0.6 | EV22: 0.6 | EW22: 14.6 | EX22: 13.6 | EY22: 0.6 | EZ22: 0 | FA22: 7.1 | FB22: 19.5 | FC22: 9.2 | FD22: 33.6 | FE22: 29.4 | FF22: 13.9 | FG22: 18.3 | FH22: 9.4 | FI22: 10.05 | FJ22: 6643.9539 | FL22: 20.51399 | FM22: 0 | FN22: 6.1 | FO22: 6.2 | FP22: 27.4 | FQ22: 18.92235 | FR22: 5.2 | FS22: 5.1 | FU22: 89.43634
... A58: 29/08/2025 | B58: 00:00 | C58: 99.8 | D58: 638.4 | E58: 217.2 | H58: 11.8 | I58: 79.2 | L58: 189.4 | M58: 191.4 | N58: 191.3 | O58: 275.1 | P58: 217.7 | Q58: 111.1 | R58: 296.6 | S58: 3.2 | T58: 0 | X58: 121.2 | Y58: 7.6 | Z58: 3.3 | AA58: 22.5 | AB58: 6.39 | AC58: 10.14 | AD58: 73.39 | AI58: 74.5 | AJ58: 132.93014 | AN58: 6.5 | AO58: 0 | AP58: 26.1 | AQ58: 0 | AR58: 18.5 | AS58: 18.4 | AT58: 10.8 | AU58: 63.3 | AV58: 184.7 | AW58: 185 | AX58: 184.3 | AY58: 71.5 | BA58: 5.8 | BB58: 0 | BC58: 28.3 | BD58: 2 | BE58: 0 | BF58: 28.5 | BI58: 82 | BL58: 47.9 | BP58: 55.9 | BQ58: 179.1 | BR58: 176.7 | BS58: 106.6 | BT58: 252.5 | BU58: 76.7 | BV58: 37.2 | CC58: 0.4 | CD58: 67.7 | CE58: 81.4 | CF58: 64.3 | CG58: 69.8 | CH58: 29.6 | CL58: 147.4 | CM58: 149.8 | CN58: 172.1 | CO58: 193 | CT58: 218.4 | CU58: 104.6 | CV58: 0 | CW58: 22 | CX58: 0 | CY58: 16.5 | CZ58: 0 | DA58: 4.9 | DB58: 5.2 | DC58: 9.9 | DD58: 1 | DE58: 0.3 | DF58: 1.8 | DG58: 4.6 | DH58: 14.8 | DI58: 4.1 | DJ58: 3.1 | DK58: 3.3 | DL58: 18.5 | DM58: 0 | DN58: 0 | DO58: 7.7 | DP58: 25.2 | DQ58: 4.4 | DR58: 1.2 | DS58: 1.2 | DT58: 3 | DU58: 0 | DV58: 2.6 | DW58: 20.1 | DX58: 1.4 | DZ58: 4.9 | EA58: 3.1 | EB58: 4.2 | EC58: 6.3 | ED58: 10 | EE58: 22.8 | EF58: 16.3 | EG58: 0 | EH58: 47.2 | EI58: 51.9 | EJ58: 6.3 | EK58: 2.3 | EL58: 5.8 | EM58: 1.8 | EO58: 4 | EP58: 4.5 | EQ58: 4.7 | ER58: 12.8 | ES58: 0 | ET58: 0 | EU58: 0 | EV58: 0.6 | EW58: 26.4 | EX58: 36.5 | EY58: 0 | EZ58: 0 | FA58: 7.2 | FB58: 19 | FC58: 9.7 | FD58: 34.1 | FE58: 26.9 | FF58: 13.2 | FG58: 18.3 | FH58: 7 | FI58: 11.03 | FJ58: 6716.5801 | FL58: 18.84181 | FM58: 0 | FN58: 6.1 | FO58: 6.2 | FP58: 27.6 | FQ58: 18.91949 | FR58: 5.7 | FS58: 5 | FU58: 88.3613
A59: EJEC | C59: 2375.2 | D59: 15292.75 | E59: 5174.15 | F59: 0 | G59: 0 | H59: 229.65 | I59: 1984.5 | J59: 0 | K59: 0 | L59: 4535.3 | M59: 4875.6 | N59: 4880.75 | O59: 6802.75 | P59: 5190.25 | Q59: 2659.95 | R59: 6758.55 | S59: 76.5 | T59: 157.1 | U59: 0 | V59: 0 | W59: 0 | X59: 2873.7 | Y59: 177.05 | Z59: 79.2 | AA59: 209.45 | AB59: 152.305 | AC59: 231.91 | AD59: 1496.375 | AE59: 0 | AF59: 0 | AG59: 0 | AH59: 0 | AI59: 1840.5 | AJ59: 2335.4856 | AK59: 0 | AL59: 0 | AM59: 0 | AN59: 156 | AO59: 301.45 | AP59: 721.05 | AQ59: 1531.6 | AR59: 456.75 | AS59: 443.05 | AT59: 261 | AU59: 1499.3 | AV59: 4374.65 | AW59: 4384.15 | AX59: 4432.55 | AY59: 1803.1 | AZ59: 0 | BA59: 30.6 | BB59: 183.35 | BC59: 691.1 | BD59: 48 | BE59: 256.55 | BF59: 1757.15 | BG59: 0 | BH59: 0 | BI59: 1319.6 | BJ59: 0 | BK59: 0 | BL59: 1134.75 | BM59: 0 | BN59: 0 | BO59: 0 | BP59: 1460.85 | BQ59: 4291.1 | BR59: 4233.9 | BS59: 5009.65 | BT59: 6546.75 | BU59: 1526.15 | BV59: 710.55 | BW59: 0 | BX59: 0 | BY59: 0 | BZ59: 0 | CA59: 0 | CB59: 0 | CC59: 9.6 | CD59: 3001.05 | CE59: 2078.15 | CF59: 1536.2 | CG59: 1677.55 | CH59: 697.3 | CI59: 0 | CJ59: 0 | CK59: 0 | CL59: 3532.6 | CM59: 3592.15 | CN59: 3795.9 | CO59: 1412.35 | CP59: 0 | CQ59: 0 | CR59: 0 | CS59: 0 | CT59: 5241 | CU59: 2511.6 | CV59: 9.1 | CW59: 685 | CX59: 745.9 | CY59: 415.35 | CZ59: 3 | DA59: 119.25 | DB59: 122.2 | DC59: 181.6 | DD59: 21.5 | DE59: 170.55 | DF59: 43.2 | DG59: 112.7 | DH59: 362.6 | DI59: 109.2 | DJ59: 64.15 | DK59: 78.6 | DL59: 444 | DM59: 145.8 | DN59: 174.45 | DO59: 186.8 | DP59: 661.55 | DQ59: 104.45 | DR59: 27.7 | DS59: 18.65 | DT59: 70.9 | DU59: 128.7 | DV59: 57.9 | DW59: 325.3 | DX59: 30.2 | DY59: 0 | DZ59: 132.85 | EA59: 63.05 | EB59: 111.75 | EC59: 159.55 | ED59: 240.6 | EE59: 468.45 | EF59: 678.8 | EG59: 318.6 | EH59: 847.55 | EI59: 1106.75 | EJ59: 126.85 | EK59: 93.75 | EL59: 131.55 | EM59: 34.75 | EN59: 0 | EO59: 101.05 | EP59: 112.6 | EQ59: 117.1 | ER59: 392.85 | ES59: 2404.85 | ET59: 125.42555 | EU59: 1317.85 | EV59: 14.4 | EW59: 1319.9 | EX59: 1545.65 | EY59: 968.6 | EZ59: 134.2 | FA59: 172.15 | FB59: 460.7 | FC59: 224 | FD59: 807.95 | FE59: 701.2 | FF59: 332.05 | FG59: 437.5 | FH59: 196.25 | FI59: 250.465 | FJ59: 171311.02 | FL59: 462.50774 | FM59: 82.355 | FN59: 146.4 | FO59: 150.2 | FP59: 652.1 | FQ59: 454.12763 | FR59: 127.25 | FS59: 180.55 | FT59: 0 | FU59: 2255.4904

Sheet REACTIVA
B3: jueves, 28 de Agosto del 2025
A5: POTENCIA REACTIVA EJECUTADA DE LAS UNIDADES DE GENERACIÓN DEL COES (MVAR) | FL5: CENTRALES NO INTEGRANTES COES
A6: FECHA | B6: HORA | C6: 65333 | D6: 101 | E6: 102 | F6: 42667 | G6: 42668 | H6: 126 | I6: 127 | J6: 138 | K6: 139 | L6: 197 | M6: 203 | N6: 204 | O6: 230 | P6: 209 | Q6: 56677 | R6: 796 | S6: 2146 | T6: 142 | U6: 143 | V6: 125 | W6: 187 | X6: 163 | Y6: 298 | Z6: 299 | AA6: 219 | AB6: 151 | AC6: 152 | AD6: 153 | AE6: 154 | AF6: 756 | AG6: 156 | AH6: 155 | AI6: 182 | AJ6: 212 | AK6: 758 | AL6: 263 | AM6: 265 | AN6: 775 | AO6: 777 | AP6: 2154 | AQ6: 150 | AR6: 149 | AS6: 188 | AT6: 2131 | AU6: 755 | AV6: 252 | AW6: 249 | AX6: 250 | AY6: 117 | AZ6: 267 | BA6: 268 | BB6: 119 | BC6: 120 | BD6: 189 | BE6: 122 | BF6: 266 | BG6: 337 | BH6: 338 | BI6: 251 | BJ6: 115 | BK6: 239 | BL6: 288 | BM6: 240 | BN6: 241 | BO6: 242 | BP6: 191 | BQ6: 194 | BR6: 196 | BS6: 207 | BT6: 236 | BU6: 795 | BV6: 285 | BW6: 995 | BX6: 996 | BY6: 997 | BZ6: 766 | CA6: 926 | CB6: 924 | CC6: 121 | CD6: 103 | CE6: 104 | CF6: 106 | CG6: 105 | CH6: 107 | CI6: 110 | CJ6: 109 | CK6: 144 | CL6: 113 | CM6: 114 | CN6: 193 | CO6: 208 | CP6: 786 | CQ6: 787 | CR6: 788 | CS6: 789 | CT6: 248 | CU6: 2159 | CV6: 303 | CW6: 59715 | CX6: 62255 | CY6: 1263 | CZ6: 61800 | DA6: 2194 | DB6: 69125 | DC6: 216 | DD6: 198 | DE6: 49607 | DF6: 214 | DG6: 260 | DH6: 2152 | DI6: 2128 | DJ6: 247 | DK6: 228 | DL6: 2135 | DM6: 261 | DN6: 237 | DO6: 253 | DP6: 770 | DQ6: 225 | DR6: 2201 | DS6: 2171 | DT6: 760 | DU6: 235 | DV6: 238 | DW6: 2184 | DX6: 61855 | DY6: 223 | DZ6: 226 | EA6: 201 | EB6: 258 | EC6: 259 | ED6: 920 | EE6: 257 | EF6: 256 | EG6: 2148 | EH6: 58288 | EI6: 58289 | EJ6: 58839 | EK6: 58840 | EL6: 296 | EM6: 297 | EN6: 211 | EO6: 2175 | EP6: 2178 | EQ6: 2181 | ER6: 1262 | ES6: 63425 | ET6: 233 | EU6: 2150 | EV6: 2165 | EW6: 2161 | EX6: 61197 | EY6: 58851 | EZ6: 234 | FA6: 215 | FB6: 917 | FC6: 289 | FD6: 58333 | FE6: 58336 | FF6: 213 | FG6: 232 | FH6: 2190 | FI6: 69867 | FJ6: TOTAL COES | FL6: 221 | FM6: 222 | FN6: 224 | FO6: 2187 | FP6: 227 | FQ6: 49400 | FR6: 199 | FS6: 200 | FT6: 70400 | FU6: TOTAL NO COES
C7: SUR | D7: CENTRO | E7: CENTRO | F7: NORTE | G7: NORTE | H7: NORTE | I7: NORTE | J7: CENTRO | K7: CENTRO | L7: CENTRO | M7: CENTRO | N7: CENTRO | O7: CENTRO | P7: CENTRO | Q7: CENTRO | R7: CENTRO | S7: CENTRO | T7: CENTRO | U7: CENTRO | V7: CENTRO | W7: CENTRO | X7: SUR | Y7: SUR | Z7: SUR | AA7: CENTRO | AB7: SUR | AC7: SUR | AD7: SUR | AE7: SUR | AF7: SUR | AG7: SUR | AH7: SUR | AI7: SUR | AJ7: CENTRO | AK7: NORTE | AL7: NORTE | AM7: NORTE | AN7: CENTRO | AO7: CENTRO | AP7: CENTRO | AQ7: CENTRO | AR7: CENTRO | AS7: CENTRO | AT7: CENTRO | AU7: SUR | AV7: CENTRO | AW7: CENTRO | AX7: CENTRO | AY7: CENTRO | AZ7: CENTRO | BA7: CENTRO | BB7: CENTRO | BC7: CENTRO | BD7: SUR | BE7: NORTE | BF7: CENTRO | BG7: CENTRO | BH7: CENTRO | BI7: CENTRO | BJ7: NORTE | BK7: NORTE | BL7: NORTE | BM7: SUR | BN7: SUR | BO7: SUR | BP7: CENTRO | BQ7: CENTRO | BR7: CENTRO | BS7: CENTRO | BT7: CENTRO | BU7: CENTRO | BV7: CENTRO | BW7: SUR | BX7: SUR | BY7: SUR | BZ7: NORTE | CA7: SUR | CB7: CENTRO | CC7: NORTE | CD7: CENTRO | CE7: CENTRO | CF7: CENTRO | CG7: CENTRO | CH7: CENTRO | CI7: CENTRO | CJ7: CENTRO | CK7: CENTRO | CL7: CENTRO | CM7: CENTRO | CN7: CENTRO | CO7: CENTRO | CP7: SUR | CQ7: SUR | CR7: SUR | CS7: SUR | CT7: CENTRO | CU7: CENTRO | CV7: CENTRO | CW7: CENTRO | CX7: SUR | CY7: NORTE | CZ7: NORTE | DA7: NORTE | DB7: CENTRO | DC7: NORTE | DD7: NORTE | DE7: SUR | DF7: CENTRO | DG7: CENTRO | DH7: CENTRO | DI7: NORTE | DJ7: NORTE | DK7: CENTRO | DL7: CENTRO | DM7: SUR | DN7: SUR | DO7: CENTRO | DP7: CENTRO | DQ7: CENTRO | DR7: CENTRO | DS7: CENTRO | DT7: CENTRO | DU7: SUR | DV7: CENTRO | DW7: CENTRO | DX7: NORTE | DY7: CENTRO | DZ7: CENTRO | EA7: NORTE | EB7: CENTRO | EC7: CENTRO | ED7: CENTRO | EE7: NORTE | EF7: NORTE | EG7: SUR | EH7: CENTRO | EI7: CENTRO | EJ7: CENTRO | EK7: CENTRO | EL7: CENTRO | EM7: CENTRO | EN7: SUR | EO7: SUR | EP7: SUR | EQ7: SUR | ER7: NORTE | ES7: SUR | ET7: SUR | EU7: SUR | EV7: CENTRO | EW7: CENTRO | EX7: CENTRO | EY7: SUR | EZ7: SUR | FA7: NORTE | FB7: CENTRO | FC7: NORTE | FD7: NORTE | FE7: NORTE | FF7: CENTRO | FG7: NORTE | FH7: NORTE | FI7: NORTE | FL7: NORTE | FM7: CENTRO | FN7: NORTE | FO7: NORTE | FP7: NORTE | FQ7: NORTE | FR7: NORTE | FS7: NORTE | FT7: SUR
C8: HIDROELÉCTRICA | D8: HIDROELÉCTRICA | E8: HIDROELÉCTRICA | F8: TERMOELÉCTRICA | G8: TERMOELÉCTRICA | H8: HIDROELÉCTRICA | I8: HIDROELÉCTRICA | J8: TERMOELÉCTRICA | K8: TERMOELÉCTRICA | L8: TERMOELÉCTRICA | M8: TERMOELÉCTRICA | N8: TERMOELÉCTRICA | O8: TERMOELÉCTRICA | P8: TERMOELÉCTRICA | Q8: TERMOELÉCTRICA | R8: HIDROELÉCTRICA | S8: HIDROELÉCTRICA | T8: TERMOELÉCTRICA | U8: TERMOELÉCTRICA | V8: TERMOELÉCTRICA | W8: TERMOELÉCTRICA | X8: HIDROELÉCTRICA | Y8: HIDROELÉCTRICA | Z8: HIDROELÉCTRICA | AA8: TERMOELÉCTRICA | AB8: HIDROELÉCTRICA | AC8: HIDROELÉCTRICA | AD8: HIDROELÉCTRICA | AE8: HIDROELÉCTRICA | AF8: TERMOELÉCTRICA | AG8: TERMOELÉCTRICA | AH8: TERMOELÉCTRICA | AI8: HIDROELÉCTRICA | AJ8: HIDROELÉCTRICA | AK8: TERMOELÉCTRICA | AL8: TERMOELÉCTRICA | AM8: TERMOELÉCTRICA | AN8: HIDROELÉCTRICA | AO8: HIDROELÉCTRICA | AP8: HIDROELÉCTRICA | AQ8: HIDROELÉCTRICA | AR8: HIDROELÉCTRICA | AS8: HIDROELÉCTRICA | AT8: HIDROELÉCTRICA | AU8: HIDROELÉCTRICA | AV8: TERMOELÉCTRICA | AW8: TERMOELÉCTRICA | AX8: TERMOELÉCTRICA | AY8: HIDROELÉCTRICA | AZ8: HIDROELÉCTRICA | BA8: HIDROELÉCTRICA | BB8: HIDROELÉCTRICA | BC8: HIDROELÉCTRICA | BD8: HIDROELÉCTRICA | BE8: HIDROELÉCTRICA | BF8: HIDROELÉCTRICA | BG8: HIDROELÉCTRICA | BH8: HIDROELÉCTRICA | BI8: HIDROELÉCTRICA | BJ8: TERMOELÉCTRICA | BK8: TERMOELÉCTRICA | BL8: TERMOELÉCTRICA | BM8: TERMOELÉCTRICA | BN8: TERMOELÉCTRICA | BO8: TERMOELÉCTRICA | BP8: HIDROELÉCTRICA | BQ8: TERMOELÉCTRICA | BR8: TERMOELÉCTRICA | BS8: TERMOELÉCTRICA | BT8: TERMOELÉCTRICA | BU8: TERMOELÉCTRICA | BV8: TERMOELÉCTRICA | BW8: TERMOELÉCTRICA | BX8: TERMOELÉCTRICA | BY8: TERMOELÉCTRICA | BZ8: HIDROELÉCTRICA | CA8: TERMOELÉCTRICA | CB8: TERMOELÉCTRICA | CC8: HIDROELÉCTRICA | CD8: HIDROELÉCTRICA | CE8: HIDROELÉCTRICA | CF8: HIDROELÉCTRICA | CG8: HIDROELÉCTRICA | CH8: HIDROELÉCTRICA | CI8: TERMOELÉCTRICA | CJ8: TERMOELÉCTRICA | CK8: TERMOELÉCTRICA | CL8: TERMOELÉCTRICA | CM8: TERMOELÉCTRICA | CN8: TERMOELÉCTRICA | CO8: TERMOELÉCTRICA | CP8: TERMOELÉCTRICA | CQ8: TERMOELÉCTRICA | CR8: TERMOELÉCTRICA | CS8: TERMOELÉCTRICA | CT8: TERMOELÉCTRICA | CU8: TERMOELÉCTRICA | CV8: SOLAR | CW8: EÓLICA | CX8: SOLAR | CY8: EÓLICA | CZ8: SOLAR | DA8: HIDROELÉCTRICA | DB8: HIDROELÉCTRICA | DC8: HIDROELÉCTRICA | DD8: HIDROELÉCTRICA | DE8: HIDROELÉCTRICA | DF8: HIDROELÉCTRICA | DG8: HIDROELÉCTRICA | DH8: HIDROELÉCTRICA | DI8: HIDROELÉCTRICA | DJ8: HIDROELÉCTRICA | DK8: HIDROELÉCTRICA | DL8: HIDROELÉCTRICA | DM8: SOLAR | DN8: SOLAR | DO8: EÓLICA | DP8: EÓLICA | DQ8: TERMOELÉCTRICA | DR8: TERMOELÉCTRICA | DS8: TERMOELÉCTRICA | DT8: TERMOELÉCTRICA | DU8: SOLAR | DV8: HIDROELÉCTRICA | DW8: HIDROELÉCTRICA | DX8: HIDROELÉCTRICA | DY8: HIDROELÉCTRICA | DZ8: HIDROELÉCTRICA | EA8: HIDROELÉCTRICA | EB8: HIDROELÉCTRICA | EC8: HIDROELÉCTRICA | ED8: HIDROELÉCTRICA | EE8: EÓLICA | EF8: EÓLICA | EG8: SOLAR | EH8: EÓLICA | EI8: EÓLICA | EJ8: EÓLICA | EK8: EÓLICA | EL8: HIDROELÉCTRICA | EM8: HIDROELÉCTRICA | EN8: HIDROELÉCTRICA | EO8: HIDROELÉCTRICA | EP8: HIDROELÉCTRICA | EQ8: HIDROELÉCTRICA | ER8: EÓLICA | ES8: SOLAR | ET8: SOLAR | EU8: SOLAR | EV8: HIDROELÉCTRICA | EW8: EÓLICA | EX8: EÓLICA | EY8: SOLAR | EZ8: SOLAR | FA8: HIDROELÉCTRICA | FB8: HIDROELÉCTRICA | FC8: TERMOELÉCTRICA | FD8: TERMOELÉCTRICA | FE8: TERMOELÉCTRICA | FF8: TERMOELÉCTRICA | FG8: TERMOELÉCTRICA | FH8: TERMOELÉCTRICA | FI8: TERMOELÉCTRICA | FL8: HIDROELÉCTRICA | FM8: HIDROELÉCTRICA | FN8: HIDROELÉCTRICA | FO8: HIDROELÉCTRICA | FP8: TERMOELÉCTRICA | FQ8: TERMOELÉCTRICA | FR8: HIDROELÉCTRICA | FS8: HIDROELÉCTRICA | FT8: SOLAR
C9: HYDRO GLOBAL PERÚ S.A.C. | D9: ELECTROPERU | E9: ELECTROPERU | F9: ELECTROPERU | G9: ELECTROPERU | H9: ORAZUL ENERGY PERÚ | I9: ORAZUL ENERGY PERÚ | J9: TERMOSELVA | K9: TERMOSELVA | L9: KALLPA GENERACION S.A. | M9: KALLPA GENERACION S.A. | N9: KALLPA GENERACION S.A. | O9: KALLPA GENERACION S.A. | P9: KALLPA GENERACION S.A. | Q9: KALLPA GENERACION S.A. | R9: KALLPA GENERACION S.A. | S9: KALLPA GENERACION S.A. | T9: SHOUGESA | U9: SHOUGESA | V9: SHOUGESA | W9: SHOUGESA | X9: EGEMSA | Y9: EGESUR | Z9: EGESUR | AA9: EGESUR | AB9: EGASA | AC9: EGASA | AD9: EGASA | AE9: EGASA | AF9: EGASA | AG9: EGASA | AH9: EGASA | AI9: SAN GABAN | AJ9: CELEPSA | AK9: MINERA CERRO VERDE | AL9: PLANTA DE RESERVA FRIA DE GENERACION DE ETEN S.A. | AM9: PLANTA DE RESERVA FRIA DE GENERACION DE ETEN S.A. | AN9: EMPRESA DE GENERACION HUALLAGA | AO9: EMPRESA DE GENERACION HUALLAGA | AP9: LA VIRGEN | AQ9: CHINANGO S.A.C. | AR9: CHINANGO S.A.C. | AS9: HIDROELECTRICA HUANCHOR S.A.C. | AT9: CELEPSA RENOVABLES S.R.L. | AU9: INLAND ENERGY SAC | AV9: FENIX POWER PERÚ | AW9: FENIX POWER PERÚ | AX9: FENIX POWER PERÚ | AY9: STATKRAFT S.A | AZ9: STATKRAFT S.A | BA9: STATKRAFT S.A | BB9: STATKRAFT S.A | BC9: STATKRAFT S.A | BD9: STATKRAFT S.A | BE9: STATKRAFT S.A | BF9: STATKRAFT S.A | BG9: CENTRALES SANTA ROSA S.A.C. | BH9: CENTRALES SANTA ROSA S.A.C. | BI9: EMPRESA DE GENERACION HUANZA | BJ9: ENEL GENERACION PIURA S.A. | BK9: ENEL GENERACION PIURA S.A. | BL9: ENEL GENERACION PIURA S.A. | BM9: ENGIE | BN9: ENGIE | BO9: ENGIE | BP9: ENGIE | BQ9: ENGIE | BR9: ENGIE | BS9: ENGIE | BT9: ENGIE | BU9: ENGIE | BV9: ENGIE | BW9: ENGIE | BX9: ENGIE | BY9: ENGIE | BZ9: ENGIE | CA9: INFRAESTRUCTURAS Y ENERGIAS DEL PERU S.A.C. | CB9: INFRAESTRUCTURAS Y ENERGIAS DEL PERU S.A.C. | CC9: INVERSIONES SHAQSHA S.A.C. | CD9: ORYGEN PERU S.A.A. | CE9: ORYGEN PERU S.A.A. | CF9: ORYGEN PERU S.A.A. | CG9: ORYGEN PERU S.A.A. | CH9: ORYGEN PERU S.A.A. | CI9: ORYGEN PERU S.A.A. | CJ9: ORYGEN PERU S.A.A. | CK9: ORYGEN PERU S.A.A. | CL9: ORYGEN PERU S.A.A. | CM9: ORYGEN PERU S.A.A. | CN9: ORYGEN PERU S.A.A. | CO9: ORYGEN PERU S.A.A. | CP9: SAMAY I S.A.C | CQ9: SAMAY I S.A.C | CR9: SAMAY I S.A.C | CS9: SAMAY I S.A.C | CT9: TERMOCHILCA S.A.C. | CU9: TERMOCHILCA S.A.C. | CV9: COLCA SOLAR S.A.C. | CW9: ENERGIA RENOVABLE DEL SUR S.A. | CX9: GR CORTARRAMA SOCIEDAD ANONIMA CERRADA | CY9: GR TARUCA SOCIEDAD ANONIMA CERRADA | CZ9: KONDU SAC | DA9: PERUANA DE INVERSIONES EN ENERGIAS RENOVABLES S.A. | DB9: VARI ENERGIA S.A.C. | DC9: ORAZUL ENERGY PERÚ | DD9: ORAZUL ENERGY PERÚ | DE9: SAN GABAN | DF9: MAJA ENERGIA S.A.C. | DG9: EMPRESA DE GENERACION ELECTRICA CANCHAYLLO SAC | DH9: EMPRESA DE GENERACION ELECTRICA SANTA ANA S.A.C. | DI9: EMPRESA ELECTRICA AGUA AZUL | DJ9: EMPRESA ELECTRICA RIO DOBLE | DK9: HIDROCAÑETE S.A. | DL9: HUAURA POWER GROUP S.A. | DM9: MOQUEGUA FV S.A.C. | DN9: PANAMERICANA SOLAR SAC. | DO9: PARQUE EOLICO MARCONA S.A.C. | DP9: PARQUE EOLICO TRES HERMANAS S.A.C. | DQ9: PETRAMAS | DR9: PETRAMAS | DS9: PETRAMAS | DT9: PETRAMAS | DU9: TACNA SOLAR SAC. | DV9: ELECTRICA YANAPAMPA SAC | DW9: ANDEAN POWER S.A.C. | DX9: ASOCIACIÓN SANTA LUCIA DE CHACAS | DY9: ATRIA ENERGIA S.A.C. | DZ9: EGEJUNIN | EA9: EGEJUNIN | EB9: EGEJUNIN | EC9: EGEJUNIN | ED9: EMPRESA DE GENERACION ELECTRICA RIO BAÑOS S.A.C. | EE9: ENERGÍA EÓLICA S.A. | EF9: ENERGÍA EÓLICA S.A. | EG9: ENGIE | EH9: ENGIE | EI9: ENGIE | EJ9: ENGIE | EK9: ENGIE | EL9: GENERACIÓN ANDINA S.A.C. | EM9: GENERACIÓN ANDINA S.A.C. | EN9: GENERADORA DE ENERGÍA DEL PERÚ | EO9: GENERADORA DE ENERGÍA DEL PERÚ | EP9: GENERADORA DE ENERGÍA DEL PERÚ | EQ9: GENERADORA DE ENERGÍA DEL PERÚ | ER9: GR PAINO SOCIEDAD ANONIMA CERRADA | ES9: JOYA SOLAR S.A.C. | ET9: MAJES ARCUS S.A.C. | EU9: ORYGEN PERU S.A.A. | EV9: ORYGEN PERU S.A.A. | EW9: ORYGEN PERU S.A.A. | EX9: ORYGEN PERU S.A.A. | EY9: ORYGEN PERU S.A.A. | EZ9: REPARTICIÓN ARCUS S.A.C. | FA9: SINERSA | FB9: SINERSA | FC9: BIOENERGIA DEL CHIRA S.A. | FD9: GM OPERACIONES S.A.C. | FE9: GM OPERACIONES S.A.C. | FF9: AGRO INDUSTRIAL PARAMONGA S.A. | FG9: AGROAURORA S.A.C. | FH9: AGROINDUSTRIAS SAN JACINTO S.A.A. | FI9: AGROLMOS SOCIEDAD ANONIMA - AGROLMOS S.A. | FL9: UNACEM PERU S.A. | FM9: ELECTRO ORIENTE | FN9: AGUAS Y ENERGIA PERU | FO9: ELECTRO ZAÑA S.A.C. | FP9: ELECTRONOROESTE S.A. | FQ9: SDE PIURA | FR9: SINERSA | FS9: SINERSA | FT9: KALLPA GENERACION S.A.
C10: SAN GABAN III | D10: MANTARO | E10: RESTITUCION | F10: TUMBES MAK 1 | G10: TUMBES MAK 2 | H10: CARHUAQUERO | I10: CAÑON DEL PATO | J10: AGUAYTIA TG1 | K10: AGUAYTIA TG2 | L10: KALLPA TG1 | M10: KALLPA TG2 | N10: KALLPA TG3 | O10: KALLPA TV | P10: LFLORES TG1 | Q10: LFLORES TV | R10: CERRO DEL AGUILA | S10: CERRODELAGUILAG4 | T10: SHOUGESA TV1 | U10: SHOUGESA TV2 | V10: SHOUGESA TV3 | W10: SHOUGESA CUMMINS | X10: MACHUPICCHU | Y10: ARICOTA 1 | Z10: ARICOTA 2 | AA10: INDEPENDENCIA | AB10: CHARCANI I,II,III | AC10: CHARCANI IV | AD10: CHARCANI V | AE10: CHARCANI VI | AF10: CHILINA TG | AG10: MOLLENDO 1, 2, 3 | AH10: CHILINA (SULZ 1,2) | AI10: SAN GABAN II | AJ10: PLATANAL | AK10: RECKA | AL10: RF ETEN TG1 | AM10: RF ETEN TG2 | AN10: CHAGLLA GP1 | AO10: CHAGLLA | AP10: LA VIRGEN | AQ10: CHIMAY | AR10: YANANGO | AS10: HUANCHOR | AT10: MARAÑON | AU10: STA TERESA | AV10: FENIX GT11 | AW10: FENIX GT12 | AX10: FENIX TV10 | AY10: YAUPI | AZ10: OROYA | BA10: PACHACHACA | BB10: MALPASO | BC10: CAHUA | BD10: ARCATA | BE10: GALLITO CIEGO | BF10: CHEVES | BG10: SANTA ROSA 1 | BH10: SANTA ROSA 2 | BI10: HUANZA | BJ10: MALACAS2 TG4 | BK10: MALACAS3 TG 5 | BL10: MALACAS1 TG6 | BM10: RF ILO2 TG1 | BN10: RF ILO2 TG2 | BO10: RF ILO2 TG3 | BP10: YUNCAN | BQ10: CHILCA1 TG1 | BR10: CHILCA1 TG2 | BS10: CHILCA1 TG3 | BT10: CHILCA-TV | BU10: CHILCA2 TG41 | BV10: CHILCA2-TV | BW10: CTNEPI_TG41 | BX10: CTNEPI_TG42 | BY10: CTNEPI_TG43 | BZ10: QUITARACSA | CA10: RF PTO MALDONADO | CB10: RF PUCALLPA | CC10: PARIAC | CD10: HUINCO | CE10: MATUCANA | CF10: MOYOPAMPA | CG10: CALLAHUANCA | CH10: HUAMPANI | CI10: STA ROSA WEST TG7 | CJ10: UTI_5 | CK10: UTI_6 | CL10: VENTANILLA 3 | CM10: VENTANILLA 4 | CN10: VENTANILLA TV | CO10: STAROSA TG8 | CP10: PTO_BRVO TG1 | CQ10: PTO_BRVO TG2 | CR10: PTO_BRVO TG3 | CS10: PTO_BRVO TG4 | CT10: OLLEROS TG1 | CU10: OLLEROS TV | CV10: CS YARUCAYA | CW10: SAN JUAN | CX10: MATARANI | CY10: DUNA | CZ10: CARHUAQUERO (CS) | DA10: MANTA I | DB10: ANASHIRONI | DC10: CARHUAQUERO4 | DD10: CAÑA BRAVA | DE10: TUPURI | DF10: RONCADOR | DG10: CANCHAYLLO | DH10: RENOVANDESH1 | DI10: POTRERO | DJ10: PIZARRAS | DK10: NIMPERIAL | DL10: YARUCAYA | DM10: MOQUEGUA-SOLAR | DN10: PANAMERICANA-SOLAR | DO10: PQE-EOLICO-MARCONA | DP10: PQE-EOLICO-3-HERMANAS | DQ10: HUAYCOLORO | DR10: CALLAO | DS10: DONA_CATALINA | DT10: LAGRINGAV | DU10: TACNA-SOLAR | DV10: YANAPAMPA | DW10: CARHUAC | DX10: HUALLIN | DY10: PURMACANA | DZ10: HUASAHUASI | EA10: STACRUZ_1_2 | EB10: RUNATULLO_II | EC10: RUNATULLO_III | ED10: RUCUY | EE10: PQE-EOLICO-TALARA | EF10: PQE-EOLICO-CUPISNIQUE | EG10: INTIPAMPA | EH10: PUNTA LOMITAS-BL1 | EI10: PUNTA LOMITAS-BL2 | EJ10: PUN LOMITAS_EXP-BL1 | EK10: PUN LOMITAS_EXP-BL2 | EL10: 8AGOSTO | EM10: EL CARMEN | EN10: LA JOYA | EO10: ANGEL_I | EP10: ANGEL_II | EQ10: ANGEL_III | ER10: HUAMBOS | ES10: SAN MARTIN SOLAR | ET10: MAJES | EU10: RUBI | EV10: CH_HER1 | EW10: WAYRA-I | EX10: WAYRA EXTENSION | EY10: CLEMESI | EZ10: REPARTICION | FA10: POECHOS2 | FB10: CHANCAY | FC10: CANA BRAVA | FD10: REFINERIA TALARA TV1 | FE10: REFINERÍA TALARA TV2 | FF10: PARAMONGA | FG10: MAPLE | FH10: SAN_JACINTO | FI10: AGROLMOS | FJ10: MVAR | FL10: CARPAPATA | FM10: CENTRALES ELOR | FN10: PIAS1 | FO10: ZANA | FP10: TABLAZO | FQ10: TALLANCA | FR10: CURUMUY | FS10: POECHOS1 | FT10: SUNNY | FU10: MVAR
A11: 28/08/2025 | B11: 00:30 | C11: 1.7 | D11: -9.2 | E11: 4.8 | H11: 0 | I11: -7.7 | L11: -30 | M11: -30.8 | N11: 0.9 | O11: 31.8 | P11: 24.6 | Q11: 13.7 | R11: 39.7 | S11: 0 | T11: 0 | X11: -0.5 | Y11: 1.2 | Z11: 1.6 | AA11: 0 | AB11: -3.2 | AC11: 3.7 | AD11: 4.4 | AI11: -0.6 | AJ11: -10.4 | AN11: -1.1 | AO11: -28.1 | AP11: -0.1 | AQ11: 12.1 | AR11: 8.3 | AS11: 0.5 | AT11: 1.5 | AU11: 0.9 | AV11: 32.4 | AW11: 2.3 | AX11: -45.4 | AY11: -2.6 | AZ11: 0 | BA11: 0 | BB11: -2.3 | BC11: 1.5 | BD11: 0.5 | BE11: 0 | BF11: 1.7 | BI11: 0 | BL11: 2.6 | BP11: 0.4 | BQ11: -50.9 | BR11: -38.6 | BS11: 22.3 | BT11: -7.1 | BU11: 5.2 | BV11: 0 | CC11: -0.6 | CD11: 22.8 | CE11: 13.5 | CF11: -0.6 | CG11: 0.6 | CH11: -0.3 | CL11: 10.5 | CM11: 14.2 | CN11: -48 | CO11: 0 | CT11: 10.3 | CU11: 1.9 | CW11: -11.7 | CX11: 0 | CY11: -6.9 | DA11: 0.3 | DB11: 0.01694 | DC11: 0 | DE11: 0 | DF11: 0 | DG11: 1.2 | DH11: 0.1 | DI11: 0.4 | DJ11: 0.1 | DK11: 0.5 | DM11: 0 | DN11: 0 | DO11: 0.4 | DP11: -2.7 | DQ11: 1.5 | DR11: 0.4 | DS11: 0.3 | DT11: 1.2 | DU11: 0 | DV11: -0.1 | DW11: 0.5 | DX11: 0.2 | DZ11: -1.8 | EA11: 0.1 | EB11: 0.5 | EC11: 0.4 | ED11: 0.1 | EE11: 3.5 | EF11: 4 | EG11: 0 | EH11: -7.2 | EI11: -8.3 | EJ11: -0.7 | EK11: -0.8 | EL11: 1.5 | EM11: -0.1 | EO11: 0.1 | EP11: 0.1 | EQ11: 0.1 | ER11: -6.6 | ES11: 0 | EU11: 0 | EV11: -0.2 | EW11: -7.9 | EX11: 0 | EY11: 0 | EZ11: 0 | FA11: 0.4 | FB11: 0.4 | FC11: 1.5 | FD11: 9.8 | FE11: 0.2 | FF11: 2.4 | FG11: 0 | FH11: 2.4 | FI11: 3.47 | FJ11: -40.91306 | FM11: -0.38 | FN11: 1.2 | FO11: 0.9 | FP11: 0.3 | FQ11: 18.91854 | FR11: -0.1 | FS11: 0.8 | FU11: 21.63854
A12: 28/08/2025 | B12: 01:00 | C12: 0.8 | D12: -3.5 | E12: 4.6 | H12: 0 | I12: 1.4 | L12: -26.8 | M12: -34.9 | N12: -3.5 | O12: 35.3 | P12: 25.4 | Q12: 14.9 | R12: 41.8 | S12: 0 | T12: 0 | X12: -1.5 | Y12: 1 | Z12: 1.6 | AA12: 0 | AB12: -3.4 | AC12: 3.5 | AD12: 3.2 | AI12: 0.4 | AJ12: -9.1 | AN12: -1.3 | AO12: -28.7 | AP12: -0.1 | AQ12: 13.1 | AR12: 8.8 | AS12: 0.6 | AT12: 1.5 | AU12: 1.2 | AV12: 34.6 | AW12: 4.2 | AX12: -43.4 | AY12: -7.3 | AZ12: 0 | BA12: 0 | BB12: -2.4 | BC12: 1.5 | BD12: 0.4 | BE12: 0 | BF12: -0.2 | BI12: 0 | BL12: 2.8 | BP12: 1.7 | BQ12: -49 | BR12: -36.8 | BS12: 23.7 | BT12: -5.4 | BU12: 5.6 | BV12: 0 | CC12: -0.6 | CD12: 22.7 | CE12: 15.4 | CF12: 0.7 | CG12: -0.6 | CH12: -0.1 | CL12: 10.9 | CM12: 14.8 | CN12: -46.3 | CO12: 0 | CT12: 10.5 | CU12: 2 | CW12: -11.1 | CX12: 0 | CY12: -7.1 | DA12: 0.3 | DB12: 0.01058 | DC12: 0 | DE12: 0 | DF12: 0 | DG12: 1.2 | DH12: 0.2 | DI12: 0.3 | DJ12: 0.1 | DK12: 0.5 | DM12: 0 | DN12: 0 | DO12: 0.6 | DP12: -1.9 | DQ12: 1.6 | DR12: 0.2 | DS12: 0.3 | DT12: 1.2 | DU12: 0 | DV12: 0 | DW12: 0.1 | DX12: 0.2 | DZ12: -1.8 | EA12: 0.2 | EB12: 0.5 | EC12: 0.5 | ED12: 0.1 | EE12: 4.8 | EF12: 4 | EG12: 0 | EH12: -7.7 | EI12: -9.5 | EJ12: -0.9 | EK12: -1 | EL12: 1.4 | EM12: -0.1 | EO12: 0.1 | EP12: 0.1 | EQ12: 0.1 | ER12: -6.9 | ES12: 0 | EU12: 0 | EV12: -0.2 | EW12: -7.3 | EX12: 0 | EY12: 0 | EZ12: 0 | FA12: 0.4 | FB12: 0.3 | FC12: 1.5 | FD12: 9.5 | FE12: 0.4 | FF12: 3 | FG12: 0 | FH12: 2.4 | FI12: 3.47 | FJ12: -10.21942 | FM12: 0.2 | FN12: 1.1 | FO12: 0.9 | FP12: 0.3 | FQ12: 18.91825 | FR12: -0.2 | FS12: 0.8 | FU12: 22.01825
A13: 28/08/2025 | B13: 01:30 | C13: 0 | D13: -9.1 | E13: 4.5 | H13: 0 | I13: -8.2 | L13: -32.3 | M13: -33 | N13: -1.3 | O13: 28 | P13: 23.9 | Q13: 13 | R13: 36.3 | S13: 0.1 | T13: 0 | X13: -2.3 | Y13: 1.2 | Z13: 1.6 | AA13: 0 | AB13: -3.4 | AC13: 3.4 | AD13: 2.4 | AI13: -0.2 | AJ13: -9.5 | AN13: -1.2 | AO13: 0 | AP13: 0.1 | AQ13: 12.4 | AR13: 8.4 | AS13: 0.6 | AT13: 1.5 | AU13: 1.3 | AV13: 30.2 | AW13: -0.1 | AX13: -42.6 | AY13: -2.7 | AZ13: 0 | BA13: 0 | BB13: 1.4 | BC13: 2 | BD13: 0.4 | BE13: 0 | BF13: 1.8 | BI13: 0 | BL13: 3 | BP13: 3.9 | BQ13: -51.7 | BR13: -39.1 | BS13: 21.6 | BT13: -7.5 | BU13: 4.8 | BV13: 0 | CC13: -0.6 | CD13: 23.1 | CE13: 10.4 | CF13: 0 | CG13: -0.6 | CH13: -0.2 | CL13: 6.4 | CM13: 10.1 | CN13: -42.5 | CO13: 0 | CT13: 8.8 | CU13: 1 | CW13: -11.6 | CX13: 0 | CY13: -7.3 | DA13: 0.3 | DB13: 0.01577 | DC13: 0 | DE13: 0 | DF13: 0 | DG13: 1.2 | DH13: -0.1 | DI13: -0.1 | DJ13: 0.1 | DK13: 0.5 | DM13: 0 | DN13: 0 | DO13: 0.3 | DP13: -2.3 | DQ13: 1.8 | DR13: 0.2 | DS13: 0.3 | DT13: 1.5 | DU13: 0 | DV13: -0.2 | DW13: 0 | DX13: 0.2 | DZ13: -1.8 | EA13: 0.2 | EB13: 0.5 | EC13: 0.2 | ED13: 0 | EE13: 5.9 | EF13: 4 | EG13: 0 | EH13: -9.6 | EI13: -11.5 | EJ13: -1.2 | EK13: -1.4 | EL13: 1.4 | EM13: -0.1 | EO13: 0.1 | EP13: 0.1 | EQ13: 0.1 | ER13: -6.9 | ES13: 0 | EU13: 0 | EV13: -0.2 | EW13: -7.8 | EX13: 0 | EY13: 0 | EZ13: 0 | FA13: 0.4 | FB13: 0.2 | FC13: 1.3 | FD13: 9.8 | FE13: 0.2 | FF13: 4 | FG13: 0 | FH13: 2.6 | FI13: 3.44 | FJ13: -41.74423 | FM13: 0 | FN13: 1.3 | FO13: 0.9 | FP13: 0.3 | FQ13: 18.91818 | FR13: -0.2 | FS13: 0.8 | FU13: 22.01818
A14: 28/08/2025 | B14: 02:00 | C14: 0.6 | D14: 0.2 | E14: 6.3 | H14: 0 | I14: -0.3 | L14: -29.8 | M14: -30 | N14: 3.2 | O14: 32.6 | P14: 24.2 | Q14: 13.6 | R14: 45.4 | S14: 0.1 | T14: 0 | X14: -2.1 | Y14: 0.6 | Z14: 1.2 | AA14: 0 | AB14: -3.4 | AC14: 3.4 | AD14: 2.9 | AI14: -0.2 | AJ14: -6 | AN14: -1.1 | AO14: 0 | AP14: 0.9 | AQ14: 12.2 | AR14: 8.7 | AS14: 0.4 | AT14: 1.5 | AU14: 1.5 | AV14: 31.6 | AW14: 1.6 | AX14: -41.4 | AY14: -1.4 | AZ14: 0 | BA14: 0 | BB14: 0.2 | BC14: 1.7 | BD14: 0.5 | BE14: 0 | BF14: 0.5 | BI14: 0 | BL14: 2.8 | BP14: 4.8 | BQ14: -51 | BR14: -38.5 | BS14: 22.1 | BT14: -7.1 | BU14: 4.7 | BV14: 0 | CC14: -0.6 | CD14: 21.8 | CE14: 10.5 | CF14: 0.1 | CG14: -0.5 | CH14: -0.1 | CL14: 7.2 | CM14: 10.9 | CN14: -41.7 | CO14: 0 | CT14: 8.7 | CU14: 1 | CW14: -12.3 | CX14: 0 | CY14: -6.7 | DA14: 0.3 | DB14: 0.01458 | DC14: 0 | DE14: 0 | DF14: 0.1 | DG14: 1.3 | DH14: 0.2 | DI14: 0.3 | DJ14: 0 | DK14: 0.5 | DM14: 0 | DN14: 0 | DO14: 0.2 | DP14: -2.5 | DQ14: 1.9 | DR14: 0.3 | DS14: 0.3 | DT14: 1.5 | DU14: 0 | DV14: 0 | DW14: 0 | DX14: 0.2 | DZ14: -1.8 | EA14: 0.2 | EB14: 0.5 | EC14: 0.3 | ED14: 0.1 | EE14: 5.8 | EF14: 4 | EG14: 0 | EH14: -7.1 | EI14: -8.6 | EJ14: -0.8 | EK14: -1 | EL14: 1.4 | EM14: -0.1 | EO14: 0.1 | EP14: 0.1 | EQ14: 0.1 | ER14: -6 | ES14: 0 | EU14: 0 | EV14: -0.2 | EW14: -8.9 | EX14: 0 | EY14: 0 | EZ14: 0 | FA14: 0.4 | FB14: 0.2 | FC14: 1.3 | FD14: 9.9 | FE14: 0.2 | FF14: 3.7 | FG14: 0 | FH14: 2.8 | FI14: 3.47 | FJ14: 20.68458 | FM14: 0 | FN14: 1.5 | FO14: 0.9 | FP14: 0.3 | FQ14: 18.91809 | FR14: -0.2 | FS14: 0.9 | FU14: 22.31809
A15: 28/08/2025 | B15: 02:30 | C15: 0.9 | D15: -11.8 | E15: 3.5 | H15: 0 | I15: -9.2 | L15: -34.6 | M15: -39.2 | N15: -7.6 | O15: 25.2 | P15: 22.2 | Q15: 12.2 | R15: 41.4 | S15: 0 | T15: 0 | X15: -3.5 | Y15: 0.6 | Z15: 1.2 | AA15: 0 | AB15: -3.4 | AC15: 3.2 | AD15: 2.6 | AI15: 0.2 | AJ15: -4.6 | AN15: -1.2 | AO15: 0 | AP15: 0.7 | AQ15: 12.8 | AR15: 8.4 | AS15: -0.6 | AT15: 1.5 | AU15: 1.6 | AV15: 28.7 | AW15: -1.3 | AX15: -44.3 | AY15: -3.9 | AZ15: 0 | BA15: 0 | BB15: -1.2 | BC15: 2.8 | BD15: 0.5 | BE15: 0 | BF15: 1.2 | BI15: 0 | BL15: 2.8 | BP15: 3.5 | BQ15: -52.8 | BR15: -40.7 | BS15: 19.8 | BT15: -9.4 | BU15: 4 | BV15: 0 | CC15: -0.6 | CD15: 21.5 | CE15: 10.7 | CF15: 0.4 | CG15: -0.5 | CH15: -0.1 | CL15: 4 | CM15: 7.8 | CN15: -46.4 | CO15: 0 | CT15: 7.9 | CU15: 0.5 | CW15: -11.5 | CX15: 0 | CY15: -6.6 | DA15: 0.4 | DB15: 0.02183 | DC15: 0 | DE15: 0 | DF15: 0 | DG15: 1.2 | DH15: 0.1 | DI15: 0 | DJ15: 0.1 | DK15: 0.5 | DM15: 0 | DN15: 0 | DO15: 0.2 | DP15: -3.1 | DQ15: 1.9 | DR15: 0.4 | DS15: 0.3 | DT15: 1.5 | DU15: 0 | DV15: 0 | DW15: 0 | DX15: 0.2 | DZ15: -1.8 | EA15: 0.2 | EB15: 0.5 | EC15: 0.2 | ED15: 0 | EE15: 5.4 | EF15: 4 | EG15: 0 | EH15: -9.7 | EI15: -11.4 | EJ15: -1.2 | EK15: -1.4 | EL15: 1.4 | EM15: -0.1 | EO15: 0.1 | EP15: 0.1 | EQ15: 0.1 | ER15: -6.1 | ES15: 0 | EU15: 0 | EV15: -0.2 | EW15: -9.2 | EX15: 0 | EY15: 0 | EZ15: 0 | FA15: 0.4 | FB15: 0.2 | FC15: 1.4 | FD15: 9.8 | FE15: 0.4 | FF15: 2.2 | FG15: 0 | FH15: 2.9 | FI15: 3.46 | FJ15: -85.31817 | FM15: 0 | FN15: 1.3 | FO15: 0.9 | FP15: 0.3 | FQ15: 18.91806 | FR15: -0.2 | FS15: 0.8 | FU15: 22.01806
A16: 28/08/2025 | B16: 03:00 | C16: 1.2 | D16: 1 | E16: 5.9 | H16: 0 | I16: -0.9 | L16: -30.1 | M16: -31.7 | N16: -0.5 | O16: 30.7 | P16: 24.2 | Q16: 13.2 | R16: 39.5 | S16: 0.1 | T16: 0 | X16: -2.6 | Y16: 1.2 | Z16: 1.6 | AA16: 0 | AB16: -3.4 | AC16: 3.3 | AD16: 3.1 | AI16: 0.2 | AJ16: -8.6 | AN16: -1.2 | AO16: 0 | AP16: 0.4 | AQ16: 12.2 | AR16: 8.7 | AS16: -0.4 | AT16: 1.5 | AU16: 0.4 | AV16: 31.7 | AW16: 1.3 | AX16: -41.7 | AY16: -3.1 | AZ16: 0 | BA16: 0 | BB16: -1 | BC16: 1 | BD16: 0.5 | BE16: 0 | BF16: 3.1 | BI16: 0 | BL16: 3 | BP16: 3.1 | BQ16: -51.2 | BR16: -38.8 | BS16: 21.7 | BT16: -7.4 | BU16: 4.8 | BV16: 0 | CC16: -0.6 | CD16: 22.1 | CE16: 10.5 | CF16: -0.2 | CG16: -0.5 | CH16: -0.1 | CL16: 5.8 | CM16: 9.6 | CN16: -44.2 | CO16: 0 | CT16: 7.6 | CU16: 0.4 | CW16: -11.1 | CX16: 0 | CY16: -6.3 | DA16: 0.4 | DB16: 0.00687 | DC16: 0 | DE16: 0 | DF16: 0 | DG16: 1.2 | DH16: 0.2 | DI16: -0.5 | DJ16: 0.1 | DK16: 0.6 | DM16: 0 | DN16: 0 | DO16: 0.6 | DP16: -1.3 | DQ16: 1.9 | DR16: 0.4 | DS16: 0.3 | DT16: 1.5 | DU16: 0 | DV16: 0.2 | DW16: 0 | DX16: 0.2 | DZ16: -1.8 | EA16: 0.1 | EB16: 0.5 | EC16: 0.3 | ED16: 0 | EE16: 5.9 | EF16: 4 | EG16: 0 | EH16: -6 | EI16: -7.4 | EJ16: -0.7 | EK16: -0.9 | EL16: 1.4 | EM16: -0.1 | EO16: 0.1 | EP16: 0.1 | EQ16: 0.1 | ER16: -6.2 | ES16: 0 | EU16: 0 | EV16: -0.2 | EW16: -7.9 | EX16: 0 | EY16: 0 | EZ16: 0 | FA16: 0.4 | FB16: 0 | FC16: 1.5 | FD16: 9.9 | FE16: 0.2 | FF16: 3.3 | FG16: 0 | FH16: 2.8 | FI16: 3.52 | FJ16: -2.27313 | FM16: 0 | FN16: 1.4 | FO16: 0.9 | FP16: 0.3 | FQ16: 18.91821 | FR16: -0.2 | FS16: 0.8 | FU16: 22.11821
A17: 28/08/2025 | B17: 03:30 | C17: 0.5 | D17: -7.4 | E17: 5.8 | H17: 0 | I17: -4.2 | L17: -32.7 | M17: -34.1 | N17: -2.3 | O17: 27.5 | P17: 23.6 | Q17: 12.7 | R17: 39.3 | S17: 0.1 | T17: 0 | X17: -4 | Y17: 0.6 | Z17: 1.3 | AA17: 0 | AB17: -3.2 | AC17: 3.4 | AD17: 2.9 | AI17: -0.4 | AJ17: -10.1 | AN17: -1.2 | AO17: 0 | AP17: 0.5 | AQ17: 11.2 | AR17: 8.9 | AS17: -0.2 | AT17: 1.5 | AU17: 1.3 | AV17: 30.8 | AW17: 0.9 | AX17: -42.2 | AY17: -0.7 | AZ17: 0 | BA17: 0 | BB17: 0.7 | BC17: 2.5 | BD17: 0.4 | BE17: 0 | BF17: 0.7 | BI17: 0 | BL17: 2.2 | BP17: 2.9 | BQ17: -51.9 | BR17: -40.2 | BS17: 20.8 | BT17: -8.8 | BU17: 4.5 | BV17: 0 | CC17: -0.5 | CD17: 22.4 | CE17: 9.2 | CF17: -1.2 | CG17: -0.5 | CH17: -0.1 | CL17: 5.3 | CM17: 8.9 | CN17: -44.3 | CO17: 0 | CT17: 7.4 | CU17: 0.2 | CW17: -10.1 | CX17: 0 | CY17: -6.7 | DA17: 0.3 | DB17: -0.00028 | DC17: 0 | DE17: 0 | DF17: 0 | DG17: 1.2 | DH17: 0.2 | DI17: 0.2 | DJ17: 0.1 | DK17: 0.5 | DM17: 0 | DN17: 0 | DO17: 0.8 | DP17: -1.1 | DQ17: 1.9 | DR17: 0.4 | DS17: 0.3 | DT17: 1.5 | DU17: 0 | DV17: 0.2 | DW17: 0 | DX17: 0.2 | DZ17: -1.8 | EA17: 0.1 | EB17: 0.5 | EC17: 0.3 | ED17: 0 | EE17: 5.3 | EF17: 4 | EG17: 0 | EH17: -7.8 | EI17: -9.2 | EJ17: -0.9 | EK17: -1.1 | EL17: 1.4 | EM17: -0.1 | EO17: 0.1 | EP17: 0.1 | EQ17: 0.1 | ER17: -5.9 | ES17: 0 | EU17: 0 | EV17: -0.2 | EW17: -8.8 | EX17: 0.1 | EY17: 0 | EZ17: 0 | FA17: 0.4 | FB17: 0.1 | FC17: 1.4 | FD17: 9.8 | FE17: 0 | FF17: 2.7 | FG17: 0 | FH17: 3.7 | FI17: 3.4 | FJ17: -41.70028 | FM17: 0 | FN17: 1.3 | FO17: 0.8 | FP17: 0.3 | FQ17: 18.91822 | FR17: -0.2 | FS17: 0.8 | FU17: 21.91822
A18: 28/08/2025 | B18: 04:00 | C18: 1.3 | D18: 11.8 | E18: 7.9 | H18: 0 | I18: -1.4 | L18: -29.4 | M18: -28.7 | N18: 2 | O18: 32.8 | P18: 26.2 | Q18: 14.4 | R18: 42.6 | S18: 0.2 | T18: 0 | X18: -0.4 | Y18: 1.2 | Z18: 1.9 | AA18: 0 | AB18: -3.2 | AC18: 4 | AD18: 3.7 | AI18: 0.9 | AJ18: -7.3 | AN18: -1.2 | AO18: 0 | AP18: 0.5 | AQ18: 12.5 | AR18: 8.7 | AS18: -0.3 | AT18: 1.5 | AU18: 2 | AV18: 33.7 | AW18: 3.4 | AX18: -39.7 | AY18: -2.9 | AZ18: 0 | BA18: 0 | BB18: 0.5 | BC18: 3 | BD18: 0.5 | BE18: 0 | BF18: 3.8 | BI18: 0 | BL18: 4 | BP18: 4.3 | BQ18: -50.1 | BR18: -37.8 | BS18: 23.3 | BT18: -6.5 | BU18: 6.1 | BV18: -0.6 | CC18: -0.6 | CD18: 21.6 | CE18: 11.4 | CF18: 0.7 | CG18: -0.4 | CH18: -0.1 | CL18: 6.8 | CM18: 10.8 | CN18: -41.9 | CO18: 0 | CT18: 9.3 | CU18: 1.3 | CW18: -7.6 | CX18: 0 | CY18: -6.5 | DA18: 0.3 | DB18: 0.00778 | DC18: 0 | DE18: 0 | DF18: 0 | DG18: 1.3 | DH18: 0.2 | DI18: 0.3 | DJ18: 0 | DK18: 0.6 | DM18: 0 | DN18: 0 | DO18: 1.4 | DP18: 0.8 | DQ18: 1.9 | DR18: 0.4 | DS18: 0.3 | DT18: 1.5 | DU18: 0 | DV18: 0.4 | DW18: 0 | DX18: 0.2 | DZ18: -1.8 | EA18: 0.1 | EB18: 0.5 | EC18: 0.3 | ED18: 0.1 | EE18: 4.9 | EF18: 4 | EG18: 0 | EH18: -5.5 | EI18: -6.7 | EJ18: -0.6 | EK18: -0.8 | EL18: 1.4 | EM18: -0.1 | EO18: 0.1 | EP18: 0.1 | EQ18: 0.1 | ER18: -6.1 | ES18: 0 | EU18: 0 | EV18: -0.2 | EW18: -5.9 | EX18: 0 | EY18: 0 | EZ18: 0 | FA18: 0.4 | FB18: 0.2 | FC18: 1.1 | FD18: 9.7 | FE18: 0.2 | FF18: 3.1 | FG18: 0 | FH18: 2.9 | FI18: 3.39 | FJ18: 68.49778 | FM18: 0 | FN18: 1.3 | FO18: 0.8 | FP18: 0.3 | FQ18: 18.91841 | FR18: -0.2 | FS18: 0.8 | FU18: 21.91841
A19: 28/08/2025 | B19: 04:30 | C19: 4.8 | D19: 0.9 | E19: 6.4 | H19: 0 | I19: 0.6 | L19: -33.4 | M19: -37.3 | N19: -6.1 | O19: 27.7 | P19: 24.9 | Q19: 13.5 | R19: 50.6 | S19: -0.1 | T19: 0 | X19: -1.3 | Y19: 1.6 | Z19: 0.8 | AA19: 0 | AB19: -3.1 | AC19: 3.9 | AD19: 3.5 | AI19: -0.2 | AJ19: -7.4 | AN19: -1.2 | AO19: 0 | AP19: 0.7 | AQ19: 12.1 | AR19: 8.9 | AS19: -0.5 | AT19: 1.5 | AU19: 1.3 | AV19: 32.7 | AW19: 3 | AX19: -39.8 | AY19: -2.4 | AZ19: 0 | BA19: 0 | BB19: -1.2 | BC19: 2.3 | BD19: 0.5 | BE19: 0 | BF19: 1.5 | BI19: -2.3 | BL19: 2.3 | BP19: 1.3 | BQ19: -50.5 | BR19: -38.5 | BS19: 22 | BT19: -7.3 | BU19: 5.2 | BV19: -0.8 | CC19: -0.6 | CD19: 22.6 | CE19: 10.5 | CF19: -0.5 | CG19: -0.5 | CH19: -0.1 | CL19: 7 | CM19: 10.7 | CN19: -42.1 | CO19: 0 | CT19: 9.8 | CU19: 1.6 | CW19: -8.4 | CX19: 0 | CY19: -6.4 | DA19: 0.4 | DB19: 0.01826 | DC19: 0 | DE19: 0 | DF19: 0 | DG19: 1.2 | DH19: 0.2 | DI19: 0.6 | DJ19: 0 | DK19: 0.5 | DM19: 0 | DN19: 0 | DO19: 1.4 | DP19: 1.3 | DQ19: 1.9 | DR19: 0.4 | DS19: 0.3 | DT19: 1.5 | DU19: 0 | DV19: 0.4 | DW19: 0.1 | DX19: 0.2 | DZ19: -1.9 | EA19: 0.2 | EB19: 0.5 | EC19: 0.3 | ED19: 0.1 | EE19: 3.2 | EF19: 4 | EG19: 0 | EH19: -7.4 | EI19: -9.1 | EJ19: -0.9 | EK19: 0 | EL19: 1.3 | EM19: -0.1 | EO19: 0.1 | EP19: 0.1 | EQ19: 0.1 | ER19: -6.2 | ES19: 0 | EU19: 0 | EV19: -0.2 | EW19: -6.6 | EX19: 0 | EY19: 0 | EZ19: 0 | FA19: 0.4 | FB19: 0.2 | FC19: 1.5 | FD19: 9.5 | FE19: 0.3 | FF19: 2.1 | FG19: 0 | FH19: 4 | FI19: 3.51 | FJ19: 14.12826 | FM19: 0 | FN19: 1.3 | FO19: 0.9 | FP19: 0.3 | FQ19: 18.91924 | FR19: -0.2 | FS19: 0.9 | FU19: 22.11924
A20: 28/08/2025 | B20: 05:00 | C20: 7 | D20: 14.8 | E20: 8.4 | H20: 0 | I20: 1.5 | L20: -29.6 | M20: -30.2 | N20: 1.2 | O20: 31.7 | P20: 26.2 | Q20: 14.8 | R20: 51.4 | S20: 0.1 | T20: 0.1 | X20: 1.3 | Y20: 1.5 | Z20: 1.5 | AA20: 0 | AB20: -3.1 | AC20: 4.2 | AD20: 5.2 | AI20: 0.6 | AJ20: -9 | AN20: -1.1 | AO20: 0 | AP20: 0.7 | AQ20: 11.9 | AR20: 8.8 | AS20: -0.8 | AT20: 1.5 | AU20: 1 | AV20: 35.2 | AW20: 5.2 | AX20: -38.2 | AY20: -3.4 | AZ20: 0 | BA20: 0 | BB20: 1.6 | BC20: 3 | BD20: 0.5 | BE20: 0 | BF20: 4 | BI20: -1.3 | BL20: 3.3 | BP20: 1.7 | BQ20: -49.5 | BR20: -37 | BS20: 24.1 | BT20: -5.7 | BU20: 6 | BV20: -0.7 | CC20: -0.6 | CD20: 21.1 | CE20: 11.2 | CF20: 0 | CG20: -0.5 | CH20: 0.1 | CL20: 9.3 | CM20: 13.1 | CN20: -39.2 | CO20: 0 | CT20: 11 | CU20: 2.4 | CW20: -8.5 | CX20: 0 | CY20: -6.4 | DA20: 0.4 | DB20: 0.01336 | DC20: 0 | DE20: 0 | DF20: 0.1 | DG20: 1.2 | DH20: 0.3 | DI20: 0.4 | DJ20: 0 | DK20: 0.5 | DM20: 0 | DN20: 0 | DO20: 1.5 | DP20: 1.7 | DQ20: 1.9 | DR20: 0.4 | DS20: 0.3 | DT20: 1.5 | DU20: 0.2 | DV20: 0.3 | DW20: 0.5 | DX20: 0.2 | DZ20: -1.9 | EA20: 0.2 | EB20: 0.5 | EC20: 0.3 | ED20: 0.2 | EE20: 1.6 | EF20: 4 | EG20: 0.4 | EH20: -5.1 | EI20: -6.6 | EJ20: -0.5 | EK20: -0.8 | EL20: 1.3 | EM20: -0.1 | EO20: 0.1 | EP20: 0.1 | EQ20: 0.1 | ER20: -6.1 | ES20: 0 | EU20: 0 | EV20: -0.2 | EW20: 0 | EX20: 0 | EY20: 0 | EZ20: 0 | FA20: 0.4 | FB20: 0.4 | FC20: 1.5 | FD20: 9.6 | FE20: 0.5 | FF20: 3.5 | FG20: 0 | FH20: 3 | FI20: 3.45 | FJ20: 104.66336 | FM20: 0 | FN20: 1.2 | FO20: 0.8 | FP20: 0.3 | FQ20: 18.92075 | FR20: -0.2 | FS20: 0.8 | FU20: 21.82075
A21: 28/08/2025 | B21: 05:30 | C21: 8.3 | D21: 12.9 | E21: 8.6 | H21: 0 | I21: -6.9 | L21: -29.2 | M21: -33 | N21: -1.3 | O21: 31.2 | P21: 26.9 | Q21: 15.2 | R21: 69.4 | S21: 0 | T21: 1.5 | X21: 0.4 | Y21: 1.6 | Z21: 1.6 | AA21: 0 | AB21: -3.1 | AC21: 4.4 | AD21: 6.1 | AI21: -0.1 | AJ21: -9.7 | AN21: -1 | AO21: 0 | AP21: 1.3 | AQ21: 12.5 | AR21: 8.6 | AS21: -0.9 | AT21: 1.5 | AU21: 1.2 | AV21: 34.8 | AW21: 4.8 | AX21: -38.2 | AY21: 0.2 | AZ21: 0 | BA21: 0 | BB21: 0.3 | BC21: 1.6 | BD21: 0.4 | BE21: 0 | BF21: 0.5 | BI21: 0.8 | BL21: 2.6 | BP21: 4.1 | BQ21: -49 | BR21: -36.9 | BS21: 23.9 | BT21: -5.2 | BU21: 6.2 | BV21: -0.7 | CC21: -0.6 | CD21: 21.9 | CE21: 10.5 | CF21: 0 | CG21: 1.5 | CH21: -0.3 | CL21: 10 | CM21: 13.7 | CN21: -37.8 | CO21: 0 | CT21: 12.2 | CU21: 3.1 | CW21: -8.4 | CX21: 0 | CY21: -6.4 | DA21: 0.4 | DB21: 0.00676 | DC21: 0 | DE21: 0 | DF21: 0 | DG21: 1.3 | DH21: 0.1 | DI21: 0.2 | DJ21: 0 | DK21: 0.5 | DM21: 0 | DN21: 0 | DO21: 1.3 | DP21: 1.4 | DQ21: 1.9 | DR21: 0.4 | DS21: 0.3 | DT21: 1.5 | DU21: 0.2 | DV21: 0.2 | DW21: 0.5 | DX21: 0.2 | DZ21: -2 | EA21: 0 | EB21: 0.5 | EC21: 0.3 | ED21: 0.3 | EE21: 0.3 | EF21: 4 | EG21: 0.4 | EH21: -5.2 | EI21: -6.5 | EJ21: -0.6 | EK21: 0 | EL21: 1.3 | EM21: -0.1 | EO21: 0.1 | EP21: 0.1 | EQ21: 0.1 | ER21: -6.1 | ES21: 0 | EU21: 0 | EV21: -0.2 | EW21: -5.4 | EX21: 0 | EY21: 0 | EZ21: 0 | FA21: 0.4 | FB21: 0.6 | FC21: 1.5 | FD21: 9.8 | FE21: 0.3 | FF21: 3 | FG21: 0 | FH21: 2.8 | FI21: 3.14 | FJ21: 110.84676 | FM21: 0 | FN21: 1.3 | FO21: 0.9 | FP21: 0.3 | FQ21: 18.9216 | FR21: 0.1 | FS21: 0.8 | FU21: 22.3216
A22: 28/08/2025 | B22: 06:00 | C22: 10 | D22: 18.8 | E22: 9.8 | H22: 0 | I22: -6.1 | L22: -28.9 | M22: -27.7 | N22: 5 | O22: 33.2 | P22: 28.4 | Q22: 16.2 | R22: 71.9 | S22: 0.1 | T22: 0.6 | X22: 2.3 | Y22: 1.4 | Z22: 1.5 | AA22: 0 | AB22: -3.1 | AC22: 4.4 | AD22: 6.6 | AI22: 0.4 | AJ22: -9.2 | AN22: -0.9 | AO22: 0 | AP22: 1.1 | AQ22: 11.7 | AR22: 8.8 | AS22: -1.1 | AT22: 1.5 | AU22: 2.1 | AV22: 37.5 | AW22: 7.6 | AX22: -36 | AY22: 3.6 | AZ22: 0 | BA22: 0 | BB22: 1.6 | BC22: 3.9 | BD22: 0.5 | BE22: 0 | BF22: 4.7 | BI22: 1.1 | BL22: 4.2 | BP22: 4.1 | BQ22: -47.5 | BR22: -35 | BS22: 26.1 | BT22: -3.6 | BU22: 9.2 | BV22: -0.1 | CC22: -0.6 | CD22: 21.7 | CE22: 10 | CF22: -0.9 | CG22: -0.5 | CH22: 0 | CL22: 12.6 | CM22: 16.5 | CN22: -34.5 | CO22: 0 | CT22: 14.2 | CU22: 4.3 | CW22: -10.3 | CX22: 0 | CY22: -6.2 | DA22: 0.4 | DB22: 0.02885 | DC22: 0 | DE22: 0 | DF22: 0 | DG22: 1.2 | DH22: 0.2 | DI22: 0.3 | DJ22: 0 | DK22: 0.5 | DM22: 0 | DN22: 0 | DO22: 1.2 | DP22: 1 | DQ22: 1.9 | DR22: 0.2 | DS22: 0.3 | DT22: 1.5 | DU22: 0.3 | DV22: 0.3 | DW22: 0.6 | DX22: 0.2 | DZ22: -1.8 | EA22: 0.1 | EB22: 0.5 | EC22: 0.3 | ED22: 0.3 | EE22: 0.8 | EF22: 4 | EG22: 0.3 | EH22: -5.4 | EI22: -7 | EJ22: -0.6 | EK22: -0.9 | EL22: 1.3 | EM22: -0.1 | EO22: 0.1 | EP22: 0.1 | EQ22: 0.1 | ER22: -6 | ES22: 1.1 | EU22: 2.2 | EV22: -0.2 | EW22: -6.4 | EX22: 0 | EY22: 0.2 | EZ22: 0 | FA22: 0.4 | FB22: 0.6 | FC22: 1.5 | FD22: 10.5 | FE22: 0.4 | FF22: 2.8 | FG22: 0 | FH22: 2.6 | FI22: 3.28 | FJ22: 182.20885 | FM22: 0 | FN22: 1.2 | FO22: 0.8 | FP22: 0.3 | FQ22: 18.92235 | FR22: 0.2 | FS22: 0.9 | FU22: 22.32235
... A58: 29/08/2025 | B58: 00:00 | C58: 2.8 | D58: 11.5 | E58: 8.3 | H58: -7.8 | I58: 2.1 | L58: -25.4 | M58: -31.1 | N58: -21.2 | O58: 27.1 | P58: -2.9 | Q58: -14.2 | R58: 56.3 | S58: 0 | T58: 0 | X58: 9.2 | Y58: 1.8 | Z58: 0.4 | AA58: 2.7 | AB58: 0 | AC58: 0 | AD58: 0 | AI58: -2.6 | AJ58: 0 | AN58: -1.3 | AO58: 0 | AP58: 0.3 | AQ58: 0 | AR58: 8.6 | AS58: 0.4 | AT58: 1.5 | AU58: 1.2 | AV58: 31.5 | AW58: 1.4 | AX58: -41.8 | AY58: -3.5 | AZ58: -2.1 | BA58: -1.1 | BB58: 0 | BC58: 3.7 | BD58: 0.5 | BE58: 0 | BF58: 0.3 | BI58: 1.1 | BL58: 1 | BP58: 0.4 | BQ58: 9.5 | BR58: 7.7 | BS58: 9.9 | BT58: 27 | BU58: 5.2 | BV58: 4.3 | CC58: -0.5 | CD58: 35.7 | CE58: 14.9 | CF58: 7.9 | CG58: 1.4 | CH58: -0.1 | CL58: 13.5 | CM58: 17.7 | CN58: -42.2 | CO58: -15.7 | CT58: 8.9 | CU58: 1.1 | CW58: -7.1 | CX58: 0 | CY58: -7.1 | DA58: 0.3 | DB58: 0.00676 | DC58: 0.1 | DE58: 0 | DF58: 0 | DG58: 0.9 | DH58: 0.2 | DI58: 0.6 | DJ58: 0 | DK58: 0.5 | DM58: 0 | DN58: 0 | DO58: 0 | DP58: 0 | DQ58: 1.8 | DR58: 0.4 | DS58: 0.3 | DT58: 1.5 | DU58: 0 | DV58: 0.1 | DW58: 0.4 | DX58: 0.2 | DZ58: -1.7 | EA58: 0.2 | EB58: 0.3 | EC58: 0.3 | ED58: 0.1 | EE58: 6 | EF58: 2.4 | EG58: 0 | EH58: -8.8 | EI58: -9.5 | EJ58: -1.3 | EK58: -1 | EL58: 1.1 | EM58: -0.1 | EO58: 0.1 | EP58: 0.1 | EQ58: 0.1 | ER58: -6.4 | ES58: 0 | EU58: 0 | EV58: -0.2 | EW58: -2.8 | EX58: 0 | EY58: 0 | EZ58: 0 | FA58: 0.4 | FB58: 0.3 | FC58: 2.5 | FD58: 11.6 | FE58: 0.1 | FF58: 2.2 | FG58: 0 | FH58: 3.1 | FI58: 3.84 | FJ58: 121.34676 | FM58: 0 | FN58: 1 | FO58: 0.8 | FP58: 0.3 | FQ58: 18.91949 | FR58: -0.2 | FS58: 1 | FU58: 21.81949
A59: EJEC | C59: 115.1 | D59: 72.15 | E59: 158.35 | F59: 0 | G59: 0 | H59: -64.85 | I59: -37.85 | J59: 0 | K59: 0 | L59: 81.45 | M59: -3.75 | N59: 306.6 | O59: 836.95 | P59: 206.85 | Q59: 139.75 | R59: 1135.6 | S59: 1.35 | T59: 44.9 | U59: 0 | V59: 0 | W59: 0 | X59: 124.35 | Y59: 28.3 | Z59: 28.05 | AA59: 24.6 | AB59: -72.3 | AC59: 96.45 | AD59: 172.25 | AE59: 0 | AF59: 0 | AG59: 0 | AH59: 0 | AI59: 72.55 | AJ59: -247.1 | AK59: 0 | AL59: 0 | AM59: 0 | AN59: -26.35 | AO59: -45.35 | AP59: 40.5 | AQ59: 323.75 | AR59: 205.45 | AS59: -5.3 | AT59: 36 | AU59: 27.1 | AV59: 875.65 | AW59: 151.65 | AX59: -947.1 | AY59: 64.6 | AZ59: -12.6 | BA59: -4.85 | BB59: 19 | BC59: 84.65 | BD59: 11.35 | BE59: 5.25 | BF59: 44.5 | BG59: 0 | BH59: 0 | BI59: 53.85 | BJ59: 0 | BK59: 0 | BL59: 28 | BM59: 0 | BN59: 0 | BO59: 0 | BP59: 51.1 | BQ59: -209.35 | BR59: -136.35 | BS59: 503.9 | BT59: 467.9 | BU59: 150.45 | BV59: 71.65 | BW59: 0 | BX59: 0 | BY59: 0 | BZ59: 0 | CA59: 0 | CB59: 0 | CC59: -14.3 | CD59: 832.8 | CE59: 523.05 | CF59: 164.35 | CG59: 63.75 | CH59: 17.05 | CI59: 0 | CJ59: 0 | CK59: 0 | CL59: 731.25 | CM59: 826.45 | CN59: -512.15 | CO59: -66.5 | CP59: 0 | CQ59: 0 | CR59: 0 | CS59: 0 | CT59: 339.95 | CU59: 103.6 | CV59: 0 | CW59: -233.9 | CX59: 78.45 | CY59: -155.35 | CZ59: 0 | DA59: 8.3 | DB59: 0.3484 | DC59: -0.05 | DD59: 0 | DE59: 15.3 | DF59: 0.2 | DG59: 28 | DH59: 2.7 | DI59: 25 | DJ59: 1.95 | DK59: 12.65 | DL59: 0 | DM59: -7.5 | DN59: -18.55 | DO59: 6.15 | DP59: -43.85 | DQ59: 42.15 | DR59: 9.1 | DS59: 4.7 | DT59: 35.4 | DU59: -20 | DV59: 2.2 | DW59: 9.25 | DX59: 4.15 | DY59: 0 | DZ59: -44.8 | EA59: 1.6 | EB59: 9.6 | EC59: 6.95 | ED59: 5.85 | EE59: 81.8 | EF59: 81.85 | EG59: 24.4 | EH59: -224.9 | EI59: -250.95 | EJ59: -33.85 | EK59: -27.7 | EL59: 23.9 | EM59: -1.95 | EN59: 0 | EO59: 2.4 | EP59: 2.4 | EQ59: 2.4 | ER59: -150.5 | ES59: 14.95 | ET59: 0 | EU59: -57.6 | EV59: -4.8 | EW59: -90.75 | EX59: 12 | EY59: 476.1 | EZ59: 16 | FA59: 14.35 | FB59: 13.95 | FC59: 39.7 | FD59: 242.55 | FE59: 5.25 | FF59: 73.25 | FG59: 6.25 | FH59: 75.3 | FI59: 85.595 | FJ59: 8295.4934 | FL59: 0 | FM59: -3.07 | FN59: 33.65 | FO59: 19.65 | FP59: 7.2 | FQ59: 454.12763 | FR59: 4.75 | FS59: 31.85 | FT59: 0 | FU59: 548.15763

Sheet DEMANDA_AREAS
B3: jueves, 28 de Agosto del 2025
B5: REPORTE DE LA DEMANDA POR ÁREAS Y SUBAREAS OPERATIVAS (MW)
B6: FECHA HORA | C6: DEMANDA | E6: AREA | H6: SUBAREAS
C7: INTERCAMBIOS INTERNACIONALES | D7: SEIN | E7: NORTE | F7: CENTRO | G7: SUR | H7: ELECTROANDES
B8: 00:30 | C8: 0 | D8: 6570.4452 | E8: 903.2837 | F8: 3984.2415 | G8: 1682.92 | H8: 251.3258
B9: 01:00 | C9: 0 | D9: 6512.8275 | E9: 936.1754 | F9: 3902.4938 | G9: 1674.1583 | H9: 249.1079
B10: 01:30 | C10: 0 | D10: 6277.5987 | E10: 880.4258 | F10: 3729.8571 | G10: 1667.3158 | H10: 254.2632
B11: 02:00 | C11: 0 | D11: 6318.5896 | E11: 916.7759 | F11: 3768.8001 | G11: 1633.0136 | H11: 246.9624
B12: 02:30 | C12: 0 | D12: 6181.9281 | E12: 867.3828 | F12: 3669.0653 | G12: 1645.48 | H12: 246.9198
B13: 03:00 | C13: 0 | D13: 6283.545 | E13: 902.2622 | F13: 3715.1653 | G13: 1666.1175 | H13: 248.1108
B14: 03:30 | C14: 0 | D14: 6241.5663 | E14: 910.2326 | F14: 3682.7582 | G14: 1648.5755 | H14: 247.0849
B15: 04:00 | C15: 0 | D15: 6278.7681 | E15: 911.7477 | F15: 3670.7344 | G15: 1696.2861 | H15: 247.0435
B16: 04:30 | C16: 0 | D16: 6244.233 | E16: 918.0557 | F16: 3649.3692 | G16: 1676.8081 | H16: 245.8215
B17: 05:00 | C17: 0 | D17: 6395.8457 | E17: 925.0225 | F17: 3768.305 | G17: 1702.5181 | H17: 240.0672
B18: 05:30 | C18: 0 | D18: 6518.822 | E18: 921.4571 | F18: 3890.0627 | G18: 1707.3022 | H18: 236.8372
B19: 06:00 | C19: 0 | D19: 6643.9539 | E19: 949.9121 | F19: 3971.3761 | G19: 1722.6657 | H19: 229.4309
... B59: ENERGÍA | C59: 0 | D59: 171311.02 | E59: 25603.06 | F59: 103156.69 | G59: 42551.269 | H59: 5816.5965
B61: LEYENDA:
D63: Potencia recibida del Ecuador
D64: Potencia entregada al Ecuador

Sheet DEMANDA_UL
B3: jueves, 28 de Agosto del 2025
B5: POTENCIA DE LOS GRANDES USUARIOS LIBRES (MW)
B6: FECHA HORA | C6: GRANDES USUARIOS LIBRES DEL ÁREA NORTE | X6: GRANDES USUARIOS LIBRES DEL ÁREA CENTRO | BP6: GRANDES USUARIOS LIBRES DEL ÁREA SUR
C7: ARCA CONTINENTAL LINDLEY S.A. | D7: AUSTRAL GROUP S.A.A | E7: CEMENTOS PACASMAYO | F7: CONSORCIO MINERO HORIZONTE S.R.L. | G7: CORPORACIÓN PESQUERA INCA S.A.C. | H7: CREDITEX: CIA IND.TEXTIL CREDISA | I7: HIPERMERCADOS TOTTUS S.A | J7: INDUSTRIA TEXTIL PIURA | K7: MINERA BOROO MISQUICHILCA S.A. | L7: MINERA GOLD FIELDS | M7: MINERA MARSA | N7: MINERA MISKY MAYO | O7: MINERA YANACOCHA | P7: OPEN PLAZA | Q7: PESQUERA DIAMANTE | R7: PETROPERU | S7: REAL PLAZA S.R.L. | T7: SIDER PERU | U7: SUPERMERCADOS PERUANOS S.A. | V7: TRUPAL S.A. | W7: UNIÓN DE CERVECERÍAS PERUANAS BACKUS Y JOHNSTON S. | X7: ACEROS AREQUIPA | Y7: ADMINISTRADORA JOCKEY PLAZA SHOPPING CENTER S.A. | Z7: ALICORP | AA7: ARCA CONTINENTAL LINDLEY S.A. | AB7: AUSTRAL GROUP S.A.A | AC7: COMPAÑIA MINERA CONDESTABLE | AD7: CORPORACIÓN PESQUERA INCA S.A.C. | AE7: CREDITEX: CIA IND.TEXTIL CREDISA | AF7: FUNDICION CHILCA S.A. | AG7: HIPERMERCADOS TOTTUS S.A | AH7: INMOBILIARIA KANPU S.A. | AI7: INMUEBLES PANAMERICANA S.A. | AJ7: KIMBERLY-CLARK PERU | AK7: LECHE GLORIA S.A. | AL7: MALL AVENTURA S.A. | AM7: MARCOBRE S.A.C. | AN7: MINERA ANTAMINA | AO7: MINERA ARES | AP7: MINERA BUENAVENTURA | AQ7: MINERA CHINALCO PERÚ S.A. | AR7: MINERA SHOUXIN PERU S.A. | AS7: MINERA VOLCAN | AT7: MINSUR | AU7: MOLYCOP-ADESUR | AV7: NEXA RESOURCES CAJAMARQUILLA S.A. | AW7: NEXA RESOURCES PERÚ S.A.A. | AX7: OPEN PLAZA | AY7: OPP FILM | AZ7: OWENS-ILLINOIS PERÚ S.A. | BA7: PAPELERA NACIONAL S.A. | BB7: PESQUERA DIAMANTE | BC7: QUIMPAC S.A. | BD7: REAL PLAZA S.R.L. | BE7: REFINERIA LA PAMPILLA S.A.A | BF7: SAGA FALABELLA | BG7: SAN MIGUEL INDUSTRIAS PET S.A. | BH7: SHOUGANG HIERRO PERU | BI7: SOFTYS PERU S.A.C. | BJ7: SUPERMERCADOS PERUANOS S.A. | BK7: TEJIDOS SAN JACINTO | BL7: TREN URBANO DE LIMA S.A. | BM7: TRUPAL S.A. | BN7: UNACEM PERU S.A. | BO7: UNIÓN DE CERVECERÍAS PERUANAS BACKUS Y JOHNSTON S. | BP7: ANGLO AMERICAN QUELLAVECO S.A. | BQ7: ARCA CONTINENTAL LINDLEY S.A. | BR7: CAL & CEMENTO SUR S.A. | BS7: COMPAÑIA MINERA ANTAPACCAY S.A. | BT7: COMPAÑÍA MINERA CHUNGAR SAC | BU7: COMPAÑIA MINERA SAN IGNACIO DE MOROCOCHA S.A.A. | BV7: EL BROCAL .S.A. | BW7: EMPRESA ADMINISTRADORA CERRO S.A.C. | BX7: EMPRESA MINERA LOS QUENUALES S.A.C. | BY7: HIPERMERCADOS TOTTUS S.A | BZ7: HUDBAY PERU S.A.C. | CA7: INDUSTRIA CACHIMAYO | CB7: MALL AVENTURA S.A. | CC7: MINERA ARES | CD7: MINERA BUENAVENTURA | CE7: MINERA CERRO VERDE | CF7: MINERA CORONA | CG7: MINERA LAS BAMBAS S.A. | CH7: MINERA VOLCAN | CI7: MINSUR | CJ7: MOLYCOP-ADESUR | CK7: NEXA RESOURCES PERÚ S.A.A. | CL7: OXIDOS DE PASCO S.A.C. | CM7: PESQUERA DIAMANTE | CN7: REAL PLAZA S.R.L. | CO7: SOBREANDES S.A.C. | CP7: SOUTHERN PERU CC | CQ7: SUPERMERCADOS PERUANOS S.A. | CR7: UNACEM PERU S.A. | CS7: UNIÓN DE CERVECERÍAS PERUANAS BACKUS Y JOHNSTON S. | CT7: YURA
B8: 00:30 | E8: 37.39634 | F8: 11.451 | H8: 4.077 | L8: 11.1321 | M8: 14.458 | N8: 3.68 | O8: 29.85 | R8: 52.887 | T8: 43.6809 | V8: 7.5 | X8: 147.92 | Z8: 4.93678 | AE8: 4.299 | AF8: 4.2 | AH8: 4.8412 | AJ8: 5.33786 | AK8: 0 | AL8: 0.968 | AM8: 49.04098 | AN8: 134.44914 | AO8: 28.1521 | AP8: 0.81 | AQ8: 167.81 | AS8: 38.80577 | AT8: 31.81639 | AV8: 195.63494 | AW8: 35.65118 | AY8: 3.06025 | BA8: 2.6 | BC8: 73.123 | BE8: 11.8 | BI8: 17.37945 | BK8: 5.63103 | BM8: 6.989 | BN8: 39.89 | BO8: 1.95 | BP8: 131.48506 | BR8: 4.79584 | BS8: 123.32688 | BT8: 15.62459 | BV8: 34.5446 | BW8: 3.85819 | BZ8: 90.9078 | CA8: 24.99026 | CB8: 0.3227 | CC8: 0.623 | CD8: 25.7911 | CE8: 393.26402 | CF8: 11.516 | CG8: 144.8757 | CH8: 17.44576 | CK8: 17.0082 | CL8: 5.26079 | CO8: 15.0327 | CP8: 273.82 | CR8: 31.464 | CS8: 2.18843 | CT8: 23.284
B9: 01:00 | E9: 38.23793 | F9: 10.987 | H9: 4.222 | L9: 11.5119 | M9: 14.3287 | N9: 3.91 | O9: 29.534 | R9: 52.933 | T9: 43.9458 | V9: 7.8 | X9: 152.597 | Z9: 5.04943 | AE9: 4.427 | AF9: 4.3 | AH9: 4.0576 | AJ9: 5.33431 | AK9: 0 | AL9: 0.8836 | AM9: 48.99111 | AN9: 136.19335 | AO9: 28.254 | AP9: 0.7 | AQ9: 167.7 | AS9: 38.25651 | AT9: 34.18407 | AV9: 195.0853 | AW9: 36.44812 | AY9: 3.06186 | BA9: 2.6 | BC9: 73.07427 | BE9: 11.8 | BI9: 17.41885 | BK9: 5.54892 | BM9: 7.213 | BN9: 42.29 | BO9: 1.9 | BP9: 133.30743 | BR9: 4.86399 | BS9: 124.27605 | BT9: 15.47638 | BV9: 34.7968 | BW9: 3.96348 | BZ9: 89.2741 | CA9: 25.00087 | CB9: 0.3087 | CC9: 0.599 | CD9: 25.67295 | CE9: 402.75259 | CF9: 11.4471 | CG9: 149.8729 | CH9: 18.65743 | CK9: 17.021 | CL9: 5.15764 | CO9: 15.22573 | CP9: 272.5 | CR9: 32.491 | CS9: 1.93859 | CT9: 21.445
B10: 01:30 | E10: 37.36889 | F10: 11.275 | H10: 4.24 | L10: 11.0045 | M10: 14.2045 | N10: 3.84 | O10: 29.474 | R10: 52.786 | T10: 39.52159 | V10: 8.2 | X10: 130.711 | Z10: 4.96565 | AE10: 4.236 | AF10: 5.6 | AH10: 2.1378 | AJ10: 5.31128 | AK10: 0 | AL10: 0.8033 | AM10: 49.16137 | AN10: 134.29689 | AO10: 28.8513 | AP10: 0.64 | AQ10: 168.02 | AS10: 37.50307 | AT10: 34.25832 | AV10: 195.0111 | AW10: 36.73191 | AY10: 3.06631 | BA10: 2.5 | BC10: 72.87676 | BE10: 11.8 | BI10: 17.59621 | BK10: 5.51032 | BM10: 6.987 | BN10: 45.48 | BO10: 1.9 | BP10: 119.01022 | BR10: 4.87351 | BS10: 124.15746 | BT10: 15.13498 | BV10: 35.1927 | BW10: 4.0073 | BZ10: 87.8688 | CA10: 24.99355 | CB10: 0.2988 | CC10: 0.617 | CD10: 27.22493 | CE10: 403.0442 | CF10: 11.3593 | CG10: 154.6712 | CH10: 18.53943 | CK10: 17.135 | CL10: 4.82596 | CO10: 14.64304 | CP10: 274.56 | CR10: 32.003 | CS10: 1.57423 | CT10: 20.834
B11: 02:00 | E11: 41.43146 | F11: 11.823 | H11: 4.304 | L11: 10.9448 | M11: 14.5362 | N11: 3.71 | O11: 29.338 | R11: 52.962 | T11: 43.03961 | V11: 8.3 | X11: 112.13 | Z11: 5.13114 | AE11: 4.272 | AF11: 4.3 | AH11: 4.4504 | AJ11: 5.27359 | AK11: 0 | AL11: 0.7886 | AM11: 49.30857 | AN11: 135.49024 | AO11: 28.7007 | AP11: 0.44 | AQ11: 166.44 | AS11: 37.05491 | AT11: 34.14316 | AV11: 193.031 | AW11: 36.58314 | AY11: 3.06964 | BA11: 2.6 | BC11: 72.8854 | BE11: 11.8 | BI11: 17.39382 | BK11: 5.22247 | BM11: 6.983 | BN11: 43.93 | BO11: 1.94 | BP11: 129.89206 | BR11: 4.74322 | BS11: 125.65158 | BT11: 15.61091 | BV11: 34.546 | BW11: 3.7307 | BZ11: 89.8909 | CA11: 25.01527 | CB11: 0.2956 | CC11: 0.603 | CD11: 27.46548 | CE11: 383.58208 | CF11: 11.4192 | CG11: 155.9343 | CH11: 18.52095 | CK11: 17.0276 | CL11: 4.77648 | CO11: 14.73572 | CP11: 264.7 | CR11: 32.069 | CS11: 1.97791 | CT11: 20.962
B12: 02:30 | E12: 41.87991 | F12: 12.644 | H12: 4.238 | L12: 10.9289 | M12: 14.231 | N12: 3.67 | O12: 28.81 | R12: 53.224 | T12: 49.91373 | V12: 8.2 | X12: 141.697 | Z12: 4.92682 | AE12: 4.365 | AF12: 1.8 | AH12: 5.0491 | AJ12: 5.22184 | AK12: 0 | AL12: 0.7855 | AM12: 48.95853 | AN12: 132.07081 | AO12: 28.2942 | AP12: 0.41 | AQ12: 166.88 | AS12: 37.25797 | AT12: 34.07246 | AV12: 192.93811 | AW12: 36.52283 | AY12: 3.07261 | BA12: 2.5 | BC12: 72.91996 | BE12: 11.8 | BI12: 17.38201 | BK12: 5.10356 | BM12: 9.631 | BN12: 42.54 | BO12: 1.99 | BP12: 133.32371 | BR12: 4.80379 | BS12: 125.11774 | BT12: 15.8511 | BV12: 34.1548 | BW12: 3.87202 | BZ12: 89.841 | CA12: 24.91814 | CB12: 0.2949 | CC12: 0.615 | CD12: 27.56755 | CE12: 390.35374 | CF12: 11.2814 | CG12: 154.9118 | CH12: 18.5869 | CK12: 16.6262 | CL12: 4.7553 | CO12: 15.34918 | CP12: 265.34 | CR12: 32.232 | CS12: 2.14533 | CT12: 20.525
B13: 03:00 | E13: 41.83739 | F13: 11.734 | H13: 4.177 | L13: 11.4923 | M13: 13.8962 | N13: 3.6 | O13: 28.648 | R13: 53.201 | T13: 47.65997 | V13: 8.1 | X13: 152.826 | Z13: 4.82001 | AE13: 4.405 | AF13: 1.7 | AH13: 4.9261 | AJ13: 4.81592 | AK13: 0 | AL13: 0.775 | AM13: 48.32321 | AN13: 135.73747 | AO13: 28.5839 | AP13: 0.67 | AQ13: 167.15 | AS13: 37.98593 | AT13: 34.35703 | AV13: 192.88988 | AW13: 36.62735 | AY13: 3.06772 | BA13: 2.5 | BC13: 73.20622 | BE13: 11.8 | BI13: 17.32278 | BK13: 5.21378 | BM13: 7.231 | BN13: 42.67 | BO13: 1.91 | BP13: 131.34098 | BR13: 4.69563 | BS13: 125.95021 | BT13: 15.28892 | BV13: 33.6859 | BW13: 3.96593 | BZ13: 89.3149 | CA13: 24.82778 | CB13: 0.2855 | CC13: 0.587 | CD13: 26.8542 | CE13: 403.5492 | CF13: 11.4035 | CG13: 154.7145 | CH13: 18.76286 | CK13: 17.1827 | CL13: 4.75567 | CO13: 14.76309 | CP13: 273.41 | CR13: 32.142 | CS13: 2.07186 | CT13: 24.116
B14: 03:30 | E14: 43.71679 | F14: 12.203 | H14: 4.24 | L14: 12.1112 | M14: 14.2209 | N14: 3.56 | O14: 28.722 | R14: 52.846 | T14: 46.34648 | V14: 8.1 | X14: 126.945 | Z14: 4.87207 | AE14: 4.351 | AF14: 2.7 | AH14: 3.4051 | AJ14: 5.05719 | AK14: 0 | AL14: 0.7492 | AM14: 49.00121 | AN14: 138.82611 | AO14: 28.1364 | AP14: 0.48 | AQ14: 166.72 | AS14: 38.34566 | AT14: 33.56799 | AV14: 195.74727 | AW14: 36.66717 | AY14: 3.06225 | BA14: 2.5 | BC14: 72.76368 | BE14: 11.8 | BI14: 17.4042 | BK14: 5.26753 | BM14: 6.989 | BN14: 40.99 | BO14: 1.82 | BP14: 128.19949 | BR14: 4.55364 | BS14: 124.2805 | BT14: 15.68498 | BV14: 34.1909 | BW14: 4.02736 | BZ14: 89.8102 | CA14: 24.90311 | CB14: 0.2714 | CC14: 0.614 | CD14: 26.73391 | CE14: 407.40176 | CF14: 11.536 | CG14: 152.2477 | CH14: 18.66164 | CK14: 17.3807 | CL14: 4.76747 | CO14: 15.4536 | CP14: 259.88 | CR14: 31.81 | CS14: 1.90639 | CT14: 24.721
B15: 04:00 | E15: 41.90109 | F15: 11.898 | H15: 4.225 | L15: 12.8611 | M15: 14.147 | N15: 3.5 | O15: 28.782 | R15: 52.978 | T15: 39.67378 | V15: 8.3 | X15: 111.125 | Z15: 4.78538 | AE15: 4.408 | AF15: 3.2 | AH15: 3.8269 | AJ15: 5.19055 | AK15: 0 | AL15: 0.7527 | AM15: 49.13627 | AN15: 138.83908 | AO15: 28.3486 | AP15: 0.18 | AQ15: 165.69 | AS15: 36.91364 | AT15: 32.96369 | AV15: 195.31068 | AW15: 35.69811 | AY15: 3.06406 | BA15: 2.5 | BC15: 72.8167 | BE15: 11.8 | BI15: 17.11704 | BK15: 5.10131 | BM15: 7.213 | BN15: 40.61 | BO15: 1.95 | BP15: 130.51895 | BR15: 4.83517 | BS15: 125.55215 | BT15: 15.57942 | BV15: 34.7955 | BW15: 3.88656 | BZ15: 89.2035 | CA15: 24.87791 | CB15: 0.2695 | CC15: 0.593 | CD15: 25.38933 | CE15: 426.06092 | CF15: 11.555 | CG15: 157.3718 | CH15: 18.383 | CK15: 17.0008 | CL15: 4.79358 | CO15: 15.6452 | CP15: 266.29 | CR15: 31.179 | CS15: 1.87634 | CT15: 24.757
B16: 04:30 | E16: 45.83646 | F16: 12.075 | H16: 4.401 | L16: 13.4608 | M16: 14.76 | N16: 3.53 | O16: 29.08 | R16: 52.569 | T16: 38.8079 | V16: 8.2 | X16: 147.231 | Z16: 4.85287 | AE16: 4.284 | AF16: 3.3 | AH16: 5.9234 | AJ16: 5.28152 | AK16: 0 | AL16: 0.7348 | AM16: 48.85424 | AN16: 138.51015 | AO16: 28.6547 | AP16: 1.65 | AQ16: 165.4 | AS16: 37.7828 | AT16: 32.84347 | AV16: 195.16636 | AW16: 34.79692 | AY16: 3.05948 | BA16: 2.5 | BC16: 72.76478 | BE16: 11.8 | BI16: 17.26268 | BK16: 5.39778 | BM16: 6.987 | BN16: 42.07 | BO16: 1.99 | BP16: 130.18077 | BR16: 4.72237 | BS16: 125.77738 | BT16: 14.81124 | BV16: 35.1481 | BW16: 3.90366 | BZ16: 88.015 | CA16: 24.99122 | CB16: 0.2691 | CC16: 0.621 | CD16: 24.54062 | CE16: 412.13119 | CF16: 11.3468 | CG16: 157.4839 | CH16: 18.67105 | CK16: 16.7332 | CL16: 5.13201 | CO16: 15.51245 | CP16: 273.44 | CR16: 31.306 | CS16: 1.95617 | CT16: 23.588
B17: 05:00 | E17: 45.78445 | F17: 12.287 | H17: 4.304 | L17: 13.7124 | M17: 15.6765 | N17: 3.52 | O17: 29.65 | R17: 52.649 | T17: 46.14456 | V17: 8.2 | X17: 143.407 | Z17: 4.90823 | AE17: 4.233 | AF17: 1.4 | AH17: 4.9596 | AJ17: 5.03627 | AK17: 0 | AL17: 0.7282 | AM17: 48.69967 | AN17: 136.79535 | AO17: 27.7252 | AP17: 2.1 | AQ17: 162.6 | AS17: 37.57885 | AT17: 32.16054 | AV17: 194.83819 | AW17: 34.62815 | AY17: 3.05883 | BA17: 2.4 | BC17: 72.77489 | BE17: 11.8 | BI17: 17.05133 | BK17: 5.27107 | BM17: 6.983 | BN17: 43.81 | BO17: 2.02 | BP17: 129.39738 | BR17: 4.67259 | BS17: 124.03783 | BT17: 13.74457 | BV17: 34.4683 | BW17: 4.37541 | BZ17: 88.5246 | CA17: 24.98559 | CB17: 0.2597 | CC17: 0.628 | CD17: 24.12726 | CE17: 410.50128 | CF17: 11.1333 | CG17: 157.0967 | CH17: 18.63451 | CK17: 16.6976 | CL17: 4.91129 | CO17: 14.27934 | CP17: 274.49 | CR17: 31.916 | CS17: 2.09194 | CT17: 22.728
B18: 05:30 | E18: 45.97461 | F18: 11.184 | H18: 4.313 | L18: 13.0131 | M18: 15.7444 | N18: 3.54 | O18: 30.24 | R18: 52.908 | T18: 49.06431 | V18: 8.1 | X18: 140.372 | Z18: 4.78662 | AE18: 4.182 | AF18: 1.6 | AH18: 3.4241 | AJ18: 5.08865 | AK18: 0 | AL18: 0.7405 | AM18: 47.97614 | AN18: 136.18052 | AO18: 28.0805 | AP18: 1.93 | AQ18: 164.37 | AS18: 35.75008 | AT18: 31.72945 | AV18: 195.34169 | AW18: 34.91583 | AY18: 3.04102 | BA18: 2.4 | BC18: 72.80602 | BE18: 11.8 | BI18: 17.27033 | BK18: 5.302 | BM18: 6.981 | BN18: 42.85 | BO18: 1.71 | BP18: 131.81098 | BR18: 4.57599 | BS18: 124.31648 | BT18: 13.92537 | BV18: 34.1614 | BW18: 3.85894 | BZ18: 88.3667 | CA18: 24.81325 | CB18: 0.2535 | CC18: 0.627 | CD18: 24.31093 | CE18: 410.62221 | CF18: 10.5168 | CG18: 154.6911 | CH18: 18.36695 | CK18: 16.695 | CL18: 4.56709 | CO18: 13.85377 | CP18: 276.38 | CR18: 32.161 | CS18: 1.64517 | CT18: 24.869
B19: 06:00 | E19: 46.14824 | F19: 10.021 | H19: 4.273 | L19: 11.7081 | M19: 15.5671 | N19: 3.66 | O19: 30.748 | R19: 52.229 | T19: 21.81245 | V19: 7.7 | X19: 125.63 | Z19: 4.79677 | AE19: 4.345 | AF19: 1.6 | AH19: 3.4628 | AJ19: 5.10208 | AK19: 0 | AL19: 0.8189 | AM19: 47.45348 | AN19: 138.27721 | AO19: 27.2497 | AP19: 1.54 | AQ19: 162.89 | AS19: 34.86743 | AT19: 31.97027 | AV19: 195.35727 | AW19: 32.40357 | AY19: 3.04044 | BA19: 2.5 | BC19: 72.68997 | BE19: 11.8 | BI19: 17.23021 | BK19: 5.45398 | BM19: 7.231 | BN19: 41.81 | BO19: 1.7 | BP19: 134.51843 | BR19: 4.44836 | BS19: 125.50308 | BT19: 13.78881 | BV19: 33.8004 | BW19: 3.65085 | BZ19: 88.8034 | CA19: 24.67537 | CB19: 0.2432 | CC19: 0.55 | CD19: 23.47623 | CE19: 416.70481 | CF19: 10.403 | CG19: 152.2286 | CH19: 18.50559 | CK19: 16.2109 | CL19: 4.4197 | CO19: 12.21105 | CP19: 273.24 | CR19: 29.814 | CS19: 1.74701 | CT19: 24.036
... B55: 00:00 | E55: 49.00034 | F55: 11.97 | H55: 0 | L55: 23.8854 | M55: 12.817 | N55: 3.68 | O55: 30.188 | R55: 52.146 | T55: 42.81912 | V55: 8.5 | X55: 146.681 | Z55: 4.51515 | AE55: 0 | AF55: 2.4 | AH55: 4.0998 | AJ55: 5.27586 | AK55: 0 | AL55: 1.3534 | AM55: 50.10511 | AN55: 133.12206 | AO55: 28.5198 | AP55: 0.83 | AQ55: 165.92 | AS55: 37.04018 | AT55: 30.99805 | AV55: 191.03902 | AW55: 36.90311 | AY55: 3.11212 | BA55: 2.8 | BC55: 73.47191 | BE55: 19.8 | BI55: 19.21932 | BK55: 5.5583 | BM55: 6.987 | BN55: 41.4 | BO55: 2.14 | BP55: 134.07642 | BR55: 4.90019 | BS55: 127.41474 | BT55: 15.1623 | BV55: 34.2232 | BW55: 3.83695 | BZ55: 88.4694 | CA55: 24.77013 | CB55: 0.3983 | CC55: 0.678 | CD55: 24.85958 | CE55: 445.11897 | CF55: 11.5879 | CG55: 153.922 | CH55: 18.38432 | CK55: 18.9292 | CL55: 4.70976 | CO55: 15.62856 | CP55: 276 | CR55: 30.808 | CS55: 2.16696 | CT55: 30.052
B56: MWh | C56: 0 | D56: 0 | E56: 1011.4715 | F56: 275.8335 | G56: 0 | H56: 100.139 | I56: 0 | J56: 0 | K56: 0 | L56: 462.826 | M56: 312.8642 | N56: 86.485 | O56: 717.951 | P56: 0 | Q56: 0 | R56: 1260.8545 | S56: 0 | T56: 945.26225 | U56: 0 | V56: 209 | W56: 0 | X56: 2511.0255 | Y56: 0 | Z56: 108.67746 | AA56: 0 | AB56: 0 | AC56: 0 | AD56: 0 | AE56: 104.3715 | AF56: 73.45 | AG56: 0 | AH56: 74.3302 | AI56: 0 | AJ56: 118.96792 | AK56: 0 | AL56: 54.2411 | AM56: 1142.1742 | AN56: 3236.0389 | AO56: 656.06575 | AP56: 18.01 | AQ56: 3977.375 | AR56: 0 | AS56: 869.63102 | AT56: 771.64156 | AU56: 0 | AV56: 3873.5997 | AW56: 830.54748 | AX56: 0 | AY56: 74.33156 | AZ56: 0 | BA56: 61.95 | BB56: 0 | BC56: 1583.4083 | BD56: 0 | BE56: 413.51 | BF56: 0 | BG56: 0 | BH56: 0 | BI56: 422.79212 | BJ56: 0 | BK56: 131.80849 | BL56: 0 | BM56: 166.699 | BN56: 816.405 | BO56: 45.55 | BP56: 3115.1588 | BQ56: 0 | BR56: 114.90749 | BS56: 3014.604 | BT56: 339.56689 | BU56: 0 | BV56: 791.70805 | BW56: 93.434645 | BX56: 0 | BY56: 0 | BZ56: 2107.8945 | CA56: 496.32035 | CB56: 19.78735 | CC56: 15.4305 | CD56: 593.43845 | CE56: 9908.0415 | CF56: 266.6191 | CG56: 3615.5542 | CH56: 428.99619 | CI56: 0 | CJ56: 0 | CK56: 396.5952 | CL56: 111.79547 | CM56: 0 | CN56: 0 | CO56: 338.66472 | CP56: 6431.135 | CQ56: 0 | CR56: 732.1765 | CS56: 51.74085 | CT56: 421.9205
B59: Nota :
B60: Información proporcionada por la empresas
C62: DATOS ESTIMADOS
C64: SIN DATOS

Sheet TIPO_RECURSO
B3: jueves, 28 de Agosto del 2025
B5: REPORTE POTENCIA GENERADA POR TIPO DE RECURSO
B6: HORA | C6: H. PASADA | D6: H. REGULACION | E6: GAS DE CAMISEA | F6: GAS DE MALACAS | G6: DIÉSEL | H6: RESIDUAL | I6: NAFTA+GAS DE REFINERIA | J6: FLEXIGAS+GAS DE REFINERIA | K6: BAGAZO | L6: BIOGÁS | M6: SOLAR | N6: EÓLICA | O6: TOTAL | T6: EMPRESA | U6: CENTRAL | V6: HIDROELECTRICA DE PASADA | W6: HIDROELECTRICA DE REGULACION
B7: 00:30 | C7: 820.04 | D7: 1926.0152 | E7: 3386.4 | F7: 47.5 | H7: =+DESPACHO_EJECUTADO!T11 -> 0 | I7: =+DESPACHO_EJECUTADO!FD11+DESPACHO_EJECUTADO!FE11 -> 63.2 | K7: 62.59 | L7: 8.3 | M7: 0 | N7: 256.4 | O7: =+SUM(C7:N7) -> 6570.4452 | T7: ANDEAN POWER S.A.C. | U7: C.H.CARHUAC | V7: 325.3
B8: 01:00 | C8: 793.28 | D8: 1913.4375 | E8: 3386.9 | F8: 47 | H8: =+DESPACHO_EJECUTADO!T12 -> 0 | I8: =+DESPACHO_EJECUTADO!FD12+DESPACHO_EJECUTADO!FE12 -> 62.7 | K8: 61.51 | L8: 8.1 | M8: 0 | N8: 239.9 | O8: =+SUM(C8:N8) -> 6512.8275 | T8: ASOCIACIÓN SANTA LUCIA DE CHACAS | U8: C.H. HUALLIN | V8: 30.2
B9: 01:30 | C9: 777.07 | D9: 1720.1987 | E9: 3376.6 | F9: 46.9 | H9: =+DESPACHO_EJECUTADO!T13 -> 0 | I9: =+DESPACHO_EJECUTADO!FD13+DESPACHO_EJECUTADO!FE13 -> 63.1 | K9: 60.83 | L9: 9 | M9: 0 | N9: 223.9 | O9: =+SUM(C9:N9) -> 6277.5987 | T9: CELEPSA | U9: C.H. EL PLATANAL | W9: 2335.4856
B10: 02:00 | C10: 792.47 | D10: 1752.6696 | E10: 3384.1 | F10: 47.2 | H10: =+DESPACHO_EJECUTADO!T14 -> 0 | I10: =+DESPACHO_EJECUTADO!FD14+DESPACHO_EJECUTADO!FE14 -> 63.2 | K10: 60.05 | L10: 9.7 | M10: 0 | N10: 209.2 | O10: =+SUM(C10:N10) -> 6318.5896 | T10: CELEPSA RENOVABLES S.R.L. | U10: C.H. MARAÑON | V10: 261
B11: 02:30 | C11: 775.06 | D11: 1662.9181 | E11: 3382.3 | F11: 47.4 | H11: =+DESPACHO_EJECUTADO!T15 -> 0 | I11: =+DESPACHO_EJECUTADO!FD15+DESPACHO_EJECUTADO!FE15 -> 63 | K11: 59.85 | L11: 9.7 | M11: 0 | N11: 181.7 | O11: =+SUM(C11:N11) -> 6181.9281 | T11: CHINANGO S.A.C. | U11: C.H. CHIMAY | W11: 1531.6
B12: 03:00 | C12: 798.03 | D12: 1754.155 | E12: 3391.6 | F12: 46.8 | H12: =+DESPACHO_EJECUTADO!T16 -> 0 | I12: =+DESPACHO_EJECUTADO!FD16+DESPACHO_EJECUTADO!FE16 -> 62.7 | K12: 60.76 | L12: 9.7 | M12: 0 | N12: 159.8 | O12: =+SUM(C12:N12) -> 6283.545 | U12: C.H. YANANGO | V12: 456.75
B13: 03:30 | C13: 793.56 | D13: 1736.0563 | E13: 3390.7 | F13: 47.8 | H13: =+DESPACHO_EJECUTADO!T17 -> 0 | I13: =+DESPACHO_EJECUTADO!FD17+DESPACHO_EJECUTADO!FE17 -> 62.9 | K13: 59.15 | L13: 9.7 | M13: 0 | N13: 141.7 | O13: =+SUM(C13:N13) -> 6241.5663 | T13: EGASA | U13: C.H. CHARCANI III | V13: 152.305
B14: 04:00 | C14: 785.91 | D14: 1819.9481 | E14: 3396.6 | F14: 47.1 | H14: =+DESPACHO_EJECUTADO!T18 -> 0 | I14: =+DESPACHO_EJECUTADO!FD18+DESPACHO_EJECUTADO!FE18 -> 62.5 | K14: 57.11 | L14: 9.8 | M14: 0 | N14: 99.8 | O14: =+SUM(C14:N14) -> 6278.7682 | U14: C.H. CHARCANI IV | W14: 231.91
B15: 04:30 | C15: 784.49 | D15: 1781.863 | E15: 3408.8 | F15: 47.7 | H15: =+DESPACHO_EJECUTADO!T19 -> 0 | I15: =+DESPACHO_EJECUTADO!FD19+DESPACHO_EJECUTADO!FE19 -> 62.8 | K15: 59.48 | L15: 9.8 | M15: 0 | N15: 89.3 | O15: =+SUM(C15:N15) -> 6244.233 | U15: C.H. CHARCANI V | W15: 1496.375
B16: 05:00 | C16: 808.32 | D16: 1893.7479 | E16: 3418.9 | F16: 47.1 | H16: =+DESPACHO_EJECUTADO!T20 -> 8.8 | I16: =+DESPACHO_EJECUTADO!FD20+DESPACHO_EJECUTADO!FE20 -> 62.4 | K16: 60.3 | L16: 9.8 | M16: 0.0777 | N16: 86.4 | O16: =+SUM(C16:N16) -> 6395.8457 | T16: EGEJUNIN | U16: C.H. HUASAHUASI I | V16: 132.85
B17: 05:30 | C17: 829.62 | D17: 1974.1742 | E17: 3439.5 | F17: 47.3 | H17: =+DESPACHO_EJECUTADO!T21 -> 11.6 | I17: =+DESPACHO_EJECUTADO!FD21+DESPACHO_EJECUTADO!FE21 -> 63.1 | K17: 60.45 | L17: 9.8 | M17: 0.0778 | N17: 83.2 | O17: =+SUM(C17:N17) -> 6518.822 | U17: C.H. RUNATULLO II | V17: 111.75
B18: 06:00 | C18: 854.95 | D18: 1969.5261 | E18: 3482 | F18: 47.5 | H18: =+DESPACHO_EJECUTADO!T22 -> 12.8 | I18: =+DESPACHO_EJECUTADO!FD22+DESPACHO_EJECUTADO!FE22 -> 63 | K18: 60.85 | L18: 9.3 | M18: 5.0278 | N18: 139 | O18: =+SUM(C18:N18) -> 6643.9539 | U18: C.H. RUNATULLO III | V18: 159.55
B19: 06:30 | C19: 848.41 | D19: 1985.3521 | E19: 3492.2 | F19: 47.3 | H19: =+DESPACHO_EJECUTADO!T23 -> 12.2 | I19: =+DESPACHO_EJECUTADO!FD23+DESPACHO_EJECUTADO!FE23 -> 62.9 | K19: 60.33 | L19: 9.5 | M19: 104.14 | N19: 207.6 | O19: =+SUM(C19:N19) -> 6829.9321 | U19: C.H. SANTA CRUZ I | V19: 63.05
B20: 07:00 | C20: 847.19 | D20: 1680.4337 | E20: 3451.5 | F20: 47.6 | H20: =+DESPACHO_EJECUTADO!T24 -> 12.4 | I20: =+DESPACHO_EJECUTADO!FD24+DESPACHO_EJECUTADO!FE24 -> 62.9 | K20: 58.85 | L20: 9.8 | M20: 329.4017 | N20: 273.1 | O20: =+SUM(C20:N20) -> 6773.1754 | T20: EGEMSA | U20: C.H. MACHUPICCHU | V20: 2873.7
B21: 07:30 | C21: 842.77 | D21: 1672.8011 | E21: 3482.7 | F21: 47.1 | H21: =+DESPACHO_EJECUTADO!T25 -> 12.7 | I21: =+DESPACHO_EJECUTADO!FD25+DESPACHO_EJECUTADO!FE25 -> 62.6 | K21: 60.54 | L21: 9.8 | M21: 537.0102 | N21: 271.9 | O21: =+SUM(C21:N21) -> 6999.9213 | T21: EGESUR | U21: C.H. ARICOTA I | W21: 177.05
B22: 08:00 | C22: 845.97 | D22: 1673.5285 | E22: 3485.6 | F22: 47.1 | H22: =+DESPACHO_EJECUTADO!T26 -> 12.5 | I22: =+DESPACHO_EJECUTADO!FD26+DESPACHO_EJECUTADO!FE26 -> 62.5 | K22: 59.73 | L22: 9.8 | M22: 615.8866 | N22: 257.1 | O22: =+SUM(C22:N22) -> 7069.7151 | U22: C.H. ARICOTA II | W22: 79.2
B23: 08:30 | C23: 845.97 | D23: 1865.5029 | E23: 3489.1 | F23: 46.3 | H23: =+DESPACHO_EJECUTADO!T27 -> 12.3 | I23: =+DESPACHO_EJECUTADO!FD27+DESPACHO_EJECUTADO!FE27 -> 63 | K23: 60.63 | L23: 8.6 | M23: 640.2242 | N23: 232.5 | O23: =+SUM(C23:N23) -> 7264.1271 | T23: ELECTRICA YANAPAMPA SAC | U23: C.H. YANAPAMPA | V23: 57.9
B24: 09:00 | C24: 856.21 | D24: 1960.219 | E24: 3476.3 | F24: 46.4 | H24: =+DESPACHO_EJECUTADO!T28 -> 12.3 | I24: =+DESPACHO_EJECUTADO!FD28+DESPACHO_EJECUTADO!FE28 -> 62.8 | K24: 62.43 | L24: 8.6 | M24: 657.116 | N24: 221.5 | O24: =+SUM(C24:N24) -> 7363.875 | T24: ELECTROPERU | U24: C.H. MANTARO | W24: 15292.75
B25: 09:30 | C25: 849.61 | D25: 1990.4555 | E25: 3462.2 | F25: 46.4 | H25: =+DESPACHO_EJECUTADO!T29 -> 12.3 | I25: =+DESPACHO_EJECUTADO!FD29+DESPACHO_EJECUTADO!FE29 -> 63.8 | K25: 60.96 | L25: 8.6 | M25: 670.4265 | N25: 225.6 | O25: =+SUM(C25:N25) -> 7390.352 | U25: C.H. RESTITUCION | V25: 5174.15
B26: 10:00 | C26: 852.03 | D26: 2065.1196 | E26: 3466.1 | F26: 46.3 | H26: =+DESPACHO_EJECUTADO!T30 -> 12.3 | I26: =+DESPACHO_EJECUTADO!FD30+DESPACHO_EJECUTADO!FE30 -> 62.7 | K26: 60.93 | L26: 8.6 | M26: 677.129 | N26: 255.6 | O26: =+SUM(C26:N26) -> 7506.8086 | T26: EMPRESA DE GENERACION ELECTRICA CANCHAYLLO SAC | U26: C.H. CANCHAYLLO | V26: 112.7
B27: 10:30 | C27: 832.52 | D27: 2051.6071 | E27: 3453.3 | F27: 46.7 | H27: =+DESPACHO_EJECUTADO!T31 -> 12.5 | I27: =+DESPACHO_EJECUTADO!FD31+DESPACHO_EJECUTADO!FE31 -> 63.8 | K27: 61.19 | L27: 8.6 | M27: 681.5323 | N27: 283.3 | O27: =+SUM(C27:N27) -> 7495.0494 | T27: EMPRESA DE GENERACION ELECTRICA RIO BAÑOS S.A.C. | U27: C.H. RUCUY | V27: 240.6
B28: 11:00 | C28: 855.92 | D28: 2117.2507 | E28: 3482.5 | F28: 46.8 | H28: =+DESPACHO_EJECUTADO!T32 -> 12.1 | I28: =+DESPACHO_EJECUTADO!FD32+DESPACHO_EJECUTADO!FE32 -> 63 | K28: 60.57 | L28: 8.6 | M28: 687.8969 | N28: 309.7 | O28: =+SUM(C28:N28) -> 7644.3376 | T28: EMPRESA DE GENERACION ELECTRICA SANTA ANA S.A.C. | U28: C.H. RENOVANDES H1 | V28: 362.6
B29: 11:30 | C29: 840.82 | D29: 2098.1367 | E29: 3434.7 | F29: 46.9 | H29: =+DESPACHO_EJECUTADO!T33 -> 12 | I29: =+DESPACHO_EJECUTADO!FD33+DESPACHO_EJECUTADO!FE33 -> 62.4 | K29: 55.56 | L29: 8.6 | M29: 693.3494 | N29: 339.4 | O29: =+SUM(C29:N29) -> 7591.8661 | T29: EMPRESA DE GENERACION HUALLAGA | U29: C.H. CHAGLLA | W29: 301.45
B30: 12:00 | C30: 842.82 | D30: 2077.8617 | E30: 3486.9 | F30: 46.7 | H30: =+DESPACHO_EJECUTADO!T34 -> 12.1 | I30: =+DESPACHO_EJECUTADO!FD34+DESPACHO_EJECUTADO!FE34 -> 61.3 | K30: 56.69 | L30: 8.6 | M30: 695.1122 | N30: 392.6 | O30: =+SUM(C30:N30) -> 7680.6839 | U30: P.C.H. CHAGLLA | V30: 156
B31: 12:30 | C31: 836.34 | D31: 1930.2327 | E31: 3490.4 | F31: 47.2 | H31: =+DESPACHO_EJECUTADO!T35 -> 11.8 | I31: =+DESPACHO_EJECUTADO!FD35+DESPACHO_EJECUTADO!FE35 -> 62.6 | K31: 56.09 | L31: 8.6 | M31: 676.7 | N31: 431 | O31: =+SUM(C31:N31) -> 7550.9627 | T31: EMPRESA DE GENERACION HUANZA | U31: C.H. HUANZA | W31: 1319.6
B32: 13:00 | C32: 828.83 | D32: 1839.3512 | E32: 3482.4 | F32: 47.2 | H32: =+DESPACHO_EJECUTADO!T36 -> 12.4 | I32: =+DESPACHO_EJECUTADO!FD36+DESPACHO_EJECUTADO!FE36 -> 62.3 | K32: 58.54 | L32: 8.6 | M32: 695.9632 | N32: 448.1 | O32: =+SUM(C32:N32) -> 7483.6844 | T32: EMPRESA ELECTRICA AGUA AZUL | U32: C.H. POTRERO | V32: 109.2
B33: 13:30 | C33: 823.94 | D33: 1741.022 | E33: 3492.5 | F33: 47.3 | H33: =+DESPACHO_EJECUTADO!T37 -> 12.2 | I33: =+DESPACHO_EJECUTADO!FD37+DESPACHO_EJECUTADO!FE37 -> 63.4 | K33: 55.9 | L33: 8.6 | M33: 694.9589 | N33: 427.6 | O33: =+SUM(C33:N33) -> 7367.4209 | T33: EMPRESA ELECTRICA RIO DOBLE | U33: C.H. LAS PIZARRAS | V33: 64.15
B34: 14:00 | C34: 819.34 | D34: 1868.1446 | E34: 3480.5 | F34: 47.1 | H34: =+DESPACHO_EJECUTADO!T38 -> 12.5 | I34: =+DESPACHO_EJECUTADO!FD38+DESPACHO_EJECUTADO!FE38 -> 62.9 | K34: 61.45 | L34: 8.6 | M34: 691.242 | N34: 418.5 | O34: =+SUM(C34:N34) -> 7470.2766 | T34: ENGIE | U34: C.H. YUNCAN | W34: 1460.85
B35: 14:30 | C35: 830.81 | D35: 2032.4623 | E35: 3487 | F35: 47.1 | H35: =+DESPACHO_EJECUTADO!T39 -> 12.1 | I35: =+DESPACHO_EJECUTADO!FD39+DESPACHO_EJECUTADO!FE39 -> 63.1 | K35: 59.59 | L35: 8.5 | M35: 685.7907 | N35: 446.2 | O35: =+SUM(C35:N35) -> 7672.653 | T35: GENERACIÓN ANDINA S.A.C. | U35: C.H. 8 DE AGOSTO | V35: 131.55
B36: 15:00 | C36: 818.58 | D36: 2019.2241 | E36: 3502 | F36: 47 | H36: =+DESPACHO_EJECUTADO!T40 -> 12.1 | I36: =+DESPACHO_EJECUTADO!FD40+DESPACHO_EJECUTADO!FE40 -> 62.8 | K36: 59.26 | L36: 8.1 | M36: 676.7846 | N36: 446.4 | O36: =+SUM(C36:N36) -> 7652.2487 | U36: C.H. EL CARMEN | V36: 34.75
B37: 15:30 | C37: 824.4 | D37: 1925.0946 | E37: 3510 | F37: 47.2 | H37: =+DESPACHO_EJECUTADO!T41 -> 12 | I37: =+DESPACHO_EJECUTADO!FD41+DESPACHO_EJECUTADO!FE41 -> 62.6 | K37: 58.97 | L37: 8.4 | M37: 655.6138 | N37: 460.4 | O37: =+SUM(C37:N37) -> 7564.6784 | T37: GENERADORA DE ENERGÍA DEL PERÚ | U37: C.H. ÁNGEL I | V37: 101.05
B38: 16:00 | C38: 813.26 | D38: 1876.4412 | E38: 3511.9 | F38: 46.8 | H38: =+DESPACHO_EJECUTADO!T42 -> 12.1 | I38: =+DESPACHO_EJECUTADO!FD42+DESPACHO_EJECUTADO!FE42 -> 62.2 | K38: 60.23 | L38: 8.3 | M38: 597.0276 | N38: 568 | O38: =+SUM(C38:N38) -> 7556.2588 | U38: C.H. ÁNGEL II | V38: 112.6
B39: 16:30 | C39: 827.33 | D39: 1942.1909 | E39: 3520.7 | F39: 46.9 | H39: =+DESPACHO_EJECUTADO!T43 -> 12.1 | I39: =+DESPACHO_EJECUTADO!FD43+DESPACHO_EJECUTADO!FE43 -> 63.7 | K39: 59.49 | L39: 8.5 | M39: 407.8414 | N39: 625.4 | O39: =+SUM(C39:N39) -> 7514.1523 | U39: C.H. ÁNGEL III | V39: 117.1
B40: 17:00 | C40: 830.1 | D40: 1933.9024 | E40: 3645.8 | F40: 47.1 | H40: =+DESPACHO_EJECUTADO!T44 -> 12.1 | I40: =+DESPACHO_EJECUTADO!FD44+DESPACHO_EJECUTADO!FE44 -> 63.8 | K40: 59.29 | L40: 9.6 | M40: 162.8537 | N40: 617.8 | O40: =+SUM(C40:N40) -> 7382.3461 | T40: HIDROCAÑETE S.A. | U40: C.H. IMPERIAL | V40: 78.6
B41: 17:30 | C41: 812.08 | D41: 2005.5136 | E41: 3706.2 | F41: 47 | H41: =+DESPACHO_EJECUTADO!T45 -> 11.9 | I41: =+DESPACHO_EJECUTADO!FD45+DESPACHO_EJECUTADO!FE45 -> 64.5 | K41: 60.72 | L41: 9.8 | M41: 13.4069 | N41: 606.6 | O41: =+SUM(C41:N41) -> 7337.7205 | T41: HIDROELECTRICA HUANCHOR S.A.C. | U41: C.H. HUANCHOR | V41: 443.05
B42: 18:00 | C42: 825.88 | D42: 1988.5758 | E42: 3701.4 | F42: 47.6 | H42: =+DESPACHO_EJECUTADO!T46 -> 0 | I42: =+DESPACHO_EJECUTADO!FD46+DESPACHO_EJECUTADO!FE46 -> 63.6 | K42: 59.49 | L42: 9.8 | M42: 0.1225 | N42: 625.8 | O42: =+SUM(C42:N42) -> 7322.2683 | T42: HUAURA POWER GROUP S.A. | U42: C.H. YARUCAYA | V42: 444
B43: 18:30 | C43: 888.59 | D43: 2205.0358 | E43: 3722.8 | F43: 47.4 | H43: =+DESPACHO_EJECUTADO!T47 -> 0 | I43: =+DESPACHO_EJECUTADO!FD47+DESPACHO_EJECUTADO!FE47 -> 63.6 | K43: 61.83 | L43: 9.8 | M43: 0.0802 | N43: 590.5 | O43: =+SUM(C43:N43) -> 7589.636 | T43: HYDRO GLOBAL PERÚ S.A.C. | U43: CH SAN GABAN III | W43: 2375.2
B44: 19:00 | C44: 892.8 | D44: 2274.6402 | E44: 3718 | F44: 47.8 | H44: =+DESPACHO_EJECUTADO!T48 -> 0 | I44: =+DESPACHO_EJECUTADO!FD48+DESPACHO_EJECUTADO!FE48 -> 63.6 | K44: 60.15 | L44: 9.8 | M44: 0.0788 | N44: 559 | O44: =+SUM(C44:N44) -> 7625.869 | T44: INLAND ENERGY SAC | U44: C.H. SANTA TERESA | V44: 1499.3
B45: 19:30 | C45: 899.83 | D45: 2270.3184 | E45: 3715.8 | F45: 47.7 | H45: =+DESPACHO_EJECUTADO!T49 -> 0 | I45: =+DESPACHO_EJECUTADO!FD49+DESPACHO_EJECUTADO!FE49 -> 63.7 | K45: 60.65 | L45: 9.8 | M45: 0.0785 | N45: 544.5 | O45: =+SUM(C45:N45) -> 7612.3769 | T45: INVERSIONES SHAQSHA S.A.C. | U45: C.H. PARIAC | V45: 9.6
B46: 20:00 | C46: 897.64 | D46: 2261.3907 | E46: 3715.3 | F46: 47.6 | H46: =+DESPACHO_EJECUTADO!T50 -> 0 | I46: =+DESPACHO_EJECUTADO!FD50+DESPACHO_EJECUTADO!FE50 -> 63.7 | K46: 61.7 | L46: 9.8 | M46: 0 | N46: 560.3 | O46: =+SUM(C46:N46) -> 7617.4307 | T46: KALLPA GENERACION S.A. | U46: C.H. CERRO DEL AGUILA | W46: 6758.55
B47: 20:30 | C47: 899.76 | D47: 2223.1171 | E47: 3713.2 | F47: 47.7 | H47: =+DESPACHO_EJECUTADO!T51 -> 0 | I47: =+DESPACHO_EJECUTADO!FD51+DESPACHO_EJECUTADO!FE51 -> 63.8 | K47: 62.86 | L47: 9.8 | M47: 0 | N47: 574.8 | O47: =+SUM(C47:N47) -> 7595.0371 | U47: M.C.H. CERRO DEL AGUILA | V47: 76.5
B48: 21:00 | C48: 891.43 | D48: 2252.9343 | E48: 3727.2 | F48: 48.3 | H48: =+DESPACHO_EJECUTADO!T52 -> 0 | I48: =+DESPACHO_EJECUTADO!FD52+DESPACHO_EJECUTADO!FE52 -> 63.5 | K48: 61.68 | L48: 9.8 | M48: 0 | N48: 571.2 | O48: =+SUM(C48:N48) -> 7626.0444 | T48: LA VIRGEN | U48: C.H. LA VIRGEN | W48: 721.05
B49: 21:30 | C49: 832.94 | D49: 2176.1249 | E49: 3730.2 | F49: 48.9 | H49: =+DESPACHO_EJECUTADO!T53 -> 0 | I49: =+DESPACHO_EJECUTADO!FD53+DESPACHO_EJECUTADO!FE53 -> 63.4 | K49: 60.78 | L49: 9.8 | M49: 0 | N49: 531.5 | O49: =+SUM(C49:N49) -> 7453.6449 | T49: MAJA ENERGIA S.A.C. | U49: C.H. RONCADOR | V49: 43.2
B50: 22:00 | C50: 832.35 | D50: 2224.9778 | E50: 3719.3 | F50: 47.8 | H50: =+DESPACHO_EJECUTADO!T54 -> 0 | I50: =+DESPACHO_EJECUTADO!FD54+DESPACHO_EJECUTADO!FE54 -> 62.7 | K50: 60.29 | L50: 9.8 | M50: 0 | N50: 433.6 | O50: =+SUM(C50:N50) -> 7390.8178 | T50: ORAZUL ENERGY PERÚ | U50: C.H. CAÑA BRAVA | V50: 21.5
B51: 22:30 | C51: 819.65 | D51: 2240.9463 | E51: 3716.9 | F51: 47.6 | H51: =+DESPACHO_EJECUTADO!T55 -> 0 | I51: =+DESPACHO_EJECUTADO!FD55+DESPACHO_EJECUTADO!FE55 -> 61.8 | K51: 59.57 | L51: 9.8 | M51: 0 | N51: 399.1 | O51: =+SUM(C51:N51) -> 7355.3663 | U51: C.H. CAÑON DEL PATO | W51: 1984.5
B52: 23:00 | C52: 820.11 | D52: 1977.7217 | E52: 3712.4 | F52: 48.5 | H52: =+DESPACHO_EJECUTADO!T56 -> 0 | I52: =+DESPACHO_EJECUTADO!FD56+DESPACHO_EJECUTADO!FE56 -> 60.8 | K52: 61.46 | L52: 9.8 | M52: 0 | N52: 384.2 | O52: =+SUM(C52:N52) -> 7074.9917 | U52: C.H. CARHUAQUERO | W52: 229.65
B53: 23:30 | C53: 829.29 | D53: 1987.6398 | E53: 3702.2 | F53: 47.9 | H53: =+DESPACHO_EJECUTADO!T57 -> 0 | I53: =+DESPACHO_EJECUTADO!FD57+DESPACHO_EJECUTADO!FE57 -> 60.9 | K53: 59.97 | L53: 9.8 | M53: 0 | N53: 313.9 | O53: =+SUM(C53:N53) -> 7011.5998 | U53: C.H. CARHUAQUERO IV | V53: 181.6
B54: 00:00 | C54: 839.09 | D54: 1839.0601 | E54: 3566.6 | F54: 47.9 | H54: =+DESPACHO_EJECUTADO!T58 -> 0 | I54: =+DESPACHO_EJECUTADO!FD58+DESPACHO_EJECUTADO!FE58 -> 61 | K54: 59.23 | L54: 9.8 | M54: 0 | N54: 293.9 | O54: =+SUM(C54:N54) -> 6716.5801 | T54: ORYGEN PERU S.A.A. | U54: C.H. CALLAHUANCA | W54: 1677.55
B55: TOTAL MWh | C55: =SUM(C7:C54)/2 -> 20003.705 | D55: =SUM(D7:D54)/2 -> 47089.521 | E55: =SUM(E7:E54)/2 -> 84749.1 | F55: =SUM(F7:F54)/2 -> 1134.75 | G55: =SUM(G7:G54)/2 -> 0 | H55: =SUM(H7:H54)/2 -> 157.1 | I55: =SUM(I7:I54)/2 -> 1509.15 | J55: =SUM(J7:J54)/2 -> 0 | ... O55: =SUM(O7:O54)/2 -> 171311.02 | U55: C.H. HER 1 | V55: 14.4
B56: % | C56: =+C55/$O$55 -> 0.11676835 | D56: =+D55/$O$55 -> 0.27487736 | E56: =+E55/$O$55 -> 0.49470899 | F56: =+F55/$O$55 -> 0.0066239173 | G56: =+G55/$O$55 -> 0 | H56: =+H55/$O$55 -> 0.00091704552 | I56: =+I55/$O$55 -> 0.008809416 | J56: =+J55/$O$55 -> 0 | ... O56: =+O55/$O$55 -> 1 | U56: C.H. HUAMPANI | V56: 697.3
U57: C.H. HUINCO | W57: 3001.05
U58: C.H. MATUCANA | W58: 2078.15
U59: C.H. MOYOPAMPA | V59: 1536.2
T60: PERUANA DE INVERSIONES EN ENERGIAS RENOVABLES S.A. | U60: C.H. MANTA I | V60: 119.25
T61: SAN GABAN | U61: C.H. SAN GABAN II | W61: 1840.5
U62: PCH TUPURI | V62: 170.55
T63: SINERSA | U63: C.H. CHANCAY | V63: 460.7
U64: C.H. POECHOS II | V64: 172.15
T65: STATKRAFT S.A | U65: C.H. ARCATA | V65: 48
U66: C.H. CAHUA | V66: 691.1
U67: C.H. CHEVES | W67: 1757.15
U68: C.H. GALLITO CIEGO | W68: 256.55
U69: C.H. MALPASO | W69: 183.35
U70: C.H. PACHACHACA | V70: 30.6
U71: C.H. YAUPI | V71: 1803.1
T72: VARI ENERGIA S.A.C. | U72: C.H. ANASHIRONI | V72: 122.2
T73: TOTAL MWh | V73: 20003.705 | W73: 47089.521

Sheet GENERACION RER
B3: jueves, 28 de Agosto del 2025
B5: GENERACIÓN ELÉCTRICA DE LAS CENTRALES RER (MW)
B6: HORA | C6: AGRO INDUSTRIAL PARAMONGA S.A. | D6: AGROAURORA S.A.C. | E6: AGROINDUSTRIAS SAN JACINTO S.A.A. | F6: AGROLMOS SOCIEDAD ANONIMA - AGROLMOS S.A. | G6: ANDEAN POWER S.A.C. | H6: ASOCIACIÓN SANTA LUCIA DE CHACAS | I6: ATRIA ENERGIA S.A.C. | J6: BIOENERGIA DEL CHIRA S.A. | K6: COLCA SOLAR S.A.C. | L6: EGEJUNIN | Q6: ELECTRICA YANAPAMPA SAC | R6: EMPRESA DE GENERACION ELECTRICA CANCHAYLLO SAC | S6: EMPRESA DE GENERACION ELECTRICA RIO BAÑOS S.A.C. | T6: EMPRESA DE GENERACION ELECTRICA SANTA ANA S.A.C. | U6: EMPRESA ELECTRICA AGUA AZUL | V6: EMPRESA ELECTRICA RIO DOBLE | W6: ENERGÍA EÓLICA S.A. | Y6: ENERGIA RENOVABLE DEL SUR S.A. | Z6: ENGIE | AE6: GENERACIÓN ANDINA S.A.C. | AG6: GENERADORA DE ENERGÍA DEL PERÚ | AK6: GR CORTARRAMA SOCIEDAD ANONIMA CERRADA | AL6: GR PAINO SOCIEDAD ANONIMA CERRADA | AM6: GR TARUCA SOCIEDAD ANONIMA CERRADA | AN6: HIDROCAÑETE S.A. | AO6: HUAURA POWER GROUP S.A. | AP6: HYDRO PATAPO S.A.C. | AQ6: JOYA SOLAR S.A.C. | AR6: KONDU SAC | AS6: MAJA ENERGIA S.A.C. | AT6: MAJES ARCUS S.A.C. | AU6: MOQUEGUA FV S.A.C. | AV6: ORAZUL ENERGY PERÚ | AX6: ORYGEN PERU S.A.A. | BC6: PANAMERICANA SOLAR SAC. | BD6: PARQUE EOLICO MARCONA S.A.C. | BE6: PARQUE EOLICO TRES HERMANAS S.A.C. | BF6: PERUANA DE INVERSIONES EN ENERGIAS RENOVABLES S.A. | BG6: PETRAMAS | BK6: REPARTICIÓN ARCUS S.A.C. | BL6: SAN GABAN | BM6: SINERSA | BO6: TACNA SOLAR SAC. | BP6: VARI ENERGIA S.A.C. | BQ6: TOTAL RER
C7: C.T. PARAMONGA | D7: C.T. MAPLE | E7: C.T SAN JACINTO | F7: C.T. AGROLMOS | G7: C.H. CARHUAC | H7: C.H. HUALLIN | I7: C.H. PURMACANA | J7: C.T. CAÑA BRAVA | L7: C.H. HUASAHUASI I | M7: C.H. HUASAHUASI II | N7: C.H. RUNATULLO II | O7: C.H. RUNATULLO III | P7: C.H. STA CRUZ I y II | Q7: C.H. YANAPAMPA | R7: C.H. CANCHAYLLO | S7: C.H. RUCUY | T7: C.H. RENOVANDES H1 | U7: C.H. POTRERO | V7: C.H. LAS PIZARRAS | AE7: C.H. 8 DE AGOSTO | AF7: C.H. EL CARMEN | AG7: C.H. ANGEL I | AH7: C.H. ANGEL II | AI7: C.H. ANGEL III | AJ7: C.H. LA JOYA | AN7: C.H. NUEVAIMPERIAL | AO7: C.H. YARUCAYA | AP7: MCH PATAPO | AS7: C.H. RONCADOR | AV7: C.H. CANA BRAVA | AW7: C.H. CARHUAQUERO4 | BB7: C.H. HER 1 | BF7: C.H. MANTA | BG7: C.T. HUAYCOLORO | BH7: C.T. LA GRINGA V | BI7: CTB CALLAO | BJ7: CTB. DONA CATALINA | BL7: C.H. TUPURI | BM7: C.H. CHANCAY | BN7: C.H. POECHOS2 | BP7: C.H. ANASHIRONI | BQ7: MW
B8: 0:30 | C8: 14.5 | D8: 18.3 | E8: 9.1 | F8: 11.09 | G8: 8.8 | H8: 1.3 | J8: 9.6 | L8: 5.5 | N8: 5.1 | O8: 6.8 | P8: 3 | Q8: 2.3 | R8: 4.4 | S8: 10 | T8: 15.9 | U8: 3.9 | V8: 3.1 | W8: 22.5 | X8: 9.2 | Y8: 26.9 | AA8: 34.5 | AB8: 49.1 | AC8: 3.4 | AD8: 3 | AE8: 8.2 | AF8: 1.8 | AG8: 4 | AH8: 4.5 | AI8: 5.2 | AL8: 16.7 | AM8: 18.1 | AN8: 3.3 | AO8: 18.5 | AS8: 1.8 | AV8: 2.5 | AW8: 6.5 | AX8: 22.1 | AZ8: 22.2 | BB8: 0.6 | BD8: 5 | BE8: 23.7 | BF8: 4.9 | BG8: 3.6 | BH8: 2.4 | BI8: 1.1 | BJ8: 1.2 | BL8: 0.3 | BM8: 19.7 | BN8: 7.6 | BP8: 5.1 | BQ8: 491.89
B9: 1:00 | C9: 14.6 | D9: 18.3 | E9: 8.6 | F9: 11.01 | G9: 0.6 | H9: 1.3 | J9: 9 | L9: 5.4 | N9: 4.8 | O9: 6.8 | P9: 3.2 | Q9: 2.4 | R9: 4.4 | S9: 10 | T9: 15.6 | U9: 3.9 | V9: 3.1 | W9: 26.8 | X9: 7.3 | Y9: 19.5 | AA9: 28.9 | AB9: 45.5 | AC9: 3.9 | AD9: 3.1 | AE9: 8 | AF9: 1.8 | AG9: 4 | AH9: 4.5 | AI9: 4.7 | AL9: 17.4 | AM9: 18.1 | AN9: 3.3 | AO9: 18.5 | AS9: 1.8 | AX9: 22.8 | AZ9: 21 | BB9: 0.6 | BD9: 4.7 | BE9: 20.9 | BF9: 4.9 | BG9: 3.7 | BH9: 2.4 | BI9: 0.8 | BJ9: 1.2 | BL9: 0.3 | BM9: 19.5 | BN9: 7.1 | BP9: 5.1 | BQ9: 455.11
B10: 1:30 | C10: 13.5 | D10: 18.3 | E10: 9.4 | F10: 10.73 | H10: 1.3 | J10: 8.9 | L10: 5.4 | N10: 5 | O10: 7 | P10: 3.2 | Q10: 2.5 | R10: 4.8 | S10: 10 | T10: 15.2 | U10: 4.1 | V10: 3.1 | W10: 26.8 | X10: 6.4 | Y10: 22.1 | AA10: 23.6 | AB10: 39.1 | AC10: 2.9 | AD10: 2.8 | AE10: 8 | AF10: 1.8 | AG10: 4.2 | AH10: 4.5 | AI10: 4.7 | AL10: 16.2 | AM10: 17.8 | AN10: 3.3 | AO10: 18.5 | AS10: 1.8 | AX10: 17.7 | AZ10: 20.6 | BB10: 0.6 | BD10: 6.1 | BE10: 21.8 | BF10: 5 | BG10: 4.1 | BH10: 3 | BI10: 0.7 | BJ10: 1.2 | BL10: 0.3 | BM10: 19.2 | BN10: 7.1 | BP10: 4.9 | BQ10: 439.23
B11: 2:00 | C11: 13.5 | D11: 18.3 | E11: 7.9 | F11: 11.05 | H11: 1.3 | J11: 9.3 | L11: 5.4 | N11: 5 | O11: 7.2 | P11: 3.2 | Q11: 2.5 | R11: 4.8 | S11: 10 | T11: 15.9 | U11: 4.2 | V11: 3.1 | W11: 27.2 | X11: 4.7 | Y11: 22.4 | AA11: 22.3 | AB11: 32.9 | AC11: 3 | AD11: 2.3 | AE11: 7.8 | AF11: 1.8 | AG11: 4.5 | AH11: 4.5 | AI11: 4.7 | AL11: 13.9 | AM11: 17.2 | AN11: 3.3 | AO11: 18.5 | AS11: 1.8 | AX11: 17.3 | AZ11: 19.9 | BB11: 0.6 | BD11: 5.9 | BE11: 20.2 | BF11: 5 | BG11: 4.4 | BH11: 3 | BI11: 1.1 | BJ11: 1.2 | BL11: 0.3 | BM11: 19.2 | BN11: 7.1 | BP11: 5.1 | BQ11: 425.75
B12: 2:30 | C12: 14 | D12: 18.3 | E12: 7.3 | F12: 11.05 | H12: 1.2 | J12: 9.2 | L12: 5.4 | N12: 4.8 | O12: 7.1 | P12: 3.2 | Q12: 2.3 | R12: 4.8 | S12: 10 | T12: 15.6 | U12: 4.2 | V12: 3.1 | W12: 26.8 | X12: 2.3 | Y12: 21.2 | AA12: 18.9 | AB12: 31.5 | AC12: 2.1 | AD12: 1.3 | AE12: 7.7 | AF12: 1.8 | AG12: 4.7 | AH12: 4.5 | AI12: 4.7 | AL12: 11 | AM12: 14.6 | AN12: 3.3 | AO12: 18.5 | AS12: 1.8 | AX12: 11.4 | AZ12: 14.9 | BB12: 0.6 | BD12: 5.1 | BE12: 20.6 | BF12: 5.1 | BG12: 4.4 | BH12: 3 | BI12: 1.1 | BJ12: 1.2 | BL12: 0.3 | BM12: 19.2 | BN12: 7.1 | BP12: 5.1 | BQ12: 397.35
B13: 3:00 | C13: 13.7 | D13: 18.3 | E13: 8.2 | F13: 11.06 | H13: 1.2 | J13: 9.5 | L13: 5.5 | N13: 4.8 | O13: 7.2 | P13: 3.2 | Q13: 2.4 | R13: 4.7 | S13: 10 | T13: 15.8 | U13: 4.3 | V13: 3.1 | W13: 26.1 | X13: 2.6 | Y13: 19.2 | AA13: 15.5 | AB13: 26.8 | AC13: 2.1 | AD13: 1.3 | AE13: 7.6 | AF13: 1.8 | AG13: 4.5 | AH13: 5.2 | AI13: 5.2 | AL13: 11.6 | AM13: 12.5 | AN13: 3.3 | AO13: 18.5 | AS13: 1.8 | AX13: 9 | AZ13: 14.1 | BB13: 0.6 | BD13: 4.4 | BE13: 14.6 | BF13: 5 | BG13: 4.4 | BH13: 3 | BI13: 1.1 | BJ13: 1.2 | BL13: 0.3 | BM13: 19.5 | BN13: 7.1 | BP13: 5.2 | BQ13: 378.06
B14: 3:30 | C14: 13.5 | D14: 18.3 | E14: 7.5 | F14: 11.05 | H14: 1.2 | J14: 8.8 | L14: 5.5 | N14: 5.1 | O14: 7.2 | P14: 3.2 | Q14: 2.4 | R14: 4.7 | S14: 10 | T14: 16.1 | U14: 4.4 | V14: 3.1 | W14: 23 | X14: 5.7 | Y14: 18.2 | AA14: 15.1 | AB14: 23.3 | AC14: 1.6 | AD14: 1.4 | AE14: 7.6 | AF14: 1.8 | AG14: 4.5 | AH14: 5.2 | AI14: 5.4 | AL14: 10.2 | AM14: 15.1 | AN14: 3.3 | AO14: 18.5 | AS14: 1.8 | AX14: 5 | AZ14: 10.3 | BB14: 0.6 | BD14: 2.7 | BE14: 10.1 | BF14: 5 | BG14: 4.4 | BH14: 3 | BI14: 1.1 | BJ14: 1.2 | BL14: 0.3 | BM14: 19.5 | BN14: 7.1 | BP14: 5.2 | BQ14: 359.25
B15: 4:00 | C15: 13.5 | D15: 18.3 | E15: 7.2 | F15: 11.01 | H15: 1.2 | J15: 7.1 | L15: 5.4 | N15: 4.8 | O15: 7.2 | P15: 3.2 | Q15: 1.6 | R15: 4.6 | S15: 10 | T15: 15 | U15: 4.4 | V15: 3.1 | W15: 20.6 | X15: 4.7 | Y15: 9.4 | AA15: 6.5 | AB15: 18.9 | AC15: 0.8 | AD15: 0.8 | AE15: 7.6 | AF15: 1.8 | AG15: 4.5 | AH15: 5.2 | AI15: 5.4 | AL15: 13.5 | AM15: 15.7 | AN15: 3.3 | AO15: 18.5 | AS15: 1.8 | AX15: 1.1 | AZ15: 2.3 | BB15: 0.6 | BD15: 1.1 | BE15: 4.4 | BF15: 4.9 | BG15: 4.4 | BH15: 3 | BI15: 1.2 | BJ15: 1.2 | BL15: 0.3 | BM15: 19.7 | BN15: 7.1 | BP15: 5.2 | BQ15: 313.11
B16: 4:30 | C16: 13.9 | D16: 18.3 | E16: 7 | F16: 11.08 | G16: 2.4 | H16: 1.2 | J16: 9.2 | L16: 5.5 | N16: 5 | O16: 7.1 | P16: 3.2 | Q16: 1.6 | R16: 4.5 | S16: 10 | T16: 14.9 | U16: 4.5 | V16: 3.1 | W16: 15.6 | X16: 4.1 | Y16: 12.6 | AA16: 5 | AB16: 16.8 | AC16: 0.5 | AE16: 7.4 | AF16: 1.8 | AG16: 4.5 | AH16: 5 | AI16: 5.2 | AL16: 15.2 | AM16: 15.5 | AN16: 3.3 | AO16: 18.5 | AS16: 1.8 | AX16: 0.2 | AZ16: 0.3 | BB16: 0.6 | BD16: 0.8 | BE16: 2.7 | BF16: 5 | BG16: 4.4 | BH16: 3 | BI16: 1.2 | BJ16: 1.2 | BL16: 0.3 | BM16: 19.6 | BN16: 7.1 | BP16: 5 | BQ16: 306.68
B17: 5:00 | C17: 14 | D17: 18.3 | E17: 7.9 | F17: 10.8 | G17: 10.4 | H17: 1.2 | J17: 9.3 | L17: 5.6 | N17: 5 | O17: 7.2 | P17: 3.2 | Q17: 2 | R17: 4.5 | S17: 10 | T17: 15.6 | U17: 4.9 | V17: 3.1 | W17: 11.1 | X17: 5.9 | Y17: 14.5 | AA17: 4.3 | AB17: 12.3 | AC17: 0.6 | AD17: 0.1 | AE17: 7.4 | AF17: 1.8 | AG17: 4.5 | AH17: 5 | AI17: 5.2 | AL17: 15.6 | AM17: 17.1 | AN17: 3.3 | AO17: 18.5 | AS17: 1.8 | AT17: 0.0777 | BB17: 0.6 | BD17: 1.7 | BE17: 3.2 | BF17: 5 | BG17: 4.4 | BH17: 3 | BI17: 1.2 | BJ17: 1.2 | BL17: 0.3 | BM17: 19.5 | BN17: 7.1 | BP17: 5.1 | BQ17: 314.3777
B18: 5:30 | C18: 14 | D18: 18.3 | E18: 9.1 | F18: 9.95 | G18: 14.6 | H18: 1.2 | J18: 9.1 | L18: 5.6 | N18: 4.8 | O18: 7.2 | P18: 3 | Q18: 2.6 | R18: 4.5 | S18: 10 | T18: 15.5 | U18: 5 | V18: 3.1 | W18: 10.1 | X18: 6.6 | Y18: 14.7 | AA18: 3.1 | AB18: 12.1 | AC18: 0.2 | AE18: 7.4 | AF18: 1.8 | AG18: 4.5 | AH18: 5 | AI18: 5.2 | AL18: 16 | AM18: 17.3 | AN18: 3.3 | AO18: 18.5 | AS18: 1.8 | AT18: 0.0778 | AX18: 0.1 | BB18: 0.6 | BD18: 0.9 | BE18: 2.1 | BF18: 5.1 | BG18: 4.4 | BH18: 3 | BI18: 1.2 | BJ18: 1.2 | BL18: 0.3 | BM18: 19.5 | BN18: 7.1 | BP18: 5.1 | BQ18: 315.8278
B19: 6:00 | C19: 13.9 | D19: 18.3 | E19: 9.4 | F19: 10.05 | G19: 20.1 | H19: 1.2 | J19: 9.2 | L19: 5.6 | N19: 4.8 | O19: 7.3 | P19: 2.9 | Q19: 2.6 | R19: 4.5 | S19: 10 | T19: 15.8 | U19: 5.1 | V19: 3.1 | W19: 9.5 | X19: 10.6 | Y19: 21.8 | AA19: 7.8 | AB19: 16 | AC19: 0.6 | AD19: 1.1 | AE19: 7.4 | AF19: 1.8 | AG19: 4.5 | AH19: 5 | AI19: 5.2 | AL19: 17.2 | AM19: 18.1 | AN19: 3.3 | AO19: 18.5 | AQ19: 1.4 | AS19: 1.8 | AT19: 0.1278 | AU19: 1.1 | AX19: 13.6 | AY19: 0.6 | AZ19: 14.6 | BA19: 0.6 | BB19: 0.6 | BC19: 1.2 | BD19: 2.6 | BE19: 5.5 | BF19: 5.1 | BG19: 4.4 | BH19: 3 | BI19: 0.7 | BJ19: 1.2 | BL19: 0.3 | BM19: 19.5 | BN19: 7.1 | BP19: 5.2 | BQ19: 382.4778
B20: 6:30 | C20: 13.9 | D20: 18.3 | E20: 9.1 | F20: 10.03 | G20: 20.1 | H20: 1.1 | J20: 9 | K20: 0.1 | L20: 5.9 | N20: 4.8 | O20: 7.1 | P20: 2.8 | Q20: 2.6 | R20: 4.5 | S20: 10 | T20: 15.4 | U20: 4.4 | V20: 3.1 | W20: 10.4 | X20: 8.7 | Y20: 23.8 | Z20: 3.9 | AA20: 13.2 | AB20: 26 | AC20: 1.5 | AD20: 1.4 | AE20: 7.2 | AF20: 1.8 | AG20: 4.5 | AH20: 5 | AI20: 5.2 | AK20: 11.9 | AL20: 16.5 | AM20: 17.2 | AN20: 3.3 | AO20: 18.5 | AQ20: 33 | AS20: 1.8 | AT20: 1.24 | AU20: 6.9 | AW20: 9.9 | AX20: 43.7 | AY20: 20.9 | AZ20: 28.9 | BA20: 17.1 | BB20: 0.6 | BC20: 8.1 | BD20: 5.1 | BE20: 11.2 | BF20: 5 | BG20: 4.4 | BH20: 3 | BI20: 0.9 | BJ20: 1.2 | BK20: 0.5 | BL20: 0.3 | BM20: 19.5 | BN20: 7.1 | BO20: 0.5 | BP20: 5.1 | BQ20: 558.17
B21: 7:00 | C21: 14.1 | D21: 18.3 | E21: 6.6 | F21: 10.05 | G21: 20.1 | H21: 1.1 | J21: 9.8 | K21: 0.2 | L21: 5.9 | N21: 4.9 | O21: 7.2 | P21: 2.7 | Q21: 2.3 | R21: 4.8 | S21: 10 | T21: 15.4 | U21: 4.4 | V21: 3.1 | W21: 11.1 | X21: 7.9 | Y21: 28.8 | Z21: 14.9 | AA21: 20.9 | AB21: 26.9 | AC21: 3 | AD21: 3.5 | AE21: 7.1 | AF21: 1.8 | AG21: 4.5 | AH21: 5 | AI21: 5.2 | AK21: 37.3 | AL21: 17.1 | AM21: 17.3 | AN21: 3.3 | AO21: 18.5 | AQ21: 116 | AS21: 1.8 | AT21: 3.8017 | AU21: 12.6 | AW21: 9.9 | AX21: 65.4 | AY21: 69.7 | AZ21: 44.9 | BA21: 55.6 | BB21: 0.6 | BC21: 14.9 | BD21: 7.8 | BE21: 18.5 | BF21: 5 | BG21: 4.4 | BH21: 3 | BI21: 1.2 | BJ21: 1.2 | BK21: 3 | BL21: 0.3 | BM21: 19.5 | BN21: 7.2 | BO21: 1.4 | BP21: 5 | BQ21: 847.7517
B22: 7:30 | C22: 14 | D22: 18.3 | E22: 7.7 | F22: 11.04 | G22: 16.7 | H22: 1.1 | J22: 9.5 | K22: 0.3 | L22: 5.9 | N22: 4.8 | O22: 7.1 | P22: 2.3 | Q22: 2.6 | R22: 4.8 | S22: 10 | T22: 15.3 | U22: 4.5 | W22: 10.1 | X22: 8 | Y22: 35.6 | Z22: 26.8 | AA22: 19.4 | AB22: 30.5 | AC22: 2.3 | AD22: 2.4 | AE22: 7 | AF22: 1.8 | AG22: 4.2 | AH22: 5 | AI22: 5.2 | AK22: 61.3 | AL22: 17.5 | AM22: 18.1 | AN22: 3.2 | AO22: 18.5 | AQ22: 201.3 | AR22: 0.1 | AS22: 1.8 | AT22: 6.5102 | AU22: 13.9 | AV22: 1.5 | AW22: 9.9 | AX22: 54.1 | AY22: 113.7 | AZ22: 41.2 | BA22: 88.3 | BB22: 0.6 | BC22: 16.7 | BD22: 6.8 | BE22: 25.9 | BF22: 5 | BG22: 4.4 | BH22: 3 | BI22: 1.2 | BJ22: 1.2 | BK22: 5.7 | BL22: 0.3 | BM22: 19.6 | BN22: 7.2 | BO22: 2.4 | BP22: 5 | BQ22: 1050.1502
B23: 8:00 | C23: 14.2 | D23: 18.3 | E23: 7 | F23: 10.63 | G23: 16.3 | H23: 1.1 | J23: 9.6 | K23: 0.6 | L23: 5.9 | N23: 4.8 | O23: 7.2 | P23: 2.3 | Q23: 2.6 | R23: 4.8 | S23: 10 | T23: 15.7 | U23: 4.9 | W23: 8.5 | X23: 9.1 | Y23: 39.7 | Z23: 33.3 | AA23: 23 | AB23: 32 | AC23: 2.9 | AD23: 2.6 | AE23: 7 | AF23: 1.8 | AG23: 4 | AH23: 5 | AI23: 5.2 | AK23: 72.9 | AL23: 17.7 | AM23: 18.1 | AN23: 3.2 | AO23: 18.5 | AQ23: 229.4 | AR23: 0.1 | AS23: 1.8 | AT23: 8.9866 | AU23: 14.3 | AV23: 0.9 | AW23: 9.8 | AX23: 38 | AY23: 132.8 | AZ23: 26.3 | BA23: 94.7 | BB23: 0.6 | BC23: 17.2 | BD23: 9.2 | BE23: 30 | BF23: 5 | BG23: 4.4 | BH23: 3 | BI23: 1.2 | BJ23: 1.2 | BK23: 8.2 | BL23: 0.3 | BM23: 19.5 | BN23: 7.1 | BO23: 3.4 | BP23: 5.2 | BQ23: 1113.0166
B24: 8:30 | C24: 14.1 | D24: 18.3 | E24: 8.2 | F24: 10.73 | G24: 17.8 | H24: 1.1 | J24: 9.3 | K24: 1 | L24: 5.9 | N24: 4.8 | O24: 7.3 | P24: 2.3 | Q24: 2.6 | R24: 4.8 | S24: 9.8 | T24: 15.5 | U24: 5 | W24: 7.7 | X24: 8.5 | Y24: 33.6 | Z24: 34.1 | AA24: 23.7 | AB24: 33 | AC24: 2.4 | AD24: 2.7 | AE24: 7 | AF24: 1.8 | AG24: 4 | AH24: 4.8 | AI24: 5 | AK24: 74.7 | AL24: 18.2 | AM24: 18.1 | AN24: 3.2 | AO24: 18.5 | AQ24: 239.1 | AR24: 0.2 | AS24: 1.8 | AT24: 11.1242 | AU24: 14.4 | AV24: 1.1 | AW24: 9.9 | AX24: 27.8 | AY24: 135.1 | AZ24: 16.6 | BA24: 96.9 | BB24: 0.6 | BC24: 17.8 | BD24: 9 | BE24: 31.2 | BF24: 5 | BG24: 4.4 | BH24: 3 | BI24: 1.2 | BK24: 10.5 | BL24: 0.3 | BM24: 19.7 | BN24: 7.1 | BO24: 5.3 | BP24: 5.1 | BQ24: 1113.7542
B25: 9:00 | C25: 14 | D25: 18.3 | E25: 9.8 | F25: 10.93 | G25: 17.9 | H25: 1.1 | J25: 9.4 | K25: 1 | L25: 5.9 | N25: 4.7 | O25: 7.2 | P25: 2.3 | Q25: 2.6 | R25: 4.8 | S25: 10.2 | T25: 15.1 | U25: 5.1 | W25: 5.3 | X25: 11.9 | Y25: 34.1 | Z25: 34.2 | AA25: 22.6 | AB25: 32.8 | AC25: 3 | AD25: 3.9 | AE25: 7 | AF25: 1.8 | AG25: 4 | AH25: 4.8 | AI25: 5 | AK25: 75.8 | AL25: 18.1 | AM25: 18.1 | AN25: 3.3 | AO25: 18.5 | AQ25: 243.2 | AR25: 0.2 | AS25: 1.8 | AT25: 13.016 | AU25: 14.6 | AV25: 1 | AW25: 10 | AX25: 27.4 | AY25: 137.2 | AZ25: 17 | BA25: 98.4 | BB25: 0.6 | BC25: 18.1 | BD25: 6.4 | BE25: 20.9 | BF25: 5.1 | BG25: 4.4 | BH25: 3 | BI25: 1.2 | BK25: 12.6 | BL25: 0.3 | BM25: 19.5 | BN25: 7.2 | BO25: 8.8 | BP25: 5.2 | BQ25: 1121.646
B26: 9:30 | C26: 13.2 | D26: 18.3 | E26: 8.9 | F26: 11.06 | G26: 18 | H26: 1.1 | J26: 9.5 | K26: 1.1 | L26: 5.9 | N26: 4.7 | O26: 6.8 | P26: 2.3 | Q26: 2.6 | R26: 4.8 | S26: 11.2 | T26: 15.3 | U26: 5.1 | W26: 4.3 | X26: 13 | Y26: 42.8 | Z26: 33.9 | AA26: 15.5 | AB26: 25.1 | AC26: 2.5 | AD26: 2.5 | AE26: 6.9 | AF26: 1.8 | AG26: 4 | AH26: 4.8 | AI26: 5 | AK26: 76.1 | AL26: 18.1 | AM26: 18.1 | AN26: 3.2 | AO26: 18.5 | AQ26: 245.4 | AR26: 0.3 | AS26: 1.8 | AT26: 14.5265 | AU26: 14.6 | AV26: 1 | AW26: 9.9 | AX26: 32.7 | AY26: 137.8 | AZ26: 15.8 | BA26: 99.7 | BB26: 0.6 | BC26: 18.1 | BD26: 10 | BE26: 25.2 | BF26: 5.2 | BG26: 4.4 | BH26: 3 | BI26: 1.2 | BK26: 14.2 | BL26: 0.3 | BM26: 18.1 | BN26: 7.2 | BO26: 14.7 | BP26: 5.1 | BQ26: 1136.7865
B27: 10:00 | C27: 14 | D27: 18.3 | E27: 8.2 | F27: 11.03 | G27: 18 | H27: 1.1 | J27: 9.4 | K27: 1.2 | L27: 5.9 | N27: 4.6 | O27: 6.8 | P27: 2.3 | Q27: 2.4 | R27: 4.8 | S27: 10 | T27: 15.3 | U27: 5.4 | W27: 3.9 | X27: 20.1 | Y27: 42.3 | Z27: 33.9 | AA27: 22.6 | AB27: 29.4 | AC27: 3.8 | AD27: 2.4 | AE27: 6.8 | AF27: 1.8 | AG27: 4 | AH27: 4.8 | AI27: 5 | AK27: 76.1 | AL27: 18 | AM27: 18 | AN27: 3.3 | AO27: 18.5 | AQ27: 247.9 | AR27: 0.3 | AS27: 1.8 | AT27: 15.929 | AU27: 14.7 | AV27: 1 | AW27: 10 | AX27: 40.5 | AY27: 137.2 | AZ27: 13 | BA27: 99.5 | BB27: 0.6 | BC27: 17.8 | BD27: 10.7 | BE27: 30.9 | BF27: 5.1 | BG27: 4.4 | BH27: 3 | BI27: 1.2 | BK27: 15.5 | BL27: 0.3 | BM27: 19.6 | BN27: 7.2 | BO27: 17.1 | BP27: 5.1 | BQ27: 1173.759
B28: 10:30 | C28: 14 | D28: 18.3 | E28: 8.5 | F28: 10.99 | G28: 18 | H28: 1.1 | J28: 9.4 | K28: 1.3 | L28: 5.9 | N28: 4.3 | O28: 6.6 | P28: 2.3 | Q28: 2.6 | R28: 4.8 | S28: 10 | T28: 14.8 | U28: 5.5 | W28: 2.2 | X28: 19.9 | Y28: 40.6 | Z28: 33.9 | AA28: 28.7 | AB28: 33.8 | AC28: 7.8 | AD28: 4.9 | AE28: 6.7 | AF28: 1.8 | AG28: 4.1 | AH28: 4.7 | AI28: 4.9 | AK28: 76.5 | AL28: 18 | AM28: 18.1 | AN28: 3.3 | AO28: 18.5 | AQ28: 249.1 | AR28: 0.4 | AS28: 1.8 | AT28: 17.1323 | AU28: 14.7 | AV28: 1.2 | AW28: 9.8 | AX28: 53.9 | AY28: 136.7 | AZ28: 14.3 | BA28: 99.6 | BB28: 0.6 | BC28: 17.6 | BD28: 10.7 | BE28: 30.4 | BF28: 5.1 | BG28: 4.4 | BH28: 3 | BI28: 1.2 | BK28: 16.8 | BL28: 0.3 | BM28: 19.7 | BN28: 7.2 | BO28: 17.8 | BP28: 4.9 | BQ28: 1205.1223
B29: 11:00 | C29: 13.8 | D29: 18.3 | E29: 7.9 | F29: 11.07 | G29: 18 | H29: 1 | J29: 9.5 | K29: 1.3 | L29: 5.9 | N29: 4.6 | O29: 6.8 | P29: 2.3 | Q29: 2.6 | R29: 4.9 | S29: 10 | T29: 15.3 | U29: 5.5 | V29: 3.2 | W29: 3.8 | X29: 19.4 | Y29: 41.4 | Z29: 32.1 | AA29: 23.2 | AB29: 27.2 | AC29: 4.7 | AD29: 3.5 | AE29: 6.6 | AF29: 1.8 | AG29: 4.1 | AH29: 4.7 | AI29: 4.9 | AK29: 79.8 | AL29: 18.1 | AM29: 18.1 | AN29: 3.3 | AO29: 18.5 | AQ29: 251.5 | AR29: 0.4 | AS29: 1.8 | AT29: 18.0969 | AU29: 14.6 | AV29: 1.8 | AW29: 9.9 | AX29: 73 | AY29: 137 | AZ29: 30.7 | BA29: 100 | BB29: 0.6 | BC29: 17.5 | BD29: 11.2 | BE29: 35.4 | BF29: 5.1 | BG29: 4.4 | BH29: 3 | BI29: 1.2 | BK29: 17.8 | BL29: 0.3 | BM29: 19.7 | BN29: 7.2 | BO29: 17.8 | BP29: 5.1 | BQ29: 1242.2669
B30: 11:30 | C30: 14 | D30: 18.3 | E30: 7.4 | F30: 6.36 | G30: 18 | H30: 1.1 | J30: 9.5 | K30: 1.3 | L30: 5.9 | N30: 4.4 | O30: 6.7 | P30: 2.3 | Q30: 2.6 | R30: 4.8 | S30: 10 | T30: 15.1 | U30: 5.1 | V30: 3.2 | W30: 11.7 | X30: 17.5 | Y30: 26.8 | Z30: 34 | AA30: 20.2 | AB30: 25.8 | AC30: 5.8 | AD30: 3.1 | AE30: 6.6 | AF30: 1.8 | AG30: 4.1 | AH30: 4.7 | AI30: 4.9 | AK30: 80.6 | AL30: 18.1 | AM30: 18.1 | AN30: 3.2 | AO30: 18.5 | AQ30: 253.2 | AR30: 0.4 | AS30: 1.8 | AT30: 18.6494 | AU30: 14.7 | AV30: 0.8 | AW30: 10 | AX30: 98.2 | AY30: 137.1 | AZ30: 51.6 | BA30: 100 | BB30: 0.6 | BC30: 17.6 | BD30: 11.9 | BE30: 30.6 | BF30: 5.1 | BG30: 4.4 | BH30: 3 | BI30: 1.2 | BK30: 18.2 | BL30: 0.3 | BM30: 19.8 | BN30: 7.2 | BO30: 17.6 | BP30: 5.1 | BQ30: 1270.6094
B31: 12:00 | C31: 14.1 | D31: 18.3 | E31: 7.4 | F31: 7.39 | G31: 18 | H31: 1 | J31: 9.5 | K31: 1.3 | L31: 5.9 | N31: 4.5 | O31: 6.5 | P31: 2.3 | Q31: 2.6 | R31: 4.8 | S31: 10 | T31: 15.1 | U31: 5.1 | V31: 3.2 | W31: 14.2 | X31: 22.5 | Y31: 15.6 | Z31: 33.8 | AA31: 27.3 | AB31: 34 | AC31: 5.8 | AD31: 3.4 | AE31: 4.3 | AF31: 1.3 | AG31: 4.1 | AH31: 4.7 | AI31: 4.9 | AK31: 80.7 | AL31: 18.1 | AM31: 17.9 | AN31: 3.2 | AO31: 18.5 | AQ31: 252.9 | AR31: 0.4 | AS31: 1.8 | AT31: 18.9122 | AU31: 14.8 | AV31: 2.8 | AW31: 10 | AX31: 114.1 | AY31: 137.9 | AZ31: 86.7 | BA31: 100.5 | BB31: 0.6 | BC31: 17.6 | BD31: 7.3 | BE31: 25.7 | BF31: 5.2 | BG31: 4.4 | BH31: 3 | BI31: 1.2 | BK31: 18.4 | BL31: 0.3 | BM31: 19.7 | BN31: 7.2 | BO31: 17.9 | BP31: 5.1 | BQ31: 1325.7022
B32: 12:30 | C32: 13.8 | D32: 18.3 | E32: 8.2 | F32: 6.69 | G32: 18 | H32: 1 | J32: 9.1 | K32: 1.3 | L32: 5.9 | N32: 4.6 | O32: 6.5 | P32: 2.3 | Q32: 2.6 | R32: 4.8 | S32: 10 | T32: 15 | U32: 5.1 | V32: 3.2 | W32: 15.3 | X32: 28.4 | Y32: 16.2 | Z32: 33.5 | AA32: 42.1 | AB32: 49.6 | AC32: 7.9 | AD32: 5.8 | AG32: 4.2 | AH32: 4.7 | AI32: 4.9 | AK32: 80.6 | AL32: 18.1 | AM32: 17.7 | AN32: 3.2 | AO32: 18.5 | AQ32: 253.1 | AR32: 0.4 | AS32: 1.8 | AU32: 15.1 | AV32: 2.5 | AW32: 9.9 | AX32: 98.2 | AY32: 138.1 | AZ32: 97.6 | BA32: 100.6 | BB32: 0.6 | BC32: 17.8 | BD32: 6.3 | BE32: 27.8 | BF32: 5.1 | BG32: 4.4 | BH32: 3 | BI32: 1.2 | BK32: 18.4 | BL32: 0.3 | BM32: 19.3 | BN32: 7.2 | BO32: 17.8 | BP32: 5.1 | BQ32: 1338.69
B33: 13:00 | C33: 13.9 | D33: 18.3 | E33: 8.7 | F33: 8.54 | G33: 14.5 | H33: 1 | J33: 9.1 | K33: 1.2 | L33: 5.9 | N33: 4.6 | O33: 6.5 | P33: 2.3 | Q33: 2.4 | R33: 4.8 | S33: 10 | T33: 15.3 | U33: 5.1 | V33: 3.2 | W33: 18 | X33: 29.4 | Y33: 27.6 | Z33: 33.6 | AA33: 49.1 | AB33: 62.9 | AC33: 8.2 | AD33: 7.2 | AG33: 4.2 | AH33: 4.7 | AI33: 4.9 | AK33: 80.6 | AL33: 17.9 | AM33: 18.1 | AN33: 3.2 | AO33: 18.5 | AQ33: 252.9 | AR33: 0.4 | AS33: 1.8 | AT33: 17.9632 | AU33: 15 | AV33: 1.6 | AW33: 9.9 | AX33: 95.6 | AY33: 140.2 | AZ33: 81.5 | BA33: 100.5 | BB33: 0.6 | BC33: 17.7 | BD33: 6.6 | BE33: 26 | BF33: 5.1 | BG33: 4.4 | BH33: 3 | BI33: 1.2 | BK33: 18.4 | BL33: 0.3 | BM33: 19.1 | BN33: 7.1 | BO33: 17.5 | BP33: 5.1 | BQ33: 1372.9032
B34: 13:30 | C34: 13.9 | D34: 18.3 | E34: 8.3 | F34: 6.2 | G34: 9.3 | H34: 1 | J34: 9.2 | K34: 1.2 | L34: 5.8 | N34: 4.5 | O34: 6.2 | P34: 2.3 | Q34: 2.3 | R34: 4.8 | S34: 10 | T34: 15.1 | U34: 4.9 | V34: 3.2 | W34: 17.4 | X34: 30.2 | Y34: 34.7 | Z34: 33.6 | AA34: 54.4 | AB34: 72.2 | AC34: 10.2 | AD34: 7.2 | AG34: 4.2 | AH34: 4.7 | AI34: 4.9 | AK34: 80.7 | AL34: 18.1 | AM34: 18 | AN34: 3.2 | AO34: 18.5 | AQ34: 252.8 | AR34: 0.4 | AS34: 1.8 | AT34: 17.0589 | AU34: 14.9 | AV34: 0.8 | AW34: 9.9 | AX34: 80.1 | AY34: 141.2 | AZ34: 50.9 | BA34: 100.7 | BB34: 0.6 | BC34: 17.5 | BD34: 5.5 | BE34: 28.7 | BF34: 5.1 | BG34: 4.4 | BH34: 3 | BI34: 1.2 | BK34: 17.4 | BM34: 19.3 | BN34: 7.2 | BO34: 17.5 | BP34: 5.1 | BQ34: 1341.7589
B35: 14:00 | C35: 13.9 | D35: 18.3 | E35: 8.9 | F35: 10.95 | G35: 9.5 | H35: 1 | J35: 9.4 | K35: 1.1 | L35: 5.6 | N35: 4.5 | O35: 6.2 | P35: 2.3 | Q35: 2.6 | R35: 4.9 | S35: 10 | T35: 14.2 | U35: 4.9 | V35: 3.2 | W35: 18.5 | X35: 36.7 | Y35: 31.2 | Z35: 33.9 | AA35: 54.5 | AB35: 63.7 | AC35: 10.5 | AD35: 6 | AG35: 4.2 | AH35: 4.7 | AI35: 4.9 | AK35: 80.6 | AL35: 17.8 | AM35: 17.8 | AN35: 3.2 | AO35: 18.5 | AQ35: 253 | AR35: 0.4 | AS35: 1.8 | AT35: 16.042 | AU35: 14.9 | AV35: 1.1 | AW35: 9.9 | AX35: 72.2 | AY35: 139.8 | AZ35: 51.1 | BA35: 100.7 | BB35: 0.6 | BC35: 17.5 | BD35: 7.3 | BE35: 31.2 | BF35: 5.1 | BG35: 4.4 | BH35: 3 | BI35: 1.2 | BK35: 16.2 | BM35: 19.5 | BN35: 7.1 | BO35: 17.1 | BP35: 4.9 | BQ35: 1334.192
B36: 14:30 | C36: 14 | D36: 17.4 | E36: 8.2 | F36: 10.89 | G36: 9.5 | H36: 1 | J36: 9.1 | K36: 0.9 | L36: 5.5 | N36: 4.6 | O36: 6.3 | P36: 2.3 | Q36: 2.6 | R36: 4.8 | S36: 10 | T36: 15 | U36: 4.9 | V36: 3.2 | W36: 23.8 | X36: 53.6 | Y36: 32.5 | Z36: 34 | AA36: 47.8 | AB36: 61.3 | AC36: 8.2 | AD36: 5.5 | AG36: 4.2 | AH36: 4.7 | AI36: 4.9 | AK36: 79.6 | AL36: 17.4 | AM36: 16.2 | AN36: 3.2 | AO36: 18.5 | AQ36: 253.1 | AR36: 0.4 | AS36: 1.8 | AT36: 14.2907 | AU36: 14.9 | AV36: 1 | AW36: 10 | AX36: 81.7 | AY36: 139.4 | AZ36: 56.6 | BA36: 100.1 | BB36: 0.6 | BC36: 17.5 | BD36: 9.7 | BE36: 31.9 | BF36: 5 | BG36: 4.3 | BH36: 3 | BI36: 1.2 | BK36: 14.8 | BM36: 19.3 | BN36: 7.2 | BO36: 16.8 | BP36: 5.1 | BQ36: 1355.2807
B37: 15:00 | C37: 14 | D37: 17.2 | E37: 8.4 | F37: 10.86 | G37: 9.5 | H37: 1 | J37: 8.8 | K37: 0.8 | L37: 5.6 | N37: 4.7 | O37: 6.2 | P37: 2.3 | Q37: 2.6 | R37: 4.8 | S37: 10 | T37: 14.9 | U37: 4.9 | V37: 3.2 | W37: 27.6 | X37: 53.6 | Y37: 33.5 | Z37: 33.8 | AA37: 46.4 | AB37: 47.6 | AC37: 7.9 | AD37: 5.2 | AG37: 4.2 | AH37: 4.7 | AI37: 4.9 | AK37: 79.2 | AL37: 17.3 | AM37: 17.1 | AN37: 3.2 | AO37: 18.5 | AQ37: 252.9 | AR37: 0.3 | AS37: 1.8 | AT37: 12.2846 | AU37: 14.8 | AV37: 1.1 | AW37: 10 | AX37: 84.3 | AY37: 138.1 | AZ37: 61.6 | BA37: 97.8 | BB37: 0.6 | BC37: 17.4 | BD37: 8.4 | BE37: 35.9 | BF37: 4.9 | BG37: 4.1 | BH37: 2.8 | BI37: 1.2 | BK37: 13.1 | BL37: 0.2 | BM37: 19.2 | BN37: 7.2 | BO37: 16.3 | BP37: 5 | BQ37: 1345.7446
B38: 15:30 | C38: 13.9 | D38: 18.3 | E38: 7.7 | F38: 9.97 | G38: 9.5 | H38: 1.1 | J38: 9.1 | K38: 0.6 | L38: 5.7 | N38: 4.8 | O38: 6.3 | P38: 2.3 | Q38: 2.6 | R38: 4.7 | S38: 10 | T38: 15.1 | U38: 4.7 | V38: 3.2 | W38: 27.1 | X38: 61.7 | Y38: 25.1 | Z38: 32.8 | AA38: 40.4 | AB38: 44.8 | AC38: 9.6 | AD38: 3 | AG38: 4.2 | AH38: 4.7 | AI38: 4.9 | AK38: 76.8 | AL38: 17.8 | AM38: 16.7 | AN38: 3.2 | AO38: 18.5 | AQ38: 246.3 | AR38: 0.3 | AS38: 1.8 | AT38: 10.1138 | AU38: 14.1 | AV38: 1.1 | AW38: 9.9 | AX38: 94.6 | AY38: 136 | AZ38: 74.5 | BA38: 96 | BB38: 0.6 | BC38: 16.7 | BD38: 8.6 | BE38: 36.5 | BF38: 4.9 | BG38: 4.4 | BH38: 2.8 | BI38: 1.2 | BK38: 11 | BL38: 0.3 | BM38: 19.2 | BN38: 7.2 | BO38: 14.9 | BP38: 5.1 | BQ38: 1338.9838
B39: 16:00 | C39: 13.7 | D39: 18.3 | E39: 8 | F39: 10.83 | G39: 9.5 | H39: 1.2 | J39: 9.4 | K39: 0.4 | L39: 5.5 | N39: 4.7 | O39: 6.2 | P39: 2.3 | Q39: 2.6 | R39: 4.7 | S39: 10 | T39: 14.8 | U39: 4.4 | V39: 3.2 | W39: 28.7 | X39: 68.1 | Y39: 25.4 | Z39: 27.8 | AA39: 49.7 | AB39: 58.8 | AC39: 7.1 | AD39: 4.2 | AG39: 4.2 | AH39: 4.7 | AI39: 4.9 | AK39: 70 | AL39: 18.1 | AM39: 18 | AN39: 3.2 | AO39: 18.5 | AQ39: 232.1 | AR39: 0.2 | AS39: 1.8 | AT39: 7.5276 | AU39: 12.9 | AV39: 1 | AW39: 9.9 | AX39: 126.6 | AY39: 120.8 | AZ39: 116.5 | BA39: 90.7 | BB39: 0.6 | BC39: 15 | BD39: 9 | BE39: 37.8 | BF39: 4.9 | BG39: 4.3 | BH39: 2.8 | BI39: 1.2 | BK39: 8.5 | BL39: 0.3 | BM39: 19 | BN39: 7.2 | BO39: 11.1 | BP39: 5 | BQ39: 1387.8576
B40: 16:30 | C40: 13.5 | D40: 18.3 | E40: 7.5 | F40: 10.89 | G40: 9.5 | H40: 1.3 | J40: 9.3 | L40: 5.4 | N40: 4.7 | O40: 6.3 | P40: 2.3 | Q40: 2.6 | R40: 4.8 | S40: 10 | T40: 15 | U40: 4.3 | V40: 3.2 | W40: 29.5 | X40: 72.9 | Y40: 30.5 | Z40: 17.8 | AA40: 62.2 | AB40: 65.8 | AC40: 9.8 | AD40: 7 | AE40: 1.6 | AF40: 0.4 | AG40: 4.2 | AH40: 4.7 | AI40: 4.9 | AK40: 42.5 | AL40: 16.4 | AM40: 17.5 | AN40: 3.3 | AO40: 18.5 | AQ40: 171.4 | AR40: 0.2 | AS40: 1.8 | AT40: 4.7414 | AU40: 7.2 | AV40: 1.1 | AW40: 9.9 | AX40: 142.9 | AY40: 76.8 | AZ40: 122.9 | BA40: 68.4 | BB40: 0.6 | BC40: 9.5 | BD40: 9.3 | BE40: 38.7 | BF40: 4.9 | BG40: 4.4 | BH40: 2.8 | BI40: 1.2 | BJ40: 0.1 | BK40: 5.7 | BL40: 0.3 | BM40: 19.1 | BN40: 7.2 | BO40: 3.6 | BP40: 5.1 | BQ40: 1258.2314
B41: 17:00 | C41: 13.9 | D41: 18.3 | E41: 7.4 | F41: 10.99 | G41: 9.5 | H41: 1.4 | J41: 8.7 | L41: 5.7 | N41: 4.6 | O41: 6.2 | P41: 2.3 | Q41: 2.6 | R41: 4.9 | S41: 10 | T41: 14.9 | U41: 4.3 | V41: 3.1 | W41: 29 | X41: 71.8 | Y41: 34.8 | Z41: 7.2 | AA41: 48.9 | AB41: 57.2 | AC41: 9.7 | AD41: 6.7 | AE41: 6 | AF41: 1.6 | AG41: 4.2 | AH41: 4.7 | AI41: 4.9 | AK41: 16.3 | AL41: 16.4 | AM41: 17.2 | AN41: 3.3 | AO41: 18.5 | AQ41: 71.3 | AR41: 0.1 | AS41: 1.8 | AT41: 2.0537 | AU41: 1.9 | AV41: 1 | AW41: 9.9 | AX41: 147.3 | AY41: 30.2 | AZ41: 129.5 | BA41: 28.7 | BB41: 0.6 | BC41: 2.1 | BD41: 9.7 | BE41: 39.6 | BF41: 4.9 | BG41: 4.4 | BH41: 2.8 | BI41: 1.2 | BJ41: 1.2 | BK41: 2.9 | BL41: 0.3 | BM41: 19.1 | BN41: 7.2 | BO41: 0.1 | BP41: 5.1 | BQ41: 1012.1437
B42: 17:30 | C42: 13.9 | D42: 18.3 | E42: 9.2 | F42: 10.82 | G42: 9.5 | H42: 1.4 | J42: 8.5 | L42: 5.7 | N42: 4.6 | O42: 6.2 | P42: 2.3 | Q42: 2 | R42: 4.8 | S42: 10 | T42: 14.8 | U42: 4.3 | V42: 3.1 | W42: 29.5 | X42: 72 | Y42: 41.6 | Z42: 0.4 | AA42: 45.9 | AB42: 52.8 | AC42: 4.5 | AD42: 4.7 | AE42: 6 | AF42: 1.7 | AG42: 4.2 | AH42: 4.5 | AI42: 4.7 | AK42: 1.2 | AL42: 15.9 | AM42: 16.6 | AN42: 3.3 | AO42: 18.5 | AQ42: 7.4 | AR42: 0.1 | AS42: 1.8 | AT42: 0.2069 | AV42: 1.1 | AW42: 9.9 | AX42: 142.6 | AY42: 1.4 | AZ42: 129.8 | BA42: 2.1 | BB42: 0.6 | BD42: 10.2 | BE42: 40.5 | BF42: 4.9 | BG42: 4.4 | BH42: 3 | BI42: 1.2 | BJ42: 1.2 | BK42: 0.6 | BL42: 0.3 | BM42: 19.1 | BN42: 7.2 | BP42: 5 | BQ42: 852.0269
B43: 18:00 | C43: 13.5 | D43: 18.3 | E43: 7.7 | F43: 10.59 | G43: 17.2 | H43: 1.6 | J43: 9.4 | L43: 5.8 | N43: 4.6 | O43: 6.3 | P43: 2.3 | Q43: 2.6 | R43: 4.8 | S43: 10 | T43: 15 | U43: 4.3 | V43: 3.1 | W43: 29.5 | X43: 76 | Y43: 42.3 | AA43: 57.3 | AB43: 67 | AC43: 9.8 | AD43: 8.6 | AE43: 6 | AF43: 1.7 | AG43: 4.2 | AH43: 4.5 | AI43: 4.7 | AL43: 17 | AM43: 18 | AN43: 3.3 | AO43: 18.5 | AS43: 1.8 | AT43: 0.1225 | AV43: 1.1 | AW43: 9.9 | AX43: 123.7 | AZ43: 124.5 | BB43: 0.6 | BD43: 10.7 | BE43: 41.4 | BF43: 4.9 | BG43: 4.4 | BH43: 3 | BI43: 1.2 | BJ43: 1.2 | BL43: 0.3 | BM43: 19 | BN43: 7.2 | BP43: 5 | BQ43: 865.5125
B44: 18:30 | C44: 13.5 | D44: 18.3 | E44: 8.8 | F44: 11.03 | G44: 20.2 | H44: 1.6 | J44: 10.2 | L44: 5.8 | N44: 4.7 | O44: 6.3 | P44: 2.3 | Q44: 2.6 | R44: 4.8 | S44: 10 | T44: 14.4 | U44: 4.3 | V44: 3.1 | W44: 29.5 | X44: 67.2 | Y44: 32.7 | AA44: 56.3 | AB44: 76.1 | AC44: 6.3 | AD44: 4.7 | AE44: 6 | AF44: 1.7 | AG44: 4.2 | AH44: 4.5 | AI44: 4.7 | AL44: 17.4 | AM44: 18.1 | AN44: 3.3 | AO44: 18.5 | AS44: 1.8 | AT44: 0.0802 | AV44: 1.1 | AW44: 9.9 | AX44: 109.4 | AZ44: 119.5 | BB44: 0.6 | BD44: 11.1 | BE44: 42.2 | BF44: 4.9 | BG44: 4.4 | BH44: 3 | BI44: 1.2 | BJ44: 1.2 | BL44: 55.2 | BM44: 18.7 | BN44: 7.2 | BP44: 5.1 | BQ44: 889.7102
B45: 19:00 | C45: 13.5 | D45: 17.2 | E45: 9 | F45: 10.85 | G45: 20.2 | H45: 1.6 | J45: 9.6 | L45: 5.8 | N45: 4.6 | O45: 6.3 | P45: 2.3 | Q45: 1.8 | R45: 4.6 | S45: 10 | T45: 14.8 | U45: 4.1 | V45: 3.1 | W45: 28.5 | X45: 61.1 | Y45: 36.7 | AA45: 54.7 | AB45: 72.8 | AC45: 10.5 | AD45: 6.8 | AE45: 6.1 | AF45: 1.7 | AG45: 4.2 | AH45: 4.5 | AI45: 4.7 | AL45: 17.1 | AM45: 18.1 | AN45: 3.3 | AO45: 18.5 | AS45: 1.8 | AT45: 0.0788 | AV45: 1.1 | AW45: 9.9 | AX45: 91.7 | AZ45: 107.1 | BB45: 0.6 | BD45: 11.4 | BE45: 42.5 | BF45: 4.8 | BG45: 4.4 | BH45: 3 | BI45: 1.2 | BJ45: 1.2 | BL45: 55 | BM45: 17.9 | BN45: 7.2 | BP45: 5.1 | BQ45: 854.6288
B46: 19:30 | C46: 13.5 | D46: 18.3 | E46: 7.6 | F46: 11.05 | G46: 20.2 | H46: 1.6 | J46: 10.2 | L46: 5.3 | N46: 4.5 | O46: 6.3 | P46: 2.3 | Q46: 1.4 | R46: 4.6 | S46: 10 | T46: 15 | U46: 4.1 | V46: 3.1 | W46: 27.6 | X46: 56.6 | Y46: 33.8 | AA46: 54.3 | AB46: 68.3 | AC46: 6 | AD46: 5.4 | AE46: 6.2 | AF46: 1.8 | AG46: 4.2 | AH46: 4.5 | AI46: 4.7 | AL46: 17.9 | AM46: 18.1 | AN46: 3.3 | AO46: 18.5 | AS46: 1.8 | AT46: 0.0785 | AV46: 1 | AW46: 9.9 | AX46: 100 | AZ46: 102.7 | BB46: 0.6 | BD46: 11.6 | BE46: 42.2 | BF46: 4.8 | BG46: 4.4 | BH46: 3 | BI46: 1.2 | BJ46: 1.2 | BL46: 54.9 | BM46: 18.3 | BN46: 7.2 | BP46: 5.2 | BQ46: 840.3285
B47: 20:00 | C47: 13.7 | D47: 18.3 | E47: 8.6 | F47: 11 | G47: 20.2 | H47: 1.6 | J47: 10.1 | L47: 5.3 | N47: 4.6 | O47: 6.3 | P47: 2.3 | Q47: 1.8 | R47: 4.6 | S47: 10 | T47: 14.7 | U47: 4.1 | V47: 3.1 | W47: 27.8 | X47: 58.5 | Y47: 30.3 | AA47: 52.4 | AB47: 73.3 | AC47: 7.1 | AD47: 4.2 | AE47: 6.2 | AF47: 1.8 | AG47: 4.2 | AH47: 4.2 | AI47: 4.4 | AL47: 17.3 | AM47: 18.1 | AN47: 3.3 | AO47: 18.5 | AS47: 1.8 | AV47: 1.1 | AW47: 9.9 | AX47: 108.6 | AZ47: 109.3 | BB47: 0.6 | BD47: 11.6 | BE47: 41.8 | BF47: 4.9 | BG47: 4.4 | BH47: 3 | BI47: 1.2 | BJ47: 1.2 | BL47: 54.8 | BM47: 18.7 | BN47: 7.2 | BP47: 5.1 | BQ47: 857.1
B48: 20:30 | C48: 13.9 | D48: 18.3 | E48: 9.4 | F48: 10.96 | G48: 20.2 | H48: 1.6 | J48: 10.3 | L48: 4.9 | N48: 4.5 | O48: 6.3 | P48: 2.3 | Q48: 2.6 | R48: 4.5 | S48: 10 | T48: 14.9 | U48: 4.1 | V48: 3.1 | W48: 25 | X48: 46.2 | Y48: 36 | AA48: 58.2 | AB48: 72.2 | AC48: 5.6 | AD48: 5.5 | AE48: 6.1 | AF48: 1.8 | AG48: 4.2 | AH48: 4.2 | AI48: 4.4 | AL48: 17.6 | AM48: 18 | AN48: 3.3 | AO48: 18.5 | AS48: 1.8 | AV48: 1.1 | AW48: 9.9 | AX48: 121.4 | AZ48: 116.4 | BB48: 0.6 | BD48: 11.6 | BE48: 41.1 | BF48: 4.8 | BG48: 4.4 | BH48: 3 | BI48: 1.2 | BJ48: 1.2 | BL48: 54.7 | BM48: 18.8 | BN48: 7.2 | BP48: 5.2 | BQ48: 873.06
B49: 21:00 | C49: 13.5 | D49: 18.3 | E49: 9 | F49: 10.98 | G49: 20.2 | H49: 1.6 | J49: 9.9 | L49: 4.8 | N49: 4.5 | O49: 6.3 | P49: 2.6 | Q49: 2.6 | R49: 4.4 | S49: 10 | T49: 14.9 | U49: 4.1 | V49: 3.1 | W49: 21.5 | X49: 41.9 | Y49: 38.7 | AA49: 68.3 | AB49: 84.5 | AC49: 6.9 | AD49: 9.3 | AE49: 5.8 | AF49: 1.8 | AG49: 4.2 | AH49: 4.2 | AI49: 4.4 | AL49: 16.8 | AM49: 18.1 | AN49: 3.3 | AO49: 18.5 | AS49: 1.8 | AV49: 1.1 | AW49: 9.9 | AX49: 104.9 | AZ49: 109.2 | BB49: 0.6 | BD49: 11.4 | BE49: 39.7 | BF49: 4.8 | BG49: 4.4 | BH49: 3 | BI49: 1.2 | BJ49: 1.2 | BL49: 54.9 | BM49: 18.9 | BN49: 7.2 | BP49: 5.2 | BQ49: 868.38
B50: 21:30 | C50: 13.7 | D50: 18.3 | E50: 8.5 | F50: 10.98 | G50: 20.1 | H50: 1.6 | J50: 9.3 | L50: 4.8 | N50: 4.5 | O50: 6.2 | P50: 2.8 | Q50: 2.6 | R50: 4.4 | S50: 10 | T50: 14.6 | U50: 4.1 | V50: 3.1 | W50: 21.8 | X50: 36.5 | Y50: 31.2 | AA50: 66.7 | AB50: 81 | AC50: 8.1 | AD50: 6.7 | AE50: 5.8 | AF50: 1.8 | AG50: 4 | AH50: 4.5 | AI50: 4.4 | AL50: 16.5 | AM50: 18.1 | AN50: 3.3 | AO50: 18.5 | AS50: 1.8 | AV50: 1 | AW50: 9.8 | AX50: 98.5 | AZ50: 97.8 | BB50: 0.6 | BD50: 10.9 | BE50: 37.7 | BF50: 4.8 | BG50: 4.4 | BH50: 3 | BI50: 1.2 | BJ50: 1.2 | BL50: 0.3 | BM50: 18.9 | BN50: 7.2 | BP50: 5.1 | BQ50: 772.68
B51: 22:00 | C51: 14 | D51: 18 | E51: 7.9 | F51: 10.99 | G51: 20.1 | H51: 1.6 | J51: 9.4 | L51: 4.8 | N51: 4.5 | O51: 6.2 | P51: 2.9 | Q51: 2.6 | R51: 4.6 | S51: 10 | T51: 14.5 | U51: 4.1 | V51: 3.1 | W51: 25 | X51: 21.5 | Y51: 24.8 | AA51: 54.8 | AB51: 67 | AC51: 9.1 | AD51: 5.5 | AE51: 5.8 | AF51: 1.8 | AG51: 4 | AH51: 4.5 | AI51: 4.4 | AL51: 15.3 | AM51: 17.2 | AN51: 3.3 | AO51: 18.5 | AS51: 1.8 | AV51: 1.1 | AW51: 9.9 | AX51: 73.9 | AZ51: 73.3 | BB51: 0.6 | BD51: 10.4 | BE51: 35.8 | BF51: 4.8 | BG51: 4.4 | BH51: 3 | BI51: 1.2 | BJ51: 1.2 | BL51: 0.3 | BM51: 18.8 | BN51: 7.2 | BP51: 5.1 | BQ51: 674.59
B52: 22:30 | C52: 14 | D52: 18.3 | E52: 6.6 | F52: 10.97 | G52: 20.1 | H52: 1.5 | J52: 9.7 | L52: 4.8 | N52: 4.2 | O52: 6.2 | P52: 3 | Q52: 2.4 | R52: 4.8 | S52: 10 | T52: 14.3 | U52: 4.1 | V52: 3.1 | W52: 25.7 | X52: 18.7 | Y52: 24.9 | AA52: 43.2 | AB52: 63.5 | AC52: 7.6 | AD52: 3.1 | AE52: 5.8 | AF52: 1.8 | AG52: 4 | AH52: 4.5 | AI52: 4.4 | AL52: 14.8 | AM52: 17.3 | AN52: 3.3 | AO52: 18.5 | AS52: 1.8 | AV52: 1.1 | AW52: 9.9 | AX52: 71.7 | AZ52: 64.8 | BB52: 0.6 | BD52: 9.9 | BE52: 33.9 | BF52: 4.8 | BG52: 4.4 | BH52: 3 | BI52: 1.2 | BJ52: 1.2 | BL52: 0.3 | BM52: 18.5 | BN52: 7.1 | BP52: 5 | BQ52: 638.37
B53: 23:00 | C53: 14 | D53: 18.3 | E53: 8.8 | F53: 10.66 | G53: 20.1 | H53: 1.5 | J53: 9.7 | L53: 4.9 | N53: 4 | O53: 6.1 | P53: 3.2 | Q53: 2.4 | R53: 4.7 | S53: 10 | T53: 14.5 | U53: 4.1 | V53: 3.1 | W53: 25.1 | X53: 21.2 | Y53: 27.3 | AA53: 49.8 | AB53: 63.6 | AC53: 5.1 | AD53: 6.5 | AE53: 5.8 | AF53: 1.8 | AG53: 4 | AH53: 4.5 | AI53: 4.7 | AL53: 13.2 | AM53: 16 | AN53: 3.4 | AO53: 18.5 | AS53: 1.8 | AV53: 1.1 | AW53: 9.9 | AX53: 59.2 | AZ53: 56.7 | BB53: 0.6 | BD53: 9.2 | BE53: 31.3 | BF53: 4.8 | BG53: 4.4 | BH53: 3 | BI53: 1.2 | BJ53: 1.2 | BL53: 0.3 | BM53: 18.5 | BN53: 7.2 | BP53: 5.1 | BQ53: 626.06
B54: 23:30 | C54: 13.7 | D54: 18.3 | E54: 7.8 | F54: 10.97 | G54: 20.1 | H54: 1.4 | J54: 9.2 | L54: 4.9 | N54: 4.3 | O54: 6.3 | P54: 3.2 | Q54: 2.4 | R54: 4.6 | S54: 10 | T54: 14.5 | U54: 4.1 | V54: 3.1 | W54: 23.4 | X54: 20.9 | Y54: 28.6 | AA54: 44.7 | AB54: 54.8 | AC54: 4.5 | AD54: 2.9 | AE54: 5.8 | AF54: 1.8 | AG54: 4 | AH54: 4.5 | AI54: 4.7 | AL54: 12.8 | AM54: 15.9 | AN54: 3.4 | AO54: 18.5 | AS54: 1.8 | AV54: 1.1 | AW54: 9.9 | AX54: 36.6 | AZ54: 32.4 | BB54: 0.6 | BD54: 8.4 | BE54: 28 | BF54: 4.8 | BG54: 4.4 | BH54: 3 | BI54: 1.2 | BJ54: 1.2 | BL54: 0.3 | BM54: 18.7 | BN54: 7.2 | BP54: 5.1 | BQ54: 554.77
B55: 0:00 | C55: 13.2 | D55: 18.3 | E55: 7 | F55: 11.03 | G55: 20.1 | H55: 1.4 | J55: 9.7 | L55: 4.9 | N55: 4.2 | O55: 6.3 | P55: 3.1 | Q55: 2.6 | R55: 4.6 | S55: 10 | T55: 14.8 | U55: 4.1 | V55: 3.1 | W55: 22.8 | X55: 16.3 | Y55: 22 | AA55: 47.2 | AB55: 51.9 | AC55: 6.3 | AD55: 2.3 | AE55: 5.8 | AF55: 1.8 | AG55: 4 | AH55: 4.5 | AI55: 4.7 | AL55: 12.8 | AM55: 16.5 | AN55: 3.3 | AO55: 18.5 | AS55: 1.8 | AV55: 1 | AW55: 9.9 | AX55: 36.5 | AZ55: 26.4 | BB55: 0.6 | BD55: 7.7 | BE55: 25.2 | BF55: 4.9 | BG55: 4.4 | BH55: 3 | BI55: 1.2 | BJ55: 1.2 | BL55: 0.3 | BM55: 19 | BN55: 7.2 | BP55: 5.2 | BQ55: 534.63
B56: EJEC MWh | C56: 332.05 | D56: 437.5 | E56: 196.25 | F56: 250.465 | G56: 325.3 | H56: 30.2 | I56: 0 | J56: 224 | K56: 9.1 | L56: 132.85 | M56: 0 | N56: 111.75 | O56: 159.55 | P56: 63.05 | Q56: 57.9 | R56: 112.7 | S56: 240.6 | T56: 362.6 | U56: 109.2 | V56: 64.15 | W56: 468.45 | X56: 678.8 | Y56: 685 | Z56: 318.6 | AA56: 847.55 | AB56: 1106.75 | AC56: 126.85 | AD56: 93.75 | AE56: 131.55 | AF56: 34.75 | AG56: 101.05 | AH56: 112.6 | AI56: 117.1 | AJ56: 0 | AK56: 745.9 | AL56: 392.85 | AM56: 415.35 | AN56: 78.6 | AO56: 444 | AP56: 0 | AQ56: 2404.85 | AR56: 3 | AS56: 43.2 | AT56: 125.42555 | AU56: 145.8 | AV56: 21.5 | AW56: 181.6 | AX56: 1545.65 | AY56: 1317.85 | AZ56: 1319.9 | BA56: 968.6 | BB56: 14.4 | BC56: 174.45 | BD56: 186.8 | BE56: 661.55 | BF56: 119.25 | BG56: 104.45 | BH56: 70.9 | BI56: 27.7 | BJ56: 18.65 | BK56: 134.2 | BL56: 170.55 | BM56: 460.7 | BN56: 172.15 | BO56: 128.7 | BP56: 122.2 | BQ56: 20762.741
L70: TERMOELÉCTRICA | M70: 1661.965 | N70: 8.0045551 | O70: #FFA975
L71: HIDROELÉCTRICA | M71: 4095.05 | N71: 19.723071 | O71: #98D2FF
L72: SOLAR | M72: 6476.4756 | N72: 31.192778 | O72: #FFD272
L73: EÓLICA | M73: 8529.25 | N73: 41.079596 | O73: #B9ACFF

Sheet COGENERACIÓN
B3: jueves, 28 de Agosto del 2025
B5: CENTRALES DE COGENERACIÓN DEL SEIN
B6: HORA | C6: AGRO INDUSTRIAL PARAMONGA S.A. | D6: AGROAURORA S.A.C. | E6: AGROINDUSTRIAS SAN JACINTO S.A.A. | F6: AGROLMOS SOCIEDAD ANONIMA - AGROLMOS S.A. | G6: BIOENERGIA DEL CHIRA S.A. | H6: GM OPERACIONES S.A.C. | I6: TOTAL COGENERACION
C7: C.T. PARAMONGA | D7: C.T. MAPLE | E7: C.T SAN JACINTO | F7: C.T. AGROLMOS | G7: C.T. CAÑA BRAVA | H7: C.T. REFINERÍA TALARA | I7: MW
B8: 0:30 | C8: 14.5 | D8: 18.3 | E8: 9.1 | F8: 11.09 | G8: 9.6 | H8: 63.2 | I8: 125.79
B9: 1:00 | C9: 14.6 | D9: 18.3 | E9: 8.6 | F9: 11.01 | G9: 9 | H9: 62.7 | I9: 124.21
B10: 1:30 | C10: 13.5 | D10: 18.3 | E10: 9.4 | F10: 10.73 | G10: 8.9 | H10: 63.1 | I10: 123.93
B11: 2:00 | C11: 13.5 | D11: 18.3 | E11: 7.9 | F11: 11.05 | G11: 9.3 | H11: 63.2 | I11: 123.25
B12: 2:30 | C12: 14 | D12: 18.3 | E12: 7.3 | F12: 11.05 | G12: 9.2 | H12: 63 | I12: 122.85
B13: 3:00 | C13: 13.7 | D13: 18.3 | E13: 8.2 | F13: 11.06 | G13: 9.5 | H13: 62.7 | I13: 123.46
B14: 3:30 | C14: 13.5 | D14: 18.3 | E14: 7.5 | F14: 11.05 | G14: 8.8 | H14: 62.9 | I14: 122.05
B15: 4:00 | C15: 13.5 | D15: 18.3 | E15: 7.2 | F15: 11.01 | G15: 7.1 | H15: 62.5 | I15: 119.61
B16: 4:30 | C16: 13.9 | D16: 18.3 | E16: 7 | F16: 11.08 | G16: 9.2 | H16: 62.8 | I16: 122.28
B17: 5:00 | C17: 14 | D17: 18.3 | E17: 7.9 | F17: 10.8 | G17: 9.3 | H17: 62.4 | I17: 122.7
B18: 5:30 | C18: 14 | D18: 18.3 | E18: 9.1 | F18: 9.95 | G18: 9.1 | H18: 63.1 | I18: 123.55
B19: 6:00 | C19: 13.9 | D19: 18.3 | E19: 9.4 | F19: 10.05 | G19: 9.2 | H19: 63 | I19: 123.85
... B56: EJEC MWh | C56: 332.05 | D56: 437.5 | E56: 196.25 | F56: 250.465 | G56: 224 | H56: 1509.15 | I56: 2949.415

Sheet EVO_PRO_ENE
B3: viernes, 1 de Agosto del 2025 - jueves, 28 de Agosto del 2025
B5: EVOLUCIÓN DE LA PRODUCCIÓN DE LA ENERGÍA DIARIA DE LOS INTEGRANTES DEL COES (MWh)
B6: EMPRESA | C6: CENTRAL | D6: UNIDAD | E6: TIPO | F6: Agosto
F7: 1 | G7: 2 | H7: 3 | I7: 4 | J7: 5 | K7: 6 | L7: 7 | M7: 8 | N7: 9 | O7: 10 | P7: 11 | Q7: 12 | R7: 13 | S7: 14 | T7: 15 | U7: 16 | V7: 17 | W7: 18 | X7: 19 | Y7: 20 | Z7: 21 | AA7: 22 | AB7: 23 | AC7: 24 | AD7: 25 | AE7: 26 | AF7: 27 | AG7: 28 | AH7: TOTAL
B8: AGRO INDUSTRIAL PARAMONGA S.A. | C8: C.T. PARAMONGA | D8: TV-01 | E8: TERMOELÉCTRICA | G8: 87 | H8: 358.3 | I8: 359.75 | J8: 358.75 | K8: 358.85 | L8: 340.25 | M8: 346.75 | N8: 341.4 | O8: 344.1 | P8: 332.4 | Q8: 329.5 | R8: 347.85 | S8: 350.95 | T8: 353.4 | U8: 347.05 | V8: 353.6 | W8: 354.25 | X8: 356.05 | Y8: 291.3 | Z8: 349.95 | AA8: 353.8 | AB8: 353.1 | AC8: 354.2 | AD8: 353.05 | AE8: 353.95 | AF8: 343.55 | AG8: 332.05 | AH8: 9105.15
B9: AGROAURORA S.A.C. | C9: C.T. MAPLE ETANOL | D9: TV | E9: TERMOELÉCTRICA | F9: 447.75 | G9: 401.6 | H9: 400.05 | I9: 376.95 | J9: 390 | K9: 381.3 | L9: 410.9 | M9: 386.52 | N9: 411.665 | O9: 411 | P9: 398.85 | Q9: 412.65 | R9: 406.25 | S9: 406.15 | T9: 337.5 | U9: 375.9 | V9: 389.4 | W9: 392.65 | X9: 388.85 | Y9: 338.35 | Z9: 392.1 | AA9: 400.05 | AB9: 422.45 | AC9: 429.15 | AD9: 439.15 | AE9: 306.65 | AF9: 418.35 | AG9: 437.5 | AH9: 11109.685
B10: AGROINDUSTRIAS SAN JACINTO S.A.A. | C10: C.T. SAN JACINTO | D10: CENTRAL | E10: TERMOELÉCTRICA | I10: 57.4 | J10: 178.1 | K10: 175.4 | L10: 175.7 | M10: 189.35 | N10: 190.2 | O10: 179.3 | P10: 175.1 | Q10: 170.61 | R10: 170.35 | S10: 170.35 | T10: 158.65 | U10: 166.25 | V10: 164.25 | W10: 152.45 | X10: 182.8 | Y10: 192.3 | Z10: 180.5 | AA10: 192.15 | AB10: 181.95 | AC10: 199.735 | AD10: 149.71 | AE10: 190.05 | AF10: 174.65 | AG10: 196.25 | AH10: 4313.555
B11: AGROLMOS SOCIEDAD ANONIMA - AGROLMOS S.A. | C11: C.T. AGROLMOS | D11: CENTRAL | E11: TERMOELÉCTRICA | U11: 155.605 | V11: 155.585 | W11: 168.675 | X11: 151.405 | Y11: 192.06 | Z11: 208.02 | AA11: 229.84 | AB11: 102.275 | AC11: 172.13 | AD11: 184.77 | AE11: 253.675 | AF11: 259.085 | AG11: 250.465 | AH11: 2483.59
B12: ANDEAN POWER S.A.C. | C12: C.H.CARHUAC | D12: CENTRAL | E12: HIDROELÉCTRICA | F12: 293.95 | G12: 315.6 | H12: 295.6 | I12: 289.4 | J12: 281.3 | K12: 289.5 | L12: 302.65 | M12: 284.7 | N12: 299.45 | O12: 264.75 | P12: 300.9 | Q12: 269.3 | R12: 273.3 | S12: 299.2 | T12: 317.6 | U12: 303.8 | V12: 76.8 | W12: 239.15 | X12: 247.6 | Y12: 266.35 | Z12: 255.15 | AA12: 333.55 | AB12: 337.3 | AC12: 297.85 | AD12: 327.7 | AE12: 335.85 | AF12: 335.05 | AG12: 325.3 | AH12: 8058.65
B13: ASOCIACIÓN SANTA LUCIA DE CHACAS | C13: C.H. HUALLIN | D13: CENTRAL | E13: HIDROELÉCTRICA | F13: 27.55 | G13: 26.3 | H13: 24.9 | I13: 25.25 | J13: 26.65 | K13: 24.25 | L13: 24 | M13: 26.75 | N13: 26.2 | O13: 26.1 | P13: 23.9 | Q13: 23.1 | R13: 23 | S13: 25.45 | T13: 22.75 | U13: 23.65 | V13: 25.5 | W13: 24.7 | X13: 26.05 | Y13: 28.4 | Z13: 33.05 | AA13: 32.4 | AB13: 29.55 | AC13: 28 | AD13: 27.35 | AE13: 26.7 | AF13: 28.05 | AG13: 30.2 | AH13: 739.75
B14: ATRIA ENERGIA S.A.C. | C14: C.H. PURMACANA | D14: CENTRAL | E14: HIDROELÉCTRICA | F14: 2.95 | G14: 4.05 | M14: 5.75 | N14: 9.6 | O14: 9.6 | P14: 3.95 | AA14: 5.55 | AB14: 9.6 | AC14: 9.6 | AD14: 3.95 | AH14: 64.6
B15: BIOENERGIA DEL CHIRA S.A. | C15: C.T. CAÑA BRAVA | D15: CENTRAL | E15: TERMOELÉCTRICA | F15: 227.75 | G15: 225 | H15: 227.15 | I15: 233.15 | J15: 245.05 | K15: 235.15 | L15: 206.3 | M15: 205.3 | N15: 226.7 | O15: 220.7 | P15: 208.9 | Q15: 213.7 | R15: 221.45 | S15: 186.45 | T15: 243.8 | U15: 218.65 | V15: 222.3 | W15: 226.15 | X15: 224.2 | Y15: 201 | Z15: 220.4 | AA15: 223.1 | AB15: 114.05 | AC15: 103.25 | AD15: 225.95 | AE15: 225 | AF15: 211.25 | AG15: 224 | AH15: 5965.85
B16: CELEPSA | C16: C.H. EL PLATANAL | D16: CENTRAL | E16: HIDROELÉCTRICA | F16: 1927.35 | G16: 2094.15 | H16: 1681.1 | I16: 2283.1 | J16: 2070.2 | K16: 1601.8 | L16: 2297.8 | M16: 2183.3 | N16: 2008.85 | O16: 1930.95 | P16: 2225.45 | Q16: 2086.05 | R16: 2034.8 | S16: 1945.65 | T16: 2117.1 | U16: 2156.6 | V16: 2252.45 | W16: 2220 | X16: 2183.5 | Y16: 2418.75 | Z16: 2457.4 | AA16: 2378.1 | AB16: 2312.1 | AC16: 2437.25 | AD16: 2484.25 | AE16: 2405.05 | AF16: 2562.45 | AG16: 2335.4856 | AH16: 61091.036
B17: CELEPSA RENOVABLES S.R.L. | C17: C.H. MARAÑON | D17: CENTRAL | E17: HIDROELÉCTRICA | F17: 339.9 | G17: 312.35 | H17: 300.45 | I17: 287.35 | J17: 277.95 | K17: 271.85 | L17: 266.1 | M17: 265.7 | N17: 265.35 | O17: 378.5 | P17: 305.15 | Q17: 287.2 | R17: 278.3 | S17: 277.9 | T17: 290.35 | U17: 294.45 | V17: 294.65 | W17: 293 | X17: 290.7 | Y17: 282.3 | Z17: 280 | AA17: 285.65 | AB17: 283.3 | AC17: 278.5 | AD17: 274.9 | AE17: 272.25 | AF17: 264.85 | AG17: 261 | AH17: 8059.95
B18: CENTRALES SANTA ROSA S.A.C. | C18: C.H. SANTA ROSA I | D18: CENTRAL | E18: HIDROELÉCTRICA | AH18: 0
B19: CENTRALES SANTA ROSA S.A.C. | C19: C.H. SANTA ROSA II | D19: CENTRAL | E19: HIDROELÉCTRICA | AH19: 0
B20: CHINANGO S.A.C. | C20: C.H. CHIMAY | D20: CENTRAL | E20: HIDROELÉCTRICA | F20: 1763.2 | G20: 1506.35 | H20: 1273.8 | I20: 1396.45 | J20: 1288.35 | K20: 1147.5 | L20: 1094.15 | M20: 1082.1 | N20: 1232.25 | O20: 1076 | P20: 1797.8 | Q20: 1344.55 | R20: 1223.6 | S20: 1442.25 | T20: 1291.95 | U20: 1166.55 | V20: 1018.9 | W20: 1249.2 | X20: 1262.45 | Y20: 1070.45 | Z20: 1012.2 | AA20: 1120.15 | AB20: 1227.75 | AC20: 1241.45 | AD20: 1543.7 | AE20: 1975 | AF20: 1834.05 | AG20: 1531.6 | AH20: 37213.75
B21: CHINANGO S.A.C. | C21: C.H. YANANGO | D21: CENTRAL | E21: HIDROELÉCTRICA | F21: 527.85 | G21: 563.25 | H21: 553.05 | I21: 519.9 | J21: 536.4 | K21: 522.5 | L21: 501.65 | M21: 486.25 | N21: 478.2 | O21: 366.25 | P21: 471.5 | Q21: 453.2 | R21: 437.2 | S21: 445.7 | T21: 457.55 | U21: 428.6 | V21: 433.85 | W21: 429.35 | X21: 434.35 | Y21: 402 | Z21: 415.95 | AA21: 408.9 | AB21: 425.65 | AC21: 432.75 | AD21: 456.15 | AE21: 295.2 | AF21: 523.75 | AG21: 456.75 | AH21: 12863.7
B22: COLCA SOLAR S.A.C. | C22: C.S. YARUCAYA | D22: CENTRAL | E22: SOLAR | F22: 8.4 | G22: 8.7 | H22: 8.95 | I22: 8.9 | J22: 9 | K22: 8.65 | L22: 8.85 | M22: 9 | N22: 8.95 | O22: 7.1 | P22: 8.85 | Q22: 8.95 | R22: 8.9 | S22: 8.85 | T22: 8.95 | U22: 8.75 | V22: 8.8 | W22: 8.85 | X22: 8.8 | Y22: 8.95 | Z22: 9.1 | AA22: 7.65 | AB22: 8.55 | AC22: 9 | AD22: 9.05 | AE22: 8.75 | AF22: 9 | AG22: 9.1 | AH22: 245.35
B23: EGASA | C23: C.H. CHARCANI III | D23: CENTRAL | E23: HIDROELÉCTRICA | F23: 164.45 | G23: 167.75 | H23: 167.7 | I23: 168.8 | J23: 168.5 | K23: 168.35 | L23: 168.7 | M23: 168.5 | N23: 165.9 | O23: 166.25 | P23: 165.65 | Q23: 165.92 | R23: 166.445 | S23: 168.45 | T23: 168.85 | U23: 168.85 | V23: 168.85 | W23: 167.5 | X23: 167.55 | Y23: 168.5 | Z23: 168.45 | AA23: 168.9 | AB23: 168.05 | AC23: 166.4105 | AD23: 166.6 | AE23: 160.5 | AF23: 155.7 | AG23: 152.305 | AH23: 4658.3805
B24: EGASA | C24: C.H. CHARCANI IV | D24: CENTRAL | E24: HIDROELÉCTRICA | F24: 297.65 | G24: 298.4 | H24: 295.1 | I24: 294.6 | J24: 295.4 | K24: 295.2 | L24: 295.75 | M24: 297.45 | N24: 297.7 | O24: 296 | P24: 291 | Q24: 294.835 | R24: 296.975 | S24: 297.25 | T24: 297 | U24: 299.35 | V24: 299.6 | W24: 298.85 | X24: 294 | Y24: 300.1 | Z24: 298.6 | AA24: 298.6 | AB24: 296.85 | AC24: 295.2 | AD24: 299.05 | AE24: 291.6 | AF24: 254.15 | AG24: 231.91 | AH24: 8198.17
B25: EGASA | C25: C.H. CHARCANI V | D25: CENTRAL | E25: HIDROELÉCTRICA | F25: 1871.5 | G25: 1875.6 | H25: 1866.35 | I25: 1855.45 | J25: 1871.45 | K25: 1848.4 | L25: 1862.4 | M25: 1873 | N25: 1870.3 | O25: 1863.5 | P25: 1863.1 | Q25: 1847.835 | R25: 1866.07 | S25: 1867.8 | T25: 1882.5 | U25: 1853.4 | V25: 1845.85 | W25: 1854.3 | X25: 1870.2 | Y25: 1886.5 | Z25: 1867.35 | AA25: 1877.95 | AB25: 1862.85 | AC25: 1861.49 | AD25: 1877.45 | AE25: 1847.75 | AF25: 1626.6 | AG25: 1496.375 | AH25: 51613.32
B26: EGASA | C26: C.H. CHARCANI VI | D26: CENTRAL | E26: HIDROELÉCTRICA | AH26: 0
B27: EGASA | C27: C.T. CHILINA DIESEL | D27: CENTRAL | E27: TERMOELÉCTRICA | U27: 4 | V27: 3.55 | Y27: 1.9 | AH27: 9.45
B28: EGASA | C28: C.T. CHILINA DIESEL | D28: TG | E28: TERMOELÉCTRICA | AH28: 0
B29: EGASA | C29: C.T. MOLLENDO DIESEL | D29: CENTRAL | E29: TERMOELÉCTRICA | T29: 20.6 | AH29: 20.6
B30: EGEJUNIN | C30: C.H. HUASAHUASI I | D30: CENTRAL | E30: HIDROELÉCTRICA | F30: 177.55 | G30: 161.3 | H30: 149.6 | I30: 141.45 | J30: 147.95 | K30: 145.4 | L30: 129.5 | M30: 116.65 | N30: 116 | O30: 140.25 | P30: 123.75 | Q30: 115.3 | R30: 110.95 | S30: 104.1 | T30: 111.95 | U30: 104.1 | V30: 103.25 | W30: 95.1 | X30: 94.95 | Y30: 88.85 | Z30: 90.95 | AA30: 90.35 | AB30: 95.15 | AC30: 106.75 | AD30: 129.65 | AE30: 178.7 | AF30: 174.95 | AG30: 132.85 | AH30: 3477.3
B31: EGEJUNIN | C31: C.H. RUNATULLO II | D31: CENTRAL | E31: HIDROELÉCTRICA | F31: 100.9 | G31: 96 | H31: 88.45 | I31: 86.4 | J31: 84.65 | K31: 90.05 | L31: 81 | M31: 79.05 | N31: 87.1 | O31: 86.15 | P31: 81.15 | Q31: 78.6 | R31: 81.85 | S31: 89.3 | T31: 97.1 | U31: 85.65 | V31: 81.35 | W31: 77.95 | X31: 81.2 | Y31: 75.6 | Z31: 73 | AA31: 76.1 | AB31: 77.95 | AC31: 89 | AD31: 110.7 | AE31: 163.85 | AF31: 146.7 | AG31: 111.75 | AH31: 2558.55
B32: EGEJUNIN | C32: C.H. RUNATULLO III | D32: CENTRAL | E32: HIDROELÉCTRICA | F32: 144.5 | G32: 135.45 | H32: 127.15 | I32: 123.6 | J32: 119.5 | K32: 129.05 | L32: 117.05 | M32: 114.4 | N32: 124.8 | O32: 123.15 | P32: 118.35 | Q32: 110.55 | R32: 114.55 | S32: 127.7 | T32: 139.85 | U32: 123.3 | V32: 115.2 | W32: 112.25 | X32: 117.4 | Y32: 107.7 | Z32: 102 | AA32: 105.15 | AB32: 116.8 | AC32: 121.9 | AD32: 150.45 | AE32: 229.25 | AF32: 204.55 | AG32: 159.55 | AH32: 3635.15
B33: EGEJUNIN | C33: C.H. SANTA CRUZ I | D33: CENTRAL | E33: HIDROELÉCTRICA | F33: 81.35 | G33: 82.15 | H33: 74.3 | I33: 65.2 | J33: 62.75 | K33: 57.2 | L33: 70.3 | M33: 66.55 | N33: 71 | O33: 92.8 | P33: 89.55 | Q33: 71.85 | R33: 58.25 | S33: 60.45 | T33: 53.9 | U33: 52.8 | V33: 56.6 | W33: 56.5 | X33: 52.9 | Y33: 61.4 | Z33: 68.7 | AA33: 62.25 | AB33: 68.2 | AC33: 65.9 | AD33: 65.4 | AE33: 62.05 | AF33: 55.2 | AG33: 63.05 | AH33: 1848.55
B34: EGEMSA | C34: C.H. MACHUPICCHU | D34: CENTRAL | E34: HIDROELÉCTRICA | F34: 2564.95 | G34: 2569.55 | H34: 2944.15 | I34: 3169.35 | J34: 3125.6 | K34: 3075.5 | L34: 3029.15 | M34: 3005.6 | N34: 3044.5 | O34: 3052 | P34: 3045.7 | Q34: 2999.75 | R34: 2992.5 | S34: 2951.35 | T34: 2929.3 | U34: 2928.4 | V34: 2887 | W34: 2882.6 | X34: 2900.45 | Y34: 2881.5 | Z34: 2851.65 | AA34: 2846.15 | AB34: 2832.9 | AC34: 2635.85 | AD34: 3107.6 | AE34: 2805.15 | AF34: 3039.75 | AG34: 2873.7 | AH34: 81971.65
B35: EGESUR | C35: C.H. ARICOTA I | D35: CENTRAL | E35: HIDROELÉCTRICA | F35: 186.85 | G35: 184.15 | H35: 183 | I35: 183.1 | J35: 183.25 | K35: 184.3 | L35: 183.25 | M35: 187 | N35: 188.75 | O35: 185.95 | P35: 183 | Q35: 183.2 | R35: 183.25 | S35: 181.15 | T35: 180.7 | U35: 180.9 | V35: 141.8 | W35: 150.4 | X35: 188.35 | Y35: 188.25 | Z35: 188.25 | AA35: 186.8 | AB35: 176.25 | AC35: 180.6 | AD35: 175.5 | AE35: 140.4 | AF35: 178.6 | AG35: 177.05 | AH35: 5014.05
B36: EGESUR | C36: C.H. ARICOTA II | D36: CENTRAL | E36: HIDROELÉCTRICA | F36: 124.9 | G36: 124 | H36: 121 | I36: 125.9 | J36: 132.85 | K36: 131.7 | L36: 133.25 | M36: 132.45 | N36: 129 | O36: 130.75 | P36: 132.25 | Q36: 131.55 | R36: 130.05 | S36: 128.35 | T36: 128.05 | U36: 125.65 | V36: 57.9 | W36: 77.85 | X36: 75.25 | Y36: 77.8 | Z36: 80.1 | AA36: 79.4 | AB36: 80.45 | AC36: 80.3 | AD36: 68 | AE36: 59.3 | AF36: 71.7 | AG36: 79.2 | AH36: 2948.95
B37: EGESUR | C37: C.T. INDEPENDENCIA | D37: CENTRAL | E37: TERMOELÉCTRICA | I37: 252.85 | Q37: 174.75 | R37: 404.05 | S37: 403.85 | T37: 260.95 | U37: 331.95 | V37: 416.95 | W37: 168.8 | X37: 136.2 | Y37: 77.45 | Z37: 10.05 | AC37: 4.35 | AD37: 179.35 | AE37: 66.1 | AG37: 209.45 | AH37: 3097.1
B38: ELECTRICA YANAPAMPA SAC | C38: C.H. YANAPAMPA | D38: CENTRAL | E38: HIDROELÉCTRICA | F38: 53.25 | G38: 53.35 | H38: 51.85 | I38: 53.25 | J38: 54.85 | K38: 55.25 | L38: 55 | M38: 55.15 | N38: 53.95 | O38: 54.05 | P38: 17.35 | X38: 23.9 | Y38: 56.55 | Z38: 56.15 | AA38: 59.55 | AB38: 57.7 | AC38: 55.95 | AD38: 58.05 | AE38: 58.2 | AF38: 58.65 | AG38: 57.9 | AH38: 1099.9
B39: ELECTROPERU | C39: C.H. MANTARO | D39: CENTRAL | E39: HIDROELÉCTRICA | F39: 14936.4 | G39: 15359.8 | H39: 15330.35 | I39: 15352.6 | J39: 15309.75 | K39: 15344.9 | L39: 15326.55 | M39: 15351.6 | N39: 15316.85 | O39: 15274.05 | P39: 15271.25 | Q39: 15308.45 | R39: 14970.25 | S39: 15221.8 | T39: 14803.2 | U39: 14714.4 | V39: 13860.6 | W39: 14294.3 | X39: 15161.55 | Y39: 14886.4 | Z39: 14891.2 | AA39: 14405.1 | AB39: 13984.1 | AC39: 14862.4 | AD39: 15102.5 | AE39: 15004.85 | AF39: 15304.6 | AG39: 15292.75 | AH39: 420242.55
B40: ELECTROPERU | C40: C.H. RESTITUCION | D40: CENTRAL | E40: HIDROELÉCTRICA | F40: 5036.15 | G40: 5181.2 | H40: 4505.7 | I40: 3523.6 | J40: 3495.5 | K40: 3496.45 | L40: 3482.7 | M40: 3486.35 | N40: 3486.3 | O40: 4495.45 | P40: 5145.05 | Q40: 5115.25 | R40: 5066.9 | S40: 5160.6 | T40: 5062.25 | U40: 4978.95 | V40: 4711.25 | W40: 4869.4 | X40: 5145.45 | Y40: 5053.35 | Z40: 5086.45 | AA40: 4864.1 | AB40: 4704.45 | AC40: 5090.2 | AD40: 5158.25 | AE40: 4292.6 | AF40: 5147.45 | AG40: 5174.15 | AH40: 130015.5
B41: ELECTROPERU | C41: C.T. TUMBES | D41: MAK1 | E41: TERMOELÉCTRICA | R41: 47.85 | S41: 38.25 | U41: 53.25 | Y41: 14.3 | AH41: 153.65
B42: ELECTROPERU | C42: C.T. TUMBES | D42: MAK2 | E42: TERMOELÉCTRICA | M42: 7.3 | R42: 47.8 | S42: 45.5 | U42: 52.4 | Y42: 14.7 | AH42: 167.7
B43: EMPRESA DE GENERACION ELECTRICA CANCHAYLLO SAC | C43: C.H. CANCHAYLLO | D43: CENTRAL | E43: HIDROELÉCTRICA | F43: 44.8 | G43: 45.6 | H43: 43.55 | I43: 42.2 | J43: 41.45 | K43: 39.05 | L43: 41.05 | M43: 41.5 | N43: 41.75 | O43: 42.45 | P43: 41.6 | Q43: 40.05 | R43: 41.2 | S43: 41.2 | T43: 40.65 | U43: 39.8 | V43: 38.8 | W43: 38.85 | X43: 41.5 | Y43: 89.8 | Z43: 100.25 | AA43: 108.15 | AB43: 110.2 | AC43: 110.45 | AD43: 111.4 | AE43: 112 | AF43: 111.885 | AG43: 112.7 | AH43: 1753.885
B44: EMPRESA DE GENERACION ELECTRICA RIO BAÑOS S.A.C. | C44: C.H. RUCUY | D44: CENTRAL | E44: HIDROELÉCTRICA | F44: 277.5 | G44: 240 | H44: 239.65 | I44: 240.15 | J44: 239.8 | K44: 239.7 | L44: 239.95 | M44: 239.9 | N44: 239.7 | O44: 240.05 | P44: 135.85 | Q44: 239.6 | R44: 239.6 | S44: 239.6 | T44: 239.45 | U44: 239.5 | V44: 239.7 | W44: 239.45 | X44: 239.05 | Y44: 239.65 | Z44: 239.8 | AA44: 239.2 | AB44: 239.65 | AC44: 239.85 | AD44: 239.8 | AE44: 239.4 | AF44: 240 | AG44: 240.6 | AH44: 6646.15
B45: EMPRESA DE GENERACION ELECTRICA SANTA ANA S.A.C. | C45: C.H. RENOVANDES H1 | D45: CENTRAL | E45: HIDROELÉCTRICA | F45: 396.1 | G45: 461.05 | H45: 447.5 | I45: 444.1 | J45: 442.4 | K45: 481.7 | L45: 448.45 | M45: 427.85 | N45: 475.4 | O45: 486.45 | P45: 485.85 | Q45: 487.95 | R45: 487.9 | S45: 486.9 | T45: 483.25 | U45: 481.9 | V45: 483 | W45: 485.25 | X45: 485.2 | Y45: 456.3 | Z45: 477.95 | AA45: 418 | AB45: 152 | AC45: 352.6 | AD45: 366.45 | AE45: 417.5 | AF45: 403.75 | AG45: 362.6 | AH45: 12285.35
B46: EMPRESA DE GENERACION HUALLAGA | C46: C.H. CHAGLLA | D46: CENTRAL | E46: HIDROELÉCTRICA | F46: 624.9 | G46: 1371 | H46: 5021.6 | I46: 3923.9 | J46: 2781.95 | K46: 3013.1 | L46: 3820.8 | M46: 2915.6 | N46: 2767.9 | O46: 1376 | P46: 2822.25 | Q46: 5020.288 | R46: 5710.3 | S46: 1183.9 | T46: 2141.6 | U46: 242.45 | V46: 221.05 | W46: 2184.85 | X46: 2490.15 | Y46: 3455.65 | Z46: 2053.25 | AA46: 1670.45 | AB46: 445.45 | AC46: 875.1 | AD46: 2636.5 | AE46: 2721.65 | AF46: 2367.4 | AG46: 301.45 | AH46: 66160.488
B47: EMPRESA DE GENERACION HUALLAGA | C47: P.C.H. CHAGLLA | D47: CENTRAL | E47: HIDROELÉCTRICA | F47: 156 | G47: 97.1 | H47: 155.35 | I47: 155.6 | J47: 154.6 | K47: 154.45 | L47: 154.4 | M47: 153.95 | N47: 154.5 | O47: 153.8 | P47: 154.15 | Q47: 154.77908 | R47: 154 | S47: 153.95 | T47: 153.95 | U47: 108.35 | V47: 156 | W47: 156 | X47: 155.95 | Y47: 155.95 | Z47: 155.95 | AA47: 155.95 | AB47: 107.1 | AC47: 156 | AD47: 156 | AE47: 155.9 | AF47: 156 | AG47: 156 | AH47: 4191.7291
B48: EMPRESA DE GENERACION HUANZA | C48: C.H. HUANZA | D48: CENTRAL | E48: HIDROELÉCTRICA | F48: 1206.65 | G48: 1226.4 | H48: 1146.2 | I48: 1083.3 | J48: 1075.45 | K48: 1107.15 | L48: 1166.05 | M48: 1082.75 | N48: 1111.5 | O48: 1046.65 | P48: 1121.05 | Q48: 1065.25 | R48: 1134.2 | S48: 1198.1 | T48: 1273.9 | U48: 1298.95 | V48: 1203.3 | W48: 1398.85 | X48: 1483.5 | Y48: 1305.8 | Z48: 1397.1 | AA48: 1424.45 | AB48: 1401.75 | AC48: 1382 | AD48: 1398 | AE48: 1418.35 | AF48: 1360.85 | AG48: 1319.6 | AH48: 34837.1
B49: EMPRESA ELECTRICA AGUA AZUL | C49: C.H. POTRERO | D49: CENTRAL | E49: HIDROELÉCTRICA | F49: 166.5 | G49: 163.3 | H49: 151 | I49: 144.3 | J49: 141.35 | K49: 149.35 | L49: 149.4 | M49: 149.85 | N49: 146 | O49: 178.2 | P49: 209.2 | Q49: 200.5 | R49: 171.7 | S49: 165.15 | T49: 154.9 | U49: 130.6 | V49: 119.75 | W49: 127.75 | X49: 130.8 | Y49: 124.35 | Z49: 82.9 | AA49: 123.8 | AB49: 110.45 | AC49: 96.5 | AD49: 97.5 | AE49: 97.15 | AF49: 107.4 | AG49: 109.2 | AH49: 3898.85
B50: EMPRESA ELECTRICA RIO DOBLE | C50: C.H. LAS PIZARRAS | D50: CENTRAL | E50: HIDROELÉCTRICA | F50: 110.5 | G50: 102.95 | H50: 96 | I50: 95.95 | J50: 91.35 | K50: 103 | L50: 102.9 | M50: 89.8 | N50: 89.95 | O50: 127.85 | P50: 103.15 | Q50: 94.6 | R50: 90.3 | S50: 108.95 | T50: 112.8 | U50: 110.95 | V50: 101.2 | W50: 99.6 | X50: 85.5 | Y50: 89.35 | Z50: 84.75 | AA50: 83.05 | AB50: 85.9 | AC50: 82.95 | AD50: 82.1 | AE50: 76.45 | AF50: 76.55 | AG50: 64.15 | AH50: 2642.55
B51: ENEL GENERACION PIURA S.A. | C51: C.T. MALACAS 1 | D51: TG6 | E51: TERMOELÉCTRICA | F51: 979.5 | G51: 714 | H51: 23.5 | J51: 1017.15 | K51: 1087.6 | L51: 240.55 | M51: 451.25 | N51: 505.25 | O51: 61.35 | T51: 511.95 | U51: 1141.05 | V51: 1139.2 | W51: 890.85 | X51: 655.6 | Y51: 769.5 | Z51: 734.65 | AA51: 648.7 | AB51: 47.65 | AD51: 784.2 | AE51: 835.3 | AF51: 1125.6 | AG51: 1134.75 | AH51: 15499.15
B52: ENEL GENERACION PIURA S.A. | C52: C.T. MALACAS 2 | D52: TG4 | E52: TERMOELÉCTRICA | I52: 728.4 | J52: 50.05 | L52: 650.95 | M52: 405.35 | N52: 323.85 | P52: 635.4 | Q52: 671.15 | R52: 645.8 | S52: 505.85 | T52: 465.4 | AH52: 5082.2
B53: ENEL GENERACION PIURA S.A. | C53: C.T. RF DE GENERACION TALARA | D53: TG5 | E53: TERMOELÉCTRICA | AH53: 0
B54: ENERGÍA EÓLICA S.A. | C54: C.E. CUPISNIQUE | D54: CENTRAL | E54: EÓLICA | F54: 982.9 | G54: 419.25 | H54: 305.85 | I54: 139.5 | J54: 782.25 | K54: 840.3 | L54: 320.4 | M54: 571.5 | N54: 1056.45 | O54: 1065.65 | P54: 592.75 | Q54: 526.25 | R54: 526.75 | S54: 659 | T54: 567.4 | U54: 415.4 | V54: 1221.8 | W54: 1069.15 | X54: 804.25 | Y54: 552.25 | Z54: 957.05 | AA54: 1306.3 | AB54: 1412.35 | AC54: 1150.55 | AD54: 961.3 | AE54: 1150.85 | AF54: 776.15 | AG54: 678.8 | AH54: 21812.4
B55: ENERGÍA EÓLICA S.A. | C55: C.E. TALARA | D55: CENTRAL | E55: EÓLICA | F55: 460.3 | G55: 328.75 | H55: 318.05 | I55: 121.7 | J55: 83.6 | K55: 351.4 | L55: 554.05 | M55: 540.5 | N55: 604.9 | O55: 548.85 | P55: 355.55 | Q55: 228.25 | R55: 240.55 | S55: 544.8 | T55: 291.6 | U55: 356 | V55: 413.4 | W55: 643.45 | X55: 571.65 | Y55: 468.9 | Z55: 595.05 | AA55: 685.5 | AB55: 721.2 | AC55: 537.75 | AD55: 521.05 | AE55: 558.8 | AF55: 545.45 | AG55: 468.45 | AH55: 12659.5
B56: ENERGIA RENOVABLE DEL SUR S.A. | C56: C.E. SAN JUAN | D56: CENTRAL | E56: EÓLICA | F56: 2444.55 | G56: 2933.05 | H56: 1923.4 | I56: 586.6 | J56: 1797.2 | K56: 1339.4 | L56: 1593.15 | M56: 757.25 | N56: 1941.2 | O56: 2500.7 | P56: 2132.85 | Q56: 935.2 | R56: 45.95 | S56: 254.85 | T56: 1187.85 | U56: 353.4 | V56: 209.45 | W56: 991.3 | X56: 2663.9 | Y56: 1731.8 | Z56: 1549.15 | AA56: 2667.5 | AB56: 3025.6 | AC56: 2821.75 | AD56: 2356.7 | AE56: 1551.2 | AF56: 1275.95 | AG56: 685 | AH56: 44255.9
B57: ENGIE | C57: C.E. PUNTA LOMITAS | D57: PL-BL1 | E57: EÓLICA | F57: 2083.7 | G57: 2524.65 | H57: 940.35 | I57: 277.8 | J57: 1191.5 | K57: 907.55 | L57: 852.1 | M57: 306.25 | N57: 1423.9 | O57: 1733.75 | P57: 1371.45 | Q57: 820 | R57: 416.55 | S57: 551.35 | T57: 1113 | U57: 629.4 | V57: 510.85 | W57: 960.05 | X57: 2045.05 | Y57: 1641.7 | Z57: 1763.6 | AA57: 2520.75 | AB57: 2478.35 | AC57: 2207.4 | AD57: 1746.55 | AE57: 983.35 | AF57: 950.5 | AG57: 847.55 | AH57: 35799
B58: ENGIE | C58: C.E. PUNTA LOMITAS | D58: PL-BL2 | E58: EÓLICA | F58: 2425.4 | G58: 2546.9 | H58: 1374.8 | I58: 529.55 | J58: 1410.9 | K58: 1473.85 | L58: 1460.75 | M58: 577.95 | N58: 2139.8 | O58: 2278.4 | P58: 2050.05 | Q58: 675.65 | R58: 124.9 | S58: 328.65 | T58: 1219.35 | U58: 390.8 | V58: 452.95 | W58: 1369.35 | X58: 2574.25 | Y58: 1748.8 | Z58: 1976.2 | AA58: 2503.75 | AB58: 2478.35 | AC58: 2179.1 | AD58: 2115.4 | AE58: 1289.4 | AF58: 1463.35 | AG58: 1106.75 | AH58: 42265.35
B59: ENGIE | C59: C.E. PUNTA LOMITAS_EXP | D59: PUN LOM_EXP-BL1 | E59: EÓLICA | F59: 350.45 | G59: 434.35 | H59: 171.35 | I59: 43.85 | J59: 123.65 | K59: 129.7 | L59: 139.2 | M59: 46.4 | N59: 206.45 | O59: 255.35 | P59: 175.3 | Q59: 52.85 | R59: 7.2 | S59: 34.8 | T59: 118.4 | U59: 44.8 | V59: 36.45 | W59: 149 | X59: 365.5 | Y59: 226.95 | Z59: 239.1 | AA59: 417.35 | AB59: 433.8 | AC59: 355.3 | AD59: 252.3 | AE59: 191.4 | AF59: 153.85 | AG59: 126.85 | AH59: 5281.95
B60: ENGIE | C60: C.E. PUNTA LOMITAS_EXP | D60: PUN LOM_EXP-BL2 | E60: EÓLICA | F60: 232.1 | G60: 234.75 | H60: 87.9 | I60: 26.1 | J60: 63.55 | K60: 79.55 | L60: 62.15 | M60: 29.9 | N60: 146.15 | O60: 194.55 | P60: 129.75 | Q60: 49.25 | R60: 5.75 | S60: 20.55 | T60: 86.45 | U60: 29.4 | V60: 25.2 | W60: 108.4 | X60: 222.8 | Y60: 129.4 | Z60: 94.1 | AA60: 218.25 | AB60: 245.4 | AC60: 211.4 | AD60: 147.2 | AE60: 108.2 | AF60: 101.8 | AG60: 93.75 | AH60: 3183.75
B61: ENGIE | C61: C.H. QUITARACSA | D61: CENTRAL | E61: HIDROELÉCTRICA | I61: 226.05 | L61: 175.05 | Q61: 301.65 | S61: 96.05 | U61: 125.1 | AH61: 923.9
B62: ENGIE | C62: C.H. YUNCAN | D62: CENTRAL | E62: HIDROELÉCTRICA | F62: 1935.25 | G62: 1527.8 | H62: 1539.3 | I62: 1457.6 | J62: 1258.05 | K62: 1326.15 | L62: 1528.15 | M62: 1394 | N62: 1238 | O62: 1550 | P62: 1496.6 | Q62: 1364.85 | R62: 1435.2 | S62: 1409.25 | T62: 1195.35 | U62: 1576.15 | V62: 870.5 | W62: 1150.75 | X62: 1294 | Y62: 1532.65 | Z62: 1369.2 | AA62: 1259.45 | AB62: 1482.95 | AC62: 1566.45 | AD62: 1463.95 | AE62: 1494.85 | AF62: 1335 | AG62: 1460.85 | AH62: 39512.3
B63: ENGIE | C63: C.S. INTIPAMPA | D63: CENTRAL | E63: SOLAR | F63: 263.1 | G63: 276 | H63: 279.4 | I63: 281.75 | J63: 281.6 | K63: 286.35 | L63: 291.45 | M63: 296.65 | N63: 291.85 | O63: 296.9 | P63: 296.2 | Q63: 298.4 | R63: 299.7 | S63: 299.05 | T63: 300.6 | U63: 303.45 | V63: 303.3 | W63: 305.35 | X63: 314.15 | Y63: 314.4 | Z63: 313.4 | AA63: 297.5 | AB63: 310.45 | AC63: 280.15 | AD63: 316.9 | AE63: 291 | AF63: 315 | AG63: 318.6 | AH63: 8322.65
B64: ENGIE | C64: C.T. CHILCA 1 | D64: TG1 | E64: TERMOELÉCTRICA | F64: 4265.15 | G64: 4233.7 | H64: 4214.65 | I64: 4245.6 | J64: 4268.4 | K64: 4230.75 | L64: 4261.8 | M64: 4281.95 | N64: 4267.6 | O64: 4004.25 | P64: 4234.45 | Q64: 4251.8 | R64: 4209.75 | S64: 4228.35 | T64: 4270.65 | U64: 4245.25 | V64: 4153 | W64: 4267.1 | X64: 4170.1 | Y64: 4224.9 | Z64: 4249.35 | AA64: 4228.45 | AB64: 4261.85 | AC64: 3918.15 | AD64: 3955.15 | AE64: 4126.2 | AF64: 4268.3 | AG64: 4291.1 | AH64: 117827.75
B65: ENGIE | C65: C.T. CHILCA 1 | D65: TG2 | E65: TERMOELÉCTRICA | F65: 4206.45 | G65: 4181.85 | H65: 4165.7 | I65: 4191.8 | J65: 4210.8 | K65: 4177.8 | L65: 4204.7 | M65: 4221.85 | N65: 4210.6 | O65: 3959.1 | P65: 4184.95 | Q65: 4197.5 | R65: 4162.25 | S65: 4180.1 | T65: 4212.35 | U65: 4186.6 | V65: 4110 | W65: 4206.95 | X65: 4131.3 | Y65: 4170.5 | Z65: 4198 | AA65: 4176.95 | AB65: 4206.25 | AC65: 3878.15 | AD65: 3909.05 | AE65: 4087.7 | AF65: 4217.05 | AG65: 4233.9 | AH65: 116380.2
B66: ENGIE | C66: C.T. CHILCA 1 | D66: TG3 | E66: TERMOELÉCTRICA | F66: 5020.85 | G66: 4800 | H66: 4800 | I66: 4800 | J66: 5033.35 | K66: 4931.9 | L66: 5017.1 | M66: 5044.5 | N66: 4956.05 | O66: 26.25 | P66: 3923.95 | Q66: 5003.05 | R66: 4837.45 | S66: 4850.7 | T66: 5036.9 | U66: 5003.7 | V66: 4728.55 | W66: 4800 | X66: 4626.85 | Y66: 5005 | Z66: 5017.3 | AA66: 4886.3 | AB66: 4996.75 | AC66: 4436.25 | AD66: 4560.45 | AE66: 4594.9 | AF66: 4867 | AG66: 5009.65 | AH66: 130614.75
B67: ENGIE | C67: C.T. CHILCA 1 | D67: TV | E67: TERMOELÉCTRICA | F67: 6576.55 | G67: 6546.75 | H67: 6533.6 | I67: 6553.65 | J67: 6583.5 | K67: 6538.15 | L67: 6609.7 | M67: 6613.85 | N67: 6581.65 | O67: 4002.65 | P67: 6075.4 | Q67: 6580.4 | R67: 6495.55 | S67: 6485.15 | T67: 6572.55 | U67: 6576.85 | V67: 6402.4 | W67: 6591.55 | X67: 6451.2 | Y67: 6534.85 | Z67: 6557.4 | AA67: 6485.45 | AB67: 6556 | AC67: 6156.2 | AD67: 6193.8 | AE67: 6345.5 | AF67: 6551.45 | AG67: 6546.75 | AH67: 179298.5
B68: ENGIE | C68: C.T. CHILCA 2 | D68: TG41 | E68: TERMOELÉCTRICA | H68: 17.3 | I68: 1321.05 | J68: 1351.8 | K68: 1109.85 | L68: 1296.7 | M68: 1792.9 | N68: 1480.75 | O68: 1126.15 | P68: 1214.75 | Q68: 1775.85 | R68: 1818.15 | S68: 1825.85 | T68: 1828.2 | U68: 1818.7 | V68: 1638.5 | W68: 1825.9 | X68: 177.75 | AF68: 48.05 | AG68: 1526.15 | AH68: 24994.35
B69: ENGIE | C69: C.T. CHILCA 2 | D69: TV42 | E69: TERMOELÉCTRICA | I69: 586.6 | J69: 760.9 | K69: 697.65 | L69: 748.75 | M69: 878.35 | N69: 794.45 | O69: 703.55 | P69: 723.15 | Q69: 874.4 | R69: 885.4 | S69: 887.75 | T69: 889.2 | U69: 885.1 | V69: 836.4 | W69: 888.65 | X69: 89.05 | AG69: 710.55 | AH69: 12839.9
B70: ENGIE | C70: C.T. NEPI | D70: TG41 | E70: TERMOELÉCTRICA | AE70: 245.45 | AH70: 245.45
B71: ENGIE | C71: C.T. NEPI | D71: TG42 | E71: TERMOELÉCTRICA | AH71: 0
B72: ENGIE | C72: C.T. NEPI | D72: TG43 | E72: TERMOELÉCTRICA | AH72: 0
B73: ENGIE | C73: C.T. RF PLANTA ILO | D73: TG1 | E73: TERMOELÉCTRICA | AH73: 0
B74: ENGIE | C74: C.T. RF PLANTA ILO | D74: TG2 | E74: TERMOELÉCTRICA | P74: 81.55 | W74: 394.05 | AH74: 475.6
B75: ENGIE | C75: C.T. RF PLANTA ILO | D75: TG3 | E75: TERMOELÉCTRICA | AH75: 0
B76: FENIX POWER PERÚ | C76: C.T. FENIX | D76: GT11 | E76: TERMOELÉCTRICA | F76: 4167.15 | G76: 3908.25 | H76: 3112.9 | I76: 4284.4 | J76: 3986.75 | K76: 3503.6 | L76: 3815.95 | M76: 4373.65 | N76: 4006.1 | O76: 3345.75 | P76: 4024.85 | Q76: 4319 | R76: 4383.95 | S76: 4366.15 | T76: 4361.4 | U76: 4372.6 | V76: 4100.3 | W76: 4371.1 | X76: 3800.55 | Y76: 4058.18 | Z76: 4187.35 | AA76: 3888.65 | AB76: 3887.9 | AC76: 98.95 | AD76: 3567.85 | AE76: 3315.7 | AF76: 4363.7 | AG76: 4374.65 | AH76: 108347.33
B77: FENIX POWER PERÚ | C77: C.T. FENIX | D77: GT12 | E77: TERMOELÉCTRICA | F77: 4175.4 | G77: 3915.65 | H77: 3121.7 | I77: 4295 | J77: 3996.7 | K77: 3511.1 | L77: 3823.1 | M77: 4384.55 | N77: 4014.45 | O77: 3350.65 | P77: 4034.1 | Q77: 4331.3 | R77: 4393.45 | S77: 4375.9 | T77: 4373.55 | U77: 4384.55 | V77: 4110.85 | W77: 4381.1 | X77: 3809.35 | Y77: 4065.17 | Z77: 4198.9 | AA77: 3897.8 | AB77: 3892.9 | AC77: 1085.05 | AD77: 3812.55 | AE77: 3982.25 | AF77: 4370.25 | AG77: 4384.15 | AH77: 110471.47
B78: FENIX POWER PERÚ | C78: C.T. FENIX | D78: TV10 | E78: TERMOELÉCTRICA | F78: 4309.4 | G78: 4174.9 | H78: 3771.45 | I78: 4368.55 | J78: 4218.5 | K78: 3959.85 | L78: 4127.6 | M78: 4417.65 | N78: 4223.15 | O78: 3894.05 | P78: 4228.1 | Q78: 4397.55 | R78: 4431.55 | S78: 4415.55 | T78: 4408.15 | U78: 4413.4 | V78: 4285.15 | W78: 4408.1 | X78: 4149.15 | Y78: 4337.59 | Z78: 4365.8 | AA78: 4153.75 | AB78: 4160.85 | AC78: 607.85 | AD78: 3878.35 | AE78: 3786.2 | AF78: 4413.9 | AG78: 4432.55 | AH78: 114738.64
B79: GENERACIÓN ANDINA S.A.C. | C79: C.H. 8 DE AGOSTO | D79: CENTRAL | E79: HIDROELÉCTRICA | F79: 250.5 | G79: 243.65 | H79: 213.2 | I79: 186.35 | J79: 168.45 | K79: 192.45 | L79: 158 | M79: 135.4 | N79: 153 | O79: 249.45 | P79: 252 | Q79: 242.55 | R79: 207.45 | S79: 176.8 | T79: 182.7 | U79: 197.55 | V79: 179.45 | W79: 195.05 | X79: 153.85 | Y79: 172.85 | Z79: 143.4 | AA79: 127.95 | AB79: 119.5 | AC79: 123.15 | AD79: 180.95 | AE79: 214.7 | AF79: 223.45 | AG79: 131.55 | AH79: 5175.35
B80: GENERACIÓN ANDINA S.A.C. | C80: C.H. EL CARMEN | D80: CENTRAL | E80: HIDROELÉCTRICA | F80: 131.85 | G80: 81.8 | H80: 71.5 | I80: 60.65 | J80: 60.25 | K80: 69.35 | L80: 56.85 | M80: 50.9 | N80: 52.9 | O80: 105.05 | P80: 100.6 | Q80: 74.9 | R80: 57.9 | S80: 52.15 | T80: 67.25 | U80: 58.5 | V80: 57.8 | W80: 58.35 | X80: 64.8 | Y80: 52.25 | Z80: 47.7 | AA80: 45.15 | AB80: 42.55 | AC80: 43.35 | AD80: 56.45 | AE80: 66.15 | AF80: 48.6 | AG80: 34.75 | AH80: 1770.3
B81: GENERADORA DE ENERGÍA DEL PERÚ | C81: C.H. ÁNGEL I | D81: CENTRAL | E81: HIDROELÉCTRICA | F81: 91.9 | G81: 88.55 | H81: 87.25 | I81: 93.4 | J81: 97.35 | K81: 90.1 | L81: 82.35 | M81: 79.25 | N81: 83.7 | O81: 85.8 | P81: 80.35 | Q81: 76.55 | R81: 74.15 | S81: 71.7 | T81: 74.3 | U81: 74.95 | V81: 71.55 | W81: 70.7 | X81: 70.5 | Y81: 70.1 | Z81: 71.3 | AA81: 72.1 | AB81: 104.05 | AC81: 199.35 | AD81: 181.63 | AE81: 148.35 | AF81: 128.85 | AG81: 101.05 | AH81: 2621.18
B82: GENERADORA DE ENERGÍA DEL PERÚ | C82: C.H. ÁNGEL II | D82: CENTRAL | E82: HIDROELÉCTRICA | F82: 103.7 | G82: 99.1 | H82: 98.65 | I82: 104.3 | J82: 108.65 | K82: 101.1 | L82: 93.3 | M82: 89.75 | N82: 94.05 | O82: 96.6 | P82: 91.2 | Q82: 87.25 | R82: 84.35 | S82: 83.05 | T82: 86.35 | U82: 86.9 | V82: 83.15 | W82: 81.9 | X82: 82.5 | Y82: 82.15 | Z82: 82.4 | AA82: 83.9 | AB82: 107.05 | AC82: 197.85 | AD82: 194.97 | AE82: 166.2 | AF82: 142.05 | AG82: 112.6 | AH82: 2925.02
B83: GENERADORA DE ENERGÍA DEL PERÚ | C83: C.H. ÁNGEL III | D83: CENTRAL | E83: HIDROELÉCTRICA | F83: 107.9 | G83: 101.65 | H83: 101 | I83: 103.7 | J83: 112.5 | K83: 105.9 | L83: 95.15 | M83: 93.2 | N83: 95.45 | O83: 98.4 | P83: 96.6 | Q83: 91.05 | R83: 86.85 | S83: 86.55 | T83: 88.35 | U83: 90.95 | V83: 86.15 | W83: 84.15 | X83: 86.35 | Y83: 84.7 | Z83: 86 | AA83: 86.9 | AB83: 103.2 | AC83: 190.65 | AD83: 188.89 | AE83: 151.8 | AF83: 146.5 | AG83: 117.1 | AH83: 2967.59
B84: GENERADORA DE ENERGÍA DEL PERÚ | C84: C.H. LA JOYA | D84: CENTRAL | E84: HIDROELÉCTRICA | F84: 188.95 | G84: 190.9 | H84: 191.15 | I84: 199.1 | J84: 197.4 | K84: 184.95 | L84: 189.45 | M84: 198.15 | N84: 198 | O84: 200.6 | P84: 205 | Q84: 101.2 | R84: 184.6 | S84: 191.6 | T84: 181.55 | U84: 159.7 | V84: 121.9 | W84: 121.9 | X84: 123.35 | Y84: 123.9 | Z84: 141.45 | AA84: 185.5 | AB84: 189.25 | AC84: 186.15 | AD84: 181.25 | AE84: 107.2 | AF84: 2.4 | AH84: 4446.55
B85: GM OPERACIONES S.A.C. | C85: CT REFINERIA TALARA | D85: TV1 REF TALARA | E85: TERMOELÉCTRICA | F85: 589.35 | G85: 48.45 | Z85: 327.1 | AA85: 566.995 | AB85: 770.7 | AC85: 770.6 | AD85: 761.35 | AE85: 773.95 | AF85: 807 | AG85: 807.95 | AH85: 6223.445
B86: GM OPERACIONES S.A.C. | C86: CT REFINERIA TALARA | D86: TV2 REF TALARA | E86: TERMOELÉCTRICA | F86: 844.75 | G86: 218.05 | Z86: 268.1 | AA86: 397.93 | AB86: 663.1 | AC86: 705.15 | AD86: 636.5 | AE86: 513.35 | AF86: 703.25 | AG86: 701.2 | AH86: 5651.38
B87: GR CORTARRAMA SOCIEDAD ANONIMA CERRADA | C87: C.S. MATARANI | D87: C.S. MATARANI | E87: SOLAR | F87: 565.3 | G87: 621.6 | H87: 637.6 | I87: 645 | J87: 635.25 | K87: 646.35 | L87: 662.75 | M87: 661.7 | N87: 627.15 | O87: 666.05 | P87: 666.4 | Q87: 575.85 | R87: 604.65 | S87: 652.05 | T87: 665.3 | U87: 669.95 | V87: 668.85 | W87: 683.05 | X87: 703.05 | Y87: 698.1 | Z87: 691.5 | AA87: 490.15 | AB87: 349.75 | AC87: 621.65 | AD87: 741.1 | AE87: 710.1 | AF87: 744.35 | AG87: 745.9 | AH87: 18050.5
B88: GR PAINO SOCIEDAD ANONIMA CERRADA | C88: C.E. HUAMBOS | D88: CENTRAL | E88: EÓLICA | F88: 235.75 | G88: 310.15 | H88: 284.6 | I88: 231.3 | J88: 215.6 | K88: 293 | L88: 91.35 | M88: 116.4 | N88: 187.25 | O88: 300.2 | P88: 306.25 | Q88: 300.5 | R88: 107.45 | S88: 160.8 | T88: 193.05 | U88: 147.7 | V88: 123.35 | W88: 260.3 | X88: 234.4 | Y88: 204.7 | Z88: 173.45 | AA88: 103.35 | AB88: 193.35 | AC88: 276.2 | AD88: 325.1 | AE88: 323.3 | AF88: 377.55 | AG88: 392.85 | AH88: 6469.25
B89: GR TARUCA SOCIEDAD ANONIMA CERRADA | C89: C.E. DUNA | D89: CENTRAL | E89: EÓLICA | F89: 308.6 | G89: 346.3 | H89: 323.35 | I89: 285.25 | J89: 313.75 | K89: 361.05 | L89: 99.15 | M89: 134.85 | N89: 248.85 | O89: 358.9 | P89: 362.15 | Q89: 353.4 | R89: 145.3 | S89: 208.1 | T89: 242.7 | U89: 198.8 | V89: 155 | W89: 325.3 | X89: 306.25 | Y89: 286.85 | Z89: 231.2 | AA89: 130.95 | AB89: 268.2 | AC89: 334.59 | AD89: 382.65 | AE89: 377.95 | AF89: 394.9 | AG89: 415.35 | AH89: 7899.69
B90: HIDROCAÑETE S.A. | C90: C.H. IMPERIAL | D90: CENTRAL | E90: HIDROELÉCTRICA | F90: 61.35 | G90: 74.4 | H90: 80.7 | I90: 83.05 | J90: 81.6 | K90: 81.45 | L90: 82.75 | M90: 84 | N90: 81.5 | O90: 82 | P90: 81.9 | Q90: 82.3 | R90: 82.3 | S90: 81.9 | T90: 82.1 | U90: 80.8 | V90: 80 | W90: 80 | X90: 77.9 | Y90: 78.15 | Z90: 79.7 | AA90: 81.3 | AB90: 80.45 | AC90: 82 | AD90: 46.15 | AE90: 78 | AF90: 79.5 | AG90: 78.6 | AH90: 2205.85
B91: HIDROELECTRICA HUANCHOR S.A.C. | C91: C.H. HUANCHOR | D91: CENTRAL | E91: HIDROELÉCTRICA | F91: 445.75 | G91: 445.85 | H91: 445.1 | I91: 446.1673 | J91: 443.95 | K91: 444.2 | L91: 444.2 | M91: 445.65 | N91: 447.55 | O91: 446.35 | P91: 444.05 | Q91: 439.45 | R91: 439.05 | S91: 440.5 | T91: 444.8 | U91: 444.3 | V91: 442.75 | W91: 442.25 | X91: 442.6 | Y91: 441.45 | Z91: 443.75 | AA91: 443.6 | AB91: 442.27 | AC91: 343.05 | AD91: 445.65 | AE91: 442.65 | AF91: 442.3 | AG91: 443.05 | AH91: 12322.287
B92: HUAURA POWER GROUP S.A. | C92: C.H. YARUCAYA | D92: CENTRAL | E92: HIDROELÉCTRICA | F92: 442.8 | G92: 441.6 | H92: 438.8 | I92: 435.35 | J92: 428.8 | K92: 427.2 | L92: 424.25 | M92: 422.4 | N92: 421.25 | O92: 420 | P92: 422 | Q92: 416.2 | R92: 405.85 | S92: 402.2 | T92: 367.45 | U92: 349.6 | V92: 399 | W92: 413.85 | X92: 402.75 | Y92: 375.55 | Z92: 378.3 | AA92: 383.5 | AB92: 413.2 | AC92: 426.35 | AD92: 430.7 | AE92: 437.15 | AF92: 444 | AG92: 444 | AH92: 11614.1
B93: HYDRO GLOBAL PERÚ S.A.C. | C93: CH SAN GABAN III | D93: CENTRAL | E93: HIDROELÉCTRICA | F93: 1841.3 | G93: 1799.9 | H93: 1636.5 | I93: 1823.95 | J93: 1650.2 | K93: 1972.45 | L93: 2012.05 | M93: 1830.25 | N93: 1905.95 | O93: 2083.35 | P93: 1720.7 | Q93: 2114.35 | R93: 1832.75 | S93: 2020.8 | T93: 1777.9 | U93: 2067.45 | V93: 2074.2 | W93: 1906.25 | X93: 2254.95 | Y93: 1907 | Z93: 1802 | AA93: 2131.25 | AB93: 1914.4 | AC93: 2386.35 | AD93: 2388.1 | AE93: 1884.8 | AF93: 2378.45 | AG93: 2375.2 | AH93: 55492.8
B94: INFRAESTRUCTURAS Y ENERGIAS DEL PERU S.A.C. | C94: C.T. RF PTO MALDONADO | D94: CENTRAL | E94: TERMOELÉCTRICA | V94: 118.25 | AH94: 118.25
B95: INFRAESTRUCTURAS Y ENERGIAS DEL PERU S.A.C. | C95: C.T. RF PUCALLPA | D95: CENTRAL | E95: TERMOELÉCTRICA | O95: 214.95 | S95: 10.45 | U95: 1.65 | AF95: 1.65 | AH95: 228.7
B96: INLAND ENERGY SAC | C96: C.H. SANTA TERESA | D96: CENTRAL | E96: HIDROELÉCTRICA | F96: 1368.75 | G96: 1367.15 | H96: 1554.35 | I96: 1672.25 | J96: 1648.25 | K96: 1626.75 | L96: 1588 | M96: 1571.6 | N96: 1603.45 | O96: 1612.05 | P96: 1592.95 | Q96: 1559.2 | R96: 1555.5 | S96: 1535.05 | T96: 1522 | U96: 1525.45 | V96: 1495.65 | W96: 1640.25 | X96: 1505.25 | Y96: 1506.75 | Z96: 1481.8 | AA96: 1476.3 | AB96: 1467.2 | AC96: 1407.7 | AD96: 1628.55 | AE96: 1432.9 | AF96: 1605.15 | AG96: 1499.3 | AH96: 43049.55
B97: INVERSIONES SHAQSHA S.A.C. | C97: C.H. PARIAC | D97: CENTRAL | E97: HIDROELÉCTRICA | F97: 18.65 | G97: 22 | H97: 15 | I97: 20.1 | J97: 19.9 | K97: 19.2 | L97: 19.2 | M97: 19.65 | N97: 17.05 | O97: 10.15 | P97: 18.2 | Q97: 19.2 | R97: 17.05 | S97: 18.2 | T97: 18.5 | U97: 18.55 | V97: 16.65 | W97: 13.15 | X97: 13.9 | Y97: 11.95 | Z97: 13.55 | AA97: 12 | AB97: 13.55 | AC97: 12 | AD97: 305.8 | AE97: 9.5 | AF97: 9.55 | AG97: 9.6 | AH97: 731.8
B98: JOYA SOLAR S.A.C. | C98: C.S. SAN MARTIN SOLAR | D98: CENTRAL | E98: SOLAR | F98: 1827.85 | G98: 2033.35 | H98: 2082.7 | I98: 2099.1 | J98: 2070.7 | K98: 2104.95 | L98: 2151 | M98: 2139 | N98: 2036.35 | O98: 2171.25 | P98: 2166.05 | Q98: 2130.25 | R98: 2146.5 | S98: 2128.9 | T98: 2166.7 | U98: 2198.15 | V98: 2200.85 | W98: 2227.75 | X98: 2299.75 | Y98: 2284.95 | Z98: 2260.2 | AA98: 1911.45 | AB98: 1593.55 | AC98: 2348.2 | AD98: 2415.25 | AE98: 2371 | AF98: 2410.7 | AG98: 2404.85 | AH98: 60381.3
B99: KALLPA GENERACION S.A. | C99: C.H. CERRO DEL AGUILA | D99: CENTRAL | E99: HIDROELÉCTRICA | F99: 5226.65 | G99: 7987.15 | H99: 9009.75 | I99: 9042.65 | J99: 8416.9 | K99: 6268.65 | L99: 7680 | M99: 8894.95 | N99: 4908.85 | O99: 6684.85 | P99: 7512.05 | Q99: 7340.75 | R99: 7557.6 | S99: 7732.9 | T99: 5659.5 | U99: 6281.35 | V99: 6229.2 | W99: 5438.4 | X99: 6170.05 | Y99: 6601.05 | Z99: 6821.45 | AA99: 6325.15 | AB99: 5861.85 | AC99: 6067.35 | AD99: 6802.4 | AE99: 7663.7475 | AF99: 7085 | AG99: 6758.55 | AH99: 194028.75
B100: KALLPA GENERACION S.A. | C100: C.T. KALLPA | D100: TG1 | E100: TERMOELÉCTRICA | F100: 4465.75 | G100: 3473.2 | H100: 3258.65 | I100: 4232.1 | J100: 4356.3 | K100: 4024.05 | L100: 4220.95 | M100: 4487.95 | N100: 4313.65 | O100: 3632.7 | P100: 4208.8 | Q100: 4410.5 | R100: 4415 | S100: 4350.15 | T100: 4423.5 | U100: 4414.85 | V100: 4391.35 | W100: 4366.6 | X100: 4388.6 | Y100: 4470.95 | Z100: 4467.1 | AA100: 4326.95 | AB100: 4284.4 | AC100: 4042.05 | AD100: 4119.45 | AE100: 4305.8962 | AF100: 4514.7 | AG100: 4535.3 | AH100: 118901.45
B101: KALLPA GENERACION S.A. | C101: C.T. KALLPA | D101: TG2 | E101: TERMOELÉCTRICA | F101: 4887.85 | G101: 3486.25 | H101: 3330.6 | I101: 4605.75 | J101: 4699.2 | K101: 4336.4 | L101: 4471.1 | M101: 4924 | N101: 4660.8 | O101: 3763.45 | P101: 4504.95 | Q101: 4766.7 | R101: 4735.15 | S101: 4862.85 | T101: 4705.4 | U101: 4721.8 | V101: 4718.45 | W101: 4630.7 | X101: 4623.95 | Y101: 4856.95 | Z101: 4834.15 | AA101: 4611.35 | AB101: 4534.8 | AC101: 4275 | AD101: 4398.45 | AE101: 4631.6027 | AF101: 4910.15 | AG101: 4875.6 | AH101: 127363.4
B102: KALLPA GENERACION S.A. | C102: C.T. KALLPA | D102: TG3 | E102: TERMOELÉCTRICA | F102: 4947.05 | G102: 3486.75 | H102: 3338.85 | I102: 4656.9 | J102: 4759.55 | K102: 4376.4 | L102: 4505.5 | M102: 5000.55 | N102: 4702.1 | O102: 3791 | P102: 4543.85 | Q102: 4816.15 | R102: 4768.15 | S102: 4923.55 | T102: 4705.75 | U102: 4729.85 | V102: 4739.1 | W102: 4655.25 | X102: 4734.05 | Y102: 4889.45 | Z102: 4873.2 | AA102: 4640.2 | AB102: 4567.65 | AC102: 4307.8 | AD102: 4438.35 | AE102: 4693.6748 | AF102: 4935.4 | AG102: 4880.75 | AH102: 128406.82
B103: KALLPA GENERACION S.A. | C103: C.T. KALLPA | D103: TV | E103: TERMOELÉCTRICA | F103: 6849.55 | G103: 5744.6 | H103: 5618.5 | I103: 6669.15 | J103: 6685.9 | K103: 6459.35 | L103: 6596.25 | M103: 6926.95 | N103: 6690.5 | O103: 5963.95 | P103: 6539.1 | Q103: 6780 | R103: 6631.8 | S103: 6597.9 | T103: 6633.6 | U103: 6750.9 | V103: 6610.6 | W103: 6591.1 | X103: 6724.65 | Y103: 6773.15 | Z103: 6803.65 | AA103: 6618.4 | AB103: 6587.65 | AC103: 6318.35 | AD103: 6440.15 | AE103: 6637.1613 | AF103: 6879.75 | AG103: 6802.75 | AH103: 183925.36
...

Sheet G_AREAS
B3: jueves, 28 de Agosto del 2025
B5: HORA | C5: RESUMEN DE GENERACIÓN POR ÁREAS DEL SEIN | D5: RESUMEN DE GENERACIÓN POR ÁREAS DEL SEIN | E5: RESUMEN DE GENERACIÓN POR ÁREAS DEL SEIN | F5: RESUMEN DE GENERACIÓN POR ÁREAS DEL SEIN | G5: RESUMEN DE GENERACIÓN POR ÁREAS DEL SEIN | H5: RESUMEN DE GENERACIÓN POR ÁREAS DEL SEIN | I5: RESUMEN DE GENERACIÓN POR ÁREAS DEL SEIN | J5: RESUMEN DE GENERACIÓN POR ÁREAS DEL SEIN | K5: RESUMEN DE GENERACIÓN POR ÁREAS DEL SEIN | L5: RESUMEN DE GENERACIÓN POR ÁREAS DEL SEIN | M5: RESUMEN DE GENERACIÓN POR ÁREAS DEL SEIN | N5: RESUMEN DE GENERACIÓN POR ÁREAS DEL SEIN | O5: RESUMEN DE GENERACIÓN POR ÁREAS DEL SEIN | P5: RESUMEN DE GENERACIÓN POR ÁREAS DEL SEIN | Q5: RESUMEN DE GENERACIÓN POR ÁREAS DEL SEIN | R5: RESUMEN DE GENERACIÓN POR ÁREAS DEL SEIN | S5: HORA | T5: GENERACIÓN POR TIPO DE GENERACIÓN | U5: GENERACIÓN POR TIPO DE GENERACIÓN | V5: GENERACIÓN POR TIPO DE GENERACIÓN | W5: GENERACIÓN POR TIPO DE GENERACIÓN | X5: GENERACIÓN POR TIPO DE GENERACIÓN | Y5: HORA | Z5: GENERACIÓN POR TIPO DE GENERACIÓN | AA5: GENERACIÓN POR TIPO DE GENERACIÓN | AB5: GENERACIÓN POR TIPO DE GENERACIÓN | AC5: GENERACIÓN POR TIPO DE GENERACIÓN | AD5: GENERACIÓN POR TIPO DE GENERACIÓN
