Workbook

Sheet EVENTOS
B3: martes, 13 de Enero del 2026
B5: INFORMACIÓN DE EVENTOS PRINCIPALES EN SUS INSTALACIONES
B6: TIPO DE EVENTO | C6: EMPRESA | D6: UBICACIÓN | E6: TIPO DE EQUIPO | F6: EQUIPO | G6: INICIO | H6: FINAL | I6: DESCRIPCIÓN | J6: MW INDISP. | K6: INTERRUPCIÓN (SI/NO) | L6: TENSIÓN DE FALLA (kV)
B7: EVENTO | C7: CONELSUR LT SAC | D7: PORTILLO | E7: SUBESTACION | F7: SS.EE. | G7: 13/01/2026 00:00:00 | H7: 14/01/2026 00:00:00 | I7: DECLARACIÓN DE SITUACIÓN EXCEPCIONAL EN LA S.E. PORTILLO 60 kV | K7: NO
B8: EVENTO | C8: ELECTRO ORIENTE | D8: BELAUNDE TERRY - TARAPOTO | E8: LINEA DE TRANSMISION | F8: L-1018 | G8: 13/01/2026 11:25:00 | H8: 13/01/2026 11:57:00 | I8: DECLARACIÓN DE SITUACIÓN EXCEPCIONAL EN LA LÍNEA L-1018 (BELAUNDE TERRY - TARAPOTO) DE 138 kV | K8: NO
B9: FALLA | C9: PLUZ ENERGÍA PERÚ S.A.A. | D9: CHAVARRÍA | E9: BARRA | F9: SCV_CH | G9: 13/01/2026 14:04:51 | H9: 13/01/2026 15:21:00 | I9: DESCONEXIÓN DEL SVC DE LA S.E. CHAVARRIA | K9: NO | L9: 0
B10: EVENTO | C10: RED DE ENERGIA DEL PERU S.A. | D10: QUENCORO | E10: TRANSFORMADOR 3D | F10: T47-131 | G10: 13/01/2026 11:49:00 | H10: 13/01/2026 18:35:00 | I10: RECHAZO MANUAL DE CARGA POR SOBRECARGA DEL TRANSFORMADOR T47-131 DE 138/34,5/10,5 kV DE LA S.E. QUENCORO | K10: SI

Sheet RESTRIC_OPE
B3: martes, 13 de Enero del 2026
B5: RESTRICCIONES OPERATIVAS
B6: FECHA | C6: HORA INICIO | D6: HORA FINAL | E6: EMPRESA | F6: UBICACIÓN | G6: T.Eq. | H6: EQUIPO | I6: DESCRIPCIÓN
B7: 13/01/2026 | C7: 00:00 | D7: 24:00 | E7: ATLANTICA TRANSMISION SUR S.A. | F7: L. POROMA - OCONA | G7: LINEA | H7: L-5034 | I7: Capacidad limitado a 750 MVA debido a corte de hilo conductor caído(FASE S) en el tramo T50-T51.
B8: 13/01/2026 | C8: 00:00 | D8: 24:00 | E8: EGASA | F8: S.E. CONVERTIDOR | G8: BARRA | H8: BARRA138KV | I8: EGASA limitó la capacidad del transformador 138 kV/33 kV a 50 MVA por deterioro del aislamiento.
B9: 13/01/2026 | C9: 00:00 | D9: 24:00 | E9: ELECTROPERU | F9: C.H. MANTARO | G9: CH | H9: CENTRAL | I9: De acuerdo con el correo del día 25.08.2025, la central tiene una limitación de potencia máxima de 650 MW por seguridad de la central.
B10: 13/01/2026 | C10: 00:00 | D10: 12:29 | E10: EMPRESA DE GENERACION ELECTRICA SANTA ANA S.A.C. | F10: C.H. RENOVANDES H1 | G10: CH | H10: CENTRAL | I10: Indisponible por alta concentración de sólidos en suspensión
B11: 13/01/2026 | C11: 00:00 | D11: 24:00 | E11: ENEL GENERACION PIURA S.A. | F11: C.T. MALACAS | G11: CT | H11: CENTRAL | I11: De acuerdo con la comunicación vía correo del día 24.10.2024. ENEL GENERACIÓN PIURA informa una restricción de potencia para alcanzar 105 MW en simultaneo (TG6+TGN4).
B12: 13/01/2026 | C12: 00:00 | D12: 24:00 | E12: ENEL GENERACION PIURA S.A. | F12: C.T. MALACAS | G12: GT | H12: TG4 | I12: De acuerdo a lo informado mediante correo electrónico el día 25.10, con la disponibilidad actual de aproximadamente 13 MMPCD (368.12 Mm³) la unidad TG4 puede con una generación de 80 MW durante 5 horas, y a potencia mínima durante el resto de los periodos
B13: 13/01/2026 | C13: 00:00 | D13: 24:00 | E13: ENGIE ENERGIA PERU S.A.A. | F13: C.H. YUNCÁN | G13: GH | H13: G3 | I13: Según la carta N° ENG/ 198-2024 enviada por su representada, se opera de forma continua el G3 de la CH Yuncán, debido a la ejecución de mantenimientos necesarios para evitar daños en los sellos de seguridad de la válvula esférica del grupo.
B14: 13/01/2026 | C14: 00:00 | D14: 24:00 | E14: ENGIE ENERGIA PERU S.A.A. | F14: C.T. CHILCA 1 | G14: CT | H14: CENTRAL | I14: Restricción de temperatura de la C.T Chilca, ver valor en el modelo de despacho.
B15: 13/01/2026 | C15: 00:00 | D15: 24:00 | E15: ENGIE ENERGIA PERU S.A.A. | F15: C.T. CHILCA 1 | G15: CT | H15: CENTRAL | I15: Con carta ENG/971-2023, indica que no puede cumplir con las IO considerada en el PDO_17122023 dado que vulneran la seguridad de sus activos. Indican que se debe tomar TMO=168h.
B16: 13/01/2026 | C16: 00:00 | D16: 24:00 | E16: ENGIE ENERGIA PERU S.A.A. | F16: C.T. CHILCA 2 | G16: CT | H16: CENTRAL | I16: Con carta ENG/971-2023, indica que no puede cumplir con las IO considerada en el PDO_17122023 dado que vulneran la seguridad de sus activos. Indican que se debe tomar TMO=168h.
B17: 13/01/2026 | C17: 00:00 | D17: 24:00 | E17: FENIX POWER PERÚ | F17: C.T. FENIX | G17: CT | H17: CENTRAL | I17: De acuerdo con lo comunicado en el correo del día 06.05.2025, la CT Fenix cuenta con TMO de 168 hrs en todos sus modos de operación.
... B58: 13/01/2026 | C58: 00:00 | D58: 12:23 | E58: VARI ENERGIA S.A.C. | F58: C.H. ANASHIRONI | G58: CH | H58: C.H. ANASHIRONI | I58: Indisponible por alta concentración de sólidos en suspensión

Sheet MANTENIMIENTO EJECUTADOS
B3: martes, 13 de Enero del 2026
B5: Mantenimiento Ejecutado
B6: Empresa | C6: Ubicación | D6: Equipo | E6: Inicio | F6: Final | G6: Descripción | H6: MW Indisp. | I6: Prog. | J6: Dispon | K6: Interrupc. | L6: Tipo | M6: CodEq | N6: TipoEq_Osinerg
B7: ATLANTICA TRANSMISION SUR S.A. | C7: OCONA | D7: INT-5450 | E7: 13/01/2026 00:00 | F7: 14/01/2026 00:00 | G7: Interruptor INT-5450 cerrado con restriccion operativa, REB-5450 en servicio y suministrando los SS.AA. de la S.E. Oco?a. | H7: 0 | I7: P | J7: E/S | K7: N | L7: OTROS | M7: 13761 | N7: T
B8: ATLANTICA TRANSMISION SUR S.A. | C8: POROMA | D8: INT-5371 | E8: 13/01/2026 00:00 | F8: 14/01/2026 00:00 | G8: Seccionador SBB-5371 fase T indisponible por problemas mecanicos, el seccionador permanece cerrado y bloqueado | H8: 0 | I8: P | J8: E/S | K8: N | L8: OTROS | M8: 13751 | N8: T
B9: ATLANTICA TRANSMISION SUR S.A. | C9: POROMA | D9: REB-5350 | E9: 13/01/2026 00:00 | F9: 14/01/2026 00:00 | G9: Fuera de servicio por falla en el equipo. | H9: 0 | I9: P | J9: F/S | K9: N | L9: OTROS | M9: 13771 | N9: T
B10: ATLANTICA TRANSMISION SUR S.A. | C10: POROMA - OCONA | D10: L-5034 | E10: 13/01/2026 08:49 | F10: 13/01/2026 17:51 | G10: Mantenimiento en pedestales de torres de la L-5034. | H10: 0 | I10: P | J10: E/S | K10: N | L10: PREV. | M10: 13743 | N10: T
B11: ATN 2 S.A. | C11: COTARUSE - LAS BAMBAS | D11: L-2055 | E11: 13/01/2026 07:47 | F11: 13/01/2026 14:37 | G11: A solicitud de REP: Revision y pruebas de disparo al interruptor IN-2786 | H11: 0 | I11: P | J11: F/S | K11: N | L11: OTROS | M11: 14930 | N11: T
B12: ATN S.A. | C12: KIMAN AYLLU | D12: AUT-501 | E12: 13/01/2026 00:00 | F12: 14/01/2026 00:00 | G12: Restriccion Operativa en el circuito de control de cambiador de tap s del AUT-501 | H12: 0 | I12: P | J12: E/S | K12: N | L12: OTROS | M12: 13099 | N12: T
B13: CHINANGO S.A.C. | C13: CHIMAY | D13: CENTRAL | E13: 13/01/2026 00:00 | F13: 14/01/2026 00:00 | G13: Fuera de servicio por alta concentracion de solidos 2.3 gr/lt y caudal 170 m3/seg. | H13: 150 | I13: F | J13: F/S | K13: N | L13: OTROS | M13: 1191 | N13: G
B14: CHINANGO S.A.C. | C14: YANANGO | D14: G1 | E14: 13/01/2026 07:14 | F14: 14/01/2026 00:00 | G14: FUERA DE SERVICIO POR ALTA CONCENTRACION DE SOLIDOS 6.2 gr/lt Y CAUDAL 65 m3/seg. | H14: 42 | I14: F | J14: F/S | K14: N | L14: OTROS | M14: 108 | N14: G
B15: CONELSUR LT SAC | C15: CALLAHUANCA (CNS) | D15: S.E. | E15: 13/01/2026 00:00 | F15: 14/01/2026 00:00 | G15: RELE DIFERENCIAL DE BARRAS DE CALLAHUANCA 220KV INOPERATIVO | H15: 0 | I15: P | J15: E/S | K15: N | L15: OTROS | M15: 316 | N15: T
B16: EGASA | C16: SANTUARIO | D16: ACOPLE 138 | E16: 13/01/2026 00:00 | F16: 14/01/2026 00:00 | G16: En servicio barra 2,uso en grupo N1 Charcani V con interruptor de acoplamiento, por falla | H16: 0 | I16: P | J16: E/S | K16: N | L16: OTROS | M16: 11052 | N16: T
B17: EGESUR | C17: CT INDEPENDENCIA | D17: TR1 (Reserva) | E17: 13/01/2026 00:00 | F17: 14/01/2026 00:00 | G17: Transformador E/S con el Conmutador de Taps sin carga Deshabilitado | H17: 0 | I17: P | J17: E/S | K17: N | L17: OTROS | M17: 19961 | N17: T
B18: EGESUR | C18: INDEPENDENCIA | D18: INDEP_G3 | E18: 13/01/2026 00:00 | F18: 14/01/2026 00:00 | G18: Mantenimiento correctivo de lazo de comunicacion WECS - PLC | H18: 5.732 | I18: P | J18: F/S | K18: N | L18: CORR. | M18: 12779 | N18: G
... B120: TRANSMANTARO | C120: YARABAMBA | D120: CL-R-30 | E120: 13/01/2026 00:00 | F120: 14/01/2026 00:00 | G120: CL-R30 CON MANDO SINCRONIZADO ASOCIADO AL INTERRUPTOR IN-5147 INDISPONIBLE. EL 20.11.25 NO PUDO SER AJUSTADO DEBIDO A ANOMALIA EN LA CUCHILLA DE PUESTA A TIERRA ST-5027. | H120: 0 | I120: P | J120: E/S | K120: N | L120: OTROS | M120: 17424 | N120: T

Sheet INGRESO OC
A3: martes, 13 de Enero del 2026
A5: INGRESO A OPERACIÓN COMERCIAL
A6: EMPRESA | B6: TIPO DE EQUIPO | C6: UBICACIÓN | D6: EQUIPO | E6: Fecha y hora de Ingreso a Operación Comercial

Sheet DESPACHO_EJECUTADO
B3: martes, 13 de Enero del 2026
A5: POTENCIA ACTIVA EJECUTADA DE LAS UNIDADES DE GENERACIÓN DEL SEIN (MW) | FP5: CENTRALES NO INTEGRANTES COES
A6: FECHA | B6: HORA | C6: 65333 | D6: 101 | E6: 102 | F6: 42667 | G6: 42668 | H6: 126 | I6: 127 | J6: 138 | K6: 139 | L6: 197 | M6: 203 | N6: 204 | O6: 230 | P6: 209 | Q6: 56677 | R6: 796 | S6: 2146 | T6: 142 | U6: 143 | V6: 125 | W6: 187 | X6: 163 | Y6: 298 | Z6: 299 | AA6: 219 | AB6: 151 | AC6: 152 | AD6: 153 | AE6: 154 | AF6: 756 | AG6: 156 | AH6: 155 | AI6: 182 | AJ6: 212 | AK6: 758 | AL6: 263 | AM6: 265 | AN6: 775 | AO6: 777 | AP6: 2154 | AQ6: 150 | AR6: 149 | AS6: 188 | AT6: 2131 | AU6: 755 | AV6: 252 | AW6: 249 | AX6: 250 | AY6: 117 | AZ6: 119 | BA6: 120 | BB6: 189 | BC6: 122 | BD6: 266 | BE6: 337 | BF6: 338 | BG6: 251 | BH6: 115 | BI6: 239 | BJ6: 288 | BK6: 240 | BL6: 241 | BM6: 242 | BN6: 191 | BO6: 194 | BP6: 196 | BQ6: 207 | BR6: 236 | BS6: 795 | BT6: 285 | BU6: 995 | BV6: 996 | BW6: 997 | BX6: 766 | BY6: 926 | BZ6: 924 | CA6: 121 | CB6: 103 | CC6: 104 | CD6: 106 | CE6: 105 | CF6: 107 | CG6: 110 | CH6: 109 | CI6: 144 | CJ6: 113 | CK6: 114 | CL6: 193 | CM6: 208 | CN6: 786 | CO6: 787 | CP6: 788 | CQ6: 789 | CR6: 248 | CS6: 2159 | CT6: 267 | CU6: 268 | CV6: 2194 | CW6: 303 | CX6: 59715 | CY6: 62255 | CZ6: 1263 | DA6: 61800 | DB6: 69125 | DC6: 216 | DD6: 198 | DE6: 70400 | DF6: 49607 | DG6: 214 | DH6: 260 | DI6: 2152 | DJ6: 2128 | DK6: 247 | DL6: 228 | DM6: 2135 | DN6: 261 | DO6: 237 | DP6: 253 | DQ6: 770 | DR6: 235 | DS6: 238 | DT6: 2184 | DU6: 61855 | DV6: 223 | DW6: 75566 | DX6: 226 | DY6: 201 | DZ6: 258 | EA6: 259 | EB6: 920 | EC6: 257 | ED6: 256 | EE6: 2148 | EF6: 58288 | EG6: 58289 | EH6: 58839 | EI6: 58840 | EJ6: 75260 | EK6: 296 | EL6: 297 | EM6: 211 | EN6: 2175 | EO6: 2178 | EP6: 2181 | EQ6: 1262 | ER6: 63425 | ES6: 233 | ET6: 2150 | EU6: 2165 | EV6: 2161 | EW6: 61197 | EX6: 58851 | EY6: 225 | EZ6: 2201 | FA6: 2171 | FB6: 760 | FC6: 234 | FD6: 215 | FE6: 917 | FF6: 289 | FG6: 58333 | FH6: 58336 | FI6: 213 | FJ6: 232 | FK6: 2190 | FL6: 69867 | FM6: 75066 | FN6: TOTAL COES | FP6: 221 | FQ6: 222 | FR6: 224 | FS6: 2187 | FT6: 227 | FU6: 49400 | FV6: 199 | FW6: 200 | FX6: TOTAL NO COES
C7: SUR | D7: CENTRO | E7: CENTRO | F7: NORTE | G7: NORTE | H7: NORTE | I7: NORTE | J7: CENTRO | K7: CENTRO | L7: CENTRO | M7: CENTRO | N7: CENTRO | O7: CENTRO | P7: CENTRO | Q7: CENTRO | R7: CENTRO | S7: CENTRO | T7: CENTRO | U7: CENTRO | V7: CENTRO | W7: CENTRO | X7: SUR | Y7: SUR | Z7: SUR | AA7: CENTRO | AB7: SUR | AC7: SUR | AD7: SUR | AE7: SUR | AF7: SUR | AG7: SUR | AH7: SUR | AI7: SUR | AJ7: CENTRO | AK7: NORTE | AL7: NORTE | AM7: NORTE | AN7: CENTRO | AO7: CENTRO | AP7: CENTRO | AQ7: CENTRO | AR7: CENTRO | AS7: CENTRO | AT7: CENTRO | AU7: SUR | AV7: CENTRO | AW7: CENTRO | AX7: CENTRO | AY7: CENTRO | AZ7: CENTRO | BA7: CENTRO | BB7: SUR | BC7: NORTE | BD7: CENTRO | BE7: CENTRO | BF7: CENTRO | BG7: CENTRO | BH7: NORTE | BI7: NORTE | BJ7: NORTE | BK7: SUR | BL7: SUR | BM7: SUR | BN7: CENTRO | BO7: CENTRO | BP7: CENTRO | BQ7: CENTRO | BR7: CENTRO | BS7: CENTRO | BT7: CENTRO | BU7: SUR | BV7: SUR | BW7: SUR | BX7: NORTE | BY7: SUR | BZ7: CENTRO | CA7: NORTE | CB7: CENTRO | CC7: CENTRO | CD7: CENTRO | CE7: CENTRO | CF7: CENTRO | CG7: CENTRO | CH7: CENTRO | CI7: CENTRO | CJ7: CENTRO | CK7: CENTRO | CL7: CENTRO | CM7: CENTRO | CN7: SUR | CO7: SUR | CP7: SUR | CQ7: SUR | CR7: CENTRO | CS7: CENTRO | CT7: CENTRO | CU7: CENTRO | CV7: NORTE | CW7: CENTRO | CX7: CENTRO | CY7: SUR | CZ7: NORTE | DA7: NORTE | DB7: CENTRO | DC7: NORTE | DD7: NORTE | DE7: SUR | DF7: SUR | DG7: CENTRO | DH7: CENTRO | DI7: CENTRO | DJ7: NORTE | DK7: NORTE | DL7: CENTRO | DM7: CENTRO | DN7: SUR | DO7: SUR | DP7: CENTRO | DQ7: CENTRO | DR7: SUR | DS7: CENTRO | DT7: CENTRO | DU7: NORTE | DV7: CENTRO | DW7: CENTRO | DX7: CENTRO | DY7: NORTE | DZ7: CENTRO | EA7: CENTRO | EB7: CENTRO | EC7: NORTE | ED7: NORTE | EE7: SUR | EF7: CENTRO | EG7: CENTRO | EH7: CENTRO | EI7: CENTRO | EJ7: SUR | EK7: CENTRO | EL7: CENTRO | EM7: SUR | EN7: SUR | EO7: SUR | EP7: SUR | EQ7: NORTE | ER7: SUR | ES7: SUR | ET7: SUR | EU7: CENTRO | EV7: CENTRO | EW7: CENTRO | EX7: SUR | EY7: CENTRO | EZ7: CENTRO | FA7: CENTRO | FB7: CENTRO | FC7: SUR | FD7: NORTE | FE7: CENTRO | FF7: NORTE | FG7: NORTE | FH7: NORTE | FI7: CENTRO | FJ7: NORTE | FK7: NORTE | FL7: NORTE | FM7: NORTE | FP7: NORTE | FQ7: CENTRO | FR7: NORTE | FS7: NORTE | FT7: NORTE | FU7: NORTE | FV7: NORTE | FW7: NORTE
C8: HIDROELÉCTRICA | D8: HIDROELÉCTRICA | E8: HIDROELÉCTRICA | F8: TERMOELÉCTRICA | G8: TERMOELÉCTRICA | H8: HIDROELÉCTRICA | I8: HIDROELÉCTRICA | J8: TERMOELÉCTRICA | K8: TERMOELÉCTRICA | L8: TERMOELÉCTRICA | M8: TERMOELÉCTRICA | N8: TERMOELÉCTRICA | O8: TERMOELÉCTRICA | P8: TERMOELÉCTRICA | Q8: TERMOELÉCTRICA | R8: HIDROELÉCTRICA | S8: HIDROELÉCTRICA | T8: TERMOELÉCTRICA | U8: TERMOELÉCTRICA | V8: TERMOELÉCTRICA | W8: TERMOELÉCTRICA | X8: HIDROELÉCTRICA | Y8: HIDROELÉCTRICA | Z8: HIDROELÉCTRICA | AA8: TERMOELÉCTRICA | AB8: HIDROELÉCTRICA | AC8: HIDROELÉCTRICA | AD8: HIDROELÉCTRICA | AE8: HIDROELÉCTRICA | AF8: TERMOELÉCTRICA | AG8: TERMOELÉCTRICA | AH8: TERMOELÉCTRICA | AI8: HIDROELÉCTRICA | AJ8: HIDROELÉCTRICA | AK8: TERMOELÉCTRICA | AL8: TERMOELÉCTRICA | AM8: TERMOELÉCTRICA | AN8: HIDROELÉCTRICA | AO8: HIDROELÉCTRICA | AP8: HIDROELÉCTRICA | AQ8: HIDROELÉCTRICA | AR8: HIDROELÉCTRICA | AS8: HIDROELÉCTRICA | AT8: HIDROELÉCTRICA | AU8: HIDROELÉCTRICA | AV8: TERMOELÉCTRICA | AW8: TERMOELÉCTRICA | AX8: TERMOELÉCTRICA | AY8: HIDROELÉCTRICA | AZ8: HIDROELÉCTRICA | BA8: HIDROELÉCTRICA | BB8: HIDROELÉCTRICA | BC8: HIDROELÉCTRICA | BD8: HIDROELÉCTRICA | BE8: HIDROELÉCTRICA | BF8: HIDROELÉCTRICA | BG8: HIDROELÉCTRICA | BH8: TERMOELÉCTRICA | BI8: TERMOELÉCTRICA | BJ8: TERMOELÉCTRICA | BK8: TERMOELÉCTRICA | BL8: TERMOELÉCTRICA | BM8: TERMOELÉCTRICA | BN8: HIDROELÉCTRICA | BO8: TERMOELÉCTRICA | BP8: TERMOELÉCTRICA | BQ8: TERMOELÉCTRICA | BR8: TERMOELÉCTRICA | BS8: TERMOELÉCTRICA | BT8: TERMOELÉCTRICA | BU8: TERMOELÉCTRICA | BV8: TERMOELÉCTRICA | BW8: TERMOELÉCTRICA | BX8: HIDROELÉCTRICA | BY8: TERMOELÉCTRICA | BZ8: TERMOELÉCTRICA | CA8: HIDROELÉCTRICA | CB8: HIDROELÉCTRICA | CC8: HIDROELÉCTRICA | CD8: HIDROELÉCTRICA | CE8: HIDROELÉCTRICA | CF8: HIDROELÉCTRICA | CG8: TERMOELÉCTRICA | CH8: TERMOELÉCTRICA | CI8: TERMOELÉCTRICA | CJ8: TERMOELÉCTRICA | CK8: TERMOELÉCTRICA | CL8: TERMOELÉCTRICA | CM8: TERMOELÉCTRICA | CN8: TERMOELÉCTRICA | CO8: TERMOELÉCTRICA | CP8: TERMOELÉCTRICA | CQ8: TERMOELÉCTRICA | CR8: TERMOELÉCTRICA | CS8: TERMOELÉCTRICA | CT8: HIDROELÉCTRICA | CU8: HIDROELÉCTRICA | CV8: HIDROELÉCTRICA | CW8: SOLAR | CX8: EÓLICA | CY8: SOLAR | CZ8: EÓLICA | DA8: SOLAR | DB8: HIDROELÉCTRICA | DC8: HIDROELÉCTRICA | DD8: HIDROELÉCTRICA | DE8: SOLAR | DF8: HIDROELÉCTRICA | DG8: HIDROELÉCTRICA | DH8: HIDROELÉCTRICA | DI8: HIDROELÉCTRICA | DJ8: HIDROELÉCTRICA | DK8: HIDROELÉCTRICA | DL8: HIDROELÉCTRICA | DM8: HIDROELÉCTRICA | DN8: SOLAR | DO8: SOLAR | DP8: EÓLICA | DQ8: EÓLICA | DR8: SOLAR | DS8: HIDROELÉCTRICA | DT8: HIDROELÉCTRICA | DU8: HIDROELÉCTRICA | DV8: HIDROELÉCTRICA | DW8: SOLAR | DX8: HIDROELÉCTRICA | DY8: HIDROELÉCTRICA | DZ8: HIDROELÉCTRICA | EA8: HIDROELÉCTRICA | EB8: HIDROELÉCTRICA | EC8: EÓLICA | ED8: EÓLICA | EE8: SOLAR | EF8: EÓLICA | EG8: EÓLICA | EH8: EÓLICA | EI8: EÓLICA | EJ8: SOLAR | EK8: HIDROELÉCTRICA | EL8: HIDROELÉCTRICA | EM8: HIDROELÉCTRICA | EN8: HIDROELÉCTRICA | EO8: HIDROELÉCTRICA | EP8: HIDROELÉCTRICA | EQ8: EÓLICA | ER8: SOLAR | ES8: SOLAR | ET8: SOLAR | EU8: HIDROELÉCTRICA | EV8: EÓLICA | EW8: EÓLICA | EX8: SOLAR | EY8: TERMOELÉCTRICA | EZ8: TERMOELÉCTRICA | FA8: TERMOELÉCTRICA | FB8: TERMOELÉCTRICA | FC8: SOLAR | FD8: HIDROELÉCTRICA | FE8: HIDROELÉCTRICA | FF8: TERMOELÉCTRICA | FG8: TERMOELÉCTRICA | FH8: TERMOELÉCTRICA | FI8: TERMOELÉCTRICA | FJ8: TERMOELÉCTRICA | FK8: TERMOELÉCTRICA | FL8: TERMOELÉCTRICA | FM8: TERMOELÉCTRICA | FP8: HIDROELÉCTRICA | FQ8: HIDROELÉCTRICA | FR8: HIDROELÉCTRICA | FS8: HIDROELÉCTRICA | FT8: TERMOELÉCTRICA | FU8: TERMOELÉCTRICA | FV8: HIDROELÉCTRICA | FW8: HIDROELÉCTRICA
C9: HYDRO GLOBAL PERÚ S.A.C. | D9: ELECTROPERU | E9: ELECTROPERU | F9: ELECTROPERU | G9: ELECTROPERU | H9: ORAZUL ENERGY PERÚ | I9: ORAZUL ENERGY PERÚ | J9: TERMOSELVA | K9: TERMOSELVA | L9: KALLPA GENERACION S.A. | M9: KALLPA GENERACION S.A. | N9: KALLPA GENERACION S.A. | O9: KALLPA GENERACION S.A. | P9: KALLPA GENERACION S.A. | Q9: KALLPA GENERACION S.A. | R9: KALLPA GENERACION S.A. | S9: KALLPA GENERACION S.A. | T9: SHOUGESA | U9: SHOUGESA | V9: SHOUGESA | W9: SHOUGESA | X9: EGEMSA | Y9: EGESUR | Z9: EGESUR | AA9: EGESUR | AB9: EGASA | AC9: EGASA | AD9: EGASA | AE9: EGASA | AF9: EGASA | AG9: EGASA | AH9: EGASA | AI9: SAN GABAN | AJ9: CELEPSA | AK9: MINERA CERRO VERDE | AL9: PLANTA DE RESERVA FRIA DE GENERACION DE ETEN S.A. | AM9: PLANTA DE RESERVA FRIA DE GENERACION DE ETEN S.A. | AN9: EMPRESA DE GENERACION HUALLAGA | AO9: EMPRESA DE GENERACION HUALLAGA | AP9: LA VIRGEN | AQ9: CHINANGO S.A.C. | AR9: CHINANGO S.A.C. | AS9: HIDROELECTRICA HUANCHOR S.A.C. | AT9: CELEPSA RENOVABLES S.R.L. | AU9: INLAND ENERGY SAC | AV9: FENIX POWER PERÚ | AW9: FENIX POWER PERÚ | AX9: FENIX POWER PERÚ | AY9: STATKRAFT S.A | AZ9: STATKRAFT S.A | BA9: STATKRAFT S.A | BB9: STATKRAFT S.A | BC9: STATKRAFT S.A | BD9: STATKRAFT S.A | BE9: CENTRALES SANTA ROSA S.A.C. | BF9: CENTRALES SANTA ROSA S.A.C. | BG9: EMPRESA DE GENERACION HUANZA | BH9: ENEL GENERACION PIURA S.A. | BI9: ENEL GENERACION PIURA S.A. | BJ9: ENEL GENERACION PIURA S.A. | BK9: ENGIE ENERGIA PERU S.A.A. | BL9: ENGIE ENERGIA PERU S.A.A. | BM9: ENGIE ENERGIA PERU S.A.A. | BN9: ENGIE ENERGIA PERU S.A.A. | BO9: ENGIE ENERGIA PERU S.A.A. | BP9: ENGIE ENERGIA PERU S.A.A. | BQ9: ENGIE ENERGIA PERU S.A.A. | BR9: ENGIE ENERGIA PERU S.A.A. | BS9: ENGIE ENERGIA PERU S.A.A. | BT9: ENGIE ENERGIA PERU S.A.A. | BU9: ENGIE ENERGIA PERU S.A.A. | BV9: ENGIE ENERGIA PERU S.A.A. | BW9: ENGIE ENERGIA PERU S.A.A. | BX9: ENGIE ENERGIA PERU S.A.A. | BY9: INFRAESTRUCTURAS Y ENERGIAS DEL PERU S.A.C. | BZ9: INFRAESTRUCTURAS Y ENERGIAS DEL PERU S.A.C. | CA9: INVERSIONES SHAQSHA S.A.C. | CB9: ORYGEN PERU S.A.A. | CC9: ORYGEN PERU S.A.A. | CD9: ORYGEN PERU S.A.A. | CE9: ORYGEN PERU S.A.A. | CF9: ORYGEN PERU S.A.A. | CG9: ORYGEN PERU S.A.A. | CH9: ORYGEN PERU S.A.A. | CI9: ORYGEN PERU S.A.A. | CJ9: ORYGEN PERU S.A.A. | CK9: ORYGEN PERU S.A.A. | CL9: ORYGEN PERU S.A.A. | CM9: ORYGEN PERU S.A.A. | CN9: SAMAY I S.A.C | CO9: SAMAY I S.A.C | CP9: SAMAY I S.A.C | CQ9: SAMAY I S.A.C | CR9: TERMOCHILCA S.A.C. | CS9: TERMOCHILCA S.A.C. | CT9: TRANSMISION ANDINA DE GENERACION S.A.C. | CU9: TRANSMISION ANDINA DE GENERACION S.A.C. | CV9: CELARIS ENERGY S.A. | CW9: COLCA SOLAR S.A.C. | CX9: ENERGIA RENOVABLE DEL SUR S.A. | CY9: GR CORTARRAMA SOCIEDAD ANONIMA CERRADA | CZ9: GR TARUCA SOCIEDAD ANONIMA CERRADA | DA9: KONDU SAC | DB9: VARI ENERGIA S.A.C. | DC9: ORAZUL ENERGY PERÚ | DD9: ORAZUL ENERGY PERÚ | DE9: KALLPA GENERACION S.A. | DF9: SAN GABAN | DG9: MAJA ENERGIA S.A.C. | DH9: EMPRESA DE GENERACION ELECTRICA CANCHAYLLO SAC | DI9: EMPRESA DE GENERACION ELECTRICA SANTA ANA S.A.C. | DJ9: EMPRESA ELECTRICA AGUA AZUL | DK9: EMPRESA ELECTRICA RIO DOBLE | DL9: HIDROCAÑETE S.A. | DM9: HUAURA POWER GROUP S.A. | DN9: MOQUEGUA FV S.A.C. | DO9: PANAMERICANA SOLAR SAC. | DP9: PARQUE EOLICO MARCONA S.A.C. | DQ9: PARQUE EOLICO TRES HERMANAS S.A.C. | DR9: TACNA SOLAR SAC. | DS9: ELECTRICA YANAPAMPA SAC | DT9: ANDEAN POWER S.A.C. | DU9: ASOCIACIÓN SANTA LUCIA DE CHACAS | DV9: ATRIA ENERGIA S.A.C. | DW9: COENERGY S.A.C. | DX9: EGEJUNIN | DY9: EGEJUNIN | DZ9: EGEJUNIN | EA9: EGEJUNIN | EB9: EMPRESA DE GENERACION ELECTRICA RIO BAÑOS S.A.C. | EC9: ENERGÍA EÓLICA S.A. | ED9: ENERGÍA EÓLICA S.A. | EE9: ENGIE ENERGIA PERU S.A.A. | EF9: ENGIE ENERGIA PERU S.A.A. | EG9: ENGIE ENERGIA PERU S.A.A. | EH9: ENGIE ENERGIA PERU S.A.A. | EI9: ENGIE ENERGIA PERU S.A.A. | EJ9: ENGIE ENERGIA PERU S.A.A. | EK9: GENERACIÓN ANDINA S.A.C. | EL9: GENERACIÓN ANDINA S.A.C. | EM9: GENERADORA DE ENERGÍA DEL PERÚ | EN9: GENERADORA DE ENERGÍA DEL PERÚ | EO9: GENERADORA DE ENERGÍA DEL PERÚ | EP9: GENERADORA DE ENERGÍA DEL PERÚ | EQ9: GR PAINO SOCIEDAD ANONIMA CERRADA | ER9: JOYA SOLAR S.A.C. | ES9: MAJES ARCUS S.A.C. | ET9: ORYGEN PERU S.A.A. | EU9: ORYGEN PERU S.A.A. | EV9: ORYGEN PERU S.A.A. | EW9: ORYGEN PERU S.A.A. | EX9: ORYGEN PERU S.A.A. | EY9: PETRAMAS | EZ9: PETRAMAS | FA9: PETRAMAS | FB9: PETRAMAS | FC9: REPARTICIÓN ARCUS S.A.C. | FD9: SINERSA | FE9: SINERSA | FF9: BIOENERGIA DEL CHIRA S.A. | FG9: GM OPERACIONES S.A.C. | FH9: GM OPERACIONES S.A.C. | FI9: AGRO INDUSTRIAL PARAMONGA S.A. | FJ9: AGROAURORA S.A.C. | FK9: AGROINDUSTRIAS SAN JACINTO S.A.A. | FL9: AGROLMOS SOCIEDAD ANONIMA - AGROLMOS S.A. | FM9: CASA GRANDE S.A.A. | FP9: UNACEM PERU S.A. | FQ9: ELECTRO ORIENTE | FR9: AGUAS Y ENERGIA PERU | FS9: ELECTRO ZAÑA S.A.C. | FT9: ELECTRONOROESTE S.A. | FU9: SDE PIURA | FV9: SINERSA | FW9: SINERSA
C10: SAN GABAN III | D10: MANTARO | E10: RESTITUCION | F10: TUMBES MAK 1 | G10: TUMBES MAK 2 | H10: CARHUAQUERO | I10: CAÑON DEL PATO | J10: AGUAYTIA TG1 | K10: AGUAYTIA TG2 | L10: KALLPA TG1 | M10: KALLPA TG2 | N10: KALLPA TG3 | O10: KALLPA TV | P10: LFLORES TG1 | Q10: LFLORES TV | R10: CERRO DEL AGUILA | S10: CERRODELAGUILAG4 | T10: SHOUGESA TV1 | U10: SHOUGESA TV2 | V10: SHOUGESA TV3 | W10: SHOUGESA CUMMINS | X10: MACHUPICCHU | Y10: ARICOTA 1 | Z10: ARICOTA 2 | AA10: INDEPENDENCIA | AB10: CHARCANI I,II,III | AC10: CHARCANI IV | AD10: CHARCANI V | AE10: CHARCANI VI | AF10: CHILINA TG | AG10: MOLLENDO 1, 2, 3 | AH10: CHILINA (SULZ 1,2) | AI10: SAN GABAN II | AJ10: PLATANAL | AK10: RECKA | AL10: RF ETEN TG1 | AM10: RF ETEN TG2 | AN10: CHAGLLA GP1 | AO10: CHAGLLA | AP10: LA VIRGEN | AQ10: CHIMAY | AR10: YANANGO | AS10: HUANCHOR | AT10: MARAÑON | AU10: STA TERESA | AV10: FENIX GT11 | AW10: FENIX GT12 | AX10: FENIX TV10 | AY10: YAUPI | AZ10: MALPASO | BA10: CAHUA | BB10: ARCATA | BC10: GALLITO CIEGO | BD10: CHEVES | BE10: SANTA ROSA 1 | BF10: SANTA ROSA 2 | BG10: HUANZA | BH10: MALACAS2 TG4 | BI10: MALACAS3 TG 5 | BJ10: MALACAS1 TG6 | BK10: RF ILO2 TG1 | BL10: RF ILO2 TG2 | BM10: RF ILO2 TG3 | BN10: YUNCAN | BO10: CHILCA1 TG1 | BP10: CHILCA1 TG2 | BQ10: CHILCA1 TG3 | BR10: CHILCA-TV | BS10: CHILCA2 TG41 | BT10: CHILCA2-TV | BU10: CTNEPI_TG41 | BV10: CTNEPI_TG42 | BW10: CTNEPI_TG43 | BX10: QUITARACSA | BY10: RF PTO MALDONADO | BZ10: RF PUCALLPA | CA10: PARIAC | CB10: HUINCO | CC10: MATUCANA | CD10: MOYOPAMPA | CE10: CALLAHUANCA | CF10: HUAMPANI | CG10: STA ROSA WEST TG7 | CH10: UTI_5 | CI10: UTI_6 | CJ10: VENTANILLA 3 | CK10: VENTANILLA 4 | CL10: VENTANILLA TV | CM10: STAROSA TG8 | CN10: PTO_BRVO TG1 | CO10: PTO_BRVO TG2 | CP10: PTO_BRVO TG3 | CQ10: PTO_BRVO TG4 | CR10: OLLEROS TG1 | CS10: OLLEROS TV | CT10: OROYA | CU10: PACHACHACA | CV10: MANTA I | CW10: CS YARUCAYA | CX10: SAN JUAN | CY10: MATARANI | CZ10: DUNA | DA10: CARHUAQUERO (CS) | DB10: ANASHIRONI | DC10: CARHUAQUERO4 | DD10: CAÑA BRAVA | DE10: SUNNY | DF10: TUPURI | DG10: RONCADOR | DH10: CANCHAYLLO | DI10: RENOVANDESH1 | DJ10: POTRERO | DK10: PIZARRAS | DL10: NIMPERIAL | DM10: YARUCAYA | DN10: MOQUEGUA-SOLAR | DO10: PANAMERICANA-SOLAR | DP10: PQE-EOLICO-MARCONA | DQ10: PQE-EOLICO-3-HERMANAS | DR10: TACNA-SOLAR | DS10: YANAPAMPA | DT10: CARHUAC | DU10: HUALLIN | DV10: PURMACANA | DW10: COENERGY | DX10: HUASAHUASI | DY10: STACRUZ_1_2 | DZ10: RUNATULLO_II | EA10: RUNATULLO_III | EB10: RUCUY | EC10: PQE-EOLICO-TALARA | ED10: PQE-EOLICO-CUPISNIQUE | EE10: INTIPAMPA | EF10: PUNTA LOMITAS-BL1 | EG10: PUNTA LOMITAS-BL2 | EH10: PUN LOMITAS_EXP-BL1 | EI10: PUN LOMITAS_EXP-BL2 | EJ10: EXPANSIÓN INTIPAMPA | EK10: 8AGOSTO | EL10: EL CARMEN | EM10: LA JOYA | EN10: ANGEL_I | EO10: ANGEL_II | EP10: ANGEL_III | EQ10: HUAMBOS | ER10: SAN MARTIN SOLAR | ES10: MAJES | ET10: RUBI | EU10: CH_HER1 | EV10: WAYRA-I | EW10: WAYRA EXTENSION | EX10: CLEMESI | EY10: HUAYCOLORO | EZ10: CALLAO | FA10: DONA_CATALINA | FB10: LAGRINGAV | FC10: REPARTICION | FD10: POECHOS2 | FE10: CHANCAY | FF10: CANA BRAVA | FG10: REFINERIA TALARA TV1 | FH10: REFINERÍA TALARA TV2 | FI10: PARAMONGA | FJ10: MAPLE | FK10: SAN_JACINTO | FL10: AGROLMOS | FM10: CASA GRANDE | FN10: MW | FP10: CARPAPATA | FQ10: CENTRALES ELOR | FR10: PIAS1 | FS10: ZANA | FT10: TABLAZO | FU10: TALLANCA | FV10: CURUMUY | FW10: POECHOS1 | FX10: MW
A11: 13/01/2026 | B11: 00:30 | C11: 204.3 | D11: 629.6 | E11: 214.8 | H11: 91.9 | I11: 246.3 | L11: 0 | M11: 0 | N11: 203.1 | P11: 0 | R11: 147.4 | S11: 9.7 | X11: 167.5 | Y11: 7.8 | Z11: 4.8 | AA11: 0 | AB11: 6.9 | AC11: 13.7 | AD11: 80.6 | AI11: 110.6 | AJ11: 221.7 | AN11: 6.5 | AO11: 462.1 | AP11: 81 | AR11: 42.2 | AS11: 18.4 | AT11: 16.40847 | AU11: 92 | AV11: 183 | AW11: 183.1 | AX11: 183.9 | AY11: 109.4 | AZ11: 22.3 | BA11: 30.8 | BB11: 2 | BC11: 31.7 | BD11: 171.5 | BG11: 0 | BJ11: 46.2 | BN11: 128.3 | BO11: 159.9 | BP11: 159.8 | BQ11: 160.8 | BR11: 253.9 | BS11: 72.5 | BT11: 35.7 | BX11: 0 | CA11: 2.1 | CB11: 181.9 | CC11: 135 | CD11: 63.6 | CE11: 79.3 | CF11: 30.4 | CG11: 0 | CJ11: 142.6 | CK11: 143.7 | CL11: 147.4 | CT11: 6 | CU11: 1.7 | CV11: 20 | CW11: 0 | CX11: 59.6 | CY11: 0 | CZ11: 3.1 | DA11: 0 | DB11: 0 | DC11: 10 | DD11: 5.3 | DE11: 0 | DF11: 1.3 | DG11: 3.6 | DH11: 5.2 | DI11: 0 | DJ11: 20 | DK11: 18.3 | DL11: 3.4 | DM11: 18.6 | DN11: 0 | DO11: 0 | DP11: 20.6 | DQ11: 56.9 | DR11: 0 | DS11: 3 | DT11: 6 | DU11: 3.04 | DV11: 0 | DW11: 0 | DX11: 19.833 | DY11: 12.848 | DZ11: 20.3 | EA11: 20.22 | EB11: 20 | EC11: 3.8 | ED11: 7.8 | EE11: 0 | EF11: 41 | EG11: 75.3 | EH11: 2.5 | EI11: 1.8 | EJ11: 0 | EK11: 20.9 | EL11: 8.2 | EM11: 8.5 | EN11: 20.4 | EO11: 20.4 | EP11: 20.1 | EQ11: 1.6 | ER11: 0 | ES11: 0 | ET11: 0 | EU11: 0.6 | EV11: 34.6 | EW11: 22.5 | EX11: 0 | EY11: 3.6 | FA11: 2.2 | FB11: 1 | FC11: 0 | FD11: 8.1 | FE11: 20 | FF11: 9.9 | FG11: 26.7 | FH11: 32.2 | FI11: 12.9 | FJ11: 19.1 | FK11: 7.82 | FL11: 11.22 | FM11: 24.3 | FN11: 6767.9895 | FP11: 24.4796 | FQ11: 8.1 | FS11: 13.2 | FT11: 26.13492 | FU11: 18.94368 | FV11: 9.8 | FW11: 15.8 | FX11: 116.4582
A12: 13/01/2026 | B12: 01:00 | C12: 206.2 | D12: 627.3 | E12: 213.4 | H12: 89.9 | I12: 244.9 | L12: 0 | M12: 0 | N12: 199.8 | P12: 0 | R12: 180.7 | S12: 9.7 | X12: 168.9 | Y12: 7.4 | Z12: 4.8 | AA12: 0 | AB12: 7.1 | AC12: 13.7 | AD12: 80.4 | AI12: 110.8 | AJ12: 221.5 | AN12: 6.5 | AO12: 462.7 | AP12: 81 | AR12: 41.7 | AS12: 18.2 | AT12: 16.35187 | AU12: 90.6 | AV12: 181 | AW12: 181 | AX12: 184.3 | AY12: 109.5 | AZ12: 19.6 | BA12: 32.7 | BB12: 2 | BC12: 31.8 | BD12: 169.5 | BG12: 0 | BJ12: 45.7 | BN12: 127.9 | BO12: 169.1 | BP12: 166.6 | BQ12: 170.5 | BR12: 250.6 | BS12: 72.8 | BT12: 35.6 | BX12: 0 | CA12: 2 | CB12: 105.8 | CC12: 133.1 | CD12: 63 | CE12: 79.2 | CF12: 30.2 | CG12: 0 | CJ12: 141.7 | CK12: 142.5 | CL12: 146.3 | CT12: 5.8 | CU12: 1.8 | CV12: 20 | CW12: 0 | CX12: 45.6 | CY12: 0 | CZ12: 1.9 | DA12: 0 | DB12: 0 | DC12: 9.9 | DD12: 5.4 | DE12: 0 | DF12: 1.3 | DG12: 3.6 | DH12: 5.1 | DI12: 0 | DJ12: 20 | DK12: 18.4 | DL12: 3.4 | DM12: 18.6 | DN12: 0 | DO12: 0 | DP12: 17.1 | DQ12: 44.1 | DR12: 0 | DS12: 3 | DT12: 6 | DU12: 3.04 | DV12: 0 | DW12: 0 | DX12: 19.832 | DY12: 12.824 | DZ12: 20.05 | EA12: 20.19 | EB12: 20 | EC12: 4.4 | ED12: 7.5 | EE12: 0 | EF12: 53.5 | EG12: 51.7 | EH12: 4.3 | EI12: 1.9 | EJ12: 0 | EK12: 20.9 | EL12: 8 | EM12: 8.5 | EN12: 20.4 | EO12: 20.4 | EP12: 20.1 | EQ12: 2.9 | ER12: 0 | ES12: 0 | ET12: 0 | EU12: 0.6 | EV12: 27.7 | EW12: 19.2 | EX12: 0 | EY12: 3.6 | FA12: 2.2 | FB12: 1 | FC12: 0 | FD12: 8.2 | FE12: 20 | FF12: 9.1 | FG12: 27.1 | FH12: 31.9 | FI12: 12.9 | FJ12: 19.1 | FK12: 7.34 | FL12: 11.22 | FM12: 24.1 | FN12: 6674.2479 | FP12: 24.47872 | FQ12: 8.1 | FS12: 13.2 | FT12: 26.07052 | FU12: 18.94347 | FV12: 9.8 | FW12: 15.9 | FX12: 116.49271
A13: 13/01/2026 | B13: 01:30 | C13: 199.3 | D13: 620.4 | E13: 211.8 | H13: 85.5 | I13: 240.9 | L13: 0 | M13: 0 | N13: 204.1 | P13: 0 | R13: 246.1 | S13: 9.7 | X13: 164.9 | Y13: 7 | Z13: 4.9 | AA13: 0 | AB13: 7.1 | AC13: 13.6 | AD13: 79.4 | AI13: 109.4 | AJ13: 221.7 | AN13: 6.5 | AO13: 462.2 | AP13: 81 | AR13: 41.1 | AS13: 18.4 | AT13: 16.14023 | AU13: 90.9 | AV13: 176.3 | AW13: 176.3 | AX13: 185.4 | AY13: 108.5 | AZ13: 16.7 | BA13: 31 | BB13: 2 | BC13: 31.4 | BD13: 169.9 | BG13: 0 | BJ13: 46.2 | BN13: 127.1 | BO13: 164.5 | BP13: 164.4 | BQ13: 163.8 | BR13: 253.4 | BS13: 73.3 | BT13: 35.6 | BX13: 0 | CA13: 2 | CB13: 89.4 | CC13: 119.2 | CD13: 61.2 | CE13: 79.3 | CF13: 29.4 | CG13: 0 | CJ13: 144 | CK13: 145 | CL13: 148.9 | CT13: 5.9 | CU13: 1.7 | CV13: 20 | CW13: 0 | CX13: 44 | CY13: 0 | CZ13: 2.3 | DA13: 0 | DB13: 0 | DC13: 9.9 | DD13: 5.4 | DE13: 0 | DF13: 1.3 | DG13: 3.6 | DH13: 4.4 | DI13: 0 | DJ13: 20 | DK13: 18.4 | DL13: 3.4 | DM13: 18.7 | DN13: 0 | DO13: 0 | DP13: 16.7 | DQ13: 45.8 | DR13: 0 | DS13: 3 | DT13: 5.9 | DU13: 3.04 | DV13: 0 | DW13: 0 | DX13: 19.846 | DY13: 12.848 | DZ13: 19.83 | EA13: 20.1 | EB13: 20 | EC13: 4.8 | ED13: 5.9 | EE13: 0 | EF13: 28.6 | EG13: 58 | EH13: 2.4 | EI13: 1.6 | EJ13: 0 | EK13: 20.9 | EL13: 7.9 | EM13: 8.5 | EN13: 20.4 | EO13: 20.4 | EP13: 20.1 | EQ13: 2 | ER13: 0 | ES13: 0 | ET13: 0 | EU13: 0.6 | EV13: 10.9 | EW13: 7.6 | EX13: 0 | EY13: 3.6 | FA13: 2.2 | FB13: 1 | FC13: 0 | FD13: 8.2 | FE13: 20 | FF13: 9.8 | FG13: 26.7 | FH13: 32.3 | FI13: 13.8 | FJ13: 19.1 | FK13: 7.2 | FL13: 11.24 | FM13: 23 | FN13: 6611.0442 | FP13: 24.48916 | FQ13: 8.1 | FS13: 13.2 | FT13: 26.05156 | FU13: 18.94324 | FV13: 10 | FW13: 15.8 | FX13: 116.58396
A14: 13/01/2026 | B14: 02:00 | C14: 203.8 | D14: 622.9 | E14: 212.7 | H14: 90.9 | I14: 247.1 | L14: 0 | M14: 0 | N14: 202.2 | P14: 0 | R14: 131.1 | S14: 9.8 | X14: 169.1 | Y14: 7.6 | Z14: 5.4 | AA14: 0 | AB14: 6.9 | AC14: 13.7 | AD14: 80.1 | AI14: 110.5 | AJ14: 220.7 | AN14: 6.5 | AO14: 455.9 | AP14: 81 | AR14: 41.7 | AS14: 18.2 | AT14: 15.9809 | AU14: 89 | AV14: 180 | AW14: 180.4 | AX14: 183.1 | AY14: 108.9 | AZ14: 18.6 | BA14: 31.4 | BB14: 2 | BC14: 31.7 | BD14: 170.8 | BG14: 0 | BJ14: 46 | BN14: 127.7 | BO14: 142.6 | BP14: 142.6 | BQ14: 142 | BR14: 239.1 | BS14: 72.2 | BT14: 35.7 | BX14: 0 | CA14: 2 | CB14: 129.6 | CC14: 113.3 | CD14: 62.7 | CE14: 78.8 | CF14: 30 | CG14: 0 | CJ14: 141.1 | CK14: 142.3 | CL14: 146.1 | CT14: 5.8 | CU14: 1.8 | CV14: 20 | CW14: 0 | CX14: 34.1 | CY14: 0 | CZ14: 2.6 | DA14: 0 | DB14: 0 | DC14: 10 | DD14: 5.4 | DE14: 0 | DF14: 1.3 | DG14: 3.6 | DH14: 5.1 | DI14: 0 | DJ14: 20 | DK14: 18.3 | DL14: 3.4 | DM14: 18.6 | DN14: 0 | DO14: 0 | DP14: 12.9 | DQ14: 40.7 | DR14: 0 | DS14: 2.9 | DT14: 5.8 | DU14: 3.04 | DV14: 0 | DW14: 0 | DX14: 19.844 | DY14: 12.816 | DZ14: 19.91 | EA14: 20.17 | EB14: 19.9 | EC14: 4.2 | ED14: 5.2 | EE14: 0 | EF14: 23 | EG14: 34.7 | EH14: 2 | EI14: 1.5 | EJ14: 0 | EK14: 20.9 | EL14: 7.9 | EM14: 8.5 | EN14: 20.4 | EO14: 20.4 | EP14: 20.1 | EQ14: 2.2 | ER14: 0 | ES14: 0 | ET14: 0 | EU14: 0.6 | EV14: 21.5 | EW14: 20.1 | EX14: 0 | EY14: 3.6 | FA14: 2.2 | FB14: 1 | FC14: 0 | FD14: 8.2 | FE14: 19.8 | FF14: 9.8 | FG14: 27.2 | FH14: 32.4 | FI14: 14 | FJ14: 19.1 | FK14: 7.08 | FL14: 11.24 | FM14: 23.7 | FN14: 6443.9809 | FP14: 24.48783 | FQ14: 8.1 | FS14: 13.2 | FT14: 26.0753 | FU14: 18.94331 | FV14: 9.8 | FW14: 15.9 | FX14: 116.50644
A15: 13/01/2026 | B15: 02:30 | C15: 201.8 | D15: 625.8 | E15: 214 | H15: 89.9 | I15: 244.6 | L15: 0 | M15: 0 | N15: 202.1 | P15: 0 | R15: 159.3 | S15: 9.8 | X15: 160.6 | Y15: 7.8 | Z15: 5.4 | AA15: 0 | AB15: 7.1 | AC15: 13.7 | AD15: 80.2 | AI15: 110.7 | AJ15: 221.1 | AN15: 6.5 | AO15: 459.7 | AP15: 81 | AR15: 42 | AS15: 18.3 | AT15: 15.73645 | AU15: 91.5 | AV15: 151.3 | AW15: 151.6 | AX15: 167.1 | AY15: 108.6 | AZ15: 45.2 | BA15: 34.4 | BB15: 2 | BC15: 31.8 | BD15: 172.3 | BG15: 0 | BJ15: 45.7 | BN15: 127.9 | BO15: 149.5 | BP15: 149.4 | BQ15: 149.6 | BR15: 245.7 | BS15: 72.8 | BT15: 35.8 | BX15: 0 | CA15: 2 | CB15: 82.7 | CC15: 124.2 | CD15: 63.1 | CE15: 78.8 | CF15: 30.2 | CG15: 0 | CJ15: 142.1 | CK15: 142.9 | CL15: 147 | CT15: 5.8 | CU15: 1.8 | CV15: 20 | CW15: 0 | CX15: 39.1 | CY15: 0 | CZ15: 3.3 | DA15: 0 | DB15: 0 | DC15: 9.9 | DD15: 5.4 | DE15: 0 | DF15: 1.2 | DG15: 3.6 | DH15: 5.1 | DI15: 0 | DJ15: 19.7 | DK15: 18.3 | DL15: 3.4 | DM15: 18.6 | DN15: 0 | DO15: 0 | DP15: 8.9 | DQ15: 35.3 | DR15: 0 | DS15: 2.9 | DT15: 5.8 | DU15: 3.04 | DV15: 0 | DW15: 0 | DX15: 19.849 | DY15: 12.847 | DZ15: 19.95 | EA15: 20.22 | EB15: 20 | EC15: 4 | ED15: 2.8 | EE15: 0 | EF15: 13.4 | EG15: 40.3 | EH15: 1.8 | EI15: 0.8 | EJ15: 0 | EK15: 20.9 | EL15: 7.9 | EM15: 8.5 | EN15: 20.4 | EO15: 20.4 | EP15: 20.1 | EQ15: 2.3 | ER15: 0 | ES15: 0 | ET15: 0 | EU15: 0.6 | EV15: 27.3 | EW15: 19.1 | EX15: 0 | EY15: 3.6 | FA15: 2.2 | FB15: 1 | FC15: 0 | FD15: 8.2 | FE15: 20 | FF15: 9.5 | FG15: 27 | FH15: 32.4 | FI15: 14.4 | FJ15: 19.1 | FK15: 8.29 | FL15: 11.25 | FM15: 16.4 | FN15: 6410.2824 | FP15: 24.47561 | FQ15: 8.1 | FS15: 13.2 | FT15: 26.05125 | FU15: 18.94326 | FV15: 9.9 | FW15: 15.8 | FX15: 116.47012
A16: 13/01/2026 | B16: 03:00 | C16: 202.6 | D16: 626.4 | E16: 214.1 | H16: 90 | I16: 244.3 | L16: 0 | M16: 0 | N16: 202.5 | P16: 0 | R16: 169.8 | S16: 9.7 | X16: 165 | Y16: 7.8 | Z16: 5.4 | AA16: 0 | AB16: 7.1 | AC16: 13.7 | AD16: 80.5 | AI16: 110.9 | AJ16: 221.2 | AN16: 6.5 | AO16: 461.5 | AP16: 81 | AR16: 41.8 | AS16: 18.4 | AT16: 15.49478 | AU16: 88.5 | AV16: 151.3 | AW16: 151.8 | AX16: 167.4 | AY16: 108.5 | AZ16: 0 | BA16: 34.3 | BB16: 2 | BC16: 31.8 | BD16: 164.8 | BG16: 0 | BJ16: 45.9 | BN16: 127.9 | BO16: 147.8 | BP16: 147.7 | BQ16: 148.4 | BR16: 238.2 | BS16: 73 | BT16: 35.8 | BX16: 0 | CA16: 2 | CB16: 79.5 | CC16: 122.3 | CD16: 65.5 | CE16: 78.9 | CF16: 30.2 | CG16: 0 | CJ16: 142.5 | CK16: 143.2 | CL16: 147.2 | CT16: 5.8 | CU16: 1.8 | CV16: 20 | CW16: 0 | CX16: 44.3 | CY16: 0 | CZ16: 3.4 | DA16: 0 | DB16: 0 | DC16: 9.9 | DD16: 5.4 | DE16: 0 | DF16: 1.2 | DG16: 3.6 | DH16: 5.2 | DI16: 0 | DJ16: 20 | DK16: 18.3 | DL16: 3.5 | DM16: 18.6 | DN16: 0 | DO16: 0 | DP16: 11.8 | DQ16: 31.1 | DR16: 0 | DS16: 3 | DT16: 5.8 | DU16: 3.04 | DV16: 0 | DW16: 0 | DX16: 19.849 | DY16: 12.823 | DZ16: 19.95 | EA16: 20.2 | EB16: 20 | EC16: 4.8 | ED16: 2.2 | EE16: 0 | EF16: 17.8 | EG16: 30.4 | EH16: 1.2 | EI16: 1.1 | EJ16: 0 | EK16: 20.9 | EL16: 7.9 | EM16: 8.5 | EN16: 20.4 | EO16: 20.4 | EP16: 20.1 | EQ16: 1.8 | ER16: 0 | ES16: 0 | ET16: 0 | EU16: 0.6 | EV16: 33.1 | EW16: 30.6 | EX16: 0 | EY16: 3.6 | FA16: 2.2 | FB16: 1 | FC16: 0 | FD16: 8.2 | FE16: 20 | FF16: 9.8 | FG16: 26.9 | FH16: 32.4 | FI16: 14.5 | FJ16: 19.1 | FK16: 8.21 | FL16: 11.21 | FM16: 22.7 | FN16: 6382.2768 | FP16: 24.46123 | FQ16: 8.1 | FS16: 13.2 | FT16: 26.10846 | FU16: 18.94313 | FV16: 9.8 | FW16: 15.9 | FX16: 116.51282
A17: 13/01/2026 | B17: 03:30 | C17: 206.3 | D17: 629.3 | E17: 214.9 | H17: 91.8 | I17: 247.4 | L17: 0 | M17: 0 | N17: 200.4 | P17: 0 | R17: 207.1 | S17: 9.8 | X17: 170.7 | Y17: 7.8 | Z17: 5.5 | AA17: 0 | AB17: 7 | AC17: 13.7 | AD17: 80.7 | AI17: 110.8 | AJ17: 220.6 | AN17: 6.5 | AO17: 459 | AP17: 81 | AR17: 42.1 | AS17: 18.4 | AT17: 15.9968 | AU17: 91.2 | AV17: 154.1 | AW17: 154 | AX17: 167.3 | AY17: 108.6 | AZ17: 0 | BA17: 37 | BB17: 2 | BC17: 31.8 | BD17: 154.1 | BG17: 0 | BJ17: 45.7 | BN17: 129.4 | BO17: 150.7 | BP17: 150.6 | BQ17: 150.5 | BR17: 239.7 | BS17: 71.8 | BT17: 35.6 | BX17: 0 | CA17: 2 | CB17: 84.3 | CC17: 126.2 | CD17: 66.4 | CE17: 79.1 | CF17: 30.5 | CG17: 0 | CJ17: 142.7 | CK17: 143.2 | CL17: 146.9 | CT17: 5.8 | CU17: 1.8 | CV17: 20 | CW17: 0 | CX17: 44.8 | CY17: 0 | CZ17: 3.4 | DA17: 0 | DB17: 0 | DC17: 9.9 | DD17: 5.5 | DE17: 0 | DF17: 1.2 | DG17: 3.6 | DH17: 5.2 | DI17: 0 | DJ17: 20 | DK17: 18.3 | DL17: 3.5 | DM17: 18.6 | DN17: 0 | DO17: 0 | DP17: 11 | DQ17: 28.2 | DR17: 0 | DS17: 3 | DT17: 5.9 | DU17: 3.04 | DV17: 0 | DW17: 0 | DX17: 19.852 | DY17: 12.816 | DZ17: 19.92 | EA17: 20.3 | EB17: 20 | EC17: 4.5 | ED17: 0.5 | EE17: 0 | EF17: 13.2 | EG17: 40.4 | EH17: 0.7 | EI17: 0.4 | EJ17: 0 | EK17: 20.9 | EL17: 7.7 | EM17: 8.9 | EN17: 20.4 | EO17: 20.4 | EP17: 20.1 | EQ17: 2.2 | ER17: 0 | ES17: 0 | ET17: 0 | EU17: 0.6 | EV17: 27.7 | EW17: 18.2 | EX17: 0 | EY17: 3.6 | FA17: 2.2 | FB17: 1 | FC17: 0 | FD17: 8.2 | FE17: 20 | FF17: 9.8 | FG17: 26.9 | FH17: 32.3 | FI17: 14.2 | FJ17: 18.6 | FK17: 8.45 | FL17: 10.09 | FM17: 22.7 | FN17: 6432.6648 | FP17: 24.49385 | FQ17: 8.1 | FS17: 13.2 | FT17: 26.05462 | FU17: 18.94313 | FV17: 9.8 | FW17: 15.9 | FX17: 116.4916
A18: 13/01/2026 | B18: 04:00 | C18: 198.1 | D18: 622 | E18: 212.2 | H18: 87.5 | I18: 242.2 | L18: 0 | M18: 0 | N18: 202.7 | P18: 0 | R18: 205.7 | S18: 9.7 | X18: 163.2 | Y18: 6.8 | Z18: 5.3 | AA18: 12.8 | AB18: 7.1 | AC18: 13.7 | AD18: 79.8 | AI18: 109.6 | AJ18: 221.6 | AN18: 6.5 | AO18: 459 | AP18: 81 | AR18: 41.2 | AS18: 18.4 | AT18: 16.07179 | AU18: 91 | AV18: 155.1 | AW18: 155.4 | AX18: 175.6 | AY18: 108.7 | AZ18: 0 | BA18: 29.2 | BB18: 2 | BC18: 32.3 | BD18: 149.4 | BG18: 0 | BJ18: 45.9 | BN18: 126.4 | BO18: 169 | BP18: 167.1 | BQ18: 170.9 | BR18: 253.5 | BS18: 72 | BT18: 35.6 | BX18: 0 | CA18: 2 | CB18: 103.8 | CC18: 127.3 | CD18: 64 | CE18: 77.8 | CF18: 29.4 | CG18: 0 | CJ18: 143.7 | CK18: 144.6 | CL18: 148.4 | CT18: 5.9 | CU18: 1.8 | CV18: 20 | CW18: 0 | CX18: 33.1 | CY18: 0 | CZ18: 3.3 | DA18: 0 | DB18: 0 | DC18: 9.8 | DD18: 5.4 | DE18: 0 | DF18: 1.2 | DG18: 3.6 | DH18: 5.2 | DI18: 0 | DJ18: 20 | DK18: 18.3 | DL18: 3.4 | DM18: 18.7 | DN18: 0 | DO18: 0 | DP18: 8.9 | DQ18: 24.2 | DR18: 0 | DS18: 3 | DT18: 5.9 | DU18: 3.04 | DV18: 0 | DW18: 0 | DX18: 19.853 | DY18: 12.808 | DZ18: 19.71 | EA18: 20.19 | EB18: 20 | EC18: 4.9 | ED18: 0 | EE18: 0 | EF18: 12.8 | EG18: 40.5 | EH18: 0.2 | EI18: 0 | EJ18: 0 | EK18: 20.9 | EL18: 7.7 | EM18: 8.9 | EN18: 20.4 | EO18: 20.4 | EP18: 20.1 | EQ18: 2.8 | ER18: 0 | ES18: 0 | ET18: 0 | EU18: 0.6 | EV18: 17.8 | EW18: 18.6 | EX18: 0 | EY18: 3.7 | FA18: 2.2 | FB18: 1 | FC18: 0 | FD18: 8.2 | FE18: 20 | FF18: 9.5 | FG18: 26.9 | FH18: 32.3 | FI18: 13 | FJ18: 18.3 | FK18: 7.82 | FL18: 11.11 | FM18: 22.4 | FN18: 6462.6028 | FP18: 24.49314 | FQ18: 8.1 | FS18: 13.2 | FT18: 26.02214 | FU18: 18.94315 | FV18: 9.9 | FW18: 16 | FX18: 116.65843
A19: 13/01/2026 | B19: 04:30 | C19: 205.2 | D19: 628.4 | E19: 214.5 | H19: 91.4 | I19: 244.8 | L19: 0 | M19: 0 | N19: 201.1 | P19: 0 | R19: 261.5 | S19: 9.8 | X19: 168.6 | Y19: 7.3 | Z19: 5.1 | AA19: 17 | AB19: 6.9 | AC19: 13.7 | AD19: 81 | AI19: 110.7 | AJ19: 221.7 | AN19: 6.5 | AO19: 461.1 | AP19: 81 | AR19: 41.9 | AS19: 18.4 | AT19: 15.668 | AU19: 91 | AV19: 164 | AW19: 164.1 | AX19: 170.8 | AY19: 109 | AZ19: 0 | BA19: 30.8 | BB19: 2 | BC19: 31.5 | BD19: 161 | BG19: 0 | BJ19: 45.3 | BN19: 128.3 | BO19: 168.4 | BP19: 166.5 | BQ19: 170.7 | BR19: 253.8 | BS19: 72.2 | BT19: 35.6 | BX19: 0 | CA19: 2 | CB19: 137.3 | CC19: 132.4 | CD19: 65.8 | CE19: 78.6 | CF19: 30.2 | CG19: 0 | CJ19: 141.5 | CK19: 142.4 | CL19: 146.1 | CT19: 5.8 | CU19: 1.8 | CV19: 20 | CW19: 0 | CX19: 34 | CY19: 0 | CZ19: 2.8 | DA19: 0 | DB19: 0 | DC19: 10 | DD19: 5.5 | DE19: 0 | DF19: 1.2 | DG19: 3.6 | DH19: 5.2 | DI19: 0 | DJ19: 20 | DK19: 18.3 | DL19: 3.4 | DM19: 18.6 | DN19: 0 | DO19: 0 | DP19: 6.9 | DQ19: 18.2 | DR19: 0 | DS19: 2.9 | DT19: 5.8 | DU19: 3.04 | DV19: 0 | DW19: 0 | DX19: 19.859 | DY19: 12.809 | DZ19: 19.87 | EA19: 20.24 | EB19: 20 | EC19: 0.8 | ED19: 0 | EE19: 0 | EF19: 17.8 | EG19: 33.6 | EH19: 1.2 | EI19: 0.3 | EJ19: 0 | EK19: 20.9 | EL19: 7.7 | EM19: 8.9 | EN19: 20.4 | EO19: 20.4 | EP19: 20.1 | EQ19: 2.8 | ER19: 0 | ES19: 0 | ET19: 0 | EU19: 0.6 | EV19: 24 | EW19: 17.1 | EX19: 0 | EY19: 3.7 | FA19: 2.2 | FB19: 1 | FC19: 0 | FD19: 8.2 | FE19: 20 | FF19: 10.6 | FG19: 26.6 | FH19: 32.3 | FI19: 13.4 | FJ19: 18.3 | FK19: 7.89 | FL19: 11.11 | FM19: 22.7 | FN19: 6608.986 | FP19: 24.48691 | FQ19: 8.1 | FS19: 13.2 | FT19: 25.94046 | FU19: 18.94289 | FV19: 9.7 | FW19: 3.7 | FX19: 104.07026
A20: 13/01/2026 | B20: 05:00 | C20: 202.5 | D20: 626.5 | E20: 214 | H20: 89.7 | I20: 246.2 | L20: 0 | M20: 0 | N20: 201.9 | P20: 0 | R20: 305.9 | S20: 9.8 | X20: 166.8 | Y20: 6.9 | Z20: 5.4 | AA20: 16.9 | AB20: 7 | AC20: 13.7 | AD20: 81 | AI20: 110.7 | AJ20: 221.9 | AN20: 6.5 | AO20: 461.2 | AP20: 81 | AR20: 42 | AS20: 18.4 | AT20: 14.51891 | AU20: 89.9 | AV20: 163.4 | AW20: 163.9 | AX20: 170.9 | AY20: 108.9 | AZ20: 0 | BA20: 39.8 | BB20: 2 | BC20: 31.6 | BD20: 159.3 | BG20: 0 | BJ20: 45.6 | BN20: 127.7 | BO20: 167.8 | BP20: 166.6 | BQ20: 170.9 | BR20: 253 | BS20: 72.7 | BT20: 35.7 | BX20: 0 | CA20: 2.1 | CB20: 150.3 | CC20: 131.3 | CD20: 65.4 | CE20: 78.7 | CF20: 30 | CG20: 0 | CJ20: 142 | CK20: 143.8 | CL20: 147.6 | CT20: 5.8 | CU20: 1.8 | CV20: 20 | CW20: 0 | CX20: 29.7 | CY20: 0 | CZ20: 3.9 | DA20: 0 | DB20: 0 | DC20: 9.9 | DD20: 5.4 | DE20: 0 | DF20: 1.2 | DG20: 3.6 | DH20: 5.2 | DI20: 0 | DJ20: 20 | DK20: 18.3 | DL20: 3.4 | DM20: 14.7 | DN20: 0 | DO20: 0 | DP20: 8.9 | DQ20: 19.1 | DR20: 0 | DS20: 2.9 | DT20: 5.6 | DU20: 3.04 | DV20: 0 | DW20: 0 | DX20: 19.863 | DY20: 12.805 | DZ20: 19.89 | EA20: 20.25 | EB20: 20 | EC20: 5.5 | ED20: 0 | EE20: 0 | EF20: 10.2 | EG20: 27.1 | EH20: 0.2 | EI20: 0 | EJ20: 0 | EK20: 20.9 | EL20: 7.8 | EM20: 8.9 | EN20: 20.4 | EO20: 20.4 | EP20: 20.1 | EQ20: 3.7 | ER20: 0 | ES20: 0 | ET20: 0 | EU20: 0.6 | EV20: 13.4 | EW20: 10.5 | EX20: 0 | EY20: 3.7 | FA20: 2.2 | FB20: 1 | FC20: 0 | FD20: 8.2 | FE20: 20 | FF20: 10 | FG20: 25.8 | FH20: 32.1 | FI20: 13.5 | FJ20: 18.9 | FK20: 8.11 | FL20: 11.07 | FM20: 22.4 | FN20: 6633.2469 | FP20: 24.48951 | FQ20: 8.1 | FS20: 13.2 | FT20: 25.88232 | FU20: 18.94289 | FV20: 9.7 | FW20: 3.7 | FX20: 104.01472
A21: 13/01/2026 | B21: 05:30 | C21: 202.4 | D21: 628.1 | E21: 216.4 | H21: 90.2 | I21: 245.4 | L21: 0 | M21: 0 | N21: 200.8 | P21: 0 | R21: 284.7 | S21: 9.7 | X21: 166.3 | Y21: 7.2 | Z21: 5.3 | AA21: 16.9 | AB21: 7.1 | AC21: 13.7 | AD21: 80.7 | AI21: 110.9 | AJ21: 221.4 | AN21: 6.5 | AO21: 461.2 | AP21: 81 | AR21: 41.9 | AS21: 18 | AT21: 13.9109 | AU21: 88.5 | AV21: 161.5 | AW21: 162.2 | AX21: 172.4 | AY21: 108.9 | AZ21: 0 | BA21: 38.1 | BB21: 2 | BC21: 31.5 | BD21: 169.2 | BG21: 32.4 | BJ21: 45.6 | BN21: 127.8 | BO21: 169.5 | BP21: 167.1 | BQ21: 170.3 | BR21: 254.7 | BS21: 72.9 | BT21: 35.8 | BX21: 0 | CA21: 2 | CB21: 137.1 | CC21: 131.8 | CD21: 65.6 | CE21: 78.9 | CF21: 30.2 | CG21: 0 | CJ21: 142.2 | CK21: 143.2 | CL21: 147.4 | CT21: 5.9 | CU21: 1.8 | CV21: 20 | CW21: 0 | CX21: 33.9 | CY21: 0 | CZ21: 3.8 | DA21: 0 | DB21: 0 | DC21: 9.9 | DD21: 5.4 | DE21: 0.5 | DF21: 1.1 | DG21: 3.6 | DH21: 5.1 | DI21: 0 | DJ21: 20 | DK21: 18.3 | DL21: 3.4 | DM21: 11.1 | DN21: 0.5 | DO21: 0.5 | DP21: 9.4 | DQ21: 17.3 | DR21: 0 | DS21: 3.2 | DT21: 5.7 | DU21: 3.04 | DV21: 0 | DW21: 0 | DX21: 19.863 | DY21: 12.815 | DZ21: 19.99 | EA21: 20.27 | EB21: 20 | EC21: 5.2 | ED21: 0 | EE21: 0.1 | EF21: 6.7 | EG21: 23.6 | EH21: 0 | EI21: 0 | EJ21: 0 | EK21: 20.9 | EL21: 7.8 | EM21: 8.9 | EN21: 20.4 | EO21: 20.4 | EP21: 20.1 | EQ21: 3 | ER21: 0.3 | ES21: 0 | ET21: 1.6 | EU21: 0.6 | EV21: 16.7 | EW21: 18.2 | EX21: 1.3 | EY21: 3.7 | FA21: 2.2 | FB21: 1 | FC21: 0 | FD21: 8.1 | FE21: 20 | FF21: 9.8 | FG21: 26.6 | FH21: 31.8 | FI21: 14 | FJ21: 18.8 | FK21: 8.02 | FL21: 11.07 | FM21: 22.1 | FN21: 6647.8789 | FP21: 24.47663 | FQ21: 8 | FS21: 13.2 | FT21: 25.85952 | FU21: 18.9428 | FV21: 9.7 | FW21: 3.8 | FX21: 103.97895
A22: 13/01/2026 | B22: 06:00 | C22: 198.1 | D22: 622.5 | E22: 214 | H22: 87.5 | I22: 243.4 | L22: 0 | M22: 0 | N22: 202.5 | P22: 0 | R22: 433.5 | S22: 9.7 | X22: 165.2 | Y22: 6.5 | Z22: 5.2 | AA22: 16.9 | AB22: 7.1 | AC22: 13.7 | AD22: 59.5 | AI22: 109.5 | AJ22: 220.9 | AN22: 6.5 | AO22: 457.3 | AP22: 81 | AR22: 41.3 | AS22: 18.4 | AT22: 13.87155 | AU22: 91.5 | AV22: 148.4 | AW22: 148.7 | AX22: 167.1 | AY22: 107.5 | AZ22: 0 | BA22: 37.1 | BB22: 2 | BC22: 31.2 | BD22: 169.8 | BG22: 29.4 | BJ22: 45.5 | BN22: 83.3 | BO22: 147.8 | BP22: 147.6 | BQ22: 146.7 | BR22: 240.1 | BS22: 72.9 | BT22: 35.7 | BX22: 0 | CA22: 2 | CB22: 70.7 | CC22: 115.5 | CD22: 64.1 | CE22: 77.7 | CF22: 29.5 | CG22: 0 | CJ22: 142 | CK22: 143 | CL22: 147.1 | CT22: 5.6 | CU22: 1.8 | CV22: 19.8 | CW22: 0 | CX22: 26.4 | CY22: 6 | CZ22: 4.6 | DA22: 0 | DB22: 0 | DC22: 9.9 | DD22: 5.4 | DE22: 19.1 | DF22: 1.1 | DG22: 3.6 | DH22: 5.1 | DI22: 0 | DJ22: 20 | DK22: 18.3 | DL22: 3.4 | DM22: 11.3 | DN22: 0.9 | DO22: 1.3 | DP22: 13.3 | DQ22: 15.8 | DR22: 0.2 | DS22: 3.2 | DT22: 10.7 | DU22: 3 | DV22: 0 | DW22: 0 | DX22: 19.878 | DY22: 12.801 | DZ22: 20.12 | EA22: 20.24 | EB22: 19.9 | EC22: 4.9 | ED22: 0 | EE22: 1.4 | EF22: 5.7 | EG22: 22.3 | EH22: 0 | EI22: 0 | EJ22: 0.5 | EK22: 20.9 | EL22: 7.8 | EM22: 8.9 | EN22: 20.4 | EO22: 20.4 | EP22: 20.1 | EQ22: 3.1 | ER22: 15.7 | ES22: 0 | ET22: 13.8 | EU22: 0.6 | EV22: 20.5 | EW22: 27.8 | EX22: 10.9 | EY22: 3.7 | FA22: 2.2 | FB22: 1 | FC22: 0.6 | FD22: 8.2 | FE22: 20 | FF22: 9.9 | FG22: 27.1 | FH22: 32.3 | FI22: 14 | FJ22: 19.4 | FK22: 8.07 | FL22: 11.09 | FM22: 17.4 | FN22: 6581.3705 | FP22: 24.4737 | FQ22: 8 | FS22: 13.2 | FT22: 26.00929 | FU22: 18.94268 | FV22: 9.6 | FW22: 3.8 | FX22: 104.02567
... A58: 14/01/2026 | B58: 00:00 | C58: 200.3 | D58: 626.8 | E58: 214.8 | H58: 90.8 | I58: 243 | L58: 0 | M58: 204.4 | N58: 202.3 | P58: 208.8 | R58: 370.5 | S58: 9.5 | X58: 163.9 | Y58: 7.5 | Z58: 5.2 | AA58: 16.9 | AB58: 7.1 | AC58: 13.6 | AD58: 65.9 | AI58: 110.6 | AJ58: 220.8 | AN58: 6.5 | AO58: 452.8 | AP58: 45.7 | AR58: 0 | AS58: 18.4 | AT58: 16.56065 | AU58: 95.6 | AV58: 180 | AW58: 180.8 | AX58: 185.2 | AY58: 109.3 | AZ58: 17.4 | BA58: 46 | BB58: 2 | BC58: 31.3 | BD58: 134.4 | BG58: 41.9 | BJ58: 45.6 | BN58: 127 | BO58: 160.5 | BP58: 160.5 | BQ58: 161 | BR58: 238.7 | BS58: 73.9 | BT58: 36 | BX58: 26.1 | CA58: 2 | CB58: 131.4 | CC58: 134 | CD58: 62.8 | CE58: 78.2 | CF58: 29.8 | CG58: 0 | CJ58: 142.5 | CK58: 143.8 | CL58: 148 | CT58: 5.8 | CU58: 1.8 | CV58: 20 | CW58: 0 | CX58: 11.4 | CY58: 0 | CZ58: 0 | DA58: 0 | DB58: 20.2 | DC58: 9.9 | DD58: 5.5 | DE58: 0 | DF58: 1.9 | DG58: 3.5 | DH58: 5.1 | DI58: 20.2 | DJ58: 20 | DK58: 18.7 | DL58: 3.5 | DM58: 18.5 | DN58: 0 | DO58: 0 | DP58: 2.1 | DQ58: 2.3 | DR58: 0 | DS58: 3.3 | DT58: 16.5 | DU58: 2.96 | DV58: 0.4 | DW58: 0 | DX58: 19.886 | DY58: 12.519 | DZ58: 20.22 | EA58: 20.18 | EB58: 20 | EC58: 3.2 | ED58: 2 | EE58: 0 | EF58: 12 | EG58: 0 | EH58: 0.9 | EI58: 0.3 | EJ58: 0 | EK58: 20.9 | EL58: 8.3 | EM58: 0 | EN58: 20.4 | EO58: 20.4 | EP58: 20.1 | EQ58: 0.4 | ER58: 0 | ES58: 0 | ET58: 0 | EU58: 0.6 | EV58: 8.6 | EW58: 4.6 | EX58: 0 | EY58: 3.7 | FA58: 2.2 | FB58: 1 | FC58: 0 | FD58: 8.2 | FE58: 20 | FF58: 8.9 | FG58: 26.7 | FH58: 31.7 | FI58: 14.4 | FJ58: 19.1 | FK58: 8.27 | FL58: 11.31 | FM58: 23.4 | FN58: 7036.3057 | FP58: 24.49031 | FQ58: 8.1 | FS58: 13.2 | FT58: 25.76022 | FU58: 18.94382 | FV58: 9.7 | FW58: 3.7 | FX58: 103.89435
A59: EJEC | C59: 4853.8 | D59: 15053.75 | E59: 5155.95 | F59: 0 | G59: 0 | H59: 2158.4 | I59: 5746.45 | J59: 0 | K59: 0 | L59: 2159.2 | M59: 3238.85 | N59: 4795.35 | O59: 0 | P59: 3153.15 | Q59: 0 | R59: 8340.75 | S59: 230.05 | T59: 0 | U59: 0 | V59: 0 | W59: 0 | X59: 3990.55 | Y59: 189.25 | Z59: 132.9 | AA59: 338.85 | AB59: 168.55 | AC59: 324.8 | AD59: 2008.55 | AE59: 0 | AF59: 0 | AG59: 0 | AH59: 0 | AI59: 2653.45 | AJ59: 5314 | AK59: 0 | AL59: 0 | AM59: 0 | AN59: 156 | AO59: 10988 | AP59: 1017.8 | AQ59: 0 | AR59: 274.55 | AS59: 436.3 | AT59: 361.13256 | AU59: 2172.9 | AV59: 3869.35 | AW59: 3879.25 | AX59: 4166.5 | AY59: 2608.05 | AZ59: 275.8 | BA59: 969.5 | BB59: 50.25 | BC59: 754.45 | BD59: 3622.2 | BE59: 0 | BF59: 0 | BG59: 855.4 | BH59: 0 | BI59: 0 | BJ59: 1086.15 | BK59: 0 | BL59: 0 | BM59: 0 | BN59: 2595.1 | BO59: 3830.95 | BP59: 3811.15 | BQ59: 3863.3 | BR59: 5886.65 | BS59: 1735.35 | BT59: 848.25 | BU59: 0 | BV59: 0 | BW59: 0 | BX59: 433.3 | BY59: 0 | BZ59: 0 | CA59: 48.25 | CB59: 3482.5 | CC59: 3008.1 | CD59: 1536.75 | CE59: 1885.1 | CF59: 721.35 | CG59: 899.75 | CH59: 0 | CI59: 0 | CJ59: 3384.6 | CK59: 3405.95 | CL59: 3848.6 | CM59: 0 | CN59: 0 | CO59: 0 | CP59: 0 | CQ59: 0 | CR59: 0 | CS59: 0 | CT59: 141.1 | CU59: 42.9 | CV59: 480.05 | CW59: 2.5 | CX59: 876.2 | CY59: 593 | CZ59: 95.95 | DA59: 0.95 | DB59: 236.45 | DC59: 237.7 | DD59: 130.05 | DE59: 1577.8 | DF59: 38.55 | DG59: 85 | DH59: 122.95 | DI59: 232.9 | DJ59: 479.7 | DK59: 434.55 | DL59: 82 | DM59: 417.05 | DN59: 118.95 | DO59: 157 | DP59: 201.65 | DQ59: 571 | DR59: 97.3 | DS59: 72.85 | DT59: 304 | DU59: 72.22 | DV59: 5.4 | DW59: 1.85 | DX59: 397.313 | DY59: 307.279 | DZ59: 483.145 | EA59: 485.2 | EB59: 479.7 | EC59: 82.5 | ED59: 188.2 | EE59: 228.6 | EF59: 658.45 | EG59: 1124.55 | EH59: 83.5 | EI59: 48.85 | EJ59: 297.05 | EK59: 446.85 | EL59: 192.8 | EM59: 190.25 | EN59: 489.6 | EO59: 489.6 | EP59: 482.4 | EQ59: 84.25 | ER59: 1812.05 | ES59: 117.9 | ET59: 1088.05 | EU59: 14.4 | EV59: 712.35 | EW59: 651.4 | EX59: 867.9 | EY59: 75.05 | EZ59: 0 | FA59: 52.8 | FB59: 24 | FC59: 75.85 | FD59: 196.2 | FE59: 479.9 | FF59: 204.55 | FG59: 642 | FH59: 772.35 | FI59: 320.7 | FJ59: 456.45 | FK59: 166.145 | FL59: 269.765 | FM59: 556 | FN59: 177480.65 | FP59: 586.62413 | FQ59: 194.2 | FR59: 0 | FS59: 316.8 | FT59: 617.04489 | FU59: 454.69673 | FV59: 228 | FW59: 194.75 | FX59: 2592.1158

Sheet REACTIVA
B3: martes, 13 de Enero del 2026
A5: POTENCIA REACTIVA EJECUTADA DE LAS UNIDADES DE GENERACIÓN DEL COES (MVAR) | FP5: CENTRALES NO INTEGRANTES COES
A6: FECHA | B6: HORA | C6: 65333 | D6: 101 | E6: 102 | F6: 42667 | G6: 42668 | H6: 126 | I6: 127 | J6: 138 | K6: 139 | L6: 197 | M6: 203 | N6: 204 | O6: 230 | P6: 209 | Q6: 56677 | R6: 796 | S6: 2146 | T6: 142 | U6: 143 | V6: 125 | W6: 187 | X6: 163 | Y6: 298 | Z6: 299 | AA6: 219 | AB6: 151 | AC6: 152 | AD6: 153 | AE6: 154 | AF6: 756 | AG6: 156 | AH6: 155 | AI6: 182 | AJ6: 212 | AK6: 758 | AL6: 263 | AM6: 265 | AN6: 775 | AO6: 777 | AP6: 2154 | AQ6: 150 | AR6: 149 | AS6: 188 | AT6: 2131 | AU6: 755 | AV6: 252 | AW6: 249 | AX6: 250 | AY6: 117 | AZ6: 119 | BA6: 120 | BB6: 189 | BC6: 122 | BD6: 266 | BE6: 337 | BF6: 338 | BG6: 251 | BH6: 115 | BI6: 239 | BJ6: 288 | BK6: 240 | BL6: 241 | BM6: 242 | BN6: 191 | BO6: 194 | BP6: 196 | BQ6: 207 | BR6: 236 | BS6: 795 | BT6: 285 | BU6: 995 | BV6: 996 | BW6: 997 | BX6: 766 | BY6: 926 | BZ6: 924 | CA6: 121 | CB6: 103 | CC6: 104 | CD6: 106 | CE6: 105 | CF6: 107 | CG6: 110 | CH6: 109 | CI6: 144 | CJ6: 113 | CK6: 114 | CL6: 193 | CM6: 208 | CN6: 786 | CO6: 787 | CP6: 788 | CQ6: 789 | CR6: 248 | CS6: 2159 | CT6: 267 | CU6: 268 | CV6: 2194 | CW6: 303 | CX6: 59715 | CY6: 62255 | CZ6: 1263 | DA6: 61800 | DB6: 69125 | DC6: 216 | DD6: 198 | DE6: 70400 | DF6: 49607 | DG6: 214 | DH6: 260 | DI6: 2152 | DJ6: 2128 | DK6: 247 | DL6: 228 | DM6: 2135 | DN6: 261 | DO6: 237 | DP6: 253 | DQ6: 770 | DR6: 235 | DS6: 238 | DT6: 2184 | DU6: 61855 | DV6: 223 | DW6: 75566 | DX6: 226 | DY6: 201 | DZ6: 258 | EA6: 259 | EB6: 920 | EC6: 257 | ED6: 256 | EE6: 2148 | EF6: 58288 | EG6: 58289 | EH6: 58839 | EI6: 58840 | EJ6: 75260 | EK6: 296 | EL6: 297 | EM6: 211 | EN6: 2175 | EO6: 2178 | EP6: 2181 | EQ6: 1262 | ER6: 63425 | ES6: 233 | ET6: 2150 | EU6: 2165 | EV6: 2161 | EW6: 61197 | EX6: 58851 | EY6: 225 | EZ6: 2201 | FA6: 2171 | FB6: 760 | FC6: 234 | FD6: 215 | FE6: 917 | FF6: 289 | FG6: 58333 | FH6: 58336 | FI6: 213 | FJ6: 232 | FK6: 2190 | FL6: 69867 | FM6: 75066 | FN6: TOTAL COES | FP6: 221 | FQ6: 222 | FR6: 224 | FS6: 2187 | FT6: 227 | FU6: 49400 | FV6: 199 | FW6: 200 | FX6: TOTAL NO COES
C7: SUR | D7: CENTRO | E7: CENTRO | F7: NORTE | G7: NORTE | H7: NORTE | I7: NORTE | J7: CENTRO | K7: CENTRO | L7: CENTRO | M7: CENTRO | N7: CENTRO | O7: CENTRO | P7: CENTRO | Q7: CENTRO | R7: CENTRO | S7: CENTRO | T7: CENTRO | U7: CENTRO | V7: CENTRO | W7: CENTRO | X7: SUR | Y7: SUR | Z7: SUR | AA7: CENTRO | AB7: SUR | AC7: SUR | AD7: SUR | AE7: SUR | AF7: SUR | AG7: SUR | AH7: SUR | AI7: SUR | AJ7: CENTRO | AK7: NORTE | AL7: NORTE | AM7: NORTE | AN7: CENTRO | AO7: CENTRO | AP7: CENTRO | AQ7: CENTRO | AR7: CENTRO | AS7: CENTRO | AT7: CENTRO | AU7: SUR | AV7: CENTRO | AW7: CENTRO | AX7: CENTRO | AY7: CENTRO | AZ7: CENTRO | BA7: CENTRO | BB7: SUR | BC7: NORTE | BD7: CENTRO | BE7: CENTRO | BF7: CENTRO | BG7: CENTRO | BH7: NORTE | BI7: NORTE | BJ7: NORTE | BK7: SUR | BL7: SUR | BM7: SUR | BN7: CENTRO | BO7: CENTRO | BP7: CENTRO | BQ7: CENTRO | BR7: CENTRO | BS7: CENTRO | BT7: CENTRO | BU7: SUR | BV7: SUR | BW7: SUR | BX7: NORTE | BY7: SUR | BZ7: CENTRO | CA7: NORTE | CB7: CENTRO | CC7: CENTRO | CD7: CENTRO | CE7: CENTRO | CF7: CENTRO | CG7: CENTRO | CH7: CENTRO | CI7: CENTRO | CJ7: CENTRO | CK7: CENTRO | CL7: CENTRO | CM7: CENTRO | CN7: SUR | CO7: SUR | CP7: SUR | CQ7: SUR | CR7: CENTRO | CS7: CENTRO | CT7: CENTRO | CU7: CENTRO | CV7: NORTE | CW7: CENTRO | CX7: CENTRO | CY7: SUR | CZ7: NORTE | DA7: NORTE | DB7: CENTRO | DC7: NORTE | DD7: NORTE | DE7: SUR | DF7: SUR | DG7: CENTRO | DH7: CENTRO | DI7: CENTRO | DJ7: NORTE | DK7: NORTE | DL7: CENTRO | DM7: CENTRO | DN7: SUR | DO7: SUR | DP7: CENTRO | DQ7: CENTRO | DR7: SUR | DS7: CENTRO | DT7: CENTRO | DU7: NORTE | DV7: CENTRO | DW7: CENTRO | DX7: CENTRO | DY7: NORTE | DZ7: CENTRO | EA7: CENTRO | EB7: CENTRO | EC7: NORTE | ED7: NORTE | EE7: SUR | EF7: CENTRO | EG7: CENTRO | EH7: CENTRO | EI7: CENTRO | EJ7: SUR | EK7: CENTRO | EL7: CENTRO | EM7: SUR | EN7: SUR | EO7: SUR | EP7: SUR | EQ7: NORTE | ER7: SUR | ES7: SUR | ET7: SUR | EU7: CENTRO | EV7: CENTRO | EW7: CENTRO | EX7: SUR | EY7: CENTRO | EZ7: CENTRO | FA7: CENTRO | FB7: CENTRO | FC7: SUR | FD7: NORTE | FE7: CENTRO | FF7: NORTE | FG7: NORTE | FH7: NORTE | FI7: CENTRO | FJ7: NORTE | FK7: NORTE | FL7: NORTE | FM7: NORTE | FP7: NORTE | FQ7: CENTRO | FR7: NORTE | FS7: NORTE | FT7: NORTE | FU7: NORTE | FV7: NORTE | FW7: NORTE
C8: HIDROELÉCTRICA | D8: HIDROELÉCTRICA | E8: HIDROELÉCTRICA | F8: TERMOELÉCTRICA | G8: TERMOELÉCTRICA | H8: HIDROELÉCTRICA | I8: HIDROELÉCTRICA | J8: TERMOELÉCTRICA | K8: TERMOELÉCTRICA | L8: TERMOELÉCTRICA | M8: TERMOELÉCTRICA | N8: TERMOELÉCTRICA | O8: TERMOELÉCTRICA | P8: TERMOELÉCTRICA | Q8: TERMOELÉCTRICA | R8: HIDROELÉCTRICA | S8: HIDROELÉCTRICA | T8: TERMOELÉCTRICA | U8: TERMOELÉCTRICA | V8: TERMOELÉCTRICA | W8: TERMOELÉCTRICA | X8: HIDROELÉCTRICA | Y8: HIDROELÉCTRICA | Z8: HIDROELÉCTRICA | AA8: TERMOELÉCTRICA | AB8: HIDROELÉCTRICA | AC8: HIDROELÉCTRICA | AD8: HIDROELÉCTRICA | AE8: HIDROELÉCTRICA | AF8: TERMOELÉCTRICA | AG8: TERMOELÉCTRICA | AH8: TERMOELÉCTRICA | AI8: HIDROELÉCTRICA | AJ8: HIDROELÉCTRICA | AK8: TERMOELÉCTRICA | AL8: TERMOELÉCTRICA | AM8: TERMOELÉCTRICA | AN8: HIDROELÉCTRICA | AO8: HIDROELÉCTRICA | AP8: HIDROELÉCTRICA | AQ8: HIDROELÉCTRICA | AR8: HIDROELÉCTRICA | AS8: HIDROELÉCTRICA | AT8: HIDROELÉCTRICA | AU8: HIDROELÉCTRICA | AV8: TERMOELÉCTRICA | AW8: TERMOELÉCTRICA | AX8: TERMOELÉCTRICA | AY8: HIDROELÉCTRICA | AZ8: HIDROELÉCTRICA | BA8: HIDROELÉCTRICA | BB8: HIDROELÉCTRICA | BC8: HIDROELÉCTRICA | BD8: HIDROELÉCTRICA | BE8: HIDROELÉCTRICA | BF8: HIDROELÉCTRICA | BG8: HIDROELÉCTRICA | BH8: TERMOELÉCTRICA | BI8: TERMOELÉCTRICA | BJ8: TERMOELÉCTRICA | BK8: TERMOELÉCTRICA | BL8: TERMOELÉCTRICA | BM8: TERMOELÉCTRICA | BN8: HIDROELÉCTRICA | BO8: TERMOELÉCTRICA | BP8: TERMOELÉCTRICA | BQ8: TERMOELÉCTRICA | BR8: TERMOELÉCTRICA | BS8: TERMOELÉCTRICA | BT8: TERMOELÉCTRICA | BU8: TERMOELÉCTRICA | BV8: TERMOELÉCTRICA | BW8: TERMOELÉCTRICA | BX8: HIDROELÉCTRICA | BY8: TERMOELÉCTRICA | BZ8: TERMOELÉCTRICA | CA8: HIDROELÉCTRICA | CB8: HIDROELÉCTRICA | CC8: HIDROELÉCTRICA | CD8: HIDROELÉCTRICA | CE8: HIDROELÉCTRICA | CF8: HIDROELÉCTRICA | CG8: TERMOELÉCTRICA | CH8: TERMOELÉCTRICA | CI8: TERMOELÉCTRICA | CJ8: TERMOELÉCTRICA | CK8: TERMOELÉCTRICA | CL8: TERMOELÉCTRICA | CM8: TERMOELÉCTRICA | CN8: TERMOELÉCTRICA | CO8: TERMOELÉCTRICA | CP8: TERMOELÉCTRICA | CQ8: TERMOELÉCTRICA | CR8: TERMOELÉCTRICA | CS8: TERMOELÉCTRICA | CT8: HIDROELÉCTRICA | CU8: HIDROELÉCTRICA | CV8: HIDROELÉCTRICA | CW8: SOLAR | CX8: EÓLICA | CY8: SOLAR | CZ8: EÓLICA | DA8: SOLAR | DB8: HIDROELÉCTRICA | DC8: HIDROELÉCTRICA | DD8: HIDROELÉCTRICA | DE8: SOLAR | DF8: HIDROELÉCTRICA | DG8: HIDROELÉCTRICA | DH8: HIDROELÉCTRICA | DI8: HIDROELÉCTRICA | DJ8: HIDROELÉCTRICA | DK8: HIDROELÉCTRICA | DL8: HIDROELÉCTRICA | DM8: HIDROELÉCTRICA | DN8: SOLAR | DO8: SOLAR | DP8: EÓLICA | DQ8: EÓLICA | DR8: SOLAR | DS8: HIDROELÉCTRICA | DT8: HIDROELÉCTRICA | DU8: HIDROELÉCTRICA | DV8: HIDROELÉCTRICA | DW8: SOLAR | DX8: HIDROELÉCTRICA | DY8: HIDROELÉCTRICA | DZ8: HIDROELÉCTRICA | EA8: HIDROELÉCTRICA | EB8: HIDROELÉCTRICA | EC8: EÓLICA | ED8: EÓLICA | EE8: SOLAR | EF8: EÓLICA | EG8: EÓLICA | EH8: EÓLICA | EI8: EÓLICA | EJ8: SOLAR | EK8: HIDROELÉCTRICA | EL8: HIDROELÉCTRICA | EM8: HIDROELÉCTRICA | EN8: HIDROELÉCTRICA | EO8: HIDROELÉCTRICA | EP8: HIDROELÉCTRICA | EQ8: EÓLICA | ER8: SOLAR | ES8: SOLAR | ET8: SOLAR | EU8: HIDROELÉCTRICA | EV8: EÓLICA | EW8: EÓLICA | EX8: SOLAR | EY8: TERMOELÉCTRICA | EZ8: TERMOELÉCTRICA | FA8: TERMOELÉCTRICA | FB8: TERMOELÉCTRICA | FC8: SOLAR | FD8: HIDROELÉCTRICA | FE8: HIDROELÉCTRICA | FF8: TERMOELÉCTRICA | FG8: TERMOELÉCTRICA | FH8: TERMOELÉCTRICA | FI8: TERMOELÉCTRICA | FJ8: TERMOELÉCTRICA | FK8: TERMOELÉCTRICA | FL8: TERMOELÉCTRICA | FM8: TERMOELÉCTRICA | FP8: HIDROELÉCTRICA | FQ8: HIDROELÉCTRICA | FR8: HIDROELÉCTRICA | FS8: HIDROELÉCTRICA | FT8: TERMOELÉCTRICA | FU8: TERMOELÉCTRICA | FV8: HIDROELÉCTRICA | FW8: HIDROELÉCTRICA
C9: HYDRO GLOBAL PERÚ S.A.C. | D9: ELECTROPERU | E9: ELECTROPERU | F9: ELECTROPERU | G9: ELECTROPERU | H9: ORAZUL ENERGY PERÚ | I9: ORAZUL ENERGY PERÚ | J9: TERMOSELVA | K9: TERMOSELVA | L9: KALLPA GENERACION S.A. | M9: KALLPA GENERACION S.A. | N9: KALLPA GENERACION S.A. | O9: KALLPA GENERACION S.A. | P9: KALLPA GENERACION S.A. | Q9: KALLPA GENERACION S.A. | R9: KALLPA GENERACION S.A. | S9: KALLPA GENERACION S.A. | T9: SHOUGESA | U9: SHOUGESA | V9: SHOUGESA | W9: SHOUGESA | X9: EGEMSA | Y9: EGESUR | Z9: EGESUR | AA9: EGESUR | AB9: EGASA | AC9: EGASA | AD9: EGASA | AE9: EGASA | AF9: EGASA | AG9: EGASA | AH9: EGASA | AI9: SAN GABAN | AJ9: CELEPSA | AK9: MINERA CERRO VERDE | AL9: PLANTA DE RESERVA FRIA DE GENERACION DE ETEN S.A. | AM9: PLANTA DE RESERVA FRIA DE GENERACION DE ETEN S.A. | AN9: EMPRESA DE GENERACION HUALLAGA | AO9: EMPRESA DE GENERACION HUALLAGA | AP9: LA VIRGEN | AQ9: CHINANGO S.A.C. | AR9: CHINANGO S.A.C. | AS9: HIDROELECTRICA HUANCHOR S.A.C. | AT9: CELEPSA RENOVABLES S.R.L. | AU9: INLAND ENERGY SAC | AV9: FENIX POWER PERÚ | AW9: FENIX POWER PERÚ | AX9: FENIX POWER PERÚ | AY9: STATKRAFT S.A | AZ9: STATKRAFT S.A | BA9: STATKRAFT S.A | BB9: STATKRAFT S.A | BC9: STATKRAFT S.A | BD9: STATKRAFT S.A | BE9: CENTRALES SANTA ROSA S.A.C. | BF9: CENTRALES SANTA ROSA S.A.C. | BG9: EMPRESA DE GENERACION HUANZA | BH9: ENEL GENERACION PIURA S.A. | BI9: ENEL GENERACION PIURA S.A. | BJ9: ENEL GENERACION PIURA S.A. | BK9: ENGIE ENERGIA PERU S.A.A. | BL9: ENGIE ENERGIA PERU S.A.A. | BM9: ENGIE ENERGIA PERU S.A.A. | BN9: ENGIE ENERGIA PERU S.A.A. | BO9: ENGIE ENERGIA PERU S.A.A. | BP9: ENGIE ENERGIA PERU S.A.A. | BQ9: ENGIE ENERGIA PERU S.A.A. | BR9: ENGIE ENERGIA PERU S.A.A. | BS9: ENGIE ENERGIA PERU S.A.A. | BT9: ENGIE ENERGIA PERU S.A.A. | BU9: ENGIE ENERGIA PERU S.A.A. | BV9: ENGIE ENERGIA PERU S.A.A. | BW9: ENGIE ENERGIA PERU S.A.A. | BX9: ENGIE ENERGIA PERU S.A.A. | BY9: INFRAESTRUCTURAS Y ENERGIAS DEL PERU S.A.C. | BZ9: INFRAESTRUCTURAS Y ENERGIAS DEL PERU S.A.C. | CA9: INVERSIONES SHAQSHA S.A.C. | CB9: ORYGEN PERU S.A.A. | CC9: ORYGEN PERU S.A.A. | CD9: ORYGEN PERU S.A.A. | CE9: ORYGEN PERU S.A.A. | CF9: ORYGEN PERU S.A.A. | CG9: ORYGEN PERU S.A.A. | CH9: ORYGEN PERU S.A.A. | CI9: ORYGEN PERU S.A.A. | CJ9: ORYGEN PERU S.A.A. | CK9: ORYGEN PERU S.A.A. | CL9: ORYGEN PERU S.A.A. | CM9: ORYGEN PERU S.A.A. | CN9: SAMAY I S.A.C | CO9: SAMAY I S.A.C | CP9: SAMAY I S.A.C | CQ9: SAMAY I S.A.C | CR9: TERMOCHILCA S.A.C. | CS9: TERMOCHILCA S.A.C. | CT9: TRANSMISION ANDINA DE GENERACION S.A.C. | CU9: TRANSMISION ANDINA DE GENERACION S.A.C. | CV9: CELARIS ENERGY S.A. | CW9: COLCA SOLAR S.A.C. | CX9: ENERGIA RENOVABLE DEL SUR S.A. | CY9: GR CORTARRAMA SOCIEDAD ANONIMA CERRADA | CZ9: GR TARUCA SOCIEDAD ANONIMA CERRADA | DA9: KONDU SAC | DB9: VARI ENERGIA S.A.C. | DC9: ORAZUL ENERGY PERÚ | DD9: ORAZUL ENERGY PERÚ | DE9: KALLPA GENERACION S.A. | DF9: SAN GABAN | DG9: MAJA ENERGIA S.A.C. | DH9: EMPRESA DE GENERACION ELECTRICA CANCHAYLLO SAC | DI9: EMPRESA DE GENERACION ELECTRICA SANTA ANA S.A.C. | DJ9: EMPRESA ELECTRICA AGUA AZUL | DK9: EMPRESA ELECTRICA RIO DOBLE | DL9: HIDROCAÑETE S.A. | DM9: HUAURA POWER GROUP S.A. | DN9: MOQUEGUA FV S.A.C. | DO9: PANAMERICANA SOLAR SAC. | DP9: PARQUE EOLICO MARCONA S.A.C. | DQ9: PARQUE EOLICO TRES HERMANAS S.A.C. | DR9: TACNA SOLAR SAC. | DS9: ELECTRICA YANAPAMPA SAC | DT9: ANDEAN POWER S.A.C. | DU9: ASOCIACIÓN SANTA LUCIA DE CHACAS | DV9: ATRIA ENERGIA S.A.C. | DW9: COENERGY S.A.C. | DX9: EGEJUNIN | DY9: EGEJUNIN | DZ9: EGEJUNIN | EA9: EGEJUNIN | EB9: EMPRESA DE GENERACION ELECTRICA RIO BAÑOS S.A.C. | EC9: ENERGÍA EÓLICA S.A. | ED9: ENERGÍA EÓLICA S.A. | EE9: ENGIE ENERGIA PERU S.A.A. | EF9: ENGIE ENERGIA PERU S.A.A. | EG9: ENGIE ENERGIA PERU S.A.A. | EH9: ENGIE ENERGIA PERU S.A.A. | EI9: ENGIE ENERGIA PERU S.A.A. | EJ9: ENGIE ENERGIA PERU S.A.A. | EK9: GENERACIÓN ANDINA S.A.C. | EL9: GENERACIÓN ANDINA S.A.C. | EM9: GENERADORA DE ENERGÍA DEL PERÚ | EN9: GENERADORA DE ENERGÍA DEL PERÚ | EO9: GENERADORA DE ENERGÍA DEL PERÚ | EP9: GENERADORA DE ENERGÍA DEL PERÚ | EQ9: GR PAINO SOCIEDAD ANONIMA CERRADA | ER9: JOYA SOLAR S.A.C. | ES9: MAJES ARCUS S.A.C. | ET9: ORYGEN PERU S.A.A. | EU9: ORYGEN PERU S.A.A. | EV9: ORYGEN PERU S.A.A. | EW9: ORYGEN PERU S.A.A. | EX9: ORYGEN PERU S.A.A. | EY9: PETRAMAS | EZ9: PETRAMAS | FA9: PETRAMAS | FB9: PETRAMAS | FC9: REPARTICIÓN ARCUS S.A.C. | FD9: SINERSA | FE9: SINERSA | FF9: BIOENERGIA DEL CHIRA S.A. | FG9: GM OPERACIONES S.A.C. | FH9: GM OPERACIONES S.A.C. | FI9: AGRO INDUSTRIAL PARAMONGA S.A. | FJ9: AGROAURORA S.A.C. | FK9: AGROINDUSTRIAS SAN JACINTO S.A.A. | FL9: AGROLMOS SOCIEDAD ANONIMA - AGROLMOS S.A. | FM9: CASA GRANDE S.A.A. | FP9: UNACEM PERU S.A. | FQ9: ELECTRO ORIENTE | FR9: AGUAS Y ENERGIA PERU | FS9: ELECTRO ZAÑA S.A.C. | FT9: ELECTRONOROESTE S.A. | FU9: SDE PIURA | FV9: SINERSA | FW9: SINERSA
C10: SAN GABAN III | D10: MANTARO | E10: RESTITUCION | F10: TUMBES MAK 1 | G10: TUMBES MAK 2 | H10: CARHUAQUERO | I10: CAÑON DEL PATO | J10: AGUAYTIA TG1 | K10: AGUAYTIA TG2 | L10: KALLPA TG1 | M10: KALLPA TG2 | N10: KALLPA TG3 | O10: KALLPA TV | P10: LFLORES TG1 | Q10: LFLORES TV | R10: CERRO DEL AGUILA | S10: CERRODELAGUILAG4 | T10: SHOUGESA TV1 | U10: SHOUGESA TV2 | V10: SHOUGESA TV3 | W10: SHOUGESA CUMMINS | X10: MACHUPICCHU | Y10: ARICOTA 1 | Z10: ARICOTA 2 | AA10: INDEPENDENCIA | AB10: CHARCANI I,II,III | AC10: CHARCANI IV | AD10: CHARCANI V | AE10: CHARCANI VI | AF10: CHILINA TG | AG10: MOLLENDO 1, 2, 3 | AH10: CHILINA (SULZ 1,2) | AI10: SAN GABAN II | AJ10: PLATANAL | AK10: RECKA | AL10: RF ETEN TG1 | AM10: RF ETEN TG2 | AN10: CHAGLLA GP1 | AO10: CHAGLLA | AP10: LA VIRGEN | AQ10: CHIMAY | AR10: YANANGO | AS10: HUANCHOR | AT10: MARAÑON | AU10: STA TERESA | AV10: FENIX GT11 | AW10: FENIX GT12 | AX10: FENIX TV10 | AY10: YAUPI | AZ10: MALPASO | BA10: CAHUA | BB10: ARCATA | BC10: GALLITO CIEGO | BD10: CHEVES | BE10: SANTA ROSA 1 | BF10: SANTA ROSA 2 | BG10: HUANZA | BH10: MALACAS2 TG4 | BI10: MALACAS3 TG 5 | BJ10: MALACAS1 TG6 | BK10: RF ILO2 TG1 | BL10: RF ILO2 TG2 | BM10: RF ILO2 TG3 | BN10: YUNCAN | BO10: CHILCA1 TG1 | BP10: CHILCA1 TG2 | BQ10: CHILCA1 TG3 | BR10: CHILCA-TV | BS10: CHILCA2 TG41 | BT10: CHILCA2-TV | BU10: CTNEPI_TG41 | BV10: CTNEPI_TG42 | BW10: CTNEPI_TG43 | BX10: QUITARACSA | BY10: RF PTO MALDONADO | BZ10: RF PUCALLPA | CA10: PARIAC | CB10: HUINCO | CC10: MATUCANA | CD10: MOYOPAMPA | CE10: CALLAHUANCA | CF10: HUAMPANI | CG10: STA ROSA WEST TG7 | CH10: UTI_5 | CI10: UTI_6 | CJ10: VENTANILLA 3 | CK10: VENTANILLA 4 | CL10: VENTANILLA TV | CM10: STAROSA TG8 | CN10: PTO_BRVO TG1 | CO10: PTO_BRVO TG2 | CP10: PTO_BRVO TG3 | CQ10: PTO_BRVO TG4 | CR10: OLLEROS TG1 | CS10: OLLEROS TV | CT10: OROYA | CU10: PACHACHACA | CV10: MANTA I | CW10: CS YARUCAYA | CX10: SAN JUAN | CY10: MATARANI | CZ10: DUNA | DA10: CARHUAQUERO (CS) | DB10: ANASHIRONI | DC10: CARHUAQUERO4 | DD10: CAÑA BRAVA | DE10: SUNNY | DF10: TUPURI | DG10: RONCADOR | DH10: CANCHAYLLO | DI10: RENOVANDESH1 | DJ10: POTRERO | DK10: PIZARRAS | DL10: NIMPERIAL | DM10: YARUCAYA | DN10: MOQUEGUA-SOLAR | DO10: PANAMERICANA-SOLAR | DP10: PQE-EOLICO-MARCONA | DQ10: PQE-EOLICO-3-HERMANAS | DR10: TACNA-SOLAR | DS10: YANAPAMPA | DT10: CARHUAC | DU10: HUALLIN | DV10: PURMACANA | DW10: COENERGY | DX10: HUASAHUASI | DY10: STACRUZ_1_2 | DZ10: RUNATULLO_II | EA10: RUNATULLO_III | EB10: RUCUY | EC10: PQE-EOLICO-TALARA | ED10: PQE-EOLICO-CUPISNIQUE | EE10: INTIPAMPA | EF10: PUNTA LOMITAS-BL1 | EG10: PUNTA LOMITAS-BL2 | EH10: PUN LOMITAS_EXP-BL1 | EI10: PUN LOMITAS_EXP-BL2 | EJ10: EXPANSIÓN INTIPAMPA | EK10: 8AGOSTO | EL10: EL CARMEN | EM10: LA JOYA | EN10: ANGEL_I | EO10: ANGEL_II | EP10: ANGEL_III | EQ10: HUAMBOS | ER10: SAN MARTIN SOLAR | ES10: MAJES | ET10: RUBI | EU10: CH_HER1 | EV10: WAYRA-I | EW10: WAYRA EXTENSION | EX10: CLEMESI | EY10: HUAYCOLORO | EZ10: CALLAO | FA10: DONA_CATALINA | FB10: LAGRINGAV | FC10: REPARTICION | FD10: POECHOS2 | FE10: CHANCAY | FF10: CANA BRAVA | FG10: REFINERIA TALARA TV1 | FH10: REFINERÍA TALARA TV2 | FI10: PARAMONGA | FJ10: MAPLE | FK10: SAN_JACINTO | FL10: AGROLMOS | FM10: CASA GRANDE | FN10: MVAR | FP10: CARPAPATA | FQ10: CENTRALES ELOR | FR10: PIAS1 | FS10: ZANA | FT10: TABLAZO | FU10: TALLANCA | FV10: CURUMUY | FW10: POECHOS1 | FX10: MVAR
A11: 13/01/2026 | B11: 00:30 | C11: 51.9 | D11: -29.1 | E11: 8 | H11: -11 | I11: 4.7 | L11: 0 | M11: 0 | N11: -16.3 | P11: 0 | R11: 4.9 | S11: 0.1 | X11: -3.6 | Y11: 1.2 | Z11: 0.7 | AA11: 0 | AB11: -3.6 | AC11: 3.2 | AD11: 4.8 | AI11: 10.7 | AJ11: 15.9 | AN11: -1.8 | AO11: 60.6 | AP11: 9.6 | AR11: 5.1 | AS11: -0.3 | AT11: 2.3 | AU11: 1 | AV11: 15.6 | AW11: -31.2 | AX11: -44.4 | AY11: 7.8 | AZ11: 1.5 | BA11: -2.4 | BB11: 0.5 | BC11: 2 | BD11: -3.9 | BG11: 0 | BJ11: 3.3 | BN11: 8.6 | BO11: -40.3 | BP11: -41.5 | BQ11: -7.1 | BR11: 2.4 | BS11: -12.6 | BT11: 1.1 | BX11: 0 | CA11: -0.4 | CB11: 29.7 | CC11: 18.4 | CD11: 2.5 | CE11: 3.5 | CF11: -0.2 | CG11: 0 | CJ11: 5.3 | CK11: 9.3 | CL11: -24.2 | CT11: -1.3 | CU11: 0 | CV11: 1.4 | CX11: -17.3 | CY11: 0 | CZ11: -5.1 | DB11: 0 | DC11: -0.1 | DD11: -0.9 | DE11: 0 | DG11: 0.2 | DH11: 1.3 | DI11: 0 | DJ11: -1.3 | DK11: 0.1 | DL11: 0.5 | DN11: 0 | DO11: 0 | DP11: -6.6 | DQ11: 5 | DR11: 0 | DS11: 0 | DT11: 0.3 | DU11: 0.044 | DV11: 0 | DX11: -4.7 | DY11: 0.8 | DZ11: 3.1 | EA11: 2.9 | EB11: 1.4 | EE11: 0 | EF11: -9 | EG11: -9.7 | EH11: -0.7 | EI11: -0.5 | EJ11: 0 | EK11: 2.6 | EL11: -0.3 | EM11: 1.6 | EN11: 0.2 | EO11: 0.2 | EP11: 0.2 | EQ11: -5.1 | ER11: 0 | ES11: 0 | ET11: 0 | EU11: -0.2 | EV11: -13.6 | EW11: -1.3 | EX11: 0 | EY11: 1.5 | FA11: 0.8 | FB11: 0.5 | FC11: 0 | FD11: 0.4 | FE11: 1.6 | FF11: 2.2 | FG11: 5.7 | FH11: 0 | FI11: 3.1 | FJ11: 1.4 | FK11: 2.63 | FL11: 3.85 | FN11: -9.876 | FP11: 2.59598 | FS11: 1.8 | FT11: 0.28479 | FU11: 0.30068 | FV11: -0.9 | FW11: 0.3 | FX11: 4.38145
A12: 13/01/2026 | B12: 01:00 | C12: 54 | D12: -27.9 | E12: 8.9 | H12: -8.9 | I12: 6.3 | L12: 0 | M12: 0 | N12: -17.6 | P12: 0 | R12: 7.7 | S12: 0.1 | X12: -2.4 | Y12: 1.3 | Z12: 0.9 | AA12: 0 | AB12: -3.5 | AC12: 3.4 | AD12: 4.8 | AI12: 10.4 | AJ12: 14.5 | AN12: -1.8 | AO12: 59.3 | AP12: 9.4 | AR12: 4.7 | AS12: -0.3 | AT12: 2.3 | AU12: 1.4 | AV12: 12.3 | AW12: -34.3 | AX12: -47.3 | AY12: 8.2 | AZ12: 2.6 | BA12: -1.3 | BB12: 0.5 | BC12: 2 | BD12: -1 | BG12: 0 | BJ12: 3.1 | BN12: 7 | BO12: -41.1 | BP12: -42.2 | BQ12: -8.2 | BR12: 0.5 | BS12: -13.9 | BT12: 0.7 | BX12: 0 | CA12: -0.4 | CB12: 28.5 | CC12: 16.7 | CD12: 1.3 | CE12: 3.4 | CF12: -0.2 | CG12: 0 | CJ12: 3 | CK12: 6.5 | CL12: -27.2 | CT12: -1.2 | CU12: 0 | CV12: 1.4 | CX12: -16.9 | CY12: 0 | CZ12: -4 | DB12: 0 | DC12: 0 | DD12: -0.8 | DE12: 0 | DG12: 0.2 | DH12: 1.4 | DI12: 0 | DJ12: -1.4 | DK12: 0.1 | DL12: 0.5 | DN12: 0 | DO12: 0 | DP12: -6.4 | DQ12: 5.9 | DR12: 0 | DS12: 0 | DT12: 0.3 | DU12: 0.036 | DV12: 0 | DX12: -4.6 | DY12: 1.2 | DZ12: 3 | EA12: 2.8 | EB12: 1.3 | EE12: 0 | EF12: -9 | EG12: -8.7 | EH12: -0.7 | EI12: -0.4 | EJ12: 0 | EK12: 2.6 | EL12: -0.4 | EM12: 1.7 | EN12: 0.2 | EO12: 0.2 | EP12: 0.2 | EQ12: -5.9 | ER12: 0 | ES12: 0 | ET12: 0 | EU12: -0.2 | EV12: -14.8 | EW12: -0.8 | EX12: 0 | EY12: 1.5 | FA12: 0.8 | FB12: 0.5 | FC12: 0 | FD12: 0.4 | FE12: 1.5 | FF12: 2 | FG12: 5.5 | FH12: 0.5 | FI12: 2.9 | FJ12: 1.3 | FK12: 2.33 | FL12: 3.95 | FN12: -23.784 | FP12: 2.51467 | FS12: 1.8 | FT12: 0.28068 | FU12: 0.31181 | FV12: -0.9 | FW12: 0.6 | FX12: 4.60716
A13: 13/01/2026 | B13: 01:30 | C13: 48.8 | D13: -35.7 | E13: 7.8 | H13: -11.7 | I13: 12.1 | L13: 0 | M13: 0 | N13: -17.9 | P13: 0 | R13: 18.2 | S13: 0.1 | X13: -4.3 | Y13: 1.2 | Z13: 0.7 | AA13: 0 | AB13: -3.6 | AC13: 3.2 | AD13: 3.6 | AI13: 8.5 | AJ13: 14.1 | AN13: -1.8 | AO13: 59.6 | AP13: 9.4 | AR13: 3.5 | AS13: -0.3 | AT13: 2.2 | AU13: 1.3 | AV13: 11.3 | AW13: -35.1 | AX13: -48.2 | AY13: 9.8 | AZ13: 2 | BA13: -0.4 | BB13: 0.5 | BC13: 2 | BD13: -0.5 | BG13: 0 | BJ13: 1.6 | BN13: 3.8 | BO13: -43.9 | BP13: -45.3 | BQ13: -10.9 | BR13: -2.7 | BS13: -15.3 | BT13: 0.3 | BX13: 0 | CA13: -0.4 | CB13: 31.7 | CC13: 14.6 | CD13: 0.2 | CE13: 3.6 | CF13: -0.2 | CG13: 0 | CJ13: 1.7 | CK13: 6 | CL13: -28.8 | CT13: -1 | CU13: 0.1 | CV13: 1.4 | CX13: -16.6 | CY13: 0 | CZ13: -4.9 | DB13: 0 | DC13: 0 | DD13: -0.9 | DE13: 0 | DG13: 0.1 | DH13: 1.2 | DI13: 0 | DJ13: -1.1 | DK13: 0.1 | DL13: 0.5 | DN13: 0 | DO13: 0 | DP13: -6.4 | DQ13: 5.1 | DR13: 0 | DS13: 0 | DT13: 0.3 | DU13: 0.036 | DV13: 0 | DX13: -4.5 | DY13: 1.1 | DZ13: 3 | EA13: 2.7 | EB13: 1.1 | EE13: 0 | EF13: -9.7 | EG13: -10.5 | EH13: -0.9 | EI13: -0.9 | EJ13: 0 | EK13: 2.7 | EL13: -0.5 | EM13: 1.8 | EN13: 0.2 | EO13: 0.2 | EP13: 0.2 | EQ13: -5.6 | ER13: 0 | ES13: 0 | ET13: 0 | EU13: -0.2 | EV13: -16.3 | EW13: 0.6 | EX13: 0 | EY13: 1.5 | FA13: 0.8 | FB13: 0.5 | FC13: 0 | FD13: 0.4 | FE13: 1.4 | FF13: 2.1 | FG13: 5.3 | FH13: 0.4 | FI13: 2.4 | FJ13: 0.8 | FK13: 2.87 | FL13: 3.86 | FN13: -58.834 | FP13: 2.41811 | FS13: 1.8 | FT13: 0.27479 | FU13: 0.33565 | FV13: -0.9 | FW13: 0.3 | FX13: 4.22855
A14: 13/01/2026 | B14: 02:00 | C14: 53.7 | D14: -32.5 | E14: 7 | H14: -8.9 | I14: 13.9 | L14: 0 | M14: 0 | N14: -22.2 | P14: 0 | R14: 4.9 | S14: 0.1 | X14: -0.9 | Y14: 1.7 | Z14: 1.1 | AA14: 0 | AB14: -3.6 | AC14: 3.4 | AD14: 6.5 | AI14: 11.4 | AJ14: 11.9 | AN14: -1.8 | AO14: 56.4 | AP14: 9.1 | AR14: 2.6 | AS14: -0.6 | AT14: 2.2 | AU14: 1.1 | AV14: 10.3 | AW14: -36.2 | AX14: -49.2 | AY14: 6.1 | AZ14: 2.1 | BA14: -3.2 | BB14: 0.5 | BC14: 2 | BD14: -3.5 | BG14: 0 | BJ14: 3 | BN14: 6.5 | BO14: -46.3 | BP14: -47.7 | BQ14: -14.1 | BR14: -4.7 | BS14: -15.1 | BT14: 0.1 | BX14: 0 | CA14: -0.4 | CB14: 28.6 | CC14: 18.9 | CD14: 2.7 | CE14: 3.5 | CF14: -0.2 | CG14: 0 | CJ14: -0.8 | CK14: 2.6 | CL14: -33 | CT14: -1.3 | CU14: 0 | CV14: 1.4 | CX14: -13.6 | CY14: 0 | CZ14: -4.7 | DB14: 0 | DC14: 0 | DD14: -0.9 | DE14: 0 | DG14: 0.2 | DH14: 1.3 | DI14: 0 | DJ14: -1.3 | DK14: 0.1 | DL14: 0.5 | DN14: 0 | DO14: 0 | DP14: -5.3 | DQ14: 7.6 | DR14: 0 | DS14: 0 | DT14: 0.3 | DU14: 0.044 | DV14: 0 | DX14: -4.5 | DY14: 0.8 | DZ14: 3.1 | EA14: 2.8 | EB14: 1 | EE14: 0 | EF14: -8.9 | EG14: -9.9 | EH14: -0.8 | EI14: -0.8 | EJ14: 0 | EK14: 2.7 | EL14: -0.6 | EM14: 1.8 | EN14: 0.2 | EO14: 0.2 | EP14: 0.2 | EQ14: -5.4 | ER14: 0 | ES14: 0 | ET14: 0 | EU14: -0.2 | EV14: -12.1 | EW14: -0.8 | EX14: 0 | EY14: 1.5 | FA14: 0.8 | FB14: 0.5 | FC14: 0 | FD14: 0.4 | FE14: 1.2 | FF14: 2.2 | FG14: 5.3 | FH14: 0.4 | FI14: 1.1 | FJ14: 0.8 | FK14: 2.43 | FL14: 3.9 | FN14: -77.326 | FP14: 2.37267 | FS14: 1.8 | FT14: 0.27189 | FU14: 0.26395 | FV14: -0.9 | FW14: 0.4 | FX14: 4.20851
A15: 13/01/2026 | B15: 02:30 | C15: 52.4 | D15: -24.6 | E15: 8.8 | H15: -10 | I15: 6.2 | L15: 0 | M15: 0 | N15: -16.1 | P15: 0 | R15: 10.1 | S15: 0 | X15: -2.4 | Y15: 1.5 | Z15: 1.1 | AA15: 0 | AB15: -3.6 | AC15: 3.4 | AD15: 6.5 | AI15: 11 | AJ15: -0.7 | AN15: -1.5 | AO15: 58.9 | AP15: 9.9 | AR15: 2.9 | AS15: -0.3 | AT15: 2.2 | AU15: 1.1 | AV15: 9.2 | AW15: -37.4 | AX15: -49.7 | AY15: 6.3 | AZ15: 0.2 | BA15: -2.6 | BB15: 0.5 | BC15: 1.9 | BD15: -2.6 | BG15: 0 | BJ15: 2.1 | BN15: 9.6 | BO15: -44.3 | BP15: -45.4 | BQ15: -10.9 | BR15: -1.2 | BS15: -14.2 | BT15: 0.6 | BX15: 0 | CA15: -0.4 | CB15: 21.4 | CC15: 18.4 | CD15: 2.5 | CE15: 3.5 | CF15: -0.2 | CG15: 0 | CJ15: 0.4 | CK15: 4.1 | CL15: -31.3 | CT15: -1 | CU15: 0.1 | CV15: 1.4 | CX15: -13.7 | CY15: 0 | CZ15: -5.2 | DB15: 0 | DC15: -0.1 | DD15: -0.9 | DE15: 0 | DG15: 0.2 | DH15: 1.4 | DI15: 0 | DJ15: -1.1 | DK15: 0.1 | DL15: 0.6 | DN15: 0 | DO15: 0 | DP15: -4.8 | DQ15: 8.7 | DR15: 0 | DS15: 0 | DT15: 0.3 | DU15: 0.053 | DV15: 0 | DX15: -4.5 | DY15: 0.8 | DZ15: 3.1 | EA15: 2.8 | EB15: 1.1 | EE15: 0 | EF15: -8.2 | EG15: -9 | EH15: -0.7 | EI15: -0.8 | EJ15: 0 | EK15: 2.7 | EL15: -0.1 | EM15: 1.9 | EN15: 0.2 | EO15: 0.2 | EP15: 0.2 | EQ15: -5.8 | ER15: 0 | ES15: 0 | ET15: 0 | EU15: -0.2 | EV15: -11.5 | EW15: -0.9 | EX15: 0 | EY15: 1.5 | FA15: 0.8 | FB15: 0.5 | FC15: 0 | FD15: 0.4 | FE15: 1.3 | FF15: 2 | FG15: 5.2 | FH15: 0 | FI15: 1.7 | FJ15: 0.7 | FK15: 2.21 | FL15: 3.87 | FN15: -65.167 | FP15: 2.19903 | FS15: 1.8 | FT15: 0.27972 | FU15: 0.29054 | FV15: -1 | FW15: 0.4 | FX15: 3.96929
A16: 13/01/2026 | B16: 03:00 | C16: 53.1 | D16: -26.8 | E16: 8.4 | H16: -11.5 | I16: 3.2 | L16: 0 | M16: 0 | N16: -17.5 | P16: 0 | R16: 12.9 | S16: 0 | X16: -3.6 | Y16: 1.9 | Z16: 1.4 | AA16: 0 | AB16: -3.5 | AC16: 3.4 | AD16: 6.8 | AI16: 11.6 | AJ16: -1.3 | AN16: -1.6 | AO16: 57.5 | AP16: 9.6 | AR16: 3 | AS16: -0.6 | AT16: 2.2 | AU16: 1.2 | AV16: 9.8 | AW16: -36.9 | AX16: -49.1 | AY16: 6.4 | AZ16: 0 | BA16: -3.6 | BB16: 0.5 | BC16: 2 | BD16: -6.1 | BG16: 0 | BJ16: 1.2 | BN16: 9.2 | BO16: -44.5 | BP16: -45.7 | BQ16: -11.2 | BR16: -2.6 | BS16: -14.3 | BT16: 0.5 | BX16: 0 | CA16: -0.4 | CB16: 5.8 | CC16: 17.3 | CD16: 0.3 | CE16: 4.1 | CF16: -0.2 | CG16: 0 | CJ16: 1 | CK16: 4.6 | CL16: -30.2 | CT16: -0.9 | CU16: 0.1 | CV16: 1.4 | CX16: -13.8 | CY16: 0 | CZ16: -4.8 | DB16: 0 | DC16: 0 | DD16: -0.9 | DE16: 0 | DG16: 0.2 | DH16: 1.3 | DI16: 0 | DJ16: -1.1 | DK16: 0.1 | DL16: 0.5 | DN16: 0 | DO16: 0 | DP16: -4.9 | DQ16: 9.6 | DR16: 0 | DS16: 0 | DT16: 0.3 | DU16: 0.036 | DV16: 0 | DX16: -4.5 | DY16: 0.6 | DZ16: 3.2 | EA16: 2.8 | EB16: 1 | EE16: 0 | EF16: -8.6 | EG16: -9.5 | EH16: -0.7 | EI16: -0.9 | EJ16: 0 | EK16: 2.6 | EL16: -0.1 | EM16: 1.9 | EN16: 0.2 | EO16: 0.2 | EP16: 0.2 | EQ16: -4.9 | ER16: 0 | ES16: 0 | ET16: 0 | EU16: -0.2 | EV16: -10.6 | EW16: -3 | EX16: 0 | EY16: 1.5 | FA16: 0.8 | FB16: 0.5 | FC16: 0 | FD16: 0.4 | FE16: 1.2 | FF16: 2.2 | FG16: 5 | FH16: 0 | FI16: 1 | FJ16: 0.6 | FK16: 2.17 | FL16: 3.15 | FN16: -96.944 | FP16: 1.85063 | FS16: 1.8 | FT16: 0.27365 | FU16: 0.30378 | FV16: -1.1 | FW16: 0.4 | FX16: 3.52806
A17: 13/01/2026 | B17: 03:30 | C17: 57 | D17: -23.8 | E17: 10.2 | H17: -11.2 | I17: 2.7 | L17: 0 | M17: 0 | N17: -14.4 | P17: 0 | R17: 16.6 | S17: 0 | X17: -1.9 | Y17: 1.9 | Z17: 1.4 | AA17: 0 | AB17: -3.6 | AC17: 3.5 | AD17: 7.4 | AI17: 11.3 | AJ17: -1.3 | AN17: -1.6 | AO17: 56.6 | AP17: 9.6 | AR17: 3 | AS17: -0.3 | AT17: 2.2 | AU17: 1.5 | AV17: 10 | AW17: -36.6 | AX17: -49.2 | AY17: 4.2 | AZ17: 0 | BA17: -2.6 | BB17: 0.4 | BC17: 2 | BD17: -3 | BG17: 0 | BJ17: 1.5 | BN17: 5.7 | BO17: -44.1 | BP17: -45.5 | BQ17: -11.3 | BR17: -3.3 | BS17: -14.7 | BT17: 0.6 | BX17: 0 | CA17: -0.3 | CB17: 5.1 | CC17: 16.8 | CD17: -1.2 | CE17: 3.4 | CF17: -0.2 | CG17: 0 | CJ17: 0.1 | CK17: 4.1 | CL17: -31.3 | CT17: -1 | CU17: 0.1 | CV17: 1.4 | CX17: -13.4 | CY17: 0 | CZ17: -5.2 | DB17: 0 | DC17: 0 | DD17: -1 | DE17: 0 | DG17: 0.2 | DH17: 1.3 | DI17: 0 | DJ17: -1.5 | DK17: 0.1 | DL17: 0.6 | DN17: 0 | DO17: 0 | DP17: -5 | DQ17: 9.3 | DR17: 0 | DS17: 0 | DT17: 0.3 | DU17: 0.04 | DV17: 0 | DX17: -4.4 | DY17: 0.9 | DZ17: 3.1 | EA17: 2.8 | EB17: 1 | EE17: 0 | EF17: -9 | EG17: -9.5 | EH17: -0.8 | EI17: -1 | EJ17: 0 | EK17: 2.6 | EL17: -0.1 | EM17: 1.8 | EN17: 0.2 | EO17: 0.2 | EP17: 0.2 | EQ17: -5.4 | ER17: 0 | ES17: 0 | ET17: 0 | EU17: -0.2 | EV17: -11.5 | EW17: -0.5 | EX17: 0 | EY17: 1.5 | FA17: 0.8 | FB17: 0.5 | FC17: 0 | FD17: 0.2 | FE17: 1.2 | FF17: 2.2 | FG17: 5 | FH17: 0 | FI17: 1.6 | FJ17: 0.1 | FK17: 1.83 | FL17: 3.05 | FN17: -87.98 | FP17: 1.81876 | FS17: 1.8 | FT17: 0.27385 | FU17: 0.26813 | FV17: -1 | FW17: 0.4 | FX17: 3.56074
A18: 13/01/2026 | B18: 04:00 | C18: 50.4 | D18: -27.4 | E18: 9 | H18: -11.9 | I18: 11 | L18: 0 | M18: 0 | N18: -17.3 | P18: 0 | R18: 17 | S18: 0.1 | X18: -3.6 | Y18: 2 | Z18: 1.3 | AA18: 1.5 | AB18: -3.5 | AC18: 3.4 | AD18: 7.2 | AI18: 9.1 | AJ18: 0.1 | AN18: -1.6 | AO18: 56.8 | AP18: 9.3 | AR18: 3.5 | AS18: -0.5 | AT18: 2.2 | AU18: 0.4 | AV18: 11.5 | AW18: -35.1 | AX18: -47.3 | AY18: 8 | AZ18: 0 | BA18: -1.5 | BB18: 0.4 | BC18: 2 | BD18: -3.4 | BG18: 0 | BJ18: 1.3 | BN18: 4.5 | BO18: -41.5 | BP18: -43 | BQ18: -8.4 | BR18: -0.1 | BS18: -13.9 | BT18: 0.7 | BX18: 0 | CA18: -0.4 | CB18: 6 | CC18: 16 | CD18: -1.3 | CE18: 3.6 | CF18: -0.1 | CG18: 0 | CJ18: 1.1 | CK18: 5 | CL18: -29.7 | CT18: -1 | CU18: 0 | CV18: 1.4 | CX18: -11.9 | CY18: 0 | CZ18: -5.2 | DB18: 0 | DC18: -0.1 | DD18: -0.8 | DE18: 0 | DG18: 0.2 | DH18: 1.2 | DI18: 0 | DJ18: -1.5 | DK18: 0.1 | DL18: 0.6 | DN18: 0 | DO18: 0 | DP18: -4.7 | DQ18: 10.2 | DR18: 0 | DS18: 0 | DT18: 0.3 | DU18: 0.045 | DV18: 0 | DX18: -4.4 | DY18: 0.9 | DZ18: 3.1 | EA18: 2.8 | EB18: 1.1 | EE18: 0 | EF18: -10 | EG18: -11.1 | EH18: -0.9 | EI18: 0 | EJ18: 0 | EK18: 2.6 | EL18: -0.1 | EM18: 1.7 | EN18: 0.2 | EO18: 0.2 | EP18: 0.2 | EQ18: -5.9 | ER18: 0 | ES18: 0 | ET18: 0 | EU18: -0.2 | EV18: -11.7 | EW18: -0.9 | EX18: 0 | EY18: 1.5 | FA18: 0.8 | FB18: 0.5 | FC18: 0 | FD18: 0.2 | FE18: 1.3 | FF18: 2 | FG18: 4.9 | FH18: 0.3 | FI18: 2.2 | FJ18: 0.2 | FK18: 1.87 | FL18: 3.9 | FN18: -70.985 | FP18: 1.6763 | FS18: 1.8 | FT18: 0.27473 | FU18: 0.22458 | FV18: -1.2 | FW18: 0.6 | FX18: 3.37561
A19: 13/01/2026 | B19: 04:30 | C19: 56.3 | D19: -12.7 | E19: 11 | H19: -8.6 | I19: 14.8 | L19: 0 | M19: 0 | N19: -12.7 | P19: 0 | R19: 22.5 | S19: 0 | X19: -1.8 | Y19: 2 | Z19: 1 | AA19: 2 | AB19: -3.6 | AC19: 3.4 | AD19: 8.6 | AI19: 11.7 | AJ19: 1.1 | AN19: -1.6 | AO19: 56.7 | AP19: 9 | AR19: 2.7 | AS19: -0.1 | AT19: 2.2 | AU19: 0.9 | AV19: 14.6 | AW19: -32.2 | AX19: -44.9 | AY19: 5.8 | AZ19: 0 | BA19: -1.9 | BB19: 0.5 | BC19: 1.8 | BD19: -3.6 | BG19: 0 | BJ19: 2 | BN19: 8.4 | BO19: -38.7 | BP19: -40.2 | BQ19: -5.3 | BR19: 3.9 | BS19: -12.4 | BT19: 1.3 | BX19: 0 | CA19: -0.4 | CB19: 5.1 | CC19: 18 | CD19: 0.3 | CE19: 3.3 | CF19: -0.3 | CG19: 0 | CJ19: 3.1 | CK19: 6.6 | CL19: -27.2 | CT19: -1 | CU19: 0 | CV19: 1.4 | CX19: -11.6 | CY19: 0 | CZ19: -5.2 | DB19: 0 | DC19: -0.1 | DD19: -1 | DE19: 0 | DG19: 0.2 | DH19: 1.1 | DI19: 0 | DJ19: -1.6 | DK19: 0.1 | DL19: 0.6 | DN19: 0 | DO19: 0 | DP19: -4.2 | DQ19: 11.3 | DR19: 0 | DS19: 0 | DT19: 0.3 | DU19: 0.065 | DV19: 0 | DX19: -4.4 | DY19: 0.7 | DZ19: 3.1 | EA19: 2.9 | EB19: 1.1 | EE19: 0 | EF19: -6.4 | EG19: -6.7 | EH19: -0.5 | EI19: -0.6 | EJ19: 0 | EK19: 2.6 | EL19: -0.1 | EM19: 1.7 | EN19: 0.2 | EO19: 0.2 | EP19: 0.2 | EQ19: -5.7 | ER19: 0 | ES19: 0 | ET19: 0 | EU19: -0.2 | EV19: -9.8 | EW19: -0.6 | EX19: 0 | EY19: 1.5 | FA19: 0.8 | FB19: 0.5 | FC19: 0 | FD19: 0.2 | FE19: 1.4 | FF19: 2.3 | FG19: 5.1 | FH19: 0.2 | FI19: 3.6 | FJ19: 0.2 | FK19: 1.65 | FL19: 3.9 | FN19: 21.815 | FP19: 2.03792 | FS19: 1.7 | FT19: 0.26933 | FU19: 0.28649 | FV19: -1 | FW19: 0.3 | FX19: 3.59374
A20: 13/01/2026 | B20: 05:00 | C20: 54.1 | D20: -8.9 | E20: 11.8 | H20: -9.4 | I20: 21 | L20: 0 | M20: 0 | N20: -8.8 | P20: 0 | R20: 31.2 | S20: 0 | X20: -2.3 | Y20: 1.9 | Z20: 1.1 | AA20: 2 | AB20: -3.6 | AC20: 3.4 | AD20: 8.3 | AI20: 10.8 | AJ20: 1.5 | AN20: -1.6 | AO20: 56.9 | AP20: 9.1 | AR20: 3.2 | AS20: -0.4 | AT20: 2 | AU20: 1.7 | AV20: 15.3 | AW20: -31.3 | AX20: -44.2 | AY20: 7 | AZ20: 0 | BA20: -2.7 | BB20: 0.4 | BC20: 2 | BD20: -5.4 | BG20: 0 | BJ20: 1.7 | BN20: 7.6 | BO20: -38.2 | BP20: -39.5 | BQ20: -5 | BR20: 4 | BS20: -12.1 | BT20: 1.4 | BX20: 0 | CA20: -0.4 | CB20: 5.8 | CC20: 17 | CD20: -0.3 | CE20: 3.5 | CF20: -0.1 | CG20: 0 | CJ20: 4.5 | CK20: 8.7 | CL20: -24.7 | CT20: -0.9 | CU20: 0 | CV20: 1.4 | CX20: -10.9 | CY20: 0 | CZ20: -5.2 | DB20: 0 | DC20: 0 | DD20: -0.9 | DE20: 0 | DG20: 0.2 | DH20: 1.1 | DI20: 0 | DJ20: -1.7 | DK20: 0.1 | DL20: 0.5 | DN20: 0 | DO20: 0 | DP20: -4.2 | DQ20: 11.5 | DR20: 0.4 | DS20: 0 | DT20: 0.3 | DU20: 0.04 | DV20: 0 | DX20: -4.4 | DY20: 0.6 | DZ20: 3.2 | EA20: 2.9 | EB20: 1.1 | EE20: 0 | EF20: -6.2 | EG20: -7.7 | EH20: -0.5 | EI20: 0 | EJ20: 0 | EK20: 2.6 | EL20: -0.1 | EM20: 1.7 | EN20: 0.2 | EO20: 0.2 | EP20: 0.2 | EQ20: -5.9 | ER20: 0 | ES20: 0 | ET20: 0 | EU20: -0.2 | EV20: -9.6 | EW20: 0.3 | EX20: 0 | EY20: 1.5 | FA20: 0.8 | FB20: 0.5 | FC20: 0 | FD20: 0.2 | FE20: 1.4 | FF20: 2.2 | FG20: 5 | FH20: 0.2 | FI20: 3.4 | FJ20: 0.7 | FK20: 1.61 | FL20: 3.8 | FN20: 51.45 | FP20: 2.12473 | FS20: 1.6 | FT20: 0.27415 | FU20: 0.25776 | FV20: -1 | FW20: 0.3 | FX20: 3.55664
A21: 13/01/2026 | B21: 05:30 | C21: 54.1 | D21: -12.6 | E21: 11.8 | H21: -9.8 | I21: 3.7 | L21: 0 | M21: 0 | N21: -6.4 | P21: 0 | R21: 31.5 | S21: 0.1 | X21: -1.6 | Y21: 1.6 | Z21: 1.1 | AA21: 2 | AB21: -3.6 | AC21: 3.4 | AD21: 7.8 | AI21: 11.4 | AJ21: 1.7 | AN21: -1.6 | AO21: 56.5 | AP21: 9.1 | AR21: 3.2 | AS21: -1.4 | AT21: 1.9 | AU21: 1.4 | AV21: 16.2 | AW21: -30.5 | AX21: -43.2 | AY21: 7 | AZ21: 0 | BA21: -3.1 | BB21: 0.5 | BC21: 2 | BD21: -4.8 | BG21: 0.4 | BJ21: 1.2 | BN21: 7.1 | BO21: -37.8 | BP21: -39.3 | BQ21: -4.1 | BR21: 4.8 | BS21: -12.1 | BT21: 1.6 | BX21: 0 | CA21: -0.4 | CB21: 6.4 | CC21: 16.2 | CD21: -0.1 | CE21: 3.6 | CF21: -0.3 | CG21: 0 | CJ21: 6.3 | CK21: 9.9 | CL21: -22.4 | CT21: -1.1 | CU21: 0 | CV21: 1.4 | CX21: -11.4 | CY21: 0 | CZ21: -5 | DB21: 0 | DC21: -0.1 | DD21: -0.9 | DE21: -0.1 | DG21: 0.2 | DH21: 1.1 | DI21: 0 | DJ21: -1.5 | DK21: 0.1 | DL21: 0.6 | DN21: 0 | DO21: 0 | DP21: -4.4 | DQ21: 11.8 | DR21: 0.7 | DS21: 0 | DT21: 0.3 | DU21: 0.04 | DV21: 0 | DX21: -4.5 | DY21: 0.7 | DZ21: 3.2 | EA21: 3 | EB21: 1.3 | EE21: 0.3 | EF21: -6.6 | EG21: -8.2 | EH21: 0 | EI21: 0 | EJ21: 0 | EK21: 2.6 | EL21: -0.1 | EM21: 1.7 | EN21: 0.2 | EO21: 0.2 | EP21: 0.2 | EQ21: -5.9 | ER21: 0.9 | ES21: 0 | ET21: 2.1 | EU21: -0.2 | EV21: -10 | EW21: -0.5 | EX21: 0.7 | EY21: 1.5 | FA21: 0.8 | FB21: 0.5 | FC21: 0 | FD21: 0.2 | FE21: 1.6 | FF21: 2.2 | FG21: 5 | FH21: 0.3 | FI21: 3.6 | FJ21: 0.7 | FK21: 2.14 | FL21: 3.86 | FN21: 45.64 | FP21: 2.35596 | FS21: 1.7 | FT21: 0.27288 | FU21: 0.27574 | FV21: -1.1 | FW21: 0.2 | FX21: 3.70458
A22: 13/01/2026 | B22: 06:00 | C22: 51.5 | D22: -20.5 | E22: 10.7 | H22: -10.9 | I22: -0.3 | L22: 0 | M22: 0 | N22: -14.8 | P22: 0 | R22: 44.1 | S22: 0 | X22: -3.6 | Y22: 1.5 | Z22: 0.9 | AA22: 2.2 | AB22: -3.4 | AC22: 3.4 | AD22: 6.6 | AI22: 9.7 | AJ22: 2.7 | AN22: -1.6 | AO22: 55.6 | AP22: 8.8 | AR22: 2.9 | AS22: -1.5 | AT22: 1.9 | AU22: 1.1 | AV22: 13 | AW22: -33.7 | AX22: -45.7 | AY22: 5.6 | AZ22: 0 | BA22: -2.7 | BB22: 0.5 | BC22: 2 | BD22: -5.8 | BG22: 0.4 | BJ22: 1.4 | BN22: 1.8 | BO22: -43 | BP22: -44.3 | BQ22: -9.4 | BR22: 0 | BS22: -13.6 | BT22: 0.8 | BX22: 0 | CA22: -0.4 | CB22: 5.4 | CC22: 17.1 | CD22: -0.5 | CE22: 3.4 | CF22: -0.2 | CG22: 0 | CJ22: 4.5 | CK22: 8.1 | CL22: -24.5 | CT22: -0.9 | CU22: 0.1 | CV22: 1.4 | CX22: -13.4 | CY22: 0.1 | CZ22: -5.2 | DB22: 0 | DC22: 0 | DD22: -0.8 | DE22: 0.2 | DG22: 0.2 | DH22: 1.1 | DI22: 0 | DJ22: -1.5 | DK22: 0.1 | DL22: 0.6 | DN22: 0 | DO22: 0 | DP22: -5.1 | DQ22: 10.7 | DR22: 0.3 | DS22: -0.1 | DT22: 0.3 | DU22: 0.044 | DV22: 0 | DX22: -4.2 | DY22: 0.8 | DZ22: 3.1 | EA22: 3 | EB22: 1.3 | EE22: 0.1 | EF22: -8.1 | EG22: -9.1 | EH22: 0 | EI22: 0 | EJ22: 1.4 | EK22: 2.6 | EL22: -0.1 | EM22: 1.7 | EN22: 0.2 | EO22: 0.2 | EP22: 0.2 | EQ22: -5.9 | ER22: 1 | ES22: 0 | ET22: 2.2 | EU22: -0.2 | EV22: -11.3 | EW22: -2.5 | EX22: 5.4 | EY22: 1.5 | FA22: 0.8 | FB22: 0.5 | FC22: 0 | FD22: 0.2 | FE22: 1.6 | FF22: 2.1 | FG22: 5 | FH22: 0.3 | FI22: 2 | FJ22: 0.9 | FK22: 2.19 | FL22: 3.8 | FN22: -21.966 | FP22: 1.98919 | FS22: 1.7 | FT22: 0.27106 | FU22: 0.28921 | FV22: -0.9 | FW22: 0.3 | FX22: 3.64946
... A58: 14/01/2026 | B58: 00:00 | C58: 40.5 | D58: -4.7 | E58: 14.6 | H58: -14.5 | I58: 18.2 | L58: 0 | M58: -0.4 | N58: 24.4 | P58: 6.2 | R58: 50.2 | S58: -0.1 | X58: 1 | Y58: 2 | Z58: 1.1 | AA58: 2.1 | AB58: -3.6 | AC58: 3.4 | AD58: -0.3 | AI58: 2.9 | AJ58: 9.1 | AN58: -1.7 | AO58: 46.1 | AP58: 0 | AR58: 0 | AS58: -0.1 | AT58: 0 | AU58: 0.9 | AV58: 35 | AW58: -12.2 | AX58: -39.7 | AY58: 7.6 | AZ58: 3.2 | BA58: -6.1 | BB58: 0.4 | BC58: 2 | BD58: 0.3 | BG58: 2.1 | BJ58: 0.4 | BN58: 13.3 | BO58: -31.5 | BP58: -32.5 | BQ58: -2.1 | BR58: 11.7 | BS58: -5.7 | BT58: 4.6 | BX58: -2.5 | CA58: -0.4 | CB58: 0 | CC58: 0 | CD58: 0 | CE58: 0 | CF58: 0 | CG58: 0 | CJ58: 0 | CK58: 0 | CL58: 0 | CT58: -1.2 | CU58: 0.1 | CV58: 1.4 | CX58: -5.6 | CY58: 0 | CZ58: 0 | DB58: 0.1 | DC58: -0.1 | DD58: -0.9 | DE58: 0 | DG58: 0.2 | DH58: 1.3 | DI58: 0.2 | DJ58: -2.3 | DK58: 0.1 | DL58: 0.6 | DN58: 0 | DO58: 0 | DP58: 0 | DQ58: 0 | DR58: 0 | DS58: -0.1 | DT58: 0.6 | DU58: 0.028 | DV58: 0.1 | DX58: 0 | DY58: 0 | DZ58: 0 | EA58: 0 | EB58: 1.3 | EE58: 0 | EF58: -4.3 | EG58: 0 | EH58: -0.3 | EI58: -0.4 | EJ58: 0 | EK58: 2.6 | EL58: -0.1 | EM58: 0 | EN58: 0.2 | EO58: 0.2 | EP58: 0.2 | EQ58: -1.4 | ER58: 0 | ES58: 0 | ET58: 0 | EU58: 0 | EV58: 0 | EW58: 0 | EX58: 0 | EY58: 1.5 | FA58: 0.8 | FB58: 0.5 | FC58: 0 | FD58: 0.8 | FE58: 1.6 | FF58: 2.6 | FG58: 6.4 | FH58: 0.5 | FI58: 3.8 | FJ58: 0 | FK58: 3.11 | FL58: 4.15 | FN58: 163.488 | FP58: 2.62785 | FS58: 0 | FT58: 0.29341 | FU58: 0.3033 | FV58: -1.4 | FW58: 0.4 | FX58: 2.22456
A59: EJEC | C59: 1142.95 | D59: 449.2 | E59: 479.85 | F59: 0 | G59: 0 | H59: -192.3 | I59: 229.55 | J59: 0 | K59: 0 | L59: 9.9 | M59: 393.55 | N59: 381.55 | O59: 0 | P59: -67.45 | Q59: 0 | R59: 715 | S59: 0.65 | T59: 0 | U59: 0 | V59: 0 | W59: 0 | X59: 0.75 | Y59: 43 | Z59: 24 | AA59: 40.9 | AB59: -82.2 | AC59: 78.65 | AD59: 198.75 | AE59: 0 | AF59: 0 | AG59: 0 | AH59: 0 | AI59: 226 | AJ59: 213.15 | AK59: 0 | AL59: 0 | AM59: 0 | AN59: -34.45 | AO59: 1193 | AP59: 78.4 | AQ59: 0 | AR59: 23.25 | AS59: -7.95 | AT59: 44.7 | AU59: 29.6 | AV59: 698.5 | AW59: -431.85 | AX59: -958.3 | AY59: 159.75 | AZ59: 38.95 | BA59: -71.15 | BB59: 11.75 | BC59: 49.5 | BD59: -37.85 | BE59: 0 | BF59: 0 | BG59: 55.2 | BH59: 0 | BI59: 0 | BJ59: 74 | BK59: 0 | BL59: 0 | BM59: 0 | BN59: 186.65 | BO59: 309.65 | BP59: 187.8 | BQ59: 205.75 | BR59: 766.75 | BS59: -376.5 | BT59: -1.55 | BU59: 0 | BV59: 0 | BW59: 0 | BX59: -34.1 | BY59: 0 | BZ59: 0 | CA59: -9.5 | CB59: 851.7 | CC59: 583.1 | CD59: 163.4 | CE59: 115.6 | CF59: 59.4 | CG59: -153.6 | CH59: 0 | CI59: 0 | CJ59: 716.4 | CK59: 809.2 | CL59: -251.45 | CM59: 0 | CN59: 0 | CO59: 0 | CP59: 0 | CQ59: 0 | CR59: 0 | CS59: 0 | CT59: -31.5 | CU59: 1.15 | CV59: 33.6 | CW59: 0 | CX59: -154.5 | CY59: 52.85 | CZ59: -79.35 | DA59: 0 | DB59: 0.6 | DC59: -1.15 | DD59: -21.6 | DE59: 180.05 | DF59: 0 | DG59: 2.15 | DH59: 34.7 | DI59: 2.25 | DJ59: -22.85 | DK59: 2.3 | DL59: 13.55 | DM59: 0 | DN59: -5.75 | DO59: -15 | DP59: -51.35 | DQ59: 127.95 | DR59: -14.2 | DS59: 0.8 | DT59: 9.75 | DU59: 1.019 | DV59: 0.25 | DW59: 0 | DX59: -77.3 | DY59: 10.7 | DZ59: 64.2 | EA59: 61.7 | EB59: 34.55 | EC59: 0 | ED59: 0 | EE59: 14.75 | EF59: -203 | EG59: -218.6 | EH59: -20 | EI59: -16.05 | EJ59: 2.9 | EK59: 55.85 | EL59: -3.15 | EM59: 39.8 | EN59: 4.8 | EO59: 4.8 | EP59: 4.8 | EQ59: -94.4 | ER59: 33.8 | ES59: 13.95 | ET59: -10.6 | EU59: -4.7 | EV59: -174.6 | EW59: -52.1 | EX59: 85.1 | EY59: 29.8 | EZ59: 0 | FA59: 19.2 | FB59: 12 | FC59: 2.9 | FD59: 14.1 | FE59: 40.9 | FF59: 51.35 | FG59: 176.9 | FH59: 5.1 | FI59: 69.15 | FJ59: 24.3 | FK59: 52.725 | FL59: 95.92 | FM59: 0 | FN59: 9546.464 | FP59: 56.4859 | FQ59: 0 | FR59: 0 | FS59: 32.05 | FT59: 6.778475 | FU59: 6.96439 | FV59: -6.7 | FW59: 30.95 | FX59: 126.52877

Sheet DEMANDA_AREAS
B3: martes, 13 de Enero del 2026
B5: REPORTE DE LA DEMANDA POR ÁREAS Y SUBAREAS OPERATIVAS (MW)
B6: FECHA HORA | C6: DEMANDA | E6: AREA | H6: SUBAREAS
C7: INTERCAMBIOS INTERNACIONALES | D7: SEIN | E7: NORTE | F7: CENTRO | G7: SUR | H7: ELECTROANDES
B8: 00:30 | C8: 0 | D8: 6767.9895 | E8: 965.9086 | F8: 4097.8743 | G8: 1704.2066 | H8: 229.8608
B9: 01:00 | C9: 0 | D9: 6674.2479 | E9: 992.2041 | F9: 4001.6349 | G9: 1680.4089 | H9: 234.1129
B10: 01:30 | C10: 0 | D10: 6611.0442 | E10: 942.0641 | F10: 3967.1069 | G10: 1701.8732 | H10: 225.3991
B11: 02:00 | C11: 0 | D11: 6443.9809 | E11: 950.2584 | F11: 3777.8799 | G11: 1715.8426 | H11: 229.8777
B12: 02:30 | C12: 0 | D12: 6410.2824 | E12: 954.247 | F12: 3750.2323 | G12: 1705.8032 | H12: 233.4333
B13: 03:00 | C13: 0 | D13: 6382.2768 | E13: 903.003 | F13: 3751.0513 | G13: 1728.2225 | H13: 222.1208
B14: 03:30 | C14: 0 | D14: 6432.6648 | E14: 940.9834 | F14: 3750.2694 | G14: 1741.412 | H14: 232.0709
B15: 04:00 | C15: 0 | D15: 6462.6028 | E15: 931.6952 | F15: 3797.5147 | G15: 1733.3929 | H15: 228.9982
B16: 04:30 | C16: 0 | D16: 6608.986 | E16: 946.5133 | F16: 3899.8885 | G16: 1762.5842 | H16: 225.5534
B17: 05:00 | C17: 0 | D17: 6633.2469 | E17: 934.9385 | F17: 3914.1706 | G17: 1784.1378 | H17: 226.7221
B18: 05:30 | C18: 0 | D18: 6647.8789 | E18: 940.3223 | F18: 3917.2088 | G18: 1790.3478 | H18: 222.941
B19: 06:00 | C19: 0 | D19: 6581.3705 | E19: 975.5264 | F19: 3825.6692 | G19: 1780.175 | H19: 220.4654
... B59: ENERGÍA | C59: 0 | D59: 177480.65 | E59: 26038.747 | F59: 108254.65 | G59: 43187.256 | H59: 5618.6676
B61: LEYENDA:
D63: Potencia recibida del Ecuador
D64: Potencia entregada al Ecuador

Sheet DEMANDA_UL
B3: martes, 13 de Enero del 2026
B5: POTENCIA DE LOS GRANDES USUARIOS LIBRES (MW)
B6: FECHA HORA | C6: GRANDES USUARIOS LIBRES DEL ÁREA NORTE | X6: GRANDES USUARIOS LIBRES DEL ÁREA CENTRO | BP6: GRANDES USUARIOS LIBRES DEL ÁREA SUR
C7: ARCA CONTINENTAL LINDLEY S.A. | D7: AUSTRAL GROUP S.A.A | E7: CEMENTOS PACASMAYO | F7: CONSORCIO MINERO HORIZONTE S.R.L. | G7: CORPORACIÓN PESQUERA INCA S.A.C. | H7: CREDITEX: CIA IND.TEXTIL CREDISA | I7: HIPERMERCADOS TOTTUS S.A | J7: INDUSTRIA TEXTIL PIURA | K7: MINERA BOROO MISQUICHILCA S.A. | L7: MINERA GOLD FIELDS | M7: MINERA MARSA | N7: MINERA MISKY MAYO | O7: MINERA YANACOCHA | P7: OPEN PLAZA | Q7: PESQUERA DIAMANTE | R7: PETROPERU | S7: REAL PLAZA S.R.L. | T7: SIDER PERU | U7: SUPERMERCADOS PERUANOS S.A. | V7: TRUPAL S.A. | W7: UNIÓN DE CERVECERÍAS PERUANAS BACKUS Y JOHNSTON S. | X7: ACEROS AREQUIPA | Y7: ADMINISTRADORA JOCKEY PLAZA SHOPPING CENTER S.A. | Z7: ALICORP | AA7: ARCA CONTINENTAL LINDLEY S.A. | AB7: AUSTRAL GROUP S.A.A | AC7: COMPAÑIA MINERA CONDESTABLE | AD7: CORPORACIÓN PESQUERA INCA S.A.C. | AE7: CREDITEX: CIA IND.TEXTIL CREDISA | AF7: FUNDICION CHILCA S.A. | AG7: HIPERMERCADOS TOTTUS S.A | AH7: INMOBILIARIA KANPU S.A. | AI7: INMUEBLES PANAMERICANA S.A. | AJ7: KIMBERLY-CLARK PERU | AK7: LECHE GLORIA S.A. | AL7: MALL AVENTURA S.A. | AM7: MARCOBRE S.A.C. | AN7: MINERA ANTAMINA | AO7: MINERA ARES | AP7: MINERA BUENAVENTURA | AQ7: MINERA CHINALCO PERÚ S.A. | AR7: MINERA SHOUXIN PERU S.A. | AS7: MINERA VOLCAN | AT7: MINSUR | AU7: MOLYCOP-ADESUR | AV7: NEXA RESOURCES CAJAMARQUILLA S.A. | AW7: NEXA RESOURCES PERÚ S.A.A. | AX7: OPEN PLAZA | AY7: OPP FILM | AZ7: OWENS-ILLINOIS PERÚ S.A. | BA7: PAPELERA NACIONAL S.A. | BB7: PESQUERA DIAMANTE | BC7: QUIMPAC S.A. | BD7: REAL PLAZA S.R.L. | BE7: REFINERIA LA PAMPILLA S.A.A | BF7: SAGA FALABELLA | BG7: SAN MIGUEL INDUSTRIAS PET S.A. | BH7: SHOUGANG HIERRO PERU | BI7: SOFTYS PERU S.A.C. | BJ7: SUPERMERCADOS PERUANOS S.A. | BK7: TEJIDOS SAN JACINTO | BL7: TREN URBANO DE LIMA S.A. | BM7: TRUPAL S.A. | BN7: UNACEM PERU S.A. | BO7: UNIÓN DE CERVECERÍAS PERUANAS BACKUS Y JOHNSTON S. | BP7: ANGLO AMERICAN QUELLAVECO S.A. | BQ7: ARCA CONTINENTAL LINDLEY S.A. | BR7: CAL & CEMENTO SUR S.A. | BS7: COMPAÑIA MINERA ANTAPACCAY S.A. | BT7: COMPAÑÍA MINERA CHUNGAR SAC | BU7: COMPAÑIA MINERA SAN IGNACIO DE MOROCOCHA S.A.A. | BV7: EL BROCAL .S.A. | BW7: EMPRESA ADMINISTRADORA CERRO S.A.C. | BX7: EMPRESA MINERA LOS QUENUALES S.A.C. | BY7: HIPERMERCADOS TOTTUS S.A | BZ7: HUDBAY PERU S.A.C. | CA7: INDUSTRIA CACHIMAYO | CB7: MALL AVENTURA S.A. | CC7: MINERA ARES | CD7: MINERA BUENAVENTURA | CE7: MINERA CERRO VERDE | CF7: MINERA CORONA | CG7: MINERA LAS BAMBAS S.A. | CH7: MINERA VOLCAN | CI7: MINSUR | CJ7: MOLYCOP-ADESUR | CK7: NEXA RESOURCES PERÚ S.A.A. | CL7: OXIDOS DE PASCO S.A.C. | CM7: PESQUERA DIAMANTE | CN7: REAL PLAZA S.R.L. | CO7: SOBREANDES S.A.C. | CP7: SOUTHERN PERU CC | CQ7: SUPERMERCADOS PERUANOS S.A. | CR7: UNACEM PERU S.A. | CS7: UNIÓN DE CERVECERÍAS PERUANAS BACKUS Y JOHNSTON S. | CT7: YURA
B8: 00:30 | E8: 29.4665 | F8: 11.373 | L8: 27.0185 | M8: 14.5508 | N8: 13.22 | O8: 31.47 | R8: 43.614 | T8: 39.4199 | V8: 0.4 | X8: 115.37616 | Z8: 8.19144 | AC8: 5.79 | AF8: 3.3 | AK8: 0 | AM8: 48.67364 | AN8: 122.915 | AO8: 26.9539 | AP8: 0.81 | AQ8: 165.76353 | AS8: 36.2328 | AT8: 32.30994 | AV8: 196.70489 | AW8: 10.8573 | AY8: 1.64911 | BA8: 1.4 | BC8: 70.12748 | BE8: 18 | BI8: 15.35029 | BN8: 40.764 | BO8: 2.26 | BP8: 145.13066 | BR8: 5.0459 | BS8: 130.19675 | BT8: 11.0301 | BV8: 40.3858 | BW8: 3.85819 | BZ8: 88.7645 | CA8: 10.94712 | CC8: 0.59 | CD8: 23.4501 | CE8: 348.48379 | CG8: 159.4817 | CH8: 17.11822 | CL8: 4.87999 | CO8: 16.54022 | CP8: 266.19 | CR8: 35.983 | CT8: 20.463
B9: 01:00 | E9: 32.9112 | F9: 11.894 | L9: 26.9656 | M9: 14.0164 | N9: 13.59 | O9: 31.166 | R9: 43.331 | T9: 51.3273 | V9: 0.4 | X9: 95.59313 | Z9: 8.86034 | AC9: 5.7 | AF9: 2.7 | AK9: 0 | AM9: 48.84561 | AN9: 121.291 | AO9: 26.8467 | AP9: 0.7 | AQ9: 167.10026 | AS9: 36.54555 | AT9: 34.94825 | AV9: 196.6767 | AW9: 10.6627 | AY9: 1.64425 | BA9: 1.4 | BC9: 70.05621 | BE9: 18 | BI9: 15.44497 | BN9: 41.828 | BO9: 2.17 | BP9: 145.39013 | BR9: 5.0999 | BS9: 131.56421 | BT9: 11.19712 | BV9: 40.4528 | BW9: 3.96348 | BZ9: 89.6703 | CA9: 13.97824 | CC9: 0.64 | CD9: 22.75095 | CE9: 337.87019 | CG9: 160.8953 | CH9: 17.0416 | CL9: 4.81908 | CO9: 16.70757 | CP9: 266.87 | CR9: 36.378 | CT9: 23.576
B10: 01:30 | E10: 32.8702 | F10: 12.516 | L10: 26.5175 | M10: 14.1832 | N10: 13.55 | O10: 30.936 | R10: 43.356 | T10: 52.7396 | V10: 0.4 | X10: 132.9125 | Z10: 8.45615 | AC10: 5.75 | AF10: 5 | AK10: 0 | AM10: 48.94948 | AN10: 122.306 | AO10: 27.3524 | AP10: 0.64 | AQ10: 167.79419 | AS10: 35.82619 | AT10: 35.355 | AV10: 196.37045 | AW10: 10.7659 | AY10: 1.59863 | BA10: 1.4 | BC10: 70.1736 | BE10: 18 | BI10: 17.11292 | BN10: 41.602 | BO10: 2.17 | BP10: 143.36253 | BR10: 5.2186 | BS10: 132.56736 | BT10: 9.46381 | BV10: 41.335 | BW10: 4.0073 | BZ10: 88.9046 | CA10: 15.06596 | CC10: 0.59 | CD10: 23.87393 | CE10: 347.26375 | CG10: 161.124 | CH10: 17.11869 | CL10: 4.85517 | CO10: 16.44821 | CP10: 267.19 | CR10: 36.209 | CT10: 23.81
B11: 02:00 | E11: 32.9064 | F11: 11.823 | L11: 27.0602 | M11: 14.0838 | N11: 13.62 | O11: 31.176 | R11: 43.33 | T11: 41.704 | V11: 0.4 | X11: 77.93113 | Z11: 8.25143 | AC11: 5.41 | AF11: 4.1 | AK11: 0 | AM11: 50.17682 | AN11: 122.017 | AO11: 27.5588 | AP11: 0.44 | AQ11: 167.67969 | AS11: 36.03205 | AT11: 34.9767 | AV11: 196.60854 | AW11: 10.6679 | AY11: 1.60174 | BA11: 1.3 | BC11: 70.34794 | BE11: 18 | BI11: 17.58795 | BN11: 39.108 | BO11: 2.17 | BP11: 143.95586 | BR11: 5.0953 | BS11: 132.77835 | BT11: 9.11172 | BV11: 40.7824 | BW11: 3.7307 | BZ11: 87.0757 | CA11: 15.07856 | CC11: 0.62 | CD11: 24.51248 | CE11: 363.75281 | CG11: 154.5446 | CH11: 16.73925 | CL11: 4.95479 | CO11: 16.4828 | CP11: 262.59 | CR11: 36.081 | CT11: 23.638
B12: 02:30 | E12: 35.041 | F12: 12.002 | L12: 27.0143 | M12: 13.8142 | N12: 13.62 | O12: 31.43 | R12: 43.338 | T12: 35.5012 | V12: 0.4 | X12: 119.43727 | Z12: 8.10183 | AC12: 5.38 | AF12: 4 | AK12: 0 | AM12: 50.34805 | AN12: 120.216 | AO12: 27.3652 | AP12: 0.41 | AQ12: 163.51189 | AS12: 36.60941 | AT12: 34.71954 | AV12: 196.65426 | AW12: 11.1191 | AY12: 1.69634 | BA12: 1.4 | BC12: 70.38771 | BE12: 18 | BI12: 17.6797 | BN12: 38.664 | BO12: 2.09 | BP12: 145.2755 | BR12: 5.0357 | BS12: 133.23424 | BT12: 10.32155 | BV12: 37.118 | BW12: 3.87202 | BZ12: 86.4887 | CA12: 15.11936 | CC12: 0.59 | CD12: 25.61155 | CE12: 369.27857 | CG12: 157.0959 | CH12: 16.76615 | CL12: 4.83009 | CO12: 15.63026 | CP12: 257.55 | CR12: 36.041 | CT12: 23.47
B13: 03:00 | E13: 34.7096 | F13: 10.98 | L13: 26.3787 | M13: 13.7193 | N13: 13.3 | O13: 30.988 | R13: 43.313 | T13: 41.2209 | V13: 0.4 | X13: 46.88475 | Z13: 7.99259 | AC13: 5.23 | AF13: 2 | AK13: 0 | AM13: 50.24978 | AN13: 121.286 | AO13: 27.0712 | AP13: 0.67 | AQ13: 164.41014 | AS13: 36.57697 | AT13: 35.14994 | AV13: 196.2792 | AW13: 10.8987 | AY13: 1.71196 | BA13: 1.6 | BC13: 70.2793 | BE13: 18 | BI13: 17.36354 | BN13: 41.44 | BO13: 2.16 | BP13: 142.71243 | BR13: 5.0354 | BS13: 131.8202 | BT13: 10.91919 | BV13: 38.1531 | BW13: 3.96593 | BZ13: 88.7088 | CA13: 17.32029 | CC13: 0.63 | CD13: 25.1872 | CE13: 373.49229 | CG13: 160.2225 | CH13: 16.93467 | CL13: 4.72904 | CO13: 16.3188 | CP13: 264.83 | CR13: 36.071 | CT13: 23.406
B14: 03:30 | E14: 33.8719 | F14: 11.765 | L14: 26.8293 | M14: 13.4094 | N14: 14 | O14: 30.708 | R14: 43.591 | T14: 45.7329 | V14: 0.4 | X14: 76.52967 | Z14: 8.03616 | AC14: 4.99 | AF14: 3.1 | AK14: 0 | AM14: 48.75931 | AN14: 120.904 | AO14: 26.492 | AP14: 0.48 | AQ14: 166.58527 | AS14: 36.60999 | AT14: 33.6777 | AV14: 196.15488 | AW14: 11.0097 | AY14: 1.69229 | BA14: 2.3 | BC14: 70.34159 | BE14: 18 | BI14: 17.44178 | BN14: 42.465 | BO14: 2.17 | BP14: 146.03376 | BR14: 5.0888 | BS14: 132.01829 | BT14: 11.21295 | BV14: 37.9389 | BW14: 4.02736 | BZ14: 90.5282 | CA14: 18.30811 | CC14: 0.62 | CD14: 25.10391 | CE14: 385.96643 | CG14: 156.243 | CH14: 17.46744 | CL14: 4.82083 | CO14: 16.69823 | CP14: 258.18 | CR14: 35.63 | CT14: 21.212
B15: 04:00 | E15: 34.0896 | F15: 12.267 | L15: 26.4989 | M15: 13.6803 | N15: 13.77 | O15: 30.944 | R15: 43.395 | T15: 43.9123 | V15: 0.4 | X15: 119.97541 | Z15: 8.18762 | AC15: 4.85 | AF15: 5.1 | AK15: 0 | AM15: 49.90795 | AN15: 121.264 | AO15: 26.4858 | AP15: 0.18 | AQ15: 165.18722 | AS15: 35.87431 | AT15: 33.38484 | AV15: 196.20881 | AW15: 11.04 | AY15: 1.74716 | BA15: 2.4 | BC15: 69.97391 | BE15: 18 | BI15: 17.5157 | BN15: 42.997 | BO15: 2.15 | BP15: 148.41006 | BR15: 5.0573 | BS15: 132.37657 | BT15: 11.04505 | BV15: 38.5239 | BW15: 3.88656 | BZ15: 90.8298 | CA15: 18.22768 | CC15: 0.62 | CD15: 23.95133 | CE15: 407.65074 | CG15: 152.513 | CH15: 16.56168 | CL15: 4.73827 | CO15: 16.88738 | CP15: 260.59 | CR15: 35.228 | CT15: 23.46
B16: 04:30 | E16: 34.6924 | F16: 12.276 | L16: 27.0914 | M16: 14.8406 | N16: 13.9 | O16: 31.708 | R16: 43.135 | T16: 48.5129 | V16: 0.4 | X16: 136.39377 | Z16: 8.38526 | AC16: 4.53 | AF16: 4.8 | AK16: 0 | AM16: 49.60897 | AN16: 123.069 | AO16: 25.4688 | AP16: 1.65 | AQ16: 165.35231 | AS16: 35.80533 | AT16: 33.5424 | AV16: 195.99081 | AW16: 10.6946 | AY16: 1.71926 | BA16: 2.38 | BC16: 69.95236 | BE16: 18 | BI16: 17.46627 | BN16: 44.923 | BO16: 1.72 | BP16: 145.84503 | BR16: 4.9526 | BS16: 131.29058 | BT16: 10.18423 | BV16: 37.0234 | BW16: 3.90366 | BZ16: 89.5406 | CA16: 18.12773 | CC16: 0.6 | CD16: 24.01162 | CE16: 409.03069 | CG16: 159.7765 | CH16: 16.93168 | CL16: 4.80152 | CO16: 17.08182 | CP16: 265.85 | CR16: 34.982 | CT16: 23.99
B17: 05:00 | E17: 34.805 | F17: 10.87 | L17: 26.7167 | M17: 15.3118 | N17: 13.75 | O17: 31.534 | R17: 43.39 | T17: 43.398 | V17: 0.4 | X17: 123.31737 | Z17: 8.47925 | AC17: 4.74 | AF17: 4.6 | AK17: 0 | AM17: 49.61527 | AN17: 124.263 | AO17: 25.9223 | AP17: 2.1 | AQ17: 167.0867 | AS17: 34.92162 | AT17: 32.49747 | AV17: 196.09274 | AW17: 10.4842 | AY17: 1.75617 | BA17: 1.5 | BC17: 69.32144 | BE17: 18 | BI17: 17.81437 | BN17: 45.538 | BO17: 2.4 | BP17: 146.43476 | BR17: 4.9836 | BS17: 130.76313 | BT17: 10.18441 | BV17: 34.8187 | BW17: 4.37541 | BZ17: 88.2804 | CA17: 18.16752 | CC17: 0.59 | CD17: 24.32926 | CE17: 418.57156 | CG17: 154.609 | CH17: 17.42282 | CL17: 4.94245 | CO17: 16.33528 | CP17: 264.7 | CR17: 36.005 | CT17: 24.148
B18: 05:30 | E18: 34.8563 | F18: 9.912 | L18: 26.9577 | M18: 15.3839 | N18: 13.72 | O18: 32.508 | R18: 43.43 | T18: 28.6992 | V18: 0.4 | X18: 75.78365 | Z18: 8.76112 | AC18: 4.84 | AF18: 2.3 | AK18: 0 | AM18: 48.69228 | AN18: 122.066 | AO18: 24.2567 | AP18: 1.93 | AQ18: 168.60838 | AS18: 34.13237 | AT18: 33.51442 | AV18: 196.04628 | AW18: 9.7907 | AY18: 1.80327 | BA18: 1.4 | BC18: 69.28837 | BE18: 18 | BI18: 17.68209 | BN18: 46.096 | BO18: 2.37 | BP18: 148.9559 | BR18: 5.1198 | BS18: 131.30294 | BT18: 10.46677 | BV18: 34.7839 | BW18: 3.85894 | BZ18: 88.8743 | CA18: 21.31219 | CC18: 0.56 | CD18: 24.00193 | CE18: 420.20753 | CG18: 161.0945 | CH18: 17.56133 | CL18: 4.88333 | CO18: 15.27609 | CP18: 264.23 | CR18: 35.95 | CT18: 23.93
B19: 06:00 | E19: 34.6843 | F19: 9.084 | L19: 26.9691 | M19: 14.7824 | N19: 13.51 | O19: 32.604 | R19: 43.591 | T19: 46.8985 | V19: 0.4 | X19: 132.90906 | Z19: 8.22526 | AC19: 5.23 | AF19: 3.1 | AK19: 0 | AM19: 50.26652 | AN19: 122.582 | AO19: 21.504 | AP19: 1.54 | AQ19: 168.88454 | AS19: 33.32264 | AT19: 33.49663 | AV19: 196.35373 | AW19: 9.2036 | AY19: 1.80516 | BA19: 1.4 | BC19: 68.65416 | BE19: 18 | BI19: 17.52743 | BN19: 48.221 | BO19: 2.23 | BP19: 149.77464 | BR19: 5.1362 | BS19: 130.77247 | BT19: 10.34 | BV19: 36.6344 | BW19: 3.65085 | BZ19: 88.3333 | CA19: 21.29121 | CC19: 0.54 | CD19: 23.07923 | CE19: 435.4095 | CG19: 154.6476 | CH19: 18.05467 | CL19: 4.86857 | CO19: 14.19818 | CP19: 263.2 | CR19: 35.822 | CT19: 23.066
... B55: 00:00 | E55: 27.3621 | F55: 11.926 | L55: 25.8382 | M55: 13.9203 | N55: 13.32 | O55: 33 | R55: 43.057 | T55: 39.5339 | V55: 0.5 | X55: 108.47079 | Z55: 9.82951 | AC55: 16.12 | AF55: 4.9 | AK55: 0 | AM55: 48.6129 | AN55: 118.071 | AO55: 20.5394 | AP55: 0.83 | AQ55: 169.60912 | AS55: 35.50742 | AT55: 30.7495 | AV55: 191.90952 | AW55: 12.0193 | AY55: 0.25972 | BA55: 2.1 | BC55: 69.64892 | BE55: 17.92 | BI55: 17.07209 | BN55: 48.355 | BO55: 2.05 | BP55: 147.56129 | BR55: 4.6895 | BS55: 128.87427 | BT55: 10.35894 | BV55: 39.4521 | BW55: 3.83695 | BZ55: 90.1831 | CA55: 24.49923 | CC55: 0.75 | CD55: 27.06258 | CE55: 396.97771 | CG55: 155.3946 | CH55: 17.80087 | CL55: 4.78726 | CO55: 17.06009 | CP55: 277.43 | CR55: 32.371 | CT55: 22.907
B56: MWh | C56: 0 | D56: 0 | E56: 727.6475 | F56: 269.5535 | G56: 0 | H56: 0 | I56: 0 | J56: 0 | K56: 0 | L56: 659.66975 | M56: 315.29445 | N56: 321.43 | O56: 742.283 | P56: 0 | Q56: 0 | R56: 1027.7205 | S56: 0 | T56: 753.2283 | U56: 0 | V56: 12.1 | W56: 0 | X56: 2047.6087 | Y56: 0 | Z56: 214.11494 | AA56: 0 | AB56: 0 | AC56: 217.47 | AD56: 0 | AE56: 0 | AF56: 77.2 | AG56: 0 | AH56: 0 | AI56: 0 | AJ56: 0 | AK56: 0 | AL56: 0 | AM56: 1155.698 | AN56: 2889.0535 | AO56: 487.57555 | AP56: 18.01 | AQ56: 3978.8983 | AR56: 0 | AS56: 819.72595 | AT56: 793.86463 | AU56: 0 | AV56: 4208.9278 | AW56: 236.3936 | AX56: 0 | AY56: 16.159215 | AZ56: 0 | BA56: 48.94 | BB56: 0 | BC56: 1539.9086 | BD56: 0 | BE56: 438.44 | BF56: 0 | BG56: 0 | BH56: 0 | BI56: 419.13945 | BJ56: 0 | BK56: 0 | BL56: 0 | BM56: 0 | BN56: 911.0895 | BO56: 53.92 | BP56: 3474.8605 | BQ56: 0 | BR56: 120.33715 | BS56: 3136.2077 | BT56: 228.5996 | BU56: 0 | BV56: 895.2895 | BW56: 93.385435 | BX56: 0 | BY56: 0 | BZ56: 2146.8916 | CA56: 450.81297 | CB56: 0 | CC56: 16.285 | CD56: 547.93046 | CE56: 9575.9471 | CF56: 0 | CG56: 3101.9127 | CH56: 401.12782 | CI56: 0 | CJ56: 0 | CK56: 0 | CL56: 112.75441 | CM56: 0 | CN56: 0 | CO56: 374.62951 | CP56: 6317.555 | CQ56: 0 | CR56: 785.674 | CS56: 0 | CT56: 452.702
B59: Nota :
B60: Información proporcionada por la empresas
C62: DATOS ESTIMADOS
C64: SIN DATOS

Sheet TIPO_RECURSO
B3: martes, 13 de Enero del 2026
B5: REPORTE POTENCIA GENERADA POR TIPO DE RECURSO
B6: HORA | C6: H. PASADA | D6: H. REGULACION | E6: GAS DE CAMISEA | F6: GAS DE MALACAS | G6: BAGAZO | H6: DIÉSEL | I6: RESIDUAL | J6: NAFTA+GAS DE REFINERIA | K6: FLEXIGAS+GAS DE REFINERIA | L6: BIOGÁS | M6: SOLAR | N6: EÓLICA | O6: TOTAL | T6: EMPRESA | U6: CENTRAL | V6: HIDROELECTRICA DE PASADA | W6: HIDROELECTRICA DE REGULACION
B7: 00:30 | C7: 1158.5495 | D7: 3051.8 | E7: 2029.4 | F7: 46.2 | G7: 85.24 | J7: =+DESPACHO_EJECUTADO!FG11+DESPACHO_EJECUTADO!FH11 -> 58.9 | L7: 6.8 | M7: 0 | N7: 331.1 | O7: =+SUM(C7:N7) -> 6767.9895 | T7: ANDEAN POWER S.A.C. | U7: C.H.CARHUAC | V7: 304
B8: 01:00 | C8: 1157.1879 | D8: 2998.2 | E8: 2041.8 | F8: 45.7 | G8: 83.76 | J8: =+DESPACHO_EJECUTADO!FG12+DESPACHO_EJECUTADO!FH12 -> 59 | L8: 6.8 | M8: 0 | N8: 281.8 | O8: =+SUM(C8:N8) -> 6674.2479 | T8: ASOCIACIÓN SANTA LUCIA DE CHACAS | U8: C.H. HUALLIN | V8: 72.22
B9: 01:30 | C9: 1144.9042 | D9: 3004.4 | E9: 2035 | F9: 46.2 | G9: 84.14 | J9: =+DESPACHO_EJECUTADO!FG13+DESPACHO_EJECUTADO!FH13 -> 59 | L9: 6.8 | M9: 0 | N9: 230.6 | O9: =+SUM(C9:N9) -> 6611.0442 | T9: ATRIA ENERGIA S.A.C. | U9: C.H. PURMACANA | V9: 5.4
B10: 02:00 | C10: 1151.3609 | D10: 2941.2 | E10: 1949.4 | F10: 46 | G10: 84.92 | J10: =+DESPACHO_EJECUTADO!FG14+DESPACHO_EJECUTADO!FH14 -> 59.6 | L10: 6.8 | M10: 0 | N10: 204.7 | O10: =+SUM(C10:N10) -> 6443.9809 | T10: CELARIS ENERGY S.A. | U10: C.H. MANTA I | V10: 480.05
B11: 02:30 | C11: 1150.2424 | D11: 2963.9 | E11: 1906.9 | F11: 45.7 | G11: 78.94 | J11: =+DESPACHO_EJECUTADO!FG15+DESPACHO_EJECUTADO!FH15 -> 59.4 | L11: 6.8 | M11: 0 | N11: 198.4 | O11: =+SUM(C11:N11) -> 6410.2824 | T11: CELEPSA | U11: C.H. EL PLATANAL | W11: 5314
B12: 03:00 | C12: 1154.0568 | D12: 2920.3 | E12: 1896.8 | F12: 45.9 | G12: 85.52 | J12: =+DESPACHO_EJECUTADO!FG16+DESPACHO_EJECUTADO!FH16 -> 59.3 | L12: 6.8 | M12: 0 | N12: 213.6 | O12: =+SUM(C12:N12) -> 6382.2768 | T12: CELEPSA RENOVABLES S.R.L. | U12: C.H. MARAÑON | V12: 361.13256
B13: 03:30 | C13: 1168.5248 | D13: 2965.9 | E13: 1907.5 | F13: 45.7 | G13: 83.84 | J13: =+DESPACHO_EJECUTADO!FG17+DESPACHO_EJECUTADO!FH17 -> 59.2 | L13: 6.8 | M13: 0 | N13: 195.2 | O13: =+SUM(C13:N13) -> 6432.6648 | T13: CHINANGO S.A.C. | U13: C.H. YANANGO | V13: 274.55
B14: 04:00 | C14: 1145.6728 | D14: 2949.3 | E14: 2006.4 | F14: 45.9 | G14: 82.13 | J14: =+DESPACHO_EJECUTADO!FG18+DESPACHO_EJECUTADO!FH18 -> 59.2 | L14: 6.9 | M14: 0 | N14: 167.1 | O14: =+SUM(C14:N14) -> 6462.6028 | T14: EGASA | U14: C.H. CHARCANI III | V14: 168.55
B15: 04:30 | C15: 1158.186 | D15: 3082 | E15: 2014.2 | F15: 45.3 | G15: 84 | J15: =+DESPACHO_EJECUTADO!FG19+DESPACHO_EJECUTADO!FH19 -> 58.9 | L15: 6.9 | M15: 0 | N15: 159.5 | O15: =+SUM(C15:N15) -> 6608.986 | U15: C.H. CHARCANI IV | W15: 324.8
B16: 05:00 | C16: 1158.0669 | D16: 3131.5 | E16: 2017.1 | F16: 45.6 | G16: 83.98 | J16: =+DESPACHO_EJECUTADO!FG20+DESPACHO_EJECUTADO!FH20 -> 57.9 | L16: 6.9 | M16: 0 | N16: 132.2 | O16: =+SUM(C16:N16) -> 6633.2469 | U16: C.H. CHARCANI V | W16: 2008.55
B17: 05:30 | C17: 1152.7889 | D17: 3140.9 | E17: 2016.9 | F17: 45.6 | G17: 83.79 | J17: =+DESPACHO_EJECUTADO!FG21+DESPACHO_EJECUTADO!FH21 -> 58.4 | L17: 6.9 | M17: 4.8 | N17: 137.8 | O17: =+SUM(C17:N17) -> 6647.8789 | T17: EGEJUNIN | U17: C.H. HUASAHUASI I | V17: 397.313
B18: 06:00 | C18: 1152.2106 | D18: 3116.2 | E18: 1906.5 | F18: 45.5 | G18: 79.86 | J18: =+DESPACHO_EJECUTADO!FG22+DESPACHO_EJECUTADO!FH22 -> 59.4 | L18: 6.9 | M18: 70.4 | N18: 144.4 | O18: =+SUM(C18:N18) -> 6581.3705 | U18: C.H. RUNATULLO II | V18: 483.145
B19: 06:30 | C19: 1154.2499 | D19: 3072 | E19: 1862.2 | F19: 45.7 | G19: 84.26 | J19: =+DESPACHO_EJECUTADO!FG23+DESPACHO_EJECUTADO!FH23 -> 59.7 | L19: 6.9 | M19: 301.5 | N19: 131.3 | O19: =+SUM(C19:N19) -> 6717.8099 | U19: C.H. RUNATULLO III | V19: 485.2
B20: 07:00 | C20: 1130.5533 | D20: 3007.9 | E20: 1974.6 | F20: 45.5 | G20: 83.05 | J20: =+DESPACHO_EJECUTADO!FG24+DESPACHO_EJECUTADO!FH24 -> 59.8 | L20: 6.9 | M20: 330.1 | N20: 139.9 | O20: =+SUM(C20:N20) -> 6778.3033 | U20: C.H. SANTA CRUZ I | V20: 307.279
B21: 07:30 | C21: 1117.0911 | D21: 2977.6 | E21: 1880.5 | F21: 45.7 | G21: 84.9 | J21: =+DESPACHO_EJECUTADO!FG25+DESPACHO_EJECUTADO!FH25 -> 59.8 | L21: 6.9 | M21: 593.2 | N21: 137.4 | O21: =+SUM(C21:N21) -> 6903.0911 | T21: EGEMSA | U21: C.H. MACHUPICCHU | V21: 3990.55
B22: 08:00 | C22: 1091.9538 | D22: 3153 | E22: 2016.3 | F22: 45.5 | G22: 83.8 | J22: =+DESPACHO_EJECUTADO!FG26+DESPACHO_EJECUTADO!FH26 -> 60 | L22: 6.9 | M22: 633.7 | N22: 109 | O22: =+SUM(C22:N22) -> 7200.1538 | T22: EGESUR | U22: C.H. ARICOTA I | W22: 189.25
B23: 08:30 | C23: 1111.6347 | D23: 3130.9 | E23: 2025 | F23: 45.4 | G23: 81.02 | J23: =+DESPACHO_EJECUTADO!FG27+DESPACHO_EJECUTADO!FH27 -> 59.2 | L23: 5.5 | M23: 795.5 | N23: 134.6 | O23: =+SUM(C23:N23) -> 7388.7547 | U23: C.H. ARICOTA II | W23: 132.9
B24: 09:00 | C24: 1109.3663 | D24: 3123.1 | E24: 2178.4 | F24: 45.4 | G24: 84.64 | J24: =+DESPACHO_EJECUTADO!FG28+DESPACHO_EJECUTADO!FH28 -> 59.1 | L24: 5.5 | M24: 849.4 | N24: 163.1 | O24: =+SUM(C24:N24) -> 7618.0063 | T24: ELECTRICA YANAPAMPA SAC | U24: C.H. YANAPAMPA | V24: 72.85
B25: 09:30 | C25: 1092.3548 | D25: 2972.4 | E25: 2268.9 | F25: 45.2 | G25: 82.43 | J25: =+DESPACHO_EJECUTADO!FG29+DESPACHO_EJECUTADO!FH29 -> 59.7 | L25: 5.5 | M25: 943.7 | N25: 139.6 | O25: =+SUM(C25:N25) -> 7609.7848 | T25: ELECTROPERU | U25: C.H. MANTARO | W25: 15053.75
B26: 10:00 | C26: 1094.4944 | D26: 3138.8 | E26: 2359.3 | F26: 44.8 | G26: 75.41 | J26: =+DESPACHO_EJECUTADO!FG30+DESPACHO_EJECUTADO!FH30 -> 59.5 | L26: 5.4 | M26: 950.2 | N26: 118.6 | O26: =+SUM(C26:N26) -> 7846.5044 | U26: C.H. RESTITUCION | V26: 5155.95
B27: 10:30 | C27: 1124.1041 | D27: 3245.5 | E27: 2331.4 | F27: 44.5 | G27: 75.99 | J27: =+DESPACHO_EJECUTADO!FG31+DESPACHO_EJECUTADO!FH31 -> 60.1 | L27: 5.4 | M27: 821.6 | N27: 129.6 | O27: =+SUM(C27:N27) -> 7838.1941 | T27: EMPRESA DE GENERACION ELECTRICA CANCHAYLLO SAC | U27: C.H. CANCHAYLLO | V27: 122.95
B28: 11:00 | C28: 1117.7005 | D28: 3286.6 | E28: 2342.2 | F28: 44.7 | G28: 73.2 | J28: =+DESPACHO_EJECUTADO!FG32+DESPACHO_EJECUTADO!FH32 -> 60.3 | L28: 5.4 | M28: 943.4 | N28: 169.6 | O28: =+SUM(C28:N28) -> 8043.1005 | T28: EMPRESA DE GENERACION ELECTRICA RIO BAÑOS S.A.C. | U28: C.H. RUCUY | V28: 479.7
B29: 11:30 | C29: 1113.1583 | D29: 3312.8 | E29: 2472.3 | F29: 44.9 | G29: 78.26 | J29: =+DESPACHO_EJECUTADO!FG33+DESPACHO_EJECUTADO!FH33 -> 60.1 | L29: 5.4 | M29: 838.4 | N29: 173.9 | O29: =+SUM(C29:N29) -> 8099.2183 | T29: EMPRESA DE GENERACION ELECTRICA SANTA ANA S.A.C. | U29: C.H. RENOVANDES H1 | V29: 232.9
B30: 12:00 | C30: 1129.4736 | D30: 3272.8 | E30: 2480.6 | F30: 44.6 | G30: 82.14 | J30: =+DESPACHO_EJECUTADO!FG34+DESPACHO_EJECUTADO!FH34 -> 60.5 | L30: 5.4 | M30: 836.9 | N30: 179.7 | O30: =+SUM(C30:N30) -> 8092.1136 | T30: EMPRESA DE GENERACION HUALLAGA | U30: C.H. CHAGLLA | W30: 10988
B31: 12:30 | C31: 1118.4688 | D31: 3053.9 | E31: 2540.4 | F31: 44.8 | G31: 80.75 | J31: =+DESPACHO_EJECUTADO!FG35+DESPACHO_EJECUTADO!FH35 -> 58.9 | L31: 5.4 | M31: 896.2 | N31: 173.2 | O31: =+SUM(C31:N31) -> 7972.0187 | U31: P.C.H. CHAGLLA | V31: 156
B32: 13:00 | C32: 1144.6588 | D32: 3046.6 | E32: 2629.4 | F32: 44.1 | G32: 77.11 | J32: =+DESPACHO_EJECUTADO!FG36+DESPACHO_EJECUTADO!FH36 -> 59 | L32: 5.4 | M32: 807.1 | N32: 156.4 | O32: =+SUM(C32:N32) -> 7969.7688 | T32: EMPRESA DE GENERACION HUANZA | U32: C.H. HUANZA | W32: 855.4
B33: 13:30 | C33: 1147.3022 | D33: 3012.7 | E33: 2562.8 | F33: 44.2 | G33: 72.66 | J33: =+DESPACHO_EJECUTADO!FG37+DESPACHO_EJECUTADO!FH37 -> 58.9 | L33: 5.4 | M33: 779.6 | N33: 180.4 | O33: =+SUM(C33:N33) -> 7863.9622 | T33: EMPRESA ELECTRICA AGUA AZUL | U33: C.H. POTRERO | V33: 479.7
B34: 14:00 | C34: 1133.4001 | D34: 2993 | E34: 2649.2 | F34: 44.5 | G34: 73 | J34: =+DESPACHO_EJECUTADO!FG38+DESPACHO_EJECUTADO!FH38 -> 59.1 | L34: 5.4 | M34: 702.1 | N34: 261 | O34: =+SUM(C34:N34) -> 7920.7001 | T34: EMPRESA ELECTRICA RIO DOBLE | U34: C.H. LAS PIZARRAS | V34: 434.55
B35: 14:30 | C35: 1161.27 | D35: 3152.5 | E35: 2612.6 | F35: 44.7 | G35: 80.26 | J35: =+DESPACHO_EJECUTADO!FG39+DESPACHO_EJECUTADO!FH39 -> 58.9 | L35: 5.4 | M35: 537.9 | N35: 325.8 | O35: =+SUM(C35:N35) -> 7979.33 | T35: ENGIE ENERGIA PERU S.A.A. | U35: C.H. QUITARACSA | W35: 433.3
B36: 15:00 | C36: 1161.7547 | D36: 3339.1 | E36: 2557 | F36: 44.9 | G36: 83.14 | J36: =+DESPACHO_EJECUTADO!FG40+DESPACHO_EJECUTADO!FH40 -> 58.3 | L36: 5.4 | M36: 490.2 | N36: 380 | O36: =+SUM(C36:N36) -> 8119.7947 | U36: C.H. YUNCAN | W36: 2595.1
B37: 15:30 | C37: 1168.1101 | D37: 3365 | E37: 2505 | F37: 44.8 | G37: 82.58 | J37: =+DESPACHO_EJECUTADO!FG41+DESPACHO_EJECUTADO!FH41 -> 58.5 | L37: 5.4 | M37: 370.1 | N37: 388.6 | O37: =+SUM(C37:N37) -> 7988.0901 | T37: GENERACIÓN ANDINA S.A.C. | U37: C.H. 8 DE AGOSTO | V37: 446.85
B38: 16:00 | C38: 1179.7386 | D38: 3333.2 | E38: 2630.5 | F38: 44.8 | G38: 83.06 | J38: =+DESPACHO_EJECUTADO!FG42+DESPACHO_EJECUTADO!FH42 -> 58.3 | L38: 5.4 | M38: 279 | N38: 391.4 | O38: =+SUM(C38:N38) -> 8005.3986 | U38: C.H. EL CARMEN | V38: 192.8
B39: 16:30 | C39: 1166.1196 | D39: 3347.9 | E39: 2693.3 | F39: 44.9 | G39: 83.31 | J39: =+DESPACHO_EJECUTADO!FG43+DESPACHO_EJECUTADO!FH43 -> 58.2 | L39: 5.4 | M39: 159.5 | N39: 356.9 | O39: =+SUM(C39:N39) -> 7915.5296 | T39: GENERADORA DE ENERGÍA DEL PERÚ | U39: C.H. ÁNGEL I | V39: 489.6
B40: 17:00 | C40: 1167.9507 | D40: 3339 | E40: 2668.1 | F40: 45.3 | G40: 81.74 | J40: =+DESPACHO_EJECUTADO!FG44+DESPACHO_EJECUTADO!FH44 -> 58.4 | L40: 5.4 | M40: 81.8 | N40: 393.8 | O40: =+SUM(C40:N40) -> 7841.4907 | U40: C.H. ÁNGEL II | V40: 489.6
B41: 17:30 | C41: 1180.1515 | D41: 3227.1 | E41: 2721.1 | F41: 45.2 | G41: 81.73 | J41: =+DESPACHO_EJECUTADO!FG45+DESPACHO_EJECUTADO!FH45 -> 58.5 | L41: 6.8 | M41: 42.9 | N41: 392.7 | O41: =+SUM(C41:N41) -> 7756.1815 | U41: C.H. ÁNGEL III | V41: 482.4
B42: 18:00 | C42: 1176.9895 | D42: 3116.1 | E42: 2769 | F42: 44.9 | G42: 83.51 | J42: =+DESPACHO_EJECUTADO!FG46+DESPACHO_EJECUTADO!FH46 -> 57.9 | L42: 6.9 | M42: 14 | N42: 374.1 | O42: =+SUM(C42:N42) -> 7643.3994 | U42: C.H. LA JOYA | V42: 190.25
B43: 18:30 | C43: 1171.374 | D43: 3129 | E43: 2783.9 | F43: 45.3 | G43: 83.28 | J43: =+DESPACHO_EJECUTADO!FG47+DESPACHO_EJECUTADO!FH47 -> 58.1 | L43: 6.9 | M43: 0.3 | N43: 370.4 | O43: =+SUM(C43:N43) -> 7648.554 | T43: HIDROCAÑETE S.A. | U43: C.H. IMPERIAL | V43: 82
B44: 19:00 | C44: 1176.8471 | D44: 3352.1 | E44: 2768.3 | F44: 45.4 | G44: 82.52 | J44: =+DESPACHO_EJECUTADO!FG48+DESPACHO_EJECUTADO!FH48 -> 58.2 | L44: 6.9 | M44: 0 | N44: 317.9 | O44: =+SUM(C44:N44) -> 7808.1671 | T44: HIDROELECTRICA HUANCHOR S.A.C. | U44: C.H. HUANCHOR | V44: 436.3
B45: 19:30 | C45: 1180.9886 | D45: 3355.2 | E45: 2783.6 | F45: 45.3 | G45: 83.52 | J45: =+DESPACHO_EJECUTADO!FG49+DESPACHO_EJECUTADO!FH49 -> 58.4 | L45: 6.9 | M45: 0 | N45: 291.7 | O45: =+SUM(C45:N45) -> 7805.6086 | T45: HUAURA POWER GROUP S.A. | U45: C.H. YARUCAYA | V45: 417.05
B46: 20:00 | C46: 1181.26 | D46: 3357.4 | E46: 2782.1 | F46: 45.3 | G46: 85.3 | J46: =+DESPACHO_EJECUTADO!FG50+DESPACHO_EJECUTADO!FH50 -> 58.3 | L46: 6.9 | M46: 0 | N46: 298.3 | O46: =+SUM(C46:N46) -> 7814.86 | T46: HYDRO GLOBAL PERÚ S.A.C. | U46: CH SAN GABAN III | W46: 4853.8
B47: 20:30 | C47: 1176.7627 | D47: 3313.1 | E47: 2785.4 | F47: 45.4 | G47: 84.13 | J47: =+DESPACHO_EJECUTADO!FG51+DESPACHO_EJECUTADO!FH51 -> 58.2 | L47: 6.9 | M47: 0 | N47: 290.5 | O47: =+SUM(C47:N47) -> 7760.3927 | T47: INLAND ENERGY SAC | U47: C.H. SANTA TERESA | V47: 2172.9
B48: 21:00 | C48: 1177.2484 | D48: 3361.7 | E48: 2707.3 | F48: 45.4 | G48: 85.19 | J48: =+DESPACHO_EJECUTADO!FG52+DESPACHO_EJECUTADO!FH52 -> 58.2 | L48: 6.9 | M48: 0 | N48: 282 | O48: =+SUM(C48:N48) -> 7723.9384 | T48: INVERSIONES SHAQSHA S.A.C. | U48: C.H. PARIAC | V48: 48.25
B49: 21:30 | C49: 1186.6355 | D49: 3281.1 | E49: 2760.3 | F49: 44.8 | G49: 84.98 | J49: =+DESPACHO_EJECUTADO!FG53+DESPACHO_EJECUTADO!FH53 -> 58.3 | L49: 6.9 | M49: 0 | N49: 244.1 | O49: =+SUM(C49:N49) -> 7667.1155 | T49: KALLPA GENERACION S.A. | U49: C.H. CERRO DEL AGUILA | W49: 8340.75
B50: 22:00 | C50: 1178.6372 | D50: 3272.7 | E50: 2778.7 | F50: 45.4 | G50: 85.11 | J50: =+DESPACHO_EJECUTADO!FG54+DESPACHO_EJECUTADO!FH54 -> 58.2 | L50: 6.9 | M50: 0 | N50: 256.8 | O50: =+SUM(C50:N50) -> 7682.4472 | U50: M.C.H. CERRO DEL AGUILA | V50: 230.05
B51: 22:30 | C51: 1181.9329 | D51: 3284.1 | E51: 2790.4 | F51: 45.2 | G51: 85.2 | J51: =+DESPACHO_EJECUTADO!FG55+DESPACHO_EJECUTADO!FH55 -> 58.4 | L51: 6.9 | M51: 0 | N51: 215.9 | O51: =+SUM(C51:N51) -> 7668.0329 | T51: LA VIRGEN | U51: C.H. LA VIRGEN | W51: 1017.8
B52: 23:00 | C52: 1176.1254 | D52: 3103.4 | E52: 2769.9 | F52: 45.5 | G52: 85.26 | J52: =+DESPACHO_EJECUTADO!FG56+DESPACHO_EJECUTADO!FH56 -> 58.4 | L52: 6.9 | M52: 0 | N52: 150.6 | O52: =+SUM(C52:N52) -> 7396.0854 | T52: MAJA ENERGIA S.A.C. | U52: C.H. RONCADOR | V52: 85
B53: 23:30 | C53: 1155.0406 | D53: 3117.6 | E53: 2618.9 | F53: 45.4 | G53: 85.28 | J53: =+DESPACHO_EJECUTADO!FG57+DESPACHO_EJECUTADO!FH57 -> 58.7 | L53: 6.9 | M53: 0 | N53: 94.7 | O53: =+SUM(C53:N53) -> 7182.5206 | T53: ORAZUL ENERGY PERÚ | U53: C.H. CAÑA BRAVA | V53: 130.05
B54: 00:00 | C54: 1173.7257 | D54: 3175.2 | E54: 2443.3 | F54: 45.6 | G54: 85.38 | J54: =+DESPACHO_EJECUTADO!FG58+DESPACHO_EJECUTADO!FH58 -> 58.4 | L54: 6.9 | M54: 0 | N54: 47.8 | O54: =+SUM(C54:N54) -> 7036.3057 | U54: C.H. CAÑON DEL PATO | W54: 5746.45
B55: TOTAL MWh | C55: =SUM(C7:C54)/2 -> 27630.19 | D55: =SUM(D7:D54)/2 -> 75693.85 | E55: =SUM(E7:E54)/2 -> 57115.05 | F55: =SUM(F7:F54)/2 -> 1086.15 | G55: =SUM(G7:G54)/2 -> 1973.61 | H55: =SUM(H7:H54)/2 -> 0 | I55: =SUM(I7:I54)/2 -> 0 | J55: =SUM(J7:J54)/2 -> 1414.35 | ... O55: =SUM(O7:O54)/2 -> 177480.65 | U55: C.H. CARHUAQUERO | W55: 2158.4
B56: % | C56: =+C55/$O$55 -> 0.15568001 | D56: =+D55/$O$55 -> 0.42649072 | E56: =+E55/$O$55 -> 0.32181001 | F56: =+F55/$O$55 -> 0.0061198221 | G56: =+G55/$O$55 -> 0.011120142 | H56: =+H55/$O$55 -> 0 | I56: =+I55/$O$55 -> 0 | J56: =+J55/$O$55 -> 0.0079690378 | ... O56: =+O55/$O$55 -> 1 | U56: C.H. CARHUAQUERO IV | V56: 237.7
T57: ORYGEN PERU S.A.A. | U57: C.H. CALLAHUANCA | W57: 1885.1
U58: C.H. HER 1 | V58: 14.4
U59: C.H. HUAMPANI | V59: 721.35
U60: C.H. HUINCO | W60: 3482.5
U61: C.H. MATUCANA | W61: 3008.1
U62: C.H. MOYOPAMPA | V62: 1536.75
T63: SAN GABAN | U63: C.H. SAN GABAN II | W63: 2653.45
U64: PCH TUPURI | V64: 38.55
T65: SINERSA | U65: C.H. CHANCAY | V65: 479.9
U66: C.H. POECHOS II | V66: 196.2
T67: STATKRAFT S.A | U67: C.H. ARCATA | V67: 50.25
U68: C.H. CAHUA | V68: 969.5
U69: C.H. CHEVES | W69: 3622.2
U70: C.H. GALLITO CIEGO | W70: 754.45
U71: C.H. MALPASO | W71: 275.8
U72: C.H. YAUPI | V72: 2608.05
T73: TRANSMISION ANDINA DE GENERACION S.A.C. | U73: C.H. OROYA | V73: 141.1
U74: C.H. PACHACHACA | V74: 42.9
T75: VARI ENERGIA S.A.C. | U75: C.H. ANASHIRONI | V75: 236.45
T76: TOTAL MWh | V76: 27630.19 | W76: 75693.85

Sheet GENERACION RER
B3: martes, 13 de Enero del 2026
B5: GENERACIÓN ELÉCTRICA DE LAS CENTRALES RER (MW)
B6: HORA | C6: AGRO INDUSTRIAL PARAMONGA S.A. | D6: AGROAURORA S.A.C. | E6: AGROINDUSTRIAS SAN JACINTO S.A.A. | F6: AGROLMOS SOCIEDAD ANONIMA - AGROLMOS S.A. | G6: ANDEAN POWER S.A.C. | H6: ASOCIACIÓN SANTA LUCIA DE CHACAS | I6: ATRIA ENERGIA S.A.C. | J6: BIOENERGIA DEL CHIRA S.A. | K6: CASA GRANDE S.A.A. | L6: CELARIS ENERGY S.A. | M6: COENERGY S.A.C. | N6: COLCA SOLAR S.A.C. | O6: EGEJUNIN | T6: ELECTRICA YANAPAMPA SAC | U6: EMPRESA DE GENERACION ELECTRICA CANCHAYLLO SAC | V6: EMPRESA DE GENERACION ELECTRICA RIO BAÑOS S.A.C. | W6: EMPRESA DE GENERACION ELECTRICA SANTA ANA S.A.C. | X6: EMPRESA ELECTRICA AGUA AZUL | Y6: EMPRESA ELECTRICA RIO DOBLE | Z6: ENERGÍA EÓLICA S.A. | AB6: ENERGIA RENOVABLE DEL SUR S.A. | AC6: ENGIE ENERGIA PERU S.A.A. | AG6: GENERACIÓN ANDINA S.A.C. | AI6: GENERADORA DE ENERGÍA DEL PERÚ | AM6: GR CORTARRAMA SOCIEDAD ANONIMA CERRADA | AN6: GR PAINO SOCIEDAD ANONIMA CERRADA | AO6: GR TARUCA SOCIEDAD ANONIMA CERRADA | AP6: HIDROCAÑETE S.A. | AQ6: HUAURA POWER GROUP S.A. | AR6: HYDRO PATAPO S.A.C. | AS6: JOYA SOLAR S.A.C. | AU6: KALLPA GENERACION S.A. | AW6: KONDU SAC | AX6: MAJA ENERGIA S.A.C. | AY6: MAJES ARCUS S.A.C. | BA6: MOQUEGUA FV S.A.C. | BB6: ORAZUL ENERGY PERÚ | BD6: ORYGEN PERU S.A.A. | BI6: PANAMERICANA SOLAR SAC. | BJ6: PARQUE EOLICO MARCONA S.A.C. | BK6: PARQUE EOLICO TRES HERMANAS S.A.C. | BL6: PETRAMAS | BP6: REPARTICIÓN ARCUS S.A.C. | BQ6: SAN GABAN | BR6: SINERSA | BT6: TACNA SOLAR SAC. | BU6: VARI ENERGIA S.A.C. | BV6: TOTAL RER
C7: C.T. PARAMONGA | D7: C.T. MAPLE | E7: C.T SAN JACINTO | F7: C.T. AGROLMOS | G7: C.H. CARHUAC | H7: C.H. HUALLIN | I7: C.H. PURMACANA | J7: C.T. CAÑA BRAVA | K7: C.T. CASA GRANDE | L7: C.H. MANTA | M7: CS COENERGY | N7: CS YARUCAYA | O7: C.H. HUASAHUASI I | P7: C.H. HUASAHUASI II | Q7: C.H. RUNATULLO II | R7: C.H. RUNATULLO III | S7: C.H. STA CRUZ I y II | T7: C.H. YANAPAMPA | U7: C.H. CANCHAYLLO | V7: C.H. RUCUY | W7: C.H. RENOVANDES H1 | X7: C.H. POTRERO | Y7: C.H. LAS PIZARRAS | Z7: C.E. CUPISNIQUE | AA7: C.E. TALARA | AB7: CE SAN JUAN | AC7: C.E. P LOM EXPANSION | AD7: C.E. PUNTA LOMITAS | AE7: C.S. INTIPAMPA | AF7: CS EXPANSIÓN INTIPAMPA | AG7: C.H. 8 DE AGOSTO | AH7: C.H. EL CARMEN | AI7: C.H. ANGEL I | AJ7: C.H. ANGEL II | AK7: C.H. ANGEL III | AL7: C.H. LA JOYA | AM7: CS MATARANI | AN7: C.E. HUAMBOS | AO7: C.E. DUNA | AP7: C.H. NUEVAIMPERIAL | AQ7: C.H. YARUCAYA | AR7: MCH PATAPO | AS7: C.S. ILLA 1 | AT7: CS SAN MARTIN SOLAR | AU7: C.S. SUNNY EXPANSION | AV7: CS SUNNY | AW7: CARHUAQUERO (CS) | AX7: C.H. RONCADOR | AY7: C.S. MAJES | AZ7: C.S. SOL DE VERANO | BA7: C.S. MOQUEGUA FV | BB7: C.H. CANA BRAVA | BC7: C.H. CARHUAQUERO4 | BD7: C.E. WAYRA EXTENSION | BE7: C.E. WAYRA I | BF7: C.H. HER 1 | BG7: C.S. CLEMESI | BH7: C.S. RUBI | BI7: C.S. PANAMERICANA-SOLAR | BJ7: C.E. MARCONA | BK7: C.E. 3 HERMANAS | BL7: C.T. HUAYCOLORO | BM7: C.T. LA GRINGA V | BN7: CTB CALLAO | BO7: CTB. DONA CATALINA | BP7: C.S. REPARTICION | BQ7: C.H. TUPURI | BR7: C.H. CHANCAY | BS7: C.H. POECHOS2 | BT7: C.S. TACNA-SOLAR | BU7: C.H. ANASHIRONI | BV7: MW
B8: 0:30 | C8: 12.9 | D8: 19.1 | E8: 7.82 | F8: 11.22 | G8: 6 | H8: 3.04 | J8: 9.9 | K8: 24.3 | L8: 20 | O8: 19.833 | Q8: 20.3 | R8: 20.22 | S8: 12.848 | T8: 3 | U8: 5.2 | V8: 20 | X8: 20 | Y8: 18.3 | Z8: 7.8 | AA8: 3.8 | AB8: 59.6 | AC8: 4.3 | AD8: 116.3 | AG8: 20.9 | AH8: 8.2 | AI8: 20.4 | AJ8: 20.4 | AK8: 20.1 | AL8: 8.5 | AN8: 1.6 | AO8: 3.1 | AP8: 3.4 | AQ8: 18.6 | AX8: 3.6 | BB8: 5.3 | BC8: 10 | BD8: 22.5 | BE8: 34.6 | BF8: 0.6 | BJ8: 20.6 | BK8: 56.9 | BL8: 3.6 | BM8: 1 | BO8: 2.2 | BQ8: 1.3 | BR8: 20 | BS8: 8.1 | BV8: 761.281
B9: 1:00 | C9: 12.9 | D9: 19.1 | E9: 7.34 | F9: 11.22 | G9: 6 | H9: 3.04 | J9: 9.1 | K9: 24.1 | L9: 20 | O9: 19.832 | Q9: 20.05 | R9: 20.19 | S9: 12.824 | T9: 3 | U9: 5.1 | V9: 20 | X9: 20 | Y9: 18.4 | Z9: 7.5 | AA9: 4.4 | AB9: 45.6 | AC9: 6.2 | AD9: 105.2 | AG9: 20.9 | AH9: 8 | AI9: 20.4 | AJ9: 20.4 | AK9: 20.1 | AL9: 8.5 | AN9: 2.9 | AO9: 1.9 | AP9: 3.4 | AQ9: 18.6 | AX9: 3.6 | BB9: 5.4 | BC9: 9.9 | BD9: 19.2 | BE9: 27.7 | BF9: 0.6 | BJ9: 17.1 | BK9: 44.1 | BL9: 3.6 | BM9: 1 | BO9: 2.2 | BQ9: 1.3 | BR9: 20 | BS9: 8.2 | BV9: 710.096
B10: 1:30 | C10: 13.8 | D10: 19.1 | E10: 7.2 | F10: 11.24 | G10: 5.9 | H10: 3.04 | J10: 9.8 | K10: 23 | L10: 20 | O10: 19.846 | Q10: 19.83 | R10: 20.1 | S10: 12.848 | T10: 3 | U10: 4.4 | V10: 20 | X10: 20 | Y10: 18.4 | Z10: 5.9 | AA10: 4.8 | AB10: 44 | AC10: 4 | AD10: 86.6 | AG10: 20.9 | AH10: 7.9 | AI10: 20.4 | AJ10: 20.4 | AK10: 20.1 | AL10: 8.5 | AN10: 2 | AO10: 2.3 | AP10: 3.4 | AQ10: 18.7 | AX10: 3.6 | BB10: 5.4 | BC10: 9.9 | BD10: 7.6 | BE10: 10.9 | BF10: 0.6 | BJ10: 16.7 | BK10: 45.8 | BL10: 3.6 | BM10: 1 | BO10: 2.2 | BQ10: 1.3 | BR10: 20 | BS10: 8.2 | BV10: 658.204
B11: 2:00 | C11: 14 | D11: 19.1 | E11: 7.08 | F11: 11.24 | G11: 5.8 | H11: 3.04 | J11: 9.8 | K11: 23.7 | L11: 20 | O11: 19.844 | Q11: 19.91 | R11: 20.17 | S11: 12.816 | T11: 2.9 | U11: 5.1 | V11: 19.9 | X11: 20 | Y11: 18.3 | Z11: 5.2 | AA11: 4.2 | AB11: 34.1 | AC11: 3.5 | AD11: 57.7 | AG11: 20.9 | AH11: 7.9 | AI11: 20.4 | AJ11: 20.4 | AK11: 20.1 | AL11: 8.5 | AN11: 2.2 | AO11: 2.6 | AP11: 3.4 | AQ11: 18.6 | AX11: 3.6 | BB11: 5.4 | BC11: 10 | BD11: 20.1 | BE11: 21.5 | BF11: 0.6 | BJ11: 12.9 | BK11: 40.7 | BL11: 3.6 | BM11: 1 | BO11: 2.2 | BQ11: 1.3 | BR11: 19.8 | BS11: 8.2 | BV11: 633.3
B12: 2:30 | C12: 14.4 | D12: 19.1 | E12: 8.29 | F12: 11.25 | G12: 5.8 | H12: 3.04 | J12: 9.5 | K12: 16.4 | L12: 20 | O12: 19.849 | Q12: 19.95 | R12: 20.22 | S12: 12.847 | T12: 2.9 | U12: 5.1 | V12: 20 | X12: 19.7 | Y12: 18.3 | Z12: 2.8 | AA12: 4 | AB12: 39.1 | AC12: 2.6 | AD12: 53.7 | AG12: 20.9 | AH12: 7.9 | AI12: 20.4 | AJ12: 20.4 | AK12: 20.1 | AL12: 8.5 | AN12: 2.3 | AO12: 3.3 | AP12: 3.4 | AQ12: 18.6 | AX12: 3.6 | BB12: 5.4 | BC12: 9.9 | BD12: 19.1 | BE12: 27.3 | BF12: 0.6 | BJ12: 8.9 | BK12: 35.3 | BL12: 3.6 | BM12: 1 | BO12: 2.2 | BQ12: 1.2 | BR12: 20 | BS12: 8.2 | BV12: 620.946
B13: 3:00 | C13: 14.5 | D13: 19.1 | E13: 8.21 | F13: 11.21 | G13: 5.8 | H13: 3.04 | J13: 9.8 | K13: 22.7 | L13: 20 | O13: 19.849 | Q13: 19.95 | R13: 20.2 | S13: 12.823 | T13: 3 | U13: 5.2 | V13: 20 | X13: 20 | Y13: 18.3 | Z13: 2.2 | AA13: 4.8 | AB13: 44.3 | AC13: 2.3 | AD13: 48.2 | AG13: 20.9 | AH13: 7.9 | AI13: 20.4 | AJ13: 20.4 | AK13: 20.1 | AL13: 8.5 | AN13: 1.8 | AO13: 3.4 | AP13: 3.5 | AQ13: 18.6 | AX13: 3.6 | BB13: 5.4 | BC13: 9.9 | BD13: 30.6 | BE13: 33.1 | BF13: 0.6 | BJ13: 11.8 | BK13: 31.1 | BL13: 3.6 | BM13: 1 | BO13: 2.2 | BQ13: 1.2 | BR13: 20 | BS13: 8.2 | BV13: 643.282
B14: 3:30 | C14: 14.2 | D14: 18.6 | E14: 8.45 | F14: 10.09 | G14: 5.9 | H14: 3.04 | J14: 9.8 | K14: 22.7 | L14: 20 | O14: 19.852 | Q14: 19.92 | R14: 20.3 | S14: 12.816 | T14: 3 | U14: 5.2 | V14: 20 | X14: 20 | Y14: 18.3 | Z14: 0.5 | AA14: 4.5 | AB14: 44.8 | AC14: 1.1 | AD14: 53.6 | AG14: 20.9 | AH14: 7.7 | AI14: 20.4 | AJ14: 20.4 | AK14: 20.1 | AL14: 8.9 | AN14: 2.2 | AO14: 3.4 | AP14: 3.5 | AQ14: 18.6 | AX14: 3.6 | BB14: 5.5 | BC14: 9.9 | BD14: 18.2 | BE14: 27.7 | BF14: 0.6 | BJ14: 11 | BK14: 28.2 | BL14: 3.6 | BM14: 1 | BO14: 2.2 | BQ14: 1.2 | BR14: 20 | BS14: 8.2 | BV14: 623.668
B15: 4:00 | C15: 13 | D15: 18.3 | E15: 7.82 | F15: 11.11 | G15: 5.9 | H15: 3.04 | J15: 9.5 | K15: 22.4 | L15: 20 | O15: 19.853 | Q15: 19.71 | R15: 20.19 | S15: 12.808 | T15: 3 | U15: 5.2 | V15: 20 | X15: 20 | Y15: 18.3 | AA15: 4.9 | AB15: 33.1 | AC15: 0.2 | AD15: 53.3 | AG15: 20.9 | AH15: 7.7 | AI15: 20.4 | AJ15: 20.4 | AK15: 20.1 | AL15: 8.9 | AN15: 2.8 | AO15: 3.3 | AP15: 3.4 | AQ15: 18.7 | AX15: 3.6 | BB15: 5.4 | BC15: 9.8 | BD15: 18.6 | BE15: 17.8 | BF15: 0.6 | BJ15: 8.9 | BK15: 24.2 | BL15: 3.7 | BM15: 1 | BO15: 2.2 | BQ15: 1.2 | BR15: 20 | BS15: 8.2 | BV15: 593.431
B16: 4:30 | C16: 13.4 | D16: 18.3 | E16: 7.89 | F16: 11.11 | G16: 5.8 | H16: 3.04 | J16: 10.6 | K16: 22.7 | L16: 20 | O16: 19.859 | Q16: 19.87 | R16: 20.24 | S16: 12.809 | T16: 2.9 | U16: 5.2 | V16: 20 | X16: 20 | Y16: 18.3 | AA16: 0.8 | AB16: 34 | AC16: 1.5 | AD16: 51.4 | AG16: 20.9 | AH16: 7.7 | AI16: 20.4 | AJ16: 20.4 | AK16: 20.1 | AL16: 8.9 | AN16: 2.8 | AO16: 2.8 | AP16: 3.4 | AQ16: 18.6 | AX16: 3.6 | BB16: 5.5 | BC16: 10 | BD16: 17.1 | BE16: 24 | BF16: 0.6 | BJ16: 6.9 | BK16: 18.2 | BL16: 3.7 | BM16: 1 | BO16: 2.2 | BQ16: 1.2 | BR16: 20 | BS16: 8.2 | BV16: 587.918
B17: 5:00 | C17: 13.5 | D17: 18.9 | E17: 8.11 | F17: 11.07 | G17: 5.6 | H17: 3.04 | J17: 10 | K17: 22.4 | L17: 20 | O17: 19.863 | Q17: 19.89 | R17: 20.25 | S17: 12.805 | T17: 2.9 | U17: 5.2 | V17: 20 | X17: 20 | Y17: 18.3 | AA17: 5.5 | AB17: 29.7 | AC17: 0.2 | AD17: 37.3 | AG17: 20.9 | AH17: 7.8 | AI17: 20.4 | AJ17: 20.4 | AK17: 20.1 | AL17: 8.9 | AN17: 3.7 | AO17: 3.9 | AP17: 3.4 | AQ17: 14.7 | AX17: 3.6 | BB17: 5.4 | BC17: 9.9 | BD17: 10.5 | BE17: 13.4 | BF17: 0.6 | BJ17: 8.9 | BK17: 19.1 | BL17: 3.7 | BM17: 1 | BO17: 2.2 | BQ17: 1.2 | BR17: 20 | BS17: 8.2 | BV17: 556.428
B18: 5:30 | C18: 14 | D18: 18.8 | E18: 8.02 | F18: 11.07 | G18: 5.7 | H18: 3.04 | J18: 9.8 | K18: 22.1 | L18: 20 | O18: 19.863 | Q18: 19.99 | R18: 20.27 | S18: 12.815 | T18: 3.2 | U18: 5.1 | V18: 20 | X18: 20 | Y18: 18.3 | AA18: 5.2 | AB18: 33.9 | AD18: 30.3 | AE18: 0.1 | AG18: 20.9 | AH18: 7.8 | AI18: 20.4 | AJ18: 20.4 | AK18: 20.1 | AL18: 8.9 | AN18: 3 | AO18: 3.8 | AP18: 3.4 | AQ18: 11.1 | AT18: 0.3 | AV18: 0.5 | AX18: 3.6 | BA18: 0.5 | BB18: 5.4 | BC18: 9.9 | BD18: 18.2 | BE18: 16.7 | BF18: 0.6 | BG18: 1.3 | BH18: 1.6 | BI18: 0.5 | BJ18: 9.4 | BK18: 17.3 | BL18: 3.7 | BM18: 1 | BO18: 2.2 | BQ18: 1.1 | BR18: 20 | BS18: 8.1 | BV18: 563.268
B19: 6:00 | C19: 14 | D19: 19.4 | E19: 8.07 | F19: 11.09 | G19: 10.7 | H19: 3 | J19: 9.9 | K19: 17.4 | L19: 19.8 | O19: 19.878 | Q19: 20.12 | R19: 20.24 | S19: 12.801 | T19: 3.2 | U19: 5.1 | V19: 19.9 | X19: 20 | Y19: 18.3 | AA19: 4.9 | AB19: 26.4 | AD19: 28 | AE19: 1.4 | AF19: 0.5 | AG19: 20.9 | AH19: 7.8 | AI19: 20.4 | AJ19: 20.4 | AK19: 20.1 | AL19: 8.9 | AM19: 6 | AN19: 3.1 | AO19: 4.6 | AP19: 3.4 | AQ19: 11.3 | AT19: 15.7 | AV19: 19.1 | AX19: 3.6 | BA19: 0.9 | BB19: 5.4 | BC19: 9.9 | BD19: 27.8 | BE19: 20.5 | BF19: 0.6 | BG19: 10.9 | BH19: 13.8 | BI19: 1.3 | BJ19: 13.3 | BK19: 15.8 | BL19: 3.7 | BM19: 1 | BO19: 2.2 | BP19: 0.6 | BQ19: 1.1 | BR19: 20 | BS19: 8.2 | BT19: 0.2 | BV19: 636.599
B20: 6:30 | C20: 14.3 | D20: 19.4 | E20: 7.73 | F20: 11.03 | G20: 13 | H20: 2.96 | J20: 10 | K20: 21.8 | L20: 20 | O20: 19.792 | Q20: 20.1 | R20: 20.2 | S20: 12.873 | T20: 3.1 | U20: 5.2 | V20: 20 | X20: 19.7 | Y20: 18.3 | AA20: 4.7 | AB20: 32.9 | AD20: 38.5 | AE20: 3.2 | AF20: 2.5 | AG20: 20.9 | AH20: 7.8 | AI20: 20.4 | AJ20: 20.4 | AK20: 20.1 | AL20: 9 | AM20: 29.8 | AN20: 2.8 | AO20: 3.7 | AP20: 3.4 | AQ20: 11.3 | AT20: 93.5 | AV20: 61.2 | AX20: 3.5 | AY20: 0.8 | BA20: 3.3 | BB20: 5.4 | BC20: 9.9 | BD20: 9.4 | BE20: 16 | BF20: 0.6 | BG20: 43.3 | BH20: 55.9 | BI20: 4.6 | BJ20: 9.1 | BK20: 14.2 | BL20: 3.7 | BM20: 1 | BO20: 2.2 | BP20: 2.4 | BQ20: 1.1 | BR20: 20 | BS20: 8.2 | BT20: 1 | BV20: 861.185
B21: 7:00 | C21: 14.1 | D21: 19.4 | E21: 6.47 | F21: 11.08 | G21: 14.6 | H21: 2.92 | J21: 9.8 | K21: 22.2 | L21: 20 | N21: 0.1 | O21: 19.454 | Q21: 20.24 | R21: 20.31 | S21: 12.944 | T21: 3 | U21: 5.2 | V21: 20 | X21: 20 | Y21: 18.4 | AA21: 4.7 | AB21: 28.9 | AC21: 0.9 | AD21: 48.1 | AE21: 15.3 | AF21: 5.3 | AG21: 20.9 | AH21: 7.8 | AI21: 20.4 | AJ21: 20.4 | AK21: 20.1 | AL21: 9 | AM21: 21.5 | AN21: 2 | AO21: 3.2 | AP21: 3.4 | AQ21: 11.3 | AT21: 96.9 | AV21: 78.5 | AX21: 3.5 | AY21: 1.3 | BA21: 8.4 | BB21: 5.5 | BC21: 9.9 | BD21: 12.9 | BE21: 18 | BF21: 0.6 | BG21: 39.2 | BH21: 46.2 | BI21: 12.8 | BJ21: 8.9 | BK21: 12.3 | BL21: 3.7 | BM21: 1 | BO21: 2.2 | BP21: 2.4 | BQ21: 1.1 | BR21: 20 | BS21: 8.2 | BT21: 2.2 | BV21: 899.118
B22: 7:30 | C22: 13.7 | D22: 19 | E22: 8.22 | F22: 11.08 | G22: 14.6 | H22: 2.88 | J22: 9.8 | K22: 23.1 | L22: 20 | M22: 0.1 | O22: 13.761 | Q22: 20.12 | R22: 20.23 | S22: 13.022 | T22: 2.3 | U22: 5 | V22: 20 | X22: 20 | Y22: 18.4 | AA22: 3.8 | AB22: 14.2 | AC22: 0.5 | AD22: 57.6 | AE22: 24.4 | AF22: 31.1 | AG22: 20.9 | AH22: 7.7 | AI22: 20.4 | AJ22: 20.4 | AK22: 20.1 | AL22: 9 | AM22: 20.2 | AN22: 3.3 | AO22: 6 | AP22: 3.5 | AQ22: 10.7 | AT22: 123.5 | AV22: 173.9 | AX22: 3.5 | AY22: 2.1 | BA22: 7.8 | BB22: 5.6 | BC22: 9.9 | BD22: 21.2 | BE22: 23.3 | BF22: 0.6 | BG22: 84.5 | BH22: 107 | BI22: 11.5 | BJ22: 4.2 | BK22: 3.3 | BL22: 3.7 | BM22: 1 | BO22: 2.2 | BP22: 4.7 | BQ22: 1.1 | BR22: 20 | BS22: 8.2 | BT22: 2.4 | BV22: 1154.313
B23: 8:00 | C23: 13.6 | D23: 19 | E23: 7.34 | F23: 11.06 | G23: 14.7 | H23: 2.84 | J23: 9.5 | K23: 23.3 | L23: 20 | M23: 0.1 | N23: 0.1 | Q23: 19.97 | R23: 20.15 | S23: 13.034 | T23: 3.1 | U23: 5 | V23: 20 | X23: 20 | Y23: 18.4 | Z23: 1.1 | AA23: 3.3 | AB23: 18.8 | AC23: 1.5 | AD23: 63.7 | AE23: 34.8 | AF23: 37.2 | AG23: 20.9 | AH23: 7.7 | AI23: 20.4 | AJ23: 20.4 | AK23: 20.1 | AL23: 8.2 | AM23: 29.9 | AN23: 4.2 | AO23: 6.6 | AP23: 3.4 | AQ23: 6.8 | AT23: 168.5 | AV23: 83.9 | AX23: 3.5 | AY23: 4.3 | BA23: 10.6 | BB23: 5.4 | BC23: 10 | BF23: 0.6 | BG23: 101.9 | BH23: 134.1 | BI23: 14.8 | BJ23: 5 | BK23: 4.8 | BL23: 3.7 | BM23: 1 | BO23: 2.2 | BP23: 9.8 | BQ23: 1.1 | BR23: 20.1 | BS23: 8.2 | BT23: 3.7 | BV23: 1147.394
B24: 8:30 | C24: 13.2 | D24: 18.7 | E24: 6 | F24: 11.02 | G24: 14.8 | H24: 2.8 | J24: 9.5 | K24: 22.6 | L24: 20 | M24: 0.1 | N24: 0.1 | Q24: 20.15 | R24: 20.23 | S24: 13.035 | T24: 3 | U24: 5.2 | V24: 19.9 | X24: 20 | Y24: 18.5 | Z24: 0.5 | AA24: 2.5 | AB24: 34.2 | AC24: 3.6 | AD24: 66.8 | AE24: 36.3 | AF24: 48.4 | AG24: 20.9 | AH24: 7.8 | AI24: 20.4 | AJ24: 20.4 | AK24: 20.1 | AL24: 8.2 | AM24: 74.5 | AN24: 3.7 | AO24: 5.3 | AP24: 3.4 | AQ24: 15 | AT24: 170.8 | AV24: 181.8 | AX24: 3.5 | AY24: 5.9 | BA24: 13.8 | BB24: 5.5 | BC24: 9.9 | BF24: 0.6 | BG24: 99.6 | BH24: 133.9 | BI24: 18.4 | BJ24: 7.2 | BK24: 10.8 | BL24: 2.3 | BM24: 1 | BO24: 2.2 | BP24: 7.2 | BQ24: 1.1 | BR24: 20 | BS24: 8.2 | BT24: 4.7 | BV24: 1339.235
B25: 9:00 | C25: 13.4 | D25: 19 | E25: 7.45 | F25: 11.39 | G25: 14.9 | H25: 2.8 | J25: 9.7 | K25: 23.7 | L25: 20 | M25: 0.2 | N25: 0.3 | Q25: 20.11 | R25: 20.22 | S25: 13.039 | T25: 3 | U25: 5.2 | V25: 19.9 | X25: 20 | Y25: 18.5 | Z25: 1.6 | AA25: 2.7 | AB25: 36.3 | AC25: 7.4 | AD25: 78.1 | AE25: 37.2 | AF25: 49.9 | AG25: 20.9 | AH25: 8 | AI25: 20.4 | AJ25: 20.4 | AK25: 20.1 | AL25: 8.2 | AM25: 64.6 | AN25: 5.7 | AO25: 6.4 | AP25: 3.3 | AQ25: 18.5 | AT25: 196.1 | AV25: 201.3 | AX25: 3.5 | AY25: 11.3 | BA25: 13.4 | BB25: 5.4 | BC25: 9.9 | BF25: 0.6 | BG25: 106 | BH25: 138.1 | BI25: 18.1 | BJ25: 7.9 | BK25: 17 | BL25: 2.3 | BM25: 1 | BO25: 2.2 | BP25: 7.2 | BQ25: 1.1 | BR25: 20 | BS25: 8.2 | BT25: 5.7 | BV25: 1428.809
B26: 9:30 | C26: 13.2 | D26: 19 | E26: 6.48 | F26: 11.35 | G26: 14.9 | H26: 2.8 | J26: 9.1 | K26: 23.3 | L26: 20 | M26: 0.2 | N26: 0.4 | Q26: 20.25 | R26: 20.19 | S26: 12.963 | T26: 2.9 | U26: 5.1 | V26: 20 | X26: 20 | Y26: 7.7 | AA26: 1.2 | AB26: 31.2 | AC26: 5.1 | AD26: 58.3 | AE26: 38 | AF26: 41.1 | AG26: 20.9 | AH26: 8.3 | AI26: 20.4 | AJ26: 20.4 | AK26: 20.1 | AL26: 8.4 | AM26: 79.5 | AN26: 8.4 | AO26: 8.7 | AP26: 3.3 | AQ26: 18.5 | AT26: 253 | AV26: 220.5 | AW26: 0.1 | AX26: 3.5 | AY26: 9.8 | BA26: 13.5 | BB26: 5.5 | BC26: 9.9 | BF26: 0.6 | BG26: 107.4 | BH26: 139.9 | BI26: 18 | BJ26: 7 | BK26: 19.7 | BL26: 2.3 | BM26: 1 | BO26: 2.2 | BP26: 13.7 | BQ26: 1.3 | BR26: 20 | BS26: 8.2 | BT26: 8.6 | BV26: 1487.333
B27: 10:00 | C27: 13.2 | D27: 19 | E27: 6.08 | F27: 11.33 | G27: 17 | H27: 3.04 | I27: 0.1 | J27: 2.7 | K27: 23.1 | L27: 20 | M27: 0.2 | N27: 0.4 | Q27: 20.3 | R27: 20.29 | S27: 12.955 | T27: 3 | U27: 5.1 | V27: 20 | X27: 20 | Y27: 7.4 | AB27: 19.8 | AC27: 4.2 | AD27: 47.8 | AE27: 35.9 | AF27: 48.6 | AG27: 20.9 | AH27: 8.3 | AI27: 20.4 | AJ27: 20.4 | AK27: 20.1 | AL27: 8.4 | AM27: 78 | AN27: 10.7 | AO27: 11.8 | AP27: 3.3 | AQ27: 18.5 | AT27: 253 | AV27: 209.5 | AW27: 0.2 | AX27: 3.5 | AY27: 14.7 | BA27: 13.8 | BB27: 5.5 | BC27: 9.9 | BF27: 0.6 | BG27: 109 | BH27: 142.4 | BI27: 17.9 | BJ27: 5.5 | BK27: 18.8 | BL27: 2.2 | BM27: 1 | BO27: 2.2 | BP27: 12.6 | BQ27: 1.4 | BR27: 20 | BS27: 8.2 | BT27: 14 | BV27: 1468.195
B28: 10:30 | C28: 13.3 | D28: 19 | E28: 6.22 | F28: 11.37 | G28: 20.2 | H28: 3.04 | I28: 0.3 | J28: 2.3 | K28: 23.8 | L28: 20 | M28: 0.2 | N28: 0.7 | Q28: 20.22 | R28: 20.24 | S28: 12.95 | T28: 2.9 | U28: 5.2 | V28: 20 | X28: 20 | Y28: 19 | AB28: 32.2 | AC28: 5.3 | AD28: 46.5 | AE28: 40.9 | AF28: 48.1 | AG28: 20.9 | AH28: 8.3 | AI28: 20.4 | AJ28: 20.4 | AK28: 20.1 | AL28: 8.4 | AM28: 79.7 | AN28: 11.8 | AO28: 12.3 | AP28: 3.3 | AQ28: 18.5 | AT28: 185.4 | AV28: 152.4 | AW28: 0.2 | AX28: 3.5 | AY28: 15.5 | BA28: 13.9 | BB28: 5.5 | BC28: 9.9 | BF28: 0.6 | BG28: 103.3 | BH28: 135.9 | BI28: 17.9 | BJ28: 3.2 | BK28: 18.3 | BL28: 2.2 | BM28: 1 | BO28: 2.2 | BP28: 11.6 | BQ28: 1.9 | BR28: 20 | BS28: 8.2 | BT28: 15.9 | BV28: 1366.54
B29: 11:00 | C29: 13.5 | D29: 19 | E29: 4.26 | F29: 11.24 | G29: 20.2 | H29: 3.04 | I29: 0.3 | J29: 2.4 | K29: 22.8 | L29: 20 | M29: 0.2 | N29: 0.6 | Q29: 20.27 | R29: 20.21 | S29: 12.939 | T29: 2.9 | U29: 5.2 | V29: 20 | X29: 20 | Y29: 18.8 | Z29: 0.3 | AB29: 42.5 | AC29: 7.4 | AD29: 64.5 | AE29: 20.5 | AF29: 37.4 | AG29: 20.5 | AH29: 8.3 | AI29: 20.4 | AJ29: 20.4 | AK29: 20.1 | AL29: 6.4 | AM29: 80.7 | AN29: 11.8 | AO29: 10.6 | AP29: 3.3 | AQ29: 18.5 | AT29: 254.1 | AV29: 225.7 | AW29: 0.3 | AX29: 3.5 | AY29: 16.2 | BA29: 13.9 | BB29: 5.3 | BC29: 9.9 | BF29: 0.6 | BG29: 102.3 | BH29: 145.1 | BI29: 16.8 | BJ29: 5.5 | BK29: 27 | BL29: 2.2 | BM29: 1 | BO29: 2.2 | BP29: 11.7 | BQ29: 1.9 | BR29: 20 | BS29: 8.1 | BT29: 17.9 | BV29: 1522.659
B30: 11:30 | C30: 13.3 | D30: 19 | E30: 4.71 | F30: 11.35 | G30: 20.2 | H30: 3.04 | I30: 0.3 | J30: 7.9 | K30: 22 | L30: 20 | M30: 0.2 | N30: 0.6 | O30: 7.872 | Q30: 20.27 | R30: 20.21 | S30: 12.846 | T30: 2.8 | U30: 5.1 | V30: 20 | X30: 20 | Y30: 18.8 | Z30: 2.6 | AB30: 42.4 | AC30: 8.6 | AD30: 66.6 | AE30: 21.9 | AF30: 25.7 | AG30: 12.6 | AH30: 8.3 | AI30: 20.4 | AJ30: 20.4 | AK30: 20.1 | AL30: 6.4 | AM30: 80.8 | AN30: 8.7 | AO30: 10.6 | AP30: 3.3 | AQ30: 18.6 | AT30: 252.9 | AV30: 225.3 | AW30: 0.2 | AX30: 3.6 | AY30: 17.8 | BA30: 13.4 | BB30: 5.4 | BC30: 9.9 | BF30: 0.6 | BG30: 87.5 | BH30: 68.2 | BI30: 17.8 | BJ30: 6.1 | BK30: 28.3 | BL30: 2.2 | BM30: 1 | BO30: 2.2 | BP30: 7.2 | BQ30: 1.9 | BR30: 20 | BS30: 8.2 | BT30: 18.9 | BV30: 1427.098
B31: 12:00 | C31: 13.2 | D31: 19 | E31: 4.58 | F31: 11.36 | G31: 20.2 | H31: 3.04 | I31: 0.3 | J31: 9.1 | K31: 24.9 | L31: 20 | M31: 0.3 | N31: 0.4 | O31: 18.312 | Q31: 20.2 | R31: 20.29 | S31: 12.852 | T31: 2.9 | U31: 5.2 | V31: 20 | X31: 20 | Y31: 18.7 | Z31: 4.8 | AA31: 0.2 | AB31: 42.5 | AC31: 8.4 | AD31: 73.7 | AE31: 14.7 | AF31: 28.9 | AG31: 7.4 | AH31: 8.3 | AI31: 20.4 | AJ31: 20.4 | AK31: 20.1 | AL31: 6.4 | AM31: 80.8 | AN31: 8 | AO31: 10.3 | AP31: 3.4 | AQ31: 18.5 | AT31: 253 | AV31: 229.4 | AW31: 0.2 | AX31: 3.6 | AY31: 17.7 | BA31: 14 | BB31: 5.4 | BC31: 9.9 | BF31: 0.6 | BG31: 78.2 | BH31: 73 | BI31: 17.4 | BJ31: 7.1 | BK31: 24.7 | BL31: 2.2 | BM31: 1 | BO31: 2.2 | BP31: 9.8 | BQ31: 1.9 | BR31: 20 | BS31: 8.2 | BT31: 19.1 | BV31: 1440.634
B32: 12:30 | C32: 13.2 | D32: 19 | E32: 4.68 | F32: 11.37 | G32: 20.2 | H32: 3.04 | I32: 0.3 | J32: 9.1 | K32: 23.4 | L32: 20.2 | M32: 0.3 | N32: 0.2 | O32: 19.868 | Q32: 20.13 | R32: 20.13 | S32: 12.863 | T32: 2.9 | U32: 5.2 | V32: 20 | W32: 2.5 | X32: 20 | Y32: 18.9 | Z32: 5 | AA32: 0.4 | AB32: 39.5 | AC32: 9.7 | AD32: 69.5 | AE32: 16.8 | AF32: 18.2 | AG32: 1.5 | AH32: 8.3 | AI32: 20.4 | AJ32: 20.4 | AK32: 20.1 | AL32: 6.5 | AM32: 70.7 | AN32: 10.9 | AO32: 12.1 | AP32: 3.4 | AQ32: 18.5 | AT32: 253 | AV32: 234 | AW32: 0.1 | AX32: 3.6 | AY32: 15.5 | BA32: 14.3 | BB32: 5.5 | BC32: 9.8 | BF32: 0.6 | BG32: 95.5 | BH32: 134.6 | BI32: 17.5 | BJ32: 5.4 | BK32: 20.7 | BL32: 2.2 | BM32: 1 | BO32: 2.2 | BP32: 6.6 | BQ32: 1.9 | BR32: 20 | BS32: 8.1 | BT32: 18.9 | BU32: 8.5 | BV32: 1498.881
B33: 13:00 | C33: 13.2 | D33: 19 | E33: 4.96 | F33: 11.35 | G33: 11.1 | H33: 3.04 | I33: 0.4 | J33: 8.6 | K33: 20 | L33: 20 | M33: 0.3 | N33: 0.1 | O33: 19.866 | Q33: 20.17 | R33: 20.19 | S33: 12.848 | T33: 2.9 | U33: 5.1 | V33: 20 | W33: 20 | X33: 20 | Y33: 18.8 | Z33: 6 | AA33: 0.4 | AB33: 33.3 | AC33: 6.1 | AD33: 61.9 | AE33: 30.8 | AF33: 21.7 | AH33: 8.3 | AI33: 20.4 | AJ33: 20.4 | AK33: 20.1 | AL33: 6.5 | AM33: 77.5 | AN33: 11.4 | AO33: 13.2 | AP33: 3.4 | AQ33: 18.5 | AT33: 252.9 | AV33: 224.4 | AX33: 3.6 | AY33: 15.2 | BA33: 12.3 | BB33: 5.4 | BC33: 9.9 | BF33: 0.6 | BG33: 59.6 | BH33: 69.1 | BI33: 15.6 | BJ33: 5.1 | BK33: 19 | BL33: 2.2 | BM33: 1 | BO33: 2.2 | BP33: 9.1 | BQ33: 1.9 | BR33: 20.1 | BS33: 8.2 | BT33: 18.5 | BU33: 20.2 | BV33: 1407.924
B34: 13:30 | C34: 13 | D34: 19 | E34: 6.08 | F34: 11.38 | G34: 5.2 | H34: 3.04 | I34: 0.4 | J34: 1 | K34: 22.2 | L34: 20 | M34: 0.3 | N34: 0.1 | O34: 19.856 | Q34: 20.25 | R34: 20.27 | S34: 12.858 | T34: 3 | U34: 5 | V34: 20 | W34: 20.5 | X34: 20 | Y34: 18.8 | Z34: 11.6 | AA34: 0.6 | AB34: 37.2 | AC34: 7.7 | AD34: 67.4 | AE34: 25.9 | AF34: 40.7 | AH34: 8.3 | AI34: 20.4 | AJ34: 20.4 | AK34: 20.1 | AL34: 6.3 | AM34: 77 | AN34: 11.8 | AO34: 11.6 | AP34: 3.4 | AQ34: 18.5 | AT34: 231.3 | AV34: 172.2 | AW34: 0.1 | AX34: 3.6 | AY34: 16.4 | BA34: 10.6 | BB34: 5.5 | BC34: 9.9 | BD34: 8 | BF34: 0.6 | BG34: 70.6 | BH34: 94.7 | BI34: 16 | BJ34: 5.7 | BK34: 18.8 | BL34: 2.2 | BM34: 1 | BO34: 2.2 | BP34: 6.4 | BQ34: 1.9 | BR34: 20 | BS34: 8.2 | BT34: 17.3 | BU34: 20.3 | BV34: 1394.634
B35: 14:00 | C35: 13.2 | D35: 19 | E35: 5.86 | F35: 11.34 | G35: 5.2 | H35: 3.04 | I35: 0.4 | J35: 0.8 | K35: 22.8 | L35: 20 | M35: 0.2 | N35: 0.2 | O35: 19.864 | Q35: 20.25 | R35: 20.24 | S35: 12.845 | T35: 3 | U35: 5 | V35: 20 | W35: 20.2 | X35: 20 | Y35: 18.7 | Z35: 20.7 | AA35: 1.5 | AB35: 35.6 | AC35: 10 | AD35: 81.2 | AE35: 22.4 | AF35: 31.7 | AH35: 8.3 | AI35: 20.4 | AJ35: 20.4 | AK35: 20.1 | AL35: 7 | AM35: 65 | AN35: 8.3 | AO35: 9.1 | AP35: 3.4 | AQ35: 18.5 | AT35: 157.5 | AV35: 120.4 | AW35: 0.1 | AX35: 3.6 | AY35: 18.6 | BA35: 10.7 | BB35: 5.4 | BC35: 9.8 | BD35: 41.3 | BE35: 31.8 | BF35: 0.6 | BG35: 99.8 | BH35: 144.9 | BI35: 11.9 | BJ35: 4.7 | BK35: 16.8 | BL35: 2.2 | BM35: 1 | BO35: 2.2 | BP35: 7 | BQ35: 1.9 | BR35: 20 | BS35: 8.2 | BT35: 11.7 | BU35: 20.2 | BV35: 1398.039
B36: 14:30 | C36: 13.3 | D36: 19 | E36: 4.39 | F36: 11.37 | G36: 5 | H36: 3.04 | I36: 0.4 | J36: 8 | K36: 24.2 | L36: 20 | M36: 0.2 | N36: 0.1 | O36: 19.821 | Q36: 20.14 | R36: 20.16 | S36: 12.845 | T36: 3 | U36: 5.2 | V36: 20 | W36: 20 | X36: 20 | Y36: 18.7 | Z36: 27.8 | AA36: 3.4 | AB36: 42.9 | AC36: 8.8 | AD36: 77.6 | AE36: 16.5 | AF36: 26.7 | AG36: 15.5 | AH36: 8.3 | AI36: 20.4 | AJ36: 20.4 | AK36: 20.1 | AL36: 8.3 | AM36: 49.8 | AN36: 4.9 | AO36: 5.6 | AP36: 3.4 | AQ36: 18.5 | AT36: 112.7 | AV36: 97.5 | AW36: 0.1 | AX36: 3.6 | AY36: 12.6 | BA36: 12.3 | BB36: 5.5 | BC36: 9.9 | BD36: 57.1 | BE36: 69.5 | BF36: 0.6 | BG36: 91.2 | BH36: 88.8 | BI36: 16.2 | BJ36: 7 | BK36: 21.2 | BL36: 2.2 | BM36: 1 | BO36: 2.2 | BP36: 5.7 | BQ36: 1.9 | BR36: 20 | BS36: 8.1 | BT36: 7.5 | BU36: 20.1 | BV36: 1322.266
B37: 15:00 | C37: 13.2 | D37: 19 | E37: 5.86 | F37: 11.38 | G37: 9.2 | H37: 3.04 | I37: 0.4 | J37: 9.1 | K37: 24.6 | L37: 20 | M37: 0.3 | N37: 0.1 | O37: 19.883 | Q37: 20.25 | R37: 20.22 | S37: 12.776 | T37: 3 | U37: 5.2 | V37: 20 | W37: 20.2 | X37: 20 | Y37: 18.6 | Z37: 23.9 | AA37: 5.1 | AB37: 39.1 | AC37: 7.7 | AD37: 73.1 | AE37: 11.6 | AF37: 21.6 | AG37: 20.9 | AH37: 4.3 | AI37: 20.4 | AJ37: 20.4 | AK37: 20.1 | AL37: 8.3 | AM37: 37 | AN37: 3.3 | AO37: 3.3 | AP37: 3.4 | AQ37: 18.5 | AT37: 84.9 | AV37: 68.3 | AW37: 0.1 | AX37: 3.6 | AY37: 11.2 | BA37: 10.9 | BB37: 5.5 | BC37: 9.9 | BD37: 95 | BE37: 94.2 | BF37: 0.6 | BG37: 100.9 | BH37: 119.2 | BI37: 15.7 | BJ37: 9 | BK37: 26.3 | BL37: 2.2 | BM37: 1 | BO37: 2.2 | BP37: 4.2 | BQ37: 1.9 | BR37: 20 | BS37: 8.1 | BT37: 4.2 | BU37: 20.2 | BV37: 1337.609
B38: 15:30 | C38: 13 | D38: 19 | E38: 5.84 | F38: 11.34 | G38: 10.3 | H38: 3.04 | I38: 0.4 | J38: 9.3 | K38: 24.1 | L38: 20 | M38: 0.2 | N38: 0.1 | O38: 19.896 | Q38: 20.12 | R38: 20.15 | S38: 12.764 | T38: 3 | U38: 5.1 | V38: 19.9 | W38: 19.9 | X38: 20 | Y38: 18.6 | Z38: 27.8 | AA38: 5.6 | AB38: 32.6 | AC38: 8 | AD38: 89.2 | AE38: 3.6 | AF38: 13.5 | AG38: 20.9 | AH38: 7.8 | AI38: 20.4 | AJ38: 20.4 | AK38: 20.1 | AL38: 8.4 | AM38: 31.2 | AN38: 0.7 | AO38: 2.5 | AP38: 3.4 | AQ38: 18.5 | AT38: 72.9 | AV38: 68.7 | AW38: 0.1 | AX38: 3.5 | AY38: 10.1 | BA38: 8 | BB38: 5.5 | BC38: 9.9 | BD38: 98.4 | BE38: 95.2 | BF38: 0.6 | BG38: 53.5 | BH38: 90.6 | BI38: 11.8 | BJ38: 7 | BK38: 21.6 | BL38: 2.2 | BM38: 1 | BO38: 2.2 | BP38: 3.6 | BQ38: 1.9 | BR38: 20 | BS38: 8.1 | BT38: 2.2 | BU38: 20.1 | BV38: 1229.35
B39: 16:00 | C39: 13 | D39: 19 | E39: 5.81 | F39: 11.35 | G39: 16.5 | H39: 3.04 | I39: 0.4 | J39: 9.3 | K39: 24.6 | L39: 20 | M39: 0.1 | N39: 0.1 | O39: 19.892 | Q39: 20.26 | R39: 20.24 | S39: 12.729 | T39: 3 | U39: 5.1 | V39: 20 | W39: 20.3 | X39: 20 | Y39: 18.5 | Z39: 27.4 | AA39: 6 | AB39: 39.2 | AC39: 11.1 | AD39: 92.8 | AE39: 1.2 | AF39: 5.9 | AG39: 20.9 | AH39: 8.3 | AI39: 20.4 | AJ39: 20.4 | AK39: 20.1 | AL39: 8.4 | AM39: 25.5 | AO39: 0.3 | AP39: 3.4 | AQ39: 18.5 | AT39: 64.4 | AV39: 48 | AW39: 0.1 | AX39: 3.5 | AY39: 9.2 | BA39: 7.4 | BB39: 5.5 | BC39: 10 | BD39: 90.3 | BE39: 92 | BF39: 0.6 | BG39: 51.9 | BH39: 52.9 | BI39: 8.6 | BJ39: 7.5 | BK39: 24.8 | BL39: 2.2 | BM39: 1 | BO39: 2.2 | BP39: 3.7 | BQ39: 1.9 | BR39: 20 | BS39: 8.1 | BU39: 20.2 | BV39: 1149.021
B40: 16:30 | C40: 14.2 | D40: 19.1 | E40: 5.52 | F40: 11.29 | G40: 10.6 | H40: 3.04 | I40: 0.4 | J40: 9 | K40: 24.2 | L40: 20 | N40: 0.1 | O40: 19.811 | Q40: 20.08 | R40: 20.2 | S40: 12.756 | T40: 3 | U40: 5 | V40: 20 | W40: 20 | X40: 20 | Y40: 18.5 | Z40: 19.9 | AA40: 4.1 | AB40: 36.3 | AC40: 11.6 | AD40: 108.1 | AE40: 1.5 | AF40: 2.4 | AG40: 20.9 | AH40: 8.3 | AI40: 20.4 | AJ40: 20.4 | AK40: 20.1 | AL40: 8.4 | AM40: 13 | AO40: 0.2 | AP40: 3.4 | AQ40: 18.5 | AT40: 42.3 | AV40: 30.8 | AX40: 3.5 | AY40: 5 | BA40: 6.5 | BB40: 5.2 | BC40: 10 | BD40: 71.3 | BE40: 72.1 | BF40: 0.6 | BG40: 22.9 | BH40: 25.1 | BI40: 7.9 | BJ40: 7.8 | BK40: 25.5 | BL40: 2.2 | BM40: 1 | BO40: 2.2 | BP40: 2 | BQ40: 1.9 | BR40: 20 | BS40: 8.2 | BU40: 20.2 | BV40: 988.497
B41: 17:00 | C41: 12.5 | D41: 19 | E41: 5.59 | F41: 11.35 | G41: 10.8 | H41: 3.04 | I41: 0.4 | J41: 9 | K41: 24.3 | L41: 20 | N41: 0.1 | O41: 19.894 | Q41: 20.11 | R41: 20.19 | S41: 12.765 | T41: 3 | U41: 5.2 | V41: 20 | W41: 20 | X41: 20 | Y41: 18.5 | Z41: 18.5 | AA41: 3.3 | AB41: 43.1 | AC41: 14 | AD41: 112.9 | AE41: 1 | AF41: 3 | AG41: 21 | AH41: 8.3 | AI41: 20.4 | AJ41: 20.4 | AK41: 20.1 | AL41: 8.4 | AM41: 7.7 | AP41: 3.4 | AQ41: 18.6 | AT41: 18.2 | AV41: 14.5 | AX41: 3.5 | AY41: 2.8 | BA41: 3 | BB41: 5.5 | BC41: 9.8 | BD41: 86.8 | BE41: 81.1 | BF41: 0.6 | BG41: 10.2 | BH41: 14.9 | BI41: 4.4 | BJ41: 7.5 | BK41: 26.6 | BL41: 2.2 | BM41: 1 | BO41: 2.2 | BP41: 2 | BQ41: 1.9 | BR41: 20 | BS41: 8.2 | BU41: 20.2 | BV41: 946.939
B42: 17:30 | C42: 12.1 | D42: 19.1 | E42: 5.63 | F42: 11.3 | G42: 11.4 | H42: 3.04 | I42: 0.4 | J42: 9 | K42: 24.6 | L42: 20.1 | N42: 0.1 | O42: 19.915 | Q42: 20.11 | R42: 20.21 | S42: 12.732 | T42: 3.1 | U42: 5.2 | V42: 20 | W42: 20.1 | X42: 20 | Y42: 18.5 | Z42: 15.8 | AA42: 2.9 | AB42: 43 | AC42: 12.7 | AD42: 127.1 | AE42: 1.3 | AF42: 1.8 | AG42: 20.9 | AH42: 8.3 | AI42: 20.4 | AJ42: 20.4 | AK42: 20.1 | AL42: 8.4 | AM42: 4.3 | AN42: 0.1 | AP42: 3.4 | AQ42: 18.6 | AT42: 13.3 | AV42: 10.9 | AX42: 3.5 | AY42: 1.5 | BA42: 0.6 | BB42: 5.4 | BC42: 9.9 | BD42: 74.9 | BE42: 76.1 | BF42: 0.6 | BG42: 3.7 | BH42: 4.3 | BI42: 0.6 | BJ42: 9.1 | BK42: 31 | BL42: 3.6 | BM42: 1 | BO42: 2.2 | BP42: 0.5 | BQ42: 1.9 | BR42: 20 | BS42: 8.2 | BU42: 20.2 | BV42: 909.137
B43: 18:00 | C43: 12 | D43: 19.1 | E43: 7.42 | F43: 11.29 | G43: 11.3 | H43: 3.04 | I43: 0.4 | J43: 9 | K43: 24.7 | L43: 20 | O43: 19.912 | Q43: 20.24 | R43: 20.25 | S43: 12.729 | T43: 3 | U43: 5 | V43: 20 | W43: 20.4 | X43: 20 | Y43: 18.5 | Z43: 17.9 | AA43: 2.8 | AB43: 45.6 | AC43: 10 | AD43: 132.3 | AF43: 1.9 | AG43: 20.9 | AH43: 8.3 | AI43: 20.4 | AJ43: 20.4 | AK43: 20.1 | AL43: 8.4 | AM43: 1.3 | AN43: 0.1 | AP43: 3.4 | AQ43: 18.6 | AT43: 4 | AV43: 2.9 | AX43: 3.5 | AY43: 0.3 | BA43: 0.1 | BB43: 5.3 | BC43: 9.9 | BD43: 63.7 | BE43: 66.6 | BF43: 0.6 | BG43: 1.6 | BH43: 1.9 | BJ43: 7.3 | BK43: 27.8 | BL43: 3.7 | BM43: 1 | BO43: 2.2 | BQ43: 1.9 | BR43: 20 | BS43: 8.1 | BU43: 20.2 | BV43: 863.281
B44: 18:30 | C44: 11.5 | D44: 19.1 | E44: 7.48 | F44: 11.3 | G44: 11.2 | H44: 3.04 | I44: 0.4 | J44: 9 | K44: 24.9 | L44: 20 | O44: 19.935 | Q44: 20.2 | R44: 20.25 | S44: 12.659 | T44: 3 | U44: 5 | V44: 20 | W44: 20.3 | X44: 20 | Y44: 18.5 | Z44: 23.9 | AA44: 2.8 | AB44: 50.3 | AC44: 11.9 | AD44: 139.6 | AF44: 0.3 | AG44: 20.9 | AH44: 8.3 | AI44: 20.4 | AJ44: 20.4 | AK44: 20.1 | AL44: 8.5 | AN44: 0.5 | AP44: 3.4 | AQ44: 18.6 | AX44: 3.5 | BB44: 5.2 | BC44: 9.9 | BD44: 50.5 | BE44: 56.5 | BF44: 0.6 | BJ44: 7.5 | BK44: 26.9 | BL44: 3.7 | BM44: 1 | BO44: 2.2 | BQ44: 1.9 | BR44: 20 | BS44: 8.1 | BU44: 20.2 | BV44: 845.364
B45: 19:00 | C45: 11 | D45: 19.1 | E45: 7.36 | F45: 11.36 | G45: 11.6 | H45: 3.04 | I45: 0.4 | J45: 8.9 | K45: 24.8 | L45: 20 | O45: 19.936 | Q45: 20.16 | R45: 20.21 | S45: 12.657 | T45: 3 | U45: 5.2 | V45: 20 | W45: 20.3 | X45: 20 | Y45: 18.5 | Z45: 20.1 | AA45: 2.9 | AB45: 44.9 | AC45: 8.2 | AD45: 121.5 | AG45: 20.9 | AH45: 8.3 | AI45: 20.4 | AJ45: 20.4 | AK45: 20.1 | AL45: 8.5 | AN45: 0.5 | AP45: 3.5 | AQ45: 18.6 | AX45: 3.5 | BB45: 5.4 | BC45: 9.9 | BD45: 34.5 | BE45: 45.1 | BF45: 0.6 | BJ45: 9.4 | BK45: 30.8 | BL45: 3.7 | BM45: 1 | BO45: 2.2 | BQ45: 1.9 | BR45: 20 | BS45: 8.2 | BU45: 20.3 | BV45: 792.823
B46: 19:30 | C46: 12.5 | D46: 19.1 | E46: 7.11 | F46: 11.31 | G46: 19.8 | H46: 3.04 | I46: 0.4 | J46: 9 | K46: 24.5 | L46: 20 | O46: 19.916 | Q46: 20.21 | R46: 20.22 | S46: 12.668 | T46: 3.3 | U46: 5.2 | V46: 20 | W46: 20.2 | X46: 20 | Y46: 18.5 | Z46: 10.6 | AA46: 3.8 | AB46: 38.7 | AC46: 8.1 | AD46: 112.3 | AG46: 20.9 | AH46: 8.3 | AI46: 20.4 | AJ46: 20.4 | AK46: 20.1 | AL46: 8.5 | AN46: 0.7 | AP46: 3.5 | AQ46: 18.6 | AX46: 3.5 | BB46: 5.5 | BC46: 9.9 | BD46: 36.3 | BE46: 44.1 | BF46: 0.6 | BJ46: 8.5 | BK46: 28.6 | BL46: 3.7 | BM46: 1 | BO46: 2.2 | BQ46: 1.9 | BR46: 20 | BS46: 8.2 | BU46: 20.2 | BV46: 776.074
B47: 20:00 | C47: 13 | D47: 19.1 | E47: 8.49 | F47: 11.31 | G47: 20.3 | H47: 3.04 | I47: 0.4 | J47: 8.7 | K47: 24.7 | L47: 20 | O47: 19.864 | Q47: 20.23 | R47: 20.2 | S47: 12.665 | T47: 3.3 | U47: 5.1 | V47: 20 | W47: 20.2 | X47: 20 | Y47: 18.5 | Z47: 7.6 | AA47: 4.4 | AB47: 39.7 | AC47: 7.1 | AD47: 119.2 | AG47: 20.9 | AH47: 8.3 | AI47: 20.4 | AJ47: 20.4 | AK47: 20.1 | AL47: 8.5 | AN47: 1 | AO47: 0.1 | AP47: 3.5 | AQ47: 18.5 | AX47: 3.5 | BB47: 5.2 | BC47: 9.9 | BD47: 38.1 | BE47: 46.2 | BF47: 0.6 | BJ47: 8.1 | BK47: 26.8 | BL47: 3.7 | BM47: 1 | BO47: 2.2 | BQ47: 1.9 | BR47: 20 | BS47: 8.2 | BU47: 20.2 | BV47: 784.399
B48: 20:30 | C48: 13.5 | D48: 19.1 | E48: 6.48 | F48: 11.35 | G48: 20.3 | H48: 3.04 | I48: 0.4 | J48: 9.4 | K48: 24.3 | L48: 20 | O48: 19.888 | Q48: 20.3 | R48: 20.22 | S48: 12.662 | T48: 3.3 | U48: 5.1 | V48: 20 | W48: 20 | X48: 20 | Y48: 18.7 | Z48: 8.1 | AA48: 4.2 | AB48: 44.6 | AC48: 7.1 | AD48: 107.7 | AG48: 20.9 | AH48: 8.3 | AI48: 20.4 | AJ48: 20.4 | AK48: 20.1 | AL48: 8.8 | AN48: 0.7 | AP48: 3.5 | AQ48: 18.5 | AX48: 3.5 | BB48: 5.5 | BC48: 9.9 | BD48: 38.7 | BE48: 40.8 | BF48: 0.6 | BJ48: 8.7 | BK48: 29.9 | BL48: 3.7 | BM48: 1 | BO48: 2.2 | BQ48: 1.9 | BR48: 20 | BS48: 8.1 | BU48: 20.2 | BV48: 776.04
B49: 21:00 | C49: 13.6 | D49: 19.1 | E49: 8.27 | F49: 11.32 | G49: 20.3 | H49: 3.04 | I49: 0.4 | J49: 9.1 | K49: 23.8 | L49: 20 | O49: 19.884 | Q49: 20.25 | R49: 20.25 | S49: 12.652 | T49: 3.3 | U49: 5.2 | V49: 20 | W49: 20.2 | X49: 20 | Y49: 18.9 | Z49: 7.9 | AA49: 4.6 | AB49: 50.9 | AC49: 5.5 | AD49: 101.3 | AG49: 21 | AH49: 8.3 | AI49: 20.4 | AJ49: 20.4 | AK49: 20.1 | AL49: 8.8 | AN49: 0.1 | AP49: 3.5 | AQ49: 18.5 | AX49: 3.5 | BB49: 5.4 | BC49: 9.9 | BD49: 35.1 | BE49: 38.3 | BF49: 0.6 | BJ49: 10.3 | BK49: 28 | BL49: 3.7 | BM49: 1 | BO49: 2.2 | BQ49: 1.9 | BR49: 20 | BS49: 8.2 | BU49: 20.2 | BV49: 769.166
B50: 21:30 | C50: 13.5 | D50: 19.1 | E50: 8.27 | F50: 11.31 | G50: 20.2 | H50: 3.04 | I50: 0.4 | J50: 9.2 | K50: 23.6 | L50: 20 | O50: 19.884 | Q50: 20.24 | R50: 20.25 | S50: 12.614 | T50: 3.3 | U50: 5.2 | V50: 20 | W50: 20.3 | X50: 20 | Y50: 18.9 | Z50: 8.7 | AA50: 6.2 | AB50: 49.2 | AC50: 4.6 | AD50: 78.8 | AG50: 20.9 | AH50: 8.3 | AI50: 20.4 | AJ50: 20.4 | AK50: 20.1 | AL50: 8.8 | AN50: 0.2 | AP50: 3.5 | AQ50: 18.5 | AX50: 3.5 | BB50: 5.3 | BC50: 9.8 | BD50: 22.3 | BE50: 31.6 | BF50: 0.6 | BJ50: 10.2 | BK50: 32.3 | BL50: 3.7 | BM50: 1 | BO50: 2.2 | BQ50: 1.9 | BR50: 20 | BS50: 8.2 | BU50: 20.2 | BV50: 730.708
B51: 22:00 | C51: 13.6 | D51: 19.1 | E51: 8.27 | F51: 11.34 | G51: 17.3 | H51: 3.04 | I51: 0.4 | J51: 9.1 | K51: 23.7 | L51: 20 | O51: 19.886 | Q51: 20.21 | R51: 20.23 | S51: 12.643 | T51: 3.2 | U51: 5.2 | V51: 20 | W51: 20 | X51: 20 | Y51: 18.9 | Z51: 9.9 | AA51: 7.9 | AB51: 40.1 | AC51: 6 | AD51: 79.8 | AG51: 20.9 | AH51: 8.3 | AI51: 20.4 | AJ51: 20.4 | AK51: 20.1 | AL51: 8.8 | AN51: 0.6 | AP51: 3.5 | AQ51: 18.5 | AX51: 3.5 | BB51: 5.3 | BC51: 9.9 | BD51: 25.6 | BE51: 35.6 | BF51: 0.6 | BJ51: 12.7 | BK51: 38.6 | BL51: 3.7 | BM51: 1 | BO51: 2.2 | BQ51: 1.9 | BR51: 20 | BS51: 8.2 | BU51: 20.2 | BV51: 740.319
B52: 22:30 | C52: 13.7 | D52: 19.1 | E52: 8.27 | F52: 11.33 | G52: 16.5 | H52: 3.04 | I52: 0.4 | J52: 9.2 | K52: 23.6 | L52: 20 | O52: 19.888 | Q52: 20.21 | R52: 20.2 | S52: 12.693 | T52: 3.3 | U52: 5.2 | V52: 20 | W52: 20.2 | X52: 20 | Y52: 18.9 | Z52: 6.6 | AA52: 5.2 | AB52: 32.9 | AC52: 5.2 | AD52: 72.5 | AG52: 20.9 | AH52: 8.3 | AI52: 20.4 | AJ52: 20.4 | AK52: 20.1 | AL52: 8.8 | AN52: 0.2 | AP52: 3.5 | AQ52: 18.5 | AX52: 3.5 | BB52: 5.4 | BC52: 9.9 | BD52: 30.7 | BE52: 33.4 | BF52: 0.6 | BJ52: 7.9 | BK52: 21.3 | BL52: 3.7 | BM52: 1 | BO52: 2.2 | BQ52: 1.9 | BR52: 20 | BS52: 8.1 | BU52: 20.2 | BV52: 699.031
B53: 23:00 | C53: 14.2 | D53: 19.1 | E53: 8.27 | F53: 11.29 | G53: 16.6 | H53: 3 | I53: 0.4 | J53: 9 | K53: 23.4 | L53: 20 | O53: 19.888 | Q53: 20.08 | R53: 20.17 | S53: 12.651 | T53: 3.3 | U53: 5.2 | V53: 20 | W53: 20 | X53: 20 | Y53: 18.9 | Z53: 3.8 | AA53: 4 | AB53: 24.8 | AC53: 1.5 | AD53: 57.6 | AG53: 20.9 | AH53: 8.3 | AI53: 20.4 | AJ53: 20.4 | AK53: 20.1 | AL53: 8.8 | AN53: 0.3 | AP53: 3.5 | AQ53: 18.6 | AX53: 3.5 | BB53: 5.5 | BC53: 9.9 | BD53: 18.7 | BE53: 22.2 | BF53: 0.6 | BJ53: 6.4 | BK53: 11.3 | BL53: 3.7 | BM53: 1 | BO53: 2.2 | BQ53: 1.9 | BR53: 20 | BS53: 8.2 | BU53: 20.1 | BV53: 633.649
B54: 23:30 | C54: 14.4 | D54: 19.1 | E54: 8.27 | F54: 11.31 | G54: 16.4 | H54: 3 | I54: 0.4 | J54: 9.1 | K54: 23.1 | L54: 20 | O54: 19.881 | Q54: 20.18 | R54: 20.21 | S54: 12.653 | T54: 3.3 | U54: 5.1 | V54: 19.9 | W54: 19.8 | X54: 20 | Y54: 18.9 | Z54: 2.1 | AA54: 4.8 | AB54: 13 | AC54: 2.1 | AD54: 38.8 | AG54: 20.9 | AH54: 8.3 | AI54: 20.4 | AJ54: 20.4 | AK54: 20.1 | AN54: 0.3 | AP54: 3.5 | AQ54: 18.5 | AX54: 3.5 | BB54: 5.4 | BC54: 10 | BD54: 7.9 | BE54: 11.2 | BF54: 0.6 | BJ54: 5.3 | BK54: 9.2 | BL54: 3.7 | BM54: 1 | BO54: 2.2 | BQ54: 1.9 | BR54: 19.8 | BS54: 8.2 | BU54: 20.1 | BV54: 568.204
B55: 0:00 | C55: 14.4 | D55: 19.1 | E55: 8.27 | F55: 11.31 | G55: 16.5 | H55: 2.96 | I55: 0.4 | J55: 8.9 | K55: 23.4 | L55: 20 | O55: 19.886 | Q55: 20.22 | R55: 20.18 | S55: 12.519 | T55: 3.3 | U55: 5.1 | V55: 20 | W55: 20.2 | X55: 20 | Y55: 18.7 | Z55: 2 | AA55: 3.2 | AB55: 11.4 | AC55: 1.2 | AD55: 12 | AG55: 20.9 | AH55: 8.3 | AI55: 20.4 | AJ55: 20.4 | AK55: 20.1 | AN55: 0.4 | AP55: 3.5 | AQ55: 18.5 | AX55: 3.5 | BB55: 5.5 | BC55: 9.9 | BD55: 4.6 | BE55: 8.6 | BF55: 0.6 | BJ55: 2.1 | BK55: 2.3 | BL55: 3.7 | BM55: 1 | BO55: 2.2 | BQ55: 1.9 | BR55: 20 | BS55: 8.2 | BU55: 20.2 | BV55: 521.945
B56: EJEC MWh | C56: 320.7 | D56: 456.45 | E56: 166.145 | F56: 269.765 | G56: 304 | H56: 72.22 | I56: 5.4 | J56: 204.55 | K56: 556 | L56: 480.05 | M56: 1.85 | N56: 2.5 | O56: 397.313 | P56: 0 | Q56: 483.145 | R56: 485.2 | S56: 307.279 | T56: 72.85 | U56: 122.95 | V56: 479.7 | W56: 232.9 | X56: 479.7 | Y56: 434.55 | Z56: 188.2 | AA56: 82.5 | AB56: 876.2 | AC56: 132.35 | AD56: 1783 | AE56: 228.6 | AF56: 297.05 | AG56: 446.85 | AH56: 192.8 | AI56: 489.6 | AJ56: 489.6 | AK56: 482.4 | AL56: 190.25 | AM56: 593 | AN56: 84.25 | AO56: 95.95 | AP56: 82 | AQ56: 417.05 | AR56: 0 | AS56: 0 | AT56: 1812.05 | AU56: 0 | AV56: 1577.8 | AW56: 0.95 | AX56: 85 | AY56: 117.9 | AZ56: 0 | BA56: 118.95 | BB56: 130.05 | BC56: 237.7 | BD56: 651.4 | BE56: 712.35 | BF56: 14.4 | BG56: 867.9 | BH56: 1088.05 | BI56: 157 | BJ56: 201.65 | BK56: 571 | BL56: 75.05 | BM56: 24 | BN56: 0 | BO56: 52.8 | BP56: 75.85 | BQ56: 38.55 | BR56: 479.9 | BS56: 196.2 | BT56: 97.3 | BU56: 236.45 | BV56: 23107.117
L70: TERMOELÉCTRICA | M70: 2125.46 | N70: 9.1982916 | O70: #FFA975
L71: EÓLICA | M71: 5378.85 | N71: 23.277893 | O71: #B9ACFF
L72: SOLAR | M72: 7036.75 | N72: 30.452739 | O72: #FFD272
L73: HIDROELÉCTRICA | M73: 8566.057 | N73: 37.071076 | O73: #98D2FF

Sheet COGENERACIÓN
B3: martes, 13 de Enero del 2026
B5: CENTRALES DE COGENERACIÓN DEL SEIN
B6: HORA | C6: AGRO INDUSTRIAL PARAMONGA S.A. | D6: AGROAURORA S.A.C. | E6: AGROINDUSTRIAS SAN JACINTO S.A.A. | F6: AGROLMOS SOCIEDAD ANONIMA - AGROLMOS S.A. | G6: BIOENERGIA DEL CHIRA S.A. | H6: CASA GRANDE S.A.A. | I6: GM OPERACIONES S.A.C. | J6: TOTAL COGENERACION
C7: C.T. PARAMONGA | D7: C.T. MAPLE | E7: C.T SAN JACINTO | F7: C.T. AGROLMOS | G7: C.T. CAÑA BRAVA | H7: C.T. CASA GRANDE | I7: C.T. REFINERÍA TALARA | J7: MW
B8: 0:30 | C8: 12.9 | D8: 19.1 | E8: 7.82 | F8: 11.22 | G8: 9.9 | H8: 24.3 | I8: 58.9 | J8: 144.14
B9: 1:00 | C9: 12.9 | D9: 19.1 | E9: 7.34 | F9: 11.22 | G9: 9.1 | H9: 24.1 | I9: 59 | J9: 142.76
B10: 1:30 | C10: 13.8 | D10: 19.1 | E10: 7.2 | F10: 11.24 | G10: 9.8 | H10: 23 | I10: 59 | J10: 143.14
B11: 2:00 | C11: 14 | D11: 19.1 | E11: 7.08 | F11: 11.24 | G11: 9.8 | H11: 23.7 | I11: 59.6 | J11: 144.52
B12: 2:30 | C12: 14.4 | D12: 19.1 | E12: 8.29 | F12: 11.25 | G12: 9.5 | H12: 16.4 | I12: 59.4 | J12: 138.34
B13: 3:00 | C13: 14.5 | D13: 19.1 | E13: 8.21 | F13: 11.21 | G13: 9.8 | H13: 22.7 | I13: 59.3 | J13: 144.82
B14: 3:30 | C14: 14.2 | D14: 18.6 | E14: 8.45 | F14: 10.09 | G14: 9.8 | H14: 22.7 | I14: 59.2 | J14: 143.04
B15: 4:00 | C15: 13 | D15: 18.3 | E15: 7.82 | F15: 11.11 | G15: 9.5 | H15: 22.4 | I15: 59.2 | J15: 141.33
B16: 4:30 | C16: 13.4 | D16: 18.3 | E16: 7.89 | F16: 11.11 | G16: 10.6 | H16: 22.7 | I16: 58.9 | J16: 142.9
B17: 5:00 | C17: 13.5 | D17: 18.9 | E17: 8.11 | F17: 11.07 | G17: 10 | H17: 22.4 | I17: 57.9 | J17: 141.88
B18: 5:30 | C18: 14 | D18: 18.8 | E18: 8.02 | F18: 11.07 | G18: 9.8 | H18: 22.1 | I18: 58.4 | J18: 142.19
B19: 6:00 | C19: 14 | D19: 19.4 | E19: 8.07 | F19: 11.09 | G19: 9.9 | H19: 17.4 | I19: 59.4 | J19: 139.26
... B56: EJEC MWh | C56: 320.7 | D56: 456.45 | E56: 166.145 | F56: 269.765 | G56: 204.55 | H56: 556 | I56: 1414.35 | J56: 3387.96

Sheet EVO_PRO_ENE
B3: jueves, 1 de Enero del 2026 - martes, 13 de Enero del 2026
B5: EVOLUCIÓN DE LA PRODUCCIÓN DE LA ENERGÍA DIARIA DE LOS INTEGRANTES DEL COES (MWh)
B6: EMPRESA | C6: CENTRAL | D6: UNIDAD | E6: TIPO | F6: Enero
F7: 1 | G7: 2 | H7: 3 | I7: 4 | J7: 5 | K7: 6 | L7: 7 | M7: 8 | N7: 9 | O7: 10 | P7: 11 | Q7: 12 | R7: 13 | S7: TOTAL
B8: AGRO INDUSTRIAL PARAMONGA S.A. | C8: C.T. PARAMONGA | D8: TV-01 | E8: TERMOELÉCTRICA | J8: 23.1 | K8: 288.35 | L8: 347.35 | M8: 354.6 | N8: 348.7 | O8: 277.95 | P8: 333.75 | Q8: 345 | R8: 320.7 | S8: 2639.5
B9: AGROAURORA S.A.C. | C9: C.T. MAPLE ETANOL | D9: TV | E9: TERMOELÉCTRICA | G9: 298.1 | H9: 441.7 | I9: 450.5 | J9: 452.25 | K9: 453 | L9: 456.6 | M9: 451.65 | N9: 456.4 | O9: 453.35 | P9: 423 | Q9: 433.15 | R9: 456.45 | S9: 5226.15
B10: AGROINDUSTRIAS SAN JACINTO S.A.A. | C10: C.T. SAN JACINTO | D10: CENTRAL | E10: TERMOELÉCTRICA | J10: 45.7 | K10: 185.4 | L10: 192.15 | M10: 203.523 | N10: 198.2885 | O10: 198.3 | P10: 180.3175 | Q10: 185.715 | R10: 166.145 | S10: 1555.539
B11: AGROLMOS SOCIEDAD ANONIMA - AGROLMOS S.A. | C11: C.T. AGROLMOS | D11: CENTRAL | E11: TERMOELÉCTRICA | F11: 220.25 | G11: 157.25 | H11: 123.9 | I11: 147.35 | J11: 48.81 | K11: 173.77 | L11: 260.65 | M11: 267.71815 | N11: 267.4404 | O11: 264.75 | P11: 270.3 | Q11: 267.36 | R11: 269.765 | S11: 2739.3135
B12: ANDEAN POWER S.A.C. | C12: C.H.CARHUAC | D12: CENTRAL | E12: HIDROELÉCTRICA | F12: 370.85 | G12: 357.7 | H12: 393.65 | I12: 353 | J12: 369.35 | K12: 261 | L12: 322.7 | M12: 266.15 | N12: 252.15 | O12: 279.85 | P12: 242.75 | Q12: 249.2 | R12: 304 | S12: 4022.35
B13: ASOCIACIÓN SANTA LUCIA DE CHACAS | C13: C.H. HUALLIN | D13: CENTRAL | E13: HIDROELÉCTRICA | F13: 61.85 | G13: 57.2 | H13: 59.15 | I13: 58.35 | J13: 72.1 | K13: 62.2 | L13: 61.05 | M13: 61.35 | N13: 61.2 | O13: 67.55 | P13: 48 | Q13: 71.66 | R13: 72.22 | S13: 813.88
B14: ATRIA ENERGIA S.A.C. | C14: C.H. PURMACANA | D14: CENTRAL | E14: HIDROELÉCTRICA | F14: 9.6 | G14: 2.6 | K14: 5.5 | L14: 9.6 | M14: 7.8 | N14: 2.75 | R14: 5.4 | S14: 43.25
B15: BIOENERGIA DEL CHIRA S.A. | C15: C.T. CAÑA BRAVA | D15: CENTRAL | E15: TERMOELÉCTRICA | F15: 228.5 | G15: 218.65 | H15: 231.8 | I15: 235.4 | J15: 244.15 | K15: 249.3 | L15: 230.7 | M15: 212.2 | N15: 80.4 | P15: 43.1 | Q15: 224.35 | R15: 204.55 | S15: 2403.1
B16: CASA GRANDE S.A.A. | C16: C.T. CASA GRANDE | D16: TV3 | E16: TERMOELÉCTRICA | J16: 84.46 | K16: 373.65 | L16: 469.25 | M16: 520.65 | N16: 526.7 | O16: 544.7 | P16: 529.9 | Q16: 430.525 | R16: 556 | S16: 4035.835
B17: CELARIS ENERGY S.A. | C17: C.H. MANTA I | D17: CENTRAL | E17: HIDROELÉCTRICA | F17: 136.2 | G17: 166.55 | H17: 197.25 | I17: 234.5 | J17: 312.35 | K17: 341.3 | L17: 315.85 | M17: 295.15 | N17: 374.65 | O17: 479.45 | P17: 479.7 | Q17: 474.9 | R17: 480.05 | S17: 4287.9
B18: CELEPSA | C18: C.H. EL PLATANAL | D18: CENTRAL | E18: HIDROELÉCTRICA | F18: 1301 | G18: 1357.25 | H18: 1408.15 | I18: 1458.7 | J18: 1657.55 | K18: 2586.9 | L18: 2338.4 | M18: 2235.65 | N18: 2776.735 | O18: 4327.35 | P18: 4534.8 | Q18: 4708.6 | R18: 5314 | S18: 36005.085
B19: CELEPSA RENOVABLES S.R.L. | C19: C.H. MARAÑON | D19: CENTRAL | E19: HIDROELÉCTRICA | F19: 449.2 | G19: 451.55 | H19: 450 | I19: 451.5 | J19: 423.6 | K19: 417.1 | L19: 446.9 | M19: 451.7 | N19: 452.45 | O19: 449.75 | P19: 446.05 | Q19: 438.3 | R19: 361.13256 | S19: 5689.2326
B20: CENTRALES SANTA ROSA S.A.C. | C20: C.H. SANTA ROSA I | D20: CENTRAL | E20: HIDROELÉCTRICA | S20: 0
B21: CENTRALES SANTA ROSA S.A.C. | C21: C.H. SANTA ROSA II | D21: CENTRAL | E21: HIDROELÉCTRICA | S21: 0
B22: CHINANGO S.A.C. | C22: C.H. CHIMAY | D22: CENTRAL | E22: HIDROELÉCTRICA | F22: 3145.1 | G22: 3424.9 | H22: 3473.65 | I22: 3322.75 | J22: 3428.4 | K22: 2388.7 | L22: 3452.15 | M22: 3170 | N22: 2192.15 | O22: 1670.4 | P22: 2062 | Q22: 2651.0273 | S22: 34381.227
B23: CHINANGO S.A.C. | C23: C.H. YANANGO | D23: CENTRAL | E23: HIDROELÉCTRICA | F23: 547.85 | G23: 891.75 | H23: 830.15 | I23: 682.4 | J23: 710.05 | K23: 959.05 | L23: 802.15 | M23: 713.25 | N23: 621.1 | O23: 573.75 | P23: 1005.9 | Q23: 980.73226 | R23: 274.55 | S23: 9592.6823
B24: COENERGY S.A.C. | C24: C.S. COENERGY | D24: CENTRAL | E24: SOLAR | F24: 2.8215 | G24: 2.68361 | H24: 2.838605 | I24: 2.942055 | J24: 2.253185 | K24: 2.900725 | L24: 3.15 | M24: 3.085705 | N24: 2.34472 | O24: 2.6 | P24: 2.55 | Q24: 2.45 | R24: 1.85 | S24: 34.470105
B25: COLCA SOLAR S.A.C. | C25: C.S. YARUCAYA | D25: CENTRAL | E25: SOLAR | F25: 7 | G25: 6.75 | H25: 5.25 | I25: 6.2 | J25: 3.85 | K25: 5.1 | L25: 7.1 | M25: 7.35 | N25: 2.6 | O25: 3.55 | P25: 5 | Q25: 4.45 | R25: 2.5 | S25: 66.7
B26: EGASA | C26: C.H. CHARCANI III | D26: CENTRAL | E26: HIDROELÉCTRICA | F26: 165.25 | G26: 167.7 | H26: 167.5 | I26: 167.3 | J26: 167 | K26: 166.65 | L26: 167.15 | M26: 165.55 | N26: 166.6 | O26: 166.8 | P26: 167.1 | Q26: 167.65 | R26: 168.55 | S26: 2170.8
B27: EGASA | C27: C.H. CHARCANI IV | D27: CENTRAL | E27: HIDROELÉCTRICA | F27: 285.7 | G27: 321.65 | H27: 321.2 | I27: 325.15 | J27: 324.3 | K27: 322.1 | L27: 319.15 | M27: 315.25 | N27: 320.05 | O27: 317.85 | P27: 319.65 | Q27: 318.05 | R27: 324.8 | S27: 4134.9
B28: EGASA | C28: C.H. CHARCANI V | D28: CENTRAL | E28: HIDROELÉCTRICA | F28: 2018.9 | G28: 2009.7 | H28: 2028.55 | I28: 1993.55 | J28: 2013.35 | K28: 2013.6 | L28: 2013.05 | M28: 2005.2 | N28: 2014.8 | O28: 2020.2 | P28: 2009.75 | Q28: 2013.35 | R28: 2008.55 | S28: 26162.55
B29: EGASA | C29: C.H. CHARCANI VI | D29: CENTRAL | E29: HIDROELÉCTRICA | S29: 0
B30: EGASA | C30: C.T. CHILINA DIESEL | D30: CENTRAL | E30: TERMOELÉCTRICA | S30: 0
B31: EGASA | C31: C.T. CHILINA DIESEL | D31: TG | E31: TERMOELÉCTRICA | S31: 0
B32: EGASA | C32: C.T. MOLLENDO DIESEL | D32: CENTRAL | E32: TERMOELÉCTRICA | K32: 19.8 | S32: 19.8
B33: EGEJUNIN | C33: C.H. HUASAHUASI I | D33: CENTRAL | E33: HIDROELÉCTRICA | F33: 210.95 | G33: 341.8 | H33: 377.7 | I33: 282.2 | J33: 432.8 | K33: 444.3 | L33: 330.65 | M33: 285.75 | N33: 275.35 | O33: 399.9 | P33: 475.2 | Q33: 475.25 | R33: 397.313 | S33: 4729.163
B34: EGEJUNIN | C34: C.H. RUNATULLO II | D34: CENTRAL | E34: HIDROELÉCTRICA | F34: 298.85 | G34: 459.85 | H34: 482.4 | I34: 475.55 | J34: 483.15 | K34: 483.75 | L34: 484.45 | M34: 470.4 | N34: 449.95 | O34: 475.65 | P34: 481.6 | Q34: 483.25 | R34: 483.145 | S34: 6011.995
B35: EGEJUNIN | C35: C.H. RUNATULLO III | D35: CENTRAL | E35: HIDROELÉCTRICA | F35: 403.8 | G35: 472.85 | H35: 485.05 | I35: 485.85 | J35: 485.15 | K35: 484.7 | L35: 485.15 | M35: 485.4 | N35: 484.95 | O35: 485.4 | P35: 484.9 | Q35: 484.75 | R35: 485.2 | S35: 6213.15
B36: EGEJUNIN | C36: C.H. SANTA CRUZ I | D36: CENTRAL | E36: HIDROELÉCTRICA | F36: 180.65 | G36: 175.25 | H36: 172.3 | I36: 164.1 | J36: 183.2 | K36: 176.45 | L36: 167.05 | M36: 156.85 | N36: 186.05 | O36: 214.15 | P36: 298.55 | Q36: 191.35 | R36: 307.279 | S36: 2573.229
B37: EGEMSA | C37: C.H. MACHUPICCHU | D37: CENTRAL | E37: HIDROELÉCTRICA | F37: 3996.35 | G37: 3994.6 | H37: 3956.45 | I37: 3921.95 | J37: 4006.65 | K37: 4000.8 | L37: 3988.1 | M37: 4007.6 | N37: 3985.95 | O37: 3990.85 | P37: 3507.85 | Q37: 3990.75 | R37: 3990.55 | S37: 51338.45
B38: EGESUR | C38: C.H. ARICOTA I | D38: CENTRAL | E38: HIDROELÉCTRICA | F38: 190.9 | G38: 191.4 | H38: 184 | I38: 185.9 | J38: 189.55 | K38: 190.25 | L38: 189.5 | M38: 189.65 | N38: 188.1 | O38: 191.7 | P38: 190.2 | Q38: 187.948 | R38: 189.25 | S38: 2458.348
B39: EGESUR | C39: C.H. ARICOTA II | D39: CENTRAL | E39: HIDROELÉCTRICA | F39: 127.7 | G39: 127.5 | H39: 125.45 | I39: 130.9 | J39: 133.85 | K39: 131.95 | L39: 132.4 | M39: 134.55 | N39: 130.8 | O39: 117.05 | P39: 130.4 | Q39: 131.17 | R39: 132.9 | S39: 1686.62
B40: EGESUR | C40: C.T. INDEPENDENCIA | D40: CENTRAL | E40: TERMOELÉCTRICA | G40: 221.7 | H40: 244.2 | I40: 137.45 | J40: 355.5 | K40: 276.75 | L40: 225.45 | M40: 441.7 | N40: 520.5 | O40: 438.65 | P40: 78.1 | Q40: 99.95 | R40: 338.85 | S40: 3378.8
B41: ELECTRICA YANAPAMPA SAC | C41: C.H. YANAPAMPA | D41: CENTRAL | E41: HIDROELÉCTRICA | F41: 57.8 | G41: 57.9 | H41: 58.65 | I41: 59.2 | J41: 69.85 | K41: 78.5 | L41: 79.15 | M41: 79.2 | N41: 78.6 | O41: 73.9 | P41: 79.05 | Q41: 75.65 | R41: 72.85 | S41: 920.3
B42: ELECTROPERU | C42: C.H. MANTARO | D42: CENTRAL | E42: HIDROELÉCTRICA | F42: 11988.45 | G42: 11691.4 | H42: 10017.15 | I42: 11412.95 | J42: 13167.35 | K42: 14797.8 | L42: 14925.8 | M42: 14903.85 | N42: 14800.8 | O42: 14560.545 | P42: 14733.55 | Q42: 15005.35 | R42: 15053.75 | S42: 177058.74
B43: ELECTROPERU | C43: C.H. RESTITUCION | D43: CENTRAL | E43: HIDROELÉCTRICA | F43: 4007.1 | G43: 3956.35 | H43: 3198.35 | I43: 3717.55 | J43: 4444.45 | K43: 5065.5 | L43: 5115.65 | M43: 5108 | N43: 5080.75 | O43: 4966.585 | P43: 5050.9 | Q43: 5129.4 | R43: 5155.95 | S43: 59996.535
B44: ELECTROPERU | C44: C.T. TUMBES | D44: MAK1 | E44: TERMOELÉCTRICA | S44: 0
B45: ELECTROPERU | C45: C.T. TUMBES | D45: MAK2 | E45: TERMOELÉCTRICA | S45: 0
B46: EMPRESA DE GENERACION ELECTRICA CANCHAYLLO SAC | C46: C.H. CANCHAYLLO | D46: CENTRAL | E46: HIDROELÉCTRICA | F46: 99.65 | G46: 99.6 | H46: 101.4 | I46: 101.15 | J46: 103.25 | K46: 108.2 | L46: 106.35 | M46: 104.8 | N46: 110.1 | O46: 114.5 | P46: 114.35 | Q46: 120.3 | R46: 122.95 | S46: 1406.6
B47: EMPRESA DE GENERACION ELECTRICA RIO BAÑOS S.A.C. | C47: C.H. RUCUY | D47: CENTRAL | E47: HIDROELÉCTRICA | F47: 239.95 | G47: 239.85 | H47: 239.7 | I47: 305.2 | J47: 461.15 | K47: 457.75 | L47: 433.4 | M47: 426.8 | N47: 433.1 | O47: 479.9 | P47: 479.9 | Q47: 479.35 | R47: 479.7 | S47: 5155.75
B48: EMPRESA DE GENERACION ELECTRICA SANTA ANA S.A.C. | C48: C.H. RENOVANDES H1 | D48: CENTRAL | E48: HIDROELÉCTRICA | F48: 489 | G48: 485.85 | H48: 489.55 | I48: 488.65 | J48: 325.05 | K48: 494.45 | L48: 489.65 | M48: 487.65 | N48: 490.95 | O48: 370.3 | P48: 489.9 | Q48: 400.05 | R48: 232.9 | S48: 5733.95
B49: EMPRESA DE GENERACION HUALLAGA | C49: C.H. CHAGLLA | D49: CENTRAL | E49: HIDROELÉCTRICA | F49: 4898.3 | G49: 4173.7 | H49: 7085.2 | I49: 5915.4 | J49: 8441.5 | K49: 11036.15 | L49: 10608.4 | M49: 4797.1 | N49: 6698.465 | O49: 8490.3 | P49: 5933.95 | Q49: 9030.35 | R49: 10988 | S49: 98096.815
B50: EMPRESA DE GENERACION HUALLAGA | C50: P.C.H. CHAGLLA | D50: CENTRAL | E50: HIDROELÉCTRICA | F50: 156 | G50: 156 | H50: 154.4 | I50: 156 | J50: 156 | K50: 155.95 | L50: 156 | M50: 156 | N50: 156.18 | O50: 156 | P50: 156 | Q50: 156 | R50: 156 | S50: 2026.53
B51: EMPRESA DE GENERACION HUANZA | C51: C.H. HUANZA | D51: CENTRAL | E51: HIDROELÉCTRICA | F51: 1447.2 | G51: 1399.65 | H51: 1612.75 | I51: 1385 | J51: 1353.15 | K51: 895.65 | L51: 1141.45 | M51: 985.45 | N51: 873.8 | O51: 728.25 | P51: 599.45 | Q51: 597.1 | R51: 855.4 | S51: 13874.3
B52: EMPRESA ELECTRICA AGUA AZUL | C52: C.H. POTRERO | D52: CENTRAL | E52: HIDROELÉCTRICA | F52: 193.65 | G52: 240.1 | H52: 472.8 | I52: 480 | J52: 479.55 | K52: 480 | L52: 480 | M52: 478.9 | N52: 477.85 | O52: 475.85 | P52: 478.25 | Q52: 479.9 | R52: 479.7 | S52: 5696.55
B53: EMPRESA ELECTRICA RIO DOBLE | C53: C.H. LAS PIZARRAS | D53: CENTRAL | E53: HIDROELÉCTRICA | F53: 268.4 | G53: 307.25 | H53: 419.75 | I53: 436.4 | J53: 457.25 | K53: 456.3 | L53: 457.5 | M53: 443.45 | N53: 454.15 | O53: 451.35 | P53: 446.15 | Q53: 445.7 | R53: 434.55 | S53: 5478.2
B54: ENEL GENERACION PIURA S.A. | C54: C.T. MALACAS 1 | D54: TG6 | E54: TERMOELÉCTRICA | F54: 1.8 | G54: 1064.55 | H54: 866.95 | I54: 825.95 | J54: 781.55 | K54: 787.45 | L54: 740.85 | M54: 1085.2 | N54: 961.25 | O54: 783.4 | P54: 1096 | Q54: 1092.5 | R54: 1086.15 | S54: 11173.6
B55: ENEL GENERACION PIURA S.A. | C55: C.T. MALACAS 2 | D55: TG4 | E55: TERMOELÉCTRICA | S55: 0
B56: ENEL GENERACION PIURA S.A. | C56: C.T. RF DE GENERACION TALARA | D56: TG5 | E56: TERMOELÉCTRICA | S56: 0
B57: ENERGÍA EÓLICA S.A. | C57: C.E. CUPISNIQUE | D57: CENTRAL | E57: EÓLICA | F57: 1035.5 | G57: 1197.75 | H57: 764.1 | I57: 624.65 | J57: 596.8 | K57: 870.85 | L57: 926.35 | M57: 977.55 | N57: 97.4 | O57: 255.95 | P57: 785.35 | Q57: 545.05 | R57: 188.2 | S57: 8865.5
B58: ENERGÍA EÓLICA S.A. | C58: C.E. TALARA | D58: CENTRAL | E58: EÓLICA | F58: 504 | G58: 548.6 | H58: 343.75 | I58: 153.75 | J58: 279.15 | K58: 329.1 | L58: 288.05 | M58: 393.4 | N58: 150.45 | O58: 192.1 | P58: 124.6 | Q58: 97.95 | R58: 82.5 | S58: 3487.4
B59: ENERGIA RENOVABLE DEL SUR S.A. | C59: C.E. SAN JUAN | D59: CENTRAL | E59: EÓLICA | F59: 1718.35 | G59: 2119.55 | H59: 2280.25 | I59: 1748.55 | J59: 1562.8 | K59: 872.85 | L59: 1299.35 | M59: 2616.3 | N59: 1244.85 | O59: 1802.9 | P59: 1440.4 | Q59: 2341.9 | R59: 876.2 | S59: 21924.25
B60: ENGIE ENERGIA PERU S.A.A. | C60: C.E. PUNTA LOMITAS | D60: PL-BL1 | E60: EÓLICA | F60: 1128.25 | G60: 1101.05 | H60: 1310.75 | I60: 1056.35 | J60: 831.65 | K60: 648.05 | L60: 644.4 | M60: 1421.2 | N60: 643 | O60: 900.5 | P60: 1256.55 | Q60: 1733.55 | R60: 658.45 | S60: 13333.75
B61: ENGIE ENERGIA PERU S.A.A. | C61: C.E. PUNTA LOMITAS | D61: PL-BL2 | E61: EÓLICA | F61: 1351.05 | G61: 1471.665 | H61: 1787.6 | I61: 1527.55 | J61: 1216.15 | K61: 931 | L61: 1028.25 | M61: 1787.7 | N61: 973.4 | O61: 1253.85 | P61: 1686.35 | Q61: 2236.6 | R61: 1124.55 | S61: 18375.715
B62: ENGIE ENERGIA PERU S.A.A. | C62: C.E. PUNTA LOMITAS_EXP | D62: PUN LOM_EXP-BL1 | E62: EÓLICA | F62: 134.15 | G62: 130.85 | H62: 175.95 | I62: 146.85 | J62: 96.55 | K62: 57.55 | L62: 50.35 | M62: 180.75 | N62: 66.79545 | O62: 93.9 | P62: 139.05 | Q62: 224.2 | R62: 83.5 | S62: 1580.4454
B63: ENGIE ENERGIA PERU S.A.A. | C63: C.E. PUNTA LOMITAS_EXP | D63: PUN LOM_EXP-BL2 | E63: EÓLICA | F63: 94.4 | G63: 72.9 | H63: 88.35 | I63: 87.9 | J63: 50.85 | K63: 33.95 | L63: 47.05 | M63: 139.45 | N63: 46.2901 | O63: 68.4 | P63: 96.15 | Q63: 166.55 | R63: 48.85 | S63: 1041.0901
B64: ENGIE ENERGIA PERU S.A.A. | C64: C.H. QUITARACSA | D64: CENTRAL | E64: HIDROELÉCTRICA | F64: 470.05 | H64: 127.8 | I64: 115.35 | J64: 176.45 | K64: 119.7 | L64: 151.4 | M64: 117.75 | N64: 136.35 | P64: 339.55 | R64: 433.3 | S64: 2187.7
B65: ENGIE ENERGIA PERU S.A.A. | C65: C.H. YUNCAN | D65: CENTRAL | E65: HIDROELÉCTRICA | F65: 3058.85 | G65: 2752.2 | H65: 2960.4 | I65: 3055.7 | J65: 3051.15 | K65: 3068.55 | L65: 3052.4 | M65: 2654.3 | N65: 2720.385 | O65: 2802.35 | P65: 3051.6 | Q65: 3058.75 | R65: 2595.1 | S65: 37881.735
B66: ENGIE ENERGIA PERU S.A.A. | C66: C.S. INTIPAMPA | D66: CENTRAL | E66: SOLAR | F66: 388.6 | G66: 386.95 | H66: 344.9 | I66: 283.6 | J66: 336.3 | K66: 404.15 | L66: 412.7 | M66: 340.7 | N66: 366.3 | O66: 217.05 | P66: 159.2 | Q66: 251.75 | R66: 228.6 | S66: 4120.8
B67: ENGIE ENERGIA PERU S.A.A. | C67: C.S. INTIPAMPA EXPANSIÓN | D67: CENTRAL | E67: SOLAR | F67: 511.95 | G67: 504.21 | H67: 462.215 | I67: 378.565 | J67: 440.645 | K67: 531.19 | L67: 506.15 | M67: 447.04 | N67: 406.445 | O67: 293.65 | P67: 235.2 | Q67: 350.55 | R67: 297.05 | S67: 5364.86
B68: ENGIE ENERGIA PERU S.A.A. | C68: C.T. CHILCA 1 | D68: TG1 | E68: TERMOELÉCTRICA | F68: 2656.15 | G68: 3781.15 | H68: 3784.2 | I68: 3651.8 | J68: 3861.85 | K68: 3841.55 | L68: 3729.4 | M68: 3827.2 | N68: 3854.34 | O68: 3913.65 | P68: 3851.2 | Q68: 3893 | R68: 3830.95 | S68: 48476.44
B69: ENGIE ENERGIA PERU S.A.A. | C69: C.T. CHILCA 1 | D69: TG2 | E69: TERMOELÉCTRICA | F69: 2646.75 | G69: 3767.2 | H69: 3764.75 | I69: 3634.4 | J69: 3848.55 | K69: 3813.7 | L69: 3718.5 | M69: 3802.35 | N69: 3834.085 | O69: 3884.6 | P69: 3826.8 | Q69: 3868.7 | R69: 3811.15 | S69: 48221.535
B70: ENGIE ENERGIA PERU S.A.A. | C70: C.T. CHILCA 1 | D70: TG3 | E70: TERMOELÉCTRICA | F70: 2727.65 | G70: 3852 | H70: 3947.75 | I70: 3807.3 | J70: 4032.6 | K70: 4154.55 | L70: 3829.35 | M70: 4036.75 | N70: 4012.43 | O70: 4050.95 | P70: 4015.8 | Q70: 4048.6 | R70: 3863.3 | S70: 50379.03
B71: ENGIE ENERGIA PERU S.A.A. | C71: C.T. CHILCA 1 | D71: TV | E71: TERMOELÉCTRICA | F71: 4724.05 | G71: 5831.9 | H71: 5861.95 | I71: 5727.75 | J71: 5979.1 | K71: 5974.25 | L71: 5791.2 | M71: 5936.05 | N71: 5936.865 | O71: 5946.5 | P71: 5887.75 | Q71: 5943.3 | R71: 5886.65 | S71: 75427.315
B72: ENGIE ENERGIA PERU S.A.A. | C72: C.T. CHILCA 2 | D72: TG41 | E72: TERMOELÉCTRICA | H72: 13.8 | I72: 1134.95 | J72: 261.15 | L72: 101.55 | M72: 980.2 | N72: 1363.37 | O72: 1745.9 | P72: 1649.4 | Q72: 1715.95 | R72: 1735.35 | S72: 10701.62
B73: ENGIE ENERGIA PERU S.A.A. | C73: C.T. CHILCA 2 | D73: TV42 | E73: TERMOELÉCTRICA | I73: 477.7 | M73: 23.7 | N73: 617.23 | O73: 851.15 | P73: 826.7 | Q73: 844 | R73: 848.25 | S73: 4488.73
B74: ENGIE ENERGIA PERU S.A.A. | C74: C.T. NEPI | D74: TG41 | E74: TERMOELÉCTRICA | S74: 0
B75: ENGIE ENERGIA PERU S.A.A. | C75: C.T. NEPI | D75: TG42 | E75: TERMOELÉCTRICA | S75: 0
B76: ENGIE ENERGIA PERU S.A.A. | C76: C.T. NEPI | D76: TG43 | E76: TERMOELÉCTRICA | S76: 0
B77: ENGIE ENERGIA PERU S.A.A. | C77: C.T. RF PLANTA ILO | D77: TG1 | E77: TERMOELÉCTRICA | S77: 0
B78: ENGIE ENERGIA PERU S.A.A. | C78: C.T. RF PLANTA ILO | D78: TG2 | E78: TERMOELÉCTRICA | S78: 0
B79: ENGIE ENERGIA PERU S.A.A. | C79: C.T. RF PLANTA ILO | D79: TG3 | E79: TERMOELÉCTRICA | S79: 0
B80: FENIX POWER PERÚ | C80: C.T. FENIX | D80: GT11 | E80: TERMOELÉCTRICA | F80: 4314.25 | G80: 4331.05 | H80: 4325.05 | I80: 4333.9 | J80: 4320.55 | K80: 4314.15 | L80: 4323.2 | M80: 4325 | N80: 4328.15 | O80: 4265.1 | P80: 4069.95 | Q80: 4198.658 | R80: 3869.35 | S80: 55318.358
B81: FENIX POWER PERÚ | C81: C.T. FENIX | D81: GT12 | E81: TERMOELÉCTRICA | F81: 4326.75 | G81: 4343.7 | H81: 4336.55 | I81: 4345.25 | J81: 4332.75 | K81: 4327.7 | L81: 4335 | M81: 4337.95 | N81: 4336.75 | O81: 4275.5 | P81: 4077.45 | Q81: 4210.2817 | R81: 3879.25 | S81: 55464.882
B82: FENIX POWER PERÚ | C82: C.T. FENIX | D82: TV10 | E82: TERMOELÉCTRICA | F82: 4401.15 | G82: 4412.95 | H82: 4418.6 | I82: 4422.95 | J82: 4416.3 | K82: 4409.95 | L82: 4415 | M82: 4419 | N82: 4422.75 | O82: 4390.65 | P82: 4283.5 | Q82: 4364.4452 | R82: 4166.5 | S82: 56943.745
B83: GENERACIÓN ANDINA S.A.C. | C83: C.H. 8 DE AGOSTO | D83: CENTRAL | E83: HIDROELÉCTRICA | F83: 458.95 | G83: 413.75 | H83: 494.9 | I83: 494.05 | J83: 502.2 | K83: 489.2 | L83: 415.1 | M83: 446.25 | N83: 502.9 | O83: 427.95 | P83: 501.72 | Q83: 501.67384 | R83: 446.85 | S83: 6095.4938
B84: GENERACIÓN ANDINA S.A.C. | C84: C.H. EL CARMEN | D84: CENTRAL | E84: HIDROELÉCTRICA | F84: 123.55 | G84: 127.35 | H84: 168.5 | I84: 123.45 | J84: 178.5 | K84: 153.95 | L84: 116 | M84: 108.2 | N84: 147 | O84: 185.3 | P84: 180.065 | Q84: 185.16078 | R84: 192.8 | S84: 1989.8258
B85: GENERADORA DE ENERGÍA DEL PERÚ | C85: C.H. ÁNGEL I | D85: CENTRAL | E85: HIDROELÉCTRICA | F85: 489.6 | G85: 489.6 | H85: 489.6 | I85: 428.4 | J85: 489.6 | K85: 489.6 | L85: 489.6 | M85: 489.6 | N85: 489.6 | O85: 489.6 | P85: 448.8 | Q85: 489.6 | R85: 489.6 | S85: 6262.8
B86: GENERADORA DE ENERGÍA DEL PERÚ | C86: C.H. ÁNGEL II | D86: CENTRAL | E86: HIDROELÉCTRICA | F86: 489.6 | G86: 489.6 | H86: 489.6 | I86: 459 | J86: 489.6 | K86: 489.6 | L86: 489.6 | M86: 489.6 | N86: 489.6 | O86: 489.6 | P86: 453.9 | Q86: 489.6 | R86: 489.6 | S86: 6298.5
B87: GENERADORA DE ENERGÍA DEL PERÚ | C87: C.H. ÁNGEL III | D87: CENTRAL | E87: HIDROELÉCTRICA | F87: 481.65 | G87: 482.4 | H87: 482.4 | I87: 427.4 | J87: 482.3 | K87: 482.4 | L87: 477.2 | M87: 482.4 | N87: 481.65 | O87: 482.4 | P87: 430.45 | Q87: 482.4 | R87: 482.4 | S87: 6157.45
B88: GENERADORA DE ENERGÍA DEL PERÚ | C88: C.H. LA JOYA | D88: CENTRAL | E88: HIDROELÉCTRICA | F88: 165.1 | G88: 190.5 | H88: 198.1 | I88: 181.05 | J88: 168.3 | K88: 205.95 | L88: 203.1 | M88: 197.3 | N88: 165.1 | O88: 203.35 | P88: 204.95 | Q88: 203.9 | R88: 190.25 | S88: 2476.95
B89: GM OPERACIONES S.A.C. | C89: CT REFINERIA TALARA | D89: TV1 REF TALARA | E89: TERMOELÉCTRICA | F89: 657.55 | G89: 310.4 | O89: 16.85 | P89: 609.40603 | Q89: 561.05 | R89: 642 | S89: 2797.256
B90: GM OPERACIONES S.A.C. | C90: CT REFINERIA TALARA | D90: TV2 REF TALARA | E90: TERMOELÉCTRICA | F90: 818.85 | G90: 343.25 | O90: 150.7 | P90: 776.80896 | Q90: 366.75 | R90: 772.35 | S90: 3228.709
B91: GR CORTARRAMA SOCIEDAD ANONIMA CERRADA | C91: C.S. MATARANI | D91: C.S. MATARANI | E91: SOLAR | F91: 835.55 | G91: 710.3 | H91: 835.6 | I91: 779.35 | J91: 842.05 | K91: 840.45 | L91: 831.65 | M91: 764.05 | N91: 829.1 | O91: 779.6 | P91: 799.3 | Q91: 721.25 | R91: 593 | S91: 10161.25
B92: GR PAINO SOCIEDAD ANONIMA CERRADA | C92: C.E. HUAMBOS | D92: CENTRAL | E92: EÓLICA | F92: 185.65 | G92: 20.1 | H92: 141.25 | I92: 110.55 | J92: 87.85 | K92: 65.8 | L92: 74.75 | M92: 87.4 | N92: 113.85 | O92: 32.4 | P92: 9.85 | Q92: 58.2 | R92: 84.25 | S92: 1071.9
B93: GR TARUCA SOCIEDAD ANONIMA CERRADA | C93: C.E. DUNA | D93: CENTRAL | E93: EÓLICA | F93: 216.3 | G93: 39.1 | H93: 155.35 | I93: 130.15 | J93: 109.35 | K93: 52.35 | L93: 38.9 | M93: 97.5 | N93: 134.4 | O93: 34.55 | P93: 9.7 | Q93: 70.65 | R93: 95.95 | S93: 1184.25
B94: HIDROCAÑETE S.A. | C94: C.H. IMPERIAL | D94: CENTRAL | E94: HIDROELÉCTRICA | F94: 49.85 | G94: 50.85 | H94: 52.35 | I94: 56.45 | J94: 65.1 | K94: 76.6 | L94: 81.05 | M94: 80.35 | N94: 82.55 | O94: 82.65 | P94: 83.5 | Q94: 83.15 | R94: 82 | S94: 926.45
B95: HIDROELECTRICA HUANCHOR S.A.C. | C95: C.H. HUANCHOR | D95: CENTRAL | E95: HIDROELÉCTRICA | F95: 364.96224 | G95: 372.05 | H95: 351.85 | I95: 352.6 | J95: 411.75 | K95: 396.6 | L95: 382.75 | M95: 370.5 | N95: 430.55 | O95: 441.05 | P95: 437.4 | Q95: 436.7 | R95: 436.3 | S95: 5185.0622
B96: HUAURA POWER GROUP S.A. | C96: C.H. YARUCAYA | D96: CENTRAL | E96: HIDROELÉCTRICA | F96: 366.8 | G96: 388.95 | H96: 409.4 | I96: 416.9 | J96: 446.5 | K96: 448.15 | L96: 447.5 | M96: 446.4 | N96: 446.4 | O96: 446.4 | P96: 446.4 | Q96: 446.4 | R96: 417.05 | S96: 5573.25
B97: HYDRO GLOBAL PERÚ S.A.C. | C97: CH SAN GABAN III | D97: CENTRAL | E97: HIDROELÉCTRICA | F97: 4883.75 | G97: 4870.6 | H97: 4851.2 | I97: 4854.4 | J97: 4848.1 | K97: 4851.25 | L97: 4852.05 | M97: 4855.15 | N97: 4851.9 | O97: 4855.1 | P97: 4856.8 | Q97: 4846.2 | R97: 4853.8 | S97: 63130.3
B98: INFRAESTRUCTURAS Y ENERGIAS DEL PERU S.A.C. | C98: C.T. RF PTO MALDONADO | D98: CENTRAL | E98: TERMOELÉCTRICA | L98: 26.1 | M98: 31.4 | P98: 3.25 | S98: 60.75
B99: INFRAESTRUCTURAS Y ENERGIAS DEL PERU S.A.C. | C99: C.T. RF PUCALLPA | D99: CENTRAL | E99: TERMOELÉCTRICA | S99: 0
B100: INLAND ENERGY SAC | C100: C.H. SANTA TERESA | D100: CENTRAL | E100: HIDROELÉCTRICA | F100: 2180.25 | G100: 2179.4 | H100: 2133.45 | I100: 2128.2 | J100: 2149.05 | K100: 2171.8 | L100: 2180 | M100: 2168.7 | N100: 2153.5 | O100: 2178.75 | P100: 1910.75 | Q100: 2164.95 | R100: 2172.9 | S100: 27871.7
B101: INVERSIONES SHAQSHA S.A.C. | C101: C.H. PARIAC | D101: CENTRAL | E101: HIDROELÉCTRICA | H101: 10.05 | I101: 33.7 | J101: 44.3 | K101: 41.5 | L101: 43.2 | M101: 46.45 | N101: 48.9 | O101: 48.3 | P101: 48.35 | Q101: 48.25 | R101: 48.25 | S101: 461.25
B102: JOYA SOLAR S.A.C. | C102: C.S. SAN MARTIN SOLAR | D102: CENTRAL | E102: SOLAR | F102: 2671.9 | G102: 2300.7 | H102: 2455.8 | I102: 2577.2 | J102: 2664.75 | K102: 2692.9 | L102: 2684.95 | M102: 2488.25 | N102: 2679.7 | O102: 2123.65 | P102: 2194.5 | Q102: 2215.85 | R102: 1812.05 | S102: 31562.2
B103: KALLPA GENERACION S.A. | C103: C.H. CERRO DEL AGUILA | D103: CENTRAL | E103: HIDROELÉCTRICA | F103: 3028.95 | G103: 2160.3 | H103: 2855.7 | I103: 3732.5 | J103: 4295.55 | K103: 6726.95 | L103: 6043.35 | M103: 5286.6 | N103: 6042.45 | O103: 6416.85 | P103: 4990.55 | Q103: 6858.45 | R103: 8340.75 | S103: 66778.95
...

Sheet G_AREAS
B3: martes, 13 de Enero del 2026
B5: HORA | C5: RESUMEN DE GENERACIÓN POR ÁREAS DEL SEIN | D5: RESUMEN DE GENERACIÓN POR ÁREAS DEL SEIN | E5: RESUMEN DE GENERACIÓN POR ÁREAS DEL SEIN | F5: RESUMEN DE GENERACIÓN POR ÁREAS DEL SEIN | G5: RESUMEN DE GENERACIÓN POR ÁREAS DEL SEIN | H5: RESUMEN DE GENERACIÓN POR ÁREAS DEL SEIN | I5: RESUMEN DE GENERACIÓN POR ÁREAS DEL SEIN | J5: RESUMEN DE GENERACIÓN POR ÁREAS DEL SEIN | K5: RESUMEN DE GENERACIÓN POR ÁREAS DEL SEIN | L5: RESUMEN DE GENERACIÓN POR ÁREAS DEL SEIN | M5: RESUMEN DE GENERACIÓN POR ÁREAS DEL SEIN | N5: RESUMEN DE GENERACIÓN POR ÁREAS DEL SEIN | O5: RESUMEN DE GENERACIÓN POR ÁREAS DEL SEIN | P5: RESUMEN DE GENERACIÓN POR ÁREAS DEL SEIN | Q5: RESUMEN DE GENERACIÓN POR ÁREAS DEL SEIN | R5: RESUMEN DE GENERACIÓN POR ÁREAS DEL SEIN | S5: HORA | T5: GENERACIÓN POR TIPO DE GENERACIÓN | U5: GENERACIÓN POR TIPO DE GENERACIÓN | V5: GENERACIÓN POR TIPO DE GENERACIÓN | W5: GENERACIÓN POR TIPO DE GENERACIÓN | X5: GENERACIÓN POR TIPO DE GENERACIÓN | Y5: HORA | Z5: GENERACIÓN POR TIPO DE GENERACIÓN | AA5: GENERACIÓN POR TIPO DE GENERACIÓN | AB5: GENERACIÓN POR TIPO DE GENERACIÓN | AC5: GENERACIÓN POR TIPO DE GENERACIÓN | AD5: GENERACIÓN POR TIPO DE GENERACIÓN
C6: NORTE | D6: NORTE | E6: NORTE | F6: NORTE | G6: CENTRO | H6: CENTRO | I6: CENTRO | J6: CENTRO | K6: SUR | L6: SUR | M6: SUR | N6: SUR | O6: GENERACIÓN INTEGRANTES COES | P6: GENERACIÓN INTEGRANTES COES | Q6: GENERACIÓN INTEGRANTES COES | R6: GENERACIÓN INTEGRANTES COES | T6: INTEGRANTES COES | U6: INTEGRANTES COES | V6: INTEGRANTES COES | W6: INTEGRANTES COES | X6: INTEGRANTES COES | Z6: INTEGRANTES COES RER | AA6: INTEGRANTES COES RER | AB6: INTEGRANTES COES RER | AC6: INTEGRANTES COES RER | AD6: INTEGRANTES COES RER
C7: GENERACIÓN HIDROELÉCTRICA NORTE | D7: GENERACIÓN TERMOELÉCTRICA NORTE | E7: GENERACIÓN SOLAR NORTE | F7: GENERACIÓN EÓLICA NORTE | G7: GENERACIÓN HIDROELÉCTRICA CENTRO | H7: GENERACIÓN TERMOELÉCTRICA CENTRO | I7: GENERACIÓN SOLAR CENTRO | J7: GENERACIÓN EÓLICA CENTRO | K7: GENERACIÓN HIDROELÉCTRICA SUR | L7: GENERACIÓN TERMOELÉCTRICA SUR | M7: GENERACIÓN SOLAR SUR | N7: GENERACIÓN EÓLICA SUR | O7: GENERACIÓN COES NORTE | P7: GENERACIÓN COES CENTRO | Q7: GENERACIÓN COES SUR | R7: TOTAL GENERACION | T7: HIDROELÉCTRICA | U7: TERMOELÉCTRICA | V7: SOLAR | W7: EÓLICA | X7: TOTAL GENERACION | Z7: HIDROELÉCTRICA RER | AA7: TERMOELÉCTRICA RER | AB7: SOLAR RER | AC7: EÓLICA RER | AD7: TOTAL RER
B8: 00:30 | C8: 469.588 | D8: 177.44 | E8: 0 | F8: 16.3 | G8: 2979.8615 | H8: 2049.1 | I8: 0 | J8: 314.8 | K8: 760.9 | L8: 0 | M8: 0 | N8: 0 | O8: 663.328 | P8: 5343.7615 | Q8: 760.9 | R8: 6767.9895 | S8: 00:30 | T8: 4210.3495 | U8: 2226.54 | V8: 0 | W8: 331.1 | X8: 6767.9895 | Y8: 00:30 | Z8: 338.141 | AA8: 92.04 | AB8: 0 | AC8: 331.1 | AD8: 761.281
B9: 01:00 | C9: 466.364 | D9: 175.56 | E9: 0 | F9: 16.7 | G9: 2926.4239 | H9: 2061.5 | I9: 0 | J9: 265.1 | K9: 762.6 | L9: 0 | M9: 0 | N9: 0 | O9: 658.624 | P9: 5253.0239 | Q9: 762.6 | R9: 6674.2479 | S9: 01:00 | T9: 4155.3879 | U9: 2237.06 | V9: 0 | W9: 281.8 | X9: 6674.2479 | Y9: 01:00 | Z9: 337.736 | AA9: 90.56 | AB9: 0 | AC9: 281.8 | AD9: 710.096
B10: 01:30 | C10: 457.588 | D10: 175.54 | E10: 0 | F10: 15 | G10: 2942.5162 | H10: 2055.6 | I10: 0 | J10: 215.6 | K10: 749.2 | L10: 0 | M10: 0 | N10: 0 | O10: 648.128 | P10: 5213.7162 | Q10: 749.2 | R10: 6611.0442 | S10: 01:30 | T10: 4149.3042 | U10: 2231.14 | V10: 0 | W10: 230.6 | X10: 6611.0442 | Y10: 01:30 | Z10: 336.664 | AA10: 90.94 | AB10: 0 | AC10: 230.6 | AD10: 658.204
B11: 02:00 | C11: 469.456 | D11: 176.52 | E11: 0 | F11: 14.2 | G11: 2864.3049 | H11: 1970.2 | I11: 0 | J11: 190.5 | K11: 758.8 | L11: 0 | M11: 0 | N11: 0 | O11: 660.176 | P11: 5025.0049 | Q11: 758.8 | R11: 6443.9809 | S11: 02:00 | T11: 4092.5609 | U11: 2146.72 | V11: 0 | W11: 204.7 | X11: 6443.9809 | Y11: 02:00 | Z11: 336.88 | AA11: 91.72 | AB11: 0 | AC11: 204.7 | AD11: 633.3
B12: 02:30 | C12: 465.687 | D12: 169.64 | E12: 0 | F12: 12.4 | G12: 2897.0554 | H12: 1928.1 | I12: 0 | J12: 186 | K12: 751.4 | L12: 0 | M12: 0 | N12: 0 | O12: 647.727 | P12: 5011.1555 | Q12: 751.4 | R12: 6410.2824 | S12: 02:30 | T12: 4114.1425 | U12: 2097.74 | V12: 0 | W12: 198.4 | X12: 6410.2824 | Y12: 02:30 | Z12: 336.806 | AA12: 85.74 | AB12: 0 | AC12: 198.4 | AD12: 620.946
B13: 03:00 | C13: 465.763 | D13: 176.22 | E13: 0 | F13: 12.2 | G13: 2854.4938 | H13: 1918.1 | I13: 0 | J13: 201.4 | K13: 754.1 | L13: 0 | M13: 0 | N13: 0 | O13: 654.183 | P13: 4973.9938 | Q13: 754.1 | R13: 6382.2768 | S13: 03:00 | T13: 4074.3568 | U13: 2094.32 | V13: 0 | W13: 213.6 | X13: 6382.2768 | Y13: 03:00 | Z13: 337.362 | AA13: 92.32 | AB13: 0 | AC13: 213.6 | AD13: 643.282
B14: 03:30 | C14: 470.756 | D14: 174.54 | E14: 0 | F14: 10.6 | G14: 2896.9688 | H14: 1928.5 | I14: 0 | J14: 184.6 | K14: 766.7 | L14: 0 | M14: 0 | N14: 0 | O14: 655.896 | P14: 5010.0688 | Q14: 766.7 | R14: 6432.6648 | S14: 03:30 | T14: 4134.4248 | U14: 2103.04 | V14: 0 | W14: 195.2 | X14: 6432.6648 | Y14: 03:30 | Z14: 337.828 | AA14: 90.64 | AB14: 0 | AC14: 195.2 | AD14: 623.668
B15: 04:00 | C15: 461.548 | D15: 174.23 | E15: 0 | F15: 11 | G15: 2885.8248 | H15: 2026.3 | I15: 0 | J15: 156.1 | K15: 747.6 | L15: 0 | M15: 0 | N15: 0 | O15: 646.778 | P15: 5068.2248 | Q15: 747.6 | R15: 6462.6028 | S15: 04:00 | T15: 4094.9728 | U15: 2200.53 | V15: 0 | W15: 167.1 | X15: 6462.6028 | Y15: 04:00 | Z15: 337.301 | AA15: 89.03 | AB15: 0 | AC15: 167.1 | AD15: 593.431
B16: 04:30 | C16: 467.549 | D16: 174.8 | E16: 0 | F16: 6.4 | G16: 3010.137 | H16: 2034.5 | I16: 0 | J16: 153.1 | K16: 762.5 | L16: 0 | M16: 0 | N16: 0 | O16: 648.749 | P16: 5197.737 | Q16: 762.5 | R16: 6608.986 | S16: 04:30 | T16: 4240.186 | U16: 2209.3 | V16: 0 | W16: 159.5 | X16: 6608.986 | Y16: 04:30 | Z16: 337.518 | AA16: 90.9 | AB16: 0 | AC16: 159.5 | AD16: 587.918
B17: 05:00 | C17: 467.245 | D17: 173.98 | E17: 0 | F17: 13.1 | G17: 3065.4219 | H17: 2037.5 | I17: 0 | J17: 119.1 | K17: 756.9 | L17: 0 | M17: 0 | N17: 0 | O17: 654.325 | P17: 5222.0219 | Q17: 756.9 | R17: 6633.2469 | S17: 05:00 | T17: 4289.5669 | U17: 2211.48 | V17: 0 | W17: 132.2 | X17: 6633.2469 | Y17: 05:00 | Z17: 333.348 | AA17: 90.88 | AB17: 0 | AC17: 132.2 | AD17: 556.428
B18: 05:30 | C18: 466.655 | D18: 173.79 | E18: 0 | F18: 12 | G18: 3072.0339 | H18: 2037.8 | I18: 0 | J18: 125.8 | K18: 755 | L18: 0 | M18: 4.8 | N18: 0 | O18: 652.445 | P18: 5235.6339 | Q18: 759.8 | R18: 6647.8789 | S18: 05:30 | T18: 4293.6889 | U18: 2211.59 | V18: 4.8 | W18: 137.8 | X18: 6647.8789 | Y18: 05:30 | Z18: 329.978 | AA18: 90.69 | AB18: 4.8 | AC18: 137.8 | AD18: 563.268
B19: 06:00 | C19: 461.501 | D19: 170.76 | E19: 0 | F19: 12.6 | G19: 3077.7096 | H19: 1927.4 | I19: 0 | J19: 131.8 | K19: 729.2 | L19: 0 | M19: 70.4 | N19: 0 | O19: 644.861 | P19: 5136.9096 | Q19: 799.6 | R19: 6581.3705 | S19: 06:00 | T19: 4268.4105 | U19: 2098.16 | V19: 70.4 | W19: 144.4 | X19: 6581.3705 | Y19: 06:00 | Z19: 335.039 | AA19: 86.76 | AB19: 70.4 | AC19: 144.4 | AD19: 636.599
... B56: TOTAL MWh | C56: 11478.599 | D56: 4153.41 | E56: 0.95 | F56: 450.9 | G56: 73610.041 | H56: 57587.6 | I56: 4.35 | J56: 4927.95 | K56: 18235.4 | L56: 0 | M56: 7031.45 | N56: 0 | O56: 16083.859 | P56: 136129.94 | Q56: 25266.85 | R56: 177480.65 | S56: TOTAL MWh | T56: 103324.04 | U56: 61741.01 | V56: 7036.75 | W56: 5378.85 | X56: 177480.65 | Y56: TOTAL MWh | Z56: 8566.057 | AA56: 2125.46 | AB56: 7036.75 | AC56: 5378.85 | AD56: 23107.117

Sheet HOP
B3: martes, 13 de Enero del 2026
B5: Reporte de Horas de Operación
B6: Empresa | C6: Central | D6: Grupo | E6: Modo de Operación | F6: Inicio | G6: Final | H6: O. Arranque | I6: O. Parada | J6: Tipo Operación | K6: Ensayo de Potencia Efectiva | L6: Ensayo de Potencia Mínima | M6: Sistema | N6: Lim. Transm. | O6: Causa | P6: Observación
B7: AGRO INDUSTRIAL PARAMONGA S.A. | C7: C.T. PARAMONGA | D7: CENTRAL | E7: PARAMONGA - BAGAZO | F7: 13/01/2026 00:00:00 | G7: 14/01/2026 00:00:00 | J7: POR COGENERACION | O7: ...
B8: AGROAURORA S.A.C. | C8: C.T. MAPLE ETANOL | D8: CENTRAL | E8: MAPLE- BAGAZO | F8: 13/01/2026 00:00:00 | G8: 13/01/2026 23:58:00 | J8: POR COGENERACION | O8: ...
B9: AGROAURORA S.A.C. | C9: C.T. MAPLE ETANOL | D9: CENTRAL | E9: MAPLE- BAGAZO | F9: 13/01/2026 23:58:00 | G9: 14/01/2026 00:00:00 | J9: NO IDENTIFICADO | O9: ...
B10: BIOENERGIA DEL CHIRA S.A. | C10: C.T. CAÑA BRAVA | D10: CENTRAL | E10: CANA BRAVA TV1 & TV2 - BAGAZO | F10: 13/01/2026 00:00:00 | G10: 13/01/2026 09:49:00 | J10: POR COGENERACION | O10: ...
B11: BIOENERGIA DEL CHIRA S.A. | C11: C.T. CAÑA BRAVA | D11: G-2 | E11: CANA BRAVA TV2 - BAGAZO | F11: 13/01/2026 09:49:00 | G11: 13/01/2026 10:16:00 | J11: POR COGENERACION | O11: ...
B12: BIOENERGIA DEL CHIRA S.A. | C12: C.T. CAÑA BRAVA | D12: G-2 | E12: CANA BRAVA TV2 - BAGAZO | F12: 13/01/2026 10:20:00 | G12: 13/01/2026 11:14:00 | J12: POR COGENERACION | O12: ...
B13: BIOENERGIA DEL CHIRA S.A. | C13: C.T. CAÑA BRAVA | D13: CENTRAL | E13: CANA BRAVA TV1 & TV2 - BAGAZO | F13: 13/01/2026 11:14:00 | G13: 13/01/2026 11:15:00 | J13: POR COGENERACION | O13: ...
B14: BIOENERGIA DEL CHIRA S.A. | C14: C.T. CAÑA BRAVA | D14: G-1 | E14: CANA BRAVA TV1 - BAGAZO | F14: 13/01/2026 11:15:00 | G14: 13/01/2026 11:24:00 | J14: POR COGENERACION | O14: ...
B15: BIOENERGIA DEL CHIRA S.A. | C15: C.T. CAÑA BRAVA | D15: CENTRAL | E15: CANA BRAVA TV1 & TV2 - BAGAZO | F15: 13/01/2026 11:24:00 | G15: 13/01/2026 13:11:00 | J15: POR COGENERACION | O15: ...
B16: BIOENERGIA DEL CHIRA S.A. | C16: C.T. CAÑA BRAVA | D16: G-2 | E16: CANA BRAVA TV2 - BAGAZO | F16: 13/01/2026 13:11:00 | G16: 13/01/2026 13:13:00 | J16: POR COGENERACION | O16: ...
B17: BIOENERGIA DEL CHIRA S.A. | C17: C.T. CAÑA BRAVA | D17: CENTRAL | E17: CANA BRAVA TV1 & TV2 - BAGAZO | F17: 13/01/2026 13:13:00 | G17: 13/01/2026 13:24:00 | J17: POR COGENERACION | O17: ...
B18: BIOENERGIA DEL CHIRA S.A. | C18: C.T. CAÑA BRAVA | D18: G-2 | E18: CANA BRAVA TV2 - BAGAZO | F18: 13/01/2026 13:24:00 | G18: 13/01/2026 13:32:00 | J18: POR COGENERACION | O18: ...
... B21: BIOENERGIA DEL CHIRA S.A. | C21: C.T. CAÑA BRAVA | D21: CENTRAL | E21: CANA BRAVA TV1 & TV2 - BAGAZO | F21: 13/01/2026 14:01:00 | G21: 14/01/2026 00:00:00 | J21: POR COGENERACION | O21: ...
B22: EGESUR | C22: C.T. INDEPENDENCIA | D22: CENTRAL | E22: INDEPENDENCIA GAS | F22: 13/01/2026 03:41:00 | G22: 14/01/2026 00:00:00 | H22: 13/01/2026 03:37:00 | J22: POR POTENCIA O ENERGIA | O22: ...
B23: ENEL GENERACION PIURA S.A. | C23: C.T. MALACAS 1 | D23: CENTRAL | E23: MALACAS1 TG6 - GAS | F23: 13/01/2026 00:00:00 | G23: 13/01/2026 00:06:00 | J23: POR POTENCIA O ENERGIA | O23: ...
B24: ENEL GENERACION PIURA S.A. | C24: C.T. MALACAS 1 | D24: CENTRAL | E24: MALACAS1 TG6 - GAS | F24: 13/01/2026 00:06:00 | G24: 13/01/2026 23:58:00 | J24: A MINIMA CARGA | O24: ...
B25: ENGIE ENERGIA PERU S.A.A. | C25: C.T. CHILCA 1 | D25: CENTRAL | E25: CHILCA1 CCOMB TG1 & TG2 & TG3 - GAS | F25: 13/01/2026 00:00:00 | G25: 14/01/2026 00:00:00 | J25: POR POTENCIA O ENERGIA | O25: ...
B26: ENGIE ENERGIA PERU S.A.A. | C26: C.T. CHILCA 2 | D26: CENTRAL | E26: CHILCA2 CCOMB TG41 - GAS | F26: 13/01/2026 00:00:00 | G26: 14/01/2026 00:00:00 | J26: POR POTENCIA O ENERGIA | O26: ...
B27: FENIX POWER PERÚ | C27: C.T. FENIX | D27: CENTRAL | E27: FENIX CCOMB GT11 & GT12 - GAS | F27: 13/01/2026 00:00:00 | G27: 14/01/2026 00:00:00 | J27: POR POTENCIA O ENERGIA | O27: ...
B28: GM OPERACIONES S.A.C. | C28: CT REFINERIA TALARA | D28: TV1 REF TALARA | E28: REF_TALARA TV1 - NLH_RFG | F28: 13/01/2026 00:00:00 | G28: 14/01/2026 00:00:00 | J28: POR COGENERACION | O28: ...
B29: GM OPERACIONES S.A.C. | C29: CT REFINERIA TALARA | D29: TV2 REF TALARA | E29: REF_TALARA TV2 - NLH_RFG | F29: 13/01/2026 00:00:00 | G29: 14/01/2026 00:00:00 | J29: POR COGENERACION | O29: ...
B30: KALLPA GENERACION S.A. | C30: C.T. KALLPA | D30: TG2 | E30: KALLPA TG2 - GAS | F30: 13/01/2026 00:00:00 | G30: 13/01/2026 00:22:00 | J30: A MINIMA CARGA | O30: ...
B31: KALLPA GENERACION S.A. | C31: C.T. KALLPA | D31: TG3 | E31: KALLPA TG3 - GAS | F31: 13/01/2026 00:00:00 | G31: 14/01/2026 00:00:00 | J31: POR POTENCIA O ENERGIA | O31: ...
B32: KALLPA GENERACION S.A. | C32: C.T. KALLPA | D32: TG2 | E32: KALLPA TG2 - GAS | F32: 13/01/2026 07:52:00 | G32: 14/01/2026 00:00:00 | J32: POR POTENCIA O ENERGIA | O32: ...
B33: KALLPA GENERACION S.A. | C33: C.T. KALLPA | D33: TG1 | E33: KALLPA TG1 - GAS | F33: 13/01/2026 11:10:00 | G33: 13/01/2026 23:46:00 | H33: 13/01/2026 10:40:00 | I33: 13/01/2026 23:15:00 | J33: POR POTENCIA O ENERGIA | O33: ...
B34: KALLPA GENERACION S.A. | C34: C.T. LAS FLORES | D34: TG1 | E34: LAS FLORES TG1 - GAS | F34: 13/01/2026 08:32:00 | G34: 14/01/2026 00:00:00 | H34: 13/01/2026 07:52:00 | J34: POR POTENCIA O ENERGIA | O34: ...
B35: ORYGEN PERU S.A.A. | C35: C.T. SANTA ROSA I | D35: TG7 | E35: STA ROSA WEST TG7 - GAS CON H2O | F35: 13/01/2026 15:30:00 | G35: 13/01/2026 23:11:00 | H35: 13/01/2026 14:51:00 | J35: POR POTENCIA O ENERGIA | O35: ...
B36: ORYGEN PERU S.A.A. | C36: C.T. SANTA ROSA I | D36: TG7 | E36: STA ROSA WEST TG7 - GAS CON H2O | F36: 13/01/2026 23:11:00 | G36: 13/01/2026 23:52:00 | I36: 13/01/2026 23:38:00 | J36: A MINIMA CARGA | O36: ...
B37: ORYGEN PERU S.A.A. | C37: C.T. VENTANILLA | D37: CENTRAL | E37: VENTANILLA CCOMB TG3 & TG4 - GAS | F37: 13/01/2026 00:00:00 | G37: 13/01/2026 07:44:00 | J37: POR POTENCIA O ENERGIA | O37: ...
B38: ORYGEN PERU S.A.A. | C38: C.T. VENTANILLA | D38: CENTRAL | E38: VENTANILLA CCOMB TG3 & TG4 - GAS F.DIRECTO | F38: 13/01/2026 07:44:00 | G38: 13/01/2026 23:05:00 | J38: POR POTENCIA O ENERGIA | O38: ...
B39: ORYGEN PERU S.A.A. | C39: C.T. VENTANILLA | D39: CENTRAL | E39: VENTANILLA CCOMB TG3 & TG4 - GAS | F39: 13/01/2026 23:05:00 | G39: 14/01/2026 00:00:00 | J39: POR POTENCIA O ENERGIA | O39: ...
B40: PETRAMAS | C40: C.T. HUAYCOLORO | D40: CENTRAL | E40: HUAYCOLORO - BIOGAS | F40: 13/01/2026 00:00:00 | G40: 14/01/2026 00:00:00 | H40: 13/01/2026 16:56:00 | J40: NO IDENTIFICADO | O40: ...
B41: PETRAMAS | C41: C.T. HUAYCOLORO | D41: CENTRAL | E41: HUAYCOLORO - BIOGAS | F41: 13/01/2026 00:00:00 | G41: 14/01/2026 00:00:00 | I41: 13/01/2026 08:02:00 | J41: NO IDENTIFICADO | O41: ...
B42: PETRAMAS | C42: C.T. LA GRINGA | D42: G2 | E42: LA GRINGA V - BIOGAS | F42: 13/01/2026 00:00:00 | G42: 14/01/2026 00:00:00 | J42: POR POTENCIA O ENERGIA | O42: ...
B43: PETRAMAS | C43: C.T.B DOÑA CATALINA | D43: CENTRAL | E43: DONA CATALINA - BIOGAS | F43: 13/01/2026 00:00:00 | G43: 14/01/2026 00:00:00 | J43: POR POTENCIA O ENERGIA | O43: ...

Sheet INDISP
B3: martes, 13 de Enero del 2026
B5: Hora Inicio y Fin de Indisponibilidades de las Unidades de Generación SEIN
B6: Empresa | C6: Ubicación | D6: Equipo | E6: Inicio | F6: Final | G6: Descripción | H6: MW Indisp. | I6: Prog. | J6: Dispon | K6: Interrupc. | L6: Tipo | M6: CodEq | N6: TipoEq_Osinerg
B7: CHINANGO S.A.C. | C7: CHIMAY | D7: CENTRAL | E7: 13/01/2026 00:00 | F7: 14/01/2026 00:00 | G7: Fuera de servicio por alta concentración de sólidos 2.3 gr/lt y caudal 170 m3/seg. | H7: 150 | I7: F | J7: F/S | K7: N | L7: OTROS | M7: 1191 | N7: G
B8: CHINANGO S.A.C. | C8: YANANGO | D8: G1 | E8: 13/01/2026 07:14 | F8: 14/01/2026 00:00 | G8: FUERA DE SERVICIO POR ALTA CONCENTRACIÓN DE SÓLIDOS 6.2 gr/lt Y CAUDAL 65 m3/seg. | H8: 42 | I8: F | J8: F/S | K8: N | L8: OTROS | M8: 108 | N8: G
B9: EGESUR | C9: INDEPENDENCIA | D9: INDEP_G3 | E9: 13/01/2026 00:00 | F9: 14/01/2026 00:00 | G9: Mantenimiento correctivo de lazo de comunicación WECS - PLC | H9: 5.732 | I9: P | J9: F/S | K9: N | L9: CORR. | M9: 12779 | N9: G
B10: ENGIE ENERGIA PERU S.A.A. | C10: YUNCÁN | D10: G1 | E10: 13/01/2026 05:59 | F10: 13/01/2026 16:24 | G10: LIMPIEZA INTERCAMBIADORES DE CALOR GENERADOR G1 | H10: 0 | I10: P | J10: F/S | K10: N | L10: CORR. | M10: 199 | N10: G
B11: KALLPA GENERACION S.A. | C11: KALLPA | D11: TV | E11: 13/01/2026 00:00 | F11: 14/01/2026 00:00 | G11: MANTENIMIENTO MAYOR TV KG | H11: 0 | I11: P | J11: F/S | K11: N | L11: PREV. | M11: 13204 | N11: G
B12: KALLPA GENERACION S.A. | C12: LAS FLORES | D12: TV | E12: 13/01/2026 00:00 | F12: 14/01/2026 00:00 | G12: Unidad TV de la CT Las Flores fuera de servicio por reparación de caja reductora de turbina | H12: 109 | I12: P | J12: F/S | K12: N | L12: CORR. | M12: 22082 | N12: G
B13: ORYGEN PERU S.A.A. | C13: SANTA ROSA II | D13: TG8 | E13: 13/01/2026 14:47 | F13: 13/01/2026 15:44 | G13: FALLA SISTEMA ARRANQUE - ENCENDIDO. | H13: 191 | I13: F | J13: F/S | K13: N | L13: CORR. | M13: 12329 | N13: G
B14: PETRAMAS | C14: CTB CALLAO | D14: G1 CALLAO | E14: 13/01/2026 00:00 | F14: 14/01/2026 00:00 | G14: MANTENIMIENTO DE CULATAS Y PISTONES/MANTENIMIENTO DE RADIADOR | H14: 1.2 | I14: P | J14: F/S | K14: N | L14: PREV. | M14: 20851 | N14: G
B15: PETRAMAS | C15: CTB CALLAO | D15: G2 CALLAO | E15: 13/01/2026 00:00 | F15: 14/01/2026 00:00 | G15: MANTENIMIENTO DE 38000 HRS | H15: 1.2 | I15: P | J15: F/S | K15: N | L15: PREV. | M15: 20852 | N15: G
B16: PETRAMAS | C16: HUAYCOLORO | D16: G1 | E16: 13/01/2026 08:10 | F16: 13/01/2026 17:03 | G16: MANTENIMIENTO DE 97500 HRS | H16: 1.5 | I16: P | J16: F/S | K16: N | L16: PREV. | M16: 13299 | N16: G
B17: PETRAMAS | C17: LA GRINGA V | D17: G1 | E17: 13/01/2026 00:00 | F17: 14/01/2026 00:00 | G17: REACONDICIONAMIENTO GENERAL DEL GE (COMPLETO) /MANTENIMIENTO DE RADIADOR | H17: 1.5 | I17: P | J17: F/S | K17: N | L17: PREV. | M17: 15113 | N17: G
B18: SHOUGESA | C18: SAN NICOLÁS | D18: TV3 | E18: 13/01/2026 00:00 | F18: 14/01/2026 00:00 | G18: Indisponible para inspección de tubos en el hogar de la caldera 3 y celda del auxiliar N° 3 | H18: 0 | I18: P | J18: F/S | K18: N | L18: CORR. | M18: 60 | N18: G
... B22: TERMOCHILCA S.A.C. | C22: SANTO DOMINGO DE LOS OLLEROS | D22: CENTRAL | E22: 13/01/2026 00:00 | F22: 14/01/2026 00:00 | G22: Implementación de upgrade CEMS | H22: 319 | I22: P | J22: F/S | K22: N | L22: PREV. | M22: 13656 | N22: G

Sheet RESERVA_FRÍA
B3: 13/01/2026 | E3: EJECUTADO | L3: Martes 13 de Enero del 2026 / SEM N° 2 | V3: EJECUTADO | AC3: Martes 13 de Enero del 2026 / SEM N° 2 | EE3: ENERGIA RENOVABLES | GV3: COGENERACION | HE3: NO INTEGRANTES
