Workbook

Sheet EVENTOS
B3: sábado, 21 de Febrero del 2026
B5: INFORMACIÓN DE EVENTOS PRINCIPALES EN SUS INSTALACIONES
B6: TIPO DE EVENTO | C6: EMPRESA | D6: UBICACIÓN | E6: TIPO DE EQUIPO | F6: EQUIPO | G6: INICIO | H6: FINAL | I6: DESCRIPCIÓN | J6: MW INDISP. | K6: INTERRUPCIÓN (SI/NO) | L6: TENSIÓN DE FALLA (kV)
B7: EVENTO | C7: STATKRAFT S.A | D7: MISAPUQUIO | E7: CENTRAL HIDROELÉCTRICA | F7: CENTRAL | G7: 21/02/2026 18:52:00 | H7: 21/02/2026 18:56:00 | I7: DESCONECTÓ LA LINEA L-1040 (CALLALLI - TALTA) DE 138 KV | K7: SI
B8: EVENTO | C8: CONELSUR LT SAC | D8: PORTILLO | E8: CELDA | F8: ACOPLE 60 | G8: 21/02/2026 00:00:00 | H8: 22/02/2026 00:00:00 | I8: DECLARACIÓN DE SITUACIÓN EXCEPCIONAL EN LA S.E. PORTILLO 60 kV | K8: NO
B9: EVENTO | C9: EGESUR | D9: INDEPENDENCIA | E9: GENERADOR TERMOELÉCTRICO | F9: INDEP_G2 | G9: 21/02/2026 20:43:00 | H9: 21/02/2026 20:43:00 | I9: DESCONEXIÓN DEL GENERADOR G2 DE LA C.T. INDEPENDENCIA POR FALLA | K9: NO
B10: FALLA | C10: ELECTRO PUNO | D10: PUNO - POMATA - ILAVE | E10: LINEA DE TRANSMISION | F10: L-6027 | G10: 21/02/2026 02:12:00 | H10: 21/02/2026 02:14:00 | I10: DESCONEXIÓN DE LA LINEA L-6027 (PUNO - ILAVE - POMATA) DE 60 KV | K10: SI | L10: 60
B11: FALLA | C11: ORYGEN PERU S.A.A. | D11: HUINCO | E11: GENERADOR HIDROELÉCTRICO | F11: G1 | G11: 21/02/2026 05:42:00 | H11: 21/02/2026 10:37:00 | I11: DESCONEXIÓN DEL GENERADOR G1 DE LA C.H. HUINCO | K11: NO | L11: 12.5
B12: FALLA | C12: SEAL | D12: CAMANA - LA HUERTA | E12: LINEA DE TRANSMISION | F12: L-1057 | G12: 21/02/2026 05:48:28 | H12: 21/02/2026 06:01:11 | I12: DESCONEXIÓN DE LA LÍNEA L-1057 (CAMANÁ - LA HUERTA) DE 138 KV | K12: SI | L12: 138
B13: FALLA | C13: STATKRAFT S.A | D13: MISAPUQUIO | E13: GENERADOR HIDROELÉCTRICO | F13: G2 | G13: 21/02/2026 13:17:00 | H13: 21/02/2026 13:17:00 | I13: DESCEONEXIÓN DEL GENERADOR G2 DE LA C.H. MISAPUQUIO POR FALLA | K13: NO | L13: 0

Sheet RESTRIC_OPE
B3: sábado, 21 de Febrero del 2026
B5: RESTRICCIONES OPERATIVAS
B6: FECHA | C6: HORA INICIO | D6: HORA FINAL | E6: EMPRESA | F6: UBICACIÓN | G6: T.Eq. | H6: EQUIPO | I6: DESCRIPCIÓN
B7: 21/02/2026 | C7: 00:00 | D7: 24:00 | E7: CELEPSA | F7: C.H. EL PLATANAL | G7: CH | H7: CENTRAL | I7: De acuerdo con lo informado por CELEPSA mediante correo el dia 17.01, declaran que la CH Platanal se encontrará de pasada.
B8: 21/02/2026 | C8: 00:00 | D8: 24:00 | E8: EGASA | F8: S.E. CONVERTIDOR | G8: BARRA | H8: BARRA138KV | I8: EGASA limitó la capacidad del transformador 138 kV/33 kV a 50 MVA por deterioro del aislamiento.
B9: 21/02/2026 | C9: 00:00 | D9: 24:00 | E9: ELECTROPERU | F9: C.H. MANTARO | G9: CH | H9: CENTRAL | I9: De acuerdo con el correo del día 25.08.2025, la central tiene una limitación de potencia máxima de 650 MW por seguridad de la central.
B10: 21/02/2026 | C10: 00:00 | D10: 24:00 | E10: ENEL GENERACION PIURA S.A. | F10: C.T. MALACAS | G10: CT | H10: CENTRAL | I10: De acuerdo con la comunicación vía correo del día 24.10.2024. ENEL GENERACIÓN PIURA informa una restricción de potencia para alcanzar 105 MW en simultaneo (TG6+TGN4).
B11: 21/02/2026 | C11: 00:00 | D11: 24:00 | E11: ENEL GENERACION PIURA S.A. | F11: C.T. MALACAS | G11: GT | H11: TG4 | I11: De acuerdo a lo informado por correo electrónico el día 16.01, con la disponibilidad de aproximadamente 12 MMPCD (339.8Mm³) la unidad TG4 puede con una generación de 80 MW durante 4 horas, y a potencia mínima durante el resto de los periodos
B12: 21/02/2026 | C12: 00:00 | D12: 24:00 | E12: ENGIE ENERGIA PERU S.A.A. | F12: C.H. YUNCÁN | G12: GH | H12: G3 | I12: Según la carta N° ENG/ 198-2024 enviada por su representada, se opera de forma continua el G3 de la CH Yuncán, debido a la ejecución de mantenimientos necesarios para evitar daños en los sellos de seguridad de la válvula esférica del grupo.
B13: 21/02/2026 | C13: 00:00 | D13: 24:00 | E13: ENGIE ENERGIA PERU S.A.A. | F13: C.T. CHILCA 1 | G13: CT | H13: CENTRAL | I13: Con carta ENG/971-2023, indica que no puede cumplir con las IO considerada en el PDO_17122023 dado que vulneran la seguridad de sus activos. Indican que se debe tomar TMO=168h.
B14: 21/02/2026 | C14: 00:00 | D14: 24:00 | E14: ENGIE ENERGIA PERU S.A.A. | F14: C.T. CHILCA 1 | G14: CT | H14: CENTRAL | I14: Restricción de temperatura de la C.T Chilca, ver valor en el modelo de despacho.
B15: 21/02/2026 | C15: 00:00 | D15: 24:00 | E15: ENGIE ENERGIA PERU S.A.A. | F15: C.T. CHILCA 2 | G15: CT | H15: CENTRAL | I15: Con carta ENG/971-2023, indica que no puede cumplir con las IO considerada en el PDO_17122023 dado que vulneran la seguridad de sus activos. Indican que se debe tomar TMO=168h.
B16: 21/02/2026 | C16: 00:00 | D16: 24:00 | E16: FENIX POWER PERÚ | F16: C.T. FENIX | G16: CT | H16: CENTRAL | I16: De acuerdo con lo comunicado en el correo del día 06.05.2025, la CT Fenix cuenta con TMO de 168 hrs en todos sus modos de operación.
B17: 21/02/2026 | C17: 00:00 | D17: 24:00 | E17: KALLPA GENERACION S.A. | F17: C.H. CERRO DEL AGUILA | G17: GH | H17: G1 | I17: De acuerdo a lo informado el día 17/11 por la empresa KALLPA, el G1 tiene un TA = 15min
... B59: 21/02/2026 | C59: 00:00 | D59: 24:00 | E59: TERMOSELVA | F59: C.T. AGUAYTÍA | G59: CT | H59: CENTRAL | I59: Disponibilidad de 23.5 MMSCF para la CT Aguaytía.

Sheet MANTENIMIENTO EJECUTADOS
B3: sábado, 21 de Febrero del 2026
B5: Mantenimiento Ejecutado
B6: Empresa | C6: Ubicación | D6: Equipo | E6: Inicio | F6: Final | G6: Descripción | H6: MW Indisp. | I6: Prog. | J6: Dispon | K6: Interrupc. | L6: Tipo | M6: CodEq | N6: TipoEq_Osinerg
B7: ATLANTICA TRANSMISION SUR S.A. | C7: OCONA | D7: INT-5450 | E7: 21/02/2026 00:00 | F7: 22/02/2026 00:00 | G7: Interruptor INT-5450 cerrado con restriccion operativa, REB-5450 en servicio y suministrando los SS.AA. de la S.E. Oco?a. | H7: 0 | I7: P | J7: E/S | K7: N | L7: OTROS | M7: 13761 | N7: T
B8: ATLANTICA TRANSMISION SUR S.A. | C8: POROMA | D8: REB-5350 | E8: 21/02/2026 00:00 | F8: 22/02/2026 00:00 | G8: Fuera de servicio por falla en el equipo. | H8: 0 | I8: P | J8: F/S | K8: N | L8: OTROS | M8: 13771 | N8: T
B9: ATN S.A. | C9: KIMAN AYLLU | D9: AUT-501 | E9: 21/02/2026 00:00 | F9: 22/02/2026 00:00 | G9: Restriccion Operativa en el circuito de control de cambiador de tap s del AUT-501 | H9: 0 | I9: P | J9: E/S | K9: N | L9: OTROS | M9: 13099 | N9: T
B10: CONELSUR LT SAC | C10: CAJAMARQUILLA | D10: BARRA A 220kV | E10: 21/02/2026 00:00 | F10: 22/02/2026 00:00 | G10: NO SE PUEDE INDISPONER LA BARRA A POR RESTRICCION OPERATIVA DEL SECCIONADOR DE BARRA B DE LA CL-TR1 | H10: 0 | I10: P | J10: E/S | K10: N | L10: OTROS | M10: 1103 | N10: T
B11: CONELSUR LT SAC | C11: CAJAMARQUILLA | D11: CL-TRAFO | E11: 21/02/2026 00:00 | F11: 22/02/2026 00:00 | G11: INDISPONIBLE SECCIONADOR DE BARRA B SB-20011 DE CL-TR1 | H11: 0 | I11: F | J11: E/S | K11: N | L11: OTROS | M11: 1906 | N11: T
B12: CONELSUR LT SAC | C12: CALLAHUANCA (CNS) | D12: CL-2008 | E12: 21/02/2026 00:00 | F12: 22/02/2026 00:00 | G12: RELE DE RESPALDO INOPERATIVO | H12: 0 | I12: F | J12: E/S | K12: N | L12: OTROS | M12: 1337 | N12: T
B13: CONELSUR LT SAC | C13: CALLAHUANCA (CNS) | D13: S.E. | E13: 21/02/2026 00:00 | F13: 22/02/2026 00:00 | G13: RELE DIFERENCIAL DE BARRAS DE CALLAHUANCA 220KV INOPERATIVO | H13: 0 | I13: P | J13: E/S | K13: N | L13: OTROS | M13: 316 | N13: T
B14: CONELSUR LT SAC | C14: HUAMPANI | D14: S.E. | E14: 21/02/2026 00:18 | F14: 21/02/2026 00:32 | G14: NO FUE NECESARIO DEJAR FUERA DE SERVICIO LA SUBESTACION PARA LA ACTIVIDAD DE DESHABILITAR SISTEMA DE PROTECCION Y CONTROL DE LAS CELDAS 6544, 6040, T1 Y T4, DESCONECTANDO SISTEMA 125VDC EN 60kV A SOLICITUD DE ORYGEN PARA HALLAZGO DE FALLA. | H14: 0 | I14: P | J14: E/S | K14: N | L14: OTROS | M14: 15560 | N14: T
B15: CONELSUR LT SAC | C15: LOMERA | D15: BARRA A 220 kV | E15: 21/02/2026 06:25 | F15: 21/02/2026 09:06 | G15: A SOLICITUD DE PLUZ: DESCONEXION POR INTERVENCION EN TRANSFORMADOR TR-2 220/60 KV | H15: 0 | I15: P | J15: F/S | K15: N | L15: PREV. | M15: 16951 | N15: T
B16: CONELSUR LT SAC | C16: LOMERA | D16: BARRA B 220 kV | E16: 21/02/2026 09:12 | F16: 22/02/2026 00:00 | G16: A SOLICITUD DE PLUZ: DESCONEXION POR INTERVENCION EN TRANSFORMADOR TR-2 220/60 KV | H16: 0 | I16: P | J16: F/S | K16: N | L16: PREV. | M16: 16952 | N16: T
B17: EGASA | C17: CHARCANI 123 | D17: T-123 | E17: 21/02/2026 08:10 | F17: 21/02/2026 11:08 | G17: Mantenimiento correctivo sobre pasamuros 33 kV Transformador Charcani 1 | H17: 0 | I17: R | J17: F/S | K17: N | L17: CORR. | M17: 8587 | N17: T
B18: EGASA | C18: CHARCANI I | D18: CENTRAL | E18: 21/02/2026 00:00 | F18: 21/02/2026 00:05 | G18: Central F.S. por solidos en suspension | H18: 1.6 | I18: F | J18: F/S | K18: N | L18: OTROS | M18: 1195 | N18: G
... B126: TRANSMANTARO | C126: YARABAMBA | D126: SS.EE. | E126: 21/02/2026 00:00 | F126: 22/02/2026 00:00 | G126: PROTECCION DIFERENCIAL DE BARRAS 87B 220 KV SE ENCUENTRA BLOQUEADO, LUEGO DE TENER UNA ACTUACION INDESEADA DURANTE EL EVENTO DEL 11.01.2026. | H126: 0 | I126: P | J126: E/S | K126: N | L126: OTROS | M126: 17419 | N126: T

Sheet INGRESO OC
A3: sábado, 21 de Febrero del 2026
A5: INGRESO A OPERACIÓN COMERCIAL
A6: EMPRESA | B6: TIPO DE EQUIPO | C6: UBICACIÓN | D6: EQUIPO | E6: Fecha y hora de Ingreso a Operación Comercial

Sheet DESPACHO_EJECUTADO
B3: sábado, 21 de Febrero del 2026
A5: POTENCIA ACTIVA EJECUTADA DE LAS UNIDADES DE GENERACIÓN DEL SEIN (MW) | FQ5: CENTRALES NO INTEGRANTES COES
A6: FECHA | B6: HORA | C6: 65333 | D6: 101 | E6: 102 | F6: 42667 | G6: 42668 | H6: 126 | I6: 127 | J6: 138 | K6: 139 | L6: 197 | M6: 203 | N6: 204 | O6: 230 | P6: 209 | Q6: 56677 | R6: 796 | S6: 2146 | T6: 142 | U6: 143 | V6: 125 | W6: 187 | X6: 163 | Y6: 298 | Z6: 299 | AA6: 219 | AB6: 151 | AC6: 152 | AD6: 153 | AE6: 154 | AF6: 756 | AG6: 156 | AH6: 155 | AI6: 182 | AJ6: 212 | AK6: 758 | AL6: 263 | AM6: 265 | AN6: 775 | AO6: 777 | AP6: 2154 | AQ6: 150 | AR6: 149 | AS6: 188 | AT6: 2131 | AU6: 755 | AV6: 252 | AW6: 249 | AX6: 250 | AY6: 117 | AZ6: 119 | BA6: 120 | BB6: 189 | BC6: 122 | BD6: 266 | BE6: 337 | BF6: 338 | BG6: 251 | BH6: 115 | BI6: 239 | BJ6: 288 | BK6: 240 | BL6: 241 | BM6: 242 | BN6: 191 | BO6: 194 | BP6: 196 | BQ6: 207 | BR6: 236 | BS6: 795 | BT6: 285 | BU6: 995 | BV6: 996 | BW6: 997 | BX6: 766 | BY6: 926 | BZ6: 924 | CA6: 121 | CB6: 103 | CC6: 104 | CD6: 106 | CE6: 105 | CF6: 107 | CG6: 110 | CH6: 109 | CI6: 144 | CJ6: 113 | CK6: 114 | CL6: 193 | CM6: 208 | CN6: 786 | CO6: 787 | CP6: 788 | CQ6: 789 | CR6: 248 | CS6: 2159 | CT6: 267 | CU6: 268 | CV6: 2194 | CW6: 303 | CX6: 59715 | CY6: 62255 | CZ6: 1263 | DA6: 61800 | DB6: 69125 | DC6: 216 | DD6: 198 | DE6: 70400 | DF6: 76068 | DG6: 49607 | DH6: 214 | DI6: 260 | DJ6: 2152 | DK6: 2128 | DL6: 247 | DM6: 228 | DN6: 2135 | DO6: 261 | DP6: 237 | DQ6: 253 | DR6: 770 | DS6: 235 | DT6: 238 | DU6: 2184 | DV6: 61855 | DW6: 223 | DX6: 75566 | DY6: 226 | DZ6: 201 | EA6: 258 | EB6: 259 | EC6: 257 | ED6: 256 | EE6: 2148 | EF6: 58288 | EG6: 58289 | EH6: 58839 | EI6: 58840 | EJ6: 75260 | EK6: 296 | EL6: 297 | EM6: 211 | EN6: 2175 | EO6: 2178 | EP6: 2181 | EQ6: 1262 | ER6: 63425 | ES6: 233 | ET6: 2150 | EU6: 2165 | EV6: 2161 | EW6: 61197 | EX6: 58851 | EY6: 225 | EZ6: 2201 | FA6: 2171 | FB6: 760 | FC6: 234 | FD6: 215 | FE6: 917 | FF6: 920 | FG6: 289 | FH6: 58333 | FI6: 58336 | FJ6: 213 | FK6: 232 | FL6: 2190 | FM6: 69867 | FN6: 75066 | FO6: TOTAL COES | FQ6: 221 | FR6: 222 | FS6: 224 | FT6: 2187 | FU6: 227 | FV6: 49400 | FW6: 199 | FX6: 200 | FY6: TOTAL NO COES
C7: SUR | D7: CENTRO | E7: CENTRO | F7: NORTE | G7: NORTE | H7: NORTE | I7: NORTE | J7: CENTRO | K7: CENTRO | L7: CENTRO | M7: CENTRO | N7: CENTRO | O7: CENTRO | P7: CENTRO | Q7: CENTRO | R7: CENTRO | S7: CENTRO | T7: CENTRO | U7: CENTRO | V7: CENTRO | W7: CENTRO | X7: SUR | Y7: SUR | Z7: SUR | AA7: CENTRO | AB7: SUR | AC7: SUR | AD7: SUR | AE7: SUR | AF7: SUR | AG7: SUR | AH7: SUR | AI7: SUR | AJ7: CENTRO | AK7: NORTE | AL7: NORTE | AM7: NORTE | AN7: CENTRO | AO7: CENTRO | AP7: CENTRO | AQ7: CENTRO | AR7: CENTRO | AS7: CENTRO | AT7: CENTRO | AU7: SUR | AV7: CENTRO | AW7: CENTRO | AX7: CENTRO | AY7: CENTRO | AZ7: CENTRO | BA7: CENTRO | BB7: SUR | BC7: NORTE | BD7: CENTRO | BE7: CENTRO | BF7: CENTRO | BG7: CENTRO | BH7: NORTE | BI7: NORTE | BJ7: NORTE | BK7: SUR | BL7: SUR | BM7: SUR | BN7: CENTRO | BO7: CENTRO | BP7: CENTRO | BQ7: CENTRO | BR7: CENTRO | BS7: CENTRO | BT7: CENTRO | BU7: SUR | BV7: SUR | BW7: SUR | BX7: NORTE | BY7: SUR | BZ7: CENTRO | CA7: NORTE | CB7: CENTRO | CC7: CENTRO | CD7: CENTRO | CE7: CENTRO | CF7: CENTRO | CG7: CENTRO | CH7: CENTRO | CI7: CENTRO | CJ7: CENTRO | CK7: CENTRO | CL7: CENTRO | CM7: CENTRO | CN7: SUR | CO7: SUR | CP7: SUR | CQ7: SUR | CR7: CENTRO | CS7: CENTRO | CT7: CENTRO | CU7: CENTRO | CV7: NORTE | CW7: CENTRO | CX7: CENTRO | CY7: SUR | CZ7: NORTE | DA7: NORTE | DB7: CENTRO | DC7: NORTE | DD7: NORTE | DE7: SUR | DF7: SUR | DG7: SUR | DH7: CENTRO | DI7: CENTRO | DJ7: CENTRO | DK7: NORTE | DL7: NORTE | DM7: CENTRO | DN7: CENTRO | DO7: SUR | DP7: SUR | DQ7: CENTRO | DR7: CENTRO | DS7: SUR | DT7: CENTRO | DU7: CENTRO | DV7: NORTE | DW7: CENTRO | DX7: CENTRO | DY7: CENTRO | DZ7: NORTE | EA7: CENTRO | EB7: CENTRO | EC7: NORTE | ED7: NORTE | EE7: SUR | EF7: CENTRO | EG7: CENTRO | EH7: CENTRO | EI7: CENTRO | EJ7: SUR | EK7: CENTRO | EL7: CENTRO | EM7: SUR | EN7: SUR | EO7: SUR | EP7: SUR | EQ7: NORTE | ER7: SUR | ES7: SUR | ET7: SUR | EU7: CENTRO | EV7: CENTRO | EW7: CENTRO | EX7: SUR | EY7: CENTRO | EZ7: CENTRO | FA7: CENTRO | FB7: CENTRO | FC7: SUR | FD7: NORTE | FE7: CENTRO | FF7: CENTRO | FG7: NORTE | FH7: NORTE | FI7: NORTE | FJ7: CENTRO | FK7: NORTE | FL7: NORTE | FM7: NORTE | FN7: NORTE | FQ7: NORTE | FR7: CENTRO | FS7: NORTE | FT7: NORTE | FU7: NORTE | FV7: NORTE | FW7: NORTE | FX7: NORTE
C8: HIDROELÉCTRICA | D8: HIDROELÉCTRICA | E8: HIDROELÉCTRICA | F8: TERMOELÉCTRICA | G8: TERMOELÉCTRICA | H8: HIDROELÉCTRICA | I8: HIDROELÉCTRICA | J8: TERMOELÉCTRICA | K8: TERMOELÉCTRICA | L8: TERMOELÉCTRICA | M8: TERMOELÉCTRICA | N8: TERMOELÉCTRICA | O8: TERMOELÉCTRICA | P8: TERMOELÉCTRICA | Q8: TERMOELÉCTRICA | R8: HIDROELÉCTRICA | S8: HIDROELÉCTRICA | T8: TERMOELÉCTRICA | U8: TERMOELÉCTRICA | V8: TERMOELÉCTRICA | W8: TERMOELÉCTRICA | X8: HIDROELÉCTRICA | Y8: HIDROELÉCTRICA | Z8: HIDROELÉCTRICA | AA8: TERMOELÉCTRICA | AB8: HIDROELÉCTRICA | AC8: HIDROELÉCTRICA | AD8: HIDROELÉCTRICA | AE8: HIDROELÉCTRICA | AF8: TERMOELÉCTRICA | AG8: TERMOELÉCTRICA | AH8: TERMOELÉCTRICA | AI8: HIDROELÉCTRICA | AJ8: HIDROELÉCTRICA | AK8: TERMOELÉCTRICA | AL8: TERMOELÉCTRICA | AM8: TERMOELÉCTRICA | AN8: HIDROELÉCTRICA | AO8: HIDROELÉCTRICA | AP8: HIDROELÉCTRICA | AQ8: HIDROELÉCTRICA | AR8: HIDROELÉCTRICA | AS8: HIDROELÉCTRICA | AT8: HIDROELÉCTRICA | AU8: HIDROELÉCTRICA | AV8: TERMOELÉCTRICA | AW8: TERMOELÉCTRICA | AX8: TERMOELÉCTRICA | AY8: HIDROELÉCTRICA | AZ8: HIDROELÉCTRICA | BA8: HIDROELÉCTRICA | BB8: HIDROELÉCTRICA | BC8: HIDROELÉCTRICA | BD8: HIDROELÉCTRICA | BE8: HIDROELÉCTRICA | BF8: HIDROELÉCTRICA | BG8: HIDROELÉCTRICA | BH8: TERMOELÉCTRICA | BI8: TERMOELÉCTRICA | BJ8: TERMOELÉCTRICA | BK8: TERMOELÉCTRICA | BL8: TERMOELÉCTRICA | BM8: TERMOELÉCTRICA | BN8: HIDROELÉCTRICA | BO8: TERMOELÉCTRICA | BP8: TERMOELÉCTRICA | BQ8: TERMOELÉCTRICA | BR8: TERMOELÉCTRICA | BS8: TERMOELÉCTRICA | BT8: TERMOELÉCTRICA | BU8: TERMOELÉCTRICA | BV8: TERMOELÉCTRICA | BW8: TERMOELÉCTRICA | BX8: HIDROELÉCTRICA | BY8: TERMOELÉCTRICA | BZ8: TERMOELÉCTRICA | CA8: HIDROELÉCTRICA | CB8: HIDROELÉCTRICA | CC8: HIDROELÉCTRICA | CD8: HIDROELÉCTRICA | CE8: HIDROELÉCTRICA | CF8: HIDROELÉCTRICA | CG8: TERMOELÉCTRICA | CH8: TERMOELÉCTRICA | CI8: TERMOELÉCTRICA | CJ8: TERMOELÉCTRICA | CK8: TERMOELÉCTRICA | CL8: TERMOELÉCTRICA | CM8: TERMOELÉCTRICA | CN8: TERMOELÉCTRICA | CO8: TERMOELÉCTRICA | CP8: TERMOELÉCTRICA | CQ8: TERMOELÉCTRICA | CR8: TERMOELÉCTRICA | CS8: TERMOELÉCTRICA | CT8: HIDROELÉCTRICA | CU8: HIDROELÉCTRICA | CV8: HIDROELÉCTRICA | CW8: SOLAR | CX8: EÓLICA | CY8: SOLAR | CZ8: EÓLICA | DA8: SOLAR | DB8: HIDROELÉCTRICA | DC8: HIDROELÉCTRICA | DD8: HIDROELÉCTRICA | DE8: SOLAR | DF8: SOLAR | DG8: HIDROELÉCTRICA | DH8: HIDROELÉCTRICA | DI8: HIDROELÉCTRICA | DJ8: HIDROELÉCTRICA | DK8: HIDROELÉCTRICA | DL8: HIDROELÉCTRICA | DM8: HIDROELÉCTRICA | DN8: HIDROELÉCTRICA | DO8: SOLAR | DP8: SOLAR | DQ8: EÓLICA | DR8: EÓLICA | DS8: SOLAR | DT8: HIDROELÉCTRICA | DU8: HIDROELÉCTRICA | DV8: HIDROELÉCTRICA | DW8: HIDROELÉCTRICA | DX8: SOLAR | DY8: HIDROELÉCTRICA | DZ8: HIDROELÉCTRICA | EA8: HIDROELÉCTRICA | EB8: HIDROELÉCTRICA | EC8: EÓLICA | ED8: EÓLICA | EE8: SOLAR | EF8: EÓLICA | EG8: EÓLICA | EH8: EÓLICA | EI8: EÓLICA | EJ8: SOLAR | EK8: HIDROELÉCTRICA | EL8: HIDROELÉCTRICA | EM8: HIDROELÉCTRICA | EN8: HIDROELÉCTRICA | EO8: HIDROELÉCTRICA | EP8: HIDROELÉCTRICA | EQ8: EÓLICA | ER8: SOLAR | ES8: SOLAR | ET8: SOLAR | EU8: HIDROELÉCTRICA | EV8: EÓLICA | EW8: EÓLICA | EX8: SOLAR | EY8: TERMOELÉCTRICA | EZ8: TERMOELÉCTRICA | FA8: TERMOELÉCTRICA | FB8: TERMOELÉCTRICA | FC8: SOLAR | FD8: HIDROELÉCTRICA | FE8: HIDROELÉCTRICA | FF8: HIDROELÉCTRICA | FG8: TERMOELÉCTRICA | FH8: TERMOELÉCTRICA | FI8: TERMOELÉCTRICA | FJ8: TERMOELÉCTRICA | FK8: TERMOELÉCTRICA | FL8: TERMOELÉCTRICA | FM8: TERMOELÉCTRICA | FN8: TERMOELÉCTRICA | FQ8: HIDROELÉCTRICA | FR8: HIDROELÉCTRICA | FS8: HIDROELÉCTRICA | FT8: HIDROELÉCTRICA | FU8: TERMOELÉCTRICA | FV8: TERMOELÉCTRICA | FW8: HIDROELÉCTRICA | FX8: HIDROELÉCTRICA
C9: HYDRO GLOBAL PERÚ S.A.C. | D9: ELECTROPERU | E9: ELECTROPERU | F9: ELECTROPERU | G9: ELECTROPERU | H9: ORAZUL ENERGY PERÚ | I9: ORAZUL ENERGY PERÚ | J9: TERMOSELVA | K9: TERMOSELVA | L9: KALLPA GENERACION S.A. | M9: KALLPA GENERACION S.A. | N9: KALLPA GENERACION S.A. | O9: KALLPA GENERACION S.A. | P9: KALLPA GENERACION S.A. | Q9: KALLPA GENERACION S.A. | R9: KALLPA GENERACION S.A. | S9: KALLPA GENERACION S.A. | T9: SHOUGESA | U9: SHOUGESA | V9: SHOUGESA | W9: SHOUGESA | X9: EGEMSA | Y9: EGESUR | Z9: EGESUR | AA9: EGESUR | AB9: EGASA | AC9: EGASA | AD9: EGASA | AE9: EGASA | AF9: EGASA | AG9: EGASA | AH9: EGASA | AI9: SAN GABAN | AJ9: CELEPSA | AK9: MINERA CERRO VERDE | AL9: PLANTA DE RESERVA FRIA DE GENERACION DE ETEN S.A. | AM9: PLANTA DE RESERVA FRIA DE GENERACION DE ETEN S.A. | AN9: EMPRESA DE GENERACION HUALLAGA | AO9: EMPRESA DE GENERACION HUALLAGA | AP9: LA VIRGEN | AQ9: CHINANGO S.A.C. | AR9: CHINANGO S.A.C. | AS9: HIDROELECTRICA HUANCHOR S.A.C. | AT9: CELEPSA RENOVABLES S.R.L. | AU9: INLAND ENERGY SAC | AV9: FENIX POWER PERÚ | AW9: FENIX POWER PERÚ | AX9: FENIX POWER PERÚ | AY9: STATKRAFT S.A | AZ9: STATKRAFT S.A | BA9: STATKRAFT S.A | BB9: STATKRAFT S.A | BC9: STATKRAFT S.A | BD9: STATKRAFT S.A | BE9: CENTRALES SANTA ROSA S.A.C. | BF9: CENTRALES SANTA ROSA S.A.C. | BG9: EMPRESA DE GENERACION HUANZA | BH9: ENEL GENERACION PIURA S.A. | BI9: ENEL GENERACION PIURA S.A. | BJ9: ENEL GENERACION PIURA S.A. | BK9: ENGIE ENERGIA PERU S.A.A. | BL9: ENGIE ENERGIA PERU S.A.A. | BM9: ENGIE ENERGIA PERU S.A.A. | BN9: ENGIE ENERGIA PERU S.A.A. | BO9: ENGIE ENERGIA PERU S.A.A. | BP9: ENGIE ENERGIA PERU S.A.A. | BQ9: ENGIE ENERGIA PERU S.A.A. | BR9: ENGIE ENERGIA PERU S.A.A. | BS9: ENGIE ENERGIA PERU S.A.A. | BT9: ENGIE ENERGIA PERU S.A.A. | BU9: ENGIE ENERGIA PERU S.A.A. | BV9: ENGIE ENERGIA PERU S.A.A. | BW9: ENGIE ENERGIA PERU S.A.A. | BX9: ENGIE ENERGIA PERU S.A.A. | BY9: INFRAESTRUCTURAS Y ENERGIAS DEL PERU S.A.C. | BZ9: INFRAESTRUCTURAS Y ENERGIAS DEL PERU S.A.C. | CA9: INVERSIONES SHAQSHA S.A.C. | CB9: ORYGEN PERU S.A.A. | CC9: ORYGEN PERU S.A.A. | CD9: ORYGEN PERU S.A.A. | CE9: ORYGEN PERU S.A.A. | CF9: ORYGEN PERU S.A.A. | CG9: ORYGEN PERU S.A.A. | CH9: ORYGEN PERU S.A.A. | CI9: ORYGEN PERU S.A.A. | CJ9: ORYGEN PERU S.A.A. | CK9: ORYGEN PERU S.A.A. | CL9: ORYGEN PERU S.A.A. | CM9: ORYGEN PERU S.A.A. | CN9: SAMAY I S.A.C | CO9: SAMAY I S.A.C | CP9: SAMAY I S.A.C | CQ9: SAMAY I S.A.C | CR9: TERMOCHILCA S.A.C. | CS9: TERMOCHILCA S.A.C. | CT9: TRANSMISION ANDINA DE GENERACION S.A.C. | CU9: TRANSMISION ANDINA DE GENERACION S.A.C. | CV9: CELARIS ENERGY S.A. | CW9: COLCA SOLAR S.A.C. | CX9: ENERGIA RENOVABLE DEL SUR S.A. | CY9: GR CORTARRAMA SOCIEDAD ANONIMA CERRADA | CZ9: GR TARUCA SOCIEDAD ANONIMA CERRADA | DA9: KONDU SAC | DB9: VARI ENERGIA S.A.C. | DC9: ORAZUL ENERGY PERÚ | DD9: ORAZUL ENERGY PERÚ | DE9: KALLPA GENERACION S.A. | DF9: KALLPA GENERACION S.A. | DG9: SAN GABAN | DH9: MAJA ENERGIA S.A.C. | DI9: EMPRESA DE GENERACION ELECTRICA CANCHAYLLO SAC | DJ9: EMPRESA DE GENERACION ELECTRICA SANTA ANA S.A.C. | DK9: EMPRESA ELECTRICA AGUA AZUL | DL9: EMPRESA ELECTRICA RIO DOBLE | DM9: HIDROCAÑETE S.A. | DN9: HUAURA POWER GROUP S.A. | DO9: MOQUEGUA FV S.A.C. | DP9: PANAMERICANA SOLAR SAC. | DQ9: PARQUE EOLICO MARCONA S.A.C. | DR9: PARQUE EOLICO TRES HERMANAS S.A.C. | DS9: TACNA SOLAR SAC. | DT9: ELECTRICA YANAPAMPA SAC | DU9: ANDEAN POWER S.A.C. | DV9: ASOCIACIÓN SANTA LUCIA DE CHACAS | DW9: ATRIA ENERGIA S.A.C. | DX9: COENERGY S.A.C. | DY9: EGEJUNIN | DZ9: EGEJUNIN | EA9: EGEJUNIN | EB9: EGEJUNIN | EC9: ENERGÍA EÓLICA S.A. | ED9: ENERGÍA EÓLICA S.A. | EE9: ENGIE ENERGIA PERU S.A.A. | EF9: ENGIE ENERGIA PERU S.A.A. | EG9: ENGIE ENERGIA PERU S.A.A. | EH9: ENGIE ENERGIA PERU S.A.A. | EI9: ENGIE ENERGIA PERU S.A.A. | EJ9: ENGIE ENERGIA PERU S.A.A. | EK9: GENERACIÓN ANDINA S.A.C. | EL9: GENERACIÓN ANDINA S.A.C. | EM9: GENERADORA DE ENERGÍA DEL PERÚ | EN9: GENERADORA DE ENERGÍA DEL PERÚ | EO9: GENERADORA DE ENERGÍA DEL PERÚ | EP9: GENERADORA DE ENERGÍA DEL PERÚ | EQ9: GR PAINO SOCIEDAD ANONIMA CERRADA | ER9: JOYA SOLAR S.A.C. | ES9: MAJES ARCUS S.A.C. | ET9: ORYGEN PERU S.A.A. | EU9: ORYGEN PERU S.A.A. | EV9: ORYGEN PERU S.A.A. | EW9: ORYGEN PERU S.A.A. | EX9: ORYGEN PERU S.A.A. | EY9: PETRAMAS | EZ9: PETRAMAS | FA9: PETRAMAS | FB9: PETRAMAS | FC9: REPARTICIÓN ARCUS S.A.C. | FD9: SINERSA | FE9: SINERSA | FF9: SINERSA | FG9: BIOENERGIA DEL CHIRA S.A. | FH9: GM OPERACIONES S.A.C. | FI9: GM OPERACIONES S.A.C. | FJ9: AGRO INDUSTRIAL PARAMONGA S.A. | FK9: AGROAURORA S.A.C. | FL9: AGROINDUSTRIAS SAN JACINTO S.A.A. | FM9: AGROLMOS SOCIEDAD ANONIMA - AGROLMOS S.A. | FN9: CASA GRANDE S.A.A. | FQ9: UNACEM PERU S.A. | FR9: ELECTRO ORIENTE | FS9: AGUAS Y ENERGIA PERU | FT9: ELECTRO ZAÑA S.A.C. | FU9: ELECTRONOROESTE S.A. | FV9: SDE PIURA | FW9: SINERSA | FX9: SINERSA
C10: SAN GABAN III | D10: MANTARO | E10: RESTITUCION | F10: TUMBES MAK 1 | G10: TUMBES MAK 2 | H10: CARHUAQUERO | I10: CAÑON DEL PATO | J10: AGUAYTIA TG1 | K10: AGUAYTIA TG2 | L10: KALLPA TG1 | M10: KALLPA TG2 | N10: KALLPA TG3 | O10: KALLPA TV | P10: LFLORES TG1 | Q10: LFLORES TV | R10: CERRO DEL AGUILA | S10: CERRODELAGUILAG4 | T10: SHOUGESA TV1 | U10: SHOUGESA TV2 | V10: SHOUGESA TV3 | W10: SHOUGESA CUMMINS | X10: MACHUPICCHU | Y10: ARICOTA 1 | Z10: ARICOTA 2 | AA10: INDEPENDENCIA | AB10: CHARCANI I,II,III | AC10: CHARCANI IV | AD10: CHARCANI V | AE10: CHARCANI VI | AF10: CHILINA TG | AG10: MOLLENDO 1, 2, 3 | AH10: CHILINA (SULZ 1,2) | AI10: SAN GABAN II | AJ10: PLATANAL | AK10: RECKA | AL10: RF ETEN TG1 | AM10: RF ETEN TG2 | AN10: CHAGLLA GP1 | AO10: CHAGLLA | AP10: LA VIRGEN | AQ10: CHIMAY | AR10: YANANGO | AS10: HUANCHOR | AT10: MARAÑON | AU10: STA TERESA | AV10: FENIX GT11 | AW10: FENIX GT12 | AX10: FENIX TV10 | AY10: YAUPI | AZ10: MALPASO | BA10: CAHUA | BB10: ARCATA | BC10: GALLITO CIEGO | BD10: CHEVES | BE10: SANTA ROSA 1 | BF10: SANTA ROSA 2 | BG10: HUANZA | BH10: MALACAS2 TG4 | BI10: MALACAS3 TG 5 | BJ10: MALACAS1 TG6 | BK10: RF ILO2 TG1 | BL10: RF ILO2 TG2 | BM10: RF ILO2 TG3 | BN10: YUNCAN | BO10: CHILCA1 TG1 | BP10: CHILCA1 TG2 | BQ10: CHILCA1 TG3 | BR10: CHILCA-TV | BS10: CHILCA2 TG41 | BT10: CHILCA2-TV | BU10: CTNEPI_TG41 | BV10: CTNEPI_TG42 | BW10: CTNEPI_TG43 | BX10: QUITARACSA | BY10: RF PTO MALDONADO | BZ10: RF PUCALLPA | CA10: PARIAC | CB10: HUINCO | CC10: MATUCANA | CD10: MOYOPAMPA | CE10: CALLAHUANCA | CF10: HUAMPANI | CG10: STA ROSA WEST TG7 | CH10: UTI_5 | CI10: UTI_6 | CJ10: VENTANILLA 3 | CK10: VENTANILLA 4 | CL10: VENTANILLA TV | CM10: STAROSA TG8 | CN10: PTO_BRVO TG1 | CO10: PTO_BRVO TG2 | CP10: PTO_BRVO TG3 | CQ10: PTO_BRVO TG4 | CR10: OLLEROS TG1 | CS10: OLLEROS TV | CT10: OROYA | CU10: PACHACHACA | CV10: MANTA I | CW10: CS YARUCAYA | CX10: SAN JUAN | CY10: MATARANI | CZ10: DUNA | DA10: CARHUAQUERO (CS) | DB10: ANASHIRONI | DC10: CARHUAQUERO4 | DD10: CAÑA BRAVA | DE10: SUNNY | DF10: SUNNY EXPANSION | DG10: TUPURI | DH10: RONCADOR | DI10: CANCHAYLLO | DJ10: RENOVANDESH1 | DK10: POTRERO | DL10: PIZARRAS | DM10: NIMPERIAL | DN10: YARUCAYA | DO10: MOQUEGUA-SOLAR | DP10: PANAMERICANA-SOLAR | DQ10: PQE-EOLICO-MARCONA | DR10: PQE-EOLICO-3-HERMANAS | DS10: TACNA-SOLAR | DT10: YANAPAMPA | DU10: CARHUAC | DV10: HUALLIN | DW10: PURMACANA | DX10: COENERGY | DY10: HUASAHUASI | DZ10: STACRUZ_1_2 | EA10: RUNATULLO_II | EB10: RUNATULLO_III | EC10: PQE-EOLICO-TALARA | ED10: PQE-EOLICO-CUPISNIQUE | EE10: INTIPAMPA | EF10: PUNTA LOMITAS-BL1 | EG10: PUNTA LOMITAS-BL2 | EH10: PUN LOMITAS_EXP-BL1 | EI10: PUN LOMITAS_EXP-BL2 | EJ10: EXPANSIÓN INTIPAMPA | EK10: 8AGOSTO | EL10: EL CARMEN | EM10: LA JOYA | EN10: ANGEL_I | EO10: ANGEL_II | EP10: ANGEL_III | EQ10: HUAMBOS | ER10: SAN MARTIN SOLAR | ES10: MAJES | ET10: RUBI | EU10: CH_HER1 | EV10: WAYRA-I | EW10: WAYRA EXTENSION | EX10: CLEMESI | EY10: HUAYCOLORO | EZ10: CALLAO | FA10: DONA_CATALINA | FB10: LAGRINGAV | FC10: REPARTICION | FD10: POECHOS2 | FE10: CHANCAY | FF10: RUCUY | FG10: CANA BRAVA | FH10: REFINERIA TALARA TV1 | FI10: REFINERÍA TALARA TV2 | FJ10: PARAMONGA | FK10: MAPLE | FL10: SAN_JACINTO | FM10: AGROLMOS | FN10: CASA GRANDE | FO10: MW | FQ10: CARPAPATA | FR10: CENTRALES ELOR | FS10: PIAS1 | FT10: ZANA | FU10: TABLAZO | FV10: TALLANCA | FW10: CURUMUY | FX10: POECHOS1 | FY10: MW
A11: 21/02/2026 | B11: 00:30 | C11: 198.2 | D11: 625.1 | E11: 213.1 | H11: 88.1 | I11: 230.1 | J11: 26.6 | L11: 176 | M11: 182.2 | N11: 180.8 | O11: 263 | P11: 204.8 | Q11: 108.4 | R11: 370.8 | S11: 9.9 | T11: 13.9 | X11: 164.1 | Y11: 8.269 | Z11: 6.036 | AA11: 0 | AB11: 5.47 | AD11: 142.12 | AI11: 109.4 | AJ11: 214.8 | AN11: 6.5 | AO11: 458.3 | AP11: 81.6 | AQ11: 150 | AR11: 40.9 | AS11: 18.4 | AT11: 18.8 | AU11: 89.2 | AV11: 175.9 | AW11: 176.2 | AX11: 185.5 | AY11: 104.9 | AZ11: 44 | BA11: 44 | BB11: 2 | BC11: 31.6 | BD11: 166.7 | BG11: 61.1 | BJ11: 45.4 | BN11: 125.8 | BO11: 0 | BP11: 0 | BQ11: 0 | BS11: 72.2 | BT11: 34.9 | BY11: 0 | CA11: 2.1 | CB11: 255.4 | CC11: 128.6 | CD11: 61.1 | CE11: 63.8 | CF11: 0 | CJ11: 113.7 | CL11: 57.8 | CM11: 0 | CR11: 206.1 | CS11: 98.6 | CT11: 7.2 | CW11: 0 | CX11: 4.8 | CY11: 0 | CZ11: 1.8 | DA11: 0 | DB11: 20.1 | DC11: 10 | DD11: 5.5 | DE11: 0 | DG11: 2.2 | DH11: 2 | DI11: 5 | DJ11: 20.1 | DK11: 20 | DL11: 18.9 | DM11: 3.6 | DN11: 18.5 | DO11: 0 | DP11: 0 | DQ11: 1.1 | DR11: 2.4 | DS11: 0 | DT11: 3.1 | DU11: 20 | DV11: 3.2 | DX11: 0 | DY11: 19.8 | DZ11: 13.1 | EA11: 20.2 | EB11: 20.2 | EC11: 1.9 | ED11: 18.6 | EE11: 0 | EF11: 0 | EG11: 0.9 | EH11: 0 | EI11: 0 | EJ11: 0 | EK11: 0 | EL11: 0 | EN11: 20.4 | EO11: 20.4 | EP11: 20 | EQ11: 1.8 | ER11: 0 | ES11: 0 | ET11: 0 | EU11: 0 | EV11: 9.5 | EW11: 7 | EX11: 0 | EY11: 3 | EZ11: 2.4 | FA11: 2 | FB11: 0.7 | FC11: 0 | FD11: 8.1 | FE11: 20 | FF11: 20 | FG11: 8.9 | FI11: 29.8 | FJ11: 16 | FK11: 12.49 | FL11: 8.22 | FM11: 4.97 | FN11: 14.69 | FO11: 7156.865 | FQ11: 24.41085 | FR11: 7.934 | FS11: 9.952 | FT11: 0 | FU11: 24.19363 | FV11: 18.95134 | FW11: 11.7 | FX11: 16 | FY11: 113.14182
A12: 21/02/2026 | B12: 01:00 | C12: 202 | D12: 635.7 | E12: 216.7 | H12: 90 | I12: 232.5 | J12: 27.2 | L12: 135.2 | M12: 134.2 | N12: 134.6 | O12: 231.4 | P12: 203.5 | Q12: 107.9 | R12: 380.5 | S12: 10.2 | T12: 15.8 | X12: 167 | Y12: 6.678 | Z12: 6.698 | AA12: 0 | AB12: 6.17 | AD12: 142.9 | AI12: 110 | AJ12: 211.4 | AN12: 6.5 | AO12: 462.6 | AP12: 81.5 | AQ12: 151.3 | AR12: 42.1 | AS12: 18.4 | AT12: 18.8 | AU12: 88.8 | AV12: 179.6 | AW12: 179.9 | AX12: 184.8 | AY12: 107.2 | AZ12: 45.3 | BA12: 45.7 | BB12: 2 | BC12: 31.5 | BD12: 171.6 | BG12: 63.4 | BJ12: 45.4 | BN12: 127.5 | BO12: 0 | BP12: 0 | BQ12: 0 | BS12: 71.7 | BT12: 34.8 | BY12: 0 | CA12: 2.1 | CB12: 262.4 | CC12: 132.2 | CD12: 62.7 | CE12: 64.4 | CF12: 0 | CJ12: 113.2 | CL12: 56.7 | CM12: 0 | CR12: 206.3 | CS12: 98.6 | CT12: 7.2 | CW12: 0 | CX12: 7.2 | CY12: 0 | CZ12: 2 | DA12: 0 | DB12: 20.4 | DC12: 9.9 | DD12: 5.5 | DE12: 0 | DG12: 2.2 | DH12: 2 | DI12: 4.9 | DJ12: 20.6 | DK12: 20 | DL12: 18.9 | DM12: 3.5 | DN12: 18.5 | DO12: 0 | DP12: 0 | DQ12: 0.6 | DR12: 1.8 | DS12: 0 | DT12: 3.1 | DU12: 20.1 | DV12: 3.2 | DX12: 0 | DY12: 19.8 | DZ12: 13.1 | EA12: 20.3 | EB12: 20.2 | EC12: 3.5 | ED12: 13.2 | EE12: 0 | EF12: 0 | EG12: 0 | EH12: 0 | EI12: 0 | EJ12: 0 | EK12: 0 | EL12: 0 | EN12: 20.4 | EO12: 20.4 | EP12: 20 | EQ12: 2 | ER12: 0 | ES12: 0 | ET12: 0 | EU12: 0 | EV12: 3.3 | EW12: 1.7 | EX12: 0 | EY12: 3 | EZ12: 2.4 | FA12: 2 | FB12: 0.7 | FC12: 0 | FD12: 8.2 | FE12: 20 | FF12: 20 | FG12: 8.8 | FI12: 30 | FJ12: 16.2 | FK12: 12.49 | FL12: 7.88 | FM12: 4.97 | FN12: 15.64 | FO12: 7049.026 | FQ12: 24.41123 | FR12: 7.931 | FS12: 9.922 | FT12: 0 | FU12: 24.25291 | FV12: 18.95101 | FW12: 11.7 | FX12: 16 | FY12: 113.16815
A13: 21/02/2026 | B13: 01:30 | C13: 202.4 | D13: 632.6 | E13: 216.1 | H13: 90.1 | I13: 231.8 | J13: 26.9 | L13: 118.6 | M13: 117.6 | N13: 119.2 | O13: 220.9 | P13: 204.6 | Q13: 108.5 | R13: 375.2 | S13: 10.2 | T13: 16.1 | X13: 161.3 | Y13: 7.305 | Z13: 5.948 | AA13: 0 | AB13: 6.39 | AD13: 142.54 | AI13: 110 | AJ13: 177.3 | AN13: 6.5 | AO13: 461.1 | AP13: 81.5 | AQ13: 151.2 | AR13: 41.9 | AS13: 18.5 | AT13: 18.8 | AU13: 89.9 | AV13: 180.4 | AW13: 180.6 | AX13: 184.9 | AY13: 106 | AZ13: 45 | BA13: 45.3 | BB13: 2 | BC13: 31.6 | BD13: 171 | BG13: 63.2 | BJ13: 14.4 | BN13: 127.5 | BO13: 0 | BP13: 0 | BQ13: 0 | BS13: 71.9 | BT13: 34.9 | BY13: 0 | CA13: 2.1 | CB13: 244.3 | CC13: 126.8 | CD13: 62.6 | CE13: 64.3 | CF13: 0 | CJ13: 113.5 | CL13: 56.4 | CM13: 0 | CR13: 206.2 | CS13: 98.9 | CT13: 7.2 | CW13: 0 | CX13: 14.5 | CY13: 0 | CZ13: 1.8 | DA13: 0 | DB13: 20.4 | DC13: 9.9 | DD13: 5.5 | DE13: 0 | DG13: 2.2 | DH13: 2 | DI13: 5.1 | DJ13: 20.6 | DK13: 20 | DL13: 18.9 | DM13: 3.5 | DN13: 18.5 | DO13: 0 | DP13: 0 | DQ13: 1.4 | DR13: 4 | DS13: 0 | DT13: 3.1 | DU13: 20.1 | DV13: 3.2 | DX13: 0 | DY13: 19.8 | DZ13: 13 | EA13: 20.2 | EB13: 20.2 | EC13: 2 | ED13: 7.3 | EE13: 0 | EF13: 0 | EG13: 0 | EH13: 0 | EI13: 0 | EJ13: 0 | EK13: 0 | EL13: 0 | EN13: 20.4 | EO13: 20.4 | EP13: 20 | EQ13: 1.8 | ER13: 0 | ES13: 0 | ET13: 0 | EU13: 0 | EV13: 1.7 | EW13: 0.3 | EX13: 0 | EY13: 3 | EZ13: 2.4 | FA13: 2 | FB13: 0.7 | FC13: 0 | FD13: 8.1 | FE13: 20 | FF13: 19.9 | FG13: 8.5 | FI13: 29.8 | FJ13: 16.5 | FK13: 12.49 | FL13: 8.23 | FM13: 4.97 | FN13: 15.42 | FO13: 6885.793 | FQ13: 24.41372 | FR13: 7.927 | FS13: 9.908 | FT13: 0 | FU13: 24.20662 | FV13: 18.95089 | FW13: 11.8 | FX13: 16 | FY13: 113.20623
A14: 21/02/2026 | B14: 02:00 | C14: 203.7 | D14: 632.8 | E14: 216 | H14: 90 | I14: 233 | J14: 27.3 | L14: 121.4 | M14: 120.3 | N14: 121.3 | O14: 209.6 | P14: 202.5 | Q14: 108.1 | R14: 379.6 | S14: 10.3 | T14: 16.1 | X14: 168.6 | Y14: 7.301 | Z14: 5.408 | AA14: 0 | AB14: 6.5 | AD14: 142.78 | AI14: 110.1 | AJ14: 165.3 | AN14: 6.5 | AO14: 458.9 | AP14: 81.5 | AQ14: 151.2 | AR14: 42 | AS14: 18.4 | AT14: 18.8 | AU14: 92.5 | AV14: 179.9 | AW14: 179.9 | AX14: 185.1 | AY14: 105.9 | AZ14: 45.4 | BA14: 45.2 | BB14: 2 | BC14: 31.4 | BD14: 170.5 | BG14: 63.1 | BJ14: 0 | BN14: 127.5 | BO14: 0 | BP14: 0 | BQ14: 0 | BS14: 72.1 | BT14: 35 | BY14: 0 | CA14: 2.1 | CB14: 244.7 | CC14: 125.8 | CD14: 62.3 | CE14: 64.4 | CF14: 30.1 | CJ14: 69.6 | CL14: 0 | CM14: 0 | CR14: 206.1 | CS14: 98.7 | CT14: 7.2 | CW14: 0 | CX14: 16.4 | CY14: 0 | CZ14: 2 | DA14: 0 | DB14: 20.3 | DC14: 9.9 | DD14: 5.5 | DE14: 0 | DG14: 2.2 | DH14: 2.7 | DI14: 5.1 | DJ14: 20.4 | DK14: 20 | DL14: 18.9 | DM14: 3.5 | DN14: 18.5 | DO14: 0 | DP14: 0 | DQ14: 1.6 | DR14: 3.6 | DS14: 0 | DT14: 3.1 | DU14: 20.1 | DV14: 3.2 | DX14: 0 | DY14: 19.8 | DZ14: 13 | EA14: 20.3 | EB14: 20.2 | EC14: 0 | ED14: 7.3 | EE14: 0 | EF14: 0 | EG14: 1.5 | EH14: 0 | EI14: 0 | EJ14: 0 | EK14: 0 | EL14: 0 | EN14: 20.4 | EO14: 20.4 | EP14: 20 | EQ14: 2 | ER14: 0 | ES14: 0 | ET14: 0 | EU14: 0 | EV14: 1.7 | EW14: 1.8 | EX14: 0 | EY14: 3 | EZ14: 2.4 | FA14: 2 | FB14: 0.7 | FC14: 0 | FD14: 8.1 | FE14: 20 | FF14: 20 | FG14: 8.2 | FI14: 29.8 | FJ14: 17 | FK14: 12.48 | FL14: 8.07 | FM14: 4.97 | FN14: 15.69 | FO14: 6799.599 | FQ14: 24.41212 | FR14: 7.926 | FS14: 9.872 | FT14: 0 | FU14: 24.23611 | FV14: 18.95041 | FW14: 11.7 | FX14: 16 | FY14: 113.09664
A15: 21/02/2026 | B15: 02:30 | C15: 203.5 | D15: 633.6 | E15: 216.4 | H15: 90.4 | I15: 233 | J15: 0 | L15: 117.2 | M15: 116.8 | N15: 117.4 | O15: 222 | P15: 161.5 | Q15: 95.9 | R15: 376 | S15: 10.3 | T15: 16.1 | X15: 167.2 | Y15: 7.616 | Z15: 5.367 | AA15: 0 | AB15: 6.51 | AD15: 142.53 | AI15: 110.3 | AJ15: 197.6 | AN15: 6.5 | AO15: 460.8 | AP15: 81.5 | AQ15: 151.5 | AR15: 42 | AS15: 18.5 | AT15: 18.8 | AU15: 91.8 | AV15: 180.1 | AW15: 180.5 | AX15: 184.7 | AY15: 106.1 | AZ15: 44 | BA15: 45.3 | BB15: 2 | BC15: 31.4 | BD15: 170.6 | BG15: 63.2 | BJ15: 0 | BN15: 127.4 | BO15: 0 | BP15: 0 | BQ15: 0 | BS15: 40.2 | BT15: 27.7 | BY15: 0 | CA15: 2.1 | CB15: 244.1 | CC15: 126.2 | CD15: 62.6 | CE15: 64.5 | CF15: 30 | CJ15: 0 | CL15: 0 | CM15: 0 | CR15: 206.6 | CS15: 99 | CT15: 7.2 | CW15: 0 | CX15: 15.3 | CY15: 0 | CZ15: 2 | DA15: 0 | DB15: 20.3 | DC15: 9.9 | DD15: 5.5 | DE15: 0 | DG15: 2.2 | DH15: 2.7 | DI15: 5.1 | DJ15: 20.4 | DK15: 20 | DL15: 18.9 | DM15: 3.5 | DN15: 18.5 | DO15: 0 | DP15: 0 | DQ15: 0.8 | DR15: 2.4 | DS15: 0 | DT15: 3.1 | DU15: 20.2 | DV15: 3.2 | DX15: 0 | DY15: 19.8 | DZ15: 13 | EA15: 20.3 | EB15: 20.3 | EC15: 0 | ED15: 7.7 | EE15: 0 | EF15: 0 | EG15: 0 | EH15: 0 | EI15: 0 | EJ15: 0 | EK15: 0 | EL15: 0 | EN15: 20.4 | EO15: 20.4 | EP15: 20 | EQ15: 2 | ER15: 0 | ES15: 0 | ET15: 0 | EU15: 0 | EV15: 0 | EW15: 0 | EX15: 0 | EY15: 3 | EZ15: 2.4 | FA15: 2 | FB15: 0.7 | FC15: 0 | FD15: 8.1 | FE15: 20 | FF15: 20 | FG15: 8.2 | FI15: 30.3 | FJ15: 16.7 | FK15: 12.5 | FL15: 8.04 | FM15: 4.97 | FN15: 16.51 | FO15: 6635.443 | FQ15: 24.4144 | FR15: 7.921 | FS15: 9.84 | FT15: 0 | FU15: 24.26561 | FV15: 18.95056 | FW15: 11.8 | FX15: 15.7 | FY15: 112.89157
A16: 21/02/2026 | B16: 03:00 | C16: 198.5 | D16: 623.5 | E16: 212.3 | H16: 88.1 | I16: 228.3 | J16: 0 | L16: 124.4 | M16: 124.3 | N16: 124.1 | O16: 242.4 | P16: 111.2 | Q16: 71.9 | R16: 526.8 | S16: 10 | T16: 16.1 | X16: 163.5 | Y16: 7.136 | Z16: 4.929 | AA16: 0 | AB16: 6.51 | AD16: 141.06 | AI16: 109.8 | AJ16: 219.7 | AN16: 6.5 | AO16: 454.6 | AP16: 81.5 | AQ16: 134.8 | AR16: 41 | AS16: 18.4 | AT16: 18.8 | AU16: 88.2 | AV16: 176.1 | AW16: 176.5 | AX16: 183.1 | AY16: 105 | AZ16: 42.9 | BA16: 41 | BB16: 2 | BC16: 31.4 | BD16: 167 | BG16: 61.2 | BJ16: 0 | BN16: 126 | BO16: 0 | BP16: 0 | BQ16: 0 | BS16: 40.1 | BT16: 28 | BY16: 0 | CA16: 2.1 | CB16: 231.6 | CC16: 116.3 | CD16: 61.2 | CE16: 63.9 | CF16: 29.5 | CJ16: 0 | CL16: 0 | CM16: 0 | CR16: 206.8 | CS16: 99.2 | CT16: 7.2 | CW16: 0 | CX16: 16.4 | CY16: 0 | CZ16: 0.8 | DA16: 0 | DB16: 20.1 | DC16: 9.9 | DD16: 5.5 | DE16: 0 | DG16: 2.2 | DH16: 2.7 | DI16: 5.1 | DJ16: 20.1 | DK16: 20 | DL16: 18.9 | DM16: 3.6 | DN16: 18.5 | DO16: 0 | DP16: 0 | DQ16: 1.9 | DR16: 5.5 | DS16: 0 | DT16: 3.2 | DU16: 20.2 | DV16: 3.2 | DX16: 0 | DY16: 19.8 | DZ16: 13 | EA16: 20.2 | EB16: 20.2 | EC16: 0.4 | ED16: 9.3 | EE16: 0 | EF16: 0 | EG16: 0 | EH16: 0 | EI16: 0 | EJ16: 0 | EK16: 0 | EL16: 0 | EN16: 20.4 | EO16: 20.4 | EP16: 20 | EQ16: 0.8 | ER16: 0 | ES16: 0 | ET16: 0 | EU16: 0.6 | EV16: 0 | EW16: 0 | EX16: 0 | EY16: 3 | EZ16: 2.4 | FA16: 2 | FB16: 0.7 | FC16: 0 | FD16: 8.1 | FE16: 20 | FF16: 20 | FG16: 8.5 | FI16: 30.8 | FJ16: 17.2 | FK16: 12.5 | FL16: 7.33 | FM16: 4.97 | FN16: 15.79 | FO16: 6672.625 | FQ16: 24.4113 | FR16: 7.915 | FS16: 9.778 | FT16: 13.2 | FU16: 24.37856 | FV16: 18.9509 | FW16: 11.7 | FX16: 15.8 | FY16: 126.13376
A17: 21/02/2026 | B17: 03:30 | C17: 199.6 | D17: 623.9 | E17: 212.6 | H17: 89.2 | I17: 230.7 | J17: 0 | L17: 114.3 | M17: 114.4 | N17: 114.6 | O17: 214.9 | P17: 108.8 | Q17: 68.1 | R17: 547.5 | S17: 10.1 | T17: 16.3 | X17: 150.2 | Y17: 7.173 | Z17: 5.007 | AA17: 0 | AB17: 6.51 | AD17: 141.69 | AI17: 109.8 | AJ17: 162.1 | AN17: 6.5 | AO17: 459.9 | AP17: 81.4 | AQ17: 150.2 | AR17: 41 | AS17: 18.4 | AT17: 18.8 | AU17: 78.6 | AV17: 177.2 | AW17: 177.8 | AX17: 184 | AY17: 104.9 | AZ17: 42.8 | BA17: 44.7 | BB17: 2 | BC17: 31.5 | BD17: 166.7 | BG17: 61.5 | BJ17: 0 | BN17: 126.1 | BO17: 0 | BP17: 0 | BQ17: 0 | BS17: 39.9 | BT17: 28.1 | BY17: 0 | CA17: 2.1 | CB17: 227.1 | CC17: 115.8 | CD17: 66.2 | CE17: 64.1 | CF17: 29.6 | CJ17: 0 | CL17: 0 | CM17: 0 | CR17: 153.6 | CS17: 85.5 | CT17: 7.3 | CW17: 0 | CX17: 17.4 | CY17: 0 | CZ17: 1.5 | DA17: 0 | DB17: 20.3 | DC17: 10 | DD17: 5.4 | DE17: 0 | DG17: 2.2 | DH17: 2.1 | DI17: 5.1 | DJ17: 20.2 | DK17: 20 | DL17: 18.9 | DM17: 3.6 | DN17: 18.5 | DO17: 0 | DP17: 0 | DQ17: 1.9 | DR17: 4.3 | DS17: 0 | DT17: 3.2 | DU17: 20.1 | DV17: 3.2 | DX17: 0 | DY17: 19.8 | DZ17: 13 | EA17: 20.3 | EB17: 20.2 | EC17: 1.5 | ED17: 11 | EE17: 0 | EF17: 0 | EG17: 0 | EH17: 0 | EI17: 0 | EJ17: 0 | EK17: 0 | EL17: 0 | EN17: 20.4 | EO17: 20.4 | EP17: 20 | EQ17: 1.5 | ER17: 0 | ES17: 0 | ET17: 0 | EU17: 0.6 | EV17: 0 | EW17: 0 | EX17: 0 | EY17: 3 | EZ17: 2.4 | FA17: 2 | FB17: 0.7 | FC17: 0 | FD17: 8.1 | FE17: 19.9 | FF17: 19.8 | FG17: 8.9 | FI17: 30.7 | FJ17: 17.2 | FK17: 12.5 | FL17: 7.21 | FM17: 4.97 | FN17: 15.86 | FO17: 6520.62 | FQ17: 24.41109 | FR17: 7.913 | FS17: 9.742 | FT17: 13.2 | FU17: 24.4672 | FV17: 18.9513 | FW17: 11.7 | FX17: 15.9 | FY17: 126.28459
A18: 21/02/2026 | B18: 04:00 | C18: 202.1 | D18: 634.1 | E18: 216 | H18: 91.2 | I18: 232.7 | J18: 0 | L18: 142.2 | M18: 141.7 | N18: 141.9 | O18: 226.8 | P18: 107.6 | Q18: 68.1 | R18: 561.4 | S18: 10.2 | T18: 16.2 | X18: 166.5 | Y18: 7.596 | Z18: 5.229 | AA18: 0 | AB18: 6.51 | AD18: 143.42 | AI18: 110.1 | AJ18: 195.4 | AN18: 6.5 | AO18: 460.6 | AP18: 81.6 | AQ18: 151.2 | AR18: 42.1 | AS18: 18.4 | AT18: 18.8 | AU18: 91.6 | AV18: 132.9 | AW18: 132.1 | AX18: 162.4 | AY18: 105.7 | AZ18: 43.3 | BA18: 45.9 | BB18: 2 | BC18: 31.8 | BD18: 171.4 | BG18: 63 | BJ18: 0 | BN18: 127.2 | BO18: 0 | BP18: 0 | BQ18: 0 | BS18: 40.4 | BT18: 28.3 | BY18: 0 | CA18: 2.1 | CB18: 270.5 | CC18: 131.8 | CD18: 66.2 | CE18: 64.5 | CF18: 30.1 | CJ18: 0 | CL18: 0 | CM18: 0 | CR18: 137.2 | CS18: 77.6 | CT18: 7.2 | CW18: 0 | CX18: 13.7 | CY18: 0 | CZ18: 1 | DA18: 0 | DB18: 20.2 | DC18: 9.9 | DD18: 5.5 | DE18: 0 | DG18: 2.2 | DH18: 2.5 | DI18: 5.1 | DJ18: 20.2 | DK18: 20 | DL18: 18.9 | DM18: 3.6 | DN18: 18.5 | DO18: 0 | DP18: 0 | DQ18: 1.2 | DR18: 2.9 | DS18: 0 | DT18: 3.2 | DU18: 20.3 | DV18: 3.2 | DX18: 0 | DY18: 19.8 | DZ18: 13 | EA18: 20.4 | EB18: 20.2 | EC18: 0.8 | ED18: 6.4 | EE18: 0 | EF18: 0 | EG18: 0 | EH18: 0 | EI18: 0 | EJ18: 0 | EK18: 0 | EL18: 0 | EN18: 20.4 | EO18: 20.4 | EP18: 20 | EQ18: 1 | ER18: 0 | ES18: 0 | ET18: 0 | EU18: 0.6 | EV18: 0 | EW18: 0 | EX18: 0 | EY18: 3 | EZ18: 2.4 | FA18: 2 | FB18: 0.7 | FC18: 0 | FD18: 8 | FE18: 20.1 | FF18: 20 | FG18: 8.9 | FI18: 31.2 | FJ18: 17.3 | FK18: 12.49 | FL18: 6.76 | FM18: 4.97 | FN18: 16.4 | FO18: 6640.675 | FQ18: 24.41521 | FR18: 7.914 | FS18: 9.72 | FT18: 13.2 | FU18: 24.29612 | FV18: 18.95074 | FW18: 11.7 | FX18: 15.7 | FY18: 125.89607
A19: 21/02/2026 | B19: 04:30 | C19: 206.1 | D19: 636.3 | E19: 216.4 | H19: 92.1 | I19: 235.6 | J19: 0 | L19: 129.8 | M19: 130.4 | N19: 129.3 | O19: 229.7 | P19: 109.4 | Q19: 68.4 | R19: 563.4 | S19: 10.3 | T19: 16.1 | X19: 169.5 | Y19: 7.684 | Z19: 5.837 | AA19: 0 | AB19: 6.51 | AD19: 143.21 | AI19: 110.3 | AJ19: 218.9 | AN19: 6.5 | AO19: 461.4 | AP19: 81.4 | AQ19: 152.4 | AR19: 42.3 | AS19: 18.4 | AT19: 18.8 | AU19: 93.1 | AV19: 125.3 | AW19: 125.8 | AX19: 152.4 | AY19: 106.8 | AZ19: 44.8 | BA19: 46.4 | BB19: 2 | BC19: 31.8 | BD19: 172.2 | BG19: 64.1 | BJ19: 0 | BN19: 128.1 | BO19: 0 | BP19: 0 | BQ19: 0 | BS19: 40.4 | BT19: 28.2 | BY19: 0 | CA19: 2.1 | CB19: 271.4 | CC19: 133.8 | CD19: 66.8 | CE19: 64.6 | CF19: 30.4 | CJ19: 0 | CL19: 0 | CM19: 0 | CR19: 137.2 | CS19: 77.6 | CT19: 7.2 | CW19: 0 | CX19: 18.4 | CY19: 0 | CZ19: 1.6 | DA19: 0 | DB19: 20.5 | DC19: 9.8 | DD19: 5.4 | DE19: 0 | DG19: 2.2 | DH19: 2.6 | DI19: 5 | DJ19: 20.6 | DK19: 20 | DL19: 18.9 | DM19: 3.6 | DN19: 18.5 | DO19: 0 | DP19: 0 | DQ19: 1.5 | DR19: 4.4 | DS19: 0 | DT19: 3.2 | DU19: 20.2 | DV19: 3.2 | DX19: 0 | DY19: 19.8 | DZ19: 13 | EA19: 20.3 | EB19: 20.3 | EC19: 0.1 | ED19: 3.1 | EE19: 0 | EF19: 0 | EG19: 0.2 | EH19: 0 | EI19: 0 | EJ19: 0 | EK19: 0 | EL19: 0 | EN19: 20.4 | EO19: 20.4 | EP19: 20 | EQ19: 1.6 | ER19: 0 | ES19: 0 | ET19: 0 | EU19: 0.6 | EV19: 0 | EW19: 0 | EX19: 0 | EY19: 3 | EZ19: 2.4 | FA19: 2 | FB19: 0.7 | FC19: 0 | FD19: 8 | FE19: 20 | FF19: 20 | FG19: 8.4 | FI19: 30.9 | FJ19: 16.7 | FK19: 12.5 | FL19: 5.92 | FM19: 4.97 | FN19: 16.66 | FO19: 6640.491 | FQ19: 24.41036 | FR19: 7.909 | FS19: 9.684 | FT19: 13.2 | FU19: 24.368 | FV19: 18.95083 | FW19: 11.9 | FX19: 15.8 | FY19: 126.22219
A20: 21/02/2026 | B20: 05:00 | C20: 205.1 | D20: 625.3 | E20: 212.9 | H20: 92.5 | I20: 230.4 | J20: 0 | L20: 111.6 | M20: 112.1 | N20: 111.3 | O20: 224.4 | P20: 109.5 | Q20: 68.3 | R20: 547.1 | S20: 10.5 | T20: 16.4 | X20: 168 | Y20: 7.353 | Z20: 5.704 | AA20: 0 | AB20: 6.48 | AD20: 142.03 | AI20: 110.2 | AJ20: 209.5 | AN20: 6.5 | AO20: 460.4 | AP20: 81.5 | AQ20: 155.1 | AR20: 41.7 | AS20: 18.4 | AT20: 18.8 | AU20: 90.8 | AV20: 162.1 | AW20: 161.8 | AX20: 170.1 | AY20: 105.9 | AZ20: 45.3 | BA20: 45.7 | BB20: 2 | BC20: 31.7 | BD20: 167.9 | BG20: 63.3 | BJ20: 0 | BN20: 127.6 | BO20: 0 | BP20: 0 | BQ20: 0 | BS20: 39.5 | BT20: 28.1 | BY20: 0 | CA20: 2.1 | CB20: 236.8 | CC20: 121.5 | CD20: 66.1 | CE20: 64.6 | CF20: 30.3 | CJ20: 0 | CL20: 0 | CM20: 0 | CR20: 137.2 | CS20: 77.7 | CT20: 7.2 | CW20: 0 | CX20: 25.7 | CY20: 0 | CZ20: 1.6 | DA20: 0 | DB20: 20.3 | DC20: 9.9 | DD20: 5.5 | DE20: 0 | DG20: 2.2 | DH20: 2.6 | DI20: 5 | DJ20: 20.1 | DK20: 20 | DL20: 18.9 | DM20: 3.7 | DN20: 18.5 | DO20: 0 | DP20: 0 | DQ20: 1.8 | DR20: 3.6 | DS20: 0 | DT20: 3.1 | DU20: 20.2 | DV20: 3.2 | DX20: 0 | DY20: 19.8 | DZ20: 13 | EA20: 20.3 | EB20: 20.2 | EC20: 0.4 | ED20: 3.9 | EE20: 0 | EF20: 0 | EG20: 0 | EH20: 0 | EI20: 0 | EJ20: 0 | EK20: 0 | EL20: 0 | EN20: 20.4 | EO20: 20.4 | EP20: 20 | EQ20: 1.6 | ER20: 0 | ES20: 0 | ET20: 0 | EU20: 0.6 | EV20: 0 | EW20: 0 | EX20: 0 | EY20: 3 | EZ20: 2.4 | FA20: 2 | FB20: 0.7 | FC20: 0 | FD20: 8 | FE20: 20 | FF20: 20 | FG20: 8.5 | FI20: 30.7 | FJ20: 16.6 | FK20: 12.51 | FL20: 8.44 | FM20: 4.98 | FN20: 16.2 | FO20: 6574.897 | FQ20: 24.40671 | FR20: 7.909 | FS20: 9.65 | FT20: 13.2 | FU20: 24.40064 | FV20: 18.95075 | FW20: 11.7 | FX20: 15.9 | FY20: 126.1171
A21: 21/02/2026 | B21: 05:30 | C21: 201.3 | D21: 631 | E21: 215.5 | H21: 89.1 | I21: 232.7 | J21: 0 | L21: 126 | M21: 125.9 | N21: 125.9 | O21: 227.4 | P21: 109.3 | Q21: 68.2 | R21: 557 | S21: 10.1 | T21: 16.4 | X21: 164.9 | Y21: 7.384 | Z21: 5.503 | AA21: 0 | AB21: 6.51 | AD21: 142.25 | AI21: 110.3 | AJ21: 213.3 | AN21: 6.5 | AO21: 462.1 | AP21: 81.6 | AQ21: 151.1 | AR21: 41.7 | AS21: 18.4 | AT21: 18.8 | AU21: 88.8 | AV21: 158.3 | AW21: 158.5 | AX21: 171.3 | AY21: 105.9 | AZ21: 43.2 | BA21: 45.7 | BB21: 2 | BC21: 31.1 | BD21: 169.6 | BG21: 62.5 | BJ21: 0 | BN21: 127.1 | BO21: 0 | BP21: 0 | BQ21: 0 | BS21: 40.3 | BT21: 28.2 | BY21: 0 | CA21: 2.1 | CB21: 262.8 | CC21: 129.7 | CD21: 65.7 | CE21: 64.4 | CF21: 30 | CJ21: 0 | CL21: 0 | CM21: 0 | CR21: 137.2 | CS21: 77.6 | CT21: 7.2 | CW21: 0 | CX21: 22 | CY21: 0 | CZ21: 2 | DA21: 0 | DB21: 20.3 | DC21: 10 | DD21: 5.5 | DE21: 0 | DG21: 2.2 | DH21: 2 | DI21: 5.1 | DJ21: 20.4 | DK21: 20 | DL21: 18.9 | DM21: 3.6 | DN21: 18.5 | DO21: 0.1 | DP21: 0 | DQ21: 1.2 | DR21: 4 | DS21: 0 | DT21: 3 | DU21: 20.2 | DV21: 3.2 | DX21: 0 | DY21: 19.8 | DZ21: 13 | EA21: 20.2 | EB21: 20.2 | EC21: 0.1 | ED21: 3 | EE21: 0 | EF21: 0 | EG21: 0 | EH21: 0 | EI21: 0 | EJ21: 0 | EK21: 0 | EL21: 0 | EN21: 20.4 | EO21: 20.4 | EP21: 20 | EQ21: 2 | ER21: 0 | ES21: 0 | ET21: 0 | EU21: 0.6 | EV21: 0 | EW21: 0 | EX21: 0 | EY21: 3 | EZ21: 2.4 | FA21: 2 | FB21: 0.7 | FC21: 0 | FD21: 8 | FE21: 20 | FF21: 20 | FG21: 8.7 | FI21: 30.8 | FJ21: 16.3 | FK21: 11.53 | FL21: 8.12 | FM21: 5.27 | FN21: 17.93 | FO21: 6651.997 | FQ21: 24.40998 | FR21: 7.907 | FS21: 9.61 | FT21: 13.2 | FU21: 24.28266 | FV21: 18.95043 | FW21: 11.9 | FX21: 15.8 | FY21: 126.06007
A22: 21/02/2026 | B22: 06:00 | C22: 200.2 | D22: 631.8 | E22: 213.5 | H22: 89.1 | I22: 231.6 | J22: 0 | L22: 125 | M22: 125.2 | N22: 125.3 | O22: 229.5 | P22: 109.3 | Q22: 68.4 | R22: 558.2 | S22: 10.2 | T22: 16.3 | X22: 164.8 | Y22: 7.154 | Z22: 5.474 | AA22: 0 | AB22: 6.6 | AD22: 142.22 | AI22: 110.4 | AJ22: 215.8 | AN22: 6.5 | AO22: 459.1 | AP22: 81.5 | AQ22: 151.3 | AR22: 41.8 | AS22: 18.4 | AT22: 18.8 | AU22: 89.8 | AV22: 177.9 | AW22: 178.6 | AX22: 180.7 | AY22: 105.6 | AZ22: 43.4 | BA22: 45.3 | BB22: 2 | BC22: 31.4 | BD22: 169.7 | BG22: 62.5 | BJ22: 0 | BN22: 127.1 | BO22: 0 | BP22: 0 | BQ22: 0 | BS22: 40.2 | BT22: 28.1 | BY22: 0 | CA22: 2.1 | CB22: 199 | CC22: 129.7 | CD22: 65.8 | CE22: 64.3 | CF22: 30 | CJ22: 0 | CL22: 0 | CM22: 0 | CR22: 137.2 | CS22: 77.9 | CT22: 7.2 | CW22: 0 | CX22: 18.6 | CY22: 0 | CZ22: 2 | DA22: 0 | DB22: 20.3 | DC22: 10.1 | DD22: 5.5 | DE22: 1.7 | DG22: 2.2 | DH22: 2.1 | DI22: 5.1 | DJ22: 20.3 | DK22: 20 | DL22: 18.9 | DM22: 3.6 | DN22: 18.5 | DO22: 2.1 | DP22: 2.3 | DQ22: 1.1 | DR22: 2.8 | DS22: 1.2 | DT22: 3.2 | DU22: 20.2 | DV22: 3.2 | DX22: 0 | DY22: 19.8 | DZ22: 13 | EA22: 20.3 | EB22: 20.3 | EC22: 0.6 | ED22: 5.6 | EE22: 0 | EF22: 0 | EG22: 0 | EH22: 0 | EI22: 0 | EJ22: 0 | EK22: 0 | EL22: 0 | EN22: 20.4 | EO22: 20.4 | EP22: 20 | EQ22: 2 | ER22: 2.6 | ES22: 0 | ET22: 1 | EU22: 0.6 | EV22: 0 | EW22: 0 | EX22: 1 | EY22: 3 | EZ22: 2.4 | FA22: 2 | FB22: 0.7 | FC22: 0 | FD22: 8 | FE22: 20 | FF22: 20 | FG22: 8.8 | FI22: 30.9 | FJ22: 17 | FK22: 11.44 | FL22: 7.77 | FM22: 5.27 | FN22: 17.96 | FO22: 6646.788 | FQ22: 24.41001 | FR22: 7.906 | FS22: 9.584 | FT22: 13.2 | FU22: 24.36347 | FV22: 18.95045 | FW22: 11.8 | FX22: 15.9 | FY22: 126.11393
... A58: 22/02/2026 | B58: 00:00 | C58: 202.8 | D58: 642 | E58: 216.2 | H58: 89.8 | I58: 159.9 | J58: 0 | L58: 130.5 | M58: 130.7 | N58: 130.8 | O58: 231.3 | P58: 203.8 | Q58: 108 | R58: 557.1 | S58: 10.2 | T58: 0 | X58: 167.1 | Y58: 8.52 | Z58: 6.313 | AA58: 0 | AB58: 6.81 | AD58: 142.67 | AI58: 110.4 | AJ58: 194.7 | AN58: 6.5 | AO58: 461 | AP58: 81.6 | AQ58: 151.6 | AR58: 41.9 | AS58: 18.4 | AT58: 18.8 | AU58: 91.3 | AV58: 180.4 | AW58: 180.7 | AX58: 184.9 | AY58: 106 | AZ58: 44.6 | BA58: 26.1 | BB58: 0 | BC58: 32.4 | BD58: 171.1 | BG58: 94.2 | BJ58: 44 | BN58: 127.4 | BO58: 0 | BP58: 0 | BQ58: 19.1 | BS58: 72.1 | BT58: 35.1 | BY58: 0 | CA58: 2.1 | CB58: 254.6 | CC58: 131.6 | CD58: 62.9 | CE58: 64.3 | CF58: 29.7 | CJ58: 0 | CL58: 0 | CM58: 0 | CR58: 206.2 | CS58: 99.1 | CT58: 7.3 | CW58: 0 | CX58: 27 | CY58: 0 | CZ58: 0 | DA58: 0 | DB58: 20.3 | DC58: 9.9 | DD58: 5.6 | DE58: 0 | DG58: 2.1 | DH58: 2.1 | DI58: 5.1 | DJ58: 20.5 | DK58: 20 | DL58: 18 | DM58: 3.5 | DN58: 18.5 | DO58: 0 | DP58: 0 | DQ58: 4.9 | DR58: 19.9 | DS58: 0 | DT58: 3.2 | DU58: 20.3 | DV58: 3.2 | DX58: 0 | DY58: 19.8 | DZ58: 13 | EA58: 20.3 | EB58: 20.3 | EC58: 0 | ED58: 2.2 | EE58: 0 | EF58: 9.8 | EG58: 33.5 | EH58: 0.4 | EI58: 0 | EJ58: 0 | EK58: 20.9 | EL58: 8.2 | EN58: 20.4 | EO58: 20.4 | EP58: 20 | EQ58: 0.2 | ER58: 0 | ES58: 0 | ET58: 0 | EU58: 0.6 | EV58: 12.1 | EW58: 13.9 | EX58: 0 | EY58: 3 | EZ58: 2.4 | FA58: 2 | FB58: 0.7 | FC58: 0 | FD58: 7.5 | FE58: 20 | FF58: 20 | FG58: 8.8 | FI58: 17.9 | FJ58: 17 | FK58: 13.01 | FL58: 6.74 | FM58: 11 | FN58: 16.32 | FO58: 7083.083 | FQ58: 24.55751 | FR58: 7.879 | FS58: 11.864 | FT58: 0 | FU58: 24.37518 | FV58: 18.95309 | FW58: 11.6 | FX58: 15.3 | FY58: 114.52878
A59: EJEC | C59: 4851.7 | D59: 13850.75 | E59: 4663.9 | F59: 0 | G59: 0 | H59: 2158.45 | I59: 5430.45 | J59: 54 | K59: 0 | L59: 3183.25 | M59: 3205.5 | N59: 3205.25 | O59: 5584.1 | P59: 4006.7 | Q59: 2229.15 | R59: 12876.45 | S59: 244.85 | T59: 146.7 | U59: 0 | V59: 0 | W59: 0 | X59: 3964.15 | Y59: 189.404 | Z59: 142.713 | AA59: 130.7315 | AB59: 131.555 | AC59: 0 | AD59: 3421.115 | AE59: 0 | AF59: 0 | AG59: 0 | AH59: 0 | AI59: 2644.55 | AJ59: 4668.5 | AK59: 0 | AL59: 0 | AM59: 0 | AN59: 156 | AO59: 10945.9 | AP59: 1947.7 | AQ59: 3617.25 | AR59: 999 | AS59: 441.95 | AT59: 451.2 | AU59: 2162.55 | AV59: 4076.5 | AW59: 4080.45 | AX59: 4305.25 | AY59: 2542.65 | AZ59: 1061.05 | BA59: 1042.7 | BB59: 33.6 | BC59: 762.2 | BD59: 4059.2 | BE59: 0 | BF59: 0 | BG59: 1415.3 | BH59: 0 | BI59: 0 | BJ59: 764.35 | BK59: 0 | BL59: 0 | BM59: 0 | BN59: 3052.05 | BO59: 720.2 | BP59: 963 | BQ59: 1855.7 | BR59: 0 | BS59: 1352.3 | BT59: 752.7 | BU59: 0 | BV59: 0 | BW59: 0 | BX59: 0 | BY59: 0.9 | BZ59: 0 | CA59: 50.4 | CB59: 5642.45 | CC59: 3112.05 | CD59: 1528.05 | CE59: 1541.6 | CF59: 672.4 | CG59: 0 | CH59: 0 | CI59: 0 | CJ59: 950.1 | CK59: 0 | CL59: 85.45 | CM59: 721.95 | CN59: 0 | CO59: 0 | CP59: 0 | CQ59: 0 | CR59: 4093.95 | CS59: 2103.85 | CT59: 173.8 | CU59: 0 | CV59: 0 | CW59: 6.8 | CX59: 1131.95 | CY59: 550.3 | CZ59: 31.5 | DA59: 1.75 | DB59: 416.5 | DC59: 238.5 | DD59: 132.25 | DE59: 1320.8 | DF59: 0 | DG59: 52.65 | DH59: 50.7 | DI59: 121.35 | DJ59: 407.15 | DK59: 478.55 | DL59: 451.85 | DM59: 84.8 | DN59: 444 | DO59: 85.35 | DP59: 84.3 | DQ59: 216.4 | DR59: 706.55 | DS59: 134.45 | DT59: 76.05 | DU59: 463.3 | DV59: 76.8 | DW59: 0 | DX59: 2.9 | DY59: 475.4 | DZ59: 275.05 | EA59: 486.4 | EB59: 485.6 | EC59: 24.95 | ED59: 301.8 | EE59: 135.5 | EF59: 620.25 | EG59: 1064.55 | EH59: 76.2 | EI59: 52.4 | EJ59: 182.05 | EK59: 132.9 | EL59: 49.85 | EM59: 0 | EN59: 489.6 | EO59: 489.6 | EP59: 480 | EQ59: 34.35 | ER59: 1614.55 | ES59: 115.75 | ET59: 588.85 | EU59: 12.95 | EV59: 747.7 | EW59: 1009.2 | EX59: 439.75 | EY59: 69.85 | EZ59: 54.45 | FA59: 45.8 | FB59: 16.8 | FC59: 82.45 | FD59: 188.8 | FE59: 480.25 | FF59: 479.9 | FG59: 207.25 | FH59: 0 | FI59: 692.85 | FJ59: 401.25 | FK59: 303.83 | FL59: 185.455 | FM59: 157.67 | FN59: 398.86 | FO59: 177139.78 | FQ59: 584.87208 | FR59: 189.1365 | FS59: 224.527 | FT59: 191.4 | FU59: 577.69539 | FV59: 454.85462 | FW59: 282.75 | FX59: 376.2 | FY59: 2881.4356

Sheet REACTIVA
B3: sábado, 21 de Febrero del 2026
A5: POTENCIA REACTIVA EJECUTADA DE LAS UNIDADES DE GENERACIÓN DEL COES (MVAR) | FQ5: CENTRALES NO INTEGRANTES COES
A6: FECHA | B6: HORA | C6: 65333 | D6: 101 | E6: 102 | F6: 42667 | G6: 42668 | H6: 126 | I6: 127 | J6: 138 | K6: 139 | L6: 197 | M6: 203 | N6: 204 | O6: 230 | P6: 209 | Q6: 56677 | R6: 796 | S6: 2146 | T6: 142 | U6: 143 | V6: 125 | W6: 187 | X6: 163 | Y6: 298 | Z6: 299 | AA6: 219 | AB6: 151 | AC6: 152 | AD6: 153 | AE6: 154 | AF6: 756 | AG6: 156 | AH6: 155 | AI6: 182 | AJ6: 212 | AK6: 758 | AL6: 263 | AM6: 265 | AN6: 775 | AO6: 777 | AP6: 2154 | AQ6: 150 | AR6: 149 | AS6: 188 | AT6: 2131 | AU6: 755 | AV6: 252 | AW6: 249 | AX6: 250 | AY6: 117 | AZ6: 119 | BA6: 120 | BB6: 189 | BC6: 122 | BD6: 266 | BE6: 337 | BF6: 338 | BG6: 251 | BH6: 115 | BI6: 239 | BJ6: 288 | BK6: 240 | BL6: 241 | BM6: 242 | BN6: 191 | BO6: 194 | BP6: 196 | BQ6: 207 | BR6: 236 | BS6: 795 | BT6: 285 | BU6: 995 | BV6: 996 | BW6: 997 | BX6: 766 | BY6: 926 | BZ6: 924 | CA6: 121 | CB6: 103 | CC6: 104 | CD6: 106 | CE6: 105 | CF6: 107 | CG6: 110 | CH6: 109 | CI6: 144 | CJ6: 113 | CK6: 114 | CL6: 193 | CM6: 208 | CN6: 786 | CO6: 787 | CP6: 788 | CQ6: 789 | CR6: 248 | CS6: 2159 | CT6: 267 | CU6: 268 | CV6: 2194 | CW6: 303 | CX6: 59715 | CY6: 62255 | CZ6: 1263 | DA6: 61800 | DB6: 69125 | DC6: 216 | DD6: 198 | DE6: 70400 | DF6: 76068 | DG6: 49607 | DH6: 214 | DI6: 260 | DJ6: 2152 | DK6: 2128 | DL6: 247 | DM6: 228 | DN6: 2135 | DO6: 261 | DP6: 237 | DQ6: 253 | DR6: 770 | DS6: 235 | DT6: 238 | DU6: 2184 | DV6: 61855 | DW6: 223 | DX6: 75566 | DY6: 226 | DZ6: 201 | EA6: 258 | EB6: 259 | EC6: 257 | ED6: 256 | EE6: 2148 | EF6: 58288 | EG6: 58289 | EH6: 58839 | EI6: 58840 | EJ6: 75260 | EK6: 296 | EL6: 297 | EM6: 211 | EN6: 2175 | EO6: 2178 | EP6: 2181 | EQ6: 1262 | ER6: 63425 | ES6: 233 | ET6: 2150 | EU6: 2165 | EV6: 2161 | EW6: 61197 | EX6: 58851 | EY6: 225 | EZ6: 2201 | FA6: 2171 | FB6: 760 | FC6: 234 | FD6: 215 | FE6: 917 | FF6: 920 | FG6: 289 | FH6: 58333 | FI6: 58336 | FJ6: 213 | FK6: 232 | FL6: 2190 | FM6: 69867 | FN6: 75066 | FO6: TOTAL COES | FQ6: 221 | FR6: 222 | FS6: 224 | FT6: 2187 | FU6: 227 | FV6: 49400 | FW6: 199 | FX6: 200 | FY6: TOTAL NO COES
C7: SUR | D7: CENTRO | E7: CENTRO | F7: NORTE | G7: NORTE | H7: NORTE | I7: NORTE | J7: CENTRO | K7: CENTRO | L7: CENTRO | M7: CENTRO | N7: CENTRO | O7: CENTRO | P7: CENTRO | Q7: CENTRO | R7: CENTRO | S7: CENTRO | T7: CENTRO | U7: CENTRO | V7: CENTRO | W7: CENTRO | X7: SUR | Y7: SUR | Z7: SUR | AA7: CENTRO | AB7: SUR | AC7: SUR | AD7: SUR | AE7: SUR | AF7: SUR | AG7: SUR | AH7: SUR | AI7: SUR | AJ7: CENTRO | AK7: NORTE | AL7: NORTE | AM7: NORTE | AN7: CENTRO | AO7: CENTRO | AP7: CENTRO | AQ7: CENTRO | AR7: CENTRO | AS7: CENTRO | AT7: CENTRO | AU7: SUR | AV7: CENTRO | AW7: CENTRO | AX7: CENTRO | AY7: CENTRO | AZ7: CENTRO | BA7: CENTRO | BB7: SUR | BC7: NORTE | BD7: CENTRO | BE7: CENTRO | BF7: CENTRO | BG7: CENTRO | BH7: NORTE | BI7: NORTE | BJ7: NORTE | BK7: SUR | BL7: SUR | BM7: SUR | BN7: CENTRO | BO7: CENTRO | BP7: CENTRO | BQ7: CENTRO | BR7: CENTRO | BS7: CENTRO | BT7: CENTRO | BU7: SUR | BV7: SUR | BW7: SUR | BX7: NORTE | BY7: SUR | BZ7: CENTRO | CA7: NORTE | CB7: CENTRO | CC7: CENTRO | CD7: CENTRO | CE7: CENTRO | CF7: CENTRO | CG7: CENTRO | CH7: CENTRO | CI7: CENTRO | CJ7: CENTRO | CK7: CENTRO | CL7: CENTRO | CM7: CENTRO | CN7: SUR | CO7: SUR | CP7: SUR | CQ7: SUR | CR7: CENTRO | CS7: CENTRO | CT7: CENTRO | CU7: CENTRO | CV7: NORTE | CW7: CENTRO | CX7: CENTRO | CY7: SUR | CZ7: NORTE | DA7: NORTE | DB7: CENTRO | DC7: NORTE | DD7: NORTE | DE7: SUR | DF7: SUR | DG7: SUR | DH7: CENTRO | DI7: CENTRO | DJ7: CENTRO | DK7: NORTE | DL7: NORTE | DM7: CENTRO | DN7: CENTRO | DO7: SUR | DP7: SUR | DQ7: CENTRO | DR7: CENTRO | DS7: SUR | DT7: CENTRO | DU7: CENTRO | DV7: NORTE | DW7: CENTRO | DX7: CENTRO | DY7: CENTRO | DZ7: NORTE | EA7: CENTRO | EB7: CENTRO | EC7: NORTE | ED7: NORTE | EE7: SUR | EF7: CENTRO | EG7: CENTRO | EH7: CENTRO | EI7: CENTRO | EJ7: SUR | EK7: CENTRO | EL7: CENTRO | EM7: SUR | EN7: SUR | EO7: SUR | EP7: SUR | EQ7: NORTE | ER7: SUR | ES7: SUR | ET7: SUR | EU7: CENTRO | EV7: CENTRO | EW7: CENTRO | EX7: SUR | EY7: CENTRO | EZ7: CENTRO | FA7: CENTRO | FB7: CENTRO | FC7: SUR | FD7: NORTE | FE7: CENTRO | FF7: CENTRO | FG7: NORTE | FH7: NORTE | FI7: NORTE | FJ7: CENTRO | FK7: NORTE | FL7: NORTE | FM7: NORTE | FN7: NORTE | FQ7: NORTE | FR7: CENTRO | FS7: NORTE | FT7: NORTE | FU7: NORTE | FV7: NORTE | FW7: NORTE | FX7: NORTE
C8: HIDROELÉCTRICA | D8: HIDROELÉCTRICA | E8: HIDROELÉCTRICA | F8: TERMOELÉCTRICA | G8: TERMOELÉCTRICA | H8: HIDROELÉCTRICA | I8: HIDROELÉCTRICA | J8: TERMOELÉCTRICA | K8: TERMOELÉCTRICA | L8: TERMOELÉCTRICA | M8: TERMOELÉCTRICA | N8: TERMOELÉCTRICA | O8: TERMOELÉCTRICA | P8: TERMOELÉCTRICA | Q8: TERMOELÉCTRICA | R8: HIDROELÉCTRICA | S8: HIDROELÉCTRICA | T8: TERMOELÉCTRICA | U8: TERMOELÉCTRICA | V8: TERMOELÉCTRICA | W8: TERMOELÉCTRICA | X8: HIDROELÉCTRICA | Y8: HIDROELÉCTRICA | Z8: HIDROELÉCTRICA | AA8: TERMOELÉCTRICA | AB8: HIDROELÉCTRICA | AC8: HIDROELÉCTRICA | AD8: HIDROELÉCTRICA | AE8: HIDROELÉCTRICA | AF8: TERMOELÉCTRICA | AG8: TERMOELÉCTRICA | AH8: TERMOELÉCTRICA | AI8: HIDROELÉCTRICA | AJ8: HIDROELÉCTRICA | AK8: TERMOELÉCTRICA | AL8: TERMOELÉCTRICA | AM8: TERMOELÉCTRICA | AN8: HIDROELÉCTRICA | AO8: HIDROELÉCTRICA | AP8: HIDROELÉCTRICA | AQ8: HIDROELÉCTRICA | AR8: HIDROELÉCTRICA | AS8: HIDROELÉCTRICA | AT8: HIDROELÉCTRICA | AU8: HIDROELÉCTRICA | AV8: TERMOELÉCTRICA | AW8: TERMOELÉCTRICA | AX8: TERMOELÉCTRICA | AY8: HIDROELÉCTRICA | AZ8: HIDROELÉCTRICA | BA8: HIDROELÉCTRICA | BB8: HIDROELÉCTRICA | BC8: HIDROELÉCTRICA | BD8: HIDROELÉCTRICA | BE8: HIDROELÉCTRICA | BF8: HIDROELÉCTRICA | BG8: HIDROELÉCTRICA | BH8: TERMOELÉCTRICA | BI8: TERMOELÉCTRICA | BJ8: TERMOELÉCTRICA | BK8: TERMOELÉCTRICA | BL8: TERMOELÉCTRICA | BM8: TERMOELÉCTRICA | BN8: HIDROELÉCTRICA | BO8: TERMOELÉCTRICA | BP8: TERMOELÉCTRICA | BQ8: TERMOELÉCTRICA | BR8: TERMOELÉCTRICA | BS8: TERMOELÉCTRICA | BT8: TERMOELÉCTRICA | BU8: TERMOELÉCTRICA | BV8: TERMOELÉCTRICA | BW8: TERMOELÉCTRICA | BX8: HIDROELÉCTRICA | BY8: TERMOELÉCTRICA | BZ8: TERMOELÉCTRICA | CA8: HIDROELÉCTRICA | CB8: HIDROELÉCTRICA | CC8: HIDROELÉCTRICA | CD8: HIDROELÉCTRICA | CE8: HIDROELÉCTRICA | CF8: HIDROELÉCTRICA | CG8: TERMOELÉCTRICA | CH8: TERMOELÉCTRICA | CI8: TERMOELÉCTRICA | CJ8: TERMOELÉCTRICA | CK8: TERMOELÉCTRICA | CL8: TERMOELÉCTRICA | CM8: TERMOELÉCTRICA | CN8: TERMOELÉCTRICA | CO8: TERMOELÉCTRICA | CP8: TERMOELÉCTRICA | CQ8: TERMOELÉCTRICA | CR8: TERMOELÉCTRICA | CS8: TERMOELÉCTRICA | CT8: HIDROELÉCTRICA | CU8: HIDROELÉCTRICA | CV8: HIDROELÉCTRICA | CW8: SOLAR | CX8: EÓLICA | CY8: SOLAR | CZ8: EÓLICA | DA8: SOLAR | DB8: HIDROELÉCTRICA | DC8: HIDROELÉCTRICA | DD8: HIDROELÉCTRICA | DE8: SOLAR | DF8: SOLAR | DG8: HIDROELÉCTRICA | DH8: HIDROELÉCTRICA | DI8: HIDROELÉCTRICA | DJ8: HIDROELÉCTRICA | DK8: HIDROELÉCTRICA | DL8: HIDROELÉCTRICA | DM8: HIDROELÉCTRICA | DN8: HIDROELÉCTRICA | DO8: SOLAR | DP8: SOLAR | DQ8: EÓLICA | DR8: EÓLICA | DS8: SOLAR | DT8: HIDROELÉCTRICA | DU8: HIDROELÉCTRICA | DV8: HIDROELÉCTRICA | DW8: HIDROELÉCTRICA | DX8: SOLAR | DY8: HIDROELÉCTRICA | DZ8: HIDROELÉCTRICA | EA8: HIDROELÉCTRICA | EB8: HIDROELÉCTRICA | EC8: EÓLICA | ED8: EÓLICA | EE8: SOLAR | EF8: EÓLICA | EG8: EÓLICA | EH8: EÓLICA | EI8: EÓLICA | EJ8: SOLAR | EK8: HIDROELÉCTRICA | EL8: HIDROELÉCTRICA | EM8: HIDROELÉCTRICA | EN8: HIDROELÉCTRICA | EO8: HIDROELÉCTRICA | EP8: HIDROELÉCTRICA | EQ8: EÓLICA | ER8: SOLAR | ES8: SOLAR | ET8: SOLAR | EU8: HIDROELÉCTRICA | EV8: EÓLICA | EW8: EÓLICA | EX8: SOLAR | EY8: TERMOELÉCTRICA | EZ8: TERMOELÉCTRICA | FA8: TERMOELÉCTRICA | FB8: TERMOELÉCTRICA | FC8: SOLAR | FD8: HIDROELÉCTRICA | FE8: HIDROELÉCTRICA | FF8: HIDROELÉCTRICA | FG8: TERMOELÉCTRICA | FH8: TERMOELÉCTRICA | FI8: TERMOELÉCTRICA | FJ8: TERMOELÉCTRICA | FK8: TERMOELÉCTRICA | FL8: TERMOELÉCTRICA | FM8: TERMOELÉCTRICA | FN8: TERMOELÉCTRICA | FQ8: HIDROELÉCTRICA | FR8: HIDROELÉCTRICA | FS8: HIDROELÉCTRICA | FT8: HIDROELÉCTRICA | FU8: TERMOELÉCTRICA | FV8: TERMOELÉCTRICA | FW8: HIDROELÉCTRICA | FX8: HIDROELÉCTRICA
C9: HYDRO GLOBAL PERÚ S.A.C. | D9: ELECTROPERU | E9: ELECTROPERU | F9: ELECTROPERU | G9: ELECTROPERU | H9: ORAZUL ENERGY PERÚ | I9: ORAZUL ENERGY PERÚ | J9: TERMOSELVA | K9: TERMOSELVA | L9: KALLPA GENERACION S.A. | M9: KALLPA GENERACION S.A. | N9: KALLPA GENERACION S.A. | O9: KALLPA GENERACION S.A. | P9: KALLPA GENERACION S.A. | Q9: KALLPA GENERACION S.A. | R9: KALLPA GENERACION S.A. | S9: KALLPA GENERACION S.A. | T9: SHOUGESA | U9: SHOUGESA | V9: SHOUGESA | W9: SHOUGESA | X9: EGEMSA | Y9: EGESUR | Z9: EGESUR | AA9: EGESUR | AB9: EGASA | AC9: EGASA | AD9: EGASA | AE9: EGASA | AF9: EGASA | AG9: EGASA | AH9: EGASA | AI9: SAN GABAN | AJ9: CELEPSA | AK9: MINERA CERRO VERDE | AL9: PLANTA DE RESERVA FRIA DE GENERACION DE ETEN S.A. | AM9: PLANTA DE RESERVA FRIA DE GENERACION DE ETEN S.A. | AN9: EMPRESA DE GENERACION HUALLAGA | AO9: EMPRESA DE GENERACION HUALLAGA | AP9: LA VIRGEN | AQ9: CHINANGO S.A.C. | AR9: CHINANGO S.A.C. | AS9: HIDROELECTRICA HUANCHOR S.A.C. | AT9: CELEPSA RENOVABLES S.R.L. | AU9: INLAND ENERGY SAC | AV9: FENIX POWER PERÚ | AW9: FENIX POWER PERÚ | AX9: FENIX POWER PERÚ | AY9: STATKRAFT S.A | AZ9: STATKRAFT S.A | BA9: STATKRAFT S.A | BB9: STATKRAFT S.A | BC9: STATKRAFT S.A | BD9: STATKRAFT S.A | BE9: CENTRALES SANTA ROSA S.A.C. | BF9: CENTRALES SANTA ROSA S.A.C. | BG9: EMPRESA DE GENERACION HUANZA | BH9: ENEL GENERACION PIURA S.A. | BI9: ENEL GENERACION PIURA S.A. | BJ9: ENEL GENERACION PIURA S.A. | BK9: ENGIE ENERGIA PERU S.A.A. | BL9: ENGIE ENERGIA PERU S.A.A. | BM9: ENGIE ENERGIA PERU S.A.A. | BN9: ENGIE ENERGIA PERU S.A.A. | BO9: ENGIE ENERGIA PERU S.A.A. | BP9: ENGIE ENERGIA PERU S.A.A. | BQ9: ENGIE ENERGIA PERU S.A.A. | BR9: ENGIE ENERGIA PERU S.A.A. | BS9: ENGIE ENERGIA PERU S.A.A. | BT9: ENGIE ENERGIA PERU S.A.A. | BU9: ENGIE ENERGIA PERU S.A.A. | BV9: ENGIE ENERGIA PERU S.A.A. | BW9: ENGIE ENERGIA PERU S.A.A. | BX9: ENGIE ENERGIA PERU S.A.A. | BY9: INFRAESTRUCTURAS Y ENERGIAS DEL PERU S.A.C. | BZ9: INFRAESTRUCTURAS Y ENERGIAS DEL PERU S.A.C. | CA9: INVERSIONES SHAQSHA S.A.C. | CB9: ORYGEN PERU S.A.A. | CC9: ORYGEN PERU S.A.A. | CD9: ORYGEN PERU S.A.A. | CE9: ORYGEN PERU S.A.A. | CF9: ORYGEN PERU S.A.A. | CG9: ORYGEN PERU S.A.A. | CH9: ORYGEN PERU S.A.A. | CI9: ORYGEN PERU S.A.A. | CJ9: ORYGEN PERU S.A.A. | CK9: ORYGEN PERU S.A.A. | CL9: ORYGEN PERU S.A.A. | CM9: ORYGEN PERU S.A.A. | CN9: SAMAY I S.A.C | CO9: SAMAY I S.A.C | CP9: SAMAY I S.A.C | CQ9: SAMAY I S.A.C | CR9: TERMOCHILCA S.A.C. | CS9: TERMOCHILCA S.A.C. | CT9: TRANSMISION ANDINA DE GENERACION S.A.C. | CU9: TRANSMISION ANDINA DE GENERACION S.A.C. | CV9: CELARIS ENERGY S.A. | CW9: COLCA SOLAR S.A.C. | CX9: ENERGIA RENOVABLE DEL SUR S.A. | CY9: GR CORTARRAMA SOCIEDAD ANONIMA CERRADA | CZ9: GR TARUCA SOCIEDAD ANONIMA CERRADA | DA9: KONDU SAC | DB9: VARI ENERGIA S.A.C. | DC9: ORAZUL ENERGY PERÚ | DD9: ORAZUL ENERGY PERÚ | DE9: KALLPA GENERACION S.A. | DF9: KALLPA GENERACION S.A. | DG9: SAN GABAN | DH9: MAJA ENERGIA S.A.C. | DI9: EMPRESA DE GENERACION ELECTRICA CANCHAYLLO SAC | DJ9: EMPRESA DE GENERACION ELECTRICA SANTA ANA S.A.C. | DK9: EMPRESA ELECTRICA AGUA AZUL | DL9: EMPRESA ELECTRICA RIO DOBLE | DM9: HIDROCAÑETE S.A. | DN9: HUAURA POWER GROUP S.A. | DO9: MOQUEGUA FV S.A.C. | DP9: PANAMERICANA SOLAR SAC. | DQ9: PARQUE EOLICO MARCONA S.A.C. | DR9: PARQUE EOLICO TRES HERMANAS S.A.C. | DS9: TACNA SOLAR SAC. | DT9: ELECTRICA YANAPAMPA SAC | DU9: ANDEAN POWER S.A.C. | DV9: ASOCIACIÓN SANTA LUCIA DE CHACAS | DW9: ATRIA ENERGIA S.A.C. | DX9: COENERGY S.A.C. | DY9: EGEJUNIN | DZ9: EGEJUNIN | EA9: EGEJUNIN | EB9: EGEJUNIN | EC9: ENERGÍA EÓLICA S.A. | ED9: ENERGÍA EÓLICA S.A. | EE9: ENGIE ENERGIA PERU S.A.A. | EF9: ENGIE ENERGIA PERU S.A.A. | EG9: ENGIE ENERGIA PERU S.A.A. | EH9: ENGIE ENERGIA PERU S.A.A. | EI9: ENGIE ENERGIA PERU S.A.A. | EJ9: ENGIE ENERGIA PERU S.A.A. | EK9: GENERACIÓN ANDINA S.A.C. | EL9: GENERACIÓN ANDINA S.A.C. | EM9: GENERADORA DE ENERGÍA DEL PERÚ | EN9: GENERADORA DE ENERGÍA DEL PERÚ | EO9: GENERADORA DE ENERGÍA DEL PERÚ | EP9: GENERADORA DE ENERGÍA DEL PERÚ | EQ9: GR PAINO SOCIEDAD ANONIMA CERRADA | ER9: JOYA SOLAR S.A.C. | ES9: MAJES ARCUS S.A.C. | ET9: ORYGEN PERU S.A.A. | EU9: ORYGEN PERU S.A.A. | EV9: ORYGEN PERU S.A.A. | EW9: ORYGEN PERU S.A.A. | EX9: ORYGEN PERU S.A.A. | EY9: PETRAMAS | EZ9: PETRAMAS | FA9: PETRAMAS | FB9: PETRAMAS | FC9: REPARTICIÓN ARCUS S.A.C. | FD9: SINERSA | FE9: SINERSA | FF9: SINERSA | FG9: BIOENERGIA DEL CHIRA S.A. | FH9: GM OPERACIONES S.A.C. | FI9: GM OPERACIONES S.A.C. | FJ9: AGRO INDUSTRIAL PARAMONGA S.A. | FK9: AGROAURORA S.A.C. | FL9: AGROINDUSTRIAS SAN JACINTO S.A.A. | FM9: AGROLMOS SOCIEDAD ANONIMA - AGROLMOS S.A. | FN9: CASA GRANDE S.A.A. | FQ9: UNACEM PERU S.A. | FR9: ELECTRO ORIENTE | FS9: AGUAS Y ENERGIA PERU | FT9: ELECTRO ZAÑA S.A.C. | FU9: ELECTRONOROESTE S.A. | FV9: SDE PIURA | FW9: SINERSA | FX9: SINERSA
C10: SAN GABAN III | D10: MANTARO | E10: RESTITUCION | F10: TUMBES MAK 1 | G10: TUMBES MAK 2 | H10: CARHUAQUERO | I10: CAÑON DEL PATO | J10: AGUAYTIA TG1 | K10: AGUAYTIA TG2 | L10: KALLPA TG1 | M10: KALLPA TG2 | N10: KALLPA TG3 | O10: KALLPA TV | P10: LFLORES TG1 | Q10: LFLORES TV | R10: CERRO DEL AGUILA | S10: CERRODELAGUILAG4 | T10: SHOUGESA TV1 | U10: SHOUGESA TV2 | V10: SHOUGESA TV3 | W10: SHOUGESA CUMMINS | X10: MACHUPICCHU | Y10: ARICOTA 1 | Z10: ARICOTA 2 | AA10: INDEPENDENCIA | AB10: CHARCANI I,II,III | AC10: CHARCANI IV | AD10: CHARCANI V | AE10: CHARCANI VI | AF10: CHILINA TG | AG10: MOLLENDO 1, 2, 3 | AH10: CHILINA (SULZ 1,2) | AI10: SAN GABAN II | AJ10: PLATANAL | AK10: RECKA | AL10: RF ETEN TG1 | AM10: RF ETEN TG2 | AN10: CHAGLLA GP1 | AO10: CHAGLLA | AP10: LA VIRGEN | AQ10: CHIMAY | AR10: YANANGO | AS10: HUANCHOR | AT10: MARAÑON | AU10: STA TERESA | AV10: FENIX GT11 | AW10: FENIX GT12 | AX10: FENIX TV10 | AY10: YAUPI | AZ10: MALPASO | BA10: CAHUA | BB10: ARCATA | BC10: GALLITO CIEGO | BD10: CHEVES | BE10: SANTA ROSA 1 | BF10: SANTA ROSA 2 | BG10: HUANZA | BH10: MALACAS2 TG4 | BI10: MALACAS3 TG 5 | BJ10: MALACAS1 TG6 | BK10: RF ILO2 TG1 | BL10: RF ILO2 TG2 | BM10: RF ILO2 TG3 | BN10: YUNCAN | BO10: CHILCA1 TG1 | BP10: CHILCA1 TG2 | BQ10: CHILCA1 TG3 | BR10: CHILCA-TV | BS10: CHILCA2 TG41 | BT10: CHILCA2-TV | BU10: CTNEPI_TG41 | BV10: CTNEPI_TG42 | BW10: CTNEPI_TG43 | BX10: QUITARACSA | BY10: RF PTO MALDONADO | BZ10: RF PUCALLPA | CA10: PARIAC | CB10: HUINCO | CC10: MATUCANA | CD10: MOYOPAMPA | CE10: CALLAHUANCA | CF10: HUAMPANI | CG10: STA ROSA WEST TG7 | CH10: UTI_5 | CI10: UTI_6 | CJ10: VENTANILLA 3 | CK10: VENTANILLA 4 | CL10: VENTANILLA TV | CM10: STAROSA TG8 | CN10: PTO_BRVO TG1 | CO10: PTO_BRVO TG2 | CP10: PTO_BRVO TG3 | CQ10: PTO_BRVO TG4 | CR10: OLLEROS TG1 | CS10: OLLEROS TV | CT10: OROYA | CU10: PACHACHACA | CV10: MANTA I | CW10: CS YARUCAYA | CX10: SAN JUAN | CY10: MATARANI | CZ10: DUNA | DA10: CARHUAQUERO (CS) | DB10: ANASHIRONI | DC10: CARHUAQUERO4 | DD10: CAÑA BRAVA | DE10: SUNNY | DF10: SUNNY EXPANSION | DG10: TUPURI | DH10: RONCADOR | DI10: CANCHAYLLO | DJ10: RENOVANDESH1 | DK10: POTRERO | DL10: PIZARRAS | DM10: NIMPERIAL | DN10: YARUCAYA | DO10: MOQUEGUA-SOLAR | DP10: PANAMERICANA-SOLAR | DQ10: PQE-EOLICO-MARCONA | DR10: PQE-EOLICO-3-HERMANAS | DS10: TACNA-SOLAR | DT10: YANAPAMPA | DU10: CARHUAC | DV10: HUALLIN | DW10: PURMACANA | DX10: COENERGY | DY10: HUASAHUASI | DZ10: STACRUZ_1_2 | EA10: RUNATULLO_II | EB10: RUNATULLO_III | EC10: PQE-EOLICO-TALARA | ED10: PQE-EOLICO-CUPISNIQUE | EE10: INTIPAMPA | EF10: PUNTA LOMITAS-BL1 | EG10: PUNTA LOMITAS-BL2 | EH10: PUN LOMITAS_EXP-BL1 | EI10: PUN LOMITAS_EXP-BL2 | EJ10: EXPANSIÓN INTIPAMPA | EK10: 8AGOSTO | EL10: EL CARMEN | EM10: LA JOYA | EN10: ANGEL_I | EO10: ANGEL_II | EP10: ANGEL_III | EQ10: HUAMBOS | ER10: SAN MARTIN SOLAR | ES10: MAJES | ET10: RUBI | EU10: CH_HER1 | EV10: WAYRA-I | EW10: WAYRA EXTENSION | EX10: CLEMESI | EY10: HUAYCOLORO | EZ10: CALLAO | FA10: DONA_CATALINA | FB10: LAGRINGAV | FC10: REPARTICION | FD10: POECHOS2 | FE10: CHANCAY | FF10: RUCUY | FG10: CANA BRAVA | FH10: REFINERIA TALARA TV1 | FI10: REFINERÍA TALARA TV2 | FJ10: PARAMONGA | FK10: MAPLE | FL10: SAN_JACINTO | FM10: AGROLMOS | FN10: CASA GRANDE | FO10: MVAR | FQ10: CARPAPATA | FR10: CENTRALES ELOR | FS10: PIAS1 | FT10: ZANA | FU10: TABLAZO | FV10: TALLANCA | FW10: CURUMUY | FX10: POECHOS1 | FY10: MVAR
A11: 21/02/2026 | B11: 00:30 | C11: 32.1 | D11: 11.6 | E11: 19.1 | H11: -8.7 | I11: 4.7 | L11: 7.7 | M11: 15.8 | N11: 12 | O11: 29.1 | P11: 13 | Q11: 11.9 | R11: 43.3 | S11: 0.1 | T11: 2 | X11: 0.1 | Y11: 0.586 | Z11: 1.686 | AA11: 0 | AB11: -3.35 | AD11: 0 | AI11: 9.9 | AJ11: 18.2 | AN11: -0.9 | AO11: 63 | AP11: 8.1 | AQ11: 32.8 | AR11: 9.7 | AS11: 0.2 | AT11: 2.6 | AU11: 1.5 | AV11: 16.6 | AW11: -9.1 | AX11: -44 | AY11: 10.5 | AZ11: -1.6 | BA11: -0.8 | BB11: 0.6 | BC11: 0.6 | BD11: 18.6 | BG11: 6.5 | BJ11: -1.2 | BN11: 1.8 | BO11: 0 | BP11: 0 | BQ11: 0 | BS11: 1.3 | BT11: -7 | BY11: 0 | CA11: -0.4 | CB11: 21.3 | CC11: 21 | CD11: 11.6 | CE11: 6.2 | CF11: 0 | CJ11: 24.1 | CL11: -14.5 | CM11: 0 | CR11: -4.6 | CS11: -0.9 | CT11: -1.2 | CX11: -5.6 | CY11: 0 | CZ11: -0.9 | DB11: 0.1 | DC11: 0 | DD11: -1 | DE11: 0 | DH11: 0.2 | DI11: 1.1 | DJ11: 0.2 | DK11: -1.6 | DL11: 0.3 | DM11: 0.6 | DO11: 0 | DP11: 0 | DQ11: 1.2 | DR11: 10.5 | DS11: 0 | DT11: 0 | DU11: 0.2 | DV11: 0.1 | DY11: -4.6 | DZ11: 1 | EA11: 3.2 | EB11: 2.8 | EE11: 0 | EF11: 0 | EG11: -7.2 | EH11: 0 | EI11: 0 | EK11: 0 | EL11: 0 | EN11: 0.2 | EO11: 0.2 | EP11: 0.2 | EQ11: -0.9 | ER11: 0 | ES11: 0 | ET11: 0 | EU11: 0 | EV11: -10.2 | EW11: 9.5 | EX11: 0 | EY11: 1.5 | EZ11: 0.8 | FA11: 0.6 | FB11: 0.3 | FC11: 0 | FD11: 0.2 | FE11: 1.8 | FF11: 1.5 | FG11: 1.8 | FI11: 6.6 | FJ11: 4.6 | FK11: 0.37 | FL11: 2.31 | FM11: 1.22 | FN11: 10.38 | FO11: 426.802 | FQ11: 2.415 | FR11: 0.023 | FS11: 1.72412 | FT11: 0 | FU11: 0.2917 | FV11: 0.34115 | FW11: -1.3 | FX11: 2.1 | FY11: 5.59497
A12: 21/02/2026 | B12: 01:00 | C12: 33.9 | D12: 13.7 | E12: 19.5 | H12: -8 | I12: 14.3 | L12: 2.2 | M12: 9.9 | N12: 4.5 | O12: 24.2 | P12: 10.3 | Q12: 11.7 | R12: 46.6 | S12: 0 | T12: 1.5 | X12: 1.2 | Y12: 1.049 | Z12: 1.915 | AA12: 0 | AB12: -3.28 | AD12: -0.29 | AI12: 10.8 | AJ12: 9.9 | AN12: -1 | AO12: 63.8 | AP12: 8.4 | AQ12: 35.8 | AR12: 9.9 | AS12: 0.3 | AT12: 2.6 | AU12: 1.4 | AV12: 16.1 | AW12: -9.6 | AX12: -40.1 | AY12: 12.7 | AZ12: -2.4 | BA12: -1 | BB12: 0.6 | BC12: 0.6 | BD12: 18.5 | BG12: 6.1 | BJ12: -1.7 | BN12: 3.1 | BO12: 0 | BP12: 0 | BQ12: 0 | BS12: 0.8 | BT12: -7.1 | BY12: 0 | CA12: -0.3 | CB12: 30.2 | CC12: 21.4 | CD12: 5.8 | CE12: 5.8 | CF12: 0 | CJ12: 21.4 | CL12: -19.1 | CM12: 0 | CR12: -6.9 | CS12: -1.6 | CT12: -1.2 | CX12: -5.6 | CY12: 0 | CZ12: -0.9 | DB12: 0.1 | DC12: -0.1 | DD12: -1 | DE12: 0 | DH12: 0.1 | DI12: 1.1 | DJ12: 0.2 | DK12: -2.2 | DL12: 0.3 | DM12: 0.6 | DO12: 0 | DP12: 0 | DQ12: 0.5 | DR12: 8.4 | DS12: 0 | DT12: 0 | DU12: 0.1 | DV12: 0.1 | DY12: -4.6 | DZ12: 0.8 | EA12: 3.2 | EB12: 2.9 | EE12: 0 | EF12: 0 | EG12: 0 | EH12: 0 | EI12: 0 | EK12: 0 | EL12: 0 | EN12: 0.2 | EO12: 0.2 | EP12: 0.2 | EQ12: -0.9 | ER12: 0 | ES12: 0 | ET12: 0 | EU12: 0 | EV12: -13.2 | EW12: 7.1 | EX12: 0 | EY12: 1.5 | EZ12: 0.8 | FA12: 0.6 | FB12: 0.3 | FC12: 0 | FD12: 0.2 | FE12: 1.8 | FF12: 1.5 | FG12: 1.9 | FI12: 6.3 | FJ12: 3 | FK12: 0 | FL12: 1.88 | FM12: 1.29 | FN12: 10.47 | FO12: 408.034 | FQ12: 2.5299 | FR12: -0.174 | FS12: 1.81988 | FT12: 0 | FU12: 0.29371 | FV12: 0.35927 | FW12: -1.3 | FX12: 1.6 | FY12: 5.12876
A13: 21/02/2026 | B13: 01:30 | C13: 33.8 | D13: 6.1 | E13: 18.4 | H13: -9.2 | I13: 2.1 | L13: -4 | M13: 3.8 | N13: 1 | O13: 14.6 | P13: 6.8 | Q13: 8.3 | R13: 41.3 | S13: 0.1 | T13: 1.5 | X13: -0.3 | Y13: 0.846 | Z13: 1.565 | AA13: 0 | AB13: -3.35 | AD13: -1.24 | AI13: 10.3 | AJ13: 0.5 | AN13: -1 | AO13: 63 | AP13: 8.2 | AQ13: 35.5 | AR13: 9.6 | AS13: 0.4 | AT13: 2.6 | AU13: 0.9 | AV13: 12.2 | AW13: -13.7 | AX13: -44.1 | AY13: 11.5 | AZ13: -1.8 | BA13: -1.5 | BB13: 0.6 | BC13: 0.6 | BD13: 18.4 | BG13: 4.7 | BJ13: 0.4 | BN13: 1.5 | BO13: 0 | BP13: 0 | BQ13: 0 | BS13: -1 | BT13: -7.1 | BY13: 0 | CA13: -0.3 | CB13: 27.2 | CC13: 21.3 | CD13: 5.5 | CE13: 6 | CF13: 0 | CJ13: 16.1 | CL13: -27.1 | CM13: 0 | CR13: -9.7 | CS13: -3.4 | CT13: -1.3 | CX13: -5.6 | CY13: 0 | CZ13: -0.9 | DB13: 0.1 | DC13: 0 | DD13: -1 | DE13: 0 | DH13: 0.1 | DI13: 1.1 | DJ13: 0.2 | DK13: -2.2 | DL13: 0.3 | DM13: 0.6 | DO13: 0 | DP13: 0 | DQ13: 0.1 | DR13: 7.3 | DS13: 0 | DT13: -0.1 | DU13: 0 | DV13: 0.1 | DY13: -4.6 | DZ13: 0.9 | EA13: 3.2 | EB13: 2.9 | EE13: 0 | EF13: 0 | EG13: 0 | EH13: 0 | EI13: 0 | EK13: 0 | EL13: 0 | EN13: 0.2 | EO13: 0.2 | EP13: 0.2 | EQ13: -0.9 | ER13: 0 | ES13: 0 | ET13: 0 | EU13: 0 | EV13: -14.6 | EW13: 7 | EX13: 0 | EY13: 1.5 | EZ13: 0.8 | FA13: 0.6 | FB13: 0.3 | FC13: 0 | FD13: 0.2 | FE13: 1.6 | FF13: 1.3 | FG13: 1.9 | FI13: 6.8 | FJ13: 4 | FK13: 0 | FL13: 1.94 | FM13: 1.43 | FN13: 10.7 | FO13: 294.791 | FQ13: 2.49703 | FR13: -0.197 | FS13: 2.00181 | FT13: 0 | FU13: 0.29449 | FV13: 0.37508 | FW13: -1.4 | FX13: 1.1 | FY13: 4.67141
A14: 21/02/2026 | B14: 02:00 | C14: 35.6 | D14: 4 | E14: 17.6 | H14: -8.8 | I14: 9.7 | L14: -6.5 | M14: -0.6 | N14: -6 | O14: 10.5 | P14: 6.1 | Q14: 8 | R14: 41.7 | S14: 0.1 | T14: 1.6 | X14: 2.1 | Y14: 0.562 | Z14: 1.393 | AA14: 0 | AB14: -3.3 | AD14: -0.18 | AI14: 11.3 | AJ14: -2.5 | AN14: -1 | AO14: 62.5 | AP14: 8.1 | AQ14: 36.6 | AR14: 5.3 | AS14: 0.7 | AT14: 2.6 | AU14: 1.7 | AV14: 10.5 | AW14: -15.1 | AX14: -45.4 | AY14: 9.8 | AZ14: -2 | BA14: -1.5 | BB14: 0.6 | BC14: 0.4 | BD14: 18.4 | BG14: 3.2 | BJ14: 0 | BN14: 3.6 | BO14: 0 | BP14: 0 | BQ14: 0 | BS14: -1.1 | BT14: -7.2 | BY14: 0 | CA14: -0.3 | CB14: 28.3 | CC14: 22.3 | CD14: 6 | CE14: 5.8 | CF14: -2.7 | CJ14: 8.8 | CL14: 0 | CM14: 0 | CR14: -11.9 | CS14: -5 | CT14: -1.3 | CX14: -5.6 | CY14: 0 | CZ14: -0.9 | DB14: 0 | DC14: -0.1 | DD14: -1 | DE14: 0 | DH14: 0.1 | DI14: 1.2 | DJ14: 0.1 | DK14: -2.1 | DL14: 0.3 | DM14: 0.6 | DO14: 0 | DP14: 0 | DQ14: -0.2 | DR14: 6.4 | DS14: 0 | DT14: 0.1 | DU14: 0 | DV14: 0.1 | DY14: -4.6 | DZ14: 0.8 | EA14: 3.2 | EB14: 3 | EE14: 0 | EF14: 0 | EG14: -3.8 | EH14: 0 | EI14: 0 | EK14: 0 | EL14: 0 | EN14: 0.2 | EO14: 0.2 | EP14: 0.2 | EQ14: -0.9 | ER14: 0 | ES14: 0 | ET14: 0 | EU14: 0 | EV14: -14.9 | EW14: 7.3 | EX14: 0 | EY14: 1.5 | EZ14: 0.8 | FA14: 0.6 | FB14: 0.3 | FC14: 0 | FD14: 0.2 | FE14: 1.5 | FF14: 1.2 | FG14: 1.9 | FI14: 6.9 | FJ14: 1.6 | FK14: 1.2 | FL14: 1.9 | FM14: 1.51 | FN14: 10.02 | FO14: 283.905 | FQ14: 2.44861 | FR14: -0.295 | FS14: 1.98819 | FT14: 0 | FU14: 0.33034 | FV14: 0.39223 | FW14: -1.3 | FX14: 1.1 | FY14: 4.66437
A15: 21/02/2026 | B15: 02:30 | C15: 33.4 | D15: -9.1 | E15: 15.5 | H15: -10.1 | I15: 9.2 | L15: -9.9 | M15: -5.8 | N15: -9.4 | O15: 9.4 | P15: -1.7 | Q15: 4.7 | R15: 40.1 | S15: 0 | T15: 1.5 | X15: -1.4 | Y15: 0.558 | Z15: 1.415 | AA15: 0 | AB15: -3.33 | AD15: -1.52 | AI15: 9.4 | AJ15: 3.2 | AN15: -1 | AO15: 62.3 | AP15: 8.1 | AQ15: 35.8 | AR15: 4.7 | AS15: 0.7 | AT15: 2.6 | AU15: 1.7 | AV15: 8.5 | AW15: -17.2 | AX15: -42.7 | AY15: 10.4 | AZ15: -2.2 | BA15: -1.6 | BB15: 0.6 | BC15: 0.4 | BD15: 17.7 | BG15: 3.6 | BJ15: 0 | BN15: 2 | BO15: 0 | BP15: 0 | BQ15: 0 | BS15: -4.7 | BT15: -8.7 | BY15: 0 | CA15: -0.3 | CB15: 28.4 | CC15: 21.1 | CD15: 5.8 | CE15: 5.9 | CF15: -2.5 | CJ15: 0 | CL15: 0 | CM15: 0 | CR15: -13.7 | CS15: -6.3 | CT15: -1.3 | CX15: -5.6 | CY15: 0 | CZ15: -0.9 | DB15: -0.2 | DC15: 0 | DD15: -1 | DE15: 0 | DH15: 0.2 | DI15: 1.3 | DJ15: 0.2 | DK15: -1.6 | DL15: 0.3 | DM15: 0.6 | DO15: 0 | DP15: 0 | DQ15: -0.2 | DR15: 6.3 | DS15: 0 | DT15: 0 | DU15: 0 | DV15: 0.1 | DY15: -4.6 | DZ15: 0.4 | EA15: 3.2 | EB15: 3 | EE15: 0 | EF15: 0 | EG15: 0 | EH15: 0 | EI15: 0 | EK15: 0 | EL15: 0 | EN15: 0.2 | EO15: 0.2 | EP15: 0.2 | EQ15: -0.9 | ER15: 0 | ES15: 0 | ET15: 0 | EU15: 0 | EV15: 0 | EW15: 0 | EX15: 0 | EY15: 1.5 | EZ15: 0.8 | FA15: 0.6 | FB15: 0.3 | FC15: 0 | FD15: 0.2 | FE15: 1.4 | FF15: 1.1 | FG15: 1.6 | FI15: 6.9 | FJ15: 1.8 | FK15: 0.25 | FL15: 2.39 | FM15: 1.52 | FN15: 11.02 | FO15: 226.803 | FQ15: 2.45224 | FR15: -0.378 | FS15: 2.18112 | FT15: 0 | FU15: 0.33136 | FV15: 0.38214 | FW15: -1.3 | FX15: 0.2 | FY15: 3.86886
A16: 21/02/2026 | B16: 03:00 | C16: 30.9 | D16: -4.7 | E16: 16.1 | H16: -11.8 | I16: 7 | L16: -10 | M16: -4.4 | N16: -8.2 | O16: 11 | P16: -7.4 | Q16: 1.7 | R16: 63.1 | S16: 0 | T16: 1.5 | X16: -1.3 | Y16: 0.67 | Z16: 1.518 | AA16: 0 | AB16: -3.34 | AD16: -1.57 | AI16: 9.3 | AJ16: 9.4 | AN16: -1.1 | AO16: 61.6 | AP16: 7.9 | AQ16: 36.1 | AR16: 4.7 | AS16: 0.3 | AT16: 2.6 | AU16: 1.5 | AV16: 5.1 | AW16: -20.4 | AX16: -45.7 | AY16: 10.1 | AZ16: -2.3 | BA16: -1.7 | BB16: 0.6 | BC16: 0.6 | BD16: 18.3 | BG16: 2.8 | BJ16: 0 | BN16: 0.5 | BO16: 0 | BP16: 0 | BQ16: 0 | BS16: -6 | BT16: -8.7 | BY16: 0 | CA16: -0.4 | CB16: 28.1 | CC16: 21.8 | CD16: 5.7 | CE16: 5.9 | CF16: -2.6 | CJ16: 0 | CL16: 0 | CM16: 0 | CR16: -14.9 | CS16: -7.1 | CT16: -1.3 | CX16: -5.6 | CY16: 0 | CZ16: -0.8 | DB16: 0 | DC16: 0 | DD16: -1 | DE16: 0 | DH16: 0.2 | DI16: 1.2 | DJ16: 0.2 | DK16: -1.6 | DL16: 0.3 | DM16: 0.6 | DO16: 0 | DP16: 0 | DQ16: -0.7 | DR16: 5.1 | DS16: 0 | DT16: 0 | DU16: 0 | DV16: 0.1 | DY16: -4.6 | DZ16: 0.6 | EA16: 3.1 | EB16: 2.8 | EE16: 0 | EF16: 0 | EG16: 0 | EH16: 0 | EI16: 0 | EK16: 0 | EL16: 0 | EN16: 0.2 | EO16: 0.2 | EP16: 0.2 | EQ16: -0.8 | ER16: 0 | ES16: 0 | ET16: 0 | EU16: 0 | EV16: 0 | EW16: 0 | EX16: 0 | EY16: 1.5 | EZ16: 0.8 | FA16: 0.6 | FB16: 0.3 | FC16: 0 | FD16: 0.1 | FE16: 1.5 | FF16: 1.3 | FG16: 1.9 | FI16: 6.5 | FJ16: 1.5 | FK16: 0.68 | FL16: 2.53 | FM16: 1.38 | FN16: 10.54 | FO16: 232.308 | FQ16: 2.40582 | FR16: -0.562 | FS16: 2.23525 | FT16: 1.7 | FU16: 0.33439 | FV16: 0.35076 | FW16: -1.6 | FX16: 0.2 | FY16: 5.06422
A17: 21/02/2026 | B17: 03:30 | C17: 30.6 | D17: -6.6 | E17: 15.7 | H17: -13.8 | I17: -6.1 | L17: -13.1 | M17: -7.4 | N17: -10.9 | O17: 4.7 | P17: -9.8 | Q17: -0.7 | R17: 67.1 | S17: 0.1 | T17: 1.1 | X17: -4.5 | Y17: 0.624 | Z17: 1.444 | AA17: 0 | AB17: -3.34 | AD17: -1.78 | AI17: 9.1 | AJ17: -4.7 | AN17: -1.1 | AO17: 60.8 | AP17: 7.8 | AQ17: 35.8 | AR17: 4.8 | AS17: 0.4 | AT17: 2.6 | AU17: 1 | AV17: 1.9 | AW17: -23.6 | AX17: -44.1 | AY17: 9.9 | AZ17: -2.4 | BA17: -2.2 | BB17: 0.6 | BC17: 0.6 | BD17: 17.2 | BG17: 1.8 | BJ17: 0 | BN17: -0.1 | BO17: 0 | BP17: 0 | BQ17: 0 | BS17: -7.1 | BT17: -8.7 | BY17: 0 | CA17: -0.3 | CB17: 28.8 | CC17: 20.7 | CD17: 5.7 | CE17: 5.9 | CF17: -2.4 | CJ17: 0 | CL17: 0 | CM17: 0 | CR17: -23.9 | CS17: -10.4 | CT17: -1.1 | CX17: -5.6 | CY17: 0 | CZ17: -0.9 | DB17: 0.1 | DC17: -0.1 | DD17: -0.8 | DE17: 0 | DH17: 0.1 | DI17: 1.3 | DJ17: 0.2 | DK17: -2 | DL17: 0.3 | DM17: 0.6 | DO17: 0 | DP17: 0 | DQ17: -0.6 | DR17: 5.2 | DS17: 0 | DT17: 0 | DU17: -0.1 | DV17: 0.1 | DY17: -4.6 | DZ17: 1.2 | EA17: 3.1 | EB17: 2.9 | EE17: 0 | EF17: 0 | EG17: 0 | EH17: 0 | EI17: 0 | EK17: 0 | EL17: 0 | EN17: 0.2 | EO17: 0.2 | EP17: 0.2 | EQ17: -0.9 | ER17: 0 | ES17: 0 | ET17: 0 | EU17: -0.2 | EV17: 0 | EW17: 0 | EX17: 0 | EY17: 1.5 | EZ17: 0.8 | FA17: 0.6 | FB17: 0.3 | FC17: 0 | FD17: 0.1 | FE17: 1.5 | FF17: 1.2 | FG17: 1.9 | FI17: 6.4 | FJ17: 1.1 | FK17: 0.85 | FL17: 2.7 | FM17: 1.33 | FN17: 10.16 | FO17: 156.988 | FQ17: 2.34727 | FR17: -0.685 | FS17: 1.83112 | FT17: 1.6 | FU17: 0.3282 | FV17: 0.28509 | FW17: -1.6 | FX17: 0.2 | FY17: 4.30668
A18: 21/02/2026 | B18: 04:00 | C18: 33.4 | D18: 9.9 | E18: 17.4 | H18: -9.8 | I18: 10.1 | L18: -4.4 | M18: -3 | N18: -5.8 | O18: 12.2 | P18: -8.1 | Q18: 2.7 | R18: 72.3 | S18: -0.1 | T18: 1.3 | X18: 2.2 | Y18: 0.785 | Z18: 1.757 | AA18: 0 | AB18: -3.36 | AD18: 0.38 | AI18: 11.2 | AJ18: 1.7 | AN18: -1.1 | AO18: 61.3 | AP18: 7.8 | AQ18: 37.5 | AR18: 6.1 | AS18: 0.2 | AT18: 2.6 | AU18: 0.9 | AV18: 1.8 | AW18: -24 | AX18: -42.9 | AY18: 10 | AZ18: -5 | BA18: -3.1 | BB18: 0.6 | BC18: 0.4 | BD18: 12.3 | BG18: 2.8 | BJ18: 0 | BN18: 4.6 | BO18: 0 | BP18: 0 | BQ18: 0 | BS18: -5.2 | BT18: -8.6 | BY18: 0 | CA18: -0.4 | CB18: 28 | CC18: 21.7 | CD18: 7.6 | CE18: 5.7 | CF18: -2.7 | CJ18: 0 | CL18: 0 | CM18: 0 | CR18: -26 | CS18: -11.4 | CT18: -1 | CX18: -5.6 | CY18: 0 | CZ18: -0.8 | DB18: 0 | DC18: 0 | DD18: -1.1 | DE18: 0 | DH18: 0.2 | DI18: 1.2 | DJ18: 0.2 | DK18: -2.4 | DL18: 0.3 | DM18: 0.6 | DO18: 0 | DP18: 0 | DQ18: -0.3 | DR18: 6.3 | DS18: 0 | DT18: 0.2 | DU18: 0 | DV18: 0.1 | DY18: -4.6 | DZ18: 1.5 | EA18: 3.2 | EB18: 2.9 | EE18: 0 | EF18: 0 | EG18: 0 | EH18: 0 | EI18: 0 | EK18: 0 | EL18: 0 | EN18: 0.2 | EO18: 0.2 | EP18: 0.2 | EQ18: -0.8 | ER18: 0 | ES18: 0 | ET18: 0 | EU18: -0.2 | EV18: 0 | EW18: 0 | EX18: 0 | EY18: 1.5 | EZ18: 0.8 | FA18: 0.6 | FB18: 0.3 | FC18: 0 | FD18: 0.1 | FE18: 1.6 | FF18: 1.3 | FG18: 2 | FI18: 6.2 | FJ18: 1.9 | FK18: 0.4 | FL18: 2.99 | FM18: 1.36 | FN18: 9.81 | FO18: 255.622 | FQ18: 2.35807 | FR18: -0.599 | FS18: 1.84275 | FT18: 1.6 | FU18: 0.32027 | FV18: 0.31005 | FW18: -1.5 | FX18: 0.2 | FY18: 4.53214
A19: 21/02/2026 | B19: 04:30 | C19: 35.7 | D19: 8.5 | E19: 18.4 | H19: -10.6 | I19: 13.4 | L19: -6.5 | M19: -0.3 | N19: -4.7 | O19: 13.5 | P19: -6.3 | Q19: 1.5 | R19: 74.9 | S19: 0 | T19: 1.3 | X19: 1.7 | Y19: 0.699 | Z19: 1.406 | AA19: 0 | AB19: -3.34 | AD19: 0.48 | AI19: 10 | AJ19: 8.4 | AN19: -1 | AO19: 61.9 | AP19: 7.9 | AQ19: 36.8 | AR19: 5.5 | AS19: 0.3 | AT19: 2.6 | AU19: 1.7 | AV19: 0.6 | AW19: -25.1 | AX19: -44.7 | AY19: 9.8 | AZ19: -2.5 | BA19: -2.1 | BB19: 0.6 | BC19: 0.6 | BD19: 16.8 | BG19: 3.2 | BJ19: 0 | BN19: 3 | BO19: 0 | BP19: 0 | BQ19: 0 | BS19: -5.6 | BT19: -8.6 | BY19: 0 | CA19: -0.4 | CB19: 29 | CC19: 22.2 | CD19: 6 | CE19: 8.2 | CF19: -2.6 | CJ19: 0 | CL19: 0 | CM19: 0 | CR19: -25.3 | CS19: -10.6 | CT19: -1.3 | CX19: -5.6 | CY19: 0 | CZ19: -0.9 | DB19: 0.1 | DC19: -0.1 | DD19: -0.9 | DE19: 0 | DH19: 0.2 | DI19: 1.2 | DJ19: 0.3 | DK19: -1.9 | DL19: 0.3 | DM19: 0.5 | DO19: 0 | DP19: 0 | DQ19: -0.5 | DR19: 5.5 | DS19: 0 | DT19: 0 | DU19: 0 | DV19: 0.1 | DY19: -4.6 | DZ19: 0.9 | EA19: 3.2 | EB19: 3 | EE19: 0 | EF19: 0 | EG19: -6.1 | EH19: 0 | EI19: 0 | EK19: 0 | EL19: 0 | EN19: 0.2 | EO19: 0.2 | EP19: 0.2 | EQ19: -0.9 | ER19: 0 | ES19: 0 | ET19: 0 | EU19: -0.2 | EV19: 0 | EW19: 0 | EX19: 0 | EY19: 1.5 | EZ19: 0.8 | FA19: 0.6 | FB19: 0.3 | FC19: 0 | FD19: 0.2 | FE19: 1.6 | FF19: 1.3 | FG19: 1.8 | FI19: 6.4 | FJ19: 2.7 | FK19: 0.41 | FL19: 3.22 | FM19: 1.23 | FN19: 9.87 | FO19: 271.175 | FQ19: 2.4028 | FR19: -0.437 | FS19: 2.37538 | FT19: 1.6 | FU19: 0.31986 | FV19: 0.33218 | FW19: -1.5 | FX19: 0.2 | FY19: 5.29322
A20: 21/02/2026 | B20: 05:00 | C20: 34.6 | D20: 0.8 | E20: 15.9 | H20: -9.3 | I20: 9.4 | L20: -12.1 | M20: -3.7 | N20: -9.5 | O20: 5.9 | P20: -9 | Q20: -0.2 | R20: 63.8 | S20: 0.3 | T20: 1.1 | X20: 1.2 | Y20: 0.931 | Z20: 1.83 | AA20: 0 | AB20: -3.35 | AD20: 0.31 | AI20: 9.2 | AJ20: 5.4 | AN20: -1 | AO20: 60.1 | AP20: 7.6 | AQ20: 36 | AR20: 6.2 | AS20: 0.2 | AT20: 2.6 | AU20: 2 | AV20: 0.9 | AW20: -24.8 | AX20: -45.1 | AY20: 9 | AZ20: -2.3 | BA20: -4.6 | BB20: 0.6 | BC20: 0.4 | BD20: 21.8 | BG20: 2.1 | BJ20: 0 | BN20: 1 | BO20: 0 | BP20: 0 | BQ20: 0 | BS20: -6 | BT20: -8.6 | BY20: 0 | CA20: -0.3 | CB20: 27.6 | CC20: 21.8 | CD20: 6.3 | CE20: 5.9 | CF20: -2.6 | CJ20: 0 | CL20: 0 | CM20: 0 | CR20: -25.5 | CS20: -10.7 | CT20: -1.5 | CX20: -5.5 | CY20: 0 | CZ20: -0.9 | DB20: 0.1 | DC20: -0.1 | DD20: -1 | DE20: 0.1 | DH20: 0.2 | DI20: 1.2 | DJ20: 0.2 | DK20: -2.1 | DL20: 0.3 | DM20: 0.6 | DO20: 0 | DP20: 0 | DQ20: -0.9 | DR20: 4.5 | DS20: 0.2 | DT20: 0 | DU20: 0.4 | DV20: 0.1 | DY20: -4.6 | DZ20: 1 | EA20: 3.1 | EB20: 3 | EE20: 0 | EF20: 0 | EG20: 0 | EH20: 0 | EI20: 0 | EK20: 0 | EL20: 0 | EN20: 0.2 | EO20: 0.2 | EP20: 0.2 | EQ20: -0.9 | ER20: 0 | ES20: 0.3 | ET20: 0 | EU20: -0.2 | EV20: 0 | EW20: 0 | EX20: 0 | EY20: 1.5 | EZ20: 0.8 | FA20: 0.6 | FB20: 0.3 | FC20: 0.3 | FD20: 0.2 | FE20: 1.6 | FF20: 1.3 | FG20: 1.9 | FI20: 7 | FJ20: 0.9 | FK20: 0.49 | FL20: 2.68 | FM20: 1.2 | FN20: 10.15 | FO20: 213.241 | FQ20: 2.30379 | FR20: -0.302 | FS20: 2.2695 | FT20: 1.6 | FU20: 0.31447 | FV20: 0.33466 | FW20: -1.5 | FX20: 0.2 | FY20: 5.22042
A21: 21/02/2026 | B21: 05:30 | C21: 31.9 | D21: -0.8 | E21: 17.2 | H21: -12.8 | I21: -5 | L21: -7.8 | M21: -0.8 | N21: -4.3 | O21: 11.7 | P21: -7.5 | Q21: 0.5 | R21: 70.9 | S21: 0.1 | T21: 1.3 | X21: -0.3 | Y21: 0.833 | Z21: 1.68 | AA21: 0 | AB21: -3.35 | AD21: -0.83 | AI21: 8.9 | AJ21: 6.6 | AN21: -1 | AO21: 60.1 | AP21: 7.8 | AQ21: 33.5 | AR21: 4.6 | AS21: 0.4 | AT21: 2.6 | AU21: 0.3 | AV21: 2.2 | AW21: -23.4 | AX21: -43.5 | AY21: 11.4 | AZ21: -2.1 | BA21: -4.2 | BB21: 0.6 | BC21: 0.6 | BD21: 18.9 | BG21: 3.2 | BJ21: 0 | BN21: -0.3 | BO21: 0 | BP21: 0 | BQ21: 0 | BS21: -6.2 | BT21: -8.7 | BY21: 0 | CA21: -0.3 | CB21: 29.2 | CC21: 20.6 | CD21: 5.5 | CE21: 5.9 | CF21: -2.6 | CJ21: 0 | CL21: 0 | CM21: 0 | CR21: -24.4 | CS21: -9.6 | CT21: -1.3 | CX21: -5.6 | CY21: 0 | CZ21: -0.9 | DB21: 0 | DC21: -0.1 | DD21: -1 | DE21: -0.1 | DH21: 0.1 | DI21: 1.2 | DJ21: 0.2 | DK21: -2.2 | DL21: 0.3 | DM21: 0.6 | DO21: 0 | DP21: 0 | DQ21: -0.7 | DR21: 4.8 | DS21: 0.5 | DT21: -0.1 | DU21: 0.4 | DV21: 0.1 | DY21: -4.6 | DZ21: 1.1 | EA21: 3.2 | EB21: 3 | EE21: 0 | EF21: 0 | EG21: 0 | EH21: 0 | EI21: 0 | EK21: 0 | EL21: 0 | EN21: 0.2 | EO21: 0.2 | EP21: 0.2 | EQ21: -0.9 | ER21: 0 | ES21: 0.3 | ET21: 0 | EU21: -0.2 | EV21: 0 | EW21: 0 | EX21: 0 | EY21: 1.5 | EZ21: 0.8 | FA21: 0.6 | FB21: 0.3 | FC21: 0.3 | FD21: 0.2 | FE21: 1.6 | FF21: 1.3 | FG21: 1.9 | FI21: 6.8 | FJ21: 1 | FK21: 0.6 | FL21: 1.85 | FM21: 1.2 | FN21: 9.59 | FO21: 217.473 | FQ21: 2.36972 | FR21: -0.283 | FS21: 1.94188 | FT21: 1.6 | FU21: 0.31723 | FV21: 0.36684 | FW21: -1.5 | FX21: 0.3 | FY21: 5.11267
A22: 21/02/2026 | B22: 06:00 | C22: 32.2 | D22: -0.7 | E22: 16.8 | H22: -12.2 | I22: 6.5 | L22: -8.5 | M22: -3.3 | N22: -6.5 | O22: 11.7 | P22: -6.6 | Q22: 1.2 | R22: 72.6 | S22: 0 | T22: 1.2 | X22: -0.9 | Y22: 1.076 | Z22: 1.737 | AA22: 0 | AB22: -3.37 | AD22: -2.28 | AI22: 9.3 | AJ22: 7.6 | AN22: -1 | AO22: 59.4 | AP22: 7.5 | AQ22: 33.5 | AR22: 4.5 | AS22: 0.1 | AT22: 2.6 | AU22: 1 | AV22: 5.5 | AW22: -20 | AX22: -41 | AY22: 10.4 | AZ22: -2.3 | BA22: 1.4 | BB22: 0.6 | BC22: 0.6 | BD22: 18 | BG22: 3.2 | BJ22: 0 | BN22: -0.9 | BO22: 0 | BP22: 0 | BQ22: 0 | BS22: -5.9 | BT22: -8.7 | BY22: 0 | CA22: -0.4 | CB22: 20.8 | CC22: 19.9 | CD22: 5.7 | CE22: 5.9 | CF22: -2.5 | CJ22: 0 | CL22: 0 | CM22: 0 | CR22: -23.4 | CS22: -9.2 | CT22: -1.3 | CX22: -5.6 | CY22: 0 | CZ22: -0.9 | DB22: 0.1 | DC22: -0.1 | DD22: -0.9 | DE22: 0 | DH22: 0.1 | DI22: 1.2 | DJ22: 0.2 | DK22: -2.1 | DL22: 0.3 | DM22: 0.6 | DO22: -0.1 | DP22: 0 | DQ22: -0.8 | DR22: 4.8 | DS22: 0.3 | DT22: -0.1 | DU22: 0.3 | DV22: 0.1 | DY22: -4.6 | DZ22: 1 | EA22: 3.2 | EB22: 2.9 | EE22: 0 | EF22: 0 | EG22: 0 | EH22: 0 | EI22: 0 | EK22: 0 | EL22: 0 | EN22: 0.2 | EO22: 0.2 | EP22: 0.2 | EQ22: -0.9 | ER22: 1.1 | ES22: 1.1 | ET22: -0.3 | EU22: -0.2 | EV22: 0 | EW22: 0 | EX22: -0.4 | EY22: 1.5 | EZ22: 0.8 | FA22: 0.6 | FB22: 0.3 | FC22: 1.4 | FD22: 0.2 | FE22: 1.8 | FF22: 1.5 | FG22: 2 | FI22: 7.2 | FJ22: 2 | FK22: 0.82 | FL22: 3.25 | FM22: 1.15 | FN22: 10.13 | FO22: 237.113 | FQ22: 2.37931 | FR22: -0.381 | FS22: 1.805 | FT22: 1.6 | FU22: 0.31357 | FV22: 0.34353 | FW22: -1.3 | FX22: 0.3 | FY22: 5.06041
... A58: 22/02/2026 | B58: 00:00 | C58: 36.9 | D58: 5.1 | E58: 14.9 | H58: -16.9 | I58: 9.7 | L58: 6.8 | M58: -7.7 | N58: 11.7 | O58: 29.4 | P58: 16 | Q58: 8.1 | R58: 82.2 | S58: 0 | T58: 0 | X58: 10.2 | Y58: 0.801 | Z58: 0.782 | AA58: 0 | AB58: -3.27 | AD58: 1.96 | AI58: 12.4 | AJ58: 8.1 | AN58: -1.3 | AO58: 65 | AP58: 8.5 | AQ58: 29.2 | AR58: 7 | AS58: 0.6 | AT58: 2.6 | AU58: 0.9 | AV58: 33.4 | AW58: 0.9 | AX58: -42.9 | AY58: 9.8 | AZ58: -1.9 | BA58: -0.6 | BB58: 0 | BC58: 0.8 | BD58: 16.9 | BG58: 8.3 | BJ58: -3.1 | BN58: 6.3 | BO58: 0 | BP58: 0 | BQ58: 1.9 | BS58: 0.1 | BT58: -1.8 | BY58: 0 | CA58: -0.3 | CB58: 23.2 | CC58: 18.2 | CD58: 1.8 | CE58: 9.7 | CF58: -0.1 | CJ58: 0 | CL58: 0 | CM58: 0 | CR58: -3.7 | CS58: -0.6 | CT58: -1.1 | CX58: -5.4 | CY58: 0 | CZ58: 0 | DB58: 0 | DC58: 0 | DD58: -1.1 | DE58: 0 | DH58: 0.1 | DI58: 1.5 | DJ58: 0.2 | DK58: -0.8 | DL58: 0.3 | DM58: 0.6 | DO58: 0 | DP58: 0 | DQ58: -5.3 | DR58: -3.6 | DS58: 0 | DT58: 0.1 | DU58: 0.5 | DV58: 0.1 | DY58: -4.6 | DZ58: 0.8 | EA58: 3.2 | EB58: 2.9 | EE58: 0 | EF58: -8.7 | EG58: -9.8 | EH58: -1.3 | EI58: 0 | EK58: 2.6 | EL58: -0.1 | EN58: 0.2 | EO58: 0.2 | EP58: 0.2 | EQ58: -0.8 | ER58: 0 | ES58: 0 | ET58: 0 | EU58: -0.2 | EV58: -10.7 | EW58: 8.7 | EX58: 0 | EY58: 1.5 | EZ58: 0.8 | FA58: 0.6 | FB58: 0.3 | FC58: 0 | FD58: 0.4 | FE58: 2 | FF58: 1.7 | FG58: 1.9 | FI58: 7 | FJ58: 1 | FK58: 0.57 | FL58: 2.72 | FM58: 3.52 | FN58: 10.42 | FO58: 419.103 | FQ58: 2.57843 | FR58: 0.311 | FS58: 2.50625 | FT58: 0 | FU58: 0.31676 | FV58: 0.34299 | FW58: -1.3 | FX58: 1.2 | FY58: 5.95543
A59: EJEC | C59: 834.35 | D59: 171.35 | E59: 409.3 | F59: 0 | G59: 0 | H59: -223.1 | I59: 227.15 | J59: 0 | K59: 0 | L59: 144.45 | M59: 8.5 | N59: 263.05 | O59: 682.05 | P59: 354.75 | Q59: 256.25 | R59: 1761.3 | S59: 1.05 | T59: 14.8 | U59: 0 | V59: 0 | W59: 0 | X59: 108.2 | Y59: 20.255 | Z59: 39.39 | AA59: 16.773 | AB59: -66.805 | AC59: 0 | AD59: 155.135 | AE59: 0 | AF59: 0 | AG59: 0 | AH59: 0 | AI59: 315.75 | AJ59: 205.9 | AK59: 0 | AL59: 0 | AM59: 0 | AN59: -22.2 | AO59: 1510.85 | AP59: 186.3 | AQ59: 791.4 | AR59: 193.05 | AS59: -7 | AT59: 62.4 | AU59: 35.15 | AV59: 597 | AW59: -41.9 | AX59: -889.95 | AY59: 259.05 | AZ59: -50.05 | BA59: 25.95 | BB59: 10 | BC59: 15.2 | BD59: 426.55 | BE59: 0 | BF59: 0 | BG59: 140.45 | BH59: 0 | BI59: 0 | BJ59: 3.6 | BK59: 0 | BL59: 0 | BM59: 0 | BN59: 159.7 | BO59: 97.95 | BP59: 53.75 | BQ59: 212.1 | BR59: 0 | BS59: 28.55 | BT59: -72.7 | BU59: 0 | BV59: 0 | BW59: 0 | BX59: 0 | BY59: 0.15 | BZ59: 0 | CA59: -8.45 | CB59: 1013.4 | CC59: 609 | CD59: 196.55 | CE59: 207.45 | CF59: 40.05 | CG59: 0 | CH59: 0 | CI59: 0 | CJ59: 506.05 | CK59: 0 | CL59: -30.35 | CM59: -69.95 | CN59: 0 | CO59: 0 | CP59: 0 | CQ59: 0 | CR59: -54.75 | CS59: 40.35 | CT59: -31.55 | CU59: 0 | CV59: 0 | CW59: 0 | CX59: -112.15 | CY59: 53.7 | CZ59: -16.05 | DA59: 0 | DB59: 1 | DC59: -0.65 | DD59: -24.1 | DE59: 137.7 | DF59: 0 | DG59: 0 | DH59: 3.6 | DI59: 37.6 | DJ59: 3.8 | DK59: -24.5 | DL59: 7.5 | DM59: 14.2 | DN59: 0 | DO59: -4.35 | DP59: -5.1 | DQ59: -61.65 | DR59: -16.45 | DS59: -21.1 | DT59: 0.7 | DU59: 8.6 | DV59: 2.4 | DW59: 0 | DX59: 0 | DY59: -108.7 | DZ59: 17.4 | EA59: 72.25 | EB59: 71.1 | EC59: 0 | ED59: 0 | EE59: 5.85 | EF59: -123.1 | EG59: -188.1 | EH59: -16.7 | EI59: -13 | EJ59: 0 | EK59: 16.35 | EL59: -0.65 | EM59: 0 | EN59: 4.8 | EO59: 4.8 | EP59: 4.8 | EQ59: -20.8 | ER59: 36.95 | ES59: 2.85 | ET59: 47 | EU59: -4.2 | EV59: -19.45 | EW59: 117.55 | EX59: -13.75 | EY59: 34.85 | EZ59: 17.95 | FA59: 12.4 | FB59: 7.2 | FC59: 3.2 | FD59: 12.2 | FE59: 44.5 | FF59: 36.9 | FG59: 45.45 | FH59: 0 | FI59: 192.05 | FJ59: 66.45 | FK59: 29.295 | FL59: 61.285 | FM59: 45.73 | FN59: 256.935 | FO59: 12587.343 | FQ59: 55.12445 | FR59: -10.1305 | FS59: 45.11687 | FT59: 24.5 | FU59: 32.92136 | FV59: 24.91541 | FW59: -11.75 | FX59: 11.65 | FY59: 172.34759

Sheet DEMANDA_AREAS
B3: sábado, 21 de Febrero del 2026
B5: REPORTE DE LA DEMANDA POR ÁREAS Y SUBAREAS OPERATIVAS (MW)
B6: FECHA HORA | C6: DEMANDA | E6: AREA | H6: SUBAREAS
C7: INTERCAMBIOS INTERNACIONALES | D7: SEIN | E7: NORTE | F7: CENTRO | G7: SUR | H7: ELECTROANDES
B8: 00:30 | C8: 0 | D8: 7156.865 | E8: 1051.9675 | F8: 4390.6475 | G8: 1714.25 | H8: 250.8322
B9: 01:00 | C9: 0 | D9: 7049.026 | E9: 1065.6833 | F9: 4255.7901 | G9: 1727.5526 | H9: 249.9611
B10: 01:30 | C10: 0 | D10: 6885.793 | E10: 1006.8657 | F10: 4173.3832 | G10: 1705.5441 | H10: 251.1628
B11: 02:00 | C11: 0 | D11: 6799.599 | E11: 1022.0147 | F11: 4084.1484 | G11: 1693.4359 | H11: 249.2976
B12: 02:30 | C12: 0 | D12: 6635.443 | E12: 1020.9204 | F12: 3953.3901 | G12: 1661.1325 | H12: 254.392
B13: 03:00 | C13: 0 | D13: 6672.625 | E13: 993.1892 | F13: 3997.8608 | G13: 1681.575 | H13: 253.7322
B14: 03:30 | C14: 0 | D14: 6520.62 | E14: 947.5901 | F14: 3898.2287 | G14: 1674.8012 | H14: 249.1977
B15: 04:00 | C15: 0 | D15: 6640.675 | E15: 990.4342 | F15: 3950.8011 | G15: 1699.4397 | H15: 246.5404
B16: 04:30 | C16: 0 | D16: 6640.491 | E16: 968.0357 | F16: 3972.5603 | G16: 1699.895 | H16: 245.1728
B17: 05:00 | C17: 0 | D17: 6574.897 | E17: 982.8138 | F17: 3899.3507 | G17: 1692.7325 | H17: 242.6887
B18: 05:30 | C18: 0 | D18: 6651.997 | E18: 959.3168 | F18: 3995.4302 | G18: 1697.25 | H18: 243.2734
B19: 06:00 | C19: 0 | D19: 6646.788 | E19: 1004.3796 | F19: 3954.9893 | G19: 1687.4191 | H19: 235.4646
... B59: ENERGÍA | C59: 0 | D59: 177139.78 | E59: 27516.382 | F59: 107756.09 | G59: 41867.312 | H59: 5773.1737
B61: LEYENDA:
D63: Potencia recibida del Ecuador
D64: Potencia entregada al Ecuador

Sheet DEMANDA_UL
B3: sábado, 21 de Febrero del 2026
B5: POTENCIA DE LOS GRANDES USUARIOS LIBRES (MW)
B6: FECHA HORA | C6: GRANDES USUARIOS LIBRES DEL ÁREA NORTE | X6: GRANDES USUARIOS LIBRES DEL ÁREA CENTRO | BP6: GRANDES USUARIOS LIBRES DEL ÁREA SUR
C7: ARCA CONTINENTAL LINDLEY S.A. | D7: AUSTRAL GROUP S.A.A | E7: CEMENTOS PACASMAYO | F7: CONSORCIO MINERO HORIZONTE S.R.L. | G7: CORPORACIÓN PESQUERA INCA S.A.C. | H7: CREDITEX: CIA IND.TEXTIL CREDISA | I7: HIPERMERCADOS TOTTUS S.A | J7: INDUSTRIA TEXTIL PIURA | K7: MINERA BOROO MISQUICHILCA S.A. | L7: MINERA GOLD FIELDS | M7: MINERA MARSA | N7: MINERA MISKY MAYO | O7: MINERA YANACOCHA | P7: OPEN PLAZA | Q7: PESQUERA DIAMANTE | R7: PETROPERU | S7: REAL PLAZA S.R.L. | T7: SIDER PERU | U7: SUPERMERCADOS PERUANOS S.A. | V7: TRUPAL S.A. | W7: UNIÓN DE CERVECERÍAS PERUANAS BACKUS Y JOHNSTON S. | X7: ACEROS AREQUIPA | Y7: ADMINISTRADORA JOCKEY PLAZA SHOPPING CENTER S.A. | Z7: ALICORP | AA7: ARCA CONTINENTAL LINDLEY S.A. | AB7: AUSTRAL GROUP S.A.A | AC7: COMPAÑIA MINERA CONDESTABLE | AD7: CORPORACIÓN PESQUERA INCA S.A.C. | AE7: CREDITEX: CIA IND.TEXTIL CREDISA | AF7: FUNDICION CHILCA S.A. | AG7: HIPERMERCADOS TOTTUS S.A | AH7: INMOBILIARIA KANPU S.A. | AI7: INMUEBLES PANAMERICANA S.A. | AJ7: KIMBERLY-CLARK PERU | AK7: LECHE GLORIA S.A. | AL7: MALL AVENTURA S.A. | AM7: MARCOBRE S.A.C. | AN7: MINERA ANTAMINA | AO7: MINERA ARES | AP7: MINERA BUENAVENTURA | AQ7: MINERA CHINALCO PERÚ S.A. | AR7: MINERA SHOUXIN PERU S.A. | AS7: MINERA VOLCAN | AT7: MINSUR | AU7: MOLYCOP-ADESUR | AV7: NEXA RESOURCES CAJAMARQUILLA S.A. | AW7: NEXA RESOURCES PERÚ S.A.A. | AX7: OPEN PLAZA | AY7: OPP FILM | AZ7: OWENS-ILLINOIS PERÚ S.A. | BA7: PAPELERA NACIONAL S.A. | BB7: PESQUERA DIAMANTE | BC7: QUIMPAC S.A. | BD7: REAL PLAZA S.R.L. | BE7: REFINERIA LA PAMPILLA S.A.A | BF7: SAGA FALABELLA | BG7: SAN MIGUEL INDUSTRIAS PET S.A. | BH7: SHOUGANG HIERRO PERU | BI7: SOFTYS PERU S.A.C. | BJ7: SUPERMERCADOS PERUANOS S.A. | BK7: TEJIDOS SAN JACINTO | BL7: TREN URBANO DE LIMA S.A. | BM7: TRUPAL S.A. | BN7: UNACEM PERU S.A. | BO7: UNIÓN DE CERVECERÍAS PERUANAS BACKUS Y JOHNSTON S. | BP7: ANGLO AMERICAN QUELLAVECO S.A. | BQ7: ARCA CONTINENTAL LINDLEY S.A. | BR7: CAL & CEMENTO SUR S.A. | BS7: COMPAÑIA MINERA ANTAPACCAY S.A. | BT7: COMPAÑÍA MINERA CHUNGAR SAC | BU7: COMPAÑIA MINERA SAN IGNACIO DE MOROCOCHA S.A.A. | BV7: EL BROCAL .S.A. | BW7: EMPRESA ADMINISTRADORA CERRO S.A.C. | BX7: EMPRESA MINERA LOS QUENUALES S.A.C. | BY7: HIPERMERCADOS TOTTUS S.A | BZ7: HUDBAY PERU S.A.C. | CA7: INDUSTRIA CACHIMAYO | CB7: MALL AVENTURA S.A. | CC7: MINERA ARES | CD7: MINERA BUENAVENTURA | CE7: MINERA CERRO VERDE | CF7: MINERA CORONA | CG7: MINERA LAS BAMBAS S.A. | CH7: MINERA VOLCAN | CI7: MINSUR | CJ7: MOLYCOP-ADESUR | CK7: NEXA RESOURCES PERÚ S.A.A. | CL7: OXIDOS DE PASCO S.A.C. | CM7: PESQUERA DIAMANTE | CN7: REAL PLAZA S.R.L. | CO7: SOBREANDES S.A.C. | CP7: SOUTHERN PERU CC | CQ7: SUPERMERCADOS PERUANOS S.A. | CR7: UNACEM PERU S.A. | CS7: UNIÓN DE CERVECERÍAS PERUANAS BACKUS Y JOHNSTON S. | CT7: YURA
B8: 00:30 | E8: 40.4783 | F8: 12.252 | K8: 20.8978 | L8: 26.1702 | M8: 14.8672 | N8: 12.5 | O8: 31.498 | R8: 41.554 | T8: 39.6567 | V8: 9.4 | X8: 152.16753 | Z8: 9.75357 | AC8: 15.53 | AK8: 0 | AL8: 1.8188 | AM8: 48.8324 | AN8: 122.27 | AO8: 28.504 | AP8: 0.81 | AQ8: 161.84 | AS8: 37.283 | AT8: 33.537 | AV8: 196.9602 | AW8: 31.132 | BA8: 2.5 | BC8: 68.87515 | BE8: 21.7 | BI8: 9.54741 | BN8: 57.257 | BO8: 2.01 | BP8: 141.0757 | BR8: 4.8551 | BS8: 135.65992 | BT8: 13.61461 | BV8: 29.481 | BW8: 3.85819 | BZ8: 87.41784 | CA8: 1.39815 | CB8: 0.5004 | CC8: 0.61 | CD8: 29.5341 | CE8: 415.21683 | CG8: 106.3029 | CH8: 17.614 | CI8: 0 | CK8: 16.1843 | CL8: 4.90013 | CO8: 16.55444 | CP8: 289.39 | CR8: 38.519 | CT8: 19.256
B9: 01:00 | E9: 40.75539 | F9: 11.441 | K9: 21.0276 | L9: 26.2012 | M9: 14.6362 | N9: 12.74 | O9: 31.704 | R9: 42.083 | T9: 43.2848 | V9: 9.4 | X9: 153.80589 | Z9: 9.60178 | AC9: 15.54 | AK9: 0 | AL9: 1.4859 | AM9: 49.9133 | AN9: 122.61 | AO9: 27.4548 | AP9: 0.7 | AQ9: 162.41 | AS9: 37.231 | AT9: 33.437 | AV9: 194.98762 | AW9: 30.6722 | BA9: 2.4 | BC9: 69.54647 | BE9: 21.7 | BI9: 9.65006 | BN9: 57.301 | BO9: 1.97 | BP9: 137.98627 | BR9: 4.9434 | BS9: 134.7357 | BT9: 14.09601 | BV9: 28.8901 | BW9: 3.96348 | BZ9: 91.18034 | CA9: 1.38581 | CB9: 0.4543 | CC9: 0.57 | CD9: 29.02895 | CE9: 414.37444 | CG9: 119.6199 | CH9: 17.786 | CI9: 0 | CK9: 16.1832 | CL9: 4.91855 | CO9: 16.59759 | CP9: 287.57 | CR9: 40.013 | CT9: 19.771
B10: 01:30 | E10: 40.77038 | F10: 11.983 | K10: 21.1888 | L10: 26.24 | M10: 15.002 | N10: 13.09 | O10: 32.214 | R10: 42.534 | T10: 52.6121 | V10: 9.3 | X10: 119.93776 | Z10: 9.35721 | AC10: 16.24 | AK10: 0 | AL10: 1.369 | AM10: 50.0126 | AN10: 121.83 | AO10: 27.6833 | AP10: 0.64 | AQ10: 164 | AS10: 36.243 | AT10: 30.632 | AV10: 196.82364 | AW10: 30.6872 | BA10: 2.5 | BC10: 69.68232 | BE10: 21.7 | BI10: 9.4143 | BN10: 57.024 | BO10: 1.94 | BP10: 141.45701 | BR10: 4.9365 | BS10: 134.52457 | BT10: 14.44536 | BV10: 28.3582 | BW10: 4.0073 | BZ10: 89.48454 | CA10: 1.37715 | CB10: 0.404 | CC10: 0.56 | CD10: 28.74893 | CE10: 419.41776 | CG10: 106.7993 | CH10: 17.716 | CI10: 0 | CK10: 16.2453 | CL10: 4.9088 | CO10: 17.05384 | CP10: 289.09 | CR10: 40.073 | CT10: 17.546
B11: 02:00 | E11: 40.31533 | F11: 11.904 | K11: 21.6444 | L11: 25.8751 | M11: 14.7394 | N11: 13.4 | O11: 31.784 | R11: 42.317 | T11: 52.7305 | V11: 9.4 | X11: 110.55462 | Z11: 9.56225 | AC11: 16.4 | AK11: 0 | AL11: 1.3335 | AM11: 50.4454 | AN11: 118.74 | AO11: 28.4563 | AP11: 0.44 | AQ11: 163.55 | AS11: 37.002 | AT11: 32.675 | AV11: 196.22938 | AW11: 31.9679 | BA11: 2.6 | BC11: 69.82332 | BE11: 21.7 | BI11: 9.44902 | BN11: 56.838 | BO11: 1.69 | BP11: 139.23452 | BR11: 4.9161 | BS11: 136.23857 | BT11: 14.02679 | BV11: 28.7487 | BW11: 3.7307 | BZ11: 88.72922 | CA11: 1.38295 | CB11: 0.3871 | CC11: 0.56 | CD11: 29.85848 | CE11: 416.03155 | CG11: 107.2256 | CH11: 17.336 | CI11: 0 | CK11: 16.8242 | CL11: 4.92159 | CO11: 16.40268 | CP11: 278.12 | CR11: 40.347 | CT11: 20.305
B12: 02:30 | E12: 39.54212 | F12: 12.669 | K12: 21.1332 | L12: 26.1773 | M12: 14.5778 | N12: 12.8 | O12: 31.402 | R12: 42.325 | T12: 46.1732 | V12: 9.5 | X12: 151.41425 | Z12: 9.42333 | AC12: 15.58 | AK12: 0 | AL12: 1.2945 | AM12: 50.4355 | AN12: 118.1 | AO12: 28.4106 | AP12: 0.41 | AQ12: 161.29 | AS12: 37.638 | AT12: 33 | AV12: 197.291 | AW12: 31.1754 | BA12: 2.4 | BC12: 69.47299 | BE12: 21.7 | BI12: 9.45531 | BN12: 56.718 | BO12: 2.07 | BP12: 139.31342 | BR12: 4.9083 | BS12: 134.54182 | BT12: 14.23654 | BV12: 26.7768 | BW12: 3.87202 | BZ12: 87.77 | CA12: 1.37529 | CB12: 0.3806 | CC12: 0.56 | CD12: 30.46055 | CE12: 413.24347 | CG12: 95.0603 | CH12: 17.165 | CI12: 0 | CK12: 17.5553 | CL12: 4.69877 | CO12: 16.9247 | CP12: 276.67 | CR12: 40.421 | CT12: 21.394
B13: 03:00 | E13: 39.23076 | F13: 12.883 | K13: 20.6803 | L13: 26.4112 | M13: 14.4646 | N13: 13.42 | O13: 31.068 | R13: 43.334 | T13: 46.1478 | V13: 9.6 | X13: 168.34945 | Z13: 9.36254 | AC13: 14.57 | AK13: 0 | AL13: 1.2672 | AM13: 50.7986 | AN13: 116.97 | AO13: 27.7754 | AP13: 0.67 | AQ13: 161.33 | AS13: 36.627 | AT13: 31.766 | AV13: 198.6527 | AW13: 32.0702 | BA13: 2.5 | BC13: 69.56062 | BE13: 21.7 | BI13: 9.27089 | BN13: 57.164 | BO13: 2.06 | BP13: 141.69821 | BR13: 4.9619 | BS13: 135.9155 | BT13: 14.63388 | BV13: 27.408 | BW13: 3.96593 | BZ13: 87.13091 | CA13: 1.38977 | CB13: 0.3718 | CC13: 0.56 | CD13: 28.6352 | CE13: 417.10506 | CG13: 106.5109 | CH13: 16.469 | CI13: 0 | CK13: 17.6598 | CL13: 4.65235 | CO13: 17.2643 | CP13: 283.35 | CR13: 40.291 | CT13: 21.538
B14: 03:30 | E14: 38.86066 | F14: 12.203 | K14: 17.1178 | L14: 26.2662 | M14: 14.8696 | N14: 13.4 | O14: 31.588 | R14: 43.264 | T14: 17.7905 | V14: 9.5 | X14: 135.98309 | Z14: 9.35604 | AC14: 14.63 | AK14: 0 | AL14: 1.2149 | AM14: 51.7045 | AN14: 116.3 | AO14: 27.8755 | AP14: 0.48 | AQ14: 160.52 | AS14: 37.323 | AT14: 31.221 | AV14: 197.87974 | AW14: 32.2096 | BA14: 2.5 | BC14: 69.66105 | BE14: 21.7 | BI14: 9.58597 | BN14: 64.415 | BO14: 2.05 | BP14: 141.68183 | BR14: 4.9825 | BS14: 133.69336 | BT14: 14.32909 | BV14: 28.1136 | BW14: 4.02736 | BZ14: 87.83722 | CA14: 1.38127 | CB14: 0.3703 | CC14: 0.57 | CD14: 28.78491 | CE14: 414.9282 | CG14: 105.7501 | CH14: 17.213 | CI14: 0 | CK14: 17.2173 | CL14: 4.92823 | CO14: 17.34677 | CP14: 277.21 | CR14: 39.732 | CT14: 21.753
B15: 04:00 | E15: 38.79907 | F15: 11.655 | K15: 15.9521 | L15: 26.1481 | M15: 14.7079 | N15: 12.91 | O15: 31.008 | R15: 42.74 | T15: 24.7545 | V15: 9.6 | X15: 125.7727 | Z15: 9.23544 | AC15: 15.34 | AK15: 0 | AL15: 1.2097 | AM15: 51.7644 | AN15: 117.84 | AO15: 27.5689 | AP15: 0.18 | AQ15: 163.33 | AS15: 37.827 | AT15: 31.513 | AV15: 196.19709 | AW15: 31.8233 | BA15: 2.2 | BC15: 69.50737 | BE15: 21.7 | BI15: 9.20579 | BN15: 65.9 | BO15: 2.14 | BP15: 142.07239 | BR15: 4.9317 | BS15: 136.79641 | BT15: 13.90796 | BV15: 28.2601 | BW15: 3.88656 | BZ15: 87.43122 | CA15: 1.38507 | CB15: 0.3576 | CC15: 0.59 | CD15: 28.86233 | CE15: 414.60196 | CG15: 114.575 | CH15: 17.412 | CI15: 0 | CK15: 16.9691 | CL15: 4.91675 | CO15: 17.38774 | CP15: 281.51 | CR15: 39.617 | CT15: 23.132
B16: 04:30 | E16: 38.80704 | F16: 11.839 | K16: 16.3585 | L16: 26.0146 | M16: 15.6083 | N16: 12.72 | O16: 31.578 | R16: 42.811 | T16: 38.6383 | V16: 9.4 | X16: 134.76623 | Z16: 9.12454 | AC16: 15.63 | AK16: 0 | AL16: 1.1723 | AM16: 49.7835 | AN16: 117.21 | AO16: 27.8426 | AP16: 1.65 | AQ16: 163.41 | AS16: 37.59 | AT16: 30.429 | AV16: 196.61669 | AW16: 32.0166 | BA16: 2.5 | BC16: 69.4419 | BE16: 21.7 | BI16: 9.41519 | BN16: 65.648 | BO16: 2.2 | BP16: 143.98222 | BR16: 4.9233 | BS16: 133.73726 | BT16: 13.39939 | BV16: 28.5365 | BW16: 3.90366 | BZ16: 86.82406 | CA16: 1.35465 | CB16: 0.3482 | CC16: 0.57 | CD16: 28.84262 | CE16: 417.97715 | CG16: 113.8473 | CH16: 17.3 | CI16: 0 | CK16: 16.4629 | CL16: 4.91023 | CO16: 17.43766 | CP16: 283.04 | CR16: 39.707 | CT16: 23.866
B17: 05:00 | E17: 38.75853 | F17: 12.248 | K17: 19.1082 | L17: 26.4088 | M17: 15.7532 | N17: 13.04 | O17: 32.01 | R17: 42.539 | T17: 38.2959 | V17: 9.4 | X17: 161.65145 | Z17: 9.3204 | AC17: 15.53 | AK17: 0 | AL17: 1.155 | AM17: 49.8009 | AN17: 117.94 | AO17: 27.0371 | AP17: 2.1 | AQ17: 163.87 | AS17: 36.431 | AT17: 32.077 | AV17: 197.32005 | AW17: 30.7992 | BA17: 2.6 | BC17: 61.49757 | BE17: 21.7 | BI17: 9.51998 | BN17: 65.92 | BO17: 2.16 | BP17: 141.05423 | BR17: 4.8975 | BS17: 136.60123 | BT17: 13.85384 | BV17: 27.2205 | BW17: 4.37541 | BZ17: 86.38834 | CA17: 1.33424 | CB17: 0.342 | CC17: 0.61 | CD17: 28.47826 | CE17: 414.06132 | CG17: 111.2456 | CH17: 18.154 | CI17: 0 | CK17: 15.6709 | CL17: 4.95763 | CO17: 16.34105 | CP17: 272.83 | CR17: 40.005 | CT17: 24.064
B18: 05:30 | E18: 38.25443 | F18: 10.841 | K18: 18.6835 | L18: 26.4928 | M18: 15.9299 | N18: 12.94 | O18: 31.96 | R18: 43.002 | T18: 33.9786 | V18: 9.5 | X18: 155.85519 | Z18: 9.42229 | AC18: 15.99 | AK18: 0 | AL18: 1.1414 | AM18: 48.9261 | AN18: 119 | AO18: 26.7634 | AP18: 1.93 | AQ18: 163.68 | AS18: 35.564 | AT18: 34.182 | AV18: 197.98258 | AW18: 30.9031 | BA18: 2.5 | BC18: 47.20331 | BE18: 21.7 | BI18: 9.33495 | BN18: 65.959 | BO18: 2.09 | BP18: 142.91292 | BR18: 4.8791 | BS18: 136.47025 | BT18: 12.33752 | BV18: 26.6646 | BW18: 3.85894 | BZ18: 86.43272 | CA18: 1.32975 | CB18: 0.3399 | CC18: 0.57 | CD18: 28.75293 | CE18: 422.70994 | CG18: 105.7372 | CH18: 18.126 | CI18: 0 | CK18: 16.0959 | CL18: 4.93786 | CO18: 14.96667 | CP18: 271.94 | CR18: 40.296 | CT18: 23.908
B19: 06:00 | E19: 34.2227 | F19: 10.134 | K19: 17.1661 | L19: 26.421 | M19: 16.0072 | N19: 13.24 | O19: 31.932 | R19: 42.84 | T19: 51.8054 | V19: 9.8 | X19: 153.3978 | Z19: 9.3174 | AC19: 16.29 | AK19: 0 | AL19: 1.2019 | AM19: 49.5793 | AN19: 117.45 | AO19: 21.4933 | AP19: 1.54 | AQ19: 163.86 | AS19: 34.789 | AT19: 33.998 | AV19: 197.15466 | AW19: 30.8557 | BA19: 2.5 | BC19: 47.08285 | BE19: 21.7 | BI19: 9.46832 | BN19: 65.88 | BO19: 2.14 | BP19: 144.10958 | BR19: 4.7178 | BS19: 134.58317 | BT19: 12.6462 | BV19: 25.8198 | BW19: 3.65085 | BZ19: 87.38048 | CA19: 1.28136 | CB19: 0.3394 | CC19: 0.65 | CD19: 28.09923 | CE19: 423.164 | CG19: 109.2964 | CH19: 18.118 | CI19: 0 | CK19: 16.4917 | CL19: 4.87732 | CO19: 14.19566 | CP19: 276.37 | CR19: 40.6 | CT19: 23.354
... B55: 00:00 | E55: 29.34285 | F55: 12.575 | K55: 17.9843 | L55: 26.8904 | M55: 14.5139 | N55: 14.07 | O55: 31.784 | R55: 44.246 | T55: 42.1392 | V55: 9.3 | X55: 45.22464 | Z55: 8.1914 | AC55: 17.66 | AK55: 0 | AL55: 2.1916 | AM55: 46.8815 | AN55: 117.89 | AO55: 27.1151 | AP55: 0.83 | AQ55: 162.89 | AS55: 36.919 | AT55: 34.783 | AV55: 196.71166 | AW55: 24.9519 | BA55: 2.5 | BC55: 70.10033 | BE55: 23.6 | BI55: 8.41451 | BN55: 63.291 | BO55: 2.04 | BP55: 144.14578 | BR55: 4.8516 | BS55: 134.8478 | BT55: 16.25462 | BV55: 29.3141 | BW55: 3.83695 | BZ55: 89.47 | CA55: 1.33394 | CB55: 0.5678 | CC55: 0.56 | CD55: 28.12558 | CE55: 424.74913 | CG55: 137.6329 | CH55: 18.111 | CI55: 0 | CK55: 17.4791 | CL55: 5.1685 | CO55: 15.22584 | CP55: 286.76 | CR55: 40.682 | CT55: 21.727
B56: MWh | C56: 0 | D56: 0 | E56: 793.91549 | F56: 274.62875 | G56: 0 | H56: 0 | I56: 0 | J56: 0 | K56: 447.3695 | L56: 659.78955 | M56: 331.08695 | N56: 327.83 | O56: 750.937 | P56: 0 | Q56: 0 | R56: 1026.389 | S56: 0 | T56: 972.96735 | U56: 0 | V56: 212.85 | W56: 0 | X56: 2484.2532 | Y56: 0 | Z56: 226.61084 | AA56: 0 | AB56: 0 | AC56: 394.66 | AD56: 0 | AE56: 0 | AF56: 0 | AG56: 0 | AH56: 0 | AI56: 0 | AJ56: 0 | AK56: 0 | AL56: 80.08925 | AM56: 1114.8029 | AN56: 2816.495 | AO56: 643.3331 | AP56: 18.01 | AQ56: 3882.37 | AR56: 0 | AS56: 862.3945 | AT56: 778.479 | AU56: 0 | AV56: 4379.481 | AW56: 678.2506 | AX56: 0 | AY56: 0 | AZ56: 0 | BA56: 59.55 | BB56: 0 | BC56: 1427.7409 | BD56: 0 | BE56: 530.6 | BF56: 0 | BG56: 0 | BH56: 0 | BI56: 212.01796 | BJ56: 0 | BK56: 0 | BL56: 0 | BM56: 0 | BN56: 1231.5765 | BO56: 49.415 | BP56: 3430.1773 | BQ56: 0 | BR56: 114.96755 | BS56: 3242.8295 | BT56: 320.3159 | BU56: 0 | BV56: 654.88055 | BW56: 93.385435 | BX56: 0 | BY56: 0 | BZ56: 2110.8143 | CA56: 31.34744 | CB56: 24.4278 | CC56: 13.975 | CD56: 689.79545 | CE56: 9804.6235 | CF56: 0 | CG56: 2377.4124 | CH56: 421.5745 | CI56: 0 | CJ56: 0 | CK56: 384.12505 | CL56: 114.97535 | CM56: 0 | CN56: 0 | CO56: 375.7595 | CP56: 6538.08 | CQ56: 0 | CR56: 903.676 | CS56: 0 | CT56: 443.2715
B59: Nota :
B60: Información proporcionada por la empresas
C62: DATOS ESTIMADOS
C64: SIN DATOS

Sheet TIPO_RECURSO
B3: sábado, 21 de Febrero del 2026
B5: REPORTE POTENCIA GENERADA POR TIPO DE RECURSO
B6: HORA | C6: H. PASADA | D6: H. REGULACION | E6: GAS DE CAMISEA | F6: GAS DE MALACAS | G6: GAS DE AGUAYTIA | H6: DIÉSEL | I6: RESIDUAL | J6: NAFTA+GAS DE REFINERIA | K6: FLEXIGAS+GAS DE REFINERIA | L6: BAGAZO | M6: BIOGÁS | N6: SOLAR | O6: EÓLICA | P6: TOTAL | U6: EMPRESA | V6: CENTRAL | W6: HIDROELECTRICA DE PASADA | X6: HIDROELECTRICA DE REGULACION
B7: 00:30 | C7: 1122.07 | D7: 3559.825 | E7: 2236.1 | F7: 45.4 | G7: 26.6 | H7: 0 | I7: 13.9 | K7: =DESPACHO_EJECUTADO!FI11 -> 29.8 | L7: 65.27 | M7: 8.1 | N7: 0 | O7: 49.8 | P7: =SUM(C7:O7) -> 7156.865 | U7: ANDEAN POWER S.A.C. | V7: C.H.CARHUAC | W7: 463.3
B8: 01:00 | C8: 1136.77 | D8: 3612.076 | E8: 2072.4 | F8: 45.4 | G8: 27.2 | H8: 0 | I8: 15.8 | K8: =DESPACHO_EJECUTADO!FI12 -> 30 | L8: 65.98 | M8: 8.1 | N8: 0 | O8: 35.3 | P8: =SUM(C8:O8) -> 7049.026 | U8: ASOCIACIÓN SANTA LUCIA DE CHACAS | V8: C.H. HUALLIN | W8: 76.8
B9: 01:30 | C9: 1129.79 | D9: 3542.693 | E9: 2017.1 | F9: 14.4 | G9: 26.9 | H9: 0 | I9: 16.1 | K9: =DESPACHO_EJECUTADO!FI13 -> 29.8 | L9: 66.11 | M9: 8.1 | N9: 0 | O9: 34.8 | P9: =SUM(C9:O9) -> 6885.793 | U9: CELEPSA | V9: C.H. EL PLATANAL | X9: 4668.5
B10: 02:00 | C10: 1170 | D10: 3534.389 | E10: 1909.6 | F10: 0 | G10: 27.3 | H10: 0 | I10: 16.1 | K10: =DESPACHO_EJECUTADO!FI14 -> 29.8 | L10: 66.41 | M10: 8.1 | N10: 0 | O10: 37.9 | P10: =SUM(C10:O10) -> 6799.599 | U10: CELEPSA RENOVABLES S.R.L. | V10: C.H. MARAÑON | W10: 451.2
B11: 02:30 | C11: 1169.11 | D11: 3565.113 | E11: 1749.6 | F11: 0 | G11: 0 | H11: 0 | I11: 16.1 | K11: =DESPACHO_EJECUTADO!FI15 -> 30.3 | L11: 66.92 | M11: 8.1 | N11: 0 | O11: 30.2 | P11: =SUM(C11:O11) -> 6635.443 | U11: CHINANGO S.A.C. | V11: C.H. CHIMAY | X11: 3617.25
B12: 03:00 | C12: 1149.11 | D12: 3659.025 | E12: 1708.1 | F12: 0 | G12: 0 | H12: 0 | I12: 16.1 | K12: =DESPACHO_EJECUTADO!FI16 -> 30.8 | L12: 66.29 | M12: 8.1 | N12: 0 | O12: 35.1 | P12: =SUM(C12:O12) -> 6672.625 | V12: C.H. YANANGO | W12: 999
B13: 03:30 | C13: 1134.81 | D13: 3643.77 | E13: 1581.2 | F13: 0 | G13: 0 | H13: 0 | I13: 16.3 | K13: =DESPACHO_EJECUTADO!FI17 -> 30.7 | L13: 66.64 | M13: 8.1 | N13: 0 | O13: 39.1 | P13: =SUM(C13:O13) -> 6520.62 | U13: EGASA | V13: C.H. CHARCANI III | W13: 131.555
B14: 04:00 | C14: 1172.01 | D14: 3780.145 | E14: 1539.2 | F14: 0 | G14: 0 | H14: 0 | I14: 16.2 | K14: =DESPACHO_EJECUTADO!FI18 -> 31.2 | L14: 66.82 | M14: 8.1 | N14: 0 | O14: 27 | P14: =SUM(C14:O14) -> 6640.675 | V14: C.H. CHARCANI V | X14: 3421.115
B15: 04:30 | C15: 1180.01 | D15: 3825.431 | E15: 1483.9 | F15: 0 | G15: 0 | H15: 0 | I15: 16.1 | K15: =DESPACHO_EJECUTADO!FI19 -> 30.9 | L15: 65.15 | M15: 8.1 | N15: 0 | O15: 30.9 | P15: =SUM(C15:O15) -> 6640.491 | U15: EGEJUNIN | V15: C.H. HUASAHUASI I | W15: 475.4
B16: 05:00 | C16: 1169.28 | D16: 3730.887 | E16: 1513.7 | F16: 0 | G16: 0 | H16: 0 | I16: 16.4 | K16: =DESPACHO_EJECUTADO!FI20 -> 30.7 | L16: 67.23 | M16: 8.1 | N16: 0 | O16: 38.6 | P16: =SUM(C16:O16) -> 6574.897 | V16: C.H. RUNATULLO II | W16: 486.4
B17: 05:30 | C17: 1165.31 | D17: 3775.037 | E17: 1554.1 | F17: 0 | G17: 0 | H17: 0 | I17: 16.4 | K17: =DESPACHO_EJECUTADO!FI21 -> 30.8 | L17: 67.85 | M17: 8.1 | N17: 0.1 | O17: 34.3 | P17: =SUM(C17:O17) -> 6651.997 | V17: C.H. RUNATULLO III | W17: 485.6
B18: 06:00 | C18: 1164.4 | D18: 3710.948 | E18: 1603.3 | F18: 0 | G18: 0 | H18: 0 | I18: 16.3 | K18: =DESPACHO_EJECUTADO!FI22 -> 30.9 | L18: 68.24 | M18: 8.1 | N18: 11.9 | O18: 32.7 | P18: =SUM(C18:O18) -> 6646.788 | V18: C.H. SANTA CRUZ I | W18: 275.05
B19: 06:30 | C19: 1163.52 | D19: 3555.265 | E19: 1533.5 | F19: 0 | G19: 0 | H19: 0 | I19: 16 | K19: =DESPACHO_EJECUTADO!FI23 -> 31.1 | L19: 67.57 | M19: 8.1 | N19: 74.8 | O19: 27.2 | P19: =SUM(C19:O19) -> 6477.055 | U19: EGEMSA | V19: C.H. MACHUPICCHU | W19: 3964.15
B20: 07:00 | C20: 1160.36 | D20: 3459.774 | E20: 1488.2 | F20: 0 | G20: 0 | H20: 0 | I20: 14.3 | K20: =DESPACHO_EJECUTADO!FI24 -> 30.8 | L20: 68.6 | M20: 8.1 | N20: 226.9 | O20: 63.1 | P20: =SUM(C20:O20) -> 6520.134 | U20: EGESUR | V20: C.H. ARICOTA I | X20: 189.404
B21: 07:30 | C21: 1178.14 | D21: 3608.116 | E21: 1487.9 | F21: 0 | G21: 0 | H21: 0 | I21: 14.4 | K21: =DESPACHO_EJECUTADO!FI25 -> 32.1 | L21: 69.56 | M21: 8.1 | N21: 385.2 | O21: 54 | P21: =SUM(C21:O21) -> 6837.516 | V21: C.H. ARICOTA II | X21: 142.713
B22: 08:00 | C22: 1137.77 | D22: 3481.961 | E22: 1494.5 | F22: 0 | G22: 0 | H22: 0 | I22: 14.1 | K22: =DESPACHO_EJECUTADO!FI26 -> 32.1 | L22: 69.43 | M22: 8.1 | N22: 594.3 | O22: 52 | P22: =SUM(C22:O22) -> 6884.261 | U22: ELECTRICA YANAPAMPA SAC | V22: C.H. YANAPAMPA | W22: 76.05
B23: 08:30 | C23: 1088.1 | D23: 3480.204 | E23: 1738.278 | F23: 43.9 | G23: 0 | H23: 0 | I23: 14.4 | K23: =DESPACHO_EJECUTADO!FI27 -> 31.9 | L23: 69.05 | M23: 8.1 | N23: 708 | O23: 78.2 | P23: =SUM(C23:O23) -> 7260.132 | U23: ELECTROPERU | V23: C.H. MANTARO | X23: 13850.75
B24: 09:00 | C24: 1100.1 | D24: 3478.138 | E24: 1974.104 | F24: 45.3 | G24: 0 | H24: 0 | I24: 14.1 | K24: =DESPACHO_EJECUTADO!FI28 -> 30.4 | L24: 70.65 | M24: 8.1 | N24: 636.4 | O24: 87.8 | P24: =SUM(C24:O24) -> 7445.092 | V24: C.H. RESTITUCION | W24: 4663.9
B25: 09:30 | C25: 1047.9 | D25: 3536.375 | E25: 2246.06 | F25: 45 | G25: 0 | H25: 1.8 | I25: 14.3 | K25: =DESPACHO_EJECUTADO!FI29 -> 31.9 | L25: 67.1 | M25: 8.1 | N25: 588.5 | O25: 105 | P25: =SUM(C25:O25) -> 7692.035 | U25: EMPRESA DE GENERACION ELECTRICA CANCHAYLLO SAC | V25: C.H. CANCHAYLLO | W25: 121.35
B26: 10:00 | C26: 1095.1 | D26: 3598.628 | E26: 2310.849 | F26: 44.4 | G26: 0 | H26: 0 | I26: 0 | K26: =DESPACHO_EJECUTADO!FI30 -> 30.1 | L26: 70.46 | M26: 8 | N26: 523.8 | O26: 127.1 | P26: =SUM(C26:O26) -> 7808.437 | U26: EMPRESA DE GENERACION ELECTRICA SANTA ANA S.A.C. | V26: C.H. RENOVANDES H1 | W26: 407.15
B27: 10:30 | C27: 1080.3 | D27: 3416.411 | E27: 2548.214 | F27: 44.4 | G27: 0 | H27: 0 | I27: 0 | K27: =DESPACHO_EJECUTADO!FI31 -> 29.8 | L27: 66.24 | M27: 7.9 | N27: 529.2 | O27: 178.8 | P27: =SUM(C27:O27) -> 7901.265 | U27: EMPRESA DE GENERACION HUALLAGA | V27: C.H. CHAGLLA | X27: 10945.9
B28: 11:00 | C28: 1052 | D28: 3480.339 | E28: 2576.804 | F28: 44.9 | G28: 0 | H28: 0 | I28: 0 | K28: =DESPACHO_EJECUTADO!FI32 -> 29.8 | L28: 70.77 | M28: 7.8 | N28: 481.3 | O28: 260.2 | P28: =SUM(C28:O28) -> 8003.913 | V28: P.C.H. CHAGLLA | W28: 156
B29: 11:30 | C29: 1039.3 | D29: 3353.524 | E29: 2477.435 | F29: 44.8 | G29: 0 | H29: 0 | I29: 0 | K29: =DESPACHO_EJECUTADO!FI33 -> 27.3 | L29: 69.33 | M29: 7.4 | N29: 604.3 | O29: 321.9 | P29: =SUM(C29:O29) -> 7945.289 | U29: EMPRESA DE GENERACION HUANZA | V29: C.H. HUANZA | X29: 1415.3
B30: 12:00 | C30: 1051.07 | D30: 3434.174 | E30: 2326.984 | F30: 44.7 | G30: 0 | H30: 0 | I30: 0 | K30: =DESPACHO_EJECUTADO!FI34 -> 26.8 | L30: 70.01 | M30: 7.1 | N30: 682.4 | O30: 338.3 | P30: =SUM(C30:O30) -> 7981.538 | U30: EMPRESA ELECTRICA AGUA AZUL | V30: C.H. POTRERO | W30: 478.55
B31: 12:30 | C31: 1036.82 | D31: 3303.49 | E31: 2253.29 | F31: 44.8 | G31: 0 | H31: 0 | I31: 0 | K31: =DESPACHO_EJECUTADO!FI35 -> 26.8 | L31: 69.32 | M31: 6.3 | N31: 787.1 | O31: 344.6 | P31: =SUM(C31:O31) -> 7872.52 | U31: EMPRESA ELECTRICA RIO DOBLE | V31: C.H. LAS PIZARRAS | W31: 451.85
B32: 13:00 | C32: 1047.59 | D32: 3454.073 | E32: 2185.188 | F32: 44.9 | G32: 0 | H32: 0 | I32: 0 | K32: =DESPACHO_EJECUTADO!FI36 -> 26.9 | L32: 70.57 | M32: 7.2 | N32: 646.1 | O32: 414.4 | P32: =SUM(C32:O32) -> 7896.921 | U32: ENGIE ENERGIA PERU S.A.A. | V32: C.H. YUNCAN | X32: 3052.05
B33: 13:30 | C33: 1152.49 | D33: 3686.511 | E33: 1903.8 | F33: 44.2 | G33: 0 | H33: 0 | I33: 0 | K33: =DESPACHO_EJECUTADO!FI37 -> 26.9 | L33: 66.29 | M33: 7.2 | N33: 571.4 | O33: 454.1 | P33: =SUM(C33:O33) -> 7912.891 | U33: GENERACIÓN ANDINA S.A.C. | V33: C.H. 8 DE AGOSTO | W33: 132.9
B34: 14:00 | C34: 1096.98 | D34: 3727.898 | E34: 1805.7 | F34: 44.4 | G34: 0 | H34: 0 | I34: 0 | K34: =DESPACHO_EJECUTADO!FI38 -> 26.9 | L34: 69.11 | M34: 7.2 | N34: 591.6 | O34: 506.6 | P34: =SUM(C34:O34) -> 7876.388 | V34: C.H. EL CARMEN | W34: 49.85
B35: 14:30 | C35: 1100.87 | D35: 3573.32 | E35: 1727.7 | F35: 44 | G35: 0 | H35: 0 | I35: 0 | K35: =DESPACHO_EJECUTADO!FI39 -> 26 | L35: 67.6 | M35: 7.2 | N35: 770 | O35: 572.7 | P35: =SUM(C35:O35) -> 7889.39 | U35: GENERADORA DE ENERGÍA DEL PERÚ | V35: C.H. ÁNGEL I | W35: 489.6
B36: 15:00 | C36: 1078.81 | D36: 3558.56 | E36: 1755.1 | F36: 43.9 | G36: 0 | H36: 0 | I36: 0 | K36: =DESPACHO_EJECUTADO!FI40 -> 26.8 | L36: 66.8 | M36: 7.2 | N36: 593.7 | O36: 589.2 | P36: =SUM(C36:O36) -> 7720.07 | V36: C.H. ÁNGEL II | W36: 489.6
B37: 15:30 | C37: 1104.1 | D37: 3712.828 | E37: 1801.4 | F37: 45.1 | G37: 0 | H37: 0 | I37: 0 | K37: =DESPACHO_EJECUTADO!FI41 -> 26.8 | L37: 70.61 | M37: 7.2 | N37: 347.9 | O37: 528.9 | P37: =SUM(C37:O37) -> 7644.838 | V37: C.H. ÁNGEL III | W37: 480
B38: 16:00 | C38: 1104.46 | D38: 3741.062 | E38: 1850.7 | F38: 44.2 | G38: 0 | H38: 0 | I38: 0 | K38: =DESPACHO_EJECUTADO!FI42 -> 29.9 | L38: 70.8 | M38: 7.2 | N38: 186.2 | O38: 567.4 | P38: =SUM(C38:O38) -> 7601.922 | U38: HIDROCAÑETE S.A. | V38: C.H. IMPERIAL | W38: 84.8
B39: 16:30 | C39: 1097.36 | D39: 3718.933 | E39: 1938.2 | F39: 44.2 | G39: 0 | H39: 0 | I39: 0 | K39: =DESPACHO_EJECUTADO!FI43 -> 29.7 | L39: 69.99 | M39: 7.3 | N39: 76.8 | O39: 598.5 | P39: =SUM(C39:O39) -> 7580.983 | U39: HIDROELECTRICA HUANCHOR S.A.C. | V39: C.H. HUANCHOR | W39: 441.95
B40: 17:00 | C40: 1103.81 | D40: 3682.592 | E40: 1953 | F40: 44 | G40: 0 | H40: 0 | I40: 0 | K40: =DESPACHO_EJECUTADO!FI44 -> 30 | L40: 67.73 | M40: 7.3 | N40: 47.5 | O40: 597.7 | P40: =SUM(C40:O40) -> 7533.632 | U40: HUAURA POWER GROUP S.A. | V40: C.H. YARUCAYA | W40: 444
B41: 17:30 | C41: 1137.11 | D41: 3707.379 | E41: 1914.9 | F41: 43.7 | G41: 0 | H41: 0 | I41: 0 | K41: =DESPACHO_EJECUTADO!FI45 -> 29.7 | L41: 67.39 | M41: 7.3 | N41: 20.9 | O41: 591.3 | P41: =SUM(C41:O41) -> 7519.679 | U41: HYDRO GLOBAL PERÚ S.A.C. | V41: CH SAN GABAN III | X41: 4851.7
B42: 18:00 | C42: 1169.12 | D42: 3645.768 | E42: 1794.6 | F42: 44.7 | G42: 0 | H42: 0 | I42: 0 | K42: =DESPACHO_EJECUTADO!FI46 -> 30.1 | L42: 69.12 | M42: 7.4 | N42: 4.8 | O42: 634.1 | P42: =SUM(C42:O42) -> 7399.708 | U42: INLAND ENERGY SAC | V42: C.H. SANTA TERESA | W42: 2162.55
B43: 18:30 | C43: 1191.41 | D43: 3750.68 | E43: 1933.7 | F43: 44.3 | G43: 0 | H43: 0 | I43: 0 | K43: =DESPACHO_EJECUTADO!FI47 -> 29.7 | L43: 68.02 | M43: 7.7 | N43: 0 | O43: 575.3 | P43: =SUM(C43:O43) -> 7600.81 | U43: INVERSIONES SHAQSHA S.A.C. | V43: C.H. PARIAC | W43: 50.4
B44: 19:00 | C44: 1193.34 | D44: 3811.469 | E44: 2274.4 | F44: 44.5 | G44: 0 | H44: 0 | I44: 0 | K44: =DESPACHO_EJECUTADO!FI48 -> 32.9 | L44: 68.45 | M44: 7.7 | N44: 0 | O44: 496.8 | P44: =SUM(C44:O44) -> 7929.559 | U44: KALLPA GENERACION S.A. | V44: C.H. CERRO DEL AGUILA | X44: 12876.45
B45: 19:30 | C45: 1190.79 | D45: 3835.479 | E45: 2314.4 | F45: 44.5 | G45: 0 | H45: 0 | I45: 0 | K45: =DESPACHO_EJECUTADO!FI49 -> 33.6 | L45: 69.07 | M45: 7.7 | N45: 0 | O45: 443.2 | P45: =SUM(C45:O45) -> 7938.739 | V45: M.C.H. CERRO DEL AGUILA | W45: 244.85
B46: 20:00 | C46: 1186.83 | D46: 3827.378 | E46: 2412 | F46: 44.7 | G46: 0 | H46: 0 | I46: 0 | K46: =DESPACHO_EJECUTADO!FI50 -> 34 | L46: 70.54 | M46: 8 | N46: 0 | O46: 381.1 | P46: =SUM(C46:O46) -> 7964.548 | U46: LA VIRGEN | V46: C.H. LA VIRGEN | X46: 1947.7
B47: 20:30 | C47: 1192.06 | D47: 3832.842 | E47: 2396.323 | F47: 44.8 | G47: 0 | H47: 0 | I47: 0 | K47: =DESPACHO_EJECUTADO!FI51 -> 33.7 | L47: 69.47 | M47: 8 | N47: 0 | O47: 350.4 | P47: =SUM(C47:O47) -> 7927.595 | U47: MAJA ENERGIA S.A.C. | V47: C.H. RONCADOR | W47: 50.7
B48: 21:00 | C48: 1192.25 | D48: 3821.065 | E48: 2425.285 | F48: 44.5 | G48: 0 | H48: 0 | I48: 0 | K48: =DESPACHO_EJECUTADO!FI52 -> 34.1 | L48: 69.18 | M48: 8 | N48: 0 | O48: 266.8 | P48: =SUM(C48:O48) -> 7861.18 | U48: ORAZUL ENERGY PERÚ | V48: C.H. CAÑA BRAVA | W48: 132.25
B49: 21:30 | C49: 1200.55 | D49: 3844.116 | E49: 2404.927 | F49: 44.5 | G49: 0 | H49: 0 | I49: 0 | K49: =DESPACHO_EJECUTADO!FI53 -> 28.7 | L49: 69.99 | M49: 8.1 | N49: 0 | O49: 222.1 | P49: =SUM(C49:O49) -> 7822.983 | V49: C.H. CAÑON DEL PATO | X49: 5430.45
B50: 22:00 | C50: 1191.99 | D50: 3791.077 | E50: 2395.522 | F50: 44.5 | G50: 0 | H50: 0 | I50: 0 | K50: =DESPACHO_EJECUTADO!FI54 -> 20.2 | L50: 74.13 | M50: 8.1 | N50: 0 | O50: 179.5 | P50: =SUM(C50:O50) -> 7705.019 | V50: C.H. CARHUAQUERO | X50: 2158.45
B51: 22:30 | C51: 1192.51 | D51: 3761.886 | E51: 2388.9 | F51: 45 | G51: 0 | H51: 0 | I51: 0 | K51: =DESPACHO_EJECUTADO!FI55 -> 18.9 | L51: 73.45 | M51: 8.1 | N51: 0 | O51: 169 | P51: =SUM(C51:O51) -> 7657.746 | V51: C.H. CARHUAQUERO IV | W51: 238.5
B52: 23:00 | C52: 1185.91 | D52: 3713.176 | E52: 2267.3 | F52: 44.5 | G52: 0 | H52: 0 | I52: 0 | K52: =DESPACHO_EJECUTADO!FI56 -> 17.8 | L52: 74.95 | M52: 8.1 | N52: 0 | O52: 154.1 | P52: =SUM(C52:O52) -> 7465.836 | U52: ORYGEN PERU S.A.A. | V52: C.H. CALLAHUANCA | X52: 1541.6
B53: 23:30 | C53: 1180.51 | D53: 3729.231 | E53: 2032 | F53: 44.2 | G53: 0 | H53: 0 | I53: 0 | K53: =DESPACHO_EJECUTADO!FI57 -> 17.9 | L53: 75.5 | M53: 8.1 | N53: 0 | O53: 154.6 | P53: =SUM(C53:O53) -> 7242.041 | V53: C.H. HER 1 | W53: 12.95
B54: 00:00 | C54: 1175.01 | D54: 3728.603 | E54: 1912.7 | F54: 44 | G54: 0 | H54: 0 | I54: 0 | K54: =DESPACHO_EJECUTADO!FI58 -> 17.9 | L54: 72.87 | M54: 8.1 | N54: 0 | O54: 123.9 | P54: =SUM(C54:O54) -> 7083.083 | V54: C.H. HUAMPANI | W54: 672.4
B55: TOTAL MWh | C55: =SUM(C7:C54)/2 -> 27279.505 | D55: =SUM(D7:D54)/2 -> 87390.832 | E55: =SUM(E7:E54)/2 -> 47606.081 | F55: =SUM(F7:F54)/2 -> 764.35 | G55: =SUM(G7:G54)/2 -> 54 | H55: =SUM(H7:H54)/2 -> 0.9 | I55: =SUM(I7:I54)/2 -> 146.7 | J55: =SUM(J7:J54)/2 -> 0 | ... P55: =SUM(P7:P54)/2 -> 177139.78 | V55: C.H. HUINCO | X55: 5642.45
B56: % | C56: =C55*100/$P$55 -> 15.399988 | D56: =D55*100/$P$55 -> 49.33439 | E56: =E55*100/$P$55 -> 26.874867 | F56: =F55*100/$P$55 -> 0.43149539 | G56: =G55*100/$P$55 -> 0.0304844 | H56: =H55*100/$P$55 -> 0.00050807333 | I56: =I55*100/$P$55 -> 0.082815953 | J56: =J55*100/$P$55 -> 0 | ... P56: =P55*100/$P$55 -> 100 | V56: C.H. MATUCANA | X56: 3112.05
V57: C.H. MOYOPAMPA | W57: 1528.05
U58: SAN GABAN | V58: C.H. SAN GABAN II | X58: 2644.55
V59: PCH TUPURI | W59: 52.65
U60: SINERSA | V60: C.H. CHANCAY | W60: 480.25
V61: C.H. POECHOS II | W61: 188.8
V62: C.H. RUCUY | W62: 479.9
U63: STATKRAFT S.A | V63: C.H. ARCATA | W63: 33.6
V64: C.H. CAHUA | W64: 1042.7
V65: C.H. CHEVES | X65: 4059.2
V66: C.H. GALLITO CIEGO | X66: 762.2
V67: C.H. MALPASO | X67: 1061.05
V68: C.H. YAUPI | W68: 2542.65
U69: TRANSMISION ANDINA DE GENERACION S.A.C. | V69: C.H. OROYA | W69: 173.8
U70: VARI ENERGIA S.A.C. | V70: C.H. ANASHIRONI | W70: 416.5
U71: TOTAL MWh | W71: 27279.505 | X71: 87390.832

Sheet GENERACION RER
B3: sábado, 21 de Febrero del 2026
B5: GENERACIÓN ELÉCTRICA DE LAS CENTRALES RER (MW)
B6: HORA | C6: ACCIONA ENERGIA PERU S.A.C | D6: AGRO INDUSTRIAL PARAMONGA S.A. | E6: AGROAURORA S.A.C. | F6: AGROINDUSTRIAS SAN JACINTO S.A.A. | G6: AGROLMOS SOCIEDAD ANONIMA - AGROLMOS S.A. | H6: ANDEAN POWER S.A.C. | I6: ASOCIACIÓN SANTA LUCIA DE CHACAS | J6: ATRIA ENERGIA S.A.C. | K6: BIOENERGIA DEL CHIRA S.A. | L6: CASA GRANDE S.A.A. | M6: CELARIS ENERGY S.A. | N6: COENERGY S.A.C. | O6: COLCA SOLAR S.A.C. | P6: EGEJUNIN | U6: ELECTRICA YANAPAMPA SAC | V6: EMPRESA DE GENERACION ELECTRICA CANCHAYLLO SAC | W6: EMPRESA DE GENERACION ELECTRICA SANTA ANA S.A.C. | X6: EMPRESA ELECTRICA AGUA AZUL | Y6: EMPRESA ELECTRICA RIO DOBLE | Z6: ENERGÍA EÓLICA S.A. | AB6: ENERGIA RENOVABLE DEL SUR S.A. | AC6: ENERGIA RENOVABLE LA JOYA S.A. | AE6: ENGIE ENERGIA PERU S.A.A. | AI6: GENERACIÓN ANDINA S.A.C. | AK6: GENERADORA DE ENERGÍA DEL PERÚ | AO6: GR CORTARRAMA SOCIEDAD ANONIMA CERRADA | AP6: GR PAINO SOCIEDAD ANONIMA CERRADA | AQ6: GR TARUCA SOCIEDAD ANONIMA CERRADA | AR6: GR VALE S.A.C. | AS6: HIDROCAÑETE S.A. | AT6: HUAURA POWER GROUP S.A. | AU6: HYDRO PATAPO S.A.C. | AV6: JOYA SOLAR S.A.C. | AW6: KALLPA GENERACION S.A. | AY6: KONDU SAC | AZ6: MAJA ENERGIA S.A.C. | BA6: MAJES ARCUS S.A.C. | BC6: MOQUEGUA FV S.A.C. | BD6: ORAZUL ENERGY PERÚ | BF6: ORYGEN PERU S.A.A. | BL6: PANAMERICANA SOLAR SAC. | BM6: PARQUE EOLICO MARCONA S.A.C. | BN6: PARQUE EOLICO TRES HERMANAS S.A.C. | BO6: PETRAMAS | BS6: REPARTICIÓN ARCUS S.A.C. | BT6: SAN GABAN | BU6: SINERSA | BX6: TACNA SOLAR SAC. | BY6: VARI ENERGIA S.A.C. | BZ6: TOTAL RER
C7: C.S. SAN JOSE | D7: C.T. PARAMONGA | E7: C.T. MAPLE | F7: C.T SAN JACINTO | G7: C.T. AGROLMOS | H7: C.H. CARHUAC | I7: C.H. HUALLIN | J7: C.H. PURMACANA | K7: C.T. CAÑA BRAVA | L7: C.T. CASA GRANDE | M7: C.H. MANTA | N7: CS COENERGY | O7: CS YARUCAYA | P7: C.H. HUASAHUASI I | Q7: C.H. HUASAHUASI II | R7: C.H. RUNATULLO II | S7: C.H. RUNATULLO III | T7: C.H. STA CRUZ I y II | U7: C.H. YANAPAMPA | V7: C.H. CANCHAYLLO | W7: C.H. RENOVANDES H1 | X7: C.H. POTRERO | Y7: C.H. LAS PIZARRAS | Z7: C.E. CUPISNIQUE | AA7: C.E. TALARA | AB7: CE SAN JUAN | AC7: C.S. ILLA 1 | AD7: C.S. ILLA 2 | AE7: C.E. P LOM EXPANSION | AF7: C.E. PUNTA LOMITAS | AG7: C.S. INTIPAMPA | AH7: CS EXPANSIÓN INTIPAMPA | AI7: C.H. 8 DE AGOSTO | AJ7: C.H. EL CARMEN | AK7: C.H. ANGEL I | AL7: C.H. ANGEL II | AM7: C.H. ANGEL III | AN7: C.H. LA JOYA | AO7: CS MATARANI | AP7: C.E. HUAMBOS | AQ7: C.E. DUNA | AR7: C.S. LUPI | AS7: C.H. NUEVAIMPERIAL | AT7: C.H. YARUCAYA | AU7: MCH PATAPO | AV7: CS SAN MARTIN SOLAR | AW7: CS SUNNY | AX7: CS SUNNY EXPANSION | AY7: CARHUAQUERO (CS) | AZ7: C.H. RONCADOR | BA7: C.S. MAJES | BB7: C.S. SOL DE VERANO | BC7: C.S. MOQUEGUA FV | BD7: C.H. CANA BRAVA | BE7: C.H. CARHUAQUERO4 | BF7: C.E. WAYRA EXTENSION | BG7: C.E. WAYRA I | BH7: C.H. HER 1 | BI7: C.S. CLEMESI | BJ7: C.S. RUBI | BK7: C.S. Wayra Solar | BL7: C.S. PANAMERICANA-SOLAR | BM7: C.E. MARCONA | BN7: C.E. 3 HERMANAS | BO7: C.T. HUAYCOLORO | BP7: C.T. LA GRINGA V | BQ7: CTB CALLAO | BR7: CTB. DONA CATALINA | BS7: C.S. REPARTICION | BT7: C.H. TUPURI | BU7: C.H. CHANCAY | BV7: C.H. POECHOS2 | BW7: C.H. RUCUY | BX7: C.S. TACNA-SOLAR | BY7: C.H. ANASHIRONI | BZ7: MW
B8: 0:30 | D8: 16 | E8: 12.49 | F8: 8.22 | G8: 4.97 | H8: 20 | I8: 3.2 | K8: 8.9 | L8: 14.69 | P8: 19.8 | R8: 20.2 | S8: 20.2 | T8: 13.1 | U8: 3.1 | V8: 5 | W8: 20.1 | X8: 20 | Y8: 18.9 | Z8: 18.6 | AA8: 1.9 | AB8: 4.8 | AF8: 0.9 | AK8: 20.4 | AL8: 20.4 | AM8: 20 | AP8: 1.8 | AQ8: 1.8 | AS8: 3.6 | AT8: 18.5 | AZ8: 2 | BD8: 5.5 | BE8: 10 | BF8: 7 | BG8: 9.5 | BM8: 1.1 | BN8: 2.4 | BO8: 3 | BP8: 0.7 | BQ8: 2.4 | BR8: 2 | BT8: 2.2 | BU8: 20 | BV8: 8.1 | BW8: 20 | BY8: 20.1 | BZ8: 457.57
B9: 1:00 | D9: 16.2 | E9: 12.49 | F9: 7.88 | G9: 4.97 | H9: 20.1 | I9: 3.2 | K9: 8.8 | L9: 15.64 | P9: 19.8 | R9: 20.3 | S9: 20.2 | T9: 13.1 | U9: 3.1 | V9: 4.9 | W9: 20.6 | X9: 20 | Y9: 18.9 | Z9: 13.2 | AA9: 3.5 | AB9: 7.2 | AK9: 20.4 | AL9: 20.4 | AM9: 20 | AP9: 2 | AQ9: 2 | AS9: 3.5 | AT9: 18.5 | AZ9: 2 | BD9: 5.5 | BE9: 9.9 | BF9: 1.7 | BG9: 3.3 | BM9: 0.6 | BN9: 1.8 | BO9: 3 | BP9: 0.7 | BQ9: 2.4 | BR9: 2 | BT9: 2.2 | BU9: 20 | BV9: 8.2 | BW9: 20 | BY9: 20.4 | BZ9: 444.58
B10: 1:30 | D10: 16.5 | E10: 12.49 | F10: 8.23 | G10: 4.97 | H10: 20.1 | I10: 3.2 | K10: 8.5 | L10: 15.42 | P10: 19.8 | R10: 20.2 | S10: 20.2 | T10: 13 | U10: 3.1 | V10: 5.1 | W10: 20.6 | X10: 20 | Y10: 18.9 | Z10: 7.3 | AA10: 2 | AB10: 14.5 | AK10: 20.4 | AL10: 20.4 | AM10: 20 | AP10: 1.8 | AQ10: 1.8 | AS10: 3.5 | AT10: 18.5 | AZ10: 2 | BD10: 5.5 | BE10: 9.9 | BF10: 0.3 | BG10: 1.7 | BM10: 1.4 | BN10: 4 | BO10: 3 | BP10: 0.7 | BQ10: 2.4 | BR10: 2 | BT10: 2.2 | BU10: 20 | BV10: 8.1 | BW10: 19.9 | BY10: 20.4 | BZ10: 444.01
B11: 2:00 | D11: 17 | E11: 12.48 | F11: 8.07 | G11: 4.97 | H11: 20.1 | I11: 3.2 | K11: 8.2 | L11: 15.69 | P11: 19.8 | R11: 20.3 | S11: 20.2 | T11: 13 | U11: 3.1 | V11: 5.1 | W11: 20.4 | X11: 20 | Y11: 18.9 | Z11: 7.3 | AB11: 16.4 | AF11: 1.5 | AK11: 20.4 | AL11: 20.4 | AM11: 20 | AP11: 2 | AQ11: 2 | AS11: 3.5 | AT11: 18.5 | AZ11: 2.7 | BD11: 5.5 | BE11: 9.9 | BF11: 1.8 | BG11: 1.7 | BM11: 1.6 | BN11: 3.6 | BO11: 3 | BP11: 0.7 | BQ11: 2.4 | BR11: 2 | BT11: 2.2 | BU11: 20 | BV11: 8.1 | BW11: 20 | BY11: 20.3 | BZ11: 448.01
B12: 2:30 | D12: 16.7 | E12: 12.5 | F12: 8.04 | G12: 4.97 | H12: 20.2 | I12: 3.2 | K12: 8.2 | L12: 16.51 | P12: 19.8 | R12: 20.3 | S12: 20.3 | T12: 13 | U12: 3.1 | V12: 5.1 | W12: 20.4 | X12: 20 | Y12: 18.9 | Z12: 7.7 | AB12: 15.3 | AK12: 20.4 | AL12: 20.4 | AM12: 20 | AP12: 2 | AQ12: 2 | AS12: 3.5 | AT12: 18.5 | AZ12: 2.7 | BD12: 5.5 | BE12: 9.9 | BM12: 0.8 | BN12: 2.4 | BO12: 3 | BP12: 0.7 | BQ12: 2.4 | BR12: 2 | BT12: 2.2 | BU12: 20 | BV12: 8.1 | BW12: 20 | BY12: 20.3 | BZ12: 441.02
B13: 3:00 | D13: 17.2 | E13: 12.5 | F13: 7.33 | G13: 4.97 | H13: 20.2 | I13: 3.2 | K13: 8.5 | L13: 15.79 | P13: 19.8 | R13: 20.2 | S13: 20.2 | T13: 13 | U13: 3.2 | V13: 5.1 | W13: 20.1 | X13: 20 | Y13: 18.9 | Z13: 9.3 | AA13: 0.4 | AB13: 16.4 | AK13: 20.4 | AL13: 20.4 | AM13: 20 | AP13: 0.8 | AQ13: 0.8 | AS13: 3.6 | AT13: 18.5 | AZ13: 2.7 | BD13: 5.5 | BE13: 9.9 | BH13: 0.6 | BM13: 1.9 | BN13: 5.5 | BO13: 3 | BP13: 0.7 | BQ13: 2.4 | BR13: 2 | BT13: 2.2 | BU13: 20 | BV13: 8.1 | BW13: 20 | BY13: 20.1 | BZ13: 445.39
B14: 3:30 | D14: 17.2 | E14: 12.5 | F14: 7.21 | G14: 4.97 | H14: 20.1 | I14: 3.2 | K14: 8.9 | L14: 15.86 | P14: 19.8 | R14: 20.3 | S14: 20.2 | T14: 13 | U14: 3.2 | V14: 5.1 | W14: 20.2 | X14: 20 | Y14: 18.9 | Z14: 11 | AA14: 1.5 | AB14: 17.4 | AK14: 20.4 | AL14: 20.4 | AM14: 20 | AP14: 1.5 | AQ14: 1.5 | AS14: 3.6 | AT14: 18.5 | AZ14: 2.1 | BD14: 5.4 | BE14: 10 | BH14: 0.6 | BM14: 1.9 | BN14: 4.3 | BO14: 3 | BP14: 0.7 | BQ14: 2.4 | BR14: 2 | BT14: 2.2 | BU14: 19.9 | BV14: 8.1 | BW14: 19.8 | BY14: 20.3 | BZ14: 449.14
B15: 4:00 | D15: 17.3 | E15: 12.49 | F15: 6.76 | G15: 4.97 | H15: 20.3 | I15: 3.2 | K15: 8.9 | L15: 16.4 | P15: 19.8 | R15: 20.4 | S15: 20.2 | T15: 13 | U15: 3.2 | V15: 5.1 | W15: 20.2 | X15: 20 | Y15: 18.9 | Z15: 6.4 | AA15: 0.8 | AB15: 13.7 | AK15: 20.4 | AL15: 20.4 | AM15: 20 | AP15: 1 | AQ15: 1 | AS15: 3.6 | AT15: 18.5 | AZ15: 2.5 | BD15: 5.5 | BE15: 9.9 | BH15: 0.6 | BM15: 1.2 | BN15: 2.9 | BO15: 3 | BP15: 0.7 | BQ15: 2.4 | BR15: 2 | BT15: 2.2 | BU15: 20.1 | BV15: 8 | BW15: 20 | BY15: 20.2 | BZ15: 438.12
B16: 4:30 | D16: 16.7 | E16: 12.5 | F16: 5.92 | G16: 4.97 | H16: 20.2 | I16: 3.2 | K16: 8.4 | L16: 16.66 | P16: 19.8 | R16: 20.3 | S16: 20.3 | T16: 13 | U16: 3.2 | V16: 5 | W16: 20.6 | X16: 20 | Y16: 18.9 | Z16: 3.1 | AA16: 0.1 | AB16: 18.4 | AF16: 0.2 | AK16: 20.4 | AL16: 20.4 | AM16: 20 | AP16: 1.6 | AQ16: 1.6 | AS16: 3.6 | AT16: 18.5 | AZ16: 2.6 | BD16: 5.4 | BE16: 9.8 | BH16: 0.6 | BM16: 1.5 | BN16: 4.4 | BO16: 3 | BP16: 0.7 | BQ16: 2.4 | BR16: 2 | BT16: 2.2 | BU16: 20 | BV16: 8 | BW16: 20 | BY16: 20.5 | BZ16: 440.65
B17: 5:00 | D17: 16.6 | E17: 12.51 | F17: 8.44 | G17: 4.98 | H17: 20.2 | I17: 3.2 | K17: 8.5 | L17: 16.2 | P17: 19.8 | R17: 20.3 | S17: 20.2 | T17: 13 | U17: 3.1 | V17: 5 | W17: 20.1 | X17: 20 | Y17: 18.9 | Z17: 3.9 | AA17: 0.4 | AB17: 25.7 | AK17: 20.4 | AL17: 20.4 | AM17: 20 | AP17: 1.6 | AQ17: 1.6 | AS17: 3.7 | AT17: 18.5 | AZ17: 2.6 | BD17: 5.5 | BE17: 9.9 | BH17: 0.6 | BM17: 1.8 | BN17: 3.6 | BO17: 3 | BP17: 0.7 | BQ17: 2.4 | BR17: 2 | BT17: 2.2 | BU17: 20 | BV17: 8 | BW17: 20 | BY17: 20.3 | BZ17: 449.83
B18: 5:30 | D18: 16.3 | E18: 11.53 | F18: 8.12 | G18: 5.27 | H18: 20.2 | I18: 3.2 | K18: 8.7 | L18: 17.93 | P18: 19.8 | R18: 20.2 | S18: 20.2 | T18: 13 | U18: 3 | V18: 5.1 | W18: 20.4 | X18: 20 | Y18: 18.9 | Z18: 3 | AA18: 0.1 | AB18: 22 | AK18: 20.4 | AL18: 20.4 | AM18: 20 | AP18: 2 | AQ18: 2 | AS18: 3.6 | AT18: 18.5 | AZ18: 2 | BC18: 0.1 | BD18: 5.5 | BE18: 10 | BH18: 0.6 | BM18: 1.2 | BN18: 4 | BO18: 3 | BP18: 0.7 | BQ18: 2.4 | BR18: 2 | BT18: 2.2 | BU18: 20 | BV18: 8 | BW18: 20 | BY18: 20.3 | BZ18: 445.85
B19: 6:00 | D19: 17 | E19: 11.44 | F19: 7.77 | G19: 5.27 | H19: 20.2 | I19: 3.2 | K19: 8.8 | L19: 17.96 | P19: 19.8 | R19: 20.3 | S19: 20.3 | T19: 13 | U19: 3.2 | V19: 5.1 | W19: 20.3 | X19: 20 | Y19: 18.9 | Z19: 5.6 | AA19: 0.6 | AB19: 18.6 | AK19: 20.4 | AL19: 20.4 | AM19: 20 | AP19: 2 | AQ19: 2 | AS19: 3.6 | AT19: 18.5 | AV19: 2.6 | AW19: 1.7 | AZ19: 2.1 | BC19: 2.1 | BD19: 5.5 | BE19: 10.1 | BH19: 0.6 | BI19: 1 | BJ19: 1 | BL19: 2.3 | BM19: 1.1 | BN19: 2.8 | BO19: 3 | BP19: 0.7 | BQ19: 2.4 | BR19: 2 | BT19: 2.2 | BU19: 20 | BV19: 8 | BW19: 20 | BX19: 1.2 | BY19: 20.3 | BZ19: 456.94
B20: 6:30 | D20: 16.7 | E20: 12.22 | F20: 7.89 | G20: 5.27 | H20: 20 | I20: 3.2 | K20: 8.1 | L20: 17.39 | P20: 19.9 | R20: 20.3 | S20: 20.3 | T20: 13 | U20: 3.1 | V20: 5.1 | W20: 20.6 | X20: 20 | Y20: 18.9 | Z20: 2.4 | AB20: 19.5 | AG20: 1.3 | AH20: 0.3 | AK20: 20.4 | AL20: 20.4 | AM20: 20 | AO20: 11.4 | AP20: 1.2 | AQ20: 1.2 | AS20: 3.5 | AT20: 18.5 | AV20: 8.6 | AW20: 5.8 | AZ20: 2.1 | BA20: 2.1 | BC20: 8.1 | BD20: 5.4 | BE20: 9.9 | BH20: 0.6 | BI20: 10.4 | BJ20: 8.4 | BL20: 9.1 | BM20: 1.2 | BN20: 1.7 | BO20: 3 | BP20: 0.7 | BQ20: 2.4 | BR20: 2 | BS20: 0.6 | BT20: 2.2 | BU20: 20 | BV20: 8 | BW20: 20 | BX20: 8.7 | BY20: 20.4 | BZ20: 513.47
B21: 7:00 | D21: 16.8 | E21: 12.86 | F21: 8.23 | G21: 5.27 | H21: 17.8 | I21: 3.2 | K21: 7.2 | L21: 18.24 | N21: 0.1 | O21: 0.1 | P21: 19.8 | R21: 20.3 | S21: 20.2 | T21: 13.1 | U21: 3.2 | V21: 5.1 | W21: 20.6 | X21: 20 | Y21: 18.9 | Z21: 7.7 | AB21: 34.5 | AG21: 3.2 | AH21: 2 | AK21: 20.4 | AL21: 20.4 | AM21: 20 | AO21: 12.8 | AP21: 2 | AQ21: 2 | AS21: 3.5 | AT21: 18.5 | AV21: 14.6 | AW21: 15.7 | AZ21: 2.2 | BA21: 4.3 | BC21: 11.5 | BD21: 5.4 | BE21: 9.9 | BH21: 0.7 | BI21: 57.1 | BJ21: 75.3 | BL21: 14.1 | BM21: 5.4 | BN21: 11.5 | BO21: 3 | BP21: 0.7 | BQ21: 2.4 | BR21: 2 | BS21: 1.5 | BT21: 2.2 | BU21: 20 | BV21: 8 | BW21: 20 | BX21: 14.6 | BY21: 20.5 | BZ21: 700.6
B22: 7:30 | D22: 16.7 | E22: 12.46 | F22: 7.42 | G22: 6.96 | H22: 17.3 | I22: 3.2 | K22: 7.3 | L22: 18.72 | N22: 0.1 | O22: 0.2 | P22: 19.9 | R22: 20.4 | S22: 20.3 | T22: 13.1 | U22: 3.1 | V22: 5 | W22: 20.7 | X22: 17.1 | Y22: 18.8 | Z22: 3.9 | AB22: 32.1 | AG22: 7.7 | AH22: 4 | AK22: 20.4 | AL22: 20.4 | AM22: 20 | AO22: 16.5 | AP22: 1.9 | AQ22: 1.9 | AS22: 3.4 | AT22: 18.5 | AV22: 52.3 | AW22: 45.2 | AZ22: 2 | BA22: 5.8 | BC22: 12.5 | BD22: 5.6 | BE22: 10 | BH22: 0.6 | BI22: 87.5 | BJ22: 119.9 | BL22: 15.5 | BM22: 4 | BN22: 10.2 | BO22: 3 | BP22: 0.7 | BQ22: 2.4 | BR22: 2 | BS22: 2.4 | BT22: 2.2 | BU22: 20 | BV22: 8 | BW22: 20 | BX22: 15.6 | BY22: 20.5 | BZ22: 847.36
B23: 8:00 | D23: 17.2 | E23: 12.31 | F23: 8.05 | G23: 6.96 | H23: 17.2 | I23: 3.2 | K23: 7.4 | L23: 17.51 | N23: 0.2 | O23: 0.3 | P23: 19.9 | R23: 20.2 | S23: 20.2 | T23: 13.1 | U23: 3.2 | V23: 5 | W23: 19.8 | X23: 20 | Y23: 18.8 | AB23: 32.3 | AG23: 8.9 | AH23: 9.3 | AK23: 20.4 | AL23: 20.4 | AM23: 20 | AO23: 74.8 | AP23: 2 | AQ23: 2 | AS23: 3.5 | AT23: 18.5 | AV23: 108.5 | AW23: 110.5 | AY23: 0.1 | AZ23: 2 | BA23: 8.3 | BC23: 11.5 | BD23: 5.6 | BE23: 10 | BH23: 0.6 | BI23: 96.6 | BJ23: 133 | BL23: 15.7 | BM23: 4.5 | BN23: 11.2 | BO23: 3 | BP23: 0.7 | BQ23: 2.4 | BR23: 2 | BS23: 6.3 | BT23: 2.2 | BU23: 20 | BV23: 7.9 | BW23: 19.8 | BX23: 10.3 | BY23: 20 | BZ23: 1055.33
B24: 8:30 | D24: 16.4 | E24: 13.02 | F24: 7.72 | G24: 6.96 | H24: 17.1 | I24: 3.2 | K24: 8.4 | L24: 16.55 | N24: 0.2 | O24: 0.5 | P24: 19.8 | R24: 20.3 | S24: 20.2 | T24: 13.1 | U24: 3.1 | V24: 5 | W24: 20.7 | X24: 20 | Y24: 18.9 | AB24: 47 | AG24: 36.4 | AH24: 13.4 | AK24: 20.4 | AL24: 20.4 | AM24: 20 | AO24: 76.1 | AP24: 2.1 | AQ24: 2.1 | AS24: 3.5 | AT24: 18.5 | AV24: 146.1 | AW24: 145.6 | AY24: 0.1 | AZ24: 2 | BA24: 10.3 | BC24: 8.3 | BD24: 5.5 | BE24: 10 | BH24: 0.6 | BI24: 100.1 | BJ24: 136.2 | BL24: 13 | BM24: 8.1 | BN24: 18.9 | BO24: 3 | BP24: 0.7 | BQ24: 2.4 | BR24: 2 | BS24: 7.9 | BT24: 2.2 | BU24: 20 | BV24: 7.9 | BW24: 20 | BX24: 13.8 | BY24: 20.4 | BZ24: 1196.15
B25: 9:00 | D25: 16.7 | E25: 13.03 | F25: 9.08 | G25: 6.96 | H25: 9.4 | I25: 3.2 | K25: 8.5 | L25: 16.38 | N25: 0.3 | O25: 0.9 | P25: 19.9 | R25: 20.3 | S25: 20.3 | T25: 13.1 | U25: 3.2 | V25: 4.9 | W25: 20.6 | X25: 20 | Y25: 18.9 | AB25: 53.5 | AG25: 36.6 | AH25: 48.5 | AK25: 20.4 | AL25: 20.4 | AM25: 20 | AO25: 66.7 | AP25: 2.3 | AQ25: 2.3 | AS25: 3.6 | AT25: 18.5 | AV25: 98.9 | AW25: 81.8 | AY25: 0.1 | AZ25: 2 | BA25: 12.9 | BC25: 12.2 | BD25: 5.4 | BE25: 10 | BH25: 0.6 | BI25: 99.7 | BJ25: 143.6 | BL25: 5.3 | BM25: 7.9 | BN25: 21.8 | BO25: 3 | BP25: 0.7 | BQ25: 2.4 | BR25: 2 | BS25: 12.5 | BT25: 2.2 | BU25: 20 | BV25: 7.9 | BW25: 20 | BX25: 16.4 | BY25: 20.4 | BZ25: 1128.15
B26: 9:30 | D26: 16.2 | E26: 13.02 | F26: 7.67 | G26: 6.95 | H26: 17.4 | I26: 3.2 | K26: 9.3 | L26: 13.96 | N26: 0.3 | O26: 1 | P26: 19.8 | R26: 20.5 | S26: 20.4 | T26: 13.1 | U26: 3.2 | V26: 5 | W26: 20.9 | X26: 20 | Y26: 18.8 | AB26: 54.5 | AF26: 16.8 | AG26: 19.6 | AH26: 47.1 | AK26: 20.4 | AL26: 20.4 | AM26: 20 | AO26: 54.6 | AP26: 2 | AQ26: 2 | AS26: 3.5 | AT26: 18.5 | AV26: 135.5 | AW26: 99 | AY26: 0.4 | AZ26: 2 | BA26: 14.4 | BC26: 12.1 | BD26: 5.6 | BE26: 9.9 | BH26: 0.6 | BI26: 62.6 | BJ26: 112.2 | BL26: 5.7 | BM26: 7.8 | BN26: 21.9 | BO26: 3 | BP26: 0.7 | BQ26: 2.4 | BR26: 2 | BS26: 6.5 | BT26: 2.2 | BU26: 20.2 | BV26: 8 | BW26: 20.2 | BX26: 17.5 | BY26: 20.7 | BZ26: 1103.2
B27: 10:00 | D27: 16.4 | E27: 13.05 | F27: 8.39 | G27: 6.95 | H27: 20.1 | I27: 3.2 | K27: 9.3 | L27: 16.37 | N27: 0.3 | O27: 1.1 | P27: 19.8 | R27: 20.3 | S27: 20.3 | T27: 13.3 | U27: 3.2 | V27: 5.1 | W27: 20.6 | X27: 20 | Y27: 18.9 | AB27: 39.4 | AE27: 0.4 | AF27: 60.1 | AG27: 13.5 | AH27: 24.4 | AK27: 20.4 | AL27: 20.4 | AM27: 20 | AO27: 81 | AP27: 2.3 | AQ27: 2.3 | AS27: 3.5 | AT27: 18.5 | AV27: 173.4 | AW27: 100.3 | AY27: 0.4 | AZ27: 2 | BA27: 16.7 | BC27: 12.8 | BD27: 5.7 | BE27: 9.9 | BF27: 0.2 | BH27: 0.6 | BI27: 27.6 | BJ27: 43 | BL27: 11.5 | BM27: 5.6 | BN27: 16.8 | BO27: 3 | BP27: 0.7 | BQ27: 2.3 | BR27: 2 | BS27: 5 | BT27: 2.2 | BU27: 20.4 | BV27: 8 | BW27: 20.4 | BX27: 12.8 | BY27: 20.4 | BZ27: 1066.56
B28: 10:30 | D28: 15.6 | E28: 13.07 | F28: 7.37 | G28: 6.95 | H28: 20.2 | I28: 3.2 | K28: 9.1 | L28: 14.15 | N28: 0.3 | O28: 1.2 | P28: 19.8 | R28: 20.3 | S28: 20.3 | T28: 12.8 | U28: 3.2 | V28: 5.1 | W28: 20.4 | X28: 20 | Y28: 18.8 | Z28: 0.4 | AB28: 53.2 | AE28: 6.2 | AF28: 80 | AG28: 27.2 | AH28: 15.4 | AK28: 20.4 | AL28: 20.4 | AM28: 20 | AO28: 80.9 | AP28: 2.4 | AQ28: 2.4 | AS28: 3.5 | AT28: 18.5 | AV28: 165.8 | AW28: 140 | AY28: 0.4 | AZ28: 2 | BA28: 18.7 | BC28: 9.8 | BD28: 5.5 | BE28: 10 | BF28: 0.8 | BH28: 0.6 | BI28: 15.7 | BJ28: 19.2 | BL28: 9.6 | BM28: 8.2 | BN28: 25.2 | BO28: 3 | BP28: 0.7 | BQ28: 2.3 | BR28: 1.9 | BS28: 8.4 | BT28: 2.2 | BU28: 20 | BV28: 8 | BW28: 20 | BX28: 16.6 | BY28: 20.4 | BZ28: 1117.74
B29: 11:00 | D29: 16.7 | E29: 12.69 | F29: 8.92 | G29: 6.95 | H29: 20.2 | I29: 3.2 | K29: 9.3 | L29: 16.21 | N29: 0.3 | O29: 1.3 | P29: 19.8 | R29: 20.4 | S29: 20.3 | T29: 12.1 | U29: 3.2 | V29: 5 | W29: 20.3 | X29: 20 | Y29: 18.8 | Z29: 1.9 | AB29: 67.5 | AE29: 10.1 | AF29: 113.2 | AG29: 11.5 | AH29: 25 | AK29: 20.4 | AL29: 20.4 | AM29: 20 | AO29: 80.8 | AP29: 2.1 | AQ29: 2.1 | AS29: 3.6 | AT29: 18.5 | AV29: 146 | AW29: 113.5 | AY29: 0.2 | AZ29: 2 | BA29: 15.8 | BC29: 10.4 | BD29: 5.5 | BE29: 10 | BF29: 16.7 | BH29: 0.6 | BI29: 17.7 | BJ29: 22.2 | BL29: 10.2 | BM29: 10 | BN29: 36.6 | BO29: 3 | BP29: 0.7 | BQ29: 2.2 | BR29: 1.9 | BS29: 8.6 | BT29: 2.2 | BU29: 20 | BV29: 8 | BW29: 20 | BX29: 17.8 | BY29: 20.3 | BZ29: 1154.87
B30: 11:30 | D30: 16.1 | E30: 12.97 | F30: 9.08 | G30: 6.95 | H30: 20.2 | I30: 3.2 | K30: 8.7 | L30: 15.53 | N30: 0.3 | O30: 1 | P30: 19.8 | R30: 20.1 | S30: 20.2 | T30: 11.4 | U30: 3.1 | V30: 5.1 | W30: 20.1 | X30: 20 | Y30: 18.9 | Z30: 5.7 | AB30: 72.8 | AE30: 14.4 | AF30: 140.7 | AG30: 9.4 | AH30: 14.9 | AK30: 20.4 | AL30: 20.4 | AM30: 20 | AO30: 80.8 | AP30: 2.5 | AQ30: 2.5 | AS30: 3.6 | AT30: 18.5 | AV30: 193.8 | AW30: 184.9 | AY30: 0.4 | AZ30: 2 | BA30: 17.7 | BC30: 9.8 | BD30: 5.5 | BE30: 10 | BF30: 24.6 | BG30: 1.2 | BH30: 0.6 | BI30: 27.4 | BJ30: 34.8 | BL30: 7.7 | BM30: 13.3 | BN30: 44.2 | BO30: 2.7 | BP30: 0.7 | BQ30: 2.2 | BR30: 1.8 | BS30: 7.4 | BT30: 2.2 | BU30: 19.8 | BV30: 8 | BW30: 19.8 | BX30: 14 | BY30: 20.2 | BZ30: 1336.03
B31: 12:00 | D31: 17.3 | E31: 13.05 | F31: 8.4 | G31: 6.95 | H31: 20.2 | I31: 3.2 | K31: 8.1 | L31: 16.21 | N31: 0.3 | O31: 1.3 | P31: 19.8 | R31: 20.3 | S31: 20.2 | T31: 10.8 | U31: 3.1 | V31: 5 | W31: 20.3 | X31: 20 | Y31: 18.8 | Z31: 14.1 | AB31: 66.7 | AE31: 16.9 | AF31: 157.7 | AG31: 12.3 | AH31: 11.9 | AK31: 20.4 | AL31: 20.4 | AM31: 20 | AO31: 78.6 | AP31: 2.4 | AQ31: 2.4 | AS31: 3.6 | AT31: 18.5 | AV31: 227 | AW31: 206.5 | AY31: 0.2 | AZ31: 2 | BA31: 19.7 | BC31: 7.5 | BD31: 5.5 | BE31: 9.8 | BF31: 27.5 | BG31: 1.5 | BH31: 0.6 | BI31: 42.4 | BJ31: 47.2 | BL31: 6.1 | BM31: 11.6 | BN31: 37.5 | BO31: 2.7 | BP31: 0.7 | BQ31: 2 | BR31: 1.7 | BS31: 7.8 | BT31: 2.2 | BU31: 20 | BV31: 8 | BW31: 20 | BX31: 13.6 | BY31: 20.2 | BZ31: 1430.71
B32: 12:30 | D32: 17.2 | E32: 13.11 | F32: 8 | G32: 6.95 | H32: 20.2 | I32: 3.2 | K32: 8.5 | L32: 15.56 | N32: 0.4 | O32: 1.3 | P32: 19.8 | R32: 20.2 | S32: 20.1 | T32: 10.2 | U32: 3.1 | V32: 5 | W32: 20 | X32: 20 | Y32: 18.9 | Z32: 24 | AA32: 0.1 | AB32: 68.3 | AE32: 14.2 | AF32: 150.4 | AG32: 25.1 | AH32: 17.1 | AK32: 20.4 | AL32: 20.4 | AM32: 20 | AO32: 70.4 | AP32: 1.9 | AQ32: 1.9 | AS32: 3.6 | AT32: 18.5 | AV32: 252.8 | AW32: 222 | AY32: 0.2 | AZ32: 2 | BA32: 19.6 | BC32: 8.5 | BD32: 5.5 | BE32: 10 | BF32: 24.1 | BG32: 2.5 | BH32: 0.6 | BI32: 66.3 | BJ32: 67.7 | BL32: 7.9 | BM32: 14.1 | BN32: 43.1 | BO32: 2.7 | BP32: 0.7 | BQ32: 1.2 | BR32: 1.7 | BS32: 13.6 | BT32: 2.2 | BU32: 20 | BV32: 7.9 | BW32: 19.9 | BX32: 14.2 | BY32: 20.1 | BZ32: 1539.12
B33: 13:00 | D33: 17.1 | E33: 13.08 | F33: 7.18 | G33: 6.95 | H33: 20.2 | I33: 3.2 | K33: 9.3 | L33: 16.96 | N33: 0.4 | O33: 0.6 | P33: 19.8 | R33: 20.3 | S33: 20.2 | T33: 9.4 | U33: 3.2 | V33: 5.1 | W33: 20 | X33: 20 | Y33: 18.9 | Z33: 39.3 | AA33: 1.8 | AB33: 67.8 | AE33: 18.3 | AF33: 153.9 | AG33: 18 | AH33: 33.7 | AK33: 20.4 | AL33: 20.4 | AM33: 20 | AO33: 39.2 | AP33: 1.9 | AQ33: 1.9 | AS33: 3.5 | AT33: 18.5 | AV33: 220.8 | AW33: 182.2 | AY33: 0.1 | AZ33: 2 | BA33: 19.1 | BC33: 11.4 | BD33: 5.5 | BE33: 9.9 | BF33: 60.9 | BG33: 2.8 | BH33: 0.6 | BI33: 27.4 | BJ33: 57.1 | BL33: 13.2 | BM33: 13.5 | BN33: 52.3 | BO33: 2.7 | BP33: 0.7 | BQ33: 2.1 | BR33: 1.7 | BS33: 9.4 | BT33: 2.2 | BU33: 20 | BV33: 7.9 | BW33: 20 | BX33: 13.5 | BY33: 20.2 | BZ33: 1469.67
B34: 13:30 | D34: 17.3 | E34: 13.05 | F34: 6.38 | G34: 6.94 | H34: 18.8 | I34: 3.2 | K34: 9 | L34: 13.62 | N34: 0.4 | O34: 0.6 | P34: 19.8 | R34: 20.3 | S34: 20.3 | T34: 8.8 | U34: 3.1 | V34: 5.1 | W34: 20.5 | X34: 20 | Y34: 18.9 | Z34: 39.3 | AA34: 4.6 | AB34: 83.9 | AE34: 18.6 | AF34: 143.5 | AG34: 10.8 | AH34: 32.7 | AK34: 20.4 | AL34: 20.4 | AM34: 20 | AO34: 29.2 | AP34: 2.1 | AQ34: 2.1 | AS34: 3.6 | AT34: 18.5 | AV34: 222.9 | AW34: 181.7 | AY34: 0.1 | AZ34: 2 | BA34: 15.5 | BC34: 7.1 | BD34: 5.4 | BE34: 9.9 | BF34: 83.4 | BG34: 5.2 | BH34: 0.6 | BI34: 16.6 | BJ34: 21.2 | BL34: 6.6 | BM34: 16.8 | BN34: 54.6 | BO34: 2.7 | BP34: 0.7 | BQ34: 2.1 | BR34: 1.7 | BS34: 11.8 | BT34: 2.2 | BU34: 20 | BV34: 7.8 | BW34: 20 | BX34: 14.2 | BY34: 20.4 | BZ34: 1428.99
B35: 14:00 | D35: 17.2 | E35: 13.03 | F35: 7.47 | G35: 6.87 | H35: 18.2 | I35: 3.2 | K35: 9.3 | L35: 15.24 | N35: 0.4 | O35: 0.4 | P35: 19.8 | R35: 20.2 | S35: 20.2 | T35: 8.4 | U35: 3.2 | V35: 5.1 | X35: 20 | Y35: 18.8 | Z35: 42.5 | AA35: 4.8 | AB35: 80.5 | AE35: 14.9 | AF35: 160.7 | AG35: 12 | AH35: 14.3 | AK35: 20.4 | AL35: 20.4 | AM35: 20 | AO35: 22.2 | AP35: 1.8 | AQ35: 1.8 | AS35: 3.5 | AT35: 18.5 | AV35: 244.9 | AW35: 202 | AY35: 0.2 | AZ35: 2 | BA35: 14.2 | BC35: 3.3 | BD35: 5.5 | BE35: 9.9 | BF35: 94.6 | BG35: 38.2 | BH35: 0.6 | BI35: 18.6 | BJ35: 21.7 | BL35: 5.5 | BM35: 14.7 | BN35: 52.1 | BO35: 2.7 | BP35: 0.7 | BQ35: 2.1 | BR35: 1.7 | BS35: 14.9 | BT35: 2.2 | BU35: 20 | BV35: 7.8 | BW35: 20 | BX35: 17 | BZ35: 1462.41
B36: 14:30 | D36: 17.4 | E36: 13.06 | F36: 7.15 | G36: 5.47 | H36: 17.8 | I36: 3.2 | K36: 9.2 | L36: 15.32 | N36: 0.4 | O36: 0.4 | P36: 19.8 | R36: 20.1 | S36: 20.2 | T36: 8.7 | U36: 3.2 | V36: 5 | X36: 20 | Y36: 18.9 | Z36: 36.8 | AA36: 2 | AB36: 81.7 | AE36: 14.6 | AF36: 164.9 | AG36: 4.7 | AH36: 19.1 | AK36: 20.4 | AL36: 20.4 | AM36: 20 | AO36: 80.8 | AP36: 2 | AQ36: 2 | AS36: 3.6 | AT36: 18.5 | AV36: 252.4 | AW36: 214.6 | AY36: 0.2 | AZ36: 2 | BA36: 6.5 | BC36: 1.8 | BD36: 5.3 | BE36: 10 | BF36: 105.1 | BG36: 96.2 | BH36: 0.6 | BI36: 77.4 | BJ36: 80.6 | BL36: 3.6 | BM36: 14.4 | BN36: 53 | BO36: 2.7 | BP36: 0.7 | BQ36: 2.1 | BR36: 1.7 | BS36: 14.6 | BT36: 2.2 | BU36: 20 | BV36: 7.8 | BW36: 20 | BX36: 12.9 | BZ36: 1705.2
B37: 15:00 | D37: 17.2 | E37: 13.06 | F37: 5.88 | G37: 5.47 | H37: 17.8 | I37: 3.2 | K37: 9.5 | L37: 15.69 | N37: 0.4 | O37: 0.4 | P37: 19.8 | R37: 20.1 | S37: 20.2 | T37: 9 | U37: 3.2 | V37: 5.1 | X37: 20 | Y37: 18.8 | Z37: 32.8 | AA37: 2 | AB37: 78.4 | AE37: 26.9 | AF37: 176.3 | AG37: 2.4 | AH37: 8.6 | AK37: 20.4 | AL37: 20.4 | AM37: 20 | AO37: 80.7 | AP37: 1.9 | AQ37: 1.9 | AS37: 3.6 | AT37: 18.5 | AV37: 244.2 | AW37: 213.8 | AY37: 0.1 | AZ37: 2 | BA37: 4 | BC37: 1.3 | BD37: 5.6 | BE37: 9.8 | BF37: 98.5 | BG37: 99 | BH37: 0.6 | BI37: 5.7 | BJ37: 9.5 | BL37: 1.4 | BM37: 14.4 | BN37: 57.1 | BO37: 2.7 | BP37: 0.7 | BQ37: 2.1 | BR37: 1.7 | BS37: 6.5 | BT37: 2.2 | BU37: 20 | BV37: 7.9 | BW37: 20 | BX37: 14.7 | BZ37: 1545.1
B38: 15:30 | D38: 16.6 | E38: 13.06 | F38: 8.37 | G38: 5.47 | H38: 17.9 | I38: 3.2 | K38: 9.1 | L38: 18.01 | N38: 0.3 | O38: 0.4 | P38: 19.8 | R38: 20.3 | S38: 20.3 | T38: 9 | U38: 3.2 | V38: 5.1 | X38: 20 | Y38: 18.8 | Z38: 36 | AA38: 3.8 | AB38: 76.9 | AE38: 16.3 | AF38: 154.9 | AG38: 4.8 | AH38: 4.7 | AK38: 20.4 | AL38: 20.4 | AM38: 20 | AO38: 34.2 | AP38: 1.7 | AQ38: 1.7 | AS38: 3.6 | AT38: 18.5 | AV38: 177.1 | AW38: 90.7 | AZ38: 2 | BA38: 2.9 | BC38: 2.4 | BD38: 5.6 | BE38: 9.9 | BF38: 80.6 | BG38: 96.4 | BH38: 0.6 | BI38: 5.9 | BJ38: 4.3 | BL38: 1 | BM38: 11.6 | BN38: 49 | BO38: 2.7 | BP38: 0.7 | BQ38: 2.1 | BR38: 1.7 | BS38: 9.7 | BT38: 2.2 | BU38: 20 | BV38: 7.8 | BW38: 20 | BX38: 9.5 | BZ38: 1243.21
B39: 16:00 | D39: 16.9 | E39: 13.06 | F39: 7.21 | G39: 6.32 | H39: 18.1 | I39: 3.2 | K39: 9 | L39: 18.31 | N39: 0.2 | O39: 0.2 | P39: 19.8 | R39: 20.3 | S39: 20.3 | T39: 5.1 | U39: 3.2 | V39: 5.1 | X39: 20 | Y39: 18.8 | Z39: 26 | AA39: 2.4 | AB39: 89.4 | AE39: 14.2 | AF39: 136 | AG39: 3.1 | AH39: 6.9 | AK39: 20.4 | AL39: 20.4 | AM39: 20 | AO39: 11 | AP39: 1.5 | AQ39: 1.5 | AS39: 3.6 | AT39: 18.5 | AV39: 97.9 | AW39: 50.8 | AY39: 0.1 | AZ39: 2 | BA39: 1.4 | BC39: 2.6 | BD39: 5.6 | BE39: 9.9 | BF39: 117.9 | BG39: 109.9 | BH39: 0.6 | BI39: 4.4 | BJ39: 3.4 | BL39: 1.5 | BM39: 14.8 | BN39: 53.8 | BO39: 2.7 | BP39: 0.7 | BQ39: 2.1 | BR39: 1.7 | BS39: 2.7 | BT39: 2.2 | BU39: 20 | BV39: 7.8 | BW39: 20 | BZ39: 1116.5
B40: 16:30 | D40: 16 | E40: 13.03 | F40: 7.44 | G40: 6.6 | H40: 18.1 | I40: 3.2 | K40: 8.8 | L40: 18.12 | N40: 0.1 | O40: 0.1 | P40: 19.8 | R40: 20.1 | S40: 20.2 | T40: 2.1 | U40: 3.2 | V40: 5 | X40: 20 | Y40: 18.9 | Z40: 20.5 | AA40: 2.4 | AB40: 90.4 | AE40: 9 | AF40: 128.9 | AG40: 0.9 | AH40: 6.7 | AK40: 20.4 | AL40: 20.4 | AM40: 20 | AO40: 4.3 | AP40: 1.1 | AQ40: 1.1 | AS40: 3.6 | AT40: 18.5 | AV40: 22.9 | AW40: 19.8 | AY40: 0.1 | AZ40: 2 | BA40: 0.9 | BC40: 2.4 | BD40: 5.6 | BE40: 9.9 | BF40: 159.7 | BG40: 113.7 | BH40: 0.6 | BI40: 6.7 | BJ40: 6.8 | BL40: 1.5 | BM40: 18.1 | BN40: 53.6 | BO40: 2.8 | BP40: 0.7 | BQ40: 2.1 | BR40: 1.7 | BS40: 3.6 | BT40: 2.2 | BU40: 20 | BV40: 7.7 | BW40: 20 | BZ40: 1034.09
B41: 17:00 | D41: 17 | E41: 13.01 | F41: 7.09 | G41: 5.47 | H41: 18.1 | I41: 3.2 | K41: 8 | L41: 17.16 | N41: 0.1 | O41: 0.1 | P41: 19.8 | R41: 20.2 | S41: 20.2 | T41: 2.7 | U41: 3.2 | V41: 5 | X41: 20 | Y41: 18.9 | Z41: 19 | AA41: 2.5 | AB41: 88.5 | AE41: 8.4 | AF41: 122.7 | AG41: 0.8 | AH41: 1.6 | AK41: 20.4 | AL41: 20.4 | AM41: 20 | AO41: 8.6 | AP41: 0.8 | AQ41: 0.8 | AS41: 3.5 | AT41: 18.5 | AV41: 12.9 | AW41: 9.1 | AY41: 0.1 | AZ41: 2 | BA41: 0.5 | BC41: 1.1 | BD41: 5.5 | BE41: 10 | BF41: 157 | BG41: 113.5 | BH41: 0.6 | BI41: 3 | BJ41: 6.7 | BL41: 0.6 | BM41: 20.6 | BN41: 63.9 | BO41: 2.8 | BP41: 0.7 | BQ41: 2.1 | BR41: 1.7 | BS41: 2.3 | BT41: 2.2 | BU41: 20 | BV41: 7.8 | BW41: 20 | BZ41: 1002.43
B42: 17:30 | D42: 16.5 | E42: 13.01 | F42: 6.66 | G42: 5.47 | H42: 18.7 | I42: 3.2 | K42: 8.8 | L42: 16.95 | O42: 0.1 | P42: 19.8 | R42: 20.3 | S42: 20.2 | T42: 6 | U42: 3.2 | V42: 5.1 | X42: 20 | Y42: 18.8 | Z42: 12.2 | AA42: 2.2 | AB42: 84.6 | AE42: 9.9 | AF42: 133.3 | AG42: 0.8 | AH42: 1.4 | AI42: 0.5 | AK42: 20.4 | AL42: 20.4 | AM42: 20 | AO42: 4.7 | AP42: 0.2 | AQ42: 0.2 | AS42: 3.5 | AT42: 18.5 | AV42: 6.1 | AW42: 3.3 | AZ42: 2 | BA42: 0.2 | BC42: 0.1 | BD42: 5.6 | BE42: 9.9 | BF42: 152.2 | BG42: 111.2 | BH42: 0.6 | BI42: 1.4 | BJ42: 1.9 | BM42: 21.5 | BN42: 63.8 | BO42: 2.7 | BP42: 0.7 | BQ42: 2.1 | BR42: 1.8 | BS42: 0.9 | BT42: 2.2 | BU42: 20 | BV42: 7.8 | BW42: 20 | BY42: 20.9 | BZ42: 994.49
B43: 18:00 | D43: 17.2 | E43: 13.01 | F43: 8.19 | G43: 5.46 | H43: 20.1 | I43: 3.2 | K43: 8.2 | L43: 17.06 | O43: 0.1 | P43: 19.8 | R43: 20.2 | S43: 20.2 | T43: 11.3 | U43: 3.2 | V43: 5.1 | W43: 20.4 | X43: 20 | Y43: 18.8 | Z43: 15.7 | AA43: 3.6 | AB43: 102.4 | AE43: 8.1 | AF43: 148.1 | AH43: 1.1 | AI43: 14.5 | AJ43: 1.9 | AK43: 20.4 | AL43: 20.4 | AM43: 20 | AO43: 0.3 | AP43: 0.8 | AQ43: 0.8 | AS43: 3.5 | AT43: 18.5 | AV43: 1.1 | AW43: 1.1 | AZ43: 2 | BD43: 5.5 | BE43: 10 | BF43: 145 | BG43: 113 | BH43: 0.6 | BI43: 0.3 | BJ43: 0.8 | BM43: 22.7 | BN43: 73.9 | BO43: 2.7 | BP43: 0.7 | BQ43: 2.2 | BR43: 1.8 | BT43: 2.2 | BU43: 20 | BV43: 7.7 | BW43: 20 | BY43: 20.2 | BZ43: 1065.12
B44: 18:30 | D44: 16.7 | E44: 12.03 | F44: 8.45 | G44: 5.46 | H44: 20.3 | I44: 3.2 | K44: 8.5 | L44: 16.88 | P44: 19.8 | R44: 20.2 | S44: 20.2 | T44: 12 | U44: 3.2 | V44: 5 | W44: 20.1 | X44: 20 | Y44: 18.8 | Z44: 14.1 | AA44: 2.6 | AB44: 87.7 | AE44: 6.4 | AF44: 139.6 | AI44: 20.9 | AJ44: 7.6 | AK44: 20.4 | AL44: 20.4 | AM44: 20 | AP44: 0.9 | AS44: 3.5 | AT44: 18.5 | AZ44: 2 | BD44: 5.5 | BE44: 9.9 | BF44: 132.5 | BG44: 107.7 | BH44: 0.6 | BM44: 20.6 | BN44: 63.2 | BO44: 2.9 | BP44: 0.7 | BQ44: 2.2 | BR44: 1.9 | BT44: 2.2 | BU44: 20.1 | BV44: 7.7 | BW44: 20 | BY44: 20.3 | BZ44: 1013.42
B45: 19:00 | D45: 16 | E45: 11.99 | F45: 8.05 | G45: 6.41 | H45: 20.3 | I45: 3.2 | K45: 8.7 | L45: 17.3 | P45: 19.8 | R45: 20.2 | S45: 20.2 | T45: 12.5 | U45: 3.2 | V45: 5.1 | W45: 20.5 | X45: 20 | Y45: 18.8 | Z45: 20.1 | AA45: 2 | AB45: 66.4 | AE45: 6.5 | AF45: 110 | AI45: 20.9 | AJ45: 8.2 | AK45: 20.4 | AL45: 20.4 | AM45: 20 | AP45: 0.7 | AS45: 3.5 | AT45: 18.5 | AZ45: 2.1 | BD45: 5.3 | BE45: 10.1 | BF45: 120.5 | BG45: 100 | BH45: 0.6 | BM45: 19.4 | BN45: 51.2 | BO45: 2.9 | BP45: 0.7 | BQ45: 2.2 | BR45: 1.9 | BT45: 2.2 | BU45: 20 | BV45: 7.6 | BW45: 20 | BY45: 20.3 | BZ45: 936.85
B46: 19:30 | D46: 16.2 | E46: 12.02 | F46: 7.63 | G46: 7.16 | H46: 20.3 | I46: 3.2 | K46: 8.8 | L46: 17.26 | P46: 19.8 | R46: 20.3 | S46: 20.2 | T46: 12.5 | U46: 3.2 | V46: 5 | W46: 20.5 | X46: 20 | Y46: 18.8 | Z46: 20 | AA46: 1.5 | AB46: 62.3 | AE46: 5.1 | AF46: 109.2 | AI46: 20.9 | AJ46: 8.2 | AK46: 20.4 | AL46: 20.4 | AM46: 20 | AP46: 0.5 | AS46: 3.5 | AT46: 18.5 | AZ46: 2.1 | BD46: 5.5 | BE46: 9.9 | BF46: 91.3 | BG46: 88.9 | BH46: 0.6 | BM46: 15.8 | BN46: 48.6 | BO46: 2.9 | BP46: 0.7 | BQ46: 2.2 | BR46: 1.9 | BT46: 2.2 | BU46: 20 | BV46: 7.7 | BW46: 20 | BY46: 20.3 | BZ46: 883.97
B47: 20:00 | D47: 17.6 | E47: 12.04 | F47: 8.22 | G47: 6.95 | H47: 20.3 | I47: 3.2 | K47: 8.9 | L47: 16.83 | P47: 19.8 | R47: 20.2 | S47: 20.2 | T47: 12.5 | U47: 3.2 | V47: 5.1 | W47: 20.3 | X47: 20 | Y47: 18.8 | Z47: 16.2 | AA47: 0.1 | AB47: 58.7 | AE47: 3.6 | AF47: 93.4 | AI47: 20.9 | AJ47: 8.2 | AK47: 20.4 | AL47: 20.4 | AM47: 20 | AP47: 0.4 | AS47: 3.5 | AT47: 18.5 | AZ47: 2.1 | BD47: 5.6 | BE47: 9.9 | BF47: 81.4 | BG47: 62.4 | BH47: 0.6 | BM47: 14.4 | BN47: 50.5 | BO47: 3 | BP47: 0.7 | BQ47: 2.3 | BR47: 2 | BT47: 2.2 | BU47: 20 | BV47: 7.7 | BW47: 20 | BY47: 20.3 | BZ47: 823.54
B48: 20:30 | D48: 17.1 | E48: 12.46 | F48: 7.99 | G48: 6.96 | H48: 20.3 | I48: 3.2 | K48: 8.8 | L48: 16.16 | P48: 19.8 | R48: 20.2 | S48: 20.2 | T48: 12.5 | U48: 3.2 | V48: 5.1 | W48: 20.5 | X48: 20 | Y48: 18.8 | Z48: 14.5 | AB48: 42.2 | AE48: 2.5 | AF48: 110 | AI48: 20.9 | AJ48: 8.2 | AK48: 20.4 | AL48: 20.4 | AM48: 20 | AP48: 0.4 | AS48: 3.5 | AT48: 18.5 | AZ48: 2.1 | BD48: 5.5 | BE48: 10 | BF48: 70.9 | BG48: 55 | BH48: 0.6 | BM48: 11.2 | BN48: 43.7 | BO48: 3 | BP48: 0.7 | BQ48: 2.3 | BR48: 2 | BT48: 2.2 | BU48: 20 | BV48: 7.6 | BW48: 20 | BY48: 20.3 | BZ48: 791.87
B49: 21:00 | D49: 16.1 | E49: 12.5 | F49: 7.9 | G49: 6.96 | H49: 20.3 | I49: 3.2 | K49: 8.8 | L49: 16.92 | P49: 19.8 | R49: 20.4 | S49: 20.2 | T49: 12.5 | U49: 3.2 | V49: 5.1 | W49: 20.2 | X49: 20 | Y49: 18.9 | Z49: 17 | AA49: 0.2 | AB49: 26.7 | AE49: 2.5 | AF49: 90.1 | AI49: 20.9 | AJ49: 8.2 | AK49: 20.4 | AL49: 20.4 | AM49: 20 | AP49: 0.2 | AS49: 3.5 | AT49: 18.5 | AZ49: 2.1 | BD49: 5.6 | BE49: 9.9 | BF49: 44.8 | BG49: 44.7 | BH49: 0.6 | BM49: 8.3 | BN49: 32.3 | BO49: 3 | BP49: 0.7 | BQ49: 2.3 | BR49: 2 | BT49: 2.2 | BU49: 20 | BV49: 7.6 | BW49: 20 | BY49: 20.2 | BZ49: 707.88
B50: 21:30 | D50: 17 | E50: 12.5 | F50: 7.15 | G50: 7.37 | H50: 20.3 | I50: 3.2 | K50: 8.5 | L50: 17.47 | P50: 19.8 | R50: 20.4 | S50: 20.3 | T50: 12.6 | U50: 3.2 | V50: 5 | W50: 20.6 | X50: 20 | Y50: 18.9 | Z50: 12.5 | AB50: 30.2 | AE50: 2.4 | AF50: 87.3 | AI50: 20.9 | AJ50: 8.2 | AK50: 20.4 | AL50: 20.4 | AM50: 20 | AP50: 0.4 | AS50: 3.5 | AT50: 18.5 | AZ50: 2.1 | BD50: 5.5 | BE50: 10 | BF50: 25.3 | BG50: 27 | BH50: 0.6 | BM50: 7.4 | BN50: 29.6 | BO50: 3 | BP50: 0.7 | BQ50: 2.4 | BR50: 2 | BT50: 2.2 | BU50: 20 | BV50: 7.6 | BW50: 20 | BY50: 20.4 | BZ50: 664.79
B51: 22:00 | D51: 15.7 | E51: 12.5 | F51: 8.17 | G51: 10.59 | H51: 20.3 | I51: 3.2 | K51: 8.8 | L51: 18.37 | P51: 19.8 | R51: 20.3 | S51: 20.2 | T51: 12.7 | U51: 3.2 | V51: 5 | W51: 20.1 | X51: 20 | Y51: 18.9 | Z51: 4.9 | AB51: 27.5 | AE51: 1.8 | AF51: 69.6 | AI51: 20.9 | AJ51: 8.2 | AK51: 20.4 | AL51: 20.4 | AM51: 20 | AP51: 0.4 | AS51: 3.5 | AT51: 18.5 | AZ51: 2.1 | BD51: 5.6 | BE51: 9.9 | BF51: 16.9 | BG51: 21 | BH51: 0.6 | BM51: 9.5 | BN51: 27.9 | BO51: 3 | BP51: 0.7 | BQ51: 2.4 | BR51: 2 | BT51: 2.2 | BU51: 20 | BV51: 7.6 | BW51: 20 | BY51: 20.2 | BZ51: 625.53
B52: 22:30 | D52: 16.8 | E52: 12.5 | F52: 6.85 | G52: 10.91 | H52: 20.3 | I52: 3.2 | K52: 8.1 | L52: 18.29 | P52: 19.8 | R52: 20.3 | S52: 20.3 | T52: 12.7 | U52: 3.2 | V52: 5.1 | W52: 20.3 | X52: 20 | Y52: 18.9 | Z52: 1 | AB52: 29.3 | AE52: 1.9 | AF52: 66.2 | AI52: 20.9 | AJ52: 8.2 | AK52: 20.4 | AL52: 20.4 | AM52: 20 | AP52: 0.5 | AS52: 3.4 | AT52: 18.5 | AZ52: 2.1 | BD52: 5.5 | BE52: 10 | BF52: 16.5 | BG52: 18.7 | BH52: 0.6 | BM52: 7.5 | BN52: 27.4 | BO52: 3 | BP52: 0.7 | BQ52: 2.4 | BR52: 2 | BT52: 2.2 | BU52: 20 | BV52: 7.6 | BW52: 20 | BY52: 20.3 | BZ52: 614.75
B53: 23:00 | D53: 17 | E53: 12.86 | F53: 8.14 | G53: 10.9 | H53: 20.3 | I53: 3.2 | K53: 8 | L53: 18.05 | P53: 19.8 | R53: 20.2 | S53: 20.2 | T53: 12.8 | U53: 3.2 | V53: 5.1 | W53: 20.1 | X53: 20 | Y53: 18.7 | Z53: 0.5 | AB53: 23.1 | AE53: 2 | AF53: 56.3 | AI53: 20.9 | AJ53: 8.2 | AK53: 20.4 | AL53: 20.4 | AM53: 20 | AP53: 0.6 | AS53: 3.4 | AT53: 18.5 | AZ53: 2.1 | BD53: 5.4 | BE53: 10 | BF53: 21.7 | BG53: 16.8 | BH53: 0.6 | BM53: 6.2 | BN53: 26.9 | BO53: 3 | BP53: 0.7 | BQ53: 2.4 | BR53: 2 | BT53: 2.1 | BU53: 20 | BV53: 7.6 | BW53: 20 | BY53: 20.2 | BZ53: 600.55
B54: 23:30 | D54: 16.2 | E54: 13.01 | F54: 8.39 | G54: 10.9 | H54: 20.3 | I54: 3.2 | K54: 9.1 | L54: 17.9 | P54: 19.8 | R54: 20.2 | S54: 20.2 | T54: 12.9 | U54: 3.2 | V54: 5.1 | W54: 20.1 | X54: 20 | Y54: 18.2 | Z54: 4 | AB54: 26.6 | AE54: 0.7 | AF54: 49.9 | AI54: 20.9 | AJ54: 8.2 | AK54: 20.4 | AL54: 20.4 | AM54: 20 | AP54: 0.5 | AS54: 3.4 | AT54: 18.5 | AZ54: 2.1 | BD54: 5.7 | BE54: 9.8 | BF54: 23.1 | BG54: 20.6 | BH54: 0.6 | BM54: 6.7 | BN54: 22.5 | BO54: 3 | BP54: 0.7 | BQ54: 2.4 | BR54: 2 | BT54: 2.1 | BU54: 20 | BV54: 7.6 | BW54: 20 | BY54: 20.2 | BZ54: 601.3
B55: 0:00 | D55: 17 | E55: 13.01 | F55: 6.74 | G55: 11 | H55: 20.3 | I55: 3.2 | K55: 8.8 | L55: 16.32 | P55: 19.8 | R55: 20.3 | S55: 20.3 | T55: 13 | U55: 3.2 | V55: 5.1 | W55: 20.5 | X55: 20 | Y55: 18 | Z55: 2.2 | AB55: 27 | AE55: 0.4 | AF55: 43.3 | AI55: 20.9 | AJ55: 8.2 | AK55: 20.4 | AL55: 20.4 | AM55: 20 | AP55: 0.2 | AS55: 3.5 | AT55: 18.5 | AZ55: 2.1 | BD55: 5.6 | BE55: 9.9 | BF55: 13.9 | BG55: 12.1 | BH55: 0.6 | BM55: 4.9 | BN55: 19.9 | BO55: 3 | BP55: 0.7 | BQ55: 2.4 | BR55: 2 | BT55: 2.1 | BU55: 20 | BV55: 7.5 | BW55: 20 | BY55: 20.3 | BZ55: 568.57
B56: EJEC MWh | C56: 0 | D56: 401.25 | E56: 303.83 | F56: 185.455 | G56: 157.67 | H56: 463.3 | I56: 76.8 | J56: 0 | K56: 207.25 | L56: 398.86 | M56: 0 | N56: 2.9 | O56: 6.8 | P56: 475.4 | Q56: 0 | R56: 486.4 | S56: 485.6 | T56: 275.05 | U56: 76.05 | V56: 121.35 | W56: 407.15 | X56: 478.55 | Y56: 451.85 | Z56: 301.8 | AA56: 24.95 | AB56: 1131.95 | AC56: 0 | AD56: 0 | AE56: 128.6 | AF56: 1684.8 | AG56: 135.5 | AH56: 182.05 | AI56: 132.9 | AJ56: 49.85 | AK56: 489.6 | AL56: 489.6 | AM56: 480 | AN56: 0 | AO56: 550.3 | AP56: 34.35 | AQ56: 31.5 | AR56: 0 | AS56: 84.8 | AT56: 444 | AU56: 0 | AV56: 1614.55 | AW56: 1320.8 | AX56: 0 | AY56: 1.75 | AZ56: 50.7 | BA56: 115.75 | BB56: 0 | BC56: 85.35 | BD56: 132.25 | BE56: 238.5 | BF56: 1009.2 | BG56: 747.7 | BH56: 12.95 | BI56: 439.75 | BJ56: 588.85 | BK56: 0 | BL56: 84.3 | BM56: 216.4 | BN56: 706.55 | BO56: 69.85 | BP56: 16.8 | BQ56: 54.45 | BR56: 45.8 | BS56: 82.45 | BT56: 52.65 | BU56: 480.25 | BV56: 188.8 | BW56: 479.9 | BX56: 134.45 | BY56: 416.5 | BZ56: 21225.315
L70: TERMOELÉCTRICA | M70: 1841.215 | N70: 8.674618 | O70: #FFA975
L71: SOLAR | M71: 5345.55 | N71: 25.184785 | O71: #FFD272
L72: EÓLICA | M72: 6017.8 | N72: 28.351994 | O72: #B9ACFF
L73: HIDROELÉCTRICA | M73: 8020.75 | N73: 37.788603 | O73: #98D2FF

Sheet COGENERACIÓN
B3: sábado, 21 de Febrero del 2026
B5: CENTRALES DE COGENERACIÓN DEL SEIN
B6: HORA | C6: AGRO INDUSTRIAL PARAMONGA S.A. | D6: AGROAURORA S.A.C. | E6: AGROINDUSTRIAS SAN JACINTO S.A.A. | F6: AGROLMOS SOCIEDAD ANONIMA - AGROLMOS S.A. | G6: BIOENERGIA DEL CHIRA S.A. | H6: CASA GRANDE S.A.A. | I6: GM OPERACIONES S.A.C. | J6: TOTAL COGENERACION
C7: C.T. PARAMONGA | D7: C.T. MAPLE | E7: C.T SAN JACINTO | F7: C.T. AGROLMOS | G7: C.T. CAÑA BRAVA | H7: C.T. CASA GRANDE | I7: C.T. REFINERÍA TALARA | J7: MW
B8: 0:30 | C8: 16 | D8: 12.49 | E8: 8.22 | F8: 4.97 | G8: 8.9 | H8: 14.69 | I8: 29.8 | J8: 95.07
B9: 1:00 | C9: 16.2 | D9: 12.49 | E9: 7.88 | F9: 4.97 | G9: 8.8 | H9: 15.64 | I9: 30 | J9: 95.98
B10: 1:30 | C10: 16.5 | D10: 12.49 | E10: 8.23 | F10: 4.97 | G10: 8.5 | H10: 15.42 | I10: 29.8 | J10: 95.91
B11: 2:00 | C11: 17 | D11: 12.48 | E11: 8.07 | F11: 4.97 | G11: 8.2 | H11: 15.69 | I11: 29.8 | J11: 96.21
B12: 2:30 | C12: 16.7 | D12: 12.5 | E12: 8.04 | F12: 4.97 | G12: 8.2 | H12: 16.51 | I12: 30.3 | J12: 97.22
B13: 3:00 | C13: 17.2 | D13: 12.5 | E13: 7.33 | F13: 4.97 | G13: 8.5 | H13: 15.79 | I13: 30.8 | J13: 97.09
B14: 3:30 | C14: 17.2 | D14: 12.5 | E14: 7.21 | F14: 4.97 | G14: 8.9 | H14: 15.86 | I14: 30.7 | J14: 97.34
B15: 4:00 | C15: 17.3 | D15: 12.49 | E15: 6.76 | F15: 4.97 | G15: 8.9 | H15: 16.4 | I15: 31.2 | J15: 98.02
B16: 4:30 | C16: 16.7 | D16: 12.5 | E16: 5.92 | F16: 4.97 | G16: 8.4 | H16: 16.66 | I16: 30.9 | J16: 96.05
B17: 5:00 | C17: 16.6 | D17: 12.51 | E17: 8.44 | F17: 4.98 | G17: 8.5 | H17: 16.2 | I17: 30.7 | J17: 97.93
B18: 5:30 | C18: 16.3 | D18: 11.53 | E18: 8.12 | F18: 5.27 | G18: 8.7 | H18: 17.93 | I18: 30.8 | J18: 98.65
B19: 6:00 | C19: 17 | D19: 11.44 | E19: 7.77 | F19: 5.27 | G19: 8.8 | H19: 17.96 | I19: 30.9 | J19: 99.14
... B56: EJEC MWh | C56: 401.25 | D56: 303.83 | E56: 185.455 | F56: 157.67 | G56: 207.25 | H56: 398.86 | I56: 692.85 | J56: 2347.165

Sheet EVO_PRO_ENE
B3: domingo, 1 de Febrero del 2026 - sábado, 21 de Febrero del 2026
B5: EVOLUCIÓN DE LA PRODUCCIÓN DE LA ENERGÍA DIARIA DE LOS INTEGRANTES DEL COES (MWh)
B6: EMPRESA | C6: CENTRAL | D6: UNIDAD | E6: TIPO | F6: Febrero
F7: 1 | G7: 2 | H7: 3 | I7: 4 | J7: 5 | K7: 6 | L7: 7 | M7: 8 | N7: 9 | O7: 10 | P7: 11 | Q7: 12 | R7: 13 | S7: 14 | T7: 15 | U7: 16 | V7: 17 | W7: 18 | X7: 19 | Y7: 20 | Z7: 21 | AA7: TOTAL
B8: AGRO INDUSTRIAL PARAMONGA S.A. | C8: C.T. PARAMONGA | D8: TV-01 | E8: TERMOELÉCTRICA | F8: 92.9 | H8: 156.65 | I8: 345.05 | J8: 344.4 | K8: 351.7 | L8: 348.35 | M8: 344.1 | N8: 355.8 | O8: 358.15 | P8: 366.1 | Q8: 392.25 | R8: 407.3 | S8: 389.55 | T8: 389.75 | U8: 405.15 | V8: 402.05 | W8: 366.7 | X8: 272.4 | Y8: 400.6 | Z8: 401.25 | AA8: 6890.2
B9: AGROAURORA S.A.C. | C9: C.T. MAPLE ETANOL | D9: TV | E9: TERMOELÉCTRICA | F9: 110.05 | G9: 117.1 | H9: 78.05 | I9: 116.6 | J9: 112.25 | K9: 175.5 | L9: 405.55 | M9: 393.3 | N9: 419.14 | O9: 333.35 | P9: 344.5 | Q9: 349.25 | R9: 129.4 | S9: 412.4 | T9: 412.55 | U9: 415.1 | V9: 400.705 | W9: 417.8 | X9: 394.53 | Y9: 83.7 | Z9: 303.83 | AA9: 5924.655
B10: AGROINDUSTRIAS SAN JACINTO S.A.A. | C10: C.T. SAN JACINTO | D10: CENTRAL | E10: TERMOELÉCTRICA | F10: 192 | G10: 124.86 | J10: 66.05 | K10: 176.1 | L10: 118.65 | M10: 194.1 | N10: 187.821 | O10: 187 | P10: 163.938 | Q10: 201.45 | R10: 188.75 | S10: 193.65 | T10: 191.75 | U10: 181.1 | V10: 176.1 | W10: 179.75 | X10: 189.6 | Y10: 181.95 | Z10: 185.455 | AA10: 3280.074
B11: AGROLMOS SOCIEDAD ANONIMA - AGROLMOS S.A. | C11: C.T. AGROLMOS | D11: CENTRAL | E11: TERMOELÉCTRICA | F11: 217.05 | G11: 54.5 | H11: 154.01 | I11: 184.25 | J11: 265.85 | K11: 269.95 | L11: 216.55 | M11: 269.2 | N11: 270.6273 | O11: 270.05 | P11: 271.88135 | Q11: 262.4 | R11: 261.55 | S11: 261.3 | T11: 264.05 | U11: 256.7 | V11: 243.055 | W11: 243.9 | X11: 131.75 | Y11: 29.215 | Z11: 157.67 | AA11: 4555.5086
B12: ANDEAN POWER S.A.C. | C12: C.H.CARHUAC | D12: CENTRAL | E12: HIDROELÉCTRICA | F12: 358.3 | G12: 451.75 | H12: 464.5 | I12: 443.25 | J12: 354.65 | K12: 312.35 | L12: 297.1 | M12: 254.6 | N12: 218.65 | O12: 230.4 | P12: 221.75 | Q12: 228.45 | R12: 217.05 | S12: 333.5 | T12: 441.45 | U12: 428.25 | V12: 485.3 | W12: 484.75 | X12: 484.9 | Y12: 484.2 | Z12: 463.3 | AA12: 7658.45
B13: ASOCIACIÓN SANTA LUCIA DE CHACAS | C13: C.H. HUALLIN | D13: CENTRAL | E13: HIDROELÉCTRICA | F13: 73.55 | G13: 74.4 | H13: 72.05 | I13: 73.5 | J13: 73.8 | K13: 75.7 | L13: 69.4 | M13: 64.4 | N13: 64.45 | O13: 64.15 | P13: 64.65 | Q13: 64.95 | R13: 73.35 | S13: 76.15 | T13: 76.55 | U13: 76.55 | V13: 76.25 | W13: 76.8 | X13: 76.15 | Y13: 76.8 | Z13: 76.8 | AA13: 1520.4
B14: ATRIA ENERGIA S.A.C. | C14: C.H. PURMACANA | D14: CENTRAL | E14: HIDROELÉCTRICA | F14: 9.6 | G14: 9.4 | H14: 8.5 | I14: 8.1 | J14: 7.3 | K14: 8.65 | L14: 9.6 | M14: 9.6 | N14: 9.6 | O14: 7.75 | P14: 7.8 | Q14: 9.6 | R14: 9.6 | S14: 9.6 | T14: 9 | U14: 1.45 | AA14: 135.15
B15: BIOENERGIA DEL CHIRA S.A. | C15: C.T. CAÑA BRAVA | D15: CENTRAL | E15: TERMOELÉCTRICA | F15: 218.2 | G15: 209.25 | H15: 197.7 | I15: 219.2 | J15: 219.95 | K15: 214.1 | L15: 211.45 | M15: 183.75 | N15: 218.8 | O15: 216.45 | P15: 218.55 | Q15: 195.05 | R15: 219 | S15: 215.9 | T15: 217.6 | U15: 221.1 | V15: 220.8 | W15: 208.15 | X15: 198.85 | Y15: 186.61205 | Z15: 207.25 | AA15: 4417.7121
B16: CASA GRANDE S.A.A. | C16: C.T. CASA GRANDE | D16: TV3 | E16: TERMOELÉCTRICA | F16: 500.25 | G16: 273.865 | H16: 509.65 | I16: 507.8 | J16: 509.3 | K16: 506.55 | L16: 509.15 | M16: 494.55 | N16: 487.43705 | O16: 529.85 | P16: 461.59405 | Q16: 329.15 | R16: 495.9 | S16: 347.94 | T16: 407.45 | U16: 418.55 | V16: 342.85 | W16: 322 | X16: 537.05 | Y16: 419.95 | Z16: 398.86 | AA16: 9309.6961
B17: CELARIS ENERGY S.A. | C17: C.H. MANTA I | D17: CENTRAL | E17: HIDROELÉCTRICA | F17: 480.2 | G17: 323.8 | H17: 480.4 | I17: 461.1 | J17: 480.05 | K17: 479.9 | L17: 321.75 | M17: 239.1 | N17: 479.85 | O17: 435.45 | P17: 400.65 | Q17: 480.3 | R17: 434.1 | S17: 431.3 | T17: 219.4 | U17: 382.8 | V17: 447.25 | W17: 111.95 | X17: 300.05 | AA17: 7389.4
B18: CELEPSA | C18: C.H. EL PLATANAL | D18: CENTRAL | E18: HIDROELÉCTRICA | F18: 3920.15 | G18: 4860.55 | H18: 4886.25 | I18: 4890.05 | J18: 4601.45 | K18: 4459.6 | L18: 4787.6 | M18: 4228.75 | N18: 4244.15 | O18: 4631.6 | P18: 4966.05 | Q18: 4995.15 | R18: 4843 | S18: 4877.25 | T18: 4089.3 | U18: 4912.25 | V18: 4778.1 | W18: 2935.3 | X18: 4274.05 | Y18: 4810.2 | Z18: 4668.5 | AA18: 95659.3
B19: CELEPSA RENOVABLES S.R.L. | C19: C.H. MARAÑON | D19: CENTRAL | E19: HIDROELÉCTRICA | F19: 451.2 | G19: 443.15 | H19: 446.85 | I19: 451.2 | J19: 446 | K19: 451.2 | L19: 451.2 | M19: 451.2 | N19: 413.8 | O19: 451.75 | P19: 453.6 | Q19: 453.6 | R19: 453.6 | S19: 453.6 | T19: 453.45 | U19: 453.6 | V19: 453.2 | W19: 405.15 | X19: 422.65 | Y19: 451.2 | Z19: 451.2 | AA19: 9362.4
B20: CENTRALES SANTA ROSA S.A.C. | C20: C.H. SANTA ROSA I | D20: CENTRAL | E20: HIDROELÉCTRICA | AA20: 0
B21: CENTRALES SANTA ROSA S.A.C. | C21: C.H. SANTA ROSA II | D21: CENTRAL | E21: HIDROELÉCTRICA | AA21: 0
B22: CHINANGO S.A.C. | C22: C.H. CHIMAY | D22: CENTRAL | E22: HIDROELÉCTRICA | F22: 3261.4 | G22: 3502.8 | H22: 3592.9 | I22: 3595.7 | J22: 3627.85 | K22: 3591.45 | L22: 3559.25 | M22: 2764.85 | N22: 3468.6 | O22: 3621.75 | P22: 3642.55 | Q22: 3622.2 | R22: 3626.4 | S22: 3634.85 | T22: 3572.6 | U22: 3600.8 | V22: 3629.95 | W22: 3586.15 | X22: 3633.55 | Y22: 3627.8 | Z22: 3617.25 | AA22: 74380.65
B23: CHINANGO S.A.C. | C23: C.H. YANANGO | D23: CENTRAL | E23: HIDROELÉCTRICA | F23: 1012.15 | G23: 1008.65 | H23: 1008.6 | I23: 1007.9 | J23: 1008.3 | K23: 1008.7 | L23: 1008.6 | M23: 1008.2 | N23: 1008.75 | O23: 1008.95 | P23: 954.05 | Q23: 792.85 | R23: 855.45 | S23: 1016.6 | T23: 1015.75 | U23: 958.45 | V23: 1015.25 | W23: 534.65 | X23: 1014.35 | Y23: 1007.15 | Z23: 999 | AA23: 20252.35
B24: COENERGY S.A.C. | C24: C.S. COENERGY | D24: CENTRAL | E24: SOLAR | F24: 2.55 | G24: 2.65 | H24: 2.55 | I24: 2.75 | J24: 3 | K24: 2.85 | L24: 3.1 | M24: 2.55 | N24: 2.9 | O24: 3.05 | P24: 1.8 | Q24: 2 | R24: 2.7 | S24: 2.75 | T24: 2.6 | U24: 2.2 | V24: 2.35 | W24: 2.35 | X24: 3.077275 | Y24: 2.95 | Z24: 2.9 | AA24: 55.627275
B25: COLCA SOLAR S.A.C. | C25: C.S. YARUCAYA | D25: CENTRAL | E25: SOLAR | F25: 4.6 | G25: 3.15 | H25: 4.75 | I25: 6.05 | J25: 7.9 | K25: 4.25 | L25: 3.25 | M25: 8.35 | N25: 7.05 | O25: 7 | P25: 6.1 | Q25: 3.4 | R25: 5.45 | S25: 5.5 | T25: 4.8 | U25: 5.45 | V25: 5.45 | W25: 6.1 | X25: 6.25 | Y25: 5.9 | Z25: 6.8 | AA25: 117.55
B26: EGASA | C26: C.H. CHARCANI III | D26: CENTRAL | E26: HIDROELÉCTRICA | F26: 15.6 | G26: 90.55 | H26: 143.75 | I26: 140.8 | J26: 155.7 | K26: 160.25 | L26: 162.2 | M26: 158.45 | N26: 161.1 | O26: 158 | P26: 159.95 | Q26: 160.7 | R26: 160.85 | S26: 146.655 | T26: 156.57 | U26: 157.4 | V26: 155.95 | W26: 115.55 | X26: 103.9 | Y26: 123.85 | Z26: 131.555 | AA26: 2919.33
B27: EGASA | C27: C.H. CHARCANI IV | D27: CENTRAL | E27: HIDROELÉCTRICA | AA27: 0
B28: EGASA | C28: C.H. CHARCANI V | D28: CENTRAL | E28: HIDROELÉCTRICA | F28: 3416.55 | G28: 3417.7 | H28: 3419.05 | I28: 3413.95 | J28: 3413.2 | K28: 3410.65 | L28: 3416.5 | M28: 3390.17 | N28: 3415.75 | O28: 3410.75 | P28: 3415.1 | Q28: 3420.1 | R28: 3423.95 | S28: 3425.505 | T28: 3414.9 | U28: 3425.85 | V28: 3417.9 | W28: 3418.3 | X28: 3416.8 | Y28: 3417.2 | Z28: 3421.115 | AA28: 71740.99
B29: EGASA | C29: C.H. CHARCANI VI | D29: CENTRAL | E29: HIDROELÉCTRICA | AA29: 0
B30: EGASA | C30: C.T. CHILINA DIESEL | D30: CENTRAL | E30: TERMOELÉCTRICA | H30: 1.65 | I30: 1.05 | AA30: 2.7
B31: EGASA | C31: C.T. CHILINA DIESEL | D31: TG | E31: TERMOELÉCTRICA | G31: 11.15 | AA31: 11.15
B32: EGASA | C32: C.T. MOLLENDO DIESEL | D32: CENTRAL | E32: TERMOELÉCTRICA | AA32: 0
B33: EGEJUNIN | C33: C.H. HUASAHUASI I | D33: CENTRAL | E33: HIDROELÉCTRICA | F33: 475.1 | G33: 473.7 | H33: 472.9 | I33: 474.85 | J33: 475.15 | K33: 475.25 | L33: 474.7 | M33: 475.5 | N33: 473.8 | O33: 474.85 | P33: 475.3 | Q33: 467.25 | R33: 470.5 | S33: 465.35 | T33: 466.6 | U33: 473.8 | V33: 475.25 | W33: 475.15 | X33: 475.3 | Y33: 475.2 | Z33: 475.4 | AA33: 9940.9
B34: EGEJUNIN | C34: C.H. RUNATULLO II | D34: CENTRAL | E34: HIDROELÉCTRICA | F34: 481.7 | G34: 479 | H34: 480.35 | I34: 480.25 | J34: 480.65 | K34: 481.85 | L34: 475.45 | M34: 479.1 | N34: 482.6 | O34: 483 | P34: 484.8 | Q34: 479.2 | R34: 472.65 | S34: 482.6 | T34: 482.75 | U34: 482.7 | V34: 486.4 | W34: 484.45 | X34: 483.35 | Y34: 484.35 | Z34: 486.4 | AA34: 10113.6
B35: EGEJUNIN | C35: C.H. RUNATULLO III | D35: CENTRAL | E35: HIDROELÉCTRICA | F35: 486.05 | G35: 485.95 | H35: 486.25 | I35: 486.25 | J35: 486.35 | K35: 484.75 | L35: 484.7 | M35: 484.6 | N35: 484.6 | O35: 484.65 | P35: 484.95 | Q35: 484.65 | R35: 484.7 | S35: 484.85 | T35: 484.8 | U35: 484.9 | V35: 484.65 | W35: 485.25 | X35: 485.3 | Y35: 485.55 | Z35: 485.6 | AA35: 10189.35
B36: EGEJUNIN | C36: C.H. SANTA CRUZ I | D36: CENTRAL | E36: HIDROELÉCTRICA | F36: 310.05 | G36: 306.8 | H36: 306.75 | I36: 263.75 | J36: 274.95 | K36: 266.35 | L36: 244.05 | M36: 217 | N36: 192.1 | O36: 167.25 | P36: 177.75 | Q36: 176.9 | R36: 183.3 | S36: 241.6 | T36: 291.7 | U36: 312.35 | V36: 314.9 | W36: 295.85 | X36: 82.6 | Y36: 119.2 | Z36: 275.05 | AA36: 5020.25
B37: EGEMSA | C37: C.H. MACHUPICCHU | D37: CENTRAL | E37: HIDROELÉCTRICA | F37: 3900 | G37: 3964.95 | H37: 3996.95 | I37: 3992.4 | J37: 3993.9 | K37: 3993.15 | L37: 3973.15 | M37: 3554.7 | N37: 3991.2 | O37: 3963.3 | P37: 3985.95 | Q37: 3979.95 | R37: 3981.6 | S37: 3973.55 | T37: 3896.6 | U37: 3971.65 | V37: 3965.85 | W37: 3956.25 | X37: 3987.25 | Y37: 3969.5 | Z37: 3964.15 | AA37: 82956
B38: EGESUR | C38: C.H. ARICOTA I | D38: CENTRAL | E38: HIDROELÉCTRICA | F38: 193.15 | G38: 193.75 | H38: 195.55 | I38: 189.75 | J38: 191 | K38: 191.5 | L38: 192.4 | M38: 189.3 | N38: 189.1 | O38: 189.25 | P38: 191.85 | Q38: 190.5 | R38: 187.55 | S38: 191.5 | T38: 192.6 | U38: 191.1 | V38: 192.15 | W38: 189.7 | X38: 191.85 | Y38: 192.5 | Z38: 189.404 | AA38: 4015.454
B39: EGESUR | C39: C.H. ARICOTA II | D39: CENTRAL | E39: HIDROELÉCTRICA | F39: 128.65 | G39: 131.75 | H39: 131.25 | I39: 130.8 | J39: 135.7 | K39: 135.3 | L39: 133.75 | M39: 134.55 | N39: 135.95 | O39: 134.45 | P39: 135.5 | Q39: 134.05 | R39: 136.95 | S39: 135.6 | T39: 139.95 | U39: 139.75 | V39: 142.05 | W39: 140.95 | X39: 140.35 | Y39: 144.2 | Z39: 142.713 | AA39: 2864.213
B40: EGESUR | C40: C.T. INDEPENDENCIA | D40: CENTRAL | E40: TERMOELÉCTRICA | F40: 100.3 | G40: 270.85 | H40: 77.05 | I40: 99.5 | J40: 99.75 | L40: 207.5 | M40: 190.25 | N40: 264.55 | O40: 162.15 | P40: 312.1 | Q40: 190.5 | R40: 61.6 | U40: 195.85 | V40: 151.85 | W40: 365.75 | X40: 288.85 | Y40: 267.2 | Z40: 130.7315 | AA40: 3436.3315
B41: ELECTRICA YANAPAMPA SAC | C41: C.H. YANAPAMPA | D41: CENTRAL | E41: HIDROELÉCTRICA | F41: 79.85 | G41: 74.5 | H41: 76.35 | I41: 80.15 | J41: 79.6 | K41: 81.35 | L41: 72.5 | M41: 82.2 | N41: 82.95 | O41: 78.5 | P41: 80.65 | Q41: 80.05 | R41: 84.9 | S41: 82.1 | T41: 80.2 | U41: 77.5 | V41: 71.35 | W41: 76.75 | X41: 74.95 | Y41: 73.25 | Z41: 76.05 | AA41: 1645.7
B42: ELECTROPERU | C42: C.H. MANTARO | D42: CENTRAL | E42: HIDROELÉCTRICA | F42: 15110.1 | G42: 15251.95 | H42: 15325.1 | I42: 15267.6 | J42: 15274 | K42: 15224.9 | L42: 15290.35 | M42: 14854.15 | N42: 15255.1 | O42: 15255.75 | P42: 15270.05 | Q42: 15245.95 | R42: 15250.5 | S42: 15247.75 | T42: 14863.95 | U42: 15210.35 | V42: 15202.15 | W42: 15187.85 | X42: 14967.2 | Y42: 14829.6 | Z42: 13850.75 | AA42: 317235.1
B43: ELECTROPERU | C43: C.H. RESTITUCION | D43: CENTRAL | E43: HIDROELÉCTRICA | F43: 5096.35 | G43: 5132.8 | H43: 5143.4 | I43: 5124.1 | J43: 5135.15 | K43: 5156.55 | L43: 4693.75 | M43: 5050.4 | N43: 5165 | O43: 5160.8 | P43: 5169.15 | Q43: 5175.1 | R43: 5172.25 | S43: 5175.75 | T43: 5075.9 | U43: 5139.7 | V43: 5122.85 | W43: 5112.9 | X43: 5137.4 | Y43: 5045 | Z43: 4663.9 | AA43: 106848.2
B44: ELECTROPERU | C44: C.T. TUMBES | D44: MAK1 | E44: TERMOELÉCTRICA | AA44: 0
B45: ELECTROPERU | C45: C.T. TUMBES | D45: MAK2 | E45: TERMOELÉCTRICA | AA45: 0
B46: EMPRESA DE GENERACION ELECTRICA CANCHAYLLO SAC | C46: C.H. CANCHAYLLO | D46: CENTRAL | E46: HIDROELÉCTRICA | F46: 112.5 | G46: 100.8 | H46: 124.1 | I46: 103.55 | J46: 113.3 | K46: 123.6 | L46: 123.25 | M46: 116.85 | N46: 114.45 | O46: 119.85 | P46: 117.55 | Q46: 115.85 | R46: 114.05 | S46: 119.85 | T46: 113.8 | U46: 114 | V46: 86.35 | W46: 94.5 | X46: 83.65 | Y46: 119.55 | Z46: 121.35 | AA46: 2352.75
B47: EMPRESA DE GENERACION ELECTRICA SANTA ANA S.A.C. | C47: C.H. RENOVANDES H1 | D47: CENTRAL | E47: HIDROELÉCTRICA | F47: 387.05 | G47: 388.1 | H47: 377.65 | I47: 489.2 | J47: 487.2 | K47: 486.7 | L47: 488.3 | M47: 486.6 | N47: 486.6 | O47: 485.2 | P47: 487.65 | Q47: 413.75 | R47: 340.7 | S47: 488.4 | T47: 487.3 | U47: 487.5 | V47: 487 | W47: 304.6 | X47: 489.4 | Y47: 487.95 | Z47: 407.15 | AA47: 9444
B48: EMPRESA DE GENERACION HUALLAGA | C48: C.H. CHAGLLA | D48: CENTRAL | E48: HIDROELÉCTRICA | F48: 9464.9 | G48: 10349.55 | H48: 11041.4 | I48: 10527.6 | J48: 11010.7 | K48: 10765.2 | L48: 10480.3 | M48: 10669.45 | N48: 10937.3 | O48: 10777.85 | P48: 11005.3 | Q48: 10999.6 | R48: 10989.2 | S48: 10766.95 | T48: 6095.95 | U48: 10983.85 | V48: 10980.25 | W48: 11150.3 | X48: 11047.4 | Y48: 10986.05 | Z48: 10945.9 | AA48: 221975
B49: EMPRESA DE GENERACION HUALLAGA | C49: P.C.H. CHAGLLA | D49: CENTRAL | E49: HIDROELÉCTRICA | F49: 156 | G49: 156 | H49: 156 | I49: 156 | J49: 156 | K49: 155.9 | L49: 155.95 | M49: 156 | N49: 146.15 | O49: 156 | P49: 156 | Q49: 156 | R49: 156 | S49: 156 | T49: 156.05 | U49: 156 | V49: 156 | W49: 156 | X49: 156 | Y49: 156 | Z49: 156 | AA49: 3266.05
B50: EMPRESA DE GENERACION HUANZA | C50: C.H. HUANZA | D50: CENTRAL | E50: HIDROELÉCTRICA | F50: 1009.8 | G50: 1357.1 | H50: 1200.6 | I50: 1277.05 | J50: 1010.95 | K50: 898.3 | L50: 855.85 | M50: 762.7 | N50: 571.5 | O50: 678.15 | P50: 649.15 | Q50: 689.95 | R50: 707.75 | S50: 918.05 | T50: 1314.6 | U50: 1348.05 | V50: 1556 | W50: 1672 | X50: 1543.3 | Y50: 1690.75 | Z50: 1415.3 | AA50: 23126.9
B51: EMPRESA ELECTRICA AGUA AZUL | C51: C.H. POTRERO | D51: CENTRAL | E51: HIDROELÉCTRICA | F51: 479.2 | G51: 443.5 | H51: 480 | I51: 480 | J51: 460.55 | K51: 480 | L51: 480 | M51: 480 | N51: 480 | O51: 452.35 | P51: 480 | Q51: 155.4 | R51: 464.2 | S51: 479.15 | T51: 432.85 | U51: 480 | V51: 435.6 | W51: 396.15 | X51: 466.3 | Y51: 457.85 | Z51: 478.55 | AA51: 9441.65
B52: EMPRESA ELECTRICA RIO DOBLE | C52: C.H. LAS PIZARRAS | D52: CENTRAL | E52: HIDROELÉCTRICA | F52: 445.15 | G52: 442.95 | H52: 449.1 | I52: 450.85 | J52: 451.4 | K52: 452.55 | L52: 431.8 | M52: 446.7 | N52: 450.2 | O52: 451.15 | P52: 450.55 | Q52: 446.9 | R52: 447.85 | S52: 444.5 | T52: 441.65 | U52: 430.65 | V52: 452.95 | W52: 453.8 | X52: 453.25 | Y52: 455.3 | Z52: 451.85 | AA52: 9401.1
B53: ENEL GENERACION PIURA S.A. | C53: C.T. MALACAS 1 | D53: TG6 | E53: TERMOELÉCTRICA | F53: 528.25 | G53: 146.85 | H53: 466.15 | I53: 778 | J53: 777.4 | K53: 679.35 | L53: 700.15 | M53: 748.75 | N53: 768.25 | O53: 664.75 | P53: 776.05 | Q53: 702.75 | R53: 716.7 | S53: 687.6 | T53: 291 | U53: 1032.25 | V53: 1069.8 | W53: 1076.65 | X53: 709.85 | Y53: 1075.75 | Z53: 764.35 | AA53: 15160.65
B54: ENEL GENERACION PIURA S.A. | C54: C.T. MALACAS 2 | D54: TG4 | E54: TERMOELÉCTRICA | G54: 456.25 | H54: 338.3 | AA54: 794.55
B55: ENEL GENERACION PIURA S.A. | C55: C.T. RF DE GENERACION TALARA | D55: TG5 | E55: TERMOELÉCTRICA | AA55: 0
B56: ENERGÍA EÓLICA S.A. | C56: C.E. CUPISNIQUE | D56: CENTRAL | E56: EÓLICA | F56: 185.6 | G56: 29.8 | H56: 253.05 | I56: 813.3 | J56: 860.85 | K56: 628.6 | L56: 96.15 | M56: 130.3 | N56: 232.1 | O56: 287.15 | P56: 227.95 | Q56: 512.5 | R56: 274.9 | S56: 169.05 | T56: 145.15 | U56: 242.05 | V56: 217.55 | W56: 141.85 | X56: 255.35 | Y56: 227.7 | Z56: 301.8 | AA56: 6232.75
B57: ENERGÍA EÓLICA S.A. | C57: C.E. TALARA | D57: CENTRAL | E57: EÓLICA | F57: 120.85 | G57: 102.7 | H57: 234.7 | I57: 258.65 | J57: 312.6 | K57: 259.5 | L57: 60.45 | M57: 98.7 | N57: 100.9 | O57: 65.9 | P57: 97.95 | Q57: 150.2 | R57: 35.15 | S57: 72.4 | T57: 61.6 | U57: 131.15 | V57: 14.4 | W57: 15.15 | X57: 42.65 | Y57: 51.3 | Z57: 24.95 | AA57: 2311.85
B58: ENERGIA RENOVABLE DEL SUR S.A. | C58: C.E. SAN JUAN | D58: CENTRAL | E58: EÓLICA | F58: 872.2 | G58: 357.2 | H58: 934.7 | I58: 1367.05 | J58: 2517.3 | K58: 2802.15 | L58: 1631.05 | M58: 1301.35 | N58: 1741.65 | O58: 1538.7 | P58: 1260.6 | Q58: 1170.05 | R58: 1691.6 | S58: 2036.8 | T58: 1427.2 | U58: 637.95 | V58: 1602.75 | W58: 1352 | X58: 491.4 | Y58: 334.65 | Z58: 1131.95 | AA58: 28200.3
B59: ENGIE ENERGIA PERU S.A.A. | C59: C.E. PUNTA LOMITAS | D59: PL-BL1 | E59: EÓLICA | F59: 372.47 | G59: 182.8 | H59: 344.8 | I59: 381.05 | J59: 696.7 | K59: 1768.45 | L59: 1162.7 | M59: 1101.95 | N59: 1248.2 | O59: 1018.925 | P59: 1065.55 | Q59: 717.55 | R59: 986.95 | S59: 1036.75 | T59: 1016.7 | U59: 567.35 | V59: 862.3 | W59: 912.3 | X59: 468.15 | Y59: 138 | Z59: 620.25 | AA59: 16669.895
B60: ENGIE ENERGIA PERU S.A.A. | C60: C.E. PUNTA LOMITAS | D60: PL-BL2 | E60: EÓLICA | F60: 651.42 | G60: 317.68 | H60: 622.3 | I60: 639.45 | J60: 1032.8 | K60: 2222.835 | L60: 1755 | M60: 1694.7 | N60: 1775.35 | O60: 1675.285 | P60: 1669.8 | Q60: 1261.1 | R60: 1620.75 | S60: 1675.65 | T60: 1663.85 | U60: 1022.57 | V60: 1331.8 | W60: 1366.45 | X60: 803.8 | Y60: 193.7 | Z60: 1064.55 | AA60: 26060.84
B61: ENGIE ENERGIA PERU S.A.A. | C61: C.E. PUNTA LOMITAS_EXP | D61: PUN LOM_EXP-BL1 | E61: EÓLICA | F61: 37.72 | G61: 20.85 | H61: 45.95 | I61: 34 | J61: 87.75 | K61: 255.1 | L61: 180.6 | M61: 160.6 | N61: 150.9 | O61: 117.64705 | P61: 137.75 | Q61: 95.35 | R61: 126.45 | S61: 126.95 | T61: 132.45 | U61: 68.45 | V61: 115.6 | W61: 116.55 | X61: 58.15 | Y61: 19.6 | Z61: 76.2 | AA61: 2164.617
B62: ENGIE ENERGIA PERU S.A.A. | C62: C.E. PUNTA LOMITAS_EXP | D62: PUN LOM_EXP-BL2 | E62: EÓLICA | F62: 35.66 | G62: 12.35 | H62: 26.65 | I62: 25.3 | J62: 53.1 | K62: 198.35 | L62: 133.05 | M62: 121.45 | N62: 120.35 | O62: 110.61245 | P62: 106.75 | Q62: 57.8 | R62: 90.2 | S62: 102.1 | T62: 99.45 | U62: 45.9 | V62: 85.4 | W62: 93.1 | X62: 40.25 | Y62: 14.25 | Z62: 52.4 | AA62: 1624.4724
B63: ENGIE ENERGIA PERU S.A.A. | C63: C.H. QUITARACSA | D63: CENTRAL | E63: HIDROELÉCTRICA | F63: 160.5 | H63: 363.05 | J63: 141.4 | M63: 153.65 | S63: 393.15 | T63: 442.55 | U63: 44 | V63: 910.05 | W63: 346.15 | Y63: 559.95 | AA63: 3514.45
B64: ENGIE ENERGIA PERU S.A.A. | C64: C.H. YUNCAN | D64: CENTRAL | E64: HIDROELÉCTRICA | F64: 2509.05 | G64: 3075.25 | H64: 3078.4 | I64: 3064.85 | J64: 3061.75 | K64: 3062.5 | L64: 3064.5 | M64: 3059.5 | N64: 3062.4 | O64: 3052.205 | P64: 2048.25 | Q64: 2228.15 | R64: 3064.1 | S64: 3068 | T64: 3062.6 | U64: 3065.9 | V64: 3054.35 | W64: 3041.4 | X64: 3058 | Y64: 3051.85 | Z64: 3052.05 | AA64: 61885.055
B65: ENGIE ENERGIA PERU S.A.A. | C65: C.S. EXPANSIÓN INTIPAMPA | D65: CENTRAL | E65: SOLAR | F65: 275.3 | G65: 173.9 | H65: 153.2 | I65: 201.25 | J65: 271 | K65: 387.4 | L65: 347.35 | M65: 152.55 | N65: 219 | O65: 347.5 | P65: 159.4 | Q65: 225.9 | R65: 170.4 | S65: 95.75 | T65: 114.6 | U65: 111.6 | V65: 78.7 | W65: 125.9 | X65: 290.6 | Y65: 220.15 | Z65: 182.05 | AA65: 4303.5
B66: ENGIE ENERGIA PERU S.A.A. | C66: C.S. INTIPAMPA | D66: CENTRAL | E66: SOLAR | F66: 169.75 | G66: 118.5 | H66: 170.3 | I66: 153.3 | J66: 231.05 | K66: 288.5 | L66: 252.9 | M66: 107.9 | N66: 167.75 | O66: 269.7 | P66: 211.85 | Q66: 182.7 | R66: 125.6 | S66: 64.5 | T66: 83.25 | U66: 72.9 | V66: 59.8 | W66: 85 | X66: 211.5 | Y66: 145.75 | Z66: 135.5 | AA66: 3308
B67: ENGIE ENERGIA PERU S.A.A. | C67: C.T. CHILCA 1 | D67: TG1 | E67: TERMOELÉCTRICA | K67: 314.05 | L67: 884.6 | M67: 781.7 | N67: 576.15 | P67: 1189.2 | Q67: 878.5 | R67: 941.2 | U67: 1715.5 | V67: 2269.25 | W67: 2951.9 | X67: 2111.85 | Y67: 590.1 | Z67: 720.2 | AA67: 15924.2
B68: ENGIE ENERGIA PERU S.A.A. | C68: C.T. CHILCA 1 | D68: TG2 | E68: TERMOELÉCTRICA | F68: 688.65 | G68: 2238.5 | H68: 1625.8 | I68: 1372.6 | J68: 1318.4 | K68: 518.15 | L68: 776.85 | M68: 1401.15 | N68: 1840.1 | O68: 696.055 | P68: 1815.15 | Q68: 1088.4 | R68: 1536.25 | S68: 641.05 | U68: 1812.65 | V68: 1787 | W68: 2885.1 | X68: 2106.95 | Y68: 867.75 | Z68: 963 | AA68: 27979.555
B69: ENGIE ENERGIA PERU S.A.A. | C69: C.T. CHILCA 1 | D69: TG3 | E69: TERMOELÉCTRICA | F69: 1749.05 | G69: 2707.15 | H69: 2345.55 | I69: 2401.55 | J69: 2309 | K69: 1144.35 | L69: 2425.25 | M69: 2387.9 | N69: 3178.6 | O69: 1811.015 | P69: 2715.35 | Q69: 2508.45 | R69: 2455.6 | S69: 1052.1 | U69: 2735.75 | V69: 2536.4 | W69: 3954.45 | X69: 2894.85 | Y69: 3402.75 | Z69: 1855.7 | AA69: 48570.815
B70: ENGIE ENERGIA PERU S.A.A. | C70: C.T. CHILCA 1 | D70: TV | E70: TERMOELÉCTRICA | AA70: 0
B71: ENGIE ENERGIA PERU S.A.A. | C71: C.T. CHILCA 2 | D71: TG41 | E71: TERMOELÉCTRICA | F71: 1342.6 | G71: 1401.6 | H71: 1424.65 | I71: 1410.5 | J71: 1449.55 | K71: 1274.15 | L71: 1377.2 | M71: 176.85 | N71: 1151.4 | O71: 1304.675 | P71: 1440.75 | Q71: 1455.3 | R71: 1447.7 | S71: 1224.75 | T71: 940.7 | U71: 1453.35 | V71: 1617.25 | W71: 1692.55 | X71: 1535.1 | Y71: 1554.1 | Z71: 1352.3 | AA71: 28027.025
B72: ENGIE ENERGIA PERU S.A.A. | C72: C.T. CHILCA 2 | D72: TV42 | E72: TERMOELÉCTRICA | F72: 764.75 | G72: 772.15 | H72: 773.2 | I72: 769.45 | J72: 785.95 | K72: 736.05 | L72: 755.7 | N72: 508.9 | O72: 745.765 | P72: 773.15 | Q72: 776.65 | R72: 773.3 | S72: 728.2 | T72: 663.7 | U72: 778.7 | V72: 815.8 | W72: 828.55 | X72: 789.95 | Y72: 783.05 | Z72: 752.7 | AA72: 15075.665
B73: ENGIE ENERGIA PERU S.A.A. | C73: C.T. NEPI | D73: TG41 | E73: TERMOELÉCTRICA | U73: 468.45 | AA73: 468.45
B74: ENGIE ENERGIA PERU S.A.A. | C74: C.T. NEPI | D74: TG42 | E74: TERMOELÉCTRICA | W74: 486.85 | AA74: 486.85
B75: ENGIE ENERGIA PERU S.A.A. | C75: C.T. NEPI | D75: TG43 | E75: TERMOELÉCTRICA | AA75: 0
B76: ENGIE ENERGIA PERU S.A.A. | C76: C.T. RF PLANTA ILO | D76: TG1 | E76: TERMOELÉCTRICA | Q76: 359.6 | AA76: 359.6
B77: ENGIE ENERGIA PERU S.A.A. | C77: C.T. RF PLANTA ILO | D77: TG2 | E77: TERMOELÉCTRICA | AA77: 0
B78: ENGIE ENERGIA PERU S.A.A. | C78: C.T. RF PLANTA ILO | D78: TG3 | E78: TERMOELÉCTRICA | AA78: 0
B79: FENIX POWER PERÚ | C79: C.T. FENIX | D79: GT11 | E79: TERMOELÉCTRICA | F79: 3824.55 | G79: 1322.6 | Y79: 1815.1 | Z79: 4076.5 | AA79: 11038.75
B80: FENIX POWER PERÚ | C80: C.T. FENIX | D80: GT12 | E80: TERMOELÉCTRICA | F80: 3832.7 | G80: 1262 | V80: 776.7 | Y80: 2664.5 | Z80: 4080.45 | AA80: 12616.35
B81: FENIX POWER PERÚ | C81: C.T. FENIX | D81: TV10 | E81: TERMOELÉCTRICA | F81: 4132.7 | G81: 1449.3 | V81: 297.45 | Y81: 2005.55 | Z81: 4305.25 | AA81: 12190.25
B82: GENERACIÓN ANDINA S.A.C. | C82: C.H. 8 DE AGOSTO | D82: CENTRAL | E82: HIDROELÉCTRICA | F82: 503.2 | G82: 504.5 | H82: 506.9 | I82: 510.9 | J82: 510.65 | K82: 511.25 | L82: 510.5 | M82: 350.25 | N82: 467.2 | O82: 475.8 | P82: 423.5 | Q82: 486.6 | R82: 494.4 | S82: 299.3 | T82: 504 | U82: 502.95 | V82: 502 | W82: 498.9 | X82: 499.75 | Y82: 323.15 | Z82: 132.9 | AA82: 9518.6
B83: GENERACIÓN ANDINA S.A.C. | C83: C.H. EL CARMEN | D83: CENTRAL | E83: HIDROELÉCTRICA | F83: 186.7 | G83: 168.9 | H83: 192.15 | I83: 187.5 | J83: 161.5 | K83: 178.8 | L83: 174.55 | M83: 170.75 | N83: 155.75 | O83: 145.45 | P83: 141.3 | Q83: 180.95 | R83: 186.15 | S83: 184.95 | T83: 192.05 | U83: 190.8 | V83: 181.3 | W83: 190.35 | X83: 186.95 | Y83: 134.05 | Z83: 49.85 | AA83: 3540.75
B84: GENERADORA DE ENERGÍA DEL PERÚ | C84: C.H. ÁNGEL I | D84: CENTRAL | E84: HIDROELÉCTRICA | F84: 489.6 | G84: 489.6 | H84: 488.15 | I84: 489.6 | J84: 489.6 | K84: 489.6 | L84: 489.6 | M84: 489.6 | N84: 487.5 | O84: 489.6 | P84: 489.6 | Q84: 489.6 | R84: 489.4 | S84: 489.6 | T84: 489.6 | U84: 489.6 | V84: 489.6 | W84: 438.6 | X84: 489.6 | Y84: 489.6 | Z84: 489.6 | AA84: 10226.85
B85: GENERADORA DE ENERGÍA DEL PERÚ | C85: C.H. ÁNGEL II | D85: CENTRAL | E85: HIDROELÉCTRICA | F85: 489.6 | G85: 489.6 | H85: 488.09 | I85: 489.6 | J85: 489.6 | K85: 489.6 | L85: 489.6 | M85: 489.6 | N85: 476.8 | O85: 489.6 | P85: 489.6 | Q85: 489.6 | R85: 489.6 | S85: 489.6 | T85: 489.6 | U85: 489.6 | V85: 489.6 | W85: 434.4 | X85: 489.6 | Y85: 489.6 | Z85: 489.6 | AA85: 10212.09
B86: GENERADORA DE ENERGÍA DEL PERÚ | C86: C.H. ÁNGEL III | D86: CENTRAL | E86: HIDROELÉCTRICA | F86: 482.4 | G86: 482.4 | H86: 481.77 | I86: 482.25 | J86: 372.4 | K86: 395.85 | L86: 481.85 | M86: 480 | N86: 464.1 | O86: 481.4 | P86: 480 | Q86: 480 | R86: 480 | S86: 480 | T86: 480 | U86: 480 | V86: 480 | W86: 422.5 | X86: 480 | Y86: 480 | Z86: 480 | AA86: 9826.92
B87: GENERADORA DE ENERGÍA DEL PERÚ | C87: C.H. LA JOYA | D87: CENTRAL | E87: HIDROELÉCTRICA | H87: 11.35 | I87: 146.85 | J87: 149.25 | K87: 151.7 | L87: 141.35 | M87: 138.6 | N87: 153.8 | O87: 7.05 | P87: 135.25 | Q87: 139.7 | R87: 160.1 | S87: 141.6 | T87: 127.4 | U87: 122.4 | V87: 34.85 | W87: 157.6 | X87: 108.85 | AA87: 2027.7
B88: GM OPERACIONES S.A.C. | C88: CT REFINERIA TALARA | D88: TV1 REF TALARA | E88: TERMOELÉCTRICA | F88: 643.7 | G88: 650.4 | H88: 646.1 | I88: 648.85 | J88: 636.55 | K88: 658.1 | L88: 658.25 | M88: 663.75 | N88: 659 | O88: 658.05 | P88: 656.55 | Q88: 663.8 | R88: 659.15 | S88: 653.4 | T88: 654 | U88: 650.6 | V88: 646.3 | W88: 580.1 | X88: 613.9 | Y88: 66.45 | AA88: 12367
B89: GM OPERACIONES S.A.C. | C89: CT REFINERIA TALARA | D89: TV2 REF TALARA | E89: TERMOELÉCTRICA | F89: 798.05 | G89: 814.9 | H89: 811.85 | I89: 804.9 | J89: 806.8 | K89: 822.5 | L89: 821.5 | M89: 828.45 | N89: 820.5 | O89: 818.25 | P89: 820.8 | Q89: 828.7 | R89: 819.3 | S89: 818.9 | T89: 822.3 | U89: 819.2 | V89: 813.4 | W89: 810.4 | X89: 798.05 | Y89: 401.9 | Z89: 692.85 | AA89: 16593.5
B90: GR CORTARRAMA SOCIEDAD ANONIMA CERRADA | C90: C.S. MATARANI | D90: C.S. MATARANI | E90: SOLAR | F90: 697.55 | G90: 485.55 | H90: 712.35 | I90: 759.6 | J90: 691.2 | K90: 742.8 | L90: 577.85 | M90: 406.85 | N90: 813.65 | O90: 767.95 | P90: 477.65 | Q90: 610.5 | R90: 632.55 | S90: 480.15 | T90: 617.45 | U90: 532.7 | V90: 486.9 | W90: 343.8 | X90: 757.4 | Y90: 734.2 | Z90: 550.3 | AA90: 12878.95
B91: GR PAINO SOCIEDAD ANONIMA CERRADA | C91: C.E. HUAMBOS | D91: CENTRAL | E91: EÓLICA | F91: 33.9 | G91: 3.45 | H91: 23.38 | I91: 119.45 | J91: 108.4 | K91: 24.55 | L91: 43.4 | M91: 166.1 | N91: 125.25 | O91: 45.92 | P91: 42.8 | Q91: 76.6 | R91: 94.9 | S91: 67.05 | T91: 77.4 | U91: 139.75 | V91: 183.4 | W91: 43.2 | X91: 212.84 | Y91: 41.9 | Z91: 34.35 | AA91: 1707.99
B92: GR TARUCA SOCIEDAD ANONIMA CERRADA | C92: C.E. DUNA | D92: CENTRAL | E92: EÓLICA | F92: 20.15 | G92: 1.45 | H92: 22.875 | I92: 122.7 | J92: 120.55 | K92: 13.95 | L92: 47.65 | M92: 195.15 | N92: 136 | O92: 39.495 | P92: 0.5 | Q92: 43.75 | R92: 48.3 | S92: 41.1 | T92: 48.5 | U92: 69.35 | V92: 108.65 | W92: 28.6 | X92: 118.42 | Y92: 50.5 | Z92: 31.5 | AA92: 1309.14
B93: HIDROCAÑETE S.A. | C93: C.H. IMPERIAL | D93: CENTRAL | E93: HIDROELÉCTRICA | F93: 80.1 | G93: 79.4 | H93: 77.3 | I93: 76.1 | J93: 79.6 | K93: 80.35 | L93: 79.25 | M93: 69 | N93: 57.95 | O93: 63.3 | P93: 73.05 | Q93: 81.6 | R93: 81.65 | S93: 82.3 | T93: 81.65 | U93: 81.65 | V93: 79.95 | W93: 55.7 | X93: 53.9 | Y93: 83.05 | Z93: 84.8 | AA93: 1581.65
B94: HIDROELECTRICA HUANCHOR S.A.C. | C94: C.H. HUANCHOR | D94: CENTRAL | E94: HIDROELÉCTRICA | F94: 442.35 | G94: 441.85 | H94: 444.25 | I94: 444.05 | J94: 445.45 | K94: 444.65 | L94: 441.75 | M94: 442.55 | N94: 443.2 | O94: 442.7 | P94: 442.45 | Q94: 441.75 | R94: 442.9 | S94: 441.3 | T94: 441.95 | U94: 440.75 | V94: 440.45 | W94: 441.4 | X94: 440.05 | Y94: 442.8 | Z94: 441.95 | AA94: 9290.55
B95: HUAURA POWER GROUP S.A. | C95: C.H. YARUCAYA | D95: CENTRAL | E95: HIDROELÉCTRICA | F95: 444.15 | G95: 444.9 | H95: 414 | I95: 444.55 | J95: 444 | K95: 407.95 | L95: 445.85 | M95: 443.25 | N95: 441.6 | O95: 441.6 | P95: 441.6 | Q95: 441.6 | R95: 441.6 | S95: 442.15 | T95: 442.55 | U95: 443 | V95: 443.95 | W95: 444 | X95: 442.775 | Y95: 442.725 | Z95: 444 | AA95: 9241.8
B96: HYDRO GLOBAL PERÚ S.A.C. | C96: CH SAN GABAN III | D96: CENTRAL | E96: HIDROELÉCTRICA | F96: 4870.1 | G96: 4860.15 | H96: 4181.5 | I96: 4832.05 | J96: 4836.35 | K96: 4856.5 | L96: 3440.165 | M96: 3481.85 | N96: 4821.6 | O96: 4846.65 | P96: 4803.8 | Q96: 4845.15 | R96: 4849.55 | S96: 4863.25 | T96: 4849.4 | U96: 4852.7 | V96: 4849 | W96: 4836.6 | X96: 4853.95 | Y96: 4850.45 | Z96: 4851.7 | AA96: 98332.465
B97: INFRAESTRUCTURAS Y ENERGIAS DEL PERU S.A.C. | C97: C.T. RF PTO MALDONADO | D97: CENTRAL | E97: TERMOELÉCTRICA | F97: 116.15 | T97: 130.75 | Z97: 0.9 | AA97: 247.8
B98: INFRAESTRUCTURAS Y ENERGIAS DEL PERU S.A.C. | C98: C.T. RF PUCALLPA | D98: CENTRAL | E98: TERMOELÉCTRICA | H98: 1.65 | AA98: 1.65
B99: INLAND ENERGY SAC | C99: C.H. SANTA TERESA | D99: CENTRAL | E99: HIDROELÉCTRICA | F99: 2121.8 | G99: 2171.6 | H99: 2181.9 | I99: 2168.6 | J99: 2181.3 | K99: 2178.4 | L99: 2178.1 | M99: 1842.25 | N99: 2182.9 | O99: 2183 | P99: 2188.25 | Q99: 2174.55 | R99: 2173.15 | S99: 2178.25 | T99: 2133.75 | U99: 2153.7 | V99: 2170.05 | W99: 2162.85 | X99: 2180.8 | Y99: 2168.75 | Z99: 2162.55 | AA99: 45236.5
B100: INVERSIONES SHAQSHA S.A.C. | C100: C.H. PARIAC | D100: CENTRAL | E100: HIDROELÉCTRICA | F100: 55.2 | G100: 55.2 | H100: 53.75 | I100: 23.35 | J100: 26.3 | K100: 55.2 | L100: 57.6 | M100: 56.25 | N100: 55.15 | O100: 51.25 | P100: 52 | Q100: 57.6 | R100: 57.6 | S100: 57.6 | T100: 57.6 | U100: 52.65 | V100: 56.4 | W100: 53.05 | X100: 50.2755 | Y100: 50.4 | Z100: 50.4 | AA100: 1084.8255
B101: JOYA SOLAR S.A.C. | C101: C.S. SAN MARTIN SOLAR | D101: CENTRAL | E101: SOLAR | F101: 2235.75 | G101: 1360.05 | H101: 1920.65 | I101: 2422.6 | J101: 2091.95 | K101: 2507.15 | L101: 1888.9 | M101: 950.75 | N101: 2553.5 | O101: 2243.65 | P101: 1265.6 | Q101: 1570.7 | R101: 1519.2 | S101: 1094.1 | T101: 1786.75 | U101: 1657.75 | V101: 1078.4 | W101: 1011.5 | X101: 2393.25 | Y101: 1712.15 | Z101: 1614.55 | AA101: 36878.9
B102: KALLPA GENERACION S.A. | C102: C.H. CERRO DEL AGUILA | D102: CENTRAL | E102: HIDROELÉCTRICA | F102: 12999.15 | G102: 13385.9 | H102: 13468.165 | I102: 13399.45 | J102: 13384.15 | K102: 13334.9 | L102: 13380.85 | M102: 13180.15 | N102: 13226.95 | O102: 13288.35 | P102: 13401.8 | Q102: 13227.9 | R102: 13377.4 | S102: 13393.7 | T102: 12388.6 | U102: 13390.6 | V102: 13336.05 | W102: 13309.05 | X102: 13364.2 | Y102: 13315.6 | Z102: 12876.45 | AA102: 278429.36
B103: KALLPA GENERACION S.A. | C103: C.S. SUNNY | D103: CENTRAL | E103: SOLAR | F103: 1347.3 | G103: 985.75 | H103: 1702.5 | I103: 1960.45 | J103: 0.6 | K103: 1590.7 | L103: 1529.05 | M103: 732.5 | N103: 2068.1 | O103: 1902.8 | P103: 977.95 | Q103: 1304.8 | R103: 1179.5 | S103: 871.65 | T103: 1485.3 | U103: 1419.95 | V103: 851.85 | W103: 714.9 | X103: 1948.1 | Y103: 1384.15 | Z103: 1320.8 | AA103: 27278.7
...

Sheet G_AREAS
B3: sábado, 21 de Febrero del 2026
B5: HORA | C5: RESUMEN DE GENERACIÓN POR ÁREAS DEL SEIN | D5: RESUMEN DE GENERACIÓN POR ÁREAS DEL SEIN | E5: RESUMEN DE GENERACIÓN POR ÁREAS DEL SEIN | F5: RESUMEN DE GENERACIÓN POR ÁREAS DEL SEIN | G5: RESUMEN DE GENERACIÓN POR ÁREAS DEL SEIN | H5: RESUMEN DE GENERACIÓN POR ÁREAS DEL SEIN | I5: RESUMEN DE GENERACIÓN POR ÁREAS DEL SEIN | J5: RESUMEN DE GENERACIÓN POR ÁREAS DEL SEIN | K5: RESUMEN DE GENERACIÓN POR ÁREAS DEL SEIN | L5: RESUMEN DE GENERACIÓN POR ÁREAS DEL SEIN | M5: RESUMEN DE GENERACIÓN POR ÁREAS DEL SEIN | N5: RESUMEN DE GENERACIÓN POR ÁREAS DEL SEIN | O5: RESUMEN DE GENERACIÓN POR ÁREAS DEL SEIN | P5: RESUMEN DE GENERACIÓN POR ÁREAS DEL SEIN | Q5: RESUMEN DE GENERACIÓN POR ÁREAS DEL SEIN | R5: RESUMEN DE GENERACIÓN POR ÁREAS DEL SEIN | S5: HORA | T5: GENERACIÓN POR TIPO DE GENERACIÓN | U5: GENERACIÓN POR TIPO DE GENERACIÓN | V5: GENERACIÓN POR TIPO DE GENERACIÓN | W5: GENERACIÓN POR TIPO DE GENERACIÓN | X5: GENERACIÓN POR TIPO DE GENERACIÓN | Y5: HORA | Z5: GENERACIÓN POR TIPO DE GENERACIÓN | AA5: GENERACIÓN POR TIPO DE GENERACIÓN | AB5: GENERACIÓN POR TIPO DE GENERACIÓN | AC5: GENERACIÓN POR TIPO DE GENERACIÓN | AD5: GENERACIÓN POR TIPO DE GENERACIÓN
C6: NORTE | D6: NORTE | E6: NORTE | F6: NORTE | G6: CENTRO | H6: CENTRO | I6: CENTRO | J6: CENTRO | K6: SUR | L6: SUR | M6: SUR | N6: SUR | O6: GENERACIÓN INTEGRANTES COES | P6: GENERACIÓN INTEGRANTES COES | Q6: GENERACIÓN INTEGRANTES COES | R6: GENERACIÓN INTEGRANTES COES | T6: INTEGRANTES COES | U6: INTEGRANTES COES | V6: INTEGRANTES COES | W6: INTEGRANTES COES | X6: INTEGRANTES COES | Z6: INTEGRANTES COES RER | AA6: INTEGRANTES COES RER | AB6: INTEGRANTES COES RER | AC6: INTEGRANTES COES RER | AD6: INTEGRANTES COES RER
C7: GENERACIÓN HIDROELÉCTRICA NORTE | D7: GENERACIÓN TERMOELÉCTRICA NORTE | E7: GENERACIÓN SOLAR NORTE | F7: GENERACIÓN EÓLICA NORTE | G7: GENERACIÓN HIDROELÉCTRICA CENTRO | H7: GENERACIÓN TERMOELÉCTRICA CENTRO | I7: GENERACIÓN SOLAR CENTRO | J7: GENERACIÓN EÓLICA CENTRO | K7: GENERACIÓN HIDROELÉCTRICA SUR | L7: GENERACIÓN TERMOELÉCTRICA SUR | M7: GENERACIÓN SOLAR SUR | N7: GENERACIÓN EÓLICA SUR | O7: GENERACIÓN COES NORTE | P7: GENERACIÓN COES CENTRO | Q7: GENERACIÓN COES SUR | R7: TOTAL GENERACION | T7: HIDROELÉCTRICA | U7: TERMOELÉCTRICA | V7: SOLAR | W7: EÓLICA | X7: TOTAL GENERACION | Z7: HIDROELÉCTRICA RER | AA7: TERMOELÉCTRICA RER | AB7: SOLAR RER | AC7: EÓLICA RER | AD7: TOTAL RER
B8: 00:30 | C8: 430.7 | D8: 124.47 | E8: 0 | F8: 24.1 | G8: 3463.4 | H8: 2300.7 | I8: 0 | J8: 25.7 | K8: 787.795 | L8: 0 | M8: 0 | N8: 0 | O8: 579.27 | P8: 5789.8 | Q8: 787.795 | R8: 7156.865 | S8: 00:30 | T8: 4681.895 | U8: 2425.17 | V8: 0 | W8: 49.8 | X8: 7156.865 | Y8: 00:30 | Z8: 334.4 | AA8: 73.37 | AB8: 0 | AC8: 49.8 | AD8: 457.57
B9: 01:00 | C9: 434.9 | D9: 125.18 | E9: 0 | F9: 20.7 | G9: 3518.7 | H9: 2139.7 | I9: 0 | J9: 14.6 | K9: 795.246 | L9: 0 | M9: 0 | N9: 0 | O9: 580.78 | P9: 5673 | Q9: 795.246 | R9: 7049.026 | S9: 01:00 | T9: 4748.846 | U9: 2264.88 | V9: 0 | W9: 35.3 | X9: 7049.026 | Y9: 01:00 | Z9: 335.2 | AA9: 74.08 | AB9: 0 | AC9: 35.3 | AD9: 444.58
B10: 01:30 | C10: 434.2 | D10: 93.81 | E10: 0 | F10: 12.9 | G10: 3447.5 | H10: 2084.7 | I10: 0 | J10: 21.9 | K10: 790.783 | L10: 0 | M10: 0 | N10: 0 | O10: 540.91 | P10: 5554.1 | Q10: 790.783 | R10: 6885.793 | S10: 01:30 | T10: 4672.483 | U10: 2178.51 | V10: 0 | W10: 34.8 | X10: 6885.793 | Y10: 01:30 | Z10: 335 | AA10: 74.21 | AB10: 0 | AC10: 34.8 | AD10: 444.01
B11: 02:00 | C11: 435.1 | D11: 79.21 | E11: 0 | F11: 11.3 | G11: 3467.4 | H11: 1978.1 | I11: 0 | J11: 26.6 | K11: 801.889 | L11: 0 | M11: 0 | N11: 0 | O11: 525.61 | P11: 5472.1 | Q11: 801.889 | R11: 6799.599 | S11: 02:00 | T11: 4704.389 | U11: 2057.31 | V11: 0 | W11: 37.9 | X11: 6799.599 | Y11: 02:00 | Z11: 335.6 | AA11: 74.51 | AB11: 0 | AC11: 37.9 | AD11: 448.01
B12: 02:30 | C12: 435.5 | D12: 80.52 | E12: 0 | F12: 11.7 | G12: 3498.9 | H12: 1790.5 | I12: 0 | J12: 18.5 | K12: 799.823 | L12: 0 | M12: 0 | N12: 0 | O12: 527.72 | P12: 5307.9 | Q12: 799.823 | R12: 6635.443 | S12: 02:30 | T12: 4734.223 | U12: 1871.02 | V12: 0 | W12: 30.2 | X12: 6635.443 | Y12: 02:30 | Z12: 335.8 | AA12: 75.02 | AB12: 0 | AC12: 30.2 | AD12: 441.02
B13: 03:00 | C13: 428.5 | D13: 79.89 | E13: 0 | F13: 11.3 | G13: 3595 | H13: 1749.5 | I13: 0 | J13: 23.8 | K13: 784.635 | L13: 0 | M13: 0 | N13: 0 | O13: 519.69 | P13: 5368.3 | Q13: 784.635 | R13: 6672.625 | S13: 03:00 | T13: 4808.135 | U13: 1829.39 | V13: 0 | W13: 35.1 | X13: 6672.625 | Y13: 03:00 | Z13: 335.9 | AA13: 74.39 | AB13: 0 | AC13: 35.1 | AD13: 445.39
B14: 03:30 | C14: 432.1 | D14: 80.14 | E14: 0 | F14: 15.5 | G14: 3582.9 | H14: 1622.8 | I14: 0 | J14: 23.6 | K14: 763.58 | L14: 0 | M14: 0 | N14: 0 | O14: 527.74 | P14: 5229.3 | Q14: 763.58 | R14: 6520.62 | S14: 03:30 | T14: 4778.58 | U14: 1702.94 | V14: 0 | W14: 39.1 | X14: 6520.62 | Y14: 03:30 | Z14: 335.3 | AA14: 74.74 | AB14: 0 | AC14: 39.1 | AD14: 449.14
B15: 04:00 | C15: 436.3 | D15: 80.72 | E15: 0 | F15: 9.2 | G15: 3717.8 | H15: 1580.8 | I15: 0 | J15: 17.8 | K15: 798.055 | L15: 0 | M15: 0 | N15: 0 | O15: 526.22 | P15: 5316.4 | Q15: 798.055 | R15: 6640.675 | S15: 04:00 | T15: 4952.155 | U15: 1661.52 | V15: 0 | W15: 27 | X15: 6640.675 | Y15: 04:00 | Z15: 336.2 | AA15: 74.92 | AB15: 0 | AC15: 27 | AD15: 438.12
B16: 04:30 | C16: 439.9 | D16: 79.35 | E16: 0 | F16: 6.4 | G16: 3758.3 | H16: 1524.8 | I16: 0 | J16: 24.5 | K16: 807.241 | L16: 0 | M16: 0 | N16: 0 | O16: 525.65 | P16: 5307.6 | Q16: 807.241 | R16: 6640.491 | S16: 04:30 | T16: 5005.441 | U16: 1604.15 | V16: 0 | W16: 30.9 | X16: 6640.491 | Y16: 04:30 | Z16: 336.5 | AA16: 73.25 | AB16: 0 | AC16: 30.9 | AD16: 440.65
B17: 05:00 | C17: 435.2 | D17: 81.33 | E17: 0 | F17: 7.5 | G17: 3664.3 | H17: 1554.8 | I17: 0 | J17: 31.1 | K17: 800.667 | L17: 0 | M17: 0 | N17: 0 | O17: 524.03 | P17: 5250.2 | Q17: 800.667 | R17: 6574.897 | S17: 05:00 | T17: 4900.167 | U17: 1636.13 | V17: 0 | W17: 38.6 | X17: 6574.897 | Y17: 05:00 | Z17: 335.9 | AA17: 75.33 | AB17: 0 | AC17: 38.6 | AD17: 449.83
B18: 05:30 | C18: 433.6 | D18: 82.35 | E18: 0 | F18: 7.1 | G18: 3714.8 | H18: 1594.9 | I18: 0 | J18: 27.2 | K18: 791.947 | L18: 0 | M18: 0.1 | N18: 0 | O18: 523.05 | P18: 5336.9 | Q18: 792.047 | R18: 6651.997 | S18: 05:30 | T18: 4940.347 | U18: 1677.25 | V18: 0.1 | W18: 34.3 | X18: 6651.997 | Y18: 05:30 | Z18: 335.5 | AA18: 75.95 | AB18: 0.1 | AC18: 34.3 | AD18: 445.85
B19: 06:00 | C19: 432.9 | D19: 82.14 | E19: 0 | F19: 10.2 | G19: 3650.8 | H19: 1644.7 | I19: 0 | J19: 22.5 | K19: 791.648 | L19: 0 | M19: 11.9 | N19: 0 | O19: 525.24 | P19: 5318 | Q19: 803.548 | R19: 6646.788 | S19: 06:00 | T19: 4875.348 | U19: 1726.84 | V19: 11.9 | W19: 32.7 | X19: 6646.788 | Y19: 06:00 | Z19: 336 | AA19: 76.34 | AB19: 11.9 | AC19: 32.7 | AD19: 456.94
... B56: TOTAL MWh | C56: 10243.3 | D56: 2710.265 | E56: 1.75 | F56: 392.6 | G56: 85373.85 | H56: 48394.931 | I56: 9.7 | J56: 5625.2 | K56: 19053.187 | L56: 0.9 | M56: 5334.1 | N56: 0 | O56: 13347.915 | P56: 139403.68 | Q56: 24388.187 | R56: 177139.78 | S56: TOTAL MWh | T56: 114670.34 | U56: 51106.096 | V56: 5345.55 | W56: 6017.8 | X56: 177139.78 | Y56: TOTAL MWh | Z56: 8020.75 | AA56: 1841.215 | AB56: 5345.55 | AC56: 6017.8 | AD56: 21225.315

Sheet HOP
B3: sábado, 21 de Febrero del 2026
B5: Reporte de Horas de Operación
B6: Empresa | C6: Central | D6: Grupo | E6: Modo de Operación | F6: Inicio | G6: Final | H6: O. Arranque | I6: O. Parada | J6: Tipo Operación | K6: Ensayo de Potencia Efectiva | L6: Ensayo de Potencia Mínima | M6: Sistema | N6: Lim. Transm. | O6: Causa | P6: Observación
B7: AGRO INDUSTRIAL PARAMONGA S.A. | C7: C.T. PARAMONGA | D7: CENTRAL | E7: PARAMONGA - BAGAZO | F7: 21/02/2026 00:00:00 | G7: 22/02/2026 00:00:00 | J7: POR COGENERACION | O7: ...
B8: AGROAURORA S.A.C. | C8: C.T. MAPLE ETANOL | D8: CENTRAL | E8: MAPLE- BAGAZO | F8: 21/02/2026 00:00:00 | G8: 22/02/2026 00:00:00 | J8: POR COGENERACION | O8: ...
B9: AGROINDUSTRIAS SAN JACINTO S.A.A. | C9: C.T. SAN JACINTO | D9: CENTRAL | E9: SAN_JACINTO - BAGAZO | F9: 21/02/2026 00:00:00 | G9: 22/02/2026 00:00:00 | J9: POR COGENERACION | O9: ...
B10: AGROLMOS SOCIEDAD ANONIMA - AGROLMOS S.A. | C10: C.T. AGROLMOS | D10: TV1 | E10: AGROLMOS TV1 - BAGAZO | F10: 21/02/2026 00:00:00 | G10: 21/02/2026 15:42:01 | J10: POR COGENERACION | O10: ...
B11: AGROLMOS SOCIEDAD ANONIMA - AGROLMOS S.A. | C11: C.T. AGROLMOS | D11: CENTRAL | E11: AGROLMOS TV1 & TV2 - BAGAZO | F11: 21/02/2026 15:42:01 | G11: 21/02/2026 16:19:38 | J11: POR COGENERACION | O11: ...
B12: AGROLMOS SOCIEDAD ANONIMA - AGROLMOS S.A. | C12: C.T. AGROLMOS | D12: TV1 | E12: AGROLMOS TV1 - BAGAZO | F12: 21/02/2026 16:19:38 | G12: 21/02/2026 21:25:21 | J12: POR COGENERACION | O12: ...
B13: AGROLMOS SOCIEDAD ANONIMA - AGROLMOS S.A. | C13: C.T. AGROLMOS | D13: CENTRAL | E13: AGROLMOS TV1 & TV2 - BAGAZO | F13: 21/02/2026 21:25:21 | G13: 22/02/2026 00:00:00 | J13: POR COGENERACION | O13: ...
B14: BIOENERGIA DEL CHIRA S.A. | C14: C.T. CAÑA BRAVA | D14: G-1 | E14: CANA BRAVA TV1 - BAGAZO | F14: 21/02/2026 00:00:00 | G14: 22/02/2026 00:00:00 | J14: POR COGENERACION | O14: ...
B15: CASA GRANDE S.A.A. | C15: C.T. CASA GRANDE | D15: CENTRAL | E15: CASA GRANDE TV1 & TV3 - BAGAZO | F15: 21/02/2026 00:00:00 | G15: 21/02/2026 13:22:17 | J15: POR COGENERACION | O15: ...
B16: CASA GRANDE S.A.A. | C16: C.T. CASA GRANDE | D16: CENTRAL | E16: CASA GRANDE TV1 & TV3 - BAGAZO | F16: 21/02/2026 13:22:17 | G16: 21/02/2026 14:44:42 | J16: POR COGENERACION | O16: ...
B17: CASA GRANDE S.A.A. | C17: C.T. CASA GRANDE | D17: CENTRAL | E17: CASA GRANDE TV1 & TV3 - BAGAZO | F17: 21/02/2026 14:44:42 | G17: 22/02/2026 00:00:00 | J17: POR COGENERACION | O17: ...
B18: EGESUR | C18: C.T. INDEPENDENCIA | D18: CENTRAL | E18: INDEPENDENCIA GAS | F18: 21/02/2026 08:16:00 | G18: 21/02/2026 13:00:00 | H18: 21/02/2026 08:13:00 | J18: POR POTENCIA O ENERGIA | O18: ...
B19: EGESUR | C19: C.T. INDEPENDENCIA | D19: CENTRAL | E19: INDEPENDENCIA GAS | F19: 21/02/2026 13:00:00 | G19: 21/02/2026 13:09:00 | J19: A MINIMA CARGA | O19: ...
B20: EGESUR | C20: C.T. INDEPENDENCIA | D20: CENTRAL | E20: INDEPENDENCIA GAS | F20: 21/02/2026 20:18:00 | G20: 21/02/2026 22:06:00 | H20: 21/02/2026 20:15:00 | I20: 21/02/2026 21:55:00 | J20: POR POTENCIA O ENERGIA | O20: ... | P20: Fallo G2
B21: ENEL GENERACION PIURA S.A. | C21: C.T. MALACAS 1 | D21: CENTRAL | E21: MALACAS1 TG6 - GAS | F21: 21/02/2026 00:00:00 | G21: 21/02/2026 01:34:00 | I21: 21/02/2026 01:18:00 | J21: POR POTENCIA O ENERGIA | O21: ...
B22: ENEL GENERACION PIURA S.A. | C22: C.T. MALACAS 1 | D22: CENTRAL | E22: MALACAS1 TG6 - GAS | F22: 21/02/2026 08:00:00 | G22: 22/02/2026 00:00:00 | H22: 21/02/2026 07:47:00 | J22: POR POTENCIA O ENERGIA | O22: ...
B23: ENGIE ENERGIA PERU S.A.A. | C23: C.T. CHILCA 1 | D23: TG3 | E23: CHILCA1 TG3 - GAS | F23: 21/02/2026 00:00:00 | G23: 21/02/2026 00:15:00 | J23: A MINIMA CARGA | O23: ...
B24: ENGIE ENERGIA PERU S.A.A. | C24: C.T. CHILCA 1 | D24: TG2 | E24: CHILCA1 TG2 - GAS | F24: 21/02/2026 08:24:00 | G24: 21/02/2026 11:30:00 | H24: 21/02/2026 08:12:00 | J24: POR POTENCIA O ENERGIA | O24: ...
B25: ENGIE ENERGIA PERU S.A.A. | C25: C.T. CHILCA 1 | D25: TG3 | E25: CHILCA1 TG3 - GAS | F25: 21/02/2026 08:28:00 | G25: 21/02/2026 13:01:00 | H25: 21/02/2026 08:08:00 | J25: POR POTENCIA O ENERGIA | O25: ...
B26: ENGIE ENERGIA PERU S.A.A. | C26: C.T. CHILCA 1 | D26: TG1 | E26: CHILCA1 TG1 - GAS | F26: 21/02/2026 09:43:00 | G26: 21/02/2026 12:34:00 | H26: 21/02/2026 09:21:00 | J26: POR POTENCIA O ENERGIA | O26: ...
B27: ENGIE ENERGIA PERU S.A.A. | C27: C.T. CHILCA 1 | D27: TG2 | E27: CHILCA1 TG2 - GAS | F27: 21/02/2026 11:30:00 | G27: 21/02/2026 11:58:00 | J27: A MINIMA CARGA | O27: ...
B28: ENGIE ENERGIA PERU S.A.A. | C28: C.T. CHILCA 1 | D28: TG1 | E28: CHILCA1 TG1 - GAS | F28: 21/02/2026 12:34:00 | G28: 21/02/2026 13:04:00 | J28: A MINIMA CARGA | O28: ...
B29: ENGIE ENERGIA PERU S.A.A. | C29: C.T. CHILCA 1 | D29: TG3 | E29: CHILCA1 TG3 - GAS | F29: 21/02/2026 13:01:00 | G29: 21/02/2026 13:35:00 | J29: A MINIMA CARGA | O29: ...
B30: ENGIE ENERGIA PERU S.A.A. | C30: C.T. CHILCA 1 | D30: TG3 | E30: CHILCA1 TG3 - GAS | F30: 21/02/2026 18:05:00 | G30: 21/02/2026 18:23:00 | H30: 21/02/2026 17:35:00 | J30: A MINIMA CARGA | O30: ...
B31: ENGIE ENERGIA PERU S.A.A. | C31: C.T. CHILCA 1 | D31: TG3 | E31: CHILCA1 TG3 - GAS | F31: 21/02/2026 18:23:00 | G31: 21/02/2026 23:03:00 | J31: POR POTENCIA O ENERGIA | O31: ...
B32: ENGIE ENERGIA PERU S.A.A. | C32: C.T. CHILCA 1 | D32: TG2 | E32: CHILCA1 TG2 - GAS | F32: 21/02/2026 18:38:00 | G32: 21/02/2026 19:13:00 | H32: 21/02/2026 18:23:00 | J32: A MINIMA CARGA | O32: ...
