Workbook

Sheet EVENTOS
B3: viernes, 4 de Julio del 2025
B5: INFORMACIÓN DE EVENTOS PRINCIPALES EN SUS INSTALACIONES
B6: TIPO DE EVENTO | C6: EMPRESA | D6: UBICACIÓN | E6: TIPO DE EQUIPO | F6: EQUIPO | G6: INICIO | H6: FINAL | I6: DESCRIPCIÓN | J6: MW INDISP. | K6: INTERRUPCIÓN (SI/NO) | L6: TENSIÓN DE FALLA (kV)
B7: EVENTO | C7: CONELSUR LT SAC | D7: PORTILLO | E7: SUBESTACION | F7: SS.EE. | G7: 04/07/2025 00:00:00 | H7: 05/07/2025 00:00:00 | I7: DECLARACIÓN DE SITUACIÓN EXCEPCIONAL EN LA S.E. PORTILLO DE 60 kV | K7: NO
B8: FALLA | C8: GM OPERACIONES S.A.C. | D8: REFINERIA TALARA | E8: CENTRAL TERMOELÉCTRICA | F8: CENTRAL | G8: 04/07/2025 20:30:00 | H8: 04/07/2025 20:30:00 | I8: DESCONEXIÓN DE LA C.T. REFINERÍA TALARA POR FALLA EN CALDERA | K8: SI | L8: 13.8
B9: P.ENERG | C9: RED DE ENERGIA DEL PERU S.A. | D9: PIURA OESTE - MIGUEL GRAU | E9: LINEA DE TRANSMISION | F9: L-2143 | G9: 04/07/2025 19:30:00 | H9: 04/07/2025 19:30:00 | I9: PRIMERA ENERGIZACION DE LA LINEA L-2143 (PIURA OESTE - MIGUEL GRAU) DE 220 kV | K9: NO
B10: FALLA | C10: RED DE ENERGIA DEL PERU S.A. | D10: COMBAPATA | E10: TRANSFORMADOR 3D | F10: T46-162 | G10: 04/07/2025 08:38:00 | H10: 04/07/2025 08:52:00 | I10: DESCONEXIÓN DE LA BARRA DE 24 kV DE LA SE COMBAPATA POR FALLA | K10: SI | L10: 0

Sheet RESTRIC_OPE
B3: viernes, 4 de Julio del 2025
B5: RESTRICCIONES OPERATIVAS
B6: FECHA | C6: HORA INICIO | D6: HORA FINAL | E6: EMPRESA | F6: UBICACIÓN | G6: T.Eq. | H6: EQUIPO | I6: DESCRIPCIÓN
B7: 04/07/2025 | C7: 00:00 | D7: 24:00 | E7: EGASA | F7: C.H. CHARCANI II | G7: GH | H7: G2 | I7: El Grupo N°02 esta operando con una potencia no mayor a 0.07MW en referencia a 0.18MW de su potencia efectiva, con el fin de no generar daños mayores hasta la reparación de su cojinete.
B8: 04/07/2025 | C8: 00:00 | D8: 24:00 | E8: EGASA | F8: S.E. CONVERTIDOR | G8: BARRA | H8: BARRA138KV | I8: EGASA limitó la capacidad del transformador 138 kV/33 kV a 50 MVA por deterioro del aislamiento.
B9: 04/07/2025 | C9: 00:00 | D9: 24:00 | E9: ENEL GENERACION PIURA S.A. | F9: C.T. MALACAS | G9: CT | H9: CENTRAL | I9: De acuerdo con la comunicación vía correo del día 24.10.2024. ENEL GENERACIÓN PIURA informa una restricción de potencia para alcanzar 105 MW en simultaneo (TG6+TGN4).
B10: 04/07/2025 | C10: 00:00 | D10: 24:00 | E10: ENEL GENERACION PIURA S.A. | F10: C.T. MALACAS | G10: GT | H10: TG4 | I10: De acuerdo a lo informado mediante correo electronico el día 19.05, la TG4 solo puede operar a máxima generación dos horas y el resto a carga a mínima carga.
B11: 04/07/2025 | C11: 00:00 | D11: 24:00 | E11: ENGIE | F11: C.E. PUNTA LOMITAS | G11: CE | H11: CENTRAL | I11: De acuerdo a la carta ENG/737-2024 (Exp:202400007555). Limitación de cables de media tensión a 100 MW de los transformadores PLT1 y PLT2 de la CE Punta Lomitas. Quedan limitados a 200 MW la generación de CE Punta Lomitas y Punta Lomitas Extensión.
B12: 04/07/2025 | C12: 00:00 | D12: 24:00 | E12: ENGIE | F12: C.H. YUNCÁN | G12: GH | H12: G3 | I12: Según la carta N° ENG/ 198-2024 enviada por su representada, se opera de forma continua el G3 de la CH Yuncán, debido a la ejecución de mantenimientos necesarios para evitar daños en los sellos de seguridad de la válvula esférica del grupo.
B13: 04/07/2025 | C13: 00:00 | D13: 24:00 | E13: ENGIE | F13: C.T. CHILCA 1 | G13: CT | H13: CENTRAL | I13: Restricción de temperatura de la C.T Chilca, ver valor en el modelo de despacho.
B14: 04/07/2025 | C14: 00:00 | D14: 24:00 | E14: ENGIE | F14: C.T. CHILCA 1 | G14: CT | H14: CENTRAL | I14: Con carta ENG/971-2023, indica que no puede cumplir con las IO considerada en el PDO_17122023 dado que vulneran la seguridad de sus activos. Indican que se debe tomar TMO=168h.
B15: 04/07/2025 | C15: 00:00 | D15: 24:00 | E15: ENGIE | F15: C.T. CHILCA 2 | G15: CT | H15: CENTRAL | I15: Restricción de temperatura de la C.T Chilca2, ver valor en el modelo de despacho.
B16: 04/07/2025 | C16: 00:00 | D16: 24:00 | E16: ENGIE | F16: C.T. CHILCA 2 | G16: CT | H16: CENTRAL | I16: Con carta ENG/971-2023, indica que no puede cumplir con las IO considerada en el PDO_17122023 dado que vulneran la seguridad de sus activos. Indican que se debe tomar TMO=168h.
B17: 04/07/2025 | C17: 00:00 | D17: 24:00 | E17: FENIX POWER PERÚ | F17: C.T. FENIX | G17: CT | H17: CENTRAL | I17: De acuerdo con lo comunicado en el correo del día 06.05.2024, la CT Fenix cuenta con TMO de 168 hrs en todos su modos de operación.
... B41: 04/07/2025 | C41: 00:00 | D41: 24:00 | E41: TERMOSELVA | F41: C.T. AGUAYTÍA | G41: CT | H41: CENTRAL | I41: Disponibilidad de 23.5 MMSCF para la CT Aguaytía.

Sheet MANTENIMIENTO EJECUTADOS
B3: viernes, 4 de Julio del 2025
B5: Mantenimiento Ejecutado
B6: Empresa | C6: Ubicación | D6: Equipo | E6: Inicio | F6: Final | G6: Descripción | H6: MW Indisp. | I6: Prog. | J6: Dispon | K6: Interrupc. | L6: Tipo | M6: CodEq | N6: TipoEq_Osinerg
B7: AGROAURORA S.A.C. | C7: MAPLE ETANOL | D7: CENTRAL | E7: 04/07/2025 00:00 | F7: 05/07/2025 00:00 | G7: CENTRAL TERMOELECTRICA FUERA DE SERVICIO POR FALTA DE MATERIA PRIMA PARA LOS REQUERIMIENTOS DE CALOR UTIL EN FABRICA. | H7: 17 | I7: P | J7: F/S | K7: N | L7: OTROS | M7: 13417 | N7: G
B8: ATLANTICA TRANSMISION SUR S.A. | C8: MONTALVO | D8: ACOPLE 220 | E8: 04/07/2025 00:00 | F8: 05/07/2025 00:00 | G8: Proyecto Refuerzos: Reemplazo del HMI existente, Pruebas y Configuracion. No se contara con nivel 1 de operacion. | H8: 0 | I8: P | J8: E/S | K8: N | L8: P.ENERG | M8: 14767 | N8: T
B9: ATLANTICA TRANSMISION SUR S.A. | C9: MONTALVO | D9: BARRA A_220KV | E9: 04/07/2025 00:00 | F9: 05/07/2025 00:00 | G9: Proyecto Refuerzos: Indisponibilidad de la proteccion diferencial de barras 220 kV por Conexion de la nueva UB-87B hacia la UC existente,Configuracion y Pruebas. | H9: 0 | I9: P | J9: E/S | K9: N | L9: P.ENERG | M9: 13869 | N9: T
B10: ATLANTICA TRANSMISION SUR S.A. | C10: MONTALVO | D10: BARRA A_500KV | E10: 04/07/2025 00:00 | F10: 05/07/2025 00:00 | G10: Proyecto Refuerzos: Indisponibilidad de la proteccion diferencial de barras 500kV por conexion de nueva UB-87B hacia la UC existente, Configuracion y Pruebas. | H10: 0 | I10: P | J10: E/S | K10: N | L10: P.ENERG | M10: 13870 | N10: T
B11: ATLANTICA TRANSMISION SUR S.A. | C11: MONTALVO | D11: BARRA B_220kV | E11: 04/07/2025 00:00 | F11: 05/07/2025 00:00 | G11: Proyecto Refuerzos: Indisponibilidad de la proteccion diferencial de barras 220 kV por Conexion de la nueva UB-87B hacia la UC existente,Configuracion y Pruebas. | H11: 0 | I11: P | J11: E/S | K11: N | L11: P.ENERG | M11: 14765 | N11: T
B12: ATLANTICA TRANSMISION SUR S.A. | C12: MONTALVO | D12: BARRA B_500KV | E12: 04/07/2025 00:00 | F12: 05/07/2025 00:00 | G12: Proyecto Refuerzos: Indisponibilidad de la proteccion diferencial de barras 500kV por conexion de nueva UB-87B hacia la UC existente, Configuracion y Pruebas. | H12: 0 | I12: P | J12: E/S | K12: N | L12: P.ENERG | M12: 13871 | N12: T
B13: ATLANTICA TRANSMISION SUR S.A. | C13: MONTALVO | D13: CL-2057 | E13: 04/07/2025 00:00 | F13: 05/07/2025 00:00 | G13: Proyecto Refuerzos: Reemplazo del HMI existente, Pruebas y Configuracion. No se contara con nivel 1 de operacion. | H13: 0 | I13: P | J13: E/S | K13: N | L13: P.ENERG | M13: 13812 | N13: T
B14: ATLANTICA TRANSMISION SUR S.A. | C14: MONTALVO | D14: CL-AUT-5671_500 | E14: 04/07/2025 00:00 | F14: 05/07/2025 00:00 | G14: Proyecto Refuerzos: Reemplazo del HMI existente, Pruebas y Configuracion. No se contara con nivel 1 de operacion en INT-5671, INT-5652 y SAT-5671. | H14: 0 | I14: P | J14: E/S | K14: N | L14: P.ENERG | M14: 13809 | N14: T
B15: ATLANTICA TRANSMISION SUR S.A. | C15: MONTALVO | D15: INT-5652 | E15: 04/07/2025 00:00 | F15: 05/07/2025 00:00 | G15: Proyecto Refuerzos: Indisponible por Implementacion de Conexion de corrientes, disparos, posiciones, enclavamientos hacia los equipos del nuevo Autotransformador. AUT-5671 en servicio solo por Barra A 500kV. | H15: 0 | I15: P | J15: F/S | K15: N | L15: P.ENERG | M15: 13765 | N15: T
B16: ATLANTICA TRANSMISION SUR S.A. | C16: OCONA | D16: INT-5450 | E16: 04/07/2025 00:00 | F16: 05/07/2025 00:00 | G16: Interruptor INT-5450 cerrado con restriccion operativa, REB-5450 en servicio y suministrando los SS.AA. de la S.E. Oco?a. | H16: 0 | I16: P | J16: E/S | K16: N | L16: OTROS | M16: 13761 | N16: T
B17: ATLANTICA TRANSMISION SUR S.A. | C17: OCONA | D17: INT-5462 | E17: 04/07/2025 00:00 | F17: 05/07/2025 00:00 | G17: Seccionador SBA-5462 fase T indisponible por problemas mecanicos, el seccionador permanece cerrado y bloqueado | H17: 0 | I17: P | J17: E/S | K17: N | L17: OTROS | M17: 13758 | N17: T
B18: ATLANTICA TRANSMISION SUR S.A. | C18: POROMA | D18: ACOPLE 220 | E18: 04/07/2025 00:00 | F18: 05/07/2025 00:00 | G18: Proyecto Refuerzos: Reemplazo del HMI existente, Pruebas y Configuracion. No se contara con nivel 1 de operacion. | H18: 0 | I18: P | J18: E/S | K18: N | L18: P.ENERG | M18: 13797 | N18: T
... B147: VARI ENERGIA S.A.C. | C147: ANASHIRONI | D147: G1 | E147: 04/07/2025 15:19 | F147: 04/07/2025 18:00 | G147: * Pruebas de regulacion grupo generador Anashironi Subir y bajar potencia entre 2 y 20MW * Culminada las pruebas CH ANASHIRONI queda en servicio (segun disponibilidad hidrica) maximo hasta 15 MW por restriccion EDAG. | H147: 0 | I147: P | J147: E/S | K147: N | L147: PRUEBA | M147: 24348 | N147: G

Sheet INGRESO OC
A3: viernes, 4 de Julio del 2025
A5: INGRESO A OPERACIÓN COMERCIAL
A6: EMPRESA | B6: TIPO DE EQUIPO | C6: UBICACIÓN | D6: EQUIPO | E6: Fecha y hora de Ingreso a Operación Comercial

Sheet DESPACHO_EJECUTADO
B3: viernes, 4 de Julio del 2025
A5: POTENCIA ACTIVA EJECUTADA DE LAS UNIDADES DE GENERACIÓN DEL SEIN (MW) | FL5: CENTRALES NO INTEGRANTES COES
A6: FECHA | B6: HORA | C6: 65333 | D6: 101 | E6: 102 | F6: 42667 | G6: 42668 | H6: 126 | I6: 127 | J6: 138 | K6: 139 | L6: 197 | M6: 203 | N6: 204 | O6: 230 | P6: 209 | Q6: 56677 | R6: 796 | S6: 2146 | T6: 142 | U6: 143 | V6: 125 | W6: 187 | X6: 163 | Y6: 298 | Z6: 299 | AA6: 219 | AB6: 151 | AC6: 152 | AD6: 153 | AE6: 154 | AF6: 756 | AG6: 156 | AH6: 155 | AI6: 182 | AJ6: 212 | AK6: 758 | AL6: 263 | AM6: 265 | AN6: 775 | AO6: 777 | AP6: 2154 | AQ6: 150 | AR6: 149 | AS6: 188 | AT6: 2131 | AU6: 755 | AV6: 252 | AW6: 249 | AX6: 250 | AY6: 117 | AZ6: 267 | BA6: 268 | BB6: 119 | BC6: 120 | BD6: 189 | BE6: 122 | BF6: 266 | BG6: 337 | BH6: 338 | BI6: 251 | BJ6: 115 | BK6: 239 | BL6: 288 | BM6: 240 | BN6: 241 | BO6: 242 | BP6: 191 | BQ6: 194 | BR6: 196 | BS6: 207 | BT6: 236 | BU6: 795 | BV6: 285 | BW6: 995 | BX6: 996 | BY6: 997 | BZ6: 766 | CA6: 926 | CB6: 924 | CC6: 121 | CD6: 103 | CE6: 104 | CF6: 106 | CG6: 105 | CH6: 107 | CI6: 110 | CJ6: 109 | CK6: 144 | CL6: 113 | CM6: 114 | CN6: 193 | CO6: 208 | CP6: 786 | CQ6: 787 | CR6: 788 | CS6: 789 | CT6: 248 | CU6: 2159 | CV6: 303 | CW6: 59715 | CX6: 62255 | CY6: 1263 | CZ6: 61800 | DA6: 2194 | DB6: 216 | DC6: 198 | DD6: 49607 | DE6: 214 | DF6: 260 | DG6: 2152 | DH6: 2128 | DI6: 247 | DJ6: 228 | DK6: 2135 | DL6: 261 | DM6: 237 | DN6: 253 | DO6: 770 | DP6: 225 | DQ6: 2201 | DR6: 2171 | DS6: 760 | DT6: 235 | DU6: 238 | DV6: 2184 | DW6: 61855 | DX6: 223 | DY6: 226 | DZ6: 201 | EA6: 258 | EB6: 259 | EC6: 920 | ED6: 257 | EE6: 256 | EF6: 2148 | EG6: 58288 | EH6: 58289 | EI6: 58839 | EJ6: 58840 | EK6: 296 | EL6: 297 | EM6: 211 | EN6: 2175 | EO6: 2178 | EP6: 2181 | EQ6: 1262 | ER6: 63425 | ES6: 233 | ET6: 2150 | EU6: 2165 | EV6: 2161 | EW6: 61197 | EX6: 58851 | EY6: 234 | EZ6: 215 | FA6: 917 | FB6: 289 | FC6: 58333 | FD6: 58336 | FE6: 213 | FF6: 232 | FG6: 2190 | FH6: 202 | FI6: 58487 | FJ6: TOTAL COES | FL6: 221 | FM6: 222 | FN6: 224 | FO6: 2187 | FP6: 227 | FQ6: 49400 | FR6: 199 | FS6: 200 | FT6: TOTAL NO COES
C7: SUR | D7: CENTRO | E7: CENTRO | F7: NORTE | G7: NORTE | H7: NORTE | I7: NORTE | J7: CENTRO | K7: CENTRO | L7: CENTRO | M7: CENTRO | N7: CENTRO | O7: CENTRO | P7: CENTRO | Q7: CENTRO | R7: CENTRO | S7: CENTRO | T7: CENTRO | U7: CENTRO | V7: CENTRO | W7: CENTRO | X7: SUR | Y7: SUR | Z7: SUR | AA7: CENTRO | AB7: SUR | AC7: SUR | AD7: SUR | AE7: SUR | AF7: SUR | AG7: SUR | AH7: SUR | AI7: SUR | AJ7: CENTRO | AK7: NORTE | AL7: NORTE | AM7: NORTE | AN7: CENTRO | AO7: CENTRO | AP7: CENTRO | AQ7: CENTRO | AR7: CENTRO | AS7: CENTRO | AT7: CENTRO | AU7: SUR | AV7: CENTRO | AW7: CENTRO | AX7: CENTRO | AY7: CENTRO | AZ7: CENTRO | BA7: CENTRO | BB7: CENTRO | BC7: CENTRO | BD7: SUR | BE7: NORTE | BF7: CENTRO | BG7: CENTRO | BH7: CENTRO | BI7: CENTRO | BJ7: NORTE | BK7: NORTE | BL7: NORTE | BM7: SUR | BN7: SUR | BO7: SUR | BP7: CENTRO | BQ7: CENTRO | BR7: CENTRO | BS7: CENTRO | BT7: CENTRO | BU7: CENTRO | BV7: CENTRO | BW7: SUR | BX7: SUR | BY7: SUR | BZ7: NORTE | CA7: SUR | CB7: CENTRO | CC7: NORTE | CD7: CENTRO | CE7: CENTRO | CF7: CENTRO | CG7: CENTRO | CH7: CENTRO | CI7: CENTRO | CJ7: CENTRO | CK7: CENTRO | CL7: CENTRO | CM7: CENTRO | CN7: CENTRO | CO7: CENTRO | CP7: SUR | CQ7: SUR | CR7: SUR | CS7: SUR | CT7: CENTRO | CU7: CENTRO | CV7: CENTRO | CW7: CENTRO | CX7: SUR | CY7: NORTE | CZ7: NORTE | DA7: NORTE | DB7: NORTE | DC7: NORTE | DD7: SUR | DE7: CENTRO | DF7: CENTRO | DG7: CENTRO | DH7: NORTE | DI7: NORTE | DJ7: CENTRO | DK7: CENTRO | DL7: SUR | DM7: SUR | DN7: CENTRO | DO7: CENTRO | DP7: CENTRO | DQ7: CENTRO | DR7: CENTRO | DS7: CENTRO | DT7: SUR | DU7: CENTRO | DV7: CENTRO | DW7: NORTE | DX7: CENTRO | DY7: CENTRO | DZ7: NORTE | EA7: CENTRO | EB7: CENTRO | EC7: CENTRO | ED7: NORTE | EE7: NORTE | EF7: SUR | EG7: CENTRO | EH7: CENTRO | EI7: CENTRO | EJ7: CENTRO | EK7: CENTRO | EL7: CENTRO | EM7: SUR | EN7: SUR | EO7: SUR | EP7: SUR | EQ7: NORTE | ER7: SUR | ES7: SUR | ET7: SUR | EU7: CENTRO | EV7: CENTRO | EW7: CENTRO | EX7: SUR | EY7: SUR | EZ7: NORTE | FA7: CENTRO | FB7: NORTE | FC7: NORTE | FD7: NORTE | FE7: CENTRO | FF7: NORTE | FG7: NORTE | FH7: CENTRO | FI7: CENTRO | FL7: NORTE | FM7: CENTRO | FN7: NORTE | FO7: NORTE | FP7: NORTE | FQ7: NORTE | FR7: NORTE | FS7: NORTE
C8: HIDROELÉCTRICA | D8: HIDROELÉCTRICA | E8: HIDROELÉCTRICA | F8: TERMOELÉCTRICA | G8: TERMOELÉCTRICA | H8: HIDROELÉCTRICA | I8: HIDROELÉCTRICA | J8: TERMOELÉCTRICA | K8: TERMOELÉCTRICA | L8: TERMOELÉCTRICA | M8: TERMOELÉCTRICA | N8: TERMOELÉCTRICA | O8: TERMOELÉCTRICA | P8: TERMOELÉCTRICA | Q8: TERMOELÉCTRICA | R8: HIDROELÉCTRICA | S8: HIDROELÉCTRICA | T8: TERMOELÉCTRICA | U8: TERMOELÉCTRICA | V8: TERMOELÉCTRICA | W8: TERMOELÉCTRICA | X8: HIDROELÉCTRICA | Y8: HIDROELÉCTRICA | Z8: HIDROELÉCTRICA | AA8: TERMOELÉCTRICA | AB8: HIDROELÉCTRICA | AC8: HIDROELÉCTRICA | AD8: HIDROELÉCTRICA | AE8: HIDROELÉCTRICA | AF8: TERMOELÉCTRICA | AG8: TERMOELÉCTRICA | AH8: TERMOELÉCTRICA | AI8: HIDROELÉCTRICA | AJ8: HIDROELÉCTRICA | AK8: TERMOELÉCTRICA | AL8: TERMOELÉCTRICA | AM8: TERMOELÉCTRICA | AN8: HIDROELÉCTRICA | AO8: HIDROELÉCTRICA | AP8: HIDROELÉCTRICA | AQ8: HIDROELÉCTRICA | AR8: HIDROELÉCTRICA | AS8: HIDROELÉCTRICA | AT8: HIDROELÉCTRICA | AU8: HIDROELÉCTRICA | AV8: TERMOELÉCTRICA | AW8: TERMOELÉCTRICA | AX8: TERMOELÉCTRICA | AY8: HIDROELÉCTRICA | AZ8: HIDROELÉCTRICA | BA8: HIDROELÉCTRICA | BB8: HIDROELÉCTRICA | BC8: HIDROELÉCTRICA | BD8: HIDROELÉCTRICA | BE8: HIDROELÉCTRICA | BF8: HIDROELÉCTRICA | BG8: HIDROELÉCTRICA | BH8: HIDROELÉCTRICA | BI8: HIDROELÉCTRICA | BJ8: TERMOELÉCTRICA | BK8: TERMOELÉCTRICA | BL8: TERMOELÉCTRICA | BM8: TERMOELÉCTRICA | BN8: TERMOELÉCTRICA | BO8: TERMOELÉCTRICA | BP8: HIDROELÉCTRICA | BQ8: TERMOELÉCTRICA | BR8: TERMOELÉCTRICA | BS8: TERMOELÉCTRICA | BT8: TERMOELÉCTRICA | BU8: TERMOELÉCTRICA | BV8: TERMOELÉCTRICA | BW8: TERMOELÉCTRICA | BX8: TERMOELÉCTRICA | BY8: TERMOELÉCTRICA | BZ8: HIDROELÉCTRICA | CA8: TERMOELÉCTRICA | CB8: TERMOELÉCTRICA | CC8: HIDROELÉCTRICA | CD8: HIDROELÉCTRICA | CE8: HIDROELÉCTRICA | CF8: HIDROELÉCTRICA | CG8: HIDROELÉCTRICA | CH8: HIDROELÉCTRICA | CI8: TERMOELÉCTRICA | CJ8: TERMOELÉCTRICA | CK8: TERMOELÉCTRICA | CL8: TERMOELÉCTRICA | CM8: TERMOELÉCTRICA | CN8: TERMOELÉCTRICA | CO8: TERMOELÉCTRICA | CP8: TERMOELÉCTRICA | CQ8: TERMOELÉCTRICA | CR8: TERMOELÉCTRICA | CS8: TERMOELÉCTRICA | CT8: TERMOELÉCTRICA | CU8: TERMOELÉCTRICA | CV8: SOLAR | CW8: EÓLICA | CX8: SOLAR | CY8: EÓLICA | CZ8: SOLAR | DA8: HIDROELÉCTRICA | DB8: HIDROELÉCTRICA | DC8: HIDROELÉCTRICA | DD8: HIDROELÉCTRICA | DE8: HIDROELÉCTRICA | DF8: HIDROELÉCTRICA | DG8: HIDROELÉCTRICA | DH8: HIDROELÉCTRICA | DI8: HIDROELÉCTRICA | DJ8: HIDROELÉCTRICA | DK8: HIDROELÉCTRICA | DL8: SOLAR | DM8: SOLAR | DN8: EÓLICA | DO8: EÓLICA | DP8: TERMOELÉCTRICA | DQ8: TERMOELÉCTRICA | DR8: TERMOELÉCTRICA | DS8: TERMOELÉCTRICA | DT8: SOLAR | DU8: HIDROELÉCTRICA | DV8: HIDROELÉCTRICA | DW8: HIDROELÉCTRICA | DX8: HIDROELÉCTRICA | DY8: HIDROELÉCTRICA | DZ8: HIDROELÉCTRICA | EA8: HIDROELÉCTRICA | EB8: HIDROELÉCTRICA | EC8: HIDROELÉCTRICA | ED8: EÓLICA | EE8: EÓLICA | EF8: SOLAR | EG8: EÓLICA | EH8: EÓLICA | EI8: EÓLICA | EJ8: EÓLICA | EK8: HIDROELÉCTRICA | EL8: HIDROELÉCTRICA | EM8: HIDROELÉCTRICA | EN8: HIDROELÉCTRICA | EO8: HIDROELÉCTRICA | EP8: HIDROELÉCTRICA | EQ8: EÓLICA | ER8: SOLAR | ES8: SOLAR | ET8: SOLAR | EU8: HIDROELÉCTRICA | EV8: EÓLICA | EW8: EÓLICA | EX8: SOLAR | EY8: SOLAR | EZ8: HIDROELÉCTRICA | FA8: HIDROELÉCTRICA | FB8: TERMOELÉCTRICA | FC8: TERMOELÉCTRICA | FD8: TERMOELÉCTRICA | FE8: TERMOELÉCTRICA | FF8: TERMOELÉCTRICA | FG8: TERMOELÉCTRICA | FH8: TERMOELÉCTRICA | FI8: TERMOELÉCTRICA | FL8: HIDROELÉCTRICA | FM8: HIDROELÉCTRICA | FN8: HIDROELÉCTRICA | FO8: HIDROELÉCTRICA | FP8: TERMOELÉCTRICA | FQ8: TERMOELÉCTRICA | FR8: HIDROELÉCTRICA | FS8: HIDROELÉCTRICA
C9: HYDRO GLOBAL PERÚ S.A.C. | D9: ELECTROPERU | E9: ELECTROPERU | F9: ELECTROPERU | G9: ELECTROPERU | H9: ORAZUL ENERGY PERÚ | I9: ORAZUL ENERGY PERÚ | J9: TERMOSELVA | K9: TERMOSELVA | L9: KALLPA GENERACION S.A. | M9: KALLPA GENERACION S.A. | N9: KALLPA GENERACION S.A. | O9: KALLPA GENERACION S.A. | P9: KALLPA GENERACION S.A. | Q9: KALLPA GENERACION S.A. | R9: KALLPA GENERACION S.A. | S9: KALLPA GENERACION S.A. | T9: SHOUGESA | U9: SHOUGESA | V9: SHOUGESA | W9: SHOUGESA | X9: EGEMSA | Y9: EGESUR | Z9: EGESUR | AA9: EGESUR | AB9: EGASA | AC9: EGASA | AD9: EGASA | AE9: EGASA | AF9: EGASA | AG9: EGASA | AH9: EGASA | AI9: SAN GABAN | AJ9: CELEPSA | AK9: MINERA CERRO VERDE | AL9: PLANTA DE RESERVA FRIA DE GENERACION DE ETEN S.A. | AM9: PLANTA DE RESERVA FRIA DE GENERACION DE ETEN S.A. | AN9: EMPRESA DE GENERACION HUALLAGA | AO9: EMPRESA DE GENERACION HUALLAGA | AP9: LA VIRGEN | AQ9: CHINANGO S.A.C. | AR9: CHINANGO S.A.C. | AS9: HIDROELECTRICA HUANCHOR S.A.C. | AT9: CELEPSA RENOVABLES S.R.L. | AU9: INLAND ENERGY SAC | AV9: FENIX POWER PERÚ | AW9: FENIX POWER PERÚ | AX9: FENIX POWER PERÚ | AY9: STATKRAFT S.A | AZ9: STATKRAFT S.A | BA9: STATKRAFT S.A | BB9: STATKRAFT S.A | BC9: STATKRAFT S.A | BD9: STATKRAFT S.A | BE9: STATKRAFT S.A | BF9: STATKRAFT S.A | BG9: CENTRALES SANTA ROSA S.A.C. | BH9: CENTRALES SANTA ROSA S.A.C. | BI9: EMPRESA DE GENERACION HUANZA | BJ9: ENEL GENERACION PIURA S.A. | BK9: ENEL GENERACION PIURA S.A. | BL9: ENEL GENERACION PIURA S.A. | BM9: ENGIE | BN9: ENGIE | BO9: ENGIE | BP9: ENGIE | BQ9: ENGIE | BR9: ENGIE | BS9: ENGIE | BT9: ENGIE | BU9: ENGIE | BV9: ENGIE | BW9: ENGIE | BX9: ENGIE | BY9: ENGIE | BZ9: ENGIE | CA9: INFRAESTRUCTURAS Y ENERGIAS DEL PERU S.A.C. | CB9: INFRAESTRUCTURAS Y ENERGIAS DEL PERU S.A.C. | CC9: INVERSIONES SHAQSHA S.A.C. | CD9: ORYGEN PERU S.A.A. | CE9: ORYGEN PERU S.A.A. | CF9: ORYGEN PERU S.A.A. | CG9: ORYGEN PERU S.A.A. | CH9: ORYGEN PERU S.A.A. | CI9: ORYGEN PERU S.A.A. | CJ9: ORYGEN PERU S.A.A. | CK9: ORYGEN PERU S.A.A. | CL9: ORYGEN PERU S.A.A. | CM9: ORYGEN PERU S.A.A. | CN9: ORYGEN PERU S.A.A. | CO9: ORYGEN PERU S.A.A. | CP9: SAMAY I S.A.C | CQ9: SAMAY I S.A.C | CR9: SAMAY I S.A.C | CS9: SAMAY I S.A.C | CT9: TERMOCHILCA S.A.C. | CU9: TERMOCHILCA S.A.C. | CV9: COLCA SOLAR S.A.C. | CW9: ENERGIA RENOVABLE DEL SUR S.A. | CX9: GR CORTARRAMA SOCIEDAD ANONIMA CERRADA | CY9: GR TARUCA SOCIEDAD ANONIMA CERRADA | CZ9: KONDU SAC | DA9: PERUANA DE INVERSIONES EN ENERGIAS RENOVABLES S.A. | DB9: ORAZUL ENERGY PERÚ | DC9: ORAZUL ENERGY PERÚ | DD9: SAN GABAN | DE9: MAJA ENERGIA S.A.C. | DF9: EMPRESA DE GENERACION ELECTRICA CANCHAYLLO SAC | DG9: EMPRESA DE GENERACION ELECTRICA SANTA ANA S.A.C. | DH9: EMPRESA ELECTRICA AGUA AZUL | DI9: EMPRESA ELECTRICA RIO DOBLE | DJ9: HIDROCAÑETE S.A. | DK9: HUAURA POWER GROUP S.A. | DL9: MOQUEGUA FV S.A.C. | DM9: PANAMERICANA SOLAR SAC. | DN9: PARQUE EOLICO MARCONA S.A.C. | DO9: PARQUE EOLICO TRES HERMANAS S.A.C. | DP9: PETRAMAS | DQ9: PETRAMAS | DR9: PETRAMAS | DS9: PETRAMAS | DT9: TACNA SOLAR SAC. | DU9: ELECTRICA YANAPAMPA SAC | DV9: ANDEAN POWER S.A.C. | DW9: ASOCIACIÓN SANTA LUCIA DE CHACAS | DX9: ATRIA ENERGIA S.A.C. | DY9: EGEJUNIN | DZ9: EGEJUNIN | EA9: EGEJUNIN | EB9: EGEJUNIN | EC9: EMPRESA DE GENERACION ELECTRICA RIO BAÑOS S.A.C. | ED9: ENERGÍA EÓLICA S.A. | EE9: ENERGÍA EÓLICA S.A. | EF9: ENGIE | EG9: ENGIE | EH9: ENGIE | EI9: ENGIE | EJ9: ENGIE | EK9: GENERACIÓN ANDINA S.A.C. | EL9: GENERACIÓN ANDINA S.A.C. | EM9: GENERADORA DE ENERGÍA DEL PERÚ | EN9: GENERADORA DE ENERGÍA DEL PERÚ | EO9: GENERADORA DE ENERGÍA DEL PERÚ | EP9: GENERADORA DE ENERGÍA DEL PERÚ | EQ9: GR PAINO SOCIEDAD ANONIMA CERRADA | ER9: JOYA SOLAR S.A.C. | ES9: MAJES ARCUS S.A.C. | ET9: ORYGEN PERU S.A.A. | EU9: ORYGEN PERU S.A.A. | EV9: ORYGEN PERU S.A.A. | EW9: ORYGEN PERU S.A.A. | EX9: ORYGEN PERU S.A.A. | EY9: REPARTICIÓN ARCUS S.A.C. | EZ9: SINERSA | FA9: SINERSA | FB9: BIOENERGIA DEL CHIRA S.A. | FC9: GM OPERACIONES S.A.C. | FD9: GM OPERACIONES S.A.C. | FE9: AGRO INDUSTRIAL PARAMONGA S.A. | FF9: AGROAURORA S.A.C. | FG9: AGROINDUSTRIAS SAN JACINTO S.A.A. | FH9: SDF ENERGIA SAC | FI9: SDF ENERGIA SAC | FL9: UNACEM PERU S.A. | FM9: ELECTRO ORIENTE | FN9: AGUAS Y ENERGIA PERU | FO9: ELECTRO ZAÑA S.A.C. | FP9: ELECTRONOROESTE S.A. | FQ9: SDE PIURA | FR9: SINERSA | FS9: SINERSA
C10: SAN GABAN III | D10: MANTARO | E10: RESTITUCION | F10: TUMBES MAK 1 | G10: TUMBES MAK 2 | H10: CARHUAQUERO | I10: CAÑON DEL PATO | J10: AGUAYTIA TG1 | K10: AGUAYTIA TG2 | L10: KALLPA TG1 | M10: KALLPA TG2 | N10: KALLPA TG3 | O10: KALLPA TV | P10: LFLORES TG1 | Q10: LFLORES TV | R10: CERRO DEL AGUILA | S10: CERRODELAGUILAG4 | T10: SHOUGESA TV1 | U10: SHOUGESA TV2 | V10: SHOUGESA TV3 | W10: SHOUGESA CUMMINS | X10: MACHUPICCHU | Y10: ARICOTA 1 | Z10: ARICOTA 2 | AA10: INDEPENDENCIA | AB10: CHARCANI I,II,III | AC10: CHARCANI IV | AD10: CHARCANI V | AE10: CHARCANI VI | AF10: CHILINA TG | AG10: MOLLENDO 1, 2, 3 | AH10: CHILINA (SULZ 1,2) | AI10: SAN GABAN II | AJ10: PLATANAL | AK10: RECKA | AL10: RF ETEN TG1 | AM10: RF ETEN TG2 | AN10: CHAGLLA GP1 | AO10: CHAGLLA | AP10: LA VIRGEN | AQ10: CHIMAY | AR10: YANANGO | AS10: HUANCHOR | AT10: MARAÑON | AU10: STA TERESA | AV10: FENIX GT11 | AW10: FENIX GT12 | AX10: FENIX TV10 | AY10: YAUPI | AZ10: OROYA | BA10: PACHACHACA | BB10: MALPASO | BC10: CAHUA | BD10: ARCATA | BE10: GALLITO CIEGO | BF10: CHEVES | BG10: SANTA ROSA 1 | BH10: SANTA ROSA 2 | BI10: HUANZA | BJ10: MALACAS2 TG4 | BK10: MALACAS3 TG 5 | BL10: MALACAS1 TG6 | BM10: RF ILO2 TG1 | BN10: RF ILO2 TG2 | BO10: RF ILO2 TG3 | BP10: YUNCAN | BQ10: CHILCA1 TG1 | BR10: CHILCA1 TG2 | BS10: CHILCA1 TG3 | BT10: CHILCA-TV | BU10: CHILCA2 TG41 | BV10: CHILCA2-TV | BW10: CTNEPI_TG41 | BX10: CTNEPI_TG42 | BY10: CTNEPI_TG43 | BZ10: QUITARACSA | CA10: RF PTO MALDONADO | CB10: RF PUCALLPA | CC10: PARIAC | CD10: HUINCO | CE10: MATUCANA | CF10: MOYOPAMPA | CG10: CALLAHUANCA | CH10: HUAMPANI | CI10: STA ROSA WEST TG7 | CJ10: UTI_5 | CK10: UTI_6 | CL10: VENTANILLA 3 | CM10: VENTANILLA 4 | CN10: VENTANILLA TV | CO10: STAROSA TG8 | CP10: PTO_BRVO TG1 | CQ10: PTO_BRVO TG2 | CR10: PTO_BRVO TG3 | CS10: PTO_BRVO TG4 | CT10: OLLEROS TG1 | CU10: OLLEROS TV | CV10: CS YARUCAYA | CW10: SAN JUAN | CX10: MATARANI | CY10: DUNA | CZ10: CARHUAQUERO (CS) | DA10: MANTA I | DB10: CARHUAQUERO4 | DC10: CAÑA BRAVA | DD10: TUPURI | DE10: RONCADOR | DF10: CANCHAYLLO | DG10: RENOVANDESH1 | DH10: POTRERO | DI10: PIZARRAS | DJ10: NIMPERIAL | DK10: YARUCAYA | DL10: MOQUEGUA-SOLAR | DM10: PANAMERICANA-SOLAR | DN10: PQE-EOLICO-MARCONA | DO10: PQE-EOLICO-3-HERMANAS | DP10: HUAYCOLORO | DQ10: CALLAO | DR10: DONA_CATALINA | DS10: LAGRINGAV | DT10: TACNA-SOLAR | DU10: YANAPAMPA | DV10: CARHUAC | DW10: HUALLIN | DX10: PURMACANA | DY10: HUASAHUASI | DZ10: STACRUZ_1_2 | EA10: RUNATULLO_II | EB10: RUNATULLO_III | EC10: RUCUY | ED10: PQE-EOLICO-TALARA | EE10: PQE-EOLICO-CUPISNIQUE | EF10: INTIPAMPA | EG10: PUNTA LOMITAS-BL1 | EH10: PUNTA LOMITAS-BL2 | EI10: PUN LOMITAS_EXP-BL1 | EJ10: PUN LOMITAS_EXP-BL2 | EK10: 8AGOSTO | EL10: EL CARMEN | EM10: LA JOYA | EN10: ANGEL_I | EO10: ANGEL_II | EP10: ANGEL_III | EQ10: HUAMBOS | ER10: SAN MARTIN SOLAR | ES10: MAJES | ET10: RUBI | EU10: CH_HER1 | EV10: WAYRA-I | EW10: WAYRA EXTENSION | EX10: CLEMESI | EY10: REPARTICION | EZ10: POECHOS2 | FA10: CHANCAY | FB10: CANA BRAVA | FC10: REFINERIA TALARA TV1 | FD10: REFINERÍA TALARA TV2 | FE10: PARAMONGA | FF10: MAPLE | FG10: SAN_JACINTO | FH10: OQUENDO TG1 | FI10: OQUENDO TV1 | FJ10: MW | FL10: CARPAPATA | FM10: CENTRALES ELOR | FN10: PIAS1 | FO10: ZANA | FP10: TABLAZO | FQ10: TALLANCA | FR10: CURUMUY | FS10: POECHOS1 | FT10: MW
A11: 04/07/2025 | B11: 00:30 | C11: 144.6 | D11: 596.7 | E11: 201.81 | H11: 60.1 | I11: 87.2 | L11: 188.9 | M11: 201.8 | N11: 201.4 | O11: 288 | P11: 216.8 | Q11: 111.7 | R11: 451.1 | S11: 4.3 | X11: 127.6 | Y11: 7.5 | Z11: 5.2 | AB11: 6.8 | AC11: 12.4 | AD11: 84 | AI11: 45.3 | AJ11: 109.8 | AN11: 6.4 | AO11: 0 | AP11: 41.1 | AQ11: 55.8 | AR11: 27.5 | AS11: 18 | AT11: 19.7 | AU11: 70.1 | AV11: 182.559 | AW11: 182.833 | AX11: 184.041 | AY11: 86.2 | AZ11: 6.3 | BA11: 1.5 | BB11: 33.7 | BC11: 30.4 | BD11: 3.8 | BE11: 0 | BF11: 40.6 | BI11: 14.5 | BL11: 0 | BP11: 65.7 | BQ11: 177.9 | BR11: 176.1 | BS11: 200 | BT11: 274.8 | BZ11: 0 | CC11: 1.2 | CD11: 91.1 | CE11: 84.3 | CF11: 64.5 | CG11: 70.6 | CH11: 29.3 | CL11: 146.4 | CM11: 148.8 | CN11: 150.6 | CT11: 147.5 | CU11: 79.4 | CV11: 0 | CW11: 0.1 | CX11: 0 | CY11: 15.6 | CZ11: 0 | DA11: 11.3 | DB11: 9.9 | DC11: 4.9 | DD11: 0.4 | DE11: 2.7 | DF11: 2.6 | DG11: 19.9 | DH11: 13.2 | DI11: 8.9 | DJ11: 3.3 | DK11: 18.5 | DL11: 0 | DM11: 0 | DN11: 0 | DO11: 0 | DP11: 4.5 | DQ11: 2.2 | DR11: 1 | DS11: 2.7 | DT11: 0 | DU11: 2.2 | DV11: 14.4 | DW11: 1.4 | DX11: 0 | DY11: 8.6 | DZ11: 3.9 | EA11: 5.1 | EB11: 7.2 | EC11: 13.6 | ED11: 8.1 | EE11: 3.9 | EF11: 0 | EG11: 0 | EH11: 0 | EI11: 0 | EJ11: 0 | EK11: 10.5 | EL11: 4 | EM11: 7.6 | EN11: 4.9 | EO11: 5.4 | EP11: 5.4 | EQ11: 10.7 | ER11: 0 | ES11: 0 | ET11: 0 | EU11: 0.6 | EV11: 0 | EW11: 4.9 | EX11: 0 | EY11: 0 | EZ11: 10 | FA11: 18 | FB11: 9.3 | FC11: 42.62 | FD11: 35.15 | FE11: 15.2 | FG11: 7.3 | FJ11: 6447.913 | FL11: 23.00829 | FM11: 7.881 | FN11: 0 | FO11: 9.4 | FP11: 27.07262 | FQ11: 18.92109 | FR11: 11.6 | FS11: 16 | FT11: 113.883
A12: 04/07/2025 | B12: 01:00 | C12: 138.2 | D12: 591.08 | E12: 205.28 | H12: 49.2 | I12: 85.1 | L12: 169.5 | M12: 170 | N12: 170 | O12: 264.8 | P12: 217.3 | Q12: 111.4 | R12: 433.7 | S12: 4.1 | X12: 129.8 | Y12: 6.9 | Z12: 5.2 | AB12: 6.9 | AC12: 11.7 | AD12: 38 | AI12: 43.8 | AJ12: 108.1 | AN12: 6.5 | AO12: 0 | AP12: 39.8 | AQ12: 43.9 | AR12: 27.3 | AS12: 17.8 | AT12: 19.7 | AU12: 72.5 | AV12: 178.941 | AW12: 179.439 | AX12: 183.254 | AY12: 74.8 | AZ12: 6.3 | BA12: 1.5 | BB12: 32.6 | BC12: 29 | BD12: 3.8 | BE12: 0 | BF12: 20 | BI12: 13.2 | BL12: 0 | BP12: 54 | BQ12: 177.6 | BR12: 175.6 | BS12: 200 | BT12: 274.7 | BZ12: 0 | CC12: 1.2 | CD12: 81 | CE12: 80.9 | CF12: 63.3 | CG12: 70.3 | CH12: 28.8 | CL12: 146.3 | CM12: 149.2 | CN12: 150.3 | CT12: 216.8 | CU12: 103 | CV12: 0 | CW12: 0.1 | CX12: 0 | CY12: 14 | CZ12: 0 | DA12: 11.3 | DB12: 10 | DC12: 4.8 | DD12: 0.4 | DE12: 2.7 | DF12: 2.6 | DG12: 19.6 | DH12: 13.2 | DI12: 8.9 | DJ12: 3.3 | DK12: 18.5 | DL12: 0 | DM12: 0 | DN12: 0.2 | DO12: 0.3 | DP12: 4.5 | DQ12: 2.2 | DR12: 1 | DS12: 2.7 | DT12: 0 | DU12: 2.2 | DV12: 3.4 | DW12: 1.4 | DX12: 0 | DY12: 8.5 | DZ12: 3.8 | EA12: 4.8 | EB12: 7 | EC12: 13.1 | ED12: 5.2 | EE12: 4.9 | EF12: 0 | EG12: 0 | EH12: 0 | EI12: 0 | EJ12: 0 | EK12: 10.5 | EL12: 4 | EM12: 7.7 | EN12: 5.2 | EO12: 5.4 | EP12: 5.4 | EQ12: 11.1 | ER12: 0 | ES12: 0 | ET12: 0 | EU12: 0.6 | EV12: 0 | EW12: 9.2 | EX12: 0 | EY12: 0 | EZ12: 9.9 | FA12: 17.8 | FB12: 9.3 | FC12: 42.59 | FD12: 36.06 | FE12: 15.3 | FG12: 7.5 | FJ12: 6255.544 | FL12: 23.32322 | FM12: 7.883 | FN12: 0 | FO12: 9.4 | FP12: 27.02249 | FQ12: 18.92102 | FR12: 11.6 | FS12: 16 | FT12: 114.14973
A13: 04/07/2025 | B13: 01:30 | C13: 143.5 | D13: 598.22 | E13: 200.99 | H13: 50 | I13: 85.9 | L13: 167.4 | M13: 167.8 | N13: 168 | O13: 254.9 | P13: 215.5 | Q13: 111.8 | R13: 351.1 | S13: 4.3 | X13: 135.6 | Y13: 7.3 | Z13: 5.3 | AB13: 6.8 | AC13: 12.1 | AD13: 39.6 | AI13: 45 | AJ13: 107.9 | AN13: 6.5 | AO13: 0 | AP13: 43.2 | AQ13: 45.1 | AR13: 27.4 | AS13: 18 | AT13: 19.7 | AU13: 73.5 | AV13: 182.507 | AW13: 182.832 | AX13: 184.43 | AY13: 76.4 | AZ13: 6.3 | BA13: 1.6 | BB13: 33.2 | BC13: 29.5 | BD13: 3.8 | BE13: 0 | BF13: 21.5 | BI13: 14.3 | BL13: 0 | BP13: 55.3 | BQ13: 178.2 | BR13: 176.5 | BS13: 200 | BT13: 274.6 | BZ13: 0 | CC13: 1.2 | CD13: 75.2 | CE13: 84 | CF13: 64.4 | CG13: 70.7 | CH13: 29.1 | CL13: 147.1 | CM13: 149.6 | CN13: 150.8 | CT13: 216.2 | CU13: 103.6 | CV13: 0 | CW13: 0.1 | CX13: 0 | CY13: 15.1 | CZ13: 0 | DA13: 11.4 | DB13: 9.9 | DC13: 3.9 | DD13: 0.4 | DE13: 2.7 | DF13: 2.6 | DG13: 19.8 | DH13: 13 | DI13: 8.9 | DJ13: 3.3 | DK13: 18.5 | DL13: 0 | DM13: 0 | DN13: 0 | DO13: 0 | DP13: 4.5 | DQ13: 2.2 | DR13: 1 | DS13: 2.7 | DT13: 0 | DU13: 2.1 | DV13: 4.4 | DW13: 1.4 | DX13: 0 | DY13: 8.6 | DZ13: 3.8 | EA13: 5 | EB13: 7.2 | EC13: 13.2 | ED13: 4.8 | EE13: 5.5 | EF13: 0 | EG13: 0 | EH13: 0 | EI13: 0 | EJ13: 0 | EK13: 10.5 | EL13: 4 | EM13: 7.8 | EN13: 5.6 | EO13: 5.4 | EP13: 5.4 | EQ13: 12.7 | ER13: 0 | ES13: 0 | ET13: 0 | EU13: 0.6 | EV13: 0 | EW13: 11.7 | EX13: 0 | EY13: 0 | EZ13: 10 | FA13: 17.9 | FB13: 9.6 | FC13: 42.68 | FD13: 35.21 | FE13: 15.4 | FG13: 7.3 | FJ13: 6203.069 | FL13: 23.41913 | FM13: 7.882 | FN13: 0 | FO13: 9.5 | FP13: 26.90449 | FQ13: 18.92145 | FR13: 11.7 | FS13: 16.1 | FT13: 114.42707
A14: 04/07/2025 | B14: 02:00 | C14: 75.4 | D14: 603.44 | E14: 203.76 | H14: 50.4 | I14: 87.4 | L14: 165.6 | M14: 166.4 | N14: 166.2 | O14: 265.6 | P14: 217.7 | Q14: 111.8 | R14: 253.1 | S14: 4.4 | X14: 139.2 | Y14: 7.8 | Z14: 5.5 | AB14: 6.8 | AC14: 12.2 | AD14: 41.6 | AI14: 43.8 | AJ14: 107.7 | AN14: 6.5 | AO14: 0 | AP14: 43.5 | AQ14: 45.8 | AR14: 30.3 | AS14: 18 | AT14: 19.7 | AU14: 71.8 | AV14: 185.014 | AW14: 185.329 | AX14: 183.989 | AY14: 79.8 | AZ14: 6.4 | BA14: 1.5 | BB14: 33.9 | BC14: 30 | BD14: 3.8 | BE14: 0 | BF14: 22.9 | BI14: 15.5 | BL14: 0 | BP14: 55.6 | BQ14: 178.7 | BR14: 176.9 | BS14: 200 | BT14: 274.7 | BZ14: 0 | CC14: 1.2 | CD14: 76.3 | CE14: 86.5 | CF14: 65.7 | CG14: 69.1 | CH14: 29.4 | CL14: 147.5 | CM14: 150.2 | CN14: 151.8 | CT14: 216.1 | CU14: 103.7 | CV14: 0 | CW14: 0.1 | CX14: 0 | CY14: 15.7 | CZ14: 0 | DA14: 11.5 | DB14: 10 | DC14: 4.1 | DD14: 0.4 | DE14: 2.4 | DF14: 2.6 | DG14: 20.3 | DH14: 13 | DI14: 9 | DJ14: 3.4 | DK14: 18.5 | DL14: 0 | DM14: 0 | DN14: 0 | DO14: 0 | DP14: 4.5 | DQ14: 2.2 | DR14: 1 | DS14: 2.7 | DT14: 0 | DU14: 2.1 | DV14: 4.8 | DW14: 1.3 | DX14: 0 | DY14: 8.6 | DZ14: 3.9 | EA14: 5.3 | EB14: 7.4 | EC14: 13.4 | ED14: 6.9 | EE14: 3.2 | EF14: 0 | EG14: 0 | EH14: 0 | EI14: 0 | EJ14: 0 | EK14: 10.5 | EL14: 4 | EM14: 7.8 | EN14: 5.5 | EO14: 5.4 | EP14: 5.4 | EQ14: 12.6 | ER14: 0 | ES14: 0 | ET14: 0 | EU14: 0.6 | EV14: 0 | EW14: 8.7 | EX14: 0 | EY14: 0 | EZ14: 10 | FA14: 17.9 | FB14: 9.4 | FC14: 42.63 | FD14: 35.18 | FE14: 15.3 | FG14: 7.4 | FJ14: 6079.542 | FL14: 23.48189 | FM14: 7.882 | FN14: 0 | FO14: 9.6 | FP14: 26.91826 | FQ14: 18.92132 | FR14: 11.8 | FS14: 16 | FT14: 114.60347
A15: 04/07/2025 | B15: 02:30 | C15: 66.6 | D15: 598.57 | E15: 201.81 | H15: 50 | I15: 86 | L15: 174.6 | M15: 174.5 | N15: 175 | O15: 265.3 | P15: 217.2 | Q15: 111.6 | R15: 248.1 | S15: 4.3 | X15: 134.5 | Y15: 7.4 | Z15: 5.4 | AB15: 6.8 | AC15: 12.1 | AD15: 40.2 | AI15: 42.3 | AJ15: 108 | AN15: 6.5 | AO15: 0 | AP15: 43.5 | AQ15: 73.1 | AR15: 29.6 | AS15: 18.2 | AT15: 19.7 | AU15: 73.4 | AV15: 181.963 | AW15: 182.169 | AX15: 184.085 | AY15: 77.6 | AZ15: 6.3 | BA15: 1.5 | BB15: 33.4 | BC15: 29.7 | BD15: 3.8 | BE15: 0 | BF15: 21.5 | BI15: 14.7 | BL15: 0 | BP15: 55.3 | BQ15: 178.3 | BR15: 176.1 | BS15: 200 | BT15: 275 | BZ15: 0 | CC15: 1.2 | CD15: 111.3 | CE15: 83.9 | CF15: 64.8 | CG15: 68.7 | CH15: 28.9 | CL15: 146.5 | CM15: 149.3 | CN15: 150.3 | CT15: 216.4 | CU15: 103.7 | CV15: 0 | CW15: 0.1 | CX15: 0 | CY15: 14.3 | CZ15: 0 | DA15: 11.5 | DB15: 9.9 | DC15: 4 | DD15: 0.4 | DE15: 2.4 | DF15: 2.6 | DG15: 20 | DH15: 13 | DI15: 8.9 | DJ15: 3.4 | DK15: 18.5 | DL15: 0 | DM15: 0 | DN15: 0 | DO15: 0 | DP15: 4.5 | DQ15: 2.2 | DR15: 1 | DS15: 2.7 | DT15: 0 | DU15: 2.1 | DV15: 5.2 | DW15: 1.3 | DX15: 0 | DY15: 8.6 | DZ15: 3.8 | EA15: 5.2 | EB15: 7.3 | EC15: 13.6 | ED15: 6.6 | EE15: 1.3 | EF15: 0 | EG15: 0 | EH15: 0 | EI15: 0 | EJ15: 0 | EK15: 10.5 | EL15: 4.1 | EM15: 7.8 | EN15: 5.5 | EO15: 5.4 | EP15: 5.4 | EQ15: 10.1 | ER15: 0 | ES15: 0 | ET15: 0 | EU15: 0.6 | EV15: 0 | EW15: 3.3 | EX15: 0 | EY15: 0 | EZ15: 10 | FA15: 18 | FB15: 9.5 | FC15: 42.68 | FD15: 35.17 | FE15: 15.2 | FG15: 7.1 | FJ15: 6105.447 | FL15: 23.50843 | FM15: 7.883 | FN15: 0 | FO15: 9.4 | FP15: 26.90302 | FQ15: 18.92128 | FR15: 11.6 | FS15: 16.2 | FT15: 114.41573
A16: 04/07/2025 | B16: 03:00 | C16: 71.1 | D16: 601.03 | E16: 204.31 | H16: 50.7 | I16: 87.9 | L16: 169.9 | M16: 169.4 | N16: 170.7 | O16: 262.5 | P16: 214.2 | Q16: 111.9 | R16: 246.5 | S16: 4.3 | X16: 137.1 | Y16: 7.7 | Z16: 5.5 | AB16: 6.8 | AC16: 12.1 | AD16: 40.6 | AI16: 43.4 | AJ16: 109 | AN16: 6.5 | AO16: 0 | AP16: 43.5 | AQ16: 65.9 | AR16: 30.9 | AS16: 18.2 | AT16: 19.7 | AU16: 72.6 | AV16: 184.458 | AW16: 185.347 | AX16: 183.821 | AY16: 78.5 | AZ16: 6.3 | BA16: 1.5 | BB16: 34 | BC16: 30.2 | BD16: 3.8 | BE16: 0 | BF16: 23.8 | BI16: 15.2 | BL16: 0 | BP16: 55.9 | BQ16: 177.6 | BR16: 175.7 | BS16: 200 | BT16: 275.7 | BZ16: 0 | CC16: 1.2 | CD16: 99.7 | CE16: 86.7 | CF16: 65.2 | CG16: 68.7 | CH16: 29.2 | CL16: 146.4 | CM16: 149.5 | CN16: 150.1 | CT16: 216.4 | CU16: 103.8 | CV16: 0 | CW16: 0.2 | CX16: 0 | CY16: 11.4 | CZ16: 0 | DA16: 11.5 | DB16: 9.9 | DC16: 4 | DD16: 0.4 | DE16: 2.5 | DF16: 2.6 | DG16: 20.3 | DH16: 13.2 | DI16: 8.9 | DJ16: 3.4 | DK16: 18.5 | DL16: 0 | DM16: 0 | DN16: 0.5 | DO16: 1 | DP16: 4.5 | DQ16: 2.2 | DR16: 1 | DS16: 2.7 | DT16: 0 | DU16: 2.1 | DV16: 5.8 | DW16: 1.3 | DX16: 0 | DY16: 8.5 | DZ16: 3.9 | EA16: 5.3 | EB16: 7.4 | EC16: 13.6 | ED16: 4.4 | EE16: 0.2 | EF16: 0 | EG16: 0 | EH16: 0 | EI16: 0 | EJ16: 0 | EK16: 10.5 | EL16: 3.7 | EM16: 7.8 | EN16: 5.4 | EO16: 5.4 | EP16: 5.4 | EQ16: 8 | ER16: 0 | ES16: 0 | ET16: 0 | EU16: 0.6 | EV16: 0 | EW16: 2.6 | EX16: 0 | EY16: 0 | EZ16: 10 | FA16: 18 | FB16: 9.6 | FC16: 42.68 | FD16: 35.18 | FE16: 15.3 | FG16: 7.5 | FJ16: 6091.526 | FL16: 23.56228 | FM16: 7.882 | FN16: 0 | FO16: 9.4 | FP16: 26.85076 | FQ16: 18.92153 | FR16: 11.6 | FS16: 16 | FT16: 114.21657
A17: 04/07/2025 | B17: 03:30 | C17: 64 | D17: 598.91 | E17: 200.89 | H17: 50.4 | I17: 86.6 | L17: 189.8 | M17: 195.1 | N17: 194.6 | O17: 275.3 | P17: 218.2 | Q17: 112.3 | R17: 249.4 | S17: 4.3 | X17: 135.1 | Y17: 7.2 | Z17: 5.3 | AB17: 6.9 | AC17: 12 | AD17: 39.4 | AI17: 42.4 | AJ17: 108.1 | AN17: 6.5 | AO17: 0 | AP17: 43.5 | AQ17: 0 | AR17: 28.7 | AS17: 18 | AT17: 19.7 | AU17: 74.3 | AV17: 181.807 | AW17: 182.288 | AX17: 184.432 | AY17: 77.2 | AZ17: 6.4 | BA17: 1.6 | BB17: 33.1 | BC17: 29.2 | BD17: 3.8 | BE17: 0 | BF17: 21.5 | BI17: 14.6 | BL17: 0 | BP17: 55.3 | BQ17: 178.7 | BR17: 176.6 | BS17: 200 | BT17: 275.4 | BZ17: 0 | CC17: 1.2 | CD17: 70 | CE17: 74.5 | CF17: 64.5 | CG17: 67.8 | CH17: 28.8 | CL17: 146.7 | CM17: 149.9 | CN17: 150.8 | CT17: 216.3 | CU17: 103.7 | CV17: 0 | CW17: 0.4 | CX17: 0 | CY17: 11.1 | CZ17: 0 | DA17: 11.4 | DB17: 9.9 | DC17: 4 | DD17: 0.4 | DE17: 2.5 | DF17: 2.6 | DG17: 20 | DH17: 13.3 | DI17: 8.9 | DJ17: 3.4 | DK17: 18.5 | DL17: 0 | DM17: 0 | DN17: 0.3 | DO17: 1.5 | DP17: 4.5 | DQ17: 1.7 | DR17: 1 | DS17: 2.7 | DT17: 0 | DU17: 2.1 | DV17: 5.8 | DW17: 1.3 | DX17: 0 | DY17: 8.6 | DZ17: 3.8 | EA17: 5 | EB17: 7.2 | EC17: 13.6 | ED17: 7.7 | EE17: 0 | EF17: 0 | EG17: 0 | EH17: 0 | EI17: 0 | EJ17: 0 | EK17: 10.5 | EL17: 3.7 | EM17: 7.8 | EN17: 5.4 | EO17: 5.4 | EP17: 5.4 | EQ17: 7.8 | ER17: 0 | ES17: 0 | ET17: 0 | EU17: 0.6 | EV17: 0 | EW17: 4.7 | EX17: 0 | EY17: 0 | EZ17: 10 | FA17: 18 | FB17: 9.5 | FC17: 42.7 | FD17: 35.02 | FE17: 15.3 | FG17: 7.6 | FJ17: 6045.647 | FL17: 23.58276 | FM17: 7.882 | FN17: 0 | FO17: 9.4 | FP17: 26.95729 | FQ17: 18.92138 | FR17: 11.5 | FS17: 16.1 | FT17: 114.34343
A18: 04/07/2025 | B18: 04:00 | C18: 71 | D18: 601.06 | E18: 203.41 | H18: 60.7 | I18: 88.8 | L18: 175.3 | M18: 175.7 | N18: 175.6 | O18: 274.5 | P18: 215.8 | Q18: 112 | R18: 249.2 | S18: 4.3 | X18: 139.2 | Y18: 7.6 | Z18: 5.1 | AB18: 6.8 | AC18: 12 | AD18: 41.1 | AI18: 43.2 | AJ18: 107.6 | AN18: 6.4 | AO18: 0 | AP18: 43.9 | AQ18: 0 | AR18: 30.8 | AS18: 18 | AT18: 19.7 | AU18: 74.1 | AV18: 185.802 | AW18: 186.197 | AX18: 183.215 | AY18: 78.3 | AZ18: 6.4 | BA18: 1.5 | BB18: 34.1 | BC18: 30 | BD18: 3.8 | BE18: 0 | BF18: 22.5 | BI18: 15.4 | BL18: 0 | BP18: 56.3 | BQ18: 178.8 | BR18: 176.8 | BS18: 200 | BT18: 275.2 | BZ18: 0 | CC18: 1.2 | CD18: 68.6 | CE18: 71.8 | CF18: 65.3 | CG18: 67.9 | CH18: 29.2 | CL18: 147 | CM18: 150 | CN18: 151.4 | CT18: 216.3 | CU18: 103.7 | CV18: 0 | CW18: 0 | CX18: 0 | CY18: 10.6 | CZ18: 0 | DA18: 11.6 | DB18: 9.9 | DC18: 4.8 | DD18: 0.4 | DE18: 2.5 | DF18: 2.6 | DG18: 20.3 | DH18: 13.6 | DI18: 8.9 | DJ18: 3.4 | DK18: 18.5 | DL18: 0 | DM18: 0 | DN18: 0 | DO18: 0 | DP18: 4.5 | DQ18: 2.2 | DR18: 1 | DS18: 2.7 | DT18: 0 | DU18: 2.1 | DV18: 5.8 | DW18: 1.3 | DX18: 0 | DY18: 8.5 | DZ18: 3.8 | EA18: 5.2 | EB18: 7.3 | EC18: 13.6 | ED18: 10.2 | EE18: 2.1 | EF18: 0 | EG18: 0 | EH18: 0 | EI18: 0 | EJ18: 0 | EK18: 10.5 | EL18: 3.7 | EM18: 7.8 | EN18: 5.4 | EO18: 5.4 | EP18: 5.4 | EQ18: 5.7 | ER18: 0 | ES18: 0 | ET18: 0 | EU18: 0.6 | EV18: 0 | EW18: 4.5 | EX18: 0 | EY18: 0 | EZ18: 10 | FA18: 18 | FB18: 9.4 | FC18: 42.83 | FD18: 35.25 | FE18: 15.3 | FG18: 8 | FJ18: 6034.764 | FL18: 23.57874 | FM18: 7.881 | FN18: 0 | FO18: 9.5 | FP18: 26.8716 | FQ18: 18.92143 | FR18: 11.8 | FS18: 16.1 | FT18: 114.65277
A19: 04/07/2025 | B19: 04:30 | C19: 71.8 | D19: 600.35 | E19: 202.67 | H19: 60.5 | I19: 88.6 | L19: 188.8 | M19: 188.8 | N19: 189.3 | O19: 283.3 | P19: 218.4 | Q19: 111.8 | R19: 248.8 | S19: 4.3 | X19: 138.8 | Y19: 7.6 | Z19: 5.2 | AB19: 6.8 | AC19: 12 | AD19: 40.2 | AI19: 42.9 | AJ19: 108.2 | AN19: 6.5 | AO19: 0 | AP19: 44 | AQ19: 0 | AR19: 30.6 | AS19: 18 | AT19: 19.7 | AU19: 70.5 | AV19: 183.771 | AW19: 183.945 | AX19: 184.112 | AY19: 78 | AZ19: 6.3 | BA19: 1.5 | BB19: 33.5 | BC19: 29.8 | BD19: 3.8 | BE19: 0 | BF19: 21.7 | BI19: 15.1 | BL19: 0 | BP19: 55.5 | BQ19: 178.2 | BR19: 176 | BS19: 200 | BT19: 274.6 | BZ19: 0 | CC19: 1.2 | CD19: 68.2 | CE19: 72.2 | CF19: 65.1 | CG19: 67.9 | CH19: 29.1 | CL19: 146.7 | CM19: 149.3 | CN19: 150.6 | CT19: 216.3 | CU19: 103.7 | CV19: 0 | CW19: 0 | CX19: 0 | CY19: 10.4 | CZ19: 0 | DA19: 11.7 | DB19: 10 | DC19: 4.8 | DD19: 0.4 | DE19: 2.5 | DF19: 2.6 | DG19: 20.2 | DH19: 13.7 | DI19: 8.9 | DJ19: 3.4 | DK19: 18.5 | DL19: 0 | DM19: 0 | DN19: 0 | DO19: 0 | DP19: 4.5 | DQ19: 2.2 | DR19: 1 | DS19: 2.7 | DT19: 0 | DU19: 2.1 | DV19: 5.8 | DW19: 1.3 | DX19: 0 | DY19: 8.6 | DZ19: 3.6 | EA19: 5.2 | EB19: 7.3 | EC19: 13.7 | ED19: 11.1 | EE19: 3.6 | EF19: 0 | EG19: 0 | EH19: 0 | EI19: 0 | EJ19: 0 | EK19: 10.5 | EL19: 3.7 | EM19: 8 | EN19: 5.4 | EO19: 5.4 | EP19: 5.4 | EQ19: 5.2 | ER19: 0 | ES19: 0 | ET19: 0 | EU19: 0.6 | EV19: 0 | EW19: 2.1 | EX19: 0 | EY19: 0 | EZ19: 10 | FA19: 18.1 | FB19: 9.5 | FC19: 42.72 | FD19: 35.13 | FE19: 15.2 | FG19: 7.6 | FJ19: 6068.898 | FL19: 23.64534 | FM19: 7.883 | FN19: 0 | FO19: 9.4 | FP19: 26.9604 | FQ19: 18.92146 | FR19: 11.7 | FS19: 16 | FT19: 114.5102
A20: 04/07/2025 | B20: 05:00 | C20: 119.2 | D20: 597.33 | E20: 201.75 | H20: 60 | I20: 89 | L20: 183.1 | M20: 183.4 | N20: 183.5 | O20: 274.7 | P20: 214.2 | Q20: 111.4 | R20: 246.3 | S20: 4.3 | X20: 135.4 | Y20: 7.1 | Z20: 5.1 | AB20: 6.8 | AC20: 11.7 | AD20: 41.2 | AI20: 42.1 | AJ20: 107.6 | AN20: 6.4 | AO20: 0 | AP20: 44 | AQ20: 0 | AR20: 29 | AS20: 18 | AT20: 19.7 | AU20: 72.3 | AV20: 180.231 | AW20: 180.814 | AX20: 183.959 | AY20: 76.9 | AZ20: 6.1 | BA20: 1.5 | BB20: 33 | BC20: 29.9 | BD20: 3.8 | BE20: 0 | BF20: 40 | BI20: 14.5 | BL20: 0 | BP20: 54.9 | BQ20: 177.9 | BR20: 175.9 | BS20: 200 | BT20: 275.4 | BZ20: 0 | CC20: 1.2 | CD20: 66.3 | CE20: 71.6 | CF20: 63 | CG20: 67.7 | CH20: 28.8 | CL20: 146 | CM20: 149.2 | CN20: 150.3 | CT20: 216.3 | CU20: 103.6 | CV20: 0 | CW20: 0 | CX20: 0 | CY20: 9.3 | CZ20: 0 | DA20: 11.7 | DB20: 10 | DC20: 4.8 | DD20: 0.4 | DE20: 2.6 | DF20: 2.6 | DG20: 19.8 | DH20: 14 | DI20: 8 | DJ20: 3.4 | DK20: 18.5 | DL20: 0 | DM20: 0 | DN20: 0 | DO20: 0 | DP20: 4.5 | DQ20: 2.2 | DR20: 1.1 | DS20: 2.7 | DT20: 0 | DU20: 2.1 | DV20: 5.8 | DW20: 1.3 | DX20: 0 | DY20: 8.6 | DZ20: 3.5 | EA20: 5.2 | EB20: 7.2 | EC20: 13.6 | ED20: 8.2 | EE20: 3.2 | EF20: 0 | EG20: 0 | EH20: 0 | EI20: 0 | EJ20: 0 | EK20: 10.5 | EL20: 3.7 | EM20: 8 | EN20: 5 | EO20: 5.4 | EP20: 5.4 | EQ20: 4.4 | ER20: 0 | ES20: 0 | ET20: 0 | EU20: 0.6 | EV20: 0 | EW20: 0.3 | EX20: 0 | EY20: 0 | EZ20: 10 | FA20: 18 | FB20: 9.6 | FC20: 42.49 | FD20: 34.92 | FE20: 15.1 | FG20: 7.4 | FJ20: 6068.494 | FL20: 23.66286 | FM20: 7.88 | FN20: 0 | FO20: 9.4 | FP20: 26.95778 | FQ20: 18.92137 | FR20: 11.8 | FS20: 16 | FT20: 114.62201
A21: 04/07/2025 | B21: 05:30 | C21: 118.6 | D21: 597.14 | E21: 201.25 | H21: 60 | I21: 90 | L21: 183.2 | M21: 183.2 | N21: 183.5 | O21: 266.8 | P21: 217.4 | Q21: 111.4 | R21: 250.1 | S21: 4.2 | X21: 133.7 | Y21: 7.1 | Z21: 5.5 | AB21: 6.8 | AC21: 12 | AD21: 41.4 | AI21: 45.2 | AJ21: 108.3 | AN21: 6.5 | AO21: 147.2 | AP21: 44 | AQ21: 0 | AR21: 28.9 | AS21: 18 | AT21: 19.7 | AU21: 72.3 | AV21: 180.759 | AW21: 181.123 | AX21: 183.841 | AY21: 76.8 | AZ21: 6.1 | BA21: 1.5 | BB21: 33.4 | BC21: 30.4 | BD21: 3.8 | BE21: 0 | BF21: 39.9 | BI21: 14.4 | BL21: 0 | BP21: 55.2 | BQ21: 178.1 | BR21: 175.8 | BS21: 200 | BT21: 274.9 | BZ21: 0 | CC21: 1.2 | CD21: 76.5 | CE21: 71.6 | CF21: 62.9 | CG21: 67.8 | CH21: 27.8 | CL21: 146.2 | CM21: 149.4 | CN21: 150 | CT21: 216.3 | CU21: 103.7 | CV21: 0 | CW21: 0 | CX21: 0 | CY21: 10.9 | CZ21: 0 | DA21: 11.6 | DB21: 9.9 | DC21: 4.8 | DD21: 0.4 | DE21: 2.6 | DF21: 2.6 | DG21: 19.8 | DH21: 14 | DI21: 8 | DJ21: 3.4 | DK21: 18.5 | DL21: 0 | DM21: 0 | DN21: 0.1 | DO21: 0 | DP21: 4.5 | DQ21: 2.2 | DR21: 1.1 | DS21: 2.7 | DT21: 0 | DU21: 2.1 | DV21: 5.8 | DW21: 1.2 | DX21: 0 | DY21: 8.6 | DZ21: 3.5 | EA21: 5.1 | EB21: 7.2 | EC21: 13.6 | ED21: 7.2 | EE21: 4.5 | EF21: 0 | EG21: 0 | EH21: 0 | EI21: 0 | EJ21: 0 | EK21: 10.5 | EL21: 3.7 | EM21: 8 | EN21: 5 | EO21: 5.4 | EP21: 5.4 | EQ21: 4.8 | ER21: 0 | ES21: 0 | ET21: 0 | EU21: 0.6 | EV21: 0 | EW21: 0 | EX21: 0 | EY21: 0 | EZ21: 10 | FA21: 18.1 | FB21: 9.7 | FC21: 42.37 | FD21: 34.81 | FE21: 15 | FG21: 7.5 | FJ21: 6229.593 | FL21: 24.17068 | FM21: 7.881 | FN21: 0 | FO21: 9.4 | FP21: 26.89368 | FQ21: 18.92156 | FR21: 11.6 | FS21: 16 | FT21: 114.86692
A22: 04/07/2025 | B22: 06:00 | C22: 115.9 | D22: 599.39 | E22: 202.47 | H22: 59.7 | I22: 88.6 | L22: 190.2 | M22: 190.2 | N22: 190.6 | O22: 275.2 | P22: 213.9 | Q22: 111.8 | R22: 250.9 | S22: 4.2 | X22: 130.8 | Y22: 7.1 | Z22: 5.3 | AB22: 6.8 | AC22: 12.6 | AD22: 39.4 | AI22: 44.6 | AJ22: 108.8 | AN22: 6.5 | AO22: 146.7 | AP22: 44 | AQ22: 0 | AR22: 30 | AS22: 18.1 | AT22: 19.7 | AU22: 70.1 | AV22: 181.085 | AW22: 181.26 | AX22: 184.754 | AY22: 77 | AZ22: 6.1 | BA22: 1.5 | BB22: 32.3 | BC22: 29.9 | BD22: 3.8 | BE22: 0 | BF22: 53 | BI22: 14.3 | BL22: 0 | BP22: 55.1 | BQ22: 178.8 | BR22: 176.8 | BS22: 200 | BT22: 275.3 | BZ22: 0 | CC22: 1.2 | CD22: 74.8 | CE22: 70.7 | CF22: 62.9 | CG22: 67.7 | CH22: 27.8 | CL22: 147 | CM22: 150.2 | CN22: 151.3 | CT22: 216.6 | CU22: 103.7 | CV22: 0 | CW22: 0 | CX22: 0 | CY22: 11.4 | CZ22: 0 | DA22: 11.5 | DB22: 9.9 | DC22: 4.9 | DD22: 0.4 | DE22: 2.7 | DF22: 2.6 | DG22: 19.8 | DH22: 14 | DI22: 8 | DJ22: 3.4 | DK22: 18.5 | DL22: 0.1 | DM22: 0 | DN22: 0 | DO22: 0 | DP22: 4.5 | DQ22: 2.2 | DR22: 1.1 | DS22: 2.7 | DT22: 0 | DU22: 2.2 | DV22: 5.8 | DW22: 1.2 | DX22: 0 | DY22: 8.5 | DZ22: 3.5 | EA22: 5.1 | EB22: 7.2 | EC22: 13.5 | ED22: 8.6 | EE22: 7.9 | EF22: 0 | EG22: 0 | EH22: 0 | EI22: 0 | EJ22: 0 | EK22: 10.5 | EL22: 3.7 | EM22: 7.9 | EN22: 5 | EO22: 5.4 | EP22: 5.4 | EQ22: 5.5 | ER22: 0 | ES22: 0 | ET22: 0 | EU22: 0.6 | EV22: 0 | EW22: 0 | EX22: 0 | EY22: 0 | EZ22: 10.1 | FA22: 18.1 | FB22: 9.8 | FC22: 42.49 | FD22: 34.92 | FE22: 15.3 | FG22: 7.5 | FJ22: 6271.869 | FL22: 23.85031 | FM22: 7.879 | FN22: 0 | FO22: 9.6 | FP22: 26.92222 | FQ22: 18.92073 | FR22: 11.8 | FS22: 16 | FT22: 114.97226
... A58: 05/07/2025 | B58: 00:00 | C58: 137.2 | D58: 647.26 | E58: 215.51 | H58: 55 | I58: 84.1 | L58: 166.7 | M58: 167.3 | N58: 167.8 | O58: 254.3 | P58: 217.3 | Q58: 111.4 | R58: 448 | S58: 4.3 | X58: 136.7 | Y58: 7.3 | Z58: 5.1 | AB58: 6.9 | AC58: 15 | AD58: 88 | AI58: 64.3 | AJ58: 100.9 | AN58: 6.5 | AO58: 230.5 | AP58: 39.9 | AQ58: 73.2 | AR58: 26.6 | AS58: 17.8 | AT58: 19 | AU58: 73.1 | AV58: 182.76622 | AW58: 0 | AX58: 92.5424 | AY58: 76.1 | AZ58: 5.8 | BA58: 1.2 | BB58: 33.2 | BC58: 28.9 | BD58: 3.8 | BE58: 0 | BF58: 47.6 | BI58: 16.9 | BL58: 46.9 | BP58: 55.3 | BQ58: 178.3 | BR58: 176.2 | BS58: 200 | BT58: 274.4 | BZ58: 0 | CC58: 1.2 | CD58: 160.3 | CE58: 71.8 | CF58: 66.3 | CG58: 68.9 | CH58: 29 | CL58: 147.2 | CM58: 150 | CN58: 150.5 | CT58: 216 | CU58: 103.4 | CV58: 0 | CW58: 16.7 | CX58: 0 | CY58: 17 | CZ58: 0 | DA58: 10.9 | DB58: 9.9 | DC58: 4.4 | DD58: 0.4 | DE58: 2.2 | DF58: 2.5 | DG58: 20.1 | DH58: 12 | DI58: 8.7 | DJ58: 3.4 | DK58: 18.5 | DL58: 0 | DM58: 0 | DN58: 4.5 | DO58: 8.9 | DP58: 4.5 | DQ58: 2.2 | DR58: 1.1 | DS58: 2.9 | DT58: 0 | DU58: 2.1 | DV58: 5.6 | DW58: 1.3 | DX58: 0.3 | DY58: 8.1 | DZ58: 3.5 | EA58: 5.1 | EB58: 7.2 | EC58: 13.5 | ED58: 1.7 | EE58: 17.2 | EF58: 0 | EG58: 6.8 | EH58: 13.1 | EI58: 0.3 | EJ58: 0 | EK58: 10.5 | EL58: 3.3 | EM58: 7.5 | EN58: 5.1 | EO58: 5.7 | EP58: 5.7 | EQ58: 12 | ER58: 0 | ES58: 0 | ET58: 0 | EU58: 0.6 | EV58: 0 | EW58: 0 | EX58: 0 | EY58: 0 | EZ58: 10 | FA58: 17.9 | FB58: 8.9 | FC58: 0 | FD58: 0 | FE58: 15 | FG58: 8.4 | FJ58: 6518.6786 | FL58: 22.12026 | FM58: 7.909 | FN58: 6.13 | FO58: 9.4 | FP58: 26.99043 | FQ58: 18.92148 | FR58: 11.6 | FS58: 16 | FT58: 119.07117
A59: EJEC | C59: 2321.55 | D59: 14799.655 | E59: 4977.64 | F59: 0 | G59: 0 | H59: 1323.05 | I59: 2081.1 | J59: 0 | K59: 0 | L59: 4329.25 | M59: 4499.85 | N59: 4512.4 | O59: 6606.1 | P59: 5138.05 | Q59: 2665.7 | R59: 9202.7 | S59: 102.65 | T59: 0 | U59: 0 | V59: 0 | W59: 0 | X59: 3300.8 | Y59: 176.8 | Z59: 126.2 | AA59: 0 | AB59: 164.15 | AC59: 286.25 | AD59: 1817.7 | AE59: 0 | AF59: 0 | AG59: 0 | AH59: 0 | AI59: 1573.65 | AJ59: 2535.35 | AK59: 0 | AL59: 0 | AM59: 0 | AN59: 155.45 | AO59: 3924.95 | AP59: 984.15 | AQ59: 1723.05 | AR59: 664.4 | AS59: 431.85 | AT59: 467.5 | AU59: 1759.55 | AV59: 4284.1525 | AW59: 4196.948 | AX59: 4319.5261 | AY59: 1851.45 | AZ59: 143.1 | BA59: 35.9 | BB59: 799.65 | BC59: 699.85 | BD59: 91.2 | BE59: 212.8 | BF59: 1615.7 | BG59: 0 | BH59: 0 | BI59: 1274.25 | BJ59: 0 | BK59: 0 | BL59: 818.85 | BM59: 0 | BN59: 0 | BO59: 0 | BP59: 1331.7 | BQ59: 4241.4 | BR59: 4194 | BS59: 4800 | BT59: 6568.4 | BU59: 0 | BV59: 0 | BW59: 0 | BX59: 0 | BY59: 0 | BZ59: 379.9 | CA59: 0 | CB59: 0 | CC59: 29.45 | CD59: 3010.25 | CE59: 1936.45 | CF59: 1544.7 | CG59: 1626.6 | CH59: 695.05 | CI59: 0 | CJ59: 0 | CK59: 0 | CL59: 3507.15 | CM59: 3573.7 | CN59: 3603 | CO59: 0 | CP59: 0 | CQ59: 0 | CR59: 0 | CS59: 0 | CT59: 5136.9 | CU59: 2462.3 | CV59: 8.35 | CW59: 80.45 | CX59: 555.35 | CY59: 334.35 | CZ59: 2.65 | DA59: 272 | DB59: 238.15 | DC59: 106.9 | DD59: 9.6 | DE59: 58.25 | DF59: 62.2 | DG59: 480.1 | DH59: 314.5 | DI59: 204.8 | DJ59: 80.05 | DK59: 444 | DL59: 115.7 | DM59: 138.8 | DN59: 22.85 | DO59: 77 | DP59: 98.75 | DQ59: 51.65 | DR59: 25.75 | DS59: 62.7 | DT59: 134.2 | DU59: 51.15 | DV59: 330.65 | DW59: 30.55 | DX59: 4.4 | DY59: 197.15 | DZ59: 79.75 | EA59: 122.9 | EB59: 176.25 | EC59: 325.9 | ED59: 132.1 | EE59: 262.7 | EF59: 249.9 | EG59: 54.8 | EH59: 96.2 | EI59: 6.5 | EJ59: 2.9 | EK59: 252 | EL59: 86.1 | EM59: 189 | EN59: 124.55 | EO59: 134.15 | EP59: 134.5 | EQ59: 249.85 | ER59: 1886.85 | ES59: 115.7 | ET59: 1048.35 | EU59: 14.4 | EV59: 188.2 | EW59: 181.15 | EX59: 781.5 | EY59: 115.85 | EZ59: 239.95 | FA59: 431.95 | FB59: 229.65 | FC59: 880.19 | FD59: 707.585 | FE59: 335.95 | FF59: 0 | FG59: 171.1 | FH59: 0 | FI59: 0 | FJ59: 166237.25 | FL59: 538.20416 | FM59: 170.765 | FN59: 95.659 | FO59: 226.25 | FP59: 640.05471 | FQ59: 454.16694 | FR59: 280.5 | FS59: 385.7 | FT59: 2791.2998

Sheet REACTIVA
B3: viernes, 4 de Julio del 2025
A5: POTENCIA REACTIVA EJECUTADA DE LAS UNIDADES DE GENERACIÓN DEL COES (MVAR) | FK5: CENTRALES NO INTEGRANTES COES
A6: FECHA | B6: HORA | C6: 65333 | D6: 101 | E6: 102 | F6: 42667 | G6: 42668 | H6: 126 | I6: 127 | J6: 138 | K6: 139 | L6: 197 | M6: 203 | N6: 204 | O6: 230 | P6: 209 | Q6: 56677 | R6: 796 | S6: 2146 | T6: 142 | U6: 143 | V6: 125 | W6: 187 | X6: 163 | Y6: 298 | Z6: 219 | AA6: 151 | AB6: 152 | AC6: 153 | AD6: 154 | AE6: 756 | AF6: 156 | AG6: 155 | AH6: 182 | AI6: 212 | AJ6: 758 | AK6: 263 | AL6: 265 | AM6: 775 | AN6: 777 | AO6: 2154 | AP6: 150 | AQ6: 149 | AR6: 188 | AS6: 2131 | AT6: 755 | AU6: 252 | AV6: 249 | AW6: 250 | AX6: 117 | AY6: 267 | AZ6: 268 | BA6: 119 | BB6: 120 | BC6: 189 | BD6: 122 | BE6: 266 | BF6: 337 | BG6: 338 | BH6: 251 | BI6: 115 | BJ6: 239 | BK6: 288 | BL6: 240 | BM6: 241 | BN6: 242 | BO6: 191 | BP6: 194 | BQ6: 196 | BR6: 207 | BS6: 236 | BT6: 795 | BU6: 285 | BV6: 995 | BW6: 996 | BX6: 997 | BY6: 766 | BZ6: 926 | CA6: 924 | CB6: 121 | CC6: 103 | CD6: 104 | CE6: 106 | CF6: 105 | CG6: 107 | CH6: 110 | CI6: 109 | CJ6: 144 | CK6: 113 | CL6: 114 | CM6: 193 | CN6: 208 | CO6: 786 | CP6: 787 | CQ6: 788 | CR6: 789 | CS6: 248 | CT6: 2159 | CU6: 303 | CV6: 59715 | CW6: 62255 | CX6: 1263 | CY6: 61800 | CZ6: 2194 | DA6: 216 | DB6: 198 | DC6: 49607 | DD6: 214 | DE6: 260 | DF6: 2152 | DG6: 2128 | DH6: 247 | DI6: 228 | DJ6: 2135 | DK6: 261 | DL6: 237 | DM6: 253 | DN6: 770 | DO6: 225 | DP6: 2201 | DQ6: 2171 | DR6: 760 | DS6: 235 | DT6: 238 | DU6: 2184 | DV6: 61855 | DW6: 223 | DX6: 226 | DY6: 201 | DZ6: 258 | EA6: 259 | EB6: 920 | EC6: 257 | ED6: 256 | EE6: 2148 | EF6: 58288 | EG6: 58289 | EH6: 58839 | EI6: 58840 | EJ6: 296 | EK6: 297 | EL6: 211 | EM6: 2175 | EN6: 2178 | EO6: 2181 | EP6: 1262 | EQ6: 63425 | ER6: 233 | ES6: 2150 | ET6: 2165 | EU6: 2161 | EV6: 61197 | EW6: 58851 | EX6: 234 | EY6: 215 | EZ6: 917 | FA6: 289 | FB6: 58333 | FC6: 58336 | FD6: 213 | FE6: 232 | FF6: 2190 | FG6: 202 | FH6: 58487 | FI6: TOTAL COES | FK6: 221 | FL6: 222 | FM6: 224 | FN6: 2187 | FO6: 227 | FP6: 49400 | FQ6: 199 | FR6: 200 | FS6: TOTAL NO COES
C7: SUR | D7: CENTRO | E7: CENTRO | F7: NORTE | G7: NORTE | H7: NORTE | I7: NORTE | J7: CENTRO | K7: CENTRO | L7: CENTRO | M7: CENTRO | N7: CENTRO | O7: CENTRO | P7: CENTRO | Q7: CENTRO | R7: CENTRO | S7: CENTRO | T7: CENTRO | U7: CENTRO | V7: CENTRO | W7: CENTRO | X7: SUR | Y7: SUR | Z7: CENTRO | AA7: SUR | AB7: SUR | AC7: SUR | AD7: SUR | AE7: SUR | AF7: SUR | AG7: SUR | AH7: SUR | AI7: CENTRO | AJ7: NORTE | AK7: NORTE | AL7: NORTE | AM7: CENTRO | AN7: CENTRO | AO7: CENTRO | AP7: CENTRO | AQ7: CENTRO | AR7: CENTRO | AS7: CENTRO | AT7: SUR | AU7: CENTRO | AV7: CENTRO | AW7: CENTRO | AX7: CENTRO | AY7: CENTRO | AZ7: CENTRO | BA7: CENTRO | BB7: CENTRO | BC7: SUR | BD7: NORTE | BE7: CENTRO | BF7: CENTRO | BG7: CENTRO | BH7: CENTRO | BI7: NORTE | BJ7: NORTE | BK7: NORTE | BL7: SUR | BM7: SUR | BN7: SUR | BO7: CENTRO | BP7: CENTRO | BQ7: CENTRO | BR7: CENTRO | BS7: CENTRO | BT7: CENTRO | BU7: CENTRO | BV7: SUR | BW7: SUR | BX7: SUR | BY7: NORTE | BZ7: SUR | CA7: CENTRO | CB7: NORTE | CC7: CENTRO | CD7: CENTRO | CE7: CENTRO | CF7: CENTRO | CG7: CENTRO | CH7: CENTRO | CI7: CENTRO | CJ7: CENTRO | CK7: CENTRO | CL7: CENTRO | CM7: CENTRO | CN7: CENTRO | CO7: SUR | CP7: SUR | CQ7: SUR | CR7: SUR | CS7: CENTRO | CT7: CENTRO | CU7: CENTRO | CV7: CENTRO | CW7: SUR | CX7: NORTE | CY7: NORTE | CZ7: NORTE | DA7: NORTE | DB7: NORTE | DC7: SUR | DD7: CENTRO | DE7: CENTRO | DF7: CENTRO | DG7: NORTE | DH7: NORTE | DI7: CENTRO | DJ7: CENTRO | DK7: SUR | DL7: SUR | DM7: CENTRO | DN7: CENTRO | DO7: CENTRO | DP7: CENTRO | DQ7: CENTRO | DR7: CENTRO | DS7: SUR | DT7: CENTRO | DU7: CENTRO | DV7: NORTE | DW7: CENTRO | DX7: CENTRO | DY7: NORTE | DZ7: CENTRO | EA7: CENTRO | EB7: CENTRO | EC7: NORTE | ED7: NORTE | EE7: SUR | EF7: CENTRO | EG7: CENTRO | EH7: CENTRO | EI7: CENTRO | EJ7: CENTRO | EK7: CENTRO | EL7: SUR | EM7: SUR | EN7: SUR | EO7: SUR | EP7: NORTE | EQ7: SUR | ER7: SUR | ES7: SUR | ET7: CENTRO | EU7: CENTRO | EV7: CENTRO | EW7: SUR | EX7: SUR | EY7: NORTE | EZ7: CENTRO | FA7: NORTE | FB7: NORTE | FC7: NORTE | FD7: CENTRO | FE7: NORTE | FF7: NORTE | FG7: CENTRO | FH7: CENTRO | FK7: NORTE | FL7: CENTRO | FM7: NORTE | FN7: NORTE | FO7: NORTE | FP7: NORTE | FQ7: NORTE | FR7: NORTE
C8: HIDROELÉCTRICA | D8: HIDROELÉCTRICA | E8: HIDROELÉCTRICA | F8: TERMOELÉCTRICA | G8: TERMOELÉCTRICA | H8: HIDROELÉCTRICA | I8: HIDROELÉCTRICA | J8: TERMOELÉCTRICA | K8: TERMOELÉCTRICA | L8: TERMOELÉCTRICA | M8: TERMOELÉCTRICA | N8: TERMOELÉCTRICA | O8: TERMOELÉCTRICA | P8: TERMOELÉCTRICA | Q8: TERMOELÉCTRICA | R8: HIDROELÉCTRICA | S8: HIDROELÉCTRICA | T8: TERMOELÉCTRICA | U8: TERMOELÉCTRICA | V8: TERMOELÉCTRICA | W8: TERMOELÉCTRICA | X8: HIDROELÉCTRICA | Y8: HIDROELÉCTRICA | Z8: TERMOELÉCTRICA | AA8: HIDROELÉCTRICA | AB8: HIDROELÉCTRICA | AC8: HIDROELÉCTRICA | AD8: HIDROELÉCTRICA | AE8: TERMOELÉCTRICA | AF8: TERMOELÉCTRICA | AG8: TERMOELÉCTRICA | AH8: HIDROELÉCTRICA | AI8: HIDROELÉCTRICA | AJ8: TERMOELÉCTRICA | AK8: TERMOELÉCTRICA | AL8: TERMOELÉCTRICA | AM8: HIDROELÉCTRICA | AN8: HIDROELÉCTRICA | AO8: HIDROELÉCTRICA | AP8: HIDROELÉCTRICA | AQ8: HIDROELÉCTRICA | AR8: HIDROELÉCTRICA | AS8: HIDROELÉCTRICA | AT8: HIDROELÉCTRICA | AU8: TERMOELÉCTRICA | AV8: TERMOELÉCTRICA | AW8: TERMOELÉCTRICA | AX8: HIDROELÉCTRICA | AY8: HIDROELÉCTRICA | AZ8: HIDROELÉCTRICA | BA8: HIDROELÉCTRICA | BB8: HIDROELÉCTRICA | BC8: HIDROELÉCTRICA | BD8: HIDROELÉCTRICA | BE8: HIDROELÉCTRICA | BF8: HIDROELÉCTRICA | BG8: HIDROELÉCTRICA | BH8: HIDROELÉCTRICA | BI8: TERMOELÉCTRICA | BJ8: TERMOELÉCTRICA | BK8: TERMOELÉCTRICA | BL8: TERMOELÉCTRICA | BM8: TERMOELÉCTRICA | BN8: TERMOELÉCTRICA | BO8: HIDROELÉCTRICA | BP8: TERMOELÉCTRICA | BQ8: TERMOELÉCTRICA | BR8: TERMOELÉCTRICA | BS8: TERMOELÉCTRICA | BT8: TERMOELÉCTRICA | BU8: TERMOELÉCTRICA | BV8: TERMOELÉCTRICA | BW8: TERMOELÉCTRICA | BX8: TERMOELÉCTRICA | BY8: HIDROELÉCTRICA | BZ8: TERMOELÉCTRICA | CA8: TERMOELÉCTRICA | CB8: HIDROELÉCTRICA | CC8: HIDROELÉCTRICA | CD8: HIDROELÉCTRICA | CE8: HIDROELÉCTRICA | CF8: HIDROELÉCTRICA | CG8: HIDROELÉCTRICA | CH8: TERMOELÉCTRICA | CI8: TERMOELÉCTRICA | CJ8: TERMOELÉCTRICA | CK8: TERMOELÉCTRICA | CL8: TERMOELÉCTRICA | CM8: TERMOELÉCTRICA | CN8: TERMOELÉCTRICA | CO8: TERMOELÉCTRICA | CP8: TERMOELÉCTRICA | CQ8: TERMOELÉCTRICA | CR8: TERMOELÉCTRICA | CS8: TERMOELÉCTRICA | CT8: TERMOELÉCTRICA | CU8: SOLAR | CV8: EÓLICA | CW8: SOLAR | CX8: EÓLICA | CY8: SOLAR | CZ8: HIDROELÉCTRICA | DA8: HIDROELÉCTRICA | DB8: HIDROELÉCTRICA | DC8: HIDROELÉCTRICA | DD8: HIDROELÉCTRICA | DE8: HIDROELÉCTRICA | DF8: HIDROELÉCTRICA | DG8: HIDROELÉCTRICA | DH8: HIDROELÉCTRICA | DI8: HIDROELÉCTRICA | DJ8: HIDROELÉCTRICA | DK8: SOLAR | DL8: SOLAR | DM8: EÓLICA | DN8: EÓLICA | DO8: TERMOELÉCTRICA | DP8: TERMOELÉCTRICA | DQ8: TERMOELÉCTRICA | DR8: TERMOELÉCTRICA | DS8: SOLAR | DT8: HIDROELÉCTRICA | DU8: HIDROELÉCTRICA | DV8: HIDROELÉCTRICA | DW8: HIDROELÉCTRICA | DX8: HIDROELÉCTRICA | DY8: HIDROELÉCTRICA | DZ8: HIDROELÉCTRICA | EA8: HIDROELÉCTRICA | EB8: HIDROELÉCTRICA | EC8: EÓLICA | ED8: EÓLICA | EE8: SOLAR | EF8: EÓLICA | EG8: EÓLICA | EH8: EÓLICA | EI8: EÓLICA | EJ8: HIDROELÉCTRICA | EK8: HIDROELÉCTRICA | EL8: HIDROELÉCTRICA | EM8: HIDROELÉCTRICA | EN8: HIDROELÉCTRICA | EO8: HIDROELÉCTRICA | EP8: EÓLICA | EQ8: SOLAR | ER8: SOLAR | ES8: SOLAR | ET8: HIDROELÉCTRICA | EU8: EÓLICA | EV8: EÓLICA | EW8: SOLAR | EX8: SOLAR | EY8: HIDROELÉCTRICA | EZ8: HIDROELÉCTRICA | FA8: TERMOELÉCTRICA | FB8: TERMOELÉCTRICA | FC8: TERMOELÉCTRICA | FD8: TERMOELÉCTRICA | FE8: TERMOELÉCTRICA | FF8: TERMOELÉCTRICA | FG8: TERMOELÉCTRICA | FH8: TERMOELÉCTRICA | FK8: HIDROELÉCTRICA | FL8: HIDROELÉCTRICA | FM8: HIDROELÉCTRICA | FN8: HIDROELÉCTRICA | FO8: TERMOELÉCTRICA | FP8: TERMOELÉCTRICA | FQ8: HIDROELÉCTRICA | FR8: HIDROELÉCTRICA
C9: HYDRO GLOBAL PERÚ S.A.C. | D9: ELECTROPERU | E9: ELECTROPERU | F9: ELECTROPERU | G9: ELECTROPERU | H9: ORAZUL ENERGY PERÚ | I9: ORAZUL ENERGY PERÚ | J9: TERMOSELVA | K9: TERMOSELVA | L9: KALLPA GENERACION S.A. | M9: KALLPA GENERACION S.A. | N9: KALLPA GENERACION S.A. | O9: KALLPA GENERACION S.A. | P9: KALLPA GENERACION S.A. | Q9: KALLPA GENERACION S.A. | R9: KALLPA GENERACION S.A. | S9: KALLPA GENERACION S.A. | T9: SHOUGESA | U9: SHOUGESA | V9: SHOUGESA | W9: SHOUGESA | X9: EGEMSA | Y9: EGESUR | Z9: EGESUR | AA9: EGASA | AB9: EGASA | AC9: EGASA | AD9: EGASA | AE9: EGASA | AF9: EGASA | AG9: EGASA | AH9: SAN GABAN | AI9: CELEPSA | AJ9: MINERA CERRO VERDE | AK9: PLANTA DE RESERVA FRIA DE GENERACION DE ETEN S.A. | AL9: PLANTA DE RESERVA FRIA DE GENERACION DE ETEN S.A. | AM9: EMPRESA DE GENERACION HUALLAGA | AN9: EMPRESA DE GENERACION HUALLAGA | AO9: LA VIRGEN | AP9: CHINANGO S.A.C. | AQ9: CHINANGO S.A.C. | AR9: HIDROELECTRICA HUANCHOR S.A.C. | AS9: CELEPSA RENOVABLES S.R.L. | AT9: INLAND ENERGY SAC | AU9: FENIX POWER PERÚ | AV9: FENIX POWER PERÚ | AW9: FENIX POWER PERÚ | AX9: STATKRAFT S.A | AY9: STATKRAFT S.A | AZ9: STATKRAFT S.A | BA9: STATKRAFT S.A | BB9: STATKRAFT S.A | BC9: STATKRAFT S.A | BD9: STATKRAFT S.A | BE9: STATKRAFT S.A | BF9: CENTRALES SANTA ROSA S.A.C. | BG9: CENTRALES SANTA ROSA S.A.C. | BH9: EMPRESA DE GENERACION HUANZA | BI9: ENEL GENERACION PIURA S.A. | BJ9: ENEL GENERACION PIURA S.A. | BK9: ENEL GENERACION PIURA S.A. | BL9: ENGIE | BM9: ENGIE | BN9: ENGIE | BO9: ENGIE | BP9: ENGIE | BQ9: ENGIE | BR9: ENGIE | BS9: ENGIE | BT9: ENGIE | BU9: ENGIE | BV9: ENGIE | BW9: ENGIE | BX9: ENGIE | BY9: ENGIE | BZ9: INFRAESTRUCTURAS Y ENERGIAS DEL PERU S.A.C. | CA9: INFRAESTRUCTURAS Y ENERGIAS DEL PERU S.A.C. | CB9: INVERSIONES SHAQSHA S.A.C. | CC9: ORYGEN PERU S.A.A. | CD9: ORYGEN PERU S.A.A. | CE9: ORYGEN PERU S.A.A. | CF9: ORYGEN PERU S.A.A. | CG9: ORYGEN PERU S.A.A. | CH9: ORYGEN PERU S.A.A. | CI9: ORYGEN PERU S.A.A. | CJ9: ORYGEN PERU S.A.A. | CK9: ORYGEN PERU S.A.A. | CL9: ORYGEN PERU S.A.A. | CM9: ORYGEN PERU S.A.A. | CN9: ORYGEN PERU S.A.A. | CO9: SAMAY I S.A.C | CP9: SAMAY I S.A.C | CQ9: SAMAY I S.A.C | CR9: SAMAY I S.A.C | CS9: TERMOCHILCA S.A.C. | CT9: TERMOCHILCA S.A.C. | CU9: COLCA SOLAR S.A.C. | CV9: ENERGIA RENOVABLE DEL SUR S.A. | CW9: GR CORTARRAMA SOCIEDAD ANONIMA CERRADA | CX9: GR TARUCA SOCIEDAD ANONIMA CERRADA | CY9: KONDU SAC | CZ9: PERUANA DE INVERSIONES EN ENERGIAS RENOVABLES S.A. | DA9: ORAZUL ENERGY PERÚ | DB9: ORAZUL ENERGY PERÚ | DC9: SAN GABAN | DD9: MAJA ENERGIA S.A.C. | DE9: EMPRESA DE GENERACION ELECTRICA CANCHAYLLO SAC | DF9: EMPRESA DE GENERACION ELECTRICA SANTA ANA S.A.C. | DG9: EMPRESA ELECTRICA AGUA AZUL | DH9: EMPRESA ELECTRICA RIO DOBLE | DI9: HIDROCAÑETE S.A. | DJ9: HUAURA POWER GROUP S.A. | DK9: MOQUEGUA FV S.A.C. | DL9: PANAMERICANA SOLAR SAC. | DM9: PARQUE EOLICO MARCONA S.A.C. | DN9: PARQUE EOLICO TRES HERMANAS S.A.C. | DO9: PETRAMAS | DP9: PETRAMAS | DQ9: PETRAMAS | DR9: PETRAMAS | DS9: TACNA SOLAR SAC. | DT9: ELECTRICA YANAPAMPA SAC | DU9: ANDEAN POWER S.A.C. | DV9: ASOCIACIÓN SANTA LUCIA DE CHACAS | DW9: ATRIA ENERGIA S.A.C. | DX9: EGEJUNIN | DY9: EGEJUNIN | DZ9: EGEJUNIN | EA9: EGEJUNIN | EB9: EMPRESA DE GENERACION ELECTRICA RIO BAÑOS S.A.C. | EC9: ENERGÍA EÓLICA S.A. | ED9: ENERGÍA EÓLICA S.A. | EE9: ENGIE | EF9: ENGIE | EG9: ENGIE | EH9: ENGIE | EI9: ENGIE | EJ9: GENERACIÓN ANDINA S.A.C. | EK9: GENERACIÓN ANDINA S.A.C. | EL9: GENERADORA DE ENERGÍA DEL PERÚ | EM9: GENERADORA DE ENERGÍA DEL PERÚ | EN9: GENERADORA DE ENERGÍA DEL PERÚ | EO9: GENERADORA DE ENERGÍA DEL PERÚ | EP9: GR PAINO SOCIEDAD ANONIMA CERRADA | EQ9: JOYA SOLAR S.A.C. | ER9: MAJES ARCUS S.A.C. | ES9: ORYGEN PERU S.A.A. | ET9: ORYGEN PERU S.A.A. | EU9: ORYGEN PERU S.A.A. | EV9: ORYGEN PERU S.A.A. | EW9: ORYGEN PERU S.A.A. | EX9: REPARTICIÓN ARCUS S.A.C. | EY9: SINERSA | EZ9: SINERSA | FA9: BIOENERGIA DEL CHIRA S.A. | FB9: GM OPERACIONES S.A.C. | FC9: GM OPERACIONES S.A.C. | FD9: AGRO INDUSTRIAL PARAMONGA S.A. | FE9: AGROAURORA S.A.C. | FF9: AGROINDUSTRIAS SAN JACINTO S.A.A. | FG9: SDF ENERGIA SAC | FH9: SDF ENERGIA SAC | FK9: UNACEM PERU S.A. | FL9: ELECTRO ORIENTE | FM9: AGUAS Y ENERGIA PERU | FN9: ELECTRO ZAÑA S.A.C. | FO9: ELECTRONOROESTE S.A. | FP9: SDE PIURA | FQ9: SINERSA | FR9: SINERSA
C10: SAN GABAN III | D10: MANTARO | E10: RESTITUCION | F10: TUMBES MAK 1 | G10: TUMBES MAK 2 | H10: CARHUAQUERO | I10: CAÑON DEL PATO | J10: AGUAYTIA TG1 | K10: AGUAYTIA TG2 | L10: KALLPA TG1 | M10: KALLPA TG2 | N10: KALLPA TG3 | O10: KALLPA TV | P10: LFLORES TG1 | Q10: LFLORES TV | R10: CERRO DEL AGUILA | S10: CERRODELAGUILAG4 | T10: SHOUGESA TV1 | U10: SHOUGESA TV2 | V10: SHOUGESA TV3 | W10: SHOUGESA CUMMINS | X10: MACHUPICCHU | Y10: ARICOTA 1 | Z10: INDEPENDENCIA | AA10: CHARCANI I,II,III | AB10: CHARCANI IV | AC10: CHARCANI V | AD10: CHARCANI VI | AE10: CHILINA TG | AF10: MOLLENDO 1, 2, 3 | AG10: CHILINA (SULZ 1,2) | AH10: SAN GABAN II | AI10: PLATANAL | AJ10: RECKA | AK10: RF ETEN TG1 | AL10: RF ETEN TG2 | AM10: CHAGLLA GP1 | AN10: CHAGLLA | AO10: LA VIRGEN | AP10: CHIMAY | AQ10: YANANGO | AR10: HUANCHOR | AS10: MARAÑON | AT10: STA TERESA | AU10: FENIX GT11 | AV10: FENIX GT12 | AW10: FENIX TV10 | AX10: YAUPI | AY10: OROYA | AZ10: PACHACHACA | BA10: MALPASO | BB10: CAHUA | BC10: ARCATA | BD10: GALLITO CIEGO | BE10: CHEVES | BF10: SANTA ROSA 1 | BG10: SANTA ROSA 2 | BH10: HUANZA | BI10: MALACAS2 TG4 | BJ10: MALACAS3 TG 5 | BK10: MALACAS1 TG6 | BL10: RF ILO2 TG1 | BM10: RF ILO2 TG2 | BN10: RF ILO2 TG3 | BO10: YUNCAN | BP10: CHILCA1 TG1 | BQ10: CHILCA1 TG2 | BR10: CHILCA1 TG3 | BS10: CHILCA-TV | BT10: CHILCA2 TG41 | BU10: CHILCA2-TV | BV10: CTNEPI_TG41 | BW10: CTNEPI_TG42 | BX10: CTNEPI_TG43 | BY10: QUITARACSA | BZ10: RF PTO MALDONADO | CA10: RF PUCALLPA | CB10: PARIAC | CC10: HUINCO | CD10: MATUCANA | CE10: MOYOPAMPA | CF10: CALLAHUANCA | CG10: HUAMPANI | CH10: STA ROSA WEST TG7 | CI10: UTI_5 | CJ10: UTI_6 | CK10: VENTANILLA 3 | CL10: VENTANILLA 4 | CM10: VENTANILLA TV | CN10: STAROSA TG8 | CO10: PTO_BRVO TG1 | CP10: PTO_BRVO TG2 | CQ10: PTO_BRVO TG3 | CR10: PTO_BRVO TG4 | CS10: OLLEROS TG1 | CT10: OLLEROS TV | CU10: CS YARUCAYA | CV10: SAN JUAN | CW10: MATARANI | CX10: DUNA | CY10: CARHUAQUERO (CS) | CZ10: MANTA I | DA10: CARHUAQUERO4 | DB10: CAÑA BRAVA | DC10: TUPURI | DD10: RONCADOR | DE10: CANCHAYLLO | DF10: RENOVANDESH1 | DG10: POTRERO | DH10: PIZARRAS | DI10: NIMPERIAL | DJ10: YARUCAYA | DK10: MOQUEGUA-SOLAR | DL10: PANAMERICANA-SOLAR | DM10: PQE-EOLICO-MARCONA | DN10: PQE-EOLICO-3-HERMANAS | DO10: HUAYCOLORO | DP10: CALLAO | DQ10: DONA_CATALINA | DR10: LAGRINGAV | DS10: TACNA-SOLAR | DT10: YANAPAMPA | DU10: CARHUAC | DV10: HUALLIN | DW10: PURMACANA | DX10: HUASAHUASI | DY10: STACRUZ_1_2 | DZ10: RUNATULLO_II | EA10: RUNATULLO_III | EB10: RUCUY | EC10: PQE-EOLICO-TALARA | ED10: PQE-EOLICO-CUPISNIQUE | EE10: INTIPAMPA | EF10: PUNTA LOMITAS-BL1 | EG10: PUNTA LOMITAS-BL2 | EH10: PUN LOMITAS_EXP-BL1 | EI10: PUN LOMITAS_EXP-BL2 | EJ10: 8AGOSTO | EK10: EL CARMEN | EL10: LA JOYA | EM10: ANGEL_I | EN10: ANGEL_II | EO10: ANGEL_III | EP10: HUAMBOS | EQ10: SAN MARTIN SOLAR | ER10: MAJES | ES10: RUBI | ET10: CH_HER1 | EU10: WAYRA-I | EV10: WAYRA EXTENSION | EW10: CLEMESI | EX10: REPARTICION | EY10: POECHOS2 | EZ10: CHANCAY | FA10: CANA BRAVA | FB10: REFINERIA TALARA TV1 | FC10: REFINERÍA TALARA TV2 | FD10: PARAMONGA | FE10: MAPLE | FF10: SAN_JACINTO | FG10: OQUENDO TG1 | FH10: OQUENDO TV1 | FI10: MVAR | FK10: CARPAPATA | FL10: CENTRALES ELOR | FM10: PIAS1 | FN10: ZANA | FO10: TABLAZO | FP10: TALLANCA | FQ10: CURUMUY | FR10: POECHOS1 | FS10: MVAR
A11: 04/07/2025 | B11: 00:30 | C11: 10 | D11: 40.79 | E11: 25.53 | H11: -12.9 | I11: -12.9 | L11: -24 | M11: -25.2 | N11: -0.4 | O11: 29.7 | P11: 20.9 | Q11: 30 | R11: 58.5 | S11: 0.2 | X11: -0.8 | Y11: 0.7 | AA11: -3.4 | AB11: 5.4 | AC11: 6.5 | AH11: -4.2 | AI11: 0.1 | AM11: -1.3 | AN11: 0 | AO11: 1.8 | AP11: 8.5 | AQ11: 7.7 | AR11: -0.3 | AS11: 2.7 | AT11: 0.9 | AU11: 17.936 | AV11: 14.327 | AW11: -47.529 | AX11: -2.4 | AY11: -2.5 | AZ11: 0.6 | BA11: -1 | BB11: 1.9 | BC11: 0.9 | BD11: 0 | BE11: 2.5 | BH11: -3.6 | BK11: 0 | BO11: 0.1 | BP11: -22.8 | BQ11: -24.3 | BR11: -4.5 | BS11: 12.3 | BY11: 0 | CB11: -0.7 | CC11: 14.5 | CD11: 16 | CE11: 5.8 | CF11: 0.1 | CG11: -0.1 | CK11: -2.5 | CL11: -0.2 | CM11: -37.7 | CS11: -6.1 | CT11: -6.8 | CV11: -5.7 | CW11: 0 | CZ11: 0.9 | DA11: 0 | DB11: -0.4 | DD11: 0.2 | DE11: 0.6 | DF11: 0.1 | DG11: -1.1 | DH11: 0 | DI11: 0.5 | DK11: 0 | DL11: 0 | DM11: 0.2 | DN11: 5.2 | DO11: 1.5 | DP11: 0.7 | DQ11: 0.4 | DR11: 1.2 | DS11: 0 | DT11: 0 | DU11: 0.2 | DV11: 0.2 | DX11: -2.9 | DY11: 0.3 | DZ11: 0.6 | EA11: 0.5 | EB11: 0.2 | EC11: 0.8 | ED11: 4 | EE11: 0 | EF11: 0 | EG11: 0 | EJ11: 1.9 | EK11: 0 | EL11: 1.4 | EM11: 0.1 | EN11: 0.1 | EO11: 0.1 | EQ11: 0 | ER11: 0 | ES11: 0 | ET11: -0.2 | EU11: 0 | EV11: 3.6 | EW11: 0 | EX11: 0 | EY11: 0.2 | EZ11: 0.4 | FA11: 2.9 | FB11: 10.79 | FC11: 11 | FD11: 2.5 | FF11: 2 | FI11: 133.744 | FK11: 1.93053 | FL11: 0.297 | FM11: 0 | FN11: 1.2 | FO11: 0.31194 | FP11: 0.25438 | FQ11: -0.8 | FR11: 1.6 | FS11: 4.79385
A12: 04/07/2025 | B12: 01:00 | C12: 8.8 | D12: 32.34 | E12: 24.08 | H12: -7.8 | I12: -3 | L12: -28 | M12: -32.6 | N12: -6 | O12: 21.7 | P12: 19.8 | Q12: 29.2 | R12: 55 | S12: 0.1 | X12: -1.4 | Y12: 0.7 | AA12: -3.4 | AB12: 5.2 | AC12: 4.7 | AH12: -4.9 | AI12: -1.4 | AM12: -1.3 | AN12: 0 | AO12: 1.4 | AP12: 8.3 | AQ12: 7.3 | AR12: -0.9 | AS12: 2.7 | AT12: 0.4 | AU12: 17.516 | AV12: 14.079 | AW12: -48.932 | AX12: -3.3 | AY12: -2.4 | AZ12: 0.6 | BA12: -2.5 | BB12: 1.5 | BC12: 0.9 | BD12: 0 | BE12: -2 | BH12: -4 | BK12: 0 | BO12: -2.7 | BP12: -23.6 | BQ12: -25 | BR12: -5.8 | BS12: 10.8 | BY12: 0 | CB12: -0.7 | CC12: 14.2 | CD12: 15.7 | CE12: 6 | CF12: 0.7 | CG12: -0.1 | CK12: -4.4 | CL12: -1.2 | CM12: -39.9 | CS12: 0.6 | CT12: -5.3 | CV12: -5.7 | CW12: 0 | CZ12: 0.9 | DA12: 0 | DB12: -0.3 | DD12: 0 | DE12: 0.6 | DF12: 0.1 | DG12: -0.7 | DH12: 0 | DI12: 0.6 | DK12: 0 | DL12: 0 | DM12: 0.2 | DN12: 5.6 | DO12: 1.5 | DP12: 0.7 | DQ12: 0.4 | DR12: 1.2 | DS12: 0 | DT12: 0.1 | DU12: 0.1 | DV12: 0.2 | DX12: -2.9 | DY12: 0.3 | DZ12: 0.5 | EA12: 0.4 | EB12: 0.1 | EC12: 0.8 | ED12: 4 | EE12: 0 | EF12: 0 | EG12: 0 | EJ12: 1.9 | EK12: 0 | EL12: 1.4 | EM12: 0.1 | EN12: 0.1 | EO12: 0.1 | EQ12: 0 | ER12: 0 | ES12: 0 | ET12: -0.2 | EU12: 0 | EV12: 3.6 | EW12: 0 | EX12: 0 | EY12: 0.2 | EZ12: 0.2 | FA12: 2.8 | FB12: 12.56 | FC12: 12.82 | FD12: 2.7 | FF12: 1.9 | FI12: 90.663 | FK12: 1.88919 | FL12: 0.529 | FM12: 0 | FN12: 1.3 | FO12: 0.30574 | FP12: 0.21763 | FQ12: -0.3 | FR12: 1.6 | FS12: 5.54156
A13: 04/07/2025 | B13: 01:30 | C13: 10.6 | D13: 27.6 | E13: 23.21 | H13: -10.2 | I13: -12.7 | L13: -27.7 | M13: -36.6 | N13: -11.2 | O13: 22.6 | P13: 19.6 | Q13: 27.9 | R13: 44.6 | S13: 0 | X13: -1.1 | Y13: 0.9 | AA13: -3.4 | AB13: 4.9 | AC13: 3.8 | AH13: -4.8 | AI13: -2.2 | AM13: -1.4 | AN13: 0 | AO13: 1.4 | AP13: 8.6 | AQ13: 8.2 | AR13: -1.5 | AS13: 2.7 | AT13: 1.8 | AU13: 16.388 | AV13: 12.755 | AW13: -43.674 | AX13: -1.7 | AY13: -2.3 | AZ13: 0.6 | BA13: -3.2 | BB13: 0.3 | BC13: 0.9 | BD13: 0 | BE13: -1.2 | BH13: -5.1 | BK13: 0 | BO13: -2.7 | BP13: -23.7 | BQ13: -25.1 | BR13: -6.2 | BS13: 11.7 | BY13: 0 | CB13: -0.7 | CC13: 15.8 | CD13: 15.8 | CE13: 5.5 | CF13: 0.5 | CG13: 0 | CK13: -6.1 | CL13: -4.1 | CM13: -43.1 | CS13: -2.2 | CT13: -6.8 | CV13: -5.7 | CW13: 0 | CZ13: 0.9 | DA13: 0 | DB13: 0 | DD13: -0.1 | DE13: 0.6 | DF13: 0.1 | DG13: 0.1 | DH13: 0.1 | DI13: 0.5 | DK13: 0 | DL13: 0 | DM13: 1.1 | DN13: 5.8 | DO13: 1.5 | DP13: 0.7 | DQ13: 0.4 | DR13: 1.2 | DS13: 0 | DT13: 0.1 | DU13: 0.1 | DV13: 0.2 | DX13: -2.9 | DY13: 0.1 | DZ13: 0.5 | EA13: 0.3 | EB13: 0.2 | EC13: 0.8 | ED13: 4 | EE13: 0 | EF13: 0 | EG13: 0 | EJ13: 1.9 | EK13: 0 | EL13: 1.4 | EM13: 0.1 | EN13: 0.1 | EO13: 0.1 | EQ13: 0 | ER13: 0 | ES13: 0 | ET13: -0.2 | EU13: 0 | EV13: 3.5 | EW13: 0 | EX13: 0 | EY13: 0.1 | EZ13: 0.4 | FA13: 3 | FB13: 12.11 | FC13: 12.37 | FD13: 2 | FF13: 1.9 | FI13: 47.359 | FK13: 1.79378 | FL13: 0.598 | FM13: 0 | FN13: 1.4 | FO13: 0.3015 | FP13: 0.1966 | FQ13: -0.3 | FR13: 1.4 | FS13: 5.38988
A14: 04/07/2025 | B14: 02:00 | C14: -5.2 | D14: 34.96 | E14: 24.95 | H14: -10 | I14: -3.7 | L14: -30.1 | M14: -35.3 | N14: -7.5 | O14: 23.7 | P14: 20.6 | Q14: 29 | R14: 34.6 | S14: 0.1 | X14: 0.4 | Y14: 0.4 | AA14: -3.6 | AB14: 4.9 | AC14: 4.5 | AH14: -5.8 | AI14: -1.7 | AM14: -1.4 | AN14: 0 | AO14: 1.4 | AP14: 7.8 | AQ14: 8.2 | AR14: -0.9 | AS14: 2.7 | AT14: 1.7 | AU14: 18.453 | AV14: 14.969 | AW14: -41.113 | AX14: -1.6 | AY14: -2.2 | AZ14: 0.6 | BA14: -2.1 | BB14: 0.9 | BC14: 1 | BD14: 0 | BE14: 0.1 | BH14: -5.2 | BK14: 0 | BO14: -2 | BP14: -22.5 | BQ14: -24 | BR14: -5.1 | BS14: 10 | BY14: 0 | CB14: -0.7 | CC14: 15.7 | CD14: 15.1 | CE14: 4.9 | CF14: -0.5 | CG14: 0.1 | CK14: -5.2 | CL14: -3.3 | CM14: -42.1 | CS14: -1.6 | CT14: -6.4 | CV14: -5.7 | CW14: 0 | CZ14: 0.9 | DA14: -0.1 | DB14: 0 | DD14: 0 | DE14: 0.6 | DF14: 0.1 | DG14: -0.4 | DH14: 0.3 | DI14: 0.6 | DK14: 0 | DL14: 0 | DM14: 0.2 | DN14: 5.1 | DO14: 1.5 | DP14: 0.7 | DQ14: 0.3 | DR14: 1.2 | DS14: 0 | DT14: -0.1 | DU14: 0.1 | DV14: 0.2 | DX14: -2.9 | DY14: 0.1 | DZ14: 0.6 | EA14: 0.3 | EB14: 0.3 | EC14: 0.8 | ED14: 4 | EE14: 0 | EF14: 0 | EG14: 0 | EJ14: 1.9 | EK14: 0 | EL14: 1.5 | EM14: 0.1 | EN14: 0.1 | EO14: 0.1 | EQ14: 0 | ER14: 0 | ES14: 0 | ET14: -0.2 | EU14: 0 | EV14: 3.6 | EW14: 0 | EX14: 0 | EY14: 0.1 | EZ14: 0.4 | FA14: 2.9 | FB14: 11.56 | FC14: 11.76 | FD14: 1.7 | FF14: 1.6 | FI14: 56.739 | FK14: 1.8305 | FL14: 0.587 | FM14: 0 | FN14: 1.3 | FO14: 0.30108 | FP14: 0.21093 | FQ14: -0.1 | FR14: 1.7 | FS14: 5.82951
A15: 04/07/2025 | B15: 02:30 | C15: -6.8 | D15: 36.2 | E15: 24.86 | H15: -10.9 | I15: -14.1 | L15: -28.4 | M15: -32.1 | N15: -6.6 | O15: 23.2 | P15: 19.6 | Q15: 28 | R15: 32.9 | S15: 0.1 | X15: -0.1 | Y15: 0.4 | AA15: -3.5 | AB15: 5 | AC15: 4.6 | AH15: -5.9 | AI15: -1.8 | AM15: -1.4 | AN15: 0 | AO15: 1.4 | AP15: 7.6 | AQ15: 7.6 | AR15: -1.4 | AS15: 2.7 | AT15: 0.8 | AU15: 15.524 | AV15: 12.016 | AW15: -44.722 | AX15: -5.1 | AY15: -2.2 | AZ15: 0.7 | BA15: -1.8 | BB15: 0.8 | BC15: 0.9 | BD15: 0 | BE15: -0.9 | BH15: -6 | BK15: 0 | BO15: -4.2 | BP15: -23.9 | BQ15: -25.5 | BR15: -6.2 | BS15: 11.1 | BY15: 0 | CB15: -0.7 | CC15: 15.7 | CD15: 15.4 | CE15: 5.6 | CF15: -0.6 | CG15: 0 | CK15: -8.7 | CL15: -6.3 | CM15: -46.4 | CS15: -1.6 | CT15: -6.4 | CV15: -5.7 | CW15: 0 | CZ15: 0.9 | DA15: 0 | DB15: 0 | DD15: 0 | DE15: 0.6 | DF15: 0.1 | DG15: -0.5 | DH15: 0 | DI15: 0.6 | DK15: 0 | DL15: 0 | DM15: 0.1 | DN15: 5 | DO15: 1.5 | DP15: 0.7 | DQ15: 0.3 | DR15: 1.2 | DS15: 0 | DT15: 0.1 | DU15: 0.1 | DV15: 0.2 | DX15: -2.9 | DY15: 0.2 | DZ15: 0.6 | EA15: 0.2 | EB15: 0.2 | EC15: 0.8 | ED15: 3.9 | EE15: 0 | EF15: 0 | EG15: 0 | EJ15: 1.9 | EK15: 0 | EL15: 1.6 | EM15: 0.1 | EN15: 0.1 | EO15: 0.1 | EQ15: 0 | ER15: 0 | ES15: 0 | ET15: -0.2 | EU15: 0 | EV15: 3.6 | EW15: 0 | EX15: 0 | EY15: 0.1 | EZ15: 0.4 | FA15: 2.9 | FB15: 11.1 | FC15: 11.31 | FD15: 3.3 | FF15: 1.9 | FI15: 14.888 | FK15: 1.90255 | FL15: 0.513 | FM15: 0 | FN15: 1.3 | FO15: 0.30068 | FP15: 0.21855 | FQ15: -0.7 | FR15: 1.5 | FS15: 5.03478
A16: 04/07/2025 | B16: 03:00 | C16: -6.9 | D16: 39.05 | E16: 25.45 | H16: -10.7 | I16: -7 | L16: -26.7 | M16: -33.1 | N16: -8.8 | O16: 25.6 | P16: 21 | Q16: 28.8 | R16: 35.7 | S16: 0 | X16: 0.1 | Y16: 0.6 | AA16: -3.6 | AB16: 4.9 | AC16: 4.6 | AH16: -7.8 | AI16: -2 | AM16: -1.4 | AN16: 0 | AO16: 1.4 | AP16: 7.9 | AQ16: 7.5 | AR16: -1.1 | AS16: 2.7 | AT16: 0.2 | AU16: 17.711 | AV16: 14.176 | AW16: -42.98 | AX16: -2.8 | AY16: -2.1 | AZ16: 0.7 | BA16: -2.8 | BB16: 0.5 | BC16: 0.9 | BD16: 0 | BE16: -1.4 | BH16: -5.1 | BK16: 0 | BO16: -1.3 | BP16: -23.3 | BQ16: -24.7 | BR16: -5.4 | BS16: 12.6 | BY16: 0 | CB16: -0.7 | CC16: 16.1 | CD16: 15.5 | CE16: 5.9 | CF16: -0.6 | CG16: -0.1 | CK16: -6.5 | CL16: -4 | CM16: -43.5 | CS16: -1.5 | CT16: -6.4 | CV16: -5.7 | CW16: 0 | CZ16: 0.9 | DA16: 0 | DB16: 0 | DD16: 0 | DE16: 0.6 | DF16: 0.1 | DG16: -0.9 | DH16: 0 | DI16: 0.5 | DK16: 0 | DL16: 0 | DM16: 1.5 | DN16: 5.7 | DO16: 1.5 | DP16: 0.7 | DQ16: 0.3 | DR16: 1.2 | DS16: 0 | DT16: 0.1 | DU16: 0.1 | DV16: 0.2 | DX16: -2.9 | DY16: 0.2 | DZ16: 0.6 | EA16: 0.3 | EB16: 0.2 | EC16: 0.8 | ED16: 1.4 | EE16: 0 | EF16: 0 | EG16: 0 | EJ16: 1.9 | EK16: 0.2 | EL16: 1.5 | EM16: 0.1 | EN16: 0.1 | EO16: 0.1 | EQ16: 0 | ER16: 0 | ES16: 0 | ET16: -0.2 | EU16: 0 | EV16: 3.6 | EW16: 0 | EX16: 0 | EY16: 0.2 | EZ16: 0.4 | FA16: 2.9 | FB16: 11.89 | FC16: 12.07 | FD16: 1.2 | FF16: 1.5 | FI16: 50.167 | FK16: 1.90316 | FL16: 0.512 | FM16: 0 | FN16: 1.3 | FO16: 0.30116 | FP16: 0.1992 | FQ16: -0.3 | FR16: 1.7 | FS16: 5.61552
A17: 04/07/2025 | B17: 03:30 | C17: -8.4 | D17: 29.89 | E17: 23.44 | H17: -10 | I17: -7.1 | L17: -26.7 | M17: -31.1 | N17: -4.2 | O17: 28.5 | P17: 20.7 | Q17: 29.5 | R17: 33.7 | S17: -0.1 | X17: 0 | Y17: 0.2 | AA17: -3.5 | AB17: 5.1 | AC17: 3.8 | AH17: -7.9 | AI17: -1.9 | AM17: -1.5 | AN17: 0 | AO17: 1.6 | AP17: 0 | AQ17: 7.7 | AR17: -1.1 | AS17: 2.7 | AT17: 0.4 | AU17: 18.082 | AV17: 14.541 | AW17: -42.677 | AX17: -0.3 | AY17: -1.9 | AZ17: 0.7 | BA17: -3.9 | BB17: 0.1 | BC17: 0.9 | BD17: 0 | BE17: -0.8 | BH17: -5.4 | BK17: 0 | BO17: -0.6 | BP17: -22.2 | BQ17: -23.7 | BR17: -4.6 | BS17: 13.1 | BY17: 0 | CB17: -0.7 | CC17: 16.3 | CD17: 15.6 | CE17: 6.8 | CF17: -0.5 | CG17: 0 | CK17: -6.3 | CL17: -3.7 | CM17: -43 | CS17: -1.9 | CT17: -6.6 | CV17: -5.7 | CW17: 0 | CZ17: 0.9 | DA17: -0.1 | DB17: 0 | DD17: 0.1 | DE17: 0.6 | DF17: 0.1 | DG17: -1.1 | DH17: 0 | DI17: 0.5 | DK17: 0 | DL17: 0 | DM17: 1.3 | DN17: 4.9 | DO17: 1.5 | DP17: 0.5 | DQ17: 0.3 | DR17: 1.2 | DS17: 0 | DT17: 0.1 | DU17: 0.1 | DV17: 0.2 | DX17: -2.9 | DY17: 0.2 | DZ17: 0.6 | EA17: 0.3 | EB17: 0.2 | EC17: 0.8 | ED17: 0.3 | EE17: 0 | EF17: 0 | EG17: 0 | EJ17: 1.9 | EK17: 0.2 | EL17: 1.4 | EM17: 0.1 | EN17: 0.1 | EO17: 0.1 | EQ17: 0 | ER17: 0 | ES17: 0 | ET17: -0.2 | EU17: 0 | EV17: 3.6 | EW17: 0 | EX17: 0 | EY17: 0.2 | EZ17: 0.4 | FA17: 2.9 | FB17: 11.66 | FC17: 11.9 | FD17: 1.5 | FF17: 1.7 | FI17: 43.436 | FK17: 1.91302 | FL17: 0.46 | FM17: 0 | FN17: 1.4 | FO17: 0.30343 | FP17: 0.19717 | FQ17: -0.3 | FR17: 1.8 | FS17: 5.77362
A18: 04/07/2025 | B18: 04:00 | C18: -7.4 | D18: 29.73 | E18: 23.5 | H18: -10.6 | I18: -11.9 | L18: -27.1 | M18: -35.5 | N18: -8.5 | O18: 27.8 | P18: 20.4 | Q18: 28.8 | R18: 35.8 | S18: -0.1 | X18: 0 | Y18: 0.4 | AA18: -3.6 | AB18: 5.2 | AC18: 3.9 | AH18: -7.7 | AI18: -1.6 | AM18: -1.5 | AN18: 0 | AO18: 1.5 | AP18: 0 | AQ18: 8 | AR18: -1 | AS18: 2.7 | AT18: 1.1 | AU18: 18.432 | AV18: 14.28 | AW18: -42.74 | AX18: -3.2 | AY18: -2.1 | AZ18: 0.6 | BA18: -4.1 | BB18: -0.3 | BC18: 0.9 | BD18: 0 | BE18: -2.2 | BH18: -5.9 | BK18: 0 | BO18: -1.5 | BP18: -22.4 | BQ18: -24 | BR18: -5.1 | BS18: 12.8 | BY18: 0 | CB18: -0.7 | CC18: 15.9 | CD18: 15.9 | CE18: 6 | CF18: -0.5 | CG18: 0 | CK18: -6.7 | CL18: -4.3 | CM18: -43.7 | CS18: -1.5 | CT18: -6.4 | CV18: -5.7 | CW18: 0 | CZ18: 0.9 | DA18: -0.1 | DB18: -0.3 | DD18: 0 | DE18: 0.6 | DF18: 0.1 | DG18: -1.1 | DH18: 0 | DI18: 0.5 | DK18: 0 | DL18: 0 | DM18: 1.6 | DN18: 6.7 | DO18: 1.5 | DP18: 0.7 | DQ18: 0.3 | DR18: 1.2 | DS18: 0 | DT18: 0.1 | DU18: 0.1 | DV18: 0.2 | DX18: -2.9 | DY18: 0.1 | DZ18: 0.6 | EA18: 0.3 | EB18: 0.2 | EC18: 0.8 | ED18: 4 | EE18: 0 | EF18: 0 | EG18: 0 | EJ18: 1.9 | EK18: 0.2 | EL18: 1.4 | EM18: 0.1 | EN18: 0.1 | EO18: 0.1 | EQ18: 0 | ER18: 0 | ES18: 0 | ET18: -0.2 | EU18: 0 | EV18: 3.6 | EW18: 0 | EX18: 0 | EY18: 0.2 | EZ18: 0.4 | FA18: 2.9 | FB18: 11.7 | FC18: 11.96 | FD18: 1.2 | FF18: 2.1 | FI18: 27.862 | FK18: 1.9309 | FL18: 0.459 | FM18: 0 | FN18: 1.4 | FO18: 0.29699 | FP18: 0.19033 | FQ18: -0.3 | FR18: 1.7 | FS18: 5.67722
A19: 04/07/2025 | B19: 04:30 | C19: -7.5 | D19: 35.44 | E19: 24.89 | H19: -9.6 | I19: -2 | L19: -25.9 | M19: -29.8 | N19: -3.3 | O19: 27.5 | P19: 20.9 | Q19: 29 | R19: 34.3 | S19: 0.1 | X19: 0.1 | Y19: 0.8 | AA19: -3.5 | AB19: 5.3 | AC19: 4.3 | AH19: -7 | AI19: -1.2 | AM19: -1.4 | AN19: 0 | AO19: 1.6 | AP19: 0 | AQ19: 7.6 | AR19: -0.9 | AS19: 2.7 | AT19: 0.6 | AU19: 18.636 | AV19: 15.036 | AW19: -41.957 | AX19: -2.8 | AY19: -2.1 | AZ19: 0.6 | BA19: -1.9 | BB19: 0.7 | BC19: 0.9 | BD19: 0 | BE19: -1.1 | BH19: -5.3 | BK19: 0 | BO19: -1.6 | BP19: -22.6 | BQ19: -24.2 | BR19: -4.8 | BS19: 10.6 | BY19: 0 | CB19: -0.7 | CC19: 15.3 | CD19: 15.3 | CE19: 5.5 | CF19: -0.3 | CG19: 0 | CK19: -5.6 | CL19: -3.1 | CM19: -42 | CS19: -1.3 | CT19: -6.2 | CV19: -5.7 | CW19: 0 | CZ19: 0.9 | DA19: 0 | DB19: -0.3 | DD19: 0 | DE19: 0.5 | DF19: 0.1 | DG19: -1.1 | DH19: 0 | DI19: 0.5 | DK19: 0 | DL19: 0 | DM19: 0.1 | DN19: 5.3 | DO19: 1.5 | DP19: 0.7 | DQ19: 0.3 | DR19: 1.2 | DS19: 0 | DT19: 0.2 | DU19: 0.1 | DV19: 0.2 | DX19: -2.9 | DY19: 0.1 | DZ19: 0.6 | EA19: 0.3 | EB19: 0.2 | EC19: 0.8 | ED19: 4 | EE19: 0 | EF19: 0 | EG19: 0 | EJ19: 1.9 | EK19: 0.2 | EL19: 1.6 | EM19: 0.1 | EN19: 0.1 | EO19: 0.1 | EQ19: 0 | ER19: 0 | ES19: 0 | ET19: -0.2 | EU19: 0 | EV19: 3.7 | EW19: 0 | EX19: 0 | EY19: 0.2 | EZ19: 0.4 | FA19: 2.9 | FB19: 11.89 | FC19: 12.19 | FD19: 3 | FF19: 1.7 | FI19: 65.425 | FK19: 1.98027 | FL19: 0.461 | FM19: 0 | FN19: 1.4 | FO19: 0.29845 | FP19: 0.18812 | FQ19: -0.3 | FR19: 1.8 | FS19: 5.82784
A20: 04/07/2025 | B20: 05:00 | C20: -0.3 | D20: 27.79 | E20: 22.91 | H20: -10.5 | I20: -14.3 | L20: -27.7 | M20: -32.6 | N20: -6.1 | O20: 23.7 | P20: 18.8 | Q20: 28 | R20: 29.3 | S20: 0.1 | X20: -1.2 | Y20: 0.4 | AA20: -3.4 | AB20: 5.6 | AC20: 5.3 | AH20: -6.7 | AI20: -1.4 | AM20: -1.4 | AN20: 0 | AO20: 1.6 | AP20: 0 | AQ20: 7.4 | AR20: -1.4 | AS20: 2.7 | AT20: 0.8 | AU20: 14.739 | AV20: 11.133 | AW20: -45.671 | AX20: -2.6 | AY20: -2 | AZ20: 0.6 | BA20: -2.9 | BB20: 0.5 | BC20: 0.9 | BD20: 0 | BE20: -1 | BH20: -6.1 | BK20: 0 | BO20: -3.6 | BP20: -24.4 | BQ20: -26 | BR20: -6.6 | BS20: 10.3 | BY20: 0 | CB20: -0.7 | CC20: 14.6 | CD20: 15.6 | CE20: 5.8 | CF20: 1.2 | CG20: -0.2 | CK20: -8.4 | CL20: -5.7 | CM20: -45.9 | CS20: -1.2 | CT20: -6.2 | CV20: -5.7 | CW20: 0 | CZ20: 0.9 | DA20: 0 | DB20: -0.3 | DD20: 0 | DE20: 0.5 | DF20: 0.1 | DG20: -1.5 | DH20: 0 | DI20: 0.5 | DK20: 0 | DL20: 0 | DM20: 0.2 | DN20: 5.4 | DO20: 1.5 | DP20: 0.7 | DQ20: 0.4 | DR20: 1.2 | DS20: 0.2 | DT20: 0.1 | DU20: 0.1 | DV20: 0.1 | DX20: -2.9 | DY20: 0 | DZ20: 0.6 | EA20: 0.2 | EB20: 0.2 | EC20: 0.8 | ED20: 4 | EE20: 0.4 | EF20: 0 | EG20: 0 | EJ20: 1.9 | EK20: 0.2 | EL20: 1.8 | EM20: 0.1 | EN20: 0.1 | EO20: 0.1 | EQ20: 0 | ER20: 0 | ES20: 0 | ET20: -0.2 | EU20: 0 | EV20: 3.6 | EW20: 0 | EX20: 0 | EY20: 0.2 | EZ20: 0.4 | FA20: 3 | FB20: 11.7 | FC20: 12.07 | FD20: 2.9 | FF20: 1.8 | FI20: 0.971 | FK20: 1.97562 | FL20: 0.567 | FM20: 0 | FN20: 1.3 | FO20: 0.30446 | FP20: 0.26364 | FQ20: -0.5 | FR20: 1.5 | FS20: 5.41072
A21: 04/07/2025 | B21: 05:30 | C21: 0.4 | D21: 28.81 | E21: 23.07 | H21: -8.1 | I21: -15.5 | L21: -25.6 | M21: -30 | N21: -3.8 | O21: 25.5 | P21: 20.3 | Q21: 29.2 | R21: 29.8 | S21: 0.1 | X21: 0.3 | Y21: 0.9 | AA21: -3.4 | AB21: 5.6 | AC21: 4.6 | AH21: -7.4 | AI21: -1.4 | AM21: -1.5 | AN21: -25.3 | AO21: 1.2 | AP21: 0 | AQ21: 7.3 | AR21: -0.1 | AS21: 2.7 | AT21: 0.9 | AU21: 16.802 | AV21: 13.111 | AW21: -44.277 | AX21: -3.1 | AY21: -2.1 | AZ21: 0.6 | BA21: -3.5 | BB21: 0.8 | BC21: 1 | BD21: 0 | BE21: -1.9 | BH21: -5.4 | BK21: 0 | BO21: -9.7 | BP21: -23.2 | BQ21: -24.7 | BR21: -5.2 | BS21: 10.5 | BY21: 0 | CB21: -0.7 | CC21: 14.8 | CD21: 15.8 | CE21: 6.4 | CF21: -0.6 | CG21: -0.1 | CK21: -6 | CL21: -3.5 | CM21: -42.7 | CS21: -0.8 | CT21: -6 | CV21: -5.7 | CW21: 0 | CZ21: 0.9 | DA21: 0 | DB21: -0.3 | DD21: 0 | DE21: 0.5 | DF21: 0.1 | DG21: -0.9 | DH21: 0 | DI21: 0.5 | DK21: 0 | DL21: 0 | DM21: 1.4 | DN21: 5.4 | DO21: 1.5 | DP21: 0.7 | DQ21: 0.4 | DR21: 1.2 | DS21: 0.2 | DT21: 0.1 | DU21: 0.1 | DV21: 0.1 | DX21: -2.9 | DY21: 0.2 | DZ21: 0.6 | EA21: 0.3 | EB21: 0.2 | EC21: 0.8 | ED21: 4 | EE21: 0.4 | EF21: 0 | EG21: 0 | EJ21: 1.9 | EK21: 0.1 | EL21: 1.8 | EM21: 0.1 | EN21: 0.1 | EO21: 0.1 | EQ21: 0 | ER21: 0 | ES21: 0 | ET21: -0.2 | EU21: 0 | EV21: 3.7 | EW21: 0 | EX21: 0 | EY21: 0.1 | EZ21: 0.4 | FA21: 3 | FB21: 13.14 | FC21: 13.4 | FD21: 2.1 | FF21: 2 | FI21: 6.456 | FK21: 1.76512 | FL21: 0.573 | FM21: 0 | FN21: 1.4 | FO21: 0.30696 | FP21: 0.19703 | FQ21: 0 | FR21: 1.5 | FS21: 5.74211
A22: 04/07/2025 | B22: 06:00 | C22: 0.5 | D22: 24.15 | E22: 22.59 | H22: -8.4 | I22: -13.6 | L22: -25 | M22: -31.7 | N22: -5.7 | O22: 28.8 | P22: 21.4 | Q22: 29.8 | R22: 35.1 | S22: 0 | X22: -0.1 | Y22: 1 | AA22: -3.4 | AB22: 5.7 | AC22: 5.9 | AH22: -7 | AI22: -1.2 | AM22: -1.4 | AN22: -27.8 | AO22: 0.7 | AP22: 0 | AQ22: 7.8 | AR22: -1 | AS22: 2.7 | AT22: 0.8 | AU22: 20.747 | AV22: 17.023 | AW22: -39.63 | AX22: -4.6 | AY22: -2 | AZ22: 0.5 | BA22: -5.4 | BB22: -0.5 | BC22: 1 | BD22: 0 | BE22: -4.5 | BH22: -4 | BK22: 0 | BO22: -8.7 | BP22: -21.2 | BQ22: -22.7 | BR22: -3.8 | BS22: 13.6 | BY22: 0 | CB22: -0.7 | CC22: 15.6 | CD22: 15.4 | CE22: 5.5 | CF22: -0.5 | CG22: 0.1 | CK22: -1.5 | CL22: 0.8 | CM22: -36.2 | CS22: 1.5 | CT22: -4.7 | CV22: -5.7 | CW22: 0 | CZ22: 0.9 | DA22: 0 | DB22: -0.3 | DD22: -0.1 | DE22: 0.8 | DF22: 0.1 | DG22: -0.1 | DH22: 0 | DI22: 0.6 | DK22: 0 | DL22: 0 | DM22: 0.7 | DN22: 5.7 | DO22: 1.5 | DP22: 0.7 | DQ22: 0.4 | DR22: 1.2 | DS22: 0.8 | DT22: 0.1 | DU22: 0.1 | DV22: 0.1 | DX22: -2.9 | DY22: 0.1 | DZ22: 0.6 | EA22: 0.3 | EB22: 0.3 | EC22: 0.8 | ED22: 4 | EE22: 0.3 | EF22: 0 | EG22: 0 | EJ22: 1.9 | EK22: 0.2 | EL22: 1.8 | EM22: 0.1 | EN22: 0.1 | EO22: 0.1 | EQ22: 0 | ER22: 0 | ES22: 0 | ET22: -0.2 | EU22: 0 | EV22: 3.7 | EW22: 0 | EX22: 0 | EY22: 0.2 | EZ22: 0.4 | FA22: 3 | FB22: 13.71 | FC22: 13.88 | FD22: 4 | FF22: 2.7 | FI22: 48.37 | FK22: 1.72839 | FL22: 0.604 | FM22: 0 | FN22: 1.3 | FO22: 0.30798 | FP22: 0.26268 | FQ22: 0.5 | FR22: 1.6 | FS22: 6.30305
... A58: 05/07/2025 | B58: 00:00 | C58: 12.4 | D58: 38.34 | E58: 23.4 | H58: -14.1 | I58: -3.6 | L58: -29.3 | M58: -41 | N58: -15.7 | O58: 16.4 | P58: -4.1 | Q58: 0.7 | R58: 52.9 | S58: 0.1 | X58: 2.4 | Y58: 0.6 | AA58: -3.3 | AB58: 2.1 | AC58: 7 | AH58: -3.8 | AI58: -1.3 | AM58: -1.8 | AN58: -15.3 | AO58: 1 | AP58: 12.6 | AQ58: 5.8 | AR58: 0.2 | AS58: 2.6 | AT58: 1.5 | AU58: 21.55107 | AV58: 0 | AW58: -57.01905 | AX58: -6.1 | AY58: -1.4 | AZ58: 0.6 | BA58: -3.6 | BB58: 1.1 | BC58: 0.9 | BD58: 0 | BE58: -1.1 | BH58: -2.5 | BK58: -1.9 | BO58: 3 | BP58: -14.2 | BQ58: -15.6 | BR58: -3.4 | BS58: 28.4 | BY58: 0 | CB58: -0.5 | CC58: 22.1 | CD58: 19.7 | CE58: 2.9 | CF58: 4.7 | CG58: -0.1 | CK58: 1.5 | CL58: 4 | CM58: -31.8 | CS58: -3.1 | CT58: -7.3 | CV58: -5.3 | CW58: 0 | CZ58: 0.9 | DA58: -0.1 | DB58: -0.1 | DD58: -0.2 | DE58: 0.5 | DF58: 0.1 | DG58: 0 | DH58: 0.2 | DI58: 0.5 | DK58: 0 | DL58: 0 | DM58: -0.1 | DN58: 6 | DO58: 1.8 | DP58: 0.7 | DQ58: 0.3 | DR58: 1.2 | DS58: 0 | DT58: -0.1 | DU58: 0.1 | DV58: 0.2 | DX58: -2.8 | DY58: 0 | DZ58: 0.6 | EA58: 0.4 | EB58: 0.6 | EC58: 0.8 | ED58: 4 | EE58: 0 | EF58: -8.5 | EG58: -11.3 | EJ58: 1.9 | EK58: 0.1 | EL58: 1.4 | EM58: 0.1 | EN58: 0.1 | EO58: 0.1 | EQ58: 0 | ER58: 0 | ES58: 0 | ET58: -0.2 | EU58: 0 | EV58: 1 | EW58: 0 | EX58: 0 | EY58: 0.2 | EZ58: 0.8 | FA58: 2.7 | FB58: 0 | FC58: 0 | FD58: 3.1 | FF58: 2.4 | FI58: 11.67202 | FK58: 1.73986 | FL58: -0.292 | FM58: 1.68 | FN58: 1.1 | FO58: 0.32339 | FP58: 0.25643 | FQ58: -0.7 | FR58: 0.4 | FS58: 4.50768
A59: EJEC | C59: 115.45 | D59: 768.38 | E59: 562.395 | F59: 0 | G59: 0 | H59: -191.9 | I59: 91.9 | J59: 0 | K59: 0 | L59: 294.45 | M59: 50.55 | N59: 123.3 | O59: 685.05 | P59: 511.45 | Q59: 610.15 | R59: 1082.55 | S59: 1.3 | T59: 0 | U59: 0 | V59: 0 | W59: 0 | X59: 27.25 | Y59: 15 | Z59: 0 | AA59: -80.5 | AB59: 82.75 | AC59: 272.6 | AD59: 0 | AE59: 0 | AF59: 0 | AG59: 0 | AH59: -25 | AI59: -50.9 | AJ59: 0 | AK59: 0 | AL59: 0 | AM59: -28.2 | AN59: -302.8 | AO59: 36.85 | AP59: 386.7 | AQ59: 182.6 | AR59: -10.3 | AS59: 64.1 | AT59: 21.5 | AU59: 615.40272 | AV59: 450.47131 | AW59: -1068.5228 | AX59: -52.45 | AY59: -53.9 | AZ59: 14.35 | BA59: -62.9 | BB59: 40.2 | BC59: 22.95 | BD59: 1.7 | BE59: -28.2 | BF59: 0 | BG59: 0 | BH59: -15.9 | BI59: 0 | BJ59: 0 | BK59: 28.4 | BL59: 0 | BM59: 0 | BN59: 0 | BO59: 82 | BP59: -219.8 | BQ59: -237.7 | BR59: -55.05 | BS59: 709.35 | BT59: 0 | BU59: 0 | BV59: 0 | BW59: 0 | BX59: 0 | BY59: -25.4 | BZ59: 0 | CA59: 0 | CB59: -14.95 | CC59: 803.45 | CD59: 652.35 | CE59: 200.2 | CF59: 96 | CG59: 7.1 | CH59: 0 | CI59: 0 | CJ59: 0 | CK59: 69.55 | CL59: 129.45 | CM59: -708.1 | CN59: 0 | CO59: 0 | CP59: 0 | CQ59: 0 | CR59: 0 | CS59: 83.15 | CT59: -80.95 | CU59: 0 | CV59: -132.05 | CW59: 48.85 | CX59: 0 | CY59: 0 | CZ59: 21.6 | DA59: -0.35 | DB59: -2.25 | DC59: 0 | DD59: -0.75 | DE59: 19.85 | DF59: 2.5 | DG59: 12.1 | DH59: 4.3 | DI59: 12.7 | DJ59: 0 | DK59: -6.4 | DL59: -12 | DM59: 14.5 | DN59: 158.75 | DO59: 34.65 | DP59: 15.4 | DQ59: 7.6 | DR59: 25.8 | DS59: -19.15 | DT59: 0.15 | DU59: 4.95 | DV59: 4.65 | DW59: 0 | DX59: -65.7 | DY59: 2.45 | DZ59: 14.05 | EA59: 8.6 | EB59: 12.65 | EC59: 18.45 | ED59: 87.6 | EE59: 15.9 | EF59: -88.85 | EG59: -103.95 | EH59: 0 | EI59: 0 | EJ59: 45.6 | EK59: 3.55 | EL59: 39.15 | EM59: 2.4 | EN59: 2.4 | EO59: 2.4 | EP59: 0 | EQ59: 19.35 | ER59: 12.9 | ES59: -9.95 | ET59: -4.8 | EU59: 31.9 | EV59: 59.15 | EW59: -27.65 | EX59: 11.6 | EY59: 7.85 | EZ59: 16.85 | FA59: 70.15 | FB59: 277.655 | FC59: 246.375 | FD59: 58.7 | FE59: 0 | FF59: 50.4 | FG59: 0 | FH59: 0 | FI59: 7711.5062 | FK59: 41.50788 | FL59: 0.226 | FM59: 23.595 | FN59: 30.55 | FO59: 7.078725 | FP59: 10.879235 | FQ59: 10.95 | FR59: 40.1 | FS59: 164.88684

Sheet DEMANDA_AREAS
B3: viernes, 4 de Julio del 2025
B5: REPORTE DE LA DEMANDA POR ÁREAS Y SUBAREAS OPERATIVAS (MW)
B6: FECHA HORA | C6: DEMANDA | E6: AREA | H6: SUBAREAS
C7: INTERCAMBIOS INTERNACIONALES | D7: SEIN | E7: NORTE | F7: CENTRO | G7: SUR | H7: ELECTROANDES
B8: 00:30 | C8: 0 | D8: 6447.913 | E8: 925.824 | F8: 3812.9298 | G8: 1709.1592 | H8: 239.9204
B9: 01:00 | C9: 0 | D9: 6255.544 | E9: 936.3212 | F9: 3654.5247 | G9: 1664.6981 | H9: 226.9481
B10: 01:30 | C10: 0 | D10: 6203.069 | E10: 884.6523 | F10: 3650.614 | G10: 1667.8027 | H10: 231.6678
B11: 02:00 | C11: 0 | D11: 6079.542 | E11: 898.453 | F11: 3541.9543 | G11: 1639.1347 | H11: 234.9179
B12: 02:30 | C12: 0 | D12: 6105.447 | E12: 854.5214 | F12: 3619.1037 | G12: 1631.8219 | H12: 237.0574
B13: 03:00 | C13: 0 | D13: 6091.526 | E13: 891.2439 | F13: 3565.2763 | G13: 1635.0058 | H13: 236.5427
B14: 03:30 | C14: 0 | D14: 6045.647 | E14: 885.201 | F14: 3544.0305 | G14: 1616.4155 | H14: 239.2079
B15: 04:00 | C15: 0 | D15: 6034.764 | E15: 860.4717 | F15: 3545.866 | G15: 1628.4263 | H15: 238.3714
B16: 04:30 | C16: 0 | D16: 6068.898 | E16: 897.4621 | F16: 3534.527 | G16: 1636.9089 | H16: 237.6433
B17: 05:00 | C17: 0 | D17: 6068.494 | E17: 864.9018 | F17: 3564.631 | G17: 1638.9612 | H17: 238.4549
B18: 05:30 | C18: 0 | D18: 6229.593 | E18: 891.3273 | F18: 3674.0578 | G18: 1664.2079 | H18: 232.6042
B19: 06:00 | C19: 0 | D19: 6271.869 | E19: 920.0737 | F19: 3679.7203 | G19: 1672.075 | H19: 221.9888
... B59: ENERGÍA | C59: 0 | D59: 166237.25 | E59: 24874.551 | F59: 100085.15 | G59: 41277.544 | H59: 5379.4453
B61: LEYENDA:
D63: Potencia recibida del Ecuador
D64: Potencia entregada al Ecuador

Sheet DEMANDA_UL
B3: viernes, 4 de Julio del 2025
B5: POTENCIA DE LOS GRANDES USUARIOS LIBRES (MW)
B6: FECHA HORA | C6: GRANDES USUARIOS LIBRES DEL ÁREA NORTE | X6: GRANDES USUARIOS LIBRES DEL ÁREA CENTRO | BP6: GRANDES USUARIOS LIBRES DEL ÁREA SUR
C7: ARCA CONTINENTAL LINDLEY S.A. | D7: AUSTRAL GROUP S.A.A | E7: CEMENTOS PACASMAYO | F7: CONSORCIO MINERO HORIZONTE S.R.L. | G7: CORPORACIÓN PESQUERA INCA S.A.C. | H7: CREDITEX: CIA IND.TEXTIL CREDISA | I7: HIPERMERCADOS TOTTUS S.A | J7: INDUSTRIA TEXTIL PIURA | K7: MINERA BOROO MISQUICHILCA S.A. | L7: MINERA GOLD FIELDS | M7: MINERA MARSA | N7: MINERA MISKY MAYO | O7: MINERA YANACOCHA | P7: OPEN PLAZA | Q7: PESQUERA DIAMANTE | R7: PETROPERU | S7: REAL PLAZA S.R.L. | T7: SIDER PERU | U7: SUPERMERCADOS PERUANOS S.A. | V7: TRUPAL S.A. | W7: UNIÓN DE CERVECERÍAS PERUANAS BACKUS Y JOHNSTON S. | X7: ACEROS AREQUIPA | Y7: ADMINISTRADORA JOCKEY PLAZA SHOPPING CENTER S.A. | Z7: ALICORP | AA7: ARCA CONTINENTAL LINDLEY S.A. | AB7: AUSTRAL GROUP S.A.A | AC7: COMPAÑIA MINERA CONDESTABLE | AD7: CORPORACIÓN PESQUERA INCA S.A.C. | AE7: CREDITEX: CIA IND.TEXTIL CREDISA | AF7: FUNDICION CHILCA S.A. | AG7: HIPERMERCADOS TOTTUS S.A | AH7: INMOBILIARIA KANPU S.A. | AI7: INMUEBLES PANAMERICANA S.A. | AJ7: KIMBERLY-CLARK PERU | AK7: LECHE GLORIA S.A. | AL7: MALL AVENTURA S.A. | AM7: MARCOBRE S.A.C. | AN7: MINERA ANTAMINA | AO7: MINERA ARES | AP7: MINERA BUENAVENTURA | AQ7: MINERA CHINALCO PERÚ S.A. | AR7: MINERA SHOUXIN PERU S.A. | AS7: MINERA VOLCAN | AT7: MINSUR | AU7: MOLYCOP-ADESUR | AV7: NEXA RESOURCES CAJAMARQUILLA S.A. | AW7: NEXA RESOURCES PERÚ S.A.A. | AX7: OPEN PLAZA | AY7: OPP FILM | AZ7: OWENS-ILLINOIS PERÚ S.A. | BA7: PAPELERA NACIONAL S.A. | BB7: PESQUERA DIAMANTE | BC7: QUIMPAC S.A. | BD7: REAL PLAZA S.R.L. | BE7: REFINERIA LA PAMPILLA S.A.A | BF7: SAGA FALABELLA | BG7: SAN MIGUEL INDUSTRIAS PET S.A. | BH7: SHOUGANG HIERRO PERU | BI7: SOFTYS PERU S.A.C. | BJ7: SUPERMERCADOS PERUANOS S.A. | BK7: TEJIDOS SAN JACINTO | BL7: TREN URBANO DE LIMA S.A. | BM7: TRUPAL S.A. | BN7: UNACEM PERU S.A. | BO7: UNIÓN DE CERVECERÍAS PERUANAS BACKUS Y JOHNSTON S. | BP7: ANGLO AMERICAN QUELLAVECO S.A. | BQ7: ARCA CONTINENTAL LINDLEY S.A. | BR7: CAL & CEMENTO SUR S.A. | BS7: COMPAÑIA MINERA ANTAPACCAY S.A. | BT7: COMPAÑÍA MINERA CHUNGAR SAC | BU7: COMPAÑIA MINERA SAN IGNACIO DE MOROCOCHA S.A.A. | BV7: EL BROCAL .S.A. | BW7: EMPRESA ADMINISTRADORA CERRO S.A.C. | BX7: EMPRESA MINERA LOS QUENUALES S.A.C. | BY7: HIPERMERCADOS TOTTUS S.A | BZ7: HUDBAY PERU S.A.C. | CA7: INDUSTRIA CACHIMAYO | CB7: MALL AVENTURA S.A. | CC7: MINERA ARES | CD7: MINERA BUENAVENTURA | CE7: MINERA CERRO VERDE | CF7: MINERA CORONA | CG7: MINERA LAS BAMBAS S.A. | CH7: MINERA VOLCAN | CI7: MINSUR | CJ7: MOLYCOP-ADESUR | CK7: NEXA RESOURCES PERÚ S.A.A. | CL7: OXIDOS DE PASCO S.A.C. | CM7: PESQUERA DIAMANTE | CN7: REAL PLAZA S.R.L. | CO7: SOBREANDES S.A.C. | CP7: SOUTHERN PERU CC | CQ7: SUPERMERCADOS PERUANOS S.A. | CR7: UNACEM PERU S.A. | CS7: UNIÓN DE CERVECERÍAS PERUANAS BACKUS Y JOHNSTON S. | CT7: YURA
B8: 00:30 | E8: 32.4453 | F8: 12.947 | L8: 25.88 | M8: 13.7282 | N8: 14.01 | O8: 34.384 | R8: 50.25 | T8: 43.534 | V8: 0.6 | X8: 140.44997 | Z8: 8.7237 | AF8: 3.8 | AJ8: 5.33786 | AK8: 0 | AL8: 1.1023 | AM8: 48.94459 | AN8: 132.21157 | AO8: 28.52 | AP8: 0.81 | AQ8: 162.38 | AS8: 38.27668 | AT8: 27.825 | AV8: 195.71554 | AW8: 30.1296 | AY8: 1.49131 | BA8: 2.7 | BC8: 67.30032 | BE8: 12.5 | BH8: 71.00762 | BI8: 12.69181 | BK8: 5.76316 | BM8: 6.9897 | BN8: 37.42 | BO8: 1.92 | BP8: 135.49445 | BR8: 4.21047 | BS8: 136.53965 | BT8: 16.95171 | BV8: 34.0289 | BW8: 3.85819 | BZ8: 89.6622 | CA8: 24.74299 | CB8: 0.3316 | CC8: 0.58 | CD8: 23.4651 | CE8: 340.57309 | CF8: 11.2208 | CG8: 159.1802 | CH8: 17.40519 | CL8: 4.89985 | CO8: 16.50588 | CP8: 290.89 | CR8: 28.172 | CT8: 24.377
B9: 01:00 | E9: 36.2493 | F9: 13.484 | L9: 26.28771 | M9: 12.9748 | N9: 13.75 | O9: 33.996 | R9: 50.633 | T9: 50.5197 | V9: 0.6 | X9: 125.43695 | Z9: 8.68073 | AF9: 5.6 | AJ9: 5.33431 | AK9: 0 | AL9: 0.9038 | AM9: 49.14155 | AN9: 131.83497 | AO9: 27.5902 | AP9: 0.7 | AQ9: 159.19 | AS9: 37.94249 | AT9: 28.827 | AV9: 199.45859 | AW9: 29.4637 | AY9: 1.83695 | BA9: 2.8 | BC9: 67.66731 | BE9: 12.5 | BH9: 71.29466 | BI9: 13.32798 | BK9: 5.82238 | BM9: 7.142 | BN9: 38.02 | BO9: 1.95 | BP9: 136.04469 | BR9: 4.25332 | BS9: 137.73435 | BT9: 15.5644 | BV9: 34.026 | BW9: 3.96348 | BZ9: 89.1849 | CA9: 24.72894 | CB9: 0.3181 | CC9: 0.56 | CD9: 24.37095 | CE9: 343.8106 | CF9: 11.3555 | CG9: 157.0032 | CH9: 17.69389 | CL9: 4.54455 | CO9: 15.50671 | CP9: 291.11 | CR9: 28.209 | CT9: 24.307
B10: 01:30 | E10: 37.0392 | F10: 13.813 | L10: 25.93113 | M10: 12.9528 | N10: 13.74 | O10: 34.094 | R10: 50.391 | T10: 29.5165 | V10: 0.6 | X10: 106.44303 | Z10: 8.71138 | AF10: 3.6 | AJ10: 5.31128 | AK10: 0 | AL10: 0.8277 | AM10: 49.53529 | AN10: 128.73809 | AO10: 28.5836 | AP10: 0.64 | AQ10: 161.73 | AS10: 38.24244 | AT10: 28.799 | AV10: 197.95054 | AW10: 29.2588 | AY10: 2.02743 | BA10: 2.9 | BC10: 67.66985 | BE10: 12.5 | BH10: 70.87664 | BI10: 12.94756 | BK10: 5.83052 | BM10: 6.987 | BN10: 36.43 | BO10: 2.19 | BP10: 136.11043 | BR10: 4.3352 | BS10: 139.04621 | BT10: 16.92263 | BV10: 33.3084 | BW10: 4.0073 | BZ10: 88.918 | CA10: 24.83966 | CB10: 0.3377 | CC10: 0.57 | CD10: 24.28793 | CE10: 341.1392 | CF10: 11.18 | CG10: 155.1445 | CH10: 16.93758 | CL10: 4.35952 | CO10: 15.79385 | CP10: 289.63 | CR10: 27.516 | CT10: 24.379
B11: 02:00 | E11: 36.8432 | F11: 13.206 | L11: 26.03219 | M11: 13.105 | N11: 13.61 | O11: 33.624 | R11: 50.405 | T11: 37.2724 | V11: 0.6 | X11: 130.85024 | Z11: 8.47413 | AF11: 4.3 | AJ11: 5.27359 | AK11: 0 | AL11: 0.8051 | AM11: 48.16379 | AN11: 129.89086 | AO11: 28.8822 | AP11: 0.44 | AQ11: 162.27 | AS11: 38.48164 | AT11: 28.353 | AV11: 198.08032 | AW11: 29.6593 | AY11: 1.96115 | BA11: 2.7 | BC11: 67.51025 | BE11: 12.5 | BH11: 76.97653 | BI11: 12.94886 | BK11: 5.79667 | BM11: 7.321 | BN11: 36.5 | BO11: 2.11 | BP11: 139.86502 | BR11: 4.2385 | BS11: 137.7528 | BT11: 15.80935 | BV11: 34.0295 | BW11: 3.7307 | BZ11: 91.5778 | CA11: 24.83862 | CB11: 0.3448 | CC11: 0.56 | CD11: 24.93548 | CE11: 343.62143 | CF11: 11.1601 | CG11: 154.8277 | CH11: 16.72515 | CL11: 4.35968 | CO11: 15.75285 | CP11: 281.82 | CR11: 28.498 | CT11: 24.54
B12: 02:30 | E12: 31.6895 | F12: 13.254 | L12: 26.23949 | M12: 13.3606 | N12: 13.71 | O12: 33.538 | R12: 50.481 | T12: 43.5896 | V12: 0.6 | X12: 144.29742 | Z12: 8.35225 | AF12: 3.5 | AJ12: 5.22184 | AK12: 0 | AL12: 0.7782 | AM12: 47.83302 | AN12: 130.6964 | AO12: 28.9356 | AP12: 0.41 | AQ12: 161.16 | AS12: 39.19009 | AT12: 28.622 | AV12: 199.46687 | AW12: 29.4557 | AY12: 2.09175 | BA12: 2.7 | BC12: 67.43084 | BE12: 12.5 | BH12: 73.12142 | BI12: 13.26738 | BK12: 5.76553 | BM12: 7.121 | BN12: 38.29 | BO12: 2.1 | BP12: 135.76314 | BR12: 4.32158 | BS12: 137.01975 | BT12: 14.39191 | BV12: 33.9463 | BW12: 3.87202 | BZ12: 90.515 | CA12: 24.85513 | CB12: 0.3305 | CC12: 0.55 | CD12: 26.34755 | CE12: 339.50214 | CF12: 11.1484 | CG12: 152.08 | CH12: 16.80498 | CL12: 4.37541 | CO12: 15.97382 | CP12: 281.3 | CR12: 29.166 | CT12: 24.343
B13: 03:00 | E13: 33.4209 | F13: 13.466 | L13: 26.15042 | M13: 13.2648 | N13: 13.71 | O13: 33.356 | R13: 50.69 | T13: 45.2161 | V13: 0.6 | X13: 133.89138 | Z13: 8.20822 | AF13: 4.3 | AJ13: 4.81592 | AK13: 0 | AL13: 0.7312 | AM13: 49.62152 | AN13: 131.73447 | AO13: 29.2492 | AP13: 0.67 | AQ13: 160.04 | AS13: 37.82484 | AT13: 27.948 | AV13: 199.50234 | AW13: 29.8021 | AY13: 2.1948 | BA13: 2.8 | BC13: 67.36379 | BE13: 12.5 | BH13: 69.18199 | BI13: 13.21042 | BK13: 5.68432 | BM13: 6.987 | BN13: 38.85 | BO13: 1.92 | BP13: 137.68155 | BR13: 4.29771 | BS13: 134.95419 | BT13: 14.92129 | BV13: 34.1775 | BW13: 3.96593 | BZ13: 89.0432 | CA13: 24.85801 | CB13: 0.3176 | CC13: 0.55 | CD13: 26.1392 | CE13: 337.46635 | CF13: 11.4739 | CG13: 155.5203 | CH13: 17.44586 | CL13: 4.37253 | CO13: 16.33993 | CP13: 292.18 | CR13: 28.728 | CT13: 24.409
B14: 03:30 | E14: 35.9161 | F14: 13.121 | L14: 25.74655 | M14: 13.2462 | N14: 13.75 | O14: 32.638 | R14: 50.267 | T14: 42.3176 | V14: 0.6 | X14: 91.12377 | Z14: 8.291 | AF14: 5.9 | AJ14: 5.05719 | AK14: 0 | AL14: 0.7036 | AM14: 47.61054 | AN14: 129.23087 | AO14: 28.5545 | AP14: 0.48 | AQ14: 162.13 | AS14: 38.80158 | AT14: 28.509 | AV14: 199.61537 | AW14: 29.4889 | AY14: 2.50265 | BA14: 2.7 | BC14: 67.25582 | BE14: 12.5 | BH14: 66.48154 | BI14: 13.19753 | BK14: 5.67628 | BM14: 6.897 | BN14: 44.41 | BO14: 2 | BP14: 136.26533 | BR14: 4.18185 | BS14: 132.19235 | BT14: 15.05257 | BV14: 34.6523 | BW14: 4.02736 | BZ14: 88.7967 | CA14: 24.88501 | CB14: 0.3036 | CC14: 0.53 | CD14: 25.50091 | CE14: 341.57382 | CF14: 11.4534 | CG14: 156.1076 | CH14: 17.81315 | CL14: 4.38294 | CO14: 15.99861 | CP14: 281.15 | CR14: 28.989 | CT14: 24.606
B15: 04:00 | E15: 37.7628 | F15: 13.053 | L15: 26.19718 | M15: 13.5524 | N15: 13.8 | O15: 32.476 | R15: 50.012 | T15: 41.2834 | V15: 0.6 | X15: 119.58834 | Z15: 8.77032 | AF15: 4.4 | AJ15: 5.19055 | AK15: 0 | AL15: 0.7363 | AM15: 47.73583 | AN15: 129.64383 | AO15: 28.5802 | AP15: 0.18 | AQ15: 161.42 | AS15: 39.0236 | AT15: 28.019 | AV15: 199.45949 | AW15: 29.2597 | AY15: 2.48754 | BA15: 2.8 | BC15: 66.97508 | BE15: 12.5 | BH15: 70.19323 | BI15: 13.14548 | BK15: 5.55131 | BM15: 6.987 | BN15: 48.79 | BO15: 1.96 | BP15: 136.49673 | BR15: 4.20092 | BS15: 129.86229 | BT15: 14.83268 | BV15: 34.94 | BW15: 3.88656 | BZ15: 87.2792 | CA15: 24.92102 | CB15: 0.2893 | CC15: 0.55 | CD15: 24.92233 | CE15: 345.56432 | CF15: 11.4839 | CG15: 155.0808 | CH15: 18.0081 | CL15: 4.52567 | CO15: 16.62422 | CP15: 287.17 | CR15: 30.123 | CT15: 24.553
B16: 04:30 | E16: 37.9724 | F16: 13.022 | L16: 26.09189 | M16: 14.7769 | N16: 13.52 | O16: 31.73 | R16: 50.712 | T16: 26.9046 | V16: 0.6 | X16: 160.62031 | Z16: 9.12734 | AF16: 3.3 | AJ16: 5.28152 | AK16: 0 | AL16: 0.7053 | AM16: 47.85091 | AN16: 125.56195 | AO16: 28.1771 | AP16: 1.65 | AQ16: 160.76 | AS16: 38.16629 | AT16: 27.598 | AV16: 199.00691 | AW16: 29.5568 | AY16: 2.28733 | BA16: 2.78 | BC16: 67.17546 | BE16: 12.5 | BH16: 71.96787 | BI16: 12.87739 | BK16: 5.8299 | BM16: 6.9897 | BN16: 49.17 | BO16: 1.66 | BP16: 137.80676 | BR16: 4.22442 | BS16: 131.42311 | BT16: 16.84418 | BV16: 36.0499 | BW16: 3.90366 | BZ16: 87.6175 | CA16: 25.19152 | CB16: 0.2783 | CC16: 0.56 | CD16: 24.03162 | CE16: 338.12506 | CF16: 11.0831 | CG16: 153.9229 | CH16: 17.8084 | CL16: 4.92286 | CO16: 16.29825 | CP16: 289.6 | CR16: 31.47 | CT16: 24.368
B17: 05:00 | E17: 38.8016 | F17: 13.049 | L17: 26.4596 | M17: 15.0564 | N17: 13.77 | O17: 30.204 | R17: 50.341 | T17: 39.9447 | V17: 0.6 | X17: 146.01092 | Z17: 9.15733 | AF17: 1.9 | AJ17: 5.03627 | AK17: 0 | AL17: 0.696 | AM17: 48.02222 | AN17: 125.70962 | AO17: 28.3451 | AP17: 2.1 | AQ17: 159.15 | AS17: 38.11746 | AT17: 27.275 | AV17: 199.03262 | AW17: 28.9232 | AY17: 2.26729 | BA17: 2.7 | BC17: 67.14412 | BE17: 12.5 | BH17: 72.76453 | BI17: 12.86139 | BK17: 5.69275 | BM17: 7.142 | BN17: 48.9 | BO17: 1.68 | BP17: 135.93002 | BR17: 4.39633 | BS17: 130.80549 | BT17: 18.50328 | BV17: 34.618 | BW17: 4.37541 | BZ17: 88.3724 | CA17: 25.19995 | CB17: 0.2696 | CC17: 0.58 | CD17: 23.19826 | CE17: 340.15813 | CF17: 10.9343 | CG17: 155.2587 | CH17: 18.29319 | CL17: 4.85053 | CO17: 15.70389 | CP17: 288.29 | CR17: 31.759 | CT17: 24.597
B18: 05:30 | E18: 43.6034 | F18: 11.888 | L18: 26.58329 | M18: 13.9939 | N18: 13.61 | O18: 32.428 | R18: 50.756 | T18: 45.6407 | V18: 0.6 | X18: 145.90675 | Z18: 9.30167 | AF18: 2.3 | AJ18: 5.08865 | AK18: 0 | AL18: 0.6934 | AM18: 47.02209 | AN18: 126.26609 | AO18: 27.8141 | AP18: 1.93 | AQ18: 162.51 | AS18: 37.85704 | AT18: 26.312 | AV18: 199.29002 | AW18: 28.1069 | AY18: 2.19954 | BA18: 2.9 | BC18: 67.2999 | BE18: 12.5 | BH18: 72.30389 | BI18: 12.98096 | BK18: 5.57415 | BM18: 6.987 | BN18: 48.84 | BO18: 1.66 | BP18: 135.45787 | BR18: 4.50343 | BS18: 130.37956 | BT18: 17.75006 | BV18: 34.1696 | BW18: 3.85894 | BZ18: 88.5853 | CA18: 25.19123 | CB18: 0.2565 | CC18: 0.59 | CD18: 23.54593 | CE18: 340.70271 | CF18: 10.8334 | CG18: 160.5628 | CH18: 18.1216 | CL18: 4.92101 | CO18: 14.93929 | CP18: 279.84 | CR18: 32.192 | CT18: 24.633
B19: 06:00 | E19: 43.6818 | F19: 11.732 | L19: 26.90985 | M19: 13.6295 | N19: 13.62 | O19: 34.666 | R19: 50.235 | T19: 42.5487 | V19: 0.6 | X19: 73.83773 | Z19: 9.24695 | AF19: 2.7 | AJ19: 5.10208 | AK19: 0 | AL19: 0.8873 | AM19: 48.22368 | AN19: 131.47635 | AO19: 25.4487 | AP19: 1.54 | AQ19: 161.53 | AS19: 35.51527 | AT19: 27.44 | AV19: 199.29917 | AW19: 27.6415 | AY19: 2.28247 | BA19: 2.7 | BC19: 67.17205 | BE19: 12.5 | BH19: 66.65286 | BI19: 12.66386 | BK19: 5.47746 | BM19: 7.321 | BN19: 49.21 | BO19: 1.65 | BP19: 133.26975 | BR19: 4.47936 | BS19: 129.82324 | BT19: 16.73133 | BV19: 34.4969 | BW19: 3.65085 | BZ19: 87.3378 | CA19: 25.1882 | CB19: 0.2412 | CC19: 0.61 | CD19: 22.83823 | CE19: 339.00026 | CF19: 10.5747 | CG19: 156.1489 | CH19: 17.79006 | CL19: 4.5687 | CO19: 13.32025 | CP19: 287.95 | CR19: 32.69 | CT19: 26.342
... B55: 00:00 | E55: 36.1912 | F55: 12.923 | L55: 26.23267 | M55: 13.8902 | N55: 13.63 | O55: 36.33 | R55: 37.524 | T55: 13.1099 | V55: 0.9 | X55: 46.84996 | Z55: 9.79754 | AF55: 3.9 | AJ55: 5.27586 | AK55: 0 | AL55: 1.3675 | AM55: 51.55163 | AN55: 128.88944 | AO55: 28.3835 | AP55: 0.83 | AQ55: 155.87 | AS55: 38.97309 | AT55: 30.794 | AV55: 194.74145 | AW55: 36.1025 | AY55: 3.59611 | BA55: 2.5 | BC55: 72.58434 | BE55: 12.5 | BH55: 68.11269 | BI55: 13.88543 | BK55: 5.8095 | BM55: 6.987 | BN55: 38.24 | BO55: 1.7 | BP55: 144.1937 | BR55: 4.32497 | BS55: 135.92284 | BT55: 17.51371 | BV55: 33.6664 | BW55: 3.83695 | BZ55: 93.9205 | CA55: 24.73915 | CB55: 0.3945 | CC55: 0.58 | CD55: 22.04558 | CE55: 360.77238 | CF55: 11.1464 | CG55: 158.9101 | CH55: 15.12755 | CL55: 4.87402 | CO55: 15.77495 | CP55: 294.42 | CR55: 29.359 | CT55: 24.435
B56: MWh | C56: 0 | D56: 0 | E56: 874.39245 | F56: 300.1265 | G56: 0 | H56: 0 | I56: 0 | J56: 0 | K56: 0 | L56: 636.1032 | M56: 310.62435 | N56: 326.52 | O56: 807.517 | P56: 0 | Q56: 0 | R56: 1178.728 | S56: 0 | T56: 721.84685 | U56: 0 | V56: 18 | W56: 0 | X56: 2503.7783 | Y56: 0 | Z56: 216.30021 | AA56: 0 | AB56: 0 | AC56: 0 | AD56: 0 | AE56: 0 | AF56: 78.3 | AG56: 0 | AH56: 0 | AI56: 0 | AJ56: 118.96792 | AK56: 0 | AL56: 61.4985 | AM56: 1122.0853 | AN56: 3159.4899 | AO56: 642.259 | AP56: 18.01 | AQ56: 3761.495 | AR56: 0 | AS56: 889.49394 | AT56: 697.309 | AU56: 0 | AV56: 4349.6788 | AW56: 729.09595 | AX56: 0 | AY56: 69.06663 | AZ56: 0 | BA56: 66.14 | BB56: 0 | BC56: 1432.4969 | BD56: 0 | BE56: 300 | BF56: 0 | BG56: 0 | BH56: 1669.844 | BI56: 311.75327 | BJ56: 0 | BK56: 135.84218 | BL56: 0 | BM56: 169.2951 | BN56: 754.745 | BO56: 45.95 | BP56: 3329.1262 | BQ56: 0 | BR56: 105.47203 | BS56: 3144.5526 | BT56: 400.50684 | BU56: 0 | BV56: 789.58105 | BW56: 93.42783 | BX56: 0 | BY56: 0 | BZ56: 2147.2503 | CA56: 513.45957 | CB56: 19.8865 | CC56: 13.69 | CD56: 561.56845 | CE56: 8180.2673 | CF56: 255.3772 | CG56: 3544.539 | CH56: 404.66492 | CI56: 0 | CJ56: 0 | CK56: 0 | CL56: 109.84132 | CM56: 0 | CN56: 0 | CO56: 336.94194 | CP56: 6728.625 | CQ56: 0 | CR56: 674.525 | CS56: 0 | CT56: 518.8505
B59: Nota :
B60: Información proporcionada por la empresas
C62: DATOS ESTIMADOS
C64: SIN DATOS

Sheet TIPO_RECURSO
B3: viernes, 4 de Julio del 2025
B5: REPORTE POTENCIA GENERADA POR TIPO DE RECURSO
B6: HORA | C6: H. PASADA | D6: H. REGULACION | E6: GAS DE CAMISEA | F6: GAS DE MALACAS | G6: GAS DE AGUAYTIA | H6: DIÉSEL | I6: RESIDUAL | J6: NAFTA+GAS DE REFINERIA | K6: FLEXIGAS+GAS DE REFINERIA | L6: BAGAZO | M6: BIOGÁS | N6: SOLAR | O6: EÓLICA | P6: TOTAL | U6: EMPRESA | V6: CENTRAL | W6: HIDROELECTRICA DE PASADA | X6: HIDROELECTRICA DE REGULACION
B7: 00:30 | C7: 923.81 | D7: 2101.3 | E7: 3259.533 | F7: 0 | J7: =DESPACHO_EJECUTADO!FC11+DESPACHO_EJECUTADO!FD11 -> 77.77 | L7: 31.8 | M7: 10.4 | N7: 0 | O7: 43.3 | P7: =SUM(C7:O7) -> 6447.913 | U7: ANDEAN POWER S.A.C. | V7: C.H.CARHUAC | W7: 330.65
B8: 01:00 | C8: 904.58 | D8: 1946.68 | E8: 3238.134 | F8: 0 | J8: =DESPACHO_EJECUTADO!FC12+DESPACHO_EJECUTADO!FD12 -> 78.65 | L8: 32.1 | M8: 10.4 | N8: 0 | O8: 45 | P8: =SUM(C8:O8) -> 6255.544 | U8: ASOCIACIÓN SANTA LUCIA DE CHACAS | V8: C.H. HUALLIN | W8: 30.55
B9: 01:30 | C9: 912.39 | D9: 1888.42 | E9: 3231.769 | F9: 0 | J9: =DESPACHO_EJECUTADO!FC13+DESPACHO_EJECUTADO!FD13 -> 77.89 | L9: 32.3 | M9: 10.4 | N9: 0 | O9: 49.9 | P9: =SUM(C9:O9) -> 6203.069 | U9: ATRIA ENERGIA S.A.C. | V9: C.H. PURMACANA | W9: 4.4
B10: 02:00 | C10: 927.36 | D10: 1737.44 | E10: 3247.232 | F10: 0 | J10: =DESPACHO_EJECUTADO!FC14+DESPACHO_EJECUTADO!FD14 -> 77.81 | L10: 32.1 | M10: 10.4 | N10: 0 | O10: 47.2 | P10: =SUM(C10:O10) -> 6079.542 | U10: CELEPSA | V10: C.H. EL PLATANAL | X10: 2535.35
B11: 02:30 | C11: 917.61 | D11: 1770.07 | E11: 3262.017 | F11: 0 | J11: =DESPACHO_EJECUTADO!FC15+DESPACHO_EJECUTADO!FD15 -> 77.85 | L11: 31.8 | M11: 10.4 | N11: 0 | O11: 35.7 | P11: =SUM(C11:O11) -> 6105.447 | U11: CELEPSA RENOVABLES S.R.L. | V11: C.H. MARAÑON | W11: 467.5
B12: 03:00 | C12: 926.21 | D12: 1768.93 | E12: 3247.426 | F12: 0 | J12: =DESPACHO_EJECUTADO!FC16+DESPACHO_EJECUTADO!FD16 -> 77.86 | L12: 32.4 | M12: 10.4 | N12: 0 | O12: 28.3 | P12: =SUM(C12:O12) -> 6091.526 | U12: CHINANGO S.A.C. | V12: C.H. CHIMAY | X12: 1723.05
B13: 03:30 | C13: 916.19 | D13: 1644.01 | E13: 3331.927 | F13: 0 | J13: =DESPACHO_EJECUTADO!FC17+DESPACHO_EJECUTADO!FD17 -> 77.72 | L13: 32.4 | M13: 9.9 | N13: 0 | O13: 33.5 | P13: =SUM(C13:O13) -> 6045.647 | V13: C.H. YANANGO | W13: 664.4
B14: 04:00 | C14: 929.31 | D14: 1667.86 | E14: 3283.314 | F14: 0 | J14: =DESPACHO_EJECUTADO!FC18+DESPACHO_EJECUTADO!FD18 -> 78.08 | L14: 32.7 | M14: 10.4 | N14: 0 | O14: 33.1 | P14: =SUM(C14:O14) -> 6034.764 | U14: EGASA | V14: C.H. CHARCANI III | W14: 164.15
B15: 04:30 | C15: 924.07 | D15: 1664.25 | E15: 3327.628 | F15: 0 | J15: =DESPACHO_EJECUTADO!FC19+DESPACHO_EJECUTADO!FD19 -> 77.85 | L15: 32.3 | M15: 10.4 | N15: 0 | O15: 32.4 | P15: =SUM(C15:O15) -> 6068.898 | V15: C.H. CHARCANI IV | X15: 286.25
B16: 05:00 | C16: 914.55 | D16: 1718.63 | E16: 3289.904 | F16: 0 | J16: =DESPACHO_EJECUTADO!FC20+DESPACHO_EJECUTADO!FD20 -> 77.41 | L16: 32.1 | M16: 10.5 | N16: 0 | O16: 25.4 | P16: =SUM(C16:O16) -> 6068.494 | V16: C.H. CHARCANI V | X16: 1817.7
B17: 05:30 | C17: 911.25 | D17: 1885.34 | E17: 3285.623 | F17: 0 | J17: =DESPACHO_EJECUTADO!FC21+DESPACHO_EJECUTADO!FD21 -> 77.18 | L17: 32.2 | M17: 10.5 | N17: 0 | O17: 27.5 | P17: =SUM(C17:O17) -> 6229.593 | U17: EGEJUNIN | V17: C.H. HUASAHUASI I | W17: 197.15
B18: 06:00 | C18: 908.27 | D18: 1890.89 | E18: 3318.699 | F18: 0 | J18: =DESPACHO_EJECUTADO!FC22+DESPACHO_EJECUTADO!FD22 -> 77.41 | L18: 32.6 | M18: 10.5 | N18: 0.1 | O18: 33.4 | P18: =SUM(C18:O18) -> 6271.869 | V18: C.H. RUNATULLO II | W18: 122.9
B19: 06:30 | C19: 902.31 | D19: 2043.09 | E19: 3345.288 | F19: 28.3 | J19: =DESPACHO_EJECUTADO!FC23+DESPACHO_EJECUTADO!FD23 -> 77.49 | L19: 31.5 | M19: 10.5 | N19: 10.5 | O19: 34 | P19: =SUM(C19:O19) -> 6482.978 | V19: C.H. RUNATULLO III | W19: 176.25
B20: 07:00 | C20: 914.79 | D20: 2012.88 | E20: 3291.519 | F20: 46.1 | J20: =DESPACHO_EJECUTADO!FC24+DESPACHO_EJECUTADO!FD24 -> 77.18 | L20: 32.2 | M20: 10.5 | N20: 130.3 | O20: 26.9 | P20: =SUM(C20:O20) -> 6542.369 | V20: C.H. SANTA CRUZ I | W20: 79.75
B21: 07:30 | C21: 924.31 | D21: 1936.93 | E21: 3345.603 | F21: 46.5 | J21: =DESPACHO_EJECUTADO!FC25+DESPACHO_EJECUTADO!FD25 -> 77.44 | L21: 26.7 | M21: 10.5 | N21: 334.8 | O21: 22 | P21: =SUM(C21:O21) -> 6724.783 | U21: EGEMSA | V21: C.H. MACHUPICCHU | W21: 3300.8
B22: 08:00 | C22: 926.83 | D22: 1921.15 | E22: 3265.466 | F22: 46.3 | J22: =DESPACHO_EJECUTADO!FC26+DESPACHO_EJECUTADO!FD26 -> 76.73 | L22: 27.3 | M22: 10.5 | N22: 507.4 | O22: 20.3 | P22: =SUM(C22:O22) -> 6801.976 | U22: EGESUR | V22: C.H. ARICOTA I | X22: 176.8
B23: 08:30 | C23: 924.91 | D23: 2027.01 | E23: 3247.907 | F23: 46.3 | J23: =DESPACHO_EJECUTADO!FC27+DESPACHO_EJECUTADO!FD27 -> 76.89 | L23: 27.7 | M23: 9.4 | N23: 546.6 | O23: 23.4 | P23: =SUM(C23:O23) -> 6930.117 | V23: C.H. ARICOTA II | X23: 126.2
B24: 09:00 | C24: 929.14 | D24: 2105.14 | E24: 3343.057 | F24: 46.3 | J24: =DESPACHO_EJECUTADO!FC28+DESPACHO_EJECUTADO!FD28 -> 77.67 | L24: 26.8 | M24: 9.4 | N24: 563.4 | O24: 31.8 | P24: =SUM(C24:O24) -> 7132.707 | U24: ELECTRICA YANAPAMPA SAC | V24: C.H. YANAPAMPA | W24: 51.15
B25: 09:30 | C25: 934.41 | D25: 2208.1 | E25: 3325.818 | F25: 45.4 | J25: =DESPACHO_EJECUTADO!FC29+DESPACHO_EJECUTADO!FD29 -> 77.4 | L25: 26.6 | M25: 9.4 | N25: 572.3 | O25: 31.5 | P25: =SUM(C25:O25) -> 7230.928 | U25: ELECTROPERU | V25: C.H. MANTARO | X25: 14799.655
B26: 10:00 | C26: 922.83 | D26: 2265.45 | E26: 3277.042 | F26: 45.4 | J26: =DESPACHO_EJECUTADO!FC30+DESPACHO_EJECUTADO!FD30 -> 77.72 | L26: 26.4 | M26: 9.4 | N26: 576.9 | O26: 32.5 | P26: =SUM(C26:O26) -> 7233.642 | V26: C.H. RESTITUCION | W26: 4977.64
B27: 10:30 | C27: 950.5 | D27: 2344.21 | E27: 3285.419 | F27: 45.2 | J27: =DESPACHO_EJECUTADO!FC31+DESPACHO_EJECUTADO!FD31 -> 77.32 | L27: 30.4 | M27: 9.4 | N27: 579.8 | O27: 40.6 | P27: =SUM(C27:O27) -> 7362.849 | U27: EMPRESA DE GENERACION ELECTRICA CANCHAYLLO SAC | V27: C.H. CANCHAYLLO | W27: 62.2
B28: 11:00 | C28: 944.7 | D28: 2321.45 | E28: 3265.352 | F28: 44.7 | J28: =DESPACHO_EJECUTADO!FC32+DESPACHO_EJECUTADO!FD32 -> 76.98 | L28: 27.9 | M28: 9.3 | N28: 581.7 | O28: 53 | P28: =SUM(C28:O28) -> 7325.082 | U28: EMPRESA DE GENERACION ELECTRICA RIO BAÑOS S.A.C. | V28: C.H. RUCUY | W28: 325.9
B29: 11:30 | C29: 946.73 | D29: 2371.18 | E29: 3337.361 | F29: 44.3 | J29: =DESPACHO_EJECUTADO!FC33+DESPACHO_EJECUTADO!FD33 -> 77.7 | L29: 28.8 | M29: 9.3 | N29: 582 | O29: 73.1 | P29: =SUM(C29:O29) -> 7470.471 | U29: EMPRESA DE GENERACION ELECTRICA SANTA ANA S.A.C. | V29: C.H. RENOVANDES H1 | W29: 480.1
B30: 12:00 | C30: 949.45 | D30: 2331.54 | E30: 3334.679 | F30: 44.2 | J30: =DESPACHO_EJECUTADO!FC34+DESPACHO_EJECUTADO!FD34 -> 77.16 | L30: 29.6 | M30: 9.3 | N30: 581.4 | O30: 87 | P30: =SUM(C30:O30) -> 7444.329 | U30: EMPRESA DE GENERACION HUALLAGA | V30: C.H. CHAGLLA | X30: 3924.95
B31: 12:30 | C31: 945.04 | D31: 2268.01 | E31: 3287.24 | F31: 44.8 | J31: =DESPACHO_EJECUTADO!FC35+DESPACHO_EJECUTADO!FD35 -> 77.67 | L31: 30.2 | M31: 7.7 | N31: 579.9 | O31: 76.6 | P31: =SUM(C31:O31) -> 7317.16 | V31: P.C.H. CHAGLLA | W31: 155.45
B32: 13:00 | C32: 946.33 | D32: 2280.25 | E32: 3178.467 | F32: 45.4 | J32: =DESPACHO_EJECUTADO!FC36+DESPACHO_EJECUTADO!FD36 -> 77.26 | L32: 29.9 | M32: 7.7 | N32: 580 | O32: 62.8 | P32: =SUM(C32:O32) -> 7208.107 | U32: EMPRESA DE GENERACION HUANZA | V32: C.H. HUANZA | X32: 1274.25
B33: 13:30 | C33: 932.38 | D33: 2198.22 | E33: 3321.9068 | F33: 45.2 | J33: =DESPACHO_EJECUTADO!FC37+DESPACHO_EJECUTADO!FD37 -> 77.31 | L33: 29.6 | M33: 7.9 | N33: 581.7 | O33: 72.6 | P33: =SUM(C33:O33) -> 7266.8168 | U33: EMPRESA ELECTRICA AGUA AZUL | V33: C.H. POTRERO | W33: 314.5
B34: 14:00 | C34: 931.25 | D34: 2278.36 | E34: 3304.3571 | F34: 44.8 | J34: =DESPACHO_EJECUTADO!FC38+DESPACHO_EJECUTADO!FD38 -> 77.95 | L34: 29.6 | M34: 8.5 | N34: 579.1 | O34: 78.6 | P34: =SUM(C34:O34) -> 7332.5171 | U34: EMPRESA ELECTRICA RIO DOBLE | V34: C.H. LAS PIZARRAS | W34: 204.8
B35: 14:30 | C35: 938.01 | D35: 2406.33 | E35: 3270.6176 | F35: 45 | J35: =DESPACHO_EJECUTADO!FC39+DESPACHO_EJECUTADO!FD39 -> 78.35 | L35: 30.1 | M35: 8.8 | N35: 576.6 | O35: 80.6 | P35: =SUM(C35:O35) -> 7434.4076 | U35: ENGIE | V35: C.H. QUITARACSA | X35: 379.9
B36: 15:00 | C36: 933.6 | D36: 2477.38 | E36: 3208.0427 | F36: 46 | J36: =DESPACHO_EJECUTADO!FC40+DESPACHO_EJECUTADO!FD40 -> 77.82 | L36: 29.4 | M36: 8.8 | N36: 563.6 | O36: 85.6 | P36: =SUM(C36:O36) -> 7430.2427 | V36: C.H. YUNCAN | X36: 1331.7
B37: 15:30 | C37: 941.94 | D37: 2659.15 | E37: 3321.6188 | F37: 45.2 | J37: =DESPACHO_EJECUTADO!FC41+DESPACHO_EJECUTADO!FD41 -> 77.38 | L37: 29.7 | M37: 7.8 | N37: 540.6 | O37: 79.4 | P37: =SUM(C37:O37) -> 7702.7888 | U37: GENERACIÓN ANDINA S.A.C. | V37: C.H. 8 DE AGOSTO | W37: 252
B38: 16:00 | C38: 935.66 | D38: 2696.95 | E38: 3201.7517 | F38: 46.1 | J38: =DESPACHO_EJECUTADO!FC42+DESPACHO_EJECUTADO!FD42 -> 77.62 | L38: 31.6 | M38: 8.5 | N38: 442.5 | O38: 73.6 | P38: =SUM(C38:O38) -> 7514.2817 | V38: C.H. EL CARMEN | W38: 86.1
B39: 16:30 | C39: 949.11 | D39: 2699.14 | E39: 3330.9611 | F39: 45.8 | J39: =DESPACHO_EJECUTADO!FC43+DESPACHO_EJECUTADO!FD43 -> 77.83 | L39: 30.9 | M39: 10.1 | N39: 239.5 | O39: 74 | P39: =SUM(C39:O39) -> 7457.3411 | U39: GENERADORA DE ENERGÍA DEL PERÚ | V39: C.H. ÁNGEL I | W39: 124.55
B40: 17:00 | C40: 937.47 | D40: 2806.2 | E40: 3337.0246 | F40: 46.4 | J40: =DESPACHO_EJECUTADO!FC44+DESPACHO_EJECUTADO!FD44 -> 77.83 | L40: 32 | M40: 10.6 | N40: 55.4 | O40: 82.2 | P40: =SUM(C40:O40) -> 7385.1246 | V40: C.H. ÁNGEL II | W40: 134.15
B41: 17:30 | C41: 931.55 | D41: 2720.24 | E41: 3279.5614 | F41: 46.6 | J41: =DESPACHO_EJECUTADO!FC45+DESPACHO_EJECUTADO!FD45 -> 77.78 | L41: 31.9 | M41: 10.7 | N41: 0.3 | O41: 109.6 | P41: =SUM(C41:O41) -> 7208.2314 | V41: C.H. ÁNGEL III | W41: 134.5
B42: 18:00 | C42: 930.91 | D42: 2623.1 | E42: 3298.5246 | F42: 46.4 | J42: =DESPACHO_EJECUTADO!FC46+DESPACHO_EJECUTADO!FD46 -> 77.42 | L42: 31.2 | M42: 10.7 | N42: 0 | O42: 159.4 | P42: =SUM(C42:O42) -> 7177.6546 | V42: C.H. LA JOYA | W42: 189
B43: 18:30 | C43: 929.74 | D43: 2775.5 | E43: 3344.1956 | F43: 47.2 | J43: =DESPACHO_EJECUTADO!FC47+DESPACHO_EJECUTADO!FD47 -> 76.85 | L43: 31 | M43: 10.7 | N43: 0 | O43: 171.8 | P43: =SUM(C43:O43) -> 7386.9856 | U43: HIDROCAÑETE S.A. | V43: C.H. IMPERIAL | W43: 80.05
B44: 19:00 | C44: 934.53 | D44: 2762.37 | E44: 3344.3106 | F44: 46.3 | J44: =DESPACHO_EJECUTADO!FC48+DESPACHO_EJECUTADO!FD48 -> 77.49 | L44: 30.8 | M44: 10.7 | N44: 0 | O44: 165.1 | P44: =SUM(C44:O44) -> 7371.6006 | U44: HIDROELECTRICA HUANCHOR S.A.C. | V44: C.H. HUANCHOR | W44: 431.85
B45: 19:30 | C45: 934.26 | D45: 2801.66 | E45: 3319.3324 | F45: 46.2 | J45: =DESPACHO_EJECUTADO!FC49+DESPACHO_EJECUTADO!FD49 -> 76.9 | L45: 31 | M45: 10.7 | N45: 0 | O45: 155.2 | P45: =SUM(C45:O45) -> 7375.2524 | U45: HUAURA POWER GROUP S.A. | V45: C.H. YARUCAYA | W45: 444
B46: 20:00 | C46: 934.61 | D46: 2762.96 | E46: 3349.1367 | F46: 46.9 | J46: =DESPACHO_EJECUTADO!FC50+DESPACHO_EJECUTADO!FD50 -> 77.09 | L46: 31.9 | M46: 10.7 | N46: 0 | O46: 122.7 | P46: =SUM(C46:O46) -> 7335.9967 | U46: HYDRO GLOBAL PERÚ S.A.C. | V46: CH SAN GABAN III | X46: 2321.55
B47: 20:30 | C47: 932.37 | D47: 2788.96 | E47: 3198.8321 | F47: 46.3 | J47: =DESPACHO_EJECUTADO!FC51+DESPACHO_EJECUTADO!FD51 -> 73.84 | L47: 32.5 | M47: 10.7 | N47: 0 | O47: 100.6 | P47: =SUM(C47:O47) -> 7184.1021 | U47: INLAND ENERGY SAC | V47: C.H. SANTA TERESA | W47: 1759.55
B48: 21:00 | C48: 931.24 | D48: 2807.35 | E48: 3302.2069 | F48: 46.8 | J48: =DESPACHO_EJECUTADO!FC52+DESPACHO_EJECUTADO!FD52 -> 0 | L48: 32 | M48: 10.7 | N48: 0 | O48: 94 | P48: =SUM(C48:O48) -> 7224.2969 | U48: INVERSIONES SHAQSHA S.A.C. | V48: C.H. PARIAC | W48: 29.45
B49: 21:30 | C49: 933.5 | D49: 2784.68 | E49: 3313.3022 | F49: 46.8 | J49: =DESPACHO_EJECUTADO!FC53+DESPACHO_EJECUTADO!FD53 -> 0 | L49: 31.1 | M49: 10.7 | N49: 0 | O49: 99.2 | P49: =SUM(C49:O49) -> 7219.2822 | U49: KALLPA GENERACION S.A. | V49: C.H. CERRO DEL AGUILA | X49: 9202.7
B50: 22:00 | C50: 931.66 | D50: 2757.09 | E50: 3309.1983 | F50: 47.1 | J50: =DESPACHO_EJECUTADO!FC54+DESPACHO_EJECUTADO!FD54 -> 0 | L50: 32.2 | M50: 10.7 | N50: 0 | O50: 95.4 | P50: =SUM(C50:O50) -> 7183.3483 | V50: M.C.H. CERRO DEL AGUILA | W50: 102.65
B51: 22:30 | C51: 926.55 | D51: 2695.06 | E51: 3291.6449 | F51: 46.7 | J51: =DESPACHO_EJECUTADO!FC55+DESPACHO_EJECUTADO!FD55 -> 0 | L51: 32.2 | M51: 10.7 | N51: 0 | O51: 99.7 | P51: =SUM(C51:O51) -> 7102.5549 | U51: LA VIRGEN | V51: C.H. LA VIRGEN | X51: 984.15
B52: 23:00 | C52: 935.43 | D52: 2533.34 | E52: 3155.3154 | F52: 46.9 | J52: =DESPACHO_EJECUTADO!FC56+DESPACHO_EJECUTADO!FD56 -> 0 | L52: 29.9 | M52: 10.7 | N52: 0 | O52: 118.5 | P52: =SUM(C52:O52) -> 6830.0854 | U52: MAJA ENERGIA S.A.C. | V52: C.H. RONCADOR | W52: 58.25
B53: 23:30 | C53: 932.72 | D53: 2522.9 | E53: 3066.2791 | F53: 46.9 | J53: =DESPACHO_EJECUTADO!FC57+DESPACHO_EJECUTADO!FD57 -> 0 | L53: 31.7 | M53: 10.7 | N53: 0 | O53: 111.9 | P53: =SUM(C53:O53) -> 6723.0991 | U53: ORAZUL ENERGY PERÚ | V53: C.H. CAÑA BRAVA | W53: 106.9
B54: 00:00 | C54: 924.71 | D54: 2449.76 | E54: 2956.1086 | F54: 46.9 | J54: =DESPACHO_EJECUTADO!FC58+DESPACHO_EJECUTADO!FD58 -> 0 | L54: 32.3 | M54: 10.7 | N54: 0 | O54: 98.2 | P54: =SUM(C54:O54) -> 6518.6786 | V54: C.H. CAÑON DEL PATO | X54: 2081.1
B55: TOTAL MWh | C55: =SUM(C7:C54)/2 -> 22310.54 | D55: =SUM(D7:D54)/2 -> 55063.455 | E55: =SUM(E7:E54)/2 -> 78638.827 | F55: =SUM(F7:F54)/2 -> 818.85 | G55: =SUM(G7:G54)/2 -> 0 | H55: =SUM(H7:H54)/2 -> 0 | I55: =SUM(I7:I54)/2 -> 0 | J55: =SUM(J7:J54)/2 -> 1587.775 | ... P55: =SUM(P7:P54)/2 -> 166237.25 | V55: C.H. CARHUAQUERO | X55: 1323.05
B56: % | C56: =C55/$P$55 -> 0.13420903 | D56: =D55/$P$55 -> 0.33123416 | E56: =E55/$P$55 -> 0.47305179 | F56: =F55/$P$55 -> 0.0049257914 | G56: =G55/$P$55 -> 0 | H56: =H55/$P$55 -> 0 | I56: =I55/$P$55 -> 0 | J56: =J55/$P$55 -> 0.009551259 | ... P56: =P55/$P$55 -> 1 | V56: C.H. CARHUAQUERO IV | W56: 238.15
U57: ORYGEN PERU S.A.A. | V57: C.H. CALLAHUANCA | X57: 1626.6
V58: C.H. HER 1 | W58: 14.4
V59: C.H. HUAMPANI | W59: 695.05
V60: C.H. HUINCO | X60: 3010.25
V61: C.H. MATUCANA | X61: 1936.45
V62: C.H. MOYOPAMPA | W62: 1544.7
U63: PERUANA DE INVERSIONES EN ENERGIAS RENOVABLES S.A. | V63: C.H. MANTA I | W63: 272
U64: SAN GABAN | V64: C.H. SAN GABAN II | X64: 1573.65
V65: PCH TUPURI | W65: 9.6
U66: SINERSA | V66: C.H. CHANCAY | W66: 431.95
V67: C.H. POECHOS II | W67: 239.95
U68: STATKRAFT S.A | V68: C.H. ARCATA | W68: 91.2
V69: C.H. CAHUA | W69: 699.85
V70: C.H. CHEVES | X70: 1615.7
V71: C.H. GALLITO CIEGO | X71: 212.8
V72: C.H. MALPASO | X72: 799.65
V73: C.H. OROYA | W73: 143.1
V74: C.H. PACHACHACA | W74: 35.9
V75: C.H. YAUPI | W75: 1851.45
U76: TOTAL MWh | W76: 22310.54 | X76: 55063.455

Sheet GENERACION RER
B3: viernes, 4 de Julio del 2025
B5: GENERACIÓN ELÉCTRICA DE LAS CENTRALES RER (MW)
B6: HORA | C6: AGRO INDUSTRIAL PARAMONGA S.A. | D6: AGROAURORA S.A.C. | E6: AGROINDUSTRIAS SAN JACINTO S.A.A. | F6: ANDEAN POWER S.A.C. | G6: ASOCIACIÓN SANTA LUCIA DE CHACAS | H6: ATRIA ENERGIA S.A.C. | I6: BIOENERGIA DEL CHIRA S.A. | J6: COLCA SOLAR S.A.C. | K6: EGEJUNIN | P6: ELECTRICA YANAPAMPA SAC | Q6: EMPRESA DE GENERACION ELECTRICA CANCHAYLLO SAC | R6: EMPRESA DE GENERACION ELECTRICA RIO BAÑOS S.A.C. | S6: EMPRESA DE GENERACION ELECTRICA SANTA ANA S.A.C. | T6: EMPRESA ELECTRICA AGUA AZUL | U6: EMPRESA ELECTRICA RIO DOBLE | V6: ENERGÍA EÓLICA S.A. | X6: ENERGIA RENOVABLE DEL SUR S.A. | Y6: ENGIE | AD6: GENERACIÓN ANDINA S.A.C. | AF6: GENERADORA DE ENERGÍA DEL PERÚ | AJ6: GR CORTARRAMA SOCIEDAD ANONIMA CERRADA | AK6: GR PAINO SOCIEDAD ANONIMA CERRADA | AL6: GR TARUCA SOCIEDAD ANONIMA CERRADA | AM6: HIDROCAÑETE S.A. | AN6: HUAURA POWER GROUP S.A. | AO6: HYDRO PATAPO S.A.C. | AP6: JOYA SOLAR S.A.C. | AQ6: KONDU SAC | AR6: MAJA ENERGIA S.A.C. | AS6: MAJES ARCUS S.A.C. | AT6: MOQUEGUA FV S.A.C. | AU6: ORAZUL ENERGY PERÚ | AW6: ORYGEN PERU S.A.A. | BB6: PANAMERICANA SOLAR SAC. | BC6: PARQUE EOLICO MARCONA S.A.C. | BD6: PARQUE EOLICO TRES HERMANAS S.A.C. | BE6: PERUANA DE INVERSIONES EN ENERGIAS RENOVABLES S.A. | BF6: PETRAMAS | BJ6: REPARTICIÓN ARCUS S.A.C. | BK6: SAN GABAN | BL6: SDF ENERGIA SAC | BM6: SINERSA | BO6: TACNA SOLAR SAC. | BP6: TOTAL RER
C7: C.T. PARAMONGA | D7: C.T. MAPLE | E7: C.T SAN JACINTO | F7: C.H. CARHUAC | G7: C.H. HUALLIN | H7: C.H. PURMACANA | I7: C.T. CAÑA BRAVA | K7: C.H. HUASAHUASI I | L7: C.H. HUASAHUASI II | M7: C.H. RUNATULLO II | N7: C.H. RUNATULLO III | O7: C.H. STA CRUZ I y II | P7: C.H. YANAPAMPA | Q7: C.H. CANCHAYLLO | R7: C.H. RUCUY | S7: C.H. RENOVANDES H1 | T7: C.H. POTRERO | U7: C.H. LAS PIZARRAS | AD7: C.H. 8 DE AGOSTO | AE7: C.H. EL CARMEN | AF7: C.H. ANGEL I | AG7: C.H. ANGEL II | AH7: C.H. ANGEL III | AI7: C.H. LA JOYA | AM7: C.H. NUEVAIMPERIAL | AN7: C.H. YARUCAYA | AO7: MCH PATAPO | AR7: C.H. RONCADOR | AU7: C.H. CANA BRAVA | AV7: C.H. CARHUAQUERO4 | BA7: C.H. HER 1 | BE7: C.H. MANTA | BF7: C.T. HUAYCOLORO | BG7: C.T. LA GRINGA V | BH7: CTB CALLAO | BI7: CTB. DONA CATALINA | BK7: C.H. TUPURI | BL7: C.T. OQUENDO | BM7: C.H. CHANCAY | BN7: C.H. POECHOS2 | BP7: MW
B8: 0:30 | C8: 15.2 | E8: 7.3 | F8: 14.4 | G8: 1.4 | I8: 9.3 | K8: 8.6 | M8: 5.1 | N8: 7.2 | O8: 3.9 | P8: 2.2 | Q8: 2.6 | R8: 13.6 | S8: 19.9 | T8: 13.2 | U8: 8.9 | V8: 8.1 | W8: 3.9 | X8: 0.1 | AD8: 10.5 | AE8: 4 | AF8: 4.9 | AG8: 5.4 | AH8: 5.4 | AI8: 7.6 | AK8: 10.7 | AL8: 15.6 | AM8: 3.3 | AN8: 18.5 | AR8: 2.7 | AU8: 4.9 | AV8: 9.9 | AW8: 4.9 | BA8: 0.6 | BE8: 11.3 | BF8: 4.5 | BG8: 2.7 | BH8: 2.2 | BI8: 1 | BK8: 0.4 | BM8: 18 | BN8: 10 | BP8: 303.9
B9: 1:00 | C9: 15.3 | E9: 7.5 | F9: 3.4 | G9: 1.4 | I9: 9.3 | K9: 8.5 | M9: 4.8 | N9: 7 | O9: 3.8 | P9: 2.2 | Q9: 2.6 | R9: 13.1 | S9: 19.6 | T9: 13.2 | U9: 8.9 | V9: 5.2 | W9: 4.9 | X9: 0.1 | AD9: 10.5 | AE9: 4 | AF9: 5.2 | AG9: 5.4 | AH9: 5.4 | AI9: 7.7 | AK9: 11.1 | AL9: 14 | AM9: 3.3 | AN9: 18.5 | AR9: 2.7 | AU9: 4.8 | AV9: 10 | AW9: 9.2 | BA9: 0.6 | BC9: 0.2 | BD9: 0.3 | BE9: 11.3 | BF9: 4.5 | BG9: 2.7 | BH9: 2.2 | BI9: 1 | BK9: 0.4 | BM9: 17.8 | BN9: 9.9 | BP9: 293.5
B10: 1:30 | C10: 15.4 | E10: 7.3 | F10: 4.4 | G10: 1.4 | I10: 9.6 | K10: 8.6 | M10: 5 | N10: 7.2 | O10: 3.8 | P10: 2.1 | Q10: 2.6 | R10: 13.2 | S10: 19.8 | T10: 13 | U10: 8.9 | V10: 4.8 | W10: 5.5 | X10: 0.1 | AD10: 10.5 | AE10: 4 | AF10: 5.6 | AG10: 5.4 | AH10: 5.4 | AI10: 7.8 | AK10: 12.7 | AL10: 15.1 | AM10: 3.3 | AN10: 18.5 | AR10: 2.7 | AU10: 3.9 | AV10: 9.9 | AW10: 11.7 | BA10: 0.6 | BE10: 11.4 | BF10: 4.5 | BG10: 2.7 | BH10: 2.2 | BI10: 1 | BK10: 0.4 | BM10: 17.9 | BN10: 10 | BP10: 299.9
B11: 2:00 | C11: 15.3 | E11: 7.4 | F11: 4.8 | G11: 1.3 | I11: 9.4 | K11: 8.6 | M11: 5.3 | N11: 7.4 | O11: 3.9 | P11: 2.1 | Q11: 2.6 | R11: 13.4 | S11: 20.3 | T11: 13 | U11: 9 | V11: 6.9 | W11: 3.2 | X11: 0.1 | AD11: 10.5 | AE11: 4 | AF11: 5.5 | AG11: 5.4 | AH11: 5.4 | AI11: 7.8 | AK11: 12.6 | AL11: 15.7 | AM11: 3.4 | AN11: 18.5 | AR11: 2.4 | AU11: 4.1 | AV11: 10 | AW11: 8.7 | BA11: 0.6 | BE11: 11.5 | BF11: 4.5 | BG11: 2.7 | BH11: 2.2 | BI11: 1 | BK11: 0.4 | BM11: 17.9 | BN11: 10 | BP11: 298.8
B12: 2:30 | C12: 15.2 | E12: 7.1 | F12: 5.2 | G12: 1.3 | I12: 9.5 | K12: 8.6 | M12: 5.2 | N12: 7.3 | O12: 3.8 | P12: 2.1 | Q12: 2.6 | R12: 13.6 | S12: 20 | T12: 13 | U12: 8.9 | V12: 6.6 | W12: 1.3 | X12: 0.1 | AD12: 10.5 | AE12: 4.1 | AF12: 5.5 | AG12: 5.4 | AH12: 5.4 | AI12: 7.8 | AK12: 10.1 | AL12: 14.3 | AM12: 3.4 | AN12: 18.5 | AR12: 2.4 | AU12: 4 | AV12: 9.9 | AW12: 3.3 | BA12: 0.6 | BE12: 11.5 | BF12: 4.5 | BG12: 2.7 | BH12: 2.2 | BI12: 1 | BK12: 0.4 | BM12: 18 | BN12: 10 | BP12: 286.9
B13: 3:00 | C13: 15.3 | E13: 7.5 | F13: 5.8 | G13: 1.3 | I13: 9.6 | K13: 8.5 | M13: 5.3 | N13: 7.4 | O13: 3.9 | P13: 2.1 | Q13: 2.6 | R13: 13.6 | S13: 20.3 | T13: 13.2 | U13: 8.9 | V13: 4.4 | W13: 0.2 | X13: 0.2 | AD13: 10.5 | AE13: 3.7 | AF13: 5.4 | AG13: 5.4 | AH13: 5.4 | AI13: 7.8 | AK13: 8 | AL13: 11.4 | AM13: 3.4 | AN13: 18.5 | AR13: 2.5 | AU13: 4 | AV13: 9.9 | AW13: 2.6 | BA13: 0.6 | BC13: 0.5 | BD13: 1 | BE13: 11.5 | BF13: 4.5 | BG13: 2.7 | BH13: 2.2 | BI13: 1 | BK13: 0.4 | BM13: 18 | BN13: 10 | BP13: 281
B14: 3:30 | C14: 15.3 | E14: 7.6 | F14: 5.8 | G14: 1.3 | I14: 9.5 | K14: 8.6 | M14: 5 | N14: 7.2 | O14: 3.8 | P14: 2.1 | Q14: 2.6 | R14: 13.6 | S14: 20 | T14: 13.3 | U14: 8.9 | V14: 7.7 | X14: 0.4 | AD14: 10.5 | AE14: 3.7 | AF14: 5.4 | AG14: 5.4 | AH14: 5.4 | AI14: 7.8 | AK14: 7.8 | AL14: 11.1 | AM14: 3.4 | AN14: 18.5 | AR14: 2.5 | AU14: 4 | AV14: 9.9 | AW14: 4.7 | BA14: 0.6 | BC14: 0.3 | BD14: 1.5 | BE14: 11.4 | BF14: 4.5 | BG14: 2.7 | BH14: 1.7 | BI14: 1 | BK14: 0.4 | BM14: 18 | BN14: 10 | BP14: 284.9
B15: 4:00 | C15: 15.3 | E15: 8 | F15: 5.8 | G15: 1.3 | I15: 9.4 | K15: 8.5 | M15: 5.2 | N15: 7.3 | O15: 3.8 | P15: 2.1 | Q15: 2.6 | R15: 13.6 | S15: 20.3 | T15: 13.6 | U15: 8.9 | V15: 10.2 | W15: 2.1 | AD15: 10.5 | AE15: 3.7 | AF15: 5.4 | AG15: 5.4 | AH15: 5.4 | AI15: 7.8 | AK15: 5.7 | AL15: 10.6 | AM15: 3.4 | AN15: 18.5 | AR15: 2.5 | AU15: 4.8 | AV15: 9.9 | AW15: 4.5 | BA15: 0.6 | BE15: 11.6 | BF15: 4.5 | BG15: 2.7 | BH15: 2.2 | BI15: 1 | BK15: 0.4 | BM15: 18 | BN15: 10 | BP15: 287.1
B16: 4:30 | C16: 15.2 | E16: 7.6 | F16: 5.8 | G16: 1.3 | I16: 9.5 | K16: 8.6 | M16: 5.2 | N16: 7.3 | O16: 3.6 | P16: 2.1 | Q16: 2.6 | R16: 13.7 | S16: 20.2 | T16: 13.7 | U16: 8.9 | V16: 11.1 | W16: 3.6 | AD16: 10.5 | AE16: 3.7 | AF16: 5.4 | AG16: 5.4 | AH16: 5.4 | AI16: 8 | AK16: 5.2 | AL16: 10.4 | AM16: 3.4 | AN16: 18.5 | AR16: 2.5 | AU16: 4.8 | AV16: 10 | AW16: 2.1 | BA16: 0.6 | BE16: 11.7 | BF16: 4.5 | BG16: 2.7 | BH16: 2.2 | BI16: 1 | BK16: 0.4 | BM16: 18.1 | BN16: 10 | BP16: 286.5
B17: 5:00 | C17: 15.1 | E17: 7.4 | F17: 5.8 | G17: 1.3 | I17: 9.6 | K17: 8.6 | M17: 5.2 | N17: 7.2 | O17: 3.5 | P17: 2.1 | Q17: 2.6 | R17: 13.6 | S17: 19.8 | T17: 14 | U17: 8 | V17: 8.2 | W17: 3.2 | AD17: 10.5 | AE17: 3.7 | AF17: 5 | AG17: 5.4 | AH17: 5.4 | AI17: 8 | AK17: 4.4 | AL17: 9.3 | AM17: 3.4 | AN17: 18.5 | AR17: 2.6 | AU17: 4.8 | AV17: 10 | AW17: 0.3 | BA17: 0.6 | BE17: 11.7 | BF17: 4.5 | BG17: 2.7 | BH17: 2.2 | BI17: 1.1 | BK17: 0.4 | BM17: 18 | BN17: 10 | BP17: 277.7
B18: 5:30 | C18: 15 | E18: 7.5 | F18: 5.8 | G18: 1.2 | I18: 9.7 | K18: 8.6 | M18: 5.1 | N18: 7.2 | O18: 3.5 | P18: 2.1 | Q18: 2.6 | R18: 13.6 | S18: 19.8 | T18: 14 | U18: 8 | V18: 7.2 | W18: 4.5 | AD18: 10.5 | AE18: 3.7 | AF18: 5 | AG18: 5.4 | AH18: 5.4 | AI18: 8 | AK18: 4.8 | AL18: 10.9 | AM18: 3.4 | AN18: 18.5 | AR18: 2.6 | AU18: 4.8 | AV18: 9.9 | BA18: 0.6 | BC18: 0.1 | BE18: 11.6 | BF18: 4.5 | BG18: 2.7 | BH18: 2.2 | BI18: 1.1 | BK18: 0.4 | BM18: 18.1 | BN18: 10 | BP18: 279.6
B19: 6:00 | C19: 15.3 | E19: 7.5 | F19: 5.8 | G19: 1.2 | I19: 9.8 | K19: 8.5 | M19: 5.1 | N19: 7.2 | O19: 3.5 | P19: 2.2 | Q19: 2.6 | R19: 13.5 | S19: 19.8 | T19: 14 | U19: 8 | V19: 8.6 | W19: 7.9 | AD19: 10.5 | AE19: 3.7 | AF19: 5 | AG19: 5.4 | AH19: 5.4 | AI19: 7.9 | AK19: 5.5 | AL19: 11.4 | AM19: 3.4 | AN19: 18.5 | AR19: 2.7 | AT19: 0.1 | AU19: 4.9 | AV19: 9.9 | BA19: 0.6 | BE19: 11.5 | BF19: 4.5 | BG19: 2.7 | BH19: 2.2 | BI19: 1.1 | BK19: 0.4 | BM19: 18.1 | BN19: 10.1 | BP19: 286
B20: 6:30 | C20: 15.1 | E20: 6.6 | F20: 5.8 | G20: 1.3 | I20: 9.8 | K20: 8.8 | M20: 4.9 | N20: 7.1 | O20: 2.7 | P20: 2.2 | Q20: 2.6 | R20: 13.6 | S20: 19.5 | T20: 13.9 | U20: 8 | V20: 10.7 | W20: 5.9 | AA20: 0.2 | AD20: 10.5 | AE20: 3.7 | AF20: 5 | AG20: 5.4 | AH20: 5.4 | AI20: 7.8 | AK20: 5.7 | AL20: 11.7 | AM20: 3.4 | AN20: 18.5 | AP20: 2.2 | AR20: 2.7 | AT20: 2.1 | AU20: 4.7 | AV20: 10 | AX20: 2 | AZ20: 1.5 | BA20: 0.6 | BB20: 2.2 | BE20: 11.6 | BF20: 4.5 | BG20: 2.7 | BH20: 2.2 | BI20: 1.1 | BK20: 0.4 | BM20: 18 | BN20: 10 | BO20: 0.3 | BP20: 294.6
B21: 7:00 | C21: 15.1 | E21: 7.3 | F21: 5.8 | G21: 1.2 | I21: 9.8 | K21: 8.8 | M21: 5.2 | N21: 7.9 | O21: 2.4 | P21: 2.3 | Q21: 2.6 | R21: 13.5 | S21: 20.1 | T21: 13.8 | U21: 8.1 | V21: 6 | W21: 1.6 | AA21: 4.8 | AD21: 10.5 | AE21: 3.7 | AF21: 5.2 | AG21: 5.4 | AH21: 5.4 | AI21: 8 | AJ21: 13.3 | AK21: 7.1 | AL21: 12.2 | AM21: 3.4 | AN21: 18.5 | AP21: 44.2 | AR21: 2.6 | AS21: 1.7 | AT21: 8.2 | AU21: 4.4 | AV21: 10 | AX21: 25.2 | AZ21: 20.9 | BA21: 0.6 | BB21: 8.7 | BE21: 11.6 | BF21: 4.5 | BG21: 2.7 | BH21: 2.2 | BI21: 1.1 | BJ21: 1.6 | BK21: 0.4 | BM21: 18 | BN21: 10 | BO21: 1.7 | BP21: 409.3
B22: 7:30 | C22: 11 | E22: 6.3 | F22: 5.8 | G22: 1.3 | I22: 9.4 | K22: 8.7 | M22: 5.1 | N22: 7.9 | O22: 2.8 | P22: 2.3 | Q22: 2.6 | R22: 13.7 | S22: 20.2 | T22: 14 | U22: 8 | V22: 5.9 | W22: 0.2 | AA22: 14.1 | AD22: 10.5 | AE22: 3.7 | AF22: 5.4 | AG22: 5.6 | AH22: 5.4 | AI22: 8 | AJ22: 34.2 | AK22: 5.6 | AL22: 10.3 | AM22: 3.4 | AN22: 18.5 | AP22: 119.3 | AR22: 2.5 | AS22: 4.3 | AT22: 11.4 | AU22: 4.5 | AV22: 9.9 | AX22: 68.1 | AZ22: 55.1 | BA22: 0.6 | BB22: 13.3 | BE22: 11.6 | BF22: 4.5 | BG22: 2.7 | BH22: 2.2 | BI22: 1.1 | BJ22: 4.1 | BK22: 0.4 | BM22: 18.1 | BN22: 10 | BO22: 10.9 | BP22: 604.5
B23: 8:00 | C23: 11 | E23: 6.7 | F23: 5.8 | G23: 1.3 | I23: 9.6 | J23: 0.2 | K23: 8.7 | M23: 5.2 | N23: 7.9 | O23: 3.1 | P23: 2.3 | Q23: 2.6 | R23: 13.6 | S23: 20.1 | T23: 14 | U23: 8 | V23: 4 | W23: 1 | AA23: 23.3 | AD23: 10.5 | AE23: 3.7 | AF23: 5.3 | AG23: 5.6 | AH23: 5.6 | AI23: 8 | AJ23: 54.9 | AK23: 4.8 | AL23: 8.6 | AM23: 3.3 | AN23: 18.5 | AP23: 186.6 | AQ23: 0.1 | AR23: 2.4 | AS23: 6.8 | AT23: 12 | AU23: 4.3 | AV23: 9.9 | AW23: 1.9 | AX23: 107.8 | AZ23: 79.2 | BA23: 0.6 | BB23: 14.5 | BE23: 11.6 | BF23: 4.5 | BG23: 2.7 | BH23: 2.2 | BI23: 1.1 | BJ23: 6.7 | BK23: 0.4 | BM23: 18 | BN23: 9.9 | BO23: 15.3 | BP23: 775.7
B24: 8:30 | C24: 11 | E24: 7.3 | F24: 8.7 | G24: 1.1 | I24: 9.4 | J24: 0.7 | K24: 8.7 | M24: 5.2 | N24: 7.9 | O24: 3.3 | P24: 2.3 | Q24: 2.6 | R24: 13.8 | S24: 20.2 | T24: 14 | U24: 8.1 | V24: 4.9 | AA24: 28.6 | AD24: 10.5 | AE24: 3.7 | AF24: 5.3 | AG24: 5.6 | AH24: 5.6 | AI24: 8 | AJ24: 59.3 | AK24: 6.6 | AL24: 10.1 | AM24: 3.3 | AN24: 18.5 | AP24: 196.1 | AQ24: 0.1 | AR24: 2.4 | AS24: 9 | AT24: 12.2 | AU24: 4.5 | AV24: 9.9 | AW24: 1.8 | AX24: 116.8 | AZ24: 84.2 | BA24: 0.6 | BB24: 14.9 | BE24: 11.8 | BF24: 3.6 | BG24: 2.5 | BH24: 2.2 | BI24: 1.1 | BJ24: 8.9 | BK24: 0.4 | BM24: 18.1 | BN24: 10 | BO24: 15.8 | BP24: 821.2
B25: 9:00 | C25: 11 | E25: 6.2 | F25: 11.4 | G25: 1.1 | I25: 9.6 | J25: 0.8 | K25: 8.7 | M25: 5 | N25: 7.8 | O25: 3.5 | P25: 2.3 | Q25: 2.6 | R25: 13.9 | S25: 19.8 | T25: 14 | U25: 8.1 | V25: 4.4 | W25: 0.1 | AA25: 28.8 | AD25: 10.5 | AE25: 3.7 | AF25: 5.3 | AG25: 5.8 | AH25: 5.8 | AI25: 8 | AJ25: 60.7 | AK25: 8.7 | AL25: 11.9 | AM25: 3.3 | AN25: 18.5 | AP25: 202.6 | AQ25: 0.2 | AR25: 2.2 | AS25: 10.9 | AT25: 12.4 | AU25: 4.5 | AV25: 9.9 | AW25: 6.1 | AX25: 119.1 | AY25: 0.6 | AZ25: 86.2 | BA25: 0.6 | BB25: 15.1 | BE25: 11.7 | BF25: 3.6 | BG25: 2.5 | BH25: 2.2 | BI25: 1.1 | BJ25: 10.8 | BK25: 0.4 | BM25: 18.1 | BN25: 10 | BO25: 15.8 | BP25: 847.9
B26: 9:30 | C26: 11 | E26: 6 | F26: 11.6 | G26: 1.2 | H26: 0.1 | I26: 9.6 | J26: 0.9 | K26: 8.7 | M26: 5.2 | N26: 8 | O26: 3.5 | P26: 2.3 | Q26: 2.6 | R26: 13.6 | S26: 20.4 | T26: 14 | U26: 8.1 | V26: 4.3 | W26: 1.2 | AA26: 28.6 | AD26: 10.5 | AE26: 3.6 | AF26: 5.3 | AG26: 5.8 | AH26: 5.8 | AI26: 8 | AJ26: 61.4 | AK26: 7.7 | AL26: 10.3 | AM26: 3.3 | AN26: 18.5 | AP26: 205.4 | AQ26: 0.3 | AR26: 2.2 | AS26: 12.5 | AT26: 12.8 | AU26: 4.5 | AV26: 10 | AW26: 5.3 | AX26: 119.7 | AY26: 1 | AZ26: 86.8 | BA26: 0.6 | BB26: 15.4 | BC26: 0.3 | BD26: 1.4 | BE26: 11.6 | BF26: 3.6 | BG26: 2.5 | BH26: 2.2 | BI26: 1.1 | BJ26: 12.5 | BK26: 0.4 | BM26: 18.1 | BN26: 10 | BO26: 16 | BP26: 857.3
B27: 10:00 | C27: 11 | E27: 5.9 | F27: 12.7 | G27: 1.2 | H27: 0.3 | I27: 9.5 | J27: 1 | K27: 8.7 | M27: 4.8 | N27: 7.8 | O27: 3.4 | P27: 2.2 | Q27: 2.6 | R27: 13.3 | S27: 19.6 | T27: 13.9 | U27: 8 | V27: 6.9 | W27: 2.1 | AA27: 28.5 | AD27: 10.5 | AE27: 3.6 | AF27: 5.3 | AG27: 6 | AH27: 6 | AI27: 7.9 | AJ27: 61.8 | AK27: 7.9 | AL27: 8.1 | AM27: 3.3 | AN27: 18.5 | AP27: 208.3 | AQ27: 0.3 | AR27: 2.2 | AS27: 14 | AT27: 12.6 | AU27: 4.4 | AV27: 9.9 | AW27: 4.6 | AX27: 119.1 | AZ27: 86.9 | BA27: 0.6 | BB27: 15.2 | BC27: 1.5 | BD27: 1.4 | BE27: 11.8 | BF27: 3.6 | BG27: 2.5 | BH27: 2.2 | BI27: 1.1 | BJ27: 13.9 | BK27: 0.4 | BM27: 17.9 | BN27: 10 | BO27: 15.3 | BP27: 862
B28: 10:30 | C28: 14.9 | E28: 6 | F28: 20.2 | G28: 1.2 | H28: 0.3 | I28: 9.5 | J28: 1.1 | K28: 8.7 | M28: 5.2 | N28: 7.5 | O28: 3.5 | P28: 2.3 | Q28: 2.6 | R28: 13.4 | S28: 20.2 | T28: 13.5 | U28: 8.1 | V28: 5.6 | W28: 4.3 | AA28: 28.1 | AD28: 10.5 | AE28: 3.6 | AF28: 5.3 | AG28: 6 | AH28: 6.1 | AI28: 7.9 | AJ28: 62.2 | AK28: 6.9 | AL28: 10.2 | AM28: 3.3 | AN28: 18.5 | AP28: 210.7 | AQ28: 0.3 | AR28: 2.3 | AS28: 14.9 | AT28: 12.2 | AU28: 4.4 | AV28: 9.9 | AW28: 5.3 | AX28: 118.5 | AY28: 3.8 | AZ28: 86.9 | BA28: 0.6 | BB28: 15 | BC28: 0.9 | BD28: 3.6 | BE28: 11.8 | BF28: 3.6 | BG28: 2.5 | BH28: 2.2 | BI28: 1.1 | BJ28: 15 | BK28: 0.4 | BM28: 17.9 | BN28: 10 | BO28: 14.9 | BP28: 885.4
B29: 11:00 | C29: 12.4 | E29: 5.8 | F29: 20.2 | G29: 1.1 | H29: 0.3 | I29: 9.7 | J29: 1.2 | K29: 8.7 | M29: 5.2 | N29: 7.2 | O29: 3.4 | P29: 2.3 | Q29: 2.6 | R29: 13.7 | S29: 20.2 | T29: 13.4 | U29: 8.1 | V29: 3.9 | W29: 7.2 | AA29: 28.3 | AD29: 10.5 | AE29: 3.6 | AF29: 5.3 | AG29: 6.2 | AH29: 6.1 | AI29: 7.9 | AJ29: 62.4 | AK29: 7.9 | AL29: 11.7 | AM29: 3.3 | AN29: 18.5 | AP29: 210.9 | AQ29: 0.4 | AR29: 2.1 | AS29: 15.8 | AT29: 12.5 | AU29: 4.4 | AV29: 9.9 | AW29: 11.5 | AX29: 118 | AY29: 7.4 | AZ29: 86.7 | BA29: 0.6 | BB29: 15 | BC29: 0.6 | BD29: 2.8 | BE29: 11.7 | BF29: 3.6 | BG29: 2.4 | BH29: 2.2 | BI29: 1.1 | BJ29: 15.9 | BK29: 0.4 | BM29: 18.1 | BN29: 10 | BO29: 14.6 | BP29: 896.9
B30: 11:30 | C30: 12.7 | E30: 6.6 | F30: 20.2 | G30: 1.2 | H30: 0.3 | I30: 9.5 | J30: 1.2 | K30: 8.4 | M30: 5.1 | N30: 7.3 | O30: 3.4 | P30: 2.3 | Q30: 2.6 | R30: 13.8 | S30: 20.1 | T30: 13.4 | U30: 8.1 | V30: 5.8 | W30: 12.9 | AA30: 28.2 | AD30: 10.5 | AE30: 3.6 | AF30: 5.3 | AG30: 6.2 | AH30: 6.1 | AI30: 8 | AJ30: 62.2 | AK30: 8.8 | AL30: 11.1 | AM30: 3.3 | AN30: 18.5 | AP30: 211.4 | AQ30: 0.4 | AR30: 2.1 | AS30: 16.2 | AT30: 12.3 | AU30: 4.5 | AV30: 9.9 | AW30: 19.2 | AX30: 117.3 | AY30: 15 | AZ30: 86.7 | BA30: 0.6 | BB30: 14.9 | BD30: 0.3 | BE30: 11.6 | BF30: 3.6 | BG30: 2.4 | BH30: 2.2 | BI30: 1.1 | BJ30: 16.4 | BK30: 0.4 | BM30: 18.1 | BN30: 10 | BO30: 14.8 | BP30: 918.1
B31: 12:00 | C31: 14 | E31: 6.1 | F31: 20.1 | G31: 1.2 | H31: 0.3 | I31: 9.5 | J31: 1.2 | K31: 8.5 | M31: 5.1 | N31: 7.3 | O31: 3.4 | P31: 2.4 | Q31: 2.6 | R31: 13.6 | S31: 19.8 | T31: 13.6 | U31: 8.1 | V31: 7.9 | W31: 17.2 | AA31: 28.2 | AD31: 10.5 | AE31: 3.6 | AF31: 5.3 | AG31: 6 | AH31: 6.1 | AI31: 8.9 | AJ31: 62.8 | AK31: 10.5 | AL31: 11.9 | AM31: 3.3 | AN31: 18.5 | AP31: 211 | AQ31: 0.4 | AR31: 2.1 | AS31: 16.3 | AT31: 12.4 | AU31: 4.4 | AV31: 9.8 | AW31: 21.1 | AX31: 116.4 | AY31: 18.4 | AZ31: 86.3 | BA31: 0.6 | BB31: 15.1 | BE31: 11.5 | BF31: 3.6 | BG31: 2.4 | BH31: 2.2 | BI31: 1.1 | BJ31: 16.7 | BK31: 0.4 | BM31: 18 | BN31: 10 | BO31: 14.6 | BP31: 932.3
B32: 12:30 | C32: 13 | E32: 7.5 | F32: 20.1 | G32: 1.1 | H32: 0.3 | I32: 9.7 | J32: 1.3 | K32: 8.2 | M32: 5.2 | N32: 7.4 | O32: 3.4 | P32: 2 | Q32: 2.6 | R32: 13.2 | S32: 20.3 | T32: 13.8 | U32: 8.1 | V32: 7.2 | W32: 19 | AA32: 27.9 | AD32: 10.5 | AE32: 3.6 | AF32: 5.3 | AG32: 6 | AH32: 6.1 | AI32: 7.9 | AJ32: 63.4 | AK32: 12.8 | AL32: 15.5 | AM32: 3.3 | AN32: 18.5 | AP32: 210.3 | AQ32: 0.4 | AR32: 2.1 | AS32: 16.6 | AT32: 12.4 | AU32: 4.3 | AV32: 9.9 | AW32: 8.8 | AX32: 115.5 | AY32: 13.3 | AZ32: 85.9 | BA32: 0.6 | BB32: 15.2 | BE32: 11.4 | BF32: 2.7 | BG32: 1.8 | BH32: 2.2 | BI32: 1 | BJ32: 16.4 | BK32: 0.4 | BM32: 17.9 | BN32: 10 | BO32: 14.6 | BP32: 917.9
B33: 13:00 | C33: 13 | E33: 7.3 | F33: 20.2 | G33: 1.1 | H33: 0.3 | I33: 9.6 | J33: 1.2 | K33: 8 | M33: 5.2 | N33: 7.3 | O33: 3.4 | P33: 2.1 | Q33: 2.6 | R33: 13.1 | S33: 20.2 | T33: 13.9 | U33: 8.7 | V33: 6.1 | W33: 17.3 | AA33: 28.3 | AD33: 10.5 | AE33: 3.5 | AF33: 5.2 | AG33: 5.6 | AH33: 5.7 | AI33: 7.9 | AJ33: 63.5 | AK33: 12.7 | AL33: 14.1 | AM33: 3.3 | AN33: 18.5 | AP33: 210.3 | AQ33: 0.4 | AR33: 2.1 | AS33: 16 | AT33: 12.5 | AU33: 4.5 | AV33: 10 | AW33: 3.7 | AX33: 115.9 | AY33: 8.9 | AZ33: 85.9 | BA33: 0.6 | BB33: 15.2 | BE33: 11.6 | BF33: 2.7 | BG33: 1.8 | BH33: 2.2 | BI33: 1 | BJ33: 16.1 | BK33: 0.4 | BM33: 17.9 | BN33: 10 | BO33: 14.7 | BP33: 903.8
B34: 13:30 | C34: 13 | E34: 7.1 | F34: 20.2 | G34: 1.1 | H34: 0.3 | I34: 9.5 | J34: 1.2 | K34: 7.7 | M34: 4.9 | N34: 7.2 | O34: 3.3 | P34: 2.1 | Q34: 2.6 | R34: 13.2 | S34: 20.1 | T34: 14 | U34: 8.8 | V34: 11.5 | W34: 12.2 | AA34: 28.6 | AD34: 10.5 | AE34: 3.5 | AF34: 5.2 | AG34: 5.4 | AH34: 5.5 | AI34: 7.9 | AJ34: 64.1 | AK34: 14.7 | AL34: 17.3 | AM34: 3.3 | AN34: 18.5 | AP34: 210.6 | AQ34: 0.3 | AR34: 2.1 | AS34: 15.4 | AT34: 12.3 | AU34: 4.5 | AV34: 9.9 | AW34: 5.9 | AX34: 117.5 | AY34: 11 | AZ34: 86.3 | BA34: 0.6 | BB34: 15.1 | BE34: 11.4 | BF34: 2.9 | BG34: 1.8 | BH34: 2.2 | BI34: 1 | BJ34: 15.2 | BK34: 0.4 | BM34: 17.9 | BN34: 10 | BO34: 15.1 | BP34: 913.9
B35: 14:00 | C35: 13 | E35: 7.4 | F35: 20.2 | G35: 1.1 | H35: 0.3 | I35: 9.2 | J35: 1.1 | K35: 7.5 | M35: 5.2 | N35: 7.4 | O35: 3.2 | P35: 2.1 | Q35: 2.6 | R35: 13.3 | S35: 20.2 | T35: 14 | U35: 8.8 | V35: 17.5 | W35: 10.6 | Y35: 0.6 | AA35: 28.8 | AD35: 10.5 | AE35: 3.5 | AF35: 5 | AG35: 5.4 | AH35: 5.5 | AI35: 7.7 | AJ35: 63.5 | AK35: 15.2 | AL35: 17 | AM35: 3.3 | AN35: 18.5 | AP35: 209.6 | AQ35: 0.3 | AR35: 2.1 | AS35: 14.4 | AT35: 12 | AU35: 4.5 | AV35: 9.9 | AW35: 8.3 | AX35: 118.7 | AY35: 9.4 | AZ35: 86.6 | BA35: 0.6 | BB35: 14.5 | BE35: 11.3 | BF35: 3.2 | BG35: 2.1 | BH35: 2.2 | BI35: 1 | BJ35: 14.2 | BK35: 0.4 | BM35: 17.9 | BN35: 10 | BO35: 15.4 | BP35: 917.8
B36: 14:30 | C36: 13.2 | E36: 7.5 | F36: 20.2 | G36: 1.1 | H36: 0.3 | I36: 9.4 | J36: 1 | K36: 7.5 | M36: 5.4 | N36: 7.5 | O36: 3.2 | P36: 2.4 | Q36: 2.6 | R36: 13.4 | S36: 20.1 | T36: 13.9 | U36: 8.8 | V36: 15.2 | W36: 11 | Y36: 0.4 | Z36: 0.3 | AA36: 28.9 | AD36: 10.5 | AE36: 3.5 | AF36: 5 | AG36: 5.4 | AH36: 5.5 | AI36: 7.6 | AJ36: 63.2 | AK36: 13.7 | AL36: 15.3 | AM36: 3.3 | AN36: 18.5 | AP36: 211.3 | AQ36: 0.3 | AR36: 2.1 | AS36: 12.9 | AT36: 11.6 | AU36: 4.3 | AV36: 9.9 | AW36: 12.9 | AX36: 118.8 | AY36: 11.8 | AZ36: 86.2 | BA36: 0.6 | BB36: 14.3 | BE36: 11.2 | BF36: 3.3 | BG36: 2.2 | BH36: 2.2 | BI36: 1.1 | BJ36: 12.9 | BK36: 0.4 | BM36: 17.9 | BN36: 10 | BO36: 15.2 | BP36: 918.2
B37: 15:00 | C37: 13.6 | E37: 6.7 | F37: 20.2 | G37: 1.1 | H37: 0.3 | I37: 9.1 | J37: 0.9 | K37: 7.6 | M37: 5.2 | N37: 7.3 | O37: 3.1 | P37: 2 | Q37: 2.6 | R37: 13.6 | S37: 20.3 | T37: 13.2 | U37: 8.7 | V37: 12 | W37: 9.2 | Y37: 1 | Z37: 0.8 | AA37: 28.1 | AB37: 0.4 | AD37: 10.5 | AE37: 3.5 | AF37: 5 | AG37: 5.4 | AH37: 5.5 | AI37: 7.6 | AJ37: 61.5 | AK37: 14.4 | AL37: 15.2 | AM37: 3.3 | AN37: 18.5 | AP37: 207.3 | AQ37: 0.3 | AR37: 2.1 | AS37: 11.2 | AT37: 12 | AU37: 4.3 | AV37: 9.9 | AW37: 19.2 | AX37: 117.2 | AY37: 13.4 | AZ37: 84.6 | BA37: 0.6 | BB37: 14.4 | BE37: 11.3 | BF37: 3.3 | BG37: 2.2 | BH37: 2.2 | BI37: 1.1 | BJ37: 11.2 | BK37: 0.4 | BM37: 18 | BN37: 10 | BO37: 14.9 | BP37: 908.5
B38: 15:30 | C38: 14.3 | E38: 6 | F38: 20.2 | G38: 1.2 | H38: 0.3 | I38: 9.4 | J38: 0.8 | K38: 7.5 | M38: 5.3 | N38: 7.5 | O38: 3.1 | P38: 2.2 | Q38: 2.6 | R38: 13.8 | S38: 20 | T38: 12.8 | U38: 8.8 | V38: 11.1 | W38: 7.5 | Y38: 0.9 | Z38: 0.8 | AA38: 26.6 | AB38: 0.2 | AD38: 10.5 | AE38: 3.5 | AF38: 5.3 | AG38: 5.6 | AH38: 5.7 | AI38: 7.6 | AJ38: 60.2 | AK38: 15.6 | AL38: 17 | AM38: 3.3 | AN38: 18.5 | AP38: 201.6 | AQ38: 0.2 | AR38: 2.1 | AS38: 9.3 | AT38: 11.5 | AU38: 4.5 | AV38: 10 | AW38: 14.6 | AX38: 112.8 | AY38: 11.7 | AZ38: 80.9 | BA38: 0.6 | BB38: 13.4 | BE38: 11.2 | BF38: 3.3 | BG38: 2.2 | BH38: 1.2 | BI38: 1.1 | BJ38: 9.3 | BK38: 0.4 | BM38: 18.2 | BN38: 10 | BO38: 14 | BP38: 879.8
B39: 16:00 | C39: 14.5 | E39: 7.8 | F39: 20.2 | G39: 1.3 | H39: 0.3 | I39: 9.3 | J39: 0.6 | K39: 7.6 | M39: 5 | N39: 7 | O39: 3.1 | P39: 1.8 | Q39: 2.6 | R39: 13.6 | S39: 20 | T39: 12.6 | U39: 8.7 | V39: 8.4 | W39: 7.4 | X39: 0.3 | Y39: 1 | Z39: 0.4 | AA39: 20.2 | AB39: 0.2 | AD39: 10.5 | AE39: 3.5 | AF39: 5.4 | AG39: 5.7 | AH39: 5.7 | AI39: 8.2 | AJ39: 46.5 | AK39: 15.8 | AL39: 17 | AM39: 3.3 | AN39: 18.5 | AP39: 176.5 | AQ39: 0.2 | AR39: 2.5 | AS39: 6.9 | AT39: 9.5 | AU39: 4.4 | AV39: 10 | AW39: 9.7 | AX39: 82.2 | AY39: 13.4 | AZ39: 70.7 | BA39: 0.6 | BB39: 11.3 | BE39: 11.2 | BF39: 3.8 | BG39: 2.2 | BH39: 1.4 | BI39: 1.1 | BJ39: 7.1 | BK39: 0.4 | BM39: 16.9 | BN39: 10 | BO39: 10.8 | BP39: 776.8
B40: 16:30 | C40: 14.5 | E40: 6.9 | F40: 20.2 | G40: 1.3 | H40: 0.3 | I40: 9.5 | J40: 0.3 | K40: 7.6 | M40: 5.2 | N40: 7.3 | O40: 3 | P40: 2.3 | Q40: 2.6 | R40: 13.7 | S40: 20 | T40: 12.6 | U40: 8.7 | V40: 4.6 | W40: 15.6 | X40: 2 | Y40: 1.9 | Z40: 1.7 | AA40: 10.5 | AB40: 0.4 | AD40: 10.5 | AE40: 3.5 | AF40: 5.4 | AG40: 5.7 | AH40: 5.7 | AI40: 8.1 | AJ40: 23.6 | AK40: 13.1 | AL40: 17.9 | AM40: 3.3 | AN40: 18.5 | AP40: 101.5 | AQ40: 0.2 | AR40: 2.2 | AS40: 4.4 | AT40: 4.1 | AU40: 4.5 | AV40: 9.9 | AW40: 5.2 | AX40: 42.2 | AY40: 11.3 | AZ40: 39.7 | BA40: 0.6 | BB40: 4.7 | BD40: 0.3 | BE40: 11.1 | BF40: 4.1 | BG40: 2.7 | BH40: 2.2 | BI40: 1.1 | BJ40: 4.6 | BK40: 0.4 | BM40: 18.1 | BN40: 10 | BO40: 3.7 | BP40: 576.8
B41: 17:00 | C41: 14.6 | E41: 8.3 | F41: 20.2 | G41: 1.3 | H41: 0.3 | I41: 9.1 | K41: 7.6 | M41: 5.1 | N41: 7.2 | O41: 2.9 | P41: 2.4 | Q41: 2.6 | R41: 13.3 | S41: 20.1 | T41: 12.4 | U41: 8.7 | V41: 2.4 | W41: 16.5 | X41: 3.4 | Y41: 2 | Z41: 3.2 | AA41: 2.2 | AB41: 0.2 | AC41: 0.1 | AD41: 10.5 | AE41: 3.5 | AF41: 5.2 | AG41: 5.7 | AH41: 5.7 | AI41: 8.1 | AJ41: 6 | AK41: 15.5 | AL41: 16.9 | AM41: 3.3 | AN41: 18.5 | AP41: 26 | AQ41: 0.1 | AR41: 2.5 | AS41: 1.8 | AT41: 0.3 | AU41: 4.4 | AV41: 9.9 | AW41: 9.4 | AX41: 7.9 | AY41: 9.5 | AZ41: 8.8 | BA41: 0.6 | BB41: 0.2 | BC41: 0.6 | BD41: 2.5 | BE41: 11.1 | BF41: 4.4 | BG41: 2.9 | BH41: 2.2 | BI41: 1.1 | BJ41: 2.1 | BK41: 0.4 | BM41: 17.9 | BN41: 10 | BP41: 401.6
B42: 17:30 | C42: 14.5 | E42: 7.9 | F42: 20.2 | G42: 1.3 | H42: 0.3 | I42: 9.5 | K42: 7.7 | M42: 5.1 | N42: 7.2 | O42: 2.8 | P42: 2.3 | Q42: 2.6 | R42: 13.4 | S42: 19.8 | T42: 12.4 | U42: 8.7 | V42: 0.8 | W42: 19.8 | X42: 6.6 | Y42: 2.9 | Z42: 5 | AB42: 0.5 | AC42: 0.2 | AD42: 10.5 | AE42: 3.5 | AF42: 4.9 | AG42: 5.7 | AH42: 5.7 | AI42: 8.1 | AK42: 14.2 | AL42: 15.9 | AM42: 3.3 | AN42: 18.5 | AQ42: 0.1 | AR42: 2.4 | AS42: 0.1 | AU42: 4.4 | AV42: 9.9 | AW42: 21.1 | AY42: 18.2 | BA42: 0.6 | BC42: 0.7 | BD42: 3.7 | BE42: 11 | BF42: 4.5 | BG42: 2.9 | BH42: 2.2 | BI42: 1.1 | BJ42: 0.1 | BK42: 0.4 | BM42: 17.9 | BN42: 10 | BP42: 373.1
B43: 18:00 | C43: 14.6 | E43: 7.2 | F43: 20.2 | G43: 1.3 | H43: 0.3 | I43: 9.4 | K43: 7.7 | M43: 5 | N43: 7.1 | O43: 2.8 | P43: 2.3 | Q43: 2.6 | R43: 14 | S43: 19.2 | T43: 12.3 | U43: 8.7 | V43: 0.7 | W43: 19.9 | X43: 7.7 | Y43: 2.4 | Z43: 7.3 | AB43: 0.6 | AC43: 0.1 | AD43: 10.5 | AE43: 3.5 | AF43: 4.9 | AG43: 5.4 | AH43: 5.7 | AI43: 8.1 | AK43: 13.6 | AL43: 16.1 | AM43: 3.3 | AN43: 18.5 | AR43: 2.4 | AU43: 4.5 | AV43: 9.9 | AW43: 37.2 | AY43: 43.2 | BA43: 0.6 | BC43: 1.3 | BD43: 9.3 | BE43: 11.1 | BF43: 4.5 | BG43: 2.9 | BH43: 2.2 | BI43: 1.1 | BK43: 0.4 | BM43: 18.2 | BN43: 10 | BP43: 421.8
B44: 18:30 | C44: 14 | E44: 6.6 | F44: 20.2 | G44: 1.4 | H44: 0.3 | I44: 10.4 | K44: 7.7 | M44: 5.1 | N44: 7.2 | O44: 2.8 | P44: 1.5 | Q44: 2.6 | R44: 14.1 | S44: 19.3 | T44: 12 | U44: 8.7 | V44: 0.2 | W44: 13.1 | X44: 9.8 | Y44: 6.8 | Z44: 14.7 | AB44: 0.5 | AC44: 0.4 | AD44: 10.5 | AE44: 3.4 | AF44: 4.9 | AG44: 5.4 | AH44: 5.7 | AI44: 8.1 | AK44: 12 | AL44: 16.7 | AM44: 3.2 | AN44: 18.5 | AR44: 2.7 | AU44: 4.4 | AV44: 10 | AW44: 32.4 | AY44: 47.8 | BA44: 0.6 | BC44: 2.7 | BD44: 14.7 | BE44: 11 | BF44: 4.5 | BG44: 2.9 | BH44: 2.2 | BI44: 1.1 | BK44: 0.4 | BM44: 18.3 | BN44: 10 | BP44: 433.5
B45: 19:00 | C45: 14 | E45: 6.5 | F45: 20.3 | G45: 1.5 | H45: 0.3 | I45: 10.3 | K45: 7.7 | M45: 5.1 | N45: 7.2 | O45: 2.8 | P45: 1.8 | Q45: 2.6 | R45: 13.7 | S45: 20.1 | T45: 12 | U45: 8.7 | W45: 21.7 | X45: 14.6 | Y45: 8.8 | Z45: 13.5 | AB45: 0.9 | AC45: 0.7 | AD45: 10.5 | AE45: 3.4 | AF45: 5 | AG45: 5.4 | AH45: 5.4 | AI45: 8.4 | AK45: 14 | AL45: 17 | AM45: 3.3 | AN45: 18.5 | AR45: 2.8 | AU45: 4.5 | AV45: 9.9 | AW45: 17.1 | AY45: 34.3 | BA45: 0.6 | BC45: 3.6 | BD45: 18.9 | BE45: 11 | BF45: 4.5 | BG45: 2.9 | BH45: 2.2 | BI45: 1.1 | BK45: 0.4 | BM45: 18.1 | BN45: 10 | BP45: 427.6
B46: 19:30 | C46: 14 | E46: 6.6 | F46: 20.2 | G46: 1.5 | H46: 0.3 | I46: 10.4 | K46: 7.7 | M46: 5.1 | N46: 7.3 | O46: 2.8 | P46: 1.8 | Q46: 2.6 | R46: 13.7 | S46: 20.2 | T46: 12 | U46: 8.7 | W46: 33.3 | X46: 12.9 | Y46: 9.1 | Z46: 14.8 | AB46: 0.9 | AC46: 0.7 | AD46: 10.5 | AE46: 3.4 | AF46: 5.2 | AG46: 5.4 | AH46: 5.4 | AI46: 8.1 | AK46: 12.8 | AL46: 16.9 | AM46: 3.3 | AN46: 18.5 | AR46: 2.6 | AU46: 4.4 | AV46: 9.9 | AW46: 9.3 | AY46: 22.7 | BA46: 0.6 | BC46: 4.2 | BD46: 17.6 | BE46: 11 | BF46: 4.5 | BG46: 2.9 | BH46: 2.2 | BI46: 1.1 | BK46: 0.4 | BM46: 18 | BN46: 10 | BP46: 417.5
B47: 20:00 | C47: 14.5 | E47: 7.1 | F47: 20.2 | G47: 1.4 | H47: 0.3 | I47: 10.3 | K47: 7.7 | M47: 5.2 | N47: 7.2 | O47: 2.9 | P47: 1.8 | Q47: 2.6 | R47: 13.7 | S47: 19.8 | T47: 12 | U47: 8.7 | V47: 0.6 | W47: 19.9 | X47: 5.8 | Y47: 7.6 | Z47: 12.9 | AB47: 0.8 | AC47: 0.3 | AD47: 10.5 | AE47: 3.4 | AF47: 5.2 | AG47: 5.6 | AH47: 5.4 | AI47: 8.1 | AK47: 11.3 | AL47: 15.4 | AM47: 3.3 | AN47: 18.5 | AR47: 2.7 | AU47: 4.4 | AV47: 9.9 | AW47: 8.2 | AY47: 22.9 | BA47: 0.6 | BC47: 3 | BD47: 14 | BE47: 11 | BF47: 4.5 | BG47: 2.9 | BH47: 2.2 | BI47: 1.1 | BK47: 0.4 | BM47: 18.1 | BN47: 10 | BP47: 385.9
B48: 20:30 | C48: 14.5 | E48: 8 | F48: 20.3 | G48: 1.5 | H48: 0.3 | I48: 10 | K48: 7.7 | M48: 5.1 | N48: 7.2 | O48: 3.1 | P48: 1.7 | Q48: 2.6 | R48: 13.8 | S48: 19.7 | T48: 12 | U48: 8.7 | V48: 0.6 | W48: 22.7 | X48: 1.4 | Y48: 5.9 | Z48: 11.6 | AB48: 0.7 | AC48: 0.5 | AD48: 10.5 | AE48: 3.4 | AF48: 5.2 | AG48: 5.6 | AH48: 5.6 | AI48: 7.9 | AK48: 10.4 | AL48: 16 | AM48: 3.3 | AN48: 18.5 | AR48: 2.9 | AU48: 4.4 | AV48: 9.8 | AW48: 5.9 | AY48: 16.2 | BA48: 0.6 | BC48: 1.3 | BD48: 7.4 | BE48: 10.9 | BF48: 4.5 | BG48: 2.9 | BH48: 2.2 | BI48: 1.1 | BK48: 0.4 | BM48: 18.1 | BN48: 10 | BP48: 364.6
B49: 21:00 | C49: 14.5 | E49: 7.2 | F49: 19.7 | G49: 1.4 | H49: 0.3 | I49: 10.3 | K49: 7.8 | M49: 5.1 | N49: 7.2 | O49: 3.3 | P49: 1.8 | Q49: 2.6 | R49: 13.8 | S49: 20 | T49: 12 | U49: 8.7 | V49: 0.5 | W49: 23.7 | X49: 3 | Y49: 9.6 | Z49: 15.4 | AB49: 1.1 | AC49: 0.5 | AD49: 10.5 | AE49: 3.4 | AF49: 5 | AG49: 5.6 | AH49: 5.6 | AI49: 7.8 | AK49: 11.4 | AL49: 16 | AM49: 3.3 | AN49: 18.5 | AR49: 2.5 | AU49: 4.5 | AV49: 9.9 | AW49: 2.1 | AY49: 5.4 | BA49: 0.6 | BC49: 0.8 | BD49: 4.5 | BE49: 10.9 | BF49: 4.5 | BG49: 2.9 | BH49: 2.2 | BI49: 1.1 | BK49: 0.4 | BM49: 18.1 | BN49: 10 | BP49: 357
B50: 21:30 | C50: 14.5 | E50: 7.1 | F50: 15 | G50: 1.4 | H50: 0.3 | I50: 9.5 | K50: 8.2 | M50: 5.1 | N50: 7.2 | O50: 3.5 | P50: 2.1 | Q50: 2.6 | R50: 13.7 | S50: 20.2 | T50: 11.9 | U50: 8.7 | V50: 0.7 | W50: 21.8 | X50: 6.4 | Y50: 10.9 | Z50: 18 | AB50: 1.4 | AC50: 0.9 | AD50: 10.5 | AE50: 3.4 | AF50: 5 | AG50: 5.6 | AH50: 5.6 | AI50: 7.3 | AK50: 12.6 | AL50: 16.3 | AM50: 3.4 | AN50: 18.5 | AR50: 2.7 | AU50: 4.5 | AV50: 9.9 | AW50: 2.3 | AY50: 3.6 | BA50: 0.6 | BC50: 0.8 | BD50: 3.5 | BE50: 11 | BF50: 4.5 | BG50: 2.9 | BH50: 2.2 | BI50: 1.1 | BK50: 0.4 | BM50: 18.1 | BN50: 10 | BP50: 357.4
B51: 22:00 | C51: 14.5 | E51: 8.2 | F51: 15 | G51: 1.4 | H51: 0.3 | I51: 9.5 | K51: 8.2 | M51: 5.1 | N51: 7.2 | O51: 3.6 | P51: 2.2 | Q51: 2.6 | R51: 13.4 | S51: 20.1 | T51: 11.9 | U51: 8.7 | V51: 1 | W51: 21.7 | X51: 9.8 | Y51: 9.3 | Z51: 15.5 | AB51: 1.1 | AC51: 0.6 | AD51: 10.5 | AE51: 3.3 | AF51: 5 | AG51: 5.6 | AH51: 5.6 | AI51: 7.3 | AK51: 11 | AL51: 15.7 | AM51: 3.4 | AN51: 18.5 | AR51: 2.7 | AU51: 4.5 | AV51: 10 | AW51: 0.2 | AY51: 2.2 | BA51: 0.6 | BC51: 1.4 | BD51: 5.9 | BE51: 10.9 | BF51: 4.5 | BG51: 2.9 | BH51: 2.2 | BI51: 1.1 | BK51: 0.4 | BM51: 18 | BN51: 10 | BP51: 354.3
B52: 22:30 | C52: 14.5 | E52: 8.2 | F52: 14.9 | G52: 1.3 | H52: 0.3 | I52: 9.5 | K52: 8.2 | M52: 5 | N52: 7.2 | O52: 3.6 | P52: 2.2 | Q52: 2.5 | R52: 13.6 | S52: 20 | T52: 12 | U52: 8.7 | V52: 0.7 | W52: 21.3 | X52: 15.2 | Y52: 8.8 | Z52: 15.3 | AB52: 1.4 | AC52: 0.3 | AD52: 10.5 | AE52: 3.3 | AF52: 5 | AG52: 5.6 | AH52: 5.6 | AI52: 7.3 | AK52: 10.6 | AL52: 14.7 | AM52: 3.4 | AN52: 18.5 | AR52: 2.8 | AU52: 4.4 | AV52: 9.9 | BA52: 0.6 | BC52: 3.8 | BD52: 7.6 | BE52: 10.9 | BF52: 4.5 | BG52: 2.9 | BH52: 2.2 | BI52: 1.1 | BK52: 0.4 | BM52: 18 | BN52: 10 | BP52: 358.3
B53: 23:00 | C53: 14.5 | E53: 6.5 | F53: 14.5 | G53: 1.3 | H53: 0.3 | I53: 8.9 | K53: 8.1 | M53: 5.1 | N53: 7.3 | O53: 3.6 | P53: 2.1 | Q53: 2.5 | R53: 13.8 | S53: 20.2 | T53: 12.3 | U53: 8.7 | V53: 0.6 | W53: 26.5 | X53: 22.7 | Y53: 6.6 | Z53: 13.9 | AB53: 0.8 | AC53: 0.3 | AD53: 10.5 | AE53: 3.3 | AF53: 5 | AG53: 5.7 | AH53: 5.6 | AI53: 7.5 | AK53: 11.2 | AL53: 17 | AM53: 3.4 | AN53: 18.5 | AR53: 2.4 | AU53: 4.5 | AV53: 10 | BA53: 0.6 | BC53: 7.5 | BD53: 11.4 | BE53: 10.9 | BF53: 4.5 | BG53: 2.9 | BH53: 2.2 | BI53: 1.1 | BK53: 0.4 | BM53: 18.1 | BN53: 10 | BP53: 375.3
B54: 23:30 | C54: 14.5 | E54: 7.7 | F54: 12 | G54: 1.3 | H54: 0.3 | I54: 9.5 | K54: 8.1 | M54: 5.2 | N54: 7.2 | O54: 3.5 | P54: 2.2 | Q54: 2.5 | R54: 13.8 | S54: 20.2 | T54: 12.3 | U54: 8.7 | V54: 0.8 | W54: 22.5 | X54: 21.5 | Y54: 6.3 | Z54: 14.2 | AB54: 0.6 | AC54: 0.2 | AD54: 10.5 | AE54: 3.3 | AF54: 5.1 | AG54: 5.7 | AH54: 5.6 | AI54: 7.5 | AK54: 12.3 | AL54: 16.9 | AM54: 3.4 | AN54: 18.5 | AR54: 2.2 | AU54: 4.5 | AV54: 9.9 | BA54: 0.6 | BC54: 5.1 | BD54: 11.5 | BE54: 10.8 | BF54: 4.5 | BG54: 2.9 | BH54: 2.2 | BI54: 1.1 | BK54: 0.4 | BM54: 18.1 | BN54: 10 | BP54: 367.7
B55: 0:00 | C55: 15 | E55: 8.4 | F55: 5.6 | G55: 1.3 | H55: 0.3 | I55: 8.9 | K55: 8.1 | M55: 5.1 | N55: 7.2 | O55: 3.5 | P55: 2.1 | Q55: 2.5 | R55: 13.5 | S55: 20.1 | T55: 12 | U55: 8.7 | V55: 1.7 | W55: 17.2 | X55: 16.7 | Y55: 6.8 | Z55: 13.1 | AB55: 0.3 | AD55: 10.5 | AE55: 3.3 | AF55: 5.1 | AG55: 5.7 | AH55: 5.7 | AI55: 7.5 | AK55: 12 | AL55: 17 | AM55: 3.4 | AN55: 18.5 | AR55: 2.2 | AU55: 4.4 | AV55: 9.9 | BA55: 0.6 | BC55: 4.5 | BD55: 8.9 | BE55: 10.9 | BF55: 4.5 | BG55: 2.9 | BH55: 2.2 | BI55: 1.1 | BK55: 0.4 | BM55: 17.9 | BN55: 10 | BP55: 347.2
B56: EJEC MWh | C56: 335.95 | D56: 0 | E56: 171.1 | F56: 330.65 | G56: 30.55 | H56: 4.4 | I56: 229.65 | J56: 8.35 | K56: 197.15 | L56: 0 | M56: 122.9 | N56: 176.25 | O56: 79.75 | P56: 51.15 | Q56: 62.2 | R56: 325.9 | S56: 480.1 | T56: 314.5 | U56: 204.8 | V56: 132.1 | W56: 262.7 | X56: 80.45 | Y56: 54.8 | Z56: 96.2 | AA56: 249.9 | AB56: 6.5 | AC56: 2.9 | AD56: 252 | AE56: 86.1 | AF56: 124.55 | AG56: 134.15 | AH56: 134.5 | AI56: 189 | AJ56: 555.35 | AK56: 249.85 | AL56: 334.35 | AM56: 80.05 | AN56: 444 | AO56: 0 | AP56: 1886.85 | AQ56: 2.65 | AR56: 58.25 | AS56: 115.7 | AT56: 115.7 | AU56: 106.9 | AV56: 238.15 | AW56: 181.15 | AX56: 1048.35 | AY56: 188.2 | AZ56: 781.5 | BA56: 14.4 | BB56: 138.8 | BC56: 22.85 | BD56: 77 | BE56: 272 | BF56: 98.75 | BG56: 62.7 | BH56: 51.65 | BI56: 25.75 | BJ56: 115.85 | BK56: 9.6 | BL56: 0 | BM56: 431.95 | BN56: 239.95 | BO56: 134.2 | BP56: 13013.65
L70: TERMOELÉCTRICA | M70: 975.55 | N70: 7.4963596 | O70: #FFA975
L71: EÓLICA | M71: 1689.05 | N71: 12.979064 | O71: #B9ACFF
L72: SOLAR | M72: 5153.2 | N72: 39.598422 | O72: #FFD272
L73: HIDROELÉCTRICA | M73: 5195.85 | N73: 39.926154 | O73: #98D2FF

Sheet COGENERACIÓN
B3: viernes, 4 de Julio del 2025
B5: CENTRALES DE COGENERACIÓN DEL SEIN
B6: HORA | C6: AGRO INDUSTRIAL PARAMONGA S.A. | D6: AGROAURORA S.A.C. | E6: AGROINDUSTRIAS SAN JACINTO S.A.A. | F6: BIOENERGIA DEL CHIRA S.A. | G6: GM OPERACIONES S.A.C. | H6: SDF ENERGIA SAC | I6: TOTAL COGENERACION
C7: C.T. PARAMONGA | D7: C.T. MAPLE | E7: C.T SAN JACINTO | F7: C.T. CAÑA BRAVA | G7: C.T. REFINERÍA TALARA | H7: C.T. OQUENDO | I7: MW
B8: 0:30 | C8: 15.2 | E8: 7.3 | F8: 9.3 | G8: 77.77 | I8: 109.57
B9: 1:00 | C9: 15.3 | E9: 7.5 | F9: 9.3 | G9: 78.65 | I9: 110.75
B10: 1:30 | C10: 15.4 | E10: 7.3 | F10: 9.6 | G10: 77.89 | I10: 110.19
B11: 2:00 | C11: 15.3 | E11: 7.4 | F11: 9.4 | G11: 77.81 | I11: 109.91
B12: 2:30 | C12: 15.2 | E12: 7.1 | F12: 9.5 | G12: 77.85 | I12: 109.65
B13: 3:00 | C13: 15.3 | E13: 7.5 | F13: 9.6 | G13: 77.86 | I13: 110.26
B14: 3:30 | C14: 15.3 | E14: 7.6 | F14: 9.5 | G14: 77.72 | I14: 110.12
B15: 4:00 | C15: 15.3 | E15: 8 | F15: 9.4 | G15: 78.08 | I15: 110.78
B16: 4:30 | C16: 15.2 | E16: 7.6 | F16: 9.5 | G16: 77.85 | I16: 110.15
B17: 5:00 | C17: 15.1 | E17: 7.4 | F17: 9.6 | G17: 77.41 | I17: 109.51
B18: 5:30 | C18: 15 | E18: 7.5 | F18: 9.7 | G18: 77.18 | I18: 109.38
B19: 6:00 | C19: 15.3 | E19: 7.5 | F19: 9.8 | G19: 77.41 | I19: 110.01
... B48: 20:30 | C48: 14.5 | E48: 8 | F48: 10 | G48: 73.84 | I48: 106.34
B49: 21:00 | C49: 14.5 | E49: 7.2 | F49: 10.3 | I49: 32
B50: 21:30 | C50: 14.5 | E50: 7.1 | F50: 9.5 | I50: 31.1
B51: 22:00 | C51: 14.5 | E51: 8.2 | F51: 9.5 | I51: 32.2
B52: 22:30 | C52: 14.5 | E52: 8.2 | F52: 9.5 | I52: 32.2
B53: 23:00 | C53: 14.5 | E53: 6.5 | F53: 8.9 | I53: 29.9
B54: 23:30 | C54: 14.5 | E54: 7.7 | F54: 9.5 | I54: 31.7
B55: 0:00 | C55: 15 | E55: 8.4 | F55: 8.9 | I55: 32.3
B56: EJEC MWh | C56: 335.95 | D56: 0 | E56: 171.1 | F56: 229.65 | G56: 1587.775 | H56: 0 | I56: 2324.475

Sheet EVO_PRO_ENE
B3: martes, 1 de Julio del 2025 - viernes, 4 de Julio del 2025
B5: EVOLUCIÓN DE LA PRODUCCIÓN DE LA ENERGÍA DIARIA DE LOS INTEGRANTES DEL COES (MWh)
B6: EMPRESA | C6: CENTRAL | D6: UNIDAD | E6: TIPO | F6: Julio
F7: 1 | G7: 2 | H7: 3 | I7: 4 | J7: TOTAL
B8: AGRO INDUSTRIAL PARAMONGA S.A. | C8: C.T. PARAMONGA | D8: TV-01 | E8: TERMOELÉCTRICA | H8: 66.2 | I8: 335.95 | J8: 402.15
B9: AGROAURORA S.A.C. | C9: C.T. MAPLE ETANOL | D9: TV | E9: TERMOELÉCTRICA | J9: 0
B10: AGROINDUSTRIAS SAN JACINTO S.A.A. | C10: C.T. SAN JACINTO | D10: CENTRAL | E10: TERMOELÉCTRICA | F10: 181.65 | G10: 167.65 | H10: 167.1 | I10: 171.1 | J10: 687.5
B11: ANDEAN POWER S.A.C. | C11: C.H.CARHUAC | D11: CENTRAL | E11: HIDROELÉCTRICA | F11: 316.65 | G11: 284.2 | H11: 324.2 | I11: 330.65 | J11: 1255.7
B12: ASOCIACIÓN SANTA LUCIA DE CHACAS | C12: C.H. HUALLIN | D12: CENTRAL | E12: HIDROELÉCTRICA | F12: 33.25 | G12: 32.748 | H12: 31.4 | I12: 30.55 | J12: 127.948
B13: ATRIA ENERGIA S.A.C. | C13: C.H. PURMACANA | D13: CENTRAL | E13: HIDROELÉCTRICA | I13: 4.4 | J13: 4.4
B14: BIOENERGIA DEL CHIRA S.A. | C14: C.T. CAÑA BRAVA | D14: CENTRAL | E14: TERMOELÉCTRICA | F14: 201.95 | G14: 229.7 | H14: 227.6 | I14: 229.65 | J14: 888.9
B15: CELEPSA | C15: C.H. EL PLATANAL | D15: CENTRAL | E15: HIDROELÉCTRICA | F15: 2672.3 | G15: 2594.5 | H15: 2573.75 | I15: 2535.35 | J15: 10375.9
B16: CELEPSA RENOVABLES S.R.L. | C16: C.H. MARAÑON | D16: CENTRAL | E16: HIDROELÉCTRICA | F16: 474.4 | G16: 475.2 | H16: 473.9 | I16: 467.5 | J16: 1891
B17: CENTRALES SANTA ROSA S.A.C. | C17: C.H. SANTA ROSA I | D17: CENTRAL | E17: HIDROELÉCTRICA | J17: 0
B18: CENTRALES SANTA ROSA S.A.C. | C18: C.H. SANTA ROSA II | D18: CENTRAL | E18: HIDROELÉCTRICA | J18: 0
B19: CHINANGO S.A.C. | C19: C.H. CHIMAY | D19: CENTRAL | E19: HIDROELÉCTRICA | F19: 1885.7 | G19: 2270.7 | H19: 1903.7 | I19: 1723.05 | J19: 7783.15
B20: CHINANGO S.A.C. | C20: C.H. YANANGO | D20: CENTRAL | E20: HIDROELÉCTRICA | F20: 690.8 | G20: 692.3 | H20: 684.2 | I20: 664.4 | J20: 2731.7
B21: COLCA SOLAR S.A.C. | C21: C.S. YARUCAYA | D21: CENTRAL | E21: SOLAR | F21: 6.55 | G21: 8.25 | H21: 8.25 | I21: 8.35 | J21: 31.4
B22: EGASA | C22: C.H. CHARCANI III | D22: CENTRAL | E22: HIDROELÉCTRICA | F22: 164.65 | G22: 164.15 | H22: 164.45 | I22: 164.15 | J22: 657.4
B23: EGASA | C23: C.H. CHARCANI IV | D23: CENTRAL | E23: HIDROELÉCTRICA | F23: 291.2 | G23: 289.3 | H23: 290.9 | I23: 286.25 | J23: 1157.65
B24: EGASA | C24: C.H. CHARCANI V | D24: CENTRAL | E24: HIDROELÉCTRICA | F24: 1784.8 | G24: 1768.85 | H24: 1801 | I24: 1817.7 | J24: 7172.35
B25: EGASA | C25: C.H. CHARCANI VI | D25: CENTRAL | E25: HIDROELÉCTRICA | J25: 0
B26: EGASA | C26: C.T. CHILINA DIESEL | D26: CENTRAL | E26: TERMOELÉCTRICA | J26: 0
B27: EGASA | C27: C.T. CHILINA DIESEL | D27: TG | E27: TERMOELÉCTRICA | J27: 0
B28: EGASA | C28: C.T. MOLLENDO DIESEL | D28: CENTRAL | E28: TERMOELÉCTRICA | J28: 0
B29: EGEJUNIN | C29: C.H. HUASAHUASI I | D29: CENTRAL | E29: HIDROELÉCTRICA | F29: 228.3 | G29: 223.85 | H29: 209.5 | I29: 197.15 | J29: 858.8
B30: EGEJUNIN | C30: C.H. RUNATULLO II | D30: CENTRAL | E30: HIDROELÉCTRICA | F30: 131.55 | G30: 128.35 | H30: 128.1 | I30: 122.9 | J30: 510.9
B31: EGEJUNIN | C31: C.H. RUNATULLO III | D31: CENTRAL | E31: HIDROELÉCTRICA | F31: 185.4 | G31: 190.6 | H31: 180.2 | I31: 176.25 | J31: 732.45
B32: EGEJUNIN | C32: C.H. SANTA CRUZ I | D32: CENTRAL | E32: HIDROELÉCTRICA | F32: 94.8 | G32: 96.2 | H32: 89.9 | I32: 79.75 | J32: 360.65
B33: EGEMSA | C33: C.H. MACHUPICCHU | D33: CENTRAL | E33: HIDROELÉCTRICA | F33: 3354.25 | G33: 3343.75 | H33: 3285.5 | I33: 3300.8 | J33: 13284.3
B34: EGESUR | C34: C.H. ARICOTA I | D34: CENTRAL | E34: HIDROELÉCTRICA | F34: 173.8 | G34: 173.85 | H34: 177.45 | I34: 176.8 | J34: 701.9
B35: EGESUR | C35: C.H. ARICOTA II | D35: CENTRAL | E35: HIDROELÉCTRICA | F35: 126 | G35: 124.65 | H35: 127.35 | I35: 126.2 | J35: 504.2
B36: EGESUR | C36: C.T. INDEPENDENCIA | D36: CENTRAL | E36: TERMOELÉCTRICA | G36: 20.35 | J36: 20.35
B37: ELECTRICA YANAPAMPA SAC | C37: C.H. YANAPAMPA | D37: CENTRAL | E37: HIDROELÉCTRICA | F37: 53.1 | G37: 53.6 | H37: 54.9 | I37: 51.15 | J37: 212.75
B38: ELECTROPERU | C38: C.H. MANTARO | D38: CENTRAL | E38: HIDROELÉCTRICA | F38: 15565.4 | G38: 15560.2 | H38: 15569.3 | I38: 14799.655 | J38: 61494.555
B39: ELECTROPERU | C39: C.H. RESTITUCION | D39: CENTRAL | E39: HIDROELÉCTRICA | F39: 5165.4 | G39: 5164.05 | H39: 5166.25 | I39: 4977.64 | J39: 20473.34
B40: ELECTROPERU | C40: C.T. TUMBES | D40: MAK1 | E40: TERMOELÉCTRICA | J40: 0
B41: ELECTROPERU | C41: C.T. TUMBES | D41: MAK2 | E41: TERMOELÉCTRICA | J41: 0
B42: EMPRESA DE GENERACION ELECTRICA CANCHAYLLO SAC | C42: C.H. CANCHAYLLO | D42: CENTRAL | E42: HIDROELÉCTRICA | F42: 62.4 | G42: 62.4 | H42: 62.4 | I42: 62.2 | J42: 249.4
B43: EMPRESA DE GENERACION ELECTRICA RIO BAÑOS S.A.C. | C43: C.H. RUCUY | D43: CENTRAL | E43: HIDROELÉCTRICA | F43: 346.4 | G43: 343.95 | H43: 330.3 | I43: 325.9 | J43: 1346.55
B44: EMPRESA DE GENERACION ELECTRICA SANTA ANA S.A.C. | C44: C.H. RENOVANDES H1 | D44: CENTRAL | E44: HIDROELÉCTRICA | F44: 279.35 | G44: 389.65 | H44: 432 | I44: 480.1 | J44: 1581.1
B45: EMPRESA DE GENERACION HUALLAGA | C45: C.H. CHAGLLA | D45: CENTRAL | E45: HIDROELÉCTRICA | F45: 5030.8 | G45: 3596 | H45: 4892.05 | I45: 3924.95 | J45: 17443.8
B46: EMPRESA DE GENERACION HUALLAGA | C46: P.C.H. CHAGLLA | D46: CENTRAL | E46: HIDROELÉCTRICA | F46: 156 | G46: 116.8 | H46: 35.75 | I46: 155.45 | J46: 464
B47: EMPRESA DE GENERACION HUANZA | C47: C.H. HUANZA | D47: CENTRAL | E47: HIDROELÉCTRICA | F47: 1180 | G47: 1228.7 | H47: 1318.5 | I47: 1274.25 | J47: 5001.45
B48: EMPRESA ELECTRICA AGUA AZUL | C48: C.H. POTRERO | D48: CENTRAL | E48: HIDROELÉCTRICA | F48: 367.35 | G48: 353.2 | H48: 327.85 | I48: 314.5 | J48: 1362.9
B49: EMPRESA ELECTRICA RIO DOBLE | C49: C.H. LAS PIZARRAS | D49: CENTRAL | E49: HIDROELÉCTRICA | F49: 235.35 | G49: 228.5 | H49: 219.35 | I49: 204.8 | J49: 888
B50: ENEL GENERACION PIURA S.A. | C50: C.T. MALACAS 1 | D50: TG6 | E50: TERMOELÉCTRICA | F50: 1117.05 | G50: 1045.15 | H50: 1106 | I50: 818.85 | J50: 4087.05
B51: ENEL GENERACION PIURA S.A. | C51: C.T. MALACAS 2 | D51: TG4 | E51: TERMOELÉCTRICA | J51: 0
B52: ENEL GENERACION PIURA S.A. | C52: C.T. RF DE GENERACION TALARA | D52: TG5 | E52: TERMOELÉCTRICA | J52: 0
B53: ENERGÍA EÓLICA S.A. | C53: C.E. CUPISNIQUE | D53: CENTRAL | E53: EÓLICA | F53: 622.15 | G53: 405.7 | H53: 167 | I53: 262.7 | J53: 1457.55
B54: ENERGÍA EÓLICA S.A. | C54: C.E. TALARA | D54: CENTRAL | E54: EÓLICA | F54: 352.9 | G54: 178.65 | H54: 64.65 | I54: 132.1 | J54: 728.3
B55: ENERGIA RENOVABLE DEL SUR S.A. | C55: C.E. SAN JUAN | D55: CENTRAL | E55: EÓLICA | F55: 1374.1 | G55: 624.4 | H55: 219.55 | I55: 80.45 | J55: 2298.5
B56: ENGIE | C56: C.E. PUNTA LOMITAS | D56: PL-BL1 | E56: EÓLICA | F56: 738.25 | G56: 347.05 | H56: 35.15 | I56: 54.8 | J56: 1175.25
B57: ENGIE | C57: C.E. PUNTA LOMITAS | D57: PL-BL2 | E57: EÓLICA | F57: 942.95 | G57: 588.1 | H57: 91 | I57: 96.2 | J57: 1718.25
B58: ENGIE | C58: C.E. PUNTA LOMITAS_EXP | D58: PUN LOM_EXP-BL1 | E58: EÓLICA | F58: 101.9 | G58: 31.7 | H58: 0.95 | I58: 6.5 | J58: 141.05
B59: ENGIE | C59: C.E. PUNTA LOMITAS_EXP | D59: PUN LOM_EXP-BL2 | E59: EÓLICA | F59: 69.15 | G59: 15.15 | H59: 0.05 | I59: 2.9 | J59: 87.25
B60: ENGIE | C60: C.H. QUITARACSA | D60: CENTRAL | E60: HIDROELÉCTRICA | F60: 354 | I60: 379.9 | J60: 733.9
B61: ENGIE | C61: C.H. YUNCAN | D61: CENTRAL | E61: HIDROELÉCTRICA | F61: 1370.3 | G61: 1583.5 | H61: 1360.3 | I61: 1331.7 | J61: 5645.8
B62: ENGIE | C62: C.S. INTIPAMPA | D62: CENTRAL | E62: SOLAR | F62: 216.9 | G62: 244.45 | H62: 244.5 | I62: 249.9 | J62: 955.75
B63: ENGIE | C63: C.T. CHILCA 1 | D63: TG1 | E63: TERMOELÉCTRICA | F63: 4265.65 | G63: 4246.3 | H63: 4254.15 | I63: 4241.4 | J63: 17007.5
B64: ENGIE | C64: C.T. CHILCA 1 | D64: TG2 | E64: TERMOELÉCTRICA | F64: 4221.55 | G64: 4202.2 | H64: 4208.7 | I64: 4194 | J64: 16826.45
B65: ENGIE | C65: C.T. CHILCA 1 | D65: TG3 | E65: TERMOELÉCTRICA | F65: 4800 | G65: 4800 | H65: 4800 | I65: 4800 | J65: 19200
B66: ENGIE | C66: C.T. CHILCA 1 | D66: TV | E66: TERMOELÉCTRICA | F66: 6582.75 | G66: 6568.75 | H66: 6578.55 | I66: 6568.4 | J66: 26298.45
B67: ENGIE | C67: C.T. CHILCA 2 | D67: TG41 | E67: TERMOELÉCTRICA | J67: 0
B68: ENGIE | C68: C.T. CHILCA 2 | D68: TV42 | E68: TERMOELÉCTRICA | J68: 0
B69: ENGIE | C69: C.T. NEPI | D69: TG41 | E69: TERMOELÉCTRICA | J69: 0
B70: ENGIE | C70: C.T. NEPI | D70: TG42 | E70: TERMOELÉCTRICA | J70: 0
B71: ENGIE | C71: C.T. NEPI | D71: TG43 | E71: TERMOELÉCTRICA | J71: 0
B72: ENGIE | C72: C.T. RF PLANTA ILO | D72: TG1 | E72: TERMOELÉCTRICA | J72: 0
B73: ENGIE | C73: C.T. RF PLANTA ILO | D73: TG2 | E73: TERMOELÉCTRICA | J73: 0
B74: ENGIE | C74: C.T. RF PLANTA ILO | D74: TG3 | E74: TERMOELÉCTRICA | J74: 0
B75: FENIX POWER PERÚ | C75: C.T. FENIX | D75: GT11 | E75: TERMOELÉCTRICA | F75: 4086.3 | G75: 4372.2 | H75: 4385.4981 | I75: 4284.1525 | J75: 17128.151
B76: FENIX POWER PERÚ | C76: C.T. FENIX | D76: GT12 | E76: TERMOELÉCTRICA | F76: 4092.05 | G76: 4383.15 | H76: 4396.2114 | I76: 4196.948 | J76: 17068.359
B77: FENIX POWER PERÚ | C77: C.T. FENIX | D77: TV10 | E77: TERMOELÉCTRICA | F77: 4264.7 | G77: 4413.8 | H77: 4413.8397 | I77: 4319.5261 | J77: 17411.866
B78: GENERACIÓN ANDINA S.A.C. | C78: C.H. 8 DE AGOSTO | D78: CENTRAL | E78: HIDROELÉCTRICA | F78: 245.55 | G78: 252 | H78: 252 | I78: 252 | J78: 1001.55
B79: GENERACIÓN ANDINA S.A.C. | C79: C.H. EL CARMEN | D79: CENTRAL | E79: HIDROELÉCTRICA | F79: 113.7 | G79: 140.6 | H79: 113.3 | I79: 86.1 | J79: 453.7
B80: GENERADORA DE ENERGÍA DEL PERÚ | C80: C.H. ÁNGEL I | D80: CENTRAL | E80: HIDROELÉCTRICA | F80: 142.1 | G80: 135.2 | H80: 130.3 | I80: 124.55 | J80: 532.15
B81: GENERADORA DE ENERGÍA DEL PERÚ | C81: C.H. ÁNGEL II | D81: CENTRAL | E81: HIDROELÉCTRICA | F81: 154.7 | G81: 147.75 | H81: 142.95 | I81: 134.15 | J81: 579.55
B82: GENERADORA DE ENERGÍA DEL PERÚ | C82: C.H. ÁNGEL III | D82: CENTRAL | E82: HIDROELÉCTRICA | F82: 156.7 | G82: 141.8 | H82: 142.55 | I82: 134.5 | J82: 575.55
B83: GENERADORA DE ENERGÍA DEL PERÚ | C83: C.H. LA JOYA | D83: CENTRAL | E83: HIDROELÉCTRICA | F83: 202.1 | G83: 201.35 | H83: 180.15 | I83: 189 | J83: 772.6
B84: GM OPERACIONES S.A.C. | C84: CT REFINERIA TALARA | D84: TV1 REF TALARA | E84: TERMOELÉCTRICA | F84: 1026.8 | G84: 1034.95 | H84: 1023.95 | I84: 880.19 | J84: 3965.89
B85: GM OPERACIONES S.A.C. | C85: CT REFINERIA TALARA | D85: TV2 REF TALARA | E85: TERMOELÉCTRICA | F85: 807.7 | G85: 840.5 | H85: 841.85 | I85: 707.585 | J85: 3197.635
B86: GR CORTARRAMA SOCIEDAD ANONIMA CERRADA | C86: C.S. MATARANI | D86: C.S. MATARANI | E86: SOLAR | F86: 492.05 | G86: 559.35 | H86: 561.7 | I86: 555.35 | J86: 2168.45
... B92: HYDRO GLOBAL PERÚ S.A.C. | C92: CH SAN GABAN III | D92: CENTRAL | E92: HIDROELÉCTRICA | F92: 2406.3 | G92: 2325.45 | H92: 2320.95 | I92: 2321.55 | J92: 9374.25
B93: INFRAESTRUCTURAS Y ENERGIAS DEL PERU S.A.C. | C93: C.T. RF PTO MALDONADO | D93: CENTRAL | E93: TERMOELÉCTRICA | J93: 0
B94: INFRAESTRUCTURAS Y ENERGIAS DEL PERU S.A.C. | C94: C.T. RF PUCALLPA | D94: CENTRAL | E94: TERMOELÉCTRICA | F94: 1.65 | J94: 1.65
B95: INLAND ENERGY SAC | C95: C.H. SANTA TERESA | D95: CENTRAL | E95: HIDROELÉCTRICA | F95: 1814.3 | G95: 1789.25 | H95: 1755.55 | I95: 1759.55 | J95: 7118.65
B96: INVERSIONES SHAQSHA S.A.C. | C96: C.H. PARIAC | D96: CENTRAL | E96: HIDROELÉCTRICA | F96: 34.5 | G96: 29.75 | H96: 29.75 | I96: 29.45 | J96: 123.45
B97: JOYA SOLAR S.A.C. | C97: C.S. SAN MARTIN SOLAR | D97: CENTRAL | E97: SOLAR | F97: 1597.3 | G97: 1904.35 | H97: 1887.6 | I97: 1886.85 | J97: 7276.1
B98: KALLPA GENERACION S.A. | C98: C.H. CERRO DEL AGUILA | D98: CENTRAL | E98: HIDROELÉCTRICA | F98: 10774.75 | G98: 9516.15 | H98: 9537.2 | I98: 9202.7 | J98: 39030.8
B99: KALLPA GENERACION S.A. | C99: C.T. KALLPA | D99: TG1 | E99: TERMOELÉCTRICA | F99: 3800.5 | G99: 4078.25 | H99: 4318.55 | I99: 4329.25 | J99: 16526.55
B100: KALLPA GENERACION S.A. | C100: C.T. KALLPA | D100: TG2 | E100: TERMOELÉCTRICA | F100: 3838.85 | G100: 4136.05 | H100: 4496.35 | I100: 4499.85 | J100: 16971.1
B101: KALLPA GENERACION S.A. | C101: C.T. KALLPA | D101: TG3 | E101: TERMOELÉCTRICA | F101: 3835.2 | G101: 4138.35 | H101: 4501.1 | I101: 4512.4 | J101: 16987.05
B102: KALLPA GENERACION S.A. | C102: C.T. KALLPA | D102: TV | E102: TERMOELÉCTRICA | F102: 6014.25 | G102: 6303.2 | H102: 6572.85 | I102: 6606.1 | J102: 25496.4
B103: KALLPA GENERACION S.A. | C103: C.T. LAS FLORES | D103: TG1 | E103: TERMOELÉCTRICA | F103: 4820.85 | G103: 4680.8 | H103: 4055.95 | I103: 5138.05 | J103: 18695.65
B104: KALLPA GENERACION S.A. | C104: C.T. LAS FLORES | D104: TV | E104: TERMOELÉCTRICA | F104: 2519.95 | G104: 2485.05 | H104: 1299.8 | I104: 2665.7 | J104: 8970.5
B105: KALLPA GENERACION S.A. | C105: M.C.H. CERRO DEL AGUILA | D105: CENTRAL | E105: HIDROELÉCTRICA | F105: 51.5 | G105: 102.5 | H105: 102.7 | I105: 102.65 | J105: 359.35
B106: KONDU SAC | C106: C.S. CARHUAQUERO | D106: CENTRAL | E106: SOLAR | F106: 3 | G106: 2.3 | H106: 2.9 | I106: 2.65 | J106: 10.85
... B109: MAJES ARCUS S.A.C. | C109: C.S. MAJES SOLAR | D109: CENTRAL | E109: SOLAR | F109: 104.7 | G109: 111.5 | H109: 115.15 | I109: 115.7 | J109: 447.05
B110: MINERA CERRO VERDE | C110: C.T. RECKA | D110: CENTRAL | E110: TERMOELÉCTRICA | J110: 0
...

Sheet G_AREAS
B3: viernes, 4 de Julio del 2025
B5: HORA | C5: RESUMEN DE GENERACIÓN POR ÁREAS DEL SEIN | D5: RESUMEN DE GENERACIÓN POR ÁREAS DEL SEIN | E5: RESUMEN DE GENERACIÓN POR ÁREAS DEL SEIN | F5: RESUMEN DE GENERACIÓN POR ÁREAS DEL SEIN | G5: RESUMEN DE GENERACIÓN POR ÁREAS DEL SEIN | H5: RESUMEN DE GENERACIÓN POR ÁREAS DEL SEIN | I5: RESUMEN DE GENERACIÓN POR ÁREAS DEL SEIN | J5: RESUMEN DE GENERACIÓN POR ÁREAS DEL SEIN | K5: RESUMEN DE GENERACIÓN POR ÁREAS DEL SEIN | L5: RESUMEN DE GENERACIÓN POR ÁREAS DEL SEIN | M5: RESUMEN DE GENERACIÓN POR ÁREAS DEL SEIN | N5: RESUMEN DE GENERACIÓN POR ÁREAS DEL SEIN | O5: RESUMEN DE GENERACIÓN POR ÁREAS DEL SEIN | P5: RESUMEN DE GENERACIÓN POR ÁREAS DEL SEIN | Q5: RESUMEN DE GENERACIÓN POR ÁREAS DEL SEIN | R5: RESUMEN DE GENERACIÓN POR ÁREAS DEL SEIN | S5: HORA | T5: GENERACIÓN POR TIPO DE GENERACIÓN | U5: GENERACIÓN POR TIPO DE GENERACIÓN | V5: GENERACIÓN POR TIPO DE GENERACIÓN | W5: GENERACIÓN POR TIPO DE GENERACIÓN | X5: GENERACIÓN POR TIPO DE GENERACIÓN | Y5: HORA | Z5: GENERACIÓN POR TIPO DE GENERACIÓN | AA5: GENERACIÓN POR TIPO DE GENERACIÓN | AB5: GENERACIÓN POR TIPO DE GENERACIÓN | AC5: GENERACIÓN POR TIPO DE GENERACIÓN | AD5: GENERACIÓN POR TIPO DE GENERACIÓN
C6: NORTE | D6: NORTE | E6: NORTE | F6: NORTE | G6: CENTRO | H6: CENTRO | I6: CENTRO | J6: CENTRO | K6: SUR | L6: SUR | M6: SUR | N6: SUR | O6: GENERACIÓN INTEGRANTES COES | P6: GENERACIÓN INTEGRANTES COES | Q6: GENERACIÓN INTEGRANTES COES | R6: GENERACIÓN INTEGRANTES COES | T6: INTEGRANTES COES | U6: INTEGRANTES COES | V6: INTEGRANTES COES | W6: INTEGRANTES COES | X6: INTEGRANTES COES | Z6: INTEGRANTES COES RER | AA6: INTEGRANTES COES RER | AB6: INTEGRANTES COES RER | AC6: INTEGRANTES COES RER | AD6: INTEGRANTES COES RER
C7: GENERACIÓN HIDROELÉCTRICA NORTE | D7: GENERACIÓN TERMOELÉCTRICA NORTE | E7: GENERACIÓN SOLAR NORTE | F7: GENERACIÓN EÓLICA NORTE | G7: GENERACIÓN HIDROELÉCTRICA CENTRO | H7: GENERACIÓN TERMOELÉCTRICA CENTRO | I7: GENERACIÓN SOLAR CENTRO | J7: GENERACIÓN EÓLICA CENTRO | K7: GENERACIÓN HIDROELÉCTRICA SUR | L7: GENERACIÓN TERMOELÉCTRICA SUR | M7: GENERACIÓN SOLAR SUR | N7: GENERACIÓN EÓLICA SUR | O7: GENERACIÓN COES NORTE | P7: GENERACIÓN COES CENTRO | Q7: GENERACIÓN COES SUR | R7: TOTAL GENERACION | T7: HIDROELÉCTRICA | U7: TERMOELÉCTRICA | V7: SOLAR | W7: EÓLICA | X7: TOTAL GENERACION | Z7: HIDROELÉCTRICA RER | AA7: TERMOELÉCTRICA RER | AB7: SOLAR RER | AC7: EÓLICA RER | AD7: TOTAL RER
B8: 00:30 | C8: 212 | D8: 94.37 | E8: 0 | F8: 38.3 | G8: 2282.11 | H8: 3285.133 | I8: 0 | J8: 5 | K8: 531 | L8: 0 | M8: 0 | N8: 0 | O8: 344.67 | P8: 5572.243 | Q8: 531 | R8: 6447.913 | S8: 00:30 | T8: 3025.11 | U8: 3379.503 | V8: 0 | W8: 43.3 | X8: 6447.913 | Y8: 00:30 | Z8: 218.4 | AA8: 42.2 | AB8: 0 | AC8: 43.3 | AD8: 303.9
B9: 01:00 | C9: 198.8 | D9: 95.45 | E9: 0 | F9: 35.2 | G9: 2171.56 | H9: 3263.834 | I9: 0 | J9: 9.8 | K9: 480.9 | L9: 0 | M9: 0 | N9: 0 | O9: 329.45 | P9: 5445.194 | Q9: 480.9 | R9: 6255.544 | S9: 01:00 | T9: 2851.26 | U9: 3359.284 | V9: 0 | W9: 45 | X9: 6255.544 | Y9: 01:00 | Z9: 206 | AA9: 42.5 | AB9: 0 | AC9: 45 | AD9: 293.5
B10: 01:30 | C10: 199.4 | D10: 94.79 | E10: 0 | F10: 38.1 | G10: 2104.31 | H10: 3257.569 | I10: 0 | J10: 11.8 | K10: 497.1 | L10: 0 | M10: 0 | N10: 0 | O10: 332.29 | P10: 5373.679 | Q10: 497.1 | R10: 6203.069 | S10: 01:30 | T10: 2800.81 | U10: 3352.359 | V10: 0 | W10: 49.9 | X10: 6203.069 | Y10: 01:30 | Z10: 207.3 | AA10: 42.7 | AB10: 0 | AC10: 49.9 | AD10: 299.9
B11: 02:00 | C11: 201.8 | D11: 94.61 | E11: 0 | F11: 38.4 | G11: 2030.6 | H11: 3272.932 | I11: 0 | J11: 8.8 | K11: 432.4 | L11: 0 | M11: 0 | N11: 0 | O11: 334.81 | P11: 5312.332 | Q11: 432.4 | R11: 6079.542 | S11: 02:00 | T11: 2664.8 | U11: 3367.542 | V11: 0 | W11: 47.2 | X11: 6079.542 | Y11: 02:00 | Z11: 209.1 | AA11: 42.5 | AB11: 0 | AC11: 47.2 | AD11: 298.8
B12: 02:30 | C12: 199.6 | D12: 94.45 | E12: 0 | F12: 32.3 | G12: 2071.08 | H12: 3287.617 | I12: 0 | J12: 3.4 | K12: 417 | L12: 0 | M12: 0 | N12: 0 | O12: 326.35 | P12: 5362.097 | Q12: 417 | R12: 6105.447 | S12: 02:30 | T12: 2687.68 | U12: 3382.067 | V12: 0 | W12: 35.7 | X12: 6105.447 | Y12: 02:30 | Z12: 209 | AA12: 42.2 | AB12: 0 | AC12: 35.7 | AD12: 286.9
B13: 03:00 | C13: 202.5 | D13: 94.96 | E13: 0 | F13: 24 | G13: 2067.54 | H13: 3273.126 | I13: 0 | J13: 4.3 | K13: 425.1 | L13: 0 | M13: 0 | N13: 0 | O13: 321.46 | P13: 5344.966 | Q13: 425.1 | R13: 6091.526 | S13: 03:00 | T13: 2695.14 | U13: 3368.086 | V13: 0 | W13: 28.3 | X13: 6091.526 | Y13: 03:00 | Z13: 209.9 | AA13: 42.8 | AB13: 0 | AC13: 28.3 | AD13: 281
B14: 03:30 | C14: 200.8 | D14: 94.82 | E14: 0 | F14: 26.6 | G14: 1944.6 | H14: 3357.127 | I14: 0 | J14: 6.9 | K14: 414.8 | L14: 0 | M14: 0 | N14: 0 | O14: 322.22 | P14: 5308.627 | Q14: 414.8 | R14: 6045.647 | S14: 03:30 | T14: 2560.2 | U14: 3451.947 | V14: 0 | W14: 33.5 | X14: 6045.647 | Y14: 03:30 | Z14: 209.1 | AA14: 42.3 | AB14: 0 | AC14: 33.5 | AD14: 284.9
B15: 04:00 | C15: 214.6 | D15: 95.48 | E15: 0 | F15: 28.6 | G15: 1954.27 | H15: 3309.014 | I15: 0 | J15: 4.5 | K15: 428.3 | L15: 0 | M15: 0 | N15: 0 | O15: 338.68 | P15: 5267.784 | Q15: 428.3 | R15: 6034.764 | S15: 04:00 | T15: 2597.17 | U15: 3404.494 | V15: 0 | W15: 33.1 | X15: 6034.764 | Y15: 04:00 | Z15: 210.9 | AA15: 43.1 | AB15: 0 | AC15: 33.1 | AD15: 287.1
B16: 04:30 | C16: 214.3 | D16: 94.95 | E16: 0 | F16: 30.3 | G16: 1949.82 | H16: 3353.228 | I16: 0 | J16: 2.1 | K16: 424.2 | L16: 0 | M16: 0 | N16: 0 | O16: 339.55 | P16: 5305.148 | Q16: 424.2 | R16: 6068.898 | S16: 04:30 | T16: 2588.32 | U16: 3448.178 | V16: 0 | W16: 32.4 | X16: 6068.898 | Y16: 04:30 | Z16: 211.4 | AA16: 42.7 | AB16: 0 | AC16: 32.4 | AD16: 286.5
B17: 05:00 | C17: 213.5 | D17: 94.41 | E17: 0 | F17: 25.1 | G17: 1950.78 | H17: 3315.504 | I17: 0 | J17: 0.3 | K17: 468.9 | L17: 0 | M17: 0 | N17: 0 | O17: 333.01 | P17: 5266.584 | Q17: 468.9 | R17: 6068.494 | S17: 05:00 | T17: 2633.18 | U17: 3409.914 | V17: 0 | W17: 25.4 | X17: 6068.494 | Y17: 05:00 | Z17: 209.7 | AA17: 42.6 | AB17: 0 | AC17: 25.4 | AD17: 277.7
B18: 05:30 | C18: 214.2 | D18: 94.38 | E18: 0 | F18: 27.4 | G18: 2111.79 | H18: 3311.123 | I18: 0 | J18: 0.1 | K18: 470.6 | L18: 0 | M18: 0 | N18: 0 | O18: 335.98 | P18: 5423.013 | Q18: 470.6 | R18: 6229.593 | S18: 05:30 | T18: 2796.59 | U18: 3405.503 | V18: 0 | W18: 27.5 | X18: 6229.593 | Y18: 05:30 | Z18: 209.4 | AA18: 42.7 | AB18: 0 | AC18: 27.5 | AD18: 279.6
B19: 06:00 | C19: 212.6 | D19: 94.71 | E19: 0 | F19: 33.4 | G19: 2126.06 | H19: 3344.499 | I19: 0 | J19: 0 | K19: 460.5 | L19: 0 | M19: 0.1 | N19: 0 | O19: 340.71 | P19: 5470.559 | Q19: 460.6 | R19: 6271.869 | S19: 06:00 | T19: 2799.16 | U19: 3439.209 | V19: 0.1 | W19: 33.4 | X19: 6271.869 | Y19: 06:00 | Z19: 209.4 | AA19: 43.1 | AB19: 0.1 | AC19: 33.4 | AD19: 286
... B56: TOTAL MWh | C56: 5512.9 | D56: 2807.375 | E56: 2.65 | F56: 979 | G56: 59651.445 | H56: 79213.627 | I56: 8.35 | J56: 710.05 | K56: 12209.65 | L56: 0 | M56: 5142.2 | N56: 0 | O56: 9301.925 | P56: 139583.47 | Q56: 17351.85 | R56: 166237.25 | S56: TOTAL MWh | T56: 77373.995 | U56: 82021.002 | V56: 5153.2 | W56: 1689.05 | X56: 166237.25 | Y56: TOTAL MWh | Z56: 5195.85 | AA56: 975.55 | AB56: 5153.2 | AC56: 1689.05 | AD56: 13013.65

Sheet HOP
B3: viernes, 4 de Julio del 2025
B5: Reporte de Horas de Operación
B6: Empresa | C6: Central | D6: Grupo | E6: Modo de Operación | F6: Inicio | G6: Final | H6: O. Arranque | I6: O. Parada | J6: Tipo Operación | K6: Ensayo de Potencia Efectiva | L6: Ensayo de Potencia Mínima | M6: Sistema | N6: Lim. Transm. | O6: Causa | P6: Observación
B7: AGRO INDUSTRIAL PARAMONGA S.A. | C7: C.T. PARAMONGA | D7: CENTRAL | E7: PARAMONGA - BAGAZO | F7: 04/07/2025 00:00:00 | G7: 05/07/2025 00:00:00 | J7: POR COGENERACION | O7: ...
B8: AGROINDUSTRIAS SAN JACINTO S.A.A. | C8: C.T. SAN JACINTO | D8: CENTRAL | E8: SAN_JACINTO - BAGAZO | F8: 04/07/2025 00:00:00 | G8: 05/07/2025 00:00:00 | J8: POR COGENERACION | O8: ...
B9: BIOENERGIA DEL CHIRA S.A. | C9: C.T. CAÑA BRAVA | D9: G-1 | E9: CANA BRAVA TV1 - BAGAZO | F9: 04/07/2025 00:00:00 | G9: 04/07/2025 18:22:00 | J9: POR COGENERACION | O9: ...
B10: BIOENERGIA DEL CHIRA S.A. | C10: C.T. CAÑA BRAVA | D10: CENTRAL | E10: CANA BRAVA TV1 & TV2 - BAGAZO | F10: 04/07/2025 18:22:00 | G10: 04/07/2025 21:01:00 | J10: POR COGENERACION | O10: ...
B11: BIOENERGIA DEL CHIRA S.A. | C11: C.T. CAÑA BRAVA | D11: G-1 | E11: CANA BRAVA TV1 - BAGAZO | F11: 04/07/2025 21:01:00 | G11: 05/07/2025 00:00:00 | J11: POR COGENERACION | O11: ...
B12: ENEL GENERACION PIURA S.A. | C12: C.T. MALACAS 1 | D12: CENTRAL | E12: MALACAS1 TG6 - GAS | F12: 04/07/2025 00:00:00 | G12: 04/07/2025 00:01:00 | J12: POR POTENCIA O ENERGIA | O12: ...
B13: ENEL GENERACION PIURA S.A. | C13: C.T. MALACAS 1 | D13: CENTRAL | E13: MALACAS1 TG6 - GAS | F13: 04/07/2025 06:20:00 | G13: 05/07/2025 00:00:00 | H13: 04/07/2025 06:06:00 | J13: POR POTENCIA O ENERGIA | O13: ...
B14: ENGIE | C14: C.T. CHILCA 1 | D14: CENTRAL | E14: CHILCA1 CCOMB TG1 & TG2 & TG3 - GAS | F14: 04/07/2025 00:00:00 | G14: 05/07/2025 00:00:00 | J14: POR POTENCIA O ENERGIA | O14: ...
B15: FENIX POWER PERÚ | C15: C.T. FENIX | D15: CENTRAL | E15: FENIX CCOMB GT11 & GT12 - GAS | F15: 04/07/2025 00:00:00 | G15: 04/07/2025 23:28:00 | J15: POR POTENCIA O ENERGIA | O15: ... | P15: A las 22:54h inicia proceso de desacople la unidad TG12
B16: FENIX POWER PERÚ | C16: C.T. FENIX | D16: CENTRAL | E16: FENIX CCOMB GT11 - GAS | F16: 04/07/2025 23:28:00 | G16: 05/07/2025 00:00:00 | J16: POR POTENCIA O ENERGIA | O16: ...
B17: FENIX POWER PERÚ | C17: C.T. FENIX | D17: GT12 | E17: FENIX GT12 - GAS | F17: 04/07/2025 23:28:00 | G17: 04/07/2025 23:29:00 | J17: A MINIMA CARGA | O17: ...
B18: GM OPERACIONES S.A.C. | C18: CT REFINERIA TALARA | D18: TV1 REF TALARA | E18: REF_TALARA TV1 - NLH_RFG | F18: 04/07/2025 00:00:00 | G18: 04/07/2025 20:49:00 | J18: POR COGENERACION | O18: ...
B19: GM OPERACIONES S.A.C. | C19: CT REFINERIA TALARA | D19: TV2 REF TALARA | E19: REF_TALARA TV2 - NLH_RFG | F19: 04/07/2025 00:00:00 | G19: 04/07/2025 20:32:00 | J19: POR COGENERACION | O19: ...
B20: KALLPA GENERACION S.A. | C20: C.T. KALLPA | D20: CENTRAL | E20: KALLPA CCOMB TG1 & TG2 & TG3 - GAS | F20: 04/07/2025 00:00:00 | G20: 05/07/2025 00:00:00 | J20: POR POTENCIA O ENERGIA | O20: ...
B21: KALLPA GENERACION S.A. | C21: C.T. LAS FLORES | D21: CENTRAL | E21: LAS FLORES CCOMB TG1 - GAS | F21: 04/07/2025 00:00:00 | G21: 05/07/2025 00:00:00 | J21: POR POTENCIA O ENERGIA | O21: ...
B22: ORYGEN PERU S.A.A. | C22: C.T. VENTANILLA | D22: CENTRAL | E22: VENTANILLA CCOMB TG3 & TG4 - GAS | F22: 04/07/2025 00:00:00 | G22: 04/07/2025 00:30:00 | J22: POR POTENCIA O ENERGIA | O22: ...
B23: ORYGEN PERU S.A.A. | C23: C.T. VENTANILLA | D23: CENTRAL | E23: VENTANILLA CCOMB TG3 & TG4 - GAS | F23: 04/07/2025 00:30:00 | G23: 04/07/2025 00:47:00 | J23: POR PRUEBAS | O23: ... | P23: Lavado online
B24: ORYGEN PERU S.A.A. | C24: C.T. VENTANILLA | D24: CENTRAL | E24: VENTANILLA CCOMB TG3 & TG4 - GAS | F24: 04/07/2025 00:47:00 | G24: 05/07/2025 00:00:00 | J24: POR POTENCIA O ENERGIA | O24: ...
B25: PETRAMAS | C25: C.T. HUAYCOLORO | D25: CENTRAL | E25: HUAYCOLORO - BIOGAS | F25: 04/07/2025 00:00:00 | G25: 05/07/2025 00:00:00 | J25: POR POTENCIA O ENERGIA | O25: ...
B26: PETRAMAS | C26: C.T. LA GRINGA | D26: CENTRAL | E26: LA GRINGA V - BIOGAS | F26: 04/07/2025 00:00:00 | G26: 05/07/2025 00:00:00 | J26: POR POTENCIA O ENERGIA | O26: ...
B27: PETRAMAS | C27: C.T.B DOÑA CATALINA | D27: G1 | E27: DONA CATALINA - BIOGAS | F27: 04/07/2025 00:00:00 | G27: 05/07/2025 00:00:00 | J27: POR POTENCIA O ENERGIA | O27: ...
B28: PETRAMAS | C28: C.T.B. CALLAO | D28: CENTRAL | E28: CALLAO - BIOGAS | F28: 04/07/2025 00:00:00 | G28: 05/07/2025 00:00:00 | J28: POR POTENCIA O ENERGIA | O28: ...
B29: TERMOCHILCA S.A.C. | C29: C.T. OLLEROS | D29: CENTRAL | E29: OLLEROS CCOMB TG1 - GAS | F29: 04/07/2025 00:00:00 | G29: 04/07/2025 00:19:00 | J29: A MINIMA CARGA | O29: ...
B30: TERMOCHILCA S.A.C. | C30: C.T. OLLEROS | D30: CENTRAL | E30: OLLEROS CCOMB TG1 - GAS | F30: 04/07/2025 00:19:00 | G30: 05/07/2025 00:00:00 | J30: POR POTENCIA O ENERGIA | O30: ...

Sheet INDISP
B3: viernes, 4 de Julio del 2025
B5: Hora Inicio y Fin de Indisponibilidades de las Unidades de Generación SEIN
B6: Empresa | C6: Ubicación | D6: Equipo | E6: Inicio | F6: Final | G6: Descripción | H6: MW Indisp. | I6: Prog. | J6: Dispon | K6: Interrupc. | L6: Tipo | M6: CodEq | N6: TipoEq_Osinerg
B7: AGROAURORA S.A.C. | C7: MAPLE ETANOL | D7: CENTRAL | E7: 04/07/2025 00:00 | F7: 05/07/2025 00:00 | G7: CENTRAL TERMOELECTRICA FUERA DE SERVICIO POR FALTA DE MATERIA PRIMA PARA LOS REQUERIMIENTOS DE CALOR ÚTIL EN FÁBRICA. | H7: 17 | I7: P | J7: F/S | K7: N | L7: OTROS | M7: 13417 | N7: G
B8: CELEPSA | C8: EL PLATANAL | D8: G2 | E8: 04/07/2025 00:00 | F8: 05/07/2025 00:00 | G8: Mantenimiento anual turbina, generador y SSAA. | H8: 113.5 | I8: P | J8: F/S | K8: N | L8: PREV. | M8: 12602 | N8: G
B9: EGASA | C9: CHARCANI IV | D9: G1 | E9: 04/07/2025 07:29 | F9: 04/07/2025 14:37 | G9: Mantenimiento Electromecánico Plan 1 | H9: 5.1 | I9: P | J9: F/S | K9: N | L9: PREV. | M9: 118 | N9: G
B10: EGASA | C10: CHARCANI IV | D10: G3 | E10: 04/07/2025 14:35 | F10: 04/07/2025 15:25 | G10: Revisión de porta carbones | H10: 5 | I10: F | J10: F/S | K10: N | L10: CORR. | M10: 120 | N10: G
B11: EGASA | C11: CHARCANI VI | D11: G1 | E11: 04/07/2025 00:00 | F11: 05/07/2025 00:00 | G11: Mantenimiento Generador | H11: 8.9 | I11: P | J11: F/S | K11: N | L11: PREV. | M11: 188 | N11: G
B12: EGEJUNIN | C12: HUASAHUASI II | D12: G1 | E12: 04/07/2025 00:00 | F12: 04/07/2025 16:30 | G12: Inspección de generador G1. | H12: 0 | I12: R | J12: F/S | K12: N | L12: PREV. | M12: 13409 | N12: G
B13: EGESUR | C13: ARICOTA I | D13: G2 | E13: 04/07/2025 06:46 | F13: 04/07/2025 10:12 | G13: MANTENIMIENTO ELECTROMECÁNICO 1. SE DECLARA DISPONIBLE A LAS 10:07 HRS | H13: 11.002 | I13: P | J13: F/S | K13: N | L13: PREV. | M13: 125 | N13: G
B14: ELECTROPERU | C14: MANTARO | D14: G6 | E14: 04/07/2025 00:05 | F14: 04/07/2025 16:16 | G14: MANTENIMIENTO PREVENTIVO Y CONTROLES SISTEMÁTICOS | H14: 101 | I14: P | J14: F/S | K14: N | L14: PREV. | M14: 6 | N14: G
B15: ELECTROPERU | C15: TUMBES | D15: MAK1 | E15: 04/07/2025 07:00 | F15: 04/07/2025 12:32 | G15: LIMPIEZA E INSPECCIÓN ELEMENTOS FILTRO AUTOMÁTICO DE ACEITE Y COMBUSTIBLE GRUPO MAK 1 Y MANTENIMIENTO A LOS CONTROLES SISTEMATICOS. | H15: 8.5 | I15: P | J15: F/S | K15: N | L15: PREV. | M15: 1068 | N15: G
B16: ENEL GENERACION PIURA S.A. | C16: MALACAS 1 | D16: TG6 | E16: 04/07/2025 00:01 | F16: 04/07/2025 05:00 | G16: Parada de Unidad TG6 para desconexión de instrumentos CEMS | H16: 48 | I16: P | J16: F/S | K16: N | L16: PREV. | M16: 16925 | N16: G
B17: ENGIE | C17: CHILCA 2 | D17: TG41 | E17: 04/07/2025 00:00 | F17: 05/07/2025 00:00 | G17: MEDICIÓN DE DESCARGAS PARCIALES EN GENERADOR TG41********* | H17: 74 | I17: P | J17: F/S | K17: N | L17: PREV. | M17: 15680 | N17: G
B18: ENGIE | C18: CHILCA 2 | D18: TV42 | E18: 04/07/2025 00:00 | F18: 05/07/2025 00:00 | G18: MEDICIÓN DE DESCARGAS PARCIALES EN GENERADOR TV42********* | H18: 38 | I18: P | J18: F/S | K18: N | L18: PREV. | M18: 16325 | N18: G
... B33: STATKRAFT S.A | C33: YAUPI | D33: G2 | E33: 04/07/2025 00:00 | F33: 05/07/2025 00:00 | G33: CAMBIO DE UH (Incluye Pruebas) UG2 + MANTENIMIENTO MAYOR UG2 + Inspección Semestral 1 F/S UG2 | H33: 23.23 | I33: P | J33: F/S | K33: N | L33: PREV. | M33: 51 | N33: G

Sheet RESERVA_FRÍA
B3: 04/07/2025 | E3: EJECUTADO | L3: Viernes 4 de Julio del 2025 / SEM N° 26 | V3: EJECUTADO | AC3: Viernes 4 de Julio del 2025 / SEM N° 26 | EE3: ENERGIA RENOVABLES | GP3: COGENERACION | GY3: NO INTEGRANTES
B4: Viernes | C4: HYDROG | D4: ELECTROPERU | H4: ORAZU | J4: TER | L4: KALLPA GENERACION S.A. | T4: SHOUGESA | X4: EGM | Y4: EGESUR | AB4: EGASA | AI4: SGB | AJ4: CELEP | AK4: MINCVE | AL4: ETEN | AN4: HUALLA | AP4: LAVI | AQ4: CHIN | AS4: HUANCH | AT4: CELER | AU4: INLD | AV4: FENIX POWER PERÚ | AY4: STATKRAFT S.A | BG4: STARO | BI4: HUANZA | BJ4: ENEL GENERACION PIURA S.A. | BM4: ENGIE | CA4: IYEP | CC4: SHAQSH | CD4: ORYGEN PERU S.A.A. | CP4: SAMAY I S.A.C | CT4: TCHILC | CV4: GENERACION | CY4: SALIDAS YUPANA | DC4: FLUJO EN LINEAS | DO4: COSTOS MARGINALES | DS4: RESERVA | DX4: DEMANDA POR AREAS | EE4: ACHI | EF4: COLCA | EG4: ERSUR | EH4: GRCOR | EI4: TARU | EJ4: KONDU | EK4: PIEREN | EL4: ORAZU | EN4: SGB | EO4: AIPSA | EP4: MAJA | EQ4: EGECSA | ER4: STANA | ES4: AGUAA | ET4: RDOBLE | EU4: HIDRO | EV4: HUARA | EW4: MOQUE | EX4: PANAM | EY4: PARQU | EZ4: PE3HER | FA4: PETRAMAS | FE4: TACNA | FF4: EYSAC | FG4: AURORA | FH4: AGROIN | FI4: ANDEA | FJ4: ASLC | FK4: ATRIA | FL4: EGEJUNIN | FP4: EGERBA | FQ4: EOL | FS4: ENGIE | FX4: GENE | FZ4: GENERADORA DE ENERGÍA DEL PERÚ | GD4: PAINO | GE4: JOYAS | GF4: SARCUS | GG4: ORYGEN PERU S.A.A. | GL4: RARCUS | GM4: SINERS | GP4: ACHI | GQ4: GM OP | GS4: AIPSA | GT4: AURORA | GU4: AGROIN | GV4: SDF | GY4: UNACEM | GZ4: EOR | HA4: AYEP | HB4: ELZANA | HC4: ENOSA | HD4: SDE | HE4: SINERS | HH4: RESERVA
C5: 65333 | D5: 101 | E5: 102 | F5: 42667 | G5: 42668 | H5: 126 | I5: 127 | J5: 138 | K5: 139 | L5: 197 | M5: 203 | N5: 204 | O5: 230 | P5: 209 | Q5: 56677 | R5: 796 | S5: 2146 | T5: 142 | U5: 143 | V5: 125 | W5: 187 | X5: 163 | Y5: 298 | Z5: 299 | AA5: 219 | AB5: 151 | AC5: 152 | AD5: 153 | AE5: 154 | AF5: 756 | AG5: 156 | AH5: 155 | AI5: 182 | AJ5: 212 | AK5: 758 | AL5: 263 | AM5: 265 | AN5: 775 | AO5: 777 | AP5: 2154 | AQ5: 150 | AR5: 149 | AS5: 188 | AT5: 2131 | AU5: 755 | AV5: 252 | AW5: 249 | AX5: 250 | AY5: 117 | AZ5: 267 | BA5: 268 | BB5: 119 | BC5: 120 | BD5: 189 | BE5: 122 | BF5: 266 | BG5: 337 | BH5: 338 | BI5: 251 | BJ5: 115 | BK5: 239 | BL5: 288 | BM5: 240 | BN5: 241 | BO5: 242 | BP5: 191 | BQ5: 194 | BR5: 196 | BS5: 207 | BT5: 236 | BU5: 795 | BV5: 285 | BW5: 995 | BX5: 996 | BY5: 997 | BZ5: 766 | CA5: 926 | CB5: 924 | CC5: 121 | CD5: 103 | CE5: 104 | CF5: 106 | CG5: 105 | CH5: 107 | CI5: 110 | CJ5: 109 | CK5: 144 | CL5: 113 | CM5: 114 | CN5: 193 | CO5: 208 | CP5: 786 | CQ5: 787 | CR5: 788 | CS5: 789 | CT5: 248 | CU5: 2159 | CV5: -1222 | CW5: -1223 | CX5: -1224 | CY5: 1221 | CZ5: 1222 | DA5: 1223 | DB5: 1224 | DC5: 1250 | DD5: 1251 | DE5: 1252 | DF5: 1253 | DG5: 1254 | DH5: 1255 | DI5: 1256 | DJ5: 1257 | DK5: 1258 | DL5: 1259 | DM5: 1260 | DN5: 1261 | DO5: 1226 | DP5: 1219 | DQ5: 1220 | DR5: -1203 | DS5: 1227 | DT5: 1205 | DU5: 1207 | DV5: 1206 | DW5: 1218 | DX5: 1211 | DY5: 1212 | DZ5: 1213 | EA5: 1214 | EB5: 1229 | EC5: -1221 | EE5: 289 | EF5: 303 | EG5: 59715 | EH5: 62255 | EI5: 1263 | EJ5: 61800 | EK5: 2194 | EL5: 216 | EM5: 198 | EN5: 49607 | EO5: 213 | EP5: 214 | EQ5: 260 | ER5: 2152 | ES5: 2128 | ET5: 247 | EU5: 228 | EV5: 2135 | EW5: 261 | EX5: 237 | EY5: 253 | EZ5: 770 | FA5: 225 | FB5: 2201 | FC5: 2171 | FD5: 760 | FE5: 235 | FF5: 238 | FG5: 232 | FH5: 2190 | FI5: 2184 | FJ5: 61855 | FK5: 223 | FL5: 226 | FM5: 201 | FN5: 258 | FO5: 259 | FP5: 920 | FQ5: 257 | FR5: 256 | FS5: 2148 | FT5: 58288 | FU5: 58289 | FV5: 58839 | FW5: 58840 | FX5: 296 | FY5: 297 | FZ5: 211 | GA5: 2175 | GB5: 2178 | GC5: 2181 | GD5: 1262 | GE5: 63425 | GF5: 233 | GG5: 2150 | GH5: 2165 | GI5: 2161 | GJ5: 61197 | GK5: 58851 | GL5: 234 | GM5: 215 | GN5: 917 | GP5: 289 | GQ5: 58333 | GR5: 58336 | GS5: 213 | GT5: 232 | GU5: 2190 | GV5: 202 | GW5: 58487 | GY5: 221 | GZ5: 222 | HA5: 224 | HB5: 2187 | HC5: 227 | HD5: 49400 | HE5: 199 | HF5: 200 | HH5: 7000 | HI5: 7001 | HJ5: 7002
B6: Día Hora | C6: SAN GABAN III | D6: MANTARO | E6: RESTITUCION | F6: TUMBES MAK 1 | G6: TUMBES MAK 2 | H6: CARHUAQUERO | I6: CAÑON DEL PATO | J6: AGUAYTIA TG1 | K6: AGUAYTIA TG2 | L6: KALLPA TG1 | M6: KALLPA TG2 | N6: KALLPA TG3 | O6: KALLPA TV | P6: LFLORES TG1 | Q6: LFLORES TV | R6: CERRO DEL AGUILA | S6: CERRODELAGUILAG4 | T6: SHOUGESA TV1 | U6: SHOUGESA TV2 | V6: SHOUGESA TV3 | W6: SHOUGESA CUMMINS | X6: MACHUPICCHU | Y6: ARICOTA 1 | Z6: ARICOTA 2 | AA6: INDEPENDENCIA | AB6: CHARCANI I,II,III | AC6: CHARCANI IV | AD6: CHARCANI V | AE6: CHARCANI VI | AF6: CHILINA TG | AG6: MOLLENDO 1, 2, 3 | AH6: CHILINA (SULZ 1,2) | AI6: SAN GABAN II | AJ6: PLATANAL | AK6: RECKA | AL6: RF ETEN TG1 | AM6: RF ETEN TG2 | AN6: CHAGLLA GP1 | AO6: CHAGLLA | AP6: LA VIRGEN | AQ6: CHIMAY | AR6: YANANGO | AS6: HUANCHOR | AT6: MARAÑON | AU6: STA TERESA | AV6: FENIX GT11 | AW6: FENIX GT12 | AX6: FENIX TV10 | AY6: YAUPI | AZ6: OROYA | BA6: PACHACHACA | BB6: MALPASO | BC6: CAHUA | BD6: ARCATA | BE6: GALLITO CIEGO | BF6: CHEVES | BG6: SANTA ROSA 1 | BH6: SANTA ROSA 2 | BI6: HUANZA | BJ6: MALACAS2 TG4 | BK6: MALACAS3 TG 5 | BL6: MALACAS1 TG6 | BM6: RF ILO2 TG1 | BN6: RF ILO2 TG2 | BO6: RF ILO2 TG3 | BP6: YUNCAN | BQ6: CHILCA1 TG1 | BR6: CHILCA1 TG2 | BS6: CHILCA1 TG3 | BT6: CHILCA-TV | BU6: CHILCA2 TG41 | BV6: CHILCA2-TV | BW6: CTNEPI_TG41 | BX6: CTNEPI_TG42 | BY6: CTNEPI_TG43 | BZ6: QUITARACSA | CA6: RF PTO MALDONADO | CB6: RF PUCALLPA | CC6: PARIAC | CD6: HUINCO | CE6: MATUCANA | CF6: MOYOPAMPA | CG6: CALLAHUANCA | CH6: HUAMPANI | CI6: STA ROSA WEST TG7 | CJ6: UTI_5 | CK6: UTI_6 | CL6: VENTANILLA 3 | CM6: VENTANILLA 4 | CN6: VENTANILLA TV | CO6: STAROSA TG8 | CP6: PTO_BRVO TG1 | CQ6: PTO_BRVO TG2 | CR6: PTO_BRVO TG3 | CS6: PTO_BRVO TG4 | CT6: OLLEROS TG1 | CU6: OLLEROS TV | CV6: Total CoGeneracion | CW6: Total Renovables | CX6: Total Generación COES | CY6: Demanda YUPANA | CZ6: Oferta | DA6: Perdidas YUPANA | DB6: Deficit YUPANA | DC6: FLUJO ENLACE CENTRO - SUR | DD6: FLUJO CHILCA CARAPONGO 500 KV | DE6: FLUJO CARAPONGO CARABAYLLO 500 KV | DF6: FLUJO CHIMBOTE TRUJILLO 500 KV | DG6: FLUJO TRUJILLO LA NIÑA 500 KV | DH6: FLUJO COLCABAMBA POROMA 500 KV | DI6: FLUJO CHILCA POROMA 500 KV | DJ6: FLUJO POROMA YARABAMBA 500 KV | DK6: FLUJO POROMA OCOÑA 500 KV | DL6: FLUJO YARABAMBA MOLTALVO 500 KV | DM6: FLUJO HUANCAVELICA - INDEPENDENCIA 220 KV | DN6: FLUJO CHILCA - SAN JUAN 220 KV | DO6: Cmg Santa Rosa YUPANA(US$/MWh) | DP6: Cmg Trujillo YUPANA(US$/MWh) | DQ6: Cmg Socabaya YUPANA(US$/MWh) | DR6: Nivel de Demanda | DS6: Reserva Fría Térmica | DT6: Reserva Eficiente | DU6: Reserva Eficiente Gas | DV6: Reserva Eficiente Carbón | DW6: Nivel Tablachaca | DX6: Demanda Centro | DY6: Demanda Norte | DZ6: Demanda Sur | EA6: Demanda Electroandes | EB6: Demanda Ecuador | EC6: Demanda COES | EE6: CANA BRAVA | EF6: CS YARUCAYA | EG6: SAN JUAN | EH6: MATARANI | EI6: DUNA | EJ6: CARHUAQUERO (CS) | EK6: MANTA I | EL6: CARHUAQUERO4 | EM6: CAÑA BRAVA | EN6: TUPURI | EO6: PARAMONGA | EP6: RONCADOR | EQ6: CANCHAYLLO | ER6: RENOVANDESH1 | ES6: POTRERO | ET6: PIZARRAS | EU6: NIMPERIAL | EV6: YARUCAYA | EW6: MOQUEGUA-SOLAR | EX6: PANAMERICANA-SOLAR | EY6: PQE-EOLICO-MARCONA | EZ6: PQE-EOLICO-3-HERMANAS | FA6: HUAYCOLORO | FB6: CALLAO | FC6: DONA_CATALINA | FD6: LAGRINGAV | FE6: TACNA-SOLAR | FF6: YANAPAMPA | FG6: MAPLE | FH6: SAN_JACINTO | FI6: CARHUAC | FJ6: HUALLIN | FK6: PURMACANA | FL6: HUASAHUASI | FM6: STACRUZ_1_2 | FN6: RUNATULLO_II | FO6: RUNATULLO_III | FP6: RUCUY | FQ6: PQE-EOLICO-TALARA | FR6: PQE-EOLICO-CUPISNIQUE | FS6: INTIPAMPA | FT6: PUNTA LOMITAS-BL1 | FU6: PUNTA LOMITAS-BL2 | FV6: PUN LOMITAS_EXP-BL1 | FW6: PUN LOMITAS_EXP-BL2 | FX6: 8AGOSTO | FY6: EL CARMEN | FZ6: LA JOYA | GA6: ANGEL_I | GB6: ANGEL_II | GC6: ANGEL_III | GD6: HUAMBOS | GE6: SAN MARTIN SOLAR | GF6: MAJES | GG6: RUBI | GH6: CH_HER1 | GI6: WAYRA-I | GJ6: WAYRA EXTENSION | GK6: CLEMESI | GL6: REPARTICION | GM6: POECHOS2 | GN6: CHANCAY | GP6: CANA BRAVA | GQ6: REFINERIA TALARA TV1 | GR6: REFINERÍA TALARA TV2 | GS6: PARAMONGA | GT6: MAPLE | GU6: SAN_JACINTO | GV6: OQUENDO TG1 | GW6: OQUENDO TV1 | GY6: CARPAPATA | GZ6: CENTRALES ELOR | HA6: PIAS1 | HB6: ZANA | HC6: TABLAZO | HD6: TALLANCA | HE6: CURUMUY | HF6: POECHOS1 | HH6: ReservaFriaTermica | HI6: ReservaFria Rapida Termica | HJ6: ReservaFria Termica xMantenimiento
B7: 00:30 | F7: 8.82587 | G7: 8.51669 | J7: 81.0961 | T7: 18.14123 | U7: 19.19196 | V7: 24.42536 | W7: 1.06127 | AA7: 23.06068 | AF7: 12.23925 | AG7: 24.4617 | AH7: 10.27692 | AK7: 179.37322 | AM7: 7.93273 | BJ7: 25 | BM7: 167.61232 | BN7: 166.56063 | BO7: 168.58997 | BW7: 206.49456 | BX7: 206.11549 | BY7: 205.99003 | CA7: 17.41583 | CB7: 44.05367 | CI7: 118.14735 | CJ7: 47.90514 | CK7: 53.71012 | CO7: 191.19621 | CP7: 180.55348 | CQ7: 180.52451 | CR7: 181.33356 | CS7: 181.02912 | CZ7: 6556.4632 | DR7: MIN | DS7: 2760.835 | DT7: 540.1156 | DU7: 540.1156 | EC7: 6447.9 | HH7: 2760.835 | HI7: 2699.0764 | HJ7: 377.24654
B8: 01:00 | F8: 8.82587 | G8: 8.51669 | J8: 81.0961 | T8: 18.14123 | U8: 19.19196 | V8: 24.42536 | W8: 1.06127 | AA8: 23.06068 | AF8: 12.23925 | AG8: 24.4617 | AH8: 10.27692 | AK8: 179.37322 | AM8: 7.93273 | BJ8: 25 | BM8: 167.61232 | BN8: 166.56063 | BO8: 168.58997 | BW8: 206.49456 | BX8: 206.11549 | BY8: 205.99003 | CA8: 17.41583 | CB8: 44.05367 | CI8: 118.14735 | CJ8: 47.90514 | CK8: 53.71012 | CO8: 191.19621 | CP8: 180.55348 | CQ8: 180.52451 | CR8: 181.33356 | CS8: 181.02912 | CZ8: 6364.5798 | DR8: MIN | DS8: 2760.835 | DT8: 540.1156 | DU8: 540.1156 | EC8: 6255.6 | HH8: 2760.835 | HI8: 2699.0764 | HJ8: 377.24654
B9: 01:30 | F9: 8.82587 | G9: 8.51669 | J9: 81.0961 | T9: 18.14123 | U9: 19.19196 | V9: 24.42536 | W9: 1.06127 | AA9: 23.06068 | AF9: 12.23925 | AG9: 24.4617 | AH9: 10.27692 | AK9: 179.37322 | AM9: 7.93273 | BJ9: 25 | BM9: 167.61232 | BN9: 166.56063 | BO9: 168.58997 | BW9: 206.49456 | BX9: 206.11549 | BY9: 205.99003 | CA9: 17.41583 | CB9: 44.05367 | CI9: 118.14735 | CJ9: 47.90514 | CK9: 53.71012 | CO9: 191.19621 | CP9: 180.55348 | CQ9: 180.52451 | CR9: 181.33356 | CS9: 181.02912 | CZ9: 6312.3242 | DR9: MIN | DS9: 2760.835 | DT9: 540.1156 | DU9: 540.1156 | EC9: 6203.1 | HH9: 2760.835 | HI9: 2699.0764 | HJ9: 377.24654
B10: 02:00 | F10: 8.82587 | G10: 8.51669 | J10: 81.0961 | T10: 18.14123 | U10: 19.19196 | V10: 24.42536 | W10: 1.06127 | AA10: 23.06068 | AF10: 12.23925 | AG10: 24.4617 | AH10: 10.27692 | AK10: 179.37322 | AM10: 7.93273 | BJ10: 25 | BM10: 167.61232 | BN10: 166.56063 | BO10: 168.58997 | BW10: 206.49456 | BX10: 206.11549 | BY10: 205.99003 | CA10: 17.41583 | CB10: 44.05367 | CI10: 118.14735 | CJ10: 47.90514 | CK10: 53.71012 | CO10: 191.19621 | CP10: 180.55348 | CQ10: 180.52451 | CR10: 181.33356 | CS10: 181.02912 | CZ10: 6185.7701 | DR10: MIN | DS10: 2760.835 | DT10: 540.1156 | DU10: 540.1156 | EC10: 6079.6 | HH10: 2760.835 | HI10: 2699.0764 | HJ10: 377.24654
B11: 02:30 | F11: 8.82587 | G11: 8.51669 | J11: 81.0961 | T11: 18.14123 | U11: 19.19196 | V11: 24.42536 | W11: 1.06127 | AA11: 23.06068 | AF11: 12.23925 | AG11: 24.4617 | AH11: 10.27692 | AK11: 179.37322 | AM11: 7.93273 | BJ11: 25 | BM11: 167.61232 | BN11: 166.56063 | BO11: 168.58997 | BW11: 206.49456 | BX11: 206.11549 | BY11: 205.99003 | CA11: 17.41583 | CB11: 44.05367 | CI11: 118.14735 | CJ11: 47.90514 | CK11: 53.71012 | CO11: 191.19621 | CP11: 180.55348 | CQ11: 180.52451 | CR11: 181.33356 | CS11: 181.02912 | CZ11: 6214.7399 | DR11: MIN | DS11: 2760.835 | DT11: 540.1156 | DU11: 540.1156 | EC11: 6105.7 | HH11: 2760.835 | HI11: 2699.0764 | HJ11: 377.24654
B12: 03:00 | F12: 8.82587 | G12: 8.51669 | J12: 81.0961 | T12: 18.14123 | U12: 19.19196 | V12: 24.42536 | W12: 1.06127 | AA12: 23.06068 | AF12: 12.23925 | AG12: 24.4617 | AH12: 10.27692 | AK12: 179.37322 | AM12: 7.93273 | BJ12: 25 | BM12: 167.61232 | BN12: 166.56063 | BO12: 168.58997 | BW12: 206.49456 | BX12: 206.11549 | BY12: 205.99003 | CA12: 17.41583 | CB12: 44.05367 | CI12: 118.14735 | CJ12: 47.90514 | CK12: 53.71012 | CO12: 191.19621 | CP12: 180.55348 | CQ12: 180.52451 | CR12: 181.33356 | CS12: 181.02912 | CZ12: 6200.3715 | DR12: MIN | DS12: 2760.835 | DT12: 540.1156 | DU12: 540.1156 | EC12: 6091.6 | HH12: 2760.835 | HI12: 2699.0764 | HJ12: 377.24654
B13: 03:30 | F13: 8.82587 | G13: 8.51669 | J13: 81.0961 | T13: 18.14123 | U13: 19.19196 | V13: 24.42536 | W13: 1.06127 | AA13: 23.06068 | AF13: 12.23925 | AG13: 24.4617 | AH13: 10.27692 | AK13: 179.37322 | AM13: 7.93273 | BJ13: 25 | BM13: 167.61232 | BN13: 166.56063 | BO13: 168.58997 | BW13: 206.49456 | BX13: 206.11549 | BY13: 205.99003 | CA13: 17.41583 | CB13: 44.05367 | CI13: 118.14735 | CJ13: 47.90514 | CK13: 53.71012 | CO13: 191.19621 | CP13: 180.55348 | CQ13: 180.52451 | CR13: 181.33356 | CS13: 181.02912 | CZ13: 6154.4163 | DR13: MIN | DS13: 2760.835 | DT13: 540.1156 | DU13: 540.1156 | EC13: 6045.6 | HH13: 2760.835 | HI13: 2699.0764 | HJ13: 377.24654
B14: 04:00 | F14: 8.82587 | G14: 8.51669 | J14: 81.0961 | T14: 18.14123 | U14: 19.19196 | V14: 24.42536 | W14: 1.06127 | AA14: 23.06068 | AF14: 12.23925 | AG14: 24.4617 | AH14: 10.27692 | AK14: 179.37322 | AM14: 7.93273 | BJ14: 25 | BM14: 167.61232 | BN14: 166.56063 | BO14: 168.58997 | BW14: 206.49456 | BX14: 206.11549 | BY14: 205.99003 | CA14: 17.41583 | CB14: 44.05367 | CI14: 118.14735 | CJ14: 47.90514 | CK14: 53.71012 | CO14: 191.19621 | CP14: 180.55348 | CQ14: 180.52451 | CR14: 181.33356 | CS14: 181.02912 | CZ14: 6144.0196 | DR14: MIN | DS14: 2760.835 | DT14: 540.1156 | DU14: 540.1156 | EC14: 6034.7 | HH14: 2760.835 | HI14: 2699.0764 | HJ14: 377.24654
B15: 04:30 | F15: 8.82587 | G15: 8.51669 | J15: 81.0961 | T15: 18.14123 | U15: 19.19196 | V15: 24.42536 | W15: 1.06127 | AA15: 23.06068 | AF15: 12.23925 | AG15: 24.4617 | AH15: 10.27692 | AK15: 179.37322 | AM15: 7.93273 | BJ15: 25 | BM15: 167.61232 | BN15: 166.56063 | BO15: 168.58997 | BW15: 206.49456 | BX15: 206.11549 | BY15: 205.99003 | CA15: 17.41583 | CB15: 44.05367 | CI15: 118.14735 | CJ15: 47.90514 | CK15: 53.71012 | CO15: 191.19621 | CP15: 180.55348 | CQ15: 180.52451 | CR15: 181.33356 | CS15: 181.02912 | CZ15: 6171.4388 | DR15: MIN | DS15: 2760.835 | DT15: 540.1156 | DU15: 540.1156 | EC15: 6068.8 | HH15: 2760.835 | HI15: 2699.0764 | HJ15: 377.24654
B16: 05:00 | F16: 8.82587 | G16: 8.51669 | J16: 81.0961 | T16: 18.14123 | U16: 19.19196 | V16: 24.42536 | W16: 1.06127 | AA16: 23.06068 | AF16: 12.23925 | AG16: 24.4617 | AH16: 10.27692 | AK16: 179.37322 | AM16: 7.93273 | BJ16: 25 | BM16: 167.61232 | BN16: 166.56063 | BO16: 168.58997 | BW16: 206.49456 | BX16: 206.11549 | BY16: 205.99003 | CA16: 17.41583 | CB16: 44.05367 | CI16: 118.14735 | CJ16: 47.90514 | CK16: 53.71012 | CO16: 191.19621 | CP16: 180.55348 | CQ16: 180.52451 | CR16: 181.33356 | CS16: 181.02912 | CZ16: 6177.5542 | DR16: MIN | DS16: 2760.835 | DT16: 540.1156 | DU16: 540.1156 | EC16: 6068.5 | HH16: 2760.835 | HI16: 2699.0764 | HJ16: 377.24654
B17: 05:30 | F17: 8.82587 | G17: 8.51669 | J17: 81.0961 | T17: 18.14123 | U17: 19.19196 | V17: 24.42536 | W17: 1.06127 | AA17: 23.06068 | AF17: 12.23925 | AG17: 24.4617 | AH17: 10.27692 | AK17: 179.37322 | AM17: 7.93273 | BJ17: 25 | BM17: 167.61232 | BN17: 166.56063 | BO17: 168.58997 | BW17: 206.49456 | BX17: 206.11549 | BY17: 205.99003 | CA17: 17.41583 | CB17: 44.05367 | CI17: 118.14735 | CJ17: 47.90514 | CK17: 53.71012 | CO17: 191.19621 | CP17: 180.55348 | CQ17: 180.52451 | CR17: 181.33356 | CS17: 181.02912 | CZ17: 6339.1794 | DR17: MIN | DS17: 2760.835 | DT17: 540.1156 | DU17: 540.1156 | EC17: 6229.6 | HH17: 2760.835 | HI17: 2699.0764 | HJ17: 327.61965
B18: 06:00 | F18: 8.82587 | G18: 8.51669 | J18: 81.0961 | T18: 18.14123 | U18: 19.19196 | V18: 24.42536 | W18: 1.06127 | AA18: 23.06068 | AF18: 12.23925 | AG18: 24.4617 | AH18: 10.27692 | AK18: 179.37322 | AM18: 7.93273 | BJ18: 25 | BM18: 167.61232 | BN18: 166.56063 | BO18: 168.58997 | BW18: 206.49456 | BX18: 206.11549 | BY18: 205.99003 | CA18: 17.41583 | CB18: 44.05367 | CI18: 118.14735 | CJ18: 47.90514 | CK18: 53.71012 | CO18: 191.19621 | CP18: 180.55348 | CQ18: 180.52451 | CR18: 181.33356 | CS18: 181.02912 | CZ18: 6379.1458 | DR18: MIN | DS18: 2760.835 | DT18: 540.1156 | DU18: 540.1156 | EC18: 6272 | HH18: 2760.835 | HI18: 2699.0764 | HJ18: 327.61965
B19: 06:30 | F19: 8.82587 | G19: 8.51669 | J19: 81.0961 | T19: 18.14123 | U19: 19.19196 | V19: 24.42536 | W19: 1.06127 | AA19: 23.06068 | AF19: 12.23925 | AG19: 24.4617 | AH19: 10.27692 | AK19: 179.37322 | AM19: 7.93273 | BM19: 167.61232 | BN19: 166.56063 | BO19: 168.58997 | BW19: 206.49456 | BX19: 206.11549 | BY19: 205.99003 | CA19: 17.41583 | CB19: 44.05367 | CI19: 118.14735 | CJ19: 47.90514 | CK19: 53.71012 | CO19: 191.19621 | CP19: 180.55348 | CQ19: 180.52451 | CR19: 181.33356 | CS19: 181.02912 | CZ19: 6586.34 | DR19: MIN | DS19: 2738.2198 | DT19: 515.1156 | DU19: 515.1156 | EC19: 6483 | HH19: 2735.835 | HI19: 2674.0764 | HJ19: 327.61965
B20: 07:00 | F20: 8.82587 | G20: 8.51669 | J20: 81.0961 | T20: 18.14123 | U20: 19.19196 | V20: 24.42536 | W20: 1.06127 | AA20: 23.06068 | AF20: 12.23925 | AG20: 24.4617 | AH20: 10.27692 | AK20: 179.37322 | AM20: 7.93273 | BM20: 167.61232 | BN20: 166.56063 | BO20: 168.58997 | BW20: 206.49456 | BX20: 206.11549 | BY20: 205.99003 | CA20: 17.41583 | CB20: 44.05367 | CI20: 118.14735 | CJ20: 47.90514 | CK20: 53.71012 | CO20: 191.19621 | CP20: 180.55348 | CQ20: 180.52451 | CR20: 181.33356 | CS20: 181.02912 | CZ20: 6651.6788 | DR20: MIN | DS20: 2738.2198 | DT20: 515.1156 | DU20: 515.1156 | EC20: 6542.5 | HH20: 2735.835 | HI20: 2674.0764 | HJ20: 327.61965
B21: 07:30 | G21: 8.51669 | J21: 81.0961 | T21: 18.14123 | U21: 19.19196 | V21: 24.42536 | W21: 1.06127 | AA21: 23.06068 | AF21: 12.23925 | AG21: 24.4617 | AH21: 10.27692 | AK21: 179.37322 | AM21: 7.93273 | BM21: 167.61232 | BN21: 166.56063 | BO21: 168.58997 | BW21: 206.49456 | BX21: 206.11549 | BY21: 205.99003 | CA21: 17.41583 | CB21: 44.05367 | CI21: 118.14735 | CJ21: 47.90514 | CK21: 53.71012 | CO21: 191.19621 | CP21: 180.55348 | CQ21: 180.52451 | CR21: 181.33356 | CS21: 181.02912 | CZ21: 6827.7348 | DR21: MIN | DS21: 2729.3939 | DT21: 515.1156 | DU21: 515.1156 | EC21: 6724.9 | HH21: 2727.0091 | HI21: 2665.2506 | HJ21: 336.44552
B22: 08:00 | G22: 8.51669 | J22: 81.0961 | T22: 18.14123 | U22: 19.19196 | V22: 24.42536 | W22: 1.06127 | AA22: 23.06068 | AF22: 12.23925 | AG22: 24.4617 | AH22: 10.27692 | AK22: 179.37322 | AM22: 7.93273 | BM22: 167.61232 | BN22: 166.56063 | BO22: 168.58997 | BW22: 206.49456 | BX22: 206.11549 | BY22: 205.99003 | CA22: 17.41583 | CB22: 44.05367 | CI22: 118.14735 | CJ22: 47.90514 | CK22: 53.71012 | CO22: 191.19621 | CP22: 180.55348 | CQ22: 180.52451 | CR22: 181.33356 | CS22: 181.02912 | CZ22: 6905.0108 | DR22: MED | DS22: 2729.3939 | DT22: 515.1156 | DU22: 515.1156 | EC22: 6802.1 | HH22: 2727.0091 | HI22: 2665.2506 | HJ22: 336.44552
B23: 08:30 | G23: 8.51669 | J23: 81.0961 | T23: 18.14123 | U23: 19.19196 | V23: 24.42536 | W23: 1.06127 | AA23: 23.06068 | AF23: 12.23925 | AG23: 24.4617 | AH23: 10.27692 | AK23: 179.37322 | AM23: 7.93273 | BM23: 167.61232 | BN23: 166.56063 | BO23: 168.58997 | BW23: 206.49456 | BX23: 206.11549 | BY23: 205.99003 | CA23: 17.41583 | CB23: 44.05367 | CI23: 118.14735 | CJ23: 47.90514 | CK23: 53.71012 | CO23: 191.19621 | CP23: 180.55348 | CQ23: 180.52451 | CR23: 181.33356 | CS23: 181.02912 | CZ23: 7039.146 | DR23: MED | DS23: 2729.3939 | DT23: 515.1156 | DU23: 515.1156 | EC23: 6930.3 | HH23: 2727.0091 | HI23: 2665.2506 | HJ23: 336.44552
