Workbook

Sheet EVENTOS
B3: jueves, 12 de Febrero del 2026
B5: INFORMACIÓN DE EVENTOS PRINCIPALES EN SUS INSTALACIONES
B6: TIPO DE EVENTO | C6: EMPRESA | D6: UBICACIÓN | E6: TIPO DE EQUIPO | F6: EQUIPO | G6: INICIO | H6: FINAL | I6: DESCRIPCIÓN | J6: MW INDISP. | K6: INTERRUPCIÓN (SI/NO) | L6: TENSIÓN DE FALLA (kV)
B7: FALLA | C7: AGROLMOS SOCIEDAD ANONIMA - AGROLMOS S.A. | D7: AGROLMOS | E7: GENERADOR TERMOELÉCTRICO | F7: TV2 | G7: 12/02/2026 13:11:45 | H7: 12/02/2026 13:51:16 | I7: DESCONEXIÓN DEL GENERADOR TV2 DE LA CT AGROLMOS | K7: NO | L7: 13.8
B8: EVENTO | C8: CONELSUR LT SAC | D8: PORTILLO | E8: SUBESTACION | F8: SS.EE. | G8: 12/02/2026 00:00:00 | H8: 13/02/2026 00:00:00 | I8: DECLARACIÓN DE SITUACIÓN EXCEPCIONAL EN LA S.E. PORTILLO 60 kV | K8: NO
B9: EVENTO | C9: ELECTRO ORIENTE | D9: BELAUNDE TERRY - TARAPOTO | E9: LINEA DE TRANSMISION | F9: L-1018 | G9: 12/02/2026 18:46:00 | H9: 12/02/2026 19:59:00 | I9: DECLARACIÓN DE SITUACIÓN EXCEPCIONAL EN LA LÍNEA L-1018 (BELAUNDE TERRY - TARAPOTO) DE 138 kV | K9: NO
B10: FALLA | C10: SAN GABAN | D10: PCH TUPURI | E10: CENTRAL HIDROELÉCTRICA | F10: CENTRAL | G10: 12/02/2026 15:55:00 | H10: 12/02/2026 16:36:00 | I10: DESCONEXIÓN DE LA C.H. TUPURI POR FALLA. | K10: NO | L10: 2.4
B11: FALLA | C11: SAN GABAN | D11: PCH TUPURI | E11: CENTRAL HIDROELÉCTRICA | F11: CENTRAL | G11: 12/02/2026 16:43:00 | H11: 13/02/2026 00:00:00 | I11: DESCONEXIÓN DE LA C.H. TUPURI POR FALLA. | K11: NO | L11: 2.4
B12: FALLA | C12: STATKRAFT S.A | D12: CAHUA | E12: GENERADOR HIDROELÉCTRICO | F12: G2 | G12: 12/02/2026 19:23:06 | H12: 12/02/2026 20:50:21 | I12: DESCONEXIÓN DEL GENERADOR G2 DE LA C.H. CAHUA POR FALLA | K12: NO | L12: 10
B13: FALLA | C13: STATKRAFT S.A | D13: CAHUA | E13: GENERADOR HIDROELÉCTRICO | F13: G1 | G13: 12/02/2026 19:30:23 | H13: 12/02/2026 22:30:59 | I13: DESCONEXIÓN DEL GENERADOR G1 DE LA C.H. CAHUA POR FALLA | K13: NO | L13: 10

Sheet RESTRIC_OPE
B3: jueves, 12 de Febrero del 2026
B5: RESTRICCIONES OPERATIVAS
B6: FECHA | C6: HORA INICIO | D6: HORA FINAL | E6: EMPRESA | F6: UBICACIÓN | G6: T.Eq. | H6: EQUIPO | I6: DESCRIPCIÓN
B7: 12/02/2026 | C7: 00:00 | D7: 24:00 | E7: CELEPSA | F7: C.H. EL PLATANAL | G7: CH | H7: CENTRAL | I7: De acuerdo con lo informado por CELEPSA mediante correo el dia 17.01, declaran que la CH Platanal se encontrará de pasada.
B8: 12/02/2026 | C8: 00:00 | D8: 24:00 | E8: EGASA | F8: S.E. CONVERTIDOR | G8: BARRA | H8: BARRA138KV | I8: EGASA limitó la capacidad del transformador 138 kV/33 kV a 50 MVA por deterioro del aislamiento.
B9: 12/02/2026 | C9: 00:00 | D9: 24:00 | E9: ELECTROPERU | F9: C.H. MANTARO | G9: CH | H9: CENTRAL | I9: De acuerdo con el correo del día 25.08.2025, la central tiene una limitación de potencia máxima de 650 MW por seguridad de la central.
B10: 12/02/2026 | C10: 00:00 | D10: 24:00 | E10: ENEL GENERACION PIURA S.A. | F10: C.T. MALACAS | G10: CT | H10: CENTRAL | I10: De acuerdo con la comunicación vía correo del día 24.10.2024. ENEL GENERACIÓN PIURA informa una restricción de potencia para alcanzar 105 MW en simultaneo (TG6+TGN4).
B11: 12/02/2026 | C11: 00:00 | D11: 24:00 | E11: ENEL GENERACION PIURA S.A. | F11: C.T. MALACAS | G11: GT | H11: TG4 | I11: De acuerdo a lo informado por correo electrónico el día 16.01, con la disponibilidad de aproximadamente 12 MMPCD (339.8Mm³) la unidad TG4 puede con una generación de 80 MW durante 4 horas, y a potencia mínima durante el resto de los periodos
B12: 12/02/2026 | C12: 00:00 | D12: 24:00 | E12: ENGIE ENERGIA PERU S.A.A. | F12: C.H. YUNCÁN | G12: GH | H12: G3 | I12: Según la carta N° ENG/ 198-2024 enviada por su representada, se opera de forma continua el G3 de la CH Yuncán, debido a la ejecución de mantenimientos necesarios para evitar daños en los sellos de seguridad de la válvula esférica del grupo.
B13: 12/02/2026 | C13: 00:00 | D13: 24:00 | E13: ENGIE ENERGIA PERU S.A.A. | F13: C.T. CHILCA 1 | G13: CT | H13: CENTRAL | I13: Con carta ENG/971-2023, indica que no puede cumplir con las IO considerada en el PDO_17122023 dado que vulneran la seguridad de sus activos. Indican que se debe tomar TMO=168h.
B14: 12/02/2026 | C14: 00:00 | D14: 24:00 | E14: ENGIE ENERGIA PERU S.A.A. | F14: C.T. CHILCA 1 | G14: CT | H14: CENTRAL | I14: Restricción de temperatura de la C.T Chilca, ver valor en el modelo de despacho.
B15: 12/02/2026 | C15: 00:00 | D15: 24:00 | E15: ENGIE ENERGIA PERU S.A.A. | F15: C.T. CHILCA 2 | G15: CT | H15: CENTRAL | I15: Con carta ENG/971-2023, indica que no puede cumplir con las IO considerada en el PDO_17122023 dado que vulneran la seguridad de sus activos. Indican que se debe tomar TMO=168h.
B16: 12/02/2026 | C16: 00:00 | D16: 24:00 | E16: FENIX POWER PERÚ | F16: C.T. FENIX | G16: CT | H16: CENTRAL | I16: De acuerdo con lo comunicado en el correo del día 06.05.2025, la CT Fenix cuenta con TMO de 168 hrs en todos sus modos de operación.
B17: 12/02/2026 | C17: 00:00 | D17: 24:00 | E17: KALLPA GENERACION S.A. | F17: C.H. CERRO DEL AGUILA | G17: GH | H17: G1 | I17: De acuerdo a lo informado el día 17/11 por la empresa KALLPA, el G1 tiene un TA = 15min
... B58: 12/02/2026 | C58: 00:00 | D58: 24:00 | E58: TERMOSELVA | F58: C.T. AGUAYTÍA | G58: CT | H58: CENTRAL | I58: Disponibilidad de 23.5 MMSCF para la CT Aguaytía.

Sheet MANTENIMIENTO EJECUTADOS
B3: jueves, 12 de Febrero del 2026
B5: Mantenimiento Ejecutado
B6: Empresa | C6: Ubicación | D6: Equipo | E6: Inicio | F6: Final | G6: Descripción | H6: MW Indisp. | I6: Prog. | J6: Dispon | K6: Interrupc. | L6: Tipo | M6: CodEq | N6: TipoEq_Osinerg
B7: ATLANTICA TRANSMISION SUR S.A. | C7: CHILCA CTM - POROMA | D7: L-5032 | E7: 12/02/2026 07:17 | F7: 12/02/2026 16:38 | G7: Inspeccion Anual en LLTT | H7: 0 | I7: P | J7: E/S | K7: N | L7: PREV. | M7: 13652 | N7: T
B8: ATLANTICA TRANSMISION SUR S.A. | C8: OCONA | D8: INT-5450 | E8: 12/02/2026 00:00 | F8: 13/02/2026 00:00 | G8: Interruptor INT-5450 cerrado con restriccion operativa, REB-5450 en servicio y suministrando los SS.AA. de la S.E. Oco?a. | H8: 0 | I8: P | J8: E/S | K8: N | L8: OTROS | M8: 13761 | N8: T
B9: ATLANTICA TRANSMISION SUR S.A. | C9: OCONA | D9: SE OCOÑA | E9: 12/02/2026 08:27 | F9: 12/02/2026 17:37 | G9: Inspeccion anual y termografica. | H9: 0 | I9: P | J9: E/S | K9: N | L9: PREV. | M9: 13741 | N9: T
B10: ATLANTICA TRANSMISION SUR S.A. | C10: POROMA | D10: INT-5371 | E10: 12/02/2026 00:00 | F10: 13/02/2026 00:00 | G10: Seccionador SBB-5371 fase T indisponible por problemas mecanicos, el seccionador permanece cerrado y bloqueado | H10: 0 | I10: P | J10: E/S | K10: N | L10: OTROS | M10: 13751 | N10: T
B11: ATLANTICA TRANSMISION SUR S.A. | C11: POROMA | D11: REB-5350 | E11: 12/02/2026 00:00 | F11: 13/02/2026 00:00 | G11: Fuera de servicio por falla en el equipo. | H11: 0 | I11: P | J11: F/S | K11: N | L11: OTROS | M11: 13771 | N11: T
B12: ATLANTICA TRANSMISION SUR S.A. | C12: POROMA - OCONA | D12: L-5034 | E12: 12/02/2026 09:46 | F12: 12/02/2026 17:12 | G12: Actividad de reparacion de pedestales para la Linea L5034. | H12: 0 | I12: P | J12: E/S | K12: N | L12: PREV. | M12: 13743 | N12: T
B13: ATN 2 S.A. | C13: COTARUSE - LAS BAMBAS | D13: L-2055 | E13: 12/02/2026 08:48 | F13: 12/02/2026 17:32 | G13: Inspeccion anual de LLTT | H13: 0 | I13: P | J13: E/S | K13: N | L13: PREV. | M13: 14930 | N13: T
B14: ATN 2 S.A. | C14: COTARUSE - LAS BAMBAS | D14: L-2056 | E14: 12/02/2026 08:48 | F14: 12/02/2026 17:32 | G14: Inspeccion anual de LLTT | H14: 0 | I14: P | J14: E/S | K14: N | L14: PREV. | M14: 14929 | N14: T
B15: ATN S.A. | C15: KIMAN AYLLU | D15: AUT-501 | E15: 12/02/2026 00:00 | F15: 13/02/2026 00:00 | G15: Restriccion Operativa en el circuito de control de cambiador de tap s del AUT-501 | H15: 0 | I15: P | J15: E/S | K15: N | L15: OTROS | M15: 13099 | N15: T
B16: CHINANGO S.A.C. | C16: YANANGO | D16: G1 | E16: 12/02/2026 10:50 | F16: 12/02/2026 17:06 | G16: AJUSTE DE PSS Y COMPLETAR AJUSTES PARA 42 MW - EN SERVICIO | H16: 42 | I16: P | J16: F/S | K16: N | L16: PREV. | M16: 108 | N16: G
B17: CONELSUR LT SAC | C17: CAJAMARQUILLA | D17: BARRA A 220kV | E17: 12/02/2026 07:30 | F17: 12/02/2026 17:30 | G17: POR MANTENIMIENTO EN CL-2014. | H17: 0 | I17: P | J17: F/S | K17: N | L17: PREV. | M17: 1103 | N17: T
B18: CONELSUR LT SAC | C18: CAJAMARQUILLA | D18: CL-2014 | E18: 12/02/2026 07:30 | F18: 12/02/2026 17:30 | G18: REEMPLAZO DE PASTA SILICONA | H18: 0 | I18: P | J18: F/S | K18: N | L18: PREV. | M18: 12717 | N18: T
... B123: TRANSMANTARO | C123: YARABAMBA | D123: IN-5120 | E123: 12/02/2026 00:00 | F123: 13/02/2026 00:00 | G123: SE. YARABAMBA 500KV: INTERRRUPTOR INDISPONIBLE POR PROBLEMAS DE MANDOS. REACTOR R-31 SERA OPERADO CON EL INTERRRUPTOR IN-5116. | H123: 0 | I123: P | J123: F/S | K123: N | L123: OTROS | M123: 17437 | N123: T

Sheet INGRESO OC
A3: jueves, 12 de Febrero del 2026
A5: INGRESO A OPERACIÓN COMERCIAL
A6: EMPRESA | B6: TIPO DE EQUIPO | C6: UBICACIÓN | D6: EQUIPO | E6: Fecha y hora de Ingreso a Operación Comercial

Sheet DESPACHO_EJECUTADO
B3: jueves, 12 de Febrero del 2026
A5: POTENCIA ACTIVA EJECUTADA DE LAS UNIDADES DE GENERACIÓN DEL SEIN (MW) | FQ5: CENTRALES NO INTEGRANTES COES
A6: FECHA | B6: HORA | C6: 65333 | D6: 101 | E6: 102 | F6: 42667 | G6: 42668 | H6: 126 | I6: 127 | J6: 138 | K6: 139 | L6: 197 | M6: 203 | N6: 204 | O6: 230 | P6: 209 | Q6: 56677 | R6: 796 | S6: 2146 | T6: 142 | U6: 143 | V6: 125 | W6: 187 | X6: 163 | Y6: 298 | Z6: 299 | AA6: 219 | AB6: 151 | AC6: 152 | AD6: 153 | AE6: 154 | AF6: 756 | AG6: 156 | AH6: 155 | AI6: 182 | AJ6: 212 | AK6: 758 | AL6: 263 | AM6: 265 | AN6: 775 | AO6: 777 | AP6: 2154 | AQ6: 150 | AR6: 149 | AS6: 188 | AT6: 2131 | AU6: 755 | AV6: 252 | AW6: 249 | AX6: 250 | AY6: 117 | AZ6: 119 | BA6: 120 | BB6: 189 | BC6: 122 | BD6: 266 | BE6: 337 | BF6: 338 | BG6: 251 | BH6: 115 | BI6: 239 | BJ6: 288 | BK6: 240 | BL6: 241 | BM6: 242 | BN6: 191 | BO6: 194 | BP6: 196 | BQ6: 207 | BR6: 236 | BS6: 795 | BT6: 285 | BU6: 995 | BV6: 996 | BW6: 997 | BX6: 766 | BY6: 926 | BZ6: 924 | CA6: 121 | CB6: 103 | CC6: 104 | CD6: 106 | CE6: 105 | CF6: 107 | CG6: 110 | CH6: 109 | CI6: 144 | CJ6: 113 | CK6: 114 | CL6: 193 | CM6: 208 | CN6: 786 | CO6: 787 | CP6: 788 | CQ6: 789 | CR6: 248 | CS6: 2159 | CT6: 267 | CU6: 268 | CV6: 2194 | CW6: 303 | CX6: 59715 | CY6: 62255 | CZ6: 1263 | DA6: 61800 | DB6: 69125 | DC6: 216 | DD6: 198 | DE6: 70400 | DF6: 76068 | DG6: 49607 | DH6: 214 | DI6: 260 | DJ6: 2152 | DK6: 2128 | DL6: 247 | DM6: 228 | DN6: 2135 | DO6: 261 | DP6: 237 | DQ6: 253 | DR6: 770 | DS6: 235 | DT6: 238 | DU6: 2184 | DV6: 61855 | DW6: 223 | DX6: 75566 | DY6: 226 | DZ6: 201 | EA6: 258 | EB6: 259 | EC6: 257 | ED6: 256 | EE6: 2148 | EF6: 58288 | EG6: 58289 | EH6: 58839 | EI6: 58840 | EJ6: 75260 | EK6: 296 | EL6: 297 | EM6: 211 | EN6: 2175 | EO6: 2178 | EP6: 2181 | EQ6: 1262 | ER6: 63425 | ES6: 233 | ET6: 2150 | EU6: 2165 | EV6: 2161 | EW6: 61197 | EX6: 58851 | EY6: 225 | EZ6: 2201 | FA6: 2171 | FB6: 760 | FC6: 234 | FD6: 215 | FE6: 917 | FF6: 920 | FG6: 289 | FH6: 58333 | FI6: 58336 | FJ6: 213 | FK6: 232 | FL6: 2190 | FM6: 69867 | FN6: 75066 | FO6: TOTAL COES | FQ6: 221 | FR6: 222 | FS6: 224 | FT6: 2187 | FU6: 227 | FV6: 49400 | FW6: 199 | FX6: 200 | FY6: TOTAL NO COES
C7: SUR | D7: CENTRO | E7: CENTRO | F7: NORTE | G7: NORTE | H7: NORTE | I7: NORTE | J7: CENTRO | K7: CENTRO | L7: CENTRO | M7: CENTRO | N7: CENTRO | O7: CENTRO | P7: CENTRO | Q7: CENTRO | R7: CENTRO | S7: CENTRO | T7: CENTRO | U7: CENTRO | V7: CENTRO | W7: CENTRO | X7: SUR | Y7: SUR | Z7: SUR | AA7: CENTRO | AB7: SUR | AC7: SUR | AD7: SUR | AE7: SUR | AF7: SUR | AG7: SUR | AH7: SUR | AI7: SUR | AJ7: CENTRO | AK7: NORTE | AL7: NORTE | AM7: NORTE | AN7: CENTRO | AO7: CENTRO | AP7: CENTRO | AQ7: CENTRO | AR7: CENTRO | AS7: CENTRO | AT7: CENTRO | AU7: SUR | AV7: CENTRO | AW7: CENTRO | AX7: CENTRO | AY7: CENTRO | AZ7: CENTRO | BA7: CENTRO | BB7: SUR | BC7: NORTE | BD7: CENTRO | BE7: CENTRO | BF7: CENTRO | BG7: CENTRO | BH7: NORTE | BI7: NORTE | BJ7: NORTE | BK7: SUR | BL7: SUR | BM7: SUR | BN7: CENTRO | BO7: CENTRO | BP7: CENTRO | BQ7: CENTRO | BR7: CENTRO | BS7: CENTRO | BT7: CENTRO | BU7: SUR | BV7: SUR | BW7: SUR | BX7: NORTE | BY7: SUR | BZ7: CENTRO | CA7: NORTE | CB7: CENTRO | CC7: CENTRO | CD7: CENTRO | CE7: CENTRO | CF7: CENTRO | CG7: CENTRO | CH7: CENTRO | CI7: CENTRO | CJ7: CENTRO | CK7: CENTRO | CL7: CENTRO | CM7: CENTRO | CN7: SUR | CO7: SUR | CP7: SUR | CQ7: SUR | CR7: CENTRO | CS7: CENTRO | CT7: CENTRO | CU7: CENTRO | CV7: NORTE | CW7: CENTRO | CX7: CENTRO | CY7: SUR | CZ7: NORTE | DA7: NORTE | DB7: CENTRO | DC7: NORTE | DD7: NORTE | DE7: SUR | DG7: SUR | DH7: CENTRO | DI7: CENTRO | DJ7: CENTRO | DK7: NORTE | DL7: NORTE | DM7: CENTRO | DN7: CENTRO | DO7: SUR | DP7: SUR | DQ7: CENTRO | DR7: CENTRO | DS7: SUR | DT7: CENTRO | DU7: CENTRO | DV7: NORTE | DW7: CENTRO | DX7: CENTRO | DY7: CENTRO | DZ7: NORTE | EA7: CENTRO | EB7: CENTRO | EC7: NORTE | ED7: NORTE | EE7: SUR | EF7: CENTRO | EG7: CENTRO | EH7: CENTRO | EI7: CENTRO | EJ7: SUR | EK7: CENTRO | EL7: CENTRO | EM7: SUR | EN7: SUR | EO7: SUR | EP7: SUR | EQ7: NORTE | ER7: SUR | ES7: SUR | ET7: SUR | EU7: CENTRO | EV7: CENTRO | EW7: CENTRO | EX7: SUR | EY7: CENTRO | EZ7: CENTRO | FA7: CENTRO | FB7: CENTRO | FC7: SUR | FD7: NORTE | FE7: CENTRO | FF7: CENTRO | FG7: NORTE | FH7: NORTE | FI7: NORTE | FJ7: CENTRO | FK7: NORTE | FL7: NORTE | FM7: NORTE | FN7: NORTE | FQ7: NORTE | FR7: CENTRO | FS7: NORTE | FT7: NORTE | FU7: NORTE | FV7: NORTE | FW7: NORTE | FX7: NORTE
C8: HIDROELÉCTRICA | D8: HIDROELÉCTRICA | E8: HIDROELÉCTRICA | F8: TERMOELÉCTRICA | G8: TERMOELÉCTRICA | H8: HIDROELÉCTRICA | I8: HIDROELÉCTRICA | J8: TERMOELÉCTRICA | K8: TERMOELÉCTRICA | L8: TERMOELÉCTRICA | M8: TERMOELÉCTRICA | N8: TERMOELÉCTRICA | O8: TERMOELÉCTRICA | P8: TERMOELÉCTRICA | Q8: TERMOELÉCTRICA | R8: HIDROELÉCTRICA | S8: HIDROELÉCTRICA | T8: TERMOELÉCTRICA | U8: TERMOELÉCTRICA | V8: TERMOELÉCTRICA | W8: TERMOELÉCTRICA | X8: HIDROELÉCTRICA | Y8: HIDROELÉCTRICA | Z8: HIDROELÉCTRICA | AA8: TERMOELÉCTRICA | AB8: HIDROELÉCTRICA | AC8: HIDROELÉCTRICA | AD8: HIDROELÉCTRICA | AE8: HIDROELÉCTRICA | AF8: TERMOELÉCTRICA | AG8: TERMOELÉCTRICA | AH8: TERMOELÉCTRICA | AI8: HIDROELÉCTRICA | AJ8: HIDROELÉCTRICA | AK8: TERMOELÉCTRICA | AL8: TERMOELÉCTRICA | AM8: TERMOELÉCTRICA | AN8: HIDROELÉCTRICA | AO8: HIDROELÉCTRICA | AP8: HIDROELÉCTRICA | AQ8: HIDROELÉCTRICA | AR8: HIDROELÉCTRICA | AS8: HIDROELÉCTRICA | AT8: HIDROELÉCTRICA | AU8: HIDROELÉCTRICA | AV8: TERMOELÉCTRICA | AW8: TERMOELÉCTRICA | AX8: TERMOELÉCTRICA | AY8: HIDROELÉCTRICA | AZ8: HIDROELÉCTRICA | BA8: HIDROELÉCTRICA | BB8: HIDROELÉCTRICA | BC8: HIDROELÉCTRICA | BD8: HIDROELÉCTRICA | BE8: HIDROELÉCTRICA | BF8: HIDROELÉCTRICA | BG8: HIDROELÉCTRICA | BH8: TERMOELÉCTRICA | BI8: TERMOELÉCTRICA | BJ8: TERMOELÉCTRICA | BK8: TERMOELÉCTRICA | BL8: TERMOELÉCTRICA | BM8: TERMOELÉCTRICA | BN8: HIDROELÉCTRICA | BO8: TERMOELÉCTRICA | BP8: TERMOELÉCTRICA | BQ8: TERMOELÉCTRICA | BR8: TERMOELÉCTRICA | BS8: TERMOELÉCTRICA | BT8: TERMOELÉCTRICA | BU8: TERMOELÉCTRICA | BV8: TERMOELÉCTRICA | BW8: TERMOELÉCTRICA | BX8: HIDROELÉCTRICA | BY8: TERMOELÉCTRICA | BZ8: TERMOELÉCTRICA | CA8: HIDROELÉCTRICA | CB8: HIDROELÉCTRICA | CC8: HIDROELÉCTRICA | CD8: HIDROELÉCTRICA | CE8: HIDROELÉCTRICA | CF8: HIDROELÉCTRICA | CG8: TERMOELÉCTRICA | CH8: TERMOELÉCTRICA | CI8: TERMOELÉCTRICA | CJ8: TERMOELÉCTRICA | CK8: TERMOELÉCTRICA | CL8: TERMOELÉCTRICA | CM8: TERMOELÉCTRICA | CN8: TERMOELÉCTRICA | CO8: TERMOELÉCTRICA | CP8: TERMOELÉCTRICA | CQ8: TERMOELÉCTRICA | CR8: TERMOELÉCTRICA | CS8: TERMOELÉCTRICA | CT8: HIDROELÉCTRICA | CU8: HIDROELÉCTRICA | CV8: HIDROELÉCTRICA | CW8: SOLAR | CX8: EÓLICA | CY8: SOLAR | CZ8: EÓLICA | DA8: SOLAR | DB8: HIDROELÉCTRICA | DC8: HIDROELÉCTRICA | DD8: HIDROELÉCTRICA | DE8: SOLAR | DF8: SOLAR | DG8: HIDROELÉCTRICA | DH8: HIDROELÉCTRICA | DI8: HIDROELÉCTRICA | DJ8: HIDROELÉCTRICA | DK8: HIDROELÉCTRICA | DL8: HIDROELÉCTRICA | DM8: HIDROELÉCTRICA | DN8: HIDROELÉCTRICA | DO8: SOLAR | DP8: SOLAR | DQ8: EÓLICA | DR8: EÓLICA | DS8: SOLAR | DT8: HIDROELÉCTRICA | DU8: HIDROELÉCTRICA | DV8: HIDROELÉCTRICA | DW8: HIDROELÉCTRICA | DX8: SOLAR | DY8: HIDROELÉCTRICA | DZ8: HIDROELÉCTRICA | EA8: HIDROELÉCTRICA | EB8: HIDROELÉCTRICA | EC8: EÓLICA | ED8: EÓLICA | EE8: SOLAR | EF8: EÓLICA | EG8: EÓLICA | EH8: EÓLICA | EI8: EÓLICA | EJ8: SOLAR | EK8: HIDROELÉCTRICA | EL8: HIDROELÉCTRICA | EM8: HIDROELÉCTRICA | EN8: HIDROELÉCTRICA | EO8: HIDROELÉCTRICA | EP8: HIDROELÉCTRICA | EQ8: EÓLICA | ER8: SOLAR | ES8: SOLAR | ET8: SOLAR | EU8: HIDROELÉCTRICA | EV8: EÓLICA | EW8: EÓLICA | EX8: SOLAR | EY8: TERMOELÉCTRICA | EZ8: TERMOELÉCTRICA | FA8: TERMOELÉCTRICA | FB8: TERMOELÉCTRICA | FC8: SOLAR | FD8: HIDROELÉCTRICA | FE8: HIDROELÉCTRICA | FF8: HIDROELÉCTRICA | FG8: TERMOELÉCTRICA | FH8: TERMOELÉCTRICA | FI8: TERMOELÉCTRICA | FJ8: TERMOELÉCTRICA | FK8: TERMOELÉCTRICA | FL8: TERMOELÉCTRICA | FM8: TERMOELÉCTRICA | FN8: TERMOELÉCTRICA | FQ8: HIDROELÉCTRICA | FR8: HIDROELÉCTRICA | FS8: HIDROELÉCTRICA | FT8: HIDROELÉCTRICA | FU8: TERMOELÉCTRICA | FV8: TERMOELÉCTRICA | FW8: HIDROELÉCTRICA | FX8: HIDROELÉCTRICA
C9: HYDRO GLOBAL PERÚ S.A.C. | D9: ELECTROPERU | E9: ELECTROPERU | F9: ELECTROPERU | G9: ELECTROPERU | H9: ORAZUL ENERGY PERÚ | I9: ORAZUL ENERGY PERÚ | J9: TERMOSELVA | K9: TERMOSELVA | L9: KALLPA GENERACION S.A. | M9: KALLPA GENERACION S.A. | N9: KALLPA GENERACION S.A. | O9: KALLPA GENERACION S.A. | P9: KALLPA GENERACION S.A. | Q9: KALLPA GENERACION S.A. | R9: KALLPA GENERACION S.A. | S9: KALLPA GENERACION S.A. | T9: SHOUGESA | U9: SHOUGESA | V9: SHOUGESA | W9: SHOUGESA | X9: EGEMSA | Y9: EGESUR | Z9: EGESUR | AA9: EGESUR | AB9: EGASA | AC9: EGASA | AD9: EGASA | AE9: EGASA | AF9: EGASA | AG9: EGASA | AH9: EGASA | AI9: SAN GABAN | AJ9: CELEPSA | AK9: MINERA CERRO VERDE | AL9: PLANTA DE RESERVA FRIA DE GENERACION DE ETEN S.A. | AM9: PLANTA DE RESERVA FRIA DE GENERACION DE ETEN S.A. | AN9: EMPRESA DE GENERACION HUALLAGA | AO9: EMPRESA DE GENERACION HUALLAGA | AP9: LA VIRGEN | AQ9: CHINANGO S.A.C. | AR9: CHINANGO S.A.C. | AS9: HIDROELECTRICA HUANCHOR S.A.C. | AT9: CELEPSA RENOVABLES S.R.L. | AU9: INLAND ENERGY SAC | AV9: FENIX POWER PERÚ | AW9: FENIX POWER PERÚ | AX9: FENIX POWER PERÚ | AY9: STATKRAFT S.A | AZ9: STATKRAFT S.A | BA9: STATKRAFT S.A | BB9: STATKRAFT S.A | BC9: STATKRAFT S.A | BD9: STATKRAFT S.A | BE9: CENTRALES SANTA ROSA S.A.C. | BF9: CENTRALES SANTA ROSA S.A.C. | BG9: EMPRESA DE GENERACION HUANZA | BH9: ENEL GENERACION PIURA S.A. | BI9: ENEL GENERACION PIURA S.A. | BJ9: ENEL GENERACION PIURA S.A. | BK9: ENGIE ENERGIA PERU S.A.A. | BL9: ENGIE ENERGIA PERU S.A.A. | BM9: ENGIE ENERGIA PERU S.A.A. | BN9: ENGIE ENERGIA PERU S.A.A. | BO9: ENGIE ENERGIA PERU S.A.A. | BP9: ENGIE ENERGIA PERU S.A.A. | BQ9: ENGIE ENERGIA PERU S.A.A. | BR9: ENGIE ENERGIA PERU S.A.A. | BS9: ENGIE ENERGIA PERU S.A.A. | BT9: ENGIE ENERGIA PERU S.A.A. | BU9: ENGIE ENERGIA PERU S.A.A. | BV9: ENGIE ENERGIA PERU S.A.A. | BW9: ENGIE ENERGIA PERU S.A.A. | BX9: ENGIE ENERGIA PERU S.A.A. | BY9: INFRAESTRUCTURAS Y ENERGIAS DEL PERU S.A.C. | BZ9: INFRAESTRUCTURAS Y ENERGIAS DEL PERU S.A.C. | CA9: INVERSIONES SHAQSHA S.A.C. | CB9: ORYGEN PERU S.A.A. | CC9: ORYGEN PERU S.A.A. | CD9: ORYGEN PERU S.A.A. | CE9: ORYGEN PERU S.A.A. | CF9: ORYGEN PERU S.A.A. | CG9: ORYGEN PERU S.A.A. | CH9: ORYGEN PERU S.A.A. | CI9: ORYGEN PERU S.A.A. | CJ9: ORYGEN PERU S.A.A. | CK9: ORYGEN PERU S.A.A. | CL9: ORYGEN PERU S.A.A. | CM9: ORYGEN PERU S.A.A. | CN9: SAMAY I S.A.C | CO9: SAMAY I S.A.C | CP9: SAMAY I S.A.C | CQ9: SAMAY I S.A.C | CR9: TERMOCHILCA S.A.C. | CS9: TERMOCHILCA S.A.C. | CT9: TRANSMISION ANDINA DE GENERACION S.A.C. | CU9: TRANSMISION ANDINA DE GENERACION S.A.C. | CV9: CELARIS ENERGY S.A. | CW9: COLCA SOLAR S.A.C. | CX9: ENERGIA RENOVABLE DEL SUR S.A. | CY9: GR CORTARRAMA SOCIEDAD ANONIMA CERRADA | CZ9: GR TARUCA SOCIEDAD ANONIMA CERRADA | DA9: KONDU SAC | DB9: VARI ENERGIA S.A.C. | DC9: ORAZUL ENERGY PERÚ | DD9: ORAZUL ENERGY PERÚ | DE9: KALLPA GENERACION S.A. | DF9: KALLPA GENERACION S.A. | DG9: SAN GABAN | DH9: MAJA ENERGIA S.A.C. | DI9: EMPRESA DE GENERACION ELECTRICA CANCHAYLLO SAC | DJ9: EMPRESA DE GENERACION ELECTRICA SANTA ANA S.A.C. | DK9: EMPRESA ELECTRICA AGUA AZUL | DL9: EMPRESA ELECTRICA RIO DOBLE | DM9: HIDROCAÑETE S.A. | DN9: HUAURA POWER GROUP S.A. | DO9: MOQUEGUA FV S.A.C. | DP9: PANAMERICANA SOLAR SAC. | DQ9: PARQUE EOLICO MARCONA S.A.C. | DR9: PARQUE EOLICO TRES HERMANAS S.A.C. | DS9: TACNA SOLAR SAC. | DT9: ELECTRICA YANAPAMPA SAC | DU9: ANDEAN POWER S.A.C. | DV9: ASOCIACIÓN SANTA LUCIA DE CHACAS | DW9: ATRIA ENERGIA S.A.C. | DX9: COENERGY S.A.C. | DY9: EGEJUNIN | DZ9: EGEJUNIN | EA9: EGEJUNIN | EB9: EGEJUNIN | EC9: ENERGÍA EÓLICA S.A. | ED9: ENERGÍA EÓLICA S.A. | EE9: ENGIE ENERGIA PERU S.A.A. | EF9: ENGIE ENERGIA PERU S.A.A. | EG9: ENGIE ENERGIA PERU S.A.A. | EH9: ENGIE ENERGIA PERU S.A.A. | EI9: ENGIE ENERGIA PERU S.A.A. | EJ9: ENGIE ENERGIA PERU S.A.A. | EK9: GENERACIÓN ANDINA S.A.C. | EL9: GENERACIÓN ANDINA S.A.C. | EM9: GENERADORA DE ENERGÍA DEL PERÚ | EN9: GENERADORA DE ENERGÍA DEL PERÚ | EO9: GENERADORA DE ENERGÍA DEL PERÚ | EP9: GENERADORA DE ENERGÍA DEL PERÚ | EQ9: GR PAINO SOCIEDAD ANONIMA CERRADA | ER9: JOYA SOLAR S.A.C. | ES9: MAJES ARCUS S.A.C. | ET9: ORYGEN PERU S.A.A. | EU9: ORYGEN PERU S.A.A. | EV9: ORYGEN PERU S.A.A. | EW9: ORYGEN PERU S.A.A. | EX9: ORYGEN PERU S.A.A. | EY9: PETRAMAS | EZ9: PETRAMAS | FA9: PETRAMAS | FB9: PETRAMAS | FC9: REPARTICIÓN ARCUS S.A.C. | FD9: SINERSA | FE9: SINERSA | FF9: SINERSA | FG9: BIOENERGIA DEL CHIRA S.A. | FH9: GM OPERACIONES S.A.C. | FI9: GM OPERACIONES S.A.C. | FJ9: AGRO INDUSTRIAL PARAMONGA S.A. | FK9: AGROAURORA S.A.C. | FL9: AGROINDUSTRIAS SAN JACINTO S.A.A. | FM9: AGROLMOS SOCIEDAD ANONIMA - AGROLMOS S.A. | FN9: CASA GRANDE S.A.A. | FQ9: UNACEM PERU S.A. | FR9: ELECTRO ORIENTE | FS9: AGUAS Y ENERGIA PERU | FT9: ELECTRO ZAÑA S.A.C. | FU9: ELECTRONOROESTE S.A. | FV9: SDE PIURA | FW9: SINERSA | FX9: SINERSA
C10: SAN GABAN III | D10: MANTARO | E10: RESTITUCION | F10: TUMBES MAK 1 | G10: TUMBES MAK 2 | H10: CARHUAQUERO | I10: CAÑON DEL PATO | J10: AGUAYTIA TG1 | K10: AGUAYTIA TG2 | L10: KALLPA TG1 | M10: KALLPA TG2 | N10: KALLPA TG3 | O10: KALLPA TV | P10: LFLORES TG1 | Q10: LFLORES TV | R10: CERRO DEL AGUILA | S10: CERRODELAGUILAG4 | T10: SHOUGESA TV1 | U10: SHOUGESA TV2 | V10: SHOUGESA TV3 | W10: SHOUGESA CUMMINS | X10: MACHUPICCHU | Y10: ARICOTA 1 | Z10: ARICOTA 2 | AA10: INDEPENDENCIA | AB10: CHARCANI I,II,III | AC10: CHARCANI IV | AD10: CHARCANI V | AE10: CHARCANI VI | AF10: CHILINA TG | AG10: MOLLENDO 1, 2, 3 | AH10: CHILINA (SULZ 1,2) | AI10: SAN GABAN II | AJ10: PLATANAL | AK10: RECKA | AL10: RF ETEN TG1 | AM10: RF ETEN TG2 | AN10: CHAGLLA GP1 | AO10: CHAGLLA | AP10: LA VIRGEN | AQ10: CHIMAY | AR10: YANANGO | AS10: HUANCHOR | AT10: MARAÑON | AU10: STA TERESA | AV10: FENIX GT11 | AW10: FENIX GT12 | AX10: FENIX TV10 | AY10: YAUPI | AZ10: MALPASO | BA10: CAHUA | BB10: ARCATA | BC10: GALLITO CIEGO | BD10: CHEVES | BE10: SANTA ROSA 1 | BF10: SANTA ROSA 2 | BG10: HUANZA | BH10: MALACAS2 TG4 | BI10: MALACAS3 TG 5 | BJ10: MALACAS1 TG6 | BK10: RF ILO2 TG1 | BL10: RF ILO2 TG2 | BM10: RF ILO2 TG3 | BN10: YUNCAN | BO10: CHILCA1 TG1 | BP10: CHILCA1 TG2 | BQ10: CHILCA1 TG3 | BR10: CHILCA-TV | BS10: CHILCA2 TG41 | BT10: CHILCA2-TV | BU10: CTNEPI_TG41 | BV10: CTNEPI_TG42 | BW10: CTNEPI_TG43 | BX10: QUITARACSA | BY10: RF PTO MALDONADO | BZ10: RF PUCALLPA | CA10: PARIAC | CB10: HUINCO | CC10: MATUCANA | CD10: MOYOPAMPA | CE10: CALLAHUANCA | CF10: HUAMPANI | CG10: STA ROSA WEST TG7 | CH10: UTI_5 | CI10: UTI_6 | CJ10: VENTANILLA 3 | CK10: VENTANILLA 4 | CL10: VENTANILLA TV | CM10: STAROSA TG8 | CN10: PTO_BRVO TG1 | CO10: PTO_BRVO TG2 | CP10: PTO_BRVO TG3 | CQ10: PTO_BRVO TG4 | CR10: OLLEROS TG1 | CS10: OLLEROS TV | CT10: OROYA | CU10: PACHACHACA | CV10: MANTA I | CW10: CS YARUCAYA | CX10: SAN JUAN | CY10: MATARANI | CZ10: DUNA | DA10: CARHUAQUERO (CS) | DB10: ANASHIRONI | DC10: CARHUAQUERO4 | DD10: CAÑA BRAVA | DE10: SUNNY | DF10: SUNNY EXPANSION | DG10: TUPURI | DH10: RONCADOR | DI10: CANCHAYLLO | DJ10: RENOVANDESH1 | DK10: POTRERO | DL10: PIZARRAS | DM10: NIMPERIAL | DN10: YARUCAYA | DO10: MOQUEGUA-SOLAR | DP10: PANAMERICANA-SOLAR | DQ10: PQE-EOLICO-MARCONA | DR10: PQE-EOLICO-3-HERMANAS | DS10: TACNA-SOLAR | DT10: YANAPAMPA | DU10: CARHUAC | DV10: HUALLIN | DW10: PURMACANA | DX10: COENERGY | DY10: HUASAHUASI | DZ10: STACRUZ_1_2 | EA10: RUNATULLO_II | EB10: RUNATULLO_III | EC10: PQE-EOLICO-TALARA | ED10: PQE-EOLICO-CUPISNIQUE | EE10: INTIPAMPA | EF10: PUNTA LOMITAS-BL1 | EG10: PUNTA LOMITAS-BL2 | EH10: PUN LOMITAS_EXP-BL1 | EI10: PUN LOMITAS_EXP-BL2 | EJ10: EXPANSIÓN INTIPAMPA | EK10: 8AGOSTO | EL10: EL CARMEN | EM10: LA JOYA | EN10: ANGEL_I | EO10: ANGEL_II | EP10: ANGEL_III | EQ10: HUAMBOS | ER10: SAN MARTIN SOLAR | ES10: MAJES | ET10: RUBI | EU10: CH_HER1 | EV10: WAYRA-I | EW10: WAYRA EXTENSION | EX10: CLEMESI | EY10: HUAYCOLORO | EZ10: CALLAO | FA10: DONA_CATALINA | FB10: LAGRINGAV | FC10: REPARTICION | FD10: POECHOS2 | FE10: CHANCAY | FF10: RUCUY | FG10: CANA BRAVA | FH10: REFINERIA TALARA TV1 | FI10: REFINERÍA TALARA TV2 | FJ10: PARAMONGA | FK10: MAPLE | FL10: SAN_JACINTO | FM10: AGROLMOS | FN10: CASA GRANDE | FO10: MW | FQ10: CARPAPATA | FR10: CENTRALES ELOR | FS10: PIAS1 | FT10: ZANA | FU10: TABLAZO | FV10: TALLANCA | FW10: CURUMUY | FX10: POECHOS1 | FY10: MW
A11: 12/02/2026 | B11: 00:30 | C11: 198.3 | D11: 629.3 | E11: 214.5 | H11: 87.5 | I11: 239.1 | K11: 59.6 | L11: 150 | M11: 150.2 | N11: 149.8 | O11: 247.5 | P11: 206.1 | Q11: 108.3 | R11: 551 | S11: 10 | X11: 163.2 | Y11: 8.4 | Z11: 5.7 | AA11: 0 | AB11: 6.7 | AD11: 141.9 | AI11: 109.5 | AJ11: 218.1 | AN11: 6.5 | AO11: 455.7 | AP11: 73.6 | AQ11: 146.9 | AR11: 42.2 | AS11: 17.2 | AT11: 18.9 | AU11: 88 | AY11: 85.5 | AZ11: 0 | BA11: 43.9 | BB11: 4 | BC11: 32.9 | BD11: 128 | BG11: 0 | BJ11: 0 | BK11: 0 | BN11: 82.6 | BO11: 0 | BP11: 0 | BQ11: 0 | BS11: 39.5 | BT11: 27.9 | CA11: 2.4 | CB11: 82.4 | CC11: 127.7 | CD11: 61.1 | CE11: 75.9 | CF11: 29.3 | CJ11: 140.8 | CK11: 141.4 | CL11: 146.6 | CM11: 0 | CR11: 208 | CS11: 99.7 | CT11: 7 | CU11: 4.4 | CV11: 20 | CW11: 0 | CX11: 66.7 | CY11: 0 | CZ11: 0 | DA11: 0 | DB11: 20 | DC11: 9.9 | DD11: 5.5 | DE11: 0 | DG11: 2 | DH11: 2.3 | DI11: 4.9 | DJ11: 20 | DK11: 20 | DL11: 18.9 | DM11: 3.4 | DN11: 18.4 | DO11: 0 | DP11: 0 | DQ11: 19.9 | DR11: 49 | DS11: 0 | DT11: 3.4 | DU11: 3.5 | DV11: 2.9 | DW11: 0.4 | DX11: 0 | DY11: 19.8 | DZ11: 7.8 | EA11: 20 | EB11: 20.1 | EC11: 0 | ED11: 17.8 | EE11: 0 | EF11: 49.8 | EG11: 72 | EH11: 6.1 | EI11: 4.1 | EJ11: 0 | EK11: 17.2 | EL11: 6.5 | EM11: 3.7 | EN11: 20.4 | EO11: 20.4 | EP11: 20 | EQ11: 0.1 | ER11: 0 | ES11: 0 | ET11: 0 | EU11: 0.6 | EV11: 42.5 | EW11: 46 | EX11: 0 | EY11: 3.9 | EZ11: 2.3 | FA11: 2.4 | FB11: 0.8 | FC11: 0 | FD11: 8 | FE11: 20 | FF11: 20 | FG11: 9 | FH11: 27.5 | FI11: 34.3 | FJ11: 15.4 | FK11: 13.5 | FL11: 6.1 | FM11: 11.7 | FN11: 16.2 | FO11: 6951.8 | FQ11: 24.5 | FR11: 2.561 | FS11: 11.86 | FT11: 13.2 | FU11: 25.18735 | FV11: 18.94734 | FW11: 11.6 | FX11: 14.3 | FY11: 122.15569
A12: 12/02/2026 | B12: 01:00 | C12: 203.1 | D12: 634.2 | E12: 215.3 | H12: 90.1 | I12: 242 | K12: 61.7 | L12: 144.4 | M12: 142.6 | N12: 143.8 | O12: 242.6 | P12: 206.5 | Q12: 108.9 | R12: 557.9 | S12: 10.3 | X12: 166.8 | Y12: 7.2 | Z12: 5.8 | AA12: 0 | AB12: 6.7 | AD12: 142.3 | AI12: 110.5 | AJ12: 222.5 | AN12: 6.5 | AO12: 457.1 | AP12: 73.7 | AQ12: 151.7 | AR12: 42.2 | AS12: 18.4 | AT12: 18.9 | AU12: 90.4 | AY12: 85.5 | AZ12: 0 | BA12: 44.9 | BB12: 4 | BC12: 33.6 | BD12: 135.7 | BG12: 0 | BJ12: 0 | BK12: 0 | BN12: 84.4 | BO12: 0 | BP12: 0 | BQ12: 0 | BS12: 39.2 | BT12: 27.7 | CA12: 2.4 | CB12: 25.1 | CC12: 133.9 | CD12: 62.4 | CE12: 76.7 | CF12: 30 | CJ12: 140.5 | CK12: 141.6 | CL12: 147.2 | CM12: 0 | CR12: 207.7 | CS12: 99.5 | CT12: 7 | CU12: 4.4 | CV12: 20 | CW12: 0 | CX12: 57 | CY12: 0 | CZ12: 0 | DA12: 0 | DB12: 20.2 | DC12: 9.9 | DD12: 5.5 | DE12: 0 | DG12: 2 | DH12: 2.3 | DI12: 4.9 | DJ12: 20.2 | DK12: 20 | DL12: 18.9 | DM12: 3.4 | DN12: 18.4 | DO12: 0 | DP12: 0 | DQ12: 17.9 | DR12: 44 | DS12: 0 | DT12: 2.7 | DU12: 3.5 | DV12: 2.9 | DW12: 0.4 | DX12: 0 | DY12: 19.8 | DZ12: 7.8 | EA12: 20.2 | EB12: 20.2 | EC12: 0 | ED12: 13.1 | EE12: 0 | EF12: 29.9 | EG12: 59.6 | EH12: 4.1 | EI12: 2.8 | EJ12: 0 | EK12: 17.2 | EL12: 6.5 | EM12: 3.9 | EN12: 20.4 | EO12: 20.4 | EP12: 20 | EQ12: 0 | ER12: 0 | ES12: 0 | ET12: 0 | EU12: 0.6 | EV12: 28.6 | EW12: 26.7 | EX12: 0 | EY12: 3.9 | EZ12: 2.3 | FA12: 2.4 | FB12: 0.8 | FC12: 0 | FD12: 8 | FE12: 20 | FF12: 20 | FG12: 8.4 | FH12: 27.4 | FI12: 34.3 | FJ12: 15.2 | FK12: 13.5 | FL12: 8.8 | FM12: 11.7 | FN12: 8 | FO12: 6838.1 | FQ12: 24.5 | FR12: 2.559 | FS12: 11.86 | FT12: 13.2 | FU12: 25.21992 | FV12: 18.94792 | FW12: 11.6 | FX12: 14.4 | FY12: 122.28684
A13: 12/02/2026 | B13: 01:30 | C13: 198.3 | D13: 625.7 | E13: 212.2 | H13: 89.1 | I13: 239.4 | K13: 58.9 | L13: 122.8 | M13: 122.7 | N13: 123.1 | O13: 233.6 | P13: 206.7 | Q13: 108.7 | R13: 545.5 | S13: 10 | X13: 161.9 | Y13: 7.3 | Z13: 5.7 | AA13: 0 | AB13: 6.7 | AD13: 141.4 | AI13: 109.6 | AJ13: 219.5 | AN13: 6.5 | AO13: 456.9 | AP13: 73.9 | AQ13: 150 | AR13: 42.1 | AS13: 18.6 | AT13: 18.9 | AU13: 89.5 | AY13: 85.5 | AZ13: 0 | BA13: 43.9 | BB13: 4 | BC13: 33.4 | BD13: 103.6 | BG13: 0 | BJ13: 0 | BK13: 0 | BN13: 83.4 | BO13: 0 | BP13: 0 | BQ13: 0 | BS13: 39 | BT13: 27.9 | CA13: 2.4 | CB13: 22.5 | CC13: 126.2 | CD13: 61.3 | CE13: 76 | CF13: 29.5 | CJ13: 140.9 | CK13: 141.6 | CL13: 147.2 | CM13: 0 | CR13: 208.3 | CS13: 99.7 | CT13: 7 | CU13: 4.3 | CV13: 20 | CW13: 0 | CX13: 58.1 | CY13: 0 | CZ13: 0 | DA13: 0 | DB13: 20.1 | DC13: 10 | DD13: 5.2 | DE13: 0 | DG13: 2 | DH13: 2 | DI13: 4.9 | DJ13: 20 | DK13: 20 | DL13: 18.8 | DM13: 3.4 | DN13: 18.4 | DO13: 0 | DP13: 0 | DQ13: 17.8 | DR13: 47.1 | DS13: 0 | DT13: 2.4 | DU13: 3.4 | DV13: 2.9 | DW13: 0.4 | DX13: 0 | DY13: 19.8 | DZ13: 7.7 | EA13: 20.1 | EB13: 20.2 | EC13: 0 | ED13: 9.5 | EE13: 0 | EF13: 31.6 | EG13: 52.9 | EH13: 2 | EI13: 1.6 | EJ13: 0 | EK13: 17.2 | EL13: 6.5 | EM13: 3.9 | EN13: 20.4 | EO13: 20.4 | EP13: 20 | EQ13: 0 | ER13: 0 | ES13: 0 | ET13: 0 | EU13: 0.6 | EV13: 21.8 | EW13: 17.3 | EX13: 0 | EY13: 3.9 | EZ13: 2.3 | FA13: 2.4 | FB13: 0.8 | FC13: 0 | FD13: 8 | FE13: 19.9 | FF13: 19.9 | FG13: 8.5 | FH13: 27.7 | FI13: 34.6 | FJ13: 14.7 | FK13: 13.5 | FL13: 8.9 | FM13: 11.7 | FN13: 9.8 | FO13: 6649.8 | FQ13: 24.5 | FR13: 2.558 | FS13: 11.86 | FT13: 13.2 | FU13: 25.30053 | FV13: 18.9485 | FW13: 11.6 | FX13: 14.3 | FY13: 122.26703
A14: 12/02/2026 | B14: 02:00 | C14: 201.3 | D14: 636.2 | E14: 216.1 | H14: 91.2 | I14: 242.8 | K14: 61.3 | L14: 122.3 | M14: 122.7 | N14: 122.6 | O14: 218.8 | P14: 206.1 | Q14: 108.1 | R14: 559 | S14: 10.2 | X14: 164.1 | Y14: 7.7 | Z14: 5.5 | AA14: 0 | AB14: 6.7 | AD14: 142.6 | AI14: 110.4 | AJ14: 187.3 | AN14: 6.5 | AO14: 456.6 | AP14: 74.4 | AQ14: 151 | AR14: 42.3 | AS14: 18.4 | AT14: 18.9 | AU14: 95.1 | AY14: 85.5 | AZ14: 0 | BA14: 44.6 | BB14: 4 | BC14: 33.7 | BD14: 125.4 | BG14: 0 | BJ14: 0 | BK14: 0 | BN14: 84.5 | BO14: 0 | BP14: 0 | BQ14: 0 | BS14: 38.7 | BT14: 27.9 | CA14: 2.4 | CB14: 25.3 | CC14: 131.7 | CD14: 62.5 | CE14: 76.7 | CF14: 30.1 | CJ14: 140.3 | CK14: 141.2 | CL14: 146.6 | CM14: 0 | CR14: 208.2 | CS14: 99.8 | CT14: 7 | CU14: 4.4 | CV14: 20 | CW14: 0 | CX14: 66.4 | CY14: 0 | CZ14: 0 | DA14: 0 | DB14: 20.2 | DC14: 9.9 | DD14: 5.2 | DE14: 0 | DG14: 2 | DH14: 2 | DI14: 4.9 | DJ14: 20.2 | DK14: 20 | DL14: 18.8 | DM14: 3.4 | DN14: 18.4 | DO14: 0 | DP14: 0 | DQ14: 18.2 | DR14: 44.7 | DS14: 0 | DT14: 2.4 | DU14: 3.2 | DV14: 2.9 | DW14: 0.4 | DX14: 0 | DY14: 19.8 | DZ14: 7.8 | EA14: 20.1 | EB14: 20.2 | EC14: 0 | ED14: 9.2 | EE14: 0 | EF14: 23.8 | EG14: 49.2 | EH14: 2.7 | EI14: 2.4 | EJ14: 0 | EK14: 17.2 | EL14: 6.5 | EM14: 3.9 | EN14: 20.4 | EO14: 20.4 | EP14: 20 | EQ14: 0 | ER14: 0 | ES14: 0 | ET14: 0 | EU14: 0.6 | EV14: 19.1 | EW14: 13.1 | EX14: 0 | EY14: 3.9 | EZ14: 2.3 | FA14: 2.4 | FB14: 0.8 | FC14: 0 | FD14: 7.9 | FE14: 20 | FF14: 20 | FG14: 8.7 | FH14: 27.8 | FI14: 34.6 | FJ14: 14.9 | FK14: 13.5 | FL14: 8.9 | FM14: 11.6 | FN14: 10 | FO14: 6673.6 | FQ14: 24.5 | FR14: 2.558 | FS14: 11.86 | FT14: 13.2 | FU14: 25.29746 | FV14: 18.94877 | FW14: 11.7 | FX14: 14.3 | FY14: 122.36423
A15: 12/02/2026 | B15: 02:30 | C15: 205.8 | D15: 639.4 | E15: 216.3 | H15: 90.4 | I15: 243.6 | K15: 60.7 | L15: 114.8 | M15: 114.9 | N15: 113.1 | O15: 209 | P15: 203.5 | Q15: 108.1 | R15: 561.5 | S15: 10.3 | X15: 171.7 | Y15: 8 | Z15: 5.4 | AA15: 0 | AB15: 6.7 | AD15: 142.4 | AI15: 110.4 | AJ15: 221.4 | AN15: 6.5 | AO15: 458.8 | AP15: 75.3 | AQ15: 152.5 | AR15: 42.3 | AS15: 18.4 | AT15: 18.9 | AU15: 93.7 | AY15: 85.5 | AZ15: 0 | BA15: 46.1 | BB15: 4 | BC15: 35.2 | BD15: 66.9 | BG15: 0 | BJ15: 0 | BK15: 0 | BN15: 84.8 | BO15: 0 | BP15: 0 | BQ15: 0 | BS15: 38.8 | BT15: 27.8 | CA15: 2.4 | CB15: 33.3 | CC15: 126 | CD15: 63 | CE15: 74.3 | CF15: 30.3 | CJ15: 140.2 | CK15: 141.1 | CL15: 146.5 | CM15: 0 | CR15: 208 | CS15: 99.5 | CT15: 7 | CU15: 4.4 | CV15: 20 | CW15: 0 | CX15: 45.9 | CY15: 0 | CZ15: 0 | DA15: 0 | DB15: 20.4 | DC15: 9.9 | DD15: 5.5 | DE15: 0 | DG15: 2 | DH15: 2 | DI15: 4.9 | DJ15: 20.4 | DK15: 20 | DL15: 18.8 | DM15: 3.4 | DN15: 18.4 | DO15: 0 | DP15: 0 | DQ15: 16.4 | DR15: 49.4 | DS15: 0 | DT15: 3.2 | DU15: 3.2 | DV15: 2.8 | DW15: 0.4 | DX15: 0 | DY15: 19.8 | DZ15: 7.8 | EA15: 19.8 | EB15: 20.2 | EC15: 0 | ED15: 12.6 | EE15: 0 | EF15: 29.4 | EG15: 37.7 | EH15: 2.9 | EI15: 3.9 | EJ15: 0 | EK15: 17.2 | EL15: 6.6 | EM15: 3.9 | EN15: 20.4 | EO15: 20.4 | EP15: 20 | EQ15: 0 | ER15: 0 | ES15: 0 | ET15: 0 | EU15: 0.6 | EV15: 5.9 | EW15: 6.3 | EX15: 0 | EY15: 3.9 | EZ15: 2.3 | FA15: 2.4 | FB15: 0.8 | FC15: 0 | FD15: 8 | FE15: 20 | FF15: 20 | FG15: 9.1 | FH15: 27.8 | FI15: 34.7 | FJ15: 15.2 | FK15: 13.5 | FL15: 8.9 | FM15: 11.6 | FN15: 11.6 | FO15: 6601.1 | FQ15: 24.5 | FR15: 2.559 | FS15: 11.86 | FT15: 13.2 | FU15: 25.2635 | FV15: 18.94844 | FW15: 11.6 | FX15: 14.3 | FY15: 122.23094
A16: 12/02/2026 | B16: 03:00 | C16: 202.4 | D16: 634.6 | E16: 215.5 | H16: 90.3 | I16: 242.5 | K16: 60.7 | L16: 142.3 | M16: 142.5 | N16: 142.5 | O16: 241.9 | P16: 204.3 | Q16: 108.8 | R16: 445.5 | S16: 10.2 | X16: 167.4 | Y16: 7.6 | Z16: 5.3 | AA16: 0 | AB16: 6.7 | AD16: 142.3 | AI16: 110.5 | AJ16: 222.6 | AN16: 6.5 | AO16: 459.4 | AP16: 76.1 | AQ16: 151.6 | AR16: 42.3 | AS16: 18.3 | AT16: 18.9 | AU16: 92.9 | AY16: 85.5 | AZ16: 0 | BA16: 45.2 | BB16: 4 | BC16: 34.3 | BD16: 45.9 | BG16: 0 | BJ16: 0 | BK16: 0 | BN16: 84.5 | BO16: 0 | BP16: 0 | BQ16: 0 | BS16: 39.1 | BT16: 27.9 | CA16: 2.4 | CB16: 51.3 | CC16: 134.5 | CD16: 62.5 | CE16: 74.2 | CF16: 30.2 | CJ16: 141.4 | CK16: 141.8 | CL16: 146.5 | CM16: 0 | CR16: 208 | CS16: 99.7 | CT16: 7 | CU16: 4.4 | CV16: 20.1 | CW16: 0 | CX16: 33.7 | CY16: 0 | CZ16: 0 | DA16: 0 | DB16: 20.3 | DC16: 9.9 | DD16: 5.4 | DE16: 0 | DG16: 2 | DH16: 2.1 | DI16: 4.9 | DJ16: 20.4 | DK16: 20 | DL16: 18.8 | DM16: 3.4 | DN16: 18.4 | DO16: 0 | DP16: 0 | DQ16: 11.4 | DR16: 37.3 | DS16: 0 | DT16: 3.5 | DU16: 3.2 | DV16: 2.8 | DW16: 0.4 | DX16: 0 | DY16: 19.8 | DZ16: 7.8 | EA16: 20 | EB16: 20.2 | EC16: 0 | ED16: 16.1 | EE16: 0 | EF16: 21 | EG16: 49.5 | EH16: 3.1 | EI16: 3.5 | EJ16: 0 | EK16: 17.2 | EL16: 6.6 | EM16: 3.9 | EN16: 20.4 | EO16: 20.4 | EP16: 20 | EQ16: 0 | ER16: 0 | ES16: 0 | ET16: 0 | EU16: 0.6 | EV16: 4.4 | EW16: 9.3 | EX16: 0 | EY16: 3.9 | EZ16: 2.3 | FA16: 2.4 | FB16: 0.8 | FC16: 0 | FD16: 7.9 | FE16: 20 | FF16: 20 | FG16: 9 | FH16: 27.8 | FI16: 34.7 | FJ16: 15.2 | FK16: 13.6 | FL16: 8.9 | FM16: 11.6 | FN16: 11.3 | FO16: 6573.9 | FQ16: 24.5 | FR16: 2.56 | FS16: 11.86 | FT16: 13.2 | FU16: 25.21771 | FV16: 18.94897 | FW16: 11.6 | FX16: 14.3 | FY16: 122.18668
A17: 12/02/2026 | B17: 03:30 | C17: 201.1 | D17: 636.6 | E17: 216.4 | H17: 90.2 | I17: 241.6 | K17: 60.7 | L17: 143.7 | M17: 144.1 | N17: 143.9 | O17: 239.5 | P17: 203.5 | Q17: 108.9 | R17: 449.1 | S17: 10.3 | X17: 166.2 | Y17: 7.5 | Z17: 5.3 | AA17: 0 | AB17: 6.7 | AD17: 142.5 | AI17: 110.3 | AJ17: 222.1 | AN17: 6.5 | AO17: 457.5 | AP17: 76.5 | AQ17: 151.3 | AR17: 42.3 | AS17: 18.4 | AT17: 18.9 | AU17: 89.2 | AY17: 85.5 | AZ17: 0 | BA17: 45.1 | BB17: 4 | BC17: 34 | BD17: 72 | BG17: 0 | BJ17: 0 | BK17: 0 | BN17: 84.4 | BO17: 0 | BP17: 0 | BQ17: 0 | BS17: 38.8 | BT17: 28 | CA17: 2.4 | CB17: 68.5 | CC17: 110.2 | CD17: 66.1 | CE17: 74.8 | CF17: 30.1 | CJ17: 140.9 | CK17: 141.7 | CL17: 146.6 | CM17: 0 | CR17: 208.6 | CS17: 100.5 | CT17: 7 | CU17: 4.3 | CV17: 20 | CW17: 0 | CX17: 37.5 | CY17: 0 | CZ17: 0 | DA17: 0 | DB17: 20.2 | DC17: 10 | DD17: 5.5 | DE17: 0 | DG17: 2 | DH17: 2.1 | DI17: 4.9 | DJ17: 20.3 | DK17: 20 | DL17: 18.8 | DM17: 3.4 | DN17: 18.4 | DO17: 0 | DP17: 0 | DQ17: 9.1 | DR17: 27.8 | DS17: 0 | DT17: 3.4 | DU17: 3.2 | DV17: 2.8 | DW17: 0.4 | DX17: 0 | DY17: 19.8 | DZ17: 7.8 | EA17: 20 | EB17: 20.2 | EC17: 0 | ED17: 11.1 | EE17: 0 | EF17: 19.5 | EG17: 41 | EH17: 1.4 | EI17: 0.8 | EJ17: 0 | EK17: 17.3 | EL17: 6.6 | EM17: 3.9 | EN17: 20.4 | EO17: 20.4 | EP17: 20 | EQ17: 0 | ER17: 0 | ES17: 0 | ET17: 0 | EU17: 0.6 | EV17: 0.2 | EW17: 0.3 | EX17: 0 | EY17: 3.9 | EZ17: 2.3 | FA17: 2.4 | FB17: 0.8 | FC17: 0 | FD17: 7.9 | FE17: 20 | FF17: 20 | FG17: 8.9 | FH17: 27.9 | FI17: 34.8 | FJ17: 15.1 | FK17: 13.5 | FL17: 9 | FM17: 11.6 | FN17: 11.2 | FO17: 6554.7 | FQ17: 24.5 | FR17: 2.562 | FS17: 11.51 | FT17: 13.2 | FU17: 25.20676 | FV17: 18.94911 | FW17: 11.6 | FX17: 14.3 | FY17: 121.82787
A18: 12/02/2026 | B18: 04:00 | C18: 203.6 | D18: 638.6 | E18: 216.4 | H18: 90.6 | I18: 242.1 | K18: 62.1 | L18: 127.3 | M18: 126.7 | N18: 127.9 | O18: 214.2 | P18: 208.1 | Q18: 109 | R18: 488.3 | S18: 10.3 | X18: 166.8 | Y18: 7.6 | Z18: 5.4 | AA18: 0 | AB18: 6.7 | AD18: 143.1 | AI18: 110.5 | AJ18: 175.2 | AN18: 6.5 | AO18: 460.4 | AP18: 75.9 | AQ18: 151 | AR18: 42.2 | AS18: 18.4 | AT18: 18.9 | AU18: 94.4 | AY18: 85.5 | AZ18: 0 | BA18: 44.9 | BB18: 4 | BC18: 34.2 | BD18: 151.8 | BG18: 0 | BJ18: 0 | BK18: 0 | BN18: 84.7 | BO18: 0 | BP18: 0 | BQ18: 0 | BS18: 39.2 | BT18: 28 | CA18: 2.4 | CB18: 69.7 | CC18: 119.4 | CD18: 66.4 | CE18: 74.7 | CF18: 30.2 | CJ18: 113.3 | CK18: 113.4 | CL18: 133 | CM18: 0 | CR18: 208.5 | CS18: 100.4 | CT18: 7 | CU18: 4.4 | CV18: 20 | CW18: 0 | CX18: 38.8 | CY18: 0 | CZ18: 0 | DA18: 0 | DB18: 20.3 | DC18: 9.9 | DD18: 5.3 | DE18: 0 | DG18: 2 | DH18: 2.1 | DI18: 4.9 | DJ18: 20.3 | DK18: 20 | DL18: 18.9 | DM18: 3.4 | DN18: 18.4 | DO18: 0 | DP18: 0 | DQ18: 10.9 | DR18: 25.5 | DS18: 0 | DT18: 3.4 | DU18: 3.2 | DV18: 2.8 | DW18: 0.4 | DX18: 0 | DY18: 19.8 | DZ18: 8.2 | EA18: 20 | EB18: 20.3 | EC18: 0 | ED18: 9.1 | EE18: 0 | EF18: 15.5 | EG18: 25.6 | EH18: 2 | EI18: 1.8 | EJ18: 0 | EK18: 17.9 | EL18: 6.7 | EM18: 3.9 | EN18: 20.4 | EO18: 20.4 | EP18: 20 | EQ18: 0.5 | ER18: 0 | ES18: 0 | ET18: 0 | EU18: 0.6 | EV18: 0.1 | EW18: 0 | EX18: 0 | EY18: 3.9 | EZ18: 2.3 | FA18: 2.4 | FB18: 0.8 | FC18: 0 | FD18: 7.9 | FE18: 20 | FF18: 20 | FG18: 8.9 | FH18: 27.8 | FI18: 34.7 | FJ18: 15.3 | FK18: 13.6 | FL18: 8 | FM18: 11.6 | FN18: 11.4 | FO18: 6495.2 | FQ18: 24.5 | FR18: 2.56 | FS18: 11.51 | FT18: 13.2 | FU18: 25.15103 | FV18: 18.94901 | FW18: 11.5 | FX18: 14.3 | FY18: 121.67004
A19: 12/02/2026 | B19: 04:30 | C19: 199.7 | D19: 629.9 | E19: 214.5 | H19: 89.7 | I19: 241.4 | K19: 59.7 | L19: 133 | M19: 133 | N19: 133.6 | O19: 246.6 | P19: 206.5 | Q19: 108.9 | R19: 549.7 | S19: 10.2 | X19: 165.8 | Y19: 7.3 | Z19: 5.2 | AA19: 0 | AB19: 6.7 | AD19: 141.6 | AI19: 110.3 | AJ19: 222 | AN19: 6.5 | AO19: 460.5 | AP19: 75.5 | AQ19: 150.4 | AR19: 42.3 | AS19: 18.4 | AT19: 18.9 | AU19: 90.8 | AY19: 85.5 | AZ19: 0 | BA19: 44.3 | BB19: 4 | BC19: 32.3 | BD19: 80.2 | BG19: 0 | BJ19: 0 | BK19: 0 | BN19: 83.9 | BO19: 0 | BP19: 0 | BQ19: 0 | BS19: 39.1 | BT19: 27.9 | CA19: 2.4 | CB19: 25 | CC19: 118.8 | CD19: 65.7 | CE19: 74.7 | CF19: 30 | CJ19: 102.8 | CK19: 102.9 | CL19: 122.2 | CM19: 0 | CR19: 208.8 | CS19: 100.4 | CT19: 7 | CU19: 4.4 | CV19: 20 | CW19: 0 | CX19: 31.2 | CY19: 0 | CZ19: 0 | DA19: 0 | DB19: 20.3 | DC19: 10 | DD19: 5.5 | DE19: 0 | DG19: 2 | DH19: 2.1 | DI19: 4.9 | DJ19: 20.2 | DK19: 20 | DL19: 19 | DM19: 3.4 | DN19: 18.4 | DO19: 0 | DP19: 0 | DQ19: 7.4 | DR19: 15.7 | DS19: 0 | DT19: 3.4 | DU19: 3.2 | DV19: 2.7 | DW19: 0.4 | DX19: 0 | DY19: 19.8 | DZ19: 8.4 | EA19: 20 | EB19: 20.2 | EC19: 0.4 | ED19: 8.2 | EE19: 0 | EF19: 12.5 | EG19: 18.3 | EH19: 1 | EI19: 0.3 | EJ19: 0 | EK19: 20.4 | EL19: 7.9 | EM19: 3.9 | EN19: 20.4 | EO19: 20.4 | EP19: 20 | EQ19: 0.5 | ER19: 0 | ES19: 0 | ET19: 0 | EU19: 0.6 | EV19: 0 | EW19: 0 | EX19: 0 | EY19: 3.9 | EZ19: 2.3 | FA19: 2.4 | FB19: 0.8 | FC19: 0 | FD19: 8 | FE19: 20 | FF19: 20 | FG19: 8.8 | FH19: 28.2 | FI19: 35 | FJ19: 15.2 | FK19: 13.5 | FL19: 8.7 | FM19: 11.6 | FN19: 11.2 | FO19: 6443.5 | FQ19: 24.4 | FR19: 2.558 | FS19: 10.76 | FT19: 13.2 | FU19: 25.2259 | FV19: 18.94888 | FW19: 11.6 | FX19: 14.3 | FY19: 120.99278
A20: 12/02/2026 | B20: 05:00 | C20: 202.9 | D20: 632.7 | E20: 215 | H20: 90.1 | I20: 241.3 | K20: 59.8 | L20: 149.1 | M20: 149.3 | N20: 149.2 | O20: 257.4 | P20: 205.2 | Q20: 108.9 | R20: 557.2 | S20: 10.2 | X20: 167.3 | Y20: 7.4 | Z20: 5.3 | AA20: 0 | AB20: 6.7 | AD20: 142.1 | AI20: 110.4 | AJ20: 223 | AN20: 6.5 | AO20: 459.3 | AP20: 76.1 | AQ20: 151.2 | AR20: 42.2 | AS20: 18.4 | AT20: 18.9 | AU20: 91.3 | AY20: 85.5 | AZ20: 0 | BA20: 45.2 | BB20: 4 | BC20: 32.4 | BD20: 94.6 | BG20: 0 | BJ20: 0 | BK20: 0 | BN20: 84.5 | BO20: 0 | BP20: 0 | BQ20: 0 | BS20: 38.8 | BT20: 28.1 | CA20: 2.4 | CB20: 67.2 | CC20: 119.6 | CD20: 66 | CE20: 74.7 | CF20: 30 | CJ20: 120.5 | CK20: 120.5 | CL20: 125.5 | CM20: 0 | CR20: 208.9 | CS20: 100.5 | CT20: 7 | CU20: 4.3 | CV20: 20 | CW20: 0 | CX20: 15.6 | CY20: 0 | CZ20: 0 | DA20: 0 | DB20: 20.2 | DC20: 9.9 | DD20: 5.5 | DE20: 0 | DG20: 2 | DH20: 2.1 | DI20: 4.9 | DJ20: 20.3 | DK20: 20 | DL20: 18.8 | DM20: 3.4 | DN20: 18.4 | DO20: 0 | DP20: 0 | DQ20: 5.1 | DR20: 15.3 | DS20: 0 | DT20: 3.4 | DU20: 3.3 | DV20: 2.7 | DW20: 0.4 | DX20: 0 | DY20: 19.8 | DZ20: 8.3 | EA20: 20 | EB20: 20.2 | EC20: 0.2 | ED20: 3.6 | EE20: 0 | EF20: 8.8 | EG20: 26.5 | EH20: 0.6 | EI20: 0.3 | EJ20: 0 | EK20: 21 | EL20: 8 | EM20: 3.9 | EN20: 20.4 | EO20: 20.4 | EP20: 20 | EQ20: 0 | ER20: 0 | ES20: 0 | ET20: 0 | EU20: 0.6 | EV20: 0 | EW20: 0 | EX20: 0 | EY20: 3.9 | EZ20: 2.3 | FA20: 2.4 | FB20: 0.8 | FC20: 0 | FD20: 8 | FE20: 20.2 | FF20: 20.2 | FG20: 8.5 | FH20: 27.7 | FI20: 34.7 | FJ20: 15.4 | FK20: 13.5 | FL20: 7.8 | FM20: 11.7 | FN20: 11.1 | FO20: 6596.7 | FQ20: 24.5 | FR20: 2.558 | FS20: 11.14 | FT20: 13.2 | FU20: 25.15595 | FV20: 18.9484 | FW20: 11.4 | FX20: 14.4 | FY20: 121.30235
A21: 12/02/2026 | B21: 05:30 | C21: 201.9 | D21: 633.8 | E21: 215.2 | H21: 90.3 | I21: 240.8 | K21: 59.7 | L21: 164.1 | M21: 164.4 | N21: 164.7 | O21: 263.9 | P21: 204.3 | Q21: 108.7 | R21: 558.7 | S21: 10.2 | X21: 164.1 | Y21: 7.4 | Z21: 5.4 | AA21: 0 | AB21: 6.7 | AD21: 142.3 | AI21: 110.4 | AJ21: 221.5 | AN21: 6.5 | AO21: 455.7 | AP21: 76.2 | AQ21: 151.2 | AR21: 42.2 | AS21: 18.4 | AT21: 18.9 | AU21: 88.4 | AY21: 85.5 | AZ21: 0 | BA21: 44.7 | BB21: 4 | BC21: 32.4 | BD21: 100 | BG21: 0 | BJ21: 0 | BK21: 0 | BN21: 84.4 | BO21: 0 | BP21: 0 | BQ21: 0 | BS21: 39 | BT21: 28 | CA21: 2.4 | CB21: 23.9 | CC21: 119.9 | CD21: 66 | CE21: 74.8 | CF21: 30.1 | CJ21: 140.9 | CK21: 141.5 | CL21: 145.8 | CM21: 0 | CR21: 209.2 | CS21: 100.7 | CT21: 7 | CU21: 4.3 | CV21: 20 | CW21: 0 | CX21: 6.1 | CY21: 0 | CZ21: 0 | DA21: 0 | DB21: 20.3 | DC21: 10 | DD21: 5.5 | DE21: 0 | DG21: 2 | DH21: 2.5 | DI21: 4.9 | DJ21: 20.2 | DK21: 20 | DL21: 18.8 | DM21: 3.4 | DN21: 18.4 | DO21: 0 | DP21: 0 | DQ21: 4 | DR21: 9.1 | DS21: 0 | DT21: 3.4 | DU21: 3.2 | DV21: 2.7 | DW21: 0.4 | DX21: 0 | DY21: 19.8 | DZ21: 8.3 | EA21: 20 | EB21: 20.2 | EC21: 0.3 | ED21: 4.8 | EE21: 0 | EF21: 10.3 | EG21: 27 | EH21: 0.4 | EI21: 0 | EJ21: 0 | EK21: 20.9 | EL21: 7.9 | EM21: 4.2 | EN21: 20.4 | EO21: 20.4 | EP21: 20 | EQ21: 0 | ER21: 0 | ES21: 0 | ET21: 0 | EU21: 0.6 | EV21: 0 | EW21: 0 | EX21: 0 | EY21: 3.9 | EZ21: 2.3 | FA21: 2.4 | FB21: 0.8 | FC21: 0 | FD21: 8.1 | FE21: 20 | FF21: 20 | FG21: 9.1 | FH21: 27.8 | FI21: 34.7 | FJ21: 16 | FK21: 13.5 | FL21: 7.3 | FM21: 11.6 | FN21: 11.2 | FO21: 6649.6 | FQ21: 24.5 | FR21: 2.556 | FS21: 10.28 | FT21: 13.2 | FU21: 25.15002 | FV21: 18.94854 | FW21: 11.5 | FX21: 14.4 | FY21: 120.53456
A22: 12/02/2026 | B22: 06:00 | C22: 201.8 | D22: 635.1 | E22: 216.4 | H22: 90.2 | I22: 242.7 | K22: 60.2 | L22: 149.3 | M22: 151.1 | N22: 149.8 | O22: 255.5 | P22: 205.2 | Q22: 108.6 | R22: 551.5 | S22: 10.3 | X22: 166.4 | Y22: 7.5 | Z22: 5.5 | AA22: 0 | AB22: 6.7 | AD22: 141.9 | AI22: 110.3 | AJ22: 213.6 | AN22: 6.5 | AO22: 457.7 | AP22: 75.8 | AQ22: 151.5 | AR22: 42.4 | AS22: 18.4 | AT22: 18.9 | AU22: 88.6 | AY22: 85.5 | AZ22: 0 | BA22: 45.7 | BB22: 4 | BC22: 33.4 | BD22: 111 | BG22: 0 | BJ22: 0 | BK22: 0 | BN22: 84.6 | BO22: 0 | BP22: 0 | BQ22: 0 | BS22: 39 | BT22: 28.1 | CA22: 2.4 | CB22: 21.5 | CC22: 119.8 | CD22: 66.3 | CE22: 74.7 | CF22: 30.3 | CJ22: 141.5 | CK22: 142.2 | CL22: 146.9 | CM22: 0 | CR22: 209.4 | CS22: 100.7 | CT22: 7 | CU22: 4.4 | CV22: 20 | CW22: 0 | CX22: 3.7 | CY22: 0 | CZ22: 0 | DA22: 0 | DB22: 20.3 | DC22: 9.9 | DD22: 5.4 | DE22: 2.9 | DG22: 2 | DH22: 2.5 | DI22: 4.8 | DJ22: 20.5 | DK22: 20 | DL22: 18.8 | DM22: 3.4 | DN22: 18.4 | DO22: 0.5 | DP22: 0.5 | DQ22: 2.3 | DR22: 6.8 | DS22: 0.3 | DT22: 3.4 | DU22: 3.1 | DV22: 2.7 | DW22: 0.4 | DX22: 0 | DY22: 19.8 | DZ22: 8.2 | EA22: 20 | EB22: 20.2 | EC22: 1.3 | ED22: 6.1 | EE22: 0 | EF22: 9 | EG22: 20.5 | EH22: 0.8 | EI22: 0 | EJ22: 0 | EK22: 20.9 | EL22: 7.9 | EM22: 2.9 | EN22: 20.4 | EO22: 20.4 | EP22: 20 | EQ22: 0 | ER22: 2.9 | ES22: 0 | ET22: 2.6 | EU22: 0.6 | EV22: 0 | EW22: 0 | EX22: 2.5 | EY22: 3.9 | EZ22: 2.3 | FA22: 2.4 | FB22: 0.8 | FC22: 0 | FD22: 8 | FE22: 20 | FF22: 20 | FG22: 9.1 | FH22: 27.7 | FI22: 34.7 | FJ22: 16.1 | FK22: 13.5 | FL22: 9.1 | FM22: 11.6 | FN22: 11.2 | FO22: 6607.8 | FQ22: 24.5 | FR22: 2.557 | FS22: 9.55 | FT22: 13.2 | FU22: 25.24646 | FV22: 18.94841 | FW22: 11.5 | FX22: 14.4 | FY22: 119.90187
... A58: 13/02/2026 | B58: 00:00 | C58: 202.3 | D58: 633.7 | E58: 213.9 | H58: 90.2 | I58: 240.9 | K58: 0 | L58: 174.6 | M58: 174.6 | N58: 174.7 | O58: 272.8 | P58: 204.1 | Q58: 108.3 | R58: 553.4 | S58: 10.2 | X58: 165.7 | Y58: 8.1 | Z58: 6.1 | AA58: 0 | AB58: 6.7 | AD58: 142.4 | AI58: 110.1 | AJ58: 223 | AN58: 6.5 | AO58: 457.6 | AP58: 71 | AQ58: 150.9 | AR58: 42.3 | AS58: 18.4 | AT58: 18.9 | AU58: 89.6 | AY58: 104.5 | AZ58: 42.9 | BA58: 45.1 | BB58: 4 | BC58: 27.4 | BD58: 143.9 | BG58: 0 | BJ58: 0 | BK58: 0 | BN58: 127.1 | BO58: 0 | BP58: 0 | BQ58: 0 | BS58: 44.6 | BT58: 28.8 | CA58: 2.4 | CB58: 67.3 | CC58: 112.9 | CD58: 62.5 | CE58: 75.9 | CF58: 29.8 | CJ58: 140 | CK58: 140.7 | CL58: 146.7 | CM58: 0 | CR58: 207.2 | CS58: 99.2 | CT58: 7 | CU58: 4.3 | CV58: 20 | CW58: 0 | CX58: 54.9 | CY58: 0 | CZ58: 0 | DA58: 0 | DB58: 20.1 | DC58: 9.9 | DD58: 5.5 | DE58: 0 | DG58: 0 | DH58: 3.1 | DI58: 4.8 | DJ58: 20 | DK58: 0 | DL58: 18.7 | DM58: 3.4 | DN58: 18.4 | DO58: 0 | DP58: 0 | DQ58: 8.4 | DR58: 17.3 | DS58: 0 | DT58: 3.6 | DU58: 6.1 | DV58: 3 | DW58: 0.4 | DX58: 0 | DY58: 19.5 | DZ58: 7.6 | EA58: 19.4 | EB58: 20.1 | EC58: 1.7 | ED58: 17.9 | EE58: 0 | EF58: 21.3 | EG58: 44.6 | EH58: 1.7 | EI58: 0.4 | EJ58: 0 | EK58: 20.4 | EL58: 7.8 | EM58: 6.3 | EN58: 20.4 | EO58: 20.4 | EP58: 20 | EQ58: 0 | ER58: 0 | ES58: 0 | ET58: 0 | EU58: 0.6 | EV58: 9.4 | EW58: 6 | EX58: 0 | EY58: 4.1 | EZ58: 2.4 | FA58: 2.4 | FB58: 0.8 | FC58: 0 | FD58: 8 | FE58: 20 | FF58: 20 | FG58: 9.1 | FH58: 27.5 | FI58: 34.4 | FJ58: 17.1 | FK58: 17.2 | FL58: 8.7 | FM58: 11.3 | FN58: 20 | FO58: 6921.3 | FQ58: 22.4 | FR58: 6.297 | FS58: 11.72 | FT58: 13.2 | FU58: 24.97974 | FV58: 18.94046 | FW58: 11.2 | FX58: 14.2 | FY58: 122.9372
A59: EJEC | C59: 4845.15 | D59: 15245.95 | E59: 5175.1 | F59: 0 | G59: 0 | H59: 2156.4 | I59: 5792.5 | J59: 0 | K59: 392 | L59: 3568.65 | M59: 3578.1 | N59: 3574.35 | O59: 5940.45 | P59: 4886.45 | Q59: 2591.95 | R59: 13227.9 | S59: 244.75 | T59: 0 | U59: 0 | V59: 0 | W59: 0 | X59: 3979.95 | Y59: 190.5 | Z59: 134.05 | AA59: 190.5 | AB59: 160.7 | AC59: 0 | AD59: 3420.1 | AE59: 0 | AF59: 0 | AG59: 0 | AH59: 0 | AI59: 2645.3 | AJ59: 4995.15 | AK59: 0 | AL59: 0 | AM59: 0 | AN59: 156 | AO59: 10999.6 | AP59: 1553.5 | AQ59: 3622.2 | AR59: 792.85 | AS59: 441.75 | AT59: 453.6 | AU59: 2174.55 | AV59: 0 | AW59: 0 | AX59: 0 | AY59: 2291.85 | AZ59: 613.15 | BA59: 980 | BB59: 96 | BC59: 807.45 | BD59: 3081.5 | BE59: 0 | BF59: 0 | BG59: 689.95 | BH59: 0 | BI59: 0 | BJ59: 702.75 | BK59: 359.6 | BL59: 0 | BM59: 0 | BN59: 2228.15 | BO59: 878.5 | BP59: 1088.4 | BQ59: 2508.45 | BR59: 0 | BS59: 1455.3 | BT59: 776.65 | BU59: 0 | BV59: 0 | BW59: 0 | BX59: 0 | BY59: 0 | BZ59: 0 | CA59: 57.6 | CB59: 2443.7 | CC59: 2784.3 | CD59: 1523.9 | CE59: 1793 | CF59: 722 | CG59: 0 | CH59: 0 | CI59: 0 | CJ59: 3311.15 | CK59: 3322.8 | CL59: 3527.8 | CM59: 1009.05 | CN59: 0 | CO59: 0 | CP59: 0 | CQ59: 0 | CR59: 4512.85 | CS59: 2236.65 | CT59: 168 | CU59: 104.3 | CV59: 480.3 | CW59: 3.4 | CX59: 1170.05 | CY59: 610.5 | CZ59: 43.75 | DA59: 1.5 | DB59: 426.4 | DC59: 238.65 | DD59: 130.45 | DE59: 1304.8 | DF59: 0 | DG59: 31.7 | DH59: 60.5 | DI59: 115.85 | DJ59: 413.75 | DK59: 155.4 | DL59: 446.9 | DM59: 81.6 | DN59: 441.6 | DO59: 124.75 | DP59: 155.45 | DQ59: 222.8 | DR59: 733.9 | DS59: 130.25 | DT59: 80.05 | DU59: 228.45 | DV59: 64.95 | DW59: 9.6 | DX59: 2 | DY59: 467.25 | DZ59: 176.9 | EA59: 479.2 | EB59: 484.65 | EC59: 150.2 | ED59: 512.5 | EE59: 182.7 | EF59: 717.55 | EG59: 1261.1 | EH59: 95.35 | EI59: 57.8 | EJ59: 225.9 | EK59: 486.6 | EL59: 180.95 | EM59: 139.7 | EN59: 489.6 | EO59: 489.6 | EP59: 480 | EQ59: 76.6 | ER59: 1570.7 | ES59: 105.05 | ET59: 1221.95 | EU59: 14.4 | EV59: 533.5 | EW59: 513.15 | EX59: 915.7 | EY59: 93.3 | EZ59: 54.9 | FA59: 57.6 | FB59: 19.2 | FC59: 91.15 | FD59: 191.55 | FE59: 480.95 | FF59: 480.05 | FG59: 195.05 | FH59: 663.8 | FI59: 828.7 | FJ59: 392.25 | FK59: 349.25 | FL59: 201.45 | FM59: 262.4 | FN59: 329.15 | FO59: 177833.45 | FQ59: 476.35 | FR59: 125.591 | FS59: 260.362 | FT59: 316.8 | FU59: 594.54641 | FV59: 454.68333 | FW59: 265.3 | FX59: 343.3 | FY59: 2836.9327

Sheet REACTIVA
B3: jueves, 12 de Febrero del 2026
A5: POTENCIA REACTIVA EJECUTADA DE LAS UNIDADES DE GENERACIÓN DEL COES (MVAR) | FQ5: CENTRALES NO INTEGRANTES COES
A6: FECHA | B6: HORA | C6: 65333 | D6: 101 | E6: 102 | F6: 42667 | G6: 42668 | H6: 126 | I6: 127 | J6: 138 | K6: 139 | L6: 197 | M6: 203 | N6: 204 | O6: 230 | P6: 209 | Q6: 56677 | R6: 796 | S6: 2146 | T6: 142 | U6: 143 | V6: 125 | W6: 187 | X6: 163 | Y6: 298 | Z6: 299 | AA6: 219 | AB6: 151 | AC6: 152 | AD6: 153 | AE6: 154 | AF6: 756 | AG6: 156 | AH6: 155 | AI6: 182 | AJ6: 212 | AK6: 758 | AL6: 263 | AM6: 265 | AN6: 775 | AO6: 777 | AP6: 2154 | AQ6: 150 | AR6: 149 | AS6: 188 | AT6: 2131 | AU6: 755 | AV6: 252 | AW6: 249 | AX6: 250 | AY6: 117 | AZ6: 119 | BA6: 120 | BB6: 189 | BC6: 122 | BD6: 266 | BE6: 337 | BF6: 338 | BG6: 251 | BH6: 115 | BI6: 239 | BJ6: 288 | BK6: 240 | BL6: 241 | BM6: 242 | BN6: 191 | BO6: 194 | BP6: 196 | BQ6: 207 | BR6: 236 | BS6: 795 | BT6: 285 | BU6: 995 | BV6: 996 | BW6: 997 | BX6: 766 | BY6: 926 | BZ6: 924 | CA6: 121 | CB6: 103 | CC6: 104 | CD6: 106 | CE6: 105 | CF6: 107 | CG6: 110 | CH6: 109 | CI6: 144 | CJ6: 113 | CK6: 114 | CL6: 193 | CM6: 208 | CN6: 786 | CO6: 787 | CP6: 788 | CQ6: 789 | CR6: 248 | CS6: 2159 | CT6: 267 | CU6: 268 | CV6: 2194 | CW6: 303 | CX6: 59715 | CY6: 62255 | CZ6: 1263 | DA6: 61800 | DB6: 69125 | DC6: 216 | DD6: 198 | DE6: 70400 | DF6: 76068 | DG6: 49607 | DH6: 214 | DI6: 260 | DJ6: 2152 | DK6: 2128 | DL6: 247 | DM6: 228 | DN6: 2135 | DO6: 261 | DP6: 237 | DQ6: 253 | DR6: 770 | DS6: 235 | DT6: 238 | DU6: 2184 | DV6: 61855 | DW6: 223 | DX6: 75566 | DY6: 226 | DZ6: 201 | EA6: 258 | EB6: 259 | EC6: 257 | ED6: 256 | EE6: 2148 | EF6: 58288 | EG6: 58289 | EH6: 58839 | EI6: 58840 | EJ6: 75260 | EK6: 296 | EL6: 297 | EM6: 211 | EN6: 2175 | EO6: 2178 | EP6: 2181 | EQ6: 1262 | ER6: 63425 | ES6: 233 | ET6: 2150 | EU6: 2165 | EV6: 2161 | EW6: 61197 | EX6: 58851 | EY6: 225 | EZ6: 2201 | FA6: 2171 | FB6: 760 | FC6: 234 | FD6: 215 | FE6: 917 | FF6: 920 | FG6: 289 | FH6: 58333 | FI6: 58336 | FJ6: 213 | FK6: 232 | FL6: 2190 | FM6: 69867 | FN6: 75066 | FO6: TOTAL COES | FQ6: 221 | FR6: 222 | FS6: 224 | FT6: 2187 | FU6: 227 | FV6: 49400 | FW6: 199 | FX6: 200 | FY6: TOTAL NO COES
C7: SUR | D7: CENTRO | E7: CENTRO | F7: NORTE | G7: NORTE | H7: NORTE | I7: NORTE | J7: CENTRO | K7: CENTRO | L7: CENTRO | M7: CENTRO | N7: CENTRO | O7: CENTRO | P7: CENTRO | Q7: CENTRO | R7: CENTRO | S7: CENTRO | T7: CENTRO | U7: CENTRO | V7: CENTRO | W7: CENTRO | X7: SUR | Y7: SUR | Z7: SUR | AA7: CENTRO | AB7: SUR | AC7: SUR | AD7: SUR | AE7: SUR | AF7: SUR | AG7: SUR | AH7: SUR | AI7: SUR | AJ7: CENTRO | AK7: NORTE | AL7: NORTE | AM7: NORTE | AN7: CENTRO | AO7: CENTRO | AP7: CENTRO | AQ7: CENTRO | AR7: CENTRO | AS7: CENTRO | AT7: CENTRO | AU7: SUR | AV7: CENTRO | AW7: CENTRO | AX7: CENTRO | AY7: CENTRO | AZ7: CENTRO | BA7: CENTRO | BB7: SUR | BC7: NORTE | BD7: CENTRO | BE7: CENTRO | BF7: CENTRO | BG7: CENTRO | BH7: NORTE | BI7: NORTE | BJ7: NORTE | BK7: SUR | BL7: SUR | BM7: SUR | BN7: CENTRO | BO7: CENTRO | BP7: CENTRO | BQ7: CENTRO | BR7: CENTRO | BS7: CENTRO | BT7: CENTRO | BU7: SUR | BV7: SUR | BW7: SUR | BX7: NORTE | BY7: SUR | BZ7: CENTRO | CA7: NORTE | CB7: CENTRO | CC7: CENTRO | CD7: CENTRO | CE7: CENTRO | CF7: CENTRO | CG7: CENTRO | CH7: CENTRO | CI7: CENTRO | CJ7: CENTRO | CK7: CENTRO | CL7: CENTRO | CM7: CENTRO | CN7: SUR | CO7: SUR | CP7: SUR | CQ7: SUR | CR7: CENTRO | CS7: CENTRO | CT7: CENTRO | CU7: CENTRO | CV7: NORTE | CW7: CENTRO | CX7: CENTRO | CY7: SUR | CZ7: NORTE | DA7: NORTE | DB7: CENTRO | DC7: NORTE | DD7: NORTE | DE7: SUR | DG7: SUR | DH7: CENTRO | DI7: CENTRO | DJ7: CENTRO | DK7: NORTE | DL7: NORTE | DM7: CENTRO | DN7: CENTRO | DO7: SUR | DP7: SUR | DQ7: CENTRO | DR7: CENTRO | DS7: SUR | DT7: CENTRO | DU7: CENTRO | DV7: NORTE | DW7: CENTRO | DX7: CENTRO | DY7: CENTRO | DZ7: NORTE | EA7: CENTRO | EB7: CENTRO | EC7: NORTE | ED7: NORTE | EE7: SUR | EF7: CENTRO | EG7: CENTRO | EH7: CENTRO | EI7: CENTRO | EJ7: SUR | EK7: CENTRO | EL7: CENTRO | EM7: SUR | EN7: SUR | EO7: SUR | EP7: SUR | EQ7: NORTE | ER7: SUR | ES7: SUR | ET7: SUR | EU7: CENTRO | EV7: CENTRO | EW7: CENTRO | EX7: SUR | EY7: CENTRO | EZ7: CENTRO | FA7: CENTRO | FB7: CENTRO | FC7: SUR | FD7: NORTE | FE7: CENTRO | FF7: CENTRO | FG7: NORTE | FH7: NORTE | FI7: NORTE | FJ7: CENTRO | FK7: NORTE | FL7: NORTE | FM7: NORTE | FN7: NORTE | FQ7: NORTE | FR7: CENTRO | FS7: NORTE | FT7: NORTE | FU7: NORTE | FV7: NORTE | FW7: NORTE | FX7: NORTE
C8: HIDROELÉCTRICA | D8: HIDROELÉCTRICA | E8: HIDROELÉCTRICA | F8: TERMOELÉCTRICA | G8: TERMOELÉCTRICA | H8: HIDROELÉCTRICA | I8: HIDROELÉCTRICA | J8: TERMOELÉCTRICA | K8: TERMOELÉCTRICA | L8: TERMOELÉCTRICA | M8: TERMOELÉCTRICA | N8: TERMOELÉCTRICA | O8: TERMOELÉCTRICA | P8: TERMOELÉCTRICA | Q8: TERMOELÉCTRICA | R8: HIDROELÉCTRICA | S8: HIDROELÉCTRICA | T8: TERMOELÉCTRICA | U8: TERMOELÉCTRICA | V8: TERMOELÉCTRICA | W8: TERMOELÉCTRICA | X8: HIDROELÉCTRICA | Y8: HIDROELÉCTRICA | Z8: HIDROELÉCTRICA | AA8: TERMOELÉCTRICA | AB8: HIDROELÉCTRICA | AC8: HIDROELÉCTRICA | AD8: HIDROELÉCTRICA | AE8: HIDROELÉCTRICA | AF8: TERMOELÉCTRICA | AG8: TERMOELÉCTRICA | AH8: TERMOELÉCTRICA | AI8: HIDROELÉCTRICA | AJ8: HIDROELÉCTRICA | AK8: TERMOELÉCTRICA | AL8: TERMOELÉCTRICA | AM8: TERMOELÉCTRICA | AN8: HIDROELÉCTRICA | AO8: HIDROELÉCTRICA | AP8: HIDROELÉCTRICA | AQ8: HIDROELÉCTRICA | AR8: HIDROELÉCTRICA | AS8: HIDROELÉCTRICA | AT8: HIDROELÉCTRICA | AU8: HIDROELÉCTRICA | AV8: TERMOELÉCTRICA | AW8: TERMOELÉCTRICA | AX8: TERMOELÉCTRICA | AY8: HIDROELÉCTRICA | AZ8: HIDROELÉCTRICA | BA8: HIDROELÉCTRICA | BB8: HIDROELÉCTRICA | BC8: HIDROELÉCTRICA | BD8: HIDROELÉCTRICA | BE8: HIDROELÉCTRICA | BF8: HIDROELÉCTRICA | BG8: HIDROELÉCTRICA | BH8: TERMOELÉCTRICA | BI8: TERMOELÉCTRICA | BJ8: TERMOELÉCTRICA | BK8: TERMOELÉCTRICA | BL8: TERMOELÉCTRICA | BM8: TERMOELÉCTRICA | BN8: HIDROELÉCTRICA | BO8: TERMOELÉCTRICA | BP8: TERMOELÉCTRICA | BQ8: TERMOELÉCTRICA | BR8: TERMOELÉCTRICA | BS8: TERMOELÉCTRICA | BT8: TERMOELÉCTRICA | BU8: TERMOELÉCTRICA | BV8: TERMOELÉCTRICA | BW8: TERMOELÉCTRICA | BX8: HIDROELÉCTRICA | BY8: TERMOELÉCTRICA | BZ8: TERMOELÉCTRICA | CA8: HIDROELÉCTRICA | CB8: HIDROELÉCTRICA | CC8: HIDROELÉCTRICA | CD8: HIDROELÉCTRICA | CE8: HIDROELÉCTRICA | CF8: HIDROELÉCTRICA | CG8: TERMOELÉCTRICA | CH8: TERMOELÉCTRICA | CI8: TERMOELÉCTRICA | CJ8: TERMOELÉCTRICA | CK8: TERMOELÉCTRICA | CL8: TERMOELÉCTRICA | CM8: TERMOELÉCTRICA | CN8: TERMOELÉCTRICA | CO8: TERMOELÉCTRICA | CP8: TERMOELÉCTRICA | CQ8: TERMOELÉCTRICA | CR8: TERMOELÉCTRICA | CS8: TERMOELÉCTRICA | CT8: HIDROELÉCTRICA | CU8: HIDROELÉCTRICA | CV8: HIDROELÉCTRICA | CW8: SOLAR | CX8: EÓLICA | CY8: SOLAR | CZ8: EÓLICA | DA8: SOLAR | DB8: HIDROELÉCTRICA | DC8: HIDROELÉCTRICA | DD8: HIDROELÉCTRICA | DE8: SOLAR | DF8: SOLAR | DG8: HIDROELÉCTRICA | DH8: HIDROELÉCTRICA | DI8: HIDROELÉCTRICA | DJ8: HIDROELÉCTRICA | DK8: HIDROELÉCTRICA | DL8: HIDROELÉCTRICA | DM8: HIDROELÉCTRICA | DN8: HIDROELÉCTRICA | DO8: SOLAR | DP8: SOLAR | DQ8: EÓLICA | DR8: EÓLICA | DS8: SOLAR | DT8: HIDROELÉCTRICA | DU8: HIDROELÉCTRICA | DV8: HIDROELÉCTRICA | DW8: HIDROELÉCTRICA | DX8: SOLAR | DY8: HIDROELÉCTRICA | DZ8: HIDROELÉCTRICA | EA8: HIDROELÉCTRICA | EB8: HIDROELÉCTRICA | EC8: EÓLICA | ED8: EÓLICA | EE8: SOLAR | EF8: EÓLICA | EG8: EÓLICA | EH8: EÓLICA | EI8: EÓLICA | EJ8: SOLAR | EK8: HIDROELÉCTRICA | EL8: HIDROELÉCTRICA | EM8: HIDROELÉCTRICA | EN8: HIDROELÉCTRICA | EO8: HIDROELÉCTRICA | EP8: HIDROELÉCTRICA | EQ8: EÓLICA | ER8: SOLAR | ES8: SOLAR | ET8: SOLAR | EU8: HIDROELÉCTRICA | EV8: EÓLICA | EW8: EÓLICA | EX8: SOLAR | EY8: TERMOELÉCTRICA | EZ8: TERMOELÉCTRICA | FA8: TERMOELÉCTRICA | FB8: TERMOELÉCTRICA | FC8: SOLAR | FD8: HIDROELÉCTRICA | FE8: HIDROELÉCTRICA | FF8: HIDROELÉCTRICA | FG8: TERMOELÉCTRICA | FH8: TERMOELÉCTRICA | FI8: TERMOELÉCTRICA | FJ8: TERMOELÉCTRICA | FK8: TERMOELÉCTRICA | FL8: TERMOELÉCTRICA | FM8: TERMOELÉCTRICA | FN8: TERMOELÉCTRICA | FQ8: HIDROELÉCTRICA | FR8: HIDROELÉCTRICA | FS8: HIDROELÉCTRICA | FT8: HIDROELÉCTRICA | FU8: TERMOELÉCTRICA | FV8: TERMOELÉCTRICA | FW8: HIDROELÉCTRICA | FX8: HIDROELÉCTRICA
C9: HYDRO GLOBAL PERÚ S.A.C. | D9: ELECTROPERU | E9: ELECTROPERU | F9: ELECTROPERU | G9: ELECTROPERU | H9: ORAZUL ENERGY PERÚ | I9: ORAZUL ENERGY PERÚ | J9: TERMOSELVA | K9: TERMOSELVA | L9: KALLPA GENERACION S.A. | M9: KALLPA GENERACION S.A. | N9: KALLPA GENERACION S.A. | O9: KALLPA GENERACION S.A. | P9: KALLPA GENERACION S.A. | Q9: KALLPA GENERACION S.A. | R9: KALLPA GENERACION S.A. | S9: KALLPA GENERACION S.A. | T9: SHOUGESA | U9: SHOUGESA | V9: SHOUGESA | W9: SHOUGESA | X9: EGEMSA | Y9: EGESUR | Z9: EGESUR | AA9: EGESUR | AB9: EGASA | AC9: EGASA | AD9: EGASA | AE9: EGASA | AF9: EGASA | AG9: EGASA | AH9: EGASA | AI9: SAN GABAN | AJ9: CELEPSA | AK9: MINERA CERRO VERDE | AL9: PLANTA DE RESERVA FRIA DE GENERACION DE ETEN S.A. | AM9: PLANTA DE RESERVA FRIA DE GENERACION DE ETEN S.A. | AN9: EMPRESA DE GENERACION HUALLAGA | AO9: EMPRESA DE GENERACION HUALLAGA | AP9: LA VIRGEN | AQ9: CHINANGO S.A.C. | AR9: CHINANGO S.A.C. | AS9: HIDROELECTRICA HUANCHOR S.A.C. | AT9: CELEPSA RENOVABLES S.R.L. | AU9: INLAND ENERGY SAC | AV9: FENIX POWER PERÚ | AW9: FENIX POWER PERÚ | AX9: FENIX POWER PERÚ | AY9: STATKRAFT S.A | AZ9: STATKRAFT S.A | BA9: STATKRAFT S.A | BB9: STATKRAFT S.A | BC9: STATKRAFT S.A | BD9: STATKRAFT S.A | BE9: CENTRALES SANTA ROSA S.A.C. | BF9: CENTRALES SANTA ROSA S.A.C. | BG9: EMPRESA DE GENERACION HUANZA | BH9: ENEL GENERACION PIURA S.A. | BI9: ENEL GENERACION PIURA S.A. | BJ9: ENEL GENERACION PIURA S.A. | BK9: ENGIE ENERGIA PERU S.A.A. | BL9: ENGIE ENERGIA PERU S.A.A. | BM9: ENGIE ENERGIA PERU S.A.A. | BN9: ENGIE ENERGIA PERU S.A.A. | BO9: ENGIE ENERGIA PERU S.A.A. | BP9: ENGIE ENERGIA PERU S.A.A. | BQ9: ENGIE ENERGIA PERU S.A.A. | BR9: ENGIE ENERGIA PERU S.A.A. | BS9: ENGIE ENERGIA PERU S.A.A. | BT9: ENGIE ENERGIA PERU S.A.A. | BU9: ENGIE ENERGIA PERU S.A.A. | BV9: ENGIE ENERGIA PERU S.A.A. | BW9: ENGIE ENERGIA PERU S.A.A. | BX9: ENGIE ENERGIA PERU S.A.A. | BY9: INFRAESTRUCTURAS Y ENERGIAS DEL PERU S.A.C. | BZ9: INFRAESTRUCTURAS Y ENERGIAS DEL PERU S.A.C. | CA9: INVERSIONES SHAQSHA S.A.C. | CB9: ORYGEN PERU S.A.A. | CC9: ORYGEN PERU S.A.A. | CD9: ORYGEN PERU S.A.A. | CE9: ORYGEN PERU S.A.A. | CF9: ORYGEN PERU S.A.A. | CG9: ORYGEN PERU S.A.A. | CH9: ORYGEN PERU S.A.A. | CI9: ORYGEN PERU S.A.A. | CJ9: ORYGEN PERU S.A.A. | CK9: ORYGEN PERU S.A.A. | CL9: ORYGEN PERU S.A.A. | CM9: ORYGEN PERU S.A.A. | CN9: SAMAY I S.A.C | CO9: SAMAY I S.A.C | CP9: SAMAY I S.A.C | CQ9: SAMAY I S.A.C | CR9: TERMOCHILCA S.A.C. | CS9: TERMOCHILCA S.A.C. | CT9: TRANSMISION ANDINA DE GENERACION S.A.C. | CU9: TRANSMISION ANDINA DE GENERACION S.A.C. | CV9: CELARIS ENERGY S.A. | CW9: COLCA SOLAR S.A.C. | CX9: ENERGIA RENOVABLE DEL SUR S.A. | CY9: GR CORTARRAMA SOCIEDAD ANONIMA CERRADA | CZ9: GR TARUCA SOCIEDAD ANONIMA CERRADA | DA9: KONDU SAC | DB9: VARI ENERGIA S.A.C. | DC9: ORAZUL ENERGY PERÚ | DD9: ORAZUL ENERGY PERÚ | DE9: KALLPA GENERACION S.A. | DF9: KALLPA GENERACION S.A. | DG9: SAN GABAN | DH9: MAJA ENERGIA S.A.C. | DI9: EMPRESA DE GENERACION ELECTRICA CANCHAYLLO SAC | DJ9: EMPRESA DE GENERACION ELECTRICA SANTA ANA S.A.C. | DK9: EMPRESA ELECTRICA AGUA AZUL | DL9: EMPRESA ELECTRICA RIO DOBLE | DM9: HIDROCAÑETE S.A. | DN9: HUAURA POWER GROUP S.A. | DO9: MOQUEGUA FV S.A.C. | DP9: PANAMERICANA SOLAR SAC. | DQ9: PARQUE EOLICO MARCONA S.A.C. | DR9: PARQUE EOLICO TRES HERMANAS S.A.C. | DS9: TACNA SOLAR SAC. | DT9: ELECTRICA YANAPAMPA SAC | DU9: ANDEAN POWER S.A.C. | DV9: ASOCIACIÓN SANTA LUCIA DE CHACAS | DW9: ATRIA ENERGIA S.A.C. | DX9: COENERGY S.A.C. | DY9: EGEJUNIN | DZ9: EGEJUNIN | EA9: EGEJUNIN | EB9: EGEJUNIN | EC9: ENERGÍA EÓLICA S.A. | ED9: ENERGÍA EÓLICA S.A. | EE9: ENGIE ENERGIA PERU S.A.A. | EF9: ENGIE ENERGIA PERU S.A.A. | EG9: ENGIE ENERGIA PERU S.A.A. | EH9: ENGIE ENERGIA PERU S.A.A. | EI9: ENGIE ENERGIA PERU S.A.A. | EJ9: ENGIE ENERGIA PERU S.A.A. | EK9: GENERACIÓN ANDINA S.A.C. | EL9: GENERACIÓN ANDINA S.A.C. | EM9: GENERADORA DE ENERGÍA DEL PERÚ | EN9: GENERADORA DE ENERGÍA DEL PERÚ | EO9: GENERADORA DE ENERGÍA DEL PERÚ | EP9: GENERADORA DE ENERGÍA DEL PERÚ | EQ9: GR PAINO SOCIEDAD ANONIMA CERRADA | ER9: JOYA SOLAR S.A.C. | ES9: MAJES ARCUS S.A.C. | ET9: ORYGEN PERU S.A.A. | EU9: ORYGEN PERU S.A.A. | EV9: ORYGEN PERU S.A.A. | EW9: ORYGEN PERU S.A.A. | EX9: ORYGEN PERU S.A.A. | EY9: PETRAMAS | EZ9: PETRAMAS | FA9: PETRAMAS | FB9: PETRAMAS | FC9: REPARTICIÓN ARCUS S.A.C. | FD9: SINERSA | FE9: SINERSA | FF9: SINERSA | FG9: BIOENERGIA DEL CHIRA S.A. | FH9: GM OPERACIONES S.A.C. | FI9: GM OPERACIONES S.A.C. | FJ9: AGRO INDUSTRIAL PARAMONGA S.A. | FK9: AGROAURORA S.A.C. | FL9: AGROINDUSTRIAS SAN JACINTO S.A.A. | FM9: AGROLMOS SOCIEDAD ANONIMA - AGROLMOS S.A. | FN9: CASA GRANDE S.A.A. | FQ9: UNACEM PERU S.A. | FR9: ELECTRO ORIENTE | FS9: AGUAS Y ENERGIA PERU | FT9: ELECTRO ZAÑA S.A.C. | FU9: ELECTRONOROESTE S.A. | FV9: SDE PIURA | FW9: SINERSA | FX9: SINERSA
C10: SAN GABAN III | D10: MANTARO | E10: RESTITUCION | F10: TUMBES MAK 1 | G10: TUMBES MAK 2 | H10: CARHUAQUERO | I10: CAÑON DEL PATO | J10: AGUAYTIA TG1 | K10: AGUAYTIA TG2 | L10: KALLPA TG1 | M10: KALLPA TG2 | N10: KALLPA TG3 | O10: KALLPA TV | P10: LFLORES TG1 | Q10: LFLORES TV | R10: CERRO DEL AGUILA | S10: CERRODELAGUILAG4 | T10: SHOUGESA TV1 | U10: SHOUGESA TV2 | V10: SHOUGESA TV3 | W10: SHOUGESA CUMMINS | X10: MACHUPICCHU | Y10: ARICOTA 1 | Z10: ARICOTA 2 | AA10: INDEPENDENCIA | AB10: CHARCANI I,II,III | AC10: CHARCANI IV | AD10: CHARCANI V | AE10: CHARCANI VI | AF10: CHILINA TG | AG10: MOLLENDO 1, 2, 3 | AH10: CHILINA (SULZ 1,2) | AI10: SAN GABAN II | AJ10: PLATANAL | AK10: RECKA | AL10: RF ETEN TG1 | AM10: RF ETEN TG2 | AN10: CHAGLLA GP1 | AO10: CHAGLLA | AP10: LA VIRGEN | AQ10: CHIMAY | AR10: YANANGO | AS10: HUANCHOR | AT10: MARAÑON | AU10: STA TERESA | AV10: FENIX GT11 | AW10: FENIX GT12 | AX10: FENIX TV10 | AY10: YAUPI | AZ10: MALPASO | BA10: CAHUA | BB10: ARCATA | BC10: GALLITO CIEGO | BD10: CHEVES | BE10: SANTA ROSA 1 | BF10: SANTA ROSA 2 | BG10: HUANZA | BH10: MALACAS2 TG4 | BI10: MALACAS3 TG 5 | BJ10: MALACAS1 TG6 | BK10: RF ILO2 TG1 | BL10: RF ILO2 TG2 | BM10: RF ILO2 TG3 | BN10: YUNCAN | BO10: CHILCA1 TG1 | BP10: CHILCA1 TG2 | BQ10: CHILCA1 TG3 | BR10: CHILCA-TV | BS10: CHILCA2 TG41 | BT10: CHILCA2-TV | BU10: CTNEPI_TG41 | BV10: CTNEPI_TG42 | BW10: CTNEPI_TG43 | BX10: QUITARACSA | BY10: RF PTO MALDONADO | BZ10: RF PUCALLPA | CA10: PARIAC | CB10: HUINCO | CC10: MATUCANA | CD10: MOYOPAMPA | CE10: CALLAHUANCA | CF10: HUAMPANI | CG10: STA ROSA WEST TG7 | CH10: UTI_5 | CI10: UTI_6 | CJ10: VENTANILLA 3 | CK10: VENTANILLA 4 | CL10: VENTANILLA TV | CM10: STAROSA TG8 | CN10: PTO_BRVO TG1 | CO10: PTO_BRVO TG2 | CP10: PTO_BRVO TG3 | CQ10: PTO_BRVO TG4 | CR10: OLLEROS TG1 | CS10: OLLEROS TV | CT10: OROYA | CU10: PACHACHACA | CV10: MANTA I | CW10: CS YARUCAYA | CX10: SAN JUAN | CY10: MATARANI | CZ10: DUNA | DA10: CARHUAQUERO (CS) | DB10: ANASHIRONI | DC10: CARHUAQUERO4 | DD10: CAÑA BRAVA | DE10: SUNNY | DF10: SUNNY EXPANSION | DG10: TUPURI | DH10: RONCADOR | DI10: CANCHAYLLO | DJ10: RENOVANDESH1 | DK10: POTRERO | DL10: PIZARRAS | DM10: NIMPERIAL | DN10: YARUCAYA | DO10: MOQUEGUA-SOLAR | DP10: PANAMERICANA-SOLAR | DQ10: PQE-EOLICO-MARCONA | DR10: PQE-EOLICO-3-HERMANAS | DS10: TACNA-SOLAR | DT10: YANAPAMPA | DU10: CARHUAC | DV10: HUALLIN | DW10: PURMACANA | DX10: COENERGY | DY10: HUASAHUASI | DZ10: STACRUZ_1_2 | EA10: RUNATULLO_II | EB10: RUNATULLO_III | EC10: PQE-EOLICO-TALARA | ED10: PQE-EOLICO-CUPISNIQUE | EE10: INTIPAMPA | EF10: PUNTA LOMITAS-BL1 | EG10: PUNTA LOMITAS-BL2 | EH10: PUN LOMITAS_EXP-BL1 | EI10: PUN LOMITAS_EXP-BL2 | EJ10: EXPANSIÓN INTIPAMPA | EK10: 8AGOSTO | EL10: EL CARMEN | EM10: LA JOYA | EN10: ANGEL_I | EO10: ANGEL_II | EP10: ANGEL_III | EQ10: HUAMBOS | ER10: SAN MARTIN SOLAR | ES10: MAJES | ET10: RUBI | EU10: CH_HER1 | EV10: WAYRA-I | EW10: WAYRA EXTENSION | EX10: CLEMESI | EY10: HUAYCOLORO | EZ10: CALLAO | FA10: DONA_CATALINA | FB10: LAGRINGAV | FC10: REPARTICION | FD10: POECHOS2 | FE10: CHANCAY | FF10: RUCUY | FG10: CANA BRAVA | FH10: REFINERIA TALARA TV1 | FI10: REFINERÍA TALARA TV2 | FJ10: PARAMONGA | FK10: MAPLE | FL10: SAN_JACINTO | FM10: AGROLMOS | FN10: CASA GRANDE | FO10: MVAR | FQ10: CARPAPATA | FR10: CENTRALES ELOR | FS10: PIAS1 | FT10: ZANA | FU10: TABLAZO | FV10: TALLANCA | FW10: CURUMUY | FX10: POECHOS1 | FY10: MVAR
A11: 12/02/2026 | B11: 00:30 | C11: 31.6 | D11: -14.6 | E11: 10.7 | H11: -12.7 | I11: 6.8 | K11: 0.2 | L11: -21.2 | M11: -38.4 | N11: -10.3 | O11: 16 | P11: -17.3 | Q11: -11.7 | R11: 70.8 | S11: -0.3 | X11: -7.1 | Y11: 0.6 | Z11: 0.2 | AA11: 0 | AB11: -3.2 | AD11: 8.3 | AI11: 10.4 | AJ11: 8.5 | AN11: -0.4 | AO11: 48.2 | AP11: 5.9 | AQ11: 24.8 | AR11: 6 | AS11: -0.3 | AT11: 2.6 | AU11: 1 | AY11: 10.1 | AZ11: 0 | BA11: -0.9 | BB11: 1.1 | BC11: 0.6 | BD11: -3.6 | BG11: 0 | BJ11: 0 | BK11: 0 | BN11: 6 | BO11: 0 | BP11: 0 | BQ11: 0 | BS11: -0.4 | BT11: -3.3 | CA11: -0.3 | CB11: 16.7 | CC11: 30.7 | CD11: 6.1 | CE11: 8.6 | CF11: -0.4 | CJ11: 20.3 | CK11: 23.7 | CL11: -6.7 | CM11: 0 | CR11: -9.9 | CS11: -10.5 | CT11: -1.8 | CU11: 0.7 | CV11: 1.5 | CX11: -4.3 | CY11: 0 | CZ11: 0 | DB11: 0 | DC11: -0.1 | DD11: -1 | DE11: 0 | DH11: 0 | DI11: 1.1 | DJ11: 0.2 | DK11: -0.4 | DL11: 0.1 | DM11: 0.5 | DO11: 0 | DP11: 0 | DQ11: -7.4 | DR11: 2.5 | DS11: 0 | DT11: 0 | DU11: 0.3 | DV11: 0.6 | DW11: 0 | DY11: -4.6 | DZ11: 0.5 | EA11: 2.8 | EB11: 3 | ED11: 0 | EE11: 0 | EF11: -5.8 | EG11: -6 | EH11: -0.6 | EI11: -0.1 | EK11: 2.1 | EL11: 0 | EM11: 0.7 | EN11: 0.2 | EO11: 0.2 | EP11: 0.2 | EQ11: -0.1 | ER11: 0 | ES11: 0 | ET11: 0 | EU11: -0.2 | EV11: 3.6 | EW11: -4.6 | EX11: 0 | EY11: 2 | EZ11: 0.7 | FA11: 0.8 | FB11: 0.4 | FC11: 0 | FD11: 0.2 | FE11: 2 | FF11: 1.7 | FG11: 2 | FH11: 8.6 | FI11: 0 | FJ11: 1.2 | FK11: 0 | FL11: 2.5 | FM11: 4.4 | FN11: 8.39 | FO11: 221.69 | FQ11: 2 | FR11: 0.228 | FS11: 2.56 | FT11: 1.6 | FU11: 2.32643 | FV11: 0.13546 | FW11: -1.4 | FX11: 0.4 | FY11: 7.84989
A12: 12/02/2026 | B12: 01:00 | C12: 35.2 | D12: -5.9 | E12: 12 | H12: -12.4 | I12: 6.3 | K12: 0.1 | L12: -21.9 | M12: -35.2 | N12: -7.4 | O12: 16.5 | P12: -17.2 | Q12: -13.4 | R12: 75 | S12: 0 | X12: -5.5 | Y12: 1.2 | Z12: 0.8 | AA12: 0 | AB12: -3.2 | AD12: 9.1 | AI12: 11.7 | AJ12: 9.1 | AN12: -0.5 | AO12: 47.2 | AP12: 5.9 | AQ12: 25 | AR12: 5.9 | AS12: -0.1 | AT12: 2.6 | AU12: 0.9 | AY12: 10.1 | AZ12: 0 | BA12: -0.6 | BB12: 1.1 | BC12: 0.5 | BD12: -0.5 | BG12: 0 | BJ12: 0 | BK12: 0 | BN12: 6.4 | BO12: 0 | BP12: 0 | BQ12: 0 | BS12: -0.8 | BT12: -3.5 | CA12: -0.2 | CB12: 9.1 | CC12: 26.2 | CD12: 6.2 | CE12: 5.9 | CF12: 0 | CJ12: 20.6 | CK12: 23.6 | CL12: -6.7 | CM12: 0 | CR12: -12.9 | CS12: -12.3 | CT12: -2 | CU12: 0.7 | CV12: 1.5 | CX12: -4.6 | CY12: 0 | CZ12: 0 | DB12: 0 | DC12: -0.1 | DD12: -1 | DE12: 0 | DH12: 0 | DI12: 1.1 | DJ12: 0.2 | DK12: -0.8 | DL12: 0.1 | DM12: 0.6 | DO12: 0 | DP12: 0 | DQ12: -7.6 | DR12: 1.6 | DS12: 0 | DT12: 0 | DU12: 0.3 | DV12: 0.6 | DW12: 0 | DY12: -4.6 | DZ12: 0.4 | EA12: 3.3 | EB12: 3 | ED12: 0 | EE12: 0 | EF12: -4.1 | EG12: -5.3 | EH12: -0.5 | EI12: -0.1 | EK12: 2.1 | EL12: -0.1 | EM12: 0.7 | EN12: 0.2 | EO12: 0.2 | EP12: 0.2 | EQ12: 0 | ER12: 0 | ES12: 0 | ET12: 0 | EU12: -0.2 | EV12: 4.1 | EW12: -1.7 | EX12: 0 | EY12: 2 | EZ12: 0.7 | FA12: 0.8 | FB12: 0.4 | FC12: 0 | FD12: 0.2 | FE12: 1.9 | FF12: 1.6 | FG12: 1.9 | FH12: 8.3 | FI12: 0.5 | FJ12: 1.4 | FK12: 0 | FL12: 2.2 | FM12: 4.3 | FN12: 4.28 | FO12: 232.68 | FQ12: 2.1 | FR12: 0.411 | FS12: 2.31 | FT12: 1.7 | FU12: 2.33726 | FV12: 0.11745 | FW12: -1.6 | FX12: 0.4 | FY12: 7.77571
A13: 12/02/2026 | B13: 01:30 | C13: 32.2 | D13: -22.1 | E13: 8.7 | H13: -13.5 | I13: 3.1 | K13: 0 | L13: -30.6 | M13: -43.4 | N13: -14.5 | O13: 6.2 | P13: -21.8 | Q13: -16 | R13: 64.9 | S13: -0.1 | X13: -6.8 | Y13: 1 | Z13: 0.7 | AA13: 0 | AB13: -3.2 | AD13: 7.7 | AI13: 10.8 | AJ13: 6.6 | AN13: -0.5 | AO13: 45.8 | AP13: 5.6 | AQ13: 25.2 | AR13: 6 | AS13: -1.4 | AT13: 2.6 | AU13: 2.7 | AY13: 10.1 | AZ13: 0 | BA13: -1.2 | BB13: 1.1 | BC13: 0.5 | BD13: 0.3 | BG13: 0 | BJ13: 0 | BK13: 0 | BN13: 4.3 | BO13: 0 | BP13: 0 | BQ13: 0 | BS13: -2.9 | BT13: -4.4 | CA13: -0.3 | CB13: 9.4 | CC13: 25.9 | CD13: 5.5 | CE13: 8.4 | CF13: -0.2 | CJ13: 14.8 | CK13: 17.5 | CL13: -16.1 | CM13: 0 | CR13: -16.2 | CS13: -14.2 | CT13: -2.1 | CU13: 0.5 | CV13: 1.5 | CX13: -4.6 | CY13: 0 | CZ13: 0 | DB13: 0 | DC13: -0.1 | DD13: -0.8 | DE13: 0 | DH13: 0 | DI13: 1 | DJ13: 0.2 | DK13: -0.8 | DL13: 0.1 | DM13: 0.6 | DO13: 0 | DP13: 0 | DQ13: -7.9 | DR13: 0.6 | DS13: 0 | DT13: -0.1 | DU13: 0.4 | DV13: 0.6 | DW13: 0 | DY13: -4.6 | DZ13: 0.3 | EA13: 3.3 | EB13: 3 | ED13: 0 | EE13: 0 | EF13: -8.8 | EG13: -9.9 | EH13: -1.3 | EI13: -0.8 | EK13: 2.1 | EL13: 0 | EM13: 0.7 | EN13: 0.2 | EO13: 0.2 | EP13: 0.2 | EQ13: 0 | ER13: 0 | ES13: 0 | ET13: 0 | EU13: -0.2 | EV13: 4.5 | EW13: -0.2 | EX13: 0 | EY13: 2 | EZ13: 0.8 | FA13: 0.8 | FB13: 0.4 | FC13: 0 | FD13: 0.2 | FE13: 1.6 | FF13: 1.4 | FG13: 1.9 | FH13: 8 | FI13: -0.1 | FJ13: 2 | FK13: 0 | FL13: 2.3 | FM13: 4.4 | FN13: 4.24 | FO13: 105.94 | FQ13: 2 | FR13: 0.361 | FS13: 2.13 | FT13: 1.7 | FU13: 2.34058 | FV13: 0.11657 | FW13: -1.8 | FX13: 0.4 | FY13: 7.24815
A14: 12/02/2026 | B14: 02:00 | C14: 34 | D14: -10.6 | E14: 9.9 | H14: -11.8 | I14: 13.6 | K14: 0.3 | L14: -27.7 | M14: -46.2 | N14: -17.3 | O14: 7.7 | P14: -21.6 | Q14: -14.3 | R14: 68.5 | S14: -0.2 | X14: -5.2 | Y14: 0.9 | Z14: 0.5 | AA14: 0 | AB14: -3.2 | AD14: 8.4 | AI14: 11.9 | AJ14: -3 | AN14: -0.5 | AO14: 44.8 | AP14: 5.6 | AQ14: 26.1 | AR14: 6.7 | AS14: -1.2 | AT14: 2.6 | AU14: 1.4 | AY14: 10.1 | AZ14: 0 | BA14: -1.5 | BB14: 1 | BC14: 0.4 | BD14: -4.2 | BG14: 0 | BJ14: 0 | BK14: 0 | BN14: 5.8 | BO14: 0 | BP14: 0 | BQ14: 0 | BS14: -2.1 | BT14: -4.1 | CA14: -0.2 | CB14: 8.6 | CC14: 27.2 | CD14: 7.2 | CE14: 5.8 | CF14: -0.1 | CJ14: 14.7 | CK14: 18 | CL14: -15.5 | CM14: 0 | CR14: -19 | CS14: -15.9 | CT14: -2.1 | CU14: 0.6 | CV14: 1.5 | CX14: -4.3 | CY14: 0 | CZ14: 0 | DB14: 0 | DC14: 0 | DD14: -0.8 | DE14: 0 | DH14: 0 | DI14: 1 | DJ14: 0.2 | DK14: -0.8 | DL14: 0.1 | DM14: 0.5 | DO14: 0 | DP14: 0 | DQ14: -8.3 | DR14: -0.3 | DS14: 0 | DT14: -0.1 | DU14: 0.4 | DV14: 0.6 | DW14: 0 | DY14: -4.6 | DZ14: 0.3 | EA14: 3.3 | EB14: 2.9 | ED14: 0 | EE14: 0 | EF14: -6.4 | EG14: -7.4 | EH14: -0.9 | EI14: -0.6 | EK14: 2.1 | EL14: 0 | EM14: 0.7 | EN14: 0.2 | EO14: 0.2 | EP14: 0.2 | EQ14: 0 | ER14: 0 | ES14: 0 | ET14: 0 | EU14: -0.2 | EV14: 4.5 | EW14: -0.1 | EX14: 0 | EY14: 2 | EZ14: 0.8 | FA14: 0.8 | FB14: 0.4 | FC14: 0 | FD14: 0.2 | FE14: 1.6 | FF14: 1.3 | FG14: 1.9 | FH14: 7.5 | FI14: 0.5 | FJ14: 0.9 | FK14: 0 | FL14: 2 | FM14: 4.4 | FN14: 5.01 | FO14: 128.01 | FQ14: 2.1 | FR14: 0.296 | FS14: 2.28 | FT14: 1.9 | FU14: 2.33547 | FV14: 0.08905 | FW14: -1.6 | FX14: 0.4 | FY14: 7.80052
A15: 12/02/2026 | B15: 02:30 | C15: 36.9 | D15: -11.8 | E15: 11.1 | H15: -13.7 | I15: 12.6 | K15: 0 | L15: -31.1 | M15: -43.3 | N15: -15.6 | O15: 4.9 | P15: -23.3 | Q15: -16.7 | R15: 68.6 | S15: 0.1 | X15: -4.7 | Y15: 0.8 | Z15: 0.4 | AA15: 0 | AB15: -3.2 | AD15: 8.5 | AI15: 11.6 | AJ15: 5 | AN15: -0.5 | AO15: 44 | AP15: 5.8 | AQ15: 25.1 | AR15: 5.8 | AS15: -1.6 | AT15: 2.6 | AU15: 1.7 | AY15: 10.1 | AZ15: 0 | BA15: -1 | BB15: 1 | BC15: 0.4 | BD15: 0.9 | BG15: 0 | BJ15: 0 | BK15: 0 | BN15: 4.7 | BO15: 0 | BP15: 0 | BQ15: 0 | BS15: -3.1 | BT15: -4.6 | CA15: -0.3 | CB15: 9.1 | CC15: 25.7 | CD15: 5.6 | CE15: 5.8 | CF15: -0.1 | CJ15: 11.6 | CK15: 14.7 | CL15: -20 | CM15: 0 | CR15: -21.7 | CS15: -17.5 | CT15: -2.1 | CU15: 0.6 | CV15: 1.5 | CX15: -5 | CY15: 0 | CZ15: 0 | DB15: 0 | DC15: 0 | DD15: -0.9 | DE15: 0 | DH15: 0 | DI15: 1 | DJ15: 0.2 | DK15: -0.8 | DL15: 0.1 | DM15: 0.6 | DO15: 0 | DP15: 0 | DQ15: -8.5 | DR15: -1.4 | DS15: 0 | DT15: -0.2 | DU15: 0.4 | DV15: 0.6 | DW15: 0 | DY15: -4.6 | DZ15: 0.1 | EA15: 3.3 | EB15: 3 | ED15: 0 | EE15: 0 | EF15: -7.4 | EG15: -7.7 | EH15: -1 | EI15: -0.7 | EK15: 2.1 | EL15: 0 | EM15: 0.7 | EN15: 0.2 | EO15: 0.2 | EP15: 0.2 | EQ15: 0 | ER15: 0 | ES15: 0 | ET15: 0 | EU15: -0.2 | EV15: 4.8 | EW15: 0.5 | EX15: 0 | EY15: 2 | EZ15: 0.7 | FA15: 0.8 | FB15: 0.4 | FC15: 0 | FD15: 0.2 | FE15: 1.6 | FF15: 1.3 | FG15: 2 | FH15: 7.3 | FI15: 0.6 | FJ15: 1.9 | FK15: 0 | FL15: 2.2 | FM15: 4.4 | FN15: 4.17 | FO15: 110.47 | FQ15: 2.1 | FR15: 0.179 | FS15: 1.83 | FT15: 1.7 | FU15: 2.32906 | FV15: 0.09793 | FW15: -1.7 | FX15: 0.4 | FY15: 6.93599
A16: 12/02/2026 | B16: 03:00 | C16: 35.6 | D16: -25.4 | E16: 8.7 | H16: -15.6 | I16: -2.1 | K16: 0 | L16: -29.5 | M16: -40.7 | N16: -11.9 | O16: 7.6 | P16: -24.1 | Q16: -17.2 | R16: 49.5 | S16: 0 | X16: -4.7 | Y16: 1.1 | Z16: 0.7 | AA16: 0 | AB16: -3.2 | AD16: 8.5 | AI16: 11.6 | AJ16: 5.6 | AN16: -0.6 | AO16: 43.1 | AP16: 5.8 | AQ16: 25 | AR16: 5.8 | AS16: -0.1 | AT16: 2.6 | AU16: 1.5 | AY16: 10.1 | AZ16: 0 | BA16: -2.1 | BB16: 1 | BC16: 0.4 | BD16: 0.3 | BG16: 0 | BJ16: 0 | BK16: 0 | BN16: 4.2 | BO16: 0 | BP16: 0 | BQ16: 0 | BS16: -3.8 | BT16: -4.8 | CA16: -0.2 | CB16: 9.6 | CC16: 26 | CD16: 5.9 | CE16: 5.8 | CF16: -0.2 | CJ16: 4.9 | CK16: 7.5 | CL16: -21.8 | CM16: 0 | CR16: -22.9 | CS16: -18.2 | CT16: -2.1 | CU16: 0.6 | CV16: 1.5 | CX16: -5.3 | CY16: 0 | CZ16: 0 | DB16: 0.1 | DC16: 0 | DD16: -0.8 | DE16: 0 | DH16: 0 | DI16: 1.1 | DJ16: 0.2 | DK16: -0.8 | DL16: 0.1 | DM16: 0.5 | DO16: 0 | DP16: 0 | DQ16: -8 | DR16: -0.4 | DS16: 0 | DT16: -0.3 | DU16: 0.4 | DV16: 0.6 | DW16: 0 | DY16: -4.7 | DZ16: 0.1 | EA16: 3.3 | EB16: 2.8 | ED16: 0 | EE16: 0 | EF16: -5.6 | EG16: -6.7 | EH16: -0.8 | EI16: -0.7 | EK16: 2.1 | EL16: 0 | EM16: 0.7 | EN16: 0.2 | EO16: 0.2 | EP16: 0.2 | EQ16: 0 | ER16: 0 | ES16: 0 | ET16: 0 | EU16: -0.2 | EV16: 4.9 | EW16: 0.6 | EX16: 0 | EY16: 2 | EZ16: 0.8 | FA16: 0.8 | FB16: 0.4 | FC16: 0 | FD16: 0.2 | FE16: 1.4 | FF16: 1.2 | FG16: 2 | FH16: 6.9 | FI16: 0.6 | FJ16: 0.6 | FK16: 0 | FL16: 2.3 | FM16: 4.4 | FN16: 4.19 | FO16: 50.89 | FQ16: 1.9 | FR16: 0.07 | FS16: 1.68 | FT16: 1.7 | FU16: 2.32317 | FV16: 0.12971 | FW16: -1.8 | FX16: 0.4 | FY16: 6.40288
A17: 12/02/2026 | B17: 03:30 | C17: 34.5 | D17: -18.6 | E17: 9.4 | H17: -14.8 | I17: -1.4 | K17: 0.5 | L17: -27.4 | M17: -41.2 | N17: -12.7 | O17: 8.7 | P17: -23.1 | Q17: -16.1 | R17: 52.1 | S17: 0 | X17: -5.1 | Y17: 1.1 | Z17: 0.7 | AA17: 0 | AB17: -3.2 | AD17: 7.9 | AI17: 10.5 | AJ17: 5.8 | AN17: -0.9 | AO17: 42.2 | AP17: 5.7 | AQ17: 25.5 | AR17: 6.2 | AS17: -0.6 | AT17: 2.6 | AU17: 1.3 | AY17: 10.1 | AZ17: 0 | BA17: -2.5 | BB17: 1 | BC17: 0.4 | BD17: -0.3 | BG17: 0 | BJ17: 0 | BK17: 0 | BN17: 4.8 | BO17: 0 | BP17: 0 | BQ17: 0 | BS17: -2.9 | BT17: -4.5 | CA17: -0.2 | CB17: 9.3 | CC17: 22.4 | CD17: 6.1 | CE17: 5.8 | CF17: -0.2 | CJ17: 5.3 | CK17: 8.3 | CL17: -20.6 | CM17: 0 | CR17: -22 | CS17: -17.6 | CT17: -2 | CU17: 0.6 | CV17: 1.5 | CX17: -5.2 | CY17: 0 | CZ17: 0 | DB17: 0.1 | DC17: 0 | DD17: -0.9 | DE17: 0 | DH17: 0 | DI17: 1 | DJ17: 0.2 | DK17: -0.8 | DL17: 0.1 | DM17: 0.5 | DO17: 0 | DP17: 0 | DQ17: -7.3 | DR17: 1.7 | DS17: 0 | DT17: -0.1 | DU17: 0.4 | DV17: 0.6 | DW17: 0 | DY17: -4.6 | DZ17: 0.1 | EA17: 3.3 | EB17: 2.9 | ED17: 0 | EE17: 0 | EF17: -5 | EG17: -5.9 | EH17: -0.6 | EI17: -0.4 | EK17: 2.2 | EL17: 0 | EM17: 0.7 | EN17: 0.2 | EO17: 0.2 | EP17: 0.2 | EQ17: 0 | ER17: 0 | ES17: 0 | ET17: 0 | EU17: -0.2 | EV17: 4.8 | EW17: 0 | EX17: 0 | EY17: 2 | EZ17: 0.8 | FA17: 0.8 | FB17: 0.4 | FC17: 0 | FD17: 0.2 | FE17: 1.4 | FF17: 1.1 | FG17: 1.9 | FH17: 6.9 | FI17: 0.3 | FJ17: 3.8 | FK17: 0 | FL17: 2.5 | FM17: 4.4 | FN17: 4.06 | FO17: 71.16 | FQ17: 1.9 | FR17: -0.057 | FS17: 2.3 | FT17: 1.7 | FU17: 1.97548 | FV17: 0.08524 | FW17: -1.7 | FX17: 0.4 | FY17: 6.60372
A18: 12/02/2026 | B18: 04:00 | C18: 37 | D18: -15.9 | E18: 9.6 | H18: -14.8 | I18: -0.7 | K18: 1.2 | L18: -28.6 | M18: -45.7 | N18: -16.8 | O18: 7.6 | P18: -22.9 | Q18: -15.9 | R18: 59.9 | S18: -0.1 | X18: -2.9 | Y18: 1.3 | Z18: 0.9 | AA18: 0 | AB18: -3.2 | AD18: 9.3 | AI18: 11.8 | AJ18: -6.6 | AN18: -0.9 | AO18: 42.7 | AP18: 5.5 | AQ18: 25.6 | AR18: 6.3 | AS18: -0.4 | AT18: 2.6 | AU18: 1.3 | AY18: 10.1 | AZ18: 0 | BA18: -2 | BB18: 1.2 | BC18: 0.4 | BD18: -2.2 | BG18: 0 | BJ18: 0 | BK18: 0 | BN18: 5.5 | BO18: 0 | BP18: 0 | BQ18: 0 | BS18: -3.4 | BT18: -4.7 | CA18: -0.2 | CB18: 9 | CC18: 23.4 | CD18: 7 | CE18: 5.8 | CF18: -0.2 | CJ18: 4.6 | CK18: 7.8 | CL18: -18.3 | CM18: 0 | CR18: -22.7 | CS18: -18 | CT18: -2 | CU18: 0.6 | CV18: 1.5 | CX18: -5.2 | CY18: 0 | CZ18: 0 | DB18: 0 | DC18: 0 | DD18: -0.8 | DE18: 0 | DH18: 0 | DI18: 1 | DJ18: 0.2 | DK18: -0.8 | DL18: 0.1 | DM18: 0.6 | DO18: 0 | DP18: 0 | DQ18: -7.6 | DR18: 1.5 | DS18: 0 | DT18: 0.2 | DU18: 0.4 | DV18: 0.6 | DW18: 0 | DY18: -4.6 | DZ18: 0.1 | EA18: 3.4 | EB18: 2.9 | ED18: 0 | EE18: 0 | EF18: -5.4 | EG18: -7.3 | EH18: -0.8 | EI18: -0.7 | EK18: 2.2 | EL18: 0 | EM18: 0.8 | EN18: 0.2 | EO18: 0.2 | EP18: 0.2 | EQ18: -2.2 | ER18: 0 | ES18: 0 | ET18: 0 | EU18: -0.2 | EV18: 4.7 | EW18: 0 | EX18: 0 | EY18: 2 | EZ18: 0.8 | FA18: 0.8 | FB18: 0.4 | FC18: 0 | FD18: 0.2 | FE18: 1.4 | FF18: 1.2 | FG18: 1.9 | FH18: 6.6 | FI18: 0.4 | FJ18: 3.4 | FK18: 0 | FL18: 2.3 | FM18: 4.3 | FN18: 4.7 | FO18: 64.5 | FQ18: 1.9 | FR18: -0.015 | FS18: 2.32 | FT18: 1.9 | FU18: 1.11645 | FV18: 0.08617 | FW18: -1.8 | FX18: 0.2 | FY18: 5.70762
A19: 12/02/2026 | B19: 04:30 | C19: 32.7 | D19: -23.4 | E19: 8.8 | H19: -15 | I19: -2.1 | K19: 0.7 | L19: -30 | M19: -43.2 | N19: -14.2 | O19: 7.8 | P19: -23.3 | Q19: -16.3 | R19: 70.7 | S19: 0 | X19: -5.5 | Y19: 1.2 | Z19: 0.6 | AA19: 0 | AB19: -3.2 | AD19: 8.5 | AI19: 10 | AJ19: 6.7 | AN19: -0.8 | AO19: 42.5 | AP19: 5.3 | AQ19: 25.2 | AR19: 6.1 | AS19: -0.4 | AT19: 2.6 | AU19: -0.1 | AY19: 10.1 | AZ19: 0 | BA19: -2.2 | BB19: 1 | BC19: 0.5 | BD19: -1 | BG19: 0 | BJ19: 0 | BK19: 0 | BN19: 4.6 | BO19: 0 | BP19: 0 | BQ19: 0 | BS19: -3.3 | BT19: -4.6 | CA19: -0.2 | CB19: 9.1 | CC19: 23.1 | CD19: 6.1 | CE19: 5.8 | CF19: -0.2 | CJ19: 2.9 | CK19: 5.8 | CL19: -20.4 | CM19: 0 | CR19: -19.2 | CS19: -16.1 | CT19: -2 | CU19: 0.6 | CV19: 1.5 | CX19: -5.3 | CY19: 0 | CZ19: 0 | DB19: 0 | DC19: -0.1 | DD19: -0.9 | DE19: 0 | DH19: 0 | DI19: 1.1 | DJ19: 0.2 | DK19: -0.8 | DL19: 0.1 | DM19: 0.5 | DO19: 0 | DP19: 0 | DQ19: -7 | DR19: 3.2 | DS19: 0 | DT19: -0.1 | DU19: 0.4 | DV19: 0.6 | DW19: 0.1 | DY19: -4.6 | DZ19: 0.1 | EA19: 3.3 | EB19: 2.9 | ED19: 0 | EE19: 0 | EF19: -7.2 | EG19: -8.2 | EH19: -1.1 | EI19: -0.9 | EK19: 2.6 | EL19: -0.1 | EM19: 0.8 | EN19: 0.2 | EO19: 0.2 | EP19: 0.2 | EQ19: -1.6 | ER19: 0 | ES19: 0 | ET19: 0 | EU19: -0.2 | EV19: 0 | EW19: 0 | EX19: 0 | EY19: 2 | EZ19: 0.8 | FA19: 0.8 | FB19: 0.4 | FC19: 0 | FD19: 0.2 | FE19: 1.5 | FF19: 1.3 | FG19: 2 | FH19: 6 | FI19: 0.5 | FJ19: 2.2 | FK19: 0.4 | FL19: 3 | FM19: 4.5 | FN19: 4.31 | FO19: 62.11 | FQ19: 1.8 | FR19: 0.075 | FS19: 2.3 | FT19: 1.8 | FU19: 0.3269 | FV19: 0.14014 | FW19: -1.8 | FX19: 0.2 | FY19: 4.84204
A20: 12/02/2026 | B20: 05:00 | C20: 35.3 | D20: -14.1 | E20: 10.5 | H20: -14.1 | I20: -0.9 | K20: 0.8 | L20: -26.5 | M20: -38.3 | N20: -9.9 | O20: 11.5 | P20: -21.7 | Q20: -15.8 | R20: 73.7 | S20: 0 | X20: -5.2 | Y20: 1.3 | Z20: 0.8 | AA20: 0 | AB20: -3.2 | AD20: 9 | AI20: 10.4 | AJ20: 7.4 | AN20: -0.8 | AO20: 41.9 | AP20: 5.3 | AQ20: 25.1 | AR20: 5.9 | AS20: -1.4 | AT20: 2.6 | AU20: 2.4 | AY20: 10.1 | AZ20: 0 | BA20: -2 | BB20: 1 | BC20: 0.6 | BD20: 0.4 | BG20: 0 | BJ20: 0 | BK20: 0 | BN20: 3.9 | BO20: 0 | BP20: 0 | BQ20: 0 | BS20: -2.6 | BT20: -4.3 | CA20: -0.2 | CB20: 22.9 | CC20: 23 | CD20: 5.7 | CE20: 11.7 | CF20: -0.1 | CJ20: 4.2 | CK20: 7.3 | CL20: -20 | CM20: 0 | CR20: -18 | CS20: -15.3 | CT20: -2.1 | CU20: 0.6 | CV20: 1.5 | CX20: -5.6 | CY20: 0 | CZ20: 0 | DB20: 0 | DC20: -0.1 | DD20: -0.9 | DE20: -0.1 | DH20: 0 | DI20: 1 | DJ20: 0.2 | DK20: -0.8 | DL20: 0.1 | DM20: 0.5 | DO20: 0 | DP20: 0 | DQ20: -6.7 | DR20: 3.8 | DS20: 0.2 | DT20: 0 | DU20: 0.4 | DV20: 0.6 | DW20: 0.1 | DY20: -4.6 | DZ20: 0.3 | EA20: 3.3 | EB20: 3 | ED20: 0 | EE20: 0 | EF20: -4 | EG20: -4.9 | EH20: -0.5 | EI20: -0.5 | EK20: 2.6 | EL20: -0.1 | EM20: 0.8 | EN20: 0.2 | EO20: 0.2 | EP20: 0.2 | EQ20: 0 | ER20: 0 | ES20: 0.3 | ET20: 0 | EU20: -0.2 | EV20: 0 | EW20: 0 | EX20: 0 | EY20: 2 | EZ20: 0.8 | FA20: 0.8 | FB20: 0.4 | FC20: 0.3 | FD20: 0.2 | FE20: 1.6 | FF20: 1.3 | FG20: 1.9 | FH20: 6.2 | FI20: 0.2 | FJ20: 2 | FK20: 0.7 | FL20: 2.9 | FM20: 4.5 | FN20: 4.5 | FO20: 139.4 | FQ20: 1.8 | FR20: 0.251 | FS20: 2.48 | FT20: 1.8 | FU20: 0.32494 | FV20: 0.15071 | FW20: -1.7 | FX20: 0.2 | FY20: 5.30665
A21: 12/02/2026 | B21: 05:30 | C21: 30.5 | D21: -11.1 | E21: 10.7 | H21: -12.8 | I21: 0.1 | K21: 0.6 | L21: -23.9 | M21: -34.8 | N21: -5.6 | O21: 13.6 | P21: -20.4 | Q21: -14.4 | R21: 74 | S21: 0.1 | X21: -6.5 | Y21: 1.2 | Z21: 0.8 | AA21: 0 | AB21: -3.2 | AD21: 8.1 | AI21: 8.6 | AJ21: 7.6 | AN21: -0.8 | AO21: 41.6 | AP21: 5.3 | AQ21: 25.3 | AR21: 6 | AS21: -1.8 | AT21: 2.6 | AU21: 1.5 | AY21: 10.1 | AZ21: 0 | BA21: -1.9 | BB21: 1 | BC21: 0.5 | BD21: 0.8 | BG21: 0 | BJ21: 0 | BK21: 0 | BN21: 3.7 | BO21: 0 | BP21: 0 | BQ21: 0 | BS21: -1.4 | BT21: -3.8 | CA21: -0.2 | CB21: 19.9 | CC21: 23.3 | CD21: 5.8 | CE21: 11.7 | CF21: -0.3 | CJ21: 8.3 | CK21: 11.3 | CL21: -16 | CM21: 0 | CR21: -16.7 | CS21: -14.6 | CT21: -2.1 | CU21: 0.4 | CV21: 1.5 | CX21: -5.6 | CY21: 0 | CZ21: 0 | DB21: 0 | DC21: 0 | DD21: -1 | DE21: -0.1 | DH21: 0 | DI21: 1 | DJ21: 0.2 | DK21: -0.8 | DL21: 0.1 | DM21: 0.6 | DO21: 0 | DP21: 0 | DQ21: -6.6 | DR21: 4.4 | DS21: 0.6 | DT21: 0 | DU21: 0.4 | DV21: 0.6 | DW21: 0 | DY21: -4.6 | DZ21: 0.6 | EA21: 3.3 | EB21: 3 | ED21: 0 | EE21: 0 | EF21: -4.4 | EG21: -5.2 | EH21: -0.6 | EI21: 0 | EK21: 2.6 | EL21: -0.1 | EM21: 0.8 | EN21: 0.2 | EO21: 0.2 | EP21: 0.2 | EQ21: 0 | ER21: 0 | ES21: 0.3 | ET21: 0 | EU21: -0.2 | EV21: 0 | EW21: 0 | EX21: 0 | EY21: 2 | EZ21: 0.8 | FA21: 0.8 | FB21: 0.4 | FC21: 0.3 | FD21: 0.2 | FE21: 1.5 | FF21: 1.3 | FG21: 2 | FH21: 6.2 | FI21: 0.3 | FJ21: 1.2 | FK21: 0.9 | FL21: 3.1 | FM21: 4.2 | FN21: 4.43 | FO21: 163.73 | FQ21: 1.8 | FR21: 0.463 | FS21: 2.3 | FT21: 1.7 | FU21: 0.31994 | FV21: 0.10214 | FW21: -1.6 | FX21: 0.1 | FY21: 5.18508
A22: 12/02/2026 | B22: 06:00 | C22: 29.8 | D22: -12.5 | E22: 11 | H22: -12.9 | I22: -0.2 | K22: 0.8 | L22: -25.3 | M22: -36.1 | N22: -7.4 | O22: 14.2 | P22: -19.9 | Q22: -14.6 | R22: 73.3 | S22: 0 | X22: -7.3 | Y22: 1.2 | Z22: 0.8 | AA22: 0 | AB22: -3.2 | AD22: 6.9 | AI22: 9.6 | AJ22: 5.2 | AN22: -0.8 | AO22: 41 | AP22: 5.2 | AQ22: 24.9 | AR22: 5.9 | AS22: -1.6 | AT22: 2.6 | AU22: 1.6 | AY22: 10.1 | AZ22: 0 | BA22: -2.7 | BB22: 1 | BC22: 0.6 | BD22: 1.2 | BG22: 0 | BJ22: 0 | BK22: 0 | BN22: 3.5 | BO22: 0 | BP22: 0 | BQ22: 0 | BS22: -1.8 | BT22: -4 | CA22: -0.2 | CB22: 10.3 | CC22: 23 | CD22: 6 | CE22: 11.7 | CF22: -0.2 | CJ22: 9.5 | CK22: 12.3 | CL22: -14.5 | CM22: 0 | CR22: -15.9 | CS22: -14.1 | CT22: -2 | CU22: 0.6 | CV22: 1.5 | CX22: -5.7 | CY22: 0 | CZ22: 0 | DB22: 0.1 | DC22: -0.1 | DD22: -0.9 | DE22: 0 | DH22: 0 | DI22: 1.1 | DJ22: 0.2 | DK22: -0.8 | DL22: 0.1 | DM22: 0.6 | DO22: 0 | DP22: 0 | DQ22: -6.5 | DR22: 4.3 | DS22: 0.3 | DT22: 0.1 | DU22: 0.4 | DV22: 0.6 | DW22: 0 | DY22: -4.6 | DZ22: 0.6 | EA22: 3.3 | EB22: 2.9 | ED22: 0 | EE22: 0 | EF22: -4 | EG22: -5.7 | EH22: -0.5 | EI22: 0 | EK22: 2.6 | EL22: -0.1 | EM22: 0.6 | EN22: 0.2 | EO22: 0.2 | EP22: 0.2 | EQ22: 0 | ER22: 30.9 | ES22: 1 | ET22: -0.2 | EU22: -0.2 | EV22: 0 | EW22: 0 | EX22: -1.1 | EY22: 2 | EZ22: 0.8 | FA22: 0.8 | FB22: 0.4 | FC22: 1.4 | FD22: 0.2 | FE22: 1.6 | FF22: 1.3 | FG22: 2.1 | FH22: 6.4 | FI22: 0.2 | FJ22: 0.1 | FK22: 1.2 | FL22: 2.4 | FM22: 4.4 | FN22: 4.04 | FO22: 177.34 | FQ22: 1.6 | FR22: 0.224 | FS22: 2.05 | FT22: 1.7 | FU22: 0.32709 | FV22: 0.11006 | FW22: -1.6 | FX22: 0.2 | FY22: 4.61115
... A58: 13/02/2026 | B58: 00:00 | C58: 34.2 | D58: 14.1 | E58: 12.2 | H58: -9.3 | I58: 24.6 | K58: 0 | L58: -7.2 | M58: -13.7 | N58: -9.3 | O58: 28.6 | P58: -2.8 | Q58: -11.1 | R58: 88.6 | S58: 0 | X58: 6.3 | Y58: 1.2 | Z58: 0.8 | AA58: 0 | AB58: -3.2 | AD58: 2.1 | AI58: 14.3 | AJ58: 15.6 | AN58: -1.3 | AO58: 52.9 | AP58: 5.8 | AQ58: 32 | AR58: 10.7 | AS58: -0.6 | AT58: 2.6 | AU58: 1.6 | AY58: 8.8 | AZ58: 1.4 | BA58: -0.2 | BB58: 1 | BC58: 0.6 | BD58: 4.1 | BG58: 0 | BJ58: 0 | BK58: 0 | BN58: 12.8 | BO58: 0 | BP58: 0 | BQ58: 0 | BS58: 1 | BT58: 0.2 | CA58: -0.2 | CB58: 23.1 | CC58: 29.8 | CD58: 9.5 | CE58: 9.1 | CF58: 4.1 | CJ58: 11.4 | CK58: 14.3 | CL58: -11.5 | CM58: 0 | CR58: 8.5 | CS58: 0.4 | CT58: -1.8 | CU58: 1 | CV58: 1.5 | CX58: 0 | CY58: 0 | CZ58: 0 | DB58: 0.1 | DC58: 0 | DD58: -0.9 | DE58: 0 | DH58: 0 | DI58: 1.2 | DJ58: 0.2 | DK58: 0 | DL58: 0.2 | DM58: 0.6 | DO58: 0 | DP58: 0 | DQ58: -5.7 | DR58: 6.9 | DS58: 0 | DT58: 0.1 | DU58: 0.4 | DV58: 0.7 | DW58: 0 | DY58: -4.6 | DZ58: 0 | EA58: 2.8 | EB58: 3 | ED58: 0 | EE58: 0 | EF58: -5.8 | EG58: -6.9 | EH58: -0.8 | EI58: -0.5 | EK58: 2.6 | EL58: -0.1 | EM58: 1.2 | EN58: 0.2 | EO58: 0.2 | EP58: 0.2 | EQ58: 0 | ER58: 0 | ES58: 0 | ET58: 0 | EU58: -0.2 | EV58: 4.8 | EW58: 0.8 | EX58: 0 | EY58: 2.1 | EZ58: 0.8 | FA58: 0.8 | FB58: 0.4 | FC58: 0 | FD58: 0.2 | FE58: 1.5 | FF58: 1.3 | FG58: 2.3 | FH58: 10.3 | FI58: 0.3 | FJ58: 1.3 | FK58: 0.2 | FL58: 2.2 | FM58: 4.2 | FN58: 10.27 | FO58: 457.47 | FQ58: 1.7 | FR58: 0.039 | FS58: 2.83 | FT58: 1.8 | FU58: 2.31009 | FV58: 1.36318 | FW58: -0.4 | FX58: 1.6 | FY58: 11.24227
A59: EJEC | C59: 699.65 | D59: 973.35 | E59: 495.6 | F59: 0 | G59: 0 | H59: -256.7 | I59: 253.25 | J59: 0 | K59: 2.65 | L59: 68.4 | M59: -90.25 | N59: 291.9 | O59: 854.45 | P59: 135.35 | Q59: -17.9 | R59: 1759.9 | S59: 0.65 | T59: 0 | U59: 0 | V59: 0 | W59: 0 | X59: 43.65 | Y59: 21.25 | Z59: 12.75 | AA59: 24.6 | AB59: -76.9 | AC59: 0 | AD59: 398 | AE59: 0 | AF59: 0 | AG59: 0 | AH59: 0 | AI59: 327.15 | AJ59: 187.4 | AK59: 0 | AL59: 0 | AM59: 0 | AN59: -21.35 | AO59: 1140.9 | AP59: 100.65 | AQ59: 726.7 | AR59: 118.2 | AS59: -18.5 | AT59: 62.4 | AU59: 33.3 | AV59: 0 | AW59: 0 | AX59: 0 | AY59: 243.15 | AZ59: 18.95 | BA59: 37.55 | BB59: 25.3 | BC59: 14.45 | BD59: 74.15 | BE59: 0 | BF59: 0 | BG59: 97.35 | BH59: 0 | BI59: 0 | BJ59: -5.75 | BK59: 27.8 | BL59: 0 | BM59: 0 | BN59: 187.65 | BO59: -73.3 | BP59: -8.75 | BQ59: 58.85 | BR59: 0 | BS59: 79.45 | BT59: -3.6 | BU59: 0 | BV59: 0 | BW59: 0 | BX59: 0 | BY59: 0 | BZ59: 0 | CA59: -5.8 | CB59: 872.2 | CC59: 714 | CD59: 256.35 | CE59: 235.9 | CF59: 77.1 | CG59: 0 | CH59: 0 | CI59: 0 | CJ59: 815.8 | CK59: 896.55 | CL59: -119.25 | CM59: -223.2 | CN59: 0 | CO59: 0 | CP59: 0 | CQ59: 0 | CR59: 185.95 | CS59: 13.15 | CT59: -52.75 | CU59: 14.8 | CV59: 36 | CW59: 0 | CX59: -38.8 | CY59: 68.2 | CZ59: -26.35 | DA59: 0 | DB59: 0.85 | DC59: -1.15 | DD59: -22.05 | DE59: 130.1 | DF59: 0 | DG59: 0 | DH59: 0.85 | DI59: 34.45 | DJ59: 3.75 | DK59: -3.7 | DL59: 5.85 | DM59: 13.6 | DN59: 0 | DO59: -6 | DP59: -16.15 | DQ59: -153.85 | DR59: 91.95 | DS59: 5.55 | DT59: 1.6 | DU59: 11.1 | DV59: 13.85 | DW59: 0.35 | DX59: 0 | DY59: -110.3 | DZ59: 6.4 | EA59: 72.7 | EB59: 71.4 | EC59: 0 | ED59: 31.85 | EE59: 11.6 | EF59: -142.5 | EG59: -164.9 | EH59: -17.95 | EI59: -8.8 | EJ59: 0 | EK59: 60.45 | EL59: -1.85 | EM59: 29.75 | EN59: 4.8 | EO59: 4.8 | EP59: 4.8 | EQ59: -59.6 | ER59: 187.25 | ES59: 2.9 | ET59: 132.55 | EU59: -4.8 | EV59: 60.2 | EW59: -35.75 | EX59: 79.45 | EY59: 47.8 | EZ59: 17.2 | FA59: 19.2 | FB59: 9.6 | FC59: 3.65 | FD59: 4.8 | FE59: 56.55 | FF59: 49.4 | FG59: 43 | FH59: 206.35 | FI59: 6.7 | FJ59: 52.3 | FK59: 16 | FL59: 71.55 | FM59: 97.45 | FN59: 149.105 | FO59: 13919.655 | FQ59: 34.05 | FR59: -1.258 | FS59: 57.016625 | FT59: 42.15 | FU59: 44.15872 | FV59: 30.84098 | FW59: -12.05 | FX59: 62.25 | FY59: 257.15832

Sheet DEMANDA_AREAS
B3: jueves, 12 de Febrero del 2026
B5: REPORTE DE LA DEMANDA POR ÁREAS Y SUBAREAS OPERATIVAS (MW)
B6: FECHA HORA | C6: DEMANDA | E6: AREA | H6: SUBAREAS
C7: INTERCAMBIOS INTERNACIONALES | D7: SEIN | E7: NORTE | F7: CENTRO | G7: SUR | H7: ELECTROANDES
B8: 00:30 | C8: 0 | D8: 6951.8 | E8: 1056.7433 | F8: 4224.1037 | G8: 1670.953 | H8: 246.102
B9: 01:00 | C9: 0 | D9: 6838.1 | E9: 1024.1317 | F9: 4131.8725 | G9: 1682.0958 | H9: 246.3297
B10: 01:30 | C10: 0 | D10: 6649.8 | E10: 1013.8941 | F10: 3965.6064 | G10: 1670.2995 | H10: 239.1322
B11: 02:00 | C11: 0 | D11: 6673.6 | E11: 1034.9213 | F11: 3983.2468 | G11: 1655.4319 | H11: 241.3705
B12: 02:30 | C12: 0 | D12: 6601.1 | E12: 992.1005 | F12: 3926.4805 | G12: 1682.519 | H12: 244.5926
B13: 03:00 | C13: 0 | D13: 6573.9 | E13: 972.8272 | F13: 3926.808 | G13: 1674.2648 | H13: 247.2834
B14: 03:30 | C14: 0 | D14: 6554.7 | E14: 967.4479 | F14: 3918.8278 | G14: 1668.4243 | H14: 240.7959
B15: 04:00 | C15: 0 | D15: 6495.2 | E15: 962.3463 | F15: 3852.8471 | G15: 1680.0066 | H15: 242.8738
B16: 04:30 | C16: 0 | D16: 6443.5 | E16: 967.9122 | F16: 3790.118 | G16: 1685.4698 | H16: 237.0684
B17: 05:00 | C17: 0 | D17: 6596.7 | E17: 979.0067 | F17: 3944.7144 | G17: 1672.9789 | H17: 230.5154
B18: 05:30 | C18: 0 | D18: 6649.6 | E18: 986.8532 | F18: 3976.9154 | G18: 1685.8314 | H18: 230.1996
B19: 06:00 | C19: 0 | D19: 6607.8 | E19: 1007.3938 | F19: 3955.4734 | G19: 1644.9328 | H19: 222.6759
... B59: ENERGÍA | C59: 0 | D59: 177833.45 | E59: 28418.057 | F59: 109133.72 | G59: 40281.673 | H59: 5687.1568
B61: LEYENDA:
D63: Potencia recibida del Ecuador
D64: Potencia entregada al Ecuador

Sheet DEMANDA_UL
B3: jueves, 12 de Febrero del 2026
B5: POTENCIA DE LOS GRANDES USUARIOS LIBRES (MW)
B6: FECHA HORA | C6: GRANDES USUARIOS LIBRES DEL ÁREA NORTE | X6: GRANDES USUARIOS LIBRES DEL ÁREA CENTRO | BP6: GRANDES USUARIOS LIBRES DEL ÁREA SUR
C7: ARCA CONTINENTAL LINDLEY S.A. | D7: AUSTRAL GROUP S.A.A | E7: CEMENTOS PACASMAYO | F7: CONSORCIO MINERO HORIZONTE S.R.L. | G7: CORPORACIÓN PESQUERA INCA S.A.C. | H7: CREDITEX: CIA IND.TEXTIL CREDISA | I7: HIPERMERCADOS TOTTUS S.A | J7: INDUSTRIA TEXTIL PIURA | K7: MINERA BOROO MISQUICHILCA S.A. | L7: MINERA GOLD FIELDS | M7: MINERA MARSA | N7: MINERA MISKY MAYO | O7: MINERA YANACOCHA | P7: OPEN PLAZA | Q7: PESQUERA DIAMANTE | R7: PETROPERU | S7: REAL PLAZA S.R.L. | T7: SIDER PERU | U7: SUPERMERCADOS PERUANOS S.A. | V7: TRUPAL S.A. | W7: UNIÓN DE CERVECERÍAS PERUANAS BACKUS Y JOHNSTON S. | X7: ACEROS AREQUIPA | Y7: ADMINISTRADORA JOCKEY PLAZA SHOPPING CENTER S.A. | Z7: ALICORP | AA7: ARCA CONTINENTAL LINDLEY S.A. | AB7: AUSTRAL GROUP S.A.A | AC7: COMPAÑIA MINERA CONDESTABLE | AD7: CORPORACIÓN PESQUERA INCA S.A.C. | AE7: CREDITEX: CIA IND.TEXTIL CREDISA | AF7: FUNDICION CHILCA S.A. | AG7: HIPERMERCADOS TOTTUS S.A | AH7: INMOBILIARIA KANPU S.A. | AI7: INMUEBLES PANAMERICANA S.A. | AJ7: KIMBERLY-CLARK PERU | AK7: LECHE GLORIA S.A. | AL7: MALL AVENTURA S.A. | AM7: MARCOBRE S.A.C. | AN7: MINERA ANTAMINA | AO7: MINERA ARES | AP7: MINERA BUENAVENTURA | AQ7: MINERA CHINALCO PERÚ S.A. | AR7: MINERA SHOUXIN PERU S.A. | AS7: MINERA VOLCAN | AT7: MINSUR | AU7: MOLYCOP-ADESUR | AV7: NEXA RESOURCES CAJAMARQUILLA S.A. | AW7: NEXA RESOURCES PERÚ S.A.A. | AX7: OPEN PLAZA | AY7: OPP FILM | AZ7: OWENS-ILLINOIS PERÚ S.A. | BA7: PAPELERA NACIONAL S.A. | BB7: PESQUERA DIAMANTE | BC7: QUIMPAC S.A. | BD7: REAL PLAZA S.R.L. | BE7: REFINERIA LA PAMPILLA S.A.A | BF7: SAGA FALABELLA | BG7: SAN MIGUEL INDUSTRIAS PET S.A. | BH7: SHOUGANG HIERRO PERU | BI7: SOFTYS PERU S.A.C. | BJ7: SUPERMERCADOS PERUANOS S.A. | BK7: TEJIDOS SAN JACINTO | BL7: TREN URBANO DE LIMA S.A. | BM7: TRUPAL S.A. | BN7: UNACEM PERU S.A. | BO7: UNIÓN DE CERVECERÍAS PERUANAS BACKUS Y JOHNSTON S. | BP7: ANGLO AMERICAN QUELLAVECO S.A. | BQ7: ARCA CONTINENTAL LINDLEY S.A. | BR7: CAL & CEMENTO SUR S.A. | BS7: COMPAÑIA MINERA ANTAPACCAY S.A. | BT7: COMPAÑÍA MINERA CHUNGAR SAC | BU7: COMPAÑIA MINERA SAN IGNACIO DE MOROCOCHA S.A.A. | BV7: EL BROCAL .S.A. | BW7: EMPRESA ADMINISTRADORA CERRO S.A.C. | BX7: EMPRESA MINERA LOS QUENUALES S.A.C. | BY7: HIPERMERCADOS TOTTUS S.A | BZ7: HUDBAY PERU S.A.C. | CA7: INDUSTRIA CACHIMAYO | CB7: MALL AVENTURA S.A. | CC7: MINERA ARES | CD7: MINERA BUENAVENTURA | CE7: MINERA CERRO VERDE | CF7: MINERA CORONA | CG7: MINERA LAS BAMBAS S.A. | CH7: MINERA VOLCAN | CI7: MINSUR | CJ7: MOLYCOP-ADESUR | CK7: NEXA RESOURCES PERÚ S.A.A. | CL7: OXIDOS DE PASCO S.A.C. | CM7: PESQUERA DIAMANTE | CN7: REAL PLAZA S.R.L. | CO7: SOBREANDES S.A.C. | CP7: SOUTHERN PERU CC | CQ7: SUPERMERCADOS PERUANOS S.A. | CR7: UNACEM PERU S.A. | CS7: UNIÓN DE CERVECERÍAS PERUANAS BACKUS Y JOHNSTON S. | CT7: YURA
B8: 00:30 | E8: 43.47224 | F8: 12.191 | K8: 15.5579 | L8: 26.4523 | M8: 14.8225 | N8: 14.17 | O8: 32.256 | R8: 44.839 | T8: 52.5252 | V8: 1.3 | X8: 149.60711 | Z8: 9.55911 | AC8: 15.66 | AF8: 2.8 | AJ8: 5.33786 | AK8: 0 | AL8: 1.3555 | AM8: 48.56969 | AN8: 121.60203 | AO8: 26.732 | AP8: 0.81 | AQ8: 162.69 | AS8: 37.575 | AT8: 31.71117 | AV8: 198.75527 | AW8: 29.375 | AY8: 4.75 | BA8: 1.3 | BC8: 58.13533 | BE8: 18.3 | BI8: 19.74399 | BK8: 4.88872 | BN8: 52.022 | BO8: 2.15 | BP8: 140.42501 | BR8: 4.15986 | BS8: 136.33505 | BT8: 12.33565 | BV8: 35.9358 | BW8: 3.85819 | BZ8: 89.7185 | CA8: 23.90942 | CB8: 0.3969 | CC8: 0.576 | CD8: 25.6211 | CE8: 301.01906 | CG8: 134.52229 | CH8: 18.191 | CK8: 15.5723 | CL8: 4.76132 | CO8: 16.0343 | CP8: 296.34 | CR8: 31.209 | CT8: 29.126
B9: 01:00 | E9: 45.87038 | F9: 12.285 | K9: 13.9441 | L9: 25.2762 | M9: 14.9044 | N9: 14.16 | O9: 32.26 | R9: 44.993 | T9: 27.1074 | V9: 1.3 | X9: 143.988 | Z9: 9.8497 | AC9: 15.6 | AF9: 4 | AJ9: 5.33431 | AK9: 0 | AL9: 1.2276 | AM9: 49.71371 | AN9: 121.4499 | AO9: 27.3797 | AP9: 0.7 | AQ9: 163.84 | AS9: 37.347 | AT9: 34.83609 | AV9: 198.77266 | AW9: 29.2035 | AY9: 4.65 | BA9: 1.3 | BC9: 69.29703 | BE9: 18.3 | BI9: 19.51061 | BK9: 4.85388 | BN9: 52.162 | BO9: 2.38 | BP9: 139.76572 | BR9: 4.20109 | BS9: 136.55983 | BT9: 11.52194 | BV9: 36.2117 | BW9: 3.96348 | BZ9: 90.9923 | CA9: 23.98253 | CB9: 0.3756 | CC9: 0.577 | CD9: 26.86295 | CE9: 302.38201 | CG9: 140.18954 | CH9: 18.022 | CK9: 15.3499 | CL9: 4.92928 | CO9: 16.44942 | CP9: 295.22 | CR9: 30.701 | CT9: 30.047
B10: 01:30 | E10: 45.40672 | F10: 11.918 | K10: 14.9431 | L10: 25.2946 | M10: 14.5309 | N10: 13.61 | O10: 31.816 | R10: 45.243 | T10: 35.8723 | V10: 1.2 | X10: 121.82028 | Z10: 9.7329 | AC10: 15.41 | AF10: 4.6 | AJ10: 5.31128 | AK10: 0 | AL10: 1.1257 | AM10: 48.02339 | AN10: 122.76469 | AO10: 29.0658 | AP10: 0.64 | AQ10: 162.46 | AS10: 37.494 | AT10: 34.79557 | AV10: 198.53697 | AW10: 29.3208 | AY10: 4.64 | BA10: 1.3 | BC10: 69.26557 | BE10: 18.3 | BI10: 19.44863 | BK10: 4.99944 | BN10: 48.916 | BO10: 2.41 | BP10: 145.46638 | BR10: 4.33142 | BS10: 134.32609 | BT10: 11.71758 | BV10: 36.3293 | BW10: 4.0073 | BZ10: 92.2619 | CA10: 23.97778 | CB10: 0.3592 | CC10: 0.573 | CD10: 26.01493 | CE10: 309.66886 | CG10: 133.86813 | CH10: 18.078 | CK10: 15.451 | CL10: 4.95863 | CO10: 15.32238 | CP10: 291.56 | CR10: 31.764 | CT10: 30.223
B11: 02:00 | E11: 47.54064 | F11: 11.661 | K11: 14.8824 | L11: 25.8405 | M11: 14.5561 | N11: 12.16 | O11: 32.068 | R11: 45.232 | T11: 48.3471 | V11: 1.2 | X11: 100.43581 | Z11: 9.47047 | AC11: 15.31 | AF11: 3.6 | AJ11: 5.27359 | AK11: 0 | AL11: 1.1173 | AM11: 48.95855 | AN11: 121.73744 | AO11: 28.5497 | AP11: 0.44 | AQ11: 161.25 | AS11: 36.626 | AT11: 34.59298 | AV11: 198.09597 | AW11: 29.9813 | AY11: 4.81 | BA11: 1.2 | BC11: 69.27008 | BE11: 18.3 | BI11: 19.48858 | BK11: 4.88144 | BN11: 42.719 | BO11: 2.49 | BP11: 145.39343 | BR11: 4.23779 | BS11: 135.2238 | BT11: 12.3173 | BV11: 35.2196 | BW11: 3.7307 | BZ11: 92.9345 | CA11: 24.04047 | CB11: 0.3444 | CC11: 0.571 | CD11: 27.37548 | CE11: 311.23836 | CG11: 132.86888 | CH11: 18.15 | CK11: 15.5167 | CL11: 4.91405 | CO11: 13.39973 | CP11: 284.04 | CR11: 31.922 | CT11: 29.109
B12: 02:30 | E12: 43.73302 | F12: 11.43 | K12: 15.2273 | L12: 23.0985 | M12: 13.735 | N12: 14.06 | O12: 31.71 | R12: 45.021 | T12: 35.2011 | V12: 1.2 | X12: 106.76665 | Z12: 9.43673 | AC12: 15.33 | AF12: 1.5 | AJ12: 5.22184 | AK12: 0 | AL12: 1.101 | AM12: 48.74119 | AN12: 122.2102 | AO12: 28.9158 | AP12: 0.41 | AQ12: 161.03 | AS12: 37.247 | AT12: 34.17261 | AV12: 197.87809 | AW12: 31.5636 | AY12: 5.03 | BA12: 1.2 | BC12: 69.32979 | BE12: 18.3 | BI12: 19.75256 | BK12: 4.7655 | BN12: 43.446 | BO12: 2.4 | BP12: 144.14501 | BR12: 4.18146 | BS12: 135.29986 | BT12: 11.76529 | BV12: 34.9978 | BW12: 3.87202 | BZ12: 92.5933 | CA12: 24.17293 | CB12: 0.3393 | CC12: 0.555 | CD12: 27.65755 | CE12: 316.25143 | CG12: 135.38405 | CH12: 17.91 | CK12: 16.4276 | CL12: 4.76486 | CO12: 15.24233 | CP12: 282.16 | CR12: 32.113 | CT12: 29.997
B13: 03:00 | E13: 45.71343 | F13: 11.538 | K13: 13.8896 | L13: 21.9458 | M13: 13.6195 | N13: 14.15 | O13: 32.084 | R13: 45.39 | T13: 29.4303 | V13: 1.2 | X13: 130.05361 | Z13: 9.48462 | AC13: 14.98 | AF13: 2.5 | AJ13: 4.81592 | AK13: 0 | AL13: 1.0909 | AM13: 48.97227 | AN13: 122.4785 | AO13: 29.4698 | AP13: 0.67 | AQ13: 162.95 | AS13: 37.135 | AT13: 33.65715 | AV13: 197.99555 | AW13: 31.6377 | AY13: 4.91 | BA13: 1.2 | BC13: 68.71139 | BE13: 18.3 | BI13: 19.41675 | BK13: 4.83341 | BN13: 43.35 | BO13: 2.28 | BP13: 141.76547 | BR13: 4.23802 | BS13: 134.605 | BT13: 11.77866 | BV13: 36.0675 | BW13: 3.96593 | BZ13: 92.6654 | CA13: 24.18614 | CB13: 0.3376 | CC13: 0.575 | CD13: 27.2142 | CE13: 311.49081 | CG13: 141.50181 | CH13: 17.528 | CK13: 15.8392 | CL13: 4.7857 | CO13: 15.93589 | CP13: 290.07 | CR13: 31.645 | CT13: 30.211
B14: 03:30 | E14: 49.36481 | F14: 11.655 | K14: 15.957 | L14: 21.937 | M14: 14.0299 | N14: 14.26 | O14: 31.95 | R14: 44.951 | T14: 18.1526 | V14: 1.2 | X14: 143.06636 | Z14: 9.33023 | AC14: 14.56 | AF14: 2.8 | AJ14: 5.05719 | AK14: 0 | AL14: 1.0497 | AM14: 49.82508 | AN14: 121.60782 | AO14: 28.1339 | AP14: 0.48 | AQ14: 163.35 | AS14: 38.036 | AT14: 32.6691 | AV14: 197.59498 | AW14: 31.8085 | AY14: 5.28 | BA14: 1.2 | BC14: 68.90927 | BE14: 18.3 | BI14: 19.75046 | BK14: 4.93352 | BN14: 49.248 | BO14: 2.34 | BP14: 142.18613 | BR14: 4.16682 | BS14: 135.07458 | BT14: 11.41448 | BV14: 36.8063 | BW14: 4.02736 | BZ14: 90.8337 | CA14: 24.20338 | CB14: 0.3275 | CC14: 0.589 | CD14: 26.37391 | CE14: 316.25408 | CG14: 140.20502 | CH14: 18.062 | CK14: 15.0897 | CL14: 4.82772 | CO14: 16.1575 | CP14: 286.15 | CR14: 31.335 | CT14: 29.994
B15: 04:00 | E15: 49.85811 | F15: 11.398 | K15: 15.6213 | L15: 22.4648 | M15: 14.3132 | N15: 14.37 | O15: 31.312 | R15: 45.008 | T15: 14.178 | V15: 1.2 | X15: 74.28768 | Z15: 9.38279 | AC15: 14.48 | AF15: 4.9 | AJ15: 5.19055 | AK15: 0 | AL15: 1.0582 | AM15: 50.14435 | AN15: 123.25057 | AO15: 28.1813 | AP15: 0.18 | AQ15: 163.14 | AS15: 37.22 | AT15: 31.76709 | AV15: 198.12535 | AW15: 31.4576 | AY15: 5.17 | BA15: 1.2 | BC15: 68.99176 | BE15: 18.3 | BI15: 19.5446 | BK15: 4.88123 | BN15: 55.525 | BO15: 2.29 | BP15: 143.82394 | BR15: 4.12421 | BS15: 134.18561 | BT15: 10.77162 | BV15: 37.4637 | BW15: 3.88656 | BZ15: 90.77 | CA15: 24.205 | CB15: 0.318 | CC15: 0.569 | CD15: 26.38933 | CE15: 318.18369 | CG15: 138.20502 | CH15: 18.149 | CK15: 14.7498 | CL15: 4.84819 | CO15: 16.20584 | CP15: 289.61 | CR15: 31.368 | CT15: 29.197
B16: 04:30 | E16: 49.72983 | F16: 10.741 | K16: 15.5956 | L16: 23.0823 | M16: 14.8853 | N16: 14.21 | O16: 31.956 | R16: 44.874 | T16: 13.3157 | V16: 1.2 | X16: 137.83833 | Z16: 9.46945 | AC16: 14.25 | AF16: 5.5 | AJ16: 5.28152 | AK16: 0 | AL16: 1.0498 | AM16: 49.45636 | AN16: 123.1497 | AO16: 29.1416 | AP16: 1.65 | AQ16: 161.92 | AS16: 36.462 | AT16: 31.95563 | AV16: 197.42986 | AW16: 31.3316 | AY16: 4.52 | BA16: 1.2 | BC16: 68.98811 | BE16: 18.3 | BI16: 19.86 | BK16: 4.90518 | BN16: 55.664 | BO16: 2.33 | BP16: 143.1055 | BR16: 4.23814 | BS16: 134.78366 | BT16: 10.83519 | BV16: 36.0482 | BW16: 3.90366 | BZ16: 91.1163 | CA16: 24.20921 | CB16: 0.3145 | CC16: 0.588 | CD16: 25.77062 | CE16: 317.5024 | CG16: 135.61861 | CH16: 17.918 | CK16: 14.1587 | CL16: 5.01929 | CO16: 15.98385 | CP16: 290.78 | CR16: 31.242 | CT16: 29.682
B17: 05:00 | E17: 49.72827 | F17: 11.021 | K17: 15.8386 | L17: 27.0837 | M17: 15.5501 | N17: 14.03 | O17: 32.76 | R17: 44.625 | T17: 15.5212 | V17: 1.2 | X17: 143.65334 | Z17: 9.32604 | AC17: 14.29 | AF17: 3.1 | AJ17: 5.03627 | AK17: 0 | AL17: 1.0674 | AM17: 48.3504 | AN17: 124.11973 | AO17: 28.1498 | AP17: 2.1 | AQ17: 162.23 | AS17: 35.932 | AT17: 31.33166 | AV17: 197.0914 | AW17: 31.1027 | AY17: 4.63 | BA17: 1.2 | BC17: 68.9053 | BE17: 18.3 | BI17: 19.8494 | BK17: 4.68188 | BN17: 55.662 | BO17: 2.35 | BP17: 138.46075 | BR17: 4.2298 | BS17: 135.37708 | BT17: 10.62897 | BV17: 35.5328 | BW17: 4.37541 | BZ17: 88.8616 | CA17: 24.22031 | CB17: 0.3163 | CC17: 0.611 | CD17: 24.26726 | CE17: 312.87766 | CG17: 133.56484 | CH17: 17.727 | CK17: 14.0946 | CL17: 4.98659 | CO17: 15.71336 | CP17: 292.52 | CR17: 31.673 | CT17: 29.89
B18: 05:30 | E18: 49.52327 | F18: 9.766 | K18: 15.956 | L18: 27.1977 | M18: 15.9012 | N18: 14.23 | O18: 32.758 | R18: 44.842 | T18: 15.4665 | V18: 1.2 | X18: 141.92738 | Z18: 9.47571 | AC18: 14.93 | AF18: 1.7 | AJ18: 5.08865 | AK18: 0 | AL18: 1.066 | AM18: 49.9898 | AN18: 122.65317 | AO18: 26.9775 | AP18: 1.93 | AQ18: 163.09 | AS18: 35.107 | AT18: 31.5907 | AV18: 197.78305 | AW18: 29.5265 | AY18: 5.12 | BA18: 1.2 | BC18: 69.08208 | BE18: 18.3 | BI18: 19.87231 | BK18: 4.70601 | BN18: 55.322 | BO18: 2.38 | BP18: 141.22541 | BR18: 4.20735 | BS18: 133.18587 | BT18: 10.21441 | BV18: 35.8301 | BW18: 3.85894 | BZ18: 74.8185 | CA18: 24.22676 | CB18: 0.3124 | CC18: 0.486 | CD18: 24.74093 | CE18: 312.98655 | CG18: 134.37115 | CH18: 18.193 | CK18: 14.326 | CL18: 4.83292 | CO18: 14.27484 | CP18: 292.89 | CR18: 31.685 | CT18: 30.093
B19: 06:00 | E19: 48.94481 | F19: 9.286 | K19: 15.6184 | L19: 27.4848 | M19: 15.3308 | N19: 13.98 | O19: 32.59 | R19: 44.442 | T19: 13.8193 | V19: 1.2 | X19: 120.96582 | Z19: 9.61101 | AC19: 15.57 | AF19: 2.8 | AJ19: 5.10208 | AK19: 0 | AL19: 1.1695 | AM19: 49.6328 | AN19: 125.95226 | AO19: 22.2376 | AP19: 1.54 | AQ19: 157.92 | AS19: 34.419 | AT19: 31.62755 | AV19: 197.86901 | AW19: 28.4671 | AY19: 4.88 | BA19: 1.2 | BC19: 52.41196 | BE19: 18.3 | BI19: 19.71994 | BK19: 4.65477 | BN19: 49.96 | BO19: 2.28 | BP19: 143.60277 | BR19: 4.18926 | BS19: 129.00877 | BT19: 9.81273 | BV19: 35.6953 | BW19: 3.65085 | BZ19: 57.5213 | CA19: 24.1922 | CB19: 0.3096 | CC19: 0.652 | CD19: 24.64623 | CE19: 314.96357 | CG19: 136.07066 | CH19: 18.069 | CK19: 14.0817 | CL19: 4.75621 | CO19: 13.71255 | CP19: 292.25 | CR19: 30.754 | CT19: 29.773
... B55: 00:00 | E55: 44.19218 | F55: 11.286 | K55: 13.9399 | L55: 22.9509 | M55: 14.0498 | N55: 14.25 | O55: 32.236 | R55: 48.281 | T55: 41.6279 | V55: 1 | X55: 152.35383 | Z55: 9.75012 | AC55: 16.02 | AF55: 3.7 | AJ55: 5.27586 | AK55: 0 | AL55: 1.6368 | AM55: 48.97571 | AN55: 123.74726 | AO55: 28.2719 | AP55: 0.83 | AQ55: 151.66 | AS55: 37.132 | AT55: 30.24296 | AV55: 199.16838 | AW55: 33.2825 | AY55: 5.17 | BA55: 1.2 | BC55: 43.11677 | BE55: 18.9 | BI55: 17.95592 | BK55: 5.31516 | BN55: 48.278 | BO55: 2.34 | BP55: 147.19666 | BR55: 4.4115 | BS55: 132.77475 | BT55: 10.25858 | BV55: 36.9086 | BW55: 3.83695 | BZ55: 3.6705 | CA55: 24.21887 | CB55: 0.4818 | CC55: 0.563 | CD55: 26.73958 | CE55: 304.84215 | CG55: 140.39812 | CH55: 17.849 | CK55: 15.7552 | CL55: 5.26639 | CO55: 15.98634 | CP55: 280.77 | CR55: 26.467 | CT55: 19.678
B56: MWh | C56: 0 | D56: 0 | E56: 963.86242 | F56: 262.0815 | G56: 0 | H56: 0 | I56: 0 | J56: 0 | K56: 358.93315 | L56: 640.49285 | M56: 318.1908 | N56: 327.985 | O56: 768.766 | P56: 0 | Q56: 0 | R56: 1089.6675 | S56: 0 | T56: 821.6714 | U56: 0 | V56: 27.95 | W56: 0 | X56: 2246.819 | Y56: 0 | Z56: 227.1937 | AA56: 0 | AB56: 0 | AC56: 381.22 | AD56: 0 | AE56: 0 | AF56: 74 | AG56: 0 | AH56: 0 | AI56: 0 | AJ56: 118.96792 | AK56: 0 | AL56: 71.54745 | AM56: 1148.4473 | AN56: 2863.1721 | AO56: 656.4872 | AP56: 18.01 | AQ56: 3690.845 | AR56: 0 | AS56: 856.7385 | AT56: 765.87763 | AU56: 0 | AV56: 3964.4115 | AW56: 746.0637 | AX56: 0 | AY56: 114.59 | AZ56: 0 | BA56: 29.95 | BB56: 0 | BC56: 1197.7715 | BD56: 0 | BE56: 441.7 | BF56: 0 | BG56: 0 | BH56: 0 | BI56: 460.41364 | BJ56: 0 | BK56: 116.23944 | BL56: 0 | BM56: 0 | BN56: 915.083 | BO56: 55.25 | BP56: 3328.8726 | BQ56: 0 | BR56: 102.6923 | BS56: 3159.4769 | BT56: 249.20371 | BU56: 0 | BV56: 847.03085 | BW56: 93.385435 | BX56: 0 | BY56: 0 | BZ56: 662.0564 | CA56: 488.40484 | CB56: 22.7953 | CC56: 14.1895 | CD56: 613.73346 | CE56: 7312.0001 | CF56: 0 | CG56: 3303.9663 | CH56: 424.1775 | CI56: 0 | CJ56: 0 | CK56: 352.1489 | CL56: 116.08119 | CM56: 0 | CN56: 0 | CO56: 356.33929 | CP56: 6707.57 | CQ56: 0 | CR56: 691.162 | CS56: 0 | CT56: 659.052
B59: Nota :
B60: Información proporcionada por la empresas
C62: DATOS ESTIMADOS
C64: SIN DATOS

Sheet TIPO_RECURSO
B3: jueves, 12 de Febrero del 2026
B5: REPORTE POTENCIA GENERADA POR TIPO DE RECURSO
B6: HORA | C6: H. PASADA | D6: H. REGULACION | E6: GAS DE CAMISEA | F6: GAS DE MALACAS | G6: GAS DE AGUAYTIA | H6: DIÉSEL | I6: RESIDUAL | J6: NAFTA+GAS DE REFINERIA | K6: FLEXIGAS+GAS DE REFINERIA | L6: BAGAZO | M6: BIOGÁS | N6: SOLAR | O6: EÓLICA | P6: TOTAL | U6: EMPRESA | V6: CENTRAL | W6: HIDROELECTRICA DE PASADA | X6: HIDROELECTRICA DE REGULACION
B7: 00:30 | C7: 1164.8 | D7: 3394.5 | E7: 1815.8 | F7: 0 | G7: 59.6 | H7: 0 | K7: =DESPACHO_EJECUTADO!FH11+DESPACHO_EJECUTADO!FI11 -> 61.8 | L7: 71.9 | M7: 9.4 | N7: 0 | O7: 374 | P7: =SUM(C7:O7) -> 6951.8 | U7: ANDEAN POWER S.A.C. | V7: C.H.CARHUAC | W7: 228.45
B8: 01:00 | C8: 1176.3 | D8: 3387.5 | E8: 1792.2 | F8: 0 | G8: 61.7 | H8: 0 | K8: =DESPACHO_EJECUTADO!FH12+DESPACHO_EJECUTADO!FI12 -> 61.7 | L8: 65.6 | M8: 9.4 | N8: 0 | O8: 283.7 | P8: =SUM(C8:O8) -> 6838.1 | U8: ASOCIACIÓN SANTA LUCIA DE CHACAS | V8: C.H. HUALLIN | W8: 64.95
B9: 01:30 | C9: 1162.8 | D9: 3307.4 | E9: 1722.2 | F9: 0 | G9: 58.9 | H9: 0 | K9: =DESPACHO_EJECUTADO!FH13+DESPACHO_EJECUTADO!FI13 -> 62.3 | L9: 67.1 | M9: 9.4 | N9: 0 | O9: 259.7 | P9: =SUM(C9:O9) -> 6649.8 | U9: ATRIA ENERGIA S.A.C. | V9: C.H. PURMACANA | W9: 9.6
B10: 02:00 | C10: 1177.5 | D10: 3343.3 | E10: 1703.3 | F10: 0 | G10: 61.3 | H10: 0 | K10: =DESPACHO_EJECUTADO!FH14+DESPACHO_EJECUTADO!FI14 -> 62.4 | L10: 67.6 | M10: 9.4 | N10: 0 | O10: 248.8 | P10: =SUM(C10:O10) -> 6673.6 | U10: CELARIS ENERGY S.A. | V10: C.H. MANTA I | W10: 480.3
B11: 02:30 | C11: 1187.5 | D11: 3335.4 | E11: 1665.3 | F11: 0 | G11: 60.7 | H11: 0 | K11: =DESPACHO_EJECUTADO!FH15+DESPACHO_EJECUTADO!FI15 -> 62.5 | L11: 69.9 | M11: 9.4 | N11: 0 | O11: 210.4 | P11: =SUM(C11:O11) -> 6601.1 | U11: CELEPSA | V11: C.H. EL PLATANAL | X11: 4995.15
B12: 03:00 | C12: 1180.3 | D12: 3215.4 | E12: 1786.7 | F12: 0 | G12: 60.7 | H12: 0 | K12: =DESPACHO_EJECUTADO!FH16+DESPACHO_EJECUTADO!FI16 -> 62.5 | L12: 69.6 | M12: 9.4 | N12: 0 | O12: 189.3 | P12: =SUM(C12:O12) -> 6573.9 | U12: CELEPSA RENOVABLES S.R.L. | V12: C.H. MARAÑON | W12: 453.6
B13: 03:30 | C13: 1179.7 | D13: 3235.5 | E13: 1788.7 | F13: 0 | G13: 60.7 | H13: 0 | K13: =DESPACHO_EJECUTADO!FH17+DESPACHO_EJECUTADO!FI17 -> 62.7 | L13: 69.3 | M13: 9.4 | N13: 0 | O13: 148.7 | P13: =SUM(C13:O13) -> 6554.7 | U13: CHINANGO S.A.C. | V13: C.H. CHIMAY | X13: 3622.2
B14: 04:00 | C14: 1186.8 | D14: 3326.8 | E14: 1649 | F14: 0 | G14: 62.1 | H14: 0 | K14: =DESPACHO_EJECUTADO!FH18+DESPACHO_EJECUTADO!FI18 -> 62.5 | L14: 68.8 | M14: 9.4 | N14: 0 | O14: 129.8 | P14: =SUM(C14:O14) -> 6495.2 | V14: C.H. YANANGO | W14: 792.85
B15: 04:30 | C15: 1182.9 | D15: 3298.1 | E15: 1665.7 | F15: 0 | G15: 59.7 | H15: 0 | K15: =DESPACHO_EJECUTADO!FH19+DESPACHO_EJECUTADO!FI19 -> 63.2 | L15: 69 | M15: 9.4 | N15: 0 | O15: 95.5 | P15: =SUM(C15:O15) -> 6443.5 | U15: EGASA | V15: C.H. CHARCANI III | W15: 160.7
B16: 05:00 | C16: 1187.2 | D16: 3372 | E16: 1761.9 | F16: 0 | G16: 59.8 | H16: 0 | K16: =DESPACHO_EJECUTADO!FH20+DESPACHO_EJECUTADO!FI20 -> 62.4 | L16: 68 | M16: 9.4 | N16: 0 | O16: 76 | P16: =SUM(C16:O16) -> 6596.7 | V16: C.H. CHARCANI V | X16: 3420.1
B17: 05:30 | C17: 1181.1 | D17: 3331 | E17: 1875.2 | F17: 0 | G17: 59.7 | H17: 0 | K17: =DESPACHO_EJECUTADO!FH21+DESPACHO_EJECUTADO!FI21 -> 62.5 | L17: 68.7 | M17: 9.4 | N17: 0 | O17: 62 | P17: =SUM(C17:O17) -> 6649.6 | U17: EGEJUNIN | V17: C.H. HUASAHUASI I | W17: 467.25
B18: 06:00 | C18: 1185.1 | D18: 3330.1 | E18: 1827.3 | F18: 0 | G18: 60.2 | H18: 0 | K18: =DESPACHO_EJECUTADO!FH22+DESPACHO_EJECUTADO!FI22 -> 62.4 | L18: 70.6 | M18: 9.4 | N18: 12.2 | O18: 50.5 | P18: =SUM(C18:O18) -> 6607.8 | V18: C.H. RUNATULLO II | W18: 479.2
B19: 06:30 | C19: 1159.1 | D19: 3273.7 | E19: 1833.8 | F19: 0 | G19: 58.9 | H19: 0 | K19: =DESPACHO_EJECUTADO!FH23+DESPACHO_EJECUTADO!FI23 -> 62.2 | L19: 69.6 | M19: 9.4 | N19: 96.8 | O19: 37.1 | P19: =SUM(C19:O19) -> 6600.6 | V19: C.H. RUNATULLO III | W19: 484.65
B20: 07:00 | C20: 1206.7 | D20: 3319.9 | E20: 1716.6 | F20: 0 | G20: 0 | H20: 0 | K20: =DESPACHO_EJECUTADO!FH24+DESPACHO_EJECUTADO!FI24 -> 62.2 | L20: 69.9 | M20: 9.4 | N20: 184.5 | O20: 42.3 | P20: =SUM(C20:O20) -> 6611.5 | V20: C.H. SANTA CRUZ I | W20: 176.9
B21: 07:30 | C21: 1202.8 | D21: 3451.1 | E21: 1961.8 | F21: 3.4 | G21: 0 | H21: 0 | K21: =DESPACHO_EJECUTADO!FH25+DESPACHO_EJECUTADO!FI25 -> 62.5 | L21: 69.9 | M21: 9.4 | N21: 243.4 | O21: 49.6 | P21: =SUM(C21:O21) -> 7053.9 | U21: EGEMSA | V21: C.H. MACHUPICCHU | W21: 3979.95
B22: 08:00 | C22: 1208.9 | D22: 3316 | E22: 1941.4 | F22: 43.7 | G22: 0 | H22: 0 | K22: =DESPACHO_EJECUTADO!FH26+DESPACHO_EJECUTADO!FI26 -> 62.5 | L22: 70.1 | M22: 9.4 | N22: 437.8 | O22: 79.9 | P22: =SUM(C22:O22) -> 7169.7 | U22: EGESUR | V22: C.H. ARICOTA I | X22: 190.5
B23: 08:30 | C23: 1195.6 | D23: 3424.3 | E23: 1976.1 | F23: 44.7 | G23: 0 | H23: 0 | K23: =DESPACHO_EJECUTADO!FH27+DESPACHO_EJECUTADO!FI27 -> 62.3 | L23: 69.5 | M23: 9.4 | N23: 599.1 | O23: 87.7 | P23: =SUM(C23:O23) -> 7468.7 | V23: C.H. ARICOTA II | X23: 134.05
B24: 09:00 | C24: 1190 | D24: 3515.6 | E24: 2127.3 | F24: 43.9 | G24: 0 | H24: 0 | K24: =DESPACHO_EJECUTADO!FH28+DESPACHO_EJECUTADO!FI28 -> 61.9 | L24: 68.8 | M24: 9.3 | N24: 615.2 | O24: 106.7 | P24: =SUM(C24:O24) -> 7738.7 | U24: ELECTRICA YANAPAMPA SAC | V24: C.H. YANAPAMPA | W24: 80.05
B25: 09:30 | C25: 1195.8 | D25: 3514.7 | E25: 2143.3 | F25: 43.8 | G25: 0 | H25: 0 | K25: =DESPACHO_EJECUTADO!FH29+DESPACHO_EJECUTADO!FI29 -> 62.1 | L25: 59.8 | M25: 9.2 | N25: 613.6 | O25: 118.5 | P25: =SUM(C25:O25) -> 7760.8 | U25: ELECTROPERU | V25: C.H. MANTARO | X25: 15245.95
B26: 10:00 | C26: 1191.9 | D26: 3546.7 | E26: 2248.8 | F26: 43.4 | G26: 0 | H26: 0 | K26: =DESPACHO_EJECUTADO!FH30+DESPACHO_EJECUTADO!FI30 -> 61.9 | L26: 65 | M26: 9.2 | N26: 562.7 | O26: 155.5 | P26: =SUM(C26:O26) -> 7885.1 | V26: C.H. RESTITUCION | W26: 5175.1
B27: 10:30 | C27: 1195.7 | D27: 3564.6 | E27: 2298.3 | F27: 43.1 | G27: 0 | H27: 0 | K27: =DESPACHO_EJECUTADO!FH31+DESPACHO_EJECUTADO!FI31 -> 61.6 | L27: 64.1 | M27: 9.2 | N27: 606.7 | O27: 187.9 | P27: =SUM(C27:O27) -> 8031.2 | U27: EMPRESA DE GENERACION ELECTRICA CANCHAYLLO SAC | V27: C.H. CANCHAYLLO | W27: 115.85
B28: 11:00 | C28: 1150.3 | D28: 3517.4 | E28: 2342.2 | F28: 42.3 | G28: 0 | H28: 0 | K28: =DESPACHO_EJECUTADO!FH32+DESPACHO_EJECUTADO!FI32 -> 62.1 | L28: 63.6 | M28: 9.2 | N28: 737.4 | O28: 195.7 | P28: =SUM(C28:O28) -> 8120.2 | U28: EMPRESA DE GENERACION ELECTRICA SANTA ANA S.A.C. | V28: C.H. RENOVANDES H1 | W28: 413.75
B29: 11:30 | C29: 1134.9 | D29: 3421.4 | E29: 2242.3 | F29: 43.5 | G29: 0 | H29: 0 | K29: =DESPACHO_EJECUTADO!FH33+DESPACHO_EJECUTADO!FI33 -> 62.6 | L29: 63.5 | M29: 9.2 | N29: 825.7 | O29: 225.6 | P29: =SUM(C29:O29) -> 8028.7 | U29: EMPRESA DE GENERACION HUALLAGA | V29: C.H. CHAGLLA | X29: 10999.6
B30: 12:00 | C30: 1118.7 | D30: 3436.9 | E30: 2140.3 | F30: 44.2 | G30: 0 | H30: 0 | K30: =DESPACHO_EJECUTADO!FH34+DESPACHO_EJECUTADO!FI34 -> 62.3 | L30: 65.4 | M30: 9.2 | N30: 905.9 | O30: 279 | P30: =SUM(C30:O30) -> 8061.9 | V30: P.C.H. CHAGLLA | W30: 156
B31: 12:30 | C31: 1168.1 | D31: 3468.9 | E31: 2085.8 | F31: 43.6 | G31: 0 | H31: 0 | K31: =DESPACHO_EJECUTADO!FH35+DESPACHO_EJECUTADO!FI35 -> 61.7 | L31: 65.6 | M31: 9.2 | N31: 736.2 | O31: 308 | P31: =SUM(C31:O31) -> 7947.1 | U31: EMPRESA DE GENERACION HUANZA | V31: C.H. HUANZA | X31: 689.95
B32: 13:00 | C32: 1126.9 | D32: 3428.7 | E32: 2076.9 | F32: 44.2 | G32: 0 | H32: 0 | K32: =DESPACHO_EJECUTADO!FH36+DESPACHO_EJECUTADO!FI36 -> 61.7 | L32: 65.8 | M32: 9.2 | N32: 840.8 | O32: 317.6 | P32: =SUM(C32:O32) -> 7971.8 | U32: EMPRESA ELECTRICA AGUA AZUL | V32: C.H. POTRERO | W32: 155.4
B33: 13:30 | C33: 1122.9 | D33: 3420.4 | E33: 2077.2 | F33: 43.9 | G33: 0 | H33: 0 | K33: =DESPACHO_EJECUTADO!FH37+DESPACHO_EJECUTADO!FI37 -> 61.9 | L33: 62.6 | M33: 9.2 | N33: 832.2 | O33: 348.4 | P33: =SUM(C33:O33) -> 7978.7 | U33: EMPRESA ELECTRICA RIO DOBLE | V33: C.H. LAS PIZARRAS | W33: 446.9
B34: 14:00 | C34: 1120.3 | D34: 3510 | E34: 2025.3 | F34: 43.6 | G34: 0 | H34: 0 | K34: =DESPACHO_EJECUTADO!FH38+DESPACHO_EJECUTADO!FI38 -> 62.2 | L34: 67 | M34: 9.3 | N34: 789.8 | O34: 382.1 | P34: =SUM(C34:O34) -> 8009.6 | U34: ENGIE ENERGIA PERU S.A.A. | V34: C.H. YUNCAN | X34: 2228.15
B35: 14:30 | C35: 1117.7 | D35: 3478.3 | E35: 2008.1 | F35: 43.5 | G35: 0 | H35: 0 | K35: =DESPACHO_EJECUTADO!FH39+DESPACHO_EJECUTADO!FI39 -> 62 | L35: 68 | M35: 8.3 | N35: 835.2 | O35: 389 | P35: =SUM(C35:O35) -> 8010.1 | U35: GENERACIÓN ANDINA S.A.C. | V35: C.H. 8 DE AGOSTO | W35: 486.6
B36: 15:00 | C36: 1122.1 | D36: 3494.5 | E36: 2112.7 | F36: 44.1 | G36: 0 | H36: 0 | K36: =DESPACHO_EJECUTADO!FH40+DESPACHO_EJECUTADO!FI40 -> 62 | L36: 70.9 | M36: 9.1 | N36: 801.5 | O36: 380.1 | P36: =SUM(C36:O36) -> 8097 | V36: C.H. EL CARMEN | W36: 180.95
B37: 15:30 | C37: 1114.6 | D37: 3515.9 | E37: 2285.4 | F37: 42.9 | G37: 0 | H37: 0 | K37: =DESPACHO_EJECUTADO!FH41+DESPACHO_EJECUTADO!FI41 -> 62.2 | L37: 71.6 | M37: 9.3 | N37: 673.9 | O37: 304.3 | P37: =SUM(C37:O37) -> 8080.1 | U37: GENERADORA DE ENERGÍA DEL PERÚ | V37: C.H. ÁNGEL I | W37: 489.6
B38: 16:00 | C38: 1142.5 | D38: 3554.5 | E38: 2229.7 | F38: 43.7 | G38: 0 | H38: 75.1 | K38: =DESPACHO_EJECUTADO!FH42+DESPACHO_EJECUTADO!FI42 -> 62 | L38: 68.6 | M38: 9.3 | N38: 695.7 | O38: 286.4 | P38: =SUM(C38:O38) -> 8167.5 | V38: C.H. ÁNGEL II | W38: 489.6
B39: 16:30 | C39: 1142.6 | D39: 3486.9 | E39: 2282.4 | F39: 44.1 | G39: 0 | H39: 160.9 | K39: =DESPACHO_EJECUTADO!FH43+DESPACHO_EJECUTADO!FI43 -> 62.3 | L39: 70.9 | M39: 9.3 | N39: 380.8 | O39: 332.8 | P39: =SUM(C39:O39) -> 7973 | V39: C.H. ÁNGEL III | W39: 480
B40: 17:00 | C40: 1116.1 | D40: 3452.2 | E40: 2457.4 | F40: 44 | G40: 0 | H40: 160.5 | K40: =DESPACHO_EJECUTADO!FH44+DESPACHO_EJECUTADO!FI44 -> 61.8 | L40: 70.7 | M40: 9.3 | N40: 184 | O40: 313.3 | P40: =SUM(C40:O40) -> 7869.3 | V40: C.H. LA JOYA | W40: 139.7
B41: 17:30 | C41: 1148.7 | D41: 3452.5 | E41: 2390.1 | F41: 44.5 | G41: 0 | H41: 161.7 | K41: =DESPACHO_EJECUTADO!FH45+DESPACHO_EJECUTADO!FI45 -> 61.8 | L41: 78.2 | M41: 9.3 | N41: 71.4 | O41: 321.9 | P41: =SUM(C41:O41) -> 7740.1 | U41: HIDROCAÑETE S.A. | V41: C.H. IMPERIAL | W41: 81.6
B42: 18:00 | C42: 1152.1 | D42: 3437.2 | E42: 2212.5 | F42: 44.3 | G42: 0 | H42: 161 | K42: =DESPACHO_EJECUTADO!FH46+DESPACHO_EJECUTADO!FI46 -> 61.8 | L42: 78.7 | M42: 9.4 | N42: 9.1 | O42: 364 | P42: =SUM(C42:O42) -> 7530.1 | U42: HIDROELECTRICA HUANCHOR S.A.C. | V42: C.H. HUANCHOR | W42: 441.75
B43: 18:30 | C43: 1151.9 | D43: 3536.3 | E43: 2253.6 | F43: 44.6 | G43: 0 | H43: 0 | K43: =DESPACHO_EJECUTADO!FH47+DESPACHO_EJECUTADO!FI47 -> 62.2 | L43: 81.3 | M43: 9.4 | N43: 0 | O43: 436.1 | P43: =SUM(C43:O43) -> 7575.4 | U43: HUAURA POWER GROUP S.A. | V43: C.H. YARUCAYA | W43: 441.6
B44: 19:00 | C44: 1152.1 | D44: 3599.3 | E44: 2380.3 | F44: 44.8 | G44: 0 | H44: 0 | K44: =DESPACHO_EJECUTADO!FH48+DESPACHO_EJECUTADO!FI48 -> 62.2 | L44: 83.7 | M44: 9.4 | N44: 0 | O44: 432.8 | P44: =SUM(C44:O44) -> 7764.6 | U44: HYDRO GLOBAL PERÚ S.A.C. | V44: CH SAN GABAN III | X44: 4845.15
B45: 19:30 | C45: 1161.6 | D45: 3633.8 | E45: 2391.1 | F45: 44.8 | G45: 0 | H45: 0 | K45: =DESPACHO_EJECUTADO!FH49+DESPACHO_EJECUTADO!FI49 -> 62.1 | L45: 83.3 | M45: 9.5 | N45: 0 | O45: 454 | P45: =SUM(C45:O45) -> 7840.2 | U45: INLAND ENERGY SAC | V45: C.H. SANTA TERESA | W45: 2174.55
B46: 20:00 | C46: 1131.7 | D46: 3679 | E46: 2305.6 | F46: 44.6 | G46: 0 | H46: 0 | K46: =DESPACHO_EJECUTADO!FH50+DESPACHO_EJECUTADO!FI50 -> 62.4 | L46: 84.1 | M46: 9.7 | N46: 0 | O46: 468.4 | P46: =SUM(C46:O46) -> 7785.5 | U46: INVERSIONES SHAQSHA S.A.C. | V46: C.H. PARIAC | W46: 57.6
B47: 20:30 | C47: 1161 | D47: 3703.4 | E47: 2224.7 | F47: 44.7 | G47: 0 | H47: 0 | K47: =DESPACHO_EJECUTADO!FH51+DESPACHO_EJECUTADO!FI51 -> 62.3 | L47: 83.2 | M47: 9.7 | N47: 0 | O47: 452.2 | P47: =SUM(C47:O47) -> 7741.2 | U47: KALLPA GENERACION S.A. | V47: C.H. CERRO DEL AGUILA | X47: 13227.9
B48: 21:00 | C48: 1178.4 | D48: 3722.5 | E48: 2179.3 | F48: 45 | G48: 0 | H48: 0 | K48: =DESPACHO_EJECUTADO!FH52+DESPACHO_EJECUTADO!FI52 -> 62.4 | L48: 83 | M48: 9.7 | N48: 0 | O48: 430.7 | P48: =SUM(C48:O48) -> 7711 | V48: M.C.H. CERRO DEL AGUILA | W48: 244.75
B49: 21:30 | C49: 1176 | D49: 3696.4 | E49: 2038.8 | F49: 44.7 | G49: 0 | H49: 0 | K49: =DESPACHO_EJECUTADO!FH53+DESPACHO_EJECUTADO!FI53 -> 61.7 | L49: 83.7 | M49: 9.7 | N49: 0 | O49: 419.7 | P49: =SUM(C49:O49) -> 7530.7 | U49: LA VIRGEN | V49: C.H. LA VIRGEN | X49: 1553.5
B50: 22:00 | C50: 1177.7 | D50: 3672.7 | E50: 1998.4 | F50: 45 | G50: 0 | H50: 0 | K50: =DESPACHO_EJECUTADO!FH54+DESPACHO_EJECUTADO!FI54 -> 62.1 | L50: 80.8 | M50: 9.7 | N50: 0 | O50: 394.8 | P50: =SUM(C50:O50) -> 7441.2 | U50: MAJA ENERGIA S.A.C. | V50: C.H. RONCADOR | W50: 60.5
B51: 22:30 | C51: 1178.7 | D51: 3742.6 | E51: 2102.6 | F51: 44.7 | G51: 0 | H51: 0 | K51: =DESPACHO_EJECUTADO!FH55+DESPACHO_EJECUTADO!FI55 -> 62.8 | L51: 80.9 | M51: 9.7 | N51: 0 | O51: 333.9 | P51: =SUM(C51:O51) -> 7555.9 | U51: ORAZUL ENERGY PERÚ | V51: C.H. CAÑA BRAVA | W51: 130.45
B52: 23:00 | C52: 1193.6 | D52: 3556.1 | E52: 2031.3 | F52: 45 | G52: 0 | H52: 0 | K52: =DESPACHO_EJECUTADO!FH56+DESPACHO_EJECUTADO!FI56 -> 62.3 | L52: 83 | M52: 9.6 | N52: 0 | O52: 230.4 | P52: =SUM(C52:O52) -> 7211.3 | V52: C.H. CAÑON DEL PATO | X52: 5792.5
B53: 23:30 | C53: 1201.9 | D53: 3630.5 | E53: 1825.1 | F53: 35.2 | G53: 0 | H53: 0 | K53: =DESPACHO_EJECUTADO!FH57+DESPACHO_EJECUTADO!FI57 -> 62.1 | L53: 84.8 | M53: 9.7 | N53: 0 | O53: 198.1 | P53: =SUM(C53:O53) -> 7047.4 | V53: C.H. CARHUAQUERO | X53: 2156.4
B54: 00:00 | C54: 1179.3 | D54: 3487.1 | E54: 1916.3 | F54: 0 | G54: 0 | H54: 0 | K54: =DESPACHO_EJECUTADO!FH58+DESPACHO_EJECUTADO!FI58 -> 61.9 | L54: 83.4 | M54: 9.7 | N54: 0 | O54: 183.6 | P54: =SUM(C54:O54) -> 6921.3 | V54: C.H. CARHUAQUERO IV | W54: 238.65
B55: TOTAL MWh | C55: =SUM(C7:C54)/2 -> 27970.45 | D55: =SUM(D7:D54)/2 -> 83269.5 | E55: =SUM(E7:E54)/2 -> 48958.05 | F55: =SUM(F7:F54)/2 -> 702.75 | G55: =SUM(G7:G54)/2 -> 392 | H55: =SUM(H7:H54)/2 -> 359.6 | I55: =SUM(I7:I54)/2 -> 0 | J55: =SUM(J7:J54)/2 -> 0 | ... P55: =SUM(P7:P54)/2 -> 177833.45 | U55: ORYGEN PERU S.A.A. | V55: C.H. CALLAHUANCA | X55: 1793
B56: % | C56: =C55*100/$P$55 -> 15.728453 | D56: =D55*100/$P$55 -> 46.82443 | E56: =E55*100/$P$55 -> 27.530282 | F56: =F55*100/$P$55 -> 0.39517312 | G56: =G55*100/$P$55 -> 0.22043097 | H56: =H55*100/$P$55 -> 0.20221168 | I56: =I55*100/$P$55 -> 0 | J56: =J55*100/$P$55 -> 0 | ... P56: =P55*100/$P$55 -> 100 | V56: C.H. HER 1 | W56: 14.4
V57: C.H. HUAMPANI | W57: 722
V58: C.H. HUINCO | X58: 2443.7
V59: C.H. MATUCANA | X59: 2784.3
V60: C.H. MOYOPAMPA | W60: 1523.9
U61: SAN GABAN | V61: C.H. SAN GABAN II | X61: 2645.3
V62: PCH TUPURI | W62: 31.7
U63: SINERSA | V63: C.H. CHANCAY | W63: 480.95
V64: C.H. POECHOS II | W64: 191.55
V65: C.H. RUCUY | W65: 480.05
U66: STATKRAFT S.A | V66: C.H. ARCATA | W66: 96
V67: C.H. CAHUA | W67: 980
V68: C.H. CHEVES | X68: 3081.5
V69: C.H. GALLITO CIEGO | X69: 807.45
V70: C.H. MALPASO | X70: 613.15
V71: C.H. YAUPI | W71: 2291.85
U72: TRANSMISION ANDINA DE GENERACION S.A.C. | V72: C.H. OROYA | W72: 168
V73: C.H. PACHACHACA | W73: 104.3
U74: VARI ENERGIA S.A.C. | V74: C.H. ANASHIRONI | W74: 426.4
U75: TOTAL MWh | W75: 27970.45 | X75: 83269.5

Sheet GENERACION RER
B3: jueves, 12 de Febrero del 2026
B5: GENERACIÓN ELÉCTRICA DE LAS CENTRALES RER (MW)
B6: HORA | C6: ACCIONA ENERGIA PERU S.A.C | D6: AGRO INDUSTRIAL PARAMONGA S.A. | E6: AGROAURORA S.A.C. | F6: AGROINDUSTRIAS SAN JACINTO S.A.A. | G6: AGROLMOS SOCIEDAD ANONIMA - AGROLMOS S.A. | H6: ANDEAN POWER S.A.C. | I6: ASOCIACIÓN SANTA LUCIA DE CHACAS | J6: ATRIA ENERGIA S.A.C. | K6: BIOENERGIA DEL CHIRA S.A. | L6: CASA GRANDE S.A.A. | M6: CELARIS ENERGY S.A. | N6: COENERGY S.A.C. | O6: COLCA SOLAR S.A.C. | P6: EGEJUNIN | U6: ELECTRICA YANAPAMPA SAC | V6: EMPRESA DE GENERACION ELECTRICA CANCHAYLLO SAC | W6: EMPRESA DE GENERACION ELECTRICA SANTA ANA S.A.C. | X6: EMPRESA ELECTRICA AGUA AZUL | Y6: EMPRESA ELECTRICA RIO DOBLE | Z6: ENERGÍA EÓLICA S.A. | AB6: ENERGIA RENOVABLE DEL SUR S.A. | AC6: ENERGIA RENOVABLE LA JOYA S.A. | AE6: ENGIE ENERGIA PERU S.A.A. | AI6: GENERACIÓN ANDINA S.A.C. | AK6: GENERADORA DE ENERGÍA DEL PERÚ | AO6: GR CORTARRAMA SOCIEDAD ANONIMA CERRADA | AP6: GR PAINO SOCIEDAD ANONIMA CERRADA | AQ6: GR TARUCA SOCIEDAD ANONIMA CERRADA | AR6: GR VALE S.A.C. | AS6: HIDROCAÑETE S.A. | AT6: HUAURA POWER GROUP S.A. | AU6: HYDRO PATAPO S.A.C. | AV6: JOYA SOLAR S.A.C. | AW6: KALLPA GENERACION S.A. | AY6: KONDU SAC | AZ6: MAJA ENERGIA S.A.C. | BA6: MAJES ARCUS S.A.C. | BC6: MOQUEGUA FV S.A.C. | BD6: ORAZUL ENERGY PERÚ | BF6: ORYGEN PERU S.A.A. | BL6: PANAMERICANA SOLAR SAC. | BM6: PARQUE EOLICO MARCONA S.A.C. | BN6: PARQUE EOLICO TRES HERMANAS S.A.C. | BO6: PETRAMAS | BS6: REPARTICIÓN ARCUS S.A.C. | BT6: SAN GABAN | BU6: SINERSA | BX6: TACNA SOLAR SAC. | BY6: VARI ENERGIA S.A.C. | BZ6: TOTAL RER
C7: C.S. SAN JOSE | D7: C.T. PARAMONGA | E7: C.T. MAPLE | F7: C.T SAN JACINTO | G7: C.T. AGROLMOS | H7: C.H. CARHUAC | I7: C.H. HUALLIN | J7: C.H. PURMACANA | K7: C.T. CAÑA BRAVA | L7: C.T. CASA GRANDE | M7: C.H. MANTA | N7: CS COENERGY | O7: CS YARUCAYA | P7: C.H. HUASAHUASI I | Q7: C.H. HUASAHUASI II | R7: C.H. RUNATULLO II | S7: C.H. RUNATULLO III | T7: C.H. STA CRUZ I y II | U7: C.H. YANAPAMPA | V7: C.H. CANCHAYLLO | W7: C.H. RENOVANDES H1 | X7: C.H. POTRERO | Y7: C.H. LAS PIZARRAS | Z7: C.E. CUPISNIQUE | AA7: C.E. TALARA | AB7: CE SAN JUAN | AC7: C.S. ILLA 1 | AD7: C.S. ILLA 2 | AE7: C.E. P LOM EXPANSION | AF7: C.E. PUNTA LOMITAS | AG7: C.S. INTIPAMPA | AH7: CS EXPANSIÓN INTIPAMPA | AI7: C.H. 8 DE AGOSTO | AJ7: C.H. EL CARMEN | AK7: C.H. ANGEL I | AL7: C.H. ANGEL II | AM7: C.H. ANGEL III | AN7: C.H. LA JOYA | AO7: CS MATARANI | AP7: C.E. HUAMBOS | AQ7: C.E. DUNA | AR7: C.S. LUPI | AS7: C.H. NUEVAIMPERIAL | AT7: C.H. YARUCAYA | AU7: MCH PATAPO | AV7: CS SAN MARTIN SOLAR | AW7: CS SUNNY | AX7: CS SUNNY EXPANSION | AY7: CARHUAQUERO (CS) | AZ7: C.H. RONCADOR | BA7: C.S. MAJES | BB7: C.S. SOL DE VERANO | BC7: C.S. MOQUEGUA FV | BD7: C.H. CANA BRAVA | BE7: C.H. CARHUAQUERO4 | BF7: C.E. WAYRA EXTENSION | BG7: C.E. WAYRA I | BH7: C.H. HER 1 | BI7: C.S. CLEMESI | BJ7: C.S. RUBI | BK7: C.S. Wayra Solar | BL7: C.S. PANAMERICANA-SOLAR | BM7: C.E. MARCONA | BN7: C.E. 3 HERMANAS | BO7: C.T. HUAYCOLORO | BP7: C.T. LA GRINGA V | BQ7: CTB CALLAO | BR7: CTB. DONA CATALINA | BS7: C.S. REPARTICION | BT7: C.H. TUPURI | BU7: C.H. CHANCAY | BV7: C.H. POECHOS2 | BW7: C.H. RUCUY | BX7: C.S. TACNA-SOLAR | BY7: C.H. ANASHIRONI | BZ7: MW
B8: 0:30 | D8: 15.4 | E8: 13.5 | F8: 6.1 | G8: 11.7 | H8: 3.5 | I8: 2.9 | J8: 0.4 | K8: 9 | L8: 16.2 | M8: 20 | P8: 19.8 | R8: 20 | S8: 20.1 | T8: 7.8 | U8: 3.4 | V8: 4.9 | W8: 20 | X8: 20 | Y8: 18.9 | Z8: 17.8 | AB8: 66.7 | AE8: 10.2 | AF8: 121.8 | AI8: 17.2 | AJ8: 6.5 | AK8: 20.4 | AL8: 20.4 | AM8: 20 | AN8: 3.7 | AP8: 0.1 | AS8: 3.4 | AT8: 18.4 | AZ8: 2.3 | BD8: 5.5 | BE8: 9.9 | BF8: 46 | BG8: 42.5 | BH8: 0.6 | BM8: 19.9 | BN8: 49 | BO8: 3.9 | BP8: 0.8 | BQ8: 2.3 | BR8: 2.4 | BT8: 2 | BU8: 20 | BV8: 8 | BW8: 20 | BY8: 20 | BZ8: 815.3
B9: 1:00 | D9: 15.2 | E9: 13.5 | F9: 8.8 | G9: 11.7 | H9: 3.5 | I9: 2.9 | J9: 0.4 | K9: 8.4 | L9: 8 | M9: 20 | P9: 19.8 | R9: 20.2 | S9: 20.2 | T9: 7.8 | U9: 2.7 | V9: 4.9 | W9: 20.2 | X9: 20 | Y9: 18.9 | Z9: 13.1 | AB9: 57 | AE9: 6.9 | AF9: 89.5 | AI9: 17.2 | AJ9: 6.5 | AK9: 20.4 | AL9: 20.4 | AM9: 20 | AN9: 3.9 | AS9: 3.4 | AT9: 18.4 | AZ9: 2.3 | BD9: 5.5 | BE9: 9.9 | BF9: 26.7 | BG9: 28.6 | BH9: 0.6 | BM9: 17.9 | BN9: 44 | BO9: 3.9 | BP9: 0.8 | BQ9: 2.3 | BR9: 2.4 | BT9: 2 | BU9: 20 | BV9: 8 | BW9: 20 | BY9: 20.2 | BZ9: 718.9
B10: 1:30 | D10: 14.7 | E10: 13.5 | F10: 8.9 | G10: 11.7 | H10: 3.4 | I10: 2.9 | J10: 0.4 | K10: 8.5 | L10: 9.8 | M10: 20 | P10: 19.8 | R10: 20.1 | S10: 20.2 | T10: 7.7 | U10: 2.4 | V10: 4.9 | W10: 20 | X10: 20 | Y10: 18.8 | Z10: 9.5 | AB10: 58.1 | AE10: 3.6 | AF10: 84.5 | AI10: 17.2 | AJ10: 6.5 | AK10: 20.4 | AL10: 20.4 | AM10: 20 | AN10: 3.9 | AS10: 3.4 | AT10: 18.4 | AZ10: 2 | BD10: 5.2 | BE10: 10 | BF10: 17.3 | BG10: 21.8 | BH10: 0.6 | BM10: 17.8 | BN10: 47.1 | BO10: 3.9 | BP10: 0.8 | BQ10: 2.3 | BR10: 2.4 | BT10: 2 | BU10: 19.9 | BV10: 8 | BW10: 19.9 | BY10: 20.1 | BZ10: 694.7
B11: 2:00 | D11: 14.9 | E11: 13.5 | F11: 8.9 | G11: 11.6 | H11: 3.2 | I11: 2.9 | J11: 0.4 | K11: 8.7 | L11: 10 | M11: 20 | P11: 19.8 | R11: 20.1 | S11: 20.2 | T11: 7.8 | U11: 2.4 | V11: 4.9 | W11: 20.2 | X11: 20 | Y11: 18.8 | Z11: 9.2 | AB11: 66.4 | AE11: 5.1 | AF11: 73 | AI11: 17.2 | AJ11: 6.5 | AK11: 20.4 | AL11: 20.4 | AM11: 20 | AN11: 3.9 | AS11: 3.4 | AT11: 18.4 | AZ11: 2 | BD11: 5.2 | BE11: 9.9 | BF11: 13.1 | BG11: 19.1 | BH11: 0.6 | BM11: 18.2 | BN11: 44.7 | BO11: 3.9 | BP11: 0.8 | BQ11: 2.3 | BR11: 2.4 | BT11: 2 | BU11: 20 | BV11: 7.9 | BW11: 20 | BY11: 20.2 | BZ11: 684.5
B12: 2:30 | D12: 15.2 | E12: 13.5 | F12: 8.9 | G12: 11.6 | H12: 3.2 | I12: 2.8 | J12: 0.4 | K12: 9.1 | L12: 11.6 | M12: 20 | P12: 19.8 | R12: 19.8 | S12: 20.2 | T12: 7.8 | U12: 3.2 | V12: 4.9 | W12: 20.4 | X12: 20 | Y12: 18.8 | Z12: 12.6 | AB12: 45.9 | AE12: 6.8 | AF12: 67.1 | AI12: 17.2 | AJ12: 6.6 | AK12: 20.4 | AL12: 20.4 | AM12: 20 | AN12: 3.9 | AS12: 3.4 | AT12: 18.4 | AZ12: 2 | BD12: 5.5 | BE12: 9.9 | BF12: 6.3 | BG12: 5.9 | BH12: 0.6 | BM12: 16.4 | BN12: 49.4 | BO12: 3.9 | BP12: 0.8 | BQ12: 2.3 | BR12: 2.4 | BT12: 2 | BU12: 20 | BV12: 8 | BW12: 20 | BY12: 20.4 | BZ12: 649.7
B13: 3:00 | D13: 15.2 | E13: 13.6 | F13: 8.9 | G13: 11.6 | H13: 3.2 | I13: 2.8 | J13: 0.4 | K13: 9 | L13: 11.3 | M13: 20.1 | P13: 19.8 | R13: 20 | S13: 20.2 | T13: 7.8 | U13: 3.5 | V13: 4.9 | W13: 20.4 | X13: 20 | Y13: 18.8 | Z13: 16.1 | AB13: 33.7 | AE13: 6.6 | AF13: 70.5 | AI13: 17.2 | AJ13: 6.6 | AK13: 20.4 | AL13: 20.4 | AM13: 20 | AN13: 3.9 | AS13: 3.4 | AT13: 18.4 | AZ13: 2.1 | BD13: 5.4 | BE13: 9.9 | BF13: 9.3 | BG13: 4.4 | BH13: 0.6 | BM13: 11.4 | BN13: 37.3 | BO13: 3.9 | BP13: 0.8 | BQ13: 2.3 | BR13: 2.4 | BT13: 2 | BU13: 20 | BV13: 7.9 | BW13: 20 | BY13: 20.3 | BZ13: 628.7
B14: 3:30 | D14: 15.1 | E14: 13.5 | F14: 9 | G14: 11.6 | H14: 3.2 | I14: 2.8 | J14: 0.4 | K14: 8.9 | L14: 11.2 | M14: 20 | P14: 19.8 | R14: 20 | S14: 20.2 | T14: 7.8 | U14: 3.4 | V14: 4.9 | W14: 20.3 | X14: 20 | Y14: 18.8 | Z14: 11.1 | AB14: 37.5 | AE14: 2.2 | AF14: 60.5 | AI14: 17.3 | AJ14: 6.6 | AK14: 20.4 | AL14: 20.4 | AM14: 20 | AN14: 3.9 | AS14: 3.4 | AT14: 18.4 | AZ14: 2.1 | BD14: 5.5 | BE14: 10 | BF14: 0.3 | BG14: 0.2 | BH14: 0.6 | BM14: 9.1 | BN14: 27.8 | BO14: 3.9 | BP14: 0.8 | BQ14: 2.3 | BR14: 2.4 | BT14: 2 | BU14: 20 | BV14: 7.9 | BW14: 20 | BY14: 20.2 | BZ14: 587.7
B15: 4:00 | D15: 15.3 | E15: 13.6 | F15: 8 | G15: 11.6 | H15: 3.2 | I15: 2.8 | J15: 0.4 | K15: 8.9 | L15: 11.4 | M15: 20 | P15: 19.8 | R15: 20 | S15: 20.3 | T15: 8.2 | U15: 3.4 | V15: 4.9 | W15: 20.3 | X15: 20 | Y15: 18.9 | Z15: 9.1 | AB15: 38.8 | AE15: 3.8 | AF15: 41.1 | AI15: 17.9 | AJ15: 6.7 | AK15: 20.4 | AL15: 20.4 | AM15: 20 | AN15: 3.9 | AP15: 0.5 | AS15: 3.4 | AT15: 18.4 | AZ15: 2.1 | BD15: 5.3 | BE15: 9.9 | BG15: 0.1 | BH15: 0.6 | BM15: 10.9 | BN15: 25.5 | BO15: 3.9 | BP15: 0.8 | BQ15: 2.3 | BR15: 2.4 | BT15: 2 | BU15: 20 | BV15: 7.9 | BW15: 20 | BY15: 20.3 | BZ15: 569.4
B16: 4:30 | D16: 15.2 | E16: 13.5 | F16: 8.7 | G16: 11.6 | H16: 3.2 | I16: 2.7 | J16: 0.4 | K16: 8.8 | L16: 11.2 | M16: 20 | P16: 19.8 | R16: 20 | S16: 20.2 | T16: 8.4 | U16: 3.4 | V16: 4.9 | W16: 20.2 | X16: 20 | Y16: 19 | Z16: 8.2 | AA16: 0.4 | AB16: 31.2 | AE16: 1.3 | AF16: 30.8 | AI16: 20.4 | AJ16: 7.9 | AK16: 20.4 | AL16: 20.4 | AM16: 20 | AN16: 3.9 | AP16: 0.5 | AS16: 3.4 | AT16: 18.4 | AZ16: 2.1 | BD16: 5.5 | BE16: 10 | BH16: 0.6 | BM16: 7.4 | BN16: 15.7 | BO16: 3.9 | BP16: 0.8 | BQ16: 2.3 | BR16: 2.4 | BT16: 2 | BU16: 20 | BV16: 8 | BW16: 20 | BY16: 20.3 | BZ16: 539.4
B17: 5:00 | D17: 15.4 | E17: 13.5 | F17: 7.8 | G17: 11.7 | H17: 3.3 | I17: 2.7 | J17: 0.4 | K17: 8.5 | L17: 11.1 | M17: 20 | P17: 19.8 | R17: 20 | S17: 20.2 | T17: 8.3 | U17: 3.4 | V17: 4.9 | W17: 20.3 | X17: 20 | Y17: 18.8 | Z17: 3.6 | AA17: 0.2 | AB17: 15.6 | AE17: 0.9 | AF17: 35.3 | AI17: 21 | AJ17: 8 | AK17: 20.4 | AL17: 20.4 | AM17: 20 | AN17: 3.9 | AS17: 3.4 | AT17: 18.4 | AZ17: 2.1 | BD17: 5.5 | BE17: 9.9 | BH17: 0.6 | BM17: 5.1 | BN17: 15.3 | BO17: 3.9 | BP17: 0.8 | BQ17: 2.3 | BR17: 2.4 | BT17: 2 | BU17: 20.2 | BV17: 8 | BW17: 20.2 | BY17: 20.2 | BZ17: 519.7
B18: 5:30 | D18: 16 | E18: 13.5 | F18: 7.3 | G18: 11.6 | H18: 3.2 | I18: 2.7 | J18: 0.4 | K18: 9.1 | L18: 11.2 | M18: 20 | P18: 19.8 | R18: 20 | S18: 20.2 | T18: 8.3 | U18: 3.4 | V18: 4.9 | W18: 20.2 | X18: 20 | Y18: 18.8 | Z18: 4.8 | AA18: 0.3 | AB18: 6.1 | AE18: 0.4 | AF18: 37.3 | AI18: 20.9 | AJ18: 7.9 | AK18: 20.4 | AL18: 20.4 | AM18: 20 | AN18: 4.2 | AS18: 3.4 | AT18: 18.4 | AZ18: 2.5 | BD18: 5.5 | BE18: 10 | BH18: 0.6 | BM18: 4 | BN18: 9.1 | BO18: 3.9 | BP18: 0.8 | BQ18: 2.3 | BR18: 2.4 | BT18: 2 | BU18: 20 | BV18: 8.1 | BW18: 20 | BY18: 20.3 | BZ18: 506.6
B19: 6:00 | D19: 16.1 | E19: 13.5 | F19: 9.1 | G19: 11.6 | H19: 3.1 | I19: 2.7 | J19: 0.4 | K19: 9.1 | L19: 11.2 | M19: 20 | P19: 19.8 | R19: 20 | S19: 20.2 | T19: 8.2 | U19: 3.4 | V19: 4.8 | W19: 20.5 | X19: 20 | Y19: 18.8 | Z19: 6.1 | AA19: 1.3 | AB19: 3.7 | AE19: 0.8 | AF19: 29.5 | AI19: 20.9 | AJ19: 7.9 | AK19: 20.4 | AL19: 20.4 | AM19: 20 | AN19: 2.9 | AS19: 3.4 | AT19: 18.4 | AV19: 2.9 | AW19: 2.9 | AZ19: 2.5 | BC19: 0.5 | BD19: 5.4 | BE19: 9.9 | BH19: 0.6 | BI19: 2.5 | BJ19: 2.6 | BL19: 0.5 | BM19: 2.3 | BN19: 6.8 | BO19: 3.9 | BP19: 0.8 | BQ19: 2.3 | BR19: 2.4 | BT19: 2 | BU19: 20 | BV19: 8 | BW19: 20 | BX19: 0.3 | BY19: 20.3 | BZ19: 507.6
B20: 6:30 | D20: 15.8 | E20: 13.5 | F20: 8.3 | G20: 11.7 | H20: 3 | I20: 2.6 | J20: 0.4 | K20: 9.1 | L20: 11.2 | M20: 20 | P20: 19.8 | R20: 20 | S20: 20.1 | T20: 8.2 | U20: 3.4 | V20: 4.9 | W20: 19.5 | X20: 20 | Y20: 18.8 | Z20: 1.2 | AA20: 1.2 | AB20: 6.5 | AF20: 18.6 | AG20: 0.8 | AH20: 0.3 | AI20: 20.9 | AJ20: 7.9 | AK20: 20.4 | AL20: 20.4 | AM20: 20 | AN20: 2.1 | AO20: 8 | AS20: 3.4 | AT20: 18.4 | AV20: 29 | AW20: 31.2 | AZ20: 2.5 | BA20: 0.7 | BC20: 7.3 | BD20: 5.5 | BE20: 10 | BH20: 0.6 | BI20: 4.7 | BJ20: 5.2 | BL20: 7.9 | BM20: 2.2 | BN20: 7.4 | BO20: 3.9 | BP20: 0.8 | BQ20: 2.3 | BR20: 2.4 | BS20: 0.8 | BT20: 2 | BU20: 20 | BV20: 8 | BW20: 20 | BX20: 0.9 | BY20: 19.9 | BZ20: 575.6
B21: 7:00 | D21: 15.8 | E21: 13.5 | F21: 9 | G21: 11.5 | H21: 3.1 | I21: 2.6 | J21: 0.4 | K21: 9 | L21: 11.1 | M21: 20 | P21: 19.8 | R21: 20.1 | S21: 20.2 | T21: 8.1 | U21: 3.3 | V21: 4.9 | W21: 20.3 | X21: 20 | Y21: 18.7 | AA21: 2.2 | AB21: 10.3 | AF21: 20.1 | AG21: 3.2 | AH21: 1.3 | AI21: 20.9 | AJ21: 7.9 | AK21: 20.4 | AL21: 20.4 | AM21: 20 | AN21: 2.1 | AO21: 12.5 | AS21: 3.4 | AT21: 18.4 | AV21: 59.6 | AW21: 45.2 | AZ21: 2.6 | BA21: 1.3 | BC21: 11.7 | BD21: 5.4 | BE21: 10 | BH21: 0.6 | BI21: 13.4 | BJ21: 17.9 | BL21: 14 | BM21: 2.7 | BN21: 7 | BO21: 3.9 | BP21: 0.8 | BQ21: 2.3 | BR21: 2.4 | BS21: 1.7 | BT21: 2 | BU21: 20 | BV21: 8 | BW21: 20 | BX21: 2.7 | BY21: 20.3 | BZ21: 670
B22: 7:30 | D22: 16 | E22: 13.5 | F22: 9.1 | G22: 10.9 | H22: 3.2 | I22: 2.6 | J22: 0.4 | K22: 9.1 | L22: 11.3 | M22: 20 | N22: 0.1 | O22: 0.1 | P22: 19.8 | R22: 20 | S22: 20.2 | T22: 7.7 | U22: 3.1 | V22: 4.9 | W22: 20.4 | X22: 16.4 | Y22: 18.7 | Z22: 0.4 | AA22: 3.1 | AB22: 14.7 | AF22: 18.9 | AG22: 6.4 | AH22: 3.7 | AI22: 20.9 | AJ22: 7.9 | AK22: 20.4 | AL22: 20.4 | AM22: 20 | AN22: 7 | AO22: 20.5 | AS22: 3.4 | AT22: 18.4 | AV22: 58.7 | AW22: 50.9 | AZ22: 2.8 | BA22: 7.6 | BC22: 13.3 | BD22: 5.5 | BE22: 9.9 | BH22: 0.6 | BI22: 24.1 | BJ22: 32.3 | BL22: 16.1 | BM22: 3.4 | BN22: 9.1 | BO22: 3.9 | BP22: 0.8 | BQ22: 2.3 | BR22: 2.4 | BS22: 3.9 | BT22: 2 | BU22: 20.2 | BV22: 8 | BW22: 20.2 | BX22: 5.7 | BY22: 20.4 | BZ22: 737.7
B23: 8:00 | D23: 16.2 | E23: 13.5 | F23: 9.5 | G23: 10.5 | H23: 5.2 | I23: 2.6 | J23: 0.4 | K23: 9.1 | L23: 11.3 | M23: 20 | N23: 0.1 | O23: 0.3 | P23: 19.8 | R23: 20.1 | S23: 20.2 | T23: 7.4 | U23: 3.4 | V23: 4.9 | W23: 20.4 | X23: 14.4 | Y23: 18.5 | AA23: 7.3 | AB23: 37.6 | AF23: 16.7 | AG23: 15.5 | AH23: 8.5 | AI23: 20.9 | AJ23: 7.9 | AK23: 20.4 | AL23: 20.4 | AM23: 20 | AN23: 7.5 | AO23: 18.2 | AS23: 3.4 | AT23: 18.4 | AV23: 96.5 | AW23: 52.9 | AZ23: 3.1 | BA23: 4.1 | BC23: 13.9 | BD23: 5.4 | BE23: 10 | BH23: 0.6 | BI23: 75.1 | BJ23: 121.2 | BL23: 17 | BM23: 3.7 | BN23: 14.6 | BO23: 3.9 | BP23: 0.8 | BQ23: 2.3 | BR23: 2.4 | BS23: 7.4 | BT23: 2 | BU23: 20 | BV23: 8 | BW23: 19.8 | BX23: 7.1 | BY23: 20.2 | BZ23: 962.5
B24: 8:30 | D24: 17.2 | E24: 13.6 | F24: 8.1 | G24: 10.5 | H24: 6.7 | I24: 2.6 | J24: 0.4 | K24: 8.8 | L24: 11.3 | M24: 19.8 | N24: 0.1 | O24: 0.3 | P24: 19.8 | R24: 20.1 | S24: 20.2 | T24: 7 | U24: 3.4 | V24: 4.8 | W24: 20.7 | Y24: 18.4 | AA24: 13.3 | AB24: 37.6 | AF24: 12.7 | AG24: 34.9 | AH24: 22 | AI24: 20.9 | AJ24: 7.9 | AK24: 20.4 | AL24: 20.4 | AM24: 20 | AN24: 7.3 | AO24: 75.2 | AQ24: 0.2 | AS24: 3.4 | AT24: 18.4 | AV24: 76 | AW24: 87.1 | AZ24: 3.1 | BA24: 4.9 | BC24: 14.2 | BD24: 5.4 | BE24: 10 | BF24: 1.7 | BH24: 0.6 | BI24: 104.9 | BJ24: 140.7 | BL24: 17.3 | BM24: 4.9 | BN24: 17.3 | BO24: 3.9 | BP24: 0.8 | BQ24: 2.3 | BR24: 2.4 | BS24: 8.3 | BT24: 2 | BU24: 20 | BV24: 8 | BW24: 20 | BX24: 13.2 | BY24: 20.5 | BZ24: 1117.9
B25: 9:00 | D25: 16.8 | E25: 13.6 | F25: 7.9 | G25: 10.6 | H25: 7 | I25: 2.6 | J25: 0.4 | K25: 8.7 | L25: 11.2 | M25: 20 | N25: 0.2 | O25: 0.4 | P25: 19.8 | R25: 20.2 | S25: 20.2 | T25: 7 | U25: 3.4 | V25: 4.8 | W25: 20.5 | Y25: 18.4 | AA25: 11.8 | AB25: 42.2 | AF25: 29.7 | AG25: 38.1 | AH25: 42.1 | AI25: 20.9 | AJ25: 7.9 | AK25: 20.4 | AL25: 20.4 | AM25: 20 | AN25: 7.1 | AO25: 60 | AP25: 0.2 | AQ25: 0.2 | AS25: 3.4 | AT25: 18.4 | AV25: 99.6 | AW25: 81 | AY25: 0.1 | AZ25: 3.1 | BA25: 5.8 | BC25: 14.6 | BD25: 5.4 | BE25: 10 | BF25: 6.4 | BG25: 0.3 | BH25: 0.6 | BI25: 95 | BJ25: 131.7 | BL25: 17.7 | BM25: 3.8 | BN25: 12.1 | BO25: 3.8 | BP25: 0.8 | BQ25: 2.3 | BR25: 2.4 | BS25: 13.1 | BT25: 2 | BU25: 20.1 | BV25: 8 | BW25: 20 | BX25: 15.8 | BY25: 20.4 | BZ25: 1152.4
B26: 9:30 | D26: 17 | E26: 13.6 | F26: 7.4 | G26: 10.5 | H26: 12.9 | I26: 2.6 | J26: 0.4 | L26: 11.3 | M26: 20 | N26: 0.2 | O26: 0.4 | P26: 19.8 | R26: 20.1 | S26: 20.2 | T26: 7 | U26: 3.5 | V26: 4.8 | W26: 20.4 | Y26: 18.3 | AA26: 11.4 | AB26: 42.2 | AE26: 0.1 | AF26: 45.7 | AG26: 37.1 | AH26: 45.6 | AI26: 20.9 | AJ26: 7.9 | AK26: 20.4 | AL26: 20.4 | AM26: 20 | AN26: 7.2 | AO26: 51.7 | AP26: 0.7 | AQ26: 0.6 | AS26: 3.4 | AT26: 18.4 | AV26: 95.3 | AW26: 72.8 | AY26: 0.2 | AZ26: 1.9 | BA26: 13.6 | BC26: 14.6 | BD26: 5.4 | BE26: 9.9 | BF26: 2 | BH26: 0.6 | BI26: 98.3 | BJ26: 138.9 | BL26: 18.2 | BM26: 3.4 | BN26: 12.4 | BO26: 3.7 | BP26: 0.8 | BQ26: 2.3 | BR26: 2.4 | BS26: 8.3 | BT26: 2 | BU26: 20 | BV26: 8 | BW26: 20 | BX26: 18.4 | BY26: 20.3 | BZ26: 1157.8
B27: 10:00 | D27: 17.1 | E27: 13.6 | F27: 7.8 | G27: 10.6 | H27: 19.6 | I27: 2.6 | J27: 0.4 | K27: 4.6 | L27: 11.3 | M27: 20 | N27: 0.3 | O27: 1.2 | P27: 19.8 | R27: 20.1 | S27: 20.2 | T27: 7 | U27: 3.5 | V27: 4.9 | W27: 20.1 | Y27: 18.4 | Z27: 1.4 | AA27: 9.1 | AB27: 49.7 | AE27: 3.8 | AF27: 68.9 | AG27: 38.5 | AH27: 44.6 | AI27: 20.9 | AJ27: 7.9 | AK27: 20.4 | AL27: 20.4 | AM27: 20 | AN27: 7 | AO27: 48.2 | AP27: 1.2 | AQ27: 1 | AS27: 3.4 | AT27: 18.4 | AV27: 103.4 | AW27: 82.8 | AY27: 0.1 | AZ27: 1.9 | BA27: 8.5 | BC27: 15 | BD27: 5.5 | BE27: 9.9 | BF27: 2.7 | BH27: 0.6 | BI27: 76.7 | BJ27: 95.1 | BL27: 19 | BM27: 3.2 | BN27: 14.5 | BO27: 3.7 | BP27: 0.8 | BQ27: 2.3 | BR27: 2.4 | BS27: 11 | BT27: 2 | BU27: 20 | BV27: 8 | BW27: 20 | BX27: 18.3 | BY27: 20.3 | BZ27: 1155.6
B28: 10:30 | D28: 16.3 | E28: 13.6 | F28: 7.7 | G28: 10.5 | H28: 19.7 | I28: 2.5 | J28: 0.4 | K28: 4.8 | L28: 11.2 | M28: 20 | N28: 0.4 | O28: 0.6 | P28: 19.8 | R28: 20.1 | S28: 20.2 | T28: 7 | U28: 3.5 | V28: 4.9 | W28: 20.1 | Y28: 18.4 | Z28: 4.8 | AA28: 5.4 | AB28: 49.7 | AE28: 10.1 | AF28: 81.8 | AG28: 39.2 | AH28: 45.9 | AI28: 21 | AJ28: 7.9 | AK28: 20.4 | AL28: 20.4 | AM28: 20 | AN28: 7.1 | AO28: 32 | AP28: 4.7 | AQ28: 5.4 | AS28: 3.4 | AT28: 18.4 | AV28: 134.1 | AW28: 103.7 | AY28: 0.1 | AZ28: 1.9 | BA28: 16.6 | BC28: 14.4 | BD28: 5.5 | BE28: 9.9 | BH28: 0.6 | BI28: 72.4 | BJ28: 97.7 | BL28: 18.6 | BM28: 4.4 | BN28: 21.6 | BO28: 3.7 | BP28: 0.8 | BQ28: 2.3 | BR28: 2.4 | BS28: 12.2 | BT28: 1.9 | BU28: 20.1 | BV28: 8 | BW28: 20 | BX28: 18.8 | BY28: 20.2 | BZ28: 1231.2
B29: 11:00 | D29: 16.1 | E29: 13.5 | F29: 6.9 | G29: 11 | H29: 15.1 | I29: 2.5 | J29: 0.4 | K29: 6.1 | L29: 10 | M29: 20.1 | N29: 0.3 | O29: 0.6 | P29: 19.8 | R29: 20.2 | S29: 20.2 | T29: 7 | U29: 3.5 | V29: 4.9 | W29: 20.4 | Y29: 18.5 | Z29: 12.7 | AA29: 4.3 | AB29: 56.2 | AE29: 8 | AF29: 74.7 | AG29: 39.7 | AH29: 46.7 | AI29: 21 | AJ29: 7.9 | AK29: 20.4 | AL29: 20.4 | AM29: 20 | AN29: 7.1 | AO29: 57.7 | AP29: 4.6 | AQ29: 4.1 | AS29: 3.4 | AT29: 18.4 | AV29: 185.4 | AW29: 169.4 | AY29: 0.1 | AZ29: 1.9 | BA29: 10.3 | BC29: 14.9 | BD29: 5.4 | BE29: 9.9 | BH29: 0.6 | BI29: 68.4 | BJ29: 90.7 | BL29: 18.7 | BM29: 4.2 | BN29: 26.9 | BO29: 3.7 | BP29: 0.8 | BQ29: 2.3 | BR29: 2.4 | BS29: 15.7 | BT29: 1.9 | BU29: 20.1 | BV29: 7.8 | BW29: 20 | BX29: 18.8 | BY29: 20.3 | BZ29: 1365
B30: 11:30 | D30: 16.5 | E30: 13.5 | F30: 7.6 | G30: 10.6 | H30: 9.5 | I30: 2.5 | J30: 0.4 | K30: 5.4 | L30: 9.9 | M30: 20 | N30: 0.3 | O30: 0.6 | P30: 19.8 | R30: 20 | S30: 20.2 | T30: 7.1 | U30: 3.5 | V30: 4.9 | W30: 19.9 | Y30: 18.5 | Z30: 12.7 | AA30: 3.8 | AB30: 56.2 | AE30: 11.6 | AF30: 83.5 | AG30: 20 | AH30: 35.2 | AI30: 20.9 | AJ30: 8 | AK30: 20.4 | AL30: 20.4 | AM30: 20 | AN30: 7.1 | AO30: 62.4 | AP30: 8.7 | AQ30: 5.7 | AS30: 3.4 | AT30: 18.4 | AV30: 193.8 | AW30: 183.7 | AY30: 0.2 | AZ30: 1.9 | BA30: 16 | BC30: 10.1 | BD30: 5.4 | BE30: 10 | BH30: 0.6 | BI30: 102.4 | BJ30: 147.9 | BL30: 18.9 | BM30: 6.4 | BN30: 37 | BO30: 3.7 | BP30: 0.8 | BQ30: 2.3 | BR30: 2.4 | BS30: 16.2 | BT30: 1.9 | BU30: 20.2 | BV30: 8 | BW30: 20 | BX30: 18 | BY30: 20.2 | BZ30: 1477.1
B31: 12:00 | D31: 16.7 | E31: 13.6 | F31: 8.5 | G31: 10 | H31: 9.6 | I31: 2.5 | J31: 0.4 | K31: 5.2 | L31: 11.4 | M31: 20 | N31: 0.3 | O31: 0.5 | P31: 19.8 | R31: 20 | S31: 20.1 | T31: 7.1 | U31: 3.5 | V31: 4.8 | W31: 20.4 | Y31: 18.4 | Z31: 11.6 | AA31: 4.8 | AB31: 60.9 | AE31: 10.9 | AF31: 103.3 | AG31: 17.3 | AH31: 25.1 | AI31: 20.9 | AJ31: 8 | AK31: 20.4 | AL31: 20.4 | AM31: 20 | AN31: 7.3 | AO31: 74.3 | AP31: 12.6 | AQ31: 6.2 | AS31: 3.4 | AT31: 18.4 | AV31: 241.3 | AW31: 213 | AY31: 0.2 | AZ31: 1.9 | BA31: 19.5 | BC31: 14.8 | BD31: 5.5 | BE31: 10 | BF31: 2.3 | BH31: 0.6 | BI31: 101.1 | BJ31: 144.7 | BL31: 18.9 | BM31: 12.3 | BN31: 54.1 | BO31: 3.7 | BP31: 0.8 | BQ31: 2.3 | BR31: 2.4 | BS31: 15.8 | BT31: 1.9 | BU31: 20.1 | BV31: 8 | BW31: 20 | BX31: 19.1 | BY31: 20.3 | BZ31: 1613.2
B32: 12:30 | D32: 16.6 | E32: 13.5 | F32: 8.8 | G32: 10 | H32: 7.4 | I32: 2.5 | J32: 0.4 | K32: 5.3 | L32: 11.4 | M32: 20 | N32: 0.3 | O32: 0.4 | P32: 19.8 | R32: 20.3 | S32: 20.3 | T32: 7.1 | U32: 3.6 | V32: 4.8 | W32: 20.7 | Y32: 18.5 | Z32: 17.3 | AA32: 10.1 | AB32: 60.9 | AE32: 14.9 | AF32: 120.9 | AG32: 14.3 | AH32: 22.9 | AI32: 20.9 | AJ32: 8 | AK32: 20.4 | AL32: 20.4 | AM32: 20 | AN32: 7.5 | AO32: 79.5 | AP32: 12.6 | AQ32: 7.1 | AS32: 3.4 | AT32: 18.4 | AV32: 184.2 | AW32: 132.8 | AY32: 0.2 | AZ32: 1.9 | BA32: 16.2 | BC32: 14.8 | BD32: 5.4 | BE32: 10 | BF32: 3.9 | BG32: 1.4 | BH32: 0.6 | BI32: 92.8 | BJ32: 127.5 | BL32: 19.1 | BM32: 11.7 | BN32: 47.2 | BO32: 3.7 | BP32: 0.8 | BQ32: 2.3 | BR32: 2.4 | BS32: 12.5 | BT32: 1.9 | BU32: 20 | BV32: 8 | BW32: 20 | BX32: 18.7 | BY32: 20.5 | BZ32: 1471.7
B33: 13:00 | D33: 16.5 | E33: 13.5 | F33: 8.9 | G33: 10.5 | H33: 7.3 | I33: 2.5 | J33: 0.4 | K33: 5.2 | L33: 11.2 | M33: 20 | N33: 0.3 | O33: 0.2 | P33: 19.8 | R33: 19.9 | S33: 20.2 | T33: 7.1 | U33: 3.5 | V33: 4.8 | W33: 20.5 | Y33: 18.5 | Z33: 25.5 | AA33: 11.7 | AB33: 64.5 | AE33: 13 | AF33: 118.3 | AG33: 24.5 | AH33: 19.3 | AI33: 20.9 | AJ33: 8 | AK33: 20.4 | AL33: 20.4 | AM33: 20 | AN33: 7.2 | AO33: 80.9 | AP33: 12.8 | AQ33: 7 | AS33: 3.4 | AT33: 18.4 | AV33: 230.2 | AW33: 156.2 | AY33: 0.3 | AZ33: 1.9 | BA33: 14.3 | BC33: 15.5 | BD33: 5.4 | BE33: 9.9 | BF33: 9.5 | BG33: 2.2 | BH33: 0.6 | BI33: 104.2 | BJ33: 148.7 | BL33: 18.7 | BM33: 9.5 | BN33: 43.6 | BO33: 3.7 | BP33: 0.8 | BQ33: 2.3 | BR33: 2.4 | BS33: 9.3 | BT33: 1.9 | BU33: 20 | BV33: 8 | BW33: 20 | BX33: 18.2 | BY33: 20.3 | BZ33: 1584.6
B34: 13:30 | D34: 17.2 | E34: 13.5 | F34: 8.6 | G34: 6.5 | H34: 7.1 | I34: 2.5 | J34: 0.4 | K34: 5.5 | L34: 11.3 | M34: 20 | N34: 0.2 | O34: 0.2 | P34: 19.8 | R34: 20.1 | S34: 20.2 | T34: 7.1 | U34: 3.6 | V34: 4.7 | W34: 20.5 | Y34: 18.5 | Z34: 34.1 | AA34: 14.6 | AB34: 64.5 | AE34: 15.4 | AF34: 131.8 | AG34: 9.9 | AH34: 35.7 | AI34: 20.9 | AJ34: 7.7 | AK34: 20.4 | AL34: 20.4 | AM34: 20 | AN34: 7.3 | AO34: 65 | AP34: 11.3 | AQ34: 3.1 | AS34: 3.4 | AT34: 18.4 | AV34: 234.9 | AW34: 168.6 | AY34: 0.3 | AZ34: 1.9 | BA34: 18.8 | BC34: 15.1 | BD34: 5.5 | BE34: 9.9 | BF34: 20.3 | BG34: 15.2 | BH34: 0.6 | BI34: 96.8 | BJ34: 144.5 | BL34: 18 | BM34: 6.3 | BN34: 31.8 | BO34: 3.7 | BP34: 0.8 | BQ34: 2.3 | BR34: 2.4 | BS34: 9.7 | BT34: 1.9 | BU34: 20.2 | BV34: 8 | BW34: 20 | BX34: 14.5 | BY34: 20.4 | BZ34: 1603.8
B35: 14:00 | D35: 17 | E35: 13.5 | F35: 9.4 | G35: 8.4 | H35: 7.1 | I35: 2.5 | J35: 0.4 | K35: 8.7 | L35: 10 | M35: 20 | N35: 0.1 | O35: 0.2 | P35: 19.8 | R35: 20 | S35: 20.2 | T35: 7.1 | U35: 3.5 | V35: 4.7 | W35: 20.4 | Y35: 18.5 | Z35: 41.1 | AA35: 14.6 | AB35: 65.4 | AE35: 16.7 | AF35: 142.1 | AG35: 7.7 | AH35: 12.5 | AI35: 20.9 | AJ35: 7.1 | AK35: 20.4 | AL35: 20.4 | AM35: 20 | AN35: 7.2 | AO35: 80.9 | AP35: 7.5 | AQ35: 3.6 | AS35: 3.4 | AT35: 18.4 | AV35: 213.3 | AW35: 156.5 | AY35: 0.5 | AZ35: 1.9 | BA35: 10.8 | BC35: 14.8 | BD35: 5.5 | BE35: 10 | BF35: 29 | BG35: 27.2 | BH35: 0.6 | BI35: 111.8 | BJ35: 148.4 | BL35: 17.8 | BM35: 5 | BN35: 29.9 | BO35: 3.8 | BP35: 0.8 | BQ35: 2.3 | BR35: 2.4 | BS35: 5 | BT35: 1.9 | BU35: 20.1 | BV35: 8 | BW35: 20 | BX35: 9.5 | BY35: 20.3 | BZ35: 1598.5
B36: 14:30 | D36: 17 | E36: 13.6 | F36: 8.1 | G36: 11 | H36: 7.2 | I36: 2.5 | J36: 0.4 | K36: 6.9 | L36: 11.4 | M36: 20 | N36: 0.2 | O36: 0.2 | P36: 19.8 | R36: 19.8 | S36: 20.2 | T36: 7 | U36: 3.5 | V36: 4.7 | W36: 20.3 | Y36: 18.5 | Z36: 52.6 | AA36: 12.2 | AB36: 65.4 | AE36: 17 | AF36: 138 | AG36: 3.9 | AH36: 10.1 | AI36: 20.9 | AJ36: 7 | AK36: 20.4 | AL36: 20.4 | AM36: 20 | AN36: 7.1 | AO36: 80.9 | AP36: 9.3 | AQ36: 5.4 | AS36: 3.4 | AT36: 18.4 | AV36: 232.2 | AW36: 203.3 | AY36: 0.3 | AZ36: 1.9 | BA36: 7.9 | BC36: 11.4 | BD36: 5.4 | BE36: 9.9 | BF36: 25.1 | BG36: 18.2 | BH36: 0.6 | BI36: 107.2 | BJ36: 144.1 | BL36: 14.3 | BM36: 7.8 | BN36: 38 | BO36: 3.8 | BP36: 0.8 | BQ36: 1.3 | BR36: 2.4 | BS36: 11.8 | BT36: 1.9 | BU36: 20.1 | BV36: 8 | BW36: 20 | BX36: 7.4 | BY36: 20.3 | BZ36: 1650.1
B37: 15:00 | D37: 17.1 | E37: 13.6 | F37: 9.2 | G37: 10.8 | H37: 7.3 | I37: 2.4 | J37: 0.4 | K37: 8.7 | L37: 11.5 | M37: 20.1 | N37: 0.2 | O37: 0.1 | P37: 19.8 | R37: 19.9 | S37: 20.2 | T37: 6.9 | U37: 3.5 | V37: 4.6 | W37: 20.2 | Y37: 18.5 | Z37: 50.5 | AA37: 14.2 | AB37: 63.6 | AE37: 16.3 | AF37: 135.3 | AG37: 3.8 | AH37: 6.9 | AI37: 20.9 | AJ37: 6.6 | AK37: 20.4 | AL37: 20.4 | AM37: 20 | AN37: 6.8 | AO37: 80.5 | AP37: 10.1 | AQ37: 5.5 | AS37: 3.4 | AT37: 18.4 | AV37: 243.1 | AW37: 206.4 | AY37: 0.2 | AZ37: 1.9 | BA37: 12.3 | BC37: 7.1 | BD37: 5.4 | BE37: 9.9 | BF37: 25.6 | BG37: 20.5 | BH37: 0.6 | BI37: 92.5 | BJ37: 129.3 | BL37: 8.6 | BM37: 5.6 | BN37: 32.9 | BO37: 3.8 | BP37: 0.8 | BQ37: 2.1 | BR37: 2.4 | BS37: 4 | BT37: 1.9 | BU37: 20.1 | BV37: 8 | BW37: 20 | BX37: 6.5 | BY37: 20.3 | BZ37: 1610.4
B38: 15:30 | D38: 17 | E38: 13.6 | F38: 9.2 | G38: 10.9 | H38: 10.6 | I38: 2.4 | J38: 0.4 | K38: 9.4 | L38: 11.5 | M38: 20 | N38: 0.2 | O38: 0.1 | P38: 19.8 | R38: 20 | S38: 20.2 | T38: 6.8 | U38: 2.7 | V38: 4.6 | W38: 20.4 | Y38: 18.5 | Z38: 36.6 | AA38: 15.4 | AB38: 63.6 | AE38: 11.1 | AF38: 111.3 | AG38: 3.8 | AH38: 6.2 | AI38: 20.9 | AJ38: 3.4 | AK38: 20.4 | AL38: 20.4 | AM38: 20 | AN38: 4.4 | AO38: 80.9 | AP38: 10 | AQ38: 6.4 | AS38: 3.4 | AT38: 18.4 | AV38: 202.7 | AW38: 191.3 | AZ38: 2.4 | BA38: 12.5 | BC38: 4.9 | BD38: 5.4 | BE38: 10 | BF38: 12.3 | BG38: 8.3 | BH38: 0.6 | BI38: 75.7 | BJ38: 79.2 | BL38: 5.8 | BM38: 5.1 | BN38: 24.2 | BO38: 3.8 | BP38: 0.8 | BQ38: 2.3 | BR38: 2.4 | BS38: 5.1 | BT38: 1.6 | BU38: 20.2 | BV38: 8 | BW38: 20.1 | BX38: 5.5 | BY38: 20.3 | BZ38: 1405.4
B39: 16:00 | D39: 17.1 | E39: 13.6 | F39: 6.5 | G39: 10.5 | H39: 14.8 | I39: 2.4 | J39: 0.4 | K39: 9.3 | L39: 11.6 | M39: 20.1 | N39: 0.1 | O39: 0.1 | P39: 19.8 | R39: 19.9 | S39: 20.2 | T39: 6.8 | U39: 3.2 | V39: 4.6 | W39: 20.6 | Y39: 18.6 | Z39: 35.1 | AA39: 16.5 | AB39: 62.1 | AE39: 7.3 | AF39: 100.3 | AG39: 1.1 | AH39: 6.8 | AI39: 20.9 | AJ39: 8 | AK39: 20.4 | AL39: 20.4 | AM39: 20 | AN39: 2.6 | AO39: 59.9 | AP39: 13 | AQ39: 5.9 | AS39: 3.4 | AT39: 18.4 | AV39: 186.7 | AW39: 178.5 | AZ39: 2.9 | BA39: 4.6 | BC39: 3.1 | BD39: 5.5 | BE39: 9.9 | BF39: 11.8 | BG39: 6.2 | BH39: 0.6 | BI39: 104.9 | BJ39: 133.3 | BL39: 3.1 | BM39: 5.2 | BN39: 23 | BO39: 3.8 | BP39: 0.8 | BQ39: 2.3 | BR39: 2.4 | BS39: 8.9 | BT39: 1.2 | BU39: 20 | BV39: 8 | BW39: 20 | BX39: 4.6 | BY39: 20.5 | BZ39: 1414.1
B40: 16:30 | D40: 17 | E40: 13.6 | F40: 8.6 | G40: 11 | H40: 12.5 | I40: 2.5 | J40: 0.4 | K40: 9.4 | L40: 11.3 | M40: 20 | N40: 0.1 | O40: 0.1 | P40: 19.8 | R40: 19.9 | S40: 20.2 | T40: 6.9 | U40: 3.5 | V40: 4.8 | W40: 14.6 | Y40: 18.5 | Z40: 49 | AA40: 14.9 | AB40: 62.1 | AE40: 6.8 | AF40: 103.6 | AG40: 0.9 | AH40: 2.3 | AI40: 20.9 | AJ40: 8 | AK40: 20.4 | AL40: 20.4 | AM40: 20 | AN40: 7 | AO40: 70.3 | AP40: 9.6 | AQ40: 5.1 | AS40: 3.4 | AT40: 18.4 | AV40: 32.2 | AW40: 33.5 | AY40: 0.1 | AZ40: 3.1 | BA40: 2.3 | BC40: 2 | BD40: 5.5 | BE40: 10 | BF40: 33.6 | BG40: 21.9 | BH40: 0.6 | BI40: 97.4 | BJ40: 131.5 | BL40: 1.6 | BM40: 5.1 | BN40: 21.1 | BO40: 3.8 | BP40: 0.8 | BQ40: 2.3 | BR40: 2.4 | BS40: 1 | BU40: 20.1 | BV40: 7.9 | BW40: 20 | BX40: 5.5 | BZ40: 1123.1
B41: 17:00 | D41: 16.8 | E41: 13.6 | F41: 9.3 | G41: 11.1 | H41: 9.7 | I41: 2.5 | J41: 0.4 | K41: 8.6 | L41: 11.3 | M41: 20 | O41: 0.1 | P41: 19.8 | R41: 19.8 | S41: 20.2 | T41: 6.7 | U41: 3.5 | V41: 4.8 | Y41: 18.5 | Z41: 47.2 | AA41: 13.2 | AB41: 60.5 | AE41: 7.4 | AF41: 98.6 | AG41: 2.5 | AH41: 1.6 | AI41: 20.9 | AJ41: 8 | AK41: 20.4 | AL41: 20.4 | AM41: 20 | AN41: 7 | AO41: 19.1 | AP41: 5.8 | AQ41: 4.3 | AS41: 3.4 | AT41: 18.4 | AV41: 5.3 | AW41: 4.8 | AY41: 0.1 | AZ41: 3.1 | BA41: 1 | BC41: 1.1 | BD41: 5.5 | BE41: 9.9 | BF41: 26.9 | BG41: 26.2 | BH41: 0.6 | BI41: 76.8 | BJ41: 60.2 | BL41: 0.9 | BM41: 5.4 | BN41: 17.8 | BO41: 3.8 | BP41: 0.8 | BQ41: 2.3 | BR41: 2.4 | BS41: 0.6 | BT41: 1.6 | BU41: 20 | BV41: 7.9 | BW41: 20 | BX41: 9.9 | BZ41: 890.3
B42: 17:30 | D42: 17.1 | E42: 16.8 | F42: 8.5 | G42: 11 | H42: 9.8 | I42: 2.5 | J42: 0.4 | K42: 9.1 | L42: 15.7 | M42: 20 | O42: 0.1 | P42: 19.8 | R42: 19.8 | S42: 20.2 | T42: 6.7 | U42: 3.6 | V42: 4.8 | Y42: 18.6 | Z42: 47.4 | AA42: 8.9 | AB42: 60.5 | AE42: 6.2 | AF42: 83.5 | AG42: 2.3 | AH42: 3.3 | AI42: 20.9 | AJ42: 8 | AK42: 20.4 | AL42: 20.4 | AM42: 20 | AN42: 7 | AO42: 2.4 | AP42: 8 | AQ42: 4.7 | AS42: 3.4 | AT42: 18.4 | AV42: 1 | AW42: 1.1 | AZ42: 3.1 | BA42: 0.5 | BC42: 0.4 | BD42: 5.4 | BE42: 9.9 | BF42: 43.5 | BG42: 27.3 | BH42: 0.6 | BI42: 29.6 | BJ42: 27.6 | BL42: 0.2 | BM42: 7.3 | BN42: 24.6 | BO42: 3.8 | BP42: 0.8 | BQ42: 2.3 | BR42: 2.4 | BU42: 20 | BV42: 8 | BW42: 20 | BX42: 2.9 | BZ42: 792.5
B43: 18:00 | D43: 17.1 | E43: 17.1 | F43: 8.3 | G43: 10.3 | H43: 9.7 | I43: 2.5 | J43: 0.4 | K43: 9.4 | L43: 16.5 | M43: 20 | P43: 19.8 | R43: 19.8 | S43: 20.2 | T43: 7 | U43: 3.6 | V43: 4.7 | Y43: 18.6 | Z43: 44 | AA43: 5.7 | AB43: 58.5 | AE43: 5.3 | AF43: 84.6 | AH43: 3.2 | AI43: 20.9 | AJ43: 8 | AK43: 20.4 | AL43: 20.4 | AM43: 20 | AN43: 7 | AP43: 4.1 | AQ43: 1.8 | AS43: 3.4 | AT43: 18.4 | AZ43: 3.1 | BD43: 5.5 | BE43: 10 | BF43: 59.8 | BG43: 62.2 | BH43: 0.6 | BI43: 2.7 | BJ43: 3 | BM43: 9.5 | BN43: 28.5 | BO43: 4 | BP43: 0.8 | BQ43: 2.2 | BR43: 2.4 | BU43: 20 | BV43: 7.9 | BW43: 20 | BX43: 0.2 | BZ43: 773.1
B44: 18:30 | D44: 17.1 | E44: 17.1 | F44: 8.5 | G44: 10.6 | H44: 9.7 | I44: 2.6 | J44: 0.4 | K44: 8.9 | L44: 19.1 | M44: 20 | P44: 19.8 | R44: 19.8 | S44: 20.2 | T44: 6.9 | U44: 3.6 | V44: 4.7 | Y44: 18.6 | Z44: 35.9 | AA44: 4.1 | AB44: 58.5 | AE44: 7.1 | AF44: 83.5 | AI44: 20.9 | AJ44: 8 | AK44: 20.4 | AL44: 20.4 | AM44: 20 | AN44: 7.2 | AP44: 5.3 | AQ44: 4.2 | AS44: 3.4 | AT44: 18.4 | AZ44: 3.1 | BD44: 5.4 | BE44: 10 | BF44: 92.9 | BG44: 87.8 | BH44: 0.6 | BM44: 12.8 | BN44: 44 | BO44: 4 | BP44: 0.8 | BQ44: 2.2 | BR44: 2.4 | BU44: 20 | BV44: 8 | BW44: 20 | BZ44: 838.9
B45: 19:00 | D45: 16.8 | E45: 17.1 | F45: 9.2 | G45: 11.5 | H45: 9.7 | I45: 2.7 | J45: 0.4 | K45: 8.9 | L45: 20.2 | M45: 20 | P45: 18 | R45: 19.9 | S45: 20.2 | T45: 7 | U45: 3.6 | V45: 4.9 | Y45: 18.6 | Z45: 34.5 | AA45: 3.2 | AB45: 56.9 | AE45: 8 | AF45: 96.4 | AI45: 20.9 | AJ45: 8 | AK45: 20.4 | AL45: 20.4 | AM45: 20 | AN45: 7.2 | AS45: 3.4 | AT45: 18.4 | AZ45: 3.1 | BD45: 5.5 | BE45: 9.9 | BF45: 79.6 | BG45: 89.3 | BH45: 0.6 | BM45: 15.6 | BN45: 49.3 | BO45: 4 | BP45: 0.8 | BQ45: 2.2 | BR45: 2.4 | BU45: 20 | BV45: 8 | BW45: 20 | BZ45: 836.7
B46: 19:30 | D46: 16.7 | E46: 17.1 | F46: 7.9 | G46: 11.1 | H46: 16.4 | I46: 2.8 | J46: 0.4 | K46: 9 | L46: 21.5 | M46: 20.1 | P46: 17.9 | R46: 19.9 | S46: 20.2 | T46: 7 | U46: 3.6 | V46: 4.8 | Y46: 18.6 | Z46: 34.3 | AA46: 5.2 | AB46: 56.9 | AE46: 6.1 | AF46: 125.4 | AI46: 20.9 | AJ46: 8 | AK46: 20.4 | AL46: 20.4 | AM46: 20 | AN46: 7.2 | AS46: 3.4 | AT46: 18.4 | AZ46: 3.1 | BD46: 5.4 | BE46: 10 | BF46: 79.6 | BG46: 81 | BH46: 0.6 | BM46: 15.6 | BN46: 49.9 | BO46: 4 | BP46: 0.8 | BQ46: 2.3 | BR46: 2.4 | BU46: 20 | BV46: 7.9 | BW46: 20 | BY46: 20.9 | BZ46: 885.1
B47: 20:00 | D47: 16.8 | E47: 17.1 | F47: 8.9 | G47: 11.1 | H47: 20 | I47: 2.9 | J47: 0.4 | K47: 8.8 | L47: 21.4 | M47: 20.1 | P47: 12.3 | R47: 19.9 | S47: 20.2 | T47: 7 | U47: 3.6 | V47: 4.8 | Y47: 18.5 | Z47: 36.1 | AA47: 8.3 | AB47: 56.2 | AE47: 9.9 | AF47: 143.3 | AI47: 20.9 | AJ47: 8 | AK47: 20.4 | AL47: 20.4 | AM47: 20 | AN47: 7.2 | AS47: 3.4 | AT47: 18.4 | AZ47: 3.1 | BD47: 5.5 | BE47: 9.9 | BF47: 68.1 | BG47: 81.3 | BH47: 0.6 | BM47: 15.9 | BN47: 49.3 | BO47: 4.1 | BP47: 0.8 | BQ47: 2.4 | BR47: 2.4 | BU47: 20 | BV47: 8 | BW47: 20 | BY47: 20.9 | BZ47: 898.6
B48: 20:30 | D48: 16.6 | E48: 17.2 | F48: 8 | G48: 11.1 | H48: 20.3 | I48: 3 | J48: 0.4 | K48: 8.7 | L48: 21.6 | M48: 20 | P48: 18.4 | R48: 20 | S48: 20.2 | T48: 7.1 | U48: 3.6 | V48: 4.9 | W48: 20.5 | Y48: 18.5 | Z48: 39 | AA48: 8.7 | AB48: 56.2 | AE48: 7.9 | AF48: 138.4 | AI48: 20.9 | AJ48: 8 | AK48: 20.4 | AL48: 20.4 | AM48: 20 | AN48: 7.2 | AS48: 3.4 | AT48: 18.4 | AZ48: 3.1 | BD48: 5.4 | BE48: 10 | BF48: 59.2 | BG48: 79.2 | BH48: 0.6 | BM48: 15 | BN48: 48.6 | BO48: 4.1 | BP48: 0.8 | BQ48: 2.4 | BR48: 2.4 | BU48: 20.1 | BV48: 8 | BW48: 20 | BY48: 20.3 | BZ48: 908.2
B49: 21:00 | D49: 16.7 | E49: 16.3 | F49: 8.5 | G49: 11.2 | H49: 20.3 | I49: 3.2 | J49: 0.4 | K49: 9 | L49: 21.3 | M49: 20 | P49: 19.4 | R49: 19.9 | S49: 20.2 | T49: 7.4 | U49: 3.6 | V49: 4.9 | W49: 20.4 | Y49: 18.6 | Z49: 43.5 | AA49: 8 | AB49: 54.9 | AE49: 7.3 | AF49: 133.1 | AI49: 20.9 | AJ49: 7.9 | AK49: 20.4 | AL49: 20.4 | AM49: 20 | AN49: 6 | AS49: 3.4 | AT49: 18.4 | AZ49: 3.1 | BD49: 5.5 | BE49: 9.9 | BF49: 50.9 | BG49: 70.2 | BH49: 0.6 | BM49: 15.3 | BN49: 47.5 | BO49: 4.1 | BP49: 0.8 | BQ49: 2.4 | BR49: 2.4 | BU49: 20 | BV49: 8 | BW49: 20 | BY49: 20.2 | BZ49: 886.4
B50: 21:30 | D50: 16.8 | E50: 17.1 | F50: 8.3 | G50: 11.2 | H50: 20.3 | I50: 3.2 | J50: 0.4 | K50: 9.2 | L50: 21.1 | M50: 20 | P50: 19.2 | R50: 19.8 | S50: 20.2 | T50: 7.4 | U50: 2.5 | V50: 4.8 | W50: 20.3 | Y50: 18.6 | Z50: 37 | AA50: 8 | AB50: 54.9 | AE50: 8.8 | AF50: 146.5 | AI50: 20.9 | AJ50: 7.9 | AK50: 20.4 | AL50: 20.4 | AM50: 20 | AN50: 5.8 | AS50: 3.4 | AT50: 18.4 | AZ50: 3.1 | BD50: 5.2 | BE50: 9.9 | BF50: 43.3 | BG50: 57.1 | BH50: 0.6 | BM50: 14.6 | BN50: 49.5 | BO50: 4.1 | BP50: 0.8 | BQ50: 2.4 | BR50: 2.4 | BU50: 20 | BV50: 8 | BW50: 20 | BY50: 20.2 | BZ50: 874
B51: 22:00 | D51: 15.8 | E51: 16.7 | F51: 8.5 | G51: 11.3 | H51: 20.2 | I51: 3.1 | J51: 0.4 | K51: 9.4 | L51: 19.1 | M51: 20 | P51: 19.1 | R51: 19.9 | S51: 20.2 | T51: 7.4 | U51: 2.7 | V51: 4.8 | W51: 20.5 | Y51: 18.6 | Z51: 35.2 | AA51: 7.1 | AB51: 53.8 | AE51: 5.9 | AF51: 114.3 | AI51: 20.9 | AJ51: 7.9 | AK51: 20.4 | AL51: 20.4 | AM51: 20 | AN51: 6.1 | AS51: 3.4 | AT51: 18.4 | AZ51: 3.1 | BD51: 5.5 | BE51: 9.9 | BF51: 50.7 | BG51: 64.1 | BH51: 0.6 | BM51: 15.6 | BN51: 48.1 | BO51: 4.1 | BP51: 0.8 | BQ51: 2.4 | BR51: 2.4 | BU51: 20 | BV51: 8 | BW51: 20 | BY51: 20.4 | BZ51: 847.2
B52: 22:30 | D52: 16.7 | E52: 17.1 | F52: 7.6 | G52: 11.3 | H52: 20.2 | I52: 3.1 | J52: 0.4 | K52: 9.2 | L52: 19 | M52: 20 | P52: 19.2 | R52: 19.9 | S52: 20.2 | T52: 7.4 | U52: 2.2 | V52: 4.9 | W52: 20.3 | Y52: 18.7 | Z52: 26 | AA52: 5.2 | AB52: 53.8 | AE52: 6.9 | AF52: 96.1 | AI52: 20.9 | AJ52: 7.8 | AK52: 20.4 | AL52: 20.4 | AM52: 20 | AN52: 6.1 | AS52: 3.4 | AT52: 18.4 | AZ52: 3.1 | BD52: 5.3 | BE52: 10 | BF52: 38.2 | BG52: 54.2 | BH52: 0.6 | BM52: 13.8 | BN52: 39.7 | BO52: 4.1 | BP52: 0.8 | BQ52: 2.4 | BR52: 2.4 | BU52: 20.1 | BV52: 8 | BW52: 20 | BY52: 20.2 | BZ52: 785.7
B53: 23:00 | D53: 16 | E53: 17.1 | F53: 8.3 | G53: 11.3 | H53: 20 | I53: 3.1 | J53: 0.4 | K53: 9.4 | L53: 20.9 | M53: 20 | P53: 19.4 | R53: 19.7 | S53: 20.1 | T53: 7.4 | U53: 3.6 | V53: 4.9 | W53: 20.4 | Y53: 18.7 | Z53: 20.5 | AA53: 6.3 | AB53: 53.5 | AE53: 4.1 | AF53: 67.1 | AI53: 20.9 | AJ53: 7.8 | AK53: 20.4 | AL53: 20.4 | AM53: 20 | AN53: 7 | AS53: 3.4 | AT53: 18.4 | AZ53: 3.1 | BD53: 5.5 | BE53: 10 | BF53: 14.5 | BG53: 23 | BH53: 0.6 | BM53: 11.7 | BN53: 29.7 | BO53: 4 | BP53: 0.8 | BQ53: 2.4 | BR53: 2.4 | BU53: 20 | BV53: 8 | BW53: 19.9 | BY53: 20.2 | BZ53: 686.3
B54: 23:30 | D54: 16.7 | E54: 17.1 | F54: 8.9 | G54: 11.3 | H54: 9.4 | I54: 3.1 | J54: 0.4 | K54: 9.1 | L54: 21.7 | M54: 20.2 | P54: 19.5 | R54: 19.9 | S54: 20.2 | T54: 7.5 | U54: 3.6 | V54: 4.8 | W54: 20.8 | Y54: 18.7 | Z54: 18.7 | AA54: 2.7 | AB54: 53.5 | AE54: 1.7 | AF54: 63.5 | AI54: 20.4 | AJ54: 7.8 | AK54: 20.4 | AL54: 20.4 | AM54: 20 | AN54: 6.2 | AS54: 3.4 | AT54: 18.4 | AZ54: 3.1 | BD54: 5.5 | BE54: 9.9 | BF54: 7.9 | BG54: 10.7 | BH54: 0.6 | BM54: 12.8 | BN54: 26.6 | BO54: 4.1 | BP54: 0.8 | BQ54: 2.4 | BR54: 2.4 | BU54: 20 | BV54: 8 | BW54: 20 | BY54: 20.4 | BZ54: 645.2
B55: 0:00 | D55: 17.1 | E55: 17.2 | F55: 8.7 | G55: 11.3 | H55: 6.1 | I55: 3 | J55: 0.4 | K55: 9.1 | L55: 20 | M55: 20 | P55: 19.5 | R55: 19.4 | S55: 20.1 | T55: 7.6 | U55: 3.6 | V55: 4.8 | W55: 20 | Y55: 18.7 | Z55: 17.9 | AA55: 1.7 | AB55: 54.9 | AE55: 2.1 | AF55: 65.9 | AI55: 20.4 | AJ55: 7.8 | AK55: 20.4 | AL55: 20.4 | AM55: 20 | AN55: 6.3 | AS55: 3.4 | AT55: 18.4 | AZ55: 3.1 | BD55: 5.5 | BE55: 9.9 | BF55: 6 | BG55: 9.4 | BH55: 0.6 | BM55: 8.4 | BN55: 17.3 | BO55: 4.1 | BP55: 0.8 | BQ55: 2.4 | BR55: 2.4 | BU55: 20 | BV55: 8 | BW55: 20 | BY55: 20.1 | BZ55: 624.2
B56: EJEC MWh | C56: 0 | D56: 392.25 | E56: 349.25 | F56: 201.45 | G56: 262.4 | H56: 228.45 | I56: 64.95 | J56: 9.6 | K56: 195.05 | L56: 329.15 | M56: 480.3 | N56: 2 | O56: 3.4 | P56: 467.25 | Q56: 0 | R56: 479.2 | S56: 484.65 | T56: 176.9 | U56: 80.05 | V56: 115.85 | W56: 413.75 | X56: 155.4 | Y56: 446.9 | Z56: 512.5 | AA56: 150.2 | AB56: 1170.05 | AC56: 0 | AD56: 0 | AE56: 153.15 | AF56: 1978.65 | AG56: 182.7 | AH56: 225.9 | AI56: 486.6 | AJ56: 180.95 | AK56: 489.6 | AL56: 489.6 | AM56: 480 | AN56: 139.7 | AO56: 610.5 | AP56: 76.6 | AQ56: 43.75 | AR56: 0 | AS56: 81.6 | AT56: 441.6 | AU56: 0 | AV56: 1570.7 | AW56: 1304.8 | AX56: 0 | AY56: 1.5 | AZ56: 60.5 | BA56: 105.05 | BB56: 0 | BC56: 124.75 | BD56: 130.45 | BE56: 238.65 | BF56: 513.15 | BG56: 533.5 | BH56: 14.4 | BI56: 915.7 | BJ56: 1221.95 | BK56: 0 | BL56: 155.45 | BM56: 222.8 | BN56: 733.9 | BO56: 93.3 | BP56: 19.2 | BQ56: 54.9 | BR56: 57.6 | BS56: 91.15 | BT56: 31.7 | BU56: 480.95 | BV56: 191.55 | BW56: 480.05 | BX56: 130.25 | BY56: 426.4 | BZ56: 23136.15
L70: TERMOELÉCTRICA | M70: 1954.55 | N70: 8.4480348 | O70: #FFA975
L71: EÓLICA | M71: 6088.25 | N71: 26.31488 | O71: #B9ACFF
L72: SOLAR | M72: 6645.8 | N72: 28.724745 | O72: #FFD272
L73: HIDROELÉCTRICA | M73: 8447.55 | N73: 36.512341 | O73: #98D2FF

Sheet COGENERACIÓN
B3: jueves, 12 de Febrero del 2026
B5: CENTRALES DE COGENERACIÓN DEL SEIN
B6: HORA | C6: AGRO INDUSTRIAL PARAMONGA S.A. | D6: AGROAURORA S.A.C. | E6: AGROINDUSTRIAS SAN JACINTO S.A.A. | F6: AGROLMOS SOCIEDAD ANONIMA - AGROLMOS S.A. | G6: BIOENERGIA DEL CHIRA S.A. | H6: CASA GRANDE S.A.A. | I6: GM OPERACIONES S.A.C. | J6: TOTAL COGENERACION
C7: C.T. PARAMONGA | D7: C.T. MAPLE | E7: C.T SAN JACINTO | F7: C.T. AGROLMOS | G7: C.T. CAÑA BRAVA | H7: C.T. CASA GRANDE | I7: C.T. REFINERÍA TALARA | J7: MW
B8: 0:30 | C8: 15.4 | D8: 13.5 | E8: 6.1 | F8: 11.7 | G8: 9 | H8: 16.2 | I8: 61.8 | J8: 133.7
B9: 1:00 | C9: 15.2 | D9: 13.5 | E9: 8.8 | F9: 11.7 | G9: 8.4 | H9: 8 | I9: 61.7 | J9: 127.3
B10: 1:30 | C10: 14.7 | D10: 13.5 | E10: 8.9 | F10: 11.7 | G10: 8.5 | H10: 9.8 | I10: 62.3 | J10: 129.4
B11: 2:00 | C11: 14.9 | D11: 13.5 | E11: 8.9 | F11: 11.6 | G11: 8.7 | H11: 10 | I11: 62.4 | J11: 130
B12: 2:30 | C12: 15.2 | D12: 13.5 | E12: 8.9 | F12: 11.6 | G12: 9.1 | H12: 11.6 | I12: 62.5 | J12: 132.4
B13: 3:00 | C13: 15.2 | D13: 13.6 | E13: 8.9 | F13: 11.6 | G13: 9 | H13: 11.3 | I13: 62.5 | J13: 132.1
B14: 3:30 | C14: 15.1 | D14: 13.5 | E14: 9 | F14: 11.6 | G14: 8.9 | H14: 11.2 | I14: 62.7 | J14: 132
B15: 4:00 | C15: 15.3 | D15: 13.6 | E15: 8 | F15: 11.6 | G15: 8.9 | H15: 11.4 | I15: 62.5 | J15: 131.3
B16: 4:30 | C16: 15.2 | D16: 13.5 | E16: 8.7 | F16: 11.6 | G16: 8.8 | H16: 11.2 | I16: 63.2 | J16: 132.2
B17: 5:00 | C17: 15.4 | D17: 13.5 | E17: 7.8 | F17: 11.7 | G17: 8.5 | H17: 11.1 | I17: 62.4 | J17: 130.4
B18: 5:30 | C18: 16 | D18: 13.5 | E18: 7.3 | F18: 11.6 | G18: 9.1 | H18: 11.2 | I18: 62.5 | J18: 131.2
B19: 6:00 | C19: 16.1 | D19: 13.5 | E19: 9.1 | F19: 11.6 | G19: 9.1 | H19: 11.2 | I19: 62.4 | J19: 133
... B25: 9:00 | C25: 16.8 | D25: 13.6 | E25: 7.9 | F25: 10.6 | G25: 8.7 | H25: 11.2 | I25: 61.9 | J25: 130.7
B26: 9:30 | C26: 17 | D26: 13.6 | E26: 7.4 | F26: 10.5 | H26: 11.3 | I26: 62.1 | J26: 121.9
B27: 10:00 | C27: 17.1 | D27: 13.6 | E27: 7.8 | F27: 10.6 | G27: 4.6 | H27: 11.3 | I27: 61.9 | J27: 126.9
B28: 10:30 | C28: 16.3 | D28: 13.6 | E28: 7.7 | F28: 10.5 | G28: 4.8 | H28: 11.2 | I28: 61.6 | J28: 125.7
B29: 11:00 | C29: 16.1 | D29: 13.5 | E29: 6.9 | F29: 11 | G29: 6.1 | H29: 10 | I29: 62.1 | J29: 125.7
B30: 11:30 | C30: 16.5 | D30: 13.5 | E30: 7.6 | F30: 10.6 | G30: 5.4 | H30: 9.9 | I30: 62.6 | J30: 126.1
B31: 12:00 | C31: 16.7 | D31: 13.6 | E31: 8.5 | F31: 10 | G31: 5.2 | H31: 11.4 | I31: 62.3 | J31: 127.7
B32: 12:30 | C32: 16.6 | D32: 13.5 | E32: 8.8 | F32: 10 | G32: 5.3 | H32: 11.4 | I32: 61.7 | J32: 127.3
B33: 13:00 | C33: 16.5 | D33: 13.5 | E33: 8.9 | F33: 10.5 | G33: 5.2 | H33: 11.2 | I33: 61.7 | J33: 127.5
B34: 13:30 | C34: 17.2 | D34: 13.5 | E34: 8.6 | F34: 6.5 | G34: 5.5 | H34: 11.3 | I34: 61.9 | J34: 124.5
B35: 14:00 | C35: 17 | D35: 13.5 | E35: 9.4 | F35: 8.4 | G35: 8.7 | H35: 10 | I35: 62.2 | J35: 129.2
B36: 14:30 | C36: 17 | D36: 13.6 | E36: 8.1 | F36: 11 | G36: 6.9 | H36: 11.4 | I36: 62 | J36: 130
B37: 15:00 | C37: 17.1 | D37: 13.6 | E37: 9.2 | F37: 10.8 | G37: 8.7 | H37: 11.5 | I37: 62 | J37: 132.9
B38: 15:30 | C38: 17 | D38: 13.6 | E38: 9.2 | F38: 10.9 | G38: 9.4 | H38: 11.5 | I38: 62.2 | J38: 133.8
... B56: EJEC MWh | C56: 392.25 | D56: 349.25 | E56: 201.45 | F56: 262.4 | G56: 195.05 | H56: 329.15 | I56: 1492.5 | J56: 3222.05

Sheet EVO_PRO_ENE
B3: domingo, 1 de Febrero del 2026 - jueves, 12 de Febrero del 2026
B5: EVOLUCIÓN DE LA PRODUCCIÓN DE LA ENERGÍA DIARIA DE LOS INTEGRANTES DEL COES (MWh)
B6: EMPRESA | C6: CENTRAL | D6: UNIDAD | E6: TIPO | F6: Febrero
F7: 1 | G7: 2 | H7: 3 | I7: 4 | J7: 5 | K7: 6 | L7: 7 | M7: 8 | N7: 9 | O7: 10 | P7: 11 | Q7: 12 | R7: TOTAL
B8: AGRO INDUSTRIAL PARAMONGA S.A. | C8: C.T. PARAMONGA | D8: TV-01 | E8: TERMOELÉCTRICA | F8: 92.9 | H8: 156.65 | I8: 345.05 | J8: 344.4 | K8: 351.7 | L8: 348.35 | M8: 344.1 | N8: 355.8 | O8: 358.15 | P8: 366.1 | Q8: 392.25 | R8: 3455.45
B9: AGROAURORA S.A.C. | C9: C.T. MAPLE ETANOL | D9: TV | E9: TERMOELÉCTRICA | F9: 110.05 | G9: 117.1 | H9: 78.05 | I9: 116.6 | J9: 112.25 | K9: 175.5 | L9: 405.55 | M9: 393.3 | N9: 419.14 | O9: 333.35 | P9: 344.5 | Q9: 349.25 | R9: 2954.64
B10: AGROINDUSTRIAS SAN JACINTO S.A.A. | C10: C.T. SAN JACINTO | D10: CENTRAL | E10: TERMOELÉCTRICA | F10: 192 | G10: 124.86 | J10: 66.05 | K10: 176.1 | L10: 118.65 | M10: 194.1 | N10: 187.821 | O10: 187 | P10: 163.938 | Q10: 201.45 | R10: 1611.969
B11: AGROLMOS SOCIEDAD ANONIMA - AGROLMOS S.A. | C11: C.T. AGROLMOS | D11: CENTRAL | E11: TERMOELÉCTRICA | F11: 217.05 | G11: 54.5 | H11: 154.01 | I11: 184.25 | J11: 265.85 | K11: 269.95 | L11: 216.55 | M11: 269.2 | N11: 270.6273 | O11: 270.05 | P11: 271.88135 | Q11: 262.4 | R11: 2706.3187
B12: ANDEAN POWER S.A.C. | C12: C.H.CARHUAC | D12: CENTRAL | E12: HIDROELÉCTRICA | F12: 358.3 | G12: 451.75 | H12: 464.5 | I12: 443.25 | J12: 354.65 | K12: 312.35 | L12: 297.1 | M12: 254.6 | N12: 218.65 | O12: 230.4 | P12: 221.75 | Q12: 228.45 | R12: 3835.75
B13: ASOCIACIÓN SANTA LUCIA DE CHACAS | C13: C.H. HUALLIN | D13: CENTRAL | E13: HIDROELÉCTRICA | F13: 73.55 | G13: 74.4 | H13: 72.05 | I13: 73.5 | J13: 73.8 | K13: 75.7 | L13: 69.4 | M13: 64.4 | N13: 64.45 | O13: 64.15 | P13: 64.65 | Q13: 64.95 | R13: 835
B14: ATRIA ENERGIA S.A.C. | C14: C.H. PURMACANA | D14: CENTRAL | E14: HIDROELÉCTRICA | F14: 9.6 | G14: 9.4 | H14: 8.5 | I14: 8.1 | J14: 7.3 | K14: 8.65 | L14: 9.6 | M14: 9.6 | N14: 9.6 | O14: 7.75 | P14: 7.8 | Q14: 9.6 | R14: 105.5
B15: BIOENERGIA DEL CHIRA S.A. | C15: C.T. CAÑA BRAVA | D15: CENTRAL | E15: TERMOELÉCTRICA | F15: 218.2 | G15: 209.25 | H15: 197.7 | I15: 219.2 | J15: 219.95 | K15: 214.1 | L15: 211.45 | M15: 183.75 | N15: 218.8 | O15: 216.45 | P15: 218.55 | Q15: 195.05 | R15: 2522.45
B16: CASA GRANDE S.A.A. | C16: C.T. CASA GRANDE | D16: TV3 | E16: TERMOELÉCTRICA | F16: 500.25 | G16: 273.865 | H16: 509.65 | I16: 507.8 | J16: 509.3 | K16: 506.55 | L16: 509.15 | M16: 494.55 | N16: 487.43705 | O16: 529.85 | P16: 461.59405 | Q16: 329.15 | R16: 5619.1461
B17: CELARIS ENERGY S.A. | C17: C.H. MANTA I | D17: CENTRAL | E17: HIDROELÉCTRICA | F17: 480.2 | G17: 323.8 | H17: 480.4 | I17: 461.1 | J17: 480.05 | K17: 479.9 | L17: 321.75 | M17: 239.1 | N17: 479.85 | O17: 435.45 | P17: 400.65 | Q17: 480.3 | R17: 5062.55
B18: CELEPSA | C18: C.H. EL PLATANAL | D18: CENTRAL | E18: HIDROELÉCTRICA | F18: 3920.15 | G18: 4860.55 | H18: 4886.25 | I18: 4890.05 | J18: 4601.45 | K18: 4459.6 | L18: 4787.6 | M18: 4228.75 | N18: 4244.15 | O18: 4631.6 | P18: 4966.05 | Q18: 4995.15 | R18: 55471.35
B19: CELEPSA RENOVABLES S.R.L. | C19: C.H. MARAÑON | D19: CENTRAL | E19: HIDROELÉCTRICA | F19: 451.2 | G19: 443.15 | H19: 446.85 | I19: 451.2 | J19: 446 | K19: 451.2 | L19: 451.2 | M19: 451.2 | N19: 413.8 | O19: 451.75 | P19: 453.6 | Q19: 453.6 | R19: 5364.75
B20: CENTRALES SANTA ROSA S.A.C. | C20: C.H. SANTA ROSA I | D20: CENTRAL | E20: HIDROELÉCTRICA | R20: 0
B21: CENTRALES SANTA ROSA S.A.C. | C21: C.H. SANTA ROSA II | D21: CENTRAL | E21: HIDROELÉCTRICA | R21: 0
B22: CHINANGO S.A.C. | C22: C.H. CHIMAY | D22: CENTRAL | E22: HIDROELÉCTRICA | F22: 3261.4 | G22: 3502.8 | H22: 3592.9 | I22: 3595.7 | J22: 3627.85 | K22: 3591.45 | L22: 3559.25 | M22: 2764.85 | N22: 3468.6 | O22: 3621.75 | P22: 3642.55 | Q22: 3622.2 | R22: 41851.3
B23: CHINANGO S.A.C. | C23: C.H. YANANGO | D23: CENTRAL | E23: HIDROELÉCTRICA | F23: 1012.15 | G23: 1008.65 | H23: 1008.6 | I23: 1007.9 | J23: 1008.3 | K23: 1008.7 | L23: 1008.6 | M23: 1008.2 | N23: 1008.75 | O23: 1008.95 | P23: 954.05 | Q23: 792.85 | R23: 11835.7
B24: COENERGY S.A.C. | C24: C.S. COENERGY | D24: CENTRAL | E24: SOLAR | F24: 2.55 | G24: 2.65 | H24: 2.55 | I24: 2.75 | J24: 3 | K24: 2.85 | L24: 3.1 | M24: 2.55 | N24: 2.9 | O24: 3.05 | P24: 1.8 | Q24: 2 | R24: 31.75
B25: COLCA SOLAR S.A.C. | C25: C.S. YARUCAYA | D25: CENTRAL | E25: SOLAR | F25: 4.6 | G25: 3.15 | H25: 4.75 | I25: 6.05 | J25: 7.9 | K25: 4.25 | L25: 3.25 | M25: 8.35 | N25: 7.05 | O25: 7 | P25: 6.1 | Q25: 3.4 | R25: 65.85
B26: EGASA | C26: C.H. CHARCANI III | D26: CENTRAL | E26: HIDROELÉCTRICA | F26: 15.6 | G26: 90.55 | H26: 143.75 | I26: 140.8 | J26: 155.7 | K26: 160.25 | L26: 162.2 | M26: 158.45 | N26: 161.1 | O26: 158 | P26: 159.95 | Q26: 160.7 | R26: 1667.05
B27: EGASA | C27: C.H. CHARCANI IV | D27: CENTRAL | E27: HIDROELÉCTRICA | R27: 0
B28: EGASA | C28: C.H. CHARCANI V | D28: CENTRAL | E28: HIDROELÉCTRICA | F28: 3416.55 | G28: 3417.7 | H28: 3419.05 | I28: 3413.95 | J28: 3413.2 | K28: 3410.65 | L28: 3416.5 | M28: 3390.17 | N28: 3415.75 | O28: 3410.75 | P28: 3415.1 | Q28: 3420.1 | R28: 40959.47
B29: EGASA | C29: C.H. CHARCANI VI | D29: CENTRAL | E29: HIDROELÉCTRICA | R29: 0
B30: EGASA | C30: C.T. CHILINA DIESEL | D30: CENTRAL | E30: TERMOELÉCTRICA | H30: 1.65 | I30: 1.05 | R30: 2.7
B31: EGASA | C31: C.T. CHILINA DIESEL | D31: TG | E31: TERMOELÉCTRICA | G31: 11.15 | R31: 11.15
B32: EGASA | C32: C.T. MOLLENDO DIESEL | D32: CENTRAL | E32: TERMOELÉCTRICA | R32: 0
B33: EGEJUNIN | C33: C.H. HUASAHUASI I | D33: CENTRAL | E33: HIDROELÉCTRICA | F33: 475.1 | G33: 473.7 | H33: 472.9 | I33: 474.85 | J33: 475.15 | K33: 475.25 | L33: 474.7 | M33: 475.5 | N33: 473.8 | O33: 474.85 | P33: 475.3 | Q33: 467.25 | R33: 5688.35
B34: EGEJUNIN | C34: C.H. RUNATULLO II | D34: CENTRAL | E34: HIDROELÉCTRICA | F34: 481.7 | G34: 479 | H34: 480.35 | I34: 480.25 | J34: 480.65 | K34: 481.85 | L34: 475.45 | M34: 479.1 | N34: 482.6 | O34: 483 | P34: 484.8 | Q34: 479.2 | R34: 5767.95
B35: EGEJUNIN | C35: C.H. RUNATULLO III | D35: CENTRAL | E35: HIDROELÉCTRICA | F35: 486.05 | G35: 485.95 | H35: 486.25 | I35: 486.25 | J35: 486.35 | K35: 484.75 | L35: 484.7 | M35: 484.6 | N35: 484.6 | O35: 484.65 | P35: 484.95 | Q35: 484.65 | R35: 5823.75
B36: EGEJUNIN | C36: C.H. SANTA CRUZ I | D36: CENTRAL | E36: HIDROELÉCTRICA | F36: 310.05 | G36: 306.8 | H36: 306.75 | I36: 263.75 | J36: 274.95 | K36: 266.35 | L36: 244.05 | M36: 217 | N36: 192.1 | O36: 167.25 | P36: 177.75 | Q36: 176.9 | R36: 2903.7
B37: EGEMSA | C37: C.H. MACHUPICCHU | D37: CENTRAL | E37: HIDROELÉCTRICA | F37: 3900 | G37: 3964.95 | H37: 3996.95 | I37: 3992.4 | J37: 3993.9 | K37: 3993.15 | L37: 3973.15 | M37: 3554.7 | N37: 3991.2 | O37: 3963.3 | P37: 3985.95 | Q37: 3979.95 | R37: 47289.6
B38: EGESUR | C38: C.H. ARICOTA I | D38: CENTRAL | E38: HIDROELÉCTRICA | F38: 193.15 | G38: 193.75 | H38: 195.55 | I38: 189.75 | J38: 191 | K38: 191.5 | L38: 192.4 | M38: 189.3 | N38: 189.1 | O38: 189.25 | P38: 191.85 | Q38: 190.5 | R38: 2297.1
B39: EGESUR | C39: C.H. ARICOTA II | D39: CENTRAL | E39: HIDROELÉCTRICA | F39: 128.65 | G39: 131.75 | H39: 131.25 | I39: 130.8 | J39: 135.7 | K39: 135.3 | L39: 133.75 | M39: 134.55 | N39: 135.95 | O39: 134.45 | P39: 135.5 | Q39: 134.05 | R39: 1601.7
B40: EGESUR | C40: C.T. INDEPENDENCIA | D40: CENTRAL | E40: TERMOELÉCTRICA | F40: 100.3 | G40: 270.85 | H40: 77.05 | I40: 99.5 | J40: 99.75 | L40: 207.5 | M40: 190.25 | N40: 264.55 | O40: 162.15 | P40: 312.1 | Q40: 190.5 | R40: 1974.5
B41: ELECTRICA YANAPAMPA SAC | C41: C.H. YANAPAMPA | D41: CENTRAL | E41: HIDROELÉCTRICA | F41: 79.85 | G41: 74.5 | H41: 76.35 | I41: 80.15 | J41: 79.6 | K41: 81.35 | L41: 72.5 | M41: 82.2 | N41: 82.95 | O41: 78.5 | P41: 80.65 | Q41: 80.05 | R41: 948.65
B42: ELECTROPERU | C42: C.H. MANTARO | D42: CENTRAL | E42: HIDROELÉCTRICA | F42: 15110.1 | G42: 15251.95 | H42: 15325.1 | I42: 15267.6 | J42: 15274 | K42: 15224.9 | L42: 15290.35 | M42: 14854.15 | N42: 15255.1 | O42: 15255.75 | P42: 15270.05 | Q42: 15245.95 | R42: 182625
B43: ELECTROPERU | C43: C.H. RESTITUCION | D43: CENTRAL | E43: HIDROELÉCTRICA | F43: 5096.35 | G43: 5132.8 | H43: 5143.4 | I43: 5124.1 | J43: 5135.15 | K43: 5156.55 | L43: 4693.75 | M43: 5050.4 | N43: 5165 | O43: 5160.8 | P43: 5169.15 | Q43: 5175.1 | R43: 61202.55
B44: ELECTROPERU | C44: C.T. TUMBES | D44: MAK1 | E44: TERMOELÉCTRICA | R44: 0
B45: ELECTROPERU | C45: C.T. TUMBES | D45: MAK2 | E45: TERMOELÉCTRICA | R45: 0
B46: EMPRESA DE GENERACION ELECTRICA CANCHAYLLO SAC | C46: C.H. CANCHAYLLO | D46: CENTRAL | E46: HIDROELÉCTRICA | F46: 112.5 | G46: 100.8 | H46: 124.1 | I46: 103.55 | J46: 113.3 | K46: 123.6 | L46: 123.25 | M46: 116.85 | N46: 114.45 | O46: 119.85 | P46: 117.55 | Q46: 115.85 | R46: 1385.65
B47: EMPRESA DE GENERACION ELECTRICA SANTA ANA S.A.C. | C47: C.H. RENOVANDES H1 | D47: CENTRAL | E47: HIDROELÉCTRICA | F47: 387.05 | G47: 388.1 | H47: 377.65 | I47: 489.2 | J47: 487.2 | K47: 486.7 | L47: 488.3 | M47: 486.6 | N47: 486.6 | O47: 485.2 | P47: 487.65 | Q47: 413.75 | R47: 5464
B48: EMPRESA DE GENERACION HUALLAGA | C48: C.H. CHAGLLA | D48: CENTRAL | E48: HIDROELÉCTRICA | F48: 9464.9 | G48: 10349.55 | H48: 11041.4 | I48: 10527.6 | J48: 11010.7 | K48: 10765.2 | L48: 10480.3 | M48: 10669.45 | N48: 10937.3 | O48: 10777.85 | P48: 11005.3 | Q48: 10999.6 | R48: 128029.15
B49: EMPRESA DE GENERACION HUALLAGA | C49: P.C.H. CHAGLLA | D49: CENTRAL | E49: HIDROELÉCTRICA | F49: 156 | G49: 156 | H49: 156 | I49: 156 | J49: 156 | K49: 155.9 | L49: 155.95 | M49: 156 | N49: 146.15 | O49: 156 | P49: 156 | Q49: 156 | R49: 1862
B50: EMPRESA DE GENERACION HUANZA | C50: C.H. HUANZA | D50: CENTRAL | E50: HIDROELÉCTRICA | F50: 1009.8 | G50: 1357.1 | H50: 1200.6 | I50: 1277.05 | J50: 1010.95 | K50: 898.3 | L50: 855.85 | M50: 762.7 | N50: 571.5 | O50: 678.15 | P50: 649.15 | Q50: 689.95 | R50: 10961.1
B51: EMPRESA ELECTRICA AGUA AZUL | C51: C.H. POTRERO | D51: CENTRAL | E51: HIDROELÉCTRICA | F51: 479.2 | G51: 443.5 | H51: 480 | I51: 480 | J51: 460.55 | K51: 480 | L51: 480 | M51: 480 | N51: 480 | O51: 452.35 | P51: 480 | Q51: 155.4 | R51: 5351
B52: EMPRESA ELECTRICA RIO DOBLE | C52: C.H. LAS PIZARRAS | D52: CENTRAL | E52: HIDROELÉCTRICA | F52: 445.15 | G52: 442.95 | H52: 449.1 | I52: 450.85 | J52: 451.4 | K52: 452.55 | L52: 431.8 | M52: 446.7 | N52: 450.2 | O52: 451.15 | P52: 450.55 | Q52: 446.9 | R52: 5369.3
B53: ENEL GENERACION PIURA S.A. | C53: C.T. MALACAS 1 | D53: TG6 | E53: TERMOELÉCTRICA | F53: 528.25 | G53: 146.85 | H53: 466.15 | I53: 778 | J53: 777.4 | K53: 679.35 | L53: 700.15 | M53: 748.75 | N53: 768.25 | O53: 664.75 | P53: 776.05 | Q53: 702.75 | R53: 7736.7
B54: ENEL GENERACION PIURA S.A. | C54: C.T. MALACAS 2 | D54: TG4 | E54: TERMOELÉCTRICA | G54: 456.25 | H54: 338.3 | R54: 794.55
B55: ENEL GENERACION PIURA S.A. | C55: C.T. RF DE GENERACION TALARA | D55: TG5 | E55: TERMOELÉCTRICA | R55: 0
B56: ENERGÍA EÓLICA S.A. | C56: C.E. CUPISNIQUE | D56: CENTRAL | E56: EÓLICA | F56: 185.6 | G56: 29.8 | H56: 253.05 | I56: 813.3 | J56: 860.85 | K56: 628.6 | L56: 96.15 | M56: 130.3 | N56: 232.1 | O56: 287.15 | P56: 227.95 | Q56: 512.5 | R56: 4257.35
B57: ENERGÍA EÓLICA S.A. | C57: C.E. TALARA | D57: CENTRAL | E57: EÓLICA | F57: 120.85 | G57: 102.7 | H57: 234.7 | I57: 258.65 | J57: 312.6 | K57: 259.5 | L57: 60.45 | M57: 98.7 | N57: 100.9 | O57: 65.9 | P57: 97.95 | Q57: 150.2 | R57: 1863.1
B58: ENERGIA RENOVABLE DEL SUR S.A. | C58: C.E. SAN JUAN | D58: CENTRAL | E58: EÓLICA | F58: 872.2 | G58: 357.2 | H58: 934.7 | I58: 1367.05 | J58: 2517.3 | K58: 2802.15 | L58: 1631.05 | M58: 1301.35 | N58: 1741.65 | O58: 1538.7 | P58: 1260.6 | Q58: 1170.05 | R58: 17494
B59: ENGIE ENERGIA PERU S.A.A. | C59: C.E. PUNTA LOMITAS | D59: PL-BL1 | E59: EÓLICA | F59: 372.47 | G59: 182.8 | H59: 344.8 | I59: 381.05 | J59: 696.7 | K59: 1768.45 | L59: 1162.7 | M59: 1101.95 | N59: 1248.2 | O59: 1018.925 | P59: 1065.55 | Q59: 717.55 | R59: 10061.145
B60: ENGIE ENERGIA PERU S.A.A. | C60: C.E. PUNTA LOMITAS | D60: PL-BL2 | E60: EÓLICA | F60: 651.42 | G60: 317.68 | H60: 622.3 | I60: 639.45 | J60: 1032.8 | K60: 2222.835 | L60: 1755 | M60: 1694.7 | N60: 1775.35 | O60: 1675.285 | P60: 1669.8 | Q60: 1261.1 | R60: 15317.72
B61: ENGIE ENERGIA PERU S.A.A. | C61: C.E. PUNTA LOMITAS_EXP | D61: PUN LOM_EXP-BL1 | E61: EÓLICA | F61: 37.72 | G61: 20.85 | H61: 45.95 | I61: 34 | J61: 87.75 | K61: 255.1 | L61: 180.6 | M61: 160.6 | N61: 150.9 | O61: 117.64705 | P61: 137.75 | Q61: 95.35 | R61: 1324.217
B62: ENGIE ENERGIA PERU S.A.A. | C62: C.E. PUNTA LOMITAS_EXP | D62: PUN LOM_EXP-BL2 | E62: EÓLICA | F62: 35.66 | G62: 12.35 | H62: 26.65 | I62: 25.3 | J62: 53.1 | K62: 198.35 | L62: 133.05 | M62: 121.45 | N62: 120.35 | O62: 110.61245 | P62: 106.75 | Q62: 57.8 | R62: 1001.4225
B63: ENGIE ENERGIA PERU S.A.A. | C63: C.H. QUITARACSA | D63: CENTRAL | E63: HIDROELÉCTRICA | F63: 160.5 | H63: 363.05 | J63: 141.4 | M63: 153.65 | R63: 818.6
B64: ENGIE ENERGIA PERU S.A.A. | C64: C.H. YUNCAN | D64: CENTRAL | E64: HIDROELÉCTRICA | F64: 2509.05 | G64: 3075.25 | H64: 3078.4 | I64: 3064.85 | J64: 3061.75 | K64: 3062.5 | L64: 3064.5 | M64: 3059.5 | N64: 3062.4 | O64: 3052.205 | P64: 2048.25 | Q64: 2228.15 | R64: 34366.805
B65: ENGIE ENERGIA PERU S.A.A. | C65: C.S. EXPANSIÓN INTIPAMPA | D65: CENTRAL | E65: SOLAR | F65: 275.3 | G65: 173.9 | H65: 153.2 | I65: 201.25 | J65: 271 | K65: 387.4 | L65: 347.35 | M65: 152.55 | N65: 219 | O65: 347.5 | P65: 159.4 | Q65: 225.9 | R65: 2913.75
B66: ENGIE ENERGIA PERU S.A.A. | C66: C.S. INTIPAMPA | D66: CENTRAL | E66: SOLAR | F66: 169.75 | G66: 118.5 | H66: 170.3 | I66: 153.3 | J66: 231.05 | K66: 288.5 | L66: 252.9 | M66: 107.9 | N66: 167.75 | O66: 269.7 | P66: 211.85 | Q66: 182.7 | R66: 2324.2
B67: ENGIE ENERGIA PERU S.A.A. | C67: C.T. CHILCA 1 | D67: TG1 | E67: TERMOELÉCTRICA | K67: 314.05 | L67: 884.6 | M67: 781.7 | N67: 576.15 | P67: 1189.2 | Q67: 878.5 | R67: 4624.2
B68: ENGIE ENERGIA PERU S.A.A. | C68: C.T. CHILCA 1 | D68: TG2 | E68: TERMOELÉCTRICA | F68: 688.65 | G68: 2238.5 | H68: 1625.8 | I68: 1372.6 | J68: 1318.4 | K68: 518.15 | L68: 776.85 | M68: 1401.15 | N68: 1840.1 | O68: 696.055 | P68: 1815.15 | Q68: 1088.4 | R68: 15379.805
B69: ENGIE ENERGIA PERU S.A.A. | C69: C.T. CHILCA 1 | D69: TG3 | E69: TERMOELÉCTRICA | F69: 1749.05 | G69: 2707.15 | H69: 2345.55 | I69: 2401.55 | J69: 2309 | K69: 1144.35 | L69: 2425.25 | M69: 2387.9 | N69: 3178.6 | O69: 1811.015 | P69: 2715.35 | Q69: 2508.45 | R69: 27683.215
B70: ENGIE ENERGIA PERU S.A.A. | C70: C.T. CHILCA 1 | D70: TV | E70: TERMOELÉCTRICA | R70: 0
B71: ENGIE ENERGIA PERU S.A.A. | C71: C.T. CHILCA 2 | D71: TG41 | E71: TERMOELÉCTRICA | F71: 1342.6 | G71: 1401.6 | H71: 1424.65 | I71: 1410.5 | J71: 1449.55 | K71: 1274.15 | L71: 1377.2 | M71: 176.85 | N71: 1151.4 | O71: 1304.675 | P71: 1440.75 | Q71: 1455.3 | R71: 15209.225
B72: ENGIE ENERGIA PERU S.A.A. | C72: C.T. CHILCA 2 | D72: TV42 | E72: TERMOELÉCTRICA | F72: 764.75 | G72: 772.15 | H72: 773.2 | I72: 769.45 | J72: 785.95 | K72: 736.05 | L72: 755.7 | N72: 508.9 | O72: 745.765 | P72: 773.15 | Q72: 776.65 | R72: 8161.715
B73: ENGIE ENERGIA PERU S.A.A. | C73: C.T. NEPI | D73: TG41 | E73: TERMOELÉCTRICA | R73: 0
B74: ENGIE ENERGIA PERU S.A.A. | C74: C.T. NEPI | D74: TG42 | E74: TERMOELÉCTRICA | R74: 0
B75: ENGIE ENERGIA PERU S.A.A. | C75: C.T. NEPI | D75: TG43 | E75: TERMOELÉCTRICA | R75: 0
B76: ENGIE ENERGIA PERU S.A.A. | C76: C.T. RF PLANTA ILO | D76: TG1 | E76: TERMOELÉCTRICA | Q76: 359.6 | R76: 359.6
B77: ENGIE ENERGIA PERU S.A.A. | C77: C.T. RF PLANTA ILO | D77: TG2 | E77: TERMOELÉCTRICA | R77: 0
B78: ENGIE ENERGIA PERU S.A.A. | C78: C.T. RF PLANTA ILO | D78: TG3 | E78: TERMOELÉCTRICA | R78: 0
B79: FENIX POWER PERÚ | C79: C.T. FENIX | D79: GT11 | E79: TERMOELÉCTRICA | F79: 3824.55 | G79: 1322.6 | R79: 5147.15
B80: FENIX POWER PERÚ | C80: C.T. FENIX | D80: GT12 | E80: TERMOELÉCTRICA | F80: 3832.7 | G80: 1262 | R80: 5094.7
B81: FENIX POWER PERÚ | C81: C.T. FENIX | D81: TV10 | E81: TERMOELÉCTRICA | F81: 4132.7 | G81: 1449.3 | R81: 5582
B82: GENERACIÓN ANDINA S.A.C. | C82: C.H. 8 DE AGOSTO | D82: CENTRAL | E82: HIDROELÉCTRICA | F82: 503.2 | G82: 504.5 | H82: 506.9 | I82: 510.9 | J82: 510.65 | K82: 511.25 | L82: 510.5 | M82: 350.25 | N82: 467.2 | O82: 475.8 | P82: 423.5 | Q82: 486.6 | R82: 5761.25
B83: GENERACIÓN ANDINA S.A.C. | C83: C.H. EL CARMEN | D83: CENTRAL | E83: HIDROELÉCTRICA | F83: 186.7 | G83: 168.9 | H83: 192.15 | I83: 187.5 | J83: 161.5 | K83: 178.8 | L83: 174.55 | M83: 170.75 | N83: 155.75 | O83: 145.45 | P83: 141.3 | Q83: 180.95 | R83: 2044.3
B84: GENERADORA DE ENERGÍA DEL PERÚ | C84: C.H. ÁNGEL I | D84: CENTRAL | E84: HIDROELÉCTRICA | F84: 489.6 | G84: 489.6 | H84: 488.15 | I84: 489.6 | J84: 489.6 | K84: 489.6 | L84: 489.6 | M84: 489.6 | N84: 487.5 | O84: 489.6 | P84: 489.6 | Q84: 489.6 | R84: 5871.65
B85: GENERADORA DE ENERGÍA DEL PERÚ | C85: C.H. ÁNGEL II | D85: CENTRAL | E85: HIDROELÉCTRICA | F85: 489.6 | G85: 489.6 | H85: 488.09 | I85: 489.6 | J85: 489.6 | K85: 489.6 | L85: 489.6 | M85: 489.6 | N85: 476.8 | O85: 489.6 | P85: 489.6 | Q85: 489.6 | R85: 5860.89
B86: GENERADORA DE ENERGÍA DEL PERÚ | C86: C.H. ÁNGEL III | D86: CENTRAL | E86: HIDROELÉCTRICA | F86: 482.4 | G86: 482.4 | H86: 481.77 | I86: 482.25 | J86: 372.4 | K86: 395.85 | L86: 481.85 | M86: 480 | N86: 464.1 | O86: 481.4 | P86: 480 | Q86: 480 | R86: 5564.42
B87: GENERADORA DE ENERGÍA DEL PERÚ | C87: C.H. LA JOYA | D87: CENTRAL | E87: HIDROELÉCTRICA | H87: 11.35 | I87: 146.85 | J87: 149.25 | K87: 151.7 | L87: 141.35 | M87: 138.6 | N87: 153.8 | O87: 7.05 | P87: 135.25 | Q87: 139.7 | R87: 1174.9
B88: GM OPERACIONES S.A.C. | C88: CT REFINERIA TALARA | D88: TV1 REF TALARA | E88: TERMOELÉCTRICA | F88: 643.7 | G88: 650.4 | H88: 646.1 | I88: 648.85 | J88: 636.55 | K88: 658.1 | L88: 658.25 | M88: 663.75 | N88: 659 | O88: 658.05 | P88: 656.55 | Q88: 663.8 | R88: 7843.1
B89: GM OPERACIONES S.A.C. | C89: CT REFINERIA TALARA | D89: TV2 REF TALARA | E89: TERMOELÉCTRICA | F89: 798.05 | G89: 814.9 | H89: 811.85 | I89: 804.9 | J89: 806.8 | K89: 822.5 | L89: 821.5 | M89: 828.45 | N89: 820.5 | O89: 818.25 | P89: 820.8 | Q89: 828.7 | R89: 9797.2
B90: GR CORTARRAMA SOCIEDAD ANONIMA CERRADA | C90: C.S. MATARANI | D90: C.S. MATARANI | E90: SOLAR | F90: 697.55 | G90: 485.55 | H90: 712.35 | I90: 759.6 | J90: 691.2 | K90: 742.8 | L90: 577.85 | M90: 406.85 | N90: 813.65 | O90: 767.95 | P90: 477.65 | Q90: 610.5 | R90: 7743.5
B91: GR PAINO SOCIEDAD ANONIMA CERRADA | C91: C.E. HUAMBOS | D91: CENTRAL | E91: EÓLICA | F91: 33.9 | G91: 3.45 | H91: 23.38 | I91: 119.45 | J91: 108.4 | K91: 24.55 | L91: 43.4 | M91: 166.1 | N91: 125.25 | O91: 45.92 | P91: 42.8 | Q91: 76.6 | R91: 813.2
B92: GR TARUCA SOCIEDAD ANONIMA CERRADA | C92: C.E. DUNA | D92: CENTRAL | E92: EÓLICA | F92: 20.15 | G92: 1.45 | H92: 22.875 | I92: 122.7 | J92: 120.55 | K92: 13.95 | L92: 47.65 | M92: 195.15 | N92: 136 | O92: 39.495 | P92: 0.5 | Q92: 43.75 | R92: 764.22
B93: HIDROCAÑETE S.A. | C93: C.H. IMPERIAL | D93: CENTRAL | E93: HIDROELÉCTRICA | F93: 80.1 | G93: 79.4 | H93: 77.3 | I93: 76.1 | J93: 79.6 | K93: 80.35 | L93: 79.25 | M93: 69 | N93: 57.95 | O93: 63.3 | P93: 73.05 | Q93: 81.6 | R93: 897
B94: HIDROELECTRICA HUANCHOR S.A.C. | C94: C.H. HUANCHOR | D94: CENTRAL | E94: HIDROELÉCTRICA | F94: 442.35 | G94: 441.85 | H94: 444.25 | I94: 444.05 | J94: 445.45 | K94: 444.65 | L94: 441.75 | M94: 442.55 | N94: 443.2 | O94: 442.7 | P94: 442.45 | Q94: 441.75 | R94: 5317
B95: HUAURA POWER GROUP S.A. | C95: C.H. YARUCAYA | D95: CENTRAL | E95: HIDROELÉCTRICA | F95: 444.15 | G95: 444.9 | H95: 414 | I95: 444.55 | J95: 444 | K95: 407.95 | L95: 445.85 | M95: 443.25 | N95: 441.6 | O95: 441.6 | P95: 441.6 | Q95: 441.6 | R95: 5255.05
B96: HYDRO GLOBAL PERÚ S.A.C. | C96: CH SAN GABAN III | D96: CENTRAL | E96: HIDROELÉCTRICA | F96: 4870.1 | G96: 4860.15 | H96: 4181.5 | I96: 4832.05 | J96: 4836.35 | K96: 4856.5 | L96: 3440.165 | M96: 3481.85 | N96: 4821.6 | O96: 4846.65 | P96: 4803.8 | Q96: 4845.15 | R96: 54675.865
B97: INFRAESTRUCTURAS Y ENERGIAS DEL PERU S.A.C. | C97: C.T. RF PTO MALDONADO | D97: CENTRAL | E97: TERMOELÉCTRICA | F97: 116.15 | R97: 116.15
B98: INFRAESTRUCTURAS Y ENERGIAS DEL PERU S.A.C. | C98: C.T. RF PUCALLPA | D98: CENTRAL | E98: TERMOELÉCTRICA | H98: 1.65 | R98: 1.65
B99: INLAND ENERGY SAC | C99: C.H. SANTA TERESA | D99: CENTRAL | E99: HIDROELÉCTRICA | F99: 2121.8 | G99: 2171.6 | H99: 2181.9 | I99: 2168.6 | J99: 2181.3 | K99: 2178.4 | L99: 2178.1 | M99: 1842.25 | N99: 2182.9 | O99: 2183 | P99: 2188.25 | Q99: 2174.55 | R99: 25752.65
B100: INVERSIONES SHAQSHA S.A.C. | C100: C.H. PARIAC | D100: CENTRAL | E100: HIDROELÉCTRICA | F100: 55.2 | G100: 55.2 | H100: 53.75 | I100: 23.35 | J100: 26.3 | K100: 55.2 | L100: 57.6 | M100: 56.25 | N100: 55.15 | O100: 51.25 | P100: 52 | Q100: 57.6 | R100: 598.85
B101: JOYA SOLAR S.A.C. | C101: C.S. SAN MARTIN SOLAR | D101: CENTRAL | E101: SOLAR | F101: 2235.75 | G101: 1360.05 | H101: 1920.65 | I101: 2422.6 | J101: 2091.95 | K101: 2507.15 | L101: 1888.9 | M101: 950.75 | N101: 2553.5 | O101: 2243.65 | P101: 1265.6 | Q101: 1570.7 | R101: 23011.25
B102: KALLPA GENERACION S.A. | C102: C.H. CERRO DEL AGUILA | D102: CENTRAL | E102: HIDROELÉCTRICA | F102: 12999.15 | G102: 13385.9 | H102: 13468.165 | I102: 13399.45 | J102: 13384.15 | K102: 13334.9 | L102: 13380.85 | M102: 13180.15 | N102: 13226.95 | O102: 13288.35 | P102: 13401.8 | Q102: 13227.9 | R102: 159677.71
B103: KALLPA GENERACION S.A. | C103: C.S. SUNNY | D103: CENTRAL | E103: SOLAR | F103: 1347.3 | G103: 985.75 | H103: 1702.5 | I103: 1960.45 | J103: 0.6 | K103: 1590.7 | L103: 1529.05 | M103: 732.5 | N103: 2068.1 | O103: 1902.8 | P103: 977.95 | Q103: 1304.8 | R103: 16102.5
...

Sheet G_AREAS
B3: jueves, 12 de Febrero del 2026
B5: HORA | C5: RESUMEN DE GENERACIÓN POR ÁREAS DEL SEIN | D5: RESUMEN DE GENERACIÓN POR ÁREAS DEL SEIN | E5: RESUMEN DE GENERACIÓN POR ÁREAS DEL SEIN | F5: RESUMEN DE GENERACIÓN POR ÁREAS DEL SEIN | G5: RESUMEN DE GENERACIÓN POR ÁREAS DEL SEIN | H5: RESUMEN DE GENERACIÓN POR ÁREAS DEL SEIN | I5: RESUMEN DE GENERACIÓN POR ÁREAS DEL SEIN | J5: RESUMEN DE GENERACIÓN POR ÁREAS DEL SEIN | K5: RESUMEN DE GENERACIÓN POR ÁREAS DEL SEIN | L5: RESUMEN DE GENERACIÓN POR ÁREAS DEL SEIN | M5: RESUMEN DE GENERACIÓN POR ÁREAS DEL SEIN | N5: RESUMEN DE GENERACIÓN POR ÁREAS DEL SEIN | O5: RESUMEN DE GENERACIÓN POR ÁREAS DEL SEIN | P5: RESUMEN DE GENERACIÓN POR ÁREAS DEL SEIN | Q5: RESUMEN DE GENERACIÓN POR ÁREAS DEL SEIN | R5: RESUMEN DE GENERACIÓN POR ÁREAS DEL SEIN | S5: HORA | T5: GENERACIÓN POR TIPO DE GENERACIÓN | U5: GENERACIÓN POR TIPO DE GENERACIÓN | V5: GENERACIÓN POR TIPO DE GENERACIÓN | W5: GENERACIÓN POR TIPO DE GENERACIÓN | X5: GENERACIÓN POR TIPO DE GENERACIÓN | Y5: HORA | Z5: GENERACIÓN POR TIPO DE GENERACIÓN | AA5: GENERACIÓN POR TIPO DE GENERACIÓN | AB5: GENERACIÓN POR TIPO DE GENERACIÓN | AC5: GENERACIÓN POR TIPO DE GENERACIÓN | AD5: GENERACIÓN POR TIPO DE GENERACIÓN
C6: NORTE | D6: NORTE | E6: NORTE | F6: NORTE | G6: CENTRO | H6: CENTRO | I6: CENTRO | J6: CENTRO | K6: SUR | L6: SUR | M6: SUR | N6: SUR | O6: GENERACIÓN INTEGRANTES COES | P6: GENERACIÓN INTEGRANTES COES | Q6: GENERACIÓN INTEGRANTES COES | R6: GENERACIÓN INTEGRANTES COES | T6: INTEGRANTES COES | U6: INTEGRANTES COES | V6: INTEGRANTES COES | W6: INTEGRANTES COES | X6: INTEGRANTES COES | Z6: INTEGRANTES COES RER | AA6: INTEGRANTES COES RER | AB6: INTEGRANTES COES RER | AC6: INTEGRANTES COES RER | AD6: INTEGRANTES COES RER
C7: GENERACIÓN HIDROELÉCTRICA NORTE | D7: GENERACIÓN TERMOELÉCTRICA NORTE | E7: GENERACIÓN SOLAR NORTE | F7: GENERACIÓN EÓLICA NORTE | G7: GENERACIÓN HIDROELÉCTRICA CENTRO | H7: GENERACIÓN TERMOELÉCTRICA CENTRO | I7: GENERACIÓN SOLAR CENTRO | J7: GENERACIÓN EÓLICA CENTRO | K7: GENERACIÓN HIDROELÉCTRICA SUR | L7: GENERACIÓN TERMOELÉCTRICA SUR | M7: GENERACIÓN SOLAR SUR | N7: GENERACIÓN EÓLICA SUR | O7: GENERACIÓN COES NORTE | P7: GENERACIÓN COES CENTRO | Q7: GENERACIÓN COES SUR | R7: TOTAL GENERACION | T7: HIDROELÉCTRICA | U7: TERMOELÉCTRICA | V7: SOLAR | W7: EÓLICA | X7: TOTAL GENERACION | Z7: HIDROELÉCTRICA RER | AA7: TERMOELÉCTRICA RER | AB7: SOLAR RER | AC7: EÓLICA RER | AD7: TOTAL RER
B8: 00:30 | C8: 454.9 | D8: 118.3 | E8: 0 | F8: 17.9 | G8: 3312.2 | H8: 1900.2 | I8: 0 | J8: 356.1 | K8: 792.2 | L8: 0 | M8: 0 | N8: 0 | O8: 591.1 | P8: 5568.5 | Q8: 792.2 | R8: 6951.8 | S8: 00:30 | T8: 4559.3 | U8: 2018.5 | V8: 0 | W8: 374 | X8: 6951.8 | Y8: 00:30 | Z8: 360 | AA8: 81.3 | AB8: 0 | AC8: 374 | AD8: 815.3
B9: 01:00 | C9: 461.1 | D9: 112.1 | E9: 0 | F9: 13.1 | G9: 3299.2 | H9: 1878.5 | I9: 0 | J9: 270.6 | K9: 803.5 | L9: 0 | M9: 0 | N9: 0 | O9: 586.3 | P9: 5448.3 | Q9: 803.5 | R9: 6838.1 | S9: 01:00 | T9: 4563.8 | U9: 1990.6 | V9: 0 | W9: 283.7 | X9: 6838.1 | Y9: 01:00 | Z9: 360.2 | AA9: 75 | AB9: 0 | AC9: 283.7 | AD9: 718.9
B10: 01:30 | C10: 456.9 | D10: 114.7 | E10: 0 | F10: 9.5 | G10: 3222.2 | H10: 1805.2 | I10: 0 | J10: 250.2 | K10: 791.1 | L10: 0 | M10: 0 | N10: 0 | O10: 581.1 | P10: 5277.6 | Q10: 791.1 | R10: 6649.8 | S10: 01:30 | T10: 4470.2 | U10: 1919.9 | V10: 0 | W10: 259.7 | X10: 6649.8 | Y10: 01:30 | Z10: 358.5 | AA10: 76.5 | AB10: 0 | AC10: 259.7 | AD10: 694.7
B11: 02:00 | C11: 462.6 | D11: 115.1 | E11: 0 | F11: 9.2 | G11: 3254.1 | H11: 1788.9 | I11: 0 | J11: 239.6 | K11: 804.1 | L11: 0 | M11: 0 | N11: 0 | O11: 586.9 | P11: 5282.6 | Q11: 804.1 | R11: 6673.6 | S11: 02:00 | T11: 4520.8 | U11: 1904 | V11: 0 | W11: 248.8 | X11: 6673.6 | Y11: 02:00 | Z11: 358.7 | AA11: 77 | AB11: 0 | AC11: 248.8 | AD11: 684.5
B12: 02:30 | C12: 464.4 | D12: 117.2 | E12: 0 | F12: 12.6 | G12: 3243.7 | H12: 1750.6 | I12: 0 | J12: 197.8 | K12: 814.8 | L12: 0 | M12: 0 | N12: 0 | O12: 594.2 | P12: 5192.1 | Q12: 814.8 | R12: 6601.1 | S12: 02:30 | T12: 4522.9 | U12: 1867.8 | V12: 0 | W12: 210.4 | X12: 6601.1 | Y12: 02:30 | Z12: 360 | AA12: 79.3 | AB12: 0 | AC12: 210.4 | AD12: 649.7
B13: 03:00 | C13: 462.2 | D13: 116.9 | E13: 0 | F13: 16.1 | G13: 3127.7 | H13: 1872 | I13: 0 | J13: 173.2 | K13: 805.8 | L13: 0 | M13: 0 | N13: 0 | O13: 595.2 | P13: 5172.9 | Q13: 805.8 | R13: 6573.9 | S13: 03:00 | T13: 4395.7 | U13: 1988.9 | V13: 0 | W13: 189.3 | X13: 6573.9 | Y13: 03:00 | Z13: 360.4 | AA13: 79 | AB13: 0 | AC13: 189.3 | AD13: 628.7
B14: 03:30 | C14: 461 | D14: 116.9 | E14: 0 | F14: 11.1 | G14: 3154.7 | H14: 1873.9 | I14: 0 | J14: 137.6 | K14: 799.5 | L14: 0 | M14: 0 | N14: 0 | O14: 589 | P14: 5166.2 | Q14: 799.5 | R14: 6554.7 | S14: 03:30 | T14: 4415.2 | U14: 1990.8 | V14: 0 | W14: 148.7 | X14: 6554.7 | Y14: 03:30 | Z14: 360.3 | AA14: 78.7 | AB14: 0 | AC14: 148.7 | AD14: 587.7
B15: 04:00 | C15: 462.3 | D15: 116 | E15: 0 | F15: 9.6 | G15: 3242.5 | H15: 1735.8 | I15: 0 | J15: 120.2 | K15: 808.8 | L15: 0 | M15: 0 | N15: 0 | O15: 587.9 | P15: 5098.5 | Q15: 808.8 | R15: 6495.2 | S15: 04:00 | T15: 4513.6 | U15: 1851.8 | V15: 0 | W15: 129.8 | X15: 6495.2 | Y15: 04:00 | Z15: 361.4 | AA15: 78.2 | AB15: 0 | AC15: 129.8 | AD15: 569.4
B16: 04:30 | C16: 459.4 | D16: 117 | E16: 0 | F16: 9.1 | G16: 3223.5 | H16: 1750 | I16: 0 | J16: 86.4 | K16: 798.1 | L16: 0 | M16: 0 | N16: 0 | O16: 585.5 | P16: 5059.9 | Q16: 798.1 | R16: 6443.5 | S16: 04:30 | T16: 4481 | U16: 1867 | V16: 0 | W16: 95.5 | X16: 6443.5 | Y16: 04:30 | Z16: 365.5 | AA16: 78.4 | AB16: 0 | AC16: 95.5 | AD16: 539.4
B17: 05:00 | C17: 459.4 | D17: 115 | E17: 0 | F17: 3.8 | G17: 3295.7 | H17: 1846.5 | I17: 0 | J17: 72.2 | K17: 804.1 | L17: 0 | M17: 0 | N17: 0 | O17: 578.2 | P17: 5214.4 | Q17: 804.1 | R17: 6596.7 | S17: 05:00 | T17: 4559.2 | U17: 1961.5 | V17: 0 | W17: 76 | X17: 6596.7 | Y17: 05:00 | Z17: 366.3 | AA17: 77.4 | AB17: 0 | AC17: 76 | AD17: 519.7
B18: 05:30 | C18: 459.3 | D18: 115.2 | E18: 0 | F18: 5.1 | G18: 3255.2 | H18: 1960.3 | I18: 0 | J18: 56.9 | K18: 797.6 | L18: 0 | M18: 0 | N18: 0 | O18: 579.6 | P18: 5272.4 | Q18: 797.6 | R18: 6649.6 | S18: 05:30 | T18: 4512.1 | U18: 2075.5 | V18: 0 | W18: 62 | X18: 6649.6 | Y18: 05:30 | Z18: 366.5 | AA18: 78.1 | AB18: 0 | AC18: 62 | AD18: 506.6
B19: 06:00 | C19: 461.7 | D19: 116.9 | E19: 0 | F19: 7.4 | G19: 3255.1 | H19: 1913 | I19: 0 | J19: 43.1 | K19: 798.4 | L19: 0 | M19: 12.2 | N19: 0 | O19: 586 | P19: 5211.2 | Q19: 810.6 | R19: 6607.8 | S19: 06:00 | T19: 4515.2 | U19: 2029.9 | V19: 12.2 | W19: 50.5 | X19: 6607.8 | Y19: 06:00 | Z19: 364.9 | AA19: 80 | AB19: 12.2 | AC19: 50.5 | AD19: 507.6
... B56: TOTAL MWh | C56: 10699.05 | D56: 3532.55 | E56: 1.5 | F56: 783.05 | G56: 81264 | H56: 49967.3 | I56: 5.4 | J56: 5305.2 | K56: 19276.9 | L56: 359.6 | M56: 6638.9 | N56: 0 | O56: 15016.15 | P56: 136541.9 | Q56: 26275.4 | R56: 177833.45 | S56: TOTAL MWh | T56: 111239.95 | U56: 53859.45 | V56: 6645.8 | W56: 6088.25 | X56: 177833.45 | Y56: TOTAL MWh | Z56: 8447.55 | AA56: 1954.55 | AB56: 6645.8 | AC56: 6088.25 | AD56: 23136.15

Sheet HOP
B3: jueves, 12 de Febrero del 2026
B5: Reporte de Horas de Operación
B6: Empresa | C6: Central | D6: Grupo | E6: Modo de Operación | F6: Inicio | G6: Final | H6: O. Arranque | I6: O. Parada | J6: Tipo Operación | K6: Ensayo de Potencia Efectiva | L6: Ensayo de Potencia Mínima | M6: Sistema | N6: Lim. Transm. | O6: Causa | P6: Observación
B7: AGRO INDUSTRIAL PARAMONGA S.A. | C7: C.T. PARAMONGA | D7: CENTRAL | E7: PARAMONGA - BAGAZO | F7: 12/02/2026 00:00:00 | G7: 13/02/2026 00:00:00 | J7: POR COGENERACION | O7: ...
B8: AGROAURORA S.A.C. | C8: C.T. MAPLE ETANOL | D8: CENTRAL | E8: MAPLE- BAGAZO | F8: 12/02/2026 00:00:00 | G8: 13/02/2026 00:00:00 | J8: POR COGENERACION | O8: ...
B9: AGROINDUSTRIAS SAN JACINTO S.A.A. | C9: C.T. SAN JACINTO | D9: CENTRAL | E9: SAN_JACINTO - BAGAZO | F9: 12/02/2026 00:00:00 | G9: 13/02/2026 00:00:00 | J9: POR COGENERACION | O9: ...
B10: AGROLMOS SOCIEDAD ANONIMA - AGROLMOS S.A. | C10: C.T. AGROLMOS | D10: CENTRAL | E10: AGROLMOS TV1 & TV2 - BAGAZO | F10: 12/02/2026 00:00:00 | G10: 12/02/2026 13:11:45 | J10: POR COGENERACION | O10: ...
B11: AGROLMOS SOCIEDAD ANONIMA - AGROLMOS S.A. | C11: C.T. AGROLMOS | D11: TV1 | E11: AGROLMOS TV1 - BAGAZO | F11: 12/02/2026 13:11:45 | G11: 12/02/2026 13:51:16 | J11: POR COGENERACION | O11: ...
B12: AGROLMOS SOCIEDAD ANONIMA - AGROLMOS S.A. | C12: C.T. AGROLMOS | D12: CENTRAL | E12: AGROLMOS TV1 & TV2 - BAGAZO | F12: 12/02/2026 13:51:16 | G12: 13/02/2026 00:00:00 | J12: POR COGENERACION | O12: ...
B13: BIOENERGIA DEL CHIRA S.A. | C13: C.T. CAÑA BRAVA | D13: G-1 | E13: CANA BRAVA TV1 - BAGAZO | F13: 12/02/2026 00:00:00 | G13: 12/02/2026 09:25:00 | J13: POR COGENERACION | O13: ...
B14: BIOENERGIA DEL CHIRA S.A. | C14: C.T. CAÑA BRAVA | D14: G-1 | E14: CANA BRAVA TV1 - BAGAZO | F14: 12/02/2026 09:48:00 | G14: 12/02/2026 10:18:00 | J14: POR COGENERACION | O14: ...
B15: BIOENERGIA DEL CHIRA S.A. | C15: C.T. CAÑA BRAVA | D15: CENTRAL | E15: CANA BRAVA TV1 & TV2 - BAGAZO | F15: 12/02/2026 10:18:00 | G15: 12/02/2026 14:20:00 | J15: POR COGENERACION | O15: ...
B16: BIOENERGIA DEL CHIRA S.A. | C16: C.T. CAÑA BRAVA | D16: G-1 | E16: CANA BRAVA TV1 - BAGAZO | F16: 12/02/2026 14:20:00 | G16: 12/02/2026 14:29:00 | J16: POR COGENERACION | O16: ...
B17: BIOENERGIA DEL CHIRA S.A. | C17: C.T. CAÑA BRAVA | D17: CENTRAL | E17: CANA BRAVA TV1 & TV2 - BAGAZO | F17: 12/02/2026 14:29:00 | G17: 12/02/2026 15:05:00 | J17: POR COGENERACION | O17: ...
B18: BIOENERGIA DEL CHIRA S.A. | C18: C.T. CAÑA BRAVA | D18: G-1 | E18: CANA BRAVA TV1 - BAGAZO | F18: 12/02/2026 15:05:00 | G18: 13/02/2026 00:00:00 | J18: POR COGENERACION | O18: ...
... B21: CASA GRANDE S.A.A. | C21: C.T. CASA GRANDE | D21: CENTRAL | E21: CASA GRANDE TV1 & TV3 - BAGAZO | F21: 12/02/2026 17:00:00 | G21: 13/02/2026 00:00:00 | J21: POR COGENERACION | O21: ...
B22: EGESUR | C22: C.T. INDEPENDENCIA | D22: CENTRAL | E22: INDEPENDENCIA GAS | F22: 12/02/2026 07:32:00 | G22: 12/02/2026 08:07:00 | H22: 12/02/2026 07:28:00 | J22: POR POTENCIA O ENERGIA | O22: ...
B23: EGESUR | C23: C.T. INDEPENDENCIA | D23: CENTRAL | E23: INDEPENDENCIA GAS | F23: 12/02/2026 08:07:00 | G23: 12/02/2026 08:46:00 | J23: A MINIMA CARGA | O23: ...
B24: EGESUR | C24: C.T. INDEPENDENCIA | D24: CENTRAL | E24: INDEPENDENCIA GAS | F24: 12/02/2026 08:46:00 | G24: 12/02/2026 12:09:00 | J24: POR POTENCIA O ENERGIA | O24: ...
B25: EGESUR | C25: C.T. INDEPENDENCIA | D25: CENTRAL | E25: INDEPENDENCIA GAS | F25: 12/02/2026 12:09:00 | G25: 12/02/2026 12:25:00 | J25: A MINIMA CARGA | O25: ...
B26: EGESUR | C26: C.T. INDEPENDENCIA | D26: CENTRAL | E26: INDEPENDENCIA GAS | F26: 12/02/2026 15:13:00 | G26: 12/02/2026 19:52:00 | H26: 12/02/2026 15:08:00 | I26: 12/02/2026 19:42:00 | J26: POR POTENCIA O ENERGIA | O26: ...
B27: ENEL GENERACION PIURA S.A. | C27: C.T. MALACAS 1 | D27: CENTRAL | E27: MALACAS1 TG6 - GAS | F27: 12/02/2026 00:00:00 | G27: 12/02/2026 00:17:00 | I27: 12/02/2026 00:01:00 | J27: POR POTENCIA O ENERGIA | O27: ...
B28: ENEL GENERACION PIURA S.A. | C28: C.T. MALACAS 1 | D28: CENTRAL | E28: MALACAS1 TG6 - GAS | F28: 12/02/2026 07:29:00 | G28: 12/02/2026 23:42:00 | H28: 12/02/2026 07:16:00 | I28: 12/02/2026 23:26:00 | J28: POR POTENCIA O ENERGIA | O28: ...
B29: ENGIE ENERGIA PERU S.A.A. | C29: C.T. CHILCA 1 | D29: TG3 | E29: CHILCA1 TG3 - GAS | F29: 12/02/2026 07:38:00 | G29: 12/02/2026 08:07:00 | H29: 12/02/2026 07:18:00 | J29: POR POTENCIA O ENERGIA | O29: ...
B30: ENGIE ENERGIA PERU S.A.A. | C30: C.T. CHILCA 1 | D30: TG1 | E30: CHILCA1 TG1 - GAS | F30: 12/02/2026 07:45:00 | G30: 12/02/2026 09:38:00 | H30: 12/02/2026 07:29:00 | J30: A MINIMA CARGA | O30: ...
B31: ENGIE ENERGIA PERU S.A.A. | C31: C.T. CHILCA 1 | D31: TG3 | E31: CHILCA1 TG3 - GAS | F31: 12/02/2026 08:07:00 | G31: 12/02/2026 08:45:00 | J31: A MINIMA CARGA | O31: ...
B32: ENGIE ENERGIA PERU S.A.A. | C32: C.T. CHILCA 1 | D32: TG3 | E32: CHILCA1 TG3 - GAS | F32: 12/02/2026 08:45:00 | G32: 12/02/2026 12:10:00 | J32: POR POTENCIA O ENERGIA | O32: ...
B33: ENGIE ENERGIA PERU S.A.A. | C33: C.T. CHILCA 1 | D33: TG1 | E33: CHILCA1 TG1 - GAS | F33: 12/02/2026 09:38:00 | G33: 12/02/2026 11:14:00 | J33: POR POTENCIA O ENERGIA | O33: ...
B34: ENGIE ENERGIA PERU S.A.A. | C34: C.T. CHILCA 1 | D34: TG2 | E34: CHILCA1 TG2 - GAS | F34: 12/02/2026 09:59:00 | G34: 12/02/2026 22:00:00 | H34: 12/02/2026 09:45:00 | I34: 12/02/2026 21:46:00 | J34: POR POTENCIA O ENERGIA | O34: ... | P34: A las 17:33 h, s/c generar a mínima del segundo tramo. A las 19:30 h, s/c generar a mínima del segundo tramo.
B35: ENGIE ENERGIA PERU S.A.A. | C35: C.T. CHILCA 1 | D35: TG1 | E35: CHILCA1 TG1 - GAS | F35: 12/02/2026 11:14:00 | G35: 12/02/2026 13:53:00 | I35: 12/02/2026 13:41:00 | J35: A MINIMA CARGA | O35: ...
B36: ENGIE ENERGIA PERU S.A.A. | C36: C.T. CHILCA 1 | D36: TG3 | E36: CHILCA1 TG3 - GAS | F36: 12/02/2026 12:10:00 | G36: 12/02/2026 12:43:00 | J36: A MINIMA CARGA | O36: ...
B37: ENGIE ENERGIA PERU S.A.A. | C37: C.T. CHILCA 1 | D37: TG3 | E37: CHILCA1 TG3 - GAS | F37: 12/02/2026 12:43:00 | G37: 12/02/2026 13:08:00 | J37: POR POTENCIA O ENERGIA | O37: ...
B38: ENGIE ENERGIA PERU S.A.A. | C38: C.T. CHILCA 1 | D38: TG3 | E38: CHILCA1 TG3 - GAS | F38: 12/02/2026 13:08:00 | G38: 12/02/2026 14:40:00 | J38: A MINIMA CARGA | O38: ...
B39: ENGIE ENERGIA PERU S.A.A. | C39: C.T. CHILCA 1 | D39: TG3 | E39: CHILCA1 TG3 - GAS | F39: 12/02/2026 14:40:00 | G39: 12/02/2026 22:54:00 | J39: POR POTENCIA O ENERGIA | O39: ... | P39: A las 21:09 h, s/c generar 100 MW.
B40: ENGIE ENERGIA PERU S.A.A. | C40: C.T. CHILCA 1 | D40: TG1 | E40: CHILCA1 TG1 - GAS | F40: 12/02/2026 17:18:00 | G40: 12/02/2026 18:40:00 | H40: 12/02/2026 17:05:00 | J40: A MINIMA CARGA | O40: ...
B41: ENGIE ENERGIA PERU S.A.A. | C41: C.T. CHILCA 1 | D41: TG1 | E41: CHILCA1 TG1 - GAS | F41: 12/02/2026 18:40:00 | G41: 12/02/2026 20:13:00 | J41: POR POTENCIA O ENERGIA | O41: ... | P41: A las 20:00 h, s/c generar 100 MW.
B42: ENGIE ENERGIA PERU S.A.A. | C42: C.T. CHILCA 1 | D42: TG1 | E42: CHILCA1 TG1 - GAS | F42: 12/02/2026 20:13:00 | G42: 12/02/2026 21:15:00 | I42: 12/02/2026 21:02:00 | J42: A MINIMA CARGA | O42: ...
B43: ENGIE ENERGIA PERU S.A.A. | C43: C.T. CHILCA 1 | D43: TG3 | E43: CHILCA1 TG3 - GAS | F43: 12/02/2026 22:54:00 | G43: 12/02/2026 23:45:00 | I43: 12/02/2026 23:24:00 | J43: A MINIMA CARGA | O43: ...
B44: ENGIE ENERGIA PERU S.A.A. | C44: C.T. CHILCA 2 | D44: CENTRAL | E44: CHILCA2 CCOMB TG41 - GAS | F44: 12/02/2026 00:00:00 | G44: 12/02/2026 07:18:00 | J44: A MINIMA CARGA | O44: ...
B45: ENGIE ENERGIA PERU S.A.A. | C45: C.T. CHILCA 2 | D45: CENTRAL | E45: CHILCA2 CCOMB TG41 - GAS | F45: 12/02/2026 07:18:00 | G45: 12/02/2026 08:07:00 | J45: POR POTENCIA O ENERGIA | O45: ...
B46: ENGIE ENERGIA PERU S.A.A. | C46: C.T. CHILCA 2 | D46: CENTRAL | E46: CHILCA2 CCOMB TG41 - GAS | F46: 12/02/2026 08:07:00 | G46: 12/02/2026 08:45:00 | J46: A MINIMA CARGA | O46: ...
B47: ENGIE ENERGIA PERU S.A.A. | C47: C.T. CHILCA 2 | D47: CENTRAL | E47: CHILCA2 CCOMB TG41 - GAS | F47: 12/02/2026 08:45:00 | G47: 12/02/2026 23:33:00 | J47: POR POTENCIA O ENERGIA | O47: ...
B48: ENGIE ENERGIA PERU S.A.A. | C48: C.T. CHILCA 2 | D48: CENTRAL | E48: CHILCA2 CCOMB TG41 - GAS | F48: 12/02/2026 23:33:00 | G48: 13/02/2026 00:00:00 | J48: A MINIMA CARGA | O48: ...
B49: ENGIE ENERGIA PERU S.A.A. | C49: C.T. RF PLANTA ILO | D49: TG1 | E49: RF ILO2 TG1 - D2 | F49: 12/02/2026 15:55:00 | G49: 12/02/2026 18:18:00 | H49: 12/02/2026 15:34:00 | I49: 12/02/2026 18:06:00 | J49: POR PRUEBAS ALEATORIAS PR-25 | O49: ... | P49: PRUEBA EXITOSA Y COMPENSABLE. A las 16:06 h, alcanzó su máxima generación
B50: GM OPERACIONES S.A.C. | C50: CT REFINERIA TALARA | D50: TV1 REF TALARA | E50: REF_TALARA TV1 - NLH_RFG | F50: 12/02/2026 00:00:00 | G50: 13/02/2026 00:00:00 | J50: POR COGENERACION | O50: ...
B51: GM OPERACIONES S.A.C. | C51: CT REFINERIA TALARA | D51: TV2 REF TALARA | E51: REF_TALARA TV2 - NLH_RFG | F51: 12/02/2026 00:00:00 | G51: 13/02/2026 00:00:00 | J51: POR COGENERACION | O51: ...
B52: KALLPA GENERACION S.A. | C52: C.T. KALLPA | D52: CENTRAL | E52: KALLPA CCOMB TG1 & TG2 & TG3 - GAS | F52: 12/02/2026 00:00:00 | G52: 12/02/2026 03:49:00 | J52: POR POTENCIA O ENERGIA | O52: ...
B53: KALLPA GENERACION S.A. | C53: C.T. KALLPA | D53: CENTRAL | E53: KALLPA CCOMB TG1 & TG2 & TG3 - GAS | F53: 12/02/2026 03:49:00 | G53: 12/02/2026 04:55:00 | J53: POR RSF | O53: ...
B54: KALLPA GENERACION S.A. | C54: C.T. KALLPA | D54: CENTRAL | E54: KALLPA CCOMB TG1 & TG2 & TG3 - GAS | F54: 12/02/2026 04:55:00 | G54: 12/02/2026 23:35:00 | J54: POR POTENCIA O ENERGIA | O54: ...
B55: KALLPA GENERACION S.A. | C55: C.T. KALLPA | D55: CENTRAL | E55: KALLPA CCOMB TG1 & TG2 & TG3 - GAS | F55: 12/02/2026 23:35:00 | G55: 12/02/2026 23:52:00 | J55: POR RSF | O55: ...
