Workbook

Sheet EVENTOS
B3: martes, 16 de Diciembre del 2025
B5: INFORMACIÓN DE EVENTOS PRINCIPALES EN SUS INSTALACIONES
B6: TIPO DE EVENTO | C6: EMPRESA | D6: UBICACIÓN | E6: TIPO DE EQUIPO | F6: EQUIPO | G6: INICIO | H6: FINAL | I6: DESCRIPCIÓN | J6: MW INDISP. | K6: INTERRUPCIÓN (SI/NO) | L6: TENSIÓN DE FALLA (kV)
B7: FALLA | C7: CASA GRANDE S.A.A. | D7: CASA GRANDE | E7: GENERADOR TERMOELÉCTRICO | F7: TV3 | G7: 16/12/2025 21:07:00 | H7: 16/12/2025 21:07:00 | I7: DESCONEXIÓN DEL GENERADOR TV3 DE LA C.T. CASAGRANDE | K7: NO | L7: 13.8
B8: EVENTO | C8: CONELSUR LT SAC | D8: PORTILLO | E8: SUBESTACION | F8: SS.EE. | G8: 16/12/2025 09:43:00 | H8: 17/12/2025 00:00:00 | I8: DECLARACIÓN DE SITUACIÓN EXCEPCIONAL EN LA S.E. PORTILLO 60 kV | K8: NO
B9: EVENTO | C9: ELECTRO ORIENTE | D9: BELAUNDE TERRY - TARAPOTO | E9: LINEA DE TRANSMISION | F9: L-1018 | G9: 16/12/2025 09:43:00 | H9: 16/12/2025 12:19:00 | I9: DECLARACIÓN DE SITUACIÓN EXCEPCIONAL EN LA LÍNEA L-1018 (BELAUNDE TERRY - TARAPOTO) DE 138 kV | K9: NO
B10: EVENTO | C10: ELECTRO ORIENTE | D10: BELAUNDE TERRY - TARAPOTO | E10: LINEA DE TRANSMISION | F10: L-1018 | G10: 16/12/2025 18:17:00 | H10: 16/12/2025 20:59:00 | I10: DECLARACIÓN DE SITUACIÓN EXCEPCIONAL EN LA LÍNEA L-1018 (BELAUNDE TERRY - TARAPOTO) DE 138 kV | K10: NO
B11: FALLA | C11: ELECTRO ORIENTE | D11: TOCACHE - JUANJUI | E11: LINEA DE TRANSMISION | F11: L-1016 | G11: 16/12/2025 16:02:26 | H11: 16/12/2025 16:12:18 | I11: DESCONEXIÓN DE LA LÍNEA L-1016 (TOCACHE - JUANJUI) DE 138 KV | J11: 15.12 | K11: SI | L11: 138
B12: FALLA | C12: VARI ENERGIA S.A.C. | D12: CAMPAS - SANTA ANA | E12: LINEA DE TRANSMISION | F12: L-1184 | G12: 16/12/2025 08:16:38 | H12: 16/12/2025 08:33:14 | I12: DESCONEXIÓN DE LA LÍNEA L-1184 (CAMPAS - SANTA ANA) DE 138 KV | J12: 1.36 | K12: SI | L12: 138

Sheet RESTRIC_OPE
B3: martes, 16 de Diciembre del 2025
B5: RESTRICCIONES OPERATIVAS
B6: FECHA | C6: HORA INICIO | D6: HORA FINAL | E6: EMPRESA | F6: UBICACIÓN | G6: T.Eq. | H6: EQUIPO | I6: DESCRIPCIÓN
B7: 16/12/2025 | C7: 00:00 | D7: 24:00 | E7: CELEPSA | F7: C.H. EL PLATANAL | G7: CH | H7: CENTRAL | I7: De acuerdo con el correo del 13/10/2025. Debido a problemas en el control de la compuerta de bocatoma, informaron que el servicio de RSF queda indisponible.
B8: 16/12/2025 | C8: 00:00 | D8: 24:00 | E8: EGASA | F8: S.E. CONVERTIDOR | G8: BARRA | H8: BARRA138KV | I8: EGASA limitó la capacidad del transformador 138 kV/33 kV a 50 MVA por deterioro del aislamiento.
B9: 16/12/2025 | C9: 00:00 | D9: 24:00 | E9: ELECTROPERU | F9: C.H. MANTARO | G9: CH | H9: CENTRAL | I9: De acuerdo con el correo del día 25.08.2025, la central tiene una limitación de potencia máxima de 650 MW por seguridad de la central.
B10: 16/12/2025 | C10: 00:00 | D10: 24:00 | E10: ENEL GENERACION PIURA S.A. | F10: C.T. MALACAS | G10: CT | H10: CENTRAL | I10: De acuerdo con la comunicación vía correo del día 24.10.2024. ENEL GENERACIÓN PIURA informa una restricción de potencia para alcanzar 105 MW en simultaneo (TG6+TGN4).
B11: 16/12/2025 | C11: 00:00 | D11: 24:00 | E11: ENEL GENERACION PIURA S.A. | F11: C.T. MALACAS | G11: GT | H11: TG4 | I11: De acuerdo a lo informado mediante correo electrónico el día 25.10, con la disponibilidad actual de aproximadamente 13 MMPCD (368.12 Mm³) la unidad TG4 puede con una generación de 80 MW durante 5 horas, y a potencia mínima durante el resto de los periodos
B12: 16/12/2025 | C12: 00:00 | D12: 24:00 | E12: ENGIE ENERGIA PERU S.A.A. | F12: C.H. YUNCÁN | G12: GH | H12: G3 | I12: Según la carta N° ENG/ 198-2024 enviada por su representada, se opera de forma continua el G3 de la CH Yuncán, debido a la ejecución de mantenimientos necesarios para evitar daños en los sellos de seguridad de la válvula esférica del grupo.
B13: 16/12/2025 | C13: 00:00 | D13: 24:00 | E13: ENGIE ENERGIA PERU S.A.A. | F13: C.T. CHILCA 1 | G13: CT | H13: CENTRAL | I13: Con carta ENG/971-2023, indica que no puede cumplir con las IO considerada en el PDO_17122023 dado que vulneran la seguridad de sus activos. Indican que se debe tomar TMO=168h.
B14: 16/12/2025 | C14: 00:00 | D14: 24:00 | E14: ENGIE ENERGIA PERU S.A.A. | F14: C.T. CHILCA 1 | G14: CT | H14: CENTRAL | I14: Restricción de temperatura de la C.T Chilca, ver valor en el modelo de despacho.
B15: 16/12/2025 | C15: 00:00 | D15: 24:00 | E15: ENGIE ENERGIA PERU S.A.A. | F15: C.T. CHILCA 2 | G15: CT | H15: CENTRAL | I15: Con carta ENG/971-2023, indica que no puede cumplir con las IO considerada en el PDO_17122023 dado que vulneran la seguridad de sus activos. Indican que se debe tomar TMO=168h.
B16: 16/12/2025 | C16: 00:00 | D16: 24:00 | E16: FENIX POWER PERÚ | F16: C.T. FENIX | G16: CT | H16: CENTRAL | I16: De acuerdo con lo comunicado en el correo del día 06.05.2025, la CT Fenix cuenta con TMO de 168 hrs en todos sus modos de operación.
B17: 16/12/2025 | C17: 00:00 | D17: 24:00 | E17: KALLPA GENERACION S.A. | F17: C.H. CERRO DEL AGUILA | G17: GH | H17: G1 | I17: De acuerdo a lo informado el día 17/11 por la empresa KALLPA, el G1 tiene un TA = 15min
... B52: 16/12/2025 | C52: 00:00 | D52: 24:00 | E52: TERMOSELVA | F52: C.T. AGUAYTÍA | G52: CT | H52: CENTRAL | I52: Disponibilidad de 23.5 MMSCF para la CT Aguaytía.

Sheet MANTENIMIENTO EJECUTADOS
B3: martes, 16 de Diciembre del 2025
B5: Mantenimiento Ejecutado
B6: Empresa | C6: Ubicación | D6: Equipo | E6: Inicio | F6: Final | G6: Descripción | H6: MW Indisp. | I6: Prog. | J6: Dispon | K6: Interrupc. | L6: Tipo | M6: CodEq | N6: TipoEq_Osinerg
B7: ATLANTICA TRANSMISION SUR S.A. | C7: CHILCA CTM - POROMA | D7: L-5032 | E7: 16/12/2025 00:00 | F7: 16/12/2025 05:55 | G7: Inspeccion por efluvios | H7: 0 | I7: P | J7: E/S | K7: N | L7: PREV. | M7: 13652 | N7: T
B8: ATLANTICA TRANSMISION SUR S.A. | C8: CHILCA CTM - POROMA | D8: L-5032 | E8: 16/12/2025 23:17 | F8: 17/12/2025 00:00 | G8: Inspeccion por efluvios | H8: 0 | I8: P | J8: E/S | K8: N | L8: PREV. | M8: 13652 | N8: T
B9: ATLANTICA TRANSMISION SUR S.A. | C9: MONTALVO | D9: SE MONTALVO | E9: 16/12/2025 00:00 | F9: 16/12/2025 00:16 | G9: Inspeccion por efluvios. | H9: 0 | I9: P | J9: E/S | K9: N | L9: PREV. | M9: 13742 | N9: T
B10: ATLANTICA TRANSMISION SUR S.A. | C10: OCONA | D10: INT-5450 | E10: 16/12/2025 00:00 | F10: 17/12/2025 00:00 | G10: Interruptor INT-5450 cerrado con restriccion operativa, REB-5450 en servicio y suministrando los SS.AA. de la S.E. Oco?a. | H10: 0 | I10: P | J10: E/S | K10: N | L10: OTROS | M10: 13761 | N10: T
B11: ATLANTICA TRANSMISION SUR S.A. | C11: OCONA | D11: CL-5036 | E11: 16/12/2025 08:48 | F11: 16/12/2025 15:40 | G11: Pruebas funcionales de reles de protecciones | H11: 0 | I11: P | J11: F/S | K11: N | L11: PREV. | M11: 13802 | N11: T
B12: ATLANTICA TRANSMISION SUR S.A. | C12: OCONA - SAN JOSE | D12: L-5036 | E12: 16/12/2025 08:28 | F12: 16/12/2025 16:35 | G12: INDISPONIBLE POR MANTENIMIENTO DE MINERA CERRO VERDE EN LA CL-5036 DE LA SE SAN JOSE | H12: 0 | I12: P | J12: F/S | K12: N | L12: OTROS | M12: 14961 | N12: T
B13: ATLANTICA TRANSMISION SUR S.A. | C13: POROMA | D13: REB-5350 | E13: 16/12/2025 00:00 | F13: 17/12/2025 00:00 | G13: Fuera de servicio po falla en el equipo. | H13: 0 | I13: P | J13: F/S | K13: N | L13: OTROS | M13: 13771 | N13: T
B14: ATLANTICA TRANSMISION SUR S.A. | C14: POROMA - OCONA | D14: L-5034 | E14: 16/12/2025 07:32 | F14: 16/12/2025 16:51 | G14: Mantenimiento de pedestales de las torres de la L-5034 | H14: 0 | I14: P | J14: E/S | K14: N | L14: PREV. | M14: 13743 | N14: T
B15: ATN S.A. | C15: KIMAN AYLLU | D15: AUT-501 | E15: 16/12/2025 00:00 | F15: 17/12/2025 00:00 | G15: Restriccion Operativa en el circuito de control de cambiador de tap s del AUT-501 | H15: 0 | I15: P | J15: E/S | K15: N | L15: OTROS | M15: 13099 | N15: T
B16: ATRIA ENERGIA S.A.C. | C16: PURMACANA | D16: CENTRAL | E16: 16/12/2025 00:00 | F16: 17/12/2025 00:00 | G16: mantenimiento correctivo de valvula principal. | H16: 0 | I16: P | J16: F/S | K16: N | L16: CORR. | M16: 13132 | N16: G
B17: CELARIS ENERGY S.A. | C17: MANTA I | D17: CENTRAL | E17: 16/12/2025 08:00 | F17: 16/12/2025 13:00 | G17: MANTENIMIENTO EVALUACION TERMOGRAFICA GENERAL | H17: 0 | I17: P | J17: E/S | K17: N | L17: PREV. | M17: 20667 | N17: G
B18: CONELSUR LT SAC | C18: CALLAHUANCA (CNS) | D18: S.E. | E18: 16/12/2025 00:00 | F18: 17/12/2025 00:00 | G18: RELE DIFERENCIAL DE BARRAS DE CALLAHUANCA 220KV INOPERATIVO | H18: 0 | I18: P | J18: E/S | K18: N | L18: OTROS | M18: 316 | N18: T
... B130: TRANSMANTARO | C130: YARABAMBA | D130: CL-R-30 | E130: 16/12/2025 00:00 | F130: 17/12/2025 00:00 | G130: CL-R30 CON MANDO SINCRONIZADO ASOCIADO AL INTERRUPTOR IN-5147 INDISPONIBLE. EL SABADO 19.04.25 NO PUDO SER AJUSTADO DEBIDO A FALTA DE EQUIPOS DE PARTE DE LA CONTRATISTA HITACHI. | H130: 0 | I130: P | J130: E/S | K130: N | L130: OTROS | M130: 17424 | N130: T

Sheet INGRESO OC
A3: martes, 16 de Diciembre del 2025
A5: INGRESO A OPERACIÓN COMERCIAL
A6: EMPRESA | B6: TIPO DE EQUIPO | C6: UBICACIÓN | D6: EQUIPO | E6: Fecha y hora de Ingreso a Operación Comercial

Sheet DESPACHO_EJECUTADO
B3: martes, 16 de Diciembre del 2025
A5: POTENCIA ACTIVA EJECUTADA DE LAS UNIDADES DE GENERACIÓN DEL SEIN (MW) | FO5: CENTRALES NO INTEGRANTES COES
A6: FECHA | B6: HORA | C6: 65333 | D6: 101 | E6: 102 | F6: 42667 | G6: 42668 | H6: 126 | I6: 127 | J6: 138 | K6: 139 | L6: 197 | M6: 203 | N6: 204 | O6: 230 | P6: 209 | Q6: 56677 | R6: 796 | S6: 2146 | T6: 142 | U6: 143 | V6: 125 | W6: 187 | X6: 163 | Y6: 298 | Z6: 299 | AA6: 219 | AB6: 151 | AC6: 152 | AD6: 153 | AE6: 154 | AF6: 756 | AG6: 156 | AH6: 155 | AI6: 182 | AJ6: 212 | AK6: 758 | AL6: 263 | AM6: 265 | AN6: 775 | AO6: 777 | AP6: 2154 | AQ6: 150 | AR6: 149 | AS6: 188 | AT6: 2131 | AU6: 755 | AV6: 252 | AW6: 249 | AX6: 250 | AY6: 117 | AZ6: 119 | BA6: 120 | BB6: 189 | BC6: 122 | BD6: 266 | BE6: 337 | BF6: 338 | BG6: 251 | BH6: 115 | BI6: 239 | BJ6: 288 | BK6: 240 | BL6: 241 | BM6: 242 | BN6: 191 | BO6: 194 | BP6: 196 | BQ6: 207 | BR6: 236 | BS6: 795 | BT6: 285 | BU6: 995 | BV6: 996 | BW6: 997 | BX6: 766 | BY6: 926 | BZ6: 924 | CA6: 121 | CB6: 103 | CC6: 104 | CD6: 106 | CE6: 105 | CF6: 107 | CG6: 110 | CH6: 109 | CI6: 144 | CJ6: 113 | CK6: 114 | CL6: 193 | CM6: 208 | CN6: 786 | CO6: 787 | CP6: 788 | CQ6: 789 | CR6: 248 | CS6: 2159 | CT6: 267 | CU6: 268 | CV6: 2194 | CW6: 303 | CX6: 59715 | CY6: 62255 | CZ6: 1263 | DA6: 61800 | DB6: 69125 | DC6: 216 | DD6: 198 | DE6: 70400 | DF6: 49607 | DG6: 214 | DH6: 260 | DI6: 2152 | DJ6: 2128 | DK6: 247 | DL6: 228 | DM6: 2135 | DN6: 261 | DO6: 237 | DP6: 253 | DQ6: 770 | DR6: 235 | DS6: 238 | DT6: 2184 | DU6: 61855 | DV6: 223 | DW6: 226 | DX6: 201 | DY6: 258 | DZ6: 259 | EA6: 920 | EB6: 257 | EC6: 256 | ED6: 2148 | EE6: 58288 | EF6: 58289 | EG6: 58839 | EH6: 58840 | EI6: 75260 | EJ6: 296 | EK6: 297 | EL6: 211 | EM6: 2175 | EN6: 2178 | EO6: 2181 | EP6: 1262 | EQ6: 63425 | ER6: 233 | ES6: 2150 | ET6: 2165 | EU6: 2161 | EV6: 61197 | EW6: 58851 | EX6: 225 | EY6: 2201 | EZ6: 2171 | FA6: 760 | FB6: 234 | FC6: 215 | FD6: 917 | FE6: 289 | FF6: 58333 | FG6: 58336 | FH6: 213 | FI6: 232 | FJ6: 2190 | FK6: 69867 | FL6: 75066 | FM6: TOTAL COES | FO6: 221 | FP6: 222 | FQ6: 224 | FR6: 2187 | FS6: 227 | FT6: 49400 | FU6: 199 | FV6: 200 | FW6: TOTAL NO COES
C7: SUR | D7: CENTRO | E7: CENTRO | F7: NORTE | G7: NORTE | H7: NORTE | I7: NORTE | J7: CENTRO | K7: CENTRO | L7: CENTRO | M7: CENTRO | N7: CENTRO | O7: CENTRO | P7: CENTRO | Q7: CENTRO | R7: CENTRO | S7: CENTRO | T7: CENTRO | U7: CENTRO | V7: CENTRO | W7: CENTRO | X7: SUR | Y7: SUR | Z7: SUR | AA7: CENTRO | AB7: SUR | AC7: SUR | AD7: SUR | AE7: SUR | AF7: SUR | AG7: SUR | AH7: SUR | AI7: SUR | AJ7: CENTRO | AK7: NORTE | AL7: NORTE | AM7: NORTE | AN7: CENTRO | AO7: CENTRO | AP7: CENTRO | AQ7: CENTRO | AR7: CENTRO | AS7: CENTRO | AT7: CENTRO | AU7: SUR | AV7: CENTRO | AW7: CENTRO | AX7: CENTRO | AY7: CENTRO | AZ7: CENTRO | BA7: CENTRO | BB7: SUR | BC7: NORTE | BD7: CENTRO | BE7: CENTRO | BF7: CENTRO | BG7: CENTRO | BH7: NORTE | BI7: NORTE | BJ7: NORTE | BK7: SUR | BL7: SUR | BM7: SUR | BN7: CENTRO | BO7: CENTRO | BP7: CENTRO | BQ7: CENTRO | BR7: CENTRO | BS7: CENTRO | BT7: CENTRO | BU7: SUR | BV7: SUR | BW7: SUR | BX7: NORTE | BY7: SUR | BZ7: CENTRO | CA7: NORTE | CB7: CENTRO | CC7: CENTRO | CD7: CENTRO | CE7: CENTRO | CF7: CENTRO | CG7: CENTRO | CH7: CENTRO | CI7: CENTRO | CJ7: CENTRO | CK7: CENTRO | CL7: CENTRO | CM7: CENTRO | CN7: SUR | CO7: SUR | CP7: SUR | CQ7: SUR | CR7: CENTRO | CS7: CENTRO | CT7: CENTRO | CU7: CENTRO | CV7: NORTE | CW7: CENTRO | CX7: CENTRO | CY7: SUR | CZ7: NORTE | DA7: NORTE | DB7: CENTRO | DC7: NORTE | DD7: NORTE | DE7: SUR | DF7: SUR | DG7: CENTRO | DH7: CENTRO | DI7: CENTRO | DJ7: NORTE | DK7: NORTE | DL7: CENTRO | DM7: CENTRO | DN7: SUR | DO7: SUR | DP7: CENTRO | DQ7: CENTRO | DR7: SUR | DS7: CENTRO | DT7: CENTRO | DU7: NORTE | DV7: CENTRO | DW7: CENTRO | DX7: NORTE | DY7: CENTRO | DZ7: CENTRO | EA7: CENTRO | EB7: NORTE | EC7: NORTE | ED7: SUR | EE7: CENTRO | EF7: CENTRO | EG7: CENTRO | EH7: CENTRO | EJ7: CENTRO | EK7: CENTRO | EL7: SUR | EM7: SUR | EN7: SUR | EO7: SUR | EP7: NORTE | EQ7: SUR | ER7: SUR | ES7: SUR | ET7: CENTRO | EU7: CENTRO | EV7: CENTRO | EW7: SUR | EX7: CENTRO | EY7: CENTRO | EZ7: CENTRO | FA7: CENTRO | FB7: SUR | FC7: NORTE | FD7: CENTRO | FE7: NORTE | FF7: NORTE | FG7: NORTE | FH7: CENTRO | FI7: NORTE | FJ7: NORTE | FK7: NORTE | FO7: NORTE | FP7: CENTRO | FQ7: NORTE | FR7: NORTE | FS7: NORTE | FT7: NORTE | FU7: NORTE | FV7: NORTE
C8: HIDROELÉCTRICA | D8: HIDROELÉCTRICA | E8: HIDROELÉCTRICA | F8: TERMOELÉCTRICA | G8: TERMOELÉCTRICA | H8: HIDROELÉCTRICA | I8: HIDROELÉCTRICA | J8: TERMOELÉCTRICA | K8: TERMOELÉCTRICA | L8: TERMOELÉCTRICA | M8: TERMOELÉCTRICA | N8: TERMOELÉCTRICA | O8: TERMOELÉCTRICA | P8: TERMOELÉCTRICA | Q8: TERMOELÉCTRICA | R8: HIDROELÉCTRICA | S8: HIDROELÉCTRICA | T8: TERMOELÉCTRICA | U8: TERMOELÉCTRICA | V8: TERMOELÉCTRICA | W8: TERMOELÉCTRICA | X8: HIDROELÉCTRICA | Y8: HIDROELÉCTRICA | Z8: HIDROELÉCTRICA | AA8: TERMOELÉCTRICA | AB8: HIDROELÉCTRICA | AC8: HIDROELÉCTRICA | AD8: HIDROELÉCTRICA | AE8: HIDROELÉCTRICA | AF8: TERMOELÉCTRICA | AG8: TERMOELÉCTRICA | AH8: TERMOELÉCTRICA | AI8: HIDROELÉCTRICA | AJ8: HIDROELÉCTRICA | AK8: TERMOELÉCTRICA | AL8: TERMOELÉCTRICA | AM8: TERMOELÉCTRICA | AN8: HIDROELÉCTRICA | AO8: HIDROELÉCTRICA | AP8: HIDROELÉCTRICA | AQ8: HIDROELÉCTRICA | AR8: HIDROELÉCTRICA | AS8: HIDROELÉCTRICA | AT8: HIDROELÉCTRICA | AU8: HIDROELÉCTRICA | AV8: TERMOELÉCTRICA | AW8: TERMOELÉCTRICA | AX8: TERMOELÉCTRICA | AY8: HIDROELÉCTRICA | AZ8: HIDROELÉCTRICA | BA8: HIDROELÉCTRICA | BB8: HIDROELÉCTRICA | BC8: HIDROELÉCTRICA | BD8: HIDROELÉCTRICA | BE8: HIDROELÉCTRICA | BF8: HIDROELÉCTRICA | BG8: HIDROELÉCTRICA | BH8: TERMOELÉCTRICA | BI8: TERMOELÉCTRICA | BJ8: TERMOELÉCTRICA | BK8: TERMOELÉCTRICA | BL8: TERMOELÉCTRICA | BM8: TERMOELÉCTRICA | BN8: HIDROELÉCTRICA | BO8: TERMOELÉCTRICA | BP8: TERMOELÉCTRICA | BQ8: TERMOELÉCTRICA | BR8: TERMOELÉCTRICA | BS8: TERMOELÉCTRICA | BT8: TERMOELÉCTRICA | BU8: TERMOELÉCTRICA | BV8: TERMOELÉCTRICA | BW8: TERMOELÉCTRICA | BX8: HIDROELÉCTRICA | BY8: TERMOELÉCTRICA | BZ8: TERMOELÉCTRICA | CA8: HIDROELÉCTRICA | CB8: HIDROELÉCTRICA | CC8: HIDROELÉCTRICA | CD8: HIDROELÉCTRICA | CE8: HIDROELÉCTRICA | CF8: HIDROELÉCTRICA | CG8: TERMOELÉCTRICA | CH8: TERMOELÉCTRICA | CI8: TERMOELÉCTRICA | CJ8: TERMOELÉCTRICA | CK8: TERMOELÉCTRICA | CL8: TERMOELÉCTRICA | CM8: TERMOELÉCTRICA | CN8: TERMOELÉCTRICA | CO8: TERMOELÉCTRICA | CP8: TERMOELÉCTRICA | CQ8: TERMOELÉCTRICA | CR8: TERMOELÉCTRICA | CS8: TERMOELÉCTRICA | CT8: HIDROELÉCTRICA | CU8: HIDROELÉCTRICA | CV8: HIDROELÉCTRICA | CW8: SOLAR | CX8: EÓLICA | CY8: SOLAR | CZ8: EÓLICA | DA8: SOLAR | DB8: HIDROELÉCTRICA | DC8: HIDROELÉCTRICA | DD8: HIDROELÉCTRICA | DE8: SOLAR | DF8: HIDROELÉCTRICA | DG8: HIDROELÉCTRICA | DH8: HIDROELÉCTRICA | DI8: HIDROELÉCTRICA | DJ8: HIDROELÉCTRICA | DK8: HIDROELÉCTRICA | DL8: HIDROELÉCTRICA | DM8: HIDROELÉCTRICA | DN8: SOLAR | DO8: SOLAR | DP8: EÓLICA | DQ8: EÓLICA | DR8: SOLAR | DS8: HIDROELÉCTRICA | DT8: HIDROELÉCTRICA | DU8: HIDROELÉCTRICA | DV8: HIDROELÉCTRICA | DW8: HIDROELÉCTRICA | DX8: HIDROELÉCTRICA | DY8: HIDROELÉCTRICA | DZ8: HIDROELÉCTRICA | EA8: HIDROELÉCTRICA | EB8: EÓLICA | EC8: EÓLICA | ED8: SOLAR | EE8: EÓLICA | EF8: EÓLICA | EG8: EÓLICA | EH8: EÓLICA | EI8: SOLAR | EJ8: HIDROELÉCTRICA | EK8: HIDROELÉCTRICA | EL8: HIDROELÉCTRICA | EM8: HIDROELÉCTRICA | EN8: HIDROELÉCTRICA | EO8: HIDROELÉCTRICA | EP8: EÓLICA | EQ8: SOLAR | ER8: SOLAR | ES8: SOLAR | ET8: HIDROELÉCTRICA | EU8: EÓLICA | EV8: EÓLICA | EW8: SOLAR | EX8: TERMOELÉCTRICA | EY8: TERMOELÉCTRICA | EZ8: TERMOELÉCTRICA | FA8: TERMOELÉCTRICA | FB8: SOLAR | FC8: HIDROELÉCTRICA | FD8: HIDROELÉCTRICA | FE8: TERMOELÉCTRICA | FF8: TERMOELÉCTRICA | FG8: TERMOELÉCTRICA | FH8: TERMOELÉCTRICA | FI8: TERMOELÉCTRICA | FJ8: TERMOELÉCTRICA | FK8: TERMOELÉCTRICA | FL8: TERMOELÉCTRICA | FO8: HIDROELÉCTRICA | FP8: HIDROELÉCTRICA | FQ8: HIDROELÉCTRICA | FR8: HIDROELÉCTRICA | FS8: TERMOELÉCTRICA | FT8: TERMOELÉCTRICA | FU8: HIDROELÉCTRICA | FV8: HIDROELÉCTRICA
C9: HYDRO GLOBAL PERÚ S.A.C. | D9: ELECTROPERU | E9: ELECTROPERU | F9: ELECTROPERU | G9: ELECTROPERU | H9: ORAZUL ENERGY PERÚ | I9: ORAZUL ENERGY PERÚ | J9: TERMOSELVA | K9: TERMOSELVA | L9: KALLPA GENERACION S.A. | M9: KALLPA GENERACION S.A. | N9: KALLPA GENERACION S.A. | O9: KALLPA GENERACION S.A. | P9: KALLPA GENERACION S.A. | Q9: KALLPA GENERACION S.A. | R9: KALLPA GENERACION S.A. | S9: KALLPA GENERACION S.A. | T9: SHOUGESA | U9: SHOUGESA | V9: SHOUGESA | W9: SHOUGESA | X9: EGEMSA | Y9: EGESUR | Z9: EGESUR | AA9: EGESUR | AB9: EGASA | AC9: EGASA | AD9: EGASA | AE9: EGASA | AF9: EGASA | AG9: EGASA | AH9: EGASA | AI9: SAN GABAN | AJ9: CELEPSA | AK9: MINERA CERRO VERDE | AL9: PLANTA DE RESERVA FRIA DE GENERACION DE ETEN S.A. | AM9: PLANTA DE RESERVA FRIA DE GENERACION DE ETEN S.A. | AN9: EMPRESA DE GENERACION HUALLAGA | AO9: EMPRESA DE GENERACION HUALLAGA | AP9: LA VIRGEN | AQ9: CHINANGO S.A.C. | AR9: CHINANGO S.A.C. | AS9: HIDROELECTRICA HUANCHOR S.A.C. | AT9: CELEPSA RENOVABLES S.R.L. | AU9: INLAND ENERGY SAC | AV9: FENIX POWER PERÚ | AW9: FENIX POWER PERÚ | AX9: FENIX POWER PERÚ | AY9: STATKRAFT S.A | AZ9: STATKRAFT S.A | BA9: STATKRAFT S.A | BB9: STATKRAFT S.A | BC9: STATKRAFT S.A | BD9: STATKRAFT S.A | BE9: CENTRALES SANTA ROSA S.A.C. | BF9: CENTRALES SANTA ROSA S.A.C. | BG9: EMPRESA DE GENERACION HUANZA | BH9: ENEL GENERACION PIURA S.A. | BI9: ENEL GENERACION PIURA S.A. | BJ9: ENEL GENERACION PIURA S.A. | BK9: ENGIE ENERGIA PERU S.A.A. | BL9: ENGIE ENERGIA PERU S.A.A. | BM9: ENGIE ENERGIA PERU S.A.A. | BN9: ENGIE ENERGIA PERU S.A.A. | BO9: ENGIE ENERGIA PERU S.A.A. | BP9: ENGIE ENERGIA PERU S.A.A. | BQ9: ENGIE ENERGIA PERU S.A.A. | BR9: ENGIE ENERGIA PERU S.A.A. | BS9: ENGIE ENERGIA PERU S.A.A. | BT9: ENGIE ENERGIA PERU S.A.A. | BU9: ENGIE ENERGIA PERU S.A.A. | BV9: ENGIE ENERGIA PERU S.A.A. | BW9: ENGIE ENERGIA PERU S.A.A. | BX9: ENGIE ENERGIA PERU S.A.A. | BY9: INFRAESTRUCTURAS Y ENERGIAS DEL PERU S.A.C. | BZ9: INFRAESTRUCTURAS Y ENERGIAS DEL PERU S.A.C. | CA9: INVERSIONES SHAQSHA S.A.C. | CB9: ORYGEN PERU S.A.A. | CC9: ORYGEN PERU S.A.A. | CD9: ORYGEN PERU S.A.A. | CE9: ORYGEN PERU S.A.A. | CF9: ORYGEN PERU S.A.A. | CG9: ORYGEN PERU S.A.A. | CH9: ORYGEN PERU S.A.A. | CI9: ORYGEN PERU S.A.A. | CJ9: ORYGEN PERU S.A.A. | CK9: ORYGEN PERU S.A.A. | CL9: ORYGEN PERU S.A.A. | CM9: ORYGEN PERU S.A.A. | CN9: SAMAY I S.A.C | CO9: SAMAY I S.A.C | CP9: SAMAY I S.A.C | CQ9: SAMAY I S.A.C | CR9: TERMOCHILCA S.A.C. | CS9: TERMOCHILCA S.A.C. | CT9: TRANSMISION ANDINA DE GENERACION S.A.C. | CU9: TRANSMISION ANDINA DE GENERACION S.A.C. | CV9: CELARIS ENERGY S.A. | CW9: COLCA SOLAR S.A.C. | CX9: ENERGIA RENOVABLE DEL SUR S.A. | CY9: GR CORTARRAMA SOCIEDAD ANONIMA CERRADA | CZ9: GR TARUCA SOCIEDAD ANONIMA CERRADA | DA9: KONDU SAC | DB9: VARI ENERGIA S.A.C. | DC9: ORAZUL ENERGY PERÚ | DD9: ORAZUL ENERGY PERÚ | DE9: KALLPA GENERACION S.A. | DF9: SAN GABAN | DG9: MAJA ENERGIA S.A.C. | DH9: EMPRESA DE GENERACION ELECTRICA CANCHAYLLO SAC | DI9: EMPRESA DE GENERACION ELECTRICA SANTA ANA S.A.C. | DJ9: EMPRESA ELECTRICA AGUA AZUL | DK9: EMPRESA ELECTRICA RIO DOBLE | DL9: HIDROCAÑETE S.A. | DM9: HUAURA POWER GROUP S.A. | DN9: MOQUEGUA FV S.A.C. | DO9: PANAMERICANA SOLAR SAC. | DP9: PARQUE EOLICO MARCONA S.A.C. | DQ9: PARQUE EOLICO TRES HERMANAS S.A.C. | DR9: TACNA SOLAR SAC. | DS9: ELECTRICA YANAPAMPA SAC | DT9: ANDEAN POWER S.A.C. | DU9: ASOCIACIÓN SANTA LUCIA DE CHACAS | DV9: ATRIA ENERGIA S.A.C. | DW9: EGEJUNIN | DX9: EGEJUNIN | DY9: EGEJUNIN | DZ9: EGEJUNIN | EA9: EMPRESA DE GENERACION ELECTRICA RIO BAÑOS S.A.C. | EB9: ENERGÍA EÓLICA S.A. | EC9: ENERGÍA EÓLICA S.A. | ED9: ENGIE ENERGIA PERU S.A.A. | EE9: ENGIE ENERGIA PERU S.A.A. | EF9: ENGIE ENERGIA PERU S.A.A. | EG9: ENGIE ENERGIA PERU S.A.A. | EH9: ENGIE ENERGIA PERU S.A.A. | EI9: ENGIE ENERGIA PERU S.A.A. | EJ9: GENERACIÓN ANDINA S.A.C. | EK9: GENERACIÓN ANDINA S.A.C. | EL9: GENERADORA DE ENERGÍA DEL PERÚ | EM9: GENERADORA DE ENERGÍA DEL PERÚ | EN9: GENERADORA DE ENERGÍA DEL PERÚ | EO9: GENERADORA DE ENERGÍA DEL PERÚ | EP9: GR PAINO SOCIEDAD ANONIMA CERRADA | EQ9: JOYA SOLAR S.A.C. | ER9: MAJES ARCUS S.A.C. | ES9: ORYGEN PERU S.A.A. | ET9: ORYGEN PERU S.A.A. | EU9: ORYGEN PERU S.A.A. | EV9: ORYGEN PERU S.A.A. | EW9: ORYGEN PERU S.A.A. | EX9: PETRAMAS | EY9: PETRAMAS | EZ9: PETRAMAS | FA9: PETRAMAS | FB9: REPARTICIÓN ARCUS S.A.C. | FC9: SINERSA | FD9: SINERSA | FE9: BIOENERGIA DEL CHIRA S.A. | FF9: GM OPERACIONES S.A.C. | FG9: GM OPERACIONES S.A.C. | FH9: AGRO INDUSTRIAL PARAMONGA S.A. | FI9: AGROAURORA S.A.C. | FJ9: AGROINDUSTRIAS SAN JACINTO S.A.A. | FK9: AGROLMOS SOCIEDAD ANONIMA - AGROLMOS S.A. | FL9: CASA GRANDE S.A.A. | FO9: UNACEM PERU S.A. | FP9: ELECTRO ORIENTE | FQ9: AGUAS Y ENERGIA PERU | FR9: ELECTRO ZAÑA S.A.C. | FS9: ELECTRONOROESTE S.A. | FT9: SDE PIURA | FU9: SINERSA | FV9: SINERSA
C10: SAN GABAN III | D10: MANTARO | E10: RESTITUCION | F10: TUMBES MAK 1 | G10: TUMBES MAK 2 | H10: CARHUAQUERO | I10: CAÑON DEL PATO | J10: AGUAYTIA TG1 | K10: AGUAYTIA TG2 | L10: KALLPA TG1 | M10: KALLPA TG2 | N10: KALLPA TG3 | O10: KALLPA TV | P10: LFLORES TG1 | Q10: LFLORES TV | R10: CERRO DEL AGUILA | S10: CERRODELAGUILAG4 | T10: SHOUGESA TV1 | U10: SHOUGESA TV2 | V10: SHOUGESA TV3 | W10: SHOUGESA CUMMINS | X10: MACHUPICCHU | Y10: ARICOTA 1 | Z10: ARICOTA 2 | AA10: INDEPENDENCIA | AB10: CHARCANI I,II,III | AC10: CHARCANI IV | AD10: CHARCANI V | AE10: CHARCANI VI | AF10: CHILINA TG | AG10: MOLLENDO 1, 2, 3 | AH10: CHILINA (SULZ 1,2) | AI10: SAN GABAN II | AJ10: PLATANAL | AK10: RECKA | AL10: RF ETEN TG1 | AM10: RF ETEN TG2 | AN10: CHAGLLA GP1 | AO10: CHAGLLA | AP10: LA VIRGEN | AQ10: CHIMAY | AR10: YANANGO | AS10: HUANCHOR | AT10: MARAÑON | AU10: STA TERESA | AV10: FENIX GT11 | AW10: FENIX GT12 | AX10: FENIX TV10 | AY10: YAUPI | AZ10: MALPASO | BA10: CAHUA | BB10: ARCATA | BC10: GALLITO CIEGO | BD10: CHEVES | BE10: SANTA ROSA 1 | BF10: SANTA ROSA 2 | BG10: HUANZA | BH10: MALACAS2 TG4 | BI10: MALACAS3 TG 5 | BJ10: MALACAS1 TG6 | BK10: RF ILO2 TG1 | BL10: RF ILO2 TG2 | BM10: RF ILO2 TG3 | BN10: YUNCAN | BO10: CHILCA1 TG1 | BP10: CHILCA1 TG2 | BQ10: CHILCA1 TG3 | BR10: CHILCA-TV | BS10: CHILCA2 TG41 | BT10: CHILCA2-TV | BU10: CTNEPI_TG41 | BV10: CTNEPI_TG42 | BW10: CTNEPI_TG43 | BX10: QUITARACSA | BY10: RF PTO MALDONADO | BZ10: RF PUCALLPA | CA10: PARIAC | CB10: HUINCO | CC10: MATUCANA | CD10: MOYOPAMPA | CE10: CALLAHUANCA | CF10: HUAMPANI | CG10: STA ROSA WEST TG7 | CH10: UTI_5 | CI10: UTI_6 | CJ10: VENTANILLA 3 | CK10: VENTANILLA 4 | CL10: VENTANILLA TV | CM10: STAROSA TG8 | CN10: PTO_BRVO TG1 | CO10: PTO_BRVO TG2 | CP10: PTO_BRVO TG3 | CQ10: PTO_BRVO TG4 | CR10: OLLEROS TG1 | CS10: OLLEROS TV | CT10: OROYA | CU10: PACHACHACA | CV10: MANTA I | CW10: CS YARUCAYA | CX10: SAN JUAN | CY10: MATARANI | CZ10: DUNA | DA10: CARHUAQUERO (CS) | DB10: ANASHIRONI | DC10: CARHUAQUERO4 | DD10: CAÑA BRAVA | DE10: SUNNY | DF10: TUPURI | DG10: RONCADOR | DH10: CANCHAYLLO | DI10: RENOVANDESH1 | DJ10: POTRERO | DK10: PIZARRAS | DL10: NIMPERIAL | DM10: YARUCAYA | DN10: MOQUEGUA-SOLAR | DO10: PANAMERICANA-SOLAR | DP10: PQE-EOLICO-MARCONA | DQ10: PQE-EOLICO-3-HERMANAS | DR10: TACNA-SOLAR | DS10: YANAPAMPA | DT10: CARHUAC | DU10: HUALLIN | DV10: PURMACANA | DW10: HUASAHUASI | DX10: STACRUZ_1_2 | DY10: RUNATULLO_II | DZ10: RUNATULLO_III | EA10: RUCUY | EB10: PQE-EOLICO-TALARA | EC10: PQE-EOLICO-CUPISNIQUE | ED10: INTIPAMPA | EE10: PUNTA LOMITAS-BL1 | EF10: PUNTA LOMITAS-BL2 | EG10: PUN LOMITAS_EXP-BL1 | EH10: PUN LOMITAS_EXP-BL2 | EI10: EXPANSIÓN INTIPAMPA | EJ10: 8AGOSTO | EK10: EL CARMEN | EL10: LA JOYA | EM10: ANGEL_I | EN10: ANGEL_II | EO10: ANGEL_III | EP10: HUAMBOS | EQ10: SAN MARTIN SOLAR | ER10: MAJES | ES10: RUBI | ET10: CH_HER1 | EU10: WAYRA-I | EV10: WAYRA EXTENSION | EW10: CLEMESI | EX10: HUAYCOLORO | EY10: CALLAO | EZ10: DONA_CATALINA | FA10: LAGRINGAV | FB10: REPARTICION | FC10: POECHOS2 | FD10: CHANCAY | FE10: CANA BRAVA | FF10: REFINERIA TALARA TV1 | FG10: REFINERÍA TALARA TV2 | FH10: PARAMONGA | FI10: MAPLE | FJ10: SAN_JACINTO | FK10: AGROLMOS | FL10: CASA GRANDE | FM10: MW | FO10: CARPAPATA | FP10: CENTRALES ELOR | FQ10: PIAS1 | FR10: ZANA | FS10: TABLAZO | FT10: TALLANCA | FU10: CURUMUY | FV10: POECHOS1 | FW10: MW
A11: 16/12/2025 | B11: 00:30 | C11: 199.2 | D11: 594.2 | E11: 202.8 | H11: 89.5 | I11: 114.2 | J11: 0 | L11: 185.4 | M11: 207.4 | N11: 205.6 | P11: 214 | R11: 280.4 | S11: 9.8 | X11: 163.7 | Y11: 7.1 | AA11: 22.6 | AB11: 6.8 | AC11: 15.1 | AD11: 79.2 | AI11: 110.5 | AJ11: 0 | AN11: 6.5 | AO11: 172.9 | AP11: 35.2 | AQ11: 130.5 | AR11: 18.1 | AS11: 18.4 | AT11: 16.5 | AU11: 56.6 | AV11: 181.2 | AW11: 181.3 | AX11: 183.9 | AY11: 89.5 | AZ11: 0 | BA11: 23.2 | BB11: 4 | BC11: 29.4 | BD11: 39.9 | BG11: 40.6 | BJ11: 25 | BN11: 60.29899 | BO11: 151.40144 | BP11: 151.50788 | BQ11: 151.84209 | BR11: 247.59869 | BS11: 74.83033 | BT11: 36.59705 | CB11: 42.2 | CC11: 85.7 | CD11: 61.6 | CE11: 68.7 | CF11: 30.2 | CG11: 65.7 | CH11: 0 | CI11: 0 | CJ11: 144.7 | CK11: 146.2 | CL11: 148.7 | CR11: 213.7 | CS11: 102.3 | CT11: 5.4 | CU11: 1.7 | CV11: 6.3 | CW11: 0 | CX11: 121.2 | CY11: 0 | CZ11: 0.7 | DA11: 0 | DB11: 3 | DC11: 9.9 | DE11: 0 | DF11: 1 | DG11: 1.4 | DH11: 3.8 | DI11: 20.1 | DJ11: 5.4 | DK11: 13.1 | DL11: 2.9 | DM11: 17.6 | DN11: 0 | DO11: 0 | DP11: 30.1 | DQ11: 90 | DR11: 0 | DS11: 2.3 | DT11: 8.7 | DU11: 2.8 | DW11: 6.3 | DX11: 6.7 | DY11: 9.4 | DZ11: 12.4 | EA11: 10 | EB11: 14.5 | EC11: 13 | ED11: 0 | EE11: 53.27947 | EF11: 82.21183 | EG11: 4.15382 | EH11: 1.25523 | EI11: 0 | EJ11: 12.5 | EK11: 4.5 | EL11: 8.5 | EM11: 20.4 | EN11: 20.4 | EO11: 20 | EP11: 0.9 | EQ11: 0 | ER11: 0 | ES11: 0 | ET11: 0.6 | EU11: 46.5 | EV11: 49.3 | EW11: 0 | EX11: 2.9 | EY11: 2.1 | EZ11: 1.2 | FA11: 1.2 | FB11: 0 | FC11: 4.1 | FD11: 20.2 | FE11: 9.2 | FF11: 27.1 | FG11: 34.2 | FH11: 18 | FI11: 18.6 | FJ11: 7 | FK11: 11.1 | FL11: 22.2 | FM11: 6867.2768 | FO11: 15.88539 | FP11: 0 | FQ11: 11.47 | FR11: 9.3 | FS11: 26.89393 | FT11: 18.92824 | FU11: 0 | FV11: 4.9 | FW11: 87.37756
A12: 16/12/2025 | B12: 01:00 | C12: 201 | D12: 549.2 | E12: 182.7 | H12: 89.6 | I12: 116.7 | J12: 0 | L12: 185.4 | M12: 206.7 | N12: 205.1 | P12: 212.6 | R12: 266 | S12: 9.9 | X12: 165.8 | Y12: 7.5 | AA12: 22.4 | AB12: 6.8 | AC12: 15.1 | AD12: 79.7 | AI12: 110.9 | AJ12: 0 | AN12: 6.5 | AO12: 172.2 | AP12: 36 | AQ12: 60.4 | AR12: 18.2 | AS12: 18.5 | AT12: 16.5 | AU12: 57 | AV12: 181.6 | AW12: 181.8 | AX12: 184.3 | AY12: 91.2 | AZ12: 0 | BA12: 23.5 | BB12: 4 | BC12: 29.8 | BD12: 43.5 | BG12: 40.7 | BJ12: 25 | BN12: 60.56278 | BO12: 156.9958 | BP12: 157.4918 | BQ12: 156.12148 | BR12: 238.65975 | BS12: 74.89801 | BT12: 36.61653 | CB12: 68.7 | CC12: 90.9 | CD12: 61.9 | CE12: 65.6 | CF12: 30.3 | CG12: 65.4 | CH12: 0 | CI12: 0 | CJ12: 144 | CK12: 145.6 | CL12: 148.5 | CR12: 213.6 | CS12: 102.3 | CT12: 5 | CU12: 1.7 | CV12: 6.8 | CW12: 0 | CX12: 124.1 | CY12: 0 | CZ12: 0.3 | DA12: 0 | DB12: 3.2 | DC12: 9.9 | DE12: 0 | DF12: 1 | DG12: 1.5 | DH12: 4 | DI12: 20.5 | DJ12: 5.2 | DK12: 13.1 | DL12: 2.9 | DM12: 17.6 | DN12: 0 | DO12: 0 | DP12: 30 | DQ12: 90.8 | DR12: 0 | DS12: 2.1 | DT12: 8.6 | DU12: 2.7 | DW12: 6.3 | DX12: 6.7 | DY12: 9.8 | DZ12: 12.7 | EA12: 10 | EB12: 18.2 | EC12: 8.5 | ED12: 0 | EE12: 62.95876 | EF12: 93.40423 | EG12: 9.35166 | EH12: 2.24653 | EI12: 0 | EJ12: 12.5 | EK12: 4.5 | EL12: 8.5 | EM12: 20.4 | EN12: 20.4 | EO12: 20 | EP12: 1 | EQ12: 0 | ER12: 0 | ES12: 0 | ET12: 0.6 | EU12: 80.4 | EV12: 90 | EW12: 0 | EX12: 2.9 | EY12: 2.1 | EZ12: 1.2 | FA12: 1.2 | FB12: 0 | FC12: 4.1 | FD12: 20 | FE12: 8.7 | FF12: 27 | FG12: 34.2 | FH12: 17.8 | FI12: 19.4 | FJ12: 6 | FK12: 11.1 | FL12: 21.6 | FM12: 6868.7073 | FO12: 15.92637 | FP12: 0 | FQ12: 11.68 | FR12: 9.3 | FS12: 26.82423 | FT12: 18.92833 | FU12: 0 | FV12: 4.9 | FW12: 87.55893
A13: 16/12/2025 | B13: 01:30 | C13: 201.7 | D13: 535.9 | E13: 182.1 | H13: 69.9 | I13: 115 | J13: 0 | L13: 186.6 | M13: 207.9 | N13: 205.2 | P13: 213.5 | R13: 257.7 | S13: 9.9 | X13: 159.6 | Y13: 6.8 | AA13: 22.5 | AB13: 6.8 | AC13: 15.1 | AD13: 78.6 | AI13: 109.6 | AJ13: 0 | AN13: 6.5 | AO13: 171 | AP13: 37.2 | AQ13: 47.2 | AR13: 18.5 | AS13: 18.6 | AT13: 16.5 | AU13: 55.7 | AV13: 180.5 | AW13: 180.9 | AX13: 184 | AY13: 90.7 | AZ13: 0 | BA13: 23 | BB13: 4 | BC13: 29.4 | BD13: 38.4 | BG13: 10.4 | BJ13: 23.4 | BN13: 60.0299 | BO13: 141.03912 | BP13: 140.88191 | BQ13: 141.82612 | BR13: 233.52441 | BS13: 74.75977 | BT13: 36.57257 | CB13: 55.2 | CC13: 86.6 | CD13: 60.8 | CE13: 63.1 | CF13: 29.8 | CG13: 0 | CH13: 0 | CI13: 0 | CJ13: 144.4 | CK13: 146 | CL13: 148.5 | CR13: 213.7 | CS13: 102.3 | CT13: 5 | CU13: 1.7 | CV13: 7.3 | CW13: 0 | CX13: 122.1 | CY13: 0 | CZ13: 0.4 | DA13: 0 | DB13: 3 | DC13: 10 | DE13: 0 | DF13: 1 | DG13: 1.5 | DH13: 4 | DI13: 20 | DJ13: 5.2 | DK13: 13.1 | DL13: 2.9 | DM13: 17.6 | DN13: 0 | DO13: 0 | DP13: 30.1 | DQ13: 89.9 | DR13: 0 | DS13: 2.2 | DT13: 5.6 | DU13: 2.7 | DW13: 6.4 | DX13: 6.7 | DY13: 9 | DZ13: 12.3 | EA13: 10 | EB13: 14.2 | EC13: 8.1 | ED13: 0 | EE13: 62.5564 | EF13: 95.61104 | EG13: 7.6111 | EH13: 3.49574 | EI13: 0 | EJ13: 12.5 | EK13: 4.5 | EL13: 8.5 | EM13: 20.4 | EN13: 20.4 | EO13: 20 | EP13: 0.7 | EQ13: 0 | ER13: 0 | ES13: 0 | ET13: 0.6 | EU13: 97.4 | EV13: 106.2 | EW13: 0 | EX13: 2.9 | EY13: 2.1 | EZ13: 1.2 | FA13: 1.2 | FB13: 0 | FC13: 4.1 | FD13: 20 | FE13: 9 | FF13: 27.1 | FG13: 34.3 | FH13: 17.8 | FI13: 20.3 | FJ13: 7.6 | FK13: 11.1 | FL13: 21.2 | FM13: 6651.7081 | FO13: 16.60826 | FP13: 0 | FQ13: 11.22 | FR13: 9.2 | FS13: 26.76302 | FT13: 18.92816 | FU13: 0 | FV13: 4.9 | FW13: 87.61944
A14: 16/12/2025 | B14: 02:00 | C14: 203.6 | D14: 546.9 | E14: 181.2 | H14: 31.8 | I14: 118.1 | J14: 0 | L14: 185.2 | M14: 207 | N14: 204.5 | P14: 210.9 | R14: 196.8 | S14: 9.9 | X14: 170.6 | Y14: 7.7 | AA14: 22.6 | AB14: 6.8 | AC14: 14.9 | AD14: 79 | AI14: 110.8 | AJ14: 0 | AN14: 6.5 | AO14: 173.1 | AP14: 36 | AQ14: 55.7 | AR14: 19.6 | AS14: 18.4 | AT14: 15.8 | AU14: 57.7 | AV14: 183.4 | AW14: 183.8 | AX14: 182.8 | AY14: 91.6 | AZ14: 0 | BA14: 23.7 | BB14: 4 | BC14: 30.2 | BD14: 43.2 | BG14: 11.6 | BJ14: 23.7 | BN14: 60.67693 | BO14: 133.67645 | BP14: 133.56706 | BQ14: 133.13784 | BR14: 223.51695 | BS14: 74.76055 | BT14: 36.55895 | CB14: 66.7 | CC14: 90.9 | CD14: 62.1 | CE14: 60.8 | CF14: 28.5 | CG14: 0 | CH14: 0 | CI14: 0 | CJ14: 144.1 | CK14: 145.8 | CL14: 148.1 | CR14: 213.9 | CS14: 102.3 | CT14: 5 | CU14: 1.7 | CV14: 7.5 | CW14: 0 | CX14: 121 | CY14: 0 | CZ14: 0.2 | DA14: 0 | DB14: 3.2 | DC14: 9.9 | DE14: 0 | DF14: 1 | DG14: 1.5 | DH14: 3.9 | DI14: 20.6 | DJ14: 5.2 | DK14: 13.1 | DL14: 2.9 | DM14: 17.6 | DN14: 0 | DO14: 0 | DP14: 29.9 | DQ14: 89.7 | DR14: 0 | DS14: 2.2 | DT14: 0.7 | DU14: 2.6 | DW14: 6.4 | DX14: 6.7 | DY14: 9.8 | DZ14: 12.7 | EA14: 10 | EB14: 12.7 | EC14: 9.2 | ED14: 0 | EE14: 75.34746 | EF14: 90.37828 | EG14: 6.24161 | EH14: 1.85502 | EI14: 0 | EJ14: 12.3 | EK14: 4.4 | EL14: 8.5 | EM14: 20.4 | EN14: 20.4 | EO14: 20 | EP14: 0.6 | EQ14: 0 | ER14: 0 | ES14: 0 | ET14: 0.6 | EU14: 109.1 | EV14: 131.4 | EW14: 0 | EX14: 2.9 | EY14: 2.1 | EZ14: 1.2 | FA14: 1.2 | FB14: 0 | FC14: 4.1 | FD14: 20 | FE14: 8.4 | FF14: 27.1 | FG14: 34.3 | FH14: 18 | FI14: 20.3 | FJ14: 8.3 | FK14: 11.1 | FL14: 21 | FM14: 6616.6171 | FO14: 17.80638 | FP14: 0 | FQ14: 11.54 | FR14: 9.3 | FS14: 26.74097 | FT14: 18.92861 | FU14: 0 | FV14: 4.8 | FW14: 89.11596
A15: 16/12/2025 | B15: 02:30 | C15: 202.4 | D15: 538.6 | E15: 182 | H15: 31.5 | I15: 114.8 | J15: 0 | L15: 185.1 | M15: 207 | N15: 204.4 | P15: 213.2 | R15: 105.1 | S15: 9.8 | X15: 163.1 | Y15: 6.9 | AA15: 22.6 | AB15: 6.8 | AC15: 14.9 | AD15: 78.7 | AI15: 109.9 | AJ15: 0 | AN15: 6.5 | AO15: 157 | AP15: 36 | AQ15: 52.3 | AR15: 18.7 | AS15: 18.6 | AT15: 16.1 | AU15: 56.5 | AV15: 180.3 | AW15: 180.4 | AX15: 183.5 | AY15: 89.3 | AZ15: 0 | BA15: 23.1 | BB15: 4 | BC15: 29.5 | BD15: 38.2 | BG15: 10.7 | BJ15: 23.2 | BN15: 60.32673 | BO15: 154.3042 | BP15: 154.32167 | BQ15: 155.04856 | BR15: 247.30942 | BS15: 74.62566 | BT15: 36.61266 | CB15: 65.2 | CC15: 90.6 | CD15: 61.1 | CE15: 59.6 | CF15: 26.6 | CG15: 0 | CH15: 0 | CI15: 0 | CJ15: 144.4 | CK15: 145.9 | CL15: 147.4 | CR15: 213.5 | CS15: 102.4 | CT15: 5.1 | CU15: 1.7 | CV15: 7.2 | CW15: 0 | CX15: 118.8 | CY15: 0 | CZ15: 0 | DA15: 0 | DB15: 2.9 | DC15: 9.9 | DE15: 0 | DF15: 0.9 | DG15: 1.5 | DH15: 3.8 | DI15: 20 | DJ15: 5.2 | DK15: 13 | DL15: 3 | DM15: 17.6 | DN15: 0 | DO15: 0 | DP15: 29.5 | DQ15: 86.9 | DR15: 0 | DS15: 2.1 | DT15: 0 | DU15: 2.6 | DW15: 6.6 | DX15: 6.7 | DY15: 9.2 | DZ15: 12.2 | EA15: 10 | EB15: 14 | EC15: 8.9 | ED15: 0 | EE15: 68.84061 | EF15: 95.81272 | EG15: 7.89959 | EH15: 2.0514 | EI15: 0 | EJ15: 12.2 | EK15: 4.4 | EL15: 8.4 | EM15: 20.4 | EN15: 20.4 | EO15: 20 | EP15: 0.5 | EQ15: 0 | ER15: 0 | ES15: 0 | ET15: 0.6 | EU15: 108.6 | EV15: 132.6 | EW15: 0 | EX15: 2.9 | EY15: 2.1 | EZ15: 1.2 | FA15: 1.2 | FB15: 0 | FC15: 4.1 | FD15: 20 | FE15: 9.4 | FF15: 27.3 | FG15: 34.5 | FH15: 17.9 | FI15: 20.3 | FJ15: 8.4 | FK15: 11.1 | FL15: 18.4 | FM15: 6540.7532 | FO15: 17.99146 | FP15: 0 | FQ15: 11.55 | FR15: 9.2 | FS15: 26.82878 | FT15: 18.92925 | FU15: 0 | FV15: 4.9 | FW15: 89.39949
A16: 16/12/2025 | B16: 03:00 | C16: 203 | D16: 483.1 | E16: 156 | H16: 31.9 | I16: 115.5 | J16: 0 | L16: 185.8 | M16: 206.7 | N16: 204.2 | P16: 210.7 | R16: 111.2 | S16: 9.9 | X16: 163.5 | Y16: 7.7 | AA16: 22.5 | AB16: 6.8 | AC16: 15 | AD16: 80.1 | AI16: 111.1 | AJ16: 0 | AN16: 6.5 | AO16: 157.8 | AP16: 37.1 | AQ16: 76.7 | AR16: 19.8 | AS16: 18.6 | AT16: 16.5 | AU16: 57.9 | AV16: 182.7 | AW16: 183.3 | AX16: 185.1 | AY16: 91.2 | AZ16: 0 | BA16: 23.7 | BB16: 4 | BC16: 30 | BD16: 45.7 | BG16: 11.8 | BJ16: 23.9 | BN16: 60.68127 | BO16: 148.04006 | BP16: 147.96477 | BQ16: 146.74289 | BR16: 217.2023 | BS16: 75.17179 | BT16: 36.67866 | CB16: 68.5 | CC16: 101.8 | CD16: 62 | CE16: 60 | CF16: 27.8 | CG16: 0 | CH16: 0 | CI16: 0 | CJ16: 144.5 | CK16: 146.1 | CL16: 148 | CR16: 214.2 | CS16: 102.4 | CT16: 5 | CU16: 1.7 | CV16: 7 | CW16: 0 | CX16: 112.8 | CY16: 0 | CZ16: 0 | DA16: 0 | DB16: 3.1 | DC16: 9.9 | DE16: 0 | DF16: 1 | DG16: 1.5 | DH16: 3.8 | DI16: 20.6 | DJ16: 5.3 | DK16: 13 | DL16: 3 | DM16: 17.6 | DN16: 0 | DO16: 0 | DP16: 27.6 | DQ16: 78.5 | DR16: 0 | DS16: 2.1 | DT16: 0 | DU16: 2.6 | DW16: 6.6 | DX16: 6.7 | DY16: 10 | DZ16: 12.9 | EA16: 9.9 | EB16: 15.2 | EC16: 8.9 | ED16: 0 | EE16: 83.60353 | EF16: 95.12323 | EG16: 5.7987 | EH16: 4.01097 | EI16: 0 | EJ16: 12.1 | EK16: 4.4 | EL16: 8.4 | EM16: 20.4 | EN16: 20.4 | EO16: 20 | EP16: 0.4 | EQ16: 0 | ER16: 0 | ES16: 0 | ET16: 0.6 | EU16: 106.8 | EV16: 117.1 | EW16: 0 | EX16: 2.9 | EY16: 2.1 | EZ16: 1.2 | FA16: 1.2 | FB16: 0 | FC16: 4.1 | FD16: 20 | FE16: 9.6 | FF16: 27.7 | FG16: 34.8 | FH16: 17.9 | FI16: 20.3 | FJ16: 8.5 | FK16: 11.1 | FL16: 22 | FM16: 6473.6182 | FO16: 18.31084 | FP16: 0 | FQ16: 11.55 | FR16: 9.3 | FS16: 26.8364 | FT16: 18.9291 | FU16: 0 | FV16: 4.8 | FW16: 89.72634
A17: 16/12/2025 | B17: 03:30 | C17: 205.4 | D17: 478 | E17: 156.3 | H17: 33 | I17: 115.8 | J17: 0 | L17: 185.4 | M17: 209.1 | N17: 207.7 | P17: 212 | R17: 124.4 | S17: 10 | X17: 166 | Y17: 7.5 | AA17: 22.5 | AB17: 6.9 | AC17: 15 | AD17: 80 | AI17: 110.8 | AJ17: 0 | AN17: 6.5 | AO17: 148.2 | AP17: 38 | AQ17: 53.5 | AR17: 20.9 | AS17: 18.6 | AT17: 17.4 | AU17: 56.3 | AV17: 184.4 | AW17: 184.5 | AX17: 184.4 | AY17: 93 | AZ17: 0 | BA17: 23.5 | BB17: 4 | BC17: 28.5 | BD17: 46.2 | BG17: 11.6 | BJ17: 23.8 | BN17: 61.14934 | BO17: 168.97716 | BP17: 168.81705 | BQ17: 169.67962 | BR17: 255.94238 | BS17: 74.59111 | BT17: 36.72647 | CB17: 95.8 | CC17: 104.9 | CD17: 62.2 | CE17: 62 | CF17: 27.7 | CG17: 0 | CH17: 0 | CI17: 0 | CJ17: 144.2 | CK17: 145.8 | CL17: 147.9 | CR17: 214.3 | CS17: 102.5 | CT17: 4.9 | CU17: 1.7 | CV17: 7 | CW17: 0 | CX17: 108.1 | CY17: 0 | CZ17: 0 | DA17: 0 | DB17: 3.1 | DC17: 9.9 | DE17: 0 | DF17: 0.9 | DG17: 1.5 | DH17: 4 | DI17: 20.3 | DJ17: 6 | DK17: 13 | DL17: 2.9 | DM17: 17.6 | DN17: 0 | DO17: 0 | DP17: 26 | DQ17: 77 | DR17: 0 | DS17: 2.1 | DT17: 0 | DU17: 2.6 | DW17: 6.6 | DX17: 6.7 | DY17: 10 | DZ17: 12.6 | EA17: 10 | EB17: 15.3 | EC17: 6.3 | ED17: 0 | EE17: 79.85106 | EF17: 90.60809 | EG17: 4.20693 | EH17: 4.95685 | EI17: 0 | EJ17: 12 | EK17: 4.3 | EL17: 8.4 | EM17: 20.4 | EN17: 20.4 | EO17: 20 | EP17: 0 | EQ17: 0 | ER17: 0 | ES17: 0 | ET17: 0.6 | EU17: 103.8 | EV17: 116 | EW17: 0 | EX17: 2.9 | EY17: 2.1 | EZ17: 1.2 | FA17: 1.2 | FB17: 0 | FC17: 4.1 | FD17: 20 | FE17: 9.6 | FF17: 27.6 | FG17: 34.8 | FH17: 18.5 | FI17: 20.3 | FJ17: 8.8 | FK17: 11.1 | FL17: 22.2 | FM17: 6578.3061 | FO17: 18.39252 | FP17: 0 | FQ17: 11.55 | FR17: 9.2 | FS17: 26.80493 | FT17: 18.92857 | FU17: 0 | FV17: 4.9 | FW17: 89.77602
A18: 16/12/2025 | B18: 04:00 | C18: 201.4 | D18: 477.9 | E18: 156.6 | H18: 31.9 | I18: 115.1 | J18: 0 | L18: 186.5 | M18: 207.4 | N18: 208.2 | P18: 214.3 | R18: 156.8 | S18: 10 | X18: 165.5 | Y18: 7.2 | AA18: 22.6 | AB18: 6.8 | AC18: 15 | AD18: 79.7 | AI18: 110.9 | AJ18: 0 | AN18: 6.5 | AO18: 146.5 | AP18: 38 | AQ18: 56 | AR18: 20.3 | AS18: 18.6 | AT18: 17.6 | AU18: 57.1 | AV18: 181.8 | AW18: 182.2 | AX18: 184.8 | AY18: 91.2 | AZ18: 0 | BA18: 23.5 | BB18: 4 | BC18: 27.6 | BD18: 56.5 | BG18: 11.5 | BJ18: 24 | BN18: 60.47961 | BO18: 171.16248 | BP18: 172.03114 | BQ18: 172.14169 | BR18: 254.88077 | BS18: 75.1922 | BT18: 36.66926 | CB18: 105.9 | CC18: 106.5 | CD18: 62 | CE18: 61.9 | CF18: 28 | CG18: 0 | CH18: 0 | CI18: 0 | CJ18: 144.5 | CK18: 146.2 | CL18: 148.1 | CR18: 213.1 | CS18: 102.2 | CT18: 5 | CU18: 1.7 | CV18: 6.9 | CW18: 0 | CX18: 103.6 | CY18: 0 | CZ18: 0 | DA18: 0 | DB18: 2.9 | DC18: 9.9 | DE18: 0 | DF18: 0.9 | DG18: 1.4 | DH18: 3.9 | DI18: 20.3 | DJ18: 6.2 | DK18: 13 | DL18: 2.9 | DM18: 17.6 | DN18: 0 | DO18: 0 | DP18: 27.2 | DQ18: 80.5 | DR18: 0 | DS18: 2.1 | DT18: 0 | DU18: 2.6 | DW18: 6.6 | DX18: 6.7 | DY18: 10.1 | DZ18: 12.7 | EA18: 10 | EB18: 15.1 | EC18: 6.3 | ED18: 0 | EE18: 75.00366 | EF18: 87.11828 | EG18: 2.71504 | EH18: 1.567 | EI18: 0 | EJ18: 11.8 | EK18: 4.3 | EL18: 8.7 | EM18: 20.4 | EN18: 20.4 | EO18: 20 | EP18: 0 | EQ18: 0 | ER18: 0 | ES18: 0 | ET18: 0.6 | EU18: 108.8 | EV18: 106 | EW18: 0 | EX18: 2.9 | EY18: 2.1 | EZ18: 1.2 | FA18: 1.2 | FB18: 0 | FC18: 4.1 | FD18: 20 | FE18: 9.2 | FF18: 27.7 | FG18: 34.9 | FH18: 18.2 | FI18: 20.3 | FJ18: 8.3 | FK18: 11.1 | FL18: 19.7 | FM18: 6606.8611 | FO18: 18.4721 | FP18: 0 | FQ18: 11.55 | FR18: 9.3 | FS18: 26.83447 | FT18: 18.92904 | FU18: 0 | FV18: 4.9 | FW18: 89.98561
A19: 16/12/2025 | B19: 04:30 | C19: 201.4 | D19: 478.6 | E19: 155.9 | H19: 31.7 | I19: 115.1 | J19: 0 | L19: 186.3 | M19: 207.4 | N19: 209.1 | P19: 211.9 | R19: 193.8 | S19: 9.9 | X19: 160.2 | Y19: 7.1 | AA19: 22.6 | AB19: 6.8 | AC19: 15.1 | AD19: 80 | AI19: 110.8 | AJ19: 0 | AN19: 6.5 | AO19: 146.5 | AP19: 38 | AQ19: 61 | AR19: 19.3 | AS19: 18.6 | AT19: 17.7 | AU19: 55.7 | AV19: 182.4 | AW19: 182.9 | AX19: 185.8 | AY19: 90.8 | AZ19: 0 | BA19: 23.5 | BB19: 4 | BC19: 27.8 | BD19: 75.6 | BG19: 11.4 | BJ19: 23.7 | BN19: 60.63366 | BO19: 173.12741 | BP19: 171.23333 | BQ19: 173.85675 | BR19: 247.22745 | BS19: 75.00844 | BT19: 36.63271 | CB19: 104.8 | CC19: 101.4 | CD19: 61.7 | CE19: 62 | CF19: 28 | CG19: 0 | CH19: 0 | CI19: 0 | CJ19: 145.2 | CK19: 146.9 | CL19: 148.7 | CR19: 213.1 | CS19: 102.3 | CT19: 5 | CU19: 1.7 | CV19: 6.9 | CW19: 0 | CX19: 102.6 | CY19: 0 | CZ19: 0 | DA19: 0 | DB19: 2.9 | DC19: 9.9 | DE19: 0 | DF19: 1 | DG19: 1.5 | DH19: 3.8 | DI19: 20.3 | DJ19: 6 | DK19: 13 | DL19: 2.9 | DM19: 17.6 | DN19: 0 | DO19: 0 | DP19: 25.5 | DQ19: 71.9 | DR19: 0 | DS19: 2.1 | DT19: 0 | DU19: 2.5 | DW19: 6.6 | DX19: 6.7 | DY19: 10 | DZ19: 13.7 | EA19: 10 | EB19: 14 | EC19: 8 | ED19: 0 | EE19: 51.53208 | EF19: 74.49966 | EG19: 2.6795 | EH19: 1.12692 | EI19: 0 | EJ19: 11.8 | EK19: 4.3 | EL19: 8.6 | EM19: 20.4 | EN19: 20.4 | EO19: 20 | EP19: 0 | EQ19: 0 | ER19: 0 | ES19: 0 | ET19: 0.6 | EU19: 96.4 | EV19: 93 | EW19: 0 | EX19: 2.9 | EY19: 2.1 | EZ19: 1.2 | FA19: 1.2 | FB19: 0 | FC19: 4.1 | FD19: 20 | FE19: 9.1 | FF19: 27.7 | FG19: 34.8 | FH19: 18.2 | FI19: 20.3 | FJ19: 8.2 | FK19: 11.1 | FL19: 17.4 | FM19: 6576.4579 | FO19: 18.56836 | FP19: 0 | FQ19: 11.55 | FR19: 9.4 | FS19: 26.86825 | FT19: 18.92889 | FU19: 0 | FV19: 4.9 | FW19: 90.2155
A20: 16/12/2025 | B20: 05:00 | C20: 203.6 | D20: 536.9 | E20: 178 | H20: 31.5 | I20: 107.4 | J20: 0 | L20: 185.4 | M20: 207.5 | N20: 207 | P20: 210.2 | R20: 197.1 | S20: 9.9 | X20: 164.6 | Y20: 7.3 | AA20: 22.5 | AB20: 6.8 | AC20: 15 | AD20: 79.3 | AI20: 110.9 | AJ20: 0 | AN20: 6.5 | AO20: 151.5 | AP20: 38 | AQ20: 62.3 | AR20: 21.2 | AS20: 18.6 | AT20: 17.8 | AU20: 57 | AV20: 181.7 | AW20: 182.5 | AX20: 184 | AY20: 91.5 | AZ20: 0 | BA20: 25 | BB20: 4 | BC20: 27.5 | BD20: 43.7 | BG20: 11.4 | BJ20: 23.9 | BN20: 60.6247 | BO20: 163.96995 | BP20: 163.68736 | BQ20: 164.63797 | BR20: 254.58347 | BS20: 74.29614 | BT20: 36.5304 | CB20: 96.4 | CC20: 96.5 | CD20: 61.9 | CE20: 63.9 | CF20: 28.2 | CG20: 0 | CH20: 0 | CI20: 0 | CJ20: 144.9 | CK20: 146.5 | CL20: 148.8 | CR20: 213.8 | CS20: 102.5 | CT20: 5 | CU20: 1.7 | CV20: 6.7 | CW20: 0 | CX20: 97.9 | CY20: 0 | CZ20: 0 | DA20: 0 | DB20: 3 | DC20: 10 | DE20: 0 | DF20: 1 | DG20: 1.5 | DH20: 3.8 | DI20: 20.6 | DJ20: 6 | DK20: 13 | DL20: 2.9 | DM20: 17.6 | DN20: 0 | DO20: 0 | DP20: 24.8 | DQ20: 65.2 | DR20: 0 | DS20: 2.2 | DT20: 0 | DU20: 2.5 | DW20: 6.6 | DX20: 6.7 | DY20: 10 | DZ20: 13.6 | EA20: 10 | EB20: 9.4 | EC20: 9.3 | ED20: 0 | EE20: 57.24551 | EF20: 81.60071 | EG20: 4.51155 | EH20: 1.63258 | EI20: 0 | EJ20: 11.5 | EK20: 4.2 | EL20: 8.6 | EM20: 20.4 | EN20: 20.4 | EO20: 20 | EP20: 0 | EQ20: 0 | ER20: 0 | ES20: 0 | ET20: 0.6 | EU20: 84.2 | EV20: 84 | EW20: 0 | EX20: 2.9 | EY20: 2.1 | EZ20: 1.2 | FA20: 1.2 | FB20: 0 | FC20: 4.1 | FD20: 20 | FE20: 9.3 | FF20: 27.8 | FG20: 34.8 | FH20: 18.1 | FI20: 20.3 | FJ20: 8.1 | FK20: 11.1 | FL20: 17.3 | FM20: 6578.9203 | FO20: 18.88289 | FP20: 0 | FQ20: 11.55 | FR20: 9.2 | FS20: 26.88707 | FT20: 18.92905 | FU20: 0 | FV20: 4.8 | FW20: 90.24901
A21: 16/12/2025 | B21: 05:30 | C21: 203.2 | D21: 594.9 | E21: 192.3 | H21: 31.9 | I21: 104.2 | J21: 0 | L21: 185.9 | M21: 207.4 | N21: 206.4 | P21: 212 | R21: 196.3 | S21: 9.9 | X21: 163.9 | Y21: 7.1 | AA21: 22.6 | AB21: 6.8 | AC21: 14.9 | AD21: 79.6 | AI21: 110.9 | AJ21: 0 | AN21: 6.5 | AO21: 220.8 | AP21: 38.3 | AQ21: 68.5 | AR21: 21 | AS21: 18.6 | AT21: 17.8 | AU21: 57 | AV21: 181.7 | AW21: 182.5 | AX21: 184.1 | AY21: 90.7 | AZ21: 0 | BA21: 24.8 | BB21: 4 | BC21: 27.5 | BD21: 41.6 | BG21: 19.9 | BJ21: 24 | BN21: 60.63085 | BO21: 169.20767 | BP21: 169.02072 | BQ21: 170.16177 | BR21: 256.48916 | BS21: 74.96307 | BT21: 36.6806 | CB21: 78.2 | CC21: 98.2 | CD21: 61.9 | CE21: 65.8 | CF21: 27.5 | CG21: 0 | CH21: 0 | CI21: 0 | CJ21: 144.7 | CK21: 146.2 | CL21: 148.4 | CR21: 213.8 | CS21: 102.4 | CT21: 5 | CU21: 1.7 | CV21: 6.6 | CW21: 0 | CX21: 98.1 | CY21: 0 | CZ21: 0 | DA21: 0 | DB21: 2.9 | DC21: 9.9 | DE21: 4.9 | DF21: 1.1 | DG21: 1.5 | DH21: 3.9 | DI21: 20.3 | DJ21: 5.9 | DK21: 12.3 | DL21: 2.9 | DM21: 17.6 | DN21: 0.2 | DO21: 0.1 | DP21: 25.8 | DQ21: 67 | DR21: 0.4 | DS21: 2.1 | DT21: 0 | DU21: 2.5 | DW21: 6.6 | DX21: 6.7 | DY21: 9.9 | DZ21: 13.6 | EA21: 10 | EB21: 6.1 | EC21: 8.5 | ED21: 1.91957 | EE21: 65.06395 | EF21: 65.50617 | EG21: 1.73332 | EH21: 0.91379 | EI21: 0 | EJ21: 11.5 | EK21: 4.2 | EL21: 8.5 | EM21: 20.4 | EN21: 20.4 | EO21: 20 | EP21: 0 | EQ21: 6 | ER21: 0 | ES21: 6.8 | ET21: 0.6 | EU21: 79.1 | EV21: 69.6 | EW21: 6.5 | EX21: 2.9 | EY21: 2.1 | EZ21: 1.2 | FA21: 1.2 | FB21: 0 | FC21: 4.1 | FD21: 20 | FE21: 8.7 | FF21: 27.8 | FG21: 34.8 | FH21: 18.1 | FI21: 20.3 | FJ21: 8.5 | FK21: 11.1 | FL21: 22.8 | FM21: 6730.1906 | FO21: 18.78173 | FP21: 0 | FQ21: 11.25 | FR21: 9.2 | FS21: 26.94943 | FT21: 18.92956 | FU21: 0 | FV21: 4.9 | FW21: 90.01072
A22: 16/12/2025 | B22: 06:00 | C22: 200.9 | D22: 596.3 | E22: 201.4 | H22: 31.3 | I22: 111.5 | J22: 0 | L22: 185.6 | M22: 208 | N22: 205.6 | P22: 212.3 | R22: 196.7 | S22: 9.9 | X22: 164.2 | Y22: 7.1 | AA22: 22.5 | AB22: 6.9 | AC22: 14.7 | AD22: 79.8 | AI22: 110.3 | AJ22: 0 | AN22: 6.5 | AO22: 147.9 | AP22: 39.3 | AQ22: 60.9 | AR22: 20.3 | AS22: 18.6 | AT22: 17.8 | AU22: 57.4 | AV22: 179.7 | AW22: 180 | AX22: 184.3 | AY22: 90.5 | AZ22: 0 | BA22: 24.9 | BB22: 4 | BC22: 27.9 | BD22: 40.6 | BG22: 19.5 | BJ22: 24.1 | BN22: 60.39896 | BO22: 156.57897 | BP22: 156.49645 | BQ22: 155.4983 | BR22: 235.43433 | BS22: 74.91859 | BT22: 36.56384 | CB22: 73 | CC22: 95.7 | CD22: 61.4 | CE22: 68.9 | CF22: 27.3 | CG22: 0 | CH22: 0 | CI22: 0 | CJ22: 145 | CK22: 146.6 | CL22: 148.6 | CR22: 214.2 | CS22: 102.5 | CT22: 5 | CU22: 1.7 | CV22: 6.7 | CW22: 0 | CX22: 106.2 | CY22: 2.2 | CZ22: 0 | DA22: 0 | DB22: 2.8 | DC22: 9.9 | DE22: 21.4 | DF22: 1.1 | DG22: 1.6 | DH22: 3.9 | DI22: 20 | DJ22: 5.8 | DK22: 12.3 | DL22: 3 | DM22: 17.6 | DN22: 0.5 | DO22: 0.4 | DP22: 26.3 | DQ22: 70.1 | DR22: 1.1 | DS22: 2.1 | DT22: 4 | DU22: 2.4 | DW22: 6.6 | DX22: 6.7 | DY22: 10.1 | DZ22: 13.7 | EA22: 10 | EB22: 5.7 | EC22: 7 | ED22: 11.00892 | EE22: 56.7932 | EF22: 73.82655 | EG22: 4.28153 | EH22: 1.78087 | EI22: 1.72 | EJ22: 11.5 | EK22: 4.2 | EL22: 8.5 | EM22: 20.4 | EN22: 20.4 | EO22: 20 | EP22: 0 | EQ22: 30.6 | ER22: 0.7 | ES22: 32.5 | ET22: 0.6 | EU22: 57.3 | EV22: 55.6 | EW22: 24 | EX22: 2.9 | EY22: 2.1 | EZ22: 1.2 | FA22: 1.2 | FB22: 0.7 | FC22: 4.1 | FD22: 20 | FE22: 8.8 | FF22: 28 | FG22: 35 | FH22: 17.8 | FI22: 20.3 | FJ22: 8.1 | FK22: 11.1 | FL22: 22.4 | FM22: 6675.6005 | FO22: 18.92486 | FP22: 0 | FQ22: 10.57 | FR22: 9.2 | FS22: 26.95987 | FT22: 18.92933 | FU22: 4.9 | FV22: 4.8 | FW22: 94.28406
... A58: 17/12/2025 | B58: 00:00 | C58: 204.5 | D58: 450.3 | E58: 147.3 | H58: 80.4 | I58: 120.6 | J58: 80.4 | L58: 184.4 | M58: 207.1 | N58: 204.1 | P58: 209.3 | R58: 478.1 | S58: 9.9 | X58: 163.7 | Y58: 7.6 | AA58: 16.9 | AB58: 6.9 | AC58: 15.1 | AD58: 85.5 | AI58: 110.9 | AJ58: 65.5 | AN58: 6.5 | AO58: 152.9 | AP58: 45.4 | AQ58: 131.3 | AR58: 22.9 | AS58: 18.4 | AT58: 17.2 | AU58: 57.6 | AV58: 182.6 | AW58: 183.2 | AX58: 184.5 | AY58: 106.5 | AZ58: 0 | BA58: 24.2 | BB58: 4 | BC58: 34.5 | BD58: 42.6 | BG58: 58 | BJ58: 47 | BN58: 81.22009 | BO58: 153.17812 | BP58: 153.40816 | BQ58: 152.88558 | BR58: 233.4293 | BS58: 74.19027 | BT58: 36.39774 | CB58: 80.1 | CC58: 104.6 | CD58: 64 | CE58: 74.8 | CF58: 30.3 | CG58: 118.2 | CH58: 48.2 | CI58: 49.7 | CJ58: 144.2 | CK58: 145.2 | CL58: 170.7 | CR58: 213.3 | CS58: 102.2 | CT58: 5.6 | CU58: 1.6 | CV58: 5.9 | CW58: 0 | CX58: 56.9 | CY58: 0 | CZ58: 0 | DA58: 0 | DB58: 20.2 | DC58: 10 | DE58: 0 | DF58: 1.2 | DG58: 1.7 | DH58: 3.9 | DI58: 20.3 | DJ58: 5.1 | DK58: 13 | DL58: 2.6 | DM58: 16.9 | DN58: 0 | DO58: 0 | DP58: 11.7 | DQ58: 40.9 | DR58: 0 | DS58: 2.2 | DT58: 13.9 | DU58: 3.1 | DW58: 7.1 | DX58: 6.5 | DY58: 19.4 | DZ58: 20.2 | EA58: 18.1 | EB58: 12.7 | EC58: 21.5 | ED58: 0 | EE58: 37.45426 | EF58: 56.3 | EG58: 2.16535 | EH58: 0.31 | EI58: 0 | EJ58: 15.4 | EK58: 3.8 | EL58: 8.3 | EM58: 20.4 | EN58: 20.4 | EO58: 20 | EP58: 0 | EQ58: 0 | ER58: 0 | ES58: 0 | ET58: 0.6 | EU58: 11.9 | EV58: 5.7 | EW58: 0 | EX58: 2.9 | EY58: 2.1 | EZ58: 1.2 | FA58: 1.2 | FB58: 0 | FC58: 4.1 | FD58: 19.3 | FE58: 8.6 | FF58: 27.3 | FG58: 34 | FH58: 17.6 | FI58: 19.2 | FJ58: 7.46 | FK58: 11.1 | FL58: 20 | FM58: 7118.9989 | FO58: 18.97877 | FP58: 1.298 | FQ58: 11.853 | FR58: 9.2 | FS58: 26.78348 | FT58: 9.4373 | FU58: 0 | FV58: 5.1 | FW58: 82.65055
A59: EJEC | C59: 4862.15 | D59: 12264.8 | E59: 4052.6 | F59: 0 | G59: 0 | H59: 1709.7 | I59: 3469.7 | J59: 955.9 | K59: 0 | L59: 4371.85 | M59: 4917.85 | N59: 4879.75 | O59: 0 | P59: 5015.25 | Q59: 0 | R59: 5922.1 | S59: 237.55 | T59: 0 | U59: 0 | V59: 0 | W59: 0 | X59: 3927.9 | Y59: 174.95 | Z59: 0 | AA59: 437.9 | AB59: 165.15 | AC59: 356.05 | AD59: 2230.85 | AE59: 0 | AF59: 0 | AG59: 0 | AH59: 0 | AI59: 2656.5 | AJ59: 1733.6 | AK59: 0 | AL59: 0 | AM59: 0 | AN59: 156 | AO59: 4367.5 | AP59: 1040.1 | AQ59: 2539.65 | AR59: 505.45 | AS59: 443.85 | AT59: 416.7 | AU59: 1368.3 | AV59: 4376.5 | AW59: 4386.5 | AX59: 4433.65 | AY59: 2392.7 | AZ59: 202.9 | BA59: 587.15 | BB59: 96 | BC59: 770.2 | BD59: 929.55 | BE59: 0 | BF59: 0 | BG59: 1094.05 | BH59: 0 | BI59: 0 | BJ59: 890.75 | BK59: 0 | BL59: 0 | BM59: 0 | BN59: 1624.9129 | BO59: 3896.3077 | BP59: 3882.0039 | BQ59: 4027.1191 | BR59: 5961.7851 | BS59: 1763.5293 | BT59: 863.11156 | BU59: 0 | BV59: 0 | BW59: 0 | BX59: 0 | BY59: 0 | BZ59: 0 | CA59: 0 | CB59: 2594.95 | CC59: 2377.7 | CD59: 1528.35 | CE59: 1646.55 | CF59: 674.55 | CG59: 1445.7 | CH59: 72.1 | CI59: 564.5 | CJ59: 3446.95 | CK59: 3480.35 | CL59: 3941.05 | CM59: 0 | CN59: 0 | CO59: 0 | CP59: 0 | CQ59: 0 | CR59: 5075.75 | CS59: 2422.7 | CT59: 134.8 | CU59: 38.4 | CV59: 153 | CW59: 8.05 | CX59: 2181.1 | CY59: 752.25 | CZ59: 36.75 | DA59: 1.85 | DB59: 208.55 | DC59: 237.45 | DD59: 0 | DE59: 2242.7 | DF59: 26.1 | DG59: 37.45 | DH59: 94.5 | DI59: 466.1 | DJ59: 138.1 | DK59: 308.15 | DL59: 64.95 | DM59: 422.35 | DN59: 143.05 | DO59: 176.7 | DP59: 505.4 | DQ59: 1576.5 | DR59: 141.8 | DS59: 52.75 | DT59: 244.05 | DU59: 60.45 | DV59: 0 | DW59: 159.65 | DX59: 158.1 | DY59: 340.3 | DZ59: 385.6 | EA59: 265.35 | EB59: 209.7 | EC59: 694.3 | ED59: 402.58446 | EE59: 1518.0742 | EF59: 1870.0815 | EG59: 192.36828 | EH59: 43.120915 | EI59: 211.065 | EJ59: 326.65 | EK59: 97.4 | EL59: 199.95 | EM59: 489.6 | EN59: 489.6 | EO59: 480 | EP59: 39.965 | EQ59: 2699.45 | ER59: 136.1 | ES59: 1510.1 | ET59: 13.65 | EU59: 1661.25 | EV59: 1696.5 | EW59: 1180.05 | EX59: 69.6 | EY59: 50.2 | EZ59: 28.8 | FA59: 28.8 | FB59: 133.5 | FC59: 98.4 | FD59: 470.6 | FE59: 214.6 | FF59: 657.65 | FG59: 825.25 | FH59: 419.65 | FI59: 479.3 | FJ59: 198.6195 | FK59: 265.65 | FL59: 483.75 | FM59: 178977.8 | FO59: 420.37673 | FP59: 68.1815 | FQ59: 272.23575 | FR59: 221.6 | FS59: 635.19808 | FT59: 397.31367 | FU59: 4.9 | FV59: 171.85 | FW59: 2191.6557

Sheet REACTIVA
B3: martes, 16 de Diciembre del 2025
A5: POTENCIA REACTIVA EJECUTADA DE LAS UNIDADES DE GENERACIÓN DEL COES (MVAR) | FO5: CENTRALES NO INTEGRANTES COES
A6: FECHA | B6: HORA | C6: 65333 | D6: 101 | E6: 102 | F6: 42667 | G6: 42668 | H6: 126 | I6: 127 | J6: 138 | K6: 139 | L6: 197 | M6: 203 | N6: 204 | O6: 230 | P6: 209 | Q6: 56677 | R6: 796 | S6: 2146 | T6: 142 | U6: 143 | V6: 125 | W6: 187 | X6: 163 | Y6: 298 | Z6: 299 | AA6: 219 | AB6: 151 | AC6: 152 | AD6: 153 | AE6: 154 | AF6: 756 | AG6: 156 | AH6: 155 | AI6: 182 | AJ6: 212 | AK6: 758 | AL6: 263 | AM6: 265 | AN6: 775 | AO6: 777 | AP6: 2154 | AQ6: 150 | AR6: 149 | AS6: 188 | AT6: 2131 | AU6: 755 | AV6: 252 | AW6: 249 | AX6: 250 | AY6: 117 | AZ6: 119 | BA6: 120 | BB6: 189 | BC6: 122 | BD6: 266 | BE6: 337 | BF6: 338 | BG6: 251 | BH6: 115 | BI6: 239 | BJ6: 288 | BK6: 240 | BL6: 241 | BM6: 242 | BN6: 191 | BO6: 194 | BP6: 196 | BQ6: 207 | BR6: 236 | BS6: 795 | BT6: 285 | BU6: 995 | BV6: 996 | BW6: 997 | BX6: 766 | BY6: 926 | BZ6: 924 | CA6: 121 | CB6: 103 | CC6: 104 | CD6: 106 | CE6: 105 | CF6: 107 | CG6: 110 | CH6: 109 | CI6: 144 | CJ6: 113 | CK6: 114 | CL6: 193 | CM6: 208 | CN6: 786 | CO6: 787 | CP6: 788 | CQ6: 789 | CR6: 248 | CS6: 2159 | CT6: 267 | CU6: 268 | CV6: 2194 | CW6: 303 | CX6: 59715 | CY6: 62255 | CZ6: 1263 | DA6: 61800 | DB6: 69125 | DC6: 216 | DD6: 198 | DE6: 70400 | DF6: 49607 | DG6: 214 | DH6: 260 | DI6: 2152 | DJ6: 2128 | DK6: 247 | DL6: 228 | DM6: 2135 | DN6: 261 | DO6: 237 | DP6: 253 | DQ6: 770 | DR6: 235 | DS6: 238 | DT6: 2184 | DU6: 61855 | DV6: 223 | DW6: 226 | DX6: 201 | DY6: 258 | DZ6: 259 | EA6: 920 | EB6: 257 | EC6: 256 | ED6: 2148 | EE6: 58288 | EF6: 58289 | EG6: 58839 | EH6: 58840 | EI6: 75260 | EJ6: 296 | EK6: 297 | EL6: 211 | EM6: 2175 | EN6: 2178 | EO6: 2181 | EP6: 1262 | EQ6: 63425 | ER6: 233 | ES6: 2150 | ET6: 2165 | EU6: 2161 | EV6: 61197 | EW6: 58851 | EX6: 225 | EY6: 2201 | EZ6: 2171 | FA6: 760 | FB6: 234 | FC6: 215 | FD6: 917 | FE6: 289 | FF6: 58333 | FG6: 58336 | FH6: 213 | FI6: 232 | FJ6: 2190 | FK6: 69867 | FL6: 75066 | FM6: TOTAL COES | FO6: 221 | FP6: 222 | FQ6: 224 | FR6: 2187 | FS6: 227 | FT6: 49400 | FU6: 199 | FV6: 200 | FW6: TOTAL NO COES
C7: SUR | D7: CENTRO | E7: CENTRO | F7: NORTE | G7: NORTE | H7: NORTE | I7: NORTE | J7: CENTRO | K7: CENTRO | L7: CENTRO | M7: CENTRO | N7: CENTRO | O7: CENTRO | P7: CENTRO | Q7: CENTRO | R7: CENTRO | S7: CENTRO | T7: CENTRO | U7: CENTRO | V7: CENTRO | W7: CENTRO | X7: SUR | Y7: SUR | Z7: SUR | AA7: CENTRO | AB7: SUR | AC7: SUR | AD7: SUR | AE7: SUR | AF7: SUR | AG7: SUR | AH7: SUR | AI7: SUR | AJ7: CENTRO | AK7: NORTE | AL7: NORTE | AM7: NORTE | AN7: CENTRO | AO7: CENTRO | AP7: CENTRO | AQ7: CENTRO | AR7: CENTRO | AS7: CENTRO | AT7: CENTRO | AU7: SUR | AV7: CENTRO | AW7: CENTRO | AX7: CENTRO | AY7: CENTRO | AZ7: CENTRO | BA7: CENTRO | BB7: SUR | BC7: NORTE | BD7: CENTRO | BE7: CENTRO | BF7: CENTRO | BG7: CENTRO | BH7: NORTE | BI7: NORTE | BJ7: NORTE | BK7: SUR | BL7: SUR | BM7: SUR | BN7: CENTRO | BO7: CENTRO | BP7: CENTRO | BQ7: CENTRO | BR7: CENTRO | BS7: CENTRO | BT7: CENTRO | BU7: SUR | BV7: SUR | BW7: SUR | BX7: NORTE | BY7: SUR | BZ7: CENTRO | CA7: NORTE | CB7: CENTRO | CC7: CENTRO | CD7: CENTRO | CE7: CENTRO | CF7: CENTRO | CG7: CENTRO | CH7: CENTRO | CI7: CENTRO | CJ7: CENTRO | CK7: CENTRO | CL7: CENTRO | CM7: CENTRO | CN7: SUR | CO7: SUR | CP7: SUR | CQ7: SUR | CR7: CENTRO | CS7: CENTRO | CT7: CENTRO | CU7: CENTRO | CV7: NORTE | CW7: CENTRO | CX7: CENTRO | CY7: SUR | CZ7: NORTE | DA7: NORTE | DB7: CENTRO | DC7: NORTE | DD7: NORTE | DE7: SUR | DF7: SUR | DG7: CENTRO | DH7: CENTRO | DI7: CENTRO | DJ7: NORTE | DK7: NORTE | DL7: CENTRO | DM7: CENTRO | DN7: SUR | DO7: SUR | DP7: CENTRO | DQ7: CENTRO | DR7: SUR | DS7: CENTRO | DT7: CENTRO | DU7: NORTE | DV7: CENTRO | DW7: CENTRO | DX7: NORTE | DY7: CENTRO | DZ7: CENTRO | EA7: CENTRO | EB7: NORTE | EC7: NORTE | ED7: SUR | EE7: CENTRO | EF7: CENTRO | EG7: CENTRO | EH7: CENTRO | EJ7: CENTRO | EK7: CENTRO | EL7: SUR | EM7: SUR | EN7: SUR | EO7: SUR | EP7: NORTE | EQ7: SUR | ER7: SUR | ES7: SUR | ET7: CENTRO | EU7: CENTRO | EV7: CENTRO | EW7: SUR | EX7: CENTRO | EY7: CENTRO | EZ7: CENTRO | FA7: CENTRO | FB7: SUR | FC7: NORTE | FD7: CENTRO | FE7: NORTE | FF7: NORTE | FG7: NORTE | FH7: CENTRO | FI7: NORTE | FJ7: NORTE | FK7: NORTE | FO7: NORTE | FP7: CENTRO | FQ7: NORTE | FR7: NORTE | FS7: NORTE | FT7: NORTE | FU7: NORTE | FV7: NORTE
C8: HIDROELÉCTRICA | D8: HIDROELÉCTRICA | E8: HIDROELÉCTRICA | F8: TERMOELÉCTRICA | G8: TERMOELÉCTRICA | H8: HIDROELÉCTRICA | I8: HIDROELÉCTRICA | J8: TERMOELÉCTRICA | K8: TERMOELÉCTRICA | L8: TERMOELÉCTRICA | M8: TERMOELÉCTRICA | N8: TERMOELÉCTRICA | O8: TERMOELÉCTRICA | P8: TERMOELÉCTRICA | Q8: TERMOELÉCTRICA | R8: HIDROELÉCTRICA | S8: HIDROELÉCTRICA | T8: TERMOELÉCTRICA | U8: TERMOELÉCTRICA | V8: TERMOELÉCTRICA | W8: TERMOELÉCTRICA | X8: HIDROELÉCTRICA | Y8: HIDROELÉCTRICA | Z8: HIDROELÉCTRICA | AA8: TERMOELÉCTRICA | AB8: HIDROELÉCTRICA | AC8: HIDROELÉCTRICA | AD8: HIDROELÉCTRICA | AE8: HIDROELÉCTRICA | AF8: TERMOELÉCTRICA | AG8: TERMOELÉCTRICA | AH8: TERMOELÉCTRICA | AI8: HIDROELÉCTRICA | AJ8: HIDROELÉCTRICA | AK8: TERMOELÉCTRICA | AL8: TERMOELÉCTRICA | AM8: TERMOELÉCTRICA | AN8: HIDROELÉCTRICA | AO8: HIDROELÉCTRICA | AP8: HIDROELÉCTRICA | AQ8: HIDROELÉCTRICA | AR8: HIDROELÉCTRICA | AS8: HIDROELÉCTRICA | AT8: HIDROELÉCTRICA | AU8: HIDROELÉCTRICA | AV8: TERMOELÉCTRICA | AW8: TERMOELÉCTRICA | AX8: TERMOELÉCTRICA | AY8: HIDROELÉCTRICA | AZ8: HIDROELÉCTRICA | BA8: HIDROELÉCTRICA | BB8: HIDROELÉCTRICA | BC8: HIDROELÉCTRICA | BD8: HIDROELÉCTRICA | BE8: HIDROELÉCTRICA | BF8: HIDROELÉCTRICA | BG8: HIDROELÉCTRICA | BH8: TERMOELÉCTRICA | BI8: TERMOELÉCTRICA | BJ8: TERMOELÉCTRICA | BK8: TERMOELÉCTRICA | BL8: TERMOELÉCTRICA | BM8: TERMOELÉCTRICA | BN8: HIDROELÉCTRICA | BO8: TERMOELÉCTRICA | BP8: TERMOELÉCTRICA | BQ8: TERMOELÉCTRICA | BR8: TERMOELÉCTRICA | BS8: TERMOELÉCTRICA | BT8: TERMOELÉCTRICA | BU8: TERMOELÉCTRICA | BV8: TERMOELÉCTRICA | BW8: TERMOELÉCTRICA | BX8: HIDROELÉCTRICA | BY8: TERMOELÉCTRICA | BZ8: TERMOELÉCTRICA | CA8: HIDROELÉCTRICA | CB8: HIDROELÉCTRICA | CC8: HIDROELÉCTRICA | CD8: HIDROELÉCTRICA | CE8: HIDROELÉCTRICA | CF8: HIDROELÉCTRICA | CG8: TERMOELÉCTRICA | CH8: TERMOELÉCTRICA | CI8: TERMOELÉCTRICA | CJ8: TERMOELÉCTRICA | CK8: TERMOELÉCTRICA | CL8: TERMOELÉCTRICA | CM8: TERMOELÉCTRICA | CN8: TERMOELÉCTRICA | CO8: TERMOELÉCTRICA | CP8: TERMOELÉCTRICA | CQ8: TERMOELÉCTRICA | CR8: TERMOELÉCTRICA | CS8: TERMOELÉCTRICA | CT8: HIDROELÉCTRICA | CU8: HIDROELÉCTRICA | CV8: HIDROELÉCTRICA | CW8: SOLAR | CX8: EÓLICA | CY8: SOLAR | CZ8: EÓLICA | DA8: SOLAR | DB8: HIDROELÉCTRICA | DC8: HIDROELÉCTRICA | DD8: HIDROELÉCTRICA | DE8: SOLAR | DF8: HIDROELÉCTRICA | DG8: HIDROELÉCTRICA | DH8: HIDROELÉCTRICA | DI8: HIDROELÉCTRICA | DJ8: HIDROELÉCTRICA | DK8: HIDROELÉCTRICA | DL8: HIDROELÉCTRICA | DM8: HIDROELÉCTRICA | DN8: SOLAR | DO8: SOLAR | DP8: EÓLICA | DQ8: EÓLICA | DR8: SOLAR | DS8: HIDROELÉCTRICA | DT8: HIDROELÉCTRICA | DU8: HIDROELÉCTRICA | DV8: HIDROELÉCTRICA | DW8: HIDROELÉCTRICA | DX8: HIDROELÉCTRICA | DY8: HIDROELÉCTRICA | DZ8: HIDROELÉCTRICA | EA8: HIDROELÉCTRICA | EB8: EÓLICA | EC8: EÓLICA | ED8: SOLAR | EE8: EÓLICA | EF8: EÓLICA | EG8: EÓLICA | EH8: EÓLICA | EI8: SOLAR | EJ8: HIDROELÉCTRICA | EK8: HIDROELÉCTRICA | EL8: HIDROELÉCTRICA | EM8: HIDROELÉCTRICA | EN8: HIDROELÉCTRICA | EO8: HIDROELÉCTRICA | EP8: EÓLICA | EQ8: SOLAR | ER8: SOLAR | ES8: SOLAR | ET8: HIDROELÉCTRICA | EU8: EÓLICA | EV8: EÓLICA | EW8: SOLAR | EX8: TERMOELÉCTRICA | EY8: TERMOELÉCTRICA | EZ8: TERMOELÉCTRICA | FA8: TERMOELÉCTRICA | FB8: SOLAR | FC8: HIDROELÉCTRICA | FD8: HIDROELÉCTRICA | FE8: TERMOELÉCTRICA | FF8: TERMOELÉCTRICA | FG8: TERMOELÉCTRICA | FH8: TERMOELÉCTRICA | FI8: TERMOELÉCTRICA | FJ8: TERMOELÉCTRICA | FK8: TERMOELÉCTRICA | FL8: TERMOELÉCTRICA | FO8: HIDROELÉCTRICA | FP8: HIDROELÉCTRICA | FQ8: HIDROELÉCTRICA | FR8: HIDROELÉCTRICA | FS8: TERMOELÉCTRICA | FT8: TERMOELÉCTRICA | FU8: HIDROELÉCTRICA | FV8: HIDROELÉCTRICA
C9: HYDRO GLOBAL PERÚ S.A.C. | D9: ELECTROPERU | E9: ELECTROPERU | F9: ELECTROPERU | G9: ELECTROPERU | H9: ORAZUL ENERGY PERÚ | I9: ORAZUL ENERGY PERÚ | J9: TERMOSELVA | K9: TERMOSELVA | L9: KALLPA GENERACION S.A. | M9: KALLPA GENERACION S.A. | N9: KALLPA GENERACION S.A. | O9: KALLPA GENERACION S.A. | P9: KALLPA GENERACION S.A. | Q9: KALLPA GENERACION S.A. | R9: KALLPA GENERACION S.A. | S9: KALLPA GENERACION S.A. | T9: SHOUGESA | U9: SHOUGESA | V9: SHOUGESA | W9: SHOUGESA | X9: EGEMSA | Y9: EGESUR | Z9: EGESUR | AA9: EGESUR | AB9: EGASA | AC9: EGASA | AD9: EGASA | AE9: EGASA | AF9: EGASA | AG9: EGASA | AH9: EGASA | AI9: SAN GABAN | AJ9: CELEPSA | AK9: MINERA CERRO VERDE | AL9: PLANTA DE RESERVA FRIA DE GENERACION DE ETEN S.A. | AM9: PLANTA DE RESERVA FRIA DE GENERACION DE ETEN S.A. | AN9: EMPRESA DE GENERACION HUALLAGA | AO9: EMPRESA DE GENERACION HUALLAGA | AP9: LA VIRGEN | AQ9: CHINANGO S.A.C. | AR9: CHINANGO S.A.C. | AS9: HIDROELECTRICA HUANCHOR S.A.C. | AT9: CELEPSA RENOVABLES S.R.L. | AU9: INLAND ENERGY SAC | AV9: FENIX POWER PERÚ | AW9: FENIX POWER PERÚ | AX9: FENIX POWER PERÚ | AY9: STATKRAFT S.A | AZ9: STATKRAFT S.A | BA9: STATKRAFT S.A | BB9: STATKRAFT S.A | BC9: STATKRAFT S.A | BD9: STATKRAFT S.A | BE9: CENTRALES SANTA ROSA S.A.C. | BF9: CENTRALES SANTA ROSA S.A.C. | BG9: EMPRESA DE GENERACION HUANZA | BH9: ENEL GENERACION PIURA S.A. | BI9: ENEL GENERACION PIURA S.A. | BJ9: ENEL GENERACION PIURA S.A. | BK9: ENGIE ENERGIA PERU S.A.A. | BL9: ENGIE ENERGIA PERU S.A.A. | BM9: ENGIE ENERGIA PERU S.A.A. | BN9: ENGIE ENERGIA PERU S.A.A. | BO9: ENGIE ENERGIA PERU S.A.A. | BP9: ENGIE ENERGIA PERU S.A.A. | BQ9: ENGIE ENERGIA PERU S.A.A. | BR9: ENGIE ENERGIA PERU S.A.A. | BS9: ENGIE ENERGIA PERU S.A.A. | BT9: ENGIE ENERGIA PERU S.A.A. | BU9: ENGIE ENERGIA PERU S.A.A. | BV9: ENGIE ENERGIA PERU S.A.A. | BW9: ENGIE ENERGIA PERU S.A.A. | BX9: ENGIE ENERGIA PERU S.A.A. | BY9: INFRAESTRUCTURAS Y ENERGIAS DEL PERU S.A.C. | BZ9: INFRAESTRUCTURAS Y ENERGIAS DEL PERU S.A.C. | CA9: INVERSIONES SHAQSHA S.A.C. | CB9: ORYGEN PERU S.A.A. | CC9: ORYGEN PERU S.A.A. | CD9: ORYGEN PERU S.A.A. | CE9: ORYGEN PERU S.A.A. | CF9: ORYGEN PERU S.A.A. | CG9: ORYGEN PERU S.A.A. | CH9: ORYGEN PERU S.A.A. | CI9: ORYGEN PERU S.A.A. | CJ9: ORYGEN PERU S.A.A. | CK9: ORYGEN PERU S.A.A. | CL9: ORYGEN PERU S.A.A. | CM9: ORYGEN PERU S.A.A. | CN9: SAMAY I S.A.C | CO9: SAMAY I S.A.C | CP9: SAMAY I S.A.C | CQ9: SAMAY I S.A.C | CR9: TERMOCHILCA S.A.C. | CS9: TERMOCHILCA S.A.C. | CT9: TRANSMISION ANDINA DE GENERACION S.A.C. | CU9: TRANSMISION ANDINA DE GENERACION S.A.C. | CV9: CELARIS ENERGY S.A. | CW9: COLCA SOLAR S.A.C. | CX9: ENERGIA RENOVABLE DEL SUR S.A. | CY9: GR CORTARRAMA SOCIEDAD ANONIMA CERRADA | CZ9: GR TARUCA SOCIEDAD ANONIMA CERRADA | DA9: KONDU SAC | DB9: VARI ENERGIA S.A.C. | DC9: ORAZUL ENERGY PERÚ | DD9: ORAZUL ENERGY PERÚ | DE9: KALLPA GENERACION S.A. | DF9: SAN GABAN | DG9: MAJA ENERGIA S.A.C. | DH9: EMPRESA DE GENERACION ELECTRICA CANCHAYLLO SAC | DI9: EMPRESA DE GENERACION ELECTRICA SANTA ANA S.A.C. | DJ9: EMPRESA ELECTRICA AGUA AZUL | DK9: EMPRESA ELECTRICA RIO DOBLE | DL9: HIDROCAÑETE S.A. | DM9: HUAURA POWER GROUP S.A. | DN9: MOQUEGUA FV S.A.C. | DO9: PANAMERICANA SOLAR SAC. | DP9: PARQUE EOLICO MARCONA S.A.C. | DQ9: PARQUE EOLICO TRES HERMANAS S.A.C. | DR9: TACNA SOLAR SAC. | DS9: ELECTRICA YANAPAMPA SAC | DT9: ANDEAN POWER S.A.C. | DU9: ASOCIACIÓN SANTA LUCIA DE CHACAS | DV9: ATRIA ENERGIA S.A.C. | DW9: EGEJUNIN | DX9: EGEJUNIN | DY9: EGEJUNIN | DZ9: EGEJUNIN | EA9: EMPRESA DE GENERACION ELECTRICA RIO BAÑOS S.A.C. | EB9: ENERGÍA EÓLICA S.A. | EC9: ENERGÍA EÓLICA S.A. | ED9: ENGIE ENERGIA PERU S.A.A. | EE9: ENGIE ENERGIA PERU S.A.A. | EF9: ENGIE ENERGIA PERU S.A.A. | EG9: ENGIE ENERGIA PERU S.A.A. | EH9: ENGIE ENERGIA PERU S.A.A. | EI9: ENGIE ENERGIA PERU S.A.A. | EJ9: GENERACIÓN ANDINA S.A.C. | EK9: GENERACIÓN ANDINA S.A.C. | EL9: GENERADORA DE ENERGÍA DEL PERÚ | EM9: GENERADORA DE ENERGÍA DEL PERÚ | EN9: GENERADORA DE ENERGÍA DEL PERÚ | EO9: GENERADORA DE ENERGÍA DEL PERÚ | EP9: GR PAINO SOCIEDAD ANONIMA CERRADA | EQ9: JOYA SOLAR S.A.C. | ER9: MAJES ARCUS S.A.C. | ES9: ORYGEN PERU S.A.A. | ET9: ORYGEN PERU S.A.A. | EU9: ORYGEN PERU S.A.A. | EV9: ORYGEN PERU S.A.A. | EW9: ORYGEN PERU S.A.A. | EX9: PETRAMAS | EY9: PETRAMAS | EZ9: PETRAMAS | FA9: PETRAMAS | FB9: REPARTICIÓN ARCUS S.A.C. | FC9: SINERSA | FD9: SINERSA | FE9: BIOENERGIA DEL CHIRA S.A. | FF9: GM OPERACIONES S.A.C. | FG9: GM OPERACIONES S.A.C. | FH9: AGRO INDUSTRIAL PARAMONGA S.A. | FI9: AGROAURORA S.A.C. | FJ9: AGROINDUSTRIAS SAN JACINTO S.A.A. | FK9: AGROLMOS SOCIEDAD ANONIMA - AGROLMOS S.A. | FL9: CASA GRANDE S.A.A. | FO9: UNACEM PERU S.A. | FP9: ELECTRO ORIENTE | FQ9: AGUAS Y ENERGIA PERU | FR9: ELECTRO ZAÑA S.A.C. | FS9: ELECTRONOROESTE S.A. | FT9: SDE PIURA | FU9: SINERSA | FV9: SINERSA
C10: SAN GABAN III | D10: MANTARO | E10: RESTITUCION | F10: TUMBES MAK 1 | G10: TUMBES MAK 2 | H10: CARHUAQUERO | I10: CAÑON DEL PATO | J10: AGUAYTIA TG1 | K10: AGUAYTIA TG2 | L10: KALLPA TG1 | M10: KALLPA TG2 | N10: KALLPA TG3 | O10: KALLPA TV | P10: LFLORES TG1 | Q10: LFLORES TV | R10: CERRO DEL AGUILA | S10: CERRODELAGUILAG4 | T10: SHOUGESA TV1 | U10: SHOUGESA TV2 | V10: SHOUGESA TV3 | W10: SHOUGESA CUMMINS | X10: MACHUPICCHU | Y10: ARICOTA 1 | Z10: ARICOTA 2 | AA10: INDEPENDENCIA | AB10: CHARCANI I,II,III | AC10: CHARCANI IV | AD10: CHARCANI V | AE10: CHARCANI VI | AF10: CHILINA TG | AG10: MOLLENDO 1, 2, 3 | AH10: CHILINA (SULZ 1,2) | AI10: SAN GABAN II | AJ10: PLATANAL | AK10: RECKA | AL10: RF ETEN TG1 | AM10: RF ETEN TG2 | AN10: CHAGLLA GP1 | AO10: CHAGLLA | AP10: LA VIRGEN | AQ10: CHIMAY | AR10: YANANGO | AS10: HUANCHOR | AT10: MARAÑON | AU10: STA TERESA | AV10: FENIX GT11 | AW10: FENIX GT12 | AX10: FENIX TV10 | AY10: YAUPI | AZ10: MALPASO | BA10: CAHUA | BB10: ARCATA | BC10: GALLITO CIEGO | BD10: CHEVES | BE10: SANTA ROSA 1 | BF10: SANTA ROSA 2 | BG10: HUANZA | BH10: MALACAS2 TG4 | BI10: MALACAS3 TG 5 | BJ10: MALACAS1 TG6 | BK10: RF ILO2 TG1 | BL10: RF ILO2 TG2 | BM10: RF ILO2 TG3 | BN10: YUNCAN | BO10: CHILCA1 TG1 | BP10: CHILCA1 TG2 | BQ10: CHILCA1 TG3 | BR10: CHILCA-TV | BS10: CHILCA2 TG41 | BT10: CHILCA2-TV | BU10: CTNEPI_TG41 | BV10: CTNEPI_TG42 | BW10: CTNEPI_TG43 | BX10: QUITARACSA | BY10: RF PTO MALDONADO | BZ10: RF PUCALLPA | CA10: PARIAC | CB10: HUINCO | CC10: MATUCANA | CD10: MOYOPAMPA | CE10: CALLAHUANCA | CF10: HUAMPANI | CG10: STA ROSA WEST TG7 | CH10: UTI_5 | CI10: UTI_6 | CJ10: VENTANILLA 3 | CK10: VENTANILLA 4 | CL10: VENTANILLA TV | CM10: STAROSA TG8 | CN10: PTO_BRVO TG1 | CO10: PTO_BRVO TG2 | CP10: PTO_BRVO TG3 | CQ10: PTO_BRVO TG4 | CR10: OLLEROS TG1 | CS10: OLLEROS TV | CT10: OROYA | CU10: PACHACHACA | CV10: MANTA I | CW10: CS YARUCAYA | CX10: SAN JUAN | CY10: MATARANI | CZ10: DUNA | DA10: CARHUAQUERO (CS) | DB10: ANASHIRONI | DC10: CARHUAQUERO4 | DD10: CAÑA BRAVA | DE10: SUNNY | DF10: TUPURI | DG10: RONCADOR | DH10: CANCHAYLLO | DI10: RENOVANDESH1 | DJ10: POTRERO | DK10: PIZARRAS | DL10: NIMPERIAL | DM10: YARUCAYA | DN10: MOQUEGUA-SOLAR | DO10: PANAMERICANA-SOLAR | DP10: PQE-EOLICO-MARCONA | DQ10: PQE-EOLICO-3-HERMANAS | DR10: TACNA-SOLAR | DS10: YANAPAMPA | DT10: CARHUAC | DU10: HUALLIN | DV10: PURMACANA | DW10: HUASAHUASI | DX10: STACRUZ_1_2 | DY10: RUNATULLO_II | DZ10: RUNATULLO_III | EA10: RUCUY | EB10: PQE-EOLICO-TALARA | EC10: PQE-EOLICO-CUPISNIQUE | ED10: INTIPAMPA | EE10: PUNTA LOMITAS-BL1 | EF10: PUNTA LOMITAS-BL2 | EG10: PUN LOMITAS_EXP-BL1 | EH10: PUN LOMITAS_EXP-BL2 | EI10: EXPANSIÓN INTIPAMPA | EJ10: 8AGOSTO | EK10: EL CARMEN | EL10: LA JOYA | EM10: ANGEL_I | EN10: ANGEL_II | EO10: ANGEL_III | EP10: HUAMBOS | EQ10: SAN MARTIN SOLAR | ER10: MAJES | ES10: RUBI | ET10: CH_HER1 | EU10: WAYRA-I | EV10: WAYRA EXTENSION | EW10: CLEMESI | EX10: HUAYCOLORO | EY10: CALLAO | EZ10: DONA_CATALINA | FA10: LAGRINGAV | FB10: REPARTICION | FC10: POECHOS2 | FD10: CHANCAY | FE10: CANA BRAVA | FF10: REFINERIA TALARA TV1 | FG10: REFINERÍA TALARA TV2 | FH10: PARAMONGA | FI10: MAPLE | FJ10: SAN_JACINTO | FK10: AGROLMOS | FL10: CASA GRANDE | FM10: MVAR | FO10: CARPAPATA | FP10: CENTRALES ELOR | FQ10: PIAS1 | FR10: ZANA | FS10: TABLAZO | FT10: TALLANCA | FU10: CURUMUY | FV10: POECHOS1 | FW10: MVAR
A11: 16/12/2025 | B11: 00:30 | C11: 37 | D11: -48.4 | E11: 9.4 | H11: -16.6 | I11: 11.8 | J11: 0 | L11: -0.7 | M11: -3.4 | N11: 19.7 | P11: 16.7 | R11: 32.3 | S11: -0.1 | X11: 0 | Y11: 1.1 | AA11: 2.8 | AB11: -3.4 | AC11: 3.2 | AD11: 4.7 | AI11: 2.6 | AJ11: 0 | AN11: -1.8 | AO11: -23.6 | AP11: 3.5 | AQ11: 15.7 | AR11: 2.1 | AS11: 0.9 | AT11: 2.3 | AU11: 0.2 | AV11: 13.9 | AW11: -5.1 | AX11: -47.5 | AY11: 0.3 | AZ11: 0 | BA11: -0.9 | BB11: 0.9 | BC11: 0.7 | BD11: 15.7 | BG11: -1.2 | BJ11: -5.1 | BN11: -0.7 | BO11: -27.1 | BP11: -28.1 | BQ11: -8.3 | BR11: -7.3 | BS11: 5.2 | BT11: -4.6 | CB11: 20.7 | CC11: 20.4 | CD11: 3 | CE11: 1.1 | CF11: 1.9 | CG11: -16.7 | CH11: 0 | CI11: 0 | CJ11: 10.9 | CK11: 13.9 | CL11: -18.3 | CR11: -11.3 | CS11: -9.3 | CT11: -0.8 | CU11: -0.1 | CV11: 0.4 | CX11: -11.7 | CY11: 0 | CZ11: 0 | DB11: 0 | DC11: -0.1 | DE11: 0 | DG11: 0.1 | DH11: 1.2 | DI11: 0.2 | DJ11: -1 | DK11: 0.2 | DL11: 0.5 | DN11: 0 | DO11: 0 | DP11: 1.7 | DQ11: 4.6 | DR11: 0 | DS11: 0 | DT11: 0.4 | DU11: 0.5 | DW11: -1.8 | DX11: 0.5 | DY11: 0.5 | DZ11: 0.5 | EA11: 0.3 | EB11: 0 | EC11: 1.5 | ED11: 0 | EE11: -4.8 | EF11: -4.6 | EG11: 0 | EH11: 0.2 | EJ11: 1.5 | EK11: 0 | EL11: 1.5 | EM11: 0.2 | EN11: 0.2 | EO11: 0.2 | EQ11: 0 | ER11: 0 | ES11: 0 | ET11: -0.2 | EU11: -4 | EV11: 0 | EW11: 0 | EX11: 1.4 | EY11: 0.7 | EZ11: 0.4 | FA11: 0.5 | FB11: 0 | FC11: 0.4 | FD11: 0.8 | FE11: 2.5 | FF11: 12.4 | FG11: 0 | FH11: 2.4 | FI11: 1.1 | FJ11: 3.3 | FK11: 3.6 | FM11: 2.4 | FO11: 2.35378 | FP11: 0 | FQ11: 2.66 | FR11: 1.3 | FS11: 0.2809 | FT11: 0.11979 | FU11: 0 | FV11: 1 | FW11: 7.71447
A12: 16/12/2025 | B12: 01:00 | C12: 38 | D12: -59 | E12: 7.4 | H12: -12.5 | I12: 10.8 | J12: 0 | L12: -1.5 | M12: 0.4 | N12: 23.6 | P12: 15.4 | R12: 28.5 | S12: 0.1 | X12: 1.2 | Y12: 1.2 | AA12: 2.8 | AB12: -3.4 | AC12: 3.2 | AD12: 4.8 | AI12: 3 | AJ12: 0 | AN12: -1 | AO12: -23.3 | AP12: 2.1 | AQ12: 7.9 | AR12: 1.9 | AS12: 0.6 | AT12: 2.3 | AU12: 0.6 | AV12: 10.5 | AW12: -8.7 | AX12: -50.8 | AY12: 1.9 | AZ12: 0 | BA12: -0.1 | BB12: 0.9 | BC12: 0.5 | BD12: 16.9 | BG12: -2.6 | BJ12: -6.2 | BN12: -2.1 | BO12: -28.4 | BP12: -29.4 | BQ12: -9.8 | BR12: -8.8 | BS12: 4.5 | BT12: -5 | CB12: 30.4 | CC12: 20.2 | CD12: 2.6 | CE12: 0.9 | CF12: 1.8 | CG12: -19.1 | CH12: 0 | CI12: 0 | CJ12: 6.5 | CK12: 9.5 | CL12: -24.5 | CR12: -13.6 | CS12: -10.7 | CT12: -0.9 | CU12: -0.2 | CV12: 0.4 | CX12: -12.1 | CY12: 0 | CZ12: 0 | DB12: 0 | DC12: -0.1 | DE12: 0 | DG12: 0.1 | DH12: 0.9 | DI12: 0.2 | DJ12: -0.8 | DK12: 0.2 | DL12: 0.5 | DN12: 0 | DO12: 0 | DP12: 1.5 | DQ12: 4.4 | DR12: 0 | DS12: -0.1 | DT12: 0.4 | DU12: 0.5 | DW12: -1.8 | DX12: 0.4 | DY12: 0.5 | DZ12: 0.5 | EA12: 0.3 | EB12: 0 | EC12: 1.5 | ED12: 0 | EE12: -2 | EF12: -2.3 | EG12: 0 | EH12: 0.4 | EJ12: 1.5 | EK12: 0 | EL12: 1.7 | EM12: 0.2 | EN12: 0.2 | EO12: 0.2 | EQ12: 0 | ER12: 0 | ES12: 0 | ET12: -0.2 | EU12: -0.3 | EV12: 0 | EW12: 0 | EX12: 1.4 | EY12: 0.7 | EZ12: 0.4 | FA12: 0.5 | FB12: 0 | FC12: 0.4 | FD12: 0.8 | FE12: 2.4 | FF12: 11.8 | FG12: 0.5 | FH12: 2.5 | FI12: 0.9 | FJ12: 3.3 | FK12: 3.5 | FM12: -32.8 | FO12: 2.04899 | FP12: 0 | FQ12: 2.75 | FR12: 1.2 | FS12: 0.28241 | FT12: 0.15988 | FU12: 0 | FV12: 1 | FW12: 7.44128
A13: 16/12/2025 | B13: 01:30 | C13: 37.4 | D13: -67.7 | E13: 5.5 | H13: -13.7 | I13: 2.3 | J13: 0 | L13: -6 | M13: -4.3 | N13: 18.8 | P13: 11.9 | R13: 21.7 | S13: 0.2 | X13: 0.4 | Y13: 1.1 | AA13: 2.8 | AB13: -3.4 | AC13: 3 | AD13: 4.6 | AI13: 1.9 | AJ13: 0 | AN13: -1.1 | AO13: -24.7 | AP13: 2.1 | AQ13: 8.7 | AR13: 2.1 | AS13: 0.6 | AT13: 2.3 | AU13: 0.2 | AV13: 5.1 | AW13: -13.8 | AX13: -46.3 | AY13: 1.2 | AZ13: 0 | BA13: -0.7 | BB13: 0.9 | BC13: 0.5 | BD13: 16.1 | BG13: -3.9 | BJ13: -4.6 | BN13: -3 | BO13: -32.9 | BP13: -33.8 | BQ13: -13.9 | BR13: -13.1 | BS13: 2.7 | BT13: -5.6 | CB13: 30.3 | CC13: 21 | CD13: 3.1 | CE13: 1.6 | CF13: 1.9 | CG13: 0 | CH13: 0 | CI13: 0 | CJ13: 1.9 | CK13: 5.1 | CL13: -31.2 | CR13: -17.2 | CS13: -12.9 | CT13: -0.9 | CU13: -0.1 | CV13: 0.4 | CX13: -12.7 | CY13: 0 | CZ13: 0 | DB13: 0.1 | DC13: -0.1 | DE13: 0 | DG13: 0 | DH13: 0.9 | DI13: 0.1 | DJ13: -0.5 | DK13: 0.2 | DL13: 0.5 | DN13: 0 | DO13: 0 | DP13: 1.4 | DQ13: 4 | DR13: 0 | DS13: -0.1 | DT13: 0.3 | DU13: 0.5 | DW13: -1.8 | DX13: 0.3 | DY13: 0.5 | DZ13: 0.3 | EA13: 0.2 | EB13: 0 | EC13: 1.5 | ED13: 0 | EE13: -4.3 | EF13: -4.4 | EG13: 0 | EH13: 0.3 | EJ13: 1.5 | EK13: 0 | EL13: 1.7 | EM13: 0.2 | EN13: 0.2 | EO13: 0.2 | EQ13: 0 | ER13: 0 | ES13: 0 | ET13: -0.2 | EU13: 2.5 | EV13: 0 | EW13: 0 | EX13: 1.4 | EY13: 0.7 | EZ13: 0.4 | FA13: 0.5 | FB13: 0 | FC13: 0.4 | FD13: 0.6 | FE13: 2.4 | FF13: 12.4 | FG13: 0.5 | FH13: 2.3 | FI13: 0.7 | FJ13: 2.9 | FK13: 3.7 | FM13: -113.2 | FO13: 1.95476 | FP13: 0 | FQ13: 2.86 | FR13: 1.2 | FS13: 0.28049 | FT13: 0.21187 | FU13: 0 | FV13: 1 | FW13: 7.50712
A14: 16/12/2025 | B14: 02:00 | C14: 38.8 | D14: -68.6 | E14: 4.9 | H14: -15.5 | I14: 2.1 | J14: 0 | L14: -6.9 | M14: -6.1 | N14: 16.7 | P14: 10.7 | R14: 14.8 | S14: 0.1 | X14: 1.4 | Y14: 1.2 | AA14: 2.8 | AB14: -3.4 | AC14: 2.8 | AD14: 4.3 | AI14: 2.2 | AJ14: 0 | AN14: -1.1 | AO14: -26.1 | AP14: 1.7 | AQ14: 8.2 | AR14: 1.9 | AS14: 0.6 | AT14: 2.1 | AU14: 0.2 | AV14: 4.6 | AW14: -14.5 | AX14: -47.5 | AY14: 0.9 | AZ14: 0 | BA14: -1 | BB14: 0.9 | BC14: 0.5 | BD14: 16.2 | BG14: -4.2 | BJ14: -5.2 | BN14: -1.2 | BO14: -34.6 | BP14: -35.6 | BQ14: -16.1 | BR14: -15.3 | BS14: 2.4 | BT14: -6.1 | CB14: 30 | CC14: 13.5 | CD14: 2.8 | CE14: 2.3 | CF14: 1.8 | CG14: 0 | CH14: 0 | CI14: 0 | CJ14: 0.4 | CK14: 3.5 | CL14: -33.5 | CR14: -19.6 | CS14: -14.4 | CT14: -0.9 | CU14: -0.2 | CV14: 0.5 | CX14: -12.9 | CY14: 0 | CZ14: 0 | DB14: 0 | DC14: 0 | DE14: 0 | DG14: 0.1 | DH14: 0.9 | DI14: 0.2 | DJ14: -0.6 | DK14: 0.2 | DL14: 0.5 | DN14: 0 | DO14: 0 | DP14: 1.4 | DQ14: 3.8 | DR14: 0 | DS14: 0 | DT14: 0.1 | DU14: 0.5 | DW14: -1.8 | DX14: 0.1 | DY14: 0.5 | DZ14: 0.3 | EA14: 0.1 | EB14: 0.5 | EC14: 1.5 | ED14: 0 | EE14: -2 | EF14: -1.7 | EG14: 0.4 | EH14: 0.8 | EJ14: 1.5 | EK14: 0 | EL14: 1.6 | EM14: 0.2 | EN14: 0.2 | EO14: 0.2 | EQ14: 0 | ER14: 0 | ES14: 0 | ET14: -0.2 | EU14: 4.6 | EV14: 0 | EW14: 0 | EX14: 1.4 | EY14: 0.7 | EZ14: 0.4 | FA14: 0.5 | FB14: 0 | FC14: 0.4 | FD14: 0.4 | FE14: 2.2 | FF14: 12.3 | FG14: 0.4 | FH14: 2 | FI14: 0.6 | FJ14: 2.2 | FK14: 3.7 | FM14: -151.6 | FO14: 1.75185 | FP14: 0 | FQ14: 2.9 | FR14: 1.2 | FS14: 0.27787 | FT14: 0.18434 | FU14: 0 | FV14: 1 | FW14: 7.31406
A15: 16/12/2025 | B15: 02:30 | C15: 38.4 | D15: -68.9 | E15: 5 | H15: -14.5 | I15: 10 | J15: 0 | L15: -6.3 | M15: -4.9 | N15: 18.9 | P15: 12.4 | R15: 7.1 | S15: 0.1 | X15: -0.2 | Y15: 1.4 | AA15: 2.8 | AB15: -3.4 | AC15: 2.9 | AD15: 4.5 | AI15: 2.3 | AJ15: 0 | AN15: -1.2 | AO15: -27.7 | AP15: 1.5 | AQ15: 8.2 | AR15: 1.9 | AS15: 0.3 | AT15: 2.2 | AU15: 0.4 | AV15: 5.7 | AW15: -13.4 | AX15: -46.1 | AY15: 0.5 | AZ15: 0 | BA15: 0.4 | BB15: 1 | BC15: 0.5 | BD15: 15.9 | BG15: -4.3 | BJ15: -4.7 | BN15: -1.4 | BO15: -31 | BP15: -32 | BQ15: -12 | BR15: -11.3 | BS15: 3.3 | BT15: -5.4 | CB15: 29.3 | CC15: 12.9 | CD15: 2.7 | CE15: 0.9 | CF15: 1.8 | CG15: 0 | CH15: 0 | CI15: 0 | CJ15: 0.6 | CK15: 3.6 | CL15: -34.2 | CR15: -18.3 | CS15: -13.6 | CT15: -0.8 | CU15: -0.2 | CV15: 0.4 | CX15: -13.2 | CY15: 0 | CZ15: 0.1 | DB15: 0 | DC15: 0 | DE15: 0 | DG15: 0 | DH15: 0.9 | DI15: 0.1 | DJ15: 0 | DK15: 0.2 | DL15: 0.5 | DN15: 0 | DO15: 0 | DP15: 1.5 | DQ15: 3.6 | DR15: 0 | DS15: 0.1 | DT15: 0 | DU15: 0.5 | DW15: -1.9 | DX15: 0.3 | DY15: 0.5 | DZ15: 0.3 | EA15: 0.2 | EB15: 1.3 | EC15: 1.5 | ED15: 0 | EE15: -2.9 | EF15: -3 | EG15: 0.1 | EH15: 0.5 | EJ15: 1.5 | EK15: 0 | EL15: 1.7 | EM15: 0.2 | EN15: 0.2 | EO15: 0.2 | EQ15: 0 | ER15: 0 | ES15: 0 | ET15: -0.2 | EU15: 4.4 | EV15: 0 | EW15: 0 | EX15: 1.4 | EY15: 0.7 | EZ15: 0.4 | FA15: 0.5 | FB15: 0 | FC15: 0.4 | FD15: 0.4 | FE15: 2.5 | FF15: 12.5 | FG15: 0.3 | FH15: 2.6 | FI15: 0.7 | FJ15: 1.6 | FK15: 3.7 | FM15: -129.1 | FO15: 1.7716 | FP15: 0 | FQ15: 2.99 | FR15: 1.2 | FS15: 0.27641 | FT15: 0.15173 | FU15: 0 | FV15: 1.1 | FW15: 7.48974
A16: 16/12/2025 | B16: 03:00 | C16: 38.6 | D16: -85.6 | E16: 0.8 | H16: -17.1 | I16: -0.2 | J16: 0 | L16: -9.1 | M16: -11.4 | N16: 11.5 | P16: 10.1 | R16: 6.6 | S16: 0 | X16: 0.5 | Y16: 1.2 | AA16: 2.8 | AB16: -3.5 | AC16: 2.8 | AD16: 4.6 | AI16: 2.6 | AJ16: 0 | AN16: -1.3 | AO16: -29.1 | AP16: 1.5 | AQ16: 7.7 | AR16: 2 | AS16: 0.5 | AT16: 2.3 | AU16: 0.3 | AV16: 4 | AW16: -15 | AX16: -47.7 | AY16: 0.1 | AZ16: 0 | BA16: -1.8 | BB16: 1 | BC16: 0.5 | BD16: 15.4 | BG16: -5.3 | BJ16: -5.3 | BN16: -1.5 | BO16: -33.6 | BP16: -34.5 | BQ16: -15.6 | BR16: -16.8 | BS16: 2.3 | BT16: -6 | CB16: 30.5 | CC16: 13.6 | CD16: 3 | CE16: 0.9 | CF16: 1.9 | CG16: 0 | CH16: 0 | CI16: 0 | CJ16: -1.5 | CK16: 1.7 | CL16: -36.5 | CR16: -21.9 | CS16: -15.7 | CT16: -0.9 | CU16: -0.2 | CV16: 0.4 | CX16: -12.6 | CY16: 0 | CZ16: 0 | DB16: 0 | DC16: 0 | DE16: 0 | DG16: 0.1 | DH16: 0.9 | DI16: 0.2 | DJ16: -0.1 | DK16: 0.2 | DL16: 0.5 | DN16: 0 | DO16: 0 | DP16: 1.6 | DQ16: 4 | DR16: 0 | DS16: 0 | DT16: 0 | DU16: 0.5 | DW16: -1.9 | DX16: 0.4 | DY16: 0.5 | DZ16: 0.3 | EA16: 0.1 | EB16: 2.5 | EC16: 1.5 | ED16: 0 | EE16: -4.5 | EF16: -4.9 | EG16: 0.2 | EH16: 0.3 | EJ16: 1.5 | EK16: 0 | EL16: 1.7 | EM16: 0.2 | EN16: 0.2 | EO16: 0.2 | EQ16: 0 | ER16: 0 | ES16: 0 | ET16: -0.2 | EU16: 4.4 | EV16: 0 | EW16: 0 | EX16: 1.4 | EY16: 0.7 | EZ16: 0.4 | FA16: 0.5 | FB16: 0 | FC16: 0.4 | FD16: 0.4 | FE16: 2.5 | FF16: 12.4 | FG16: 0.2 | FH16: 4.9 | FI16: 0.6 | FJ16: 2 | FK16: 3.6 | FM16: -217.6 | FO16: 1.71499 | FP16: 0 | FQ16: 2.53 | FR16: 1.2 | FS16: 0.27746 | FT16: 0.1874 | FU16: 0 | FV16: 1 | FW16: 6.90985
A17: 16/12/2025 | B17: 03:30 | C17: 41.3 | D17: -76.1 | E17: 2.4 | H17: -16.3 | I17: 0.9 | J17: 0 | L17: -7.1 | M17: -6.4 | N17: 16.5 | P17: 13.7 | R17: 9 | S17: 0.1 | X17: 1.3 | Y17: 1.6 | AA17: 2.8 | AB17: -3.4 | AC17: 2.8 | AD17: 5.5 | AI17: 3.5 | AJ17: 0 | AN17: -1.3 | AO17: -30.1 | AP17: 1.6 | AQ17: 8.5 | AR17: 1.9 | AS17: 0.5 | AT17: 2.4 | AU17: 1 | AV17: 5.1 | AW17: -13.8 | AX17: -46.8 | AY17: 0.2 | AZ17: 0 | BA17: -1 | BB17: 0.9 | BC17: 0.5 | BD17: 17 | BG17: -5.4 | BJ17: -5.3 | BN17: -1.6 | BO17: -29.4 | BP17: -30.4 | BQ17: -10.5 | BR17: -8.1 | BS17: 3.4 | BT17: -5.4 | CB17: 30 | CC17: 14.2 | CD17: 3 | CE17: 0.9 | CF17: 1.9 | CG17: 0 | CH17: 0 | CI17: 0 | CJ17: -1.4 | CK17: 1.9 | CL17: -36.4 | CR17: -19.2 | CS17: -14.2 | CT17: -1 | CU17: -0.2 | CV17: 0.4 | CX17: -12.4 | CY17: 0 | CZ17: 0 | DB17: 0 | DC17: 0 | DE17: 0 | DG17: 0.1 | DH17: 1 | DI17: 0.2 | DJ17: -0.8 | DK17: 0.1 | DL17: 0.5 | DN17: 0 | DO17: 0 | DP17: 1.7 | DQ17: 4.2 | DR17: 0 | DS17: -0.1 | DT17: 0 | DU17: 0.5 | DW17: -1.9 | DX17: 0.5 | DY17: 0.5 | DZ17: 0.3 | EA17: 0.1 | EB17: 4.2 | EC17: 1.5 | ED17: 0 | EE17: -2.5 | EF17: -3.5 | EG17: 0.5 | EH17: 0.4 | EJ17: 1.5 | EK17: 0 | EL17: 1.8 | EM17: 0.2 | EN17: 0.2 | EO17: 0.2 | EQ17: 0 | ER17: 0 | ES17: 0 | ET17: -0.2 | EU17: 4.1 | EV17: 0 | EW17: 0 | EX17: 1.4 | EY17: 0.7 | EZ17: 0.4 | FA17: 0.5 | FB17: 0 | FC17: 0.4 | FD17: 0.4 | FE17: 2.5 | FF17: 14.6 | FG17: 0.4 | FH17: 4.3 | FI17: 0.8 | FJ17: 1.9 | FK17: 3.7 | FM17: -139.2 | FO17: 1.69234 | FP17: 0 | FQ17: 2.51 | FR17: 1.2 | FS17: 0.27932 | FT17: 0.30044 | FU17: 0 | FV17: 1 | FW17: 6.9821
A18: 16/12/2025 | B18: 04:00 | C18: 38.3 | D18: -79.5 | E18: 2.3 | H18: -16.2 | I18: 8.6 | J18: 0 | L18: -6.7 | M18: -8.5 | N18: 15.2 | P18: 14.4 | R18: 12.5 | S18: 0.1 | X18: 0.8 | Y18: 1.7 | AA18: 2.9 | AB18: -3.4 | AC18: 2.8 | AD18: 5.5 | AI18: 2.3 | AJ18: 0 | AN18: -1.3 | AO18: -29.7 | AP18: 1.5 | AQ18: 8.3 | AR18: 1.9 | AS18: 0.6 | AT18: 2.4 | AU18: 0.3 | AV18: 6.4 | AW18: -12.5 | AX18: -45.2 | AY18: -0.3 | AZ18: 0 | BA18: -0.9 | BB18: 0.9 | BC18: 0.5 | BD18: 15.6 | BG18: -5 | BJ18: -6.2 | BN18: -2.2 | BO18: -28.4 | BP18: -29.1 | BQ18: -9.9 | BR18: -8.7 | BS18: 3.8 | BT18: -5.2 | CB18: 30 | CC18: 13.7 | CD18: 2.7 | CE18: 0.9 | CF18: 1.8 | CG18: 0 | CH18: 0 | CI18: 0 | CJ18: -0.2 | CK18: 2.8 | CL18: -34.7 | CR18: -18.5 | CS18: -13.7 | CT18: -0.8 | CU18: -0.2 | CV18: 0.4 | CX18: -12.4 | CY18: 0 | CZ18: 0 | DB18: 0 | DC18: 0 | DE18: 0 | DG18: 0.1 | DH18: 1 | DI18: 0.2 | DJ18: -0.6 | DK18: 0.2 | DL18: 0.5 | DN18: 0 | DO18: 0 | DP18: 1.8 | DQ18: 4.4 | DR18: 0 | DS18: -0.1 | DT18: 0 | DU18: 0.5 | DW18: -1.9 | DX18: 0.4 | DY18: 0.5 | DZ18: 0.3 | EA18: 0.2 | EB18: 3.5 | EC18: 1.5 | ED18: 0 | EE18: -4.1 | EF18: -3.5 | EG18: 0.3 | EH18: 0.4 | EJ18: 1.4 | EK18: 0 | EL18: 1.8 | EM18: 0.2 | EN18: 0.2 | EO18: 0.2 | EQ18: 0 | ER18: 0 | ES18: 0 | ET18: -0.2 | EU18: 5.4 | EV18: 0 | EW18: 0 | EX18: 1.4 | EY18: 0.7 | EZ18: 0.4 | FA18: 0.5 | FB18: 0 | FC18: 0.4 | FD18: 0.4 | FE18: 2.4 | FF18: 14.8 | FG18: 0 | FH18: 4 | FI18: 0.7 | FJ18: 1.9 | FK18: 3.7 | FM18: -131.6 | FO18: 1.65919 | FP18: 0 | FQ18: 2.71 | FR18: 1.2 | FS18: 0.27977 | FT18: 0.25015 | FU18: 0 | FV18: 1 | FW18: 7.09911
A19: 16/12/2025 | B19: 04:30 | C19: 38.3 | D19: -78.7 | E19: 2.3 | H19: -16.4 | I19: -1.7 | J19: 0 | L19: -7.3 | M19: -8.4 | N19: 15.8 | P19: 13.1 | R19: 17.7 | S19: 0 | X19: 0.9 | Y19: 2 | AA19: 2.8 | AB19: -3.4 | AC19: 2.9 | AD19: 5.2 | AI19: 2.6 | AJ19: 0 | AN19: -1.5 | AO19: -31.6 | AP19: 1.1 | AQ19: 7.6 | AR19: 2.3 | AS19: 0.8 | AT19: 2.4 | AU19: 0.1 | AV19: 5.9 | AW19: -13 | AX19: -45.6 | AY19: 0.4 | AZ19: 0 | BA19: -0.8 | BB19: 0.9 | BC19: 0.6 | BD19: 14.8 | BG19: -5 | BJ19: -6.1 | BN19: -4.2 | BO19: -28.1 | BP19: -28.2 | BQ19: -9.9 | BR19: -8.7 | BS19: 3.4 | BT19: -5.3 | CB19: 30.9 | CC19: 13.2 | CD19: 2.6 | CE19: 1 | CF19: 2 | CG19: 0 | CH19: 0 | CI19: 0 | CJ19: -0.4 | CK19: 2.5 | CL19: -34.8 | CR19: -19.1 | CS19: -14 | CT19: -0.9 | CU19: -0.2 | CV19: 0.4 | CX19: -12.2 | CY19: 0 | CZ19: 0 | DB19: 0 | DC19: 0 | DE19: 0 | DG19: 0.1 | DH19: 0.9 | DI19: 0.2 | DJ19: -0.3 | DK19: 0.2 | DL19: 0.5 | DN19: 0 | DO19: 0 | DP19: 1.8 | DQ19: 4.9 | DR19: 0 | DS19: 0.1 | DT19: 0 | DU19: 0.5 | DW19: -1.8 | DX19: 0.6 | DY19: 0.5 | DZ19: 0.5 | EA19: 0.2 | EB19: 1.6 | EC19: 1.5 | ED19: 0 | EE19: -4 | EF19: -4.9 | EG19: 0 | EH19: 0.2 | EJ19: 1.4 | EK19: 0 | EL19: 1.9 | EM19: 0.2 | EN19: 0.2 | EO19: 0.2 | EQ19: 0 | ER19: 0 | ES19: 0 | ET19: -0.2 | EU19: 2.1 | EV19: 0 | EW19: 0 | EX19: 1.4 | EY19: 0.7 | EZ19: 0.4 | FA19: 0.5 | FB19: 0 | FC19: 0.3 | FD19: 0.4 | FE19: 2.4 | FF19: 14.9 | FG19: 0 | FH19: 3.9 | FI19: 1.1 | FJ19: 2.4 | FK19: 3.7 | FM19: -147.8 | FO19: 1.50802 | FP19: 0 | FQ19: 2.89 | FR19: 1.2 | FS19: 0.28031 | FT19: 0.21087 | FU19: 0 | FV19: 1 | FW19: 7.0892
A20: 16/12/2025 | B20: 05:00 | C20: 41.2 | D20: -69.6 | E20: 5.2 | H20: -15 | I20: 10.2 | J20: 0 | L20: -9.7 | M20: -5.3 | N20: 19.1 | P20: 13.2 | R20: 18.4 | S20: 0.2 | X20: 1.6 | Y20: 2.1 | AA20: 2.9 | AB20: -3.4 | AC20: 3 | AD20: 5.7 | AI20: 2.9 | AJ20: 0 | AN20: -1.6 | AO20: -32.5 | AP20: 0.8 | AQ20: 7.2 | AR20: 2.1 | AS20: -0.2 | AT20: 2.4 | AU20: 0.3 | AV20: 6.9 | AW20: -12 | AX20: -44.9 | AY20: 2.1 | AZ20: 0 | BA20: 0.8 | BB20: 0.9 | BC20: 0.5 | BD20: 17.1 | BG20: -4.2 | BJ20: -5.2 | BN20: -3.6 | BO20: -29.5 | BP20: -30.2 | BQ20: -11 | BR20: -8.1 | BS20: 3.2 | BT20: -5.4 | CB20: 30.9 | CC20: 12.5 | CD20: 2.2 | CE20: 2.7 | CF20: 1.8 | CG20: 0 | CH20: 0 | CI20: 0 | CJ20: 0.7 | CK20: 3.7 | CL20: -32.6 | CR20: -17.4 | CS20: -13.1 | CT20: -0.9 | CU20: -0.3 | CV20: 0.4 | CX20: -12.3 | CY20: 0 | CZ20: 0 | DB20: 0 | DC20: 0 | DE20: -0.2 | DG20: 0.1 | DH20: 0.9 | DI20: 0.2 | DJ20: 0.2 | DK20: 0.2 | DL20: 0.5 | DN20: 0 | DO20: 0 | DP20: 1.9 | DQ20: 5.2 | DR20: 0.6 | DS20: 0.1 | DT20: 0 | DU20: 0.5 | DW20: -1.9 | DX20: 0.5 | DY20: 0.5 | DZ20: 0.5 | EA20: 0.1 | EB20: 0.8 | EC20: 1.5 | ED20: 0.3 | EE20: -5.5 | EF20: -5.6 | EG20: 0 | EH20: 0 | EJ20: 1.4 | EK20: 0 | EL20: 2 | EM20: 0.2 | EN20: 0.2 | EO20: 0.2 | EQ20: 0 | ER20: 0 | ES20: 0 | ET20: -0.2 | EU20: 0 | EV20: 0 | EW20: 0 | EX20: 1.4 | EY20: 0.7 | EZ20: 0.4 | FA20: 0.5 | FB20: 0 | FC20: 0.4 | FD20: 0.4 | FE20: 2.4 | FF20: 15.2 | FG20: 0.4 | FH20: 3.7 | FI20: 1.3 | FJ20: 2.2 | FK20: 3.7 | FM20: -105.2 | FO20: 1.45265 | FP20: 0 | FQ20: 2.18 | FR20: 1.2 | FS20: 0.28886 | FT20: 0.16598 | FU20: 0 | FV20: 1.1 | FW20: 6.38749
A21: 16/12/2025 | B21: 05:30 | C21: 39.9 | D21: -55.9 | E21: 8.1 | H21: -13.3 | I21: 2.3 | J21: 0 | L21: -5.2 | M21: -4.1 | N21: 19.6 | P21: 14.7 | R21: 19.7 | S21: 0.1 | X21: 2.5 | Y21: 2 | AA21: 3 | AB21: -3.4 | AC21: 2.9 | AD21: 5.9 | AI21: 2.7 | AJ21: 0 | AN21: -1.4 | AO21: -20.5 | AP21: 0.9 | AQ21: 7.7 | AR21: 1.9 | AS21: -1 | AT21: 2.5 | AU21: -0.3 | AV21: 7.5 | AW21: -11.4 | AX21: -44.2 | AY21: 0 | AZ21: 0 | BA21: 0.4 | BB21: 0.9 | BC21: 0.6 | BD21: 16.3 | BG21: -3.9 | BJ21: -4.9 | BN21: -0.4 | BO21: -28.1 | BP21: -28.8 | BQ21: -9.2 | BR21: -7.5 | BS21: 4.1 | BT21: -5.1 | CB21: 30.2 | CC21: 13.6 | CD21: 2.7 | CE21: 0.9 | CF21: 1.7 | CG21: 0 | CH21: 0 | CI21: 0 | CJ21: 1.9 | CK21: 4.9 | CL21: -31.3 | CR21: -16.4 | CS21: -12.5 | CT21: -0.9 | CU21: -0.3 | CV21: 0.4 | CX21: -13.5 | CY21: 0 | CZ21: 0 | DB21: 0 | DC21: 0 | DE21: -0.2 | DG21: 0.1 | DH21: 0.8 | DI21: 0.1 | DJ21: -0.3 | DK21: 0.2 | DL21: 0.5 | DN21: 0 | DO21: 0 | DP21: 1.6 | DQ21: 4.8 | DR21: 0.4 | DS21: 0.1 | DT21: 0 | DU21: 0.5 | DW21: -1.9 | DX21: 0.6 | DY21: 0.5 | DZ21: 0.5 | EA21: 0.2 | EB21: 0 | EC21: 1.5 | ED21: -0.1 | EE21: -4.6 | EF21: -4.8 | EG21: 0 | EH21: 0.1 | EJ21: 1.4 | EK21: 0 | EL21: 1.8 | EM21: 0.2 | EN21: 0.2 | EO21: 0.2 | EQ21: 1.1 | ER21: 0 | ES21: 2.2 | ET21: -0.2 | EU21: -1 | EV21: 0 | EW21: 3.2 | EX21: 1.4 | EY21: 0.7 | EZ21: 0.4 | FA21: 0.5 | FB21: 0 | FC21: 0.4 | FD21: 0.4 | FE21: 2.3 | FF21: 15.3 | FG21: 0.1 | FH21: 2.6 | FI21: 1.4 | FJ21: 2.2 | FK21: 3.8 | FM21: -59.8 | FO21: 1.56217 | FP21: 0 | FQ21: 2.24 | FR21: 1.2 | FS21: 0.28844 | FT21: 0.11614 | FU21: 0 | FV21: 1.1 | FW21: 6.50675
A22: 16/12/2025 | B22: 06:00 | C22: 37.7 | D22: -62 | E22: 7.2 | H22: -11.5 | I22: 12.4 | J22: 0 | L22: -6.2 | M22: -7.1 | N22: 15.7 | P22: 12.8 | R22: 17.8 | S22: 0.1 | X22: 1.5 | Y22: 1.8 | AA22: 2.8 | AB22: -3.4 | AC22: 3.3 | AD22: 6.5 | AI22: 2.4 | AJ22: 0 | AN22: -1.3 | AO22: -22.7 | AP22: 1.5 | AQ22: 8 | AR22: 2 | AS22: -1 | AT22: 2.5 | AU22: 0.1 | AV22: 7.3 | AW22: -11.8 | AX22: -44.3 | AY22: -1.2 | AZ22: 0 | BA22: 0.4 | BB22: 0.9 | BC22: 0.7 | BD22: 15.9 | BG22: -3.9 | BJ22: -4 | BN22: -1.2 | BO22: -30.3 | BP22: -31.2 | BQ22: -12 | BR22: -11.8 | BS22: 3.6 | BT22: -5.3 | CB22: 29.9 | CC22: 13 | CD22: 2.5 | CE22: 0.9 | CF22: 1.9 | CG22: 0 | CH22: 0 | CI22: 0 | CJ22: 1.9 | CK22: 4.7 | CL22: -31.3 | CR22: -17.6 | CS22: -13.3 | CT22: -0.6 | CU22: -0.2 | CV22: 0.5 | CX22: -15.1 | CY22: 0.1 | CZ22: 0 | DB22: 0 | DC22: -0.1 | DE22: 0.2 | DG22: 0.1 | DH22: 0.9 | DI22: 0.1 | DJ22: 0.4 | DK22: 0.1 | DL22: 0.5 | DN22: 0 | DO22: 0 | DP22: 1.3 | DQ22: 3.6 | DR22: 0.3 | DS22: 0.1 | DT22: 0.1 | DU22: 0.4 | DW22: -1.9 | DX22: 0.4 | DY22: 0.5 | DZ22: 0.5 | EA22: 0.2 | EB22: 0 | EC22: 1.5 | ED22: 0.1 | EE22: -5.7 | EF22: -6.2 | EG22: 0 | EH22: 0 | EJ22: 1.4 | EK22: 0 | EL22: 1.9 | EM22: 0.2 | EN22: 0.2 | EO22: 0.2 | EQ22: 1.3 | ER22: 0 | ES22: 2.1 | ET22: -0.2 | EU22: -5.5 | EV22: 0 | EW22: -4.6 | EX22: 1.4 | EY22: 0.7 | EZ22: 0.4 | FA22: 0.5 | FB22: 0 | FC22: 0.4 | FD22: 0.4 | FE22: 2.3 | FF22: 15.9 | FG22: 0.2 | FH22: 4 | FI22: 1.7 | FJ22: 2.6 | FK22: 3.5 | FM22: -101.6 | FO22: 1.71903 | FP22: 0 | FQ22: 2.27 | FR22: 1.2 | FS22: 0.2972 | FT22: 0.12645 | FU22: -0.1 | FV22: 0.9 | FW22: 6.41268
... A58: 17/12/2025 | B58: 00:00 | C58: 41.4 | D58: -38.1 | E58: 7.5 | H58: -11.5 | I58: 13.3 | J58: 9.9 | L58: -7.9 | M58: -6.8 | N58: 16.2 | P58: 16.2 | R58: 52.4 | S58: 0.1 | X58: 7.8 | Y58: 0.6 | AA58: 1.9 | AB58: -3.6 | AC58: 4.9 | AD58: 5.2 | AI58: 3.9 | AJ58: -11.7 | AN58: -1.4 | AO58: -21.1 | AP58: 3.7 | AQ58: 15.8 | AR58: 0.8 | AS58: 0.2 | AT58: 2.4 | AU58: 0.2 | AV58: 10.1 | AW58: -17.1 | AX58: -46.5 | AY58: 3.2 | AZ58: 0 | BA58: -1.3 | BB58: 0.9 | BC58: 0.5 | BD58: -0.4 | BG58: 0 | BJ58: -2.9 | BN58: 0 | BO58: 0 | BP58: 0 | BQ58: 0 | BR58: 0 | BS58: 0 | BT58: 0 | CB58: 38.8 | CC58: 19.3 | CD58: 2.5 | CE58: 6.7 | CF58: 1.9 | CG58: -6 | CH58: 0.4 | CI58: 0.9 | CJ58: 17.9 | CK58: 21.1 | CL58: -16 | CR58: -8.4 | CS58: -11.1 | CT58: -1.1 | CU58: -0.1 | CV58: 0.5 | CX58: -14.8 | CY58: 0 | CZ58: 0 | DB58: 0.1 | DC58: -0.1 | DE58: 0 | DG58: 0.1 | DH58: 1 | DI58: 0.1 | DJ58: 0.1 | DK58: 0.1 | DL58: 0.5 | DN58: 0 | DO58: 0 | DP58: 1.8 | DQ58: 9.1 | DR58: 0 | DS58: 0.2 | DT58: 0.4 | DU58: 0.6 | DW58: -2.2 | DX58: 0.3 | DY58: 2.8 | DZ58: 2.8 | EA58: 1.4 | EB58: 0 | EC58: 2.3 | ED58: 0 | EE58: 0 | EF58: 0 | EG58: 0 | EH58: 0 | EJ58: 1.9 | EK58: 0 | EL58: 1.6 | EM58: 0.2 | EN58: 0.2 | EO58: 0.2 | EQ58: 0 | ER58: 0 | ES58: 0 | ET58: -0.2 | EU58: -10.5 | EV58: 0 | EW58: 0 | EX58: 1.4 | EY58: 0.7 | EZ58: 0.4 | FA58: 0.5 | FB58: 0 | FC58: 0.3 | FD58: 1.7 | FE58: 2.2 | FF58: 10.4 | FG58: 0.3 | FH58: 3 | FI58: 0 | FJ58: 0 | FK58: 0 | FM58: 137 | FO58: 2.07982 | FP58: -0.101 | FQ58: 2.777 | FR58: 1.1 | FS58: 0.28175 | FT58: 1.5362 | FU58: 0 | FV58: 2 | FW58: 9.67377
A59: EJEC | C59: 966.45 | D59: -383.2 | E59: 297 | F59: 0 | G59: 0 | H59: -155.35 | I59: 285.4 | J59: 15.6 | K59: 0 | L59: 105.65 | M59: 106.6 | N59: 674.2 | O59: 0 | P59: 525.15 | Q59: 0 | R59: 700.9 | S59: 0.85 | T59: 0 | U59: 0 | V59: 0 | W59: 0 | X59: 130.4 | Y59: 28.85 | Z59: 0 | AA59: 54.15 | AB59: -82.2 | AC59: 111.25 | AD59: 292.5 | AE59: 0 | AF59: 0 | AG59: 0 | AH59: 0 | AI59: 87.4 | AJ59: 8.15 | AK59: 0 | AL59: 0 | AM59: 0 | AN59: -32.65 | AO59: -369.85 | AP59: 64.35 | AQ59: 365.65 | AR59: 59.95 | AS59: -9.3 | AT59: 58.05 | AU59: 4.5 | AV59: 527.55 | AW59: 31.65 | AX59: -984.85 | AY59: 100.5 | AZ59: 48.45 | BA59: -80.45 | BB59: 22.25 | BC59: 13.95 | BD59: 158.5 | BE59: 0 | BF59: 0 | BG59: -37.4 | BH59: 0 | BI59: 0 | BJ59: -91.5 | BK59: 0 | BL59: 0 | BM59: 0 | BN59: 8.95 | BO59: -234.2 | BP59: -241.05 | BQ59: -78.8 | BR59: 44.25 | BS59: 52.4 | BT59: -59.4 | BU59: 0 | BV59: 0 | BW59: 0 | BX59: 0 | BY59: 0 | BZ59: 0 | CA59: 0 | CB59: 1201.2 | CC59: 690.05 | CD59: 201.15 | CE59: 153.5 | CF59: 82.4 | CG59: -173.95 | CH59: 0.95 | CI59: 74 | CJ59: 914.45 | CK59: 998.15 | CL59: -263.55 | CM59: 0 | CN59: 0 | CO59: 0 | CP59: 0 | CQ59: 0 | CR59: -0.7 | CS59: -114 | CT59: -23.1 | CU59: -3.65 | CV59: 11.7 | CW59: 0 | CX59: -278.65 | CY59: 82.7 | CZ59: 0.15 | DA59: 0 | DB59: 0.45 | DC59: -0.7 | DD59: 0 | DE59: 292.6 | DF59: 0 | DG59: 2.05 | DH59: 25.3 | DI59: 3.45 | DJ59: 17.1 | DK59: 3.05 | DL59: 11.25 | DM59: 0 | DN59: -7.35 | DO59: -19.2 | DP59: 57.35 | DQ59: 141.4 | DR59: -25.75 | DS59: 0.45 | DT59: 6.3 | DU59: 10.8 | DV59: 0 | DW59: -46.7 | DX59: 10.5 | DY59: 38.05 | DZ59: 35.3 | EA59: 11 | EB59: 7.2 | EC59: 43.8 | ED59: 18.85 | EE59: -30.85 | EF59: -44.05 | EG59: 1.6 | EH59: 2.35 | EI59: 0 | EJ59: 40.25 | EK59: -0.25 | EL59: 42.5 | EM59: 4.8 | EN59: 4.8 | EO59: 4.8 | EP59: 0 | EQ59: 18.75 | ER59: 17 | ES59: 254.85 | ET59: -4.15 | EU59: 5.8 | EV59: 4.05 | EW59: 14.15 | EX59: 33.6 | EY59: 15.35 | EZ59: 9.6 | FA59: 12 | FB59: 15.2 | FC59: 11.7 | FD59: 21.55 | FE59: 56.95 | FF59: 297.1 | FG59: 5.75 | FH59: 65.8 | FI59: 45.15 | FJ59: 60.3 | FK59: 80.9 | FL59: 0 | FM59: 8367.95 | FO59: 45.759445 | FP59: -5.467 | FQ59: 58.6475 | FR59: 29.8 | FS59: 6.705 | FT59: 30.88496 | FU59: 0.3 | FV59: 47.3 | FW59: 213.9299

Sheet DEMANDA_AREAS
B3: martes, 16 de Diciembre del 2025
B5: REPORTE DE LA DEMANDA POR ÁREAS Y SUBAREAS OPERATIVAS (MW)
B6: FECHA HORA | C6: DEMANDA | E6: AREA | H6: SUBAREAS
C7: INTERCAMBIOS INTERNACIONALES | D7: SEIN | E7: NORTE | F7: CENTRO | G7: SUR | H7: ELECTROANDES
B8: 00:30 | C8: 0 | D8: 6845.0768 | E8: 1022.665 | F8: 4051.3378 | G8: 1771.074 | H8: 272.027
B9: 01:00 | C9: 0 | D9: 6847.1073 | E9: 986.7818 | F9: 4091.0907 | G9: 1769.2348 | H9: 268.702
B10: 01:30 | C10: 0 | D10: 6630.5081 | E10: 947.4015 | F10: 3914.4145 | G10: 1768.6921 | H10: 265.1812
B11: 02:00 | C11: 0 | D11: 6595.6171 | E11: 931.7944 | F11: 3911.6931 | G11: 1752.1296 | H11: 263.9752
B12: 02:30 | C12: 0 | D12: 6522.3532 | E12: 929.8452 | F12: 3839.1955 | G12: 1753.3125 | H12: 261.1622
B13: 03:00 | C13: 0 | D13: 6451.6182 | E13: 915.1383 | F13: 3771.93 | G13: 1764.5499 | H13: 261.1861
B14: 03:30 | C14: 0 | D14: 6556.1061 | E14: 911.6203 | F14: 3872.0789 | G14: 1772.4069 | H14: 262.7899
B15: 04:00 | C15: 0 | D15: 6587.1611 | E15: 932.3465 | F15: 3879.7869 | G15: 1775.0277 | H15: 266.1397
B16: 04:30 | C16: 0 | D16: 6559.0579 | E16: 904.5696 | F16: 3868.158 | G16: 1786.3303 | H16: 256.9408
B17: 05:00 | C17: 0 | D17: 6561.6203 | E17: 945.4617 | F17: 3811.8594 | G17: 1804.2992 | H17: 246.8193
B18: 05:30 | C18: 0 | D18: 6707.3906 | E18: 922.2579 | F18: 3984.4323 | G18: 1800.7005 | H18: 250.3772
B19: 06:00 | C19: 0 | D19: 6651.4805 | E19: 987.8543 | F19: 3879.437 | G19: 1784.1892 | H19: 247.5376
... B59: ENERGÍA | C59: 0 | D59: 178282.98 | E59: 26339.731 | F59: 108351.01 | G59: 43592.24 | H59: 6089.3659
B61: LEYENDA:
D63: Potencia recibida del Ecuador
D64: Potencia entregada al Ecuador

Sheet DEMANDA_UL
B3: martes, 16 de Diciembre del 2025
B5: POTENCIA DE LOS GRANDES USUARIOS LIBRES (MW)
B6: FECHA HORA | C6: GRANDES USUARIOS LIBRES DEL ÁREA NORTE | X6: GRANDES USUARIOS LIBRES DEL ÁREA CENTRO | BP6: GRANDES USUARIOS LIBRES DEL ÁREA SUR
C7: ARCA CONTINENTAL LINDLEY S.A. | D7: AUSTRAL GROUP S.A.A | E7: CEMENTOS PACASMAYO | F7: CONSORCIO MINERO HORIZONTE S.R.L. | G7: CORPORACIÓN PESQUERA INCA S.A.C. | H7: CREDITEX: CIA IND.TEXTIL CREDISA | I7: HIPERMERCADOS TOTTUS S.A | J7: INDUSTRIA TEXTIL PIURA | K7: MINERA BOROO MISQUICHILCA S.A. | L7: MINERA GOLD FIELDS | M7: MINERA MARSA | N7: MINERA MISKY MAYO | O7: MINERA YANACOCHA | P7: OPEN PLAZA | Q7: PESQUERA DIAMANTE | R7: PETROPERU | S7: REAL PLAZA S.R.L. | T7: SIDER PERU | U7: SUPERMERCADOS PERUANOS S.A. | V7: TRUPAL S.A. | W7: UNIÓN DE CERVECERÍAS PERUANAS BACKUS Y JOHNSTON S. | X7: ACEROS AREQUIPA | Y7: ADMINISTRADORA JOCKEY PLAZA SHOPPING CENTER S.A. | Z7: ALICORP | AA7: ARCA CONTINENTAL LINDLEY S.A. | AB7: AUSTRAL GROUP S.A.A | AC7: COMPAÑIA MINERA CONDESTABLE | AD7: CORPORACIÓN PESQUERA INCA S.A.C. | AE7: CREDITEX: CIA IND.TEXTIL CREDISA | AF7: FUNDICION CHILCA S.A. | AG7: HIPERMERCADOS TOTTUS S.A | AH7: INMOBILIARIA KANPU S.A. | AI7: INMUEBLES PANAMERICANA S.A. | AJ7: KIMBERLY-CLARK PERU | AK7: LECHE GLORIA S.A. | AL7: MALL AVENTURA S.A. | AM7: MARCOBRE S.A.C. | AN7: MINERA ANTAMINA | AO7: MINERA ARES | AP7: MINERA BUENAVENTURA | AQ7: MINERA CHINALCO PERÚ S.A. | AR7: MINERA SHOUXIN PERU S.A. | AS7: MINERA VOLCAN | AT7: MINSUR | AU7: MOLYCOP-ADESUR | AV7: NEXA RESOURCES CAJAMARQUILLA S.A. | AW7: NEXA RESOURCES PERÚ S.A.A. | AX7: OPEN PLAZA | AY7: OPP FILM | AZ7: OWENS-ILLINOIS PERÚ S.A. | BA7: PAPELERA NACIONAL S.A. | BB7: PESQUERA DIAMANTE | BC7: QUIMPAC S.A. | BD7: REAL PLAZA S.R.L. | BE7: REFINERIA LA PAMPILLA S.A.A | BF7: SAGA FALABELLA | BG7: SAN MIGUEL INDUSTRIAS PET S.A. | BH7: SHOUGANG HIERRO PERU | BI7: SOFTYS PERU S.A.C. | BJ7: SUPERMERCADOS PERUANOS S.A. | BK7: TEJIDOS SAN JACINTO | BL7: TREN URBANO DE LIMA S.A. | BM7: TRUPAL S.A. | BN7: UNACEM PERU S.A. | BO7: UNIÓN DE CERVECERÍAS PERUANAS BACKUS Y JOHNSTON S. | BP7: ANGLO AMERICAN QUELLAVECO S.A. | BQ7: ARCA CONTINENTAL LINDLEY S.A. | BR7: CAL & CEMENTO SUR S.A. | BS7: COMPAÑIA MINERA ANTAPACCAY S.A. | BT7: COMPAÑÍA MINERA CHUNGAR SAC | BU7: COMPAÑIA MINERA SAN IGNACIO DE MOROCOCHA S.A.A. | BV7: EL BROCAL .S.A. | BW7: EMPRESA ADMINISTRADORA CERRO S.A.C. | BX7: EMPRESA MINERA LOS QUENUALES S.A.C. | BY7: HIPERMERCADOS TOTTUS S.A | BZ7: HUDBAY PERU S.A.C. | CA7: INDUSTRIA CACHIMAYO | CB7: MALL AVENTURA S.A. | CC7: MINERA ARES | CD7: MINERA BUENAVENTURA | CE7: MINERA CERRO VERDE | CF7: MINERA CORONA | CG7: MINERA LAS BAMBAS S.A. | CH7: MINERA VOLCAN | CI7: MINSUR | CJ7: MOLYCOP-ADESUR | CK7: NEXA RESOURCES PERÚ S.A.A. | CL7: OXIDOS DE PASCO S.A.C. | CM7: PESQUERA DIAMANTE | CN7: REAL PLAZA S.R.L. | CO7: SOBREANDES S.A.C. | CP7: SOUTHERN PERU CC | CQ7: SUPERMERCADOS PERUANOS S.A. | CR7: UNACEM PERU S.A. | CS7: UNIÓN DE CERVECERÍAS PERUANAS BACKUS Y JOHNSTON S. | CT7: YURA
B8: 00:30 | E8: 34.85093 | F8: 11.147 | L8: 26.8968 | M8: 13.9675 | N8: 14.06 | O8: 32.464 | R8: 50.731 | V8: 0.5 | X8: 124.11211 | Z8: 8.58081 | AC8: 15.51 | AF8: 3.6 | AH8: 3.4305 | AJ8: 5.33786 | AK8: 13.123 | AM8: 45.55108 | AN8: 123.3812 | AO8: 26.98789 | AP8: 0.81 | AQ8: 164.42719 | AS8: 36.36408 | AT8: 30.99813 | AV8: 198.16172 | AW8: 30.07503 | AY8: 0.31136 | BA8: 1.4 | BC8: 71.49192 | BE8: 19.8 | BI8: 15.1174 | BK8: 4.78111 | BM8: 6.213 | BN8: 32.983 | BO8: 1.8 | BP8: 143.81995 | BR8: 4.75667 | BS8: 126.04821 | BT8: 13.04403 | BW8: 3.85819 | BZ8: 88.1215 | CA8: 24.70725 | CC8: 0.751 | CD8: 25.884 | CE8: 409.61736 | CG8: 154.64874 | CH8: 16.89702 | CK8: 17.3069 | CL8: 4.72364 | CO8: 16.72513 | CP8: 285.12 | CR8: 40.641 | CT8: 28.107
B9: 01:00 | E9: 34.86554 | F9: 11.022 | L9: 26.9835 | M9: 13.8487 | N9: 14.45 | O9: 31.502 | R9: 50.551 | V9: 0.5 | X9: 148.94089 | Z9: 8.63453 | AC9: 16.11 | AF9: 4.2 | AH9: 3.6854 | AJ9: 5.33431 | AK9: 13.202 | AM9: 46.87886 | AN9: 120.9714 | AO9: 27.07678 | AP9: 0.7 | AQ9: 163.85407 | AS9: 36.56059 | AT9: 34.17866 | AV9: 199.02218 | AW9: 30.74263 | AY9: 0.25431 | BA9: 1.3 | BC9: 71.56586 | BE9: 19.8 | BI9: 16.98328 | BK9: 4.96181 | BM9: 6.331 | BN9: 43.063 | BO9: 1.7 | BP9: 146.74149 | BR9: 4.74717 | BS9: 126.46055 | BT9: 12.80647 | BW9: 3.96348 | BZ9: 86.4913 | CA9: 24.71659 | CC9: 0.733 | CD9: 25.7397 | CE9: 411.20797 | CG9: 151.05607 | CH9: 17.01433 | CK9: 17.016 | CL9: 4.41691 | CO9: 16.62505 | CP9: 286.11 | CR9: 40.505 | CT9: 26.501
B10: 01:30 | E10: 34.84826 | F10: 11.977 | L10: 27.0527 | M10: 14.2078 | N10: 14.19 | O10: 31.352 | R10: 50.989 | V10: 0.5 | X10: 125.29145 | Z10: 8.38636 | AC10: 16.33 | AF10: 3.1 | AH10: 3.3392 | AJ10: 5.31128 | AK10: 13.204 | AM10: 46.48391 | AN10: 123.127 | AO10: 27.12606 | AP10: 0.64 | AQ10: 165.52784 | AS10: 36.96364 | AT10: 34.46057 | AV10: 198.8063 | AW10: 33.03973 | AY10: 0.26926 | BA10: 1.5 | BC10: 71.69522 | BE10: 19.8 | BI10: 18.06492 | BK10: 4.86354 | BM10: 6.251 | BN10: 43.764 | BO10: 1.7 | BP10: 144.16219 | BR10: 4.86537 | BS10: 125.68267 | BT10: 11.23686 | BW10: 4.0073 | BZ10: 87.464 | CA10: 24.73646 | CC10: 0.698 | CD10: 25.75537 | CE10: 407.49954 | CG10: 155.36541 | CH10: 17.67247 | CK10: 17.6754 | CL10: 4.50485 | CO10: 15.87742 | CP10: 289.19 | CR10: 40.544 | CT10: 29.577
B11: 02:00 | E11: 34.97511 | F11: 12.437 | L11: 26.6374 | M11: 14.0177 | N11: 14.35 | O11: 31.876 | R11: 50.577 | V11: 0.5 | X11: 100.97388 | Z11: 8.38472 | AC11: 16.45 | AF11: 2.8 | AH11: 1.6627 | AJ11: 5.27359 | AK11: 13.133 | AM11: 46.9378 | AN11: 123.8881 | AO11: 26.7119 | AP11: 0.44 | AQ11: 166.77995 | AS11: 37.41516 | AT11: 34.30769 | AV11: 198.73787 | AW11: 35.22685 | AY11: 0.27212 | BA11: 1.6 | BC11: 71.64904 | BE11: 19.8 | BI11: 18.3686 | BK11: 4.76841 | BM11: 6.326 | BN11: 43.614 | BO11: 1.71 | BP11: 142.33881 | BR11: 4.92423 | BS11: 125.21889 | BT11: 11.12865 | BW11: 3.7307 | BZ11: 87.4302 | CA11: 24.74573 | CC11: 0.727 | CD11: 26.30068 | CE11: 400.79386 | CG11: 152.28113 | CH11: 17.34426 | CK11: 17.6862 | CL11: 4.41383 | CO11: 16.56754 | CP11: 280.71 | CR11: 40.347 | CT11: 29.464
B12: 02:30 | E12: 34.82729 | F12: 12.538 | L12: 26.7025 | M12: 14.0273 | N12: 14.43 | O12: 31.73 | R12: 50.913 | V12: 0.5 | X12: 164.62328 | Z12: 8.42523 | AC12: 16.09 | AF12: 3.9 | AH12: 3.5382 | AJ12: 5.22184 | AK12: 13.58 | AM12: 46.89005 | AN12: 123.6791 | AO12: 24.40805 | AP12: 0.41 | AQ12: 165.57937 | AS12: 37.76713 | AT12: 34.17586 | AV12: 198.71194 | AW12: 35.20006 | AY12: 0.54608 | BA12: 1.6 | BC12: 71.67075 | BE12: 19.8 | BI12: 18.40927 | BK12: 4.7853 | BM12: 6.325 | BN12: 42.564 | BO12: 1.6 | BP12: 145.54523 | BR12: 4.87319 | BS12: 125.02404 | BT12: 13.087 | BW12: 3.87202 | BZ12: 87.5362 | CA12: 24.76174 | CC12: 0.729 | CD12: 25.93971 | CE12: 420.00968 | CG12: 154.11438 | CH12: 17.6329 | CK12: 17.5738 | CL12: 4.45043 | CO12: 16.12583 | CP12: 280.6 | CR12: 40.67 | CT12: 29.556
B13: 03:00 | E13: 34.46838 | F13: 11.821 | L13: 26.2517 | M13: 13.925 | N13: 14.29 | O13: 31.928 | R13: 50.717 | V13: 0.5 | X13: 60.30966 | Z13: 8.38157 | AC13: 15.88 | AF13: 4.5 | AH13: 3.3016 | AJ13: 4.81592 | AK13: 13.57 | AM13: 48.29118 | AN13: 122.5868 | AO13: 27.47971 | AP13: 0.67 | AQ13: 165.72415 | AS13: 37.09206 | AT13: 33.71046 | AV13: 197.41359 | AW13: 35.54028 | AY13: 0.24071 | BA13: 1.6 | BC13: 71.41751 | BE13: 19.8 | BI13: 18.15086 | BK13: 4.84108 | BM13: 6.3251 | BN13: 42.132 | BO13: 1.69 | BP13: 147.46677 | BR13: 4.85077 | BS13: 127.06925 | BT13: 13.23704 | BW13: 3.96593 | BZ13: 87.2245 | CA13: 24.7726 | CC13: 0.742 | CD13: 26.23633 | CE13: 440.82059 | CG13: 154.44281 | CH13: 17.6778 | CK13: 17.7595 | CL13: 4.46115 | CO13: 16.04848 | CP13: 275.28 | CR13: 40.601 | CT13: 29.889
B14: 03:30 | E14: 31.85886 | F14: 12.719 | L14: 26.137 | M14: 13.2826 | N14: 14.4 | O14: 31.336 | R14: 50.826 | V14: 0.5 | X14: 167.782 | Z14: 8.22733 | AC14: 15.82 | AF14: 2.6 | AH14: 2.4912 | AJ14: 5.05719 | AK14: 13.336 | AM14: 47.13518 | AN14: 121.313 | AO14: 25.49744 | AP14: 0.48 | AQ14: 164.48113 | AS14: 37.31572 | AT14: 33.27941 | AV14: 198.2802 | AW14: 35.09598 | AY14: 0.22646 | BA14: 1.6 | BC14: 71.48084 | BE14: 19.8 | BI14: 18.22131 | BK14: 4.81178 | BM14: 6.352 | BN14: 43.407 | BO14: 1.81 | BP14: 144.69161 | BR14: 4.91389 | BS14: 126.50273 | BT14: 13.00311 | BW14: 4.02736 | BZ14: 87.3863 | CA14: 24.79795 | CC14: 0.718 | CD14: 26.15019 | CE14: 439.22989 | CG14: 159.24139 | CH14: 17.75664 | CK14: 17.6994 | CL14: 4.63789 | CO14: 16.4712 | CP14: 275.38 | CR14: 40.302 | CT14: 29.845
B15: 04:00 | E15: 29.64634 | F15: 12.831 | L15: 26.1375 | M15: 13.0897 | N15: 14.42 | O15: 32.224 | R15: 50.884 | V15: 0.5 | X15: 140.29775 | Z15: 8.22243 | AC15: 15.3 | AF15: 2.7 | AH15: 1.8894 | AJ15: 5.19055 | AK15: 13.349 | AM15: 47.97643 | AN15: 121.9145 | AO15: 26.57142 | AP15: 0.18 | AQ15: 164.28477 | AS15: 37.43793 | AT15: 33.04792 | AV15: 198.14681 | AW15: 34.24386 | AY15: 0.37216 | BA15: 1.5 | BC15: 71.11668 | BE15: 19.8 | BI15: 18.22258 | BK15: 4.78109 | BM15: 6.623 | BN15: 43.139 | BO15: 1.72 | BP15: 146.40612 | BR15: 4.95447 | BS15: 127.54442 | BT15: 12.79554 | BW15: 3.88656 | BZ15: 88.2409 | CA15: 24.80214 | CC15: 0.71 | CD15: 27.02408 | CE15: 444.73358 | CG15: 152.57153 | CH15: 17.68112 | CK15: 17.351 | CL15: 4.72899 | CO15: 16.91703 | CP15: 281.81 | CR15: 39.949 | CT15: 29.802
B16: 04:30 | E16: 22.78294 | F16: 12.56 | L16: 26.4881 | M16: 14.2222 | N16: 14.4 | O16: 32.52 | R16: 50.668 | V16: 0.5 | X16: 81.12284 | Z16: 8.36816 | AC16: 14.69 | AF16: 3.5 | AH16: 3.3838 | AJ16: 5.28152 | AK16: 14.047 | AM16: 48.19615 | AN16: 121.9337 | AO16: 25.8523 | AP16: 1.65 | AQ16: 163.13544 | AS16: 37.69486 | AT16: 33.17517 | AV16: 198.05157 | AW16: 34.58621 | AY16: 0.27184 | BA16: 1.6 | BC16: 71.09017 | BE16: 19.8 | BI16: 18.43984 | BK16: 4.88052 | BM16: 6.3452 | BN16: 43.523 | BO16: 1.62 | BP16: 144.77511 | BR16: 4.83371 | BS16: 126.84269 | BT16: 12.87993 | BW16: 3.90366 | BZ16: 86.0589 | CA16: 24.80793 | CC16: 0.601 | CD16: 25.39801 | CE16: 440.30621 | CG16: 156.06687 | CH16: 17.02221 | CK16: 16.3512 | CL16: 4.79577 | CO16: 16.88585 | CP16: 288.19 | CR16: 40.29 | CT16: 29.6
B17: 05:00 | E17: 22.45544 | F17: 11.719 | L17: 26.4848 | M17: 14.4468 | N17: 14.38 | O17: 33.084 | R17: 50.731 | V17: 0.5 | X17: 143.197 | Z17: 8.34281 | AC17: 13.9 | AF17: 4.2 | AH17: 3.3521 | AJ17: 5.03627 | AK17: 14.476 | AM17: 47.57265 | AN17: 122.419 | AO17: 26.68068 | AP17: 2.1 | AQ17: 165.33201 | AS17: 36.1892 | AT17: 31.64273 | AV17: 198.21438 | AW17: 34.07381 | AY17: 0.28343 | BA17: 2.3 | BC17: 70.99191 | BE17: 19.8 | BI17: 17.71677 | BK17: 4.78464 | BM17: 6.421 | BN17: 44.052 | BO17: 1.68 | BP17: 144.39706 | BR17: 5.0994 | BS17: 127.07679 | BT17: 12.02247 | BW17: 4.37541 | BZ17: 86.5612 | CA17: 24.80983 | CC17: 0.595 | CD17: 25.02705 | CE17: 437.79883 | CG17: 154.13554 | CH17: 17.37655 | CK17: 16.1646 | CL17: 4.78919 | CO17: 16.36879 | CP17: 286.87 | CR17: 40.677 | CT17: 30.018
B18: 05:30 | E18: 26.28419 | F18: 11.324 | L18: 26.9747 | M18: 14.7533 | N18: 14.27 | O18: 33.38 | R18: 50.62 | V18: 0.5 | X18: 137.72384 | Z18: 8.07781 | AC18: 14.96 | AF18: 2.1 | AH18: 3.6584 | AJ18: 5.08865 | AK18: 14.251 | AM18: 45.24837 | AN18: 122.641 | AO18: 25.91266 | AP18: 1.93 | AQ18: 163.26445 | AS18: 34.29733 | AT18: 32.73795 | AV18: 197.1122 | AW18: 33.81596 | AY18: 0.25056 | BA18: 2.3 | BC18: 70.92355 | BE18: 19.8 | BI18: 17.07193 | BK18: 4.91101 | BM18: 6.326 | BN18: 43.314 | BO18: 2.11 | BP18: 145.05564 | BR18: 4.9285 | BS18: 129.55482 | BT18: 11.9514 | BW18: 3.85894 | BZ18: 87.3372 | CA18: 24.77568 | CC18: 0.547 | CD18: 25.04465 | CE18: 435.9619 | CG18: 154.65412 | CH18: 17.57189 | CK18: 15.0463 | CL18: 4.81954 | CO18: 14.59572 | CP18: 288.98 | CR18: 40.225 | CT18: 27.208
B19: 06:00 | E19: 26.98299 | F19: 10.356 | L19: 27.0356 | M19: 15.1916 | N19: 14.18 | O19: 33.662 | R19: 50.768 | V19: 0.5 | X19: 123.63429 | Z19: 7.77572 | AC19: 16.07 | AF19: 1.4 | AH19: 1.9207 | AJ19: 5.10208 | AK19: 13.88 | AM19: 47.50716 | AN19: 122.4005 | AO19: 21.48143 | AP19: 1.54 | AQ19: 164.61196 | AS19: 33.5529 | AT19: 33.367 | AV19: 198.46587 | AW19: 32.24264 | AY19: 0.43909 | BA19: 2.2 | BC19: 70.42921 | BE19: 19.8 | BI19: 16.04408 | BK19: 4.8732 | BM19: 6.213 | BN19: 45.898 | BO19: 1.96 | BP19: 145.74697 | BR19: 4.95095 | BS19: 129.08434 | BT19: 11.91449 | BW19: 3.65085 | BZ19: 86.2762 | CA19: 24.76763 | CC19: 0.621 | CD19: 24.15413 | CE19: 421.79532 | CG19: 154.71439 | CH19: 17.5906 | CK19: 15.1211 | CL19: 4.57848 | CO19: 13.61633 | CP19: 292.1 | CR19: 40.492 | CT19: 33.148
... B55: 00:00 | E55: 34.19628 | F55: 12.786 | L55: 26.8586 | M55: 13.5046 | N55: 14.93 | O55: 33.66 | R55: 49.025 | V55: 0.5 | X55: 111.5994 | Z55: 9.0922 | AC55: 14.78 | AF55: 3.1 | AH55: 0.9043 | AJ55: 5.27586 | AK55: 13.561 | AM55: 42.26138 | AN55: 123.0328 | AO55: 26.32082 | AP55: 0.83 | AQ55: 170.37808 | AS55: 36.81167 | AT55: 31.95829 | AV55: 196.22742 | AW55: 29.10871 | AY55: 0.31685 | BA55: 1.3 | BC55: 69.63924 | BE55: 20.77 | BI55: 18.34866 | BK55: 4.85065 | BM55: 6.321 | BN55: 31.478 | BO55: 1.78 | BP55: 147.39009 | BR55: 4.63153 | BS55: 129.64053 | BT55: 13.31287 | BW55: 3.83695 | BZ55: 92.3053 | CA55: 24.64774 | CC55: 0.608 | CD55: 27.67117 | CE55: 408.27211 | CG55: 155.17123 | CH55: 17.19401 | CK55: 20.3943 | CL55: 1.81405 | CO55: 16.57653 | CP55: 287.18 | CR55: 38.628 | CT55: 24.63
B56: MWh | C56: 0 | D56: 0 | E56: 647.47865 | F56: 286.9755 | G56: 0 | H56: 0 | I56: 0 | J56: 0 | K56: 0 | L56: 651.86315 | M56: 295.23155 | N56: 340.685 | O56: 768.968 | P56: 0 | Q56: 0 | R56: 1185.8725 | S56: 0 | T56: 0 | U56: 0 | V56: 14.85 | W56: 0 | X56: 2277.4615 | Y56: 0 | Z56: 205.72734 | AA56: 0 | AB56: 0 | AC56: 378.91 | AD56: 0 | AE56: 0 | AF56: 59.55 | AG56: 0 | AH56: 45.0649 | AI56: 0 | AJ56: 118.96792 | AK56: 318.6635 | AL56: 0 | AM56: 1144.6718 | AN56: 2924.0211 | AO56: 616.97249 | AP56: 18.01 | AQ56: 3938.2315 | AR56: 0 | AS56: 837.753 | AT56: 790.7011 | AU56: 0 | AV56: 4305.1135 | AW56: 771.95086 | AX56: 0 | AY56: 6.865425 | AZ56: 0 | BA56: 41.75 | BB56: 0 | BC56: 1510.9684 | BD56: 0 | BE56: 487.415 | BF56: 0 | BG56: 0 | BH56: 0 | BI56: 433.66688 | BJ56: 0 | BK56: 114.96877 | BL56: 0 | BM56: 146.29897 | BN56: 889.464 | BO56: 44.76 | BP56: 3437.0166 | BQ56: 0 | BR56: 115.84314 | BS56: 3059.4467 | BT56: 294.15107 | BU56: 0 | BV56: 0 | BW56: 93.445805 | BX56: 0 | BY56: 0 | BZ56: 2140.135 | CA56: 505.00047 | CB56: 0 | CC56: 14.586 | CD56: 605.58745 | CE56: 9655.1966 | CF56: 0 | CG56: 3714.2642 | CH56: 403.4893 | CI56: 0 | CJ56: 0 | CK56: 397.5498 | CL56: 61.1721 | CM56: 0 | CN56: 0 | CO56: 366.00471 | CP56: 6684.545 | CQ56: 0 | CR56: 889.9555 | CS56: 0 | CT56: 487.9965
B59: Nota :
B60: Información proporcionada por la empresas
C62: DATOS ESTIMADOS
C64: SIN DATOS

Sheet TIPO_RECURSO
B3: martes, 16 de Diciembre del 2025
B5: REPORTE POTENCIA GENERADA POR TIPO DE RECURSO
B6: HORA | C6: H. PASADA | D6: H. REGULACION | E6: GAS DE CAMISEA | F6: GAS DE MALACAS | G6: GAS DE AGUAYTIA | H6: DIÉSEL | I6: RESIDUAL | J6: NAFTA+GAS DE REFINERIA | K6: FLEXIGAS+GAS DE REFINERIA | L6: BAGAZO | M6: BIOGÁS | N6: SOLAR | O6: EÓLICA | P6: TOTAL | U6: EMPRESA | V6: CENTRAL | W6: HIDROELECTRICA DE PASADA | X6: HIDROELECTRICA DE REGULACION
B7: 00:30 | C7: 969.1 | D7: 2194.799 | E7: 3016.4775 | F7: 25 | G7: 0 | J7: =+DESPACHO_EJECUTADO!FF11+DESPACHO_EJECUTADO!FG11 -> 61.3 | L7: 86.1 | M7: 7.4 | N7: 0 | O7: 507.10035 | P7: =SUM(C7:O7) -> 6867.2768 | U7: ANDEAN POWER S.A.C. | V7: C.H.CARHUAC | W7: 244.05
B8: 01:00 | C8: 955.1 | D8: 2104.0628 | E8: 3020.0834 | F8: 25 | G8: 0 | J8: =+DESPACHO_EJECUTADO!FF12+DESPACHO_EJECUTADO!FG12 -> 61.2 | L8: 84.6 | M8: 7.4 | N8: 0 | O8: 611.26118 | P8: =SUM(C8:O8) -> 6868.7073 | U8: ASOCIACIÓN SANTA LUCIA DE CHACAS | V8: C.H. HUALLIN | W8: 60.45
B9: 01:30 | C9: 940.7 | D9: 1988.8299 | E9: 2904.6039 | F9: 23.4 | G9: 0 | J9: =+DESPACHO_EJECUTADO!FF13+DESPACHO_EJECUTADO!FG13 -> 61.4 | L9: 87 | M9: 7.4 | N9: 0 | O9: 638.37428 | P9: =SUM(C9:O9) -> 6651.7081 | U9: CELARIS ENERGY S.A. | V9: C.H. MANTA I | W9: 153
B10: 02:00 | C10: 951.3 | D10: 1938.4769 | E10: 2869.6178 | F10: 23.7 | G10: 0 | J10: =+DESPACHO_EJECUTADO!FF14+DESPACHO_EJECUTADO!FG14 -> 61.4 | L10: 87.1 | M10: 7.4 | N10: 0 | O10: 677.62237 | P10: =SUM(C10:O10) -> 6616.6171 | U10: CELEPSA | V10: C.H. EL PLATANAL | X10: 1733.6
B11: 02:30 | C11: 933.9 | D11: 1802.2267 | E11: 2952.3222 | F11: 23.2 | G11: 0 | J11: =+DESPACHO_EJECUTADO!FF15+DESPACHO_EJECUTADO!FG15 -> 61.8 | L11: 85.5 | M11: 7.4 | N11: 0 | O11: 674.40432 | P11: =SUM(C11:O11) -> 6540.7532 | U11: CELEPSA RENOVABLES S.R.L. | V11: C.H. MARAÑON | W11: 416.7
B12: 03:00 | C12: 917.9 | D12: 1808.6813 | E12: 2908.0005 | F12: 23.9 | G12: 0 | J12: =+DESPACHO_EJECUTADO!FF16+DESPACHO_EJECUTADO!FG16 -> 62.5 | L12: 89.4 | M12: 7.4 | N12: 0 | O12: 655.83643 | P12: =SUM(C12:O12) -> 6473.6182 | U12: CHINANGO S.A.C. | V12: C.H. CHIMAY | X12: 2539.65
B13: 03:30 | C13: 922.9 | D13: 1819.7493 | E13: 3019.4338 | F13: 23.8 | G13: 0 | J13: =+DESPACHO_EJECUTADO!FF17+DESPACHO_EJECUTADO!FG17 -> 62.4 | L13: 90.5 | M13: 7.4 | N13: 0 | O13: 632.12293 | P13: =SUM(C13:O13) -> 6578.3061 | V13: C.H. YANANGO | W13: 505.45
B14: 04:00 | C14: 921.4 | D14: 1866.7796 | E14: 3023.9775 | F14: 24 | G14: 0 | J14: =+DESPACHO_EJECUTADO!FF18+DESPACHO_EJECUTADO!FG18 -> 62.6 | L14: 86.8 | M14: 7.4 | N14: 0 | O14: 613.90398 | P14: =SUM(C14:O14) -> 6606.8611 | U14: EGASA | V14: C.H. CHARCANI III | W14: 165.15
B15: 04:30 | C15: 912.9 | D15: 1922.7337 | E15: 3021.6861 | F15: 23.7 | G15: 0 | J15: =+DESPACHO_EJECUTADO!FF19+DESPACHO_EJECUTADO!FG19 -> 62.5 | L15: 84.3 | M15: 7.4 | N15: 0 | O15: 541.23816 | P15: =SUM(C15:O15) -> 6576.4579 | V15: C.H. CHARCANI IV | X15: 356.05
B16: 05:00 | C16: 945.2 | D16: 1940.8247 | E16: 2995.0053 | F16: 23.9 | G16: 0 | J16: =+DESPACHO_EJECUTADO!FF20+DESPACHO_EJECUTADO!FG20 -> 62.6 | L16: 84.2 | M16: 7.4 | N16: 0 | O16: 519.79035 | P16: =SUM(C16:O16) -> 6578.9203 | V16: C.H. CHARCANI V | X16: 2230.85
B17: 05:30 | C17: 955.4 | D17: 2062.4309 | E17: 3014.623 | F17: 24 | G17: 0 | J17: =+DESPACHO_EJECUTADO!FF21+DESPACHO_EJECUTADO!FG21 -> 62.6 | L17: 89.5 | M17: 7.4 | N17: 26.81957 | O17: 487.41723 | P17: =SUM(C17:O17) -> 6730.1906 | U17: EGEJUNIN | V17: C.H. HUASAHUASI I | W17: 159.65
B18: 06:00 | C18: 967.8 | D18: 1982.699 | E18: 2950.3905 | F18: 24.1 | G18: 0 | J18: =+DESPACHO_EJECUTADO!FF22+DESPACHO_EJECUTADO!FG22 -> 63 | L18: 88.5 | M18: 7.4 | N18: 126.82892 | O18: 464.88215 | P18: =SUM(C18:O18) -> 6675.6005 | V18: C.H. RUNATULLO II | W18: 340.3
B19: 06:30 | C19: 928.8 | D19: 1920.6999 | E19: 2985.6098 | F19: 23.5 | G19: 0 | J19: =+DESPACHO_EJECUTADO!FF23+DESPACHO_EJECUTADO!FG23 -> 62.6 | L19: 82.4 | M19: 7.4 | N19: 417.43277 | O19: 383.08049 | P19: =SUM(C19:O19) -> 6811.523 | V19: C.H. RUNATULLO III | W19: 385.6
B20: 07:00 | C20: 949.8 | D20: 1874.0773 | E20: 2985.6896 | F20: 24.4 | G20: 0 | J20: =+DESPACHO_EJECUTADO!FF24+DESPACHO_EJECUTADO!FG24 -> 62.5 | L20: 82.8 | M20: 7.4 | N20: 653.25334 | O20: 356.25884 | P20: =SUM(C20:O20) -> 6996.1791 | V20: C.H. SANTA CRUZ I | W20: 158.1
B21: 07:30 | C21: 950.8 | D21: 1858.6881 | E21: 3013.8677 | F21: 23.9 | G21: 0 | J21: =+DESPACHO_EJECUTADO!FF25+DESPACHO_EJECUTADO!FG25 -> 62.6 | L21: 88.4 | M21: 7.4 | N21: 715.06497 | O21: 404.00198 | P21: =SUM(C21:O21) -> 7124.7227 | U21: EGEMSA | V21: C.H. MACHUPICCHU | W21: 3927.9
B22: 08:00 | C22: 945.9 | D22: 1854.1498 | E22: 2998.0972 | F22: 39.8 | G22: 0 | J22: =+DESPACHO_EJECUTADO!FF26+DESPACHO_EJECUTADO!FG26 -> 62.5 | L22: 85.3 | M22: 7.4 | N22: 890.71444 | O22: 423.3928 | P22: =SUM(C22:O22) -> 7307.2543 | U22: EGESUR | V22: C.H. ARICOTA I | X22: 174.95
B23: 08:30 | C23: 928.1 | D23: 1910.8705 | E23: 2985.2883 | F23: 47.1 | G23: 0 | J23: =+DESPACHO_EJECUTADO!FF27+DESPACHO_EJECUTADO!FG27 -> 62.3 | L23: 82 | M23: 7.4 | N23: 923.86116 | O23: 418.8559 | P23: =SUM(C23:O23) -> 7365.7759 | U23: ELECTRICA YANAPAMPA SAC | V23: C.H. YANAPAMPA | W23: 52.75
B24: 09:00 | C24: 930.5 | D24: 2082.8364 | E24: 2993.8921 | F24: 46.4 | G24: 0 | J24: =+DESPACHO_EJECUTADO!FF28+DESPACHO_EJECUTADO!FG28 -> 62.3 | L24: 86 | M24: 7.4 | N24: 941.61935 | O24: 458.61744 | P24: =SUM(C24:O24) -> 7609.5652 | U24: ELECTROPERU | V24: C.H. MANTARO | X24: 12264.8
B25: 09:30 | C25: 951.3 | D25: 2203.4958 | E25: 2980.7835 | F25: 46.3 | G25: 0 | J25: =+DESPACHO_EJECUTADO!FF29+DESPACHO_EJECUTADO!FG29 -> 62.2 | L25: 88.7 | M25: 7.4 | N25: 955.11531 | O25: 503.98094 | P25: =SUM(C25:O25) -> 7799.2755 | V25: C.H. RESTITUCION | W25: 4052.6
B26: 10:00 | C26: 952.1 | D26: 2297.1558 | E26: 2985.8304 | F26: 45.8 | G26: 0 | J26: =+DESPACHO_EJECUTADO!FF30+DESPACHO_EJECUTADO!FG30 -> 62 | L26: 86.6 | M26: 7 | N26: 962.15877 | O26: 453.03545 | P26: =SUM(C26:O26) -> 7851.6805 | U26: EMPRESA DE GENERACION ELECTRICA CANCHAYLLO SAC | V26: C.H. CANCHAYLLO | W26: 94.5
B27: 10:30 | C27: 958.3 | D27: 2491.0223 | E27: 2971.8855 | F27: 46.2 | G27: 0 | J27: =+DESPACHO_EJECUTADO!FF31+DESPACHO_EJECUTADO!FG31 -> 61.7 | L27: 87.9 | M27: 7.4 | N27: 938.45093 | O27: 414.92514 | P27: =SUM(C27:O27) -> 7977.7838 | U27: EMPRESA DE GENERACION ELECTRICA RIO BAÑOS S.A.C. | V27: C.H. RUCUY | W27: 265.35
B28: 11:00 | C28: 948.2 | D28: 2473.9051 | E28: 2975.3211 | F28: 46.2 | G28: 0 | J28: =+DESPACHO_EJECUTADO!FF32+DESPACHO_EJECUTADO!FG32 -> 62.2 | L28: 86.1 | M28: 7.4 | N28: 975.83884 | O28: 404.20154 | P28: =SUM(C28:O28) -> 7979.3666 | U28: EMPRESA DE GENERACION ELECTRICA SANTA ANA S.A.C. | V28: C.H. RENOVANDES H1 | W28: 466.1
B29: 11:30 | C29: 946.3 | D29: 2593.0208 | E29: 2951.5129 | F29: 46.7 | G29: 44.8 | J29: =+DESPACHO_EJECUTADO!FF33+DESPACHO_EJECUTADO!FG33 -> 62.1 | L29: 81.4 | M29: 7.4 | N29: 975.33831 | O29: 462.54109 | P29: =SUM(C29:O29) -> 8171.113 | U29: EMPRESA DE GENERACION HUALLAGA | V29: C.H. CHAGLLA | X29: 4367.5
B30: 12:00 | C30: 947 | D30: 2509.2328 | E30: 2931.8768 | F30: 44.5 | G30: 45 | J30: =+DESPACHO_EJECUTADO!FF34+DESPACHO_EJECUTADO!FG34 -> 62.2 | L30: 88.4 | M30: 7.4 | N30: 981.35995 | O30: 436.00406 | P30: =SUM(C30:O30) -> 8052.9736 | V30: P.C.H. CHAGLLA | W30: 156
B31: 12:30 | C31: 960.2 | D31: 2332.4623 | E31: 2960.6967 | F31: 24.1 | G31: 45.9 | J31: =+DESPACHO_EJECUTADO!FF35+DESPACHO_EJECUTADO!FG35 -> 61.7 | L31: 88.2 | M31: 7.4 | N31: 966.73656 | O31: 468.72958 | P31: =SUM(C31:O31) -> 7916.1251 | U31: EMPRESA DE GENERACION HUANZA | V31: C.H. HUANZA | X31: 1094.05
B32: 13:00 | C32: 943.1 | D32: 2138.6081 | E32: 3114.0945 | F32: 24.5 | G32: 43.7 | J32: =+DESPACHO_EJECUTADO!FF36+DESPACHO_EJECUTADO!FG36 -> 61.5 | L32: 88 | M32: 7.4 | N32: 966.05163 | O32: 480.7377 | P32: =SUM(C32:O32) -> 7867.6919 | U32: EMPRESA ELECTRICA AGUA AZUL | V32: C.H. POTRERO | W32: 138.1
B33: 13:30 | C33: 950.2 | D33: 2164.2015 | E33: 3090.3732 | F33: 25.2 | G33: 44.1 | J33: =+DESPACHO_EJECUTADO!FF37+DESPACHO_EJECUTADO!FG37 -> 61.3 | L33: 88.1 | M33: 7.4 | N33: 963.35769 | O33: 541.79941 | P33: =SUM(C33:O33) -> 7936.0318 | U33: EMPRESA ELECTRICA RIO DOBLE | V33: C.H. LAS PIZARRAS | W33: 308.15
B34: 14:00 | C34: 967.1 | D34: 2123.9465 | E34: 3046.7579 | F34: 25.2 | G34: 82.1 | J34: =+DESPACHO_EJECUTADO!FF38+DESPACHO_EJECUTADO!FG38 -> 61.3 | L34: 81.9 | M34: 7.4 | N34: 949.71796 | O34: 623.86636 | P34: =SUM(C34:O34) -> 7969.2887 | U34: ENGIE ENERGIA PERU S.A.A. | V34: C.H. YUNCAN | X34: 1624.9129
B35: 14:30 | C35: 971 | D35: 2112.2442 | E35: 3075.534 | F35: 24.3 | G35: 80.6 | J35: =+DESPACHO_EJECUTADO!FF39+DESPACHO_EJECUTADO!FG39 -> 62.2 | L35: 85 | M35: 7.4 | N35: 932.6527 | O35: 663.31777 | P35: =SUM(C35:O35) -> 8014.2486 | U35: GENERACIÓN ANDINA S.A.C. | V35: C.H. 8 DE AGOSTO | W35: 326.65
B36: 15:00 | C36: 967.6 | D36: 2128.4111 | E36: 3118.8262 | F36: 44.6 | G36: 79.7 | J36: =+DESPACHO_EJECUTADO!FF40+DESPACHO_EJECUTADO!FG40 -> 61.7 | L36: 86.4 | M36: 7.4 | N36: 920.73218 | O36: 620.74163 | P36: =SUM(C36:O36) -> 8036.1112 | V36: C.H. EL CARMEN | W36: 97.4
B37: 15:30 | C37: 968.1 | D37: 2109.3524 | E37: 3094.1875 | F37: 45.8 | G37: 78.8 | J37: =+DESPACHO_EJECUTADO!FF41+DESPACHO_EJECUTADO!FG41 -> 62.4 | L37: 85.5 | M37: 7.4 | N37: 874.75471 | O37: 636.94414 | P37: =SUM(C37:O37) -> 7963.2387 | U37: GENERADORA DE ENERGÍA DEL PERÚ | V37: C.H. ÁNGEL I | W37: 489.6
B38: 16:00 | C38: 977.2 | D38: 2100.7793 | E38: 3097.385 | F38: 45.6 | G38: 79.6 | J38: =+DESPACHO_EJECUTADO!FF42+DESPACHO_EJECUTADO!FG42 -> 62.1 | L38: 84.8 | M38: 7.4 | N38: 824.80001 | O38: 639.41929 | P38: =SUM(C38:O38) -> 7919.0836 | V38: C.H. ÁNGEL II | W38: 489.6
B39: 16:30 | C39: 973.9 | D39: 2104.8337 | E39: 3119.1659 | F39: 45.5 | G39: 78.8 | J39: =+DESPACHO_EJECUTADO!FF43+DESPACHO_EJECUTADO!FG43 -> 61.7 | L39: 86.7 | M39: 7.4 | N39: 753.51166 | O39: 663.28383 | P39: =SUM(C39:O39) -> 7894.795 | V39: C.H. ÁNGEL III | W39: 480
B40: 17:00 | C40: 975.1 | D40: 2257.755 | E40: 3134.8485 | F40: 46.3 | G40: 80.1 | J40: =+DESPACHO_EJECUTADO!FF44+DESPACHO_EJECUTADO!FG44 -> 61.5 | L40: 87.2 | M40: 7.4 | N40: 551.36214 | O40: 661.78895 | P40: =SUM(C40:O40) -> 7863.3545 | V40: C.H. LA JOYA | W40: 199.95
B41: 17:30 | C41: 1000.1 | D41: 2421.3138 | E41: 3168.6766 | F41: 47.5 | G41: 79.8 | J41: =+DESPACHO_EJECUTADO!FF45+DESPACHO_EJECUTADO!FG45 -> 61.4 | L41: 83.6 | M41: 7.4 | N41: 256.8107 | O41: 676.96203 | P41: =SUM(C41:O41) -> 7803.5631 | U41: HIDROCAÑETE S.A. | V41: C.H. IMPERIAL | W41: 64.95
B42: 18:00 | C42: 997.9 | D42: 2481.3966 | E42: 3173.825 | F42: 47.3 | G42: 80 | J42: =+DESPACHO_EJECUTADO!FF46+DESPACHO_EJECUTADO!FG46 -> 61 | L42: 87.6 | M42: 7.4 | N42: 34.15435 | O42: 650.41382 | P42: =SUM(C42:O42) -> 7620.9898 | U42: HIDROELECTRICA HUANCHOR S.A.C. | V42: C.H. HUANCHOR | W42: 443.85
B43: 18:30 | C43: 992.8 | D43: 2588.5164 | E43: 3166.9218 | F43: 47.1 | G43: 79.8 | J43: =+DESPACHO_EJECUTADO!FF47+DESPACHO_EJECUTADO!FG47 -> 61.1 | L43: 87 | M43: 7.4 | N43: 0 | O43: 669.24371 | P43: =SUM(C43:O43) -> 7699.8819 | U43: HUAURA POWER GROUP S.A. | V43: C.H. YARUCAYA | W43: 422.35
B44: 19:00 | C44: 1020.5 | D44: 2736.6838 | E44: 3231.1963 | F44: 47.2 | G44: 80.9 | J44: =+DESPACHO_EJECUTADO!FF48+DESPACHO_EJECUTADO!FG48 -> 61.1 | L44: 87.8 | M44: 7.4 | N44: 0 | O44: 587.3426 | P44: =SUM(C44:O44) -> 7860.1228 | U44: HYDRO GLOBAL PERÚ S.A.C. | V44: CH SAN GABAN III | X44: 4862.15
B45: 19:30 | C45: 1023.7 | D45: 2833.7326 | E45: 3239.6259 | F45: 47.2 | G45: 80.6 | J45: =+DESPACHO_EJECUTADO!FF49+DESPACHO_EJECUTADO!FG49 -> 61.4 | L45: 85.8 | M45: 7.4 | N45: 0 | O45: 543.70176 | P45: =SUM(C45:O45) -> 7923.1602 | U45: INLAND ENERGY SAC | V45: C.H. SANTA TERESA | W45: 1368.3
B46: 20:00 | C46: 1020.5 | D46: 2857.5454 | E46: 3243.4899 | F46: 47.3 | G46: 81.3 | J46: =+DESPACHO_EJECUTADO!FF50+DESPACHO_EJECUTADO!FG50 -> 61.1 | L46: 86.8 | M46: 7.4 | N46: 0 | O46: 473.79216 | P46: =SUM(C46:O46) -> 7879.2275 | U46: KALLPA GENERACION S.A. | V46: C.H. CERRO DEL AGUILA | X46: 5922.1
B47: 20:30 | C47: 1042.7 | D47: 2842.9639 | E47: 3267.6989 | F47: 47.4 | G47: 81.6 | J47: =+DESPACHO_EJECUTADO!FF51+DESPACHO_EJECUTADO!FG51 -> 61 | L47: 87 | M47: 7.4 | N47: 0 | O47: 446.9479 | P47: =SUM(C47:O47) -> 7884.7106 | V47: M.C.H. CERRO DEL AGUILA | W47: 237.55
B48: 21:00 | C48: 1042.2 | D48: 2871.7845 | E48: 3262.9226 | F48: 47.3 | G48: 81.4 | J48: =+DESPACHO_EJECUTADO!FF52+DESPACHO_EJECUTADO!FG52 -> 60.9 | L48: 82.8 | M48: 7.4 | N48: 0 | O48: 412.26286 | P48: =SUM(C48:O48) -> 7868.9699 | U48: LA VIRGEN | V48: C.H. LA VIRGEN | X48: 1040.1
B49: 21:30 | C49: 1039.7 | D49: 2860.6774 | E49: 3241.2727 | F49: 47.2 | G49: 80.6 | J49: =+DESPACHO_EJECUTADO!FF53+DESPACHO_EJECUTADO!FG53 -> 61 | L49: 82.682 | M49: 7.4 | N49: 0 | O49: 390.50931 | P49: =SUM(C49:O49) -> 7811.0414 | U49: MAJA ENERGIA S.A.C. | V49: C.H. RONCADOR | W49: 37.45
B50: 22:00 | C50: 1011.8 | D50: 2896.0275 | E50: 3243.1652 | F50: 47 | G50: 79.9 | J50: =+DESPACHO_EJECUTADO!FF54+DESPACHO_EJECUTADO!FG54 -> 61 | L50: 82.361 | M50: 7.4 | N50: 0 | O50: 366.19474 | P50: =SUM(C50:O50) -> 7794.8484 | U50: ORAZUL ENERGY PERÚ | V50: C.H. CAÑON DEL PATO | X50: 3469.7
B51: 22:30 | C51: 1011.3 | D51: 2939.0678 | E51: 3189.4671 | F51: 47.5 | G51: 81.3 | J51: =+DESPACHO_EJECUTADO!FF55+DESPACHO_EJECUTADO!FG55 -> 61.2 | L51: 85.253 | M51: 7.4 | N51: 0 | O51: 308.59409 | P51: =SUM(C51:O51) -> 7731.082 | V51: C.H. CARHUAQUERO | X51: 1709.7
B52: 23:00 | C52: 985.6 | D52: 2791.3867 | E52: 3224.2906 | F52: 47.2 | G52: 81.6 | J52: =+DESPACHO_EJECUTADO!FF56+DESPACHO_EJECUTADO!FG56 -> 61.2 | L52: 85.5 | M52: 7.4 | N52: 0 | O52: 265.8512 | P52: =SUM(C52:O52) -> 7550.0284 | V52: C.H. CARHUAQUERO IV | W52: 237.45
B53: 23:30 | C53: 965.3 | D53: 2517.8672 | E53: 3196.8261 | F53: 47.7 | G53: 79.4 | J53: =+DESPACHO_EJECUTADO!FF57+DESPACHO_EJECUTADO!FG57 -> 61.2 | L53: 83.683 | M53: 7.4 | N53: 0 | O53: 257.39589 | P53: =SUM(C53:O53) -> 7216.7722 | U53: ORYGEN PERU S.A.A. | V53: C.H. CALLAHUANCA | X53: 1646.55
B54: 00:00 | C54: 990.2 | D54: 2423.9201 | E54: 3167.2892 | F54: 47 | G54: 80.4 | J54: =+DESPACHO_EJECUTADO!FF58+DESPACHO_EJECUTADO!FG58 -> 61.3 | L54: 83.96 | M54: 7.4 | N54: 0 | O54: 257.52961 | P54: =SUM(C54:O54) -> 7118.9989 | V54: C.H. HER 1 | W54: 13.65
B55: TOTAL MWh | C55: =SUM(C7:C54)/2 -> 23214.25 | D55: =SUM(D7:D54)/2 -> 54568.463 | E55: =SUM(E7:E54)/2 -> 73662.207 | F55: =SUM(F7:F54)/2 -> 890.75 | G55: =SUM(G7:G54)/2 -> 955.9 | H55: =SUM(H7:H54)/2 -> 0 | I55: =SUM(I7:I54)/2 -> 0 | J55: =SUM(J7:J54)/2 -> 1482.9 | ... P55: =SUM(P7:P54)/2 -> 178977.8 | V55: C.H. HUAMPANI | W55: 674.55
B56: % | C56: =C55*100/$P$55 -> 12.970463 | D56: =D55*100/$P$55 -> 30.488956 | E56: =E55*100/$P$55 -> 41.157176 | F56: =F55*100/$P$55 -> 0.49768743 | G56: =G55*100/$P$55 -> 0.53408859 | H56: =H55*100/$P$55 -> 0 | I56: =I55*100/$P$55 -> 0 | J56: =J55*100/$P$55 -> 0.82853852 | ... P56: =P55*100/$P$55 -> 100 | V56: C.H. HUINCO | X56: 2594.95
V57: C.H. MATUCANA | X57: 2377.7
V58: C.H. MOYOPAMPA | W58: 1528.35
U59: SAN GABAN | V59: C.H. SAN GABAN II | X59: 2656.5
V60: PCH TUPURI | W60: 26.1
U61: SINERSA | V61: C.H. CHANCAY | W61: 470.6
V62: C.H. POECHOS II | W62: 98.4
U63: STATKRAFT S.A | V63: C.H. ARCATA | W63: 96
V64: C.H. CAHUA | W64: 587.15
V65: C.H. CHEVES | X65: 929.55
V66: C.H. GALLITO CIEGO | X66: 770.2
V67: C.H. MALPASO | X67: 202.9
V68: C.H. YAUPI | W68: 2392.7
U69: TRANSMISION ANDINA DE GENERACION S.A.C. | V69: C.H. OROYA | W69: 134.8
V70: C.H. PACHACHACA | W70: 38.4
U71: VARI ENERGIA S.A.C. | V71: C.H. ANASHIRONI | W71: 208.55
U72: TOTAL MWh | W72: 23214.25 | X72: 54568.463

Sheet GENERACION RER
B3: martes, 16 de Diciembre del 2025
B5: GENERACIÓN ELÉCTRICA DE LAS CENTRALES RER (MW)
B6: HORA | C6: AGRO INDUSTRIAL PARAMONGA S.A. | D6: AGROAURORA S.A.C. | E6: AGROINDUSTRIAS SAN JACINTO S.A.A. | F6: AGROLMOS SOCIEDAD ANONIMA - AGROLMOS S.A. | G6: ANDEAN POWER S.A.C. | H6: ASOCIACIÓN SANTA LUCIA DE CHACAS | I6: ATRIA ENERGIA S.A.C. | J6: BIOENERGIA DEL CHIRA S.A. | K6: CASA GRANDE S.A.A. | L6: CELARIS ENERGY S.A. | M6: COLCA SOLAR S.A.C. | N6: EGEJUNIN | S6: ELECTRICA YANAPAMPA SAC | T6: EMPRESA DE GENERACION ELECTRICA CANCHAYLLO SAC | U6: EMPRESA DE GENERACION ELECTRICA RIO BAÑOS S.A.C. | V6: EMPRESA DE GENERACION ELECTRICA SANTA ANA S.A.C. | W6: EMPRESA ELECTRICA AGUA AZUL | X6: EMPRESA ELECTRICA RIO DOBLE | Y6: ENERGÍA EÓLICA S.A. | AA6: ENERGIA RENOVABLE DEL SUR S.A. | AB6: ENGIE ENERGIA PERU S.A.A. | AF6: GENERACIÓN ANDINA S.A.C. | AH6: GENERADORA DE ENERGÍA DEL PERÚ | AL6: GR CORTARRAMA SOCIEDAD ANONIMA CERRADA | AM6: GR PAINO SOCIEDAD ANONIMA CERRADA | AN6: GR TARUCA SOCIEDAD ANONIMA CERRADA | AO6: HIDROCAÑETE S.A. | AP6: HUAURA POWER GROUP S.A. | AQ6: HYDRO PATAPO S.A.C. | AR6: JOYA SOLAR S.A.C. | AT6: KALLPA GENERACION S.A. | AV6: KONDU SAC | AW6: MAJA ENERGIA S.A.C. | AX6: MAJES ARCUS S.A.C. | AZ6: MOQUEGUA FV S.A.C. | BA6: ORAZUL ENERGY PERÚ | BC6: ORYGEN PERU S.A.A. | BH6: PANAMERICANA SOLAR SAC. | BI6: PARQUE EOLICO MARCONA S.A.C. | BJ6: PARQUE EOLICO TRES HERMANAS S.A.C. | BK6: PETRAMAS | BO6: REPARTICIÓN ARCUS S.A.C. | BP6: SAN GABAN | BQ6: SINERSA | BS6: TACNA SOLAR SAC. | BT6: VARI ENERGIA S.A.C. | BU6: TOTAL RER
C7: C.T. PARAMONGA | D7: C.T. MAPLE | E7: C.T SAN JACINTO | F7: C.T. AGROLMOS | G7: C.H. CARHUAC | H7: C.H. HUALLIN | I7: C.H. PURMACANA | J7: C.T. CAÑA BRAVA | K7: C.T. CASA GRANDE | L7: C.H. MANTA | M7: CS YARUCAYA | N7: C.H. HUASAHUASI I | O7: C.H. HUASAHUASI II | P7: C.H. RUNATULLO II | Q7: C.H. RUNATULLO III | R7: C.H. STA CRUZ I y II | S7: C.H. YANAPAMPA | T7: C.H. CANCHAYLLO | U7: C.H. RUCUY | V7: C.H. RENOVANDES H1 | W7: C.H. POTRERO | X7: C.H. LAS PIZARRAS | Y7: C.E. CUPISNIQUE | Z7: C.E. TALARA | AA7: CE SAN JUAN | AB7: C.E. P LOM EXPANSION | AC7: C.E. PUNTA LOMITAS | AD7: C.S. INTIPAMPA | AE7: CS EXPANSIÓN INTIPAMPA | AF7: C.H. 8 DE AGOSTO | AG7: C.H. EL CARMEN | AH7: C.H. ANGEL I | AI7: C.H. ANGEL II | AJ7: C.H. ANGEL III | AK7: C.H. LA JOYA | AL7: CS MATARANI | AM7: C.E. HUAMBOS | AN7: C.E. DUNA | AO7: C.H. NUEVAIMPERIAL | AP7: C.H. YARUCAYA | AQ7: MCH PATAPO | AR7: C.S. ILLA 1 | AS7: CS SAN MARTIN SOLAR | AT7: C.S. SUNNY EXPANSION | AU7: CS SUNNY | AV7: CARHUAQUERO (CS) | AW7: C.H. RONCADOR | AX7: C.S. MAJES | AY7: C.S. SOL DE VERANO | AZ7: C.S. MOQUEGUA FV | BA7: C.H. CANA BRAVA | BB7: C.H. CARHUAQUERO4 | BC7: C.E. WAYRA EXTENSION | BD7: C.E. WAYRA I | BE7: C.H. HER 1 | BF7: C.S. CLEMESI | BG7: C.S. RUBI | BH7: C.S. PANAMERICANA-SOLAR | BI7: C.E. MARCONA | BJ7: C.E. 3 HERMANAS | BK7: C.T. HUAYCOLORO | BL7: C.T. LA GRINGA V | BM7: CTB CALLAO | BN7: CTB. DONA CATALINA | BO7: C.S. REPARTICION | BP7: C.H. TUPURI | BQ7: C.H. CHANCAY | BR7: C.H. POECHOS2 | BS7: C.S. TACNA-SOLAR | BT7: C.H. ANASHIRONI | BU7: MW
B8: 0:30 | C8: 18 | D8: 18.6 | E8: 7 | F8: 11.1 | G8: 8.7 | H8: 2.8 | J8: 9.2 | K8: 22.2 | L8: 6.3 | N8: 6.3 | P8: 9.4 | Q8: 12.4 | R8: 6.7 | S8: 2.3 | T8: 3.8 | U8: 10 | V8: 20.1 | W8: 5.4 | X8: 13.1 | Y8: 13 | Z8: 14.5 | AA8: 121.2 | AB8: 5.40905 | AC8: 135.4913 | AF8: 12.5 | AG8: 4.5 | AH8: 20.4 | AI8: 20.4 | AJ8: 20 | AK8: 8.5 | AM8: 0.9 | AN8: 0.7 | AO8: 2.9 | AP8: 17.6 | AW8: 1.4 | BB8: 9.9 | BC8: 49.3 | BD8: 46.5 | BE8: 0.6 | BI8: 30.1 | BJ8: 90 | BK8: 2.9 | BL8: 1.2 | BM8: 2.1 | BN8: 1.2 | BP8: 1 | BQ8: 20.2 | BR8: 4.1 | BT8: 3 | BU8: 854.90035
B9: 1:00 | C9: 17.8 | D9: 19.4 | E9: 6 | F9: 11.1 | G9: 8.6 | H9: 2.7 | J9: 8.7 | K9: 21.6 | L9: 6.8 | N9: 6.3 | P9: 9.8 | Q9: 12.7 | R9: 6.7 | S9: 2.1 | T9: 4 | U9: 10 | V9: 20.5 | W9: 5.2 | X9: 13.1 | Y9: 8.5 | Z9: 18.2 | AA9: 124.1 | AB9: 11.59819 | AC9: 156.36299 | AF9: 12.5 | AG9: 4.5 | AH9: 20.4 | AI9: 20.4 | AJ9: 20 | AK9: 8.5 | AM9: 1 | AN9: 0.3 | AO9: 2.9 | AP9: 17.6 | AW9: 1.5 | BB9: 9.9 | BC9: 90 | BD9: 80.4 | BE9: 0.6 | BI9: 30 | BJ9: 90.8 | BK9: 2.9 | BL9: 1.2 | BM9: 2.1 | BN9: 1.2 | BP9: 1 | BQ9: 20 | BR9: 4.1 | BT9: 3.2 | BU9: 958.86118
B10: 1:30 | C10: 17.8 | D10: 20.3 | E10: 7.6 | F10: 11.1 | G10: 5.6 | H10: 2.7 | J10: 9 | K10: 21.2 | L10: 7.3 | N10: 6.4 | P10: 9 | Q10: 12.3 | R10: 6.7 | S10: 2.2 | T10: 4 | U10: 10 | V10: 20 | W10: 5.2 | X10: 13.1 | Y10: 8.1 | Z10: 14.2 | AA10: 122.1 | AB10: 11.10684 | AC10: 158.16744 | AF10: 12.5 | AG10: 4.5 | AH10: 20.4 | AI10: 20.4 | AJ10: 20 | AK10: 8.5 | AM10: 0.7 | AN10: 0.4 | AO10: 2.9 | AP10: 17.6 | AW10: 1.5 | BB10: 10 | BC10: 106.2 | BD10: 97.4 | BE10: 0.6 | BI10: 30.1 | BJ10: 89.9 | BK10: 2.9 | BL10: 1.2 | BM10: 2.1 | BN10: 1.2 | BP10: 1 | BQ10: 20 | BR10: 4.1 | BT10: 3 | BU10: 984.27428
B11: 2:00 | C11: 18 | D11: 20.3 | E11: 8.3 | F11: 11.1 | G11: 0.7 | H11: 2.6 | J11: 8.4 | K11: 21 | L11: 7.5 | N11: 6.4 | P11: 9.8 | Q11: 12.7 | R11: 6.7 | S11: 2.2 | T11: 3.9 | U11: 10 | V11: 20.6 | W11: 5.2 | X11: 13.1 | Y11: 9.2 | Z11: 12.7 | AA11: 121 | AB11: 8.09663 | AC11: 165.72574 | AF11: 12.3 | AG11: 4.4 | AH11: 20.4 | AI11: 20.4 | AJ11: 20 | AK11: 8.5 | AM11: 0.6 | AN11: 0.2 | AO11: 2.9 | AP11: 17.6 | AW11: 1.5 | BB11: 9.9 | BC11: 131.4 | BD11: 109.1 | BE11: 0.6 | BI11: 29.9 | BJ11: 89.7 | BK11: 2.9 | BL11: 1.2 | BM11: 2.1 | BN11: 1.2 | BP11: 1 | BQ11: 20 | BR11: 4.1 | BT11: 3.2 | BU11: 1020.3224
B12: 2:30 | C12: 17.9 | D12: 20.3 | E12: 8.4 | F12: 11.1 | H12: 2.6 | J12: 9.4 | K12: 18.4 | L12: 7.2 | N12: 6.6 | P12: 9.2 | Q12: 12.2 | R12: 6.7 | S12: 2.1 | T12: 3.8 | U12: 10 | V12: 20 | W12: 5.2 | X12: 13 | Y12: 8.9 | Z12: 14 | AA12: 118.8 | AB12: 9.95099 | AC12: 164.65333 | AF12: 12.2 | AG12: 4.4 | AH12: 20.4 | AI12: 20.4 | AJ12: 20 | AK12: 8.4 | AM12: 0.5 | AO12: 3 | AP12: 17.6 | AW12: 1.5 | BB12: 9.9 | BC12: 132.6 | BD12: 108.6 | BE12: 0.6 | BI12: 29.5 | BJ12: 86.9 | BK12: 2.9 | BL12: 1.2 | BM12: 2.1 | BN12: 1.2 | BP12: 0.9 | BQ12: 20 | BR12: 4.1 | BT12: 2.9 | BU12: 1012.2043
B13: 3:00 | C13: 17.9 | D13: 20.3 | E13: 8.5 | F13: 11.1 | H13: 2.6 | J13: 9.6 | K13: 22 | L13: 7 | N13: 6.6 | P13: 10 | Q13: 12.9 | R13: 6.7 | S13: 2.1 | T13: 3.8 | U13: 9.9 | V13: 20.6 | W13: 5.3 | X13: 13 | Y13: 8.9 | Z13: 15.2 | AA13: 112.8 | AB13: 9.80967 | AC13: 178.72676 | AF13: 12.1 | AG13: 4.4 | AH13: 20.4 | AI13: 20.4 | AJ13: 20 | AK13: 8.4 | AM13: 0.4 | AO13: 3 | AP13: 17.6 | AW13: 1.5 | BB13: 9.9 | BC13: 117.1 | BD13: 106.8 | BE13: 0.6 | BI13: 27.6 | BJ13: 78.5 | BK13: 2.9 | BL13: 1.2 | BM13: 2.1 | BN13: 1.2 | BP13: 1 | BQ13: 20 | BR13: 4.1 | BT13: 3.1 | BU13: 999.63643
B14: 3:30 | C14: 18.5 | D14: 20.3 | E14: 8.8 | F14: 11.1 | H14: 2.6 | J14: 9.6 | K14: 22.2 | L14: 7 | N14: 6.6 | P14: 10 | Q14: 12.6 | R14: 6.7 | S14: 2.1 | T14: 4 | U14: 10 | V14: 20.3 | W14: 6 | X14: 13 | Y14: 6.3 | Z14: 15.3 | AA14: 108.1 | AB14: 9.16378 | AC14: 170.45915 | AF14: 12 | AG14: 4.3 | AH14: 20.4 | AI14: 20.4 | AJ14: 20 | AK14: 8.4 | AO14: 2.9 | AP14: 17.6 | AW14: 1.5 | BB14: 9.9 | BC14: 116 | BD14: 103.8 | BE14: 0.6 | BI14: 26 | BJ14: 77 | BK14: 2.9 | BL14: 1.2 | BM14: 2.1 | BN14: 1.2 | BP14: 0.9 | BQ14: 20 | BR14: 4.1 | BT14: 3.1 | BU14: 977.02293
B15: 4:00 | C15: 18.2 | D15: 20.3 | E15: 8.3 | F15: 11.1 | H15: 2.6 | J15: 9.2 | K15: 19.7 | L15: 6.9 | N15: 6.6 | P15: 10.1 | Q15: 12.7 | R15: 6.7 | S15: 2.1 | T15: 3.9 | U15: 10 | V15: 20.3 | W15: 6.2 | X15: 13 | Y15: 6.3 | Z15: 15.1 | AA15: 103.6 | AB15: 4.28204 | AC15: 162.12194 | AF15: 11.8 | AG15: 4.3 | AH15: 20.4 | AI15: 20.4 | AJ15: 20 | AK15: 8.7 | AO15: 2.9 | AP15: 17.6 | AW15: 1.4 | BB15: 9.9 | BC15: 106 | BD15: 108.8 | BE15: 0.6 | BI15: 27.2 | BJ15: 80.5 | BK15: 2.9 | BL15: 1.2 | BM15: 2.1 | BN15: 1.2 | BP15: 0.9 | BQ15: 20 | BR15: 4.1 | BT15: 2.9 | BU15: 955.10398
B16: 4:30 | C16: 18.2 | D16: 20.3 | E16: 8.2 | F16: 11.1 | H16: 2.5 | J16: 9.1 | K16: 17.4 | L16: 6.9 | N16: 6.6 | P16: 10 | Q16: 13.7 | R16: 6.7 | S16: 2.1 | T16: 3.8 | U16: 10 | V16: 20.3 | W16: 6 | X16: 13 | Y16: 8 | Z16: 14 | AA16: 102.6 | AB16: 3.80642 | AC16: 126.03174 | AF16: 11.8 | AG16: 4.3 | AH16: 20.4 | AI16: 20.4 | AJ16: 20 | AK16: 8.6 | AO16: 2.9 | AP16: 17.6 | AW16: 1.5 | BB16: 9.9 | BC16: 93 | BD16: 96.4 | BE16: 0.6 | BI16: 25.5 | BJ16: 71.9 | BK16: 2.9 | BL16: 1.2 | BM16: 2.1 | BN16: 1.2 | BP16: 1 | BQ16: 20 | BR16: 4.1 | BT16: 2.9 | BU16: 880.53816
B17: 5:00 | C17: 18.1 | D17: 20.3 | E17: 8.1 | F17: 11.1 | H17: 2.5 | J17: 9.3 | K17: 17.3 | L17: 6.7 | N17: 6.6 | P17: 10 | Q17: 13.6 | R17: 6.7 | S17: 2.2 | T17: 3.8 | U17: 10 | V17: 20.6 | W17: 6 | X17: 13 | Y17: 9.3 | Z17: 9.4 | AA17: 97.9 | AB17: 6.14413 | AC17: 138.84622 | AF17: 11.5 | AG17: 4.2 | AH17: 20.4 | AI17: 20.4 | AJ17: 20 | AK17: 8.6 | AO17: 2.9 | AP17: 17.6 | AW17: 1.5 | BB17: 10 | BC17: 84 | BD17: 84.2 | BE17: 0.6 | BI17: 24.8 | BJ17: 65.2 | BK17: 2.9 | BL17: 1.2 | BM17: 2.1 | BN17: 1.2 | BP17: 1 | BQ17: 20 | BR17: 4.1 | BT17: 3 | BU17: 858.89035
B18: 5:30 | C18: 18.1 | D18: 20.3 | E18: 8.5 | F18: 11.1 | H18: 2.5 | J18: 8.7 | K18: 22.8 | L18: 6.6 | N18: 6.6 | P18: 9.9 | Q18: 13.6 | R18: 6.7 | S18: 2.1 | T18: 3.9 | U18: 10 | V18: 20.3 | W18: 5.9 | X18: 12.3 | Y18: 8.5 | Z18: 6.1 | AA18: 98.1 | AB18: 2.64711 | AC18: 130.57012 | AD18: 1.91957 | AF18: 11.5 | AG18: 4.2 | AH18: 20.4 | AI18: 20.4 | AJ18: 20 | AK18: 8.5 | AO18: 2.9 | AP18: 17.6 | AS18: 6 | AU18: 4.9 | AW18: 1.5 | AZ18: 0.2 | BB18: 9.9 | BC18: 69.6 | BD18: 79.1 | BE18: 0.6 | BF18: 6.5 | BG18: 6.8 | BH18: 0.1 | BI18: 25.8 | BJ18: 67 | BK18: 2.9 | BL18: 1.2 | BM18: 2.1 | BN18: 1.2 | BP18: 1.1 | BQ18: 20 | BR18: 4.1 | BS18: 0.4 | BT18: 2.9 | BU18: 857.1368
B19: 6:00 | C19: 17.8 | D19: 20.3 | E19: 8.1 | F19: 11.1 | G19: 4 | H19: 2.4 | J19: 8.8 | K19: 22.4 | L19: 6.7 | N19: 6.6 | P19: 10.1 | Q19: 13.7 | R19: 6.7 | S19: 2.1 | T19: 3.9 | U19: 10 | V19: 20 | W19: 5.8 | X19: 12.3 | Y19: 7 | Z19: 5.7 | AA19: 106.2 | AB19: 6.0624 | AC19: 130.61975 | AD19: 11.00892 | AE19: 1.72 | AF19: 11.5 | AG19: 4.2 | AH19: 20.4 | AI19: 20.4 | AJ19: 20 | AK19: 8.5 | AL19: 2.2 | AO19: 3 | AP19: 17.6 | AS19: 30.6 | AU19: 21.4 | AW19: 1.6 | AX19: 0.7 | AZ19: 0.5 | BB19: 9.9 | BC19: 55.6 | BD19: 57.3 | BE19: 0.6 | BF19: 24 | BG19: 32.5 | BH19: 0.4 | BI19: 26.3 | BJ19: 70.1 | BK19: 2.9 | BL19: 1.2 | BM19: 2.1 | BN19: 1.2 | BO19: 0.7 | BP19: 1.1 | BQ19: 20 | BR19: 4.1 | BS19: 1.1 | BT19: 2.8 | BU19: 937.61107
B20: 6:30 | C20: 18 | D20: 20.3 | E20: 8.8 | F20: 11.1 | G20: 5.9 | H20: 2.4 | J20: 9.3 | K20: 14.9 | L20: 6.6 | M20: 0.1 | N20: 6.6 | P20: 9.6 | Q20: 13.3 | R20: 6.7 | S20: 2.2 | T20: 3.8 | U20: 10 | V20: 20 | W20: 5.8 | X20: 12.3 | Y20: 5.3 | Z20: 4.5 | AA20: 106.8 | AB20: 3.88064 | AC20: 102.99985 | AD20: 17.78277 | AE20: 3.45 | AF20: 11.3 | AG20: 4.2 | AH20: 20.4 | AI20: 20.4 | AJ20: 20 | AK20: 8.6 | AL20: 5.5 | AO20: 3 | AP20: 17.5 | AS20: 162 | AU20: 98.9 | AW20: 1.4 | AX20: 2.1 | AZ20: 1.2 | BB20: 9.9 | BC20: 30.8 | BD20: 35.2 | BE20: 0.6 | BF20: 55 | BG20: 65.3 | BH20: 1 | BI20: 24.3 | BJ20: 69.3 | BK20: 2.9 | BL20: 1.2 | BM20: 2.1 | BN20: 1.2 | BO20: 2.3 | BP20: 1.1 | BQ20: 20 | BR20: 4.1 | BS20: 2.8 | BT20: 2.5 | BU20: 1140.5133
B21: 7:00 | C21: 18.1 | D21: 20.3 | E21: 8.4 | F21: 11.1 | G21: 8.6 | H21: 2.4 | J21: 9.3 | K21: 15.6 | L21: 6.6 | M21: 0.1 | N21: 6.6 | P21: 10.2 | Q21: 13.8 | R21: 6.7 | S21: 2.2 | T21: 3.9 | U21: 10 | V21: 20.4 | W21: 5.8 | X21: 12.4 | Y21: 3.5 | Z21: 4.5 | AA21: 96.5 | AB21: 5.36685 | AC21: 79.49199 | AD21: 27.18334 | AE21: 5.17 | AF21: 11.2 | AG21: 4.1 | AH21: 20.4 | AI21: 20.4 | AJ21: 20 | AK21: 8.6 | AL21: 8.1 | AO21: 2.9 | AP21: 17.8 | AS21: 198.1 | AU21: 155.1 | AW21: 1.4 | AX21: 4.6 | AZ21: 3.3 | BB21: 9.9 | BC21: 36.9 | BD21: 37.6 | BE21: 0.6 | BF21: 102.4 | BG21: 136.4 | BH21: 3.1 | BI21: 23.6 | BJ21: 68.8 | BK21: 2.9 | BL21: 1.2 | BM21: 2.1 | BN21: 1.2 | BO21: 3.9 | BP21: 1.1 | BQ21: 20 | BR21: 4.1 | BS21: 5.8 | BT21: 3.1 | BU21: 1354.9122
B22: 7:30 | C22: 18 | D22: 20.4 | E22: 8.3 | F22: 11.1 | G22: 8.6 | H22: 2.4 | J22: 9.3 | K22: 21.3 | L22: 6.5 | M22: 0.1 | N22: 6.5 | P22: 9.3 | Q22: 12.8 | R22: 6.7 | S22: 2.2 | T22: 3.9 | U22: 10 | V22: 20.7 | W22: 6.2 | X22: 12.4 | Y22: 1.6 | Z22: 5.3 | AA22: 100.7 | AB22: 4.98475 | AC22: 80.41723 | AD22: 34.97497 | AE22: 6.89 | AF22: 11.2 | AG22: 4.1 | AH22: 20.4 | AI22: 20.4 | AJ22: 20 | AK22: 8.6 | AL22: 27.8 | AO22: 3 | AP22: 17.8 | AS22: 220 | AU22: 170.7 | AV22: 0.1 | AW22: 1.4 | AX22: 6.4 | AZ22: 6.9 | BB22: 9.9 | BC22: 57.3 | BD22: 55.5 | BE22: 0.6 | BF22: 96.4 | BG22: 118.8 | BH22: 9.8 | BI22: 24.2 | BJ22: 74 | BK22: 2.9 | BL22: 1.2 | BM22: 2.1 | BN22: 1.2 | BO22: 6.2 | BP22: 1 | BQ22: 20 | BR22: 4.1 | BS22: 10 | BT22: 3.1 | BU22: 1468.667
B23: 8:00 | C23: 17.7 | D23: 20.4 | E23: 6.4 | F23: 11.1 | G23: 8.6 | H23: 2.4 | J23: 8.9 | K23: 20.8 | L23: 6.4 | M23: 0.2 | N23: 6.6 | P23: 9.2 | Q23: 12.5 | R23: 6.7 | S23: 2.2 | T23: 3.8 | U23: 10 | V23: 20.6 | W23: 6.2 | X23: 12.7 | Y23: 3.4 | Z23: 3.5 | AA23: 101.8 | AB23: 5.03593 | AC23: 89.05687 | AD23: 36.47444 | AE23: 10.34 | AF23: 11.2 | AG23: 4.1 | AH23: 20.4 | AI23: 20.4 | AJ23: 20 | AK23: 8.6 | AL23: 70.2 | AO23: 2.9 | AP23: 17.8 | AS23: 253 | AU23: 204.3 | AV23: 0.1 | AW23: 1.4 | AX23: 8.6 | AZ23: 14.3 | BB23: 9.9 | BC23: 58.6 | BD23: 53.7 | BE23: 0.6 | BF23: 107.9 | BG23: 142.5 | BH23: 18 | BI23: 25.9 | BJ23: 82.4 | BK23: 2.9 | BL23: 1.2 | BM23: 2.1 | BN23: 1.2 | BO23: 9.1 | BP23: 1 | BQ23: 20 | BR23: 4.1 | BS23: 15.7 | BT23: 3.9 | BU23: 1661.0072
B24: 8:30 | C24: 17.9 | D24: 20.4 | E24: 9.1 | F24: 11.1 | G24: 8.7 | H24: 2.3 | J24: 9.2 | K24: 14.3 | L24: 6.6 | M24: 0.6 | N24: 6.4 | P24: 8.5 | Q24: 12.5 | R24: 6.7 | S24: 2.3 | T24: 3.7 | U24: 10 | W24: 6.2 | X24: 12.7 | Y24: 5.6 | Z24: 1.9 | AA24: 99.8 | AB24: 8.041 | AC24: 101.2149 | AD24: 37.28116 | AE24: 13.78 | AF24: 11.1 | AG24: 4.1 | AH24: 20.4 | AI24: 20.4 | AJ24: 20 | AK24: 8.5 | AL24: 78.1 | AN24: 0.2 | AO24: 2.8 | AP24: 17.8 | AS24: 252.9 | AU24: 209.6 | AV24: 0.1 | AW24: 1.4 | AX24: 11.3 | AZ24: 15 | BB24: 10 | BC24: 51 | BD24: 48.6 | BE24: 0.6 | BF24: 110.8 | BG24: 145.4 | BH24: 18.5 | BI24: 27.3 | BJ24: 75.2 | BK24: 2.9 | BL24: 1.2 | BM24: 2.1 | BN24: 1.2 | BO24: 11 | BP24: 1 | BQ24: 20 | BR24: 4.1 | BS24: 19.5 | BU24: 1660.9171
B25: 9:00 | C25: 18 | D25: 19.8 | E25: 8.6 | F25: 11.1 | G25: 8.8 | H25: 2.3 | J25: 8.4 | K25: 20.1 | L25: 6.7 | M25: 0.8 | N25: 6.3 | P25: 8.8 | Q25: 12.3 | R25: 6.7 | S25: 2.2 | T25: 4 | U25: 10 | W25: 6.2 | X25: 12.7 | Y25: 5.3 | Z25: 0.9 | AA25: 102.5 | AB25: 9.43338 | AC25: 134.18406 | AD25: 38.28935 | AE25: 17.23 | AF25: 10.7 | AG25: 4.1 | AH25: 20.4 | AI25: 20.4 | AJ25: 20 | AK25: 8.3 | AL25: 78.5 | AM25: 0.2 | AN25: 1.1 | AO25: 2.6 | AP25: 17.8 | AS25: 253.2 | AU25: 213.8 | AV25: 0.2 | AW25: 1.4 | AX25: 12.8 | AZ25: 15.1 | BB25: 9.9 | BC25: 51.7 | BD25: 46.9 | BE25: 0.6 | BF25: 112.6 | BG25: 147.8 | BH25: 18.7 | BI25: 26.3 | BJ25: 80.1 | BK25: 2.9 | BL25: 1.2 | BM25: 2.1 | BN25: 1.2 | BO25: 13 | BP25: 0.9 | BQ25: 20 | BR25: 4.1 | BS25: 19.6 | BT25: 4.1 | BU25: 1725.9368
B26: 9:30 | C26: 17.7 | D26: 20.4 | E26: 8.8 | F26: 11.1 | G26: 8.7 | H26: 2.3 | J26: 8.1 | K26: 22.6 | L26: 6.5 | M26: 0.9 | N26: 6.3 | P26: 9.4 | Q26: 12.6 | R26: 6.7 | S26: 2.3 | T26: 4.1 | U26: 10 | V26: 20.6 | W26: 6.2 | X26: 12.7 | Y26: 8.3 | Z26: 0.4 | AA26: 92.1 | AB26: 19.19421 | AC26: 161.58673 | AD26: 39.33531 | AE26: 20.68 | AF26: 10.8 | AG26: 4.1 | AH26: 20.4 | AI26: 20.4 | AJ26: 20 | AK26: 8.6 | AL26: 78.8 | AM26: 2 | AN26: 2.8 | AO26: 2.6 | AP26: 17.8 | AS26: 253.2 | AU26: 217.8 | AV26: 0.2 | AW26: 1.4 | AX26: 14.6 | AZ26: 15.2 | BB26: 9.9 | BC26: 62.6 | BD26: 52.9 | BE26: 0.6 | BF26: 113.1 | BG26: 148.2 | BH26: 18.7 | BI26: 25 | BJ26: 77.1 | BK26: 2.9 | BL26: 1.2 | BM26: 2.1 | BN26: 1.2 | BO26: 14.7 | BP26: 0.9 | BQ26: 18.8 | BR26: 4.1 | BS26: 19.7 | BT26: 3 | BU26: 1806.9962
B27: 10:00 | C27: 17.9 | D27: 20.4 | E27: 8.4 | F27: 11.1 | G27: 8.6 | H27: 2.3 | J27: 9 | K27: 19.8 | L27: 6.5 | M27: 1 | N27: 6.3 | P27: 9.6 | Q27: 12.6 | R27: 6.7 | S27: 2.3 | T27: 4 | U27: 10 | V27: 20.6 | W27: 6.4 | X27: 12.7 | Y27: 14.4 | Z27: 0.3 | AA27: 78.3 | AB27: 26.43104 | AC27: 165.90441 | AD27: 39.43877 | AE27: 24.12 | AF27: 10.9 | AG27: 4 | AH27: 20.4 | AI27: 20.4 | AJ27: 20 | AK27: 8.6 | AL27: 78.4 | AM27: 4.3 | AN27: 4.5 | AO27: 2.6 | AP27: 17.8 | AS27: 253.1 | AU27: 220.8 | AV27: 0.3 | AW27: 1.4 | AX27: 16.1 | AZ27: 15.4 | BB27: 9.9 | BC27: 42.6 | BD27: 35.7 | BE27: 0.6 | BF27: 112.3 | BG27: 146.8 | BH27: 18.7 | BI27: 18.1 | BJ27: 62.5 | BK27: 2.9 | BL27: 1.2 | BM27: 1.7 | BN27: 1.2 | BO27: 16.1 | BP27: 0.9 | BQ27: 17.7 | BR27: 4.1 | BS27: 19.6 | BT27: 3.6 | BU27: 1760.2942
B28: 10:30 | C28: 17.8 | D28: 20.4 | E28: 8.5 | F28: 11.1 | G28: 8.6 | H28: 2.3 | J28: 9.5 | K28: 20.6 | L28: 6.5 | M28: 1.1 | N28: 6.3 | P28: 9.8 | Q28: 13 | R28: 6.6 | S28: 2.3 | T28: 4 | U28: 10 | V28: 20.6 | W28: 7.2 | X28: 12.7 | Y28: 23.2 | AA28: 76.7 | AB28: 12.7148 | AC28: 170.21034 | AD28: 39.68093 | AE28: 27.57 | AF28: 10.9 | AG28: 4 | AH28: 20.4 | AI28: 20.4 | AJ28: 20 | AK28: 8.6 | AL28: 78.2 | AM28: 4.8 | AN28: 4.6 | AO28: 2.6 | AP28: 17.7 | AS28: 252.9 | AU28: 223.8 | AV28: 0.3 | AW28: 1.4 | AX28: 17 | AZ28: 15.3 | BB28: 9.9 | BC28: 22.5 | BD28: 20 | BE28: 0.6 | BF28: 103.7 | BG28: 124 | BH28: 18.8 | BI28: 18 | BJ28: 62.2 | BK28: 2.9 | BL28: 1.2 | BM28: 2.1 | BN28: 1.2 | BO28: 17.1 | BP28: 0.8 | BQ28: 17.7 | BR28: 4.1 | BS28: 19 | BT28: 5.3 | BU28: 1702.9761
B29: 11:00 | C29: 18 | D29: 20.4 | E29: 8.4 | F29: 11.1 | G29: 8.8 | H29: 2.2 | J29: 9.5 | K29: 18.7 | L29: 6.5 | M29: 1.2 | N29: 6.3 | P29: 9.5 | Q29: 12.6 | R29: 6.4 | S29: 2.3 | T29: 4 | U29: 10 | V29: 20.5 | W29: 7.5 | X29: 12.7 | Y29: 31.5 | Z29: 0.2 | AA29: 79.9 | AB29: 12.01184 | AC29: 157.8897 | AD29: 40.32884 | AE29: 31.01 | AF29: 11.1 | AG29: 4.1 | AH29: 20.4 | AI29: 20.4 | AJ29: 20 | AK29: 8.6 | AL29: 78.4 | AM29: 3.8 | AN29: 4 | AO29: 2.6 | AP29: 17.7 | AS29: 252.7 | AU29: 224.2 | AV29: 0.2 | AW29: 1.4 | AX29: 17.7 | AZ29: 15.4 | BB29: 9.9 | BC29: 23.6 | BD29: 8.2 | BE29: 0.6 | BF29: 113.2 | BG29: 147.4 | BH29: 18.8 | BI29: 16.2 | BJ29: 66.9 | BK29: 2.9 | BL29: 1.2 | BM29: 2.1 | BN29: 1.2 | BO29: 17.8 | BP29: 0.8 | BQ29: 17.3 | BR29: 4.1 | BS29: 17.5 | BT29: 4.9 | BU29: 1726.7404
B30: 11:30 | C30: 18 | D30: 20.4 | E30: 9.3 | F30: 11.1 | G30: 8.7 | H30: 2.2 | J30: 9.5 | K30: 13.1 | L30: 6.5 | M30: 1.3 | N30: 6.5 | P30: 9.2 | Q30: 12.6 | R30: 6.5 | S30: 2.3 | T30: 4 | U30: 10 | V30: 20.3 | W30: 7.7 | X30: 12.7 | Y30: 40.1 | Z30: 2.1 | AA30: 88 | AB30: 16.53179 | AC30: 178.6093 | AD30: 37.87831 | AE30: 34.46 | AF30: 11.6 | AG30: 4.1 | AH30: 20.4 | AI30: 20.4 | AJ30: 20 | AK30: 8.5 | AL30: 79.4 | AM30: 5.2 | AN30: 5.9 | AO30: 2.6 | AP30: 17.7 | AS30: 253 | AU30: 224.1 | AV30: 0.4 | AW30: 1.4 | AX30: 18.1 | AZ30: 15.4 | BB30: 9.8 | BC30: 24.2 | BD30: 15.2 | BE30: 0.6 | BF30: 113.3 | BG30: 147.2 | BH30: 19 | BI30: 19.5 | BJ30: 67.2 | BK30: 2.9 | BL30: 1.2 | BM30: 2.1 | BN30: 1.2 | BO30: 18.1 | BP30: 0.8 | BQ30: 17.3 | BR30: 4.1 | BS30: 13.7 | BT30: 5.8 | BU30: 1780.9794
B31: 12:00 | C31: 17.6 | D31: 20.4 | E31: 9.3 | F31: 11.1 | G31: 8.7 | H31: 2.2 | J31: 8.6 | K31: 21.4 | L31: 6.5 | M31: 1.3 | N31: 6.6 | P31: 10.6 | Q31: 12.7 | R31: 6.5 | S31: 2.3 | T31: 4 | U31: 10 | V31: 20.4 | W31: 7.4 | X31: 12.8 | Y31: 40.2 | Z31: 4.3 | AA31: 95.6 | AB31: 16.31144 | AC31: 159.19262 | AD31: 40.69995 | AE31: 34.46 | AF31: 11.7 | AG31: 4.2 | AH31: 20.4 | AI31: 20.4 | AJ31: 20 | AK31: 8.3 | AL31: 79.9 | AM31: 6 | AN31: 7.6 | AO31: 2.6 | AP31: 17.7 | AS31: 253 | AU31: 221.9 | AV31: 0.4 | AW31: 1.5 | AX31: 18.2 | AZ31: 15 | BB31: 9.9 | BC31: 11.8 | BD31: 1.9 | BE31: 0.6 | BF31: 113.5 | BG31: 147 | BH31: 18.2 | BI31: 20 | BJ31: 73.1 | BK31: 2.9 | BL31: 1.2 | BM31: 2.1 | BN31: 1.2 | BO31: 18.2 | BP31: 1.2 | BQ31: 17.5 | BR31: 4.1 | BS31: 19.6 | BT31: 5.7 | BU31: 1769.664
B32: 12:30 | C32: 17 | D32: 20.4 | E32: 8.8 | F32: 11.1 | G32: 8.9 | H32: 2.3 | J32: 9.2 | K32: 21.7 | L32: 6.4 | M32: 1.1 | N32: 6.5 | P32: 11 | Q32: 14 | R32: 6.6 | S32: 2.3 | T32: 4 | U32: 9.9 | V32: 20.7 | W32: 6.1 | X32: 12.7 | Y32: 48 | Z32: 7.4 | AA32: 84.9 | AB32: 15.4606 | AC32: 160.26898 | AD32: 36.37656 | AE32: 34.46 | AF32: 11.7 | AG32: 4 | AH32: 20.4 | AI32: 20.4 | AJ32: 20 | AK32: 8.5 | AL32: 79.9 | AM32: 8.1 | AN32: 9.3 | AO32: 2.7 | AP32: 17.7 | AS32: 253.1 | AU32: 224.1 | AV32: 0.4 | AW32: 1.8 | AX32: 18.1 | AZ32: 15.3 | BB32: 9.8 | BC32: 35.4 | BD32: 13.5 | BE32: 0.6 | BF32: 111.4 | BG32: 140.4 | BH32: 18.7 | BI32: 20 | BJ32: 66.4 | BK32: 2.9 | BL32: 1.2 | BM32: 2.1 | BN32: 1.2 | BO32: 18 | BP32: 1.2 | BQ32: 19 | BR32: 4.1 | BS32: 15.4 | BT32: 6.3 | BU32: 1790.6661
B33: 13:00 | C33: 16.6 | D33: 20.4 | E33: 9.3 | F33: 11.1 | G33: 11.4 | H33: 2.3 | J33: 8.8 | K33: 21.8 | L33: 6.3 | M33: 0.9 | N33: 6.6 | P33: 11.6 | Q33: 13.4 | R33: 6.6 | S33: 2.3 | T33: 4 | U33: 10 | V33: 19.9 | W33: 6.1 | X33: 12.7 | Y33: 56.1 | Z33: 6.3 | AA33: 80 | AB33: 16.96399 | AC33: 168.87371 | AD33: 37.84163 | AE33: 31.01 | AF33: 11.8 | AG33: 4 | AH33: 20.4 | AI33: 20.4 | AJ33: 20 | AK33: 8.7 | AL33: 79.7 | AM33: 6.1 | AN33: 7.8 | AO33: 2.6 | AP33: 17.7 | AS33: 252.9 | AU33: 223.2 | AV33: 0.4 | AW33: 1.6 | AX33: 17.5 | AZ33: 14.9 | BB33: 9.9 | BC33: 39.7 | BD33: 22.1 | BE33: 0.6 | BF33: 113.5 | BG33: 147.2 | BH33: 18.7 | BI33: 14.8 | BJ33: 62 | BK33: 2.9 | BL33: 1.2 | BM33: 2.1 | BN33: 1.2 | BO33: 17.2 | BP33: 1.2 | BQ33: 20 | BR33: 4.1 | BS33: 11.1 | BT33: 9 | BU33: 1807.3893
B34: 13:30 | C34: 17.5 | D34: 20.4 | E34: 9.1 | F34: 10.7 | G34: 11.8 | H34: 2.3 | J34: 8.3 | K34: 22.1 | L34: 6.3 | M34: 0.6 | N34: 6.5 | P34: 12.2 | Q34: 15.6 | R34: 6.6 | S34: 2.3 | T34: 4 | U34: 10 | V34: 19.9 | W34: 6.1 | X34: 12.8 | Y34: 54 | Z34: 4.3 | AA34: 85.8 | AB34: 16.06881 | AC34: 170.2306 | AD34: 38.38769 | AE34: 27.57 | AF34: 11.8 | AG34: 4 | AH34: 20.4 | AI34: 20.4 | AJ34: 20 | AK34: 8.6 | AL34: 79.5 | AM34: 4.8 | AN34: 7.2 | AO34: 2.6 | AP34: 17.7 | AS34: 252.8 | AU34: 220.6 | AV34: 0.2 | AW34: 1.6 | AX34: 16.7 | AZ34: 14.7 | BB34: 10 | BC34: 71.2 | BD34: 52.8 | BE34: 0.6 | BF34: 113.1 | BG34: 147 | BH34: 18.6 | BI34: 17.7 | BJ34: 57.7 | BK34: 2.9 | BL34: 1.2 | BM34: 2.1 | BN34: 1.2 | BO34: 16.6 | BP34: 1.2 | BQ34: 20 | BR34: 4.1 | BS34: 17 | BT34: 9.2 | BU34: 1869.2571
B35: 14:00 | C35: 17.9 | D35: 20.4 | E35: 8.7 | F35: 10.1 | G35: 11.9 | H35: 2.3 | J35: 8.8 | K35: 16 | L35: 6.2 | M35: 1.1 | N35: 6.6 | P35: 16.5 | Q35: 15.9 | R35: 6.6 | S35: 2.2 | T35: 3.9 | U35: 10 | V35: 20.4 | W35: 6 | X35: 12.7 | Y35: 54.6 | Z35: 6.1 | AA35: 84.1 | AB35: 14.4382 | AC35: 166.42816 | AD35: 37.49796 | AE35: 24.12 | AF35: 11.9 | AG35: 4 | AH35: 20.4 | AI35: 20.4 | AJ35: 20 | AK35: 8.5 | AL35: 79 | AM35: 3.8 | AN35: 6.3 | AO35: 2.6 | AP35: 17.7 | AS35: 253 | AU35: 217.7 | AV35: 0.2 | AW35: 1.6 | AX35: 15.2 | AZ35: 14.9 | BB35: 9.8 | BC35: 106.7 | BD35: 103 | BE35: 0.6 | BF35: 110.8 | BG35: 144.3 | BH35: 18.7 | BI35: 18.5 | BJ35: 59.9 | BK35: 2.9 | BL35: 1.2 | BM35: 2.1 | BN35: 1.2 | BO35: 15.6 | BP35: 1.2 | BQ35: 19.8 | BR35: 4.1 | BS35: 17.6 | BT35: 11.3 | BU35: 1937.9843
B36: 14:30 | C36: 18 | D36: 20.4 | E36: 6.8 | F36: 11.1 | G36: 11.9 | H36: 2.4 | J36: 8.9 | K36: 19.8 | L36: 6.2 | M36: 0.6 | N36: 6.5 | P36: 17.9 | Q36: 20.2 | R36: 6.5 | S36: 2.3 | T36: 4 | U36: 10 | V36: 20.3 | W36: 6 | X36: 12.7 | Y36: 52.9 | Z36: 6.6 | AA36: 88.8 | AB36: 14.04582 | AC36: 172.87195 | AD36: 36.9727 | AE36: 20.68 | AF36: 11.9 | AG36: 4 | AH36: 20.4 | AI36: 20.4 | AJ36: 20 | AK36: 8.2 | AL36: 76.9 | AM36: 2 | AN36: 2.4 | AO36: 2.6 | AP36: 17.7 | AS36: 253.4 | AU36: 215.7 | AV36: 0.1 | AW36: 1.7 | AX36: 14 | AZ36: 14.6 | BB36: 9.8 | BC36: 128.3 | BD36: 112.5 | BE36: 0.3 | BF36: 109.4 | BG36: 143.3 | BH36: 18.3 | BI36: 19.5 | BJ36: 63.4 | BK36: 2.9 | BL36: 1.2 | BM36: 2.1 | BN36: 1.2 | BO36: 9.3 | BP36: 1.2 | BQ36: 20 | BR36: 4.1 | BS36: 19.4 | BT36: 11.1 | BU36: 1968.6705
B37: 15:00 | C37: 17.9 | D37: 20.4 | E37: 7 | F37: 11.1 | G37: 12 | H37: 2.4 | J37: 8.7 | K37: 21.3 | L37: 6 | M37: 0.7 | N37: 6.6 | P37: 20.3 | Q37: 20.1 | R37: 6.5 | S37: 2.3 | T37: 4.1 | U37: 10 | V37: 20.2 | W37: 6 | X37: 12.8 | Y37: 48.1 | Z37: 7.6 | AA37: 86 | AB37: 13.93911 | AC37: 167.40252 | AD37: 40.20218 | AE37: 17.23 | AF37: 12.2 | AG37: 3.8 | AH37: 20.4 | AI37: 20.4 | AJ37: 20 | AK37: 8.2 | AL37: 78 | AM37: 1.4 | AN37: 1.5 | AO37: 2.6 | AP37: 17.7 | AS37: 253 | AU37: 208.6 | AW37: 1.7 | AX37: 12.3 | AZ37: 14.2 | BB37: 9.9 | BC37: 107.3 | BD37: 107.8 | BE37: 0.3 | BF37: 107.2 | BG37: 139.9 | BH37: 18 | BI37: 21.2 | BJ37: 58.5 | BK37: 2.9 | BL37: 1.2 | BM37: 2.1 | BN37: 1.2 | BO37: 12.3 | BP37: 1.2 | BQ37: 20 | BR37: 4.1 | BS37: 19.1 | BT37: 11.2 | BU37: 1918.2738
B38: 15:30 | C38: 16.3 | D38: 20.4 | E38: 8.9 | F38: 11.1 | G38: 12 | H38: 2.4 | J38: 8.9 | K38: 19.9 | L38: 6 | M38: 0.6 | N38: 6.6 | P38: 20.2 | Q38: 20.1 | R38: 6.5 | S38: 2.4 | T38: 4 | U38: 10 | V38: 20.3 | W38: 5.8 | X38: 12.7 | Y38: 46.1 | Z38: 7.9 | AA38: 88.7 | AB38: 13.07265 | AC38: 163.57149 | AD38: 36.57471 | AE38: 13.78 | AF38: 12.3 | AG38: 4 | AH38: 20.4 | AI38: 20.4 | AJ38: 20 | AK38: 8.2 | AL38: 77.1 | AM38: 0.3 | AN38: 1 | AO38: 2.6 | AP38: 17.7 | AS38: 252.7 | AU38: 200.9 | AW38: 1.6 | AX38: 10.3 | AZ38: 13.8 | BB38: 9.9 | BC38: 117.9 | BD38: 113.1 | BE38: 0.3 | BF38: 104.4 | BG38: 136.9 | BH38: 17.3 | BI38: 20.5 | BJ38: 64.8 | BK38: 2.9 | BL38: 1.2 | BM38: 2.1 | BN38: 1.2 | BO38: 10.4 | BP38: 1.2 | BQ38: 20 | BR38: 4.1 | BT38: 11.3 | BU38: 1887.5989
B39: 16:00 | C39: 16.3 | D39: 20.4 | E39: 9 | F39: 11.1 | G39: 12 | H39: 2.4 | J39: 9.6 | K39: 18.4 | L39: 6.2 | M39: 0.8 | N39: 6.6 | P39: 20.2 | Q39: 20 | R39: 6.5 | S39: 2.3 | T39: 4 | U39: 10 | V39: 20.2 | W39: 5.6 | X39: 12.7 | Y39: 45.1 | Z39: 9 | AA39: 89.4 | AB39: 10.53406 | AC39: 158.58523 | AD39: 34.66001 | AE39: 10.34 | AF39: 12.9 | AG39: 4 | AH39: 20.4 | AI39: 20.4 | AJ39: 20 | AK39: 8.1 | AL39: 75.5 | AM39: 1.5 | AO39: 2.6 | AP39: 17.7 | AS39: 238.5 | AU39: 188.1 | AW39: 1.6 | AX39: 8 | AZ39: 13 | BB39: 9.8 | BC39: 127.8 | BD39: 118.3 | BE39: 0.3 | BF39: 99.9 | BG39: 131.5 | BH39: 16.3 | BI39: 18.1 | BJ39: 61.1 | BK39: 2.9 | BL39: 1.2 | BM39: 2.1 | BN39: 1.2 | BO39: 8.2 | BP39: 1.2 | BQ39: 20 | BR39: 4.1 | BT39: 11.1 | BU39: 1839.3193
B40: 16:30 | C40: 16 | D40: 20.4 | E40: 9.1 | F40: 11 | G40: 12 | H40: 2.4 | J40: 9 | K40: 21.2 | L40: 6.2 | M40: 0.4 | N40: 6.6 | P40: 20.2 | Q40: 20.2 | R40: 6.5 | S40: 2.3 | T40: 4 | U40: 10 | V40: 20.3 | W40: 5.5 | X40: 12.9 | Y40: 54.8 | Z40: 12.8 | AA40: 92 | AB40: 10.03183 | AC40: 153.152 | AD40: 30.82166 | AE40: 6.89 | AF40: 18.3 | AG40: 4 | AH40: 20.4 | AI40: 20.4 | AJ40: 20 | AK40: 7.9 | AL40: 69.5 | AM40: 0.9 | AN40: 0.1 | AO40: 2.6 | AP40: 17.7 | AS40: 219.7 | AU40: 177.1 | AV40: 0.1 | AW40: 1.7 | AX40: 6.7 | AZ40: 11.7 | BB40: 9.8 | BC40: 131 | BD40: 124.2 | BE40: 0.3 | BF40: 91.9 | BG40: 118.5 | BH40: 14.4 | BI40: 18.6 | BJ40: 65.7 | BK40: 2.9 | BL40: 1.2 | BM40: 2.1 | BN40: 1.2 | BO40: 5.8 | BP40: 1.2 | BQ40: 20 | BR40: 4.1 | BT40: 11.3 | BU40: 1799.6955
B41: 17:00 | C41: 16.2 | D41: 19.3 | E41: 9.1 | F41: 11.1 | G41: 16.5 | H41: 2.4 | J41: 9.3 | K41: 22.2 | L41: 6.1 | M41: 0.3 | N41: 6.6 | P41: 20.2 | Q41: 20.2 | R41: 6.4 | S41: 2.3 | T41: 4 | U41: 10 | V41: 20.4 | W41: 5.4 | X41: 13.1 | Y41: 54.3 | Z41: 15.6 | AA41: 91 | AB41: 11.5998 | AC41: 153.48915 | AD41: 21.81214 | AE41: 3.45 | AF41: 19.4 | AG41: 4 | AH41: 20.4 | AI41: 20.4 | AJ41: 20 | AK41: 7.9 | AL41: 43.9 | AM41: 1.2 | AO41: 2.6 | AP41: 17.7 | AS41: 175.6 | AU41: 131.1 | AW41: 1.7 | AX41: 3.4 | AZ41: 8.1 | BB41: 9.9 | BC41: 129.1 | BD41: 119.1 | BE41: 0.6 | BF41: 73.4 | BG41: 77 | BH41: 9.7 | BI41: 19.4 | BJ41: 67 | BK41: 2.9 | BL41: 1.2 | BM41: 2.1 | BN41: 1.2 | BO41: 3.6 | BP41: 1.2 | BQ41: 20 | BR41: 4.1 | BT41: 13 | BU41: 1604.2511
B42: 17:30 | C42: 16.9 | D42: 20.3 | E42: 6.4 | F42: 11.1 | G42: 17.2 | H42: 2.5 | J42: 9 | K42: 19.9 | L42: 5.9 | M42: 0.2 | N42: 6.6 | P42: 20.3 | Q42: 20.2 | R42: 6.4 | S42: 2.3 | T42: 3.9 | U42: 10 | V42: 20.3 | W42: 5.4 | X42: 13 | Y42: 54.2 | Z42: 17.4 | AA42: 93.3 | AB42: 17.29327 | AC42: 165.26876 | AD42: 10.2907 | AE42: 1.72 | AF42: 19.1 | AG42: 4 | AH42: 20.4 | AI42: 20.4 | AJ42: 20 | AK42: 7.9 | AL42: 19 | AM42: 1.2 | AO42: 2.5 | AP42: 17.7 | AS42: 86.6 | AU42: 61.2 | AW42: 1.6 | AX42: 1.2 | AZ42: 2.6 | BB42: 9.8 | BC42: 111.7 | BD42: 126.5 | BE42: 0.6 | BF42: 35.1 | BG42: 34.6 | BH42: 2.9 | BI42: 22.3 | BJ42: 67.8 | BK42: 2.9 | BL42: 1.2 | BM42: 2.1 | BN42: 1.2 | BO42: 1.4 | BP42: 1.2 | BQ42: 20 | BR42: 4.1 | BT42: 13 | BU42: 1321.0727
B43: 18:00 | C43: 16.1 | D43: 20.3 | E43: 8.7 | F43: 11.1 | G43: 17.3 | H43: 2.5 | J43: 9.3 | K43: 22.1 | L43: 5.9 | M43: 0.1 | N43: 6.6 | P43: 20.2 | Q43: 20.2 | R43: 6.4 | S43: 2.2 | T43: 3.8 | U43: 10 | V43: 20.1 | W43: 5.4 | X43: 13 | Y43: 61.4 | Z43: 15.8 | AA43: 88.3 | AB43: 15.13755 | AC43: 153.57627 | AD43: 1.45435 | AF43: 19 | AG43: 4 | AH43: 20.4 | AI43: 20.4 | AJ43: 20 | AK43: 8 | AL43: 3 | AM43: 0.7 | AN43: 0.1 | AO43: 2.6 | AP43: 17.7 | AS43: 13.9 | AU43: 5.8 | AW43: 1.6 | AX43: 0.6 | AZ43: 0.1 | BB43: 9.9 | BC43: 105.7 | BD43: 120 | BE43: 0.6 | BF43: 5.3 | BG43: 3.5 | BI43: 19.5 | BJ43: 70.2 | BK43: 2.9 | BL43: 1.2 | BM43: 2.1 | BN43: 1.2 | BO43: 0.4 | BP43: 1.2 | BQ43: 20 | BR43: 4.1 | BT43: 12.9 | BU43: 1075.5682
B44: 18:30 | C44: 16 | D44: 20.3 | E44: 8.7 | F44: 11.1 | G44: 17.3 | H44: 2.5 | J44: 9.1 | K44: 21.8 | L44: 5.9 | N44: 6.9 | P44: 20 | Q44: 20.2 | R44: 6.4 | S44: 2 | T44: 3.9 | U44: 10 | V44: 20.1 | W44: 5.4 | X44: 13 | Y44: 70.1 | Z44: 13.5 | AA44: 91.6 | AB44: 11.92214 | AC44: 159.72157 | AF44: 19.2 | AG44: 3.9 | AH44: 20.4 | AI44: 20.4 | AJ44: 20 | AK44: 8.4 | AM44: 1.1 | AN44: 0.1 | AO44: 2.5 | AP44: 17.7 | AW44: 1.6 | BB44: 9.8 | BC44: 114.5 | BD44: 117.7 | BE44: 0.6 | BI44: 18.7 | BJ44: 70.3 | BK44: 2.9 | BL44: 1.2 | BM44: 2.1 | BN44: 1.2 | BP44: 1.2 | BQ44: 20 | BR44: 4.1 | BT44: 13.3 | BU44: 1060.3437
B45: 19:00 | C45: 16.5 | D45: 20.3 | E45: 8.4 | F45: 11.1 | G45: 19.1 | H45: 2.6 | J45: 9 | K45: 22.5 | L45: 5.9 | N45: 7.1 | P45: 20.1 | Q45: 20.2 | R45: 6.4 | S45: 2.1 | T45: 4 | U45: 10 | V45: 20 | W45: 5.4 | X45: 13 | Y45: 60.5 | Z45: 12.1 | AA45: 84.6 | AB45: 10.97879 | AC45: 137.36381 | AF45: 18 | AG45: 3.7 | AH45: 20.4 | AI45: 20.4 | AJ45: 20 | AK45: 8.2 | AM45: 2 | AN45: 0.3 | AO45: 2.6 | AP45: 17.7 | AW45: 1.6 | BB45: 9.9 | BC45: 92.3 | BD45: 108.5 | BE45: 0.6 | BI45: 17.6 | BJ45: 61.1 | BK45: 2.9 | BL45: 1.2 | BM45: 2.1 | BN45: 1.2 | BP45: 1.2 | BQ45: 20 | BR45: 4.1 | BT45: 13.6 | BU45: 980.4426
B46: 19:30 | C46: 16.6 | D46: 20.3 | E46: 9 | F46: 11.1 | G46: 19.4 | H46: 2.8 | J46: 8.8 | K46: 20 | L46: 5.9 | N46: 7.1 | P46: 20.2 | Q46: 20.2 | R46: 6.5 | S46: 2.1 | T46: 4 | U46: 10 | V46: 20.4 | W46: 5.1 | X46: 13 | Y46: 59 | Z46: 9.9 | AA46: 77.5 | AB46: 9.33789 | AC46: 137.36387 | AF46: 17.9 | AG46: 3.8 | AH46: 20.4 | AI46: 20.4 | AJ46: 20 | AK46: 7.8 | AM46: 2.1 | AN46: 0.8 | AO46: 2.6 | AP46: 17.7 | AW46: 1.8 | BB46: 9.9 | BC46: 77.2 | BD46: 97.9 | BE46: 0.6 | BI46: 16.1 | BJ46: 56.5 | BK46: 2.9 | BL46: 1.2 | BM46: 2.1 | BN46: 1.2 | BP46: 1.2 | BQ46: 20.1 | BR46: 4.1 | BT46: 13.8 | BU46: 935.70176
B47: 20:00 | C47: 16.5 | D47: 20.3 | E47: 8.5 | F47: 11.1 | G47: 19.4 | H47: 2.8 | J47: 8.1 | K47: 22.3 | L47: 6 | N47: 7.1 | P47: 20.1 | Q47: 20.2 | R47: 6.5 | S47: 2.1 | T47: 3.9 | U47: 10 | V47: 20.2 | W47: 5.1 | X47: 13 | Y47: 55.7 | Z47: 11.1 | AA47: 69.7 | AB47: 7.26509 | AC47: 126.72707 | AF47: 17.2 | AG47: 3.8 | AH47: 20.4 | AI47: 20.4 | AJ47: 20 | AK47: 7.7 | AM47: 2.7 | AN47: 1.2 | AO47: 2.6 | AP47: 17.7 | AW47: 1.7 | BB47: 9.8 | BC47: 60.3 | BD47: 78.8 | BE47: 0.6 | BI47: 15 | BJ47: 45.3 | BK47: 2.9 | BL47: 1.2 | BM47: 2.1 | BN47: 1.2 | BP47: 1.2 | BQ47: 20 | BR47: 4.1 | BT47: 16 | BU47: 867.59216
B48: 20:30 | C48: 16.4 | D48: 18.3 | E48: 9.2 | F48: 11.1 | G48: 19.4 | H48: 2.8 | J48: 9 | K48: 23 | L48: 6 | N48: 7.1 | P48: 20.1 | Q48: 20.2 | R48: 6.5 | S48: 2.1 | T48: 4 | U48: 10 | V48: 20 | W48: 5.1 | X48: 13 | Y48: 46.8 | Z48: 10.7 | AA48: 75.1 | AB48: 6.61732 | AC48: 123.93058 | AF48: 17.3 | AG48: 3.8 | AH48: 20.4 | AI48: 20.4 | AJ48: 20 | AK48: 7.7 | AM48: 3 | AN48: 1.1 | AO48: 2.6 | AP48: 17.7 | AW48: 1.7 | BB48: 9.8 | BC48: 50.5 | BD48: 66.5 | BE48: 0.6 | BI48: 16.1 | BJ48: 46.6 | BK48: 2.9 | BL48: 1.2 | BM48: 2.1 | BN48: 1.2 | BP48: 1.2 | BQ48: 20 | BR48: 4.1 | BT48: 16 | BU48: 840.9479
B49: 21:00 | C49: 17.9 | D49: 18.3 | E49: 6.6 | F49: 11.1 | G49: 19.2 | H49: 2.8 | J49: 8.8 | K49: 20.1 | L49: 5.9 | N49: 7 | P49: 20.2 | Q49: 20.3 | R49: 6.5 | S49: 2.1 | T49: 4 | U49: 12 | V49: 20.1 | W49: 5.1 | X49: 13 | Y49: 34.1 | Z49: 11 | AA49: 75.1 | AB49: 4.88351 | AC49: 120.37935 | AF49: 16.9 | AG49: 3.8 | AH49: 20.4 | AI49: 20.4 | AJ49: 20 | AK49: 7.9 | AM49: 1.9 | AN49: 0.8 | AO49: 2.6 | AP49: 17.7 | AW49: 1.7 | BB49: 9.9 | BC49: 41.7 | BD49: 62.4 | BE49: 0.6 | BI49: 16.8 | BJ49: 43.2 | BK49: 2.9 | BL49: 1.2 | BM49: 2.1 | BN49: 1.2 | BP49: 1.2 | BQ49: 19.6 | BR49: 4.1 | BT49: 16 | BU49: 803.46286
B50: 21:30 | C50: 17.8 | D50: 18.4 | E50: 6.582 | F50: 11.1 | G50: 19.2 | H50: 2.7 | J50: 8.8 | K50: 20 | L50: 5.9 | N50: 7.1 | P50: 19.9 | Q50: 20.2 | R50: 6.5 | S50: 2.1 | T50: 4 | U50: 17.5 | V50: 20.1 | W50: 5.1 | X50: 13 | Y50: 35.2 | Z50: 7.8 | AA50: 68.2 | AB50: 5.31777 | AC50: 126.94154 | AF50: 16.6 | AG50: 3.8 | AH50: 20.4 | AI50: 20.4 | AJ50: 20 | AK50: 7.9 | AM50: 1.45 | AN50: 0.5 | AO50: 2.6 | AP50: 17.4 | AW50: 1.7 | BB50: 9.9 | BC50: 37.4 | BD50: 49.1 | BE50: 0.6 | BI50: 14.9 | BJ50: 43.7 | BK50: 2.9 | BL50: 1.2 | BM50: 2.1 | BN50: 1.2 | BP50: 1.2 | BQ50: 19.2 | BR50: 4.1 | BT50: 16 | BU50: 785.69131
B51: 22:00 | C51: 17.5 | D51: 16.4 | E51: 8.861 | F51: 11.1 | G51: 15.9 | H51: 2.7 | J51: 8.5 | K51: 20 | L51: 5.9 | N51: 7.1 | P51: 20 | Q51: 20.2 | R51: 6.5 | S51: 2.1 | T51: 3.8 | U51: 17.9 | V51: 20 | W51: 4.7 | X51: 13 | Y51: 28.9 | Z51: 6.3 | AA51: 73.1 | AB51: 4.62152 | AC51: 130.82322 | AF51: 16.4 | AG51: 3.8 | AH51: 20.4 | AI51: 20.4 | AJ51: 20 | AK51: 8.1 | AM51: 1.65 | AN51: 0.6 | AO51: 2.5 | AP51: 17 | AW51: 1.7 | BB51: 9.9 | BC51: 28.8 | BD51: 36.4 | BE51: 0.6 | BI51: 13.2 | BJ51: 41.8 | BK51: 2.9 | BL51: 1.2 | BM51: 2.1 | BN51: 1.2 | BP51: 1.2 | BQ51: 19.3 | BR51: 4.1 | BT51: 20.2 | BU51: 761.35574
B52: 22:30 | C52: 17.5 | D52: 19.4 | E52: 8.453 | F52: 11.1 | G52: 13.9 | H52: 2.8 | J52: 8.8 | K52: 20 | L52: 5.9 | N52: 7.1 | P52: 19.8 | Q52: 20.3 | R52: 6.6 | S52: 2.1 | T52: 4 | U52: 18.2 | V52: 20 | W52: 4.7 | X52: 13 | Y52: 25.1 | Z52: 6 | AA52: 67.3 | AB52: 4.96447 | AC52: 95.82962 | AF52: 16.4 | AG52: 3.8 | AH52: 20.4 | AI52: 20.4 | AJ52: 20 | AK52: 8.1 | AM52: 0.8 | AN52: 0.1 | AO52: 2.6 | AP52: 16.9 | AW52: 1.7 | BB52: 10 | BC52: 22.2 | BD52: 28.9 | BE52: 0.6 | BI52: 15 | BJ52: 42.4 | BK52: 2.9 | BL52: 1.2 | BM52: 2.1 | BN52: 1.2 | BP52: 1.2 | BQ52: 19.4 | BR52: 4.1 | BT52: 20.2 | BU52: 705.44709
B53: 23:00 | C53: 17.6 | D53: 19.8 | E53: 8.6 | F53: 11.1 | G53: 13.7 | H53: 2.9 | J53: 8.4 | K53: 20 | L53: 5.9 | N53: 7.1 | P53: 19.7 | Q53: 20.3 | R53: 6.6 | S53: 2.1 | T53: 4 | U53: 18.6 | V53: 20.1 | W53: 4.7 | X53: 13 | Y53: 18.3 | Z53: 8.8 | AA53: 59.7 | AB53: 2.98957 | AC53: 81.13163 | AF53: 16.1 | AG53: 3.8 | AH53: 20.4 | AI53: 20.4 | AJ53: 20 | AK53: 8.3 | AM53: 0.83 | AO53: 2.5 | AP53: 16.9 | AW53: 1.7 | BB53: 9.9 | BC53: 16 | BD53: 23.8 | BE53: 0.6 | BI53: 13.3 | BJ53: 41 | BK53: 2.9 | BL53: 1.2 | BM53: 2.1 | BN53: 1.2 | BP53: 1.2 | BQ53: 19.5 | BR53: 4.1 | BT53: 20.2 | BU53: 663.0512
B54: 23:30 | C54: 17.7 | D54: 19.1 | E54: 7.883 | F54: 11.1 | G54: 13.9 | H54: 3 | J54: 7.9 | K54: 20 | L54: 5.9 | N54: 7.1 | P54: 19.3 | Q54: 20.2 | R54: 6.6 | S54: 2.1 | T54: 4 | U54: 18.6 | V54: 19.6 | W54: 5.1 | X54: 13 | Y54: 19.4 | Z54: 10.4 | AA54: 55.9 | AB54: 3.00436 | AC54: 90.09153 | AF54: 15.7 | AG54: 3.8 | AH54: 20.4 | AI54: 20.4 | AJ54: 20 | AK54: 8.3 | AO54: 2.5 | AP54: 16.9 | AW54: 1.7 | BB54: 10 | BC54: 10.2 | BD54: 17.9 | BE54: 0.6 | BI54: 11.1 | BJ54: 39.4 | BK54: 2.9 | BL54: 1.2 | BM54: 2.1 | BN54: 1.2 | BP54: 1.2 | BQ54: 19.5 | BR54: 4.1 | BT54: 19.9 | BU54: 651.87889
B55: 0:00 | C55: 17.6 | D55: 19.2 | E55: 7.46 | F55: 11.1 | G55: 13.9 | H55: 3.1 | J55: 8.6 | K55: 20 | L55: 5.9 | N55: 7.1 | P55: 19.4 | Q55: 20.2 | R55: 6.5 | S55: 2.2 | T55: 3.9 | U55: 18.1 | V55: 20.3 | W55: 5.1 | X55: 13 | Y55: 21.5 | Z55: 12.7 | AA55: 56.9 | AB55: 2.47535 | AC55: 93.75426 | AF55: 15.4 | AG55: 3.8 | AH55: 20.4 | AI55: 20.4 | AJ55: 20 | AK55: 8.3 | AO55: 2.6 | AP55: 16.9 | AW55: 1.7 | BB55: 10 | BC55: 5.7 | BD55: 11.9 | BE55: 0.6 | BI55: 11.7 | BJ55: 40.9 | BK55: 2.9 | BL55: 1.2 | BM55: 2.1 | BN55: 1.2 | BP55: 1.2 | BQ55: 19.3 | BR55: 4.1 | BT55: 20.2 | BU55: 652.48961
B56: EJEC MWh | C56: 419.65 | D56: 479.3 | E56: 198.6195 | F56: 265.65 | G56: 244.05 | H56: 60.45 | I56: 0 | J56: 214.6 | K56: 483.75 | L56: 153 | M56: 8.05 | N56: 159.65 | O56: 0 | P56: 340.3 | Q56: 385.6 | R56: 158.1 | S56: 52.75 | T56: 94.5 | U56: 265.35 | V56: 466.1 | W56: 138.1 | X56: 308.15 | Y56: 694.3 | Z56: 209.7 | AA56: 2181.1 | AB56: 235.48919 | AC56: 3388.1557 | AD56: 402.58446 | AE56: 211.065 | AF56: 326.65 | AG56: 97.4 | AH56: 489.6 | AI56: 489.6 | AJ56: 480 | AK56: 199.95 | AL56: 752.25 | AM56: 39.965 | AN56: 36.75 | AO56: 64.95 | AP56: 422.35 | AQ56: 0 | AR56: 0 | AS56: 2699.45 | AT56: 0 | AU56: 2242.7 | AV56: 1.85 | AW56: 37.45 | AX56: 136.1 | AY56: 0 | AZ56: 143.05 | BA56: 0 | BB56: 237.45 | BC56: 1696.5 | BD56: 1661.25 | BE56: 13.65 | BF56: 1180.05 | BG56: 1510.1 | BH56: 176.7 | BI56: 505.4 | BJ56: 1576.5 | BK56: 69.6 | BL56: 28.8 | BM56: 50.2 | BN56: 28.8 | BO56: 133.5 | BP56: 26.1 | BQ56: 470.6 | BR56: 98.4 | BS56: 141.8 | BT56: 208.55 | BU56: 30692.129
L70: TERMOELÉCTRICA | M70: 2238.9695 | N70: 7.2949306 | O70: #FFA975
L71: HIDROELÉCTRICA | M71: 6488.8 | N71: 21.141577 | O71: #98D2FF
L72: SOLAR | M72: 9739.2495 | N72: 31.732075 | O72: #FFD272
L73: EÓLICA | M73: 12225.11 | N73: 39.831417 | O73: #B9ACFF

Sheet COGENERACIÓN
B3: martes, 16 de Diciembre del 2025
B5: CENTRALES DE COGENERACIÓN DEL SEIN
B6: HORA | C6: AGRO INDUSTRIAL PARAMONGA S.A. | D6: AGROAURORA S.A.C. | E6: AGROINDUSTRIAS SAN JACINTO S.A.A. | F6: AGROLMOS SOCIEDAD ANONIMA - AGROLMOS S.A. | G6: BIOENERGIA DEL CHIRA S.A. | H6: CASA GRANDE S.A.A. | I6: GM OPERACIONES S.A.C. | J6: TOTAL COGENERACION
C7: C.T. PARAMONGA | D7: C.T. MAPLE | E7: C.T SAN JACINTO | F7: C.T. AGROLMOS | G7: C.T. CAÑA BRAVA | H7: C.T. CASA GRANDE | I7: C.T. REFINERÍA TALARA | J7: MW
B8: 0:30 | C8: 18 | D8: 18.6 | E8: 7 | F8: 11.1 | G8: 9.2 | H8: 22.2 | I8: 61.3 | J8: 147.4
B9: 1:00 | C9: 17.8 | D9: 19.4 | E9: 6 | F9: 11.1 | G9: 8.7 | H9: 21.6 | I9: 61.2 | J9: 145.8
B10: 1:30 | C10: 17.8 | D10: 20.3 | E10: 7.6 | F10: 11.1 | G10: 9 | H10: 21.2 | I10: 61.4 | J10: 148.4
B11: 2:00 | C11: 18 | D11: 20.3 | E11: 8.3 | F11: 11.1 | G11: 8.4 | H11: 21 | I11: 61.4 | J11: 148.5
B12: 2:30 | C12: 17.9 | D12: 20.3 | E12: 8.4 | F12: 11.1 | G12: 9.4 | H12: 18.4 | I12: 61.8 | J12: 147.3
B13: 3:00 | C13: 17.9 | D13: 20.3 | E13: 8.5 | F13: 11.1 | G13: 9.6 | H13: 22 | I13: 62.5 | J13: 151.9
B14: 3:30 | C14: 18.5 | D14: 20.3 | E14: 8.8 | F14: 11.1 | G14: 9.6 | H14: 22.2 | I14: 62.4 | J14: 152.9
B15: 4:00 | C15: 18.2 | D15: 20.3 | E15: 8.3 | F15: 11.1 | G15: 9.2 | H15: 19.7 | I15: 62.6 | J15: 149.4
B16: 4:30 | C16: 18.2 | D16: 20.3 | E16: 8.2 | F16: 11.1 | G16: 9.1 | H16: 17.4 | I16: 62.5 | J16: 146.8
B17: 5:00 | C17: 18.1 | D17: 20.3 | E17: 8.1 | F17: 11.1 | G17: 9.3 | H17: 17.3 | I17: 62.6 | J17: 146.8
B18: 5:30 | C18: 18.1 | D18: 20.3 | E18: 8.5 | F18: 11.1 | G18: 8.7 | H18: 22.8 | I18: 62.6 | J18: 152.1
B19: 6:00 | C19: 17.8 | D19: 20.3 | E19: 8.1 | F19: 11.1 | G19: 8.8 | H19: 22.4 | I19: 63 | J19: 151.5
... B56: EJEC MWh | C56: 419.65 | D56: 479.3 | E56: 198.6195 | F56: 265.65 | G56: 214.6 | H56: 483.75 | I56: 1482.9 | J56: 3544.4695

Sheet EVO_PRO_ENE
B3: lunes, 1 de Diciembre del 2025 - martes, 16 de Diciembre del 2025
B5: EVOLUCIÓN DE LA PRODUCCIÓN DE LA ENERGÍA DIARIA DE LOS INTEGRANTES DEL COES (MWh)
B6: EMPRESA | C6: CENTRAL | D6: UNIDAD | E6: TIPO | F6: Diciembre
F7: 1 | G7: 2 | H7: 3 | I7: 4 | J7: 5 | K7: 6 | L7: 7 | M7: 8 | N7: 9 | O7: 10 | P7: 11 | Q7: 12 | R7: 13 | S7: 14 | T7: 15 | U7: 16 | V7: TOTAL
B8: AGRO INDUSTRIAL PARAMONGA S.A. | C8: C.T. PARAMONGA | D8: TV-01 | E8: TERMOELÉCTRICA | F8: 225.95 | H8: 244 | I8: 379.55 | J8: 390.2 | K8: 394.55 | L8: 381.75 | M8: 383 | N8: 393.5 | O8: 387.7 | P8: 384.8 | Q8: 392.3 | R8: 370.1 | S8: 424.3 | T8: 422.7 | U8: 419.65 | V8: 5594.05
B9: AGROAURORA S.A.C. | C9: C.T. MAPLE ETANOL | D9: TV | E9: TERMOELÉCTRICA | F9: 455.4 | G9: 336.6 | H9: 457.4 | I9: 461.25 | J9: 277.05 | K9: 449.65 | L9: 451.35 | M9: 451.85 | N9: 434.1 | O9: 294.1 | P9: 436.8 | Q9: 429.45 | R9: 141.84 | T9: 336.6 | U9: 479.3 | V9: 5892.74
B10: AGROINDUSTRIAS SAN JACINTO S.A.A. | C10: C.T. SAN JACINTO | D10: CENTRAL | E10: TERMOELÉCTRICA | F10: 194.745 | G10: 195.7 | H10: 171.4 | I10: 199.75 | J10: 189.4 | K10: 192.55 | L10: 193.35 | M10: 199.05 | N10: 189 | O10: 194.65 | P10: 161.05 | Q10: 196.95 | R10: 195.75 | S10: 192.72 | T10: 187.8 | U10: 198.6195 | V10: 3052.4845
B11: AGROLMOS SOCIEDAD ANONIMA - AGROLMOS S.A. | C11: C.T. AGROLMOS | D11: CENTRAL | E11: TERMOELÉCTRICA | F11: 217.08 | I11: 34.65 | J11: 262.05 | K11: 262.75 | L11: 269.3 | M11: 268.25 | N11: 261.55 | O11: 269.6 | P11: 245.525 | Q11: 270.3 | R11: 266.25 | S11: 264.65 | T11: 266 | U11: 265.65 | V11: 3423.605
B12: ANDEAN POWER S.A.C. | C12: C.H.CARHUAC | D12: CENTRAL | E12: HIDROELÉCTRICA | F12: 338.85 | G12: 363.95 | H12: 384.7 | I12: 356.85 | J12: 356.25 | K12: 372 | L12: 375.85 | M12: 326 | N12: 309.9 | O12: 365.3 | P12: 308.65 | Q12: 241.6 | R12: 227.65 | S12: 208.45 | T12: 205.35 | U12: 244.05 | V12: 4985.4
B13: ASOCIACIÓN SANTA LUCIA DE CHACAS | C13: C.H. HUALLIN | D13: CENTRAL | E13: HIDROELÉCTRICA | F13: 57.45 | G13: 58.05 | H13: 58.05 | I13: 61.1 | J13: 57.2 | K13: 55.35 | L13: 55.15 | M13: 49.9 | N13: 45.5 | O13: 45.25 | P13: 58.55 | Q13: 58.55 | R13: 56.52 | S13: 48.85 | T13: 44.05 | U13: 60.45 | V13: 869.97
B14: ATRIA ENERGIA S.A.C. | C14: C.H. PURMACANA | D14: CENTRAL | E14: HIDROELÉCTRICA | I14: 8.55 | J14: 2.2 | V14: 10.75
B15: BIOENERGIA DEL CHIRA S.A. | C15: C.T. CAÑA BRAVA | D15: CENTRAL | E15: TERMOELÉCTRICA | F15: 211.8 | G15: 190.55 | H15: 206.15 | I15: 208.1 | J15: 200.95 | K15: 203.8 | L15: 215.1 | M15: 204.4 | N15: 200.5 | O15: 177.3 | P15: 211.55 | Q15: 208.85 | R15: 204.7 | S15: 204.9 | T15: 212.1 | U15: 214.6 | V15: 3275.35
B16: CASA GRANDE S.A.A. | C16: C.T. CASA GRANDE | D16: TV3 | E16: TERMOELÉCTRICA | J16: 352.665 | K16: 526.9 | L16: 531.85 | M16: 534.7 | N16: 525.5221 | O16: 472.25 | P16: 535.49 | Q16: 533.88805 | R16: 560.55 | S16: 400.94 | T16: 501.4 | U16: 483.75 | V16: 5959.9051
B17: CELARIS ENERGY S.A. | C17: C.H. MANTA I | D17: CENTRAL | E17: HIDROELÉCTRICA | F17: 308.75 | G17: 277.75 | H17: 248.3 | I17: 224.1 | J17: 203.95 | K17: 186.6 | L17: 176.05 | M17: 165.3 | N17: 155.3 | O17: 149.8 | P17: 150 | Q17: 150.8 | R17: 146.95 | S17: 143.15 | T17: 153.55 | U17: 153 | V17: 2993.35
B18: CELEPSA | C18: C.H. EL PLATANAL | D18: CENTRAL | E18: HIDROELÉCTRICA | F18: 1883.15 | G18: 1853.75 | H18: 1826.5 | I18: 1941.5 | J18: 1801.35 | K18: 1837.05 | L18: 1755.75 | M18: 1666.3 | N18: 1723.5 | O18: 1745.6 | P18: 1831.35 | Q18: 1910.3 | R18: 1783.5 | S18: 1809.1 | T18: 1720.55 | U18: 1733.6 | V18: 28822.85
B19: CELEPSA RENOVABLES S.R.L. | C19: C.H. MARAÑON | D19: CENTRAL | E19: HIDROELÉCTRICA | F19: 451.2 | G19: 451.2 | H19: 451.2 | I19: 435.25 | J19: 391.1 | K19: 358.25 | L19: 336.4 | M19: 318.3 | N19: 304.65 | O19: 396.45 | P19: 443.9 | Q19: 436.65 | R19: 401.6 | S19: 423.7 | T19: 373.9 | U19: 416.7 | V19: 6390.45
B20: CENTRALES SANTA ROSA S.A.C. | C20: C.H. SANTA ROSA I | D20: CENTRAL | E20: HIDROELÉCTRICA | V20: 0
B21: CENTRALES SANTA ROSA S.A.C. | C21: C.H. SANTA ROSA II | D21: CENTRAL | E21: HIDROELÉCTRICA | V21: 0
B22: CHINANGO S.A.C. | C22: C.H. CHIMAY | D22: CENTRAL | E22: HIDROELÉCTRICA | F22: 2426.6 | G22: 2136.95 | H22: 3326.8 | I22: 2700.95 | J22: 2311.2 | K22: 2073.9 | L22: 1904.1 | M22: 2404.45 | N22: 1945.7 | O22: 2326.85 | P22: 2779.5 | Q22: 3568.75 | R22: 3276.6 | S22: 3095.45 | T22: 2484.5 | U22: 2539.65 | V22: 41301.95
B23: CHINANGO S.A.C. | C23: C.H. YANANGO | D23: CENTRAL | E23: HIDROELÉCTRICA | F23: 478.45 | G23: 438.6 | H23: 444.55 | I23: 423.95 | J23: 399.4 | K23: 375.3 | L23: 375.5 | M23: 374.75 | N23: 374.5 | O23: 713 | P23: 680.9 | Q23: 707.35 | R23: 594.85 | S23: 548.55 | T23: 351.65 | U23: 505.45 | V23: 7786.75
B24: COLCA SOLAR S.A.C. | C24: C.S. YARUCAYA | D24: CENTRAL | E24: SOLAR | F24: 7.85 | G24: 5.3 | H24: 9 | I24: 8.2 | J24: 8.9 | K24: 7.6 | L24: 0.05 | M24: 6.95 | N24: 5.8 | O24: 8.4 | P24: 8.45 | Q24: 8.5 | R24: 9.2 | S24: 8.85 | T24: 8.35 | U24: 8.05 | V24: 119.45
B25: EGASA | C25: C.H. CHARCANI III | D25: CENTRAL | E25: HIDROELÉCTRICA | F25: 166.75 | G25: 166.45 | H25: 164 | I25: 165.4 | J25: 163.85 | K25: 165.05 | L25: 164.6 | M25: 164.4 | N25: 164.8 | O25: 164.97 | P25: 164 | Q25: 165.55 | R25: 163.55 | S25: 164.45 | T25: 164.95 | U25: 165.15 | V25: 2637.92
B26: EGASA | C26: C.H. CHARCANI IV | D26: CENTRAL | E26: HIDROELÉCTRICA | F26: 355.45 | G26: 353.7 | H26: 352.6 | I26: 355.5 | J26: 355 | K26: 351.45 | L26: 352.775 | M26: 353.05 | N26: 352.45 | O26: 353.265 | P26: 324.05 | Q26: 351.8 | R26: 337.95 | S26: 355.95 | T26: 351.45 | U26: 356.05 | V26: 5612.49
B27: EGASA | C27: C.H. CHARCANI V | D27: CENTRAL | E27: HIDROELÉCTRICA | F27: 2279.25 | G27: 2236.2 | H27: 2266.15 | I27: 2253.1 | J27: 2232.75 | K27: 2233.8 | L27: 2226.16 | M27: 2229.05 | N27: 2247.45 | O27: 2223.435 | P27: 2231 | Q27: 2248.95 | R27: 2217.4 | S27: 2245.75 | T27: 2245.1 | U27: 2230.85 | V27: 35846.395
B28: EGASA | C28: C.H. CHARCANI VI | D28: CENTRAL | E28: HIDROELÉCTRICA | V28: 0
B29: EGASA | C29: C.T. CHILINA DIESEL | D29: CENTRAL | E29: TERMOELÉCTRICA | P29: 4.45 | V29: 4.45
B30: EGASA | C30: C.T. CHILINA DIESEL | D30: TG | E30: TERMOELÉCTRICA | I30: 4.45 | V30: 4.45
B31: EGASA | C31: C.T. MOLLENDO DIESEL | D31: CENTRAL | E31: TERMOELÉCTRICA | V31: 0
B32: EGEJUNIN | C32: C.H. HUASAHUASI I | D32: CENTRAL | E32: HIDROELÉCTRICA | F32: 135.1 | G32: 132.85 | H32: 133.2 | I32: 122.05 | J32: 111.65 | K32: 100.8 | L32: 94.65 | M32: 90.25 | N32: 87.7 | O32: 216.6 | P32: 237.95 | Q32: 238.4 | R32: 224.9 | S32: 196.55 | T32: 165.3 | U32: 159.65 | V32: 2447.6
B33: EGEJUNIN | C33: C.H. RUNATULLO II | D33: CENTRAL | E33: HIDROELÉCTRICA | F33: 223.25 | G33: 231.3 | H33: 370.9 | I33: 300.3 | J33: 260.8 | K33: 230.3 | L33: 212.2 | M33: 236.05 | N33: 215.05 | O33: 256.55 | P33: 263.1 | Q33: 273 | R33: 294.6 | S33: 277.1 | T33: 246 | U33: 340.3 | V33: 4230.8
B34: EGEJUNIN | C34: C.H. RUNATULLO III | D34: CENTRAL | E34: HIDROELÉCTRICA | F34: 313.95 | G34: 307.9 | H34: 462.6 | I34: 414.25 | J34: 359.3 | K34: 317.7 | L34: 288.7 | M34: 334.1 | N34: 292.85 | O34: 349.55 | P34: 359.3 | Q34: 376.5 | R34: 390.7 | S34: 374.85 | T34: 335.45 | U34: 385.6 | V34: 5663.3
B35: EGEJUNIN | C35: C.H. SANTA CRUZ I | D35: CENTRAL | E35: HIDROELÉCTRICA | F35: 158.95 | G35: 154.2 | H35: 153.3 | I35: 152.75 | J35: 151.85 | K35: 151.8 | L35: 151.5 | M35: 151.7 | N35: 144.6 | O35: 135.4 | P35: 137 | Q35: 142.9 | R35: 154.5 | S35: 156.85 | T35: 156.9 | U35: 158.1 | V35: 2412.3
B36: EGEMSA | C36: C.H. MACHUPICCHU | D36: CENTRAL | E36: HIDROELÉCTRICA | F36: 3998.8 | G36: 3989.75 | H36: 4012.7 | I36: 4006.55 | J36: 4018.6 | K36: 4012.25 | L36: 3899.85 | M36: 3999.8 | N36: 3992.1 | O36: 3977.55 | P36: 3999.55 | Q36: 3981.3 | R36: 3984.4 | S36: 3306.5 | T36: 3898.8 | U36: 3927.9 | V36: 63006.4
B37: EGESUR | C37: C.H. ARICOTA I | D37: CENTRAL | E37: HIDROELÉCTRICA | F37: 185.65 | G37: 185.95 | H37: 188.05 | I37: 186.85 | J37: 184.9 | K37: 179 | L37: 181.8 | M37: 181.15 | N37: 181.1 | O37: 185.3 | P37: 184.75 | Q37: 186.9 | R37: 186.7 | S37: 175.9 | T37: 172.7 | U37: 174.95 | V37: 2921.65
B38: EGESUR | C38: C.H. ARICOTA II | D38: CENTRAL | E38: HIDROELÉCTRICA | F38: 134.7 | G38: 136.6 | H38: 138.6 | I38: 133.7 | J38: 131.85 | K38: 128.95 | L38: 129.45 | M38: 126.8 | N38: 126.45 | O38: 128.2 | P38: 126.5 | Q38: 124.7 | R38: 126.65 | S38: 37.35 | V38: 1730.5
B39: EGESUR | C39: C.T. INDEPENDENCIA | D39: CENTRAL | E39: TERMOELÉCTRICA | F39: 339.45 | G39: 8.45 | I39: 295.5 | J39: 389.6 | K39: 391 | L39: 401.35 | M39: 284.9 | N39: 388.65 | O39: 401.7 | P39: 207.1 | Q39: 394.7 | R39: 335 | S39: 311.75 | T39: 531.85 | U39: 437.9 | V39: 5118.9
B40: ELECTRICA YANAPAMPA SAC | C40: C.H. YANAPAMPA | D40: CENTRAL | E40: HIDROELÉCTRICA | F40: 60.95 | G40: 55.35 | H40: 54.7 | I40: 52.7 | J40: 53.8 | K40: 57.9 | L40: 51.5 | M40: 52.1 | N40: 49.45 | O40: 55.3 | P40: 58 | Q40: 54.1 | R40: 49.2 | S40: 50.65 | T40: 50.7 | U40: 52.75 | V40: 859.15
B41: ELECTROPERU | C41: C.H. MANTARO | D41: CENTRAL | E41: HIDROELÉCTRICA | F41: 14960.9 | G41: 14445.15 | H41: 14848.25 | I41: 13733.15 | J41: 12575.6 | K41: 11380.2 | L41: 11792.8 | M41: 9845.25 | N41: 9829.75 | O41: 10399.8 | P41: 13751.4 | Q41: 12934.3 | R41: 12918.45 | S41: 11534.25 | T41: 13246.7 | U41: 12264.8 | V41: 200460.75
B42: ELECTROPERU | C42: C.H. RESTITUCION | D42: CENTRAL | E42: HIDROELÉCTRICA | F42: 5117.95 | G42: 4968.1 | H42: 5088.15 | I42: 4648.6 | J42: 4203.9 | K42: 3756.3 | L42: 3916.1 | M42: 3256.65 | N42: 3213.1 | O42: 3428.8 | P42: 4627 | Q42: 4285.1 | R42: 4338.6 | S42: 3793.95 | T42: 4464.55 | U42: 4052.6 | V42: 67159.45
B43: ELECTROPERU | C43: C.T. TUMBES | D43: MAK1 | E43: TERMOELÉCTRICA | N43: 42.65 | V43: 42.65
B44: ELECTROPERU | C44: C.T. TUMBES | D44: MAK2 | E44: TERMOELÉCTRICA | F44: 21.55 | N44: 42.6 | V44: 64.15
B45: EMPRESA DE GENERACION ELECTRICA CANCHAYLLO SAC | C45: C.H. CANCHAYLLO | D45: CENTRAL | E45: HIDROELÉCTRICA | F45: 61.05 | G45: 61.55 | H45: 59.9 | I45: 60.75 | J45: 59.75 | K45: 60.75 | L45: 59.5 | M45: 62.5 | N45: 73.05 | O45: 83.7 | P45: 83.9 | Q45: 86.35 | R45: 85.3 | S45: 88.85 | T45: 91.55 | U45: 94.5 | V45: 1172.95
B46: EMPRESA DE GENERACION ELECTRICA RIO BAÑOS S.A.C. | C46: C.H. RUCUY | D46: CENTRAL | E46: HIDROELÉCTRICA | F46: 382.05 | G46: 367.45 | H46: 352.05 | I46: 344.35 | J46: 337.05 | K46: 344 | L46: 335.85 | M46: 329.3 | N46: 330.55 | O46: 361.85 | P46: 340.55 | Q46: 324.6 | R46: 317.55 | S46: 310.9 | T46: 401.75 | U46: 265.35 | V46: 5445.2
B47: EMPRESA DE GENERACION ELECTRICA SANTA ANA S.A.C. | C47: C.H. RENOVANDES H1 | D47: CENTRAL | E47: HIDROELÉCTRICA | F47: 488 | G47: 404.55 | H47: 95.2 | I47: 439.8 | J47: 486.45 | K47: 485.1 | L47: 485.7 | M47: 484.05 | N47: 486.5 | O47: 486.35 | P47: 483.1 | Q47: 483 | R47: 479.85 | S47: 486.8 | T47: 487.4 | U47: 466.1 | V47: 7227.95
B48: EMPRESA DE GENERACION HUALLAGA | C48: C.H. CHAGLLA | D48: CENTRAL | E48: HIDROELÉCTRICA | F48: 3419.05 | G48: 3119.7 | H48: 4060.7 | I48: 3784.3 | J48: 2428.5 | K48: 2317.6 | L48: 2624.85 | M48: 2311.15 | N48: 3653.55 | O48: 1367.8 | P48: 2001.95 | Q48: 3395.55 | R48: 5462.3 | S48: 8485.2 | T48: 3096.85 | U48: 4367.5 | V48: 55896.55
B49: EMPRESA DE GENERACION HUALLAGA | C49: P.C.H. CHAGLLA | D49: CENTRAL | E49: HIDROELÉCTRICA | F49: 155.45 | G49: 154.75 | H49: 154.25 | I49: 154.35 | J49: 153.95 | K49: 153.85 | L49: 154.9 | M49: 154.55 | N49: 108 | O49: 156 | P49: 156 | Q49: 156 | R49: 156 | S49: 156 | T49: 156 | U49: 156 | V49: 2436.05
B50: EMPRESA DE GENERACION HUANZA | C50: C.H. HUANZA | D50: CENTRAL | E50: HIDROELÉCTRICA | F50: 1470.95 | G50: 1554.75 | H50: 1658.25 | I50: 1560.5 | J50: 1571.6 | K50: 1610.1 | L50: 1638.15 | M50: 1472.3 | N50: 1367.15 | O50: 1609.05 | P50: 1312.05 | Q50: 1006.65 | R50: 969.4 | S50: 871.4 | T50: 889.4 | U50: 1094.05 | V50: 21655.75
B51: EMPRESA ELECTRICA AGUA AZUL | C51: C.H. POTRERO | D51: CENTRAL | E51: HIDROELÉCTRICA | F51: 479.9 | G51: 480 | H51: 480 | I51: 479.5 | J51: 345.1 | K51: 398.85 | L51: 322.15 | M51: 258.8 | N51: 207.3 | O51: 146.15 | P51: 129.15 | Q51: 129.05 | R51: 139.05 | S51: 131.55 | T51: 128.85 | U51: 138.1 | V51: 4393.5
B52: EMPRESA ELECTRICA RIO DOBLE | C52: C.H. LAS PIZARRAS | D52: CENTRAL | E52: HIDROELÉCTRICA | F52: 457.7 | G52: 457.8 | H52: 458.7 | I52: 458.5 | J52: 458.4 | K52: 457.1 | L52: 446 | M52: 414.35 | N52: 386.75 | O52: 367.45 | P52: 365.6 | Q52: 368.35 | R52: 356.05 | S52: 345.65 | T52: 322.5 | U52: 308.15 | V52: 6429.05
B53: ENEL GENERACION PIURA S.A. | C53: C.T. MALACAS 1 | D53: TG6 | E53: TERMOELÉCTRICA | F53: 955.95 | G53: 1098.1 | H53: 625.3 | I53: 1116.2 | J53: 759.95 | K53: 425.15 | L53: 601.3 | M53: 1017.25 | N53: 963.2 | O53: 978.05 | P53: 886.25 | Q53: 945.85 | R53: 793.1 | S53: 964.2 | T53: 924.55 | U53: 890.75 | V53: 13945.15
B54: ENEL GENERACION PIURA S.A. | C54: C.T. MALACAS 2 | D54: TG4 | E54: TERMOELÉCTRICA | K54: 423 | L54: 164.9 | V54: 587.9
B55: ENEL GENERACION PIURA S.A. | C55: C.T. RF DE GENERACION TALARA | D55: TG5 | E55: TERMOELÉCTRICA | V55: 0
B56: ENERGÍA EÓLICA S.A. | C56: C.E. CUPISNIQUE | D56: CENTRAL | E56: EÓLICA | F56: 1194.75 | G56: 665.1 | H56: 1221.15 | I56: 1066.05 | J56: 442.65 | K56: 573.05 | L56: 1228.7 | M56: 948.5 | N56: 757.45 | O56: 795.15 | P56: 1007.15 | Q56: 960.3 | R56: 1077.7 | S56: 1032.2 | T56: 920.5 | U56: 694.3 | V56: 14584.7
B57: ENERGÍA EÓLICA S.A. | C57: C.E. TALARA | D57: CENTRAL | E57: EÓLICA | F57: 384.4 | G57: 415.2 | H57: 248.35 | I57: 535.05 | J57: 437.5 | K57: 524.4 | L57: 627.15 | M57: 504.1 | N57: 402.9 | O57: 478.85 | P57: 587.1 | Q57: 585.6 | R57: 325 | S57: 459.85 | T57: 294.75 | U57: 209.7 | V57: 7019.9
B58: ENERGIA RENOVABLE DEL SUR S.A. | C58: C.E. SAN JUAN | D58: CENTRAL | E58: EÓLICA | F58: 2344.7 | G58: 1630.05 | H58: 1253.3 | I58: 1333.25 | J58: 625.4 | K58: 784.25 | L58: 2099.45 | M58: 1846.6 | N58: 1315 | O58: 1851.15 | P58: 1628.7 | Q58: 1384.3 | R58: 1714.25 | S58: 2074.9 | T58: 2556.8 | U58: 2181.1 | V58: 26623.2
B59: ENGIE ENERGIA PERU S.A.A. | C59: C.E. PUNTA LOMITAS | D59: PL-BL1 | E59: EÓLICA | F59: 1328.1 | G59: 1544.9 | H59: 1386.15 | I59: 1151.4 | J59: 745.65 | K59: 638.05 | L59: 2016.3 | M59: 1676.9 | N59: 1148 | O59: 1375.1 | P59: 1436.55 | Q59: 1199.7 | R59: 1089.5712 | S59: 1337 | T59: 1868.95 | U59: 1518.0742 | V59: 21460.395
B60: ENGIE ENERGIA PERU S.A.A. | C60: C.E. PUNTA LOMITAS | D60: PL-BL2 | E60: EÓLICA | F60: 1610.4 | G60: 1899.95 | H60: 1753.4 | I60: 1491.7 | J60: 906.8 | K60: 714.65 | L60: 2356.8 | M60: 1943.25 | N60: 1407.3 | O60: 1790.4 | P60: 1753.85 | Q60: 1626.15 | R60: 1392.285 | S60: 1616.65 | T60: 2051.55 | U60: 1870.0815 | V60: 26185.217
B61: ENGIE ENERGIA PERU S.A.A. | C61: C.E. PUNTA LOMITAS_EXP | D61: PUN LOM_EXP-BL1 | E61: EÓLICA | F61: 219.95 | G61: 242.6 | H61: 217.85 | I61: 180.35 | J61: 92.8 | K61: 79.25 | L61: 309.7 | M61: 247.35 | N61: 154.6 | O61: 188.6 | P61: 207.8 | Q61: 162.8 | R61: 131.02645 | S61: 172.8 | T61: 276.5 | U61: 192.36828 | V61: 3076.3447
B62: ENGIE ENERGIA PERU S.A.A. | C62: C.E. PUNTA LOMITAS_EXP | D62: PUN LOM_EXP-BL2 | E62: EÓLICA | F62: 41.7 | G62: 185.35 | H62: 154.2 | I62: 133.05 | J62: 68.7 | K62: 60.15 | L62: 222.05 | M62: 195.05 | N62: 123.75 | O62: 134.3 | P62: 157.7 | Q62: 116.65 | R62: 91.674615 | S62: 128.15 | T62: 186.15 | U62: 43.120915 | V62: 2041.7455
B63: ENGIE ENERGIA PERU S.A.A. | C63: C.H. QUITARACSA | D63: CENTRAL | E63: HIDROELÉCTRICA | G63: 329.7 | J63: 428.5 | M63: 449.9 | P63: 109.25 | V63: 1317.35
B64: ENGIE ENERGIA PERU S.A.A. | C64: C.H. YUNCAN | D64: CENTRAL | E64: HIDROELÉCTRICA | F64: 1979.1 | G64: 2050.8 | H64: 2205.25 | I64: 2073.25 | J64: 1796.25 | K64: 1902.55 | L64: 1668.5 | M64: 1920.05 | N64: 2108.4 | O64: 2753.7 | P64: 2975.45 | Q64: 2868.7 | R64: 2832.434 | S64: 1481.95 | T64: 1961.95 | U64: 1624.9129 | V64: 34203.247
B65: ENGIE ENERGIA PERU S.A.A. | C65: C.S. INTIPAMPA | D65: CENTRAL | E65: SOLAR | F65: 374.25 | G65: 369.55 | H65: 275 | I65: 207.6 | J65: 385.45 | K65: 408.75 | L65: 376.35 | M65: 378.6 | N65: 347.05 | O65: 385.1 | P65: 393.25 | Q65: 402.9 | R65: 387.85 | S65: 388.5 | T65: 394.6 | U65: 402.58446 | V65: 5877.3845
B66: ENGIE ENERGIA PERU S.A.A. | C66: C.S. INTIPAMPA EXPANSIÓN | D66: CENTRAL | E66: SOLAR | S66: 25.52 | T66: 171.19815 | U66: 211.065 | V66: 407.78315
B67: ENGIE ENERGIA PERU S.A.A. | C67: C.T. CHILCA 1 | D67: TG1 | E67: TERMOELÉCTRICA | F67: 1064.9 | G67: 3453.65 | H67: 4123.35 | I67: 4147.95 | J67: 4154.55 | K67: 4137.4 | L67: 3949.4 | M67: 4073.65 | N67: 3924.25 | O67: 3991.85 | P67: 3864.6 | Q67: 3979.15 | R67: 3877.6604 | S67: 3850.65 | T67: 3874.1 | U67: 3896.3077 | V67: 60363.418
B68: ENGIE ENERGIA PERU S.A.A. | C68: C.T. CHILCA 1 | D68: TG2 | E68: TERMOELÉCTRICA | F68: 4051 | G68: 4063.9 | H68: 4064.9 | I68: 4092.5 | J68: 4094.45 | K68: 4076.9 | L68: 3918.4 | M68: 4024.5 | N68: 3902.25 | O68: 3956.45 | P68: 3854.2 | Q68: 3945.5 | R68: 3866.2904 | S68: 3836.1 | T68: 3863.75 | U68: 3882.0039 | V68: 63493.094
B69: ENGIE ENERGIA PERU S.A.A. | C69: C.T. CHILCA 1 | D69: TG3 | E69: TERMOELÉCTRICA | F69: 4792.6 | G69: 4892.75 | H69: 4797.4 | I69: 4909.15 | J69: 4898.1 | K69: 4799.55 | L69: 4167.8 | M69: 4702.3 | N69: 4119.75 | O69: 4267.7 | P69: 3875.55 | Q69: 4366.7 | R69: 3962.2375 | S69: 4000.1 | T69: 3989.65 | U69: 4027.1191 | V69: 70568.457
B70: ENGIE ENERGIA PERU S.A.A. | C70: C.T. CHILCA 1 | D70: TV | E70: TERMOELÉCTRICA | F70: 4317.75 | G70: 5978.3 | H70: 6385.15 | I70: 6415 | J70: 6415.85 | K70: 6388.05 | L70: 6048.15 | M70: 6344.4 | N70: 6053.2 | O70: 6114.7 | P70: 5915.9 | Q70: 6161.25 | R70: 5928.8338 | S70: 5951.25 | T70: 5972.25 | U70: 5961.7851 | V70: 96351.819
B71: ENGIE ENERGIA PERU S.A.A. | C71: C.T. CHILCA 2 | D71: TG41 | E71: TERMOELÉCTRICA | J71: 982.5 | K71: 1637.65 | L71: 1077.4 | M71: 958.95 | N71: 1122.15 | O71: 1771.4 | P71: 1770.45 | Q71: 1762.1 | R71: 1763.7918 | S71: 1667.4 | T71: 1777.55 | U71: 1763.5293 | V71: 18054.871
B72: ENGIE ENERGIA PERU S.A.A. | C72: C.T. CHILCA 2 | D72: TV42 | E72: TERMOELÉCTRICA | N72: 455.85 | O72: 862.5 | P72: 863.35 | Q72: 862.6 | R72: 864.48117 | S72: 838.3 | T72: 866.45 | U72: 863.11156 | V72: 6476.6427
B73: ENGIE ENERGIA PERU S.A.A. | C73: C.T. NEPI | D73: TG41 | E73: TERMOELÉCTRICA | V73: 0
B74: ENGIE ENERGIA PERU S.A.A. | C74: C.T. NEPI | D74: TG42 | E74: TERMOELÉCTRICA | V74: 0
B75: ENGIE ENERGIA PERU S.A.A. | C75: C.T. NEPI | D75: TG43 | E75: TERMOELÉCTRICA | V75: 0
B76: ENGIE ENERGIA PERU S.A.A. | C76: C.T. RF PLANTA ILO | D76: TG1 | E76: TERMOELÉCTRICA | V76: 0
B77: ENGIE ENERGIA PERU S.A.A. | C77: C.T. RF PLANTA ILO | D77: TG2 | E77: TERMOELÉCTRICA | V77: 0
B78: ENGIE ENERGIA PERU S.A.A. | C78: C.T. RF PLANTA ILO | D78: TG3 | E78: TERMOELÉCTRICA | V78: 0
B79: FENIX POWER PERÚ | C79: C.T. FENIX | D79: GT11 | E79: TERMOELÉCTRICA | F79: 4372.65 | G79: 4316.0271 | H79: 4382.25 | I79: 4375.1 | J79: 4387.1 | K79: 4384.6 | L79: 4378.1 | M79: 4223.2 | N79: 4365.75 | O79: 4390.93 | P79: 4367.65 | Q79: 4372.05 | R79: 4376.45 | S79: 4259.4 | T79: 4360.4 | U79: 4376.5 | V79: 69688.157
B80: FENIX POWER PERÚ | C80: C.T. FENIX | D80: GT12 | E80: TERMOELÉCTRICA | F80: 4401.1 | G80: 4329.8008 | H80: 4395.1 | I80: 4386.35 | J80: 4008.45 | K80: 4395.45 | L80: 3551.15 | M80: 4165.15 | N80: 4380.55 | O80: 4378.03 | P80: 4380.2 | Q80: 4386.55 | R80: 4389.8 | S80: 4271.05 | T80: 4372.3 | U80: 4386.5 | V80: 68577.531
B81: FENIX POWER PERÚ | C81: C.T. FENIX | D81: TV10 | E81: TERMOELÉCTRICA | F81: 4416.15 | G81: 4409.5639 | H81: 4434.4 | I81: 4439 | J81: 924.3 | L81: 117.65 | M81: 4136.9 | N81: 4420.05 | O81: 4448.59 | P81: 4428.2 | Q81: 4437.95 | R81: 4435.9 | S81: 4362.4 | T81: 4432.6 | U81: 4433.65 | V81: 58277.304
B82: GENERACIÓN ANDINA S.A.C. | C82: C.H. 8 DE AGOSTO | D82: CENTRAL | E82: HIDROELÉCTRICA | F82: 337.35 | G82: 280.95 | H82: 392.55 | I82: 280.7 | J82: 256.15 | K82: 249.6 | L82: 247.4 | M82: 236.45 | N82: 231.05 | O82: 249.6 | P82: 311.95 | Q82: 455.45 | R82: 433.45 | S82: 372.1 | T82: 302.05 | U82: 326.65 | V82: 4963.45
B83: GENERACIÓN ANDINA S.A.C. | C83: C.H. EL CARMEN | D83: CENTRAL | E83: HIDROELÉCTRICA | F83: 84.7 | G83: 75.35 | H83: 81.3 | I83: 76.45 | J83: 70.05 | K83: 66.15 | L83: 61.95 | M83: 58.8 | N83: 57.85 | O83: 77.25 | P83: 134.8 | Q83: 159.8 | R83: 160.55 | S83: 134.55 | T83: 101.4 | U83: 97.4 | V83: 1498.35
B84: GENERADORA DE ENERGÍA DEL PERÚ | C84: C.H. ÁNGEL I | D84: CENTRAL | E84: HIDROELÉCTRICA | F84: 481.6 | G84: 423 | H84: 489.6 | I84: 489.6 | J84: 489.6 | K84: 443.7 | L84: 489.6 | M84: 489.6 | N84: 464.1 | O84: 489.6 | P84: 489.6 | Q84: 489.6 | R84: 489.6 | S84: 489.6 | T84: 489.6 | U84: 489.6 | V84: 7687.6
B85: GENERADORA DE ENERGÍA DEL PERÚ | C85: C.H. ÁNGEL II | D85: CENTRAL | E85: HIDROELÉCTRICA | F85: 487.7 | G85: 452.4 | H85: 489.6 | I85: 489.6 | J85: 453.9 | K85: 458.3 | L85: 489.6 | M85: 489.6 | N85: 465.85 | O85: 489.6 | P85: 489.6 | Q85: 459.05 | R85: 489.6 | S85: 489.6 | T85: 489.6 | U85: 489.6 | V85: 7673.2
B86: GENERADORA DE ENERGÍA DEL PERÚ | C86: C.H. ÁNGEL III | D86: CENTRAL | E86: HIDROELÉCTRICA | F86: 480.2 | G86: 446.05 | H86: 482.4 | I86: 482.4 | J86: 442.2 | K86: 424.55 | L86: 480 | M86: 482.4 | N86: 440.55 | O86: 482.4 | P86: 482.4 | Q86: 453.5 | R86: 472.25 | S86: 480 | T86: 481.65 | U86: 480 | V86: 7492.95
B87: GENERADORA DE ENERGÍA DEL PERÚ | C87: C.H. LA JOYA | D87: CENTRAL | E87: HIDROELÉCTRICA | F87: 189.85 | G87: 159.55 | H87: 177.3 | I87: 118.7 | J87: 180.35 | K87: 191.4 | L87: 183.5 | M87: 183.8 | N87: 183.1 | O87: 196.75 | P87: 195.35 | Q87: 193 | R87: 195.6 | S87: 200.7 | T87: 202.45 | U87: 199.95 | V87: 2951.35
B88: GM OPERACIONES S.A.C. | C88: CT REFINERIA TALARA | D88: TV1 REF TALARA | E88: TERMOELÉCTRICA | F88: 653.4 | G88: 650.65 | H88: 657.45 | I88: 660.35 | J88: 664.3 | K88: 660.85 | L88: 660 | M88: 654.05 | N88: 657.5 | O88: 663.3 | P88: 659.45 | Q88: 660.7 | R88: 663 | S88: 667.9 | T88: 659.6 | U88: 657.65 | V88: 10550.15
B89: GM OPERACIONES S.A.C. | C89: CT REFINERIA TALARA | D89: TV2 REF TALARA | E89: TERMOELÉCTRICA | F89: 821.1 | G89: 826.25 | H89: 821.7 | I89: 832.9 | J89: 832.05 | K89: 828.8 | L89: 829.15 | M89: 825.4 | N89: 826.05 | O89: 831.05 | P89: 827 | Q89: 829.9 | R89: 833.9 | S89: 841 | T89: 830.3 | U89: 825.25 | V89: 13261.8
B90: GR CORTARRAMA SOCIEDAD ANONIMA CERRADA | C90: C.S. MATARANI | D90: C.S. MATARANI | E90: SOLAR | F90: 834 | G90: 767.25 | H90: 610.25 | I90: 598.15 | J90: 775.8 | K90: 838.25 | L90: 759.6 | M90: 739.6 | N90: 764.95 | O90: 846.45 | P90: 766.6 | Q90: 847.9 | R90: 806.7 | S90: 836.85 | T90: 817.4 | U90: 752.25 | V90: 12362
B91: GR PAINO SOCIEDAD ANONIMA CERRADA | C91: C.E. HUAMBOS | D91: CENTRAL | E91: EÓLICA | F91: 122.65 | G91: 127.6 | H91: 118.7 | I91: 103.55 | J91: 69.4 | K91: 72.3 | L91: 76.1 | M91: 70.5 | N91: 63.45 | O91: 128.1 | P91: 75 | Q91: 165.6 | R91: 86.95 | S91: 109.6 | T91: 84.95 | U91: 39.965 | V91: 1514.415
B92: GR TARUCA SOCIEDAD ANONIMA CERRADA | C92: C.E. DUNA | D92: CENTRAL | E92: EÓLICA | F92: 76.7 | G92: 71.75 | H92: 60.8 | I92: 56.15 | J92: 36.6 | K92: 31.45 | L92: 49.9 | M92: 35.2 | N92: 39.65 | O92: 111.05 | P92: 71.3 | Q92: 169.2 | R92: 80.75 | S92: 98.95 | T92: 59.15 | U92: 36.75 | V92: 1085.35
B93: HIDROCAÑETE S.A. | C93: C.H. IMPERIAL | D93: CENTRAL | E93: HIDROELÉCTRICA | F93: 78.7 | G93: 75.2 | H93: 75.8 | I93: 75.05 | J93: 76.8 | K93: 74.3 | L93: 76.15 | M93: 75.95 | N93: 72.1 | O93: 69.1 | P93: 71.5 | Q93: 75.7 | R93: 73.55 | S93: 75.55 | T93: 75.2 | U93: 64.95 | V93: 1185.6
... B96: HYDRO GLOBAL PERÚ S.A.C. | C96: CH SAN GABAN III | D96: CENTRAL | E96: HIDROELÉCTRICA | F96: 4233.85 | G96: 4873.85 | H96: 4840.85 | I96: 4876.85 | J96: 4879.4 | K96: 4871.4 | L96: 4874.35 | M96: 4869.6 | N96: 4867.25 | O96: 4860.75 | P96: 4869.15 | Q96: 4867.25 | R96: 4875.1 | S96: 4882.65 | T96: 4867.5 | U96: 4862.15 | V96: 77271.95
B97: INFRAESTRUCTURAS Y ENERGIAS DEL PERU S.A.C. | C97: C.T. RF PTO MALDONADO | D97: CENTRAL | E97: TERMOELÉCTRICA | Q97: 7.55 | S97: 121.25 | V97: 128.8
B98: INFRAESTRUCTURAS Y ENERGIAS DEL PERU S.A.C. | C98: C.T. RF PUCALLPA | D98: CENTRAL | E98: TERMOELÉCTRICA | T98: 1.45 | V98: 1.45
B99: INLAND ENERGY SAC | C99: C.H. SANTA TERESA | D99: CENTRAL | E99: HIDROELÉCTRICA | F99: 2174.955 | G99: 2156.25 | H99: 2176.55 | I99: 2181.6 | J99: 2164 | K99: 2166.75 | L99: 2125.65 | M99: 2188 | N99: 2168.3 | O99: 2180.55 | P99: 2178.7 | Q99: 1889.55 | R99: 2171.75 | S99: 1525.1 | T99: 1366.6 | U99: 1368.3 | V99: 32182.605
B100: INVERSIONES SHAQSHA S.A.C. | C100: C.H. PARIAC | D100: CENTRAL | E100: HIDROELÉCTRICA | F100: 49.9 | G100: 30.1 | H100: 22.05 | I100: 20.15 | J100: 22.65 | K100: 19.8 | L100: 19.2 | M100: 19.2 | N100: 19.2 | O100: 19.1 | P100: 16.8 | Q100: 16.8 | R100: 16 | S100: 5.45 | V100: 296.4
B101: JOYA SOLAR S.A.C. | C101: C.S. SAN MARTIN SOLAR | D101: CENTRAL | E101: SOLAR | F101: 2467.7 | G101: 2327.35 | H101: 1766.55 | I101: 1976.35 | J101: 2556.75 | K101: 2751.85 | L101: 2466.55 | M101: 2536.25 | N101: 2486.8 | O101: 2731.85 | P101: 2552.6 | Q101: 2768.1 | R101: 2682.75 | S101: 2739.5 | T101: 2753.45 | U101: 2699.45 | V101: 40263.85
B102: KALLPA GENERACION S.A. | C102: C.H. CERRO DEL AGUILA | D102: CENTRAL | E102: HIDROELÉCTRICA | F102: 5295.55 | G102: 5774.4 | H102: 6120.55 | I102: 4952.15 | J102: 5770.35 | K102: 3514.25 | L102: 3744.5 | M102: 3601.9 | N102: 2909.2 | O102: 1513.5 | P102: 4179.65 | Q102: 4789.15 | R102: 5093.9 | S102: 5039.8 | T102: 3842.25 | U102: 5922.1 | V102: 72063.2
B103: KALLPA GENERACION S.A. | C103: C.S. SUNNY | D103: CENTRAL | E103: SOLAR | F103: 2198.25 | G103: 2019 | H103: 1409.95 | I103: 1564.5 | J103: 2174.65 | K103: 2295.75 | L103: 2073.8 | M103: 2014.8 | N103: 2103.85 | O103: 2252.4 | P103: 2177.9 | Q103: 2301.6 | R103: 2169.75 | S103: 2247.65 | T103: 2305.65 | U103: 2242.7 | V103: 33552.2
B104: KALLPA GENERACION S.A. | C104: C.T. KALLPA | D104: TG1 | E104: TERMOELÉCTRICA | F104: 4146.15 | G104: 4046.6 | H104: 4104.4 | I104: 4145.1 | J104: 4296.02 | K104: 4265.7 | L104: 3211.55 | M104: 2328.65 | N104: 4267.45 | O104: 4299.85 | P104: 2776.45 | Q104: 1572.65 | R104: 2405.5 | S104: 268.95 | T104: 2885.3 | U104: 4371.85 | V104: 53392.17
B105: KALLPA GENERACION S.A. | C105: C.T. KALLPA | D105: TG2 | E105: TERMOELÉCTRICA | F105: 4439.6 | G105: 4271.2 | H105: 4371.4 | I105: 4451.95 | J105: 4544.27 | K105: 4534.15 | L105: 4856 | M105: 4294.05 | N105: 4942.3 | O105: 4921.7 | P105: 4891.9 | Q105: 4925.4 | R105: 4934.7 | S105: 968.15 | T105: 4922.45 | U105: 4917.85 | V105: 71187.07
...

Sheet G_AREAS
B3: martes, 16 de Diciembre del 2025
B5: HORA | C5: RESUMEN DE GENERACIÓN POR ÁREAS DEL SEIN | D5: RESUMEN DE GENERACIÓN POR ÁREAS DEL SEIN | E5: RESUMEN DE GENERACIÓN POR ÁREAS DEL SEIN | F5: RESUMEN DE GENERACIÓN POR ÁREAS DEL SEIN | G5: RESUMEN DE GENERACIÓN POR ÁREAS DEL SEIN | H5: RESUMEN DE GENERACIÓN POR ÁREAS DEL SEIN | I5: RESUMEN DE GENERACIÓN POR ÁREAS DEL SEIN | J5: RESUMEN DE GENERACIÓN POR ÁREAS DEL SEIN | K5: RESUMEN DE GENERACIÓN POR ÁREAS DEL SEIN | L5: RESUMEN DE GENERACIÓN POR ÁREAS DEL SEIN | M5: RESUMEN DE GENERACIÓN POR ÁREAS DEL SEIN | N5: RESUMEN DE GENERACIÓN POR ÁREAS DEL SEIN | O5: RESUMEN DE GENERACIÓN POR ÁREAS DEL SEIN | P5: RESUMEN DE GENERACIÓN POR ÁREAS DEL SEIN | Q5: RESUMEN DE GENERACIÓN POR ÁREAS DEL SEIN | R5: RESUMEN DE GENERACIÓN POR ÁREAS DEL SEIN | S5: HORA | T5: GENERACIÓN POR TIPO DE GENERACIÓN | U5: GENERACIÓN POR TIPO DE GENERACIÓN | V5: GENERACIÓN POR TIPO DE GENERACIÓN | W5: GENERACIÓN POR TIPO DE GENERACIÓN | X5: GENERACIÓN POR TIPO DE GENERACIÓN | Y5: HORA | Z5: GENERACIÓN POR TIPO DE GENERACIÓN | AA5: GENERACIÓN POR TIPO DE GENERACIÓN | AB5: GENERACIÓN POR TIPO DE GENERACIÓN | AC5: GENERACIÓN POR TIPO DE GENERACIÓN | AD5: GENERACIÓN POR TIPO DE GENERACIÓN
C6: NORTE | D6: NORTE | E6: NORTE | F6: NORTE | G6: CENTRO | H6: CENTRO | I6: CENTRO | J6: CENTRO | K6: SUR | L6: SUR | M6: SUR | N6: SUR | O6: GENERACIÓN INTEGRANTES COES | P6: GENERACIÓN INTEGRANTES COES | Q6: GENERACIÓN INTEGRANTES COES | R6: GENERACIÓN INTEGRANTES COES | T6: INTEGRANTES COES | U6: INTEGRANTES COES | V6: INTEGRANTES COES | W6: INTEGRANTES COES | X6: INTEGRANTES COES | Z6: INTEGRANTES COES RER | AA6: INTEGRANTES COES RER | AB6: INTEGRANTES COES RER | AC6: INTEGRANTES COES RER | AD6: INTEGRANTES COES RER
C7: GENERACIÓN HIDROELÉCTRICA NORTE | D7: GENERACIÓN TERMOELÉCTRICA NORTE | E7: GENERACIÓN SOLAR NORTE | F7: GENERACIÓN EÓLICA NORTE | G7: GENERACIÓN HIDROELÉCTRICA CENTRO | H7: GENERACIÓN TERMOELÉCTRICA CENTRO | I7: GENERACIÓN SOLAR CENTRO | J7: GENERACIÓN EÓLICA CENTRO | K7: GENERACIÓN HIDROELÉCTRICA SUR | L7: GENERACIÓN TERMOELÉCTRICA SUR | M7: GENERACIÓN SOLAR SUR | N7: GENERACIÓN EÓLICA SUR | O7: GENERACIÓN COES NORTE | P7: GENERACIÓN COES CENTRO | Q7: GENERACIÓN COES SUR | R7: TOTAL GENERACION | T7: HIDROELÉCTRICA | U7: TERMOELÉCTRICA | V7: SOLAR | W7: EÓLICA | X7: TOTAL GENERACION | Z7: HIDROELÉCTRICA RER | AA7: TERMOELÉCTRICA RER | AB7: SOLAR RER | AC7: EÓLICA RER | AD7: TOTAL RER
B8: 00:30 | C8: 281.4 | D8: 132.2 | E8: 0 | F8: 29.1 | G8: 2169.999 | H8: 3041.8775 | I8: 0 | J8: 478.00035 | K8: 712.5 | L8: 0 | M8: 0 | N8: 0 | O8: 442.7 | P8: 5689.8768 | Q8: 712.5 | R8: 6845.0768 | S8: 00:30 | T8: 3163.899 | U8: 3196.2775 | V8: 0 | W8: 507.10035 | X8: 6867.2768 | Y8: 00:30 | Z8: 254.3 | AA8: 93.5 | AB8: 0 | AC8: 507.10035 | AD8: 854.90035
B9: 01:00 | C9: 284.6 | D9: 131.4 | E9: 0 | F9: 28 | G9: 2056.4628 | H9: 3045.2834 | I9: 0 | J9: 583.26118 | K9: 718.1 | L9: 0 | M9: 0 | N9: 0 | O9: 444 | P9: 5685.0073 | Q9: 718.1 | R9: 6847.1073 | S9: 01:00 | T9: 3059.1628 | U9: 3198.2834 | V9: 0 | W9: 611.26118 | X9: 6868.7073 | Y9: 01:00 | Z9: 255.6 | AA9: 92 | AB9: 0 | AC9: 611.26118 | AD9: 958.86118
B10: 01:30 | C10: 263.4 | D10: 132.8 | E10: 0 | F10: 23.4 | G10: 1957.9299 | H10: 2929.8039 | I10: 0 | J10: 614.97428 | K10: 708.2 | L10: 0 | M10: 0 | N10: 0 | O10: 419.6 | P10: 5502.7081 | Q10: 708.2 | R10: 6630.5081 | S10: 01:30 | T10: 2929.5299 | U10: 3083.8039 | V10: 0 | W10: 638.37428 | X10: 6651.7081 | Y10: 01:30 | Z10: 251.5 | AA10: 94.4 | AB10: 0 | AC10: 638.37428 | AD10: 984.27428
B11: 02:00 | C11: 229.2 | D11: 133.2 | E11: 0 | F11: 22.7 | G11: 1935.1769 | H11: 2895.0178 | I11: 0 | J11: 654.92237 | K11: 725.4 | L11: 0 | M11: 0 | N11: 0 | O11: 385.1 | P11: 5485.1171 | Q11: 725.4 | R11: 6595.6171 | S11: 02:00 | T11: 2889.7769 | U11: 3049.2178 | V11: 0 | W11: 677.62237 | X11: 6616.6171 | Y11: 02:00 | Z11: 248.2 | AA11: 94.5 | AB11: 0 | AC11: 677.62237 | AD11: 1020.3224
B12: 02:30 | C12: 224.5 | D12: 134.2 | E12: 0 | F12: 23.4 | G12: 1798.3267 | H12: 2977.6222 | I12: 0 | J12: 651.00432 | K12: 713.3 | L12: 0 | M12: 0 | N12: 0 | O12: 382.1 | P12: 5426.9532 | Q12: 713.3 | R12: 6522.3532 | S12: 02:30 | T12: 2736.1267 | U12: 3130.2222 | V12: 0 | W12: 674.40432 | X12: 6540.7532 | Y12: 02:30 | Z12: 244.9 | AA12: 92.9 | AB12: 0 | AC12: 674.40432 | AD12: 1012.2043
B13: 03:00 | C13: 226 | D13: 135.9 | E13: 0 | F13: 24.5 | G13: 1781.2813 | H13: 2933.3005 | I13: 0 | J13: 631.33643 | K13: 719.3 | L13: 0 | M13: 0 | N13: 0 | O13: 386.4 | P13: 5345.9182 | Q13: 719.3 | R13: 6451.6182 | S13: 03:00 | T13: 2726.5813 | U13: 3091.2005 | V13: 0 | W13: 655.83643 | X13: 6473.6182 | Y13: 03:00 | Z13: 247 | AA13: 96.8 | AB13: 0 | AC13: 655.83643 | AD13: 999.63643
B14: 03:30 | C14: 226.6 | D14: 136 | E14: 0 | F14: 21.6 | G14: 1794.0493 | H14: 3045.3338 | I14: 0 | J14: 610.52293 | K14: 722 | L14: 0 | M14: 0 | N14: 0 | O14: 384.2 | P14: 5449.9061 | Q14: 722 | R14: 6556.1061 | S14: 03:30 | T14: 2742.6493 | U14: 3203.5338 | V14: 0 | W14: 632.12293 | X14: 6578.3061 | Y14: 03:30 | Z14: 247 | AA14: 97.9 | AB14: 0 | AC14: 632.12293 | AD14: 977.02293
B15: 04:00 | C15: 224 | D15: 135.5 | E15: 0 | F15: 21.4 | G15: 1846.1796 | H15: 3049.5775 | I15: 0 | J15: 592.50398 | K15: 718 | L15: 0 | M15: 0 | N15: 0 | O15: 380.9 | P15: 5488.2611 | Q15: 718 | R15: 6587.1611 | S15: 04:00 | T15: 2788.1796 | U15: 3204.7775 | V15: 0 | W15: 613.90398 | X15: 6606.8611 | Y15: 04:00 | Z15: 247 | AA15: 94.2 | AB15: 0 | AC15: 613.90398 | AD15: 955.10398
B16: 04:30 | C16: 223.7 | D16: 134.9 | E16: 0 | F16: 22 | G16: 1900.4337 | H16: 3047.2861 | I16: 0 | J16: 519.23816 | K16: 711.5 | L16: 0 | M16: 0 | N16: 0 | O16: 380.6 | P16: 5466.9579 | Q16: 711.5 | R16: 6559.0579 | S16: 04:30 | T16: 2835.6337 | U16: 3199.5861 | V16: 0 | W16: 541.23816 | X16: 6576.4579 | Y16: 04:30 | Z16: 247.6 | AA16: 91.7 | AB16: 0 | AC16: 541.23816 | AD16: 880.53816
B17: 05:00 | C17: 215.4 | D17: 135.3 | E17: 0 | F17: 18.7 | G17: 1951.7247 | H17: 3020.5053 | I17: 0 | J17: 501.09035 | K17: 718.9 | L17: 0 | M17: 0 | N17: 0 | O17: 369.4 | P17: 5473.3203 | Q17: 718.9 | R17: 6561.6203 | S17: 05:00 | T17: 2886.0247 | U17: 3173.1053 | V17: 0 | W17: 519.79035 | X17: 6578.9203 | Y17: 05:00 | Z17: 247.5 | AA17: 91.6 | AB17: 0 | AC17: 519.79035 | AD17: 858.89035
B18: 05:30 | C18: 211.6 | D18: 135.2 | E18: 0 | F18: 14.6 | G18: 2088.4309 | H18: 3040.123 | I18: 0 | J18: 472.81723 | K18: 717.8 | L18: 0 | M18: 26.81957 | N18: 0 | O18: 361.4 | P18: 5601.3711 | Q18: 744.61957 | R18: 6707.3906 | S18: 05:30 | T18: 3017.8308 | U18: 3198.123 | V18: 26.81957 | W18: 487.41723 | X18: 6730.1906 | Y18: 05:30 | Z18: 246 | AA18: 96.9 | AB18: 26.81957 | AC18: 487.41723 | AD18: 857.1368
B19: 06:00 | C19: 218.6 | D19: 135.4 | E19: 0 | F19: 12.7 | G19: 2016.199 | H19: 2975.5905 | I19: 0 | J19: 452.18215 | K19: 715.7 | L19: 0 | M19: 125.10892 | N19: 0 | O19: 366.7 | P19: 5443.9716 | Q19: 840.80892 | R19: 6651.4805 | S19: 06:00 | T19: 2950.499 | U19: 3133.3905 | V19: 126.82892 | W19: 464.88215 | X19: 6675.6005 | Y19: 06:00 | Z19: 250 | AA19: 95.9 | AB19: 126.82892 | AC19: 464.88215 | AD19: 937.61107
... B56: TOTAL MWh | C56: 7103.25 | D56: 3531.8195 | E56: 1.85 | F56: 980.715 | G56: 53156.363 | H56: 75215.157 | I56: 8.05 | J56: 11244.395 | K56: 17523.1 | L56: 0 | M56: 9518.2845 | N56: 0 | O56: 11617.635 | P56: 139623.96 | Q56: 27041.384 | R56: 178282.98 | S56: TOTAL MWh | T56: 77782.713 | U56: 79230.726 | V56: 9739.2495 | W56: 12225.11 | X56: 178977.8 | Y56: TOTAL MWh | Z56: 6488.8 | AA56: 2238.9695 | AB56: 9739.2495 | AC56: 12225.11 | AD56: 30692.129

Sheet HOP
B3: martes, 16 de Diciembre del 2025
B5: Reporte de Horas de Operación
B6: Empresa | C6: Central | D6: Grupo | E6: Modo de Operación | F6: Inicio | G6: Final | H6: O. Arranque | I6: O. Parada | J6: Tipo Operación | K6: Ensayo de Potencia Efectiva | L6: Ensayo de Potencia Mínima | M6: Sistema | N6: Lim. Transm. | O6: Causa | P6: Observación
B7: AGRO INDUSTRIAL PARAMONGA S.A. | C7: C.T. PARAMONGA | D7: CENTRAL | E7: PARAMONGA - BAGAZO | F7: 16/12/2025 00:00:00 | G7: 17/12/2025 00:00:00 | J7: POR COGENERACION | O7: ...
B8: AGROAURORA S.A.C. | C8: C.T. MAPLE ETANOL | D8: CENTRAL | E8: MAPLE- BAGAZO | F8: 16/12/2025 00:00:00 | G8: 16/12/2025 23:58:00 | J8: POR COGENERACION | O8: ...
B9: AGROAURORA S.A.C. | C9: C.T. MAPLE ETANOL | D9: CENTRAL | E9: MAPLE- BAGAZO | F9: 16/12/2025 23:58:00 | G9: 17/12/2025 00:00:00 | J9: NO IDENTIFICADO | O9: ...
B10: AGROINDUSTRIAS SAN JACINTO S.A.A. | C10: C.T. SAN JACINTO | D10: CENTRAL | E10: SAN_JACINTO - BAGAZO | F10: 16/12/2025 00:00:00 | G10: 17/12/2025 00:00:00 | J10: POR COGENERACION | O10: ...
B11: AGROLMOS SOCIEDAD ANONIMA - AGROLMOS S.A. | C11: C.T. AGROLMOS | D11: CENTRAL | E11: AGROLMOS TV1 & TV2 - BAGAZO | F11: 16/12/2025 00:00:00 | G11: 17/12/2025 00:00:00 | J11: POR COGENERACION | O11: ...
B12: BIOENERGIA DEL CHIRA S.A. | C12: C.T. CAÑA BRAVA | D12: G-1 | E12: CANA BRAVA TV1 - BAGAZO | F12: 16/12/2025 00:00:00 | G12: 17/12/2025 00:00:00 | J12: POR COGENERACION | O12: ...
B13: CASA GRANDE S.A.A. | C13: C.T. CASA GRANDE | D13: TV3 | E13: CASA GRANDE TV3 - BAGAZO | F13: 16/12/2025 00:00:00 | G13: 16/12/2025 21:10:00 | J13: POR COGENERACION | O13: ...
B14: EGESUR | C14: C.T. INDEPENDENCIA | D14: CENTRAL | E14: INDEPENDENCIA GAS | F14: 16/12/2025 00:00:00 | G14: 17/12/2025 00:00:00 | J14: POR POTENCIA O ENERGIA | O14: ...
B15: EGESUR | C15: C.T. INDEPENDENCIA | D15: INDEP_G3 | E15: INDEPENDENCIA GAS | F15: 16/12/2025 00:00:00 | G15: 16/12/2025 08:03:00 | J15: POR PRUEBAS | O15: ...
B16: EGESUR | C16: C.T. INDEPENDENCIA | D16: INDEP_G1 | E16: INDEPENDENCIA GAS | F16: 16/12/2025 09:55:00 | G16: 16/12/2025 10:20:00 | J16: POR PRUEBAS | O16: ...
B17: EGESUR | C17: C.T. INDEPENDENCIA | D17: INDEP_G1 | E17: INDEPENDENCIA GAS | F17: 16/12/2025 10:20:00 | G17: 17/12/2025 00:00:00 | J17: POR POTENCIA O ENERGIA | O17: ...
B18: ENEL GENERACION PIURA S.A. | C18: C.T. MALACAS 1 | D18: CENTRAL | E18: MALACAS1 TG6 - GAS | F18: 16/12/2025 00:00:00 | G18: 17/12/2025 00:00:00 | J18: POR POTENCIA O ENERGIA | O18: ... | P18: A las 14:34 h, S/C generar a máxima generación.
B19: ENGIE ENERGIA PERU S.A.A. | C19: C.T. CHILCA 1 | D19: CENTRAL | E19: CHILCA1 CCOMB TG1 & TG2 & TG3 - GAS | F19: 16/12/2025 00:00:00 | G19: 17/12/2025 00:00:00 | J19: POR POTENCIA O ENERGIA | O19: ...
B20: ENGIE ENERGIA PERU S.A.A. | C20: C.T. CHILCA 2 | D20: CENTRAL | E20: CHILCA2 CCOMB TG41 - GAS | F20: 16/12/2025 00:00:00 | G20: 17/12/2025 00:00:00 | J20: POR POTENCIA O ENERGIA | O20: ...
B21: FENIX POWER PERÚ | C21: C.T. FENIX | D21: CENTRAL | E21: FENIX CCOMB GT11 & GT12 - GAS | F21: 16/12/2025 00:00:00 | G21: 17/12/2025 00:00:00 | J21: POR POTENCIA O ENERGIA | O21: ...
B22: GM OPERACIONES S.A.C. | C22: CT REFINERIA TALARA | D22: TV1 REF TALARA | E22: REF_TALARA TV1 - NLH_RFG | F22: 16/12/2025 00:00:00 | G22: 17/12/2025 00:00:00 | J22: POR COGENERACION | O22: ...
B23: GM OPERACIONES S.A.C. | C23: CT REFINERIA TALARA | D23: TV2 REF TALARA | E23: REF_TALARA TV2 - NLH_RFG | F23: 16/12/2025 00:00:00 | G23: 17/12/2025 00:00:00 | J23: POR COGENERACION | O23: ...
B24: KALLPA GENERACION S.A. | C24: C.T. KALLPA | D24: TG1 | E24: KALLPA TG1 - GAS | F24: 16/12/2025 00:00:00 | G24: 17/12/2025 00:00:00 | J24: POR POTENCIA O ENERGIA | O24: ...
B25: KALLPA GENERACION S.A. | C25: C.T. KALLPA | D25: TG2 | E25: KALLPA TG2 - GAS | F25: 16/12/2025 00:00:00 | G25: 17/12/2025 00:00:00 | J25: POR POTENCIA O ENERGIA | O25: ...
B26: KALLPA GENERACION S.A. | C26: C.T. KALLPA | D26: TG3 | E26: KALLPA TG3 - GAS | F26: 16/12/2025 00:00:00 | G26: 17/12/2025 00:00:00 | J26: POR POTENCIA O ENERGIA | O26: ...
B27: KALLPA GENERACION S.A. | C27: C.T. LAS FLORES | D27: TG1 | E27: LAS FLORES TG1 - GAS | F27: 16/12/2025 00:00:00 | G27: 17/12/2025 00:00:00 | J27: POR POTENCIA O ENERGIA | O27: ...
B28: ORYGEN PERU S.A.A. | C28: C.T. SANTA ROSA I | D28: TG7 | E28: STA ROSA WEST TG7 - GAS CON H2O | F28: 16/12/2025 00:00:00 | G28: 16/12/2025 01:24:00 | I28: 16/12/2025 01:16:00 | J28: A MINIMA CARGA | O28: ...
