Workbook

Sheet EVENTOS
B3: lunes, 27 de Enero del 2025
B5: INFORMACIÓN DE EVENTOS PRINCIPALES EN SUS INSTALACIONES
B6: TIPO DE EVENTO | C6: EMPRESA | D6: UBICACIÓN | E6: TIPO DE EQUIPO | F6: EQUIPO | G6: INICIO | H6: FINAL | I6: DESCRIPCIÓN | J6: MW INDISP. | K6: INTERRUPCIÓN (SI/NO) | L6: TENSIÓN DE FALLA (kV)
B7: FALLA | C7: AGROAURORA S.A.C. | D7: MAPLE ETANOL | E7: CENTRAL TERMOELÉCTRICA | F7: CENTRAL | G7: 27/01/2025 04:38:00 | H7: 27/01/2025 22:08:00 | I7: DESCONEXIÓN DE LA TV DE LA C.T. MAPLE | K7: NO | L7: 0
B8: EVENTO | C8: CONELSUR LT SAC | D8: PORTILLO | E8: SUBESTACION | F8: SS.EE. | G8: 27/01/2025 00:00:00 | H8: 28/01/2025 00:00:00 | I8: DECLARACIÓN DE SITUACIÓN EXCEPCIONAL EN LA S.E. PORTILLO DE 60 kV | K8: NO
B9: EVENTO | C9: CONELSUR LT SAC | D9: PORTILLO | E9: SUBESTACION | F9: SS.EE. | G9: 28/01/2025 00:00:00 | H9: 28/01/2025 00:00:00 | I9: DECLARACIÓN DE SITUACIÓN EXCEPCIONAL EN LA S.E. PORTILLO DE 60 kV | K9: NO
B10: FALLA | C10: EGESUR | D10: INDEPENDENCIA | E10: GENERADOR TERMOELÉCTRICO | F10: INDEP_G1 | G10: 27/01/2025 14:43:00 | H10: 27/01/2025 15:49:00 | I10: DESCONEXIÓN DEL GENERADOR G1 DE LA C.T. INDEPENDENCIA | K10: NO | L10: 0
B11: FALLA | C11: HIDROCAÑETE S.A. | D11: NUEVA IMPERIAL | E11: CENTRAL HIDROELÉCTRICA | F11: CENTRAL | G11: 27/01/2025 01:47:26 | H11: 27/01/2025 05:42:00 | I11: DESCONEXIÓN DE LA C.H. NUEVA IMPERIAL POR FALLA EXTERNA | K11: NO | L11: 20
B12: FALLA | C12: HIDROCAÑETE S.A. | D12: NUEVA IMPERIAL | E12: CENTRAL HIDROELÉCTRICA | F12: CENTRAL | G12: 27/01/2025 19:57:36 | H12: 28/01/2025 00:00:00 | I12: DESCONEXIÓN DE LA C.H. NUEVA IMPERIAL POR FALLA EXTERNA | K12: NO | L12: 20
B13: FALLA | C13: ORYGEN PERU S.A.A. | D13: MOYOPAMPA | E13: GENERADOR HIDROELÉCTRICO | F13: G3 | G13: 27/01/2025 01:52:00 | H13: 27/01/2025 06:58:00 | I13: DESCONEXIÓN DEL GRUPO G3 DE LA C.H. MOYOPAMPA | K13: NO | L13: 9.5

Sheet RESTRIC_OPE
B3: lunes, 27 de Enero del 2025
B5: RESTRICCIONES OPERATIVAS
B6: FECHA | C6: HORA INICIO | D6: HORA FINAL | E6: EMPRESA | F6: UBICACIÓN | G6: T.Eq. | H6: EQUIPO | I6: DESCRIPCIÓN
B7: 27/01/2025 | C7: 00:00 | D7: 24:00 | E7: CELEPSA | F7: C.H. EL PLATANAL | G7: CH | H7: CENTRAL | I7: Debido al incremento del caudal del rio cañete y establecimiento de la temporada de avenida, se declara la C.H. El Platanal como CENTRAL HIDRÁULICA DE PASADA (correo 03/01/2025).
B8: 27/01/2025 | C8: 00:00 | D8: 24:00 | E8: CELEPSA | F8: C.H. EL PLATANAL | G8: CH | H8: CENTRAL | I8: Debido al incremento del caudal del rio cañete y establecimiento de la temporada de avenida, se declara la C.H. El Platanal como CENTRAL HIDRÁULICA DE PASADA (correo 03/01/2025).
B9: 27/01/2025 | C9: 00:00 | D9: 24:00 | E9: EGASA | F9: S.E. CONVERTIDOR | G9: BARRA | H9: BARRA138KV | I9: EGASA limitó la capacidad del transformador 138 kV/33 kV a 50 MVA por deterioro del aislamiento.
B10: 27/01/2025 | C10: 00:00 | D10: 24:00 | E10: EGASA | F10: S.E. CONVERTIDOR | G10: BARRA | H10: BARRA138KV | I10: EGASA limitó la capacidad del transformador 138 kV/33 kV a 50 MVA por deterioro del aislamiento.
B11: 27/01/2025 | C11: 00:00 | D11: 24:00 | E11: ENEL GENERACION PIURA S.A. | F11: C.T. MALACAS | G11: CT | H11: CENTRAL | I11: De acuerdo con la comunicación vía correo del día 24.10.2024. ENEL GENERACIÓN PIURA informa una restricción de potencia para alcanzar 105 MW en simultaneo (TG6+TGN4).
B12: 27/01/2025 | C12: 00:00 | D12: 24:00 | E12: ENEL GENERACION PIURA S.A. | F12: C.T. MALACAS | G12: CT | H12: CENTRAL | I12: De acuerdo con la comunicación vía correo del día 24.10.2024. ENEL GENERACIÓN PIURA informa una restricción de potencia para alcanzar 105 MW en simultaneo (TG6+TGN4).
B13: 27/01/2025 | C13: 00:00 | D13: 24:00 | E13: ENGIE | F13: C.E. PUNTA LOMITAS | G13: CE | H13: CENTRAL | I13: De acuerdo a la carta ENG/737-2024 (Exp:202400007555). Limitación de cables de media tensión a 100 MW de los transformadores PLT1 y PLT2 de la CE Punta Lomitas. Quedan limitados a 200 MW la generación de CE Punta Lomitas y Punta Lomitas Extensión.
B14: 27/01/2025 | C14: 00:00 | D14: 24:00 | E14: ENGIE | F14: C.E. PUNTA LOMITAS | G14: CE | H14: CENTRAL | I14: De acuerdo a la carta ENG/737-2024 (Exp:202400007555). Limitación de cables de media tensión a 100 MW de los transformadores PLT1 y PLT2 de la CE Punta Lomitas. Quedan limitados a 200 MW la generación de CE Punta Lomitas y Punta Lomitas Extensión.
B15: 27/01/2025 | C15: 00:00 | D15: 24:00 | E15: ENGIE | F15: C.H. QUITARACSA | G15: CH | H15: CENTRAL | I15: De acuerdo con el correo del 23.04 se considera la operación continua de la CH Quitaracsa debido a que el sistema de refrigeración de la CH Cañón del Pato se alimenta desde la descarga del caudal turbinado por la CH Quitaracsa.
B16: 27/01/2025 | C16: 00:00 | D16: 24:00 | E16: ENGIE | F16: C.H. QUITARACSA | G16: CH | H16: CENTRAL | I16: De acuerdo con el correo del 23.04 se considera la operación continua de la CH Quitaracsa debido a que el sistema de refrigeración de la CH Cañón del Pato se alimenta desde la descarga del caudal turbinado por la CH Quitaracsa.
B17: 27/01/2025 | C17: 00:00 | D17: 24:00 | E17: ENGIE | F17: C.H. YUNCÁN | G17: GH | H17: G3 | I17: Según la carta N° ENG/ 198-2024 enviada por su representada, se opera de forma continua el G3 de la CH Yuncán, debido a la ejecución de mantenimientos necesarios para evitar daños en los sellos de seguridad de la válvula esférica del grupo.
... B76: 27/01/2025 | C76: 00:00 | D76: 24:00 | E76: TRANSMANTARO | F76: S.E. SOCABAYA | G76: SSEE | H76: S.E. | I76: Opera en simple barra en 220 kV por indisponibilidad de la protección diferencial de barras por alarma.

Sheet MANTENIMIENTO EJECUTADOS
B3: lunes, 27 de Enero del 2025
B5: Mantenimiento Ejecutado
B6: Empresa | C6: Ubicación | D6: Equipo | E6: Inicio | F6: Final | G6: Descripción | H6: MW Indisp. | I6: Prog. | J6: Dispon | K6: Interrupc. | L6: Tipo | M6: CodEq | N6: TipoEq_Osinerg
B7: ATLANTICA TRANSMISION SUR S.A. | C7: CHILCA CTM - POROMA | D7: L-5032 | E7: 27/01/2025 08:00 | F7: 27/01/2025 16:00 | G7: INSPECCION ANUAL EN LLTT | H7: 0 | I7: P | J7: E/S | K7: N | L7: PREV. | M7: 13652 | N7: T
B8: ATLANTICA TRANSMISION SUR S.A. | C8: CHILCA-CTM | D8: INT-5261 | E8: 27/01/2025 00:00 | F8: 28/01/2025 00:00 | G8: Seccionador SBB-5261 fase S indisponible para maniobras de apertura y cierre por anomalia en tapa de tanque de compresion, el seccionador permanece cerrado y bloqueado. | H8: 0 | I8: P | J8: E/S | K8: N | L8: OTROS | M8: 13854 | N8: T
B9: ATLANTICA TRANSMISION SUR S.A. | C9: OCONA | D9: INT-5450 | E9: 27/01/2025 00:00 | F9: 28/01/2025 00:00 | G9: RESTRICCION OPERATIVA EN INTERRUPTOR INT-5450, POSICION CERRADA, REB-5450 EN SERVICIO SUMINISTRANDO LOS SS.AA. DE S.E. OCO?A | H9: 0 | I9: P | J9: E/S | K9: N | L9: OTROS | M9: 13761 | N9: T
B10: ATLANTICA TRANSMISION SUR S.A. | C10: OCONA | D10: INT-5462 | E10: 27/01/2025 00:00 | F10: 28/01/2025 00:00 | G10: Seccionador SBA-5462 fase T indisponible por problemas mecanicos, el seccionador permanece cerrado y bloqueado | H10: 0 | I10: P | J10: E/S | K10: N | L10: OTROS | M10: 13758 | N10: T
B11: ATLANTICA TRANSMISION SUR S.A. | C11: OCONA - SAN JOSE | D11: L-5036 | E11: 27/01/2025 08:00 | F11: 27/01/2025 16:00 | G11: INSPECCION ANUAL EN LLTT | H11: 0 | I11: P | J11: E/S | K11: N | L11: PREV. | M11: 14961 | N11: T
B12: ATLANTICA TRANSMISION SUR S.A. | C12: POROMA | D12: INT-5361 | E12: 27/01/2025 00:00 | F12: 28/01/2025 00:00 | G12: Seccionador SBA-5361 fase R indisponible por problemas mecanicos, el seccionador permanece cerrado y bloqueado | H12: 0 | I12: P | J12: E/S | K12: N | L12: OTROS | M12: 13746 | N12: T
B13: ATLANTICA TRANSMISION SUR S.A. | C13: POROMA | D13: REB-5350 | E13: 27/01/2025 00:00 | F13: 28/01/2025 00:00 | G13: FUERA DE SERVICIO POR FALLA EN EL EQUIPO. | H13: 0 | I13: P | J13: F/S | K13: N | L13: OTROS | M13: 13771 | N13: T
B14: ATLANTICA TRANSMISION SUR S.A. | C14: POROMA - OCONA | D14: L-5034 | E14: 27/01/2025 08:00 | F14: 27/01/2025 16:00 | G14: INSPECCION ANUAL EN LLTT | H14: 0 | I14: P | J14: E/S | K14: N | L14: PREV. | M14: 13743 | N14: T
B15: ATRIA ENERGIA S.A.C. | C15: PURMACANA | D15: G1 | E15: 27/01/2025 00:00 | F15: 28/01/2025 00:00 | G15: OVERHAUL DE TURBINA | H15: 0.7 | I15: P | J15: F/S | K15: N | L15: PREV. | M15: 13133 | N15: G
B16: CONELSUR LT SAC | C16: LOMERA | D16: BARRA A 220 kV | E16: 27/01/2025 00:00 | F16: 27/01/2025 14:45 | G16: POR REEMPLAZO DE COMPONENTES Y GAS SF6 EN CL2117. LOMERA OPERA EN BARRA SIMPLE | H16: 0 | I16: P | J16: F/S | K16: N | L16: OTROS | M16: 16951 | N16: T
B17: CONELSUR LT SAC | C17: LOMERA | D17: CL-2117 | E17: 27/01/2025 00:00 | F17: 27/01/2025 17:00 | G17: REEMPLAZO DE COMPONENTES Y GAS SF6 | H17: 0 | I17: P | J17: F/S | K17: N | L17: OTROS | M17: 14198 | N17: T
B18: CONELSUR LT SAC | C18: LOMERA | D18: BARRA A 220 kV | E18: 27/01/2025 08:00 | F18: 27/01/2025 14:45 | G18: POR REEMPLAZO DE COMPONENTES Y GAS SF6 EN CL-2117. CONEXION DE ACOMETIDA REFERENTE A LA BARRA A | H18: 0 | I18: P | J18: F/S | K18: N | L18: OTROS | M18: 16951 | N18: T
... B96: TRANSMANTARO | C96: YARABAMBA | D96: AT-104 523 | E96: 27/01/2025 00:00 | F96: 28/01/2025 00:00 | G96: NO SE TIENE MANDO REMOTO PARA CONTROLAR LOS TAPS DEL AUTOTRANSFORMADOR POR PROBLEMAS EN EL TRANSDUCTOR. LA MANIOBRA ES LOCAL Y REQUIERE AL ASISTENTE EN LA SUBESTACION PARA LAS MANIOBRAS. | H96: 0 | I96: P | J96: E/S | K96: N | L96: OTROS | M96: 17433 | N96: T

Sheet INGRESO OC
A3: lunes, 27 de Enero del 2025
A5: INGRESO A OPERACIÓN COMERCIAL
A6: EMPRESA | B6: TIPO DE EQUIPO | C6: UBICACIÓN | D6: EQUIPO | E6: Fecha y hora de Ingreso a Operación Comercial

Sheet DESPACHO_EJECUTADO
B3: lunes, 27 de Enero del 2025
A5: POTENCIA ACTIVA EJECUTADA DE LAS UNIDADES DE GENERACIÓN DEL SEIN (MW) | FI5: CENTRALES NO INTEGRANTES COES
A6: FECHA | B6: HORA | C6: 337 | D6: 338 | E6: 121 | F6: 101 | G6: 102 | H6: 42667 | I6: 42668 | J6: 126 | K6: 127 | L6: 138 | M6: 139 | N6: 197 | O6: 203 | P6: 204 | Q6: 230 | R6: 209 | S6: 56677 | T6: 796 | U6: 2146 | V6: 142 | W6: 143 | X6: 125 | Y6: 187 | Z6: 163 | AA6: 298 | AB6: 299 | AC6: 219 | AD6: 151 | AE6: 152 | AF6: 153 | AG6: 154 | AH6: 756 | AI6: 156 | AJ6: 155 | AK6: 182 | AL6: 212 | AM6: 758 | AN6: 263 | AO6: 265 | AP6: 775 | AQ6: 777 | AR6: 2154 | AS6: 150 | AT6: 149 | AU6: 188 | AV6: 2131 | AW6: 755 | AX6: 252 | AY6: 249 | AZ6: 250 | BA6: 117 | BB6: 267 | BC6: 268 | BD6: 119 | BE6: 120 | BF6: 189 | BG6: 122 | BH6: 266 | BI6: 251 | BJ6: 115 | BK6: 239 | BL6: 288 | BM6: 240 | BN6: 241 | BO6: 242 | BP6: 191 | BQ6: 194 | BR6: 196 | BS6: 207 | BT6: 236 | BU6: 795 | BV6: 285 | BW6: 995 | BX6: 996 | BY6: 997 | BZ6: 766 | CA6: 926 | CB6: 924 | CC6: 103 | CD6: 104 | CE6: 106 | CF6: 105 | CG6: 107 | CH6: 110 | CI6: 109 | CJ6: 144 | CK6: 113 | CL6: 114 | CM6: 193 | CN6: 208 | CO6: 786 | CP6: 787 | CQ6: 788 | CR6: 789 | CS6: 248 | CT6: 2159 | CU6: 303 | CV6: 59715 | CW6: 62255 | CX6: 1263 | CY6: 61800 | CZ6: 2194 | DA6: 216 | DB6: 198 | DC6: 214 | DD6: 260 | DE6: 2152 | DF6: 2128 | DG6: 247 | DH6: 228 | DI6: 2135 | DJ6: 261 | DK6: 237 | DL6: 253 | DM6: 770 | DN6: 225 | DO6: 2201 | DP6: 2171 | DQ6: 760 | DR6: 235 | DS6: 238 | DT6: 2184 | DU6: 61855 | DV6: 223 | DW6: 226 | DX6: 201 | DY6: 258 | DZ6: 259 | EA6: 920 | EB6: 257 | EC6: 256 | ED6: 2148 | EE6: 58288 | EF6: 58289 | EG6: 58839 | EH6: 58840 | EI6: 296 | EJ6: 297 | EK6: 211 | EL6: 2175 | EM6: 2178 | EN6: 2181 | EO6: 1262 | EP6: 233 | EQ6: 2150 | ER6: 2165 | ES6: 2161 | ET6: 61197 | EU6: 58851 | EV6: 234 | EW6: 215 | EX6: 917 | EY6: 289 | EZ6: 58333 | FA6: 58336 | FB6: 202 | FC6: 58487 | FD6: 213 | FE6: 232 | FF6: 2190 | FG6: TOTAL COES | FI6: 221 | FJ6: 49607 | FK6: 222 | FL6: 224 | FM6: 2187 | FN6: 227 | FO6: 49400 | FP6: 199 | FQ6: 200 | FR6: TOTAL NO COES
C7: CENTRO | D7: CENTRO | E7: NORTE | F7: CENTRO | G7: CENTRO | H7: NORTE | I7: NORTE | J7: NORTE | K7: NORTE | L7: CENTRO | M7: CENTRO | N7: CENTRO | O7: CENTRO | P7: CENTRO | Q7: CENTRO | R7: CENTRO | S7: CENTRO | T7: CENTRO | U7: CENTRO | V7: CENTRO | W7: CENTRO | X7: CENTRO | Y7: CENTRO | Z7: SUR | AA7: SUR | AB7: SUR | AC7: CENTRO | AD7: SUR | AE7: SUR | AF7: SUR | AG7: SUR | AH7: SUR | AI7: SUR | AJ7: SUR | AK7: SUR | AL7: CENTRO | AM7: NORTE | AN7: NORTE | AO7: NORTE | AP7: CENTRO | AQ7: CENTRO | AR7: CENTRO | AS7: CENTRO | AT7: CENTRO | AU7: CENTRO | AV7: CENTRO | AW7: SUR | AX7: CENTRO | AY7: CENTRO | AZ7: CENTRO | BA7: CENTRO | BB7: CENTRO | BC7: CENTRO | BD7: CENTRO | BE7: CENTRO | BF7: SUR | BG7: NORTE | BH7: CENTRO | BI7: CENTRO | BJ7: NORTE | BK7: NORTE | BL7: NORTE | BM7: SUR | BN7: SUR | BO7: SUR | BP7: CENTRO | BQ7: CENTRO | BR7: CENTRO | BS7: CENTRO | BT7: CENTRO | BU7: CENTRO | BV7: CENTRO | BW7: SUR | BX7: SUR | BY7: SUR | BZ7: NORTE | CA7: SUR | CB7: CENTRO | CC7: CENTRO | CD7: CENTRO | CE7: CENTRO | CF7: CENTRO | CG7: CENTRO | CH7: CENTRO | CI7: CENTRO | CJ7: CENTRO | CK7: CENTRO | CL7: CENTRO | CM7: CENTRO | CN7: CENTRO | CO7: SUR | CP7: SUR | CQ7: SUR | CR7: SUR | CS7: CENTRO | CT7: CENTRO | CU7: CENTRO | CV7: CENTRO | CW7: SUR | CX7: NORTE | CY7: NORTE | CZ7: NORTE | DA7: NORTE | DB7: NORTE | DC7: CENTRO | DD7: CENTRO | DE7: CENTRO | DF7: NORTE | DG7: NORTE | DH7: CENTRO | DI7: CENTRO | DJ7: SUR | DK7: SUR | DL7: CENTRO | DM7: CENTRO | DN7: CENTRO | DO7: CENTRO | DP7: CENTRO | DQ7: CENTRO | DR7: SUR | DS7: CENTRO | DT7: CENTRO | DU7: NORTE | DV7: CENTRO | DW7: CENTRO | DX7: NORTE | DY7: CENTRO | DZ7: CENTRO | EA7: CENTRO | EB7: NORTE | EC7: NORTE | ED7: SUR | EE7: CENTRO | EF7: CENTRO | EG7: CENTRO | EH7: CENTRO | EI7: CENTRO | EJ7: CENTRO | EK7: SUR | EL7: SUR | EM7: SUR | EN7: SUR | EO7: NORTE | EP7: SUR | EQ7: SUR | ER7: CENTRO | ES7: CENTRO | ET7: CENTRO | EU7: SUR | EV7: SUR | EW7: NORTE | EX7: CENTRO | EY7: NORTE | EZ7: NORTE | FA7: NORTE | FB7: CENTRO | FC7: CENTRO | FD7: CENTRO | FE7: NORTE | FF7: NORTE | FI7: NORTE | FJ7: SUR | FK7: CENTRO | FL7: NORTE | FM7: NORTE | FN7: NORTE | FO7: NORTE | FP7: NORTE | FQ7: NORTE
C8: HIDROELÉCTRICA | D8: HIDROELÉCTRICA | E8: HIDROELÉCTRICA | F8: HIDROELÉCTRICA | G8: HIDROELÉCTRICA | H8: TERMOELÉCTRICA | I8: TERMOELÉCTRICA | J8: HIDROELÉCTRICA | K8: HIDROELÉCTRICA | L8: TERMOELÉCTRICA | M8: TERMOELÉCTRICA | N8: TERMOELÉCTRICA | O8: TERMOELÉCTRICA | P8: TERMOELÉCTRICA | Q8: TERMOELÉCTRICA | R8: TERMOELÉCTRICA | S8: TERMOELÉCTRICA | T8: HIDROELÉCTRICA | U8: HIDROELÉCTRICA | V8: TERMOELÉCTRICA | W8: TERMOELÉCTRICA | X8: TERMOELÉCTRICA | Y8: TERMOELÉCTRICA | Z8: HIDROELÉCTRICA | AA8: HIDROELÉCTRICA | AB8: HIDROELÉCTRICA | AC8: TERMOELÉCTRICA | AD8: HIDROELÉCTRICA | AE8: HIDROELÉCTRICA | AF8: HIDROELÉCTRICA | AG8: HIDROELÉCTRICA | AH8: TERMOELÉCTRICA | AI8: TERMOELÉCTRICA | AJ8: TERMOELÉCTRICA | AK8: HIDROELÉCTRICA | AL8: HIDROELÉCTRICA | AM8: TERMOELÉCTRICA | AN8: TERMOELÉCTRICA | AO8: TERMOELÉCTRICA | AP8: HIDROELÉCTRICA | AQ8: HIDROELÉCTRICA | AR8: HIDROELÉCTRICA | AS8: HIDROELÉCTRICA | AT8: HIDROELÉCTRICA | AU8: HIDROELÉCTRICA | AV8: HIDROELÉCTRICA | AW8: HIDROELÉCTRICA | AX8: TERMOELÉCTRICA | AY8: TERMOELÉCTRICA | AZ8: TERMOELÉCTRICA | BA8: HIDROELÉCTRICA | BB8: HIDROELÉCTRICA | BC8: HIDROELÉCTRICA | BD8: HIDROELÉCTRICA | BE8: HIDROELÉCTRICA | BF8: HIDROELÉCTRICA | BG8: HIDROELÉCTRICA | BH8: HIDROELÉCTRICA | BI8: HIDROELÉCTRICA | BJ8: TERMOELÉCTRICA | BK8: TERMOELÉCTRICA | BL8: TERMOELÉCTRICA | BM8: TERMOELÉCTRICA | BN8: TERMOELÉCTRICA | BO8: TERMOELÉCTRICA | BP8: HIDROELÉCTRICA | BQ8: TERMOELÉCTRICA | BR8: TERMOELÉCTRICA | BS8: TERMOELÉCTRICA | BT8: TERMOELÉCTRICA | BU8: TERMOELÉCTRICA | BV8: TERMOELÉCTRICA | BW8: TERMOELÉCTRICA | BX8: TERMOELÉCTRICA | BY8: TERMOELÉCTRICA | BZ8: HIDROELÉCTRICA | CA8: TERMOELÉCTRICA | CB8: TERMOELÉCTRICA | CC8: HIDROELÉCTRICA | CD8: HIDROELÉCTRICA | CE8: HIDROELÉCTRICA | CF8: HIDROELÉCTRICA | CG8: HIDROELÉCTRICA | CH8: TERMOELÉCTRICA | CI8: TERMOELÉCTRICA | CJ8: TERMOELÉCTRICA | CK8: TERMOELÉCTRICA | CL8: TERMOELÉCTRICA | CM8: TERMOELÉCTRICA | CN8: TERMOELÉCTRICA | CO8: TERMOELÉCTRICA | CP8: TERMOELÉCTRICA | CQ8: TERMOELÉCTRICA | CR8: TERMOELÉCTRICA | CS8: TERMOELÉCTRICA | CT8: TERMOELÉCTRICA | CU8: SOLAR | CV8: EÓLICA | CW8: SOLAR | CX8: EÓLICA | CY8: SOLAR | CZ8: HIDROELÉCTRICA | DA8: HIDROELÉCTRICA | DB8: HIDROELÉCTRICA | DC8: HIDROELÉCTRICA | DD8: HIDROELÉCTRICA | DE8: HIDROELÉCTRICA | DF8: HIDROELÉCTRICA | DG8: HIDROELÉCTRICA | DH8: HIDROELÉCTRICA | DI8: HIDROELÉCTRICA | DJ8: SOLAR | DK8: SOLAR | DL8: EÓLICA | DM8: EÓLICA | DN8: TERMOELÉCTRICA | DO8: TERMOELÉCTRICA | DP8: TERMOELÉCTRICA | DQ8: TERMOELÉCTRICA | DR8: SOLAR | DS8: HIDROELÉCTRICA | DT8: HIDROELÉCTRICA | DU8: HIDROELÉCTRICA | DV8: HIDROELÉCTRICA | DW8: HIDROELÉCTRICA | DX8: HIDROELÉCTRICA | DY8: HIDROELÉCTRICA | DZ8: HIDROELÉCTRICA | EA8: HIDROELÉCTRICA | EB8: EÓLICA | EC8: EÓLICA | ED8: SOLAR | EE8: EÓLICA | EF8: EÓLICA | EG8: EÓLICA | EH8: EÓLICA | EI8: HIDROELÉCTRICA | EJ8: HIDROELÉCTRICA | EK8: HIDROELÉCTRICA | EL8: HIDROELÉCTRICA | EM8: HIDROELÉCTRICA | EN8: HIDROELÉCTRICA | EO8: EÓLICA | EP8: SOLAR | EQ8: SOLAR | ER8: HIDROELÉCTRICA | ES8: EÓLICA | ET8: EÓLICA | EU8: SOLAR | EV8: SOLAR | EW8: HIDROELÉCTRICA | EX8: HIDROELÉCTRICA | EY8: TERMOELÉCTRICA | EZ8: TERMOELÉCTRICA | FA8: TERMOELÉCTRICA | FB8: TERMOELÉCTRICA | FC8: TERMOELÉCTRICA | FD8: TERMOELÉCTRICA | FE8: TERMOELÉCTRICA | FF8: TERMOELÉCTRICA | FI8: HIDROELÉCTRICA | FJ8: HIDROELÉCTRICA | FK8: HIDROELÉCTRICA | FL8: HIDROELÉCTRICA | FM8: HIDROELÉCTRICA | FN8: TERMOELÉCTRICA | FO8: TERMOELÉCTRICA | FP8: HIDROELÉCTRICA | FQ8: HIDROELÉCTRICA
C9: CENTRALES SANTA ROSA S.A.C. | D9: CENTRALES SANTA ROSA S.A.C. | E9: INVERSIONES SHAQSHA S.A.C. | F9: ELECTROPERU | G9: ELECTROPERU | H9: ELECTROPERU | I9: ELECTROPERU | J9: ORAZUL ENERGY PERÚ | K9: ORAZUL ENERGY PERÚ | L9: TERMOSELVA | M9: TERMOSELVA | N9: KALLPA GENERACION S.A. | O9: KALLPA GENERACION S.A. | P9: KALLPA GENERACION S.A. | Q9: KALLPA GENERACION S.A. | R9: KALLPA GENERACION S.A. | S9: KALLPA GENERACION S.A. | T9: KALLPA GENERACION S.A. | U9: KALLPA GENERACION S.A. | V9: SHOUGESA | W9: SHOUGESA | X9: SHOUGESA | Y9: SHOUGESA | Z9: EGEMSA | AA9: EGESUR | AB9: EGESUR | AC9: EGESUR | AD9: EGASA | AE9: EGASA | AF9: EGASA | AG9: EGASA | AH9: EGASA | AI9: EGASA | AJ9: EGASA | AK9: SAN GABAN | AL9: CELEPSA | AM9: MINERA CERRO VERDE | AN9: PLANTA DE RESERVA FRIA DE GENERACION DE ETEN S.A. | AO9: PLANTA DE RESERVA FRIA DE GENERACION DE ETEN S.A. | AP9: EMPRESA DE GENERACION HUALLAGA | AQ9: EMPRESA DE GENERACION HUALLAGA | AR9: LA VIRGEN | AS9: CHINANGO S.A.C. | AT9: CHINANGO S.A.C. | AU9: HIDROELECTRICA HUANCHOR S.A.C. | AV9: CELEPSA RENOVABLES S.R.L. | AW9: INLAND ENERGY SAC | AX9: FENIX POWER PERÚ | AY9: FENIX POWER PERÚ | AZ9: FENIX POWER PERÚ | BA9: STATKRAFT S.A | BB9: STATKRAFT S.A | BC9: STATKRAFT S.A | BD9: STATKRAFT S.A | BE9: STATKRAFT S.A | BF9: STATKRAFT S.A | BG9: STATKRAFT S.A | BH9: STATKRAFT S.A | BI9: EMPRESA DE GENERACION HUANZA | BJ9: ENEL GENERACION PIURA S.A. | BK9: ENEL GENERACION PIURA S.A. | BL9: ENEL GENERACION PIURA S.A. | BM9: ENGIE | BN9: ENGIE | BO9: ENGIE | BP9: ENGIE | BQ9: ENGIE | BR9: ENGIE | BS9: ENGIE | BT9: ENGIE | BU9: ENGIE | BV9: ENGIE | BW9: ENGIE | BX9: ENGIE | BY9: ENGIE | BZ9: ENGIE | CA9: INFRAESTRUCTURAS Y ENERGIAS DEL PERU S.A.C. | CB9: INFRAESTRUCTURAS Y ENERGIAS DEL PERU S.A.C. | CC9: ORYGEN PERU S.A.A. | CD9: ORYGEN PERU S.A.A. | CE9: ORYGEN PERU S.A.A. | CF9: ORYGEN PERU S.A.A. | CG9: ORYGEN PERU S.A.A. | CH9: ORYGEN PERU S.A.A. | CI9: ORYGEN PERU S.A.A. | CJ9: ORYGEN PERU S.A.A. | CK9: ORYGEN PERU S.A.A. | CL9: ORYGEN PERU S.A.A. | CM9: ORYGEN PERU S.A.A. | CN9: ORYGEN PERU S.A.A. | CO9: SAMAY I S.A.C | CP9: SAMAY I S.A.C | CQ9: SAMAY I S.A.C | CR9: SAMAY I S.A.C | CS9: TERMOCHILCA S.A.C. | CT9: TERMOCHILCA S.A.C. | CU9: COLCA SOLAR S.A.C. | CV9: ENERGIA RENOVABLE DEL SUR S.A. | CW9: GR CORTARRAMA SOCIEDAD ANONIMA CERRADA | CX9: GR TARUCA SOCIEDAD ANONIMA CERRADA | CY9: KONDU SAC | CZ9: PERUANA DE INVERSIONES EN ENERGIAS RENOVABLES S.A. | DA9: ORAZUL ENERGY PERÚ | DB9: ORAZUL ENERGY PERÚ | DC9: MAJA ENERGIA S.A.C. | DD9: EMPRESA DE GENERACION ELECTRICA CANCHAYLLO SAC | DE9: EMPRESA DE GENERACION ELECTRICA SANTA ANA S.A.C. | DF9: EMPRESA ELECTRICA AGUA AZUL | DG9: EMPRESA ELECTRICA RIO DOBLE | DH9: HIDROCAÑETE S.A. | DI9: HUAURA POWER GROUP S.A. | DJ9: MOQUEGUA FV S.A.C. | DK9: PANAMERICANA SOLAR SAC. | DL9: PARQUE EOLICO MARCONA S.A.C. | DM9: PARQUE EOLICO TRES HERMANAS S.A.C. | DN9: PETRAMAS | DO9: PETRAMAS | DP9: PETRAMAS | DQ9: PETRAMAS | DR9: TACNA SOLAR SAC. | DS9: ELECTRICA YANAPAMPA SAC | DT9: ANDEAN POWER S.A.C. | DU9: ASOCIACIÓN SANTA LUCIA DE CHACAS | DV9: ATRIA ENERGIA S.A.C. | DW9: EGEJUNIN | DX9: EGEJUNIN | DY9: EGEJUNIN | DZ9: EGEJUNIN | EA9: EMPRESA DE GENERACION ELECTRICA RIO BAÑOS S.A.C. | EB9: ENERGÍA EÓLICA S.A. | EC9: ENERGÍA EÓLICA S.A. | ED9: ENGIE | EE9: ENGIE | EF9: ENGIE | EG9: ENGIE | EH9: ENGIE | EI9: GENERACIÓN ANDINA S.A.C. | EJ9: GENERACIÓN ANDINA S.A.C. | EK9: GENERADORA DE ENERGÍA DEL PERÚ | EL9: GENERADORA DE ENERGÍA DEL PERÚ | EM9: GENERADORA DE ENERGÍA DEL PERÚ | EN9: GENERADORA DE ENERGÍA DEL PERÚ | EO9: GR PAINO SOCIEDAD ANONIMA CERRADA | EP9: MAJES ARCUS S.A.C. | EQ9: ORYGEN PERU S.A.A. | ER9: ORYGEN PERU S.A.A. | ES9: ORYGEN PERU S.A.A. | ET9: ORYGEN PERU S.A.A. | EU9: ORYGEN PERU S.A.A. | EV9: REPARTICIÓN ARCUS S.A.C. | EW9: SINERSA | EX9: SINERSA | EY9: BIOENERGIA DEL CHIRA S.A. | EZ9: GM OPERACIONES S.A.C. | FA9: GM OPERACIONES S.A.C. | FB9: SDF ENERGIA SAC | FC9: SDF ENERGIA SAC | FD9: AGRO INDUSTRIAL PARAMONGA S.A. | FE9: AGROAURORA S.A.C. | FF9: AGROINDUSTRIAS SAN JACINTO S.A.A. | FI9: UNACEM PERU S.A. | FJ9: SAN GABAN | FK9: ELECTRO ORIENTE | FL9: AGUAS Y ENERGIA PERU | FM9: ELECTRO ZAÑA S.A.C. | FN9: ELECTRONOROESTE S.A. | FO9: SDE PIURA | FP9: SINERSA | FQ9: SINERSA
C10: SANTA ROSA 1 | D10: SANTA ROSA 2 | E10: PARIAC | F10: MANTARO | G10: RESTITUCION | H10: TUMBES MAK 1 | I10: TUMBES MAK 2 | J10: CARHUAQUERO | K10: CAÑON DEL PATO | L10: AGUAYTIA TG1 | M10: AGUAYTIA TG2 | N10: KALLPA TG1 | O10: KALLPA TG2 | P10: KALLPA TG3 | Q10: KALLPA TV | R10: LFLORES TG1 | S10: LFLORES TV | T10: CERRO DEL AGUILA | U10: CERRODELAGUILAG4 | V10: SHOUGESA TV1 | W10: SHOUGESA TV2 | X10: SHOUGESA TV3 | Y10: SHOUGESA CUMMINS | Z10: MACHUPICCHU | AA10: ARICOTA 1 | AB10: ARICOTA 2 | AC10: INDEPENDENCIA | AD10: CHARCANI I,II,III | AE10: CHARCANI IV | AF10: CHARCANI V | AG10: CHARCANI VI | AH10: CHILINA TG | AI10: MOLLENDO 1, 2, 3 | AJ10: CHILINA (SULZ 1,2) | AK10: SAN GABAN II | AL10: PLATANAL | AM10: RECKA | AN10: RF ETEN TG1 | AO10: RF ETEN TG2 | AP10: CHAGLLA GP1 | AQ10: CHAGLLA | AR10: LA VIRGEN | AS10: CHIMAY | AT10: YANANGO | AU10: HUANCHOR | AV10: MARAÑON | AW10: STA TERESA | AX10: FENIX GT11 | AY10: FENIX GT12 | AZ10: FENIX TV10 | BA10: YAUPI | BB10: OROYA | BC10: PACHACHACA | BD10: MALPASO | BE10: CAHUA | BF10: ARCATA | BG10: GALLITO CIEGO | BH10: CHEVES | BI10: HUANZA | BJ10: MALACAS2 TG4 | BK10: MALACAS3 TG 5 | BL10: MALACAS1 TG6 | BM10: RF ILO2 TG1 | BN10: RF ILO2 TG2 | BO10: RF ILO2 TG3 | BP10: YUNCAN | BQ10: CHILCA1 TG1 | BR10: CHILCA1 TG2 | BS10: CHILCA1 TG3 | BT10: CHILCA-TV | BU10: CHILCA2 TG41 | BV10: CHILCA2-TV | BW10: CTNEPI_TG41 | BX10: CTNEPI_TG42 | BY10: CTNEPI_TG43 | BZ10: QUITARACSA | CA10: RF PTO MALDONADO | CB10: RF PUCALLPA | CC10: HUINCO | CD10: MATUCANA | CE10: MOYOPAMPA | CF10: CALLAHUANCA | CG10: HUAMPANI | CH10: STA ROSA WEST TG7 | CI10: UTI_5 | CJ10: UTI_6 | CK10: VENTANILLA 3 | CL10: VENTANILLA 4 | CM10: VENTANILLA TV | CN10: STAROSA TG8 | CO10: PTO_BRVO TG1 | CP10: PTO_BRVO TG2 | CQ10: PTO_BRVO TG3 | CR10: PTO_BRVO TG4 | CS10: OLLEROS TG1 | CT10: OLLEROS TV | CU10: CS YARUCAYA | CV10: SAN JUAN | CW10: MATARANI | CX10: DUNA | CY10: CARHUAQUERO (CS) | CZ10: MANTA I | DA10: CARHUAQUERO4 | DB10: CAÑA BRAVA | DC10: RONCADOR | DD10: CANCHAYLLO | DE10: RENOVANDESH1 | DF10: POTRERO | DG10: PIZARRAS | DH10: NIMPERIAL | DI10: YARUCAYA | DJ10: MOQUEGUA-SOLAR | DK10: PANAMERICANA-SOLAR | DL10: PQE-EOLICO-MARCONA | DM10: PQE-EOLICO-3-HERMANAS | DN10: HUAYCOLORO | DO10: CALLAO | DP10: DONA_CATALINA | DQ10: LAGRINGAV | DR10: TACNA-SOLAR | DS10: YANAPAMPA | DT10: CARHUAC | DU10: HUALLIN | DV10: PURMACANA | DW10: HUASAHUASI | DX10: STACRUZ_1_2 | DY10: RUNATULLO_II | DZ10: RUNATULLO_III | EA10: RUCUY | EB10: PQE-EOLICO-TALARA | EC10: PQE-EOLICO-CUPISNIQUE | ED10: INTIPAMPA | EE10: PUNTA LOMITAS-BL1 | EF10: PUNTA LOMITAS-BL2 | EG10: PUN LOMITAS_EXP-BL1 | EH10: PUN LOMITAS_EXP-BL2 | EI10: 8AGOSTO | EJ10: EL CARMEN | EK10: LA JOYA | EL10: ANGEL_I | EM10: ANGEL_II | EN10: ANGEL_III | EO10: HUAMBOS | EP10: MAJES | EQ10: RUBI | ER10: CH_HER1 | ES10: WAYRA-I | ET10: WAYRA EXTENSION | EU10: CLEMESI | EV10: REPARTICION | EW10: POECHOS2 | EX10: CHANCAY | EY10: CANA BRAVA | EZ10: REFINERIA TALARA TV1 | FA10: REFINERÍA TALARA TV2 | FB10: OQUENDO TG1 | FC10: OQUENDO TV1 | FD10: PARAMONGA | FE10: MAPLE | FF10: SAN_JACINTO | FG10: MW | FI10: CARPAPATA | FJ10: TUPURI | FK10: CENTRALES ELOR | FL10: PIAS1 | FM10: ZANA | FN10: TABLAZO | FO10: TALLANCA | FP10: CURUMUY | FQ10: POECHOS1 | FR10: MW
A11: 27/01/2025 | B11: 00:30 | C11: 1.1 | D11: 1.6 | E11: 4.3 | F11: 651 | G11: 218.3 | J11: 90.1 | K11: 238.7 | N11: 108.9 | O11: 107.9 | P11: 108 | Q11: 207.5 | R11: 123 | S11: 74.4 | T11: 558.2 | U11: 10.6 | Z11: 166.2 | AA11: 8 | AB11: 2.7 | AC11: 0 | AD11: 6.5 | AF11: 66.2 | AG11: 5.3 | AK11: 111.3 | AL11: 171.9 | AP11: 6.5 | AQ11: 459.9 | AR11: 63 | AS11: 136.1 | AT11: 40.4 | AU11: 18.4 | AV11: 19.7 | AW11: 90.4 | AX11: 0 | AY11: 123 | AZ11: 73.4 | BA11: 108.9 | BB11: 7.9 | BC11: 2.5 | BD11: 39.8 | BE11: 47.5 | BF11: 3.7 | BG11: 30.5 | BH11: 127.4 | BI11: 0 | BL11: 46.8 | BP11: 131.2 | BQ11: 0 | BR11: 0 | BT11: 0 | BZ11: 86.6 | CC11: 222.3 | CD11: 123.1 | CE11: 64.8 | CF11: 81.8 | CG11: 30.3 | CH11: 0 | CK11: 103.5 | CL11: 102.5 | CM11: 120.1 | CU11: 0 | CV11: 97 | CW11: 0 | CX11: 15.1 | CY11: 0 | CZ11: 20 | DA11: 10 | DB11: 5.5 | DC11: 3.6 | DD11: 5.2 | DE11: 20.3 | DF11: 20 | DG11: 13.6 | DH11: 3.7 | DI11: 18.8 | DJ11: 0 | DK11: 0 | DL11: 29.3 | DM11: 69.2 | DN11: 4.8 | DO11: 2.3 | DP11: 2.4 | DQ11: 2.9 | DR11: 0 | DS11: 3.5 | DT11: 9.4 | DU11: 2 | DW11: 14.2 | DX11: 8.8 | DY11: 19.6 | DZ11: 20.4 | EA11: 19.9 | EB11: 18.1 | EC11: 30.4 | ED11: 0 | EE11: 19 | EF11: 49.2 | EG11: 1.4 | EH11: 1 | EI11: 21 | EJ11: 6.9 | EK11: 7.6 | EL11: 20 | EM11: 20 | EN11: 19.8 | EO11: 13.2 | EP11: 0 | EQ11: 0 | ER11: 0.6 | ES11: 14.9 | ET11: 14.5 | EU11: 0 | EV11: 0 | EW11: 7.5 | EX11: 19.9 | EY11: 10 | EZ11: 18 | FA11: 36.6 | FB11: 28.8 | FC11: 3.4 | FD11: 14 | FE11: 15.1 | FF11: 6.9 | FG11: 6413 | FI11: 24.2739 | FJ11: 1.3 | FK11: 0 | FL11: 6.11 | FM11: 8.3 | FO11: 18.9213 | FP11: 5.6 | FQ11: 4.3 | FR11: 68.8052
A12: 27/01/2025 | B12: 01:00 | C12: 1.1 | D12: 1.6 | E12: 4.3 | F12: 648.5 | G12: 218.6 | J12: 70.3 | K12: 238.8 | N12: 107.9 | O12: 108.6 | P12: 108.6 | Q12: 207.9 | R12: 120.7 | S12: 74 | T12: 558 | U12: 10.5 | Z12: 166.1 | AA12: 7.9 | AB12: 2.8 | AC12: 0 | AD12: 6.5 | AF12: 66.2 | AG12: 5.3 | AK12: 111.4 | AL12: 148.6 | AP12: 6.5 | AQ12: 459.9 | AR12: 61.8 | AS12: 133.2 | AT12: 40.2 | AU12: 18.3 | AV12: 19.7 | AW12: 94.4 | AX12: 0 | AY12: 124.5 | AZ12: 73.7 | BA12: 109.2 | BB12: 7.7 | BC12: 2.7 | BD12: 39.8 | BE12: 47.3 | BF12: 3.7 | BG12: 30.7 | BH12: 127.1 | BI12: 0 | BL12: 47 | BP12: 131.1 | BQ12: 0 | BR12: 0 | BT12: 0 | BZ12: 33.1 | CC12: 193.8 | CD12: 118 | CE12: 64.5 | CF12: 81.6 | CG12: 30.4 | CH12: 0 | CK12: 103.6 | CL12: 103.7 | CM12: 120 | CU12: 0 | CV12: 84.2 | CW12: 0 | CX12: 16 | CY12: 0 | CZ12: 20 | DA12: 9.9 | DB12: 5.4 | DC12: 3.7 | DD12: 5.2 | DE12: 20.5 | DF12: 20 | DG12: 14 | DH12: 3.7 | DI12: 18.8 | DJ12: 0 | DK12: 0 | DL12: 28.8 | DM12: 67.9 | DN12: 4.8 | DO12: 2.3 | DP12: 2.4 | DQ12: 2.9 | DR12: 0 | DS12: 3.7 | DT12: 6.3 | DU12: 2 | DW12: 16.1 | DX12: 8.8 | DY12: 19.1 | DZ12: 20.4 | EA12: 19.8 | EB12: 20.7 | EC12: 27.4 | ED12: 0 | EE12: 14.8 | EF12: 51 | EG12: 1.2 | EH12: 0.7 | EI12: 21 | EJ12: 7.1 | EK12: 7.6 | EL12: 20 | EM12: 20 | EN12: 19.8 | EO12: 13.1 | EP12: 0 | EQ12: 0 | ER12: 0.6 | ES12: 12.9 | ET12: 16 | EU12: 0 | EV12: 0 | EW12: 7.5 | EX12: 19.8 | EY12: 10.1 | EZ12: 18 | FA12: 36.3 | FB12: 28.8 | FC12: 3.4 | FD12: 14 | FE12: 15.1 | FF12: 7 | FG12: 6262 | FI12: 24.27621 | FJ12: 1.3 | FK12: 0 | FL12: 6.1115 | FM12: 8.2 | FO12: 18.92166 | FP12: 5.9 | FQ12: 4.2 | FR12: 68.90937
A13: 27/01/2025 | B13: 01:30 | C13: 1.1 | D13: 1.6 | E13: 4.3 | F13: 651.7 | G13: 219.1 | J13: 60.2 | K13: 239.9 | N13: 108 | O13: 108.1 | P13: 108.6 | Q13: 207.9 | R13: 122.2 | S13: 74.3 | T13: 561.2 | U13: 10.6 | Z13: 168.3 | AA13: 7.9 | AB13: 2.8 | AC13: 0 | AD13: 6.5 | AF13: 66.2 | AG13: 5.3 | AK13: 111.3 | AL13: 203.6 | AP13: 6.5 | AQ13: 459.7 | AR13: 61.1 | AS13: 137.8 | AT13: 40.5 | AU13: 18.3 | AV13: 19.7 | AW13: 93.2 | AX13: 0 | AY13: 123 | AZ13: 73.7 | BA13: 108.9 | BB13: 7.7 | BC13: 2.8 | BD13: 39.8 | BE13: 47.5 | BF13: 3.7 | BG13: 30.8 | BH13: 126.8 | BI13: 0 | BL13: 46.8 | BP13: 131.4 | BQ13: 0 | BR13: 0 | BT13: 0 | BZ13: 16.2 | CC13: 153.7 | CD13: 120.9 | CE13: 64.8 | CF13: 81.7 | CG13: 30.4 | CH13: 0 | CK13: 104.3 | CL13: 104.1 | CM13: 120.4 | CU13: 0 | CV13: 70.1 | CW13: 0 | CX13: 14.1 | CY13: 0 | CZ13: 20 | DA13: 9.9 | DB13: 4.7 | DC13: 3.6 | DD13: 5.1 | DE13: 20.4 | DF13: 20 | DG13: 14.1 | DH13: 3.7 | DI13: 18.8 | DJ13: 0 | DK13: 0 | DL13: 24.4 | DM13: 58.6 | DN13: 4.8 | DO13: 2.3 | DP13: 2.4 | DQ13: 2.9 | DR13: 0 | DS13: 3.7 | DT13: 6.5 | DU13: 2 | DW13: 16.1 | DX13: 8.8 | DY13: 19.3 | DZ13: 20.3 | EA13: 20 | EB13: 25.7 | EC13: 18.6 | ED13: 0 | EE13: 17.8 | EF13: 47.1 | EG13: 1.1 | EH13: 0.7 | EI13: 21 | EJ13: 7.3 | EK13: 7.6 | EL13: 20 | EM13: 20 | EN13: 19.8 | EO13: 10.6 | EP13: 0 | EQ13: 0 | ER13: 0.6 | ES13: 10.4 | ET13: 17.3 | EU13: 0 | EV13: 0 | EW13: 7.5 | EX13: 20 | EY13: 9.4 | EZ13: 17.9 | FA13: 36.5 | FB13: 28.8 | FC13: 3.4 | FD13: 13.9 | FE13: 15.1 | FF13: 7.2 | FG13: 6228.8 | FI13: 24.27525 | FJ13: 1.2 | FK13: 0 | FL13: 6.111 | FM13: 8.2 | FO13: 18.92229 | FP13: 6.5 | FQ13: 4.3 | FR13: 69.50854
A14: 27/01/2025 | B14: 02:00 | C14: 1.1 | D14: 1.6 | E14: 4.3 | F14: 650.2 | G14: 218.6 | J14: 60.3 | K14: 239.4 | N14: 108.1 | O14: 108.2 | P14: 108.9 | Q14: 208.5 | R14: 123.5 | S14: 73.7 | T14: 561.8 | U14: 10.5 | Z14: 168.2 | AA14: 7.9 | AB14: 2.7 | AC14: 0 | AD14: 6.5 | AF14: 29.6 | AG14: 5.5 | AK14: 111.1 | AL14: 193.8 | AP14: 6.5 | AQ14: 459.3 | AR14: 61.2 | AS14: 143.9 | AT14: 40.2 | AU14: 18.4 | AV14: 19.7 | AW14: 93 | AX14: 0 | AY14: 124.6 | AZ14: 74 | BA14: 108.7 | BB14: 7.7 | BC14: 2.7 | BD14: 40.1 | BE14: 47 | BF14: 3.7 | BG14: 30.3 | BH14: 126.3 | BI14: 0 | BL14: 46.9 | BP14: 131.1 | BQ14: 0 | BR14: 0 | BT14: 0 | BZ14: 16.4 | CC14: 160.5 | CD14: 126.1 | CE14: 44.4 | CF14: 82 | CG14: 30.2 | CH14: 0 | CK14: 103.8 | CL14: 103.6 | CM14: 120.7 | CU14: 0 | CV14: 72.5 | CW14: 0 | CX14: 14.1 | CY14: 0 | CZ14: 20 | DA14: 9.9 | DB14: 4.7 | DC14: 3.7 | DD14: 5.2 | DE14: 20.3 | DF14: 20 | DG14: 14 | DH14: 0 | DI14: 18.8 | DJ14: 0 | DK14: 0 | DL14: 21.3 | DM14: 52.6 | DN14: 4.8 | DO14: 2.3 | DP14: 2.4 | DQ14: 3 | DR14: 0 | DS14: 3.7 | DT14: 6.5 | DU14: 2 | DW14: 16.1 | DX14: 8.9 | DY14: 19.1 | DZ14: 20.4 | EA14: 20 | EB14: 22.7 | EC14: 16 | ED14: 0 | EE14: 27.4 | EF14: 65.1 | EG14: 2 | EH14: 1.1 | EI14: 21 | EJ14: 8.4 | EK14: 7.9 | EL14: 20 | EM14: 20 | EN14: 19.9 | EO14: 11.1 | EP14: 0 | EQ14: 0 | ER14: 0.6 | ES14: 10.5 | ET14: 16 | EU14: 0 | EV14: 0 | EW14: 7.6 | EX14: 20 | EY14: 9.4 | EZ14: 18 | FA14: 36.4 | FB14: 28.8 | FC14: 3.4 | FD14: 13 | FE14: 15.1 | FF14: 7.5 | FG14: 6192.2 | FI14: 24.27391 | FJ14: 1.2 | FK14: 0 | FL14: 6.1105 | FM14: 8 | FO14: 18.92225 | FP14: 6.9 | FQ14: 4.3 | FR14: 69.70666
A15: 27/01/2025 | B15: 02:30 | C15: 1.1 | D15: 1.6 | E15: 4.3 | F15: 647 | G15: 218.5 | J15: 60.6 | K15: 238.4 | N15: 108 | O15: 109 | P15: 108.1 | Q15: 208.4 | R15: 123 | S15: 73.7 | T15: 552.6 | U15: 10.5 | Z15: 168.8 | AA15: 8 | AB15: 2.6 | AC15: 0 | AD15: 6.7 | AF15: 30.5 | AG15: 5.9 | AK15: 111.3 | AL15: 193.7 | AP15: 6.5 | AQ15: 377.4 | AR15: 59.9 | AS15: 148 | AT15: 40.1 | AU15: 18.3 | AV15: 19.7 | AW15: 95.8 | AX15: 0 | AY15: 125.7 | AZ15: 73.3 | BA15: 108.8 | BB15: 7.7 | BC15: 2.7 | BD15: 44.3 | BE15: 47.2 | BF15: 3.7 | BG15: 30.9 | BH15: 126.8 | BI15: 0 | BL15: 46.7 | BP15: 131.3 | BQ15: 0 | BR15: 0 | BT15: 0 | BZ15: 16.5 | CC15: 112.5 | CD15: 130.2 | CE15: 44.5 | CF15: 81.5 | CG15: 30.3 | CH15: 0 | CK15: 103.7 | CL15: 103.3 | CM15: 120.1 | CU15: 0 | CV15: 85.2 | CW15: 0 | CX15: 15.2 | CY15: 0 | CZ15: 20 | DA15: 9.9 | DB15: 4.6 | DC15: 3.7 | DD15: 5.2 | DE15: 20.4 | DF15: 20 | DG15: 14.1 | DH15: 0 | DI15: 18.8 | DJ15: 0 | DK15: 0 | DL15: 26.1 | DM15: 64 | DN15: 4.8 | DO15: 2.3 | DP15: 2.4 | DQ15: 3 | DR15: 0 | DS15: 3.6 | DT15: 6.5 | DU15: 2 | DW15: 16.1 | DX15: 8.9 | DY15: 18.9 | DZ15: 20.4 | EA15: 19.9 | EB15: 22.1 | EC15: 16.1 | ED15: 0 | EE15: 22.5 | EF15: 66.5 | EG15: 1.3 | EH15: 1.1 | EI15: 21 | EJ15: 8.4 | EK15: 7.8 | EL15: 20 | EM15: 20 | EN15: 20 | EO15: 12.1 | EP15: 0 | EQ15: 0 | ER15: 0.6 | ES15: 19 | ET15: 21.5 | EU15: 0 | EV15: 0 | EW15: 7.6 | EX15: 20 | EY15: 9.3 | EZ15: 17.9 | FA15: 36.5 | FB15: 28.9 | FC15: 3.1 | FD15: 13.9 | FE15: 15.1 | FF15: 7.2 | FG15: 6105.2 | FI15: 24.27089 | FJ15: 1.2 | FK15: 0 | FL15: 6.109 | FM15: 8 | FO15: 18.9225 | FP15: 7.1 | FQ15: 4.3 | FR15: 69.90239
A16: 27/01/2025 | B16: 03:00 | C16: 1.1 | D16: 1.6 | E16: 4.3 | F16: 648 | G16: 218.5 | J16: 59.2 | K16: 239 | N16: 108.9 | O16: 109 | P16: 109.5 | Q16: 209.2 | R16: 123.2 | S16: 73.6 | T16: 561.3 | U16: 10.4 | Z16: 162.4 | AA16: 7.7 | AB16: 2.6 | AC16: 0 | AD16: 6.5 | AF16: 29.9 | AG16: 5.4 | AK16: 111.1 | AL16: 191.8 | AP16: 6.5 | AQ16: 441.8 | AR16: 61.4 | AS16: 148 | AT16: 40 | AU16: 18.3 | AV16: 19.7 | AW16: 92.5 | AX16: 0 | AY16: 122.8 | AZ16: 74.5 | BA16: 109.4 | BB16: 7.7 | BC16: 2.8 | BD16: 43.2 | BE16: 47.3 | BF16: 3.7 | BG16: 30.3 | BH16: 125.9 | BI16: 0 | BL16: 47.3 | BP16: 130.8 | BQ16: 0 | BR16: 0 | BT16: 0 | BZ16: 16 | CC16: 55.6 | CD16: 129.6 | CE16: 44.6 | CF16: 81.9 | CG16: 30.2 | CH16: 0 | CK16: 105.1 | CL16: 104.9 | CM16: 121.2 | CU16: 0 | CV16: 85.2 | CW16: 0 | CX16: 17.1 | CY16: 0 | CZ16: 20 | DA16: 9.9 | DB16: 4.7 | DC16: 3.7 | DD16: 5.2 | DE16: 20.4 | DF16: 20 | DG16: 14 | DH16: 0 | DI16: 18.8 | DJ16: 0 | DK16: 0 | DL16: 24.4 | DM16: 64.1 | DN16: 4.8 | DO16: 2.3 | DP16: 2.4 | DQ16: 3 | DR16: 0 | DS16: 3.7 | DT16: 6.5 | DU16: 2 | DW16: 16.1 | DX16: 8.9 | DY16: 18.9 | DZ16: 20.4 | EA16: 19.9 | EB16: 25.6 | EC16: 13.2 | ED16: 0 | EE16: 25.3 | EF16: 61.2 | EG16: 0.9 | EH16: 1.8 | EI16: 21 | EJ16: 8.4 | EK16: 7.7 | EL16: 20 | EM16: 20 | EN16: 20 | EO16: 13.1 | EP16: 0 | EQ16: 0 | ER16: 0.6 | ES16: 20.4 | ET16: 16.6 | EU16: 0 | EV16: 0 | EW16: 7.6 | EX16: 19.9 | EY16: 9.5 | EZ16: 18 | FA16: 36.3 | FB16: 28.9 | FC16: 3.1 | FD16: 13.7 | FE16: 15.1 | FF16: 8.1 | FG16: 6109.6 | FI16: 24.27044 | FJ16: 1.2 | FK16: 0 | FL16: 6.1105 | FM16: 8 | FO16: 18.53416 | FP16: 7.3 | FQ16: 4.2 | FR16: 69.6151
A17: 27/01/2025 | B17: 03:30 | C17: 1.1 | D17: 1.6 | E17: 4.3 | F17: 651.9 | G17: 218.9 | J17: 60.3 | K17: 240.9 | N17: 109.7 | O17: 108.8 | P17: 108.2 | Q17: 211 | R17: 123.6 | S17: 73.7 | T17: 561.8 | U17: 10.6 | Z17: 170.8 | AA17: 8.1 | AB17: 2.7 | AC17: 0 | AD17: 6.6 | AF17: 30.8 | AG17: 5.4 | AK17: 111.4 | AL17: 176.2 | AP17: 6.5 | AQ17: 466.5 | AR17: 62.5 | AS17: 136.2 | AT17: 40.5 | AU17: 18.3 | AV17: 19.7 | AW17: 94 | AX17: 0 | AY17: 124.7 | AZ17: 74.1 | BA17: 109 | BB17: 7.7 | BC17: 2.8 | BD17: 43.8 | BE17: 47.3 | BF17: 3.7 | BG17: 30.7 | BH17: 127.1 | BI17: 0 | BL17: 36.5 | BP17: 131.5 | BQ17: 0 | BR17: 0 | BT17: 0 | BZ17: 16.5 | CC17: 80.4 | CD17: 120.1 | CE17: 44.9 | CF17: 82 | CG17: 30.5 | CH17: 0 | CK17: 104.2 | CL17: 103.9 | CM17: 121.3 | CU17: 0 | CV17: 80.7 | CW17: 0 | CX17: 17 | CY17: 0 | CZ17: 20 | DA17: 9.9 | DB17: 4.7 | DC17: 3.7 | DD17: 5.2 | DE17: 20.5 | DF17: 20 | DG17: 14 | DH17: 0 | DI17: 18.8 | DJ17: 0 | DK17: 0 | DL17: 24.5 | DM17: 64.7 | DN17: 4.8 | DO17: 2.3 | DP17: 2.4 | DQ17: 3 | DR17: 0 | DS17: 3.6 | DT17: 6.5 | DU17: 2 | DW17: 16.2 | DX17: 8.9 | DY17: 18.8 | DZ17: 20.3 | EA17: 20 | EB17: 17.5 | EC17: 17.3 | ED17: 0 | EE17: 26.6 | EF17: 65.9 | EG17: 1.1 | EH17: 0.7 | EI17: 21 | EJ17: 8.4 | EK17: 7.6 | EL17: 20 | EM17: 20 | EN17: 20 | EO17: 12.4 | EP17: 0 | EQ17: 0 | ER17: 0.6 | ES17: 20.5 | ET17: 18.4 | EU17: 0 | EV17: 0 | EW17: 7.5 | EX17: 20 | EY17: 10.1 | EZ17: 17.8 | FA17: 36 | FB17: 28.9 | FC17: 3.2 | FD17: 12 | FE17: 15.1 | FF17: 7.6 | FG17: 6134 | FI17: 24.27101 | FJ17: 1.2 | FK17: 1.665 | FL17: 6.1105 | FM17: 8 | FO17: 18.75004 | FP17: 7.4 | FQ17: 4.3 | FR17: 71.69655
A18: 27/01/2025 | B18: 04:00 | C18: 1.1 | D18: 1.6 | E18: 4.3 | F18: 641.3 | G18: 218.9 | J18: 58.7 | K18: 233.3 | N18: 108.2 | O18: 107.9 | P18: 107.6 | Q18: 207 | R18: 122.1 | S18: 74.2 | T18: 553.5 | U18: 10.3 | Z18: 161.8 | AA18: 7.2 | AB18: 2.5 | AC18: 0 | AD18: 6.7 | AF18: 29.2 | AG18: 5.1 | AK18: 109.3 | AL18: 175.7 | AP18: 6.5 | AQ18: 459.1 | AR18: 63 | AS18: 119.1 | AT18: 39.1 | AU18: 18.3 | AV18: 19.7 | AW18: 90.5 | AX18: 0 | AY18: 119.2 | AZ18: 73.2 | BA18: 106.3 | BB18: 7.8 | BC18: 2.8 | BD18: 41.8 | BE18: 46.4 | BF18: 3.7 | BG18: 29.5 | BH18: 123.4 | BI18: 0 | BL18: 24.1 | BP18: 129.3 | BQ18: 0 | BR18: 0 | BT18: 0 | BZ18: 92.8 | CC18: 41.6 | CD18: 107.2 | CE18: 43.8 | CF18: 81 | CG18: 29.5 | CH18: 0 | CK18: 103.3 | CL18: 102.4 | CM18: 119.7 | CU18: 0 | CV18: 92.6 | CW18: 0 | CX18: 17 | CY18: 0 | CZ18: 20 | DA18: 10 | DB18: 4.7 | DC18: 3.7 | DD18: 5.2 | DE18: 19.8 | DF18: 20 | DG18: 14 | DH18: 0 | DI18: 18.8 | DJ18: 0 | DK18: 0 | DL18: 23.1 | DM18: 65.2 | DN18: 4.8 | DO18: 2.3 | DP18: 2.4 | DQ18: 3 | DR18: 0 | DS18: 3.6 | DT18: 6.5 | DU18: 2 | DW18: 16.2 | DX18: 8.9 | DY18: 18.6 | DZ18: 20.2 | EA18: 19.8 | EB18: 12.6 | EC18: 21.1 | ED18: 0 | EE18: 28.9 | EF18: 67.5 | EG18: 0.8 | EH18: 0.5 | EI18: 21 | EJ18: 8.4 | EK18: 7.5 | EL18: 20 | EM18: 20 | EN18: 20 | EO18: 13.8 | EP18: 0 | EQ18: 0 | ER18: 0.6 | ES18: 28.9 | ET18: 26.3 | EU18: 0 | EV18: 0 | EW18: 7.5 | EX18: 19.8 | EY18: 9.7 | EZ18: 17.9 | FA18: 35.8 | FB18: 28.9 | FC18: 3.2 | FD18: 13.8 | FE18: 14.8 | FF18: 8.8 | FG18: 6072.1 | FI18: 24.27359 | FJ18: 1.2 | FK18: 7.887 | FL18: 6.1105 | FM18: 8 | FO18: 18.9235 | FP18: 7.4 | FQ18: 4.2 | FR18: 77.99459
A19: 27/01/2025 | B19: 04:30 | C19: 1.1 | D19: 1.6 | E19: 4.3 | F19: 641.9 | G19: 217 | J19: 61.1 | K19: 236.9 | N19: 106.9 | O19: 106.6 | P19: 106.1 | Q19: 207.5 | R19: 122 | S19: 73.5 | T19: 552 | U19: 10.6 | Z19: 167.1 | AA19: 7.6 | AB19: 2.6 | AC19: 0 | AD19: 6.7 | AF19: 29.3 | AG19: 2.7 | AK19: 110.3 | AL19: 222.6 | AP19: 6.5 | AQ19: 374.1 | AR19: 63.8 | AS19: 136.4 | AT19: 40.5 | AU19: 18.3 | AV19: 19.7 | AW19: 93.8 | AX19: 0 | AY19: 121.5 | AZ19: 72 | BA19: 107.9 | BB19: 7.5 | BC19: 2.8 | BD19: 42.5 | BE19: 46.7 | BF19: 3.7 | BG19: 30 | BH19: 148.9 | BI19: 0 | BL19: 24.2 | BP19: 130.5 | BQ19: 0 | BR19: 0 | BT19: 0 | BZ19: 93.7 | CC19: 42.1 | CD19: 123 | CE19: 44.1 | CF19: 80.7 | CG19: 29.9 | CH19: 0 | CK19: 101.4 | CL19: 102.1 | CM19: 118 | CU19: 0 | CV19: 101.5 | CW19: 0 | CX19: 16.1 | CY19: 0 | CZ19: 19.9 | DA19: 9.9 | DB19: 4.7 | DC19: 3.7 | DD19: 5.2 | DE19: 19.9 | DF19: 20 | DG19: 14 | DH19: 0 | DI19: 18.8 | DJ19: 0 | DK19: 0 | DL19: 26.8 | DM19: 67.7 | DN19: 4.8 | DO19: 2.3 | DP19: 2.4 | DQ19: 3 | DR19: 0 | DS19: 3.6 | DT19: 6.5 | DU19: 2 | DW19: 16.2 | DX19: 9 | DY19: 18.6 | DZ19: 20.2 | EA19: 20 | EB19: 23.5 | EC19: 20.6 | ED19: 0 | EE19: 33.8 | EF19: 66.2 | EG19: 1.2 | EH19: 1 | EI19: 21 | EJ19: 8.4 | EK19: 7.5 | EL19: 20 | EM19: 20 | EN19: 20 | EO19: 13.2 | EP19: 0 | EQ19: 0 | ER19: 0.6 | ES19: 44.5 | ET19: 33.6 | EU19: 0 | EV19: 0 | EW19: 7.5 | EX19: 20 | EY19: 10.1 | EZ19: 17.9 | FA19: 35.9 | FB19: 28.9 | FC19: 3.1 | FD19: 13.9 | FE19: 15.1 | FF19: 8.3 | FG19: 6156.9 | FI19: 24.27018 | FJ19: 1.2 | FK19: 7.929 | FL19: 6.11 | FM19: 8 | FO19: 18.92347 | FP19: 7.6 | FQ19: 4.2 | FR19: 78.23265
A20: 27/01/2025 | B20: 05:00 | C20: 1.1 | D20: 1.6 | E20: 4.3 | F20: 644.2 | G20: 217.4 | J20: 61.6 | K20: 237.3 | N20: 107.7 | O20: 106.9 | P20: 107.7 | Q20: 206.7 | R20: 122.3 | S20: 74.8 | T20: 558.3 | U20: 10.7 | Z20: 169.7 | AA20: 7.7 | AB20: 2.7 | AC20: 0 | AD20: 6.7 | AF20: 29.7 | AG20: 4.7 | AK20: 110.8 | AL20: 223 | AP20: 6.5 | AQ20: 384.5 | AR20: 65 | AS20: 138.4 | AT20: 40.8 | AU20: 18.4 | AV20: 19.7 | AW20: 90.6 | AX20: 0 | AY20: 123.8 | AZ20: 72.9 | BA20: 109.3 | BB20: 7.5 | BC20: 2.8 | BD20: 44.8 | BE20: 47 | BF20: 3.7 | BG20: 31 | BH20: 153.9 | BI20: 0 | BL20: 24.7 | BP20: 131.1 | BQ20: 0 | BR20: 0 | BT20: 0 | BZ20: 95.4 | CC20: 53.5 | CD20: 124.7 | CE20: 44.5 | CF20: 78.4 | CG20: 30.3 | CH20: 0 | CK20: 103.1 | CL20: 103.7 | CM20: 119.3 | CU20: 0 | CV20: 97.5 | CW20: 0 | CX20: 15.9 | CY20: 0 | CZ20: 20 | DA20: 10 | DB20: 4.7 | DC20: 3.7 | DD20: 5.2 | DE20: 20.1 | DF20: 20 | DG20: 14 | DH20: 0 | DI20: 18.8 | DJ20: 0 | DK20: 0 | DL20: 29.8 | DM20: 71.1 | DN20: 4.8 | DO20: 2.3 | DP20: 2.4 | DQ20: 3 | DR20: 0 | DS20: 3.6 | DT20: 6.5 | DU20: 2 | DW20: 16.2 | DX20: 9.1 | DY20: 18.8 | DZ20: 20.3 | EA20: 19.8 | EB20: 23.1 | EC20: 16.4 | ED20: 0 | EE20: 29.9 | EF20: 68.5 | EG20: 1.9 | EH20: 1 | EI20: 21 | EJ20: 8.4 | EK20: 7.5 | EL20: 20 | EM20: 20 | EN20: 20 | EO20: 12.5 | EP20: 0 | EQ20: 0 | ER20: 0.6 | ES20: 45.2 | ET20: 35.2 | EU20: 0 | EV20: 0 | EW20: 7.5 | EX20: 19.8 | EY20: 9.8 | EZ20: 18 | FA20: 36 | FB20: 28.9 | FC20: 3.4 | FD20: 13.9 | FE20: 0 | FF20: 7.8 | FG20: 6202.8 | FI20: 24.2711 | FJ20: 1.2 | FK20: 7.937 | FL20: 6.113 | FM20: 8 | FO20: 18.92369 | FP20: 7.6 | FQ20: 4.3 | FR20: 78.34479
A21: 27/01/2025 | B21: 05:30 | C21: 1.1 | D21: 1.6 | E21: 4.3 | F21: 646.9 | G21: 218.2 | J21: 59.2 | K21: 238.2 | N21: 107.5 | O21: 107.9 | P21: 108.3 | Q21: 208.4 | R21: 121.4 | S21: 74.9 | T21: 558.6 | U21: 10.5 | Z21: 160.6 | AA21: 7.7 | AB21: 2.6 | AC21: 0 | AD21: 6.7 | AF21: 29.5 | AG21: 4.5 | AK21: 110.7 | AL21: 164.1 | AP21: 6.5 | AQ21: 465.3 | AR21: 63.2 | AS21: 137.1 | AT21: 40.9 | AU21: 18.4 | AV21: 19.7 | AW21: 88.2 | AX21: 0 | AY21: 122.5 | AZ21: 73.3 | BA21: 108.6 | BB21: 7.6 | BC21: 2.8 | BD21: 43.5 | BE21: 46.8 | BF21: 3.7 | BG21: 30.2 | BH21: 153.8 | BI21: 0 | BL21: 24.9 | BP21: 130.6 | BQ21: 0 | BR21: 0 | BT21: 0 | BZ21: 113.5 | CC21: 82.7 | CD21: 132 | CE21: 64.3 | CF21: 80 | CG21: 30.1 | CH21: 0 | CK21: 104 | CL21: 104.8 | CM21: 120.1 | CU21: 0 | CV21: 87.9 | CW21: 0 | CX21: 17 | CY21: 0 | CZ21: 20 | DA21: 9.9 | DB21: 4.7 | DC21: 3.6 | DD21: 5.1 | DE21: 20.2 | DF21: 20 | DG21: 14 | DH21: 0 | DI21: 18.8 | DJ21: 0.1 | DK21: 0 | DL21: 27.6 | DM21: 68.5 | DN21: 4.8 | DO21: 2.3 | DP21: 2.4 | DQ21: 3 | DR21: 0 | DS21: 3.6 | DT21: 6.5 | DU21: 2 | DW21: 16.3 | DX21: 9.1 | DY21: 19 | DZ21: 20.4 | EA21: 19.8 | EB21: 23.6 | EC21: 14.4 | ED21: 0 | EE21: 37.2 | EF21: 61.5 | EG21: 1.1 | EH21: 1.4 | EI21: 21 | EJ21: 8.4 | EK21: 7.9 | EL21: 20 | EM21: 20 | EN21: 20 | EO21: 13.9 | EP21: 0 | EQ21: 0 | ER21: 0.6 | ES21: 41.9 | ET21: 38.3 | EU21: 0.1 | EV21: 0 | EW21: 7.5 | EX21: 19.8 | EY21: 9.3 | EZ21: 17.8 | FA21: 35.7 | FB21: 28.9 | FC21: 3.4 | FD21: 13.9 | FE21: 0 | FF21: 8.5 | FG21: 6275.2 | FI21: 24.27324 | FJ21: 1.2 | FK21: 8.039 | FL21: 6.1145 | FM21: 8 | FO21: 18.92311 | FP21: 7.7 | FQ21: 4.3 | FR21: 78.54985
A22: 27/01/2025 | B22: 06:00 | C22: 1.1 | D22: 1.6 | E22: 4.3 | F22: 649.2 | G22: 218.7 | J22: 60.2 | K22: 239.6 | N22: 108.4 | O22: 108.8 | P22: 108.5 | Q22: 208.2 | R22: 122.7 | S22: 74.6 | T22: 560.5 | U22: 10.6 | Z22: 169.1 | AA22: 7.9 | AB22: 2.7 | AC22: 0 | AD22: 6.7 | AF22: 30.4 | AG22: 4.6 | AK22: 111.2 | AL22: 190.4 | AP22: 6.5 | AQ22: 465.9 | AR22: 63 | AS22: 133.2 | AT22: 41.2 | AU22: 18.3 | AV22: 19.7 | AW22: 91.1 | AX22: 0 | AY22: 125 | AZ22: 73.5 | BA22: 109.1 | BB22: 7.7 | BC22: 2.8 | BD22: 44.4 | BE22: 47 | BF22: 3.7 | BG22: 30.7 | BH22: 150.5 | BI22: 0 | BL22: 24.9 | BP22: 131 | BQ22: 0 | BR22: 0 | BT22: 0 | BZ22: 115.1 | CC22: 72.3 | CD22: 132.7 | CE22: 66.7 | CF22: 80.6 | CG22: 28.1 | CH22: 0 | CK22: 103.9 | CL22: 103.4 | CM22: 120.3 | CU22: 0 | CV22: 87.7 | CW22: 2.7 | CX22: 14.3 | CY22: 0 | CZ22: 20 | DA22: 9.9 | DB22: 4.7 | DC22: 3.7 | DD22: 5.1 | DE22: 20.4 | DF22: 20 | DG22: 14 | DH22: 2.1 | DI22: 18.8 | DJ22: 0.7 | DK22: 0.7 | DL22: 22.7 | DM22: 60.7 | DN22: 4.8 | DO22: 2.3 | DP22: 2.4 | DQ22: 3 | DR22: 0.1 | DS22: 3.6 | DT22: 6.3 | DU22: 2 | DW22: 15.8 | DX22: 9.3 | DY22: 19.3 | DZ22: 20.3 | EA22: 19.8 | EB22: 18 | EC22: 10.9 | ED22: 1.9 | EE22: 31 | EF22: 64.4 | EG22: 2 | EH22: 1.5 | EI22: 21 | EJ22: 8.4 | EK22: 7.9 | EL22: 20 | EM22: 20 | EN22: 20 | EO22: 11.3 | EP22: 0 | EQ22: 11.8 | ER22: 0.6 | ES22: 51.9 | ET22: 39.6 | EU22: 10.3 | EV22: 0 | EW22: 7.5 | EX22: 19.9 | EY22: 10.1 | EZ22: 18.1 | FA22: 36 | FB22: 28.9 | FC22: 3.4 | FD22: 14 | FE22: 0 | FF22: 9.3 | FG22: 6329.2 | FI22: 24.27081 | FJ22: 1.2 | FK22: 8.039 | FL22: 6.114 | FM22: 8 | FO22: 18.92243 | FP22: 7.6 | FQ22: 4.3 | FR22: 78.44624
... A58: 28/01/2025 | B58: 00:00 | C58: 1 | D58: 1.7 | E58: 4.3 | F58: 616.4 | G58: 219.1 | J58: 80 | K58: 240.9 | N58: 107.7 | O58: 107.7 | P58: 107.9 | Q58: 209.8 | R58: 168.3 | S58: 99.9 | T58: 562.1 | U58: 10.6 | Z58: 172.3 | AA58: 8.4 | AB58: 2.6 | AC58: 0 | AD58: 6.5 | AF58: 84.1 | AG58: 4.7 | AK58: 111.4 | AL58: 146.2 | AP58: 6.5 | AQ58: 460.4 | AR58: 57.9 | AS58: 138.8 | AT58: 40.7 | AU58: 18.2 | AV58: 19.7 | AW58: 94.1 | AX58: 125.4 | AY58: 126 | AZ58: 152.1 | BA58: 110 | BB58: 7.9 | BC58: 2 | BD58: 44.9 | BE58: 47.7 | BF58: 3.8 | BG58: 31.2 | BH58: 175.2 | BI58: 46.4 | BL58: 47.2 | BP58: 131.8 | BQ58: 0 | BR58: 162 | BT58: 65.2 | BZ58: 115.4 | CC58: 143.1 | CD58: 124.5 | CE58: 64.4 | CF58: 78.8 | CG58: 30.6 | CH58: 0 | CK58: 103.6 | CL58: 103.4 | CM58: 120.5 | CU58: 0 | CV58: 59.7 | CW58: 0 | CX58: 14.5 | CY58: 0 | CZ58: 20 | DA58: 9.8 | DB58: 5.4 | DC58: 3.6 | DD58: 5.1 | DE58: 20.6 | DF58: 20 | DG58: 13 | DH58: 0 | DI58: 18.8 | DJ58: 0 | DK58: 0 | DL58: 21.5 | DM58: 59.2 | DN58: 3.2 | DO58: 2.3 | DP58: 2.4 | DQ58: 2.9 | DR58: 0 | DS58: 3.5 | DT58: 17.4 | DU58: 2 | DW58: 13.3 | DX58: 9.2 | DY58: 20.4 | DZ58: 20.5 | EA58: 19.7 | EB58: 4 | EC58: 8.5 | ED58: 0 | EE58: 35.4 | EF58: 77.4 | EG58: 1.4 | EH58: 1.8 | EI58: 21 | EJ58: 8.4 | EK58: 1.1 | EL58: 20 | EM58: 20 | EN58: 20 | EO58: 12.5 | EP58: 0 | EQ58: 0 | ER58: 0.6 | ES58: 42.9 | ET58: 31.5 | EU58: 0 | EV58: 0 | EW58: 8.2 | EX58: 19.8 | EY58: 10.4 | EZ58: 0 | FA58: 37 | FB58: 28.7 | FC58: 3.2 | FD58: 12.7 | FE58: 3.4 | FF58: 8.6 | FG58: 6899.5 | FI58: 23.60828 | FJ58: 1.3 | FK58: 8.007 | FL58: 6.112 | FM58: 9 | FO58: 18.93879 | FP58: 9.4 | FQ58: 4.1 | FR58: 80.46607
A59: EJEC | C59: 24.8 | D59: 32 | E59: 102.8 | F59: 15500.3 | G59: 5256.7 | H59: 0 | I59: 0 | J59: 1908.25 | K59: 5712.2 | L59: 0 | M59: 0 | N59: 3143.25 | O59: 3170.7 | P59: 3170.5 | Q59: 5521.05 | R59: 4200.15 | S59: 2295.6 | T59: 13382.55 | U59: 252.2 | V59: 0 | W59: 0 | X59: 0 | Y59: 0 | Z59: 3979.75 | AA59: 183.55 | AB59: 62.7 | AC59: 44.4 | AD59: 158.2 | AE59: 0 | AF59: 1519 | AG59: 135.8 | AH59: 0 | AI59: 0 | AJ59: 0 | AK59: 2657.95 | AL59: 5011.1 | AM59: 0 | AN59: 0 | AO59: 0 | AP59: 155.95 | AQ59: 10889.7 | AR59: 1452.35 | AS59: 3386.1 | AT59: 975.35 | AU59: 440.75 | AV59: 472.8 | AW59: 2177.6 | AX59: 2769.2 | AY59: 3714.35 | AZ59: 3430.15 | BA59: 2610.55 | BB59: 189.95 | BC59: 59.9 | BD59: 1017.1 | BE59: 1121.95 | BF59: 90.55 | BG59: 726.55 | BH59: 3798.5 | BI59: 1219.6 | BJ59: 0 | BK59: 0 | BL59: 1035.2 | BM59: 0 | BN59: 0 | BO59: 0 | BP59: 3137.7 | BQ59: 288.6 | BR59: 631.55 | BS59: 0 | BT59: 129 | BU59: 0 | BV59: 0 | BW59: 0 | BX59: 0 | BY59: 0 | BZ59: 2411.75 | CA59: 0 | CB59: 0 | CC59: 4245.4 | CD59: 3067.4 | CE59: 1462.15 | CF59: 1931.55 | CG59: 722 | CH59: 422 | CI59: 0 | CJ59: 0 | CK59: 2971.2 | CL59: 2959.5 | CM59: 3207.2 | CN59: 0 | CO59: 0 | CP59: 0 | CQ59: 0 | CR59: 0 | CS59: 0 | CT59: 0 | CU59: 7.05 | CV59: 2038.1 | CW59: 626.35 | CX59: 360.75 | CY59: 1.8 | CZ59: 479.7 | DA59: 237.9 | DB59: 123.8 | DC59: 86.9 | DD59: 123.95 | DE59: 485.15 | DF59: 478.9 | DG59: 322.4 | DH59: 55.5 | DI59: 451.2 | DJ59: 114.85 | DK59: 144 | DL59: 560.55 | DM59: 1594.75 | DN59: 81.9 | DO59: 54.4 | DP59: 55.2 | DQ59: 64.15 | DR59: 156.1 | DS59: 86.2 | DT59: 355.5 | DU59: 48 | DV59: 0 | DW59: 356.7 | DX59: 217.45 | DY59: 478.9 | DZ59: 488.6 | EA59: 478.5 | EB59: 272.6 | EC59: 573.1 | ED59: 218.65 | EE59: 1359.35 | EF59: 1845 | EG59: 135.35 | EH59: 130.9 | EI59: 503.85 | EJ59: 197.95 | EK59: 176.95 | EL59: 480 | EM59: 480 | EN59: 479.65 | EO59: 297.7 | EP59: 124.7 | EQ59: 1020.6 | ER59: 14.4 | ES59: 1475.75 | ET59: 1431.2 | EU59: 843.5 | EV59: 106.3 | EW59: 184.9 | EX59: 478.95 | EY59: 239.7 | EZ59: 393.35 | FA59: 864.15 | FB59: 685.8 | FC59: 79.2 | FD59: 309.6 | FE59: 74.55 | FF59: 187.65 | FG59: 173627.2 | FI59: 565.10693 | FJ59: 30.3 | FK59: 144.9615 | FL59: 146.68875 | FM59: 198.1 | FN59: 0 | FO59: 453.97657 | FP59: 181.6 | FQ59: 164.45 | FR59: 1885.1837

Sheet REACTIVA
B3: lunes, 27 de Enero del 2025
A5: POTENCIA REACTIVA EJECUTADA DE LAS UNIDADES DE GENERACIÓN DEL COES (MVAR) | FH5: CENTRALES NO INTEGRANTES COES
A6: FECHA | B6: HORA | C6: 337 | D6: 338 | E6: 121 | F6: 101 | G6: 102 | H6: 42667 | I6: 42668 | J6: 126 | K6: 127 | L6: 138 | M6: 139 | N6: 197 | O6: 203 | P6: 204 | Q6: 230 | R6: 209 | S6: 56677 | T6: 796 | U6: 2146 | V6: 142 | W6: 143 | X6: 125 | Y6: 187 | Z6: 163 | AA6: 298 | AB6: 219 | AC6: 151 | AD6: 152 | AE6: 153 | AF6: 154 | AG6: 756 | AH6: 156 | AI6: 155 | AJ6: 182 | AK6: 212 | AL6: 758 | AM6: 263 | AN6: 265 | AO6: 775 | AP6: 777 | AQ6: 2154 | AR6: 150 | AS6: 149 | AT6: 188 | AU6: 2131 | AV6: 755 | AW6: 252 | AX6: 249 | AY6: 250 | AZ6: 117 | BA6: 267 | BB6: 268 | BC6: 119 | BD6: 120 | BE6: 189 | BF6: 122 | BG6: 266 | BH6: 251 | BI6: 115 | BJ6: 239 | BK6: 288 | BL6: 240 | BM6: 241 | BN6: 242 | BO6: 191 | BP6: 194 | BQ6: 196 | BR6: 207 | BS6: 236 | BT6: 795 | BU6: 285 | BV6: 995 | BW6: 996 | BX6: 997 | BY6: 766 | BZ6: 926 | CA6: 924 | CB6: 103 | CC6: 104 | CD6: 106 | CE6: 105 | CF6: 107 | CG6: 110 | CH6: 109 | CI6: 144 | CJ6: 113 | CK6: 114 | CL6: 193 | CM6: 208 | CN6: 786 | CO6: 787 | CP6: 788 | CQ6: 789 | CR6: 248 | CS6: 2159 | CT6: 303 | CU6: 59715 | CV6: 62255 | CW6: 1263 | CX6: 61800 | CY6: 2194 | CZ6: 216 | DA6: 198 | DB6: 214 | DC6: 260 | DD6: 2152 | DE6: 2128 | DF6: 247 | DG6: 228 | DH6: 2135 | DI6: 261 | DJ6: 237 | DK6: 253 | DL6: 770 | DM6: 225 | DN6: 2201 | DO6: 2171 | DP6: 760 | DQ6: 235 | DR6: 238 | DS6: 2184 | DT6: 61855 | DU6: 223 | DV6: 226 | DW6: 201 | DX6: 258 | DY6: 259 | DZ6: 920 | EA6: 257 | EB6: 256 | EC6: 2148 | ED6: 58288 | EE6: 58289 | EF6: 58839 | EG6: 58840 | EH6: 296 | EI6: 297 | EJ6: 211 | EK6: 2175 | EL6: 2178 | EM6: 2181 | EN6: 1262 | EO6: 233 | EP6: 2150 | EQ6: 2165 | ER6: 2161 | ES6: 61197 | ET6: 58851 | EU6: 234 | EV6: 215 | EW6: 917 | EX6: 289 | EY6: 58333 | EZ6: 58336 | FA6: 202 | FB6: 58487 | FC6: 213 | FD6: 232 | FE6: 2190 | FF6: TOTAL COES | FH6: 221 | FI6: 49607 | FJ6: 222 | FK6: 224 | FL6: 2187 | FM6: 227 | FN6: 49400 | FO6: 199 | FP6: 200 | FQ6: TOTAL NO COES
C7: CENTRO | D7: CENTRO | E7: NORTE | F7: CENTRO | G7: CENTRO | H7: NORTE | I7: NORTE | J7: NORTE | K7: NORTE | L7: CENTRO | M7: CENTRO | N7: CENTRO | O7: CENTRO | P7: CENTRO | Q7: CENTRO | R7: CENTRO | S7: CENTRO | T7: CENTRO | U7: CENTRO | V7: CENTRO | W7: CENTRO | X7: CENTRO | Y7: CENTRO | Z7: SUR | AA7: SUR | AB7: CENTRO | AC7: SUR | AD7: SUR | AE7: SUR | AF7: SUR | AG7: SUR | AH7: SUR | AI7: SUR | AJ7: SUR | AK7: CENTRO | AL7: NORTE | AM7: NORTE | AN7: NORTE | AO7: CENTRO | AP7: CENTRO | AQ7: CENTRO | AR7: CENTRO | AS7: CENTRO | AT7: CENTRO | AU7: CENTRO | AV7: SUR | AW7: CENTRO | AX7: CENTRO | AY7: CENTRO | AZ7: CENTRO | BA7: CENTRO | BB7: CENTRO | BC7: CENTRO | BD7: CENTRO | BE7: SUR | BF7: NORTE | BG7: CENTRO | BH7: CENTRO | BI7: NORTE | BJ7: NORTE | BK7: NORTE | BL7: SUR | BM7: SUR | BN7: SUR | BO7: CENTRO | BP7: CENTRO | BQ7: CENTRO | BR7: CENTRO | BS7: CENTRO | BT7: CENTRO | BU7: CENTRO | BV7: SUR | BW7: SUR | BX7: SUR | BY7: NORTE | BZ7: SUR | CA7: CENTRO | CB7: CENTRO | CC7: CENTRO | CD7: CENTRO | CE7: CENTRO | CF7: CENTRO | CG7: CENTRO | CH7: CENTRO | CI7: CENTRO | CJ7: CENTRO | CK7: CENTRO | CL7: CENTRO | CM7: CENTRO | CN7: SUR | CO7: SUR | CP7: SUR | CQ7: SUR | CR7: CENTRO | CS7: CENTRO | CT7: CENTRO | CU7: CENTRO | CV7: SUR | CW7: NORTE | CX7: NORTE | CY7: NORTE | CZ7: NORTE | DA7: NORTE | DB7: CENTRO | DC7: CENTRO | DD7: CENTRO | DE7: NORTE | DF7: NORTE | DG7: CENTRO | DH7: CENTRO | DI7: SUR | DJ7: SUR | DK7: CENTRO | DL7: CENTRO | DM7: CENTRO | DN7: CENTRO | DO7: CENTRO | DP7: CENTRO | DQ7: SUR | DR7: CENTRO | DS7: CENTRO | DT7: NORTE | DU7: CENTRO | DV7: CENTRO | DW7: NORTE | DX7: CENTRO | DY7: CENTRO | DZ7: CENTRO | EA7: NORTE | EB7: NORTE | EC7: SUR | ED7: CENTRO | EE7: CENTRO | EF7: CENTRO | EG7: CENTRO | EH7: CENTRO | EI7: CENTRO | EJ7: SUR | EK7: SUR | EL7: SUR | EM7: SUR | EN7: NORTE | EO7: SUR | EP7: SUR | EQ7: CENTRO | ER7: CENTRO | ES7: CENTRO | ET7: SUR | EU7: SUR | EV7: NORTE | EW7: CENTRO | EX7: NORTE | EY7: NORTE | EZ7: NORTE | FA7: CENTRO | FB7: CENTRO | FC7: CENTRO | FD7: NORTE | FE7: NORTE | FH7: NORTE | FI7: SUR | FJ7: CENTRO | FK7: NORTE | FL7: NORTE | FM7: NORTE | FN7: NORTE | FO7: NORTE | FP7: NORTE
C8: HIDROELÉCTRICA | D8: HIDROELÉCTRICA | E8: HIDROELÉCTRICA | F8: HIDROELÉCTRICA | G8: HIDROELÉCTRICA | H8: TERMOELÉCTRICA | I8: TERMOELÉCTRICA | J8: HIDROELÉCTRICA | K8: HIDROELÉCTRICA | L8: TERMOELÉCTRICA | M8: TERMOELÉCTRICA | N8: TERMOELÉCTRICA | O8: TERMOELÉCTRICA | P8: TERMOELÉCTRICA | Q8: TERMOELÉCTRICA | R8: TERMOELÉCTRICA | S8: TERMOELÉCTRICA | T8: HIDROELÉCTRICA | U8: HIDROELÉCTRICA | V8: TERMOELÉCTRICA | W8: TERMOELÉCTRICA | X8: TERMOELÉCTRICA | Y8: TERMOELÉCTRICA | Z8: HIDROELÉCTRICA | AA8: HIDROELÉCTRICA | AB8: TERMOELÉCTRICA | AC8: HIDROELÉCTRICA | AD8: HIDROELÉCTRICA | AE8: HIDROELÉCTRICA | AF8: HIDROELÉCTRICA | AG8: TERMOELÉCTRICA | AH8: TERMOELÉCTRICA | AI8: TERMOELÉCTRICA | AJ8: HIDROELÉCTRICA | AK8: HIDROELÉCTRICA | AL8: TERMOELÉCTRICA | AM8: TERMOELÉCTRICA | AN8: TERMOELÉCTRICA | AO8: HIDROELÉCTRICA | AP8: HIDROELÉCTRICA | AQ8: HIDROELÉCTRICA | AR8: HIDROELÉCTRICA | AS8: HIDROELÉCTRICA | AT8: HIDROELÉCTRICA | AU8: HIDROELÉCTRICA | AV8: HIDROELÉCTRICA | AW8: TERMOELÉCTRICA | AX8: TERMOELÉCTRICA | AY8: TERMOELÉCTRICA | AZ8: HIDROELÉCTRICA | BA8: HIDROELÉCTRICA | BB8: HIDROELÉCTRICA | BC8: HIDROELÉCTRICA | BD8: HIDROELÉCTRICA | BE8: HIDROELÉCTRICA | BF8: HIDROELÉCTRICA | BG8: HIDROELÉCTRICA | BH8: HIDROELÉCTRICA | BI8: TERMOELÉCTRICA | BJ8: TERMOELÉCTRICA | BK8: TERMOELÉCTRICA | BL8: TERMOELÉCTRICA | BM8: TERMOELÉCTRICA | BN8: TERMOELÉCTRICA | BO8: HIDROELÉCTRICA | BP8: TERMOELÉCTRICA | BQ8: TERMOELÉCTRICA | BR8: TERMOELÉCTRICA | BS8: TERMOELÉCTRICA | BT8: TERMOELÉCTRICA | BU8: TERMOELÉCTRICA | BV8: TERMOELÉCTRICA | BW8: TERMOELÉCTRICA | BX8: TERMOELÉCTRICA | BY8: HIDROELÉCTRICA | BZ8: TERMOELÉCTRICA | CA8: TERMOELÉCTRICA | CB8: HIDROELÉCTRICA | CC8: HIDROELÉCTRICA | CD8: HIDROELÉCTRICA | CE8: HIDROELÉCTRICA | CF8: HIDROELÉCTRICA | CG8: TERMOELÉCTRICA | CH8: TERMOELÉCTRICA | CI8: TERMOELÉCTRICA | CJ8: TERMOELÉCTRICA | CK8: TERMOELÉCTRICA | CL8: TERMOELÉCTRICA | CM8: TERMOELÉCTRICA | CN8: TERMOELÉCTRICA | CO8: TERMOELÉCTRICA | CP8: TERMOELÉCTRICA | CQ8: TERMOELÉCTRICA | CR8: TERMOELÉCTRICA | CS8: TERMOELÉCTRICA | CT8: SOLAR | CU8: EÓLICA | CV8: SOLAR | CW8: EÓLICA | CX8: SOLAR | CY8: HIDROELÉCTRICA | CZ8: HIDROELÉCTRICA | DA8: HIDROELÉCTRICA | DB8: HIDROELÉCTRICA | DC8: HIDROELÉCTRICA | DD8: HIDROELÉCTRICA | DE8: HIDROELÉCTRICA | DF8: HIDROELÉCTRICA | DG8: HIDROELÉCTRICA | DH8: HIDROELÉCTRICA | DI8: SOLAR | DJ8: SOLAR | DK8: EÓLICA | DL8: EÓLICA | DM8: TERMOELÉCTRICA | DN8: TERMOELÉCTRICA | DO8: TERMOELÉCTRICA | DP8: TERMOELÉCTRICA | DQ8: SOLAR | DR8: HIDROELÉCTRICA | DS8: HIDROELÉCTRICA | DT8: HIDROELÉCTRICA | DU8: HIDROELÉCTRICA | DV8: HIDROELÉCTRICA | DW8: HIDROELÉCTRICA | DX8: HIDROELÉCTRICA | DY8: HIDROELÉCTRICA | DZ8: HIDROELÉCTRICA | EA8: EÓLICA | EB8: EÓLICA | EC8: SOLAR | ED8: EÓLICA | EE8: EÓLICA | EF8: EÓLICA | EG8: EÓLICA | EH8: HIDROELÉCTRICA | EI8: HIDROELÉCTRICA | EJ8: HIDROELÉCTRICA | EK8: HIDROELÉCTRICA | EL8: HIDROELÉCTRICA | EM8: HIDROELÉCTRICA | EN8: EÓLICA | EO8: SOLAR | EP8: SOLAR | EQ8: HIDROELÉCTRICA | ER8: EÓLICA | ES8: EÓLICA | ET8: SOLAR | EU8: SOLAR | EV8: HIDROELÉCTRICA | EW8: HIDROELÉCTRICA | EX8: TERMOELÉCTRICA | EY8: TERMOELÉCTRICA | EZ8: TERMOELÉCTRICA | FA8: TERMOELÉCTRICA | FB8: TERMOELÉCTRICA | FC8: TERMOELÉCTRICA | FD8: TERMOELÉCTRICA | FE8: TERMOELÉCTRICA | FH8: HIDROELÉCTRICA | FI8: HIDROELÉCTRICA | FJ8: HIDROELÉCTRICA | FK8: HIDROELÉCTRICA | FL8: HIDROELÉCTRICA | FM8: TERMOELÉCTRICA | FN8: TERMOELÉCTRICA | FO8: HIDROELÉCTRICA | FP8: HIDROELÉCTRICA
C9: CENTRALES SANTA ROSA S.A.C. | D9: CENTRALES SANTA ROSA S.A.C. | E9: INVERSIONES SHAQSHA S.A.C. | F9: ELECTROPERU | G9: ELECTROPERU | H9: ELECTROPERU | I9: ELECTROPERU | J9: ORAZUL ENERGY PERÚ | K9: ORAZUL ENERGY PERÚ | L9: TERMOSELVA | M9: TERMOSELVA | N9: KALLPA GENERACION S.A. | O9: KALLPA GENERACION S.A. | P9: KALLPA GENERACION S.A. | Q9: KALLPA GENERACION S.A. | R9: KALLPA GENERACION S.A. | S9: KALLPA GENERACION S.A. | T9: KALLPA GENERACION S.A. | U9: KALLPA GENERACION S.A. | V9: SHOUGESA | W9: SHOUGESA | X9: SHOUGESA | Y9: SHOUGESA | Z9: EGEMSA | AA9: EGESUR | AB9: EGESUR | AC9: EGASA | AD9: EGASA | AE9: EGASA | AF9: EGASA | AG9: EGASA | AH9: EGASA | AI9: EGASA | AJ9: SAN GABAN | AK9: CELEPSA | AL9: MINERA CERRO VERDE | AM9: PLANTA DE RESERVA FRIA DE GENERACION DE ETEN S.A. | AN9: PLANTA DE RESERVA FRIA DE GENERACION DE ETEN S.A. | AO9: EMPRESA DE GENERACION HUALLAGA | AP9: EMPRESA DE GENERACION HUALLAGA | AQ9: LA VIRGEN | AR9: CHINANGO S.A.C. | AS9: CHINANGO S.A.C. | AT9: HIDROELECTRICA HUANCHOR S.A.C. | AU9: CELEPSA RENOVABLES S.R.L. | AV9: INLAND ENERGY SAC | AW9: FENIX POWER PERÚ | AX9: FENIX POWER PERÚ | AY9: FENIX POWER PERÚ | AZ9: STATKRAFT S.A | BA9: STATKRAFT S.A | BB9: STATKRAFT S.A | BC9: STATKRAFT S.A | BD9: STATKRAFT S.A | BE9: STATKRAFT S.A | BF9: STATKRAFT S.A | BG9: STATKRAFT S.A | BH9: EMPRESA DE GENERACION HUANZA | BI9: ENEL GENERACION PIURA S.A. | BJ9: ENEL GENERACION PIURA S.A. | BK9: ENEL GENERACION PIURA S.A. | BL9: ENGIE | BM9: ENGIE | BN9: ENGIE | BO9: ENGIE | BP9: ENGIE | BQ9: ENGIE | BR9: ENGIE | BS9: ENGIE | BT9: ENGIE | BU9: ENGIE | BV9: ENGIE | BW9: ENGIE | BX9: ENGIE | BY9: ENGIE | BZ9: INFRAESTRUCTURAS Y ENERGIAS DEL PERU S.A.C. | CA9: INFRAESTRUCTURAS Y ENERGIAS DEL PERU S.A.C. | CB9: ORYGEN PERU S.A.A. | CC9: ORYGEN PERU S.A.A. | CD9: ORYGEN PERU S.A.A. | CE9: ORYGEN PERU S.A.A. | CF9: ORYGEN PERU S.A.A. | CG9: ORYGEN PERU S.A.A. | CH9: ORYGEN PERU S.A.A. | CI9: ORYGEN PERU S.A.A. | CJ9: ORYGEN PERU S.A.A. | CK9: ORYGEN PERU S.A.A. | CL9: ORYGEN PERU S.A.A. | CM9: ORYGEN PERU S.A.A. | CN9: SAMAY I S.A.C | CO9: SAMAY I S.A.C | CP9: SAMAY I S.A.C | CQ9: SAMAY I S.A.C | CR9: TERMOCHILCA S.A.C. | CS9: TERMOCHILCA S.A.C. | CT9: COLCA SOLAR S.A.C. | CU9: ENERGIA RENOVABLE DEL SUR S.A. | CV9: GR CORTARRAMA SOCIEDAD ANONIMA CERRADA | CW9: GR TARUCA SOCIEDAD ANONIMA CERRADA | CX9: KONDU SAC | CY9: PERUANA DE INVERSIONES EN ENERGIAS RENOVABLES S.A. | CZ9: ORAZUL ENERGY PERÚ | DA9: ORAZUL ENERGY PERÚ | DB9: MAJA ENERGIA S.A.C. | DC9: EMPRESA DE GENERACION ELECTRICA CANCHAYLLO SAC | DD9: EMPRESA DE GENERACION ELECTRICA SANTA ANA S.A.C. | DE9: EMPRESA ELECTRICA AGUA AZUL | DF9: EMPRESA ELECTRICA RIO DOBLE | DG9: HIDROCAÑETE S.A. | DH9: HUAURA POWER GROUP S.A. | DI9: MOQUEGUA FV S.A.C. | DJ9: PANAMERICANA SOLAR SAC. | DK9: PARQUE EOLICO MARCONA S.A.C. | DL9: PARQUE EOLICO TRES HERMANAS S.A.C. | DM9: PETRAMAS | DN9: PETRAMAS | DO9: PETRAMAS | DP9: PETRAMAS | DQ9: TACNA SOLAR SAC. | DR9: ELECTRICA YANAPAMPA SAC | DS9: ANDEAN POWER S.A.C. | DT9: ASOCIACIÓN SANTA LUCIA DE CHACAS | DU9: ATRIA ENERGIA S.A.C. | DV9: EGEJUNIN | DW9: EGEJUNIN | DX9: EGEJUNIN | DY9: EGEJUNIN | DZ9: EMPRESA DE GENERACION ELECTRICA RIO BAÑOS S.A.C. | EA9: ENERGÍA EÓLICA S.A. | EB9: ENERGÍA EÓLICA S.A. | EC9: ENGIE | ED9: ENGIE | EE9: ENGIE | EF9: ENGIE | EG9: ENGIE | EH9: GENERACIÓN ANDINA S.A.C. | EI9: GENERACIÓN ANDINA S.A.C. | EJ9: GENERADORA DE ENERGÍA DEL PERÚ | EK9: GENERADORA DE ENERGÍA DEL PERÚ | EL9: GENERADORA DE ENERGÍA DEL PERÚ | EM9: GENERADORA DE ENERGÍA DEL PERÚ | EN9: GR PAINO SOCIEDAD ANONIMA CERRADA | EO9: MAJES ARCUS S.A.C. | EP9: ORYGEN PERU S.A.A. | EQ9: ORYGEN PERU S.A.A. | ER9: ORYGEN PERU S.A.A. | ES9: ORYGEN PERU S.A.A. | ET9: ORYGEN PERU S.A.A. | EU9: REPARTICIÓN ARCUS S.A.C. | EV9: SINERSA | EW9: SINERSA | EX9: BIOENERGIA DEL CHIRA S.A. | EY9: GM OPERACIONES S.A.C. | EZ9: GM OPERACIONES S.A.C. | FA9: SDF ENERGIA SAC | FB9: SDF ENERGIA SAC | FC9: AGRO INDUSTRIAL PARAMONGA S.A. | FD9: AGROAURORA S.A.C. | FE9: AGROINDUSTRIAS SAN JACINTO S.A.A. | FH9: UNACEM PERU S.A. | FI9: SAN GABAN | FJ9: ELECTRO ORIENTE | FK9: AGUAS Y ENERGIA PERU | FL9: ELECTRO ZAÑA S.A.C. | FM9: ELECTRONOROESTE S.A. | FN9: SDE PIURA | FO9: SINERSA | FP9: SINERSA
C10: SANTA ROSA 1 | D10: SANTA ROSA 2 | E10: PARIAC | F10: MANTARO | G10: RESTITUCION | H10: TUMBES MAK 1 | I10: TUMBES MAK 2 | J10: CARHUAQUERO | K10: CAÑON DEL PATO | L10: AGUAYTIA TG1 | M10: AGUAYTIA TG2 | N10: KALLPA TG1 | O10: KALLPA TG2 | P10: KALLPA TG3 | Q10: KALLPA TV | R10: LFLORES TG1 | S10: LFLORES TV | T10: CERRO DEL AGUILA | U10: CERRODELAGUILAG4 | V10: SHOUGESA TV1 | W10: SHOUGESA TV2 | X10: SHOUGESA TV3 | Y10: SHOUGESA CUMMINS | Z10: MACHUPICCHU | AA10: ARICOTA 1 | AB10: INDEPENDENCIA | AC10: CHARCANI I,II,III | AD10: CHARCANI IV | AE10: CHARCANI V | AF10: CHARCANI VI | AG10: CHILINA TG | AH10: MOLLENDO 1, 2, 3 | AI10: CHILINA (SULZ 1,2) | AJ10: SAN GABAN II | AK10: PLATANAL | AL10: RECKA | AM10: RF ETEN TG1 | AN10: RF ETEN TG2 | AO10: CHAGLLA GP1 | AP10: CHAGLLA | AQ10: LA VIRGEN | AR10: CHIMAY | AS10: YANANGO | AT10: HUANCHOR | AU10: MARAÑON | AV10: STA TERESA | AW10: FENIX GT11 | AX10: FENIX GT12 | AY10: FENIX TV10 | AZ10: YAUPI | BA10: OROYA | BB10: PACHACHACA | BC10: MALPASO | BD10: CAHUA | BE10: ARCATA | BF10: GALLITO CIEGO | BG10: CHEVES | BH10: HUANZA | BI10: MALACAS2 TG4 | BJ10: MALACAS3 TG 5 | BK10: MALACAS1 TG6 | BL10: RF ILO2 TG1 | BM10: RF ILO2 TG2 | BN10: RF ILO2 TG3 | BO10: YUNCAN | BP10: CHILCA1 TG1 | BQ10: CHILCA1 TG2 | BR10: CHILCA1 TG3 | BS10: CHILCA-TV | BT10: CHILCA2 TG41 | BU10: CHILCA2-TV | BV10: CTNEPI_TG41 | BW10: CTNEPI_TG42 | BX10: CTNEPI_TG43 | BY10: QUITARACSA | BZ10: RF PTO MALDONADO | CA10: RF PUCALLPA | CB10: HUINCO | CC10: MATUCANA | CD10: MOYOPAMPA | CE10: CALLAHUANCA | CF10: HUAMPANI | CG10: STA ROSA WEST TG7 | CH10: UTI_5 | CI10: UTI_6 | CJ10: VENTANILLA 3 | CK10: VENTANILLA 4 | CL10: VENTANILLA TV | CM10: STAROSA TG8 | CN10: PTO_BRVO TG1 | CO10: PTO_BRVO TG2 | CP10: PTO_BRVO TG3 | CQ10: PTO_BRVO TG4 | CR10: OLLEROS TG1 | CS10: OLLEROS TV | CT10: CS YARUCAYA | CU10: SAN JUAN | CV10: MATARANI | CW10: DUNA | CX10: CARHUAQUERO (CS) | CY10: MANTA I | CZ10: CARHUAQUERO4 | DA10: CAÑA BRAVA | DB10: RONCADOR | DC10: CANCHAYLLO | DD10: RENOVANDESH1 | DE10: POTRERO | DF10: PIZARRAS | DG10: NIMPERIAL | DH10: YARUCAYA | DI10: MOQUEGUA-SOLAR | DJ10: PANAMERICANA-SOLAR | DK10: PQE-EOLICO-MARCONA | DL10: PQE-EOLICO-3-HERMANAS | DM10: HUAYCOLORO | DN10: CALLAO | DO10: DONA_CATALINA | DP10: LAGRINGAV | DQ10: TACNA-SOLAR | DR10: YANAPAMPA | DS10: CARHUAC | DT10: HUALLIN | DU10: PURMACANA | DV10: HUASAHUASI | DW10: STACRUZ_1_2 | DX10: RUNATULLO_II | DY10: RUNATULLO_III | DZ10: RUCUY | EA10: PQE-EOLICO-TALARA | EB10: PQE-EOLICO-CUPISNIQUE | EC10: INTIPAMPA | ED10: PUNTA LOMITAS-BL1 | EE10: PUNTA LOMITAS-BL2 | EF10: PUN LOMITAS_EXP-BL1 | EG10: PUN LOMITAS_EXP-BL2 | EH10: 8AGOSTO | EI10: EL CARMEN | EJ10: LA JOYA | EK10: ANGEL_I | EL10: ANGEL_II | EM10: ANGEL_III | EN10: HUAMBOS | EO10: MAJES | EP10: RUBI | EQ10: CH_HER1 | ER10: WAYRA-I | ES10: WAYRA EXTENSION | ET10: CLEMESI | EU10: REPARTICION | EV10: POECHOS2 | EW10: CHANCAY | EX10: CANA BRAVA | EY10: REFINERIA TALARA TV1 | EZ10: REFINERÍA TALARA TV2 | FA10: OQUENDO TG1 | FB10: OQUENDO TV1 | FC10: PARAMONGA | FD10: MAPLE | FE10: SAN_JACINTO | FF10: MVAR | FH10: CARPAPATA | FI10: TUPURI | FJ10: CENTRALES ELOR | FK10: PIAS1 | FL10: ZANA | FM10: TABLAZO | FN10: TALLANCA | FO10: CURUMUY | FP10: POECHOS1 | FQ10: MVAR
A11: 27/01/2025 | B11: 00:30 | C11: 0.2 | D11: 0 | E11: 0 | F11: 20.1 | G11: 11.1 | J11: -12.3 | K11: 6.9 | N11: -32.2 | O11: -27.4 | P11: -20.9 | Q11: 18.4 | R11: -12.5 | S11: -20.1 | T11: 88.9 | U11: 0 | Z11: -1.7 | AA11: 0.6 | AB11: 0 | AC11: -3.2 | AE11: 6.6 | AF11: 1.2 | AJ11: 13 | AK11: 1.5 | AO11: -0.8 | AP11: 47.4 | AQ11: 6.4 | AR11: 11.7 | AS11: 0 | AT11: 0.5 | AU11: 2.7 | AV11: 1 | AW11: 0 | AX11: -14 | AY11: -58.5 | AZ11: 12.2 | BA11: -1 | BB11: 0.1 | BC11: -3.3 | BD11: 3.7 | BE11: 1 | BF11: 0 | BG11: -6.7 | BH11: 0 | BK11: 4.1 | BO11: 13.6 | BP11: 0 | BQ11: 0 | BS11: 0 | BY11: -9 | CB11: 18.6 | CC11: 30.2 | CD11: 0.1 | CE11: 3.7 | CF11: -0.2 | CG11: 0 | CJ11: 2 | CK11: 2.8 | CL11: -43.2 | CU11: -2.8 | CV11: 0 | CY11: 1.2 | CZ11: -0.1 | DA11: -0.9 | DB11: 0 | DC11: 0.7 | DD11: 1.9 | DE11: -0.8 | DF11: 2.3 | DG11: 0.6 | DI11: 0 | DJ11: 0 | DK11: -6.1 | DL11: -14.2 | DM11: 1.8 | DN11: 0.5 | DO11: 0.6 | DP11: 1.3 | DQ11: 0 | DR11: -0.3 | DS11: 0.4 | DT11: 0.4 | DV11: -3.5 | DW11: 0.4 | DX11: 2.5 | DY11: 2.7 | DZ11: 0.9 | EA11: 0.8 | EB11: 4 | EC11: 0 | ED11: -3.9 | EE11: -5.1 | EF11: 6.9 | EG11: 10.4 | EH11: 2.6 | EI11: 0 | EJ11: 1.5 | EK11: 0.2 | EL11: 0.2 | EM11: 0.2 | EO11: 0 | EP11: 0 | EQ11: -0.2 | ER11: 0.2 | ES11: 3.5 | ET11: 0 | EU11: 0 | EV11: 0.4 | EW11: 1.2 | EX11: 1.6 | EY11: 6.9 | EZ11: 10.4 | FA11: 0.8 | FB11: 1.5 | FC11: 2.6 | FD11: 2.1 | FE11: 3.5 | FF11: 105.1 | FH11: 2.39377 | FJ11: 0 | FK11: 1.708 | FL11: 1.2 | FN11: 0.24261 | FO11: 0 | FP11: 1 | FQ11: 6.54438
A12: 27/01/2025 | B12: 01:00 | C12: 0.2 | D12: 0.1 | E12: -0.01 | F12: 17.8 | G12: 11.7 | J12: -14.8 | K12: -2.9 | N12: -29.5 | O12: -28.9 | P12: -18.9 | Q12: 14.6 | R12: -15.8 | S12: -21.9 | T12: 88.3 | U12: 0 | Z12: -1.4 | AA12: 0.9 | AB12: 0 | AC12: -3.2 | AE12: 6.5 | AF12: 1.1 | AJ12: 13.3 | AK12: -1 | AO12: -0.9 | AP12: 45.8 | AQ12: 6.3 | AR12: 11.7 | AS12: -0.2 | AT12: 0.6 | AU12: 2.7 | AV12: 0.5 | AW12: 0 | AX12: -17.1 | AY12: -61.6 | AZ12: 9.9 | BA12: -1 | BB12: 0 | BC12: -4.7 | BD12: 3 | BE12: 1 | BF12: -0.1 | BG12: -6 | BH12: 0 | BK12: 2.7 | BO12: 12.5 | BP12: 0 | BQ12: 0 | BS12: 0 | BY12: -11.2 | CB12: 19 | CC12: 29.4 | CD12: -0.4 | CE12: 3.6 | CF12: 0 | CG12: 0 | CJ12: -1.4 | CK12: -0.8 | CL12: -48 | CU12: -3.5 | CV12: 0 | CY12: 1.2 | CZ12: 0 | DA12: -0.9 | DB12: 0.2 | DC12: 0.8 | DD12: 1.8 | DE12: -0.7 | DF12: 2.2 | DG12: 0.6 | DI12: 0 | DJ12: 0 | DK12: -6.1 | DL12: -14.6 | DM12: 1.8 | DN12: 0.5 | DO12: 0.6 | DP12: 1.3 | DQ12: 0 | DR12: 0 | DS12: 0.3 | DT12: 0.4 | DV12: -4.3 | DW12: 0.4 | DX12: 2 | DY12: 2.9 | DZ12: 0.9 | EA12: 0.8 | EB12: 4 | EC12: 0 | ED12: -1.6 | EE12: -3.9 | EF12: 6.9 | EG12: 9.6 | EH12: 2.6 | EI12: 0 | EJ12: 1.4 | EK12: 0.2 | EL12: 0.2 | EM12: 0.2 | EO12: 0 | EP12: 0 | EQ12: -0.2 | ER12: -0.5 | ES12: 3.6 | ET12: 0 | EU12: 0 | EV12: 0.4 | EW12: 1.2 | EX12: 1.7 | EY12: 6.9 | EZ12: 9.6 | FA12: 0.8 | FB12: 1.3 | FC12: 1.9 | FD12: 1.7 | FE12: 3.8 | FF12: 51.89 | FH12: 2.37028 | FJ12: 0 | FK12: 1.39 | FL12: 1.2 | FN12: 0.25747 | FO12: -0.1 | FP12: 1.1 | FQ12: 6.21775
A13: 27/01/2025 | B13: 01:30 | C13: 0.2 | D13: 0.1 | E13: 0 | F13: 15.7 | G13: 10.8 | J13: -16.7 | K13: -2.9 | N13: -30.3 | O13: -30.2 | P13: -18.9 | Q13: 14.5 | R13: -16.4 | S13: -22.5 | T13: 88.9 | U13: 0.1 | Z13: -1.3 | AA13: 1.5 | AB13: 0 | AC13: -3.2 | AE13: 6.1 | AF13: 1 | AJ13: 13.7 | AK13: 9.9 | AO13: -0.9 | AP13: 47.2 | AQ13: 6 | AR13: 11 | AS13: 0.1 | AT13: 0.4 | AU13: 2.7 | AV13: 0.7 | AW13: 0 | AX13: -17.2 | AY13: -61.8 | AZ13: 11.7 | BA13: -1 | BB13: 0 | BC13: -3.6 | BD13: 3.8 | BE13: 1 | BF13: -0.1 | BG13: -5.7 | BH13: 0 | BK13: 2.2 | BO13: 12.2 | BP13: 0 | BQ13: 0 | BS13: 0 | BY13: -6.7 | CB13: 14.7 | CC13: 27.5 | CD13: -0.4 | CE13: 3.7 | CF13: 0 | CG13: 0 | CJ13: -2.1 | CK13: -1.4 | CL13: -49 | CU13: -4.2 | CV13: 0 | CY13: 1.2 | CZ13: -0.1 | DA13: -0.3 | DB13: 0.1 | DC13: 0.7 | DD13: 1.8 | DE13: -0.8 | DF13: 1.9 | DG13: 0.6 | DI13: 0 | DJ13: 0 | DK13: -5.9 | DL13: -14.4 | DM13: 1.8 | DN13: 0.5 | DO13: 0.6 | DP13: 1.3 | DQ13: 0 | DR13: 0 | DS13: 0.3 | DT13: 0.4 | DV13: -4.3 | DW13: 0.6 | DX13: 1.9 | DY13: 2.9 | DZ13: 1.1 | EA13: 0.8 | EB13: 4 | EC13: 0 | ED13: -4.5 | EE13: -5.6 | EF13: 6.9 | EG13: 9.5 | EH13: 2.6 | EI13: 0 | EJ13: 1.4 | EK13: 0.2 | EL13: 0.2 | EM13: 0.2 | EO13: 0 | EP13: 0 | EQ13: -0.2 | ER13: -1.1 | ES13: 3.5 | ET13: 0 | EU13: 0 | EV13: 0.4 | EW13: 1.4 | EX13: 1.5 | EY13: 6.9 | EZ13: 9.5 | FA13: 0.9 | FB13: 1.2 | FC13: 2.8 | FD13: 1.4 | FE13: 3.4 | FF13: 50.1 | FH13: 2.3757 | FJ13: 0 | FK13: 1.56 | FL13: 1.1 | FN13: 0.21141 | FO13: -0.3 | FP13: 1 | FQ13: 5.94711
A14: 27/01/2025 | B14: 02:00 | C14: 0.2 | D14: 0.1 | E14: 0 | F14: 20.4 | G14: 11.2 | J14: -15.9 | K14: 9.2 | N14: -28.1 | O14: -30.9 | P14: -20.1 | Q14: 16.9 | R14: -14.3 | S14: -21.7 | T14: 91.2 | U14: 0 | Z14: -0.5 | AA14: 1.2 | AB14: 0 | AC14: -3.2 | AE14: 6.9 | AF14: 1.1 | AJ14: 13.2 | AK14: 6.6 | AO14: -0.8 | AP14: 48.1 | AQ14: 6 | AR14: 11.5 | AS14: 0.1 | AT14: 0.6 | AU14: 2.7 | AV14: 0.8 | AW14: 0 | AX14: -16.2 | AY14: -56.1 | AZ14: 11 | BA14: -1 | BB14: 0 | BC14: -4.5 | BD14: 3.9 | BE14: 1 | BF14: -0.1 | BG14: -5.9 | BH14: 0 | BK14: 2.8 | BO14: 14.4 | BP14: 0 | BQ14: 0 | BS14: 0 | BY14: -7.3 | CB14: 14.7 | CC14: 28.4 | CD14: -0.1 | CE14: 4.5 | CF14: 0 | CG14: 0 | CJ14: -1.8 | CK14: -1.2 | CL14: -49.2 | CU14: -4.2 | CV14: 0 | CY14: 1.2 | CZ14: -0.1 | DA14: -0.3 | DB14: 0 | DC14: 0.6 | DD14: 1.8 | DE14: -0.5 | DF14: 2 | DG14: 0 | DI14: 0 | DJ14: 0 | DK14: -5.6 | DL14: -13.6 | DM14: 1.8 | DN14: 0.5 | DO14: 0.6 | DP14: 1.3 | DQ14: 0 | DR14: 0.1 | DS14: 0.3 | DT14: 0.4 | DV14: -4.3 | DW14: 0.8 | DX14: 1.8 | DY14: 2.8 | DZ14: 1.1 | EA14: 0.8 | EB14: 4 | EC14: 0 | ED14: -3.8 | EE14: -4.7 | EF14: 6.9 | EG14: 9.7 | EH14: 2.6 | EI14: -0.1 | EJ14: 1.5 | EK14: 0.2 | EL14: 0.2 | EM14: 0.2 | EO14: 0 | EP14: 0 | EQ14: -0.2 | ER14: -0.3 | ES14: 3.6 | ET14: 0 | EU14: 0 | EV14: 0.4 | EW14: 1.4 | EX14: 1.5 | EY14: 6.9 | EZ14: 9.7 | FA14: 0.9 | FB14: 1.1 | FC14: 3 | FD14: 1.1 | FE14: 3.8 | FF14: 88.7 | FH14: 2.37865 | FJ14: 0 | FK14: 1.706 | FL14: 1.1 | FN14: 0.22821 | FO14: -0.2 | FP14: 1 | FQ14: 6.21286
A15: 27/01/2025 | B15: 02:30 | C15: 0.2 | D15: 0.1 | E15: -0.2 | F15: 5.4 | G15: 8.8 | J15: -16.3 | K15: -1.3 | N15: -33.1 | O15: -34.2 | P15: -23.4 | Q15: 12.2 | R15: -18.7 | S15: -24.1 | T15: 81.1 | U15: 0 | Z15: -0.1 | AA15: 0.8 | AB15: 0 | AC15: -3.2 | AE15: 6.7 | AF15: 1.1 | AJ15: 13.2 | AK15: 5.5 | AO15: -1 | AP15: 24 | AQ15: 4.8 | AR15: 11.4 | AS15: -0.3 | AT15: 0.4 | AU15: 2.7 | AV15: 0.9 | AW15: 0 | AX15: -20.9 | AY15: -60.7 | AZ15: 8.5 | BA15: -1.1 | BB15: 0 | BC15: -5.5 | BD15: 3.2 | BE15: 1 | BF15: -0.1 | BG15: -5.5 | BH15: 0 | BK15: 2.3 | BO15: 4.2 | BP15: 0 | BQ15: 0 | BS15: 0 | BY15: -8.4 | CB15: 14.7 | CC15: 28.9 | CD15: -0.1 | CE15: 3.9 | CF15: -1.9 | CG15: 0 | CJ15: -6.5 | CK15: -5.8 | CL15: -55.6 | CU15: -3.5 | CV15: 0 | CY15: 1.3 | CZ15: 0 | DA15: -0.2 | DB15: 0 | DC15: 0.5 | DD15: 1.8 | DE15: 0 | DF15: 2.1 | DG15: 0 | DI15: 0 | DJ15: 0 | DK15: -6.2 | DL15: -15.2 | DM15: 1.8 | DN15: 0.5 | DO15: 0.6 | DP15: 1.3 | DQ15: 0 | DR15: 0.1 | DS15: 0.3 | DT15: 0.4 | DV15: -4.3 | DW15: 0.6 | DX15: 1.8 | DY15: 2.7 | DZ15: 0.9 | EA15: 0.8 | EB15: 4 | EC15: 0 | ED15: -5.4 | EE15: -6.4 | EF15: 6.9 | EG15: 9.3 | EH15: 2.6 | EI15: -0.1 | EJ15: 1.5 | EK15: 0.2 | EL15: 0.2 | EM15: 0.2 | EO15: 0 | EP15: 0 | EQ15: -0.2 | ER15: -0.5 | ES15: 3.5 | ET15: 0 | EU15: 0 | EV15: 0.4 | EW15: 1.2 | EX15: 1.5 | EY15: 6.9 | EZ15: 9.3 | FA15: 0.9 | FB15: 1.7 | FC15: 2 | FD15: 1.1 | FE15: 4 | FF15: -49.1 | FH15: 2.06448 | FJ15: 0 | FK15: 1.806 | FL15: 1.1 | FN15: 0.25728 | FO15: -0.5 | FP15: 1 | FQ15: 5.72776
A16: 27/01/2025 | B16: 03:00 | C16: 0.2 | D16: 0.1 | E16: -0.2 | F16: 16.3 | G16: 11.5 | J16: -18.3 | K16: -5 | N16: -34.1 | O16: -29 | P16: -17.5 | Q16: 12.4 | R16: -18.8 | S16: -24.7 | T16: 89.1 | U16: 0.1 | Z16: -2.4 | AA16: 1.1 | AB16: 0 | AC16: -3.2 | AE16: 6.5 | AF16: 1.2 | AJ16: 12.6 | AK16: 4.7 | AO16: -1 | AP16: 23.1 | AQ16: 5.3 | AR16: 9.8 | AS16: 0.2 | AT16: 0.7 | AU16: 2.7 | AV16: 1 | AW16: 0 | AX16: -20.1 | AY16: -59.9 | AZ16: 7.1 | BA16: -1 | BB16: 0.1 | BC16: -3.5 | BD16: 3.3 | BE16: 1 | BF16: -0.1 | BG16: -4 | BH16: 0 | BK16: 1.3 | BO16: 10.5 | BP16: 0 | BQ16: 0 | BS16: 0 | BY16: -5.8 | CB16: 11.1 | CC16: 28.3 | CD16: -0.7 | CE16: 3.7 | CF16: -1.9 | CG16: 0 | CJ16: -7.2 | CK16: -6.8 | CL16: -46.1 | CU16: -3.5 | CV16: 0 | CY16: 1.2 | CZ16: 0 | DA16: -0.2 | DB16: 0 | DC16: 0.7 | DD16: 1.8 | DE16: -0.7 | DF16: 2.3 | DG16: 0 | DI16: 0 | DJ16: 0 | DK16: -5.8 | DL16: -14.5 | DM16: 1.8 | DN16: 0.5 | DO16: 0.6 | DP16: 1.3 | DQ16: 0 | DR16: 0 | DS16: 0.3 | DT16: 0.4 | DV16: -4.2 | DW16: 0.7 | DX16: 1.8 | DY16: 2.7 | DZ16: 0.9 | EA16: 0.8 | EB16: 4 | EC16: 0 | ED16: -2.3 | EE16: -3.5 | EF16: 6.9 | EG16: 9.1 | EH16: 2.6 | EI16: -0.1 | EJ16: 1.6 | EK16: 0.2 | EL16: 0.2 | EM16: 0.2 | EO16: 0 | EP16: 0 | EQ16: -0.2 | ER16: 0 | ES16: 3.5 | ET16: 0 | EU16: 0 | EV16: 0.4 | EW16: 1.2 | EX16: 1.6 | EY16: 6.9 | EZ16: 9.1 | FA16: 0.9 | FB16: 1.5 | FC16: 2.5 | FD16: 0.9 | FE16: 3.5 | FF16: -6.7 | FH16: 2.07601 | FJ16: 0 | FK16: 1.732 | FL16: 1.1 | FN16: 0.20958 | FO16: -0.5 | FP16: 0.9 | FQ16: 5.51759
A17: 27/01/2025 | B17: 03:30 | C17: 0.2 | D17: 0.1 | E17: -0.1 | F17: 14.4 | G17: 10.8 | J17: -17.2 | K17: 9.6 | N17: -32.3 | O17: -36.1 | P17: -25 | Q17: 12 | R17: -17.9 | S17: -24.2 | T17: 91.3 | U17: 0.1 | Z17: 2.5 | AA17: 0.5 | AB17: 0 | AC17: -3.2 | AE17: 6.9 | AF17: 1.3 | AJ17: 12.9 | AK17: 1.6 | AO17: -0.9 | AP17: 49.4 | AQ17: 6.4 | AR17: 11.1 | AS17: -0.1 | AT17: 0.7 | AU17: 2.7 | AV17: 0.7 | AW17: 0 | AX17: -18.6 | AY17: -58.5 | AZ17: 9.6 | BA17: -1 | BB17: 0.1 | BC17: -4.7 | BD17: 3.1 | BE17: 1 | BF17: -0.1 | BG17: -6.6 | BH17: 0 | BK17: 2.8 | BO17: 14.9 | BP17: 0 | BQ17: 0 | BS17: 0 | BY17: -7.1 | CB17: 11.1 | CC17: 27.5 | CD17: -0.5 | CE17: 3.8 | CF17: -2.1 | CG17: 0 | CJ17: -6 | CK17: -5.4 | CL17: -43.8 | CU17: -3.7 | CV17: 0 | CY17: 1.2 | CZ17: -0.1 | DA17: -0.3 | DB17: 0 | DC17: 0.7 | DD17: 2 | DE17: -0.5 | DF17: 2.3 | DG17: 0 | DI17: 0 | DJ17: 0 | DK17: -5.7 | DL17: -14.2 | DM17: 1.8 | DN17: 0.5 | DO17: 0.6 | DP17: 1.3 | DQ17: 0 | DR17: 0.3 | DS17: 0.3 | DT17: 0.4 | DV17: -4.3 | DW17: 0.5 | DX17: 1.8 | DY17: 2.8 | DZ17: 0.9 | EA17: 0.8 | EB17: 4 | EC17: 0 | ED17: -5.2 | EE17: -6.6 | EF17: 6.9 | EG17: 10.1 | EH17: 2.6 | EI17: -0.1 | EJ17: 1.6 | EK17: 0.2 | EL17: 0.2 | EM17: 0.2 | EO17: 0 | EP17: 0 | EQ17: -0.2 | ER17: 0.3 | ES17: 3.5 | ET17: 0 | EU17: 0 | EV17: 0.4 | EW17: 1.2 | EX17: 1.6 | EY17: 6.9 | EZ17: 10.1 | FA17: 0.9 | FB17: 1.6 | FC17: 2.7 | FD17: 1.3 | FE17: 3.8 | FF17: 35.1 | FH17: 2.33072 | FJ17: -0.155 | FK17: 1.694 | FL17: 1.1 | FN17: 0.08161 | FO17: -0.2 | FP17: 1.1 | FQ17: 5.95133
A18: 27/01/2025 | B18: 04:00 | C18: 0.2 | D18: 0.1 | E18: -0.2 | F18: 1.8 | G18: 8.7 | J18: -15.9 | K18: 15.2 | N18: -37 | O18: -39.9 | P18: -29.9 | Q18: 6.8 | R18: -20.3 | S18: -24.6 | T18: 84 | U18: 0 | Z18: -0.2 | AA18: 1 | AB18: 0 | AC18: -3.2 | AE18: 4.2 | AF18: 1.2 | AJ18: 11.4 | AK18: 2.2 | AO18: -0.9 | AP18: 48.8 | AQ18: 6.4 | AR18: 12.4 | AS18: 0.2 | AT18: 0.7 | AU18: 2.7 | AV18: 0.8 | AW18: 0 | AX18: -22.2 | AY18: -61.6 | AZ18: 5.2 | BA18: -1 | BB18: 0.1 | BC18: -5.1 | BD18: 2.9 | BE18: 1 | BF18: -0.1 | BG18: -7.4 | BH18: 0 | BK18: 2.7 | BO18: 11.6 | BP18: 0 | BQ18: 0 | BS18: 0 | BY18: -8.4 | CB18: 10.6 | CC18: 29.2 | CD18: 0.2 | CE18: 3.6 | CF18: -2 | CG18: 0 | CJ18: -8.5 | CK18: -7.8 | CL18: -47.6 | CU18: -3.1 | CV18: 0 | CY18: 1.3 | CZ18: -0.1 | DA18: -0.3 | DB18: 0 | DC18: 0.7 | DD18: 1.8 | DE18: -0.7 | DF18: 2.3 | DG18: 0 | DI18: 0 | DJ18: 0 | DK18: -5.6 | DL18: -14.4 | DM18: 1.8 | DN18: 0.5 | DO18: 0.6 | DP18: 1.3 | DQ18: 0 | DR18: 0 | DS18: 0.3 | DT18: 0.4 | DV18: -4.3 | DW18: 0.8 | DX18: 1.8 | DY18: 2.7 | DZ18: 0.9 | EA18: 0.8 | EB18: 4 | EC18: 0 | ED18: -6.6 | EE18: -8.4 | EF18: 6.9 | EG18: 9.7 | EH18: 2.6 | EI18: -0.1 | EJ18: 1.5 | EK18: 0.2 | EL18: 0.2 | EM18: 0.2 | EO18: 0 | EP18: 0 | EQ18: -0.2 | ER18: 1.1 | ES18: 3.5 | ET18: 0 | EU18: 0 | EV18: 0.4 | EW18: 1.2 | EX18: 1.6 | EY18: 6.9 | EZ18: 9.7 | FA18: 0.8 | FB18: 1.6 | FC18: 2.1 | FD18: 1.7 | FE18: 3.3 | FF18: -34.5 | FH18: 2.34677 | FJ18: -0.692 | FK18: 1.784 | FL18: 1.1 | FN18: 0.09701 | FO18: -0.2 | FP18: 1.1 | FQ18: 5.53578
A19: 27/01/2025 | B19: 04:30 | C19: 0.2 | D19: 0.1 | E19: -0.2 | F19: 14.6 | G19: 8.8 | J19: -13 | K19: 3.5 | N19: -31.6 | O19: -32.7 | P19: -23.9 | Q19: 11.5 | R19: -19.9 | S19: -24.4 | T19: 76.9 | U19: 0 | Z19: 4.5 | AA19: 1.4 | AB19: 0 | AC19: -3.2 | AE19: 4.1 | AF19: 1.6 | AJ19: 12.2 | AK19: 13 | AO19: -1.1 | AP19: 14.1 | AQ19: 5.2 | AR19: 14.6 | AS19: -0.6 | AT19: 0.1 | AU19: 2.7 | AV19: 0.6 | AW19: 0 | AX19: -23.5 | AY19: -57.9 | AZ19: 7.3 | BA19: -1.1 | BB19: -0.1 | BC19: -6.4 | BD19: 4.1 | BE19: 1 | BF19: -0.1 | BG19: -14.1 | BH19: 0 | BK19: 3.7 | BO19: 1.7 | BP19: 0 | BQ19: 0 | BS19: 0 | BY19: -11 | CB19: 7.9 | CC19: 31.5 | CD19: 1.2 | CE19: 3.5 | CF19: -2.2 | CG19: 0 | CJ19: -8.9 | CK19: -8.4 | CL19: -48.5 | CU19: -2.5 | CV19: 0 | CY19: 1.2 | CZ19: -0.1 | DA19: -0.3 | DB19: 0.2 | DC19: 0.6 | DD19: 1.7 | DE19: -0.4 | DF19: 2.4 | DG19: 0 | DI19: 0 | DJ19: 0 | DK19: -5.8 | DL19: -14.1 | DM19: 1.8 | DN19: 0.5 | DO19: 0.6 | DP19: 1.3 | DQ19: 0 | DR19: 0.2 | DS19: 0.3 | DT19: 0.4 | DV19: -4.2 | DW19: 0.4 | DX19: 1.8 | DY19: 2.7 | DZ19: 0.9 | EA19: 0.8 | EB19: 4 | EC19: 0 | ED19: -4.3 | EE19: -5.5 | EF19: 6.9 | EG19: 9.2 | EH19: 2.6 | EI19: -0.1 | EJ19: 1.6 | EK19: 0.2 | EL19: 0.2 | EM19: 0.2 | EO19: 0 | EP19: 0 | EQ19: -0.2 | ER19: 3.5 | ES19: 3.4 | ET19: 0 | EU19: 0 | EV19: 0.4 | EW19: 1.2 | EX19: 1.5 | EY19: 6.9 | EZ19: 9.2 | FA19: 0.8 | FB19: 1.5 | FC19: 3.1 | FD19: 1.6 | FE19: 3.4 | FF19: -39.5 | FH19: 2.01389 | FJ19: -0.42 | FK19: 1.77 | FL19: 1.1 | FN19: 0.12708 | FO19: -0.5 | FP19: 1 | FQ19: 5.09097
A20: 27/01/2025 | B20: 05:00 | C20: 0.2 | D20: 0.1 | E20: -0.1 | F20: 15.4 | G20: 10.7 | J20: -13 | K20: 9.6 | N20: -31.8 | O20: -27.5 | P20: -16.7 | Q20: 13.2 | R20: -17.4 | S20: -22.4 | T20: 84 | U20: 0 | Z20: 0.1 | AA20: 1.7 | AB20: 0 | AC20: -3.2 | AE20: 5.1 | AF20: 1.4 | AJ20: 13.1 | AK20: 13.2 | AO20: -1.1 | AP20: 11.2 | AQ20: 5.1 | AR20: 13.5 | AS20: -0.4 | AT20: -0.2 | AU20: 2.7 | AV20: 2.4 | AW20: 0 | AX20: -20.2 | AY20: -55 | AZ20: 6.7 | BA20: -1.3 | BB20: -0.1 | BC20: -2.8 | BD20: 6 | BE20: 1 | BF20: 0.1 | BG20: -8.3 | BH20: 0 | BK20: 5.3 | BO20: 2.8 | BP20: 0 | BQ20: 0 | BS20: 0 | BY20: -3.9 | CB20: 9.6 | CC20: 30.8 | CD20: -0.4 | CE20: 3.7 | CF20: -1.9 | CG20: 0 | CJ20: -6.5 | CK20: -5.8 | CL20: -44.8 | CU20: -2.7 | CV20: 0 | CY20: 1.2 | CZ20: 0 | DA20: -0.3 | DB20: 0 | DC20: 0.5 | DD20: 1.7 | DE20: -0.7 | DF20: 2.4 | DG20: 0 | DI20: 0 | DJ20: 0 | DK20: -6.1 | DL20: -14.4 | DM20: 1.8 | DN20: 0.5 | DO20: 0.6 | DP20: 1.3 | DQ20: 0.2 | DR20: 0.3 | DS20: 0.3 | DT20: 0.4 | DV20: -4.3 | DW20: 0.5 | DX20: 1.9 | DY20: 2.7 | DZ20: 1.1 | EA20: 0.8 | EB20: 4 | EC20: 0.4 | ED20: -4.8 | EE20: -6.4 | EF20: 6.9 | EG20: 10.3 | EH20: 2.6 | EI20: -0.1 | EJ20: 1.6 | EK20: 0.2 | EL20: 0.2 | EM20: 0.2 | EO20: 0 | EP20: 0 | EQ20: -0.2 | ER20: 3.4 | ES20: 3.3 | ET20: 0 | EU20: 0 | EV20: 0.4 | EW20: 1.3 | EX20: 1.6 | EY20: 6.9 | EZ20: 10.3 | FA20: 0.9 | FB20: 1.6 | FC20: 1.3 | FD20: 0 | FE20: 3.8 | FF20: 23.3 | FH20: 1.93223 | FJ20: -0.338 | FK20: 1.486 | FL20: 1.1 | FN20: 0.11442 | FO20: -0.1 | FP20: 0.9 | FQ20: 5.09465
A21: 27/01/2025 | B21: 05:30 | C21: 0.2 | D21: 0.1 | E21: -0.2 | F21: 24.6 | G21: 12.5 | J21: -14.4 | K21: 2.4 | N21: -30.2 | O21: -27.7 | P21: -16.3 | Q21: 14.2 | R21: -15.1 | S21: -21.9 | T21: 90 | U21: 0 | Z21: -0.3 | AA21: 1.6 | AB21: 0 | AC21: -3.2 | AE21: 5.1 | AF21: 1.4 | AJ21: 12.6 | AK21: 1.1 | AO21: -0.8 | AP21: 49.4 | AQ21: 6.2 | AR21: 11 | AS21: -0.5 | AT21: -0.2 | AU21: 2.7 | AV21: 1.3 | AW21: 0 | AX21: -17.2 | AY21: -52.2 | AZ21: 9.2 | BA21: -0.9 | BB21: 0 | BC21: -3.4 | BD21: 4.6 | BE21: 1 | BF21: -0.1 | BG21: -11.4 | BH21: 0 | BK21: 4.5 | BO21: 12.2 | BP21: 0 | BQ21: 0 | BS21: 0 | BY21: -4.3 | CB21: 10 | CC21: 28.7 | CD21: -0.4 | CE21: 4.7 | CF21: -2 | CG21: 0 | CJ21: -2.8 | CK21: -2.2 | CL21: -39 | CU21: -3.3 | CV21: 0 | CY21: 1.2 | CZ21: 0 | DA21: -0.2 | DB21: 0 | DC21: 0.7 | DD21: 1.8 | DE21: -0.7 | DF21: 2.4 | DG21: 0 | DI21: 0 | DJ21: 0 | DK21: -5.6 | DL21: -13.3 | DM21: 1.8 | DN21: 0.5 | DO21: 0.6 | DP21: 1.3 | DQ21: 0.8 | DR21: 0.3 | DS21: 0.3 | DT21: 0.4 | DV21: -4.1 | DW21: 0.7 | DX21: 1.8 | DY21: 2.7 | DZ21: 1.1 | EA21: 0.8 | EB21: 4 | EC21: 0.3 | ED21: -1.7 | EE21: -2.7 | EF21: 6.9 | EG21: 11.1 | EH21: 2.6 | EI21: -0.1 | EJ21: 1.5 | EK21: 0.2 | EL21: 0.2 | EM21: 0.2 | EO21: 0 | EP21: 0 | EQ21: -0.2 | ER21: 3.6 | ES21: 3.3 | ET21: 1.2 | EU21: 0 | EV21: 0.4 | EW21: 1.4 | EX21: 1.5 | EY21: 6.9 | EZ21: 11.1 | FA21: 0.8 | FB21: 1.8 | FC21: 3.3 | FD21: 0 | FE21: 3.1 | FF21: 97.3 | FH21: 2.20265 | FJ21: -0.233 | FK21: 1.282 | FL21: 1 | FN21: 0.09379 | FO21: 0.2 | FP21: 1 | FQ21: 5.54544
A22: 27/01/2025 | B22: 06:00 | C22: 0.2 | D22: 0 | E22: -0.01 | F22: 15.6 | G22: 10.8 | J22: -12.5 | K22: 17.5 | N22: -30.8 | O22: -29.5 | P22: -18.6 | Q22: 12.4 | R22: -14.9 | S22: -21.9 | T22: 89.4 | U22: 0.1 | Z22: -0.7 | AA22: 1.2 | AB22: 0 | AC22: -3.2 | AE22: 3.4 | AF22: 1.3 | AJ22: 12.6 | AK22: 7.1 | AO22: -0.9 | AP22: 47.4 | AQ22: 5.9 | AR22: 11.4 | AS22: 0.1 | AT22: 0.1 | AU22: 2.7 | AV22: 1.3 | AW22: 0 | AX22: -16 | AY22: -51.1 | AZ22: 9.2 | BA22: -1 | BB22: -0.1 | BC22: -1.8 | BD22: 5.5 | BE22: 1 | BF22: -0.1 | BG22: -10.1 | BH22: 0 | BK22: 6.6 | BO22: 11.5 | BP22: 0 | BQ22: 0 | BS22: 0 | BY22: -2.8 | CB22: 10.5 | CC22: 25.6 | CD22: -0.5 | CE22: 3.7 | CF22: -1.9 | CG22: 0 | CJ22: -2.3 | CK22: -1.6 | CL22: -38.1 | CU22: -3.3 | CV22: 0.1 | CY22: 1.2 | CZ22: -0.1 | DA22: -0.2 | DB22: 0.2 | DC22: 0.6 | DD22: 1.8 | DE22: 0.1 | DF22: 2.4 | DG22: 0.3 | DI22: 0 | DJ22: 0 | DK22: -6 | DL22: -14.3 | DM22: 1.8 | DN22: 0.5 | DO22: 0.6 | DP22: 1.3 | DQ22: 0.4 | DR22: 0.3 | DS22: 0.3 | DT22: 0.4 | DV22: -4.3 | DW22: 0.6 | DX22: 1.9 | DY22: 2.7 | DZ22: 1.3 | EA22: 0.8 | EB22: 4 | EC22: -0.1 | ED22: -5.3 | EE22: -5.9 | EF22: 7 | EG22: 12.3 | EH22: 2.6 | EI22: -0.1 | EJ22: 1.5 | EK22: 0.2 | EL22: 0.2 | EM22: 0.2 | EO22: 0 | EP22: 0.2 | EQ22: -0.2 | ER22: 2.5 | ES22: 3.3 | ET22: 1.1 | EU22: 0 | EV22: 0.4 | EW22: 1.6 | EX22: 1.7 | EY22: 7 | EZ22: 12.3 | FA22: 0.8 | FB22: 1 | FC22: 2.8 | FD22: 0 | FE22: 3.4 | FF22: 99.59 | FH22: 2.0914 | FJ22: -0.472 | FK22: 1.36 | FL22: 1 | FN22: 0.14535 | FO22: 0.7 | FP22: 1 | FQ22: 5.82475
... A58: 28/01/2025 | B58: 00:00 | C58: 0.2 | D58: 0.1 | E58: -0.3 | F58: 63.3 | G58: 30.5 | J58: -10.2 | K58: 15.2 | N58: -30.9 | O58: -32.2 | P58: 0.1 | Q58: 20.5 | R58: -10.3 | S58: -9.3 | T58: 57.6 | U58: 0.1 | Z58: 1.2 | AA58: 0.2 | AB58: 0 | AC58: -3.2 | AE58: 5.8 | AF58: 3.1 | AJ58: 4.9 | AK58: -6.6 | AO58: -1.4 | AP58: 45 | AQ58: 2.8 | AR58: 7.2 | AS58: 1.1 | AT58: 0.5 | AU58: 2.7 | AV58: 2 | AW58: -7.9 | AX58: -26.9 | AY58: -52.8 | AZ58: 12.9 | BA58: -1.3 | BB58: 0.3 | BC58: -1.8 | BD58: 3.5 | BE58: 1 | BF58: -0.1 | BG58: 11.5 | BH58: 3.4 | BK58: -0.6 | BO58: 12.2 | BP58: 0 | BQ58: -14.4 | BS58: 2.4 | BY58: 0.3 | CB58: 32.5 | CC58: 21.3 | CD58: 5.4 | CE58: 5.1 | CF58: -0.1 | CG58: 0 | CJ58: 11.6 | CK58: 11.8 | CL58: -30 | CU58: -4.9 | CV58: 0 | CY58: 1.3 | CZ58: 0 | DA58: -0.8 | DB58: -0.2 | DC58: 1.4 | DD58: 1.9 | DE58: -1.7 | DF58: 2.4 | DG58: 0 | DI58: 0 | DJ58: 0 | DK58: -1.6 | DL58: -3 | DM58: 1.2 | DN58: 0.6 | DO58: 0.6 | DP58: 1.1 | DQ58: 0 | DR58: 0.1 | DS58: 0.4 | DT58: 0.2 | DV58: -3.6 | DW58: 0 | DX58: 2.6 | DY58: 2.4 | DZ58: 1.1 | EA58: 0.8 | EB58: 4 | EC58: 0 | ED58: -5.5 | EE58: -11.8 | EF58: 0 | EG58: 8.3 | EH58: 2.6 | EI58: 0.2 | EJ58: 0.2 | EK58: 0.2 | EL58: 0.2 | EM58: 0.2 | EO58: 0 | EP58: 0 | EQ58: -0.2 | ER58: -7.1 | ES58: 3.2 | ET58: 0 | EU58: 0 | EV58: 0.8 | EW58: 1.4 | EX58: 1.7 | EY58: 0 | EZ58: 8.3 | FA58: 0.9 | FB58: 1.8 | FC58: 3 | FD58: 1.9 | FE58: 3.1 | FF58: 178.7 | FH58: 1.50541 | FJ58: -0.129 | FK58: 1.364 | FL58: 1.1 | FN58: 2.69607 | FO58: -0.6 | FP58: 1 | FQ58: 6.93648
A59: EJEC | C59: 4.65 | D59: 1.35 | E59: -3.11 | F59: 1230.85 | G59: 593.35 | H59: 0 | I59: 0 | J59: -225.55 | K59: 293.8 | L59: 0 | M59: 0 | N59: -174.15 | O59: 399.55 | P59: 402.95 | Q59: 941.8 | R59: 292.7 | S59: -140.1 | T59: 1779.7 | U59: 0.75 | V59: 0 | W59: 0 | X59: 0 | Y59: 0 | Z59: -28.8 | AA59: 25.4 | AB59: 4.9 | AC59: -76.8 | AD59: 0 | AE59: 276.55 | AF59: 52.2 | AG59: 0 | AH59: 0 | AI59: 0 | AJ59: 321.1 | AK59: 312.85 | AL59: 0 | AM59: 0 | AN59: 0 | AO59: -26.8 | AP59: 1114.9 | AQ59: 108.65 | AR59: 281 | AS59: 26.55 | AT59: 4.65 | AU59: 64.8 | AV59: 22.65 | AW59: 208.35 | AX59: -116.7 | AY59: -1113.3 | AZ59: 260.15 | BA59: -28.65 | BB59: 2.75 | BC59: -67.05 | BD59: 112.8 | BE59: 24 | BF59: 0.65 | BG59: 56.7 | BH59: 123 | BI59: 0 | BJ59: 0 | BK59: 69.2 | BL59: 0 | BM59: 0 | BN59: 0 | BO59: 284.2 | BP59: -22.75 | BQ59: -232.95 | BR59: 0 | BS59: -0.35 | BT59: 0 | BU59: 0 | BV59: 0 | BW59: 0 | BX59: 0 | BY59: -15.7 | BZ59: 0 | CA59: 0 | CB59: 1200.05 | CC59: 819.25 | CD59: 180.65 | CE59: 191.05 | CF59: 25.7 | CG59: -59.75 | CH59: 0 | CI59: 0 | CJ59: 928.35 | CK59: 939.6 | CL59: -116.6 | CM59: 0 | CN59: 0 | CO59: 0 | CP59: 0 | CQ59: 0 | CR59: 0 | CS59: 0 | CT59: 0 | CU59: -84.2 | CV59: 78.25 | CW59: 0 | CX59: 0 | CY59: 29.7 | CZ59: -1.6 | DA59: -15.9 | DB59: -2.6 | DC59: 25.55 | DD59: 43.15 | DE59: -1.8 | DF59: 54.6 | DG59: 9.15 | DH59: 0 | DI59: -5.9 | DJ59: -15.15 | DK59: -70.75 | DL59: -156.35 | DM59: 31.35 | DN59: 11.95 | DO59: 16 | DP59: 25.75 | DQ59: -27 | DR59: 1.15 | DS59: 9.6 | DT59: 9.5 | DU59: 0 | DV59: -92.05 | DW59: 12.15 | DX59: 58.3 | DY59: 72.75 | DZ59: 34.3 | EA59: 19.2 | EB59: 96 | EC59: 15.8 | ED59: -111.85 | EE59: -162.3 | EF59: 151.7 | EG59: 249.65 | EH59: 62.3 | EI59: -2.5 | EJ59: 37 | EK59: 4.8 | EL59: 4.8 | EM59: 4.8 | EN59: 0 | EO59: 16.3 | EP59: 99.05 | EQ59: -4.75 | ER59: 114.8 | ES59: 54.7 | ET59: -35.95 | EU59: 12.35 | EV59: 28.4 | EW59: 42.15 | EX59: 39.15 | EY59: 151.7 | EZ59: 249.65 | FA59: 20.2 | FB59: 40.05 | FC59: 60.1 | FD59: 11.95 | FE59: 84.35 | FF59: 12938.49 | FH59: 43.209275 | FI59: 0 | FJ59: -5.0915 | FK59: 37.008 | FL59: 26.65 | FM59: 0 | FN59: 38.40406 | FO59: 6.5 | FP59: 35.25 | FQ59: 181.92983

Sheet DEMANDA_AREAS
B3: lunes, 27 de Enero del 2025
B5: REPORTE DE LA DEMANDA POR ÁREAS Y SUBAREAS OPERATIVAS (MW)
B6: FECHA HORA | C6: DEMANDA | E6: AREA | H6: SUBAREAS
C7: INTERCAMBIOS INTERNACIONALES | D7: SEIN | E7: NORTE | F7: CENTRO | G7: SUR | H7: ELECTROANDES
B8: 00:30 | C8: 0 | D8: 6413 | E8: 961.757 | F8: 3778.223 | G8: 1673.02 | H8: 215.695
B9: 01:00 | C9: 0 | D9: 6262 | E9: 918.023 | F9: 3675.737 | G9: 1668.24 | H9: 218.062
B10: 01:30 | C10: 0 | D10: 6228.8 | E10: 909.327 | F10: 3658.163 | G10: 1661.31 | H10: 217.811
B11: 02:00 | C11: 0 | D11: 6192.2 | E11: 937.762 | F11: 3592.728 | G11: 1661.71 | H11: 219.901
B12: 02:30 | C12: 0 | D12: 6105.2 | E12: 893.112 | F12: 3549.618 | G12: 1662.47 | H12: 217.107
B13: 03:00 | C13: 0 | D13: 6109.6 | E13: 881.399 | F13: 3539.731 | G13: 1688.47 | H13: 217.497
B14: 03:30 | C14: 0 | D14: 6134 | E14: 926.26 | F14: 3510.92 | G14: 1696.82 | H14: 218.357
B15: 04:00 | C15: 0 | D15: 6072.1 | E15: 901.328 | F15: 3467.622 | G15: 1703.15 | H15: 216.64
B16: 04:30 | C16: 0 | D16: 6156.9 | E16: 894.066 | F16: 3538.984 | G16: 1723.85 | H16: 215.368
B17: 05:00 | C17: 0 | D17: 6202.8 | E17: 916.879 | F17: 3543.841 | G17: 1742.08 | H17: 215.568
B18: 05:30 | C18: 0 | D18: 6275.2 | E18: 906.058 | F18: 3626.482 | G18: 1742.66 | H18: 206.87
B19: 06:00 | C19: 0 | D19: 6329.2 | E19: 972.574 | F19: 3634.546 | G19: 1722.08 | H19: 194.445
... B59: ENERGÍA | C59: 0 | D59: 173627.2 | E59: 26307.345 | F59: 103914.73 | G59: 43405.125 | H59: 4838.6195
B61: LEYENDA:
D63: Potencia recibida del Ecuador
D64: Potencia entregada al Ecuador

Sheet DEMANDA_UL
B3: lunes, 27 de Enero del 2025
B5: POTENCIA DE LOS GRANDES USUARIOS LIBRES (MW)
B6: FECHA HORA | C6: GRANDES USUARIOS LIBRES DEL ÁREA NORTE | X6: GRANDES USUARIOS LIBRES DEL ÁREA CENTRO | BP6: GRANDES USUARIOS LIBRES DEL ÁREA SUR
C7: ARCA CONTINENTAL LINDLEY S.A. | D7: AUSTRAL GROUP S.A.A | E7: CEMENTOS PACASMAYO | F7: CORPORACIÓN PESQUERA INCA S.A.C. | G7: CREDITEX: CIA IND.TEXTIL CREDISA | H7: HIPERMERCADOS TOTTUS S.A | I7: INDUSTRIA TEXTIL PIURA | J7: MINERA BOROO MISQUICHILCA S.A. | K7: MINERA GOLD FIELDS | L7: MINERA HORIZONTE | M7: MINERA MARSA | N7: MINERA MISKY MAYO | O7: MINERA YANACOCHA | P7: OPEN PLAZA | Q7: PESQUERA DIAMANTE | R7: PETROPERU | S7: REAL PLAZA S.R.L. | T7: SIDER PERU | U7: SUPERMERCADOS PERUANOS S.A. | V7: TRUPAL S.A. | W7: UNIÓN DE CERVECERÍAS PERUANAS BACKUS Y JOHNSTON S. | X7: ACEROS AREQUIPA | Y7: ADMINISTRADORA JOCKEY PLAZA SHOPPING CENTER S.A. | Z7: ALICORP | AA7: ARCA CONTINENTAL LINDLEY S.A. | AB7: AUSTRAL GROUP S.A.A | AC7: COMPAÑIA MINERA CONDESTABLE | AD7: CORPORACIÓN PESQUERA INCA S.A.C. | AE7: CREDITEX: CIA IND.TEXTIL CREDISA | AF7: FUNDICION CHILCA S.A. | AG7: HIPERMERCADOS TOTTUS S.A | AH7: INMOBILIARIA KANPU S.A. | AI7: INMUEBLES PANAMERICANA S.A. | AJ7: KIMBERLY-CLARK PERU | AK7: LECHE GLORIA S.A. | AL7: MALL AVENTURA S.A. | AM7: MARCOBRE S.A.C. | AN7: MINERA ANTAMINA | AO7: MINERA ARES | AP7: MINERA BUENAVENTURA | AQ7: MINERA CHINALCO PERÚ S.A. | AR7: MINERA SHOUXIN PERU S.A. | AS7: MINERA VOLCAN | AT7: MINSUR | AU7: MOLYCOP-ADESUR | AV7: NEXA RESOURCES CAJAMARQUILLA S.A. | AW7: NEXA RESOURCES PERÚ S.A.A. | AX7: OPEN PLAZA | AY7: OPP FILM | AZ7: OWENS-ILLINOIS PERÚ S.A. | BA7: PAPELERA NACIONAL S.A. | BB7: PESQUERA DIAMANTE | BC7: QUIMPAC S.A. | BD7: REAL PLAZA S.R.L. | BE7: REFINERIA LA PAMPILLA S.A.A | BF7: SAGA FALABELLA | BG7: SAN MIGUEL INDUSTRIAS PET S.A. | BH7: SHOUGANG HIERRO PERU | BI7: SOFTYS PERU S.A.C. | BJ7: SUPERMERCADOS PERUANOS S.A. | BK7: TEJIDOS SAN JACINTO | BL7: TREN URBANO DE LIMA S.A. | BM7: TRUPAL S.A. | BN7: UNACEM PERU S.A. | BO7: UNIÓN DE CERVECERÍAS PERUANAS BACKUS Y JOHNSTON S. | BP7: ANGLO AMERICAN QUELLAVECO S.A. | BQ7: ARCA CONTINENTAL LINDLEY S.A. | BR7: CAL & CEMENTO SUR S.A. | BS7: COMPAÑIA MINERA ANTAPACCAY S.A. | BT7: COMPAÑÍA MINERA CHUNGAR SAC | BU7: COMPAÑIA MINERA SAN IGNACIO DE MOROCOCHA S.A.A. | BV7: EL BROCAL .S.A. | BW7: EMPRESA ADMINISTRADORA CERRO S.A.C. | BX7: EMPRESA MINERA LOS QUENUALES S.A.C. | BY7: HIPERMERCADOS TOTTUS S.A | BZ7: HUDBAY PERU S.A.C. | CA7: INDUSTRIA CACHIMAYO | CB7: MALL AVENTURA S.A. | CC7: MINERA ARES | CD7: MINERA BUENAVENTURA | CE7: MINERA CERRO VERDE | CF7: MINERA CORONA | CG7: MINERA LAS BAMBAS S.A. | CH7: MINERA VOLCAN | CI7: MINSUR | CJ7: MOLYCOP-ADESUR | CK7: NEXA RESOURCES PERÚ S.A.A. | CL7: OXIDOS DE PASCO S.A.C. | CM7: PESQUERA DIAMANTE | CN7: REAL PLAZA S.R.L. | CO7: SOBREANDES S.A.C. | CP7: SOUTHERN PERU CC | CQ7: SUPERMERCADOS PERUANOS S.A. | CR7: UNACEM PERU S.A. | CS7: UNIÓN DE CERVECERÍAS PERUANAS BACKUS Y JOHNSTON S. | CT7: YURA
B8: 00:30 | E8: 30.17464 | J8: 20.306 | K8: 27.72517 | L8: 12.016 | M8: 14.8536 | N8: 13.59 | O8: 33.85 | R8: 44.978 | T8: 32.5599 | V8: 0.6 | X8: 129.35524 | Z8: 2.74221 | AC8: 14.69 | AF8: 1.2 | AH8: 3.469 | AJ8: 5.33786 | AK8: 0 | AL8: 1.2753 | AM8: 47.5291 | AN8: 126.26721 | AO8: 26.02829 | AP8: 0.81 | AQ8: 152.8427 | AS8: 36.38008 | AT8: 28.83 | AV8: 192.71 | AW8: 36.43 | AY8: 2.94115 | BA8: 5.2 | BC8: 72.70386 | BE8: 19.5 | BI8: 19.06097 | BK8: 3.7819 | BM8: 6.633 | BN8: 55.4 | BP8: 145.04532 | BR8: 4.5963 | BS8: 127.16056 | BT8: 10.46922 | BV8: 35.4249 | BW8: 3.85819 | BZ8: 89.42205 | CB8: 0.3912 | CC8: 0.742 | CD8: 25.4311 | CE8: 362.79986 | CF8: 11.94 | CG8: 149.17983 | CH8: 18.30931 | CL8: 4.994 | CO8: 14.44744 | CP8: 287.44 | CR8: 35.719 | CS8: 1.09458 | CT8: 31.10744
B9: 01:00 | E9: 30.6875 | J9: 19.9497 | K9: 27.59132 | L9: 12.1335 | M9: 14.1577 | N9: 13.33 | O9: 33.754 | R9: 44.872 | T9: 39.975 | V9: 0.6 | X9: 104.26107 | Z9: 2.71756 | AC9: 14.85 | AF9: 1.2 | AH9: 3.6833 | AJ9: 5.33431 | AK9: 0 | AL9: 1.1577 | AM9: 46.79361 | AN9: 124.58893 | AO9: 26.66623 | AP9: 0.7 | AQ9: 151.2603 | AS9: 36.26429 | AT9: 28.92 | AV9: 193.6608 | AW9: 35.9126 | AY9: 2.91903 | BA9: 5.4 | BC9: 73.17825 | BE9: 19.5 | BI9: 18.89639 | BK9: 3.6961 | BM9: 6.709 | BN9: 55.67 | BP9: 143.79504 | BR9: 4.3667 | BS9: 129.47047 | BT9: 10.97362 | BV9: 34.6241 | BW9: 3.96348 | BZ9: 89.21763 | CB9: 0.3673 | CC9: 0.745 | CD9: 25.33295 | CE9: 362.28993 | CF9: 12.2414 | CG9: 147.11392 | CH9: 18.35642 | CL9: 4.96796 | CO9: 14.57211 | CP9: 287.59 | CR9: 37.201 | CS9: 1.28521 | CT9: 33.02345
B10: 01:30 | E10: 32.20106 | J10: 20.449 | K10: 27.43081 | L10: 12.251 | M10: 14.0069 | N10: 13.17 | O10: 34.1 | R10: 45.315 | T10: 50.8736 | V10: 0.6 | X10: 119.26559 | Z10: 2.57261 | AC10: 15.35 | AF10: 1.2 | AH10: 3.7907 | AJ10: 5.31128 | AK10: 0 | AL10: 1.0875 | AM10: 47.79917 | AN10: 122.07096 | AO10: 26.67547 | AP10: 0.64 | AQ10: 149.316 | AS10: 36.56488 | AT10: 28.32 | AV10: 195.766 | AW10: 35.7263 | AY10: 2.82969 | BA10: 5.3 | BC10: 72.38388 | BE10: 19.5 | BI10: 18.96548 | BK10: 3.71136 | BM10: 6.522 | BN10: 58.05 | BP10: 142.66247 | BR10: 4.3074 | BS10: 130.82244 | BT10: 10.88972 | BV10: 34.8416 | BW10: 4.0073 | BZ10: 89.14798 | CB10: 0.3616 | CC10: 0.732 | CD10: 25.66493 | CE10: 361.29402 | CF10: 11.9916 | CG10: 150.20506 | CH10: 18.19954 | CL10: 4.97311 | CO10: 14.40525 | CP10: 290.46 | CR10: 37.156 | CS10: 1.21946 | CT10: 33.09802
B11: 02:00 | E11: 33.27722 | J11: 20.2267 | K11: 27.40446 | L11: 12.821 | M11: 14.1682 | N11: 13.55 | O11: 34.024 | R11: 45.4 | T11: 47.4113 | V11: 0.6 | X11: 158.32766 | Z11: 2.50383 | AC11: 15.26 | AF11: 1.1 | AH11: 3.7801 | AJ11: 5.27359 | AK11: 0 | AL11: 1.0504 | AM11: 47.86708 | AN11: 124.87091 | AO11: 26.90431 | AP11: 0.44 | AQ11: 151.2002 | AS11: 37.42837 | AT11: 27.61 | AV11: 196.8335 | AW11: 36.2986 | AY11: 2.79236 | BA11: 5.3 | BC11: 72.32475 | BE11: 19.5 | BI11: 19.12978 | BK11: 3.68746 | BM11: 6.522 | BN11: 58.58 | BP11: 142.92422 | BR11: 4.2803 | BS11: 130.21622 | BT11: 11.57186 | BV11: 35.6079 | BW11: 3.7307 | BZ11: 89.8087 | CB11: 0.3502 | CC11: 0.74 | CD11: 26.56548 | CE11: 357.45705 | CF11: 11.8371 | CG11: 154.77865 | CH11: 18.11669 | CL11: 4.96583 | CO11: 14.19966 | CP11: 284.3 | CR11: 36.952 | CS11: 1.29559 | CT11: 32.76736
B12: 02:30 | E12: 34.2764 | J12: 20.8152 | K12: 27.46831 | L12: 13.079 | M12: 14.3535 | N12: 13.57 | O12: 33.834 | R12: 45.313 | T12: 45.2427 | V12: 0.6 | X12: 99.901 | Z12: 2.46372 | AC12: 15.57 | AF12: 0.8 | AH12: 2.2545 | AJ12: 5.22184 | AK12: 0 | AL12: 1.0605 | AM12: 46.94419 | AN12: 124.7102 | AO12: 27.03197 | AP12: 0.41 | AQ12: 149.7757 | AS12: 35.97286 | AT12: 28.39 | AV12: 195.9203 | AW12: 35.8842 | AY12: 2.80503 | BA12: 5.2 | BC12: 72.09785 | BE12: 19.5 | BI12: 18.93824 | BK12: 3.60646 | BM12: 6.522 | BN12: 54.84 | BP12: 142.82893 | BR12: 4.3445 | BS12: 127.24722 | BT12: 12.02153 | BV12: 33.8785 | BW12: 3.87202 | BZ12: 89.49577 | CB12: 0.3302 | CC12: 0.731 | CD12: 26.93755 | CE12: 376.75079 | CF12: 11.7325 | CG12: 153.60353 | CH12: 18.10612 | CL12: 4.64275 | CO12: 14.74833 | CP12: 283.16 | CR12: 36.017 | CS12: 1.56439 | CT12: 32.92321
B13: 03:00 | E13: 37.62227 | J13: 20.3583 | K13: 27.13846 | L13: 12.371 | M13: 14.0603 | N13: 13.69 | O13: 34.076 | R13: 45.324 | T13: 16.7494 | V13: 0.6 | X13: 104.79021 | Z13: 2.5162 | AC13: 15.02 | AF13: 0.8 | AH13: 1.7326 | AJ13: 4.81592 | AK13: 0 | AL13: 1.0192 | AM13: 47.53647 | AN13: 126.69802 | AO13: 27.32207 | AP13: 0.67 | AQ13: 151.2625 | AS13: 36.92855 | AT13: 28.34 | AV13: 195.0735 | AW13: 36.3761 | AY13: 2.84145 | BA13: 5.3 | BC13: 73.40343 | BE13: 19.5 | BI13: 19.01455 | BK13: 3.73547 | BM13: 6.522 | BN13: 52.29 | BP13: 142.16412 | BR13: 4.3297 | BS13: 131.55396 | BT13: 10.77409 | BV13: 33.1288 | BW13: 3.96593 | BZ13: 89.97471 | CB13: 0.3168 | CC13: 0.75 | CD13: 27.3842 | CE13: 389.2594 | CF13: 12.1017 | CG13: 157.95396 | CH13: 18.42753 | CL13: 4.63902 | CO13: 14.8088 | CP13: 288.86 | CR13: 35.316 | CS13: 1.74831 | CT13: 33.38143
B14: 03:30 | E14: 37.0935 | J14: 20.7963 | K14: 26.99918 | L14: 12.705 | M14: 14.1259 | N14: 13.58 | O14: 34.328 | R14: 44.779 | T14: 35.3529 | V14: 0.6 | X14: 116.69181 | Z14: 2.51794 | AC14: 15.19 | AF14: 1.4 | AH14: 2.8897 | AJ14: 5.05719 | AK14: 0 | AL14: 0.9925 | AM14: 45.52914 | AN14: 128.43371 | AO14: 27.64054 | AP14: 0.48 | AQ14: 150.94 | AS14: 37.34423 | AT14: 27.74 | AV14: 195.7012 | AW14: 35.832 | AY14: 2.93569 | BA14: 5.4 | BC14: 73.56987 | BE14: 19.5 | BI14: 19.13053 | BK14: 3.65723 | BM14: 6.522 | BN14: 48.89 | BP14: 142.84901 | BR14: 4.1989 | BS14: 131.60706 | BT14: 10.65668 | BV14: 33.5856 | BW14: 4.02736 | BZ14: 89.75152 | CB14: 0.3045 | CC14: 0.733 | CD14: 27.73391 | CE14: 405.43846 | CF14: 12.1502 | CG14: 154.1069 | CH14: 18.20088 | CL14: 4.64061 | CO14: 14.99227 | CP14: 280.52 | CR14: 34.938 | CS14: 1.806 | CT14: 33.47698
B15: 04:00 | E15: 36.79017 | J15: 21.0206 | K15: 26.3978 | L15: 12.619 | M15: 14.5473 | N15: 13.47 | O15: 34.104 | R15: 44.88 | T15: 35.7646 | V15: 0.6 | X15: 155.06458 | Z15: 2.47097 | AC15: 15.38 | AF15: 1.9 | AH15: 3.6716 | AJ15: 5.19055 | AK15: 0 | AL15: 0.9448 | AM15: 45.54454 | AN15: 128.12748 | AO15: 26.56862 | AP15: 0.18 | AQ15: 151.6559 | AS15: 37.2534 | AT15: 26.74 | AV15: 195.7709 | AW15: 35.7071 | AY15: 2.94575 | BA15: 5.4 | BC15: 73.55737 | BE15: 19.5 | BI15: 19.53856 | BK15: 3.68195 | BM15: 6.522 | BN15: 47.46 | BP15: 142.66421 | BR15: 4.2813 | BS15: 131.35233 | BT15: 11.36586 | BV15: 34.2112 | BW15: 3.88656 | BZ15: 90.54741 | CB15: 0.2954 | CC15: 0.773 | CD15: 27.03933 | CE15: 416.97675 | CF15: 11.9852 | CG15: 153.03906 | CH15: 18.16278 | CL15: 4.68283 | CO15: 14.85801 | CP15: 284.76 | CR15: 34.838 | CS15: 1.20549 | CT15: 33.74416
B16: 04:30 | E16: 36.80101 | J16: 20.6965 | K16: 26.47497 | L16: 12.372 | M16: 15.0642 | N16: 13.47 | O16: 33.438 | R16: 44.435 | T16: 46.4231 | V16: 0.6 | X16: 139.40489 | Z16: 2.41723 | AC16: 14.58 | AF16: 2.3 | AH16: 3.7806 | AJ16: 5.28152 | AK16: 0 | AL16: 0.9365 | AM16: 47.10919 | AN16: 122.67324 | AO16: 26.41404 | AP16: 1.65 | AQ16: 152.553 | AS16: 36.53637 | AT16: 26.18 | AV16: 196.0252 | AW16: 35.7452 | AY16: 2.92493 | BA16: 5.27 | BC16: 73.64699 | BE16: 19.5 | BI16: 19.89904 | BK16: 3.69846 | BM16: 6.522 | BN16: 48.9 | BP16: 142.86724 | BR16: 4.2514 | BS16: 130.22191 | BT16: 11.25279 | BV16: 34.3834 | BW16: 3.90366 | BZ16: 90.77169 | CB16: 0.2926 | CC16: 0.74 | CD16: 25.97062 | CE16: 423.16516 | CF16: 11.9263 | CG16: 156.90433 | CH16: 17.99163 | CL16: 4.86648 | CO16: 14.53189 | CP16: 291.96 | CR16: 34.976 | CS16: 1.12645 | CT16: 23.13972
B17: 05:00 | E17: 37.91295 | J17: 20.7043 | K17: 26.42229 | L17: 12.224 | M17: 14.5976 | N17: 13.33 | O17: 33.61 | R17: 45.066 | T17: 31.8736 | V17: 0.6 | X17: 144.70816 | Z17: 2.52446 | AC17: 14.23 | AF17: 2.3 | AH17: 3.3347 | AJ17: 5.03627 | AK17: 0 | AL17: 0.9394 | AM17: 46.00988 | AN17: 127.94729 | AO17: 26.21689 | AP17: 2.1 | AQ17: 154.6599 | AS17: 35.75875 | AT17: 25.58 | AV17: 195.5771 | AW17: 33.1485 | AY17: 2.87059 | BA17: 5.4 | BC17: 73.59827 | BE17: 19.5 | BI17: 19.81679 | BK17: 3.6415 | BM17: 6.522 | BN17: 49.44 | BP17: 144.07521 | BR17: 4.1823 | BS17: 128.78965 | BT17: 10.53822 | BV17: 34.5321 | BW17: 4.37541 | BZ17: 91.05686 | CB17: 0.2896 | CC17: 0.773 | CD17: 25.93726 | CE17: 432.2675 | CF17: 11.9365 | CG17: 160.04327 | CH17: 18.20301 | CL17: 4.81863 | CO17: 13.93322 | CP17: 291.58 | CR17: 34.016 | CS17: 1.2622 | CT17: 21.26493
B18: 05:30 | E18: 31.9798 | J18: 20.2225 | K18: 26.70363 | L18: 10.913 | M18: 14.4215 | N18: 13.33 | O18: 34.126 | R18: 45.061 | T18: 43.1083 | V18: 0.7 | X18: 117.99501 | Z18: 2.59555 | AC18: 15.05 | AF18: 2.9 | AH18: 1.9547 | AJ18: 5.08865 | AK18: 0 | AL18: 0.9479 | AM18: 46.32546 | AN18: 128.01323 | AO18: 26.42892 | AP18: 1.93 | AQ18: 152.498 | AS18: 33.94162 | AT18: 25.77 | AV18: 195.0284 | AW18: 34.6162 | AY18: 2.86996 | BA18: 5.3 | BC18: 73.38465 | BE18: 19.5 | BI18: 19.7378 | BK18: 3.79616 | BM18: 6.522 | BN18: 49.19 | BP18: 144.79004 | BR18: 4.2003 | BS18: 128.75041 | BT18: 10.63338 | BV18: 34.3187 | BW18: 3.85894 | BZ18: 90.67495 | CB18: 0.2881 | CC18: 0.686 | CD18: 25.25093 | CE18: 437.53009 | CF18: 11.7443 | CG18: 152.99284 | CH18: 17.61334 | CL18: 4.80202 | CO18: 13.24777 | CP18: 290.69 | CR18: 33.055 | CS18: 1.5257 | CT18: 21.14805
B19: 06:00 | E19: 34.81401 | J19: 20.5501 | K19: 26.79028 | L19: 10.481 | M19: 15.1741 | N19: 13.44 | O19: 33.968 | R19: 44.984 | T19: 48.3929 | V19: 0.7 | X19: 108.14391 | Z19: 2.6378 | AC19: 15.56 | AF19: 3.1 | AH19: 3.0111 | AJ19: 5.10208 | AK19: 0 | AL19: 0.9422 | AM19: 45.82323 | AN19: 126.3316 | AO19: 25.47914 | AP19: 1.54 | AQ19: 151.7899 | AS19: 34.15035 | AT19: 25.89 | AV19: 193.5587 | AW19: 33.2274 | AY19: 2.91411 | BA19: 5.4 | BC19: 72.76026 | BE19: 19.5 | BI19: 19.72114 | BK19: 3.83062 | BM19: 6.522 | BN19: 48.33 | BP19: 144.3476 | BR19: 4.0698 | BS19: 128.24587 | BT19: 10.04451 | BV19: 32.4341 | BW19: 3.65085 | BZ19: 90.96181 | CB19: 0.2822 | CC19: 0.769 | CD19: 23.58623 | CE19: 442.98702 | CF19: 11.0677 | CG19: 155.80986 | CH19: 18.07747 | CL19: 4.7468 | CO19: 12.91932 | CP19: 290.71 | CR19: 32.75 | CS19: 1.34203 | CT19: 20.86904
... B55: 00:00 | E55: 25.44639 | J55: 19.5007 | K55: 26.21364 | L55: 11.941 | M55: 14.4598 | N55: 13.21 | O55: 34.886 | R55: 45.042 | T55: 37.4737 | V55: 0.8 | X55: 90.61966 | Z55: 3.48173 | AC55: 14.37 | AF55: 3.8 | AH55: 8.0366 | AJ55: 5.27586 | AK55: 0 | AL55: 1.6939 | AM55: 45.33243 | AN55: 120.6621 | AO55: 27.7846 | AP55: 0.83 | AQ55: 155.2554 | AS55: 36.7637 | AT55: 28.66 | AV55: 123.4836 | AW55: 36.9449 | AY55: 2.92237 | BA55: 5.4 | BC55: 73.78243 | BE55: 20.4 | BI55: 19.29677 | BK55: 5.53009 | BM55: 6.648 | BN55: 52.11 | BP55: 145.91782 | BR55: 4.0513 | BS55: 129.9152 | BT55: 11.14658 | BV55: 34.8397 | BW55: 3.83695 | BZ55: 90.1351 | CB55: 0.4186 | CC55: 0.756 | CD55: 23.16958 | CE55: 440.26441 | CF55: 11.6371 | CG55: 150.62243 | CH55: 18.44557 | CL55: 4.78708 | CO55: 14.76715 | CP55: 287.83 | CR55: 30.878 | CS55: 2.13667 | CT55: 27.75216
B56: MWh | C56: 0 | D56: 0 | E56: 566.54179 | F56: 0 | G56: 0 | H56: 0 | I56: 0 | J56: 473.26945 | K56: 638.98068 | L56: 281.371 | M56: 322.10715 | N56: 317.495 | O56: 813.228 | P56: 0 | Q56: 0 | R56: 1082.26 | S56: 0 | T56: 812.1494 | U56: 0 | V56: 17.3 | W56: 0 | X56: 2450.5906 | Y56: 0 | Z56: 71.58776 | AA56: 0 | AB56: 0 | AC56: 368.43 | AD56: 0 | AE56: 0 | AF56: 55 | AG56: 0 | AH56: 73.19905 | AI56: 0 | AJ56: 118.96792 | AK56: 0 | AL56: 76.4515 | AM56: 1062.2269 | AN56: 2967.6861 | AO56: 630.06426 | AP56: 18.01 | AQ56: 3527.2269 | AR56: 0 | AS56: 843.907 | AT56: 671.11 | AU56: 0 | AV56: 3980.9751 | AW56: 847.70835 | AX56: 0 | AY56: 67.546465 | AZ56: 0 | BA56: 126.135 | BB56: 0 | BC56: 1579.4538 | BD56: 0 | BE56: 476.55 | BF56: 0 | BG56: 0 | BH56: 0 | BI56: 463.31218 | BJ56: 0 | BK56: 114.64235 | BL56: 0 | BM56: 155.38 | BN56: 850.44 | BO56: 0 | BP56: 3452.0953 | BQ56: 0 | BR56: 102.9648 | BS56: 3060.1917 | BT56: 243.26302 | BU56: 0 | BV56: 793.6907 | BW56: 93.30927 | BX56: 0 | BY56: 0 | BZ56: 2174.976 | CA56: 0 | CB56: 21.72385 | CC56: 17.828 | CD56: 592.95845 | CE56: 10389.996 | CF56: 271.3951 | CG56: 3553.2129 | CH56: 416.35377 | CI56: 0 | CJ56: 0 | CK56: 0 | CL56: 112.7242 | CM56: 0 | CN56: 0 | CO56: 327.92773 | CP56: 6835.33 | CQ56: 0 | CR56: 715.773 | CS56: 46.93824 | CT56: 544.67258
B59: Nota :
B60: Información proporcionada por la empresas
C62: DATOS ESTIMADOS
C64: SIN DATOS

Sheet TIPO_RECURSO
B3: lunes, 27 de Enero del 2025
B5: REPORTE POTENCIA GENERADA POR TIPO DE RECURSO
B6: HORA | C6: H. PASADA | D6: H. REGULACION | E6: GAS DE CAMISEA | F6: GAS DE MALACAS | G6: GAS DE AGUAYTÍA | H6: RESIDUAL R500 | I6: DIESEL | J6: NAFTA+GAS DE REFINERIA | K6: FLEXIGAS+GAS DE REFINERIA | L6: BAGAZO | M6: BIOGAS | N6: SOLAR | O6: EOLICA | P6: TOTAL | U6: EMPRESA | V6: CENTRAL | W6: HIDROELECTRICA DE PASADA | X6: HIDROELECTRICA DE REGULACION
B7: 00:30 | C7: 1191.4 | D7: 3405.1 | E7: 1284.4 | F7: 46.8 | J7: =DESPACHO_EJECUTADO!EZ11+DESPACHO_EJECUTADO!FA11 -> 54.6 | L7: 46 | M7: 12.4 | N7: 0 | O7: 372.3 | P7: =+SUM(C7:O7) -> 6413 | U7: ANDEAN POWER S.A.C. | V7: C.H. CARHUAC | W7: 355.5
B8: 01:00 | C8: 1194.1 | D8: 3267.9 | E8: 1285.4 | F8: 47 | J8: =DESPACHO_EJECUTADO!EZ12+DESPACHO_EJECUTADO!FA12 -> 54.3 | L8: 46.2 | M8: 12.4 | N8: 0 | O8: 354.7 | P8: =+SUM(C8:O8) -> 6262 | U8: ASOCIACIÓN SANTA LUCIA DE CHACAS | V8: C.H. HUALLIN | W8: 48
B9: 01:30 | C9: 1196.3 | D9: 3270 | E9: 1286.8 | F9: 46.8 | J9: =DESPACHO_EJECUTADO!EZ13+DESPACHO_EJECUTADO!FA13 -> 54.4 | L9: 45.6 | M9: 12.4 | N9: 0 | O9: 316.5 | P9: =+SUM(C9:O9) -> 6228.8 | U9: CELEPSA | V9: C.H. EL PLATANAL | X9: 5011.1
B10: 02:00 | C10: 1171.7 | D10: 3239.5 | E10: 1289.8 | F10: 46.9 | J10: =DESPACHO_EJECUTADO!EZ14+DESPACHO_EJECUTADO!FA14 -> 54.4 | L10: 45 | M10: 12.5 | N10: 0 | O10: 332.4 | P10: =+SUM(C10:O10) -> 6192.2 | U10: CELEPSA RENOVABLES S.R.L. | V10: C.H. MARAÑON | W10: 472.8
B11: 02:30 | C11: 1175.2 | D11: 3109.9 | E11: 1288.3 | F11: 46.7 | J11: =DESPACHO_EJECUTADO!EZ15+DESPACHO_EJECUTADO!FA15 -> 54.4 | L11: 45.5 | M11: 12.5 | N11: 0 | O11: 372.7 | P11: =+SUM(C11:O11) -> 6105.2 | U11: CENTRALES SANTA ROSA S.A.C. | V11: C.H. SANTA ROSA I | W11: 24.8
B12: 03:00 | C12: 1165.8 | D12: 3120.5 | E12: 1293.9 | F12: 47.3 | J12: =DESPACHO_EJECUTADO!EZ16+DESPACHO_EJECUTADO!FA16 -> 54.3 | L12: 46.4 | M12: 12.5 | N12: 0 | O12: 368.9 | P12: =+SUM(C12:O12) -> 6109.6 | V12: C.H. SANTA ROSA II | W12: 32
B13: 03:30 | C13: 1177 | D13: 3146.8 | E13: 1295.3 | F13: 36.5 | J13: =DESPACHO_EJECUTADO!EZ17+DESPACHO_EJECUTADO!FA17 -> 53.8 | L13: 44.8 | M13: 12.5 | N13: 0 | O13: 367.3 | P13: =+SUM(C13:O13) -> 6134 | U13: CHINANGO S.A.C. | V13: C.H. CHIMAY | X13: 3386.1
B14: 04:00 | C14: 1155.9 | D14: 3103.6 | E14: 1276.9 | F14: 24.1 | J14: =DESPACHO_EJECUTADO!EZ18+DESPACHO_EJECUTADO!FA18 -> 53.7 | L14: 47.1 | M14: 12.5 | N14: 0 | O14: 398.3 | P14: =+SUM(C14:O14) -> 6072.1 | V14: C.H. YANANGO | W14: 975.35
B15: 04:30 | C15: 1167 | D15: 3132.7 | E15: 1269.6 | F15: 24.2 | J15: =DESPACHO_EJECUTADO!EZ19+DESPACHO_EJECUTADO!FA19 -> 53.8 | L15: 47.4 | M15: 12.5 | N15: 0 | O15: 449.7 | P15: =+SUM(C15:O15) -> 6156.9 | U15: EGASA | V15: C.H. CHARCANI III | W15: 158.2
B16: 05:00 | C16: 1170.2 | D16: 3180.7 | E16: 1281.2 | F16: 24.7 | J16: =DESPACHO_EJECUTADO!EZ20+DESPACHO_EJECUTADO!FA20 -> 54 | L16: 31.5 | M16: 12.5 | N16: 0 | O16: 448 | P16: =+SUM(C16:O16) -> 6202.8 | V16: C.H. CHARCANI V | X16: 1519
B17: 05:30 | C17: 1178.8 | D17: 3253.9 | E17: 1285.4 | F17: 24.9 | J17: =DESPACHO_EJECUTADO!EZ21+DESPACHO_EJECUTADO!FA21 -> 53.5 | L17: 31.7 | M17: 12.5 | N17: 0.2 | O17: 434.3 | P17: =+SUM(C17:O17) -> 6275.2 | V17: C.H. CHARCANI VI | X17: 135.8
B18: 06:00 | C18: 1194.4 | D18: 3276.1 | E18: 1289.6 | F18: 24.9 | J18: =DESPACHO_EJECUTADO!EZ22+DESPACHO_EJECUTADO!FA22 -> 54.1 | L18: 33.4 | M18: 12.5 | N18: 28.2 | O18: 416 | P18: =+SUM(C18:O18) -> 6329.2 | U18: EGEJUNIN | V18: C.H. HUASAHUASI I | W18: 356.7
B19: 06:30 | C19: 1182.4 | D19: 3242.7 | E19: 1279.8 | F19: 24.6 | J19: =DESPACHO_EJECUTADO!EZ23+DESPACHO_EJECUTADO!FA23 -> 53.9 | L19: 32 | M19: 10.9 | N19: 59.4 | O19: 405.6 | P19: =+SUM(C19:O19) -> 6291.3 | V19: C.H. RUNATULLO II | W19: 478.9
B20: 07:00 | C20: 1198.9 | D20: 3367.9 | E20: 1317.6 | F20: 28 | J20: =DESPACHO_EJECUTADO!EZ24+DESPACHO_EJECUTADO!FA24 -> 54.4 | L20: 31 | M20: 10.9 | N20: 146.5 | O20: 357.4 | P20: =+SUM(C20:O20) -> 6512.6 | V20: C.H. RUNATULLO III | W20: 488.6
B21: 07:30 | C21: 1191.9 | D21: 3407.7 | E21: 1352.7 | F21: 46.6 | J21: =DESPACHO_EJECUTADO!EZ25+DESPACHO_EJECUTADO!FA25 -> 54.3 | L21: 30.7 | M21: 10.9 | N21: 293.3 | O21: 347.5 | P21: =+SUM(C21:O21) -> 6735.6 | V21: C.H. SANTA CRUZ I | W21: 217.45
B22: 08:00 | C22: 1191.8 | D22: 3407 | E22: 1473.2 | F22: 46.6 | J22: =DESPACHO_EJECUTADO!EZ26+DESPACHO_EJECUTADO!FA26 -> 54.3 | L22: 32 | M22: 10.9 | N22: 388.4 | O22: 348.1 | P22: =+SUM(C22:O22) -> 6952.3 | U22: EGEMSA | V22: C.H. MACHUPICCHU | W22: 3979.75
B23: 08:30 | C23: 1194.2 | D23: 3494.2 | E23: 1664.1 | F23: 46.8 | J23: =DESPACHO_EJECUTADO!EZ27+DESPACHO_EJECUTADO!FA27 -> 54.5 | L23: 31.8 | M23: 10.6 | N23: 386.1 | O23: 337.8 | P23: =+SUM(C23:O23) -> 7220.1 | U23: EGESUR | V23: C.H. ARICOTA I | X23: 183.55
B24: 09:00 | C24: 1202.9 | D24: 3425.7 | E24: 1838.5 | F24: 46.1 | J24: =DESPACHO_EJECUTADO!EZ28+DESPACHO_EJECUTADO!FA28 -> 54.3 | L24: 31.8 | M24: 10.6 | N24: 417.9 | O24: 336.9 | P24: =+SUM(C24:O24) -> 7364.7 | V24: C.H. ARICOTA II | X24: 62.7
B25: 09:30 | C25: 1206 | D25: 3604.8 | E25: 1934 | F25: 45.6 | J25: =DESPACHO_EJECUTADO!EZ29+DESPACHO_EJECUTADO!FA29 -> 54.8 | L25: 31.9 | M25: 10.5 | N25: 433.7 | O25: 372.3 | P25: =+SUM(C25:O25) -> 7693.6 | U25: ELECTRICA YANAPAMPA SAC | V25: C.H. YANAPAMPA | W25: 86.2
B26: 10:00 | C26: 1219 | D26: 3651.4 | E26: 1912.8 | F26: 45.5 | J26: =DESPACHO_EJECUTADO!EZ30+DESPACHO_EJECUTADO!FA30 -> 54.7 | L26: 31.9 | M26: 9.9 | N26: 445.5 | O26: 406 | P26: =+SUM(C26:O26) -> 7776.7 | U26: ELECTROPERU | V26: C.H. MANTARO | X26: 15500.3
B27: 10:30 | C27: 1197 | D27: 3591.9 | E27: 1979.6 | F27: 45.2 | J27: =DESPACHO_EJECUTADO!EZ31+DESPACHO_EJECUTADO!FA31 -> 54.9 | L27: 31.8 | M27: 9.4 | N27: 455.2 | O27: 499.4 | P27: =+SUM(C27:O27) -> 7864.4 | V27: C.H. RESTITUCION | W27: 5256.7
B28: 11:00 | C28: 1194.1 | D28: 3615.7 | E28: 2043 | F28: 44.6 | J28: =DESPACHO_EJECUTADO!EZ32+DESPACHO_EJECUTADO!FA32 -> 54.4 | L28: 31.6 | M28: 9.3 | N28: 460.7 | O28: 567.7 | P28: =+SUM(C28:O28) -> 8021.1 | U28: EMPRESA DE GENERACION ELECTRICA CANCHAYLLO SAC | V28: C.H. CANCHAYLLO | W28: 123.95
B29: 11:30 | C29: 1207 | D29: 3614.1 | E29: 2021.6 | F29: 45.3 | J29: =DESPACHO_EJECUTADO!EZ33+DESPACHO_EJECUTADO!FA33 -> 53.7 | L29: 30.4 | M29: 9.3 | N29: 449.4 | O29: 623.6 | P29: =+SUM(C29:O29) -> 8054.4 | U29: EMPRESA DE GENERACION ELECTRICA RIO BAÑOS S.A.C. | V29: C.H. RUCUY | W29: 478.5
B30: 12:00 | C30: 1208 | D30: 3638.8 | E30: 2026.4 | F30: 45.6 | J30: =DESPACHO_EJECUTADO!EZ34+DESPACHO_EJECUTADO!FA34 -> 54 | L30: 31.8 | M30: 9.3 | N30: 448.1 | O30: 627.4 | P30: =+SUM(C30:O30) -> 8089.4 | U30: EMPRESA DE GENERACION ELECTRICA SANTA ANA S.A.C. | V30: C.H. RENOVANDES H1 | W30: 485.15
B31: 12:30 | C31: 1208.7 | D31: 3573.2 | E31: 1999.1 | F31: 46 | J31: =DESPACHO_EJECUTADO!EZ35+DESPACHO_EJECUTADO!FA35 -> 54.4 | L31: 31.5 | M31: 9.3 | N31: 441.3 | O31: 623.3 | P31: =+SUM(C31:O31) -> 7986.8 | U31: EMPRESA DE GENERACION HUALLAGA | V31: C.H. CHAGLLA | X31: 10889.7
B32: 13:00 | C32: 1195.2 | D32: 3510.5 | E32: 2135.8 | F32: 45.7 | J32: =DESPACHO_EJECUTADO!EZ36+DESPACHO_EJECUTADO!FA36 -> 52.8 | L32: 30.3 | M32: 9.3 | N32: 375.6 | O32: 609.2 | P32: =+SUM(C32:O32) -> 7964.4 | V32: P.C.H. CHAGLLA | W32: 155.95
B33: 13:30 | C33: 1200.8 | D33: 3636.5 | E33: 1991.6 | F33: 45.4 | J33: =DESPACHO_EJECUTADO!EZ37+DESPACHO_EJECUTADO!FA37 -> 52.6 | L33: 29.4 | M33: 9.3 | N33: 330.6 | O33: 592.4 | P33: =+SUM(C33:O33) -> 7888.6 | U33: EMPRESA DE GENERACION HUANZA | V33: C.H. HUANZA | X33: 1219.6
B34: 14:00 | C34: 1210.6 | D34: 3679.5 | E34: 1980.8 | F34: 45.6 | J34: =DESPACHO_EJECUTADO!EZ38+DESPACHO_EJECUTADO!FA38 -> 51 | L34: 29.9 | M34: 9.3 | N34: 292.4 | O34: 636.9 | P34: =+SUM(C34:O34) -> 7936 | U34: EMPRESA ELECTRICA AGUA AZUL | V34: C.H. POTRERO | W34: 478.9
B35: 14:30 | C35: 1206 | D35: 3701.4 | E35: 2161.8 | F35: 45.6 | J35: =DESPACHO_EJECUTADO!EZ39+DESPACHO_EJECUTADO!FA39 -> 52.9 | L35: 30 | M35: 9.3 | N35: 213.9 | O35: 658.6 | P35: =+SUM(C35:O35) -> 8079.5 | U35: EMPRESA ELECTRICA RIO DOBLE | V35: C.H. LAS PIZARRAS | W35: 322.4
B36: 15:00 | C36: 1206.7 | D36: 3672.6 | E36: 2183.9 | F36: 46.1 | J36: =DESPACHO_EJECUTADO!EZ40+DESPACHO_EJECUTADO!FA40 -> 53.8 | L36: 29.2 | M36: 9.3 | N36: 193.7 | O36: 695.3 | P36: =+SUM(C36:O36) -> 8090.6 | U36: ENGIE | V36: C.H. QUITARACSA | X36: 2411.75
B37: 15:30 | C37: 1202.6 | D37: 3635.3 | E37: 2205.9 | F37: 45.7 | J37: =DESPACHO_EJECUTADO!EZ41+DESPACHO_EJECUTADO!FA41 -> 52.9 | L37: 26.7 | M37: 9.3 | N37: 183 | O37: 700.1 | P37: =+SUM(C37:O37) -> 8061.5 | V37: C.H. YUNCAN | X37: 3137.7
B38: 16:00 | C38: 1206.6 | D38: 3641.6 | E38: 2220.8 | F38: 46.2 | J38: =DESPACHO_EJECUTADO!EZ42+DESPACHO_EJECUTADO!FA42 -> 53.3 | L38: 30 | M38: 9.3 | N38: 101.1 | O38: 707.7 | P38: =+SUM(C38:O38) -> 8016.6 | U38: GENERACIÓN ANDINA S.A.C. | V38: C.H. 8 DE AGOSTO | W38: 503.85
B39: 16:30 | C39: 1208 | D39: 3605 | E39: 2180.7 | F39: 45.8 | J39: =DESPACHO_EJECUTADO!EZ43+DESPACHO_EJECUTADO!FA43 -> 53.3 | L39: 29.6 | M39: 9.3 | N39: 74.3 | O39: 720.6 | P39: =+SUM(C39:O39) -> 7926.6 | V39: C.H. EL CARMEN | W39: 197.95
B40: 17:00 | C40: 1168.2 | D40: 3363 | E40: 2142.6 | F40: 46.4 | J40: =DESPACHO_EJECUTADO!EZ44+DESPACHO_EJECUTADO!FA44 -> 53.6 | L40: 29.1 | M40: 9.3 | N40: 68.1 | O40: 729.4 | P40: =+SUM(C40:O40) -> 7609.7 | U40: GENERADORA DE ENERGÍA DEL PERÚ | V40: C.H. ÁNGEL I | W40: 480
B41: 17:30 | C41: 1187.6 | D41: 3464.9 | E41: 1952.7 | F41: 46.4 | J41: =DESPACHO_EJECUTADO!EZ45+DESPACHO_EJECUTADO!FA45 -> 54.2 | L41: 32.3 | M41: 9.3 | N41: 30.5 | O41: 729.2 | P41: =+SUM(C41:O41) -> 7507.1 | V41: C.H. ÁNGEL II | W41: 480
B42: 18:00 | C42: 1177.8 | D42: 3390.3 | E42: 1863.2 | F42: 46.6 | J42: =DESPACHO_EJECUTADO!EZ46+DESPACHO_EJECUTADO!FA46 -> 54.5 | L42: 30.9 | M42: 10 | N42: 10.7 | O42: 744.9 | P42: =+SUM(C42:O42) -> 7328.9 | V42: C.H. ÁNGEL III | W42: 479.65
B43: 18:30 | C43: 1191.9 | D43: 3421.8 | E43: 1878.6 | F43: 46.8 | J43: =DESPACHO_EJECUTADO!EZ47+DESPACHO_EJECUTADO!FA47 -> 53.8 | L43: 29.3 | M43: 10.1 | N43: 0 | O43: 720.1 | P43: =+SUM(C43:O43) -> 7352.4 | V43: C.H. LA JOYA | W43: 176.95
B44: 19:00 | C44: 1195.5 | D44: 3610.1 | E44: 2040.2 | F44: 47 | J44: =DESPACHO_EJECUTADO!EZ48+DESPACHO_EJECUTADO!FA48 -> 54.7 | L44: 30.8 | M44: 10.6 | N44: 0 | O44: 668.6 | P44: =+SUM(C44:O44) -> 7657.5 | U44: HIDROCAÑETE S.A. | V44: C.H. IMPERIAL | W44: 55.5
B45: 19:30 | C45: 1200.9 | D45: 3636.8 | E45: 2125.8 | F45: 47.1 | J45: =DESPACHO_EJECUTADO!EZ49+DESPACHO_EJECUTADO!FA49 -> 55.1 | L45: 31.4 | M45: 10.7 | N45: 0 | O45: 627.2 | P45: =+SUM(C45:O45) -> 7735 | U45: HIDROELECTRICA HUANCHOR S.A.C. | V45: C.H. HUANCHOR | W45: 440.75
B46: 20:00 | C46: 1201.6 | D46: 3667.8 | E46: 2151.2 | F46: 47.4 | J46: =DESPACHO_EJECUTADO!EZ50+DESPACHO_EJECUTADO!FA50 -> 55 | L46: 29.2 | M46: 9.4 | N46: 0 | O46: 563.5 | P46: =+SUM(C46:O46) -> 7725.1 | U46: HUAURA POWER GROUP S.A. | V46: C.H. YARUCAYA | W46: 451.2
B47: 20:30 | C47: 1200.4 | D47: 3718.9 | E47: 2105.8 | F47: 47.3 | J47: =DESPACHO_EJECUTADO!EZ51+DESPACHO_EJECUTADO!FA51 -> 54.3 | L47: 29.3 | M47: 10.4 | N47: 0 | O47: 531.6 | P47: =+SUM(C47:O47) -> 7698 | U47: INLAND ENERGY SAC | V47: C.H. SANTA TERESA | W47: 2177.6
B48: 21:00 | C48: 1201.2 | D48: 3715.5 | E48: 2135.3 | F48: 47.4 | J48: =DESPACHO_EJECUTADO!EZ52+DESPACHO_EJECUTADO!FA52 -> 54.6 | L48: 30.4 | M48: 10.8 | N48: 0 | O48: 483.7 | P48: =+SUM(C48:O48) -> 7678.9 | U48: INVERSIONES SHAQSHA S.A.C. | V48: C.H. PARIAC | W48: 102.8
B49: 21:30 | C49: 1200.5 | D49: 3692.3 | E49: 2079.1 | F49: 47.3 | J49: =DESPACHO_EJECUTADO!EZ53+DESPACHO_EJECUTADO!FA53 -> 53.3 | L49: 30.6 | M49: 10.8 | N49: 0 | O49: 469.1 | P49: =+SUM(C49:O49) -> 7583 | U49: KALLPA GENERACION S.A. | V49: C.H. CERRO DEL AGUILA | X49: 13382.55
B50: 22:00 | C50: 1191.3 | D50: 3654 | E50: 2034.8 | F50: 47.5 | J50: =DESPACHO_EJECUTADO!EZ54+DESPACHO_EJECUTADO!FA54 -> 46 | L50: 28.7 | M50: 10.8 | N50: 0 | O50: 486.1 | P50: =+SUM(C50:O50) -> 7499.2 | V50: M.C.H. CERRO DEL AGUILA | W50: 252.2
B51: 22:30 | C51: 1197.9 | D51: 3606.7 | E51: 2048.4 | F51: 47.3 | J51: =DESPACHO_EJECUTADO!EZ55+DESPACHO_EJECUTADO!FA55 -> 36.7 | L51: 32 | M51: 10.8 | N51: 0 | O51: 453.7 | P51: =+SUM(C51:O51) -> 7433.5 | U51: LA VIRGEN | V51: C.H. LA VIRGEN | X51: 1452.35
B52: 23:00 | C52: 1190.8 | D52: 3591.8 | E52: 2066.5 | F52: 47.7 | J52: =DESPACHO_EJECUTADO!EZ56+DESPACHO_EJECUTADO!FA56 -> 36.9 | L52: 33.3 | M52: 10.8 | N52: 0 | O52: 400.1 | P52: =+SUM(C52:O52) -> 7377.9 | U52: MAJA ENERGIA S.A.C. | V52: C.H. RONCADOR | W52: 86.9
B53: 23:30 | C53: 1191.4 | D53: 3550.9 | E53: 1920.9 | F53: 47.6 | J53: =DESPACHO_EJECUTADO!EZ57+DESPACHO_EJECUTADO!FA57 -> 36.8 | L53: 34.7 | M53: 10.8 | N53: 0 | O53: 367.8 | P53: =+SUM(C53:O53) -> 7160.9 | U53: ORAZUL ENERGY PERÚ | V53: C.H. CAÑA BRAVA | W53: 123.8
B54: 00:00 | C54: 1202.5 | D54: 3405.2 | E54: 1791.4 | F54: 47.2 | J54: =DESPACHO_EJECUTADO!EZ58+DESPACHO_EJECUTADO!FA58 -> 37 | L54: 35.1 | M54: 10.8 | N54: 0 | O54: 370.3 | P54: =+SUM(C54:O54) -> 6899.5 | V54: C.H. CAÑON DEL PATO | X54: 5712.2
B55: TOTAL MWh | C55: =+SUM(C7:C54)/2 -> 28637.85 | D55: =+SUM(D7:D54)/2 -> 83357.1 | E55: =+SUM(E7:E54)/2 -> 42833.4 | F55: =+SUM(F7:F54)/2 -> 1035.2 | G55: =+SUM(G7:G54)/2 -> 0 | H55: =+SUM(H7:H54)/2 -> 0 | I55: =+SUM(I7:I54)/2 -> 0 | J55: =+SUM(J7:J54)/2 -> 1257.5 | ... P55: =+SUM(P7:P54)/2 -> 173627.2 | V55: C.H. CARHUAQUERO | X55: 1908.25
B56: % | C56: =+C55/$P$55*100 -> 16.493873 | D56: =+D55/$P$55*100 -> 48.00924 | E56: =+E55/$P$55*100 -> 24.669752 | F56: =+F55/$P$55*100 -> 0.59621995 | G56: =+G55/$P$55*100 -> 0 | H56: =+H55/$P$55*100 -> 0 | I56: =+I55/$P$55*100 -> 0 | J56: =+J55/$P$55*100 -> 0.72425288 | ... P56: =+P55/$P$55*100 -> 100 | V56: C.H. CARHUAQUERO IV | W56: 237.9
U57: ORYGEN PERU S.A.A. | V57: C.H. CALLAHUANCA | X57: 1931.55
V58: C.H. HER 1 | W58: 14.4
V59: C.H. HUAMPANI | W59: 722
V60: C.H. HUINCO | X60: 4245.4
V61: C.H. MATUCANA | X61: 3067.4
V62: C.H. MOYOPAMPA | W62: 1462.15
U63: PERUANA DE INVERSIONES EN ENERGIAS RENOVABLES S.A. | V63: C.H. MANTA I | W63: 479.7
U64: SAN GABAN | V64: C.H. SAN GABAN II | X64: 2657.95
U65: SINERSA | V65: C.H. CHANCAY | W65: 478.95
V66: C.H. POECHOS II | W66: 184.9
U67: STATKRAFT S.A | V67: C.H. ARCATA | W67: 90.55
V68: C.H. CAHUA | W68: 1121.95
V69: C.H. CHEVES | X69: 3798.5
V70: C.H. GALLITO CIEGO | X70: 726.55
V71: C.H. MALPASO | X71: 1017.1
V72: C.H. OROYA | W72: 189.95
V73: C.H. PACHACHACA | W73: 59.9
V74: C.H. YAUPI | W74: 2610.55
U75: TOTAL MWh | W75: 28637.85 | X75: 83357.1

Sheet GENERACION RER
B3: lunes, 27 de Enero del 2025
B5: GENERACIÓN ELÉCTRICA DE LAS CENTRALES RER (MW)
B6: HORA | C6: AGRO INDUSTRIAL PARAMONGA S.A. | D6: AGROAURORA S.A.C. | E6: AGROINDUSTRIAS SAN JACINTO S.A.A. | F6: ANDEAN POWER S.A.C. | G6: ASOCIACIÓN SANTA LUCIA DE CHACAS | H6: ATRIA ENERGIA S.A.C. | I6: BIOENERGIA DEL CHIRA S.A. | J6: COLCA SOLAR S.A.C. | K6: EGEJUNIN | P6: ELECTRICA YANAPAMPA SAC | Q6: EMPRESA DE GENERACION ELECTRICA CANCHAYLLO SAC | R6: EMPRESA DE GENERACION ELECTRICA RIO BAÑOS S.A.C. | S6: EMPRESA DE GENERACION ELECTRICA SANTA ANA S.A.C. | T6: EMPRESA ELECTRICA AGUA AZUL | U6: EMPRESA ELECTRICA RIO DOBLE | V6: ENERGÍA EÓLICA S.A. | X6: ENERGIA RENOVABLE DEL SUR S.A. | Y6: ENGIE | AD6: GENERACIÓN ANDINA S.A.C. | AF6: GENERADORA DE ENERGÍA DEL PERÚ | AJ6: GR CORTARRAMA SOCIEDAD ANONIMA CERRADA | AK6: GR PAINO SOCIEDAD ANONIMA CERRADA | AL6: GR TARUCA SOCIEDAD ANONIMA CERRADA | AM6: HIDROCAÑETE S.A. | AN6: HUAURA POWER GROUP S.A. | AO6: HYDRO PATAPO S.A.C. | AP6: KONDU SAC | AQ6: MAJA ENERGIA S.A.C. | AR6: MAJES ARCUS S.A.C. | AS6: MOQUEGUA FV S.A.C. | AT6: ORAZUL ENERGY PERÚ | AV6: ORYGEN PERU S.A.A. | BA6: PANAMERICANA SOLAR SAC. | BB6: PARQUE EOLICO MARCONA S.A.C. | BC6: PARQUE EOLICO TRES HERMANAS S.A.C. | BD6: PERUANA DE INVERSIONES EN ENERGIAS RENOVABLES S.A. | BE6: PETRAMAS | BI6: REPARTICIÓN ARCUS S.A.C. | BJ6: SDF ENERGIA SAC | BK6: SINERSA | BM6: TACNA SOLAR SAC. | BN6: TOTAL RER
C7: C.T. PARAMONGA | D7: C.T. MAPLE | E7: C.T SAN JACINTO | F7: C.H. CARHUAC | G7: C.H. HUALLIN | H7: C.H. PURMACANA | I7: C.T. CAÑA BRAVA | K7: C.H. HUASAHUASI I | L7: C.H. HUASAHUASI II | M7: C.H. RUNATULLO II | N7: C.H. RUNATULLO III | O7: C.H. STA CRUZ I y II | P7: C.H. YANAPAMPA | Q7: C.H. CANCHAYLLO | R7: C.H. RUCUY | S7: C.H. RENOVANDES H1 | T7: C.H. POTRERO | U7: C.H. LAS PIZARRAS | AD7: C.H. 8 DE AGOSTO | AE7: C.H. EL CARMEN | AF7: C.H. ANGEL I | AG7: C.H. ANGEL II | AH7: C.H. ANGEL III | AI7: C.H. LA JOYA | AM7: C.H. NUEVAIMPERIAL | AN7: C.H. YARUCAYA | AO7: MCH PATAPO | AQ7: C.H. RONCADOR | AT7: C.H. CANA BRAVA | AU7: C.H. CARHUAQUERO4 | AZ7: C.H. HER 1 | BD7: C.H. MANTA | BE7: C.T. HUAYCOLORO | BF7: C.T. LA GRINGA V | BG7: CTB CALLAO | BH7: CTB. DONA CATALINA | BJ7: C.T. OQUENDO | BK7: C.H. CHANCAY | BL7: C.H. POECHOS2 | BN7: MW
B8: 0:30 | C8: 14 | D8: 15.1 | E8: 6.9 | F8: 9.4 | G8: 2 | I8: 10 | K8: 14.2 | M8: 19.6 | N8: 20.4 | O8: 8.8 | P8: 3.5 | Q8: 5.2 | R8: 19.9 | S8: 20.3 | T8: 20 | U8: 13.6 | V8: 18.1 | W8: 30.4 | X8: 97 | Y8: 19 | Z8: 49.2 | AB8: 1.4 | AC8: 1 | AD8: 21 | AE8: 6.9 | AF8: 20 | AG8: 20 | AH8: 19.8 | AI8: 7.6 | AK8: 13.2 | AL8: 15.1 | AM8: 3.7 | AN8: 18.8 | AQ8: 3.6 | AT8: 5.5 | AU8: 10 | AV8: 14.5 | AX8: 14.9 | AZ8: 0.6 | BB8: 29.3 | BC8: 69.2 | BD8: 20 | BE8: 4.8 | BF8: 2.9 | BG8: 2.3 | BH8: 2.4 | BK8: 19.9 | BL8: 7.5 | BN8: 772.5
B9: 1:00 | C9: 14 | D9: 15.1 | E9: 7 | F9: 6.3 | G9: 2 | I9: 10.1 | K9: 16.1 | M9: 19.1 | N9: 20.4 | O9: 8.8 | P9: 3.7 | Q9: 5.2 | R9: 19.8 | S9: 20.5 | T9: 20 | U9: 14 | V9: 20.7 | W9: 27.4 | X9: 84.2 | Y9: 14.8 | Z9: 51 | AB9: 1.2 | AC9: 0.7 | AD9: 21 | AE9: 7.1 | AF9: 20 | AG9: 20 | AH9: 19.8 | AI9: 7.6 | AK9: 13.1 | AL9: 16 | AM9: 3.7 | AN9: 18.8 | AQ9: 3.7 | AT9: 5.4 | AU9: 9.9 | AV9: 16 | AX9: 12.9 | AZ9: 0.6 | BB9: 28.8 | BC9: 67.9 | BD9: 20 | BE9: 4.8 | BF9: 2.9 | BG9: 2.3 | BH9: 2.4 | BK9: 19.8 | BL9: 7.5 | BN9: 754.1
B10: 1:30 | C10: 13.9 | D10: 15.1 | E10: 7.2 | F10: 6.5 | G10: 2 | I10: 9.4 | K10: 16.1 | M10: 19.3 | N10: 20.3 | O10: 8.8 | P10: 3.7 | Q10: 5.1 | R10: 20 | S10: 20.4 | T10: 20 | U10: 14.1 | V10: 25.7 | W10: 18.6 | X10: 70.1 | Y10: 17.8 | Z10: 47.1 | AB10: 1.1 | AC10: 0.7 | AD10: 21 | AE10: 7.3 | AF10: 20 | AG10: 20 | AH10: 19.8 | AI10: 7.6 | AK10: 10.6 | AL10: 14.1 | AM10: 3.7 | AN10: 18.8 | AQ10: 3.6 | AT10: 4.7 | AU10: 9.9 | AV10: 17.3 | AX10: 10.4 | AZ10: 0.6 | BB10: 24.4 | BC10: 58.6 | BD10: 20 | BE10: 4.8 | BF10: 2.9 | BG10: 2.3 | BH10: 2.4 | BK10: 20 | BL10: 7.5 | BN10: 715.3
B11: 2:00 | C11: 13 | D11: 15.1 | E11: 7.5 | F11: 6.5 | G11: 2 | I11: 9.4 | K11: 16.1 | M11: 19.1 | N11: 20.4 | O11: 8.9 | P11: 3.7 | Q11: 5.2 | R11: 20 | S11: 20.3 | T11: 20 | U11: 14 | V11: 22.7 | W11: 16 | X11: 72.5 | Y11: 27.4 | Z11: 65.1 | AB11: 2 | AC11: 1.1 | AD11: 21 | AE11: 8.4 | AF11: 20 | AG11: 20 | AH11: 19.9 | AI11: 7.9 | AK11: 11.1 | AL11: 14.1 | AN11: 18.8 | AQ11: 3.7 | AT11: 4.7 | AU11: 9.9 | AV11: 16 | AX11: 10.5 | AZ11: 0.6 | BB11: 21.3 | BC11: 52.6 | BD11: 20 | BE11: 4.8 | BF11: 3 | BG11: 2.3 | BH11: 2.4 | BK11: 20 | BL11: 7.6 | BN11: 728.6
B12: 2:30 | C12: 13.9 | D12: 15.1 | E12: 7.2 | F12: 6.5 | G12: 2 | I12: 9.3 | K12: 16.1 | M12: 18.9 | N12: 20.4 | O12: 8.9 | P12: 3.6 | Q12: 5.2 | R12: 19.9 | S12: 20.4 | T12: 20 | U12: 14.1 | V12: 22.1 | W12: 16.1 | X12: 85.2 | Y12: 22.5 | Z12: 66.5 | AB12: 1.3 | AC12: 1.1 | AD12: 21 | AE12: 8.4 | AF12: 20 | AG12: 20 | AH12: 20 | AI12: 7.8 | AK12: 12.1 | AL12: 15.2 | AN12: 18.8 | AQ12: 3.7 | AT12: 4.6 | AU12: 9.9 | AV12: 21.5 | AX12: 19 | AZ12: 0.6 | BB12: 26.1 | BC12: 64 | BD12: 20 | BE12: 4.8 | BF12: 3 | BG12: 2.3 | BH12: 2.4 | BK12: 20 | BL12: 7.6 | BN12: 769.1
B13: 3:00 | C13: 13.7 | D13: 15.1 | E13: 8.1 | F13: 6.5 | G13: 2 | I13: 9.5 | K13: 16.1 | M13: 18.9 | N13: 20.4 | O13: 8.9 | P13: 3.7 | Q13: 5.2 | R13: 19.9 | S13: 20.4 | T13: 20 | U13: 14 | V13: 25.6 | W13: 13.2 | X13: 85.2 | Y13: 25.3 | Z13: 61.2 | AB13: 0.9 | AC13: 1.8 | AD13: 21 | AE13: 8.4 | AF13: 20 | AG13: 20 | AH13: 20 | AI13: 7.7 | AK13: 13.1 | AL13: 17.1 | AN13: 18.8 | AQ13: 3.7 | AT13: 4.7 | AU13: 9.9 | AV13: 16.6 | AX13: 20.4 | AZ13: 0.6 | BB13: 24.4 | BC13: 64.1 | BD13: 20 | BE13: 4.8 | BF13: 3 | BG13: 2.3 | BH13: 2.4 | BK13: 19.9 | BL13: 7.6 | BN13: 766.1
B14: 3:30 | C14: 12 | D14: 15.1 | E14: 7.6 | F14: 6.5 | G14: 2 | I14: 10.1 | K14: 16.2 | M14: 18.8 | N14: 20.3 | O14: 8.9 | P14: 3.6 | Q14: 5.2 | R14: 20 | S14: 20.5 | T14: 20 | U14: 14 | V14: 17.5 | W14: 17.3 | X14: 80.7 | Y14: 26.6 | Z14: 65.9 | AB14: 1.1 | AC14: 0.7 | AD14: 21 | AE14: 8.4 | AF14: 20 | AG14: 20 | AH14: 20 | AI14: 7.6 | AK14: 12.4 | AL14: 17 | AN14: 18.8 | AQ14: 3.7 | AT14: 4.7 | AU14: 9.9 | AV14: 18.4 | AX14: 20.5 | AZ14: 0.6 | BB14: 24.5 | BC14: 64.7 | BD14: 20 | BE14: 4.8 | BF14: 3 | BG14: 2.3 | BH14: 2.4 | BK14: 20 | BL14: 7.5 | BN14: 762.8
B15: 4:00 | C15: 13.8 | D15: 14.8 | E15: 8.8 | F15: 6.5 | G15: 2 | I15: 9.7 | K15: 16.2 | M15: 18.6 | N15: 20.2 | O15: 8.9 | P15: 3.6 | Q15: 5.2 | R15: 19.8 | S15: 19.8 | T15: 20 | U15: 14 | V15: 12.6 | W15: 21.1 | X15: 92.6 | Y15: 28.9 | Z15: 67.5 | AB15: 0.8 | AC15: 0.5 | AD15: 21 | AE15: 8.4 | AF15: 20 | AG15: 20 | AH15: 20 | AI15: 7.5 | AK15: 13.8 | AL15: 17 | AN15: 18.8 | AQ15: 3.7 | AT15: 4.7 | AU15: 10 | AV15: 26.3 | AX15: 28.9 | AZ15: 0.6 | BB15: 23.1 | BC15: 65.2 | BD15: 20 | BE15: 4.8 | BF15: 3 | BG15: 2.3 | BH15: 2.4 | BK15: 19.8 | BL15: 7.5 | BN15: 794.7
B16: 4:30 | C16: 13.9 | D16: 15.1 | E16: 8.3 | F16: 6.5 | G16: 2 | I16: 10.1 | K16: 16.2 | M16: 18.6 | N16: 20.2 | O16: 9 | P16: 3.6 | Q16: 5.2 | R16: 20 | S16: 19.9 | T16: 20 | U16: 14 | V16: 23.5 | W16: 20.6 | X16: 101.5 | Y16: 33.8 | Z16: 66.2 | AB16: 1.2 | AC16: 1 | AD16: 21 | AE16: 8.4 | AF16: 20 | AG16: 20 | AH16: 20 | AI16: 7.5 | AK16: 13.2 | AL16: 16.1 | AN16: 18.8 | AQ16: 3.7 | AT16: 4.7 | AU16: 9.9 | AV16: 33.6 | AX16: 44.5 | AZ16: 0.6 | BB16: 26.8 | BC16: 67.7 | BD16: 19.9 | BE16: 4.8 | BF16: 3 | BG16: 2.3 | BH16: 2.4 | BK16: 20 | BL16: 7.5 | BN16: 846.8
B17: 5:00 | C17: 13.9 | E17: 7.8 | F17: 6.5 | G17: 2 | I17: 9.8 | K17: 16.2 | M17: 18.8 | N17: 20.3 | O17: 9.1 | P17: 3.6 | Q17: 5.2 | R17: 19.8 | S17: 20.1 | T17: 20 | U17: 14 | V17: 23.1 | W17: 16.4 | X17: 97.5 | Y17: 29.9 | Z17: 68.5 | AB17: 1.9 | AC17: 1 | AD17: 21 | AE17: 8.4 | AF17: 20 | AG17: 20 | AH17: 20 | AI17: 7.5 | AK17: 12.5 | AL17: 15.9 | AN17: 18.8 | AQ17: 3.7 | AT17: 4.7 | AU17: 10 | AV17: 35.2 | AX17: 45.2 | AZ17: 0.6 | BB17: 29.8 | BC17: 71.1 | BD17: 20 | BE17: 4.8 | BF17: 3 | BG17: 2.3 | BH17: 2.4 | BK17: 19.8 | BL17: 7.5 | BN17: 829.6
B18: 5:30 | C18: 13.9 | E18: 8.5 | F18: 6.5 | G18: 2 | I18: 9.3 | K18: 16.3 | M18: 19 | N18: 20.4 | O18: 9.1 | P18: 3.6 | Q18: 5.1 | R18: 19.8 | S18: 20.2 | T18: 20 | U18: 14 | V18: 23.6 | W18: 14.4 | X18: 87.9 | Y18: 37.2 | Z18: 61.5 | AB18: 1.1 | AC18: 1.4 | AD18: 21 | AE18: 8.4 | AF18: 20 | AG18: 20 | AH18: 20 | AI18: 7.9 | AK18: 13.9 | AL18: 17 | AN18: 18.8 | AQ18: 3.6 | AS18: 0.1 | AT18: 4.7 | AU18: 9.9 | AV18: 38.3 | AX18: 41.9 | AY18: 0.1 | AZ18: 0.6 | BB18: 27.6 | BC18: 68.5 | BD18: 20 | BE18: 4.8 | BF18: 3 | BG18: 2.3 | BH18: 2.4 | BK18: 19.8 | BL18: 7.5 | BN18: 816.9
B19: 6:00 | C19: 14 | E19: 9.3 | F19: 6.3 | G19: 2 | I19: 10.1 | K19: 15.8 | M19: 19.3 | N19: 20.3 | O19: 9.3 | P19: 3.6 | Q19: 5.1 | R19: 19.8 | S19: 20.4 | T19: 20 | U19: 14 | V19: 18 | W19: 10.9 | X19: 87.7 | Y19: 31 | Z19: 64.4 | AA19: 1.9 | AB19: 2 | AC19: 1.5 | AD19: 21 | AE19: 8.4 | AF19: 20 | AG19: 20 | AH19: 20 | AI19: 7.9 | AJ19: 2.7 | AK19: 11.3 | AL19: 14.3 | AM19: 2.1 | AN19: 18.8 | AQ19: 3.7 | AS19: 0.7 | AT19: 4.7 | AU19: 9.9 | AV19: 39.6 | AW19: 11.8 | AX19: 51.9 | AY19: 10.3 | AZ19: 0.6 | BA19: 0.7 | BB19: 22.7 | BC19: 60.7 | BD19: 20 | BE19: 4.8 | BF19: 3 | BG19: 2.3 | BH19: 2.4 | BK19: 19.9 | BL19: 7.5 | BM19: 0.1 | BN19: 830.5
B20: 6:30 | C20: 14 | E20: 7.4 | F20: 6.4 | G20: 2 | I20: 10.6 | K20: 15.6 | M20: 19 | N20: 20.2 | O20: 9.1 | P20: 3.6 | Q20: 5.2 | R20: 20 | S20: 19.9 | T20: 20 | U20: 14 | V20: 12.8 | W20: 10.3 | X20: 88 | Y20: 28.3 | Z20: 70.3 | AA20: 3.7 | AB20: 1.5 | AC20: 0.9 | AD20: 21 | AE20: 8.4 | AF20: 20 | AG20: 20 | AH20: 20 | AI20: 7.9 | AJ20: 20.9 | AK20: 11.8 | AL20: 14.2 | AM20: 3.8 | AN20: 18.8 | AQ20: 3.6 | AR20: 0.7 | AS20: 1.6 | AT20: 4.7 | AU20: 9.9 | AV20: 38.6 | AW20: 17.9 | AX20: 52.3 | AY20: 10.2 | AZ20: 0.6 | BA20: 1.5 | BB20: 25 | BC20: 51.6 | BD20: 20 | BE20: 3.2 | BF20: 3 | BG20: 2.3 | BH20: 2.4 | BI20: 0.8 | BK20: 20 | BL20: 7.5 | BM20: 2.1 | BN20: 849.1
B21: 7:00 | C21: 14 | E21: 7 | F21: 6.4 | G21: 2 | I21: 10 | J21: 0.1 | K21: 15.4 | M21: 19.5 | N21: 20.3 | O21: 9.1 | P21: 3.6 | Q21: 5.2 | R21: 20 | S21: 20.3 | T21: 20 | U21: 14 | V21: 12 | W21: 6.9 | X21: 82.5 | Y21: 29.6 | Z21: 53.3 | AA21: 21.9 | AB21: 1.2 | AC21: 0.7 | AD21: 21 | AE21: 8.4 | AF21: 20 | AG21: 20 | AH21: 20 | AI21: 7.9 | AJ21: 45.2 | AK21: 10.4 | AL21: 11.7 | AM21: 3.8 | AN21: 18.8 | AQ21: 3.6 | AR21: 2 | AS21: 3.5 | AT21: 4.7 | AU21: 9.9 | AV21: 36.1 | AW21: 34.8 | AX21: 44.4 | AY21: 28.9 | AZ21: 0.6 | BA21: 3.9 | BB21: 23 | BC21: 45.6 | BD21: 20 | BE21: 3.2 | BF21: 3 | BG21: 2.3 | BH21: 2.4 | BI21: 1 | BK21: 20 | BL21: 7.5 | BM21: 5.2 | BN21: 887.8
B22: 7:30 | C22: 14.1 | E22: 6.7 | F22: 6.4 | G22: 2 | I22: 9.9 | J22: 0.1 | K22: 15.5 | M22: 20.4 | N22: 20.4 | O22: 9.1 | P22: 3.6 | Q22: 5.2 | R22: 20 | S22: 20.1 | T22: 20 | U22: 14 | V22: 11.6 | W22: 9 | X22: 70.9 | Y22: 25.2 | Z22: 44.5 | AA22: 33.4 | AB22: 2.1 | AC22: 1.4 | AD22: 21 | AE22: 8.4 | AF22: 20 | AG22: 20 | AH22: 20 | AI22: 7.7 | AJ22: 54.6 | AK22: 11.5 | AL22: 16.7 | AM22: 3.7 | AN22: 18.8 | AQ22: 3.7 | AR22: 5 | AS22: 10.3 | AT22: 3.9 | AU22: 9.9 | AV22: 40.7 | AW22: 75.9 | AX22: 43.9 | AY22: 82.8 | AZ22: 0.6 | BA22: 13.6 | BB22: 22.2 | BC22: 47.8 | BD22: 20 | BE22: 3.2 | BF22: 3 | BG22: 2.3 | BH22: 2.4 | BI22: 5.4 | BK22: 20 | BL22: 7.5 | BM22: 12.2 | BN22: 1024.3
B23: 8:00 | C23: 14 | E23: 7.7 | F23: 6.1 | G23: 2 | I23: 10.3 | J23: 0.1 | K23: 15.5 | M23: 20.4 | N23: 20.4 | O23: 9.1 | P23: 3.6 | Q23: 5.2 | R23: 20 | S23: 20 | T23: 17.8 | U23: 13.5 | V23: 11.4 | W23: 9.7 | X23: 53.8 | Y23: 41.2 | Z23: 58.1 | AA23: 25.5 | AB23: 2.9 | AC23: 3.2 | AD23: 21 | AE23: 8.4 | AF23: 20 | AG23: 20 | AH23: 20 | AI23: 8.2 | AJ23: 69.2 | AK23: 15.3 | AL23: 16.5 | AM23: 3.7 | AN23: 18.8 | AP23: 0.1 | AQ23: 3.6 | AR23: 7.6 | AS23: 9.1 | AT23: 5.4 | AU23: 9.9 | AV23: 37.5 | AW23: 131.9 | AX23: 37.7 | AY23: 107.9 | AZ23: 0.6 | BA23: 15.8 | BB23: 14.6 | BC23: 46.2 | BD23: 20 | BE23: 3.2 | BF23: 3 | BG23: 2.3 | BH23: 2.4 | BI23: 6.2 | BK23: 20 | BL23: 7.5 | BM23: 15 | BN23: 1120.1
B24: 8:30 | C24: 14.1 | E24: 7.5 | F24: 8.4 | G24: 2 | I24: 10.2 | J24: 0.6 | K24: 15.3 | M24: 20.2 | N24: 20.4 | O24: 9.1 | P24: 3.6 | Q24: 5.1 | R24: 20 | S24: 20.1 | T24: 20 | U24: 13.5 | V24: 11.1 | W24: 11.8 | X24: 58.1 | Y24: 40.8 | Z24: 56.8 | AA24: 39.5 | AB24: 4.5 | AC24: 4.6 | AD24: 21 | AE24: 8.4 | AF24: 20 | AG24: 20 | AH24: 20 | AI24: 8 | AJ24: 42.9 | AK24: 12.7 | AL24: 15.9 | AM24: 3.7 | AN24: 18.8 | AP24: 0.1 | AQ24: 3.6 | AR24: 8.5 | AS24: 14.6 | AT24: 5.3 | AU24: 9.9 | AV24: 28 | AW24: 129.4 | AX24: 28 | AY24: 104.3 | AZ24: 0.6 | BA24: 18.3 | BB24: 13.5 | BC24: 52 | BD24: 20 | BE24: 3.2 | BF24: 2.7 | BG24: 2.3 | BH24: 2.4 | BI24: 10.1 | BK24: 20 | BL24: 7.5 | BM24: 17.8 | BN24: 1110.8
B25: 9:00 | C25: 14 | E25: 7.7 | F25: 19.9 | G25: 2 | I25: 10.1 | J25: 0.7 | K25: 15.3 | M25: 20.2 | N25: 20.4 | O25: 9.1 | P25: 3.6 | Q25: 5.1 | R25: 20 | S25: 20.1 | T25: 20 | U25: 13.5 | V25: 8.2 | W25: 16.1 | X25: 59.9 | Y25: 59.7 | Z25: 63.8 | AA25: 37.7 | AB25: 5.8 | AC25: 4.5 | AD25: 21 | AE25: 8.4 | AF25: 20 | AG25: 20 | AH25: 20 | AI25: 8 | AJ25: 72.4 | AK25: 12.6 | AL25: 15.3 | AM25: 3.7 | AN25: 18.8 | AP25: 0.1 | AQ25: 3.6 | AR25: 7.7 | AS25: 14.8 | AT25: 5.3 | AU25: 9.9 | AV25: 15.2 | AW25: 132.1 | AX25: 12.7 | AY25: 105.2 | AZ25: 0.6 | BA25: 18.4 | BB25: 12.2 | BC25: 50.9 | BD25: 20 | BE25: 3.2 | BF25: 2.7 | BG25: 2.3 | BH25: 2.4 | BI25: 9.6 | BK25: 20 | BL25: 7.6 | BM25: 19.2 | BN25: 1153.3
B26: 9:30 | C26: 14 | E26: 7.5 | F26: 20.4 | G26: 2 | I26: 10.4 | J26: 0.9 | K26: 15 | M26: 20.3 | N26: 20.4 | O26: 9.2 | P26: 3.6 | Q26: 5.1 | R26: 20 | S26: 20.1 | T26: 20 | U26: 13.5 | V26: 11.1 | W26: 14.6 | X26: 82.4 | Y26: 67.2 | Z26: 69.5 | AA26: 38.4 | AB26: 7 | AC26: 6.7 | AD26: 21 | AE26: 8.4 | AF26: 20 | AG26: 20 | AH26: 20 | AI26: 7.7 | AJ26: 74.3 | AK26: 10.4 | AL26: 13.7 | AM26: 3.7 | AN26: 18.8 | AP26: 0.1 | AQ26: 3.6 | AR26: 7.8 | AS26: 15 | AT26: 5.4 | AU26: 9.9 | AV26: 12.7 | AW26: 135.6 | AX26: 9.8 | AY26: 109.5 | AZ26: 0.6 | BA26: 18.6 | BB26: 13.9 | BC26: 53.3 | BD26: 20 | BE26: 3 | BF26: 2.8 | BG26: 2.3 | BH26: 2.4 | BI26: 14.1 | BK26: 20 | BL26: 7.6 | BM26: 19.4 | BN26: 1204.7
B27: 10:00 | C27: 13.9 | E27: 7.4 | F27: 20.3 | G27: 2 | I27: 10.6 | J27: 1 | K27: 15 | M27: 20.4 | N27: 20.4 | O27: 9.3 | P27: 3.6 | Q27: 5.1 | R27: 20 | S27: 20.8 | T27: 20 | U27: 13.5 | V27: 10.8 | W27: 18.3 | X27: 91.2 | Y27: 66.5 | Z27: 70.5 | AA27: 38.7 | AB27: 10.8 | AC27: 6.7 | AD27: 21 | AE27: 8.4 | AF27: 20 | AG27: 20 | AH27: 20 | AI27: 7.8 | AJ27: 75.8 | AK27: 13.6 | AL27: 15 | AM27: 3.8 | AN27: 18.8 | AP27: 0.2 | AQ27: 3.6 | AR27: 15.9 | AS27: 15.2 | AT27: 5.4 | AU27: 9.9 | AV27: 11.3 | AW27: 134.9 | AX27: 6.7 | AY27: 109.5 | AZ27: 0.6 | BA27: 19.1 | BB27: 21.7 | BC27: 62.9 | BD27: 20 | BE27: 2.9 | BF27: 2.5 | BG27: 2.3 | BH27: 2.2 | BI27: 15.6 | BK27: 20 | BL27: 7.5 | BM27: 19.6 | BN27: 1250.5
B28: 10:30 | C28: 14 | E28: 7.4 | F28: 20.3 | G28: 2 | I28: 10.4 | J28: 1.2 | K28: 14.8 | M28: 20.3 | N28: 20.4 | O28: 9.2 | P28: 3.6 | Q28: 5.2 | R28: 20 | S28: 20 | T28: 20 | U28: 13.5 | V28: 7.6 | W28: 30.6 | X28: 100.2 | Y28: 82.8 | Z28: 91 | AA28: 39.5 | AB28: 13.9 | AC28: 9.1 | AD28: 21 | AE28: 8.4 | AF28: 20 | AG28: 20 | AH28: 20 | AI28: 8 | AJ28: 76.3 | AK28: 13.5 | AL28: 16.3 | AM28: 3.7 | AN28: 18.8 | AP28: 0.4 | AQ28: 3.6 | AR28: 16.8 | AS28: 15.4 | AT28: 5.5 | AU28: 10 | AV28: 25 | AW28: 138.2 | AX28: 14.5 | AY28: 111.5 | AZ28: 0.6 | BA28: 19.4 | BB28: 22.8 | BC28: 72.1 | BD28: 20 | BE28: 2.7 | BF28: 2.3 | BG28: 2.3 | BH28: 2.1 | BI28: 16.8 | BK28: 20 | BL28: 7.4 | BM28: 19.7 | BN28: 1352.1
B29: 11:00 | C29: 13.9 | E29: 7.2 | F29: 20.3 | G29: 2 | I29: 10.5 | J29: 1.2 | K29: 14.7 | M29: 20.3 | N29: 20.4 | O29: 9.2 | P29: 3.6 | Q29: 5.2 | R29: 20 | S29: 19.9 | T29: 20 | U29: 13.5 | V29: 7.1 | W29: 35.6 | X29: 97.5 | Y29: 90.9 | Z29: 88 | AA29: 40.1 | AB29: 10.8 | AC29: 12 | AD29: 21 | AE29: 8.1 | AF29: 20 | AG29: 20 | AH29: 20 | AI29: 8.2 | AJ29: 77.2 | AK29: 12.7 | AL29: 14.2 | AM29: 3.7 | AN29: 18.8 | AP29: 0.4 | AQ29: 3.6 | AR29: 17.7 | AS29: 15.6 | AT29: 5.4 | AU29: 10 | AV29: 49.9 | AW29: 138.6 | AX29: 43.1 | AY29: 112.5 | AZ29: 0.6 | BA29: 19.5 | BB29: 27.2 | BC29: 78.7 | BD29: 20 | BE29: 2.7 | BF29: 2.2 | BG29: 2.3 | BH29: 2.1 | BI29: 18.1 | BK29: 20 | BL29: 7.4 | BM29: 19.8 | BN29: 1425.2
B30: 11:30 | C30: 12.8 | E30: 6.9 | F30: 20.3 | G30: 2 | I30: 10.7 | J30: 0.4 | K30: 14.9 | M30: 20.4 | N30: 20.4 | O30: 9.1 | P30: 3.6 | Q30: 5.2 | R30: 20 | S30: 20.1 | T30: 20 | U30: 13.5 | V30: 5.7 | W30: 43.5 | X30: 100.2 | Y30: 87.4 | Z30: 87.5 | AA30: 25.4 | AB30: 12.3 | AC30: 12.4 | AD30: 21 | AE30: 8.1 | AF30: 20 | AG30: 20 | AH30: 20 | AI30: 8.2 | AJ30: 79.2 | AK30: 10.4 | AL30: 13.1 | AM30: 3.7 | AN30: 18.8 | AP30: 0.2 | AQ30: 3.6 | AR30: 18.4 | AS30: 15.4 | AT30: 5.4 | AU30: 10 | AV30: 77.5 | AW30: 139.7 | AX30: 66.8 | AY30: 112.9 | AZ30: 0.6 | BA30: 19.5 | BB30: 27.7 | BC30: 79.1 | BD30: 20 | BE30: 2.7 | BF30: 2.2 | BG30: 2.3 | BH30: 2.1 | BI30: 18.5 | BK30: 20 | BL30: 7.6 | BM30: 19.8 | BN30: 1469.2
B31: 12:00 | C31: 12.2 | E31: 9.1 | F31: 20.4 | G31: 2 | I31: 10.5 | J31: 1.3 | K31: 15 | M31: 20.4 | N31: 20.4 | O31: 9.1 | P31: 3.6 | Q31: 5.2 | R31: 20 | S31: 20.1 | T31: 20 | U31: 13.5 | V31: 9 | W31: 52 | X31: 99.1 | Y31: 87.5 | Z31: 89.3 | AA31: 19.4 | AB31: 12.5 | AC31: 11.3 | AD31: 21 | AE31: 8 | AF31: 20 | AG31: 20 | AH31: 20 | AI31: 8 | AJ31: 79.5 | AK31: 14.6 | AL31: 16.6 | AM31: 3.7 | AN31: 18.8 | AP31: 0.3 | AQ31: 3.6 | AR31: 18.8 | AS31: 15.6 | AT31: 5.3 | AU31: 9.9 | AV31: 64.5 | AW31: 141.3 | AX31: 64.7 | AY31: 113.5 | AZ31: 0.6 | BA31: 19.5 | BB31: 26.9 | BC31: 79.4 | BD31: 20 | BE31: 2.7 | BF31: 2.2 | BG31: 2.3 | BH31: 2.1 | BI31: 19.1 | BK31: 20 | BL31: 7.4 | BM31: 19.8 | BN31: 1472.6
B32: 12:30 | C32: 11.5 | E32: 9 | F32: 20.3 | G32: 2 | I32: 11 | J32: 0.6 | K32: 14.6 | M32: 20.3 | N32: 20.5 | O32: 9.1 | P32: 3.6 | Q32: 5.2 | R32: 20 | S32: 20.5 | T32: 20 | U32: 13.5 | V32: 8.3 | W32: 45 | X32: 93.3 | Y32: 88.2 | Z32: 88.6 | AA32: 11.8 | AB32: 12.6 | AC32: 11.3 | AD32: 21 | AE32: 7.9 | AF32: 20 | AG32: 20 | AH32: 20 | AI32: 8 | AJ32: 80.5 | AK32: 13.7 | AL32: 15 | AM32: 3.7 | AN32: 18.8 | AP32: 0.5 | AQ32: 3.6 | AR32: 18.9 | AS32: 15.9 | AT32: 5.3 | AU32: 9.9 | AV32: 69.5 | AW32: 143.6 | AX32: 72.9 | AY32: 114.1 | AZ32: 0.6 | BA32: 19.5 | BB32: 24.8 | BC32: 80.1 | BD32: 20 | BE32: 2.7 | BF32: 2.2 | BG32: 2.3 | BH32: 2.1 | BI32: 16.1 | BK32: 20 | BL32: 7.4 | BM32: 19.8 | BN32: 1461.2
B33: 13:00 | C33: 11.5 | E33: 9 | F33: 20.4 | G33: 2 | I33: 9.8 | J33: 1.3 | K33: 14.6 | M33: 20.4 | N33: 20.4 | O33: 9.1 | P33: 3.6 | Q33: 5.2 | R33: 20 | S33: 19.9 | T33: 20 | U33: 13.5 | V33: 9.5 | W33: 38.7 | X33: 90.3 | Y33: 87.5 | Z33: 89.8 | AA33: 8.5 | AB33: 10.5 | AC33: 9.9 | AD33: 21 | AE33: 8 | AF33: 20 | AG33: 20 | AH33: 20 | AI33: 8 | AJ33: 80.5 | AK33: 13.5 | AL33: 14.8 | AM33: 3.7 | AN33: 18.8 | AP33: 0.3 | AQ33: 3.6 | AR33: 18.8 | AS33: 15.6 | AT33: 5.2 | AU33: 10 | AV33: 70.1 | AW33: 105.5 | AX33: 78.9 | AY33: 88.9 | AZ33: 0.6 | BA33: 19.6 | BB33: 24.1 | BC33: 71.6 | BD33: 19.9 | BE33: 2.7 | BF33: 2.2 | BG33: 2.3 | BH33: 2.1 | BI33: 16.7 | BK33: 20 | BL33: 7.4 | BM33: 19.9 | BN33: 1379.7
B34: 13:30 | C34: 11 | E34: 8.3 | F34: 20.2 | G34: 2 | I34: 10.1 | J34: 1.1 | K34: 14.5 | M34: 20.4 | N34: 20.4 | O34: 9.1 | P34: 3.6 | Q34: 5.2 | R34: 19.8 | S34: 20.4 | T34: 20 | U34: 13.5 | V34: 10.5 | W34: 37.9 | X34: 90 | Y34: 77.5 | Z34: 90.6 | AA34: 16.1 | AB34: 11.9 | AC34: 9.1 | AD34: 21 | AE34: 8 | AF34: 20 | AG34: 20 | AH34: 20 | AI34: 8 | AJ34: 80.5 | AK34: 15.5 | AL34: 17.8 | AM34: 3.7 | AN34: 18.8 | AP34: 0.3 | AQ34: 3.6 | AR34: 18.3 | AS34: 12.6 | AT34: 5.3 | AU34: 9.9 | AV34: 67.8 | AW34: 84 | AX34: 73.8 | AY34: 67.3 | AZ34: 0.6 | BA34: 14.3 | BB34: 21.1 | BC34: 68.9 | BD34: 20 | BE34: 2.7 | BF34: 2.2 | BG34: 2.3 | BH34: 2.1 | BI34: 16.2 | BK34: 19.8 | BL34: 7.4 | BM34: 19.9 | BN34: 1316.9
... B38: 15:30 | C38: 11.2 | E38: 5.9 | F38: 20.2 | G38: 2 | I38: 9.6 | J38: 0.4 | K38: 14.3 | M38: 20.4 | N38: 20.3 | O38: 9.2 | P38: 3.6 | Q38: 5.2 | R38: 19.8 | S38: 20.2 | T38: 20 | U38: 13 | V38: 9 | W38: 39.7 | X38: 91.7 | Y38: 86.1 | Z38: 91.1 | AA38: 4.2 | AB38: 8.4 | AC38: 9.4 | AD38: 21 | AE38: 8.3 | AF38: 20 | AG38: 20 | AH38: 20 | AI38: 5 | AJ38: 22.5 | AK38: 15.4 | AL38: 17.9 | AM38: 3.7 | AN38: 18.8 | AP38: 0.1 | AQ38: 3.6 | AR38: 6.9 | AS38: 3.8 | AT38: 5.3 | AU38: 9.9 | AV38: 122.5 | AW38: 74 | AX38: 111.9 | AY38: 58.3 | AZ38: 0.6 | BA38: 4.8 | BB38: 25.8 | BC38: 71.2 | BD38: 20 | BE38: 2.7 | BF38: 2.2 | BG38: 2.3 | BH38: 2.1 | BI38: 2.3 | BK38: 19.8 | BL38: 7.8 | BM38: 5.7 | BN38: 1271.1
B39: 16:00 | C39: 11.1 | E39: 8.2 | F39: 20.4 | G39: 2 | I39: 10.7 | J39: 0.1 | K39: 14.6 | M39: 20.4 | N39: 20.3 | O39: 9.2 | P39: 3.6 | Q39: 5.2 | R39: 20 | S39: 20 | T39: 20 | U39: 13 | V39: 8.8 | W39: 37.2 | X39: 88.9 | Y39: 87.2 | Z39: 89.9 | AA39: 3.6 | AB39: 8.9 | AC39: 10.4 | AD39: 21 | AE39: 8.4 | AF39: 20 | AG39: 20 | AH39: 20 | AI39: 8.3 | AJ39: 16.9 | AK39: 15.6 | AL39: 16.4 | AM39: 3.4 | AN39: 18.8 | AQ39: 3.6 | AR39: 5 | AS39: 2.8 | AT39: 5.4 | AU39: 10 | AV39: 128.6 | AW39: 33 | AX39: 120.4 | AY39: 30.7 | AZ39: 0.6 | BA39: 2.8 | BB39: 24.4 | BC39: 71 | BD39: 20 | BE39: 2.7 | BF39: 2.2 | BG39: 2.3 | BH39: 2.1 | BI39: 2.7 | BK39: 20 | BL39: 7.8 | BM39: 3.5 | BN39: 1204.1
B40: 16:30 | C40: 11 | E40: 8.2 | F40: 20.3 | G40: 2 | I40: 10.4 | J40: 0.1 | K40: 14.6 | M40: 20.2 | N40: 20.4 | O40: 9.1 | P40: 3.6 | Q40: 5.2 | R40: 19.9 | S40: 20.2 | T40: 20 | U40: 13 | V40: 8.1 | W40: 40.3 | X40: 94.7 | Y40: 88.7 | Z40: 89 | AA40: 2.5 | AB40: 10.3 | AC40: 10.5 | AD40: 21 | AE40: 8.4 | AF40: 20 | AG40: 20 | AH40: 20 | AI40: 7.8 | AJ40: 14.6 | AK40: 14 | AL40: 17.2 | AM40: 3.4 | AN40: 18.8 | AQ40: 3.6 | AR40: 3.4 | AS40: 2.2 | AT40: 5.2 | AU40: 9.9 | AV40: 126.6 | AW40: 22.5 | AX40: 124.3 | AY40: 22.5 | AZ40: 0.6 | BA40: 2.1 | BB40: 25.5 | BC40: 71.4 | BD40: 19.9 | BE40: 2.7 | BF40: 2.2 | BG40: 2.3 | BH40: 2.1 | BI40: 1.3 | BK40: 20 | BL40: 7.8 | BM40: 3.1 | BN40: 1188.7
B41: 17:00 | C41: 11 | E41: 8.2 | F41: 20.2 | G41: 2 | I41: 9.9 | J41: 0.1 | K41: 14.4 | M41: 20.1 | N41: 20.3 | O41: 9 | P41: 3.6 | Q41: 5.1 | R41: 19.8 | S41: 19.4 | T41: 20 | U41: 13 | V41: 7.5 | W41: 33.2 | X41: 96.3 | Y41: 90.6 | Z41: 88.8 | AA41: 2.6 | AB41: 9.1 | AC41: 11.4 | AD41: 21 | AE41: 8.4 | AF41: 20 | AG41: 20 | AH41: 20 | AI41: 7 | AJ41: 7.5 | AK41: 13.2 | AL41: 17.2 | AM41: 3.4 | AN41: 18.8 | AQ41: 3.6 | AR41: 2.6 | AS41: 2 | AT41: 5.3 | AU41: 9.8 | AV41: 134.3 | AW41: 25.5 | AX41: 125.8 | AY41: 22.8 | AZ41: 0.6 | BA41: 2.2 | BB41: 24.8 | BC41: 77.2 | BD41: 19.8 | BE41: 2.7 | BF41: 2.2 | BG41: 2.3 | BH41: 2.1 | BI41: 1.3 | BK41: 19.8 | BL41: 7.8 | BM41: 1.5 | BN41: 1188.1
B42: 17:30 | C42: 14 | E42: 8.2 | F42: 16.6 | G42: 2 | I42: 10.1 | J42: 0.1 | K42: 14.4 | M42: 20.5 | N42: 20.4 | O42: 9 | P42: 3.6 | Q42: 5.2 | R42: 19.6 | S42: 20.2 | T42: 20 | U42: 13 | V42: 5.9 | W42: 29.5 | X42: 100 | Y42: 92.7 | Z42: 90 | AA42: 1.4 | AB42: 8.8 | AC42: 10.5 | AD42: 21 | AE42: 8.4 | AF42: 20 | AG42: 20 | AH42: 20 | AI42: 7.5 | AJ42: 5.1 | AK42: 12.4 | AL42: 14 | AM42: 3.4 | AN42: 18.8 | AQ42: 3.6 | AR42: 1.9 | AS42: 1 | AT42: 5.4 | AU42: 9.9 | AV42: 134.2 | AW42: 9.7 | AX42: 125.8 | AY42: 8.9 | AZ42: 0.6 | BA42: 1.1 | BB42: 26.4 | BC42: 79 | BD42: 20 | BE42: 2.7 | BF42: 2.2 | BG42: 2.3 | BH42: 2.1 | BI42: 0.8 | BK42: 19.7 | BL42: 7.8 | BM42: 0.5 | BN42: 1151.9
B43: 18:00 | C43: 14 | E43: 7.5 | F43: 11 | G43: 2 | I43: 9.4 | J43: 0.1 | K43: 14.4 | M43: 20.4 | N43: 20.3 | O43: 9 | P43: 3.6 | Q43: 5.2 | R43: 19.9 | S43: 20.1 | T43: 20 | U43: 13 | V43: 6.5 | W43: 31.1 | X43: 105.8 | Y43: 91.1 | Z43: 89.6 | AA43: 0.6 | AB43: 9.1 | AC43: 11 | AD43: 21 | AE43: 8.4 | AF43: 20 | AG43: 20 | AH43: 20 | AI43: 7.4 | AJ43: 2.9 | AK43: 10 | AL43: 12.7 | AM43: 3.4 | AN43: 18.8 | AQ43: 3.6 | AR43: 0.9 | AS43: 0.2 | AT43: 5.3 | AU43: 9.9 | AV43: 134.8 | AW43: 2.9 | AX43: 125.9 | AY43: 2.8 | AZ43: 0.6 | BB43: 30.6 | BC43: 86.7 | BD43: 20 | BE43: 2.8 | BF43: 2.6 | BG43: 2.3 | BH43: 2.3 | BI43: 0.3 | BK43: 19.9 | BL43: 7.8 | BN43: 1141.5
B44: 18:30 | C44: 13.1 | E44: 6.8 | F44: 11.2 | G44: 2 | I44: 9.4 | K44: 14.4 | M44: 20.3 | N44: 20.3 | O44: 9 | P44: 3.5 | Q44: 5.2 | R44: 20 | S44: 20.5 | T44: 20 | U44: 13 | V44: 7.3 | W44: 30.9 | X44: 88.2 | Y44: 89.7 | Z44: 90.4 | AB44: 10.3 | AC44: 10.3 | AD44: 21 | AE44: 8.4 | AF44: 20 | AG44: 20 | AH44: 20 | AI44: 7.8 | AK44: 10 | AL44: 10.9 | AM44: 3.4 | AN44: 18.8 | AQ44: 3.6 | AT44: 5.3 | AU44: 9.9 | AV44: 135.1 | AX44: 126 | AZ44: 0.6 | BB44: 28.1 | BC44: 82.9 | BD44: 20 | BE44: 2.8 | BF44: 2.6 | BG44: 2.3 | BH44: 2.4 | BK44: 20 | BL44: 7.8 | BN44: 1105.5
B45: 19:00 | C45: 13.5 | E45: 7.6 | F45: 12.8 | G45: 2 | I45: 9.7 | K45: 13.6 | M45: 20.3 | N45: 20.4 | O45: 8.9 | P45: 3.5 | Q45: 5.1 | R45: 20 | S45: 20.3 | T45: 20 | U45: 13 | V45: 7.6 | W45: 25.2 | X45: 79.5 | Y45: 82.5 | Z45: 93.5 | AB45: 5.8 | AC45: 6.2 | AD45: 21 | AE45: 8.4 | AF45: 20 | AG45: 20 | AH45: 20 | AI45: 7.8 | AK45: 7.4 | AL45: 11.9 | AM45: 3.4 | AN45: 18.8 | AQ45: 3.6 | AT45: 5.4 | AU45: 9.9 | AV45: 123.3 | AX45: 123.8 | AZ45: 0.6 | BB45: 24.1 | BC45: 77.8 | BD45: 20 | BE45: 3.1 | BF45: 2.8 | BG45: 2.3 | BH45: 2.4 | BK45: 20 | BL45: 8.2 | BN45: 1057
B46: 19:30 | C46: 13.8 | E46: 7.5 | F46: 20.4 | G46: 2 | I46: 10.1 | K46: 13.5 | M46: 20.3 | N46: 20.3 | O46: 8.9 | P46: 3.5 | Q46: 5.1 | R46: 20 | S46: 20.4 | T46: 20 | U46: 13 | V46: 6.7 | W46: 21.2 | X46: 78.2 | Y46: 83.6 | Z46: 93.6 | AB46: 7.3 | AC46: 6.5 | AD46: 21 | AE46: 8.4 | AF46: 20 | AG46: 20 | AH46: 20 | AI46: 7.6 | AK46: 9.8 | AL46: 13.5 | AM46: 3.4 | AN46: 18.8 | AQ46: 3.6 | AT46: 5.4 | AU46: 9.9 | AV46: 100.8 | AX46: 117.2 | AZ46: 0.6 | BB46: 20.4 | BC46: 68.4 | BD46: 20 | BE46: 3.2 | BF46: 2.8 | BG46: 2.3 | BH46: 2.4 | BK46: 20 | BL46: 8.1 | BN46: 1023.5
B47: 20:00 | C47: 12 | E47: 7.4 | F47: 20.4 | G47: 2 | I47: 9.8 | K47: 13.7 | M47: 20.2 | N47: 20.3 | O47: 8.9 | P47: 3.5 | Q47: 5.1 | R47: 20 | S47: 20.3 | T47: 20 | U47: 13 | V47: 5.2 | W47: 23.6 | X47: 88.3 | Y47: 52.2 | Z47: 92.7 | AB47: 2.6 | AC47: 3.2 | AD47: 20.9 | AE47: 8.4 | AF47: 20 | AG47: 20 | AH47: 20 | AI47: 7.6 | AK47: 8.8 | AL47: 13.5 | AN47: 18.8 | AQ47: 3.6 | AT47: 5.4 | AU47: 9.9 | AV47: 87.3 | AX47: 99.2 | AZ47: 0.6 | BB47: 19.2 | BC47: 67.7 | BD47: 20 | BE47: 3.2 | BF47: 2.8 | BG47: 1 | BH47: 2.4 | BK47: 20 | BL47: 8.2 | BN47: 952.9
B48: 20:30 | C48: 11.7 | E48: 7.6 | F48: 20.4 | G48: 2 | I48: 10 | K48: 14.1 | M48: 20.2 | N48: 20.3 | O48: 9 | P48: 3.5 | Q48: 5.1 | R48: 20 | S48: 20.5 | T48: 20 | U48: 13 | V48: 4.1 | W48: 23.6 | X48: 85.1 | Y48: 51.3 | Z48: 95.1 | AB48: 4.1 | AC48: 2.9 | AD48: 21 | AE48: 8.4 | AF48: 20 | AG48: 20 | AH48: 20 | AI48: 7.6 | AK48: 10.3 | AL48: 14 | AN48: 18.8 | AQ48: 3.6 | AT48: 5.4 | AU48: 9.9 | AV48: 72.8 | AX48: 78.9 | AZ48: 0.6 | BB48: 20.4 | BC48: 69 | BD48: 20 | BE48: 3.1 | BF48: 2.9 | BG48: 2 | BH48: 2.4 | BK48: 20 | BL48: 8.2 | BN48: 922.9
B49: 21:00 | C49: 11.9 | E49: 8.7 | F49: 20.4 | G49: 2 | I49: 9.8 | K49: 14.1 | M49: 20.3 | N49: 20.4 | O49: 9 | P49: 3.5 | Q49: 5.2 | R49: 20 | S49: 20.1 | T49: 20 | U49: 13 | V49: 6.5 | W49: 21.9 | X49: 81.1 | Y49: 38.9 | Z49: 83.1 | AB49: 3.2 | AC49: 3.4 | AD49: 21 | AE49: 8.4 | AF49: 20 | AG49: 20 | AH49: 20 | AI49: 7.6 | AK49: 10 | AL49: 12.8 | AN49: 18.8 | AQ49: 3.6 | AT49: 5.4 | AU49: 9.9 | AV49: 62.2 | AX49: 73.1 | AZ49: 0.6 | BB49: 21.8 | BC49: 65.7 | BD49: 20 | BE49: 3.2 | BF49: 2.9 | BG49: 2.3 | BH49: 2.4 | BK49: 20 | BL49: 8.2 | BN49: 876.4
B50: 21:30 | C50: 11.9 | E50: 8.9 | F50: 20.4 | G50: 2 | I50: 9.8 | K50: 14.2 | M50: 20.3 | N50: 20.3 | O50: 9 | P50: 3.6 | Q50: 5.2 | R50: 20 | S50: 19.9 | T50: 20 | U50: 13 | V50: 5.9 | W50: 14.2 | X50: 74.3 | Y50: 47.4 | Z50: 87.1 | AB50: 2.6 | AC50: 3 | AD50: 21 | AE50: 8.4 | AF50: 20 | AG50: 20 | AH50: 20 | AI50: 7.6 | AK50: 10.4 | AL50: 13.9 | AN50: 18.8 | AQ50: 3.6 | AT50: 5.4 | AU50: 9.9 | AV50: 52.6 | AX50: 73.1 | AZ50: 0.6 | BB50: 18.7 | BC50: 65.9 | BD50: 20 | BE50: 3.2 | BF50: 2.9 | BG50: 2.3 | BH50: 2.4 | BK50: 20 | BL50: 8.2 | BN50: 861.9
B51: 22:00 | C51: 12 | E51: 6.7 | F51: 20.4 | G51: 2 | I51: 10 | K51: 14.2 | M51: 20.2 | N51: 20.4 | O51: 9.2 | P51: 3.5 | Q51: 5.2 | R51: 20 | S51: 20.1 | T51: 20 | U51: 13 | V51: 7.5 | W51: 15.6 | X51: 77.5 | Y51: 49.1 | Z51: 93.1 | AB51: 2.2 | AC51: 3.1 | AD51: 21 | AE51: 8.4 | AF51: 20 | AG51: 20 | AH51: 20 | AI51: 7.6 | AK51: 12.5 | AL51: 15.9 | AN51: 18.8 | AQ51: 3.6 | AT51: 5.2 | AU51: 9.9 | AV51: 50.6 | AX51: 74.5 | AZ51: 0.6 | BB51: 21.3 | BC51: 63.2 | BD51: 20 | BE51: 3.2 | BF51: 2.9 | BG51: 2.3 | BH51: 2.4 | BK51: 20 | BL51: 8.2 | BN51: 877.1
B52: 22:30 | C52: 11.5 | D52: 3.3 | E52: 7.6 | F52: 20.4 | G52: 2 | I52: 9.6 | K52: 14 | M52: 20.4 | N52: 20.3 | O52: 9.2 | P52: 3.6 | Q52: 5.2 | R52: 20 | S52: 20.2 | T52: 20 | U52: 13 | V52: 6.8 | W52: 12.7 | X52: 77.5 | Y52: 47.2 | Z52: 86.6 | AB52: 4.2 | AC52: 2.3 | AD52: 21 | AE52: 8.4 | AF52: 20 | AG52: 20 | AH52: 20 | AI52: 8.5 | AK52: 13.6 | AL52: 14.4 | AN52: 18.8 | AQ52: 3.6 | AT52: 5.4 | AU52: 9.9 | AV52: 50 | AX52: 55.6 | AZ52: 0.6 | BB52: 25 | BC52: 57.8 | BD52: 20 | BE52: 3.2 | BF52: 2.9 | BG52: 2.3 | BH52: 2.4 | BK52: 20 | BL52: 8.2 | BN52: 849.2
B53: 23:00 | C53: 12.7 | D53: 3.4 | E53: 7.9 | F53: 20.4 | G53: 2 | I53: 9.3 | K53: 14 | M53: 20.4 | N53: 20.3 | O53: 9.2 | P53: 3.6 | Q53: 5.2 | R53: 20 | S53: 20.2 | T53: 20 | U53: 13 | V53: 4.1 | W53: 12.1 | X53: 69.4 | Y53: 41.2 | Z53: 77.1 | AB53: 2.7 | AC53: 1.7 | AD53: 20.9 | AE53: 8.4 | AF53: 20 | AG53: 20 | AH53: 20 | AI53: 4.7 | AK53: 9.1 | AL53: 11.9 | AN53: 18.8 | AQ53: 3.6 | AT53: 5.4 | AU53: 9.9 | AV53: 37.9 | AX53: 53.8 | AZ53: 0.6 | BB53: 20.8 | BC53: 58.3 | BD53: 20 | BE53: 3.2 | BF53: 2.9 | BG53: 2.3 | BH53: 2.4 | BK53: 20 | BL53: 8.2 | BN53: 793
B54: 23:30 | C54: 13.1 | D54: 3.4 | E54: 8.4 | F54: 19.8 | G54: 2 | I54: 9.8 | K54: 13.5 | M54: 20.2 | N54: 20.3 | O54: 9.2 | P54: 3.6 | Q54: 5.1 | R54: 19.8 | S54: 20.4 | T54: 20 | U54: 13 | V54: 3.5 | W54: 12.2 | X54: 69.4 | Y54: 39.2 | Z54: 73.1 | AB54: 2.5 | AC54: 2.6 | AD54: 20.9 | AE54: 8.4 | AF54: 20 | AG54: 20 | AH54: 20 | AI54: 0.7 | AK54: 11.1 | AL54: 13.1 | AN54: 18.8 | AQ54: 3.6 | AT54: 5.3 | AU54: 9.9 | AV54: 28.5 | AX54: 34.2 | AZ54: 0.6 | BB54: 20.5 | BC54: 57.9 | BD54: 19.9 | BE54: 3.2 | BF54: 2.9 | BG54: 2.3 | BH54: 2.4 | BK54: 20 | BL54: 8.2 | BN54: 756.5
B55: 0:00 | C55: 12.7 | D55: 3.4 | E55: 8.6 | F55: 17.4 | G55: 2 | I55: 10.4 | K55: 13.3 | M55: 20.4 | N55: 20.5 | O55: 9.2 | P55: 3.5 | Q55: 5.1 | R55: 19.7 | S55: 20.6 | T55: 20 | U55: 13 | V55: 4 | W55: 8.5 | X55: 59.7 | Y55: 35.4 | Z55: 77.4 | AB55: 1.4 | AC55: 1.8 | AD55: 21 | AE55: 8.4 | AF55: 20 | AG55: 20 | AH55: 20 | AI55: 1.1 | AK55: 12.5 | AL55: 14.5 | AN55: 18.8 | AQ55: 3.6 | AT55: 5.4 | AU55: 9.8 | AV55: 31.5 | AX55: 42.9 | AZ55: 0.6 | BB55: 21.5 | BC55: 59.2 | BD55: 20 | BE55: 3.2 | BF55: 2.9 | BG55: 2.3 | BH55: 2.4 | BK55: 19.8 | BL55: 8.2 | BN55: 757.6
B56: EJEC MWh | C56: 309.6 | D56: 74.55 | E56: 187.65 | F56: 355.5 | G56: 48 | H56: 0 | I56: 239.7 | J56: 7.05 | K56: 356.7 | L56: 0 | M56: 478.9 | N56: 488.6 | O56: 217.45 | P56: 86.2 | Q56: 123.95 | R56: 478.5 | S56: 485.15 | T56: 478.9 | U56: 322.4 | V56: 272.6 | W56: 573.1 | X56: 2038.1 | Y56: 1359.35 | Z56: 1845 | AA56: 218.65 | AB56: 135.35 | AC56: 130.9 | AD56: 503.85 | AE56: 197.95 | AF56: 480 | AG56: 480 | AH56: 479.65 | AI56: 176.95 | AJ56: 626.35 | AK56: 297.7 | AL56: 360.75 | AM56: 55.5 | AN56: 451.2 | AO56: 0 | AP56: 1.8 | AQ56: 86.9 | AR56: 124.7 | AS56: 114.85 | AT56: 123.8 | AU56: 237.9 | AV56: 1431.2 | AW56: 1020.6 | AX56: 1475.75 | AY56: 843.5 | AZ56: 14.4 | BA56: 144 | BB56: 560.55 | BC56: 1594.75 | BD56: 479.7 | BE56: 81.9 | BF56: 64.15 | BG56: 54.4 | BH56: 55.2 | BI56: 106.3 | BJ56: 0 | BK56: 478.95 | BL56: 184.9 | BM56: 156.1 | BN56: 24858.05
L70: TERMOELÉCTRICA | M70: 1067.15 | N70: 4.2929755 | O70: #FF0000
L71: SOLAR | M71: 3363.9 | N71: 13.532437 | O71: #FBFB00
L72: HIDROELÉCTRICA | M72: 8351.9 | N72: 33.598372 | O72: #00B0F0
L73: EÓLICA | M73: 12075.1 | N73: 48.576216 | O73: #FBBD00

Sheet COGENERACIÓN
B3: lunes, 27 de Enero del 2025
B5: CENTRALES DE COGENERACIÓN DEL SEIN
B6: HORA | C6: AGRO INDUSTRIAL PARAMONGA S.A. | D6: AGROAURORA S.A.C. | E6: AGROINDUSTRIAS SAN JACINTO S.A.A. | F6: BIOENERGIA DEL CHIRA S.A. | G6: GM OPERACIONES S.A.C. | H6: SDF ENERGIA SAC | I6: TOTAL COGENERACION
C7: C.T. PARAMONGA | D7: C.T. MAPLE | E7: C.T SAN JACINTO | F7: C.T. CAÑA BRAVA | G7: C.T. REFINERÍA TALARA | H7: C.T. OQUENDO | I7: MW
B8: 0:30 | C8: 14 | D8: 15.1 | E8: 6.9 | F8: 10 | G8: 54.6 | H8: 32.2 | I8: 132.8
B9: 1:00 | C9: 14 | D9: 15.1 | E9: 7 | F9: 10.1 | G9: 54.3 | H9: 32.2 | I9: 132.7
B10: 1:30 | C10: 13.9 | D10: 15.1 | E10: 7.2 | F10: 9.4 | G10: 54.4 | H10: 32.2 | I10: 132.2
B11: 2:00 | C11: 13 | D11: 15.1 | E11: 7.5 | F11: 9.4 | G11: 54.4 | H11: 32.2 | I11: 131.6
B12: 2:30 | C12: 13.9 | D12: 15.1 | E12: 7.2 | F12: 9.3 | G12: 54.4 | H12: 32 | I12: 131.9
B13: 3:00 | C13: 13.7 | D13: 15.1 | E13: 8.1 | F13: 9.5 | G13: 54.3 | H13: 32 | I13: 132.7
B14: 3:30 | C14: 12 | D14: 15.1 | E14: 7.6 | F14: 10.1 | G14: 53.8 | H14: 32.1 | I14: 130.7
B15: 4:00 | C15: 13.8 | D15: 14.8 | E15: 8.8 | F15: 9.7 | G15: 53.7 | H15: 32.1 | I15: 132.9
B16: 4:30 | C16: 13.9 | D16: 15.1 | E16: 8.3 | F16: 10.1 | G16: 53.8 | H16: 32 | I16: 133.2
B17: 5:00 | C17: 13.9 | E17: 7.8 | F17: 9.8 | G17: 54 | H17: 32.3 | I17: 117.8
B18: 5:30 | C18: 13.9 | E18: 8.5 | F18: 9.3 | G18: 53.5 | H18: 32.3 | I18: 117.5
B19: 6:00 | C19: 14 | E19: 9.3 | F19: 10.1 | G19: 54.1 | H19: 32.3 | I19: 119.8
B20: 6:30 | C20: 14 | E20: 7.4 | F20: 10.6 | G20: 53.9 | H20: 32.3 | I20: 118.2
B21: 7:00 | C21: 14 | E21: 7 | F21: 10 | G21: 54.4 | H21: 32.1 | I21: 117.5
B22: 7:30 | C22: 14.1 | E22: 6.7 | F22: 9.9 | G22: 54.3 | H22: 32.4 | I22: 117.4
B23: 8:00 | C23: 14 | E23: 7.7 | F23: 10.3 | G23: 54.3 | H23: 32.4 | I23: 118.7
B24: 8:30 | C24: 14.1 | E24: 7.5 | F24: 10.2 | G24: 54.5 | H24: 32.2 | I24: 118.5
B25: 9:00 | C25: 14 | E25: 7.7 | F25: 10.1 | G25: 54.3 | H25: 32.2 | I25: 118.3
B26: 9:30 | C26: 14 | E26: 7.5 | F26: 10.4 | G26: 54.8 | H26: 32 | I26: 118.7
B27: 10:00 | C27: 13.9 | E27: 7.4 | F27: 10.6 | G27: 54.7 | H27: 31.8 | I27: 118.4
B28: 10:30 | C28: 14 | E28: 7.4 | F28: 10.4 | G28: 54.9 | H28: 31.6 | I28: 118.3
... B51: 22:00 | C51: 12 | E51: 6.7 | F51: 10 | G51: 46 | H51: 32 | I51: 106.7
B52: 22:30 | C52: 11.5 | D52: 3.3 | E52: 7.6 | F52: 9.6 | G52: 36.7 | H52: 32.1 | I52: 100.8
B53: 23:00 | C53: 12.7 | D53: 3.4 | E53: 7.9 | F53: 9.3 | G53: 36.9 | H53: 32 | I53: 102.2
B54: 23:30 | C54: 13.1 | D54: 3.4 | E54: 8.4 | F54: 9.8 | G54: 36.8 | H54: 32 | I54: 103.5
B55: 0:00 | C55: 12.7 | D55: 3.4 | E55: 8.6 | F55: 10.4 | G55: 37 | H55: 31.9 | I55: 104
B56: EJEC MWh | C56: 309.6 | D56: 74.55 | E56: 187.65 | F56: 239.7 | G56: 1257.5 | H56: 765 | I56: 2834

Sheet EVO_PRO_ENE
B3: miércoles, 1 de Enero del 2025 - lunes, 27 de Enero del 2025
B5: EVOLUCIÓN DE LA PRODUCCIÓN DE LA ENERGÍA DIARIA DE LOS INTEGRANTES DEL COES (MWh)
B6: EMPRESA | C6: CENTRAL | D6: UNIDAD | E6: TIPO | F6: Enero
F7: 1 | G7: 2 | H7: 3 | I7: 4 | J7: 5 | K7: 6 | L7: 7 | M7: 8 | N7: 9 | O7: 10 | P7: 11 | Q7: 12 | R7: 13 | S7: 14 | T7: 15 | U7: 16 | V7: 17 | W7: 18 | X7: 19 | Y7: 20 | Z7: 21 | AA7: 22 | AB7: 23 | AC7: 24 | AD7: 25 | AE7: 26 | AF7: 27 | AG7: TOTAL
B8: AGRO INDUSTRIAL PARAMONGA S.A. | C8: C.T. PARAMONGA | D8: TV-01 | E8: TERMOELÉCTRICA | L8: 224.55 | M8: 388.3 | N8: 387.45 | O8: 389.1 | P8: 389.05 | Q8: 381.85 | R8: 353.1 | S8: 355.3 | T8: 354.05 | U8: 346.3 | V8: 315.55 | W8: 319.35 | X8: 312.65 | Y8: 309.55 | Z8: 331.15 | AA8: 333.25 | AB8: 324.9 | AC8: 330.55 | AD8: 328.6 | AE8: 314.05 | AF8: 309.6 | AG8: 7098.25
B9: AGROAURORA S.A.C. | C9: C.T. MAPLE ETANOL | D9: TV | E9: TERMOELÉCTRICA | F9: 360 | H9: 179.75 | I9: 379.5 | J9: 393.65 | K9: 392.45 | L9: 383.75 | M9: 362.8 | N9: 358.2 | O9: 362.8 | P9: 359.2 | Q9: 375.75 | R9: 354.95 | S9: 349.4 | T9: 325.2 | U9: 355.95 | V9: 340.75 | W9: 305.8 | X9: 409.85 | Y9: 412.35 | Z9: 408.2 | AA9: 379.6 | AB9: 386.1 | AC9: 352.75 | AD9: 334.4 | AE9: 302.75 | AF9: 74.55 | AG9: 9000.45
B10: AGROINDUSTRIAS SAN JACINTO S.A.A. | C10: C.T. SAN JACINTO | D10: CENTRAL | E10: TERMOELÉCTRICA | K10: 58.45 | L10: 96.65 | M10: 161.7 | N10: 175.7 | O10: 179.9 | P10: 182.405 | Q10: 177.25 | R10: 172.8 | S10: 188.05 | T10: 187.3 | U10: 186.2334 | V10: 186.05 | W10: 187.85 | X10: 197.1 | Y10: 193 | Z10: 159.85 | AA10: 185.4 | AB10: 176.35 | AC10: 182.95 | AD10: 185 | AE10: 170.8 | AF10: 187.65 | AG10: 3778.4384
B11: ANDEAN POWER S.A.C. | C11: C.H. CARHUAC | D11: CENTRAL | E11: HIDROELÉCTRICA | F11: 436.45 | G11: 447.15 | H11: 484.25 | I11: 484.6 | J11: 483.35 | K11: 484 | L11: 450.25 | M11: 439.95 | N11: 429.3 | O11: 414.6 | P11: 437.75 | Q11: 418.5 | R11: 384.05 | S11: 410.75 | T11: 360.5 | U11: 432.65 | V11: 420.55 | W11: 384.55 | X11: 413.3 | Y11: 306.8 | Z11: 285.4 | AA11: 277.45 | AB11: 309 | AC11: 288.3 | AD11: 331.05 | AE11: 327.85 | AF11: 355.5 | AG11: 10697.85
B12: ASOCIACIÓN SANTA LUCIA DE CHACAS | C12: C.H. HUALLIN | D12: CENTRAL | E12: HIDROELÉCTRICA | F12: 48 | G12: 45.85 | H12: 48 | I12: 48 | J12: 48 | K12: 48 | L12: 48 | M12: 48 | N12: 48 | O12: 48 | P12: 29.55 | Q12: 48 | R12: 46.9 | S12: 48 | T12: 48 | U12: 48 | V12: 48 | W12: 48 | X12: 48 | Y12: 46.15 | Z12: 46.25 | AA12: 48 | AB12: 48 | AC12: 48 | AD12: 48 | AE12: 44.85 | AF12: 48 | AG12: 1267.55
B13: ATRIA ENERGIA S.A.C. | C13: C.H. PURMACANA | D13: CENTRAL | E13: HIDROELÉCTRICA | AG13: 0
B14: BIOENERGIA DEL CHIRA S.A. | C14: C.T. CAÑA BRAVA | D14: CENTRAL | E14: TERMOELÉCTRICA | F14: 230.05 | G14: 4.15 | H14: 207.1 | I14: 231.25 | J14: 226.25 | K14: 229.1 | L14: 220.25 | M14: 242.55 | N14: 215 | O14: 246.75 | P14: 247.3 | Q14: 230.9 | R14: 230.2 | S14: 243 | T14: 240.05 | U14: 241.5 | V14: 213.8 | W14: 244.1 | X14: 238 | Y14: 244.65 | Z14: 240.15 | AA14: 250.3 | AB14: 256.05 | AC14: 255.25 | AD14: 210.35 | AE14: 237.6 | AF14: 239.7 | AG14: 6115.35
B15: CELEPSA | C15: C.H. EL PLATANAL | D15: CENTRAL | E15: HIDROELÉCTRICA | F15: 4523.65 | G15: 4474.1 | H15: 4762.5 | I15: 5166.1 | J15: 5163.45 | K15: 5266.75 | L15: 5280.35 | M15: 5023.05 | N15: 5010.85 | O15: 5120.1 | P15: 5245 | Q15: 5145.95 | R15: 5180.55 | S15: 5298.45 | T15: 5167.65 | U15: 5203.4 | V15: 5292.25 | W15: 5062.05 | X15: 5063.7 | Y15: 5258.25 | Z15: 5275.15 | AA15: 5301.65 | AB15: 5356.7 | AC15: 5250.1 | AD15: 5063.2 | AE15: 4722.9 | AF15: 5011.1 | AG15: 137688.95
B16: CELEPSA RENOVABLES S.R.L. | C16: C.H. MARAÑON | D16: CENTRAL | E16: HIDROELÉCTRICA | F16: 473.65 | G16: 473.1 | H16: 415.2 | I16: 360.25 | J16: 431.7 | K16: 469.85 | L16: 472.8 | M16: 472.8 | N16: 473.1415 | O16: 472.8 | P16: 472.8 | Q16: 472.8 | R16: 472.8 | S16: 472.8 | T16: 472.8 | U16: 472.8 | V16: 472.8 | W16: 472.8 | X16: 472.8 | Y16: 453.45 | Z16: 475.45 | AA16: 473.55 | AB16: 448.05 | AC16: 464.95 | AD16: 466.95 | AE16: 472.75 | AF16: 472.8 | AG16: 12498.442
B17: CENTRALES SANTA ROSA S.A.C. | C17: C.H. SANTA ROSA I | D17: CENTRAL | E17: HIDROELÉCTRICA | F17: 25.45 | G17: 25.95 | H17: 19.75 | I17: 13.4 | J17: 18.1 | K17: 20.2 | L17: 22.1 | M17: 23.3 | N17: 24.3 | O17: 24.45 | P17: 25.2 | Q17: 25.2 | R17: 25.35 | S17: 23.95 | T17: 14.65 | U17: 25.4 | V17: 25.75 | W17: 26.2 | X17: 26.3 | Y17: 24.8 | Z17: 24.55 | AA17: 23.7 | AB17: 26.3 | AC17: 26.4 | AD17: 26.4 | AE17: 26.35 | AF17: 24.8 | AG17: 638.3
B18: CENTRALES SANTA ROSA S.A.C. | C18: C.H. SANTA ROSA II | D18: CENTRAL | E18: HIDROELÉCTRICA | F18: 37.7 | G18: 37.1 | H18: 31.9 | I18: 24.55 | J18: 31.45 | K18: 35.3 | L18: 35.95 | M18: 36.35 | N18: 37.05 | O18: 37.2 | P18: 38.45 | Q18: 38.2 | R18: 37.9 | S18: 36.25 | T18: 22.3 | U18: 36.7 | V18: 37.15 | W18: 39.2 | X18: 38.45 | Y18: 36.85 | Z18: 38.1 | AA18: 37.05 | AB18: 39.65 | AC18: 38.3 | AD18: 40.15 | AE18: 38.85 | AF18: 32 | AG18: 970.1
B19: CHINANGO S.A.C. | C19: C.H. CHIMAY | D19: CENTRAL | E19: HIDROELÉCTRICA | F19: 3094.35 | G19: 3340.85 | H19: 3399.5 | I19: 3452.55 | J19: 3481.7 | K19: 3446.85 | L19: 2227.35 | M19: 3331.064 | N19: 2748.9 | O19: 3452.7 | P19: 2273.8 | Q19: 3314.15 | R19: 3434.2 | S19: 3445.75 | T19: 3447 | U19: 3516.65 | V19: 3387.15 | W19: 3459.45 | X19: 3425.5 | Y19: 851.55 | Z19: 1126.4 | AA19: 1758.95 | AB19: 1615.9 | AC19: 2847.55 | AD19: 3397.55 | AE19: 3339.8 | AF19: 3386.1 | AG19: 80003.264
B20: CHINANGO S.A.C. | C20: C.H. YANANGO | D20: CENTRAL | E20: HIDROELÉCTRICA | F20: 816.75 | G20: 970.5 | H20: 1005.45 | I20: 1002.9 | J20: 1005 | K20: 1004.55 | L20: 1004.4 | M20: 1004.0105 | N20: 1004.4 | O20: 993.6 | P20: 999.4 | Q20: 1004.85 | R20: 993.1 | S20: 929.1 | T20: 853.8 | U20: 785.6 | V20: 742.25 | W20: 738.7 | X20: 823.5 | Y20: 510.57261 | Z20: 1000.85 | AA20: 1004.8 | AB20: 1000.3 | AC20: 1001.05 | AD20: 1002.7 | AE20: 975.55 | AF20: 975.35 | AG20: 25153.033
B21: COLCA SOLAR S.A.C. | C21: C.S. YARUCAYA | D21: CENTRAL | E21: SOLAR | F21: 4.85 | G21: 4.35 | H21: 6.75 | I21: 6.6 | J21: 7.6 | K21: 4.8 | L21: 5.35 | M21: 7.05 | N21: 7.3 | O21: 4.7 | P21: 6.9 | Q21: 7.95 | R21: 6.7 | S21: 6.95 | T21: 8.85 | U21: 6.85 | V21: 6.9 | W21: 6.7 | X21: 6.7 | Y21: 9 | Z21: 5.05 | AA21: 5.6 | AB21: 7.05 | AC21: 6.65 | AD21: 8.1 | AE21: 8.6 | AF21: 7.05 | AG21: 180.95
B22: EGASA | C22: C.H. CHARCANI III | D22: CENTRAL | E22: HIDROELÉCTRICA | F22: 144.4 | G22: 148.8 | H22: 151.3 | I22: 151.2 | J22: 154.25 | K22: 151.25 | L22: 151.15 | M22: 151.2 | N22: 151.2 | O22: 153.1 | P22: 156.51 | Q22: 156.7 | R22: 156.15 | S22: 155.05 | T22: 154.45 | U22: 158.35 | V22: 164.1 | W22: 163.65 | X22: 90.85 | Y22: 163.2 | Z22: 163.9 | AA22: 154.65 | AB22: 153.6 | AC22: 157.3 | AD22: 158.7 | AE22: 158.4 | AF22: 158.2 | AG22: 4131.61
B23: EGASA | C23: C.H. CHARCANI IV | D23: CENTRAL | E23: HIDROELÉCTRICA | F23: 239.55 | G23: 234.3 | H23: 245.4 | I23: 241.3 | J23: 241.65 | K23: 239.15 | L23: 234.75 | M23: 231.05 | N23: 231.35 | O23: 235.64 | P23: 230.91 | Q23: 236.25 | R23: 236.1 | S23: 231.15 | T23: 229.7 | U23: 233.5 | V23: 238.6 | W23: 172.1 | X23: 73.1 | Y23: 120 | Z23: 121.15 | AA23: 46.8 | AG23: 4543.5
B24: EGASA | C24: C.H. CHARCANI V | D24: CENTRAL | E24: HIDROELÉCTRICA | F24: 1540.9 | G24: 1524 | H24: 1529.2 | I24: 1526.8 | J24: 1554.35 | K24: 1503.95 | L24: 1515 | M24: 1511.6 | N24: 1504.7 | O24: 1496.02 | P24: 1512.455 | Q24: 1528 | R24: 1503.7 | S24: 1525.2 | T24: 1515.85 | U24: 1768.05 | V24: 1786.1 | W24: 1782.85 | X24: 1808.75 | Y24: 1817.45 | Z24: 1801.45 | AA24: 1525.8 | AB24: 1552.7 | AC24: 1510.45 | AD24: 1548.95 | AE24: 1508.8 | AF24: 1519 | AG24: 42722.075
B25: EGASA | C25: C.H. CHARCANI VI | D25: CENTRAL | E25: HIDROELÉCTRICA | F25: 134.95 | G25: 136.9 | H25: 144.1 | I25: 126 | J25: 140.8 | K25: 138.75 | L25: 141.85 | M25: 137.65 | N25: 139.9 | O25: 138.645 | P25: 139.425 | Q25: 141.25 | R25: 140.55 | S25: 137.7 | T25: 137.25 | U25: 139.15 | V25: 162.8 | W25: 168.9 | X25: 157.05 | Y25: 165.5 | Z25: 170.8 | AA25: 131.7 | AB25: 135.4 | AC25: 132.45 | AD25: 138.15 | AE25: 136.8 | AF25: 135.8 | AG25: 3850.22
B26: EGASA | C26: C.T. CHILINA DIESEL | D26: CENTRAL | E26: TERMOELÉCTRICA | G26: 4.25 | AE26: 12.8 | AG26: 17.05
B27: EGASA | C27: C.T. CHILINA DIESEL | D27: TG | E27: TERMOELÉCTRICA | AD27: 4.25 | AG27: 4.25
B28: EGASA | C28: C.T. MOLLENDO DIESEL | D28: CENTRAL | E28: TERMOELÉCTRICA | AG28: 0
B29: EGEJUNIN | C29: C.H. HUASAHUASI I | D29: CENTRAL | E29: HIDROELÉCTRICA | F29: 247.6 | G29: 430.95 | H29: 474.25 | I29: 475.2 | J29: 473.2 | K29: 475.2 | L29: 470.1 | M29: 472.65 | N29: 445.9 | O29: 414.8 | P29: 412.6 | Q29: 475.2 | R29: 464.3 | S29: 382.85 | T29: 325.1 | U29: 275.75 | V29: 261.35 | W29: 249.35 | X29: 248.6 | Y29: 402.3 | Z29: 360.7 | AA29: 453.4 | AB29: 433.3 | AC29: 414.3 | AD29: 383.65 | AE29: 336.8 | AF29: 356.7 | AG29: 10616.1
B30: EGEJUNIN | C30: C.H. RUNATULLO II | D30: CENTRAL | E30: HIDROELÉCTRICA | F30: 349.2 | G30: 426.2 | H30: 478.5 | I30: 478.35 | J30: 477.55 | K30: 477 | L30: 477.65 | M30: 478.6 | N30: 481.25 | O30: 481.2 | P30: 480 | Q30: 473.45 | R30: 475.35 | S30: 476.6 | T30: 478.8 | U30: 475.5 | V30: 464.45 | W30: 437.05 | X30: 467.85 | Y30: 474.8 | Z30: 476.9 | AA30: 475.75 | AB30: 475.6 | AC30: 474.45 | AD30: 475.25 | AE30: 441.15 | AF30: 478.9 | AG30: 12607.35
B31: EGEJUNIN | C31: C.H. RUNATULLO III | D31: CENTRAL | E31: HIDROELÉCTRICA | F31: 450.65 | G31: 490.95 | H31: 491.2 | I31: 490.75 | J31: 489.65 | K31: 490.05 | L31: 489.75 | M31: 489.8 | N31: 490.05 | O31: 490.15 | P31: 490.1 | Q31: 489.25 | R31: 489.35 | S31: 489.4 | T31: 489.05 | U31: 489.3 | V31: 489.4 | W31: 488.65 | X31: 488.4 | Y31: 485.75 | Z31: 485.45 | AA31: 486.15 | AB31: 487.75 | AC31: 488.1 | AD31: 487.8 | AE31: 452.3 | AF31: 488.6 | AG31: 13127.8
B32: EGEJUNIN | C32: C.H. SANTA CRUZ I | D32: CENTRAL | E32: HIDROELÉCTRICA | F32: 279.3 | G32: 256 | H32: 177.35 | I32: 234.2 | J32: 290.3 | K32: 280.9 | L32: 289.2 | M32: 288 | N32: 289.8 | O32: 276.3 | P32: 279.6 | Q32: 288.5 | R32: 287.6 | S32: 289.3 | T32: 289.7 | U32: 289.9 | V32: 250.4 | W32: 222.45 | X32: 143.4 | Y32: 216 | Z32: 206.35 | AA32: 191.6 | AB32: 197 | AC32: 223.8 | AD32: 212.7 | AE32: 208.5 | AF32: 217.45 | AG32: 6675.6
B33: EGEMSA | C33: C.H. MACHUPICCHU | D33: CENTRAL | E33: HIDROELÉCTRICA | F33: 4014.15 | G33: 3890.05 | H33: 4014.9 | I33: 3957.7 | J33: 3526.95 | K33: 4017.5 | L33: 4007.85 | M33: 3997.65 | N33: 3976.3 | O33: 4001.35 | P33: 3995.1 | Q33: 3227.3 | R33: 4003.9 | S33: 3993.295 | T33: 3981.75 | U33: 3999.55 | V33: 4000 | W33: 3980.55 | X33: 4005.15 | Y33: 3997 | Z33: 3984.45 | AA33: 3999.35 | AB33: 3957.35 | AC33: 3952.3 | AD33: 3979.55 | AE33: 3984.25 | AF33: 3979.75 | AG33: 106424.99
B34: EGESUR | C34: C.H. ARICOTA I | D34: CENTRAL | E34: HIDROELÉCTRICA | F34: 172.05 | G34: 172.05 | H34: 172.25 | I34: 171 | J34: 171.45 | K34: 170.85 | L34: 169.05 | M34: 169.55 | N34: 172.1 | O34: 179.4 | P34: 176.65 | Q34: 179.65 | R34: 200.4 | S34: 186.25 | T34: 187.3 | U34: 172.25 | V34: 183.85 | W34: 181.6 | X34: 182.65 | Y34: 184.05 | Z34: 183.15 | AA34: 186.45 | AB34: 180.45 | AC34: 177.8 | AD34: 181.154 | AE34: 183.7 | AF34: 183.55 | AG34: 4830.654
B35: EGESUR | C35: C.H. ARICOTA II | D35: CENTRAL | E35: HIDROELÉCTRICA | AC35: 61.75 | AD35: 62.7405 | AE35: 62.6 | AF35: 62.7 | AG35: 249.7905
B36: EGESUR | C36: C.T. INDEPENDENCIA | D36: CENTRAL | E36: TERMOELÉCTRICA | G36: 48.3 | H36: 166.35 | I36: 140.45 | J36: 64.7 | K36: 212.35 | L36: 95 | M36: 108.5 | N36: 162.35 | O36: 129.65 | P36: 74.3 | Q36: 24.3 | R36: 122.15 | S36: 125.5 | T36: 123.85 | U36: 147.9 | V36: 221.9 | W36: 265.15 | X36: 89.45 | Y36: 142.55 | Z36: 240.85 | AA36: 145.5 | AB36: 160.3 | AC36: 63.2 | AD36: 97.056 | AF36: 44.4 | AG36: 3216.006
B37: ELECTRICA YANAPAMPA SAC | C37: C.H. YANAPAMPA | D37: CENTRAL | E37: HIDROELÉCTRICA | F37: 76.35 | G37: 78.35 | H37: 67.15 | I37: 71.6 | J37: 75.8 | K37: 79.4 | L37: 74.05 | M37: 82.95 | N37: 81.65 | O37: 83.5 | P37: 84 | Q37: 83.9 | R37: 85.8 | S37: 81.9 | T37: 85.9 | U37: 86.4 | V37: 82.45 | W37: 86.7 | X37: 86.55 | Y37: 84.35 | Z37: 85.15 | AA37: 85.15 | AB37: 84.45 | AC37: 84.55 | AD37: 84.75 | AE37: 85.15 | AF37: 86.2 | AG37: 2214.15
B38: ELECTROPERU | C38: C.H. MANTARO | D38: CENTRAL | E38: HIDROELÉCTRICA | F38: 15545.15 | G38: 15118.55 | H38: 15559.05 | I38: 14563.895 | J38: 15542.75 | K38: 15304.6 | L38: 15533.6 | M38: 15528.8 | N38: 14996.7 | O38: 15556.6 | P38: 15559.7 | Q38: 15542 | R38: 15555.85 | S38: 15532.55 | T38: 15518.25 | U38: 15549.2 | V38: 15546.15 | W38: 15533.25 | X38: 15023 | Y38: 15525.8 | Z38: 15205.1 | AA38: 15550.165 | AB38: 15518.65 | AC38: 14942.8 | AD38: 15521 | AE38: 14322.465 | AF38: 15500.3 | AG38: 414695.92
B39: ELECTROPERU | C39: C.H. RESTITUCION | D39: CENTRAL | E39: HIDROELÉCTRICA | F39: 5257.75 | G39: 5067.3 | H39: 5237.45 | I39: 4858.585 | J39: 5248.6 | K39: 5140.55 | L39: 5236.45 | M39: 5237.55 | N39: 5048.15 | O39: 5256.95 | P39: 3516.65 | Q39: 3595.4 | R39: 5258.55 | S39: 5249.2 | T39: 5260.2 | U39: 5268.25 | V39: 5268.85 | W39: 5273.25 | X39: 5069.5 | Y39: 5268.8 | Z39: 5134.35 | AA39: 5270.26 | AB39: 5254.85 | AC39: 5008.2 | AD39: 5222.6 | AE39: 4892.9123 | AF39: 5256.7 | AG39: 136657.86
B40: ELECTROPERU | C40: C.T. TUMBES | D40: MAK1 | E40: TERMOELÉCTRICA | H40: 31.13 | I40: 14.71 | U40: 95.025 | V40: 138.045 | W40: 15.9 | AG40: 294.81
B41: ELECTROPERU | C41: C.T. TUMBES | D41: MAK2 | E41: TERMOELÉCTRICA | H41: 29.09 | I41: 14.83 | U41: 96.38 | V41: 137.56 | W41: 15.93 | AG41: 293.79
B42: EMPRESA DE GENERACION ELECTRICA CANCHAYLLO SAC | C42: C.H. CANCHAYLLO | D42: CENTRAL | E42: HIDROELÉCTRICA | F42: 114.5 | G42: 103.6 | H42: 121.4 | I42: 119.45 | J42: 115.45 | K42: 97.35 | L42: 122.9 | M42: 123.75 | N42: 123.75 | O42: 123 | P42: 123.65 | Q42: 123.35 | R42: 123.35 | S42: 121.85 | T42: 114.7 | U42: 108.15 | V42: 102.45 | W42: 101.2 | X42: 117 | Y42: 122.25 | Z42: 124.05 | AA42: 123.95 | AB42: 121.6 | AC42: 119.6 | AD42: 124.1 | AE42: 123.85 | AF42: 123.95 | AG42: 3184.2
B43: EMPRESA DE GENERACION ELECTRICA RIO BAÑOS S.A.C. | C43: C.H. RUCUY | D43: CENTRAL | E43: HIDROELÉCTRICA | F43: 479.95 | G43: 479.15 | H43: 479.65 | I43: 474 | J43: 479.15 | K43: 479.3 | L43: 479.45 | M43: 479.25 | N43: 479 | O43: 478.95 | P43: 479.25 | Q43: 479 | R43: 479.45 | S43: 478.9 | T43: 477.7 | U43: 478.65 | V43: 479.1 | W43: 479.7 | X43: 479.25 | Y43: 478.6 | Z43: 478.85 | AA43: 479 | AB43: 478.6 | AC43: 478.55 | AD43: 478.4 | AE43: 477.6 | AF43: 478.5 | AG43: 12926.95
B44: EMPRESA DE GENERACION ELECTRICA SANTA ANA S.A.C. | C44: C.H. RENOVANDES H1 | D44: CENTRAL | E44: HIDROELÉCTRICA | F44: 485 | G44: 423.7 | H44: 485.75 | I44: 484.65 | J44: 485.9 | K44: 465 | L44: 483.85 | M44: 484.4 | N44: 484.8 | O44: 486 | P44: 385.15 | Q44: 485.4 | R44: 486.5 | S44: 484.965 | T44: 464.4 | U44: 485.9 | V44: 486 | W44: 484.85 | X44: 486.5 | Y44: 484.95 | Z44: 484.55 | AA44: 485.15 | AB44: 483.65 | AC44: 483.8 | AD44: 484.25 | AE44: 484.65 | AF44: 485.15 | AG44: 12894.865
B45: EMPRESA DE GENERACION HUALLAGA | C45: C.H. CHAGLLA | D45: CENTRAL | E45: HIDROELÉCTRICA | F45: 3199.75 | G45: 7586.7 | H45: 10939.2 | I45: 8710.6 | J45: 10473.2 | K45: 10518.25 | L45: 10829.2 | M45: 10647.45 | N45: 10225.1 | O45: 10768.1 | P45: 10912.65 | Q45: 10121 | R45: 10631.6 | S45: 10732 | T45: 10715.3 | U45: 11168.8 | V45: 11387.7 | W45: 7963.15 | X45: 3828 | Y45: 9914.7 | Z45: 10536.25 | AA45: 10815.95 | AB45: 10882.25 | AC45: 11012.55 | AD45: 10957.85 | AE45: 10967.4 | AF45: 10889.7 | AG45: 267334.4
B46: EMPRESA DE GENERACION HUALLAGA | C46: P.C.H. CHAGLLA | D46: CENTRAL | E46: HIDROELÉCTRICA | F46: 156 | G46: 156 | H46: 156 | I46: 155.3 | J46: 156 | K46: 156 | L46: 156 | M46: 156 | N46: 156 | O46: 155.95 | P46: 156 | Q46: 156 | R46: 155.95 | S46: 156 | T46: 156 | U46: 156 | V46: 156 | W46: 156 | X46: 156 | Y46: 156 | Z46: 156 | AA46: 156 | AB46: 156 | AC46: 156 | AD46: 156 | AE46: 155.9 | AF46: 155.95 | AG46: 4211.05
B47: EMPRESA DE GENERACION HUANZA | C47: C.H. HUANZA | D47: CENTRAL | E47: HIDROELÉCTRICA | F47: 1305.9 | G47: 1930.85 | H47: 2249.7 | I47: 2277.7 | J47: 2270.7 | K47: 2002.5 | L47: 1713.8 | M47: 1676.2 | N47: 1549.45 | O47: 1463.3 | P47: 1644.65 | Q47: 1485.8 | R47: 1510.35 | S47: 1604.5 | T47: 1343.3 | U47: 1666.95 | V47: 1601.9 | W47: 1567.7 | X47: 1687.05 | Y47: 1223.6 | Z47: 1069.2 | AA47: 1054.65 | AB47: 1121.5 | AC47: 937.9 | AD47: 1035.05 | AE47: 990.3 | AF47: 1219.6 | AG47: 41204.1
B48: EMPRESA ELECTRICA AGUA AZUL | C48: C.H. POTRERO | D48: CENTRAL | E48: HIDROELÉCTRICA | F48: 476.9 | G48: 478.3 | H48: 471.8 | I48: 476.45 | J48: 475.2 | K48: 477.75 | L48: 474.7 | M48: 399.25 | N48: 425.5 | O48: 479.95 | P48: 478.8 | Q48: 477.1 | R48: 479.25 | S48: 469.8 | T48: 477.65 | U48: 478.55 | V48: 473.45 | W48: 479.75 | X48: 480 | Y48: 480 | Z48: 479.95 | AA48: 480 | AB48: 480 | AC48: 480 | AD48: 476.95 | AE48: 471.35 | AF48: 478.9 | AG48: 12757.3
B49: EMPRESA ELECTRICA RIO DOBLE | C49: C.H. LAS PIZARRAS | D49: CENTRAL | E49: HIDROELÉCTRICA | F49: 450.2 | G49: 451.5 | H49: 442.55 | I49: 428.7 | J49: 452.7 | K49: 454.2 | L49: 455.15 | M49: 454.15 | N49: 453.645 | O49: 453.2 | P49: 453.92 | Q49: 453.85 | R49: 453.5 | S49: 453.95 | T49: 453.3 | U49: 452 | V49: 451.705 | W49: 452.58 | X49: 452.55 | Y49: 453.215 | Z49: 437.035 | AA49: 432.15 | AB49: 428.1 | AC49: 387.95 | AD49: 355.35 | AE49: 336.25 | AF49: 322.4 | AG49: 11725.8
B50: ENEL GENERACION PIURA S.A. | C50: C.T. MALACAS 1 | D50: TG6 | E50: TERMOELÉCTRICA | F50: 355.85 | G50: 457.5 | H50: 359.15 | J50: 727.05 | L50: 441.55 | M50: 752.4 | N50: 738.3 | O50: 816.85 | P50: 771.75 | Q50: 766.15 | R50: 1105.15 | S50: 805.45 | T50: 816.45 | U50: 1131.85 | V50: 1135.25 | W50: 1118.5 | X50: 1129.65 | Y50: 1138.7 | Z50: 1126.05 | AA50: 1124 | AB50: 1100 | AC50: 813.05 | AD50: 1118.85 | AE50: 818.6 | AF50: 1035.2 | AG50: 21703.3
B51: ENEL GENERACION PIURA S.A. | C51: C.T. MALACAS 2 | D51: TG4 | E51: TERMOELÉCTRICA | H51: 663.05 | I51: 894.45 | J51: 44.65 | K51: 914.15 | L51: 74.85 | W51: 60.4 | AG51: 2651.55
B52: ENEL GENERACION PIURA S.A. | C52: C.T. RF DE GENERACION TALARA | D52: TG5 | E52: TERMOELÉCTRICA | H52: 407 | AE52: 200.35 | AG52: 607.35
B53: ENERGÍA EÓLICA S.A. | C53: C.E. CUPISNIQUE | D53: CENTRAL | E53: EÓLICA | F53: 826 | G53: 637.1 | H53: 565.05 | I53: 483.8 | J53: 446.9 | K53: 946.35 | L53: 1252.6 | M53: 1412.8 | N53: 1299.5 | O53: 1060.15 | P53: 721.65 | Q53: 1086.1 | R53: 1006 | S53: 1036.9 | T53: 845.9 | U53: 488.95 | V53: 523.6 | W53: 1059 | X53: 1452.95 | Y53: 1228.95 | Z53: 1002.6 | AA53: 1077.35 | AB53: 1381.8 | AC53: 1266.45 | AD53: 1193.4 | AE53: 1207.4 | AF53: 573.1 | AG53: 26082.35
B54: ENERGÍA EÓLICA S.A. | C54: C.E. TALARA | D54: CENTRAL | E54: EÓLICA | F54: 344.35 | G54: 395.75 | H54: 384.4 | I54: 141.95 | J54: 94.85 | K54: 161.95 | L54: 465.35 | M54: 531.8 | N54: 530.7 | O54: 329.8 | P54: 230.45 | Q54: 302.4 | R54: 354.85 | S54: 305.55 | T54: 349.75 | U54: 151.05 | V54: 203.55 | W54: 391.2 | X54: 580.95 | Y54: 528.2 | Z54: 443.55 | AA54: 420.2 | AB54: 561.55 | AC54: 540.7 | AD54: 384.9 | AE54: 510.65 | AF54: 272.6 | AG54: 9913
B55: ENERGIA RENOVABLE DEL SUR S.A. | C55: C.E. SAN JUAN | D55: CENTRAL | E55: EÓLICA | F55: 2667.35 | G55: 1888.4 | H55: 1031.8 | I55: 1510.75 | J55: 862.7 | K55: 715 | L55: 1712.65 | M55: 1729.05 | N55: 1633.15 | O55: 1758.3 | P55: 2050.7 | Q55: 1899.4 | R55: 1355.45 | S55: 1224.5 | T55: 1889.8 | U55: 1369.1 | V55: 1364.4 | W55: 2019.15 | X55: 2070.8 | Y55: 1645.1 | Z55: 2080.4 | AA55: 2344.45 | AB55: 2169 | AC55: 1534 | AD55: 1151.9 | AE55: 1148.5 | AF55: 2038.1 | AG55: 44863.9
B56: ENGIE | C56: C.E. PUNTA LOMITAS | D56: PL-BL1 | E56: EÓLICA | F56: 1416 | G56: 1294.2 | H56: 490.05 | I56: 910.85 | J56: 885.7 | K56: 777.2 | L56: 1793.85 | M56: 1777.65 | N56: 1646.2 | O56: 1640.35 | P56: 1225.1 | Q56: 1266.85 | R56: 1046.65 | S56: 1040.35 | T56: 1134.95 | U56: 715.35 | V56: 819.45 | W56: 1316 | X56: 1883.9 | Y56: 1525.95 | Z56: 1457.65 | AA56: 1454.1 | AB56: 1530.45 | AC56: 1137.8 | AD56: 599.35 | AE56: 573.6 | AF56: 1359.35 | AG56: 32718.9
B57: ENGIE | C57: C.E. PUNTA LOMITAS | D57: PL-BL2 | E57: EÓLICA | F57: 1675.05 | G57: 1567.65 | H57: 664.2 | I57: 1146.85 | J57: 995.45 | K57: 964.6 | L57: 1911.45 | M57: 1824.7 | N57: 1813.75 | O57: 1862.9 | P57: 1474.45 | Q57: 1526 | R57: 1347.1 | S57: 1347.25 | T57: 1469.25 | U57: 1069.55 | V57: 1271.05 | W57: 1161.7 | X57: 1830.85 | Y57: 1690.2 | Z57: 1766.25 | AA57: 1814.45 | AB57: 1914.05 | AC57: 1531.8 | AD57: 907.35 | AE57: 999.35 | AF57: 1845 | AG57: 39392.25
B58: ENGIE | C58: C.E. PUNTA LOMITAS_EXP | D58: PUN LOM_EXP-BL1 | E58: EÓLICA | F58: 74.35 | G58: 61.95 | H58: 36.6 | I58: 85.7 | J58: 74.9 | K58: 54.35 | L58: 161.2 | M58: 173 | N58: 163.95 | O58: 163.25 | P58: 110.5 | Q58: 103.95 | R58: 99.75 | S58: 102.05 | T58: 110.1 | U58: 55.9 | V58: 63.7 | W58: 113.3 | X58: 165.05 | Y58: 159.2 | Z58: 147.15 | AA58: 137.65 | AB58: 119.85 | AC58: 101.65 | AD58: 53.8 | AE58: 44.5 | AF58: 135.35 | AG58: 2872.7
B59: ENGIE | C59: C.E. PUNTA LOMITAS_EXP | D59: PUN LOM_EXP-BL2 | E59: EÓLICA | F59: 98.4 | G59: 84.15 | H59: 33.8 | I59: 60.6 | J59: 70.6 | K59: 58.2 | L59: 158.1 | M59: 184.75 | N59: 174.55 | O59: 149.95 | P59: 94.75 | Q59: 89.05 | R59: 92.45 | S59: 89.7 | T59: 90.25 | U59: 60.6 | V59: 66.85 | W59: 90.8 | X59: 210.65 | Y59: 153.65 | Z59: 129.35 | AA59: 127.55 | AB59: 128.5 | AC59: 106.5 | AD59: 53.15 | AE59: 49.45 | AF59: 130.9 | AG59: 2837.25
B60: ENGIE | C60: C.H. QUITARACSA | D60: CENTRAL | E60: HIDROELÉCTRICA | F60: 1800.35 | G60: 2646.35 | H60: 2696.9 | I60: 2692.95 | J60: 2048.55 | K60: 2695.4 | L60: 2693 | M60: 2690.65 | N60: 2689.7 | O60: 2696.7 | P60: 2277.3 | Q60: 2005.8 | R60: 2068.5 | S60: 2671.3 | T60: 2690.35 | U60: 2661.4 | V60: 1839.15 | W60: 1972.35 | X60: 1967.15 | Y60: 1658.8 | Z60: 1733.2 | AA60: 1581.55 | AB60: 1450 | AC60: 1650.7 | AD60: 2067.8 | AE60: 1774 | AF60: 2411.75 | AG60: 59831.65
B61: ENGIE | C61: C.H. YUNCAN | D61: CENTRAL | E61: HIDROELÉCTRICA | F61: 2668.75 | G61: 3146.2 | H61: 3160.15 | I61: 3169.95 | J61: 3162.05 | K61: 3086.9 | L61: 2896.45 | M61: 3154.05 | N61: 3147.05 | O61: 3136.45 | P61: 2823.6 | Q61: 2843.2 | R61: 3128.7 | S61: 3147.75 | T61: 2892.7 | U61: 2920.1 | V61: 2776.2 | W61: 2584.85 | X61: 2461.85 | Y61: 2968.8 | Z61: 3070.9 | AA61: 3140.6 | AB61: 3127.35 | AC61: 3133.05 | AD61: 3136.85 | AE61: 3139.35 | AF61: 3137.7 | AG61: 81161.55
B62: ENGIE | C62: C.S. INTIPAMPA | D62: CENTRAL | E62: SOLAR | F62: 276.8 | G62: 239.4 | H62: 187.95 | I62: 218.3 | J62: 239.15 | K62: 174.4 | L62: 248.2 | M62: 341 | N62: 337.4 | O62: 395.5 | P62: 384.95 | Q62: 390.7 | R62: 385.5 | S62: 375.45 | T62: 363.05 | U62: 358.7 | V62: 176.2 | W62: 325.05 | X62: 322.5 | Y62: 281.6 | Z62: 240 | AA62: 185.25 | AB62: 273 | AC62: 257.15 | AD62: 266.5 | AE62: 252.5 | AF62: 218.65 | AG62: 7714.85
B63: ENGIE | C63: C.T. CHILCA 1 | D63: TG1 | E63: TERMOELÉCTRICA | F63: 2419.9 | G63: 3695.6 | N63: 354.9 | O63: 277.95 | R63: 475.3 | S63: 483.45 | W63: 1518.3 | X63: 394.35 | AE63: 132 | AF63: 288.6 | AG63: 10040.35
B64: ENGIE | C64: C.T. CHILCA 1 | D64: TG2 | E64: TERMOELÉCTRICA | F64: 2390.45 | G64: 82.1 | H64: 1769.5 | I64: 568.3 | J64: 704.45 | K64: 1146.55 | L64: 312.65 | N64: 504.15 | O64: 282.05 | R64: 1185.6 | S64: 1266.75 | T64: 525.55 | U64: 645.05 | V64: 2276.95 | W64: 1864.45 | X64: 821 | Y64: 623.8 | Z64: 1818.95 | AA64: 554.75 | AD64: 233.85 | AE64: 148.45 | AF64: 631.55 | AG64: 20356.9
B65: ENGIE | C65: C.T. CHILCA 1 | D65: TG3 | E65: TERMOELÉCTRICA | H65: 1835.4 | I65: 574.55 | J65: 598.85 | K65: 808.7 | O65: 1047 | R65: 1313.45 | AG65: 6177.95
B66: ENGIE | C66: C.T. CHILCA 1 | D66: TV | E66: TERMOELÉCTRICA | F66: 2850.4 | G66: 1646 | AF66: 129 | AG66: 4625.4
B67: ENGIE | C67: C.T. CHILCA 2 | D67: TG41 | E67: TERMOELÉCTRICA | J67: 182.9 | P67: 145.15 | Q67: 214.1 | W67: 150.2 | Z67: 164.9 | AA67: 468.55 | AB67: 129.85 | AG67: 1455.65
B68: ENGIE | C68: C.T. CHILCA 2 | D68: TV42 | E68: TERMOELÉCTRICA | AG68: 0
B69: ENGIE | C69: C.T. NEPI | D69: TG41 | E69: TERMOELÉCTRICA | U69: 838.7 | V69: 2363.7 | W69: 391.65 | AG69: 3594.05
B70: ENGIE | C70: C.T. NEPI | D70: TG42 | E70: TERMOELÉCTRICA | AG70: 0
B71: ENGIE | C71: C.T. NEPI | D71: TG43 | E71: TERMOELÉCTRICA | AG71: 0
B72: ENGIE | C72: C.T. RF PLANTA ILO | D72: TG1 | E72: TERMOELÉCTRICA | H72: 367.5 | AE72: 192.95 | AG72: 560.45
B73: ENGIE | C73: C.T. RF PLANTA ILO | D73: TG2 | E73: TERMOELÉCTRICA | AC73: 361.5 | AG73: 361.5
B74: ENGIE | C74: C.T. RF PLANTA ILO | D74: TG3 | E74: TERMOELÉCTRICA | J74: 403.7 | AE74: 193.15 | AG74: 596.85
B75: FENIX POWER PERÚ | C75: C.T. FENIX | D75: GT11 | E75: TERMOELÉCTRICA | F75: 3326.015 | G75: 3251.75 | H75: 3326.1 | I75: 3474.85 | J75: 646.2 | K75: 3160.05 | L75: 3562.15 | O75: 252 | P75: 2747.3 | Q75: 1428.6 | R75: 3722.45 | S75: 3961.8 | T75: 3804.9 | Y75: 2585.65 | Z75: 4003.8 | AA75: 4018.35 | AB75: 3927.1 | AC75: 3105.1392 | AF75: 2769.2 | AG75: 57073.404
B76: FENIX POWER PERÚ | C76: C.T. FENIX | D76: GT12 | E76: TERMOELÉCTRICA | F76: 3332.585 | G76: 3258.15 | H76: 3332.05 | I76: 3542.65 | J76: 1382.55 | K76: 3910.85 | L76: 3686.2 | M76: 3731.8985 | N76: 3661.85 | O76: 3940.25 | P76: 3722.85 | Q76: 1294.4 | R76: 3728.8 | S76: 3970.45 | T76: 3866.3 | U76: 2470.7 | Y76: 3053.05 | Z76: 3690.9 | AA76: 4026.4 | AB76: 3936.25 | AC76: 3453.7755 | AD76: 2285.3 | AE76: 1736.05 | AF76: 3714.35 | AG76: 78728.609
B77: FENIX POWER PERÚ | C77: C.T. FENIX | D77: TV10 | E77: TERMOELÉCTRICA | F77: 3823.35 | G77: 3823.75 | H77: 3872 | I77: 3959.9 | J77: 596.15 | K77: 3672.25 | L77: 4004 | M77: 1994.0565 | N77: 1966.1 | O77: 2035.45 | P77: 3442.95 | Q77: 1211.8 | R77: 4080.15 | S77: 4224.3 | T77: 4122.1 | U77: 1199.75 | Y77: 2804.3 | Z77: 3372 | AA77: 4260.85 | AB77: 4217.15 | AC77: 3698.694 | AD77: 1127.95 | AE77: 901.85 | AF77: 3430.15 | AG77: 71841.001
B78: GENERACIÓN ANDINA S.A.C. | C78: C.H. 8 DE AGOSTO | D78: CENTRAL | E78: HIDROELÉCTRICA | F78: 485.75 | G78: 428.15 | H78: 474.45 | I78: 501.2 | J78: 499.85 | K78: 501.3 | L78: 502.2 | M78: 502.8 | N78: 501.6 | O78: 502.65 | P78: 499.6 | Q78: 497.8 | R78: 497.9 | S78: 497.45 | T78: 467.65 | U78: 487.5 | V78: 484.9 | W78: 441.59429 | X78: 362.1 | Y78: 447.1 | Z78: 503.9 | AA78: 504 | AB78: 504 | AC78: 504 | AD78: 504 | AE78: 504 | AF78: 503.85 | AG78: 13111.294
B79: GENERACIÓN ANDINA S.A.C. | C79: C.H. EL CARMEN | D79: CENTRAL | E79: HIDROELÉCTRICA | F79: 177.2 | G79: 190.15 | H79: 200.05 | I79: 180.2 | J79: 195.1 | K79: 184.55 | L79: 193.8 | M79: 192.85 | N79: 191.5 | O79: 145.6 | P79: 45.75 | Q79: 200 | R79: 173.45 | S79: 149.35 | T79: 136.05 | U79: 140.8 | V79: 133.45 | W79: 118.7288 | X79: 115.95 | Y79: 120.25 | Z79: 160.6 | AA79: 129.55 | AB79: 166.85 | AC79: 171.6 | AD79: 148 | AE79: 169.55 | AF79: 197.95 | AG79: 4328.8788
B80: GENERADORA DE ENERGÍA DEL PERÚ | C80: C.H. ÁNGEL I | D80: CENTRAL | E80: HIDROELÉCTRICA | F80: 329.25 | G80: 489.6 | H80: 489.6 | I80: 489.6 | J80: 489.6 | K80: 489.6 | L80: 489.6 | M80: 489.6 | N80: 489.6 | O80: 469.2 | P80: 489.6 | Q80: 489.6 | R80: 489.6 | S80: 489.6 | T80: 489.6 | U80: 484.4 | V80: 489.6 | W80: 480 | X80: 240 | Y80: 480 | Z80: 450 | AA80: 480 | AB80: 480 | AC80: 480 | AD80: 480 | AE80: 435 | AF80: 480 | AG80: 12622.25
B81: GENERADORA DE ENERGÍA DEL PERÚ | C81: C.H. ÁNGEL II | D81: CENTRAL | E81: HIDROELÉCTRICA | F81: 331.75 | G81: 489.6 | H81: 489.6 | I81: 489.6 | J81: 489.6 | K81: 489.6 | L81: 489.6 | M81: 489.6 | N81: 478.3 | O81: 462.5 | P81: 489.6 | Q81: 489.6 | R81: 484.5 | S81: 489.6 | T81: 489.6 | U81: 484.4 | V81: 489.6 | W81: 475 | X81: 235 | Y81: 480 | Z81: 437.5 | AA81: 470 | AB81: 480 | AC81: 470.6 | AD81: 480 | AE81: 430.25 | AF81: 480 | AG81: 12555
B82: GENERADORA DE ENERGÍA DEL PERÚ | C82: C.H. ÁNGEL III | D82: CENTRAL | E82: HIDROELÉCTRICA | F82: 229.4 | G82: 244.8 | H82: 244.8 | I82: 244.8 | J82: 244.8 | K82: 244.8 | L82: 244.8 | M82: 244.8 | N82: 241.1 | O82: 142.8 | T82: 122.4 | U82: 244.8 | V82: 239.7 | W82: 240 | X82: 110.5 | Y82: 240 | Z82: 222.25 | AA82: 239 | AB82: 239.4 | AC82: 339.5 | AD82: 478.45 | AE82: 418.65 | AF82: 479.65 | AG82: 5941.2
B83: GENERADORA DE ENERGÍA DEL PERÚ | C83: C.H. LA JOYA | D83: CENTRAL | E83: HIDROELÉCTRICA | F83: 144.45 | G83: 141.75 | H83: 176.25 | I83: 174.1 | J83: 167.05 | K83: 181.15 | L83: 183.2 | M83: 157.05 | N83: 148.3 | O83: 149.1 | P83: 152.85 | Q83: 145.5 | R83: 142.95 | S83: 142.05 | T83: 140.45 | U83: 138.9 | V83: 173.7 | W83: 179.1 | X83: 175.55 | Y83: 184.75 | Z83: 192.4 | AA83: 168.1 | AB83: 150 | AC83: 165.4 | AD83: 114.45 | AE83: 169.45 | AF83: 176.95 | AG83: 4334.95
B84: GM OPERACIONES S.A.C. | C84: CT REFINERIA TALARA | D84: TV1 REF TALARA | E84: TERMOELÉCTRICA | K84: 65.7 | L84: 465.35 | M84: 328.55 | N84: 364.25 | O84: 471.9 | P84: 514.3 | Q84: 564.54 | R84: 595.2 | S84: 609.25 | T84: 606.3 | U84: 611.25 | V84: 624.95 | W84: 641.5 | X84: 510.25 | Y84: 351.95 | Z84: 359.15 | AA84: 359.7 | AB84: 360.2 | AC84: 372.95 | AD84: 395.35 | AE84: 452.15 | AF84: 393.35 | AG84: 10018.09
B85: GM OPERACIONES S.A.C. | C85: CT REFINERIA TALARA | D85: TV2 REF TALARA | E85: TERMOELÉCTRICA | F85: 796.2 | G85: 802.5 | H85: 837.05 | I85: 909.62 | J85: 904.05 | K85: 862.1 | L85: 722.75 | M85: 925.4 | N85: 926.5 | O85: 917.35 | P85: 887.2 | Q85: 871.88 | R85: 852.3 | S85: 835.1 | T85: 830.8 | U85: 831.65 | V85: 858.25 | W85: 847.5 | X85: 853 | Y85: 855.45 | Z85: 857.2 | AA85: 865.35 | AB85: 867.8 | AC85: 876.5 | AD85: 852.7 | AE85: 866.55 | AF85: 864.15 | AG85: 23176.9
B86: GR CORTARRAMA SOCIEDAD ANONIMA CERRADA | C86: C.S. MATARANI | D86: C.S. MATARANI | E86: SOLAR | F86: 538.8 | G86: 418.65 | H86: 457.4 | I86: 457.85 | J86: 742.5 | K86: 640.35 | L86: 688.7 | M86: 789.4 | N86: 775.45 | O86: 774.2 | P86: 806.2 | Q86: 783.65 | R86: 757.65 | S86: 799.4 | T86: 802.55 | U86: 813.3 | V86: 714.25 | W86: 609.75 | X86: 620.75 | Y86: 665.55 | Z86: 503.9 | AA86: 671.55 | AB86: 536.75 | AC86: 686.85 | AD86: 645.3 | AE86: 666.2 | AF86: 626.35 | AG86: 17993.25
B87: GR PAINO SOCIEDAD ANONIMA CERRADA | C87: C.E. HUAMBOS | D87: CENTRAL | E87: EÓLICA | F87: 61.9 | G87: 35.15 | H87: 23.85 | I87: 54.9 | J87: 127 | K87: 84.3 | L87: 43.3 | M87: 38.6 | N87: 74.3 | O87: 47.65 | P87: 163.55 | Q87: 161.9 | R87: 31.85 | S87: 93.25 | T87: 160.25 | U87: 124.15 | V87: 82.75 | W87: 54.85 | X87: 69.7 | Y87: 59.45 | Z87: 42.55 | AA87: 214.15 | AB87: 290.2 | AC87: 274.05 | AD87: 230.9 | AE87: 226.75 | AF87: 297.7 | AG87: 3168.95
B88: GR TARUCA SOCIEDAD ANONIMA CERRADA | C88: C.E. DUNA | D88: CENTRAL | E88: EÓLICA | F88: 56.9 | G88: 33.1 | H88: 39.4 | I88: 111.35 | J88: 188.4 | K88: 139.65 | L88: 63.4 | M88: 38.45 | N88: 49.65 | O88: 41.5 | P88: 225.7 | Q88: 205.2 | R88: 34.65 | S88: 70.05 | T88: 141.35 | U88: 89.75 | V88: 72.25 | W88: 56.5 | X88: 55.75 | Y88: 45.3 | Z88: 59.75 | AA88: 282.3 | AB88: 341.15 | AC88: 339.65 | AD88: 290.3 | AE88: 318.25 | AF88: 360.75 | AG88: 3750.45
B89: HIDROCAÑETE S.A. | C89: C.H. IMPERIAL | D89: CENTRAL | E89: HIDROELÉCTRICA | F89: 73.65 | G89: 81.05 | H89: 78.8 | I89: 79.95 | J89: 75.95 | K89: 80.5 | L89: 83.35 | M89: 83.4 | N89: 84.35 | O89: 84.25 | P89: 84.6 | Q89: 83.85 | R89: 84.45 | S89: 83.65 | T89: 85.3 | U89: 84.5 | V89: 83.55 | W89: 82.75 | X89: 82.3 | Y89: 83 | Z89: 82.6 | AA89: 81.9 | AB89: 79.65 | AC89: 81.95 | AD89: 82.15 | AE89: 81.95 | AF89: 55.5 | AG89: 2188.9
B90: HIDROELECTRICA HUANCHOR S.A.C. | C90: C.H. HUANCHOR | D90: CENTRAL | E90: HIDROELÉCTRICA | F90: 437 | G90: 438.4 | H90: 431.6 | I90: 432.55 | J90: 435.15 | K90: 439.7 | L90: 440.1 | M90: 440.4 | N90: 439.6 | O90: 440.45 | P90: 440.4 | Q90: 439.15 | R90: 440.5 | S90: 441 | T90: 439.25 | U90: 440.8 | V90: 441.25 | W90: 441.25 | X90: 440.6 | Y90: 441.05 | Z90: 440.75 | AA90: 440.7 | AB90: 438.75 | AC90: 439.85 | AD90: 440.85 | AE90: 438.25 | AF90: 440.75 | AG90: 11860.1
B91: HUAURA POWER GROUP S.A. | C91: C.H. YARUCAYA | D91: CENTRAL | E91: HIDROELÉCTRICA | F91: 451.15 | G91: 450.5 | H91: 425.05 | I91: 127.2 | J91: 250.7 | K91: 451.2 | L91: 451.1 | M91: 450.45 | N91: 451.2 | O91: 451.05 | P91: 449.74 | Q91: 450.85 | R91: 450.9 | S91: 408.735 | T91: 448.8 | U91: 428.05 | V91: 451.2 | W91: 451.2 | X91: 421 | Y91: 450.65 | Z91: 448.8 | AA91: 415.05 | AB91: 450.7 | AC91: 449.2 | AD91: 431.75 | AE91: 451 | AF91: 451.2 | AG91: 11468.425
B92: INFRAESTRUCTURAS Y ENERGIAS DEL PERU S.A.C. | C92: C.T. RF PTO MALDONADO | D92: CENTRAL | E92: TERMOELÉCTRICA | AG92: 0
B93: INFRAESTRUCTURAS Y ENERGIAS DEL PERU S.A.C. | C93: C.T. RF PUCALLPA | D93: CENTRAL | E93: TERMOELÉCTRICA | AG93: 0
B94: INLAND ENERGY SAC | C94: C.H. SANTA TERESA | D94: CENTRAL | E94: HIDROELÉCTRICA | F94: 2173 | G94: 1849.5 | H94: 2179.65 | I94: 1920.05 | J94: 1893.3 | K94: 2162.5 | L94: 2164.2 | M94: 2169.3 | N94: 2173.3 | O94: 2164.15 | P94: 2172.75 | Q94: 1768.4 | R94: 2162.75 | S94: 2173.095 | T94: 2069 | U94: 2173.3 | V94: 2171.55 | W94: 2186 | X94: 2179.3 | Y94: 2182.35 | Z94: 2176.85 | AA94: 2156.45 | AB94: 2152.9 | AC94: 2160.8 | AD94: 2166.25 | AE94: 2179.2 | AF94: 2177.6 | AG94: 57257.495
B95: INVERSIONES SHAQSHA S.A.C. | C95: C.H. PARIAC | D95: CENTRAL | E95: HIDROELÉCTRICA | N95: 17.55 | O95: 83.6 | P95: 98.75 | Q95: 99.25 | R95: 102 | S95: 100.75 | T95: 101.2 | U95: 101.7 | V95: 101.25 | W95: 101.15 | X95: 101.15 | Y95: 103.15 | Z95: 103.2 | AA95: 102.85 | AB95: 103 | AC95: 103.15 | AD95: 103.05 | AE95: 99.15 | AF95: 102.8 | AG95: 1828.7
B96: KALLPA GENERACION S.A. | C96: C.H. CERRO DEL AGUILA | D96: CENTRAL | E96: HIDROELÉCTRICA | F96: 10008.95 | G96: 13509.65 | H96: 13475.45 | I96: 13406.25 | J96: 13426.15 | K96: 13440.05 | L96: 13427.6 | M96: 13408.95 | N96: 13425.7 | O96: 13273.25 | P96: 13413.7 | Q96: 13404.15 | R96: 12851.8 | S96: 13407.95 | T96: 13388.45 | U96: 13737.95 | V96: 13760.7 | W96: 13519.6 | X96: 11115.5 | Y96: 13398.2 | Z96: 13401.7 | AA96: 13439.5 | AB96: 13387.9 | AC96: 13373.55 | AD96: 13388.7 | AE96: 12058.15 | AF96: 13382.55 | AG96: 355232.05
B97: KALLPA GENERACION S.A. | C97: C.T. KALLPA | D97: TG1 | E97: TERMOELÉCTRICA | I97: 2346.15 | J97: 3078.3 | K97: 3219.7 | L97: 3035.85 | M97: 2982.7 | N97: 3067.85 | O97: 3322.05 | P97: 3056.95 | Q97: 3063.4 | R97: 3222.65 | S97: 3400.75 | T97: 3131.8 | U97: 3359.65 | V97: 3706.3 | W97: 3682.5 | X97: 3629 | Y97: 3531.75 | Z97: 3614.3 | AA97: 3337.95 | AB97: 3307.9 | AC97: 2941.6 | AD97: 3075.8 | AE97: 2973.75 | AF97: 3143.25 | AG97: 77231.9
B98: KALLPA GENERACION S.A. | C98: C.T. KALLPA | D98: TG2 | E98: TERMOELÉCTRICA | G98: 1165.5 | H98: 4076 | I98: 3216.25 | J98: 3091.45 | K98: 3217.3 | L98: 3026.8 | M98: 2977.8 | N98: 3073 | O98: 3370.8 | P98: 3064.1 | Q98: 3067.15 | R98: 3236.6 | S98: 3454 | T98: 3135.95 | U98: 3401.15 | V98: 3753.6 | W98: 3820.75 | X98: 3714.65 | Y98: 3636.9 | Z98: 3653.5 | AA98: 3370.95 | AB98: 3355.6 | AC98: 2932.75 | AD98: 3075.55 | AE98: 2968.35 | AF98: 3170.7 | AG98: 84027.15
B99: KALLPA GENERACION S.A. | C99: C.T. KALLPA | D99: TG3 | E99: TERMOELÉCTRICA | G99: 3573.15 | H99: 4104.95 | I99: 3226.3 | J99: 3094.85 | K99: 3219.05 | L99: 3029.6 | M99: 2974.85 | N99: 3071.7 | O99: 2956.1 | P99: 3066.1 | Q99: 3067.1 | R99: 3238.95 | S99: 3453.1 | T99: 3138 | U99: 3401.55 | V99: 3754.45 | W99: 3823.65 | X99: 3713.6 | Y99: 3578.8 | Z99: 3657.35 | AA99: 3369.4 | AB99: 3355.85 | AC99: 2936.45 | AD99: 3073.5 | AE99: 2968.6 | AF99: 3170.5 | AG99: 86017.5
B100: KALLPA GENERACION S.A. | C100: C.T. KALLPA | D100: TV | E100: TERMOELÉCTRICA | G100: 2135.75 | H100: 4227.75 | I100: 5016.8 | J100: 5432.85 | K100: 5552.2 | L100: 5405.7 | M100: 5333.9 | N100: 5439.7 | O100: 5450.95 | P100: 5405.4 | Q100: 5429.3 | R100: 5614.6 | S100: 5780.95 | T100: 5514.1 | U100: 5758.35 | V100: 6036.9 | W100: 5996.7 | X100: 5988.6 | Y100: 5890.85 | Z100: 5958.9 | AA100: 5654.2 | AB100: 5659.4 | AC100: 5338.4 | AD100: 5461.45 | AE100: 5353.8 | AF100: 5521.05 | AG100: 140358.55
B101: KALLPA GENERACION S.A. | C101: C.T. LAS FLORES | D101: TG1 | E101: TERMOELÉCTRICA | F101: 454.1 | G101: 3712.5 | H101: 4774.05 | I101: 4599.6 | J101: 4401.6 | K101: 3835.95 | L101: 4318.35 | M101: 4046.45 | N101: 4041.85 | O101: 4524.3 | P101: 4427.85 | Q101: 4195.75 | R101: 4222.4 | S101: 4905.55 | T101: 4816.85 | U101: 4240.45 | V101: 4298.55 | W101: 4401.8 | X101: 4738.65 | Y101: 4887.5 | Z101: 4897.25 | AA101: 4762.05 | AB101: 4448.25 | AC101: 3970.35 | AD101: 4715.05 | AE101: 3957.6 | AF101: 4200.15 | AG101: 114794.8
B102: KALLPA GENERACION S.A. | C102: C.T. LAS FLORES | D102: TV | E102: TERMOELÉCTRICA | F102: 262.75 | G102: 1823.75 | H102: 2503.5 | I102: 2442.5 | J102: 2377.45 | K102: 1992.5 | L102: 2337.85 | M102: 2234.95 | N102: 2213.8 | O102: 2422.8 | P102: 2387.8 | Q102: 2292.2 | R102: 2298.6 | S102: 2588 | T102: 2567.7 | U102: 2313.05 | V102: 2352.05 | W102: 2383.35 | X102: 2533.45 | Y102: 2580.5 | Z102: 2597 | AA102: 2528.6 | AB102: 2404.8 | AC102: 2208.7 | AD102: 2507.3 | AE102: 2193.8 | AF102: 2295.6 | AG102: 61644.35
B103: KALLPA GENERACION S.A. | C103: M.C.H. CERRO DEL AGUILA | D103: CENTRAL | E103: HIDROELÉCTRICA | F103: 246.85 | G103: 251.7 | H103: 251.3 | I103: 252 | J103: 251.45 | K103: 245.85 | L103: 250.65 | M103: 251.6 | N103: 251.2 | O103: 252 | P103: 251.1 | Q103: 250.85 | R103: 221.05 | S103: 252.45 | T103: 251.7 | U103: 252.1 | V103: 252.1 | W103: 252.4 | X103: 252.5 | Y103: 252.7 | Z103: 252.05 | AA103: 253.1 | AB103: 251.55 | AC103: 251.5 | AD103: 252.35 | AE103: 194.95 | AF103: 252.2 | AG103: 6701.25
...

Sheet G_AREAS
B3: lunes, 27 de Enero del 2025
B5: HORA | C5: RESUMEN DE GENERACIÓN POR ÁREAS DEL SEIN | D5: RESUMEN DE GENERACIÓN POR ÁREAS DEL SEIN | E5: RESUMEN DE GENERACIÓN POR ÁREAS DEL SEIN | F5: RESUMEN DE GENERACIÓN POR ÁREAS DEL SEIN | G5: RESUMEN DE GENERACIÓN POR ÁREAS DEL SEIN | H5: RESUMEN DE GENERACIÓN POR ÁREAS DEL SEIN | I5: RESUMEN DE GENERACIÓN POR ÁREAS DEL SEIN | J5: RESUMEN DE GENERACIÓN POR ÁREAS DEL SEIN | K5: RESUMEN DE GENERACIÓN POR ÁREAS DEL SEIN | L5: RESUMEN DE GENERACIÓN POR ÁREAS DEL SEIN | M5: RESUMEN DE GENERACIÓN POR ÁREAS DEL SEIN | N5: RESUMEN DE GENERACIÓN POR ÁREAS DEL SEIN | O5: RESUMEN DE GENERACIÓN POR ÁREAS DEL SEIN | P5: RESUMEN DE GENERACIÓN POR ÁREAS DEL SEIN | Q5: RESUMEN DE GENERACIÓN POR ÁREAS DEL SEIN | R5: RESUMEN DE GENERACIÓN POR ÁREAS DEL SEIN | S5: HORA | T5: GENERACIÓN POR TIPO DE GENERACIÓN | U5: GENERACIÓN POR TIPO DE GENERACIÓN | V5: GENERACIÓN POR TIPO DE GENERACIÓN | W5: GENERACIÓN POR TIPO DE GENERACIÓN | X5: GENERACIÓN POR TIPO DE GENERACIÓN | Y5: HORA | Z5: GENERACIÓN POR TIPO DE GENERACIÓN | AA5: GENERACIÓN POR TIPO DE GENERACIÓN | AB5: GENERACIÓN POR TIPO DE GENERACIÓN | AC5: GENERACIÓN POR TIPO DE GENERACIÓN | AD5: GENERACIÓN POR TIPO DE GENERACIÓN
C6: NORTE | D6: NORTE | E6: NORTE | F6: NORTE | G6: CENTRO | H6: CENTRO | I6: CENTRO | J6: CENTRO | K6: SUR | L6: SUR | M6: SUR | N6: SUR | O6: GENERACIÓN INTEGRANTES COES | P6: GENERACIÓN INTEGRANTES COES | Q6: GENERACIÓN INTEGRANTES COES | R6: GENERACIÓN INTEGRANTES COES | T6: INTEGRANTES COES | U6: INTEGRANTES COES | V6: INTEGRANTES COES | W6: INTEGRANTES COES | X6: INTEGRANTES COES | Z6: INTEGRANTES COES RER | AA6: INTEGRANTES COES RER | AB6: INTEGRANTES COES RER | AC6: INTEGRANTES COES RER | AD6: INTEGRANTES COES RER
C7: GENERACIÓN HIDROELÉCTRICA NORTE | D7: GENERACIÓN TERMOELÉCTRICA NORTE | E7: GENERACIÓN SOLAR NORTE | F7: GENERACIÓN EÓLICA NORTE | G7: GENERACIÓN HIDROELÉCTRICA CENTRO | H7: GENERACIÓN TERMOELÉCTRICA CENTRO | I7: GENERACIÓN SOLAR CENTRO | J7: GENERACIÓN EÓLICA CENTRO | K7: GENERACIÓN HIDROELÉCTRICA SUR | L7: GENERACIÓN TERMOELÉCTRICA SUR | M7: GENERACIÓN SOLAR SUR | N7: GENERACIÓN EÓLICA SUR | O7: GENERACIÓN COES NORTE | P7: GENERACIÓN COES CENTRO | Q7: GENERACIÓN COES SUR | R7: TOTAL GENERACION | T7: HIDROELÉCTRICA | U7: TERMOELÉCTRICA | V7: SOLAR | W7: EÓLICA | X7: TOTAL GENERACION | Z7: HIDROELÉCTRICA RER | AA7: TERMOELÉCTRICA RER | AB7: SOLAR RER | AC7: EÓLICA RER | AD7: TOTAL RER
B8: 00:30 | C8: 537.6 | D8: 133.4 | E8: 0 | F8: 76.8 | G8: 3531.2 | H8: 1310.8 | I8: 0 | J8: 295.5 | K8: 527.7 | L8: 0 | M8: 0 | N8: 0 | O8: 747.8 | P8: 5137.5 | Q8: 527.7 | R8: 6413 | S8: 00:30 | T8: 4596.5 | U8: 1444.2 | V8: 0 | W8: 372.3 | X8: 6413 | Y8: 00:30 | Z8: 341.8 | AA8: 58.4 | AB8: 0 | AC8: 372.3 | AD8: 772.5
B9: 01:00 | C9: 464.8 | D9: 133.5 | E9: 0 | F9: 77.2 | G9: 3465.5 | H9: 1311.8 | I9: 0 | J9: 277.5 | K9: 531.7 | L9: 0 | M9: 0 | N9: 0 | O9: 675.5 | P9: 5054.8 | Q9: 531.7 | R9: 6262 | S9: 01:00 | T9: 4462 | U9: 1445.3 | V9: 0 | W9: 354.7 | X9: 6262 | Y9: 01:00 | Z9: 340.8 | AA9: 58.6 | AB9: 0 | AC9: 354.7 | AD9: 754.1
B10: 01:30 | C10: 438.4 | D10: 132.9 | E10: 0 | F10: 69 | G10: 3495.3 | H10: 1313.1 | I10: 0 | J10: 247.5 | K10: 532.6 | L10: 0 | M10: 0 | N10: 0 | O10: 640.3 | P10: 5055.9 | Q10: 532.6 | R10: 6228.8 | S10: 01:30 | T10: 4466.3 | U10: 1446 | V10: 0 | W10: 316.5 | X10: 6228.8 | Y10: 01:30 | Z10: 340.8 | AA10: 58 | AB10: 0 | AC10: 316.5 | AD10: 715.3
B11: 02:00 | C11: 437.8 | D11: 133.3 | E11: 0 | F11: 63.9 | G11: 3477.4 | H11: 1315.3 | I11: 0 | J11: 268.5 | K11: 496 | L11: 0 | M11: 0 | N11: 0 | O11: 635 | P11: 5061.2 | Q11: 496 | R11: 6192.2 | S11: 02:00 | T11: 4411.2 | U11: 1448.6 | V11: 0 | W11: 332.4 | X11: 6192.2 | Y11: 02:00 | Z11: 338.7 | AA11: 57.5 | AB11: 0 | AC11: 332.4 | AD11: 728.6
B12: 02:30 | C12: 437.8 | D12: 132.7 | E12: 0 | F12: 65.5 | G12: 3346.2 | H12: 1314.7 | I12: 0 | J12: 307.2 | K12: 501.1 | L12: 0 | M12: 0 | N12: 0 | O12: 636 | P12: 4968.1 | Q12: 501.1 | R12: 6105.2 | S12: 02:30 | T12: 4285.1 | U12: 1447.4 | V12: 0 | W12: 372.7 | X12: 6105.2 | Y12: 02:30 | Z12: 338.4 | AA12: 58 | AB12: 0 | AC12: 372.7 | AD12: 769.1
B13: 03:00 | C13: 435.9 | D13: 134.3 | E13: 0 | F13: 69 | G13: 3360.9 | H13: 1320.1 | I13: 0 | J13: 299.9 | K13: 489.5 | L13: 0 | M13: 0 | N13: 0 | O13: 639.2 | P13: 4980.9 | Q13: 489.5 | R13: 6109.6 | S13: 03:00 | T13: 4286.3 | U13: 1454.4 | V13: 0 | W13: 368.9 | X13: 6109.6 | Y13: 03:00 | Z13: 338.3 | AA13: 58.9 | AB13: 0 | AC13: 368.9 | AD13: 766.1
B14: 03:30 | C14: 439.7 | D14: 123.1 | E14: 0 | F14: 64.2 | G14: 3383 | H14: 1319.8 | I14: 0 | J14: 303.1 | K14: 501.1 | L14: 0 | M14: 0 | N14: 0 | O14: 627 | P14: 5005.9 | Q14: 501.1 | R14: 6134 | S14: 03:30 | T14: 4323.8 | U14: 1442.9 | V14: 0 | W14: 367.3 | X14: 6134 | Y14: 03:30 | Z14: 338.2 | AA14: 57.3 | AB14: 0 | AC14: 367.3 | AD14: 762.8
B15: 04:00 | C15: 505.7 | D15: 111.1 | E15: 0 | F15: 64.5 | G15: 3270.3 | H15: 1303.2 | I15: 0 | J15: 333.8 | K15: 483.5 | L15: 0 | M15: 0 | N15: 0 | O15: 681.3 | P15: 4907.3 | Q15: 483.5 | R15: 6072.1 | S15: 04:00 | T15: 4259.5 | U15: 1414.3 | V15: 0 | W15: 398.3 | X15: 6072.1 | Y15: 04:00 | Z15: 336.8 | AA15: 59.6 | AB15: 0 | AC15: 398.3 | AD15: 794.7
B16: 04:30 | C16: 513 | D16: 111.5 | E16: 0 | F16: 73.4 | G16: 3295.4 | H16: 1296 | I16: 0 | J16: 376.3 | K16: 491.3 | L16: 0 | M16: 0 | N16: 0 | O16: 697.9 | P16: 4967.7 | Q16: 491.3 | R16: 6156.9 | S16: 04:30 | T16: 4299.7 | U16: 1407.5 | V16: 0 | W16: 449.7 | X16: 6156.9 | Y16: 04:30 | Z16: 337.2 | AA16: 59.9 | AB16: 0 | AC16: 449.7 | AD16: 846.8
B17: 05:00 | C17: 516.9 | D17: 96.3 | E17: 0 | F17: 67.9 | G17: 3340.2 | H17: 1307.6 | I17: 0 | J17: 380.1 | K17: 493.8 | L17: 0 | M17: 0 | N17: 0 | O17: 681.1 | P17: 5027.9 | Q17: 493.8 | R17: 6202.8 | S17: 05:00 | T17: 4350.9 | U17: 1403.9 | V17: 0 | W17: 448 | X17: 6202.8 | Y17: 05:00 | Z17: 337.6 | AA17: 44 | AB17: 0 | AC17: 448 | AD17: 829.6
B18: 05:30 | C18: 532.6 | D18: 96.2 | E18: 0 | F18: 68.9 | G18: 3418 | H18: 1311.8 | I18: 0 | J18: 365.4 | K18: 482.1 | L18: 0 | M18: 0.2 | N18: 0 | O18: 697.7 | P18: 5095.2 | Q18: 482.3 | R18: 6275.2 | S18: 05:30 | T18: 4432.7 | U18: 1408 | V18: 0.2 | W18: 434.3 | X18: 6275.2 | Y18: 05:30 | Z18: 338.2 | AA18: 44.2 | AB18: 0.2 | AC18: 434.3 | AD18: 816.9
B19: 06:00 | C19: 537.3 | D19: 98.4 | E19: 0 | F19: 54.5 | G19: 3437.9 | H19: 1316.1 | I19: 0 | J19: 361.5 | K19: 495.3 | L19: 0 | M19: 28.2 | N19: 0 | O19: 690.2 | P19: 5115.5 | Q19: 523.5 | R19: 6329.2 | S19: 06:00 | T19: 4470.5 | U19: 1414.5 | V19: 28.2 | W19: 416 | X19: 6329.2 | Y19: 06:00 | Z19: 340.4 | AA19: 45.9 | AB19: 28.2 | AC19: 416 | AD19: 830.5
... B56: TOTAL MWh | C56: 12954.6 | D56: 2794.6 | E56: 1.8 | F56: 1504.15 | G56: 86458.65 | H56: 43398.65 | I56: 7.05 | J56: 10570.95 | K56: 12581.7 | L56: 0 | M56: 3355.05 | N56: 0 | O56: 17255.15 | P56: 140435.3 | Q56: 15936.75 | R56: 173627.2 | S56: TOTAL MWh | T56: 111994.95 | U56: 46193.25 | V56: 3363.9 | W56: 12075.1 | X56: 173627.2 | Y56: TOTAL MWh | Z56: 8351.9 | AA56: 1067.15 | AB56: 3363.9 | AC56: 12075.1 | AD56: 24858.05

Sheet HOP
B3: lunes, 27 de Enero del 2025
B5: Reporte de Horas de Operación
B6: Empresa | C6: Central | D6: Grupo | E6: Modo de Operación | F6: Inicio | G6: Final | H6: O. Arranque | I6: O. Parada | J6: Tipo Operación | K6: Ensayo de Potencia Efectiva | L6: Ensayo de Potencia Mínima | M6: Sistema | N6: Lim. Transm. | O6: Causa | P6: Observación
B7: AGRO INDUSTRIAL PARAMONGA S.A. | C7: C.T. PARAMONGA | D7: CENTRAL | E7: PARAMONGA - BAGAZO | F7: 27/01/2025 00:00:00 | G7: 28/01/2025 00:00:00 | J7: POR COGENERACION | O7: ...
B8: AGROAURORA S.A.C. | C8: C.T. MAPLE ETANOL | D8: CENTRAL | E8: MAPLE- BAGAZO | F8: 27/01/2025 00:00:00 | G8: 27/01/2025 04:45:21 | J8: POR COGENERACION | O8: ...
B9: AGROAURORA S.A.C. | C9: C.T. MAPLE ETANOL | D9: CENTRAL | E9: MAPLE- BAGAZO | F9: 27/01/2025 22:08:25 | G9: 28/01/2025 00:00:00 | J9: POR COGENERACION | O9: ...
B10: AGROINDUSTRIAS SAN JACINTO S.A.A. | C10: C.T. SAN JACINTO | D10: CENTRAL | E10: SAN_JACINTO - BAGAZO | F10: 27/01/2025 00:00:00 | G10: 28/01/2025 00:00:00 | J10: POR COGENERACION | O10: ...
B11: BIOENERGIA DEL CHIRA S.A. | C11: C.T. CAÑA BRAVA | D11: G-1 | E11: CANA BRAVA TV1 - BAGAZO | F11: 27/01/2025 00:00:00 | G11: 27/01/2025 00:05:00 | J11: POR COGENERACION | O11: ...
B12: BIOENERGIA DEL CHIRA S.A. | C12: C.T. CAÑA BRAVA | D12: CENTRAL | E12: CANA BRAVA TV1 & TV2 - BAGAZO | F12: 27/01/2025 00:05:00 | G12: 28/01/2025 00:00:00 | J12: POR COGENERACION | O12: ...
B13: EGESUR | C13: C.T. INDEPENDENCIA | D13: INDEP_G2 | E13: INDEPENDENCIA GAS | F13: 27/01/2025 12:56:00 | G13: 27/01/2025 14:39:00 | H13: 27/01/2025 12:51:00 | J13: A MINIMA CARGA | O13: ...
B14: EGESUR | C14: C.T. INDEPENDENCIA | D14: CENTRAL | E14: INDEPENDENCIA GAS | F14: 27/01/2025 14:39:00 | G14: 27/01/2025 16:58:00 | J14: POR POTENCIA O ENERGIA | O14: ... | P14: G1 indisponible por falla.
B15: EGESUR | C15: C.T. INDEPENDENCIA | D15: INDEP_G1 | E15: INDEPENDENCIA GAS | F15: 27/01/2025 15:18:00 | G15: 27/01/2025 15:49:00 | J15: POR PRUEBAS | O15: ...
B16: EGESUR | C16: C.T. INDEPENDENCIA | D16: CENTRAL | E16: INDEPENDENCIA GAS | F16: 27/01/2025 16:58:00 | G16: 27/01/2025 17:08:00 | J16: A MINIMA CARGA | O16: ...
B17: ENEL GENERACION PIURA S.A. | C17: C.T. MALACAS 1 | D17: CENTRAL | E17: MALACAS1 TG6 - GAS | F17: 27/01/2025 00:00:00 | G17: 27/01/2025 03:26:00 | J17: POR POTENCIA O ENERGIA | O17: ...
B18: ENEL GENERACION PIURA S.A. | C18: C.T. MALACAS 1 | D18: CENTRAL | E18: MALACAS1 TG6 - GAS | F18: 27/01/2025 03:26:00 | G18: 27/01/2025 06:58:00 | J18: A MINIMA CARGA | O18: ...
B19: ENEL GENERACION PIURA S.A. | C19: C.T. MALACAS 1 | D19: CENTRAL | E19: MALACAS1 TG6 - GAS | F19: 27/01/2025 06:58:00 | G19: 28/01/2025 00:00:00 | J19: POR POTENCIA O ENERGIA | O19: ...
B20: ENGIE | C20: C.T. CHILCA 1 | D20: TG2 | E20: CHILCA1 TG2 - GAS | F20: 27/01/2025 07:20:00 | G20: 27/01/2025 14:44:00 | H20: 27/01/2025 06:28:00 | J20: A MINIMA CARGA | O20: ... | P20: Proceso de acople 1x1.
B21: ENGIE | C21: C.T. CHILCA 1 | D21: TG2 | E21: CHILCA1 TG2 - GAS | F21: 27/01/2025 14:44:00 | G21: 27/01/2025 16:52:00 | J21: POR POTENCIA O ENERGIA | O21: ...
B22: ENGIE | C22: C.T. CHILCA 1 | D22: TG1 | E22: CHILCA1 TG1 - GAS | F22: 27/01/2025 15:04:00 | G22: 27/01/2025 16:52:00 | H22: 27/01/2025 14:42:00 | J22: POR POTENCIA O ENERGIA | O22: ...
B23: ENGIE | C23: C.T. CHILCA 1 | D23: TG1 | E23: CHILCA1 TG1 - GAS | F23: 27/01/2025 16:52:00 | G23: 27/01/2025 17:30:00 | I23: 27/01/2025 17:06:00 | J23: A MINIMA CARGA | O23: ...
