Workbook

Sheet EVENTOS
B3: miércoles, 4 de Marzo del 2026
B5: INFORMACIÓN DE EVENTOS PRINCIPALES EN SUS INSTALACIONES
B6: TIPO DE EVENTO | C6: EMPRESA | D6: UBICACIÓN | E6: TIPO DE EQUIPO | F6: EQUIPO | G6: INICIO | H6: FINAL | I6: DESCRIPCIÓN | J6: MW INDISP. | K6: INTERRUPCIÓN (SI/NO) | L6: TENSIÓN DE FALLA (kV)
B7: EVENTO | C7: ATLANTICA TRANSMISION SUR S.A. | D7: CHILCA CTM - POROMA | E7: LINEA DE TRANSMISION | F7: L-5032 | G7: 04/03/2026 09:31:00 | H7: 04/03/2026 09:31:00 | I7: RECIERRE EXITOSO DE LA LÍNEA L-5032 (CHILCA - POROMA) DE 500 KV, | K7: NO
B8: FALLA | C8: COMPAÑIA TRANSMISORA ANDINA S.A. | D8: HUALLANCA - HUARAZ OESTE | E8: LINEA DE TRANSMISION | F8: L-1127 | G8: 04/03/2026 15:55:04 | H8: 05/03/2026 16:02:34 | I8: DESCONEXIÓN DE LA LINEA L-1127 (HUALLANCA - HUARAZ OESTE) DE 138 KV | K8: NO | L8: 138
B9: FALLA | C9: ELECTRO DUNAS | D9: CHINCHA-INDEPENDENCIA_60 | E9: LINEA DE TRANSMISION | F9: L-6120 | G9: 04/03/2026 08:02:57 | H9: 04/03/2026 08:06:28 | I9: DESCONEXIÓN DE LA LÍNEA L-6120 (INDEPENDENCIA – CHINCHA) DE 60 KV | K9: NO | L9: 60
B10: EVENTO | C10: ELECTRO ORIENTE | D10: BELAUNDE TERRY - TARAPOTO | E10: LINEA DE TRANSMISION | F10: L-1018 | G10: 04/03/2026 18:15:00 | H10: 04/03/2026 21:08:00 | I10: DECLARACIÓN DE SITUACIÓN EXCEPCIONAL EN LA LÍNEA L-1018 (BELAUNDE TERRY - TARAPOTO) DE 138 kV | K10: NO
B11: FALLA | C11: RED DE ENERGIA DEL PERU S.A. | D11: ABANCAY NUEVA - CACHIMAYO | E11: LINEA DE TRANSMISION | F11: L-1007 | G11: 04/03/2026 22:46:00 | H11: 04/03/2026 22:46:00 | I11: RECIERRE EXITOSO DE LA LÍNEA L-1007 (ABANCAY NUEVA – CACHIMAYO) DE 138 KV | K11: NO | L11: 138
B12: EVENTO | C12: RED DE ENERGIA DEL PERU S.A. | D12: QUENCORO | E12: TRANSFORMADOR 3D | F12: T47-131 | G12: 04/03/2026 11:35:00 | H12: 04/03/2026 22:36:00 | I12: RECHAZO MANUAL DE CARGA POR SOBRECARGA DEL TRANSFORMADOR T47-131 DE 138/34,5/10,5 kV DE LA S.E. QUENCORO | J12: 0.59 | K12: SI
B13: FALLA | C13: SAN GABAN | D13: PCH TUPURI | E13: CENTRAL HIDROELÉCTRICA | F13: CENTRAL | G13: 04/03/2026 07:44:00 | H13: 04/03/2026 08:27:00 | I13: DESCONEXIÓN DEL GENERADOR G1 DE LA P.C.H. TUPURI | K13: NO | L13: 2.4
B14: FALLA | C14: STATKRAFT S.A | D14: CAHUA | E14: GENERADOR HIDROELÉCTRICO | F14: G1 | G14: 04/03/2026 19:14:33 | H14: 04/03/2026 20:41:00 | I14: DESCONEXIÓN DEL GENERADOR G1 DE LA C.H. CAHUA | K14: NO | L14: 10
B15: FALLA | C15: STATKRAFT S.A | D15: YAUPI | E15: GENERADOR HIDROELÉCTRICO | F15: G1 | G15: 04/03/2026 05:47:56 | H15: 04/03/2026 09:58:00 | I15: DESCONEXIÓN DEL GENERADOR G1 DE LA C.H. YAUPI | K15: NO | L15: 13.8

Sheet RESTRIC_OPE
B3: miércoles, 4 de Marzo del 2026
B5: RESTRICCIONES OPERATIVAS
B6: FECHA | C6: HORA INICIO | D6: HORA FINAL | E6: EMPRESA | F6: UBICACIÓN | G6: T.Eq. | H6: EQUIPO | I6: DESCRIPCIÓN
B7: 04/03/2026 | C7: 00:00 | D7: 24:00 | E7: CELEPSA | F7: C.H. EL PLATANAL | G7: CH | H7: CENTRAL | I7: De acuerdo con lo informado por CELEPSA mediante correo el dia 17.01, declaran que la CH Platanal se encontrará de pasada.
B8: 04/03/2026 | C8: 00:00 | D8: 24:00 | E8: EGASA | F8: S.E. CONVERTIDOR | G8: BARRA | H8: BARRA138KV | I8: EGASA limitó la capacidad del transformador 138 kV/33 kV a 50 MVA por deterioro del aislamiento.
B9: 04/03/2026 | C9: 00:00 | D9: 24:00 | E9: ELECTROPERU | F9: C.H. MANTARO | G9: CH | H9: CENTRAL | I9: De acuerdo con el correo del día 25.08.2025, la central tiene una limitación de potencia máxima de 650 MW por seguridad de la central.
B10: 04/03/2026 | C10: 00:00 | D10: 24:00 | E10: EMPRESA DE GENERACION HUALLAGA | F10: C.H. CHAGLLA | G10: CH | H10: CENTRAL | I10: Según lo informado el día 19/02/2026 vía correo electrónico. Se reduce la banda de regulación (RSF) para las unidades G1 y G2 a [180 - 233]. Esto debido a un incremento de vibraciones mecánicas.
B11: 04/03/2026 | C11: 00:00 | D11: 24:00 | E11: ENEL GENERACION PIURA S.A. | F11: C.T. MALACAS | G11: CT | H11: CENTRAL | I11: De acuerdo con la comunicación vía correo del día 24.10.2024. ENEL GENERACIÓN PIURA informa una restricción de potencia para alcanzar 105 MW en simultaneo (TG6+TGN4).
B12: 04/03/2026 | C12: 00:00 | D12: 24:00 | E12: ENEL GENERACION PIURA S.A. | F12: C.T. MALACAS | G12: GT | H12: TG4 | I12: De acuerdo a lo informado por correo electrónico el día 16.01, con la disponibilidad de aproximadamente 12 MMPCD (339.8Mm³) la unidad TG4 puede con una generación de 80 MW durante 4 horas, y a potencia mínima durante el resto de los periodos
B13: 04/03/2026 | C13: 00:00 | D13: 24:00 | E13: ENGIE ENERGIA PERU S.A.A. | F13: C.H. YUNCÁN | G13: GH | H13: G3 | I13: Según la carta N° ENG/ 198-2024 enviada por su representada, se opera de forma continua el G3 de la CH Yuncán, debido a la ejecución de mantenimientos necesarios para evitar daños en los sellos de seguridad de la válvula esférica del grupo.
B14: 04/03/2026 | C14: 00:00 | D14: 24:00 | E14: ENGIE ENERGIA PERU S.A.A. | F14: C.T. CHILCA 1 | G14: CT | H14: CENTRAL | I14: Restricción de temperatura de la C.T Chilca, ver valor en el modelo de despacho.
B15: 04/03/2026 | C15: 00:00 | D15: 24:00 | E15: ENGIE ENERGIA PERU S.A.A. | F15: C.T. CHILCA 1 | G15: CT | H15: CENTRAL | I15: Con carta ENG/971-2023, indica que no puede cumplir con las IO considerada en el PDO_17122023 dado que vulneran la seguridad de sus activos. Indican que se debe tomar TMO=168h.
B16: 04/03/2026 | C16: 00:00 | D16: 24:00 | E16: ENGIE ENERGIA PERU S.A.A. | F16: C.T. CHILCA 2 | G16: CT | H16: CENTRAL | I16: Con carta ENG/971-2023, indica que no puede cumplir con las IO considerada en el PDO_17122023 dado que vulneran la seguridad de sus activos. Indican que se debe tomar TMO=168h.
B17: 04/03/2026 | C17: 00:00 | D17: 24:00 | E17: FENIX POWER PERÚ | F17: C.T. FENIX | G17: CT | H17: CENTRAL | I17: De acuerdo con lo comunicado en el correo del día 06.05.2025, la CT Fenix cuenta con TMO de 168 hrs en todos sus modos de operación.
... B58: 04/03/2026 | C58: 00:00 | D58: 24:00 | E58: TERMOSELVA | F58: C.T. AGUAYTÍA | G58: CT | H58: CENTRAL | I58: Disponibilidad de 16 MMSCF para la CT Aguaytía.

Sheet MANTENIMIENTO EJECUTADOS
B3: miércoles, 4 de Marzo del 2026
B5: Mantenimiento Ejecutado
B6: Empresa | C6: Ubicación | D6: Equipo | E6: Inicio | F6: Final | G6: Descripción | H6: MW Indisp. | I6: Prog. | J6: Dispon | K6: Interrupc. | L6: Tipo | M6: CodEq | N6: TipoEq_Osinerg
B7: AGRO INDUSTRIAL PARAMONGA S.A. | C7: PARAMONGA | D7: TV-01 | E7: 04/03/2026 00:00 | F7: 04/03/2026 07:59 | G7: LIMPIEZA E INSPECCION DE LA CALDERA CBS Y MANTENIMIENTO A SUS PERIFERICOS (CONDUCTORES, VENTILADORES, BOMBAS, MOTORES, ETC) | H7: 14 | I7: P | J7: F/S | K7: N | L7: PREV. | M7: 12664 | N7: G
B8: ATLANTICA TRANSMISION SUR S.A. | C8: OCONA | D8: INT-5450 | E8: 04/03/2026 00:00 | F8: 05/03/2026 00:00 | G8: Interruptor INT-5450 cerrado con restriccion operativa, REB-5450 en servicio y suministrando los SS.AA. de la S.E. Oco?a. | H8: 0 | I8: P | J8: E/S | K8: N | L8: OTROS | M8: 13761 | N8: T
B9: ATLANTICA TRANSMISION SUR S.A. | C9: POROMA | D9: REB-5350 | E9: 04/03/2026 00:00 | F9: 05/03/2026 00:00 | G9: Fuera de servicio por falla en el equipo. | H9: 0 | I9: P | J9: F/S | K9: N | L9: OTROS | M9: 13771 | N9: T
B10: ATN S.A. | C10: KIMAN AYLLU | D10: AUT-501 | E10: 04/03/2026 00:00 | F10: 05/03/2026 00:00 | G10: Restriccion Operativa en el circuito de control de cambiador de tap s del AUT-501 | H10: 0 | I10: P | J10: E/S | K10: N | L10: OTROS | M10: 13099 | N10: T
B11: BIOENERGIA DEL CHIRA S.A. | C11: CA?A BRAVA | D11: CENTRAL | E11: 04/03/2026 00:00 | F11: 05/03/2026 00:00 | G11: La C.T. Ca?a Brava para para mentenimiento anual programado. | H11: 11.9 | I11: P | J11: F/S | K11: N | L11: PREV. | M11: 20510 | N11: G
B12: CONELSUR LT SAC | C12: CAJAMARQUILLA | D12: BARRA A 220kV | E12: 04/03/2026 00:00 | F12: 05/03/2026 00:00 | G12: NO SE PUEDE INDISPONER LA BARRA A POR RESTRICCION OPERATIVA DEL SECCIONADOR DE BARRA B DE LA CL-TR1 | H12: 0 | I12: F | J12: E/S | K12: N | L12: OTROS | M12: 1103 | N12: T
B13: CONELSUR LT SAC | C13: CAJAMARQUILLA | D13: CL-TRAFO | E13: 04/03/2026 00:00 | F13: 05/03/2026 00:00 | G13: INDISPONIBLE SECCIONADOR DE BARRA B SB-20011 DE CL-TR1 | H13: 0 | I13: F | J13: E/S | K13: N | L13: OTROS | M13: 1906 | N13: T
B14: CONELSUR LT SAC | C14: CALLAHUANCA (CNS) | D14: CL-2008 | E14: 04/03/2026 00:00 | F14: 05/03/2026 00:00 | G14: RELE DE RESPALDO INOPERATIVO | H14: 0 | I14: F | J14: E/S | K14: N | L14: OTROS | M14: 1337 | N14: T
B15: CONELSUR LT SAC | C15: CALLAHUANCA (CNS) | D15: S.E. | E15: 04/03/2026 00:00 | F15: 05/03/2026 00:00 | G15: RELE DIFERENCIAL DE BARRAS DE CALLAHUANCA 220KV INOPERATIVO | H15: 0 | I15: P | J15: E/S | K15: N | L15: OTROS | M15: 316 | N15: T
B16: CVC ENERGIA | C16: FELAM | D16: BARRA A | E16: 04/03/2026 10:00 | F16: 04/03/2026 17:00 | G16: Se realizaran pruebas de funcionamiento de la operacion en manivela; para ello, se efectuara la transferencia de carga de la barra A hacia la barra B y viceversa. El mismo dia 04/03 a las 17:00 horas, se gestionara el retorno a la topologia inicial, restableciendo la operacion en la barra A. | H16: 0 | I16: P | J16: F/S | K16: N | L16: OTROS | M16: 14754 | N16: T
B17: EGASA | C17: CHARCANI IV | D17: CENTRAL | E17: 04/03/2026 00:00 | F17: 05/03/2026 00:00 | G17: FS Fuerza Mayor, Ingreso de huayco a la central. | H17: 15 | I17: F | J17: F/S | K17: N | L17: OTROS | M17: 1198 | N17: G
B18: EGASA | C18: CHARCANI V | D18: CAMPANARIO | E18: 04/03/2026 00:00 | F18: 05/03/2026 00:00 | G18: FS por prevencion temporada de lluvias | H18: 0 | I18: P | J18: F/S | K18: N | L18: PREV. | M18: 11422 | N18: T
... B116: TRANSMANTARO | C116: YARABAMBA | D116: SS.EE. | E116: 04/03/2026 00:00 | F116: 05/03/2026 00:00 | G116: PROTECCION DIFERENCIAL DE BARRAS 87B 220 KV SE ENCUENTRA BLOQUEADO, LUEGO DE TENER UNA ACTUACION INDESEADA DURANTE EL EVENTO DEL 11.01.2026. | H116: 0 | I116: P | J116: E/S | K116: N | L116: OTROS | M116: 17419 | N116: T

Sheet INGRESO OC
A3: miércoles, 4 de Marzo del 2026
A5: INGRESO A OPERACIÓN COMERCIAL
A6: EMPRESA | B6: TIPO DE EQUIPO | C6: UBICACIÓN | D6: EQUIPO | E6: Fecha y hora de Ingreso a Operación Comercial

Sheet DESPACHO_EJECUTADO
B3: miércoles, 4 de Marzo del 2026
A5: POTENCIA ACTIVA EJECUTADA DE LAS UNIDADES DE GENERACIÓN DEL SEIN (MW) | FQ5: CENTRALES NO INTEGRANTES COES
A6: FECHA | B6: HORA | C6: 65333 | D6: 101 | E6: 102 | F6: 42667 | G6: 42668 | H6: 126 | I6: 127 | J6: 138 | K6: 139 | L6: 197 | M6: 203 | N6: 204 | O6: 230 | P6: 209 | Q6: 56677 | R6: 796 | S6: 2146 | T6: 142 | U6: 143 | V6: 125 | W6: 187 | X6: 163 | Y6: 298 | Z6: 299 | AA6: 219 | AB6: 151 | AC6: 152 | AD6: 153 | AE6: 154 | AF6: 756 | AG6: 156 | AH6: 155 | AI6: 182 | AJ6: 212 | AK6: 758 | AL6: 263 | AM6: 265 | AN6: 775 | AO6: 777 | AP6: 2154 | AQ6: 150 | AR6: 149 | AS6: 188 | AT6: 2131 | AU6: 755 | AV6: 252 | AW6: 249 | AX6: 250 | AY6: 117 | AZ6: 119 | BA6: 120 | BB6: 189 | BC6: 122 | BD6: 266 | BE6: 337 | BF6: 338 | BG6: 251 | BH6: 115 | BI6: 239 | BJ6: 288 | BK6: 240 | BL6: 241 | BM6: 242 | BN6: 191 | BO6: 194 | BP6: 196 | BQ6: 207 | BR6: 236 | BS6: 795 | BT6: 285 | BU6: 995 | BV6: 996 | BW6: 997 | BX6: 766 | BY6: 926 | BZ6: 924 | CA6: 121 | CB6: 103 | CC6: 104 | CD6: 106 | CE6: 105 | CF6: 107 | CG6: 110 | CH6: 109 | CI6: 144 | CJ6: 113 | CK6: 114 | CL6: 193 | CM6: 208 | CN6: 786 | CO6: 787 | CP6: 788 | CQ6: 789 | CR6: 248 | CS6: 2159 | CT6: 267 | CU6: 268 | CV6: 2194 | CW6: 303 | CX6: 59715 | CY6: 62255 | CZ6: 1263 | DA6: 61800 | DB6: 69125 | DC6: 216 | DD6: 198 | DE6: 70400 | DF6: 76068 | DG6: 49607 | DH6: 214 | DI6: 260 | DJ6: 2152 | DK6: 2128 | DL6: 247 | DM6: 228 | DN6: 2135 | DO6: 261 | DP6: 237 | DQ6: 253 | DR6: 770 | DS6: 235 | DT6: 238 | DU6: 2184 | DV6: 61855 | DW6: 223 | DX6: 75566 | DY6: 226 | DZ6: 201 | EA6: 258 | EB6: 259 | EC6: 257 | ED6: 256 | EE6: 2148 | EF6: 58288 | EG6: 58289 | EH6: 58839 | EI6: 58840 | EJ6: 75260 | EK6: 296 | EL6: 297 | EM6: 211 | EN6: 2175 | EO6: 2178 | EP6: 2181 | EQ6: 1262 | ER6: 63425 | ES6: 233 | ET6: 2150 | EU6: 2165 | EV6: 2161 | EW6: 61197 | EX6: 58851 | EY6: 225 | EZ6: 2201 | FA6: 2171 | FB6: 760 | FC6: 234 | FD6: 215 | FE6: 917 | FF6: 920 | FG6: 289 | FH6: 58333 | FI6: 58336 | FJ6: 213 | FK6: 232 | FL6: 2190 | FM6: 69867 | FN6: 75066 | FO6: TOTAL COES | FQ6: 221 | FR6: 222 | FS6: 224 | FT6: 2187 | FU6: 227 | FV6: 49400 | FW6: 199 | FX6: 200 | FY6: TOTAL NO COES
C7: SUR | D7: CENTRO | E7: CENTRO | F7: NORTE | G7: NORTE | H7: NORTE | I7: NORTE | J7: CENTRO | K7: CENTRO | L7: CENTRO | M7: CENTRO | N7: CENTRO | O7: CENTRO | P7: CENTRO | Q7: CENTRO | R7: CENTRO | S7: CENTRO | T7: CENTRO | U7: CENTRO | V7: CENTRO | W7: CENTRO | X7: SUR | Y7: SUR | Z7: SUR | AA7: CENTRO | AB7: SUR | AC7: SUR | AD7: SUR | AE7: SUR | AF7: SUR | AG7: SUR | AH7: SUR | AI7: SUR | AJ7: CENTRO | AK7: NORTE | AL7: NORTE | AM7: NORTE | AN7: CENTRO | AO7: CENTRO | AP7: CENTRO | AQ7: CENTRO | AR7: CENTRO | AS7: CENTRO | AT7: CENTRO | AU7: SUR | AV7: CENTRO | AW7: CENTRO | AX7: CENTRO | AY7: CENTRO | AZ7: CENTRO | BA7: CENTRO | BB7: SUR | BC7: NORTE | BD7: CENTRO | BE7: CENTRO | BF7: CENTRO | BG7: CENTRO | BH7: NORTE | BI7: NORTE | BJ7: NORTE | BK7: SUR | BL7: SUR | BM7: SUR | BN7: CENTRO | BO7: CENTRO | BP7: CENTRO | BQ7: CENTRO | BR7: CENTRO | BS7: CENTRO | BT7: CENTRO | BU7: SUR | BV7: SUR | BW7: SUR | BX7: NORTE | BY7: SUR | BZ7: CENTRO | CA7: NORTE | CB7: CENTRO | CC7: CENTRO | CD7: CENTRO | CE7: CENTRO | CF7: CENTRO | CG7: CENTRO | CH7: CENTRO | CI7: CENTRO | CJ7: CENTRO | CK7: CENTRO | CL7: CENTRO | CM7: CENTRO | CN7: SUR | CO7: SUR | CP7: SUR | CQ7: SUR | CR7: CENTRO | CS7: CENTRO | CT7: CENTRO | CU7: CENTRO | CV7: NORTE | CW7: CENTRO | CX7: CENTRO | CY7: SUR | CZ7: NORTE | DA7: NORTE | DB7: CENTRO | DC7: NORTE | DD7: NORTE | DE7: SUR | DF7: SUR | DG7: SUR | DH7: CENTRO | DI7: CENTRO | DJ7: CENTRO | DK7: NORTE | DL7: NORTE | DM7: CENTRO | DN7: CENTRO | DO7: SUR | DP7: SUR | DQ7: CENTRO | DR7: CENTRO | DS7: SUR | DT7: CENTRO | DU7: CENTRO | DV7: NORTE | DW7: CENTRO | DX7: CENTRO | DY7: CENTRO | DZ7: NORTE | EA7: CENTRO | EB7: CENTRO | EC7: NORTE | ED7: NORTE | EE7: SUR | EF7: CENTRO | EG7: CENTRO | EH7: CENTRO | EI7: CENTRO | EJ7: SUR | EK7: CENTRO | EL7: CENTRO | EM7: SUR | EN7: SUR | EO7: SUR | EP7: SUR | EQ7: NORTE | ER7: SUR | ES7: SUR | ET7: SUR | EU7: CENTRO | EV7: CENTRO | EW7: CENTRO | EX7: SUR | EY7: CENTRO | EZ7: CENTRO | FA7: CENTRO | FB7: CENTRO | FC7: SUR | FD7: NORTE | FE7: CENTRO | FF7: CENTRO | FG7: NORTE | FH7: NORTE | FI7: NORTE | FJ7: CENTRO | FK7: NORTE | FL7: NORTE | FM7: NORTE | FN7: NORTE | FQ7: NORTE | FR7: CENTRO | FS7: NORTE | FT7: NORTE | FU7: NORTE | FV7: NORTE | FW7: NORTE | FX7: NORTE
C8: HIDROELÉCTRICA | D8: HIDROELÉCTRICA | E8: HIDROELÉCTRICA | F8: TERMOELÉCTRICA | G8: TERMOELÉCTRICA | H8: HIDROELÉCTRICA | I8: HIDROELÉCTRICA | J8: TERMOELÉCTRICA | K8: TERMOELÉCTRICA | L8: TERMOELÉCTRICA | M8: TERMOELÉCTRICA | N8: TERMOELÉCTRICA | O8: TERMOELÉCTRICA | P8: TERMOELÉCTRICA | Q8: TERMOELÉCTRICA | R8: HIDROELÉCTRICA | S8: HIDROELÉCTRICA | T8: TERMOELÉCTRICA | U8: TERMOELÉCTRICA | V8: TERMOELÉCTRICA | W8: TERMOELÉCTRICA | X8: HIDROELÉCTRICA | Y8: HIDROELÉCTRICA | Z8: HIDROELÉCTRICA | AA8: TERMOELÉCTRICA | AB8: HIDROELÉCTRICA | AC8: HIDROELÉCTRICA | AD8: HIDROELÉCTRICA | AE8: HIDROELÉCTRICA | AF8: TERMOELÉCTRICA | AG8: TERMOELÉCTRICA | AH8: TERMOELÉCTRICA | AI8: HIDROELÉCTRICA | AJ8: HIDROELÉCTRICA | AK8: TERMOELÉCTRICA | AL8: TERMOELÉCTRICA | AM8: TERMOELÉCTRICA | AN8: HIDROELÉCTRICA | AO8: HIDROELÉCTRICA | AP8: HIDROELÉCTRICA | AQ8: HIDROELÉCTRICA | AR8: HIDROELÉCTRICA | AS8: HIDROELÉCTRICA | AT8: HIDROELÉCTRICA | AU8: HIDROELÉCTRICA | AV8: TERMOELÉCTRICA | AW8: TERMOELÉCTRICA | AX8: TERMOELÉCTRICA | AY8: HIDROELÉCTRICA | AZ8: HIDROELÉCTRICA | BA8: HIDROELÉCTRICA | BB8: HIDROELÉCTRICA | BC8: HIDROELÉCTRICA | BD8: HIDROELÉCTRICA | BE8: HIDROELÉCTRICA | BF8: HIDROELÉCTRICA | BG8: HIDROELÉCTRICA | BH8: TERMOELÉCTRICA | BI8: TERMOELÉCTRICA | BJ8: TERMOELÉCTRICA | BK8: TERMOELÉCTRICA | BL8: TERMOELÉCTRICA | BM8: TERMOELÉCTRICA | BN8: HIDROELÉCTRICA | BO8: TERMOELÉCTRICA | BP8: TERMOELÉCTRICA | BQ8: TERMOELÉCTRICA | BR8: TERMOELÉCTRICA | BS8: TERMOELÉCTRICA | BT8: TERMOELÉCTRICA | BU8: TERMOELÉCTRICA | BV8: TERMOELÉCTRICA | BW8: TERMOELÉCTRICA | BX8: HIDROELÉCTRICA | BY8: TERMOELÉCTRICA | BZ8: TERMOELÉCTRICA | CA8: HIDROELÉCTRICA | CB8: HIDROELÉCTRICA | CC8: HIDROELÉCTRICA | CD8: HIDROELÉCTRICA | CE8: HIDROELÉCTRICA | CF8: HIDROELÉCTRICA | CG8: TERMOELÉCTRICA | CH8: TERMOELÉCTRICA | CI8: TERMOELÉCTRICA | CJ8: TERMOELÉCTRICA | CK8: TERMOELÉCTRICA | CL8: TERMOELÉCTRICA | CM8: TERMOELÉCTRICA | CN8: TERMOELÉCTRICA | CO8: TERMOELÉCTRICA | CP8: TERMOELÉCTRICA | CQ8: TERMOELÉCTRICA | CR8: TERMOELÉCTRICA | CS8: TERMOELÉCTRICA | CT8: HIDROELÉCTRICA | CU8: HIDROELÉCTRICA | CV8: HIDROELÉCTRICA | CW8: SOLAR | CX8: EÓLICA | CY8: SOLAR | CZ8: EÓLICA | DA8: SOLAR | DB8: HIDROELÉCTRICA | DC8: HIDROELÉCTRICA | DD8: HIDROELÉCTRICA | DE8: SOLAR | DF8: SOLAR | DG8: HIDROELÉCTRICA | DH8: HIDROELÉCTRICA | DI8: HIDROELÉCTRICA | DJ8: HIDROELÉCTRICA | DK8: HIDROELÉCTRICA | DL8: HIDROELÉCTRICA | DM8: HIDROELÉCTRICA | DN8: HIDROELÉCTRICA | DO8: SOLAR | DP8: SOLAR | DQ8: EÓLICA | DR8: EÓLICA | DS8: SOLAR | DT8: HIDROELÉCTRICA | DU8: HIDROELÉCTRICA | DV8: HIDROELÉCTRICA | DW8: HIDROELÉCTRICA | DX8: SOLAR | DY8: HIDROELÉCTRICA | DZ8: HIDROELÉCTRICA | EA8: HIDROELÉCTRICA | EB8: HIDROELÉCTRICA | EC8: EÓLICA | ED8: EÓLICA | EE8: SOLAR | EF8: EÓLICA | EG8: EÓLICA | EH8: EÓLICA | EI8: EÓLICA | EJ8: SOLAR | EK8: HIDROELÉCTRICA | EL8: HIDROELÉCTRICA | EM8: HIDROELÉCTRICA | EN8: HIDROELÉCTRICA | EO8: HIDROELÉCTRICA | EP8: HIDROELÉCTRICA | EQ8: EÓLICA | ER8: SOLAR | ES8: SOLAR | ET8: SOLAR | EU8: HIDROELÉCTRICA | EV8: EÓLICA | EW8: EÓLICA | EX8: SOLAR | EY8: TERMOELÉCTRICA | EZ8: TERMOELÉCTRICA | FA8: TERMOELÉCTRICA | FB8: TERMOELÉCTRICA | FC8: SOLAR | FD8: HIDROELÉCTRICA | FE8: HIDROELÉCTRICA | FF8: HIDROELÉCTRICA | FG8: TERMOELÉCTRICA | FH8: TERMOELÉCTRICA | FI8: TERMOELÉCTRICA | FJ8: TERMOELÉCTRICA | FK8: TERMOELÉCTRICA | FL8: TERMOELÉCTRICA | FM8: TERMOELÉCTRICA | FN8: TERMOELÉCTRICA | FQ8: HIDROELÉCTRICA | FR8: HIDROELÉCTRICA | FS8: HIDROELÉCTRICA | FT8: HIDROELÉCTRICA | FU8: TERMOELÉCTRICA | FV8: TERMOELÉCTRICA | FW8: HIDROELÉCTRICA | FX8: HIDROELÉCTRICA
C9: HYDRO GLOBAL PERÚ S.A.C. | D9: ELECTROPERU | E9: ELECTROPERU | F9: ELECTROPERU | G9: ELECTROPERU | H9: ORAZUL ENERGY PERÚ | I9: ORAZUL ENERGY PERÚ | J9: TERMOSELVA | K9: TERMOSELVA | L9: KALLPA GENERACION S.A. | M9: KALLPA GENERACION S.A. | N9: KALLPA GENERACION S.A. | O9: KALLPA GENERACION S.A. | P9: KALLPA GENERACION S.A. | Q9: KALLPA GENERACION S.A. | R9: KALLPA GENERACION S.A. | S9: KALLPA GENERACION S.A. | T9: SHOUGESA | U9: SHOUGESA | V9: SHOUGESA | W9: SHOUGESA | X9: EGEMSA | Y9: EGESUR | Z9: EGESUR | AA9: EGESUR | AB9: EGASA | AC9: EGASA | AD9: EGASA | AE9: EGASA | AF9: EGASA | AG9: EGASA | AH9: EGASA | AI9: SAN GABAN | AJ9: CELEPSA | AK9: MINERA CERRO VERDE | AL9: PLANTA DE RESERVA FRIA DE GENERACION DE ETEN S.A. | AM9: PLANTA DE RESERVA FRIA DE GENERACION DE ETEN S.A. | AN9: EMPRESA DE GENERACION HUALLAGA | AO9: EMPRESA DE GENERACION HUALLAGA | AP9: LA VIRGEN | AQ9: CHINANGO S.A.C. | AR9: CHINANGO S.A.C. | AS9: HIDROELECTRICA HUANCHOR S.A.C. | AT9: CELEPSA RENOVABLES S.R.L. | AU9: INLAND ENERGY SAC | AV9: FENIX POWER PERÚ | AW9: FENIX POWER PERÚ | AX9: FENIX POWER PERÚ | AY9: STATKRAFT S.A | AZ9: STATKRAFT S.A | BA9: STATKRAFT S.A | BB9: STATKRAFT S.A | BC9: STATKRAFT S.A | BD9: STATKRAFT S.A | BE9: CENTRALES SANTA ROSA S.A.C. | BF9: CENTRALES SANTA ROSA S.A.C. | BG9: EMPRESA DE GENERACION HUANZA | BH9: ENEL GENERACION PIURA S.A. | BI9: ENEL GENERACION PIURA S.A. | BJ9: ENEL GENERACION PIURA S.A. | BK9: ENGIE ENERGIA PERU S.A.A. | BL9: ENGIE ENERGIA PERU S.A.A. | BM9: ENGIE ENERGIA PERU S.A.A. | BN9: ENGIE ENERGIA PERU S.A.A. | BO9: ENGIE ENERGIA PERU S.A.A. | BP9: ENGIE ENERGIA PERU S.A.A. | BQ9: ENGIE ENERGIA PERU S.A.A. | BR9: ENGIE ENERGIA PERU S.A.A. | BS9: ENGIE ENERGIA PERU S.A.A. | BT9: ENGIE ENERGIA PERU S.A.A. | BU9: ENGIE ENERGIA PERU S.A.A. | BV9: ENGIE ENERGIA PERU S.A.A. | BW9: ENGIE ENERGIA PERU S.A.A. | BX9: ENGIE ENERGIA PERU S.A.A. | BY9: INFRAESTRUCTURAS Y ENERGIAS DEL PERU S.A.C. | BZ9: INFRAESTRUCTURAS Y ENERGIAS DEL PERU S.A.C. | CA9: INVERSIONES SHAQSHA S.A.C. | CB9: ORYGEN PERU S.A.A. | CC9: ORYGEN PERU S.A.A. | CD9: ORYGEN PERU S.A.A. | CE9: ORYGEN PERU S.A.A. | CF9: ORYGEN PERU S.A.A. | CG9: ORYGEN PERU S.A.A. | CH9: ORYGEN PERU S.A.A. | CI9: ORYGEN PERU S.A.A. | CJ9: ORYGEN PERU S.A.A. | CK9: ORYGEN PERU S.A.A. | CL9: ORYGEN PERU S.A.A. | CM9: ORYGEN PERU S.A.A. | CN9: SAMAY I S.A.C | CO9: SAMAY I S.A.C | CP9: SAMAY I S.A.C | CQ9: SAMAY I S.A.C | CR9: TERMOCHILCA S.A.C. | CS9: TERMOCHILCA S.A.C. | CT9: TRANSMISION ANDINA DE GENERACION S.A.C. | CU9: TRANSMISION ANDINA DE GENERACION S.A.C. | CV9: CELARIS ENERGY S.A. | CW9: COLCA SOLAR S.A.C. | CX9: ENERGIA RENOVABLE DEL SUR S.A. | CY9: GR CORTARRAMA SOCIEDAD ANONIMA CERRADA | CZ9: GR TARUCA SOCIEDAD ANONIMA CERRADA | DA9: KONDU SAC | DB9: VARI ENERGIA S.A.C. | DC9: ORAZUL ENERGY PERÚ | DD9: ORAZUL ENERGY PERÚ | DE9: KALLPA GENERACION S.A. | DF9: KALLPA GENERACION S.A. | DG9: SAN GABAN | DH9: MAJA ENERGIA S.A.C. | DI9: EMPRESA DE GENERACION ELECTRICA CANCHAYLLO SAC | DJ9: EMPRESA DE GENERACION ELECTRICA SANTA ANA S.A.C. | DK9: EMPRESA ELECTRICA AGUA AZUL | DL9: EMPRESA ELECTRICA RIO DOBLE | DM9: HIDROCAÑETE S.A. | DN9: HUAURA POWER GROUP S.A. | DO9: MOQUEGUA FV S.A.C. | DP9: PANAMERICANA SOLAR SAC. | DQ9: PARQUE EOLICO MARCONA S.A.C. | DR9: PARQUE EOLICO TRES HERMANAS S.A.C. | DS9: TACNA SOLAR SAC. | DT9: ELECTRICA YANAPAMPA SAC | DU9: ANDEAN POWER S.A.C. | DV9: ASOCIACIÓN SANTA LUCIA DE CHACAS | DW9: ATRIA ENERGIA S.A.C. | DX9: COENERGY S.A.C. | DY9: EGEJUNIN | DZ9: EGEJUNIN | EA9: EGEJUNIN | EB9: EGEJUNIN | EC9: ENERGÍA EÓLICA S.A. | ED9: ENERGÍA EÓLICA S.A. | EE9: ENGIE ENERGIA PERU S.A.A. | EF9: ENGIE ENERGIA PERU S.A.A. | EG9: ENGIE ENERGIA PERU S.A.A. | EH9: ENGIE ENERGIA PERU S.A.A. | EI9: ENGIE ENERGIA PERU S.A.A. | EJ9: ENGIE ENERGIA PERU S.A.A. | EK9: GENERACIÓN ANDINA S.A.C. | EL9: GENERACIÓN ANDINA S.A.C. | EM9: GENERADORA DE ENERGÍA DEL PERÚ | EN9: GENERADORA DE ENERGÍA DEL PERÚ | EO9: GENERADORA DE ENERGÍA DEL PERÚ | EP9: GENERADORA DE ENERGÍA DEL PERÚ | EQ9: GR PAINO SOCIEDAD ANONIMA CERRADA | ER9: JOYA SOLAR S.A.C. | ES9: MAJES ARCUS S.A.C. | ET9: ORYGEN PERU S.A.A. | EU9: ORYGEN PERU S.A.A. | EV9: ORYGEN PERU S.A.A. | EW9: ORYGEN PERU S.A.A. | EX9: ORYGEN PERU S.A.A. | EY9: PETRAMAS | EZ9: PETRAMAS | FA9: PETRAMAS | FB9: PETRAMAS | FC9: REPARTICIÓN ARCUS S.A.C. | FD9: SINERSA | FE9: SINERSA | FF9: SINERSA | FG9: BIOENERGIA DEL CHIRA S.A. | FH9: GM OPERACIONES S.A.C. | FI9: GM OPERACIONES S.A.C. | FJ9: AGRO INDUSTRIAL PARAMONGA S.A. | FK9: AGROAURORA S.A.C. | FL9: AGROINDUSTRIAS SAN JACINTO S.A.A. | FM9: AGROLMOS SOCIEDAD ANONIMA - AGROLMOS S.A. | FN9: CASA GRANDE S.A.A. | FQ9: UNACEM PERU S.A. | FR9: ELECTRO ORIENTE | FS9: AGUAS Y ENERGIA PERU | FT9: ELECTRO ZAÑA S.A.C. | FU9: ELECTRONOROESTE S.A. | FV9: SDE PIURA | FW9: SINERSA | FX9: SINERSA
C10: SAN GABAN III | D10: MANTARO | E10: RESTITUCION | F10: TUMBES MAK 1 | G10: TUMBES MAK 2 | H10: CARHUAQUERO | I10: CAÑON DEL PATO | J10: AGUAYTIA TG1 | K10: AGUAYTIA TG2 | L10: KALLPA TG1 | M10: KALLPA TG2 | N10: KALLPA TG3 | O10: KALLPA TV | P10: LFLORES TG1 | Q10: LFLORES TV | R10: CERRO DEL AGUILA | S10: CERRODELAGUILAG4 | T10: SHOUGESA TV1 | U10: SHOUGESA TV2 | V10: SHOUGESA TV3 | W10: SHOUGESA CUMMINS | X10: MACHUPICCHU | Y10: ARICOTA 1 | Z10: ARICOTA 2 | AA10: INDEPENDENCIA | AB10: CHARCANI I,II,III | AC10: CHARCANI IV | AD10: CHARCANI V | AE10: CHARCANI VI | AF10: CHILINA TG | AG10: MOLLENDO 1, 2, 3 | AH10: CHILINA (SULZ 1,2) | AI10: SAN GABAN II | AJ10: PLATANAL | AK10: RECKA | AL10: RF ETEN TG1 | AM10: RF ETEN TG2 | AN10: CHAGLLA GP1 | AO10: CHAGLLA | AP10: LA VIRGEN | AQ10: CHIMAY | AR10: YANANGO | AS10: HUANCHOR | AT10: MARAÑON | AU10: STA TERESA | AV10: FENIX GT11 | AW10: FENIX GT12 | AX10: FENIX TV10 | AY10: YAUPI | AZ10: MALPASO | BA10: CAHUA | BB10: ARCATA | BC10: GALLITO CIEGO | BD10: CHEVES | BE10: SANTA ROSA 1 | BF10: SANTA ROSA 2 | BG10: HUANZA | BH10: MALACAS2 TG4 | BI10: MALACAS3 TG 5 | BJ10: MALACAS1 TG6 | BK10: RF ILO2 TG1 | BL10: RF ILO2 TG2 | BM10: RF ILO2 TG3 | BN10: YUNCAN | BO10: CHILCA1 TG1 | BP10: CHILCA1 TG2 | BQ10: CHILCA1 TG3 | BR10: CHILCA-TV | BS10: CHILCA2 TG41 | BT10: CHILCA2-TV | BU10: CTNEPI_TG41 | BV10: CTNEPI_TG42 | BW10: CTNEPI_TG43 | BX10: QUITARACSA | BY10: RF PTO MALDONADO | BZ10: RF PUCALLPA | CA10: PARIAC | CB10: HUINCO | CC10: MATUCANA | CD10: MOYOPAMPA | CE10: CALLAHUANCA | CF10: HUAMPANI | CG10: STA ROSA WEST TG7 | CH10: UTI_5 | CI10: UTI_6 | CJ10: VENTANILLA 3 | CK10: VENTANILLA 4 | CL10: VENTANILLA TV | CM10: STAROSA TG8 | CN10: PTO_BRVO TG1 | CO10: PTO_BRVO TG2 | CP10: PTO_BRVO TG3 | CQ10: PTO_BRVO TG4 | CR10: OLLEROS TG1 | CS10: OLLEROS TV | CT10: OROYA | CU10: PACHACHACA | CV10: MANTA I | CW10: CS YARUCAYA | CX10: SAN JUAN | CY10: MATARANI | CZ10: DUNA | DA10: CARHUAQUERO (CS) | DB10: ANASHIRONI | DC10: CARHUAQUERO4 | DD10: CAÑA BRAVA | DE10: SUNNY | DF10: SUNNY EXPANSION | DG10: TUPURI | DH10: RONCADOR | DI10: CANCHAYLLO | DJ10: RENOVANDESH1 | DK10: POTRERO | DL10: PIZARRAS | DM10: NIMPERIAL | DN10: YARUCAYA | DO10: MOQUEGUA-SOLAR | DP10: PANAMERICANA-SOLAR | DQ10: PQE-EOLICO-MARCONA | DR10: PQE-EOLICO-3-HERMANAS | DS10: TACNA-SOLAR | DT10: YANAPAMPA | DU10: CARHUAC | DV10: HUALLIN | DW10: PURMACANA | DX10: COENERGY | DY10: HUASAHUASI | DZ10: STACRUZ_1_2 | EA10: RUNATULLO_II | EB10: RUNATULLO_III | EC10: PQE-EOLICO-TALARA | ED10: PQE-EOLICO-CUPISNIQUE | EE10: INTIPAMPA | EF10: PUNTA LOMITAS-BL1 | EG10: PUNTA LOMITAS-BL2 | EH10: PUN LOMITAS_EXP-BL1 | EI10: PUN LOMITAS_EXP-BL2 | EJ10: EXPANSIÓN INTIPAMPA | EK10: 8AGOSTO | EL10: EL CARMEN | EM10: LA JOYA | EN10: ANGEL_I | EO10: ANGEL_II | EP10: ANGEL_III | EQ10: HUAMBOS | ER10: SAN MARTIN SOLAR | ES10: MAJES | ET10: RUBI | EU10: CH_HER1 | EV10: WAYRA-I | EW10: WAYRA EXTENSION | EX10: CLEMESI | EY10: HUAYCOLORO | EZ10: CALLAO | FA10: DONA_CATALINA | FB10: LAGRINGAV | FC10: REPARTICION | FD10: POECHOS2 | FE10: CHANCAY | FF10: RUCUY | FG10: CANA BRAVA | FH10: REFINERIA TALARA TV1 | FI10: REFINERÍA TALARA TV2 | FJ10: PARAMONGA | FK10: MAPLE | FL10: SAN_JACINTO | FM10: AGROLMOS | FN10: CASA GRANDE | FO10: MW | FQ10: CARPAPATA | FR10: CENTRALES ELOR | FS10: PIAS1 | FT10: ZANA | FU10: TABLAZO | FV10: TALLANCA | FW10: CURUMUY | FX10: POECHOS1 | FY10: MW
A11: 04/03/2026 | B11: 00:30 | C11: 201.4 | D11: 652.2 | E11: 213.4 | F11: 7.5 | G11: 7.7 | H11: 92.1 | I11: 235.5 | J11: 0 | K11: 80.3 | R11: 532.4 | S11: 10.2 | T11: 13.6 | U11: 5.6 | X11: 166.4 | Y11: 9.9 | Z11: 6.6 | AB11: 6.4 | AD11: 79.5 | AI11: 110.2 | AJ11: 202.4 | AK11: 0 | AN11: 6.5 | AO11: 394.5 | AP11: 82.5 | AQ11: 150.5 | AR11: 42.1 | AS11: 18.6 | AT11: 18.9 | AU11: 91.8 | AV11: 0 | AW11: 91.6 | AX11: 61 | AY11: 109.7 | AZ11: 45.9 | BA11: 0 | BB11: 3.8 | BC11: 28.8 | BD11: 173.5 | BG11: 92.6 | BH11: 34.8 | BJ11: 0 | BN11: 131.6 | BU11: 194.5 | BV11: 195.4 | BW11: 195.8 | BX11: 0 | CA11: 4.4 | CB11: 257.1 | CC11: 132.6 | CD11: 62.2 | CE11: 77.8 | CF11: 26.4 | CG11: 0 | CJ11: 138.3 | CN11: 0 | CO11: 174.4 | CP11: 175 | CQ11: 174.6 | CT11: 0 | CU11: 8.5 | CV11: 20 | CW11: 0 | CX11: 62.1 | CY11: 0 | CZ11: 0 | DA11: 0 | DB11: 20.3 | DC11: 9.9 | DD11: 5.5 | DE11: 0 | DF11: 0 | DG11: 2.2 | DH11: 3.2 | DI11: 5.1 | DJ11: 20.1 | DK11: 15.1 | DL11: 18.7 | DM11: 3.5 | DN11: 18.4 | DO11: 0 | DP11: 0 | DQ11: 18.8 | DR11: 36.3 | DS11: 0 | DT11: 2.8 | DU11: 20.4 | DV11: 3.2 | DX11: 0 | DY11: 19.8 | DZ11: 13.2 | EA11: 20.3 | EB11: 20.2 | EC11: 1.1 | ED11: 0 | EE11: 0 | EF11: 17.9 | EG11: 29 | EH11: 0.6 | EI11: 0 | EJ11: 0 | EK11: 21 | EL11: 7.7 | EM11: 7.3 | EN11: 20.4 | EO11: 20.4 | EP11: 20 | EQ11: 0 | ER11: 0 | ES11: 0 | ET11: 0 | EU11: 0.3 | EV11: 0 | EW11: 0 | EX11: 0 | EY11: 4.8 | EZ11: 2.4 | FA11: 1.2 | FB11: 2.6 | FC11: 0 | FD11: 6.1 | FE11: 20 | FF11: 20 | FH11: 0 | FI11: 0 | FJ11: 0 | FK11: 13.4 | FL11: 7.3 | FM11: 12 | FN11: 14.6 | FO11: 6638.2 | FQ11: 24.5338 | FR11: 7.92 | FS11: 9.6 | FT11: 13.2 | FU11: 25.8 | FV11: 19 | FW11: 9.7 | FX11: 13.4 | FY11: 123.1538
A12: 04/03/2026 | B12: 01:00 | C12: 201.8 | D12: 652.9 | E12: 214.3 | F12: 7.6 | G12: 7.6 | H12: 92.6 | I12: 234.4 | J12: 0 | K12: 59.9 | R12: 562.8 | S12: 10.2 | T12: 13.5 | U12: 0 | X12: 166.4 | Y12: 9.9 | Z12: 6.5 | AB12: 6.4 | AD12: 90.4 | AI12: 110.1 | AJ12: 199 | AK12: 0 | AN12: 6.5 | AO12: 364.4 | AP12: 82.5 | AQ12: 150.4 | AR12: 42.1 | AS12: 18.6 | AT12: 18.9 | AU12: 90.9 | AV12: 0 | AW12: 89.8 | AX12: 61 | AY12: 109.8 | AZ12: 37.9 | BA12: 0 | BB12: 3.8 | BC12: 28.1 | BD12: 171.3 | BG12: 76.6 | BH12: 30.7 | BJ12: 0 | BN12: 131.8 | BU12: 196.2 | BV12: 196.3 | BW12: 196.4 | BX12: 0 | CA12: 4.5 | CB12: 252.2 | CC12: 126.6 | CD12: 62.4 | CE12: 78.7 | CF12: 29.8 | CG12: 0 | CJ12: 138.7 | CN12: 0 | CO12: 174.3 | CP12: 174.9 | CQ12: 174.7 | CT12: 3.6 | CU12: 8.4 | CV12: 19.9 | CW12: 0 | CX12: 63 | CY12: 0 | CZ12: 0 | DA12: 0 | DB12: 20.4 | DC12: 10 | DD12: 5.6 | DE12: 0 | DF12: 0 | DG12: 2.2 | DH12: 3.2 | DI12: 5.1 | DJ12: 20.3 | DK12: 15.1 | DL12: 18.7 | DM12: 3.5 | DN12: 18.4 | DO12: 0 | DP12: 0 | DQ12: 17.7 | DR12: 30 | DS12: 0 | DT12: 2.8 | DU12: 20.4 | DV12: 3.2 | DX12: 0 | DY12: 19.8 | DZ12: 13.2 | EA12: 20.3 | EB12: 20.2 | EC12: 1.4 | ED12: 0 | EE12: 0 | EF12: 10.6 | EG12: 21.2 | EH12: 0 | EI12: 0 | EJ12: 0 | EK12: 21 | EL12: 7.7 | EM12: 7.3 | EN12: 20.4 | EO12: 20.4 | EP12: 20 | EQ12: 0 | ER12: 0 | ES12: 0 | ET12: 0 | EU12: 0.3 | EV12: 0 | EW12: 0 | EX12: 0 | EY12: 4.8 | EZ12: 2.4 | FA12: 1.2 | FB12: 2.6 | FC12: 0 | FD12: 6.2 | FE12: 20 | FF12: 20 | FH12: 0 | FI12: 0 | FJ12: 0 | FK12: 13.2 | FL12: 7 | FM12: 11.7 | FN12: 15 | FO12: 6566.5 | FQ12: 24.48813 | FR12: 7.92 | FS12: 9.5 | FT12: 13.2 | FU12: 25.7 | FV12: 19 | FW12: 9.8 | FX12: 13.5 | FY12: 123.10813
A13: 04/03/2026 | B13: 01:30 | C13: 202 | D13: 652.7 | E13: 214.1 | F13: 7.6 | G13: 7.7 | H13: 91.4 | I13: 234.9 | J13: 0 | K13: 60.7 | R13: 482.9 | S13: 10.3 | T13: 13.3 | U13: 0 | X13: 165.6 | Y13: 9.9 | Z13: 6.5 | AB13: 6.4 | AD13: 90.6 | AI13: 110.5 | AJ13: 188.6 | AK13: 0 | AN13: 6.5 | AO13: 367.1 | AP13: 80.9 | AQ13: 150.4 | AR13: 42.2 | AS13: 18.6 | AT13: 18.9 | AU13: 90.5 | AV13: 0 | AW13: 90.8 | AX13: 61.3 | AY13: 109.6 | AZ13: 45.7 | BA13: 0 | BB13: 3.8 | BC13: 28.5 | BD13: 174.3 | BG13: 76.1 | BH13: 30.5 | BJ13: 0 | BN13: 131.6 | BU13: 195.9 | BV13: 196.8 | BW13: 196.1 | BX13: 0 | CA13: 4.4 | CB13: 233 | CC13: 124.4 | CD13: 62.3 | CE13: 78.5 | CF13: 29.7 | CG13: 0 | CJ13: 138.5 | CN13: 0 | CO13: 175.9 | CP13: 176.5 | CQ13: 176.3 | CT13: 7.9 | CU13: 8.6 | CV13: 19.8 | CW13: 0 | CX13: 57.9 | CY13: 0 | CZ13: 0 | DA13: 0 | DB13: 20.3 | DC13: 9.8 | DD13: 5.5 | DE13: 0 | DF13: 0 | DG13: 2.2 | DH13: 3.2 | DI13: 5.1 | DJ13: 20.4 | DK13: 15.1 | DL13: 18.7 | DM13: 3.6 | DN13: 18.4 | DO13: 0 | DP13: 0 | DQ13: 15.4 | DR13: 35.1 | DS13: 0 | DT13: 2.7 | DU13: 20.4 | DV13: 3.2 | DX13: 0 | DY13: 19.8 | DZ13: 13.2 | EA13: 20.3 | EB13: 20.2 | EC13: 0.1 | ED13: 0 | EE13: 0 | EF13: 14.4 | EG13: 31.9 | EH13: 0.6 | EI13: 0.1 | EJ13: 0 | EK13: 21 | EL13: 7.6 | EM13: 7.3 | EN13: 20.4 | EO13: 20.4 | EP13: 20 | EQ13: 0 | ER13: 0 | ES13: 0 | ET13: 0 | EU13: 0.3 | EV13: 0 | EW13: 0 | EX13: 0 | EY13: 4.8 | EZ13: 2.4 | FA13: 1.2 | FB13: 2.6 | FC13: 0 | FD13: 6.2 | FE13: 20 | FF13: 20 | FH13: 0 | FI13: 0 | FJ13: 0 | FK13: 15 | FL13: 7.2 | FM13: 12 | FN13: 14.7 | FO13: 6488.3 | FQ13: 24.5196 | FR13: 7.93 | FS13: 9.1 | FT13: 13.2 | FU13: 25.5 | FV13: 19 | FW13: 9.9 | FX13: 13.5 | FY13: 122.6496
A14: 04/03/2026 | B14: 02:00 | C14: 203 | D14: 653 | E14: 214.7 | F14: 7.6 | G14: 7.8 | H14: 92.3 | I14: 234.7 | J14: 0 | K14: 59 | R14: 535.2 | S14: 10.2 | T14: 13.4 | U14: 0 | X14: 166.4 | Y14: 9.5 | Z14: 6.6 | AB14: 6.4 | AD14: 90.6 | AI14: 110.2 | AJ14: 154.8 | AK14: 0 | AN14: 6.5 | AO14: 364.2 | AP14: 81.6 | AQ14: 150.4 | AR14: 42.2 | AS14: 18.6 | AT14: 18.9 | AU14: 91 | AV14: 0 | AW14: 91 | AX14: 60.4 | AY14: 110.1 | AZ14: 46.4 | BA14: 0 | BB14: 3.8 | BC14: 28.5 | BD14: 146.8 | BG14: 76.7 | BH14: 27.7 | BJ14: 0 | BN14: 132 | BU14: 195.1 | BV14: 196.2 | BW14: 196 | BX14: 0 | CA14: 4.4 | CB14: 239.3 | CC14: 128.1 | CD14: 62.4 | CE14: 78.6 | CF14: 30.9 | CG14: 0 | CJ14: 138.8 | CN14: 0 | CO14: 175.8 | CP14: 176.7 | CQ14: 29.8 | CT14: 7.8 | CU14: 8.4 | CV14: 19.8 | CW14: 0 | CX14: 63.4 | CY14: 0 | CZ14: 0 | DA14: 0 | DB14: 20.3 | DC14: 9.8 | DD14: 5.6 | DE14: 0 | DF14: 0 | DG14: 2.2 | DH14: 3.2 | DI14: 5.1 | DJ14: 20.5 | DK14: 15.1 | DL14: 18.8 | DM14: 3.6 | DN14: 17.4 | DO14: 0 | DP14: 0 | DQ14: 14.8 | DR14: 41.3 | DS14: 0 | DT14: 2.7 | DU14: 20.4 | DV14: 3.2 | DX14: 0 | DY14: 19.8 | DZ14: 13.2 | EA14: 20.2 | EB14: 20.2 | EC14: 0.2 | ED14: 0 | EE14: 0 | EF14: 14.5 | EG14: 27.3 | EH14: 0.7 | EI14: 0 | EJ14: 0 | EK14: 21 | EL14: 7.5 | EM14: 7.3 | EN14: 20.4 | EO14: 20.4 | EP14: 20 | EQ14: 0 | ER14: 0 | ES14: 0 | ET14: 0 | EU14: 0.6 | EV14: 0 | EW14: 0 | EX14: 0 | EY14: 4.8 | EZ14: 2.4 | FA14: 1.2 | FB14: 2.6 | FC14: 0 | FD14: 6.2 | FE14: 20 | FF14: 20 | FH14: 0 | FI14: 0 | FJ14: 0 | FK14: 13.1 | FL14: 6.5 | FM14: 11.7 | FN14: 14 | FO14: 6343.5 | FQ14: 24.54509 | FR14: 7.93 | FS14: 8.8 | FT14: 13.2 | FU14: 25.5 | FV14: 19 | FW14: 9.9 | FX14: 13.5 | FY14: 122.37509
A15: 04/03/2026 | B15: 02:30 | C15: 203.4 | D15: 651.6 | E15: 213 | F15: 7.7 | G15: 7.8 | H15: 92.2 | I15: 235 | J15: 0 | K15: 60.1 | R15: 532.6 | S15: 10.2 | T15: 13.2 | U15: 0 | X15: 164.7 | Y15: 9.8 | Z15: 6.6 | AB15: 6.4 | AD15: 90.3 | AI15: 110.3 | AJ15: 179 | AK15: 0 | AN15: 6.5 | AO15: 364.7 | AP15: 82.4 | AQ15: 150.2 | AR15: 42.2 | AS15: 18.6 | AT15: 18.9 | AU15: 89.7 | AV15: 0 | AW15: 91.3 | AX15: 61.1 | AY15: 109.9 | AZ15: 46.5 | BA15: 0 | BB15: 3.8 | BC15: 28.2 | BD15: 141.4 | BG15: 76.5 | BH15: 30.4 | BJ15: 0 | BN15: 131.2 | BU15: 194.6 | BV15: 195.2 | BW15: 195.3 | BX15: 0 | CA15: 4.3 | CB15: 233.6 | CC15: 125.4 | CD15: 62.7 | CE15: 78.5 | CF15: 30.8 | CG15: 0 | CJ15: 138.6 | CN15: 0 | CO15: 175.7 | CP15: 176.2 | CQ15: 0 | CT15: 5.4 | CU15: 8.5 | CV15: 19.6 | CW15: 0 | CX15: 46 | CY15: 0 | CZ15: 0 | DA15: 0 | DB15: 20.3 | DC15: 10 | DD15: 5.6 | DE15: 0 | DF15: 0 | DG15: 2.2 | DH15: 3.2 | DI15: 5.1 | DJ15: 20.3 | DK15: 15.1 | DL15: 18.8 | DM15: 3.6 | DN15: 8.5 | DO15: 0 | DP15: 0 | DQ15: 12.2 | DR15: 37.7 | DS15: 0 | DT15: 2.9 | DU15: 20.4 | DV15: 3.2 | DX15: 0 | DY15: 19.8 | DZ15: 13.2 | EA15: 20.2 | EB15: 20.2 | EC15: 0.8 | ED15: 0 | EE15: 0 | EF15: 14.8 | EG15: 29.2 | EH15: 0.4 | EI15: 0 | EJ15: 0 | EK15: 21 | EL15: 7.5 | EM15: 7.3 | EN15: 20.4 | EO15: 20.4 | EP15: 20 | EQ15: 0 | ER15: 0 | ES15: 0 | ET15: 0 | EU15: 0.6 | EV15: 0 | EW15: 0 | EX15: 0 | EY15: 4.6 | EZ15: 2.4 | FA15: 1.2 | FB15: 1.6 | FC15: 0 | FD15: 6.2 | FE15: 20 | FF15: 20 | FH15: 0 | FI15: 0 | FJ15: 0 | FK15: 13.4 | FL15: 6.5 | FM15: 12 | FN15: 13.6 | FO15: 6284.2 | FQ15: 24.52832 | FR15: 7.93 | FS15: 9.3 | FT15: 13.2 | FU15: 25.5 | FV15: 19 | FW15: 10 | FX15: 13.4 | FY15: 122.85832
A16: 04/03/2026 | B16: 03:00 | C16: 205.8 | D16: 651.7 | E16: 213.8 | F16: 7.8 | G16: 7.8 | H16: 92.1 | I16: 235.6 | J16: 0 | K16: 61.1 | R16: 525.9 | S16: 10.3 | T16: 13.2 | U16: 0 | X16: 166.8 | Y16: 9.9 | Z16: 6.5 | AB16: 6.4 | AD16: 91 | AI16: 110.4 | AJ16: 172.6 | AK16: 0 | AN16: 6.5 | AO16: 363.8 | AP16: 81.4 | AQ16: 150.3 | AR16: 42.1 | AS16: 16.9 | AT16: 18.9 | AU16: 90.2 | AV16: 0 | AW16: 93.1 | AX16: 61.5 | AY16: 110.3 | AZ16: 46.4 | BA16: 0 | BB16: 3.8 | BC16: 28.5 | BD16: 140.6 | BG16: 76.8 | BH16: 28.9 | BJ16: 0 | BN16: 131.4 | BU16: 193.9 | BV16: 195.4 | BW16: 195.3 | BX16: 0 | CA16: 4.3 | CB16: 233.3 | CC16: 125.4 | CD16: 63.2 | CE16: 78.4 | CF16: 30.9 | CG16: 0 | CJ16: 138.3 | CN16: 0 | CO16: 177.7 | CP16: 177.6 | CQ16: 0 | CT16: 0 | CU16: 8.5 | CV16: 19.6 | CW16: 0 | CX16: 44.2 | CY16: 0 | CZ16: 0 | DA16: 0 | DB16: 20.3 | DC16: 9.9 | DD16: 5.6 | DE16: 0 | DF16: 0 | DG16: 2.2 | DH16: 3.2 | DI16: 5.1 | DJ16: 20.3 | DK16: 15.1 | DL16: 18.8 | DM16: 3.6 | DN16: 6 | DO16: 0 | DP16: 0 | DQ16: 11.9 | DR16: 31.3 | DS16: 0 | DT16: 2.8 | DU16: 20.4 | DV16: 3.2 | DX16: 0 | DY16: 19.8 | DZ16: 13.2 | EA16: 20 | EB16: 20.2 | EC16: 0.4 | ED16: 0 | EE16: 0 | EF16: 13.8 | EG16: 28.9 | EH16: 1.1 | EI16: 0.1 | EJ16: 0 | EK16: 21 | EL16: 7.5 | EM16: 7.3 | EN16: 20.4 | EO16: 20.4 | EP16: 20 | EQ16: 0 | ER16: 0 | ES16: 0 | ET16: 0 | EU16: 0.6 | EV16: 0 | EW16: 1.4 | EX16: 0 | EY16: 4.8 | EZ16: 2.4 | FA16: 1.2 | FB16: 2.6 | FC16: 0 | FD16: 6.2 | FE16: 20 | FF16: 20 | FH16: 0 | FI16: 0 | FJ16: 0 | FK16: 14.3 | FL16: 6.3 | FM16: 12 | FN16: 13.7 | FO16: 6265.4 | FQ16: 24.52763 | FR16: 7.94 | FS16: 9.5 | FT16: 13.2 | FU16: 25.5 | FV16: 19 | FW16: 10 | FX16: 13.5 | FY16: 123.16763
A17: 04/03/2026 | B17: 03:30 | C17: 203.9 | D17: 652.5 | E17: 214.3 | F17: 7.7 | G17: 7.7 | H17: 92.6 | I17: 235.7 | J17: 0 | K17: 59.9 | R17: 542.8 | S17: 10.3 | T17: 13.1 | U17: 0 | X17: 164.3 | Y17: 10.2 | Z17: 6.6 | AB17: 6.3 | AD17: 90.9 | AI17: 110.2 | AJ17: 176.8 | AK17: 0 | AN17: 6.5 | AO17: 365.2 | AP17: 82.6 | AQ17: 150.7 | AR17: 42.1 | AS17: 18.6 | AT17: 18.9 | AU17: 92.1 | AV17: 0 | AW17: 91.8 | AX17: 60.6 | AY17: 109.9 | AZ17: 46.5 | BA17: 0 | BB17: 3.8 | BC17: 28.5 | BD17: 148.1 | BG17: 76.9 | BH17: 27.9 | BJ17: 0 | BN17: 131.9 | BU17: 195.3 | BV17: 196 | BW17: 196.1 | BX17: 0 | CA17: 4.3 | CB17: 242.4 | CC17: 129.2 | CD17: 63 | CE17: 78.6 | CF17: 30.9 | CG17: 0 | CJ17: 139.1 | CN17: 0 | CO17: 96.5 | CP17: 176.8 | CQ17: 0 | CT17: 0 | CU17: 8.6 | CV17: 19.5 | CW17: 0 | CX17: 49.5 | CY17: 0 | CZ17: 0 | DA17: 0 | DB17: 20.3 | DC17: 9.9 | DD17: 5.6 | DE17: 0 | DF17: 0 | DG17: 2.2 | DH17: 3.2 | DI17: 5.1 | DJ17: 20.4 | DK17: 15.1 | DL17: 18.7 | DM17: 3.6 | DN17: 6 | DO17: 0 | DP17: 0 | DQ17: 11.4 | DR17: 30.6 | DS17: 0 | DT17: 2.7 | DU17: 20.4 | DV17: 3.2 | DX17: 0 | DY17: 19.8 | DZ17: 13.2 | EA17: 20.1 | EB17: 20.2 | EC17: 1.3 | ED17: 0 | EE17: 0 | EF17: 14 | EG17: 26.7 | EH17: 0.5 | EI17: 0 | EJ17: 0 | EK17: 21 | EL17: 7.4 | EM17: 7.3 | EN17: 20.4 | EO17: 20.4 | EP17: 20 | EQ17: 0 | ER17: 0 | ES17: 0 | ET17: 0 | EU17: 0.6 | EV17: 15.4 | EW17: 5.8 | EX17: 0 | EY17: 4.8 | EZ17: 2.4 | FA17: 1.2 | FB17: 2.5 | FC17: 0 | FD17: 6.2 | FE17: 20 | FF17: 20 | FH17: 0 | FI17: 0 | FJ17: 0 | FK17: 14.7 | FL17: 7.6 | FM17: 11.9 | FN17: 16 | FO17: 6254 | FQ17: 24.55642 | FR17: 7.94 | FS17: 10.2 | FT17: 13.2 | FU17: 25.4 | FV17: 19 | FW17: 10.1 | FX17: 13.4 | FY17: 123.79642
A18: 04/03/2026 | B18: 04:00 | C18: 199.8 | D18: 649.5 | E18: 213.8 | F18: 7.5 | G18: 7.5 | H18: 91.2 | I18: 234 | J18: 0 | K18: 58.4 | R18: 541 | S18: 10.2 | T18: 13.4 | U18: 0 | X18: 159.5 | Y18: 10.1 | Z18: 6.5 | AB18: 6.3 | AD18: 90.3 | AI18: 110 | AJ18: 170.9 | AK18: 0 | AN18: 6.5 | AO18: 366.5 | AP18: 81.9 | AQ18: 150 | AR18: 42.1 | AS18: 18.6 | AT18: 18.9 | AU18: 89.8 | AV18: 0 | AW18: 87.9 | AX18: 61 | AY18: 108.9 | AZ18: 45.6 | BA18: 0 | BB18: 3.8 | BC18: 28.3 | BD18: 146.7 | BG18: 75.4 | BH18: 29 | BJ18: 0 | BN18: 131.2 | BU18: 193.9 | BV18: 195.1 | BW18: 195.3 | BX18: 0 | CA18: 4.4 | CB18: 239.9 | CC18: 126.6 | CD18: 62.2 | CE18: 78.3 | CF18: 30.4 | CG18: 0 | CJ18: 138.7 | CN18: 0 | CO18: 92.9 | CP18: 172.9 | CQ18: 0 | CT18: 0 | CU18: 8.4 | CV18: 20 | CW18: 0 | CX18: 53 | CY18: 0 | CZ18: 0 | DA18: 0 | DB18: 20.2 | DC18: 10.1 | DD18: 5.7 | DE18: 0 | DF18: 0 | DG18: 2.2 | DH18: 3.2 | DI18: 5 | DJ18: 20.1 | DK18: 15.1 | DL18: 18.8 | DM18: 3.6 | DN18: 7.7 | DO18: 0 | DP18: 0 | DQ18: 12.8 | DR18: 31 | DS18: 0 | DT18: 3 | DU18: 20.4 | DV18: 3.2 | DX18: 0 | DY18: 19.8 | DZ18: 13.2 | EA18: 20.1 | EB18: 20.2 | EC18: 1.6 | ED18: 0 | EE18: 0 | EF18: 16.7 | EG18: 31.1 | EH18: 0 | EI18: 0 | EJ18: 0 | EK18: 21 | EL18: 7.4 | EM18: 7.3 | EN18: 20.4 | EO18: 20.4 | EP18: 20 | EQ18: 0 | ER18: 0 | ES18: 0 | ET18: 0 | EU18: 0.6 | EV18: 30.5 | EW18: 12.5 | EX18: 0 | EY18: 4.8 | EZ18: 2.4 | FA18: 1.2 | FB18: 2.5 | FC18: 0 | FD18: 6.1 | FE18: 20 | FF18: 20 | FH18: 0 | FI18: 0 | FJ18: 0 | FK18: 14.7 | FL18: 6.5 | FM18: 11.5 | FN18: 15.5 | FO18: 6234.1 | FQ18: 24.53289 | FR18: 7.94 | FS18: 9.7 | FT18: 13.2 | FU18: 25.4 | FV18: 19 | FW18: 10.1 | FX18: 13.4 | FY18: 123.27289
A19: 04/03/2026 | B19: 04:30 | C19: 202.8 | D19: 651.9 | E19: 214.5 | F19: 7.7 | G19: 7.6 | H19: 92.1 | I19: 235.7 | J19: 0 | K19: 0 | R19: 546.7 | S19: 10.2 | T19: 14.1 | U19: 0 | X19: 167.4 | Y19: 10.1 | Z19: 6.6 | AB19: 6.4 | AD19: 90.6 | AI19: 110.3 | AJ19: 182 | AK19: 0 | AN19: 6.5 | AO19: 364.7 | AP19: 75.3 | AQ19: 150.7 | AR19: 42.1 | AS19: 18.6 | AT19: 18.9 | AU19: 91.1 | AV19: 0 | AW19: 90.9 | AX19: 61.8 | AY19: 110.1 | AZ19: 46.2 | BA19: 0 | BB19: 3.8 | BC19: 28.5 | BD19: 150.2 | BG19: 82.1 | BH19: 28.3 | BJ19: 0 | BN19: 131.6 | BU19: 194.9 | BV19: 195.9 | BW19: 196.1 | BX19: 0 | CA19: 4.4 | CB19: 243.5 | CC19: 130.3 | CD19: 62.9 | CE19: 78.6 | CF19: 30.9 | CG19: 0 | CJ19: 139.2 | CN19: 0 | CO19: 96.4 | CP19: 176.4 | CQ19: 0 | CT19: 0 | CU19: 8.4 | CV19: 20 | CW19: 0 | CX19: 56.6 | CY19: 0 | CZ19: 0 | DA19: 0 | DB19: 20.4 | DC19: 9.8 | DD19: 5.6 | DE19: 0 | DF19: 0 | DG19: 2.2 | DH19: 3.2 | DI19: 5 | DJ19: 20.5 | DK19: 15.1 | DL19: 18.7 | DM19: 3.6 | DN19: 10 | DO19: 0 | DP19: 0 | DQ19: 12.3 | DR19: 30.3 | DS19: 0 | DT19: 3.1 | DU19: 20.4 | DV19: 3.2 | DX19: 0 | DY19: 19.8 | DZ19: 13.2 | EA19: 20 | EB19: 20.2 | EC19: 0.9 | ED19: 0 | EE19: 0 | EF19: 18.8 | EG19: 36.7 | EH19: 0.5 | EI19: 0 | EJ19: 0 | EK19: 21 | EL19: 7.4 | EM19: 7.3 | EN19: 20.4 | EO19: 20.4 | EP19: 20 | EQ19: 0 | ER19: 0 | ES19: 0 | ET19: 0 | EU19: 0.6 | EV19: 33.4 | EW19: 30.4 | EX19: 0 | EY19: 4.8 | EZ19: 2.4 | FA19: 1.2 | FB19: 2.5 | FC19: 0 | FD19: 6.2 | FE19: 20 | FF19: 20 | FH19: 0 | FI19: 0 | FJ19: 0 | FK19: 14.7 | FL19: 7.2 | FM19: 11.1 | FN19: 15.9 | FO19: 6273 | FQ19: 24.55378 | FR19: 7.94 | FS19: 9.5 | FT19: 13.2 | FU19: 25.5 | FV19: 19 | FW19: 10.2 | FX19: 13.3 | FY19: 123.19378
A20: 04/03/2026 | B20: 05:00 | C20: 202.7 | D20: 651.4 | E20: 214.1 | F20: 7.7 | G20: 7.7 | H20: 91.9 | I20: 236 | J20: 0 | K20: 0 | R20: 538.7 | S20: 10.2 | T20: 14.7 | U20: 0 | X20: 167.6 | Y20: 10.1 | Z20: 6.6 | AB20: 6.4 | AD20: 90.4 | AI20: 110.2 | AJ20: 181.8 | AK20: 0 | AN20: 6.5 | AO20: 368.2 | AP20: 80.5 | AQ20: 150.7 | AR20: 42.1 | AS20: 18.6 | AT20: 18.9 | AU20: 92.9 | AV20: 0 | AW20: 90.8 | AX20: 60.2 | AY20: 110 | AZ20: 46.2 | BA20: 0 | BB20: 3.8 | BC20: 27.9 | BD20: 145 | BG20: 82 | BH20: 27.8 | BJ20: 0 | BN20: 131.7 | BU20: 195.2 | BV20: 196 | BW20: 195.6 | BX20: 0 | CA20: 4.3 | CB20: 239.1 | CC20: 127.9 | CD20: 62.8 | CE20: 79 | CF20: 30.8 | CG20: 0 | CJ20: 139.1 | CN20: 0 | CO20: 96 | CP20: 176.2 | CQ20: 0 | CT20: 0 | CU20: 8.4 | CV20: 20 | CW20: 0 | CX20: 53.5 | CY20: 0 | CZ20: 0 | DA20: 0 | DB20: 20.3 | DC20: 10 | DD20: 5.5 | DE20: 0 | DF20: 0 | DG20: 2.2 | DH20: 3.2 | DI20: 5.2 | DJ20: 20.3 | DK20: 15.1 | DL20: 18.7 | DM20: 3.6 | DN20: 18.4 | DO20: 0 | DP20: 0 | DQ20: 12 | DR20: 31.5 | DS20: 0 | DT20: 3 | DU20: 20.4 | DV20: 3.2 | DX20: 0 | DY20: 19.8 | DZ20: 13.2 | EA20: 20.1 | EB20: 20.2 | EC20: 0.1 | ED20: 0 | EE20: 0 | EF20: 22.4 | EG20: 42.9 | EH20: 1 | EI20: 0 | EJ20: 0 | EK20: 21 | EL20: 7.4 | EM20: 7.3 | EN20: 20.4 | EO20: 20.4 | EP20: 20 | EQ20: 0 | ER20: 0 | ES20: 0 | ET20: 0 | EU20: 0.6 | EV20: 37.6 | EW20: 29.4 | EX20: 0 | EY20: 4.8 | EZ20: 2.4 | FA20: 1.2 | FB20: 2.5 | FC20: 0 | FD20: 6.2 | FE20: 20 | FF20: 20 | FH20: 0 | FI20: 0 | FJ20: 0 | FK20: 14.7 | FL20: 7.7 | FM20: 11 | FN20: 15.9 | FO20: 6278.7 | FQ20: 24.5394 | FR20: 7.94 | FS20: 9.1 | FT20: 13.2 | FU20: 25.6 | FV20: 19 | FW20: 10.1 | FX20: 13.4 | FY20: 122.8794
A21: 04/03/2026 | B21: 05:30 | C21: 202.7 | D21: 651.5 | E21: 214.5 | F21: 7.6 | G21: 7.7 | H21: 92 | I21: 234.6 | J21: 0 | K21: 0 | R21: 564.4 | S21: 10.2 | T21: 14.2 | U21: 0 | X21: 166.9 | Y21: 10 | Z21: 6.6 | AB21: 6.4 | AD21: 90.2 | AI21: 110.3 | AJ21: 208.8 | AK21: 0 | AN21: 6.5 | AO21: 397.1 | AP21: 82.2 | AQ21: 150.9 | AR21: 42.1 | AS21: 18.6 | AT21: 18.9 | AU21: 91 | AV21: 0 | AW21: 90.9 | AX21: 60.4 | AY21: 110 | AZ21: 45.9 | BA21: 0 | BB21: 3.8 | BC21: 27.8 | BD21: 159.4 | BG21: 81.9 | BH21: 0 | BJ21: 0 | BN21: 131.3 | BU21: 194.1 | BV21: 195 | BW21: 194.9 | BX21: 0 | CA21: 4.4 | CB21: 256.8 | CC21: 133.3 | CD21: 62.8 | CE21: 79.1 | CF21: 30.8 | CG21: 0 | CJ21: 139 | CN21: 0 | CO21: 175.6 | CP21: 176.3 | CQ21: 0 | CT21: 0 | CU21: 8.4 | CV21: 20 | CW21: 0 | CX21: 64.2 | CY21: 0 | CZ21: 0 | DA21: 0 | DB21: 20.4 | DC21: 9.8 | DD21: 5.7 | DE21: 0 | DF21: 0 | DG21: 2.2 | DH21: 3.2 | DI21: 5.2 | DJ21: 20.3 | DK21: 5.1 | DL21: 18.8 | DM21: 3.5 | DN21: 18.4 | DO21: 0 | DP21: 0 | DQ21: 14.7 | DR21: 36.5 | DS21: 0 | DT21: 3 | DU21: 20.4 | DV21: 3.2 | DX21: 0 | DY21: 19.8 | DZ21: 13.2 | EA21: 20 | EB21: 20.2 | EC21: 0 | ED21: 0 | EE21: 0 | EF21: 21.2 | EG21: 51.8 | EH21: 1 | EI21: 0 | EJ21: 0 | EK21: 21 | EL21: 7.2 | EM21: 7.3 | EN21: 20.4 | EO21: 20.4 | EP21: 20 | EQ21: 0 | ER21: 0 | ES21: 0 | ET21: 0 | EU21: 0.6 | EV21: 28.1 | EW21: 23.6 | EX21: 0 | EY21: 4.8 | EZ21: 2.4 | FA21: 0.6 | FB21: 2.6 | FC21: 0 | FD21: 6.2 | FE21: 20 | FF21: 20 | FH21: 0 | FI21: 0 | FJ21: 0 | FK21: 14.7 | FL21: 6.5 | FM21: 11.1 | FN21: 16.6 | FO21: 6443.7 | FQ21: 24.54725 | FR21: 7.94 | FS21: 8.5 | FT21: 13.2 | FU21: 25.8 | FV21: 19 | FW21: 10.3 | FX21: 13.3 | FY21: 122.58725
A22: 04/03/2026 | B22: 06:00 | C22: 204.2 | D22: 652.5 | E22: 214.3 | F22: 7.7 | G22: 7.7 | H22: 92.5 | I22: 234.8 | J22: 0 | K22: 0 | R22: 562.5 | S22: 10.2 | T22: 14.2 | U22: 0 | X22: 163.6 | Y22: 10 | Z22: 6.8 | AB22: 6.5 | AD22: 90.5 | AI22: 110.2 | AJ22: 202 | AK22: 0 | AN22: 6.5 | AO22: 377.8 | AP22: 82.2 | AQ22: 150.8 | AR22: 42.1 | AS22: 18.6 | AT22: 18.9 | AU22: 91.5 | AV22: 0 | AW22: 91.7 | AX22: 60 | AY22: 87.5 | AZ22: 46.3 | BA22: 0 | BB22: 3.8 | BC22: 28.6 | BD22: 157.6 | BG22: 82.1 | BH22: 0 | BJ22: 20.2 | BN22: 131.4 | BU22: 194.3 | BV22: 194.7 | BW22: 195.2 | BX22: 0 | CA22: 4.4 | CB22: 255.6 | CC22: 134.3 | CD22: 66.1 | CE22: 78.3 | CF22: 30.9 | CG22: 0 | CJ22: 139.4 | CN22: 0 | CO22: 176.3 | CP22: 177.2 | CQ22: 0 | CT22: 0 | CU22: 8.4 | CV22: 20 | CW22: 0 | CX22: 72.3 | CY22: 0.8 | CZ22: 0 | DA22: 0 | DB22: 20.4 | DC22: 9.9 | DD22: 5.7 | DE22: 3 | DF22: 1.83 | DG22: 2.2 | DH22: 3.2 | DI22: 5.1 | DJ22: 20.6 | DK22: 5.1 | DL22: 18.7 | DM22: 3.5 | DN22: 18.4 | DO22: 0.1 | DP22: 0 | DQ22: 16.4 | DR22: 40.8 | DS22: 0.1 | DT22: 3 | DU22: 20.4 | DV22: 3.2 | DX22: 0 | DY22: 19.8 | DZ22: 13.2 | EA22: 20.3 | EB22: 20.2 | EC22: 0 | ED22: 0 | EE22: 0.4 | EF22: 24.6 | EG22: 60.8 | EH22: 1 | EI22: 0 | EJ22: 0.6 | EK22: 21 | EL22: 7.2 | EM22: 7.3 | EN22: 20.4 | EO22: 20.4 | EP22: 20 | EQ22: 0 | ER22: 4.1 | ES22: 0.1 | ET22: 2.8 | EU22: 0.6 | EV22: 20.5 | EW22: 15.1 | EX22: 1.9 | EY22: 4.8 | EZ22: 2.4 | FA22: 0.6 | FB22: 2.6 | FC22: 0 | FD22: 6.2 | FE22: 20 | FF22: 20 | FH22: 0 | FI22: 0 | FJ22: 0 | FK22: 14.6 | FL22: 7.2 | FM22: 11 | FN22: 16.3 | FO22: 6445.63 | FQ22: 24.54225 | FR22: 7.95 | FS22: 8 | FT22: 13.2 | FU22: 25.9 | FV22: 19 | FW22: 10.3 | FX22: 13.6 | FY22: 122.49225
... A58: 05/03/2026 | B58: 00:00 | C58: 204.7 | D58: 656.3 | E58: 214.6 | F58: 7.8 | G58: 7.6 | H58: 93.5 | I58: 236.5 | J58: 81.8 | K58: 0 | R58: 569.1 | S58: 10.3 | T58: 14.7 | U58: 0 | X58: 167.3 | Y58: 10.2 | Z58: 6.7 | AB58: 6.3 | AD58: 141.6 | AI58: 110.3 | AJ58: 169.3 | AK58: 0 | AN58: 6.5 | AO58: 367.4 | AP58: 83 | AQ58: 150.6 | AR58: 42.1 | AS58: 18.6 | AT58: 18.9 | AU58: 91.3 | AV58: 154.2 | AW58: 154.7 | AX58: 170.8 | AY58: 109.8 | AZ58: 47.1 | BA58: 0 | BB58: 3.8 | BC58: 28 | BD58: 148.1 | BG58: 94.2 | BH58: 34.8 | BJ58: 14.6 | BN58: 130.19 | BU58: 195.37 | BV58: 193.23 | BW58: 119.48 | BX58: 0 | CA58: 4.6 | CB58: 195.8 | CC58: 119 | CD58: 60.1 | CE58: 71.1 | CF58: 0 | CG58: 0 | CJ58: 138.4 | CN58: 96.3 | CO58: 0 | CP58: 0 | CQ58: 0 | CT58: 7.8 | CU58: 9.1 | CV58: 20.2 | CW58: 0 | CX58: 65 | CY58: 0 | CZ58: 0 | DA58: 0 | DB58: 20.3 | DC58: 10.5 | DD58: 5.7 | DE58: 0 | DF58: 0 | DG58: 2.2 | DH58: 3 | DI58: 5 | DJ58: 20.4 | DK58: 16 | DL58: 18.5 | DM58: 3.5 | DN58: 18.4 | DO58: 0 | DP58: 0 | DQ58: 14.4 | DR58: 38.9 | DS58: 0 | DT58: 1.5 | DU58: 20.4 | DV58: 3.2 | DX58: 0 | DY58: 19.9 | DZ58: 13.2 | EA58: 20.3 | EB58: 20.2 | EC58: 2.2 | ED58: 0 | EE58: 0 | EF58: 55.21 | EG58: 80.72 | EH58: 3.5023 | EI58: 4.126 | EJ58: 0 | EK58: 21 | EL58: 7.5 | EM58: 7.2 | EN58: 20.4 | EO58: 20.4 | EP58: 20 | EQ58: 0 | ER58: 0 | ES58: 0 | ET58: 0 | EU58: 0 | EV58: 18 | EW58: 15.4 | EX58: 0 | EY58: 4.8 | EZ58: 2.3 | FA58: 0.7 | FB58: 1.6 | FC58: 0 | FD58: 6.4 | FE58: 20 | FF58: 20 | FH58: 44.2 | FI58: 29.9 | FJ58: 16.8 | FK58: 14.1 | FL58: 6 | FM58: 12.3 | FN58: 18.6 | FO58: 6621.6283 | FQ58: 24.56726 | FR58: 8 | FS58: 10.6 | FT58: 13.2 | FU58: 25.1 | FV58: 19 | FW58: 10.8 | FX58: 13.4 | FY58: 124.66726
A59: EJEC | C59: 4860.25 | D59: 15726.2 | E59: 5135.55 | F59: 183.55 | G59: 183.8 | H59: 2224.05 | I59: 5644.15 | J59: 974.65 | K59: 249.7 | L59: 0 | M59: 0 | N59: 0 | O59: 0 | P59: 0 | Q59: 0 | R59: 12195.25 | S59: 245.3 | T59: 322.35 | U59: 2.8 | V59: 0 | W59: 0 | X59: 3979.55 | Y59: 240.15 | Z59: 159.65 | AA59: 0 | AB59: 152.1 | AC59: 0 | AD59: 2742.85 | AE59: 0 | AF59: 0 | AG59: 0 | AH59: 0 | AI59: 2645.75 | AJ59: 4657 | AK59: 961.9 | AL59: 0 | AM59: 0 | AN59: 156 | AO59: 9256.2 | AP59: 1974 | AQ59: 3607.9 | AR59: 1010.75 | AS59: 445.35 | AT59: 453.6 | AU59: 2180.85 | AV59: 1734 | AW59: 2500.5 | AX59: 2589.7 | AY59: 2539.2 | AZ59: 1034.9 | BA59: 299.05 | BB59: 91.2 | BC59: 694.25 | BD59: 3636.65 | BE59: 0 | BF59: 0 | BG59: 1803.65 | BH59: 719.35 | BI59: 0 | BJ59: 282.85 | BK59: 0 | BL59: 0 | BM59: 0 | BN59: 3150.775 | BO59: 0 | BP59: 0 | BQ59: 0 | BR59: 0 | BS59: 0 | BT59: 0 | BU59: 4676.27 | BV59: 4653.16 | BW59: 3865.67 | BX59: 458.315 | BY59: 0 | BZ59: 0 | CA59: 104.05 | CB59: 5313.9 | CC59: 2893.7 | CD59: 1521.25 | CE59: 1871.9 | CF59: 677.75 | CG59: 618.55 | CH59: 0 | CI59: 0 | CJ59: 3318.65 | CK59: 0 | CL59: 0 | CM59: 0 | CN59: 1371.65 | CO59: 2597.75 | CP59: 3789.1 | CQ59: 1207.8 | CR59: 0 | CS59: 0 | CT59: 124.8 | CU59: 214.65 | CV59: 474.35 | CW59: 2.65 | CX59: 1894.25 | CY59: 723.25 | CZ59: 54.15 | DA59: 1.25 | DB59: 487.8 | DC59: 243.7 | DD59: 134.75 | DE59: 2062.05 | DF59: 1033.065 | DG59: 50.55 | DH59: 68.1 | DI59: 120.95 | DJ59: 489.35 | DK59: 296.4 | DL59: 448.4 | DM59: 84.6 | DN59: 414.4 | DO59: 149.9 | DP59: 188.95 | DQ59: 405.4 | DR59: 1179.9 | DS59: 162.8 | DT59: 67.6 | DU59: 435.45 | DV59: 76.8 | DW59: 0 | DX59: 3.1 | DY59: 475.3 | DZ59: 316.85 | EA59: 485.15 | EB59: 484.65 | EC59: 23.45 | ED59: 62.05 | EE59: 353.5 | EF59: 1254.365 | EG59: 1788.83 | EH59: 109.6793 | EI59: 89.2728 | EJ59: 258.55 | EK59: 504 | EL59: 177.3 | EM59: 176.65 | EN59: 489.6 | EO59: 489.6 | EP59: 480 | EQ59: 51.15 | ER59: 2555.1 | ES59: 140.65 | ET59: 1420.7 | EU59: 12.75 | EV59: 1095.8 | EW59: 1242.05 | EX59: 1070.2 | EY59: 89.4 | EZ59: 56.05 | FA59: 23.75 | FB59: 52.75 | FC59: 141 | FD59: 152 | FE59: 479.75 | FF59: 479.75 | FG59: 0 | FH59: 629.25 | FI59: 475.05 | FJ59: 252.75 | FK59: 334.05 | FL59: 162.6 | FM59: 276.8 | FN59: 360.45 | FO59: 174252.7 | FQ59: 589.0389 | FR59: 185.45 | FS59: 221.65 | FT59: 211.2 | FU59: 610.4 | FV59: 456 | FW59: 248.6 | FX59: 321.75 | FY59: 2844.0889

Sheet REACTIVA
B3: miércoles, 4 de Marzo del 2026
A5: POTENCIA REACTIVA EJECUTADA DE LAS UNIDADES DE GENERACIÓN DEL COES (MVAR) | FQ5: CENTRALES NO INTEGRANTES COES
A6: FECHA | B6: HORA | C6: 65333 | D6: 101 | E6: 102 | F6: 42667 | G6: 42668 | H6: 126 | I6: 127 | J6: 138 | K6: 139 | L6: 197 | M6: 203 | N6: 204 | O6: 230 | P6: 209 | Q6: 56677 | R6: 796 | S6: 2146 | T6: 142 | U6: 143 | V6: 125 | W6: 187 | X6: 163 | Y6: 298 | Z6: 299 | AA6: 219 | AB6: 151 | AC6: 152 | AD6: 153 | AE6: 154 | AF6: 756 | AG6: 156 | AH6: 155 | AI6: 182 | AJ6: 212 | AK6: 758 | AL6: 263 | AM6: 265 | AN6: 775 | AO6: 777 | AP6: 2154 | AQ6: 150 | AR6: 149 | AS6: 188 | AT6: 2131 | AU6: 755 | AV6: 252 | AW6: 249 | AX6: 250 | AY6: 117 | AZ6: 119 | BA6: 120 | BB6: 189 | BC6: 122 | BD6: 266 | BE6: 337 | BF6: 338 | BG6: 251 | BH6: 115 | BI6: 239 | BJ6: 288 | BK6: 240 | BL6: 241 | BM6: 242 | BN6: 191 | BO6: 194 | BP6: 196 | BQ6: 207 | BR6: 236 | BS6: 795 | BT6: 285 | BU6: 995 | BV6: 996 | BW6: 997 | BX6: 766 | BY6: 926 | BZ6: 924 | CA6: 121 | CB6: 103 | CC6: 104 | CD6: 106 | CE6: 105 | CF6: 107 | CG6: 110 | CH6: 109 | CI6: 144 | CJ6: 113 | CK6: 114 | CL6: 193 | CM6: 208 | CN6: 786 | CO6: 787 | CP6: 788 | CQ6: 789 | CR6: 248 | CS6: 2159 | CT6: 267 | CU6: 268 | CV6: 2194 | CW6: 303 | CX6: 59715 | CY6: 62255 | CZ6: 1263 | DA6: 61800 | DB6: 69125 | DC6: 216 | DD6: 198 | DE6: 70400 | DF6: 76068 | DG6: 49607 | DH6: 214 | DI6: 260 | DJ6: 2152 | DK6: 2128 | DL6: 247 | DM6: 228 | DN6: 2135 | DO6: 261 | DP6: 237 | DQ6: 253 | DR6: 770 | DS6: 235 | DT6: 238 | DU6: 2184 | DV6: 61855 | DW6: 223 | DX6: 75566 | DY6: 226 | DZ6: 201 | EA6: 258 | EB6: 259 | EC6: 257 | ED6: 256 | EE6: 2148 | EF6: 58288 | EG6: 58289 | EH6: 58839 | EI6: 58840 | EJ6: 75260 | EK6: 296 | EL6: 297 | EM6: 211 | EN6: 2175 | EO6: 2178 | EP6: 2181 | EQ6: 1262 | ER6: 63425 | ES6: 233 | ET6: 2150 | EU6: 2165 | EV6: 2161 | EW6: 61197 | EX6: 58851 | EY6: 225 | EZ6: 2201 | FA6: 2171 | FB6: 760 | FC6: 234 | FD6: 215 | FE6: 917 | FF6: 920 | FG6: 289 | FH6: 58333 | FI6: 58336 | FJ6: 213 | FK6: 232 | FL6: 2190 | FM6: 69867 | FN6: 75066 | FO6: TOTAL COES | FQ6: 221 | FR6: 222 | FS6: 224 | FT6: 2187 | FU6: 227 | FV6: 49400 | FW6: 199 | FX6: 200 | FY6: TOTAL NO COES
C7: SUR | D7: CENTRO | E7: CENTRO | F7: NORTE | G7: NORTE | H7: NORTE | I7: NORTE | J7: CENTRO | K7: CENTRO | L7: CENTRO | M7: CENTRO | N7: CENTRO | O7: CENTRO | P7: CENTRO | Q7: CENTRO | R7: CENTRO | S7: CENTRO | T7: CENTRO | U7: CENTRO | V7: CENTRO | W7: CENTRO | X7: SUR | Y7: SUR | Z7: SUR | AA7: CENTRO | AB7: SUR | AC7: SUR | AD7: SUR | AE7: SUR | AF7: SUR | AG7: SUR | AH7: SUR | AI7: SUR | AJ7: CENTRO | AK7: NORTE | AL7: NORTE | AM7: NORTE | AN7: CENTRO | AO7: CENTRO | AP7: CENTRO | AQ7: CENTRO | AR7: CENTRO | AS7: CENTRO | AT7: CENTRO | AU7: SUR | AV7: CENTRO | AW7: CENTRO | AX7: CENTRO | AY7: CENTRO | AZ7: CENTRO | BA7: CENTRO | BB7: SUR | BC7: NORTE | BD7: CENTRO | BE7: CENTRO | BF7: CENTRO | BG7: CENTRO | BH7: NORTE | BI7: NORTE | BJ7: NORTE | BK7: SUR | BL7: SUR | BM7: SUR | BN7: CENTRO | BO7: CENTRO | BP7: CENTRO | BQ7: CENTRO | BR7: CENTRO | BS7: CENTRO | BT7: CENTRO | BU7: SUR | BV7: SUR | BW7: SUR | BX7: NORTE | BY7: SUR | BZ7: CENTRO | CA7: NORTE | CB7: CENTRO | CC7: CENTRO | CD7: CENTRO | CE7: CENTRO | CF7: CENTRO | CG7: CENTRO | CH7: CENTRO | CI7: CENTRO | CJ7: CENTRO | CK7: CENTRO | CL7: CENTRO | CM7: CENTRO | CN7: SUR | CO7: SUR | CP7: SUR | CQ7: SUR | CR7: CENTRO | CS7: CENTRO | CT7: CENTRO | CU7: CENTRO | CV7: NORTE | CW7: CENTRO | CX7: CENTRO | CY7: SUR | CZ7: NORTE | DA7: NORTE | DB7: CENTRO | DC7: NORTE | DD7: NORTE | DE7: SUR | DF7: SUR | DG7: SUR | DH7: CENTRO | DI7: CENTRO | DJ7: CENTRO | DK7: NORTE | DL7: NORTE | DM7: CENTRO | DN7: CENTRO | DO7: SUR | DP7: SUR | DQ7: CENTRO | DR7: CENTRO | DS7: SUR | DT7: CENTRO | DU7: CENTRO | DV7: NORTE | DW7: CENTRO | DX7: CENTRO | DY7: CENTRO | DZ7: NORTE | EA7: CENTRO | EB7: CENTRO | EC7: NORTE | ED7: NORTE | EE7: SUR | EF7: CENTRO | EG7: CENTRO | EH7: CENTRO | EI7: CENTRO | EJ7: SUR | EK7: CENTRO | EL7: CENTRO | EM7: SUR | EN7: SUR | EO7: SUR | EP7: SUR | EQ7: NORTE | ER7: SUR | ES7: SUR | ET7: SUR | EU7: CENTRO | EV7: CENTRO | EW7: CENTRO | EX7: SUR | EY7: CENTRO | EZ7: CENTRO | FA7: CENTRO | FB7: CENTRO | FC7: SUR | FD7: NORTE | FE7: CENTRO | FF7: CENTRO | FG7: NORTE | FH7: NORTE | FI7: NORTE | FJ7: CENTRO | FK7: NORTE | FL7: NORTE | FM7: NORTE | FN7: NORTE | FQ7: NORTE | FR7: CENTRO | FS7: NORTE | FT7: NORTE | FU7: NORTE | FV7: NORTE | FW7: NORTE | FX7: NORTE
C8: HIDROELÉCTRICA | D8: HIDROELÉCTRICA | E8: HIDROELÉCTRICA | F8: TERMOELÉCTRICA | G8: TERMOELÉCTRICA | H8: HIDROELÉCTRICA | I8: HIDROELÉCTRICA | J8: TERMOELÉCTRICA | K8: TERMOELÉCTRICA | L8: TERMOELÉCTRICA | M8: TERMOELÉCTRICA | N8: TERMOELÉCTRICA | O8: TERMOELÉCTRICA | P8: TERMOELÉCTRICA | Q8: TERMOELÉCTRICA | R8: HIDROELÉCTRICA | S8: HIDROELÉCTRICA | T8: TERMOELÉCTRICA | U8: TERMOELÉCTRICA | V8: TERMOELÉCTRICA | W8: TERMOELÉCTRICA | X8: HIDROELÉCTRICA | Y8: HIDROELÉCTRICA | Z8: HIDROELÉCTRICA | AA8: TERMOELÉCTRICA | AB8: HIDROELÉCTRICA | AC8: HIDROELÉCTRICA | AD8: HIDROELÉCTRICA | AE8: HIDROELÉCTRICA | AF8: TERMOELÉCTRICA | AG8: TERMOELÉCTRICA | AH8: TERMOELÉCTRICA | AI8: HIDROELÉCTRICA | AJ8: HIDROELÉCTRICA | AK8: TERMOELÉCTRICA | AL8: TERMOELÉCTRICA | AM8: TERMOELÉCTRICA | AN8: HIDROELÉCTRICA | AO8: HIDROELÉCTRICA | AP8: HIDROELÉCTRICA | AQ8: HIDROELÉCTRICA | AR8: HIDROELÉCTRICA | AS8: HIDROELÉCTRICA | AT8: HIDROELÉCTRICA | AU8: HIDROELÉCTRICA | AV8: TERMOELÉCTRICA | AW8: TERMOELÉCTRICA | AX8: TERMOELÉCTRICA | AY8: HIDROELÉCTRICA | AZ8: HIDROELÉCTRICA | BA8: HIDROELÉCTRICA | BB8: HIDROELÉCTRICA | BC8: HIDROELÉCTRICA | BD8: HIDROELÉCTRICA | BE8: HIDROELÉCTRICA | BF8: HIDROELÉCTRICA | BG8: HIDROELÉCTRICA | BH8: TERMOELÉCTRICA | BI8: TERMOELÉCTRICA | BJ8: TERMOELÉCTRICA | BK8: TERMOELÉCTRICA | BL8: TERMOELÉCTRICA | BM8: TERMOELÉCTRICA | BN8: HIDROELÉCTRICA | BO8: TERMOELÉCTRICA | BP8: TERMOELÉCTRICA | BQ8: TERMOELÉCTRICA | BR8: TERMOELÉCTRICA | BS8: TERMOELÉCTRICA | BT8: TERMOELÉCTRICA | BU8: TERMOELÉCTRICA | BV8: TERMOELÉCTRICA | BW8: TERMOELÉCTRICA | BX8: HIDROELÉCTRICA | BY8: TERMOELÉCTRICA | BZ8: TERMOELÉCTRICA | CA8: HIDROELÉCTRICA | CB8: HIDROELÉCTRICA | CC8: HIDROELÉCTRICA | CD8: HIDROELÉCTRICA | CE8: HIDROELÉCTRICA | CF8: HIDROELÉCTRICA | CG8: TERMOELÉCTRICA | CH8: TERMOELÉCTRICA | CI8: TERMOELÉCTRICA | CJ8: TERMOELÉCTRICA | CK8: TERMOELÉCTRICA | CL8: TERMOELÉCTRICA | CM8: TERMOELÉCTRICA | CN8: TERMOELÉCTRICA | CO8: TERMOELÉCTRICA | CP8: TERMOELÉCTRICA | CQ8: TERMOELÉCTRICA | CR8: TERMOELÉCTRICA | CS8: TERMOELÉCTRICA | CT8: HIDROELÉCTRICA | CU8: HIDROELÉCTRICA | CV8: HIDROELÉCTRICA | CW8: SOLAR | CX8: EÓLICA | CY8: SOLAR | CZ8: EÓLICA | DA8: SOLAR | DB8: HIDROELÉCTRICA | DC8: HIDROELÉCTRICA | DD8: HIDROELÉCTRICA | DE8: SOLAR | DF8: SOLAR | DG8: HIDROELÉCTRICA | DH8: HIDROELÉCTRICA | DI8: HIDROELÉCTRICA | DJ8: HIDROELÉCTRICA | DK8: HIDROELÉCTRICA | DL8: HIDROELÉCTRICA | DM8: HIDROELÉCTRICA | DN8: HIDROELÉCTRICA | DO8: SOLAR | DP8: SOLAR | DQ8: EÓLICA | DR8: EÓLICA | DS8: SOLAR | DT8: HIDROELÉCTRICA | DU8: HIDROELÉCTRICA | DV8: HIDROELÉCTRICA | DW8: HIDROELÉCTRICA | DX8: SOLAR | DY8: HIDROELÉCTRICA | DZ8: HIDROELÉCTRICA | EA8: HIDROELÉCTRICA | EB8: HIDROELÉCTRICA | EC8: EÓLICA | ED8: EÓLICA | EE8: SOLAR | EF8: EÓLICA | EG8: EÓLICA | EH8: EÓLICA | EI8: EÓLICA | EJ8: SOLAR | EK8: HIDROELÉCTRICA | EL8: HIDROELÉCTRICA | EM8: HIDROELÉCTRICA | EN8: HIDROELÉCTRICA | EO8: HIDROELÉCTRICA | EP8: HIDROELÉCTRICA | EQ8: EÓLICA | ER8: SOLAR | ES8: SOLAR | ET8: SOLAR | EU8: HIDROELÉCTRICA | EV8: EÓLICA | EW8: EÓLICA | EX8: SOLAR | EY8: TERMOELÉCTRICA | EZ8: TERMOELÉCTRICA | FA8: TERMOELÉCTRICA | FB8: TERMOELÉCTRICA | FC8: SOLAR | FD8: HIDROELÉCTRICA | FE8: HIDROELÉCTRICA | FF8: HIDROELÉCTRICA | FG8: TERMOELÉCTRICA | FH8: TERMOELÉCTRICA | FI8: TERMOELÉCTRICA | FJ8: TERMOELÉCTRICA | FK8: TERMOELÉCTRICA | FL8: TERMOELÉCTRICA | FM8: TERMOELÉCTRICA | FN8: TERMOELÉCTRICA | FQ8: HIDROELÉCTRICA | FR8: HIDROELÉCTRICA | FS8: HIDROELÉCTRICA | FT8: HIDROELÉCTRICA | FU8: TERMOELÉCTRICA | FV8: TERMOELÉCTRICA | FW8: HIDROELÉCTRICA | FX8: HIDROELÉCTRICA
C9: HYDRO GLOBAL PERÚ S.A.C. | D9: ELECTROPERU | E9: ELECTROPERU | F9: ELECTROPERU | G9: ELECTROPERU | H9: ORAZUL ENERGY PERÚ | I9: ORAZUL ENERGY PERÚ | J9: TERMOSELVA | K9: TERMOSELVA | L9: KALLPA GENERACION S.A. | M9: KALLPA GENERACION S.A. | N9: KALLPA GENERACION S.A. | O9: KALLPA GENERACION S.A. | P9: KALLPA GENERACION S.A. | Q9: KALLPA GENERACION S.A. | R9: KALLPA GENERACION S.A. | S9: KALLPA GENERACION S.A. | T9: SHOUGESA | U9: SHOUGESA | V9: SHOUGESA | W9: SHOUGESA | X9: EGEMSA | Y9: EGESUR | Z9: EGESUR | AA9: EGESUR | AB9: EGASA | AC9: EGASA | AD9: EGASA | AE9: EGASA | AF9: EGASA | AG9: EGASA | AH9: EGASA | AI9: SAN GABAN | AJ9: CELEPSA | AK9: MINERA CERRO VERDE | AL9: PLANTA DE RESERVA FRIA DE GENERACION DE ETEN S.A. | AM9: PLANTA DE RESERVA FRIA DE GENERACION DE ETEN S.A. | AN9: EMPRESA DE GENERACION HUALLAGA | AO9: EMPRESA DE GENERACION HUALLAGA | AP9: LA VIRGEN | AQ9: CHINANGO S.A.C. | AR9: CHINANGO S.A.C. | AS9: HIDROELECTRICA HUANCHOR S.A.C. | AT9: CELEPSA RENOVABLES S.R.L. | AU9: INLAND ENERGY SAC | AV9: FENIX POWER PERÚ | AW9: FENIX POWER PERÚ | AX9: FENIX POWER PERÚ | AY9: STATKRAFT S.A | AZ9: STATKRAFT S.A | BA9: STATKRAFT S.A | BB9: STATKRAFT S.A | BC9: STATKRAFT S.A | BD9: STATKRAFT S.A | BE9: CENTRALES SANTA ROSA S.A.C. | BF9: CENTRALES SANTA ROSA S.A.C. | BG9: EMPRESA DE GENERACION HUANZA | BH9: ENEL GENERACION PIURA S.A. | BI9: ENEL GENERACION PIURA S.A. | BJ9: ENEL GENERACION PIURA S.A. | BK9: ENGIE ENERGIA PERU S.A.A. | BL9: ENGIE ENERGIA PERU S.A.A. | BM9: ENGIE ENERGIA PERU S.A.A. | BN9: ENGIE ENERGIA PERU S.A.A. | BO9: ENGIE ENERGIA PERU S.A.A. | BP9: ENGIE ENERGIA PERU S.A.A. | BQ9: ENGIE ENERGIA PERU S.A.A. | BR9: ENGIE ENERGIA PERU S.A.A. | BS9: ENGIE ENERGIA PERU S.A.A. | BT9: ENGIE ENERGIA PERU S.A.A. | BU9: ENGIE ENERGIA PERU S.A.A. | BV9: ENGIE ENERGIA PERU S.A.A. | BW9: ENGIE ENERGIA PERU S.A.A. | BX9: ENGIE ENERGIA PERU S.A.A. | BY9: INFRAESTRUCTURAS Y ENERGIAS DEL PERU S.A.C. | BZ9: INFRAESTRUCTURAS Y ENERGIAS DEL PERU S.A.C. | CA9: INVERSIONES SHAQSHA S.A.C. | CB9: ORYGEN PERU S.A.A. | CC9: ORYGEN PERU S.A.A. | CD9: ORYGEN PERU S.A.A. | CE9: ORYGEN PERU S.A.A. | CF9: ORYGEN PERU S.A.A. | CG9: ORYGEN PERU S.A.A. | CH9: ORYGEN PERU S.A.A. | CI9: ORYGEN PERU S.A.A. | CJ9: ORYGEN PERU S.A.A. | CK9: ORYGEN PERU S.A.A. | CL9: ORYGEN PERU S.A.A. | CM9: ORYGEN PERU S.A.A. | CN9: SAMAY I S.A.C | CO9: SAMAY I S.A.C | CP9: SAMAY I S.A.C | CQ9: SAMAY I S.A.C | CR9: TERMOCHILCA S.A.C. | CS9: TERMOCHILCA S.A.C. | CT9: TRANSMISION ANDINA DE GENERACION S.A.C. | CU9: TRANSMISION ANDINA DE GENERACION S.A.C. | CV9: CELARIS ENERGY S.A. | CW9: COLCA SOLAR S.A.C. | CX9: ENERGIA RENOVABLE DEL SUR S.A. | CY9: GR CORTARRAMA SOCIEDAD ANONIMA CERRADA | CZ9: GR TARUCA SOCIEDAD ANONIMA CERRADA | DA9: KONDU SAC | DB9: VARI ENERGIA S.A.C. | DC9: ORAZUL ENERGY PERÚ | DD9: ORAZUL ENERGY PERÚ | DE9: KALLPA GENERACION S.A. | DF9: KALLPA GENERACION S.A. | DG9: SAN GABAN | DH9: MAJA ENERGIA S.A.C. | DI9: EMPRESA DE GENERACION ELECTRICA CANCHAYLLO SAC | DJ9: EMPRESA DE GENERACION ELECTRICA SANTA ANA S.A.C. | DK9: EMPRESA ELECTRICA AGUA AZUL | DL9: EMPRESA ELECTRICA RIO DOBLE | DM9: HIDROCAÑETE S.A. | DN9: HUAURA POWER GROUP S.A. | DO9: MOQUEGUA FV S.A.C. | DP9: PANAMERICANA SOLAR SAC. | DQ9: PARQUE EOLICO MARCONA S.A.C. | DR9: PARQUE EOLICO TRES HERMANAS S.A.C. | DS9: TACNA SOLAR SAC. | DT9: ELECTRICA YANAPAMPA SAC | DU9: ANDEAN POWER S.A.C. | DV9: ASOCIACIÓN SANTA LUCIA DE CHACAS | DW9: ATRIA ENERGIA S.A.C. | DX9: COENERGY S.A.C. | DY9: EGEJUNIN | DZ9: EGEJUNIN | EA9: EGEJUNIN | EB9: EGEJUNIN | EC9: ENERGÍA EÓLICA S.A. | ED9: ENERGÍA EÓLICA S.A. | EE9: ENGIE ENERGIA PERU S.A.A. | EF9: ENGIE ENERGIA PERU S.A.A. | EG9: ENGIE ENERGIA PERU S.A.A. | EH9: ENGIE ENERGIA PERU S.A.A. | EI9: ENGIE ENERGIA PERU S.A.A. | EJ9: ENGIE ENERGIA PERU S.A.A. | EK9: GENERACIÓN ANDINA S.A.C. | EL9: GENERACIÓN ANDINA S.A.C. | EM9: GENERADORA DE ENERGÍA DEL PERÚ | EN9: GENERADORA DE ENERGÍA DEL PERÚ | EO9: GENERADORA DE ENERGÍA DEL PERÚ | EP9: GENERADORA DE ENERGÍA DEL PERÚ | EQ9: GR PAINO SOCIEDAD ANONIMA CERRADA | ER9: JOYA SOLAR S.A.C. | ES9: MAJES ARCUS S.A.C. | ET9: ORYGEN PERU S.A.A. | EU9: ORYGEN PERU S.A.A. | EV9: ORYGEN PERU S.A.A. | EW9: ORYGEN PERU S.A.A. | EX9: ORYGEN PERU S.A.A. | EY9: PETRAMAS | EZ9: PETRAMAS | FA9: PETRAMAS | FB9: PETRAMAS | FC9: REPARTICIÓN ARCUS S.A.C. | FD9: SINERSA | FE9: SINERSA | FF9: SINERSA | FG9: BIOENERGIA DEL CHIRA S.A. | FH9: GM OPERACIONES S.A.C. | FI9: GM OPERACIONES S.A.C. | FJ9: AGRO INDUSTRIAL PARAMONGA S.A. | FK9: AGROAURORA S.A.C. | FL9: AGROINDUSTRIAS SAN JACINTO S.A.A. | FM9: AGROLMOS SOCIEDAD ANONIMA - AGROLMOS S.A. | FN9: CASA GRANDE S.A.A. | FQ9: UNACEM PERU S.A. | FR9: ELECTRO ORIENTE | FS9: AGUAS Y ENERGIA PERU | FT9: ELECTRO ZAÑA S.A.C. | FU9: ELECTRONOROESTE S.A. | FV9: SDE PIURA | FW9: SINERSA | FX9: SINERSA
C10: SAN GABAN III | D10: MANTARO | E10: RESTITUCION | F10: TUMBES MAK 1 | G10: TUMBES MAK 2 | H10: CARHUAQUERO | I10: CAÑON DEL PATO | J10: AGUAYTIA TG1 | K10: AGUAYTIA TG2 | L10: KALLPA TG1 | M10: KALLPA TG2 | N10: KALLPA TG3 | O10: KALLPA TV | P10: LFLORES TG1 | Q10: LFLORES TV | R10: CERRO DEL AGUILA | S10: CERRODELAGUILAG4 | T10: SHOUGESA TV1 | U10: SHOUGESA TV2 | V10: SHOUGESA TV3 | W10: SHOUGESA CUMMINS | X10: MACHUPICCHU | Y10: ARICOTA 1 | Z10: ARICOTA 2 | AA10: INDEPENDENCIA | AB10: CHARCANI I,II,III | AC10: CHARCANI IV | AD10: CHARCANI V | AE10: CHARCANI VI | AF10: CHILINA TG | AG10: MOLLENDO 1, 2, 3 | AH10: CHILINA (SULZ 1,2) | AI10: SAN GABAN II | AJ10: PLATANAL | AK10: RECKA | AL10: RF ETEN TG1 | AM10: RF ETEN TG2 | AN10: CHAGLLA GP1 | AO10: CHAGLLA | AP10: LA VIRGEN | AQ10: CHIMAY | AR10: YANANGO | AS10: HUANCHOR | AT10: MARAÑON | AU10: STA TERESA | AV10: FENIX GT11 | AW10: FENIX GT12 | AX10: FENIX TV10 | AY10: YAUPI | AZ10: MALPASO | BA10: CAHUA | BB10: ARCATA | BC10: GALLITO CIEGO | BD10: CHEVES | BE10: SANTA ROSA 1 | BF10: SANTA ROSA 2 | BG10: HUANZA | BH10: MALACAS2 TG4 | BI10: MALACAS3 TG 5 | BJ10: MALACAS1 TG6 | BK10: RF ILO2 TG1 | BL10: RF ILO2 TG2 | BM10: RF ILO2 TG3 | BN10: YUNCAN | BO10: CHILCA1 TG1 | BP10: CHILCA1 TG2 | BQ10: CHILCA1 TG3 | BR10: CHILCA-TV | BS10: CHILCA2 TG41 | BT10: CHILCA2-TV | BU10: CTNEPI_TG41 | BV10: CTNEPI_TG42 | BW10: CTNEPI_TG43 | BX10: QUITARACSA | BY10: RF PTO MALDONADO | BZ10: RF PUCALLPA | CA10: PARIAC | CB10: HUINCO | CC10: MATUCANA | CD10: MOYOPAMPA | CE10: CALLAHUANCA | CF10: HUAMPANI | CG10: STA ROSA WEST TG7 | CH10: UTI_5 | CI10: UTI_6 | CJ10: VENTANILLA 3 | CK10: VENTANILLA 4 | CL10: VENTANILLA TV | CM10: STAROSA TG8 | CN10: PTO_BRVO TG1 | CO10: PTO_BRVO TG2 | CP10: PTO_BRVO TG3 | CQ10: PTO_BRVO TG4 | CR10: OLLEROS TG1 | CS10: OLLEROS TV | CT10: OROYA | CU10: PACHACHACA | CV10: MANTA I | CW10: CS YARUCAYA | CX10: SAN JUAN | CY10: MATARANI | CZ10: DUNA | DA10: CARHUAQUERO (CS) | DB10: ANASHIRONI | DC10: CARHUAQUERO4 | DD10: CAÑA BRAVA | DE10: SUNNY | DF10: SUNNY EXPANSION | DG10: TUPURI | DH10: RONCADOR | DI10: CANCHAYLLO | DJ10: RENOVANDESH1 | DK10: POTRERO | DL10: PIZARRAS | DM10: NIMPERIAL | DN10: YARUCAYA | DO10: MOQUEGUA-SOLAR | DP10: PANAMERICANA-SOLAR | DQ10: PQE-EOLICO-MARCONA | DR10: PQE-EOLICO-3-HERMANAS | DS10: TACNA-SOLAR | DT10: YANAPAMPA | DU10: CARHUAC | DV10: HUALLIN | DW10: PURMACANA | DX10: COENERGY | DY10: HUASAHUASI | DZ10: STACRUZ_1_2 | EA10: RUNATULLO_II | EB10: RUNATULLO_III | EC10: PQE-EOLICO-TALARA | ED10: PQE-EOLICO-CUPISNIQUE | EE10: INTIPAMPA | EF10: PUNTA LOMITAS-BL1 | EG10: PUNTA LOMITAS-BL2 | EH10: PUN LOMITAS_EXP-BL1 | EI10: PUN LOMITAS_EXP-BL2 | EJ10: EXPANSIÓN INTIPAMPA | EK10: 8AGOSTO | EL10: EL CARMEN | EM10: LA JOYA | EN10: ANGEL_I | EO10: ANGEL_II | EP10: ANGEL_III | EQ10: HUAMBOS | ER10: SAN MARTIN SOLAR | ES10: MAJES | ET10: RUBI | EU10: CH_HER1 | EV10: WAYRA-I | EW10: WAYRA EXTENSION | EX10: CLEMESI | EY10: HUAYCOLORO | EZ10: CALLAO | FA10: DONA_CATALINA | FB10: LAGRINGAV | FC10: REPARTICION | FD10: POECHOS2 | FE10: CHANCAY | FF10: RUCUY | FG10: CANA BRAVA | FH10: REFINERIA TALARA TV1 | FI10: REFINERÍA TALARA TV2 | FJ10: PARAMONGA | FK10: MAPLE | FL10: SAN_JACINTO | FM10: AGROLMOS | FN10: CASA GRANDE | FO10: MVAR | FQ10: CARPAPATA | FR10: CENTRALES ELOR | FS10: PIAS1 | FT10: ZANA | FU10: TABLAZO | FV10: TALLANCA | FW10: CURUMUY | FX10: POECHOS1 | FY10: MVAR
A11: 04/03/2026 | B11: 00:30 | C11: 30.9 | D11: -1.6 | E11: 10 | F11: 1.1 | G11: 0.9 | H11: -14 | I11: -2.6 | J11: 0 | R11: 40 | S11: 0.1 | T11: 2.1 | U11: 5.4 | X11: -4.1 | Y11: 2.3 | Z11: 0.2 | AB11: -3.3 | AD11: -0.4 | AI11: 15.2 | AJ11: -6.6 | AK11: 0 | AN11: -1.7 | AO11: 22.9 | AP11: 8.8 | AQ11: 18.5 | AR11: 3.3 | AS11: 0.9 | AT11: 2.6 | AU11: 1.8 | AV11: 0 | AW11: -30.6 | AX11: -64.3 | AY11: 6.5 | AZ11: -2.4 | BA11: 0 | BB11: 1.2 | BC11: 0.3 | BD11: 4.4 | BG11: 1.4 | BH11: -10.9 | BJ11: 0 | BN11: 6.3 | BU11: 8.1 | BV11: -2.6 | BW11: -0.5 | BX11: 0 | CA11: 0 | CB11: 18.9 | CC11: 18.8 | CD11: -2.9 | CE11: 5.7 | CF11: 3.9 | CG11: 0 | CJ11: -8.5 | CN11: 0 | CO11: 5 | CP11: 6.3 | CQ11: 9.3 | CT11: 0 | CU11: -0.9 | CV11: 1.4 | CX11: -4.5 | CY11: 0 | CZ11: 0 | DB11: 0 | DC11: 0 | DD11: -1 | DE11: 0 | DF11: 0 | DH11: 0.2 | DI11: 1.3 | DJ11: 1.1 | DK11: -1.4 | DL11: 0.3 | DM11: 0.6 | DO11: 0 | DP11: 0 | DQ11: -1.6 | DR11: -4.7 | DS11: 0 | DT11: -0.1 | DU11: -1.3 | DV11: 0.7 | DY11: -4.5 | DZ11: 1.3 | EA11: 3.2 | EB11: 2.9 | EE11: 0 | EF11: -10.7 | EG11: -13.2 | EH11: 0 | EI11: 0 | EK11: 2.6 | EL11: -0.1 | EM11: 1.5 | EN11: 0.2 | EO11: 0.2 | EP11: 0.2 | ER11: 0 | ES11: 0 | ET11: 0 | EU11: -0.1 | EV11: 0 | EW11: 0 | EX11: 0 | EY11: 1.9 | EZ11: 0.8 | FA11: 0.4 | FB11: 1 | FC11: 0 | FD11: 0.4 | FE11: 1.6 | FF11: 1.3 | FH11: 0 | FI11: 0 | FJ11: 0 | FK11: 0.1 | FL11: 1.5 | FM11: 2 | FO11: 90.7 | FQ11: 2.3025 | FR11: 0.28 | FS11: 2.5 | FT11: 1.7 | FU11: 1.3 | FV11: 0.3 | FW11: -1 | FX11: 0.2 | FY11: 7.5825
A12: 04/03/2026 | B12: 01:00 | C12: 30.2 | D12: -6.6 | E12: 9 | F12: 1.4 | G12: 1.3 | H12: -14.4 | I12: 6.8 | J12: 0 | R12: 44 | S12: 0.1 | T12: 2.6 | U12: 0 | X12: -4.9 | Y12: 1.8 | Z12: 0.1 | AB12: -3.4 | AD12: -1.4 | AI12: 14.1 | AJ12: -11 | AK12: 0 | AN12: -1.6 | AO12: 26.1 | AP12: 8.2 | AQ12: 18.3 | AR12: 3.3 | AS12: -0.4 | AT12: 2.6 | AU12: 1.1 | AV12: 0 | AW12: -34.8 | AX12: -58.7 | AY12: 6.2 | AZ12: -4.1 | BA12: 0 | BB12: 1.2 | BC12: 0.3 | BD12: 2 | BG12: -1.4 | BH12: -11.1 | BJ12: 0 | BN12: 3.2 | BU12: 6.8 | BV12: -4 | BW12: -2 | BX12: 0 | CA12: 0 | CB12: 17.5 | CC12: 18.7 | CD12: -3.1 | CE12: 5.7 | CF12: 1.8 | CG12: 0 | CJ12: -13.4 | CN12: 0 | CO12: 2.8 | CP12: 4.5 | CQ12: 7.2 | CT12: -2.2 | CU12: -1 | CV12: 1.4 | CX12: -4.5 | CY12: 0 | CZ12: 0 | DB12: 0 | DC12: 0 | DD12: -1 | DE12: 0 | DF12: 0 | DH12: 0.2 | DI12: 1.2 | DJ12: 1.3 | DK12: -1.4 | DL12: 0.2 | DM12: 0.5 | DO12: 0 | DP12: 0 | DQ12: -1.8 | DR12: -5.2 | DS12: 0 | DT12: 0 | DU12: -1.3 | DV12: 0.7 | DY12: -4.6 | DZ12: 1 | EA12: 3.3 | EB12: 2.9 | EE12: 0 | EF12: -7.3 | EG12: -13.2 | EH12: 0 | EI12: 0 | EK12: 2.6 | EL12: -0.1 | EM12: 1.5 | EN12: 0.2 | EO12: 0.2 | EP12: 0.2 | ER12: 0 | ES12: 0 | ET12: 0 | EU12: -0.1 | EV12: 0 | EW12: 0 | EX12: 0 | EY12: 1.9 | EZ12: 0.8 | FA12: 0.4 | FB12: 1 | FC12: 0 | FD12: 0.4 | FE12: 1.4 | FF12: 1.1 | FH12: 0 | FI12: 0 | FJ12: 0 | FK12: 3.3 | FL12: 1.4 | FM12: 3.6 | FO12: 61.6 | FQ12: 2.09104 | FR12: 0.5 | FS12: 2.4 | FT12: 1.8 | FU12: 1.3 | FV12: 0.3 | FW12: -0.4 | FX12: 0.9 | FY12: 8.89104
A13: 04/03/2026 | B13: 01:30 | C13: 30.7 | D13: -27.2 | E13: 6 | F13: 1.3 | G13: 1.4 | H13: -15.3 | I13: 10.6 | J13: 0 | R13: 24 | S13: -0.1 | T13: 2.8 | U13: 0 | X13: -4.2 | Y13: 1.6 | Z13: 0.1 | AB13: -3.4 | AD13: -1.6 | AI13: 13.7 | AJ13: -16.9 | AK13: 0 | AN13: -1.6 | AO13: 18.6 | AP13: 7.5 | AQ13: 17.9 | AR13: 2.8 | AS13: -0.5 | AT13: 2.6 | AU13: 0.6 | AV13: 0 | AW13: -41.4 | AX13: -65.2 | AY13: 6.2 | AZ13: -4.9 | BA13: 0 | BB13: 1.2 | BC13: 0.3 | BD13: 0.2 | BG13: -3.2 | BH13: -8.8 | BJ13: 0 | BN13: 3.3 | BU13: 5.8 | BV13: -5 | BW13: -3 | BX13: 0 | CA13: 0.2 | CB13: 19.3 | CC13: 17.7 | CD13: -2.9 | CE13: 5.7 | CF13: 1.7 | CG13: 0 | CJ13: -19.9 | CN13: 0 | CO13: -1.8 | CP13: 0 | CQ13: 2.8 | CT13: -2 | CU13: -0.7 | CV13: 1.4 | CX13: -4.7 | CY13: 0 | CZ13: 0 | DB13: 0 | DC13: 0.1 | DD13: -1 | DE13: 0 | DF13: 0 | DH13: 0.1 | DI13: 1.2 | DJ13: 1.3 | DK13: -1.5 | DL13: 0.3 | DM13: 0.5 | DO13: 0 | DP13: 0 | DQ13: -2.1 | DR13: -6.7 | DS13: 0 | DT13: 0.1 | DU13: -1.4 | DV13: 0.8 | DY13: -4.6 | DZ13: 0.9 | EA13: 3.3 | EB13: 2.8 | EE13: 0 | EF13: -10.6 | EG13: -15.8 | EH13: 0 | EI13: 0 | EK13: 2.7 | EL13: -0.1 | EM13: 1.6 | EN13: 0.2 | EO13: 0.2 | EP13: 0.2 | ER13: 0 | ES13: 0 | ET13: 0 | EU13: -0.1 | EV13: 0 | EW13: 0 | EX13: 0 | EY13: 1.9 | EZ13: 0.8 | FA13: 0.4 | FB13: 1 | FC13: 0 | FD13: 0.4 | FE13: 1.2 | FF13: 1 | FH13: 0 | FI13: 0 | FJ13: 0 | FK13: 2.9 | FL13: 1.4 | FM13: 3.1 | FO13: -39.8 | FQ13: 2.16046 | FR13: 0.47 | FS13: 2.6 | FT13: 1.8 | FU13: 1.3 | FV13: 0.2 | FW13: -0.6 | FX13: 0.4 | FY13: 8.33046
A14: 04/03/2026 | B14: 02:00 | C14: 31.4 | D14: -17.7 | E14: 7.5 | F14: 1.2 | G14: 1.3 | H14: -16.3 | I14: -4.2 | J14: 0 | R14: 27 | S14: 0.1 | T14: 2.6 | U14: 0 | X14: -3.6 | Y14: 1.7 | Z14: -0.1 | AB14: -3.4 | AD14: -1.2 | AI14: 14.7 | AJ14: -20.8 | AK14: 0 | AN14: -1.6 | AO14: 20.3 | AP14: 7.6 | AQ14: 17.9 | AR14: 2.9 | AS14: 0 | AT14: 2.6 | AU14: 2.1 | AV14: 0 | AW14: -50.6 | AX14: -69.7 | AY14: 6.8 | AZ14: -3.4 | BA14: 0 | BB14: 1.2 | BC14: 0.3 | BD14: 5.9 | BG14: 0.4 | BH14: -9.7 | BJ14: 0 | BN14: 5.5 | BU14: 4.2 | BV14: -6.5 | BW14: -4.7 | BX14: 0 | CA14: 0 | CB14: 18.9 | CC14: 18 | CD14: -3.4 | CE14: 5.7 | CF14: 1.7 | CG14: 0 | CJ14: -11.4 | CN14: 0 | CO14: -2.2 | CP14: -0.5 | CQ14: -1.8 | CT14: -2.4 | CU14: -0.9 | CV14: 1.4 | CX14: -4.5 | CY14: 0 | CZ14: 0 | DB14: 0 | DC14: 0 | DD14: -1.1 | DE14: 0 | DF14: 0 | DH14: 0.2 | DI14: 1.3 | DJ14: 1.3 | DK14: -1.4 | DL14: 0.3 | DM14: 0.6 | DO14: 0 | DP14: 0 | DQ14: -2.7 | DR14: -9.1 | DS14: 0 | DT14: 0.1 | DU14: -1.3 | DV14: 0.8 | DY14: -4.6 | DZ14: 1.2 | EA14: 3.1 | EB14: 2.8 | EE14: 0 | EF14: -10.9 | EG14: -16.1 | EH14: 0 | EI14: 0 | EK14: 2.7 | EL14: -0.1 | EM14: 1.5 | EN14: 0.2 | EO14: 0.2 | EP14: 0.2 | ER14: 0 | ES14: 0 | ET14: 0 | EU14: -0.2 | EV14: 0 | EW14: 0 | EX14: 0 | EY14: 1.9 | EZ14: 0.8 | FA14: 0.4 | FB14: 1 | FC14: 0 | FD14: 0.4 | FE14: 1.6 | FF14: 1.3 | FH14: 0 | FI14: 0 | FJ14: 0 | FK14: 3 | FL14: 1.9 | FM14: 3.3 | FO14: -45.1 | FQ14: 2.14076 | FR14: 0.31 | FS14: 2.7 | FT14: 1.8 | FU14: 1.3 | FV14: 0.3 | FW14: -0.7 | FX14: 0.4 | FY14: 8.25076
A15: 04/03/2026 | B15: 02:30 | C15: 32.2 | D15: -8.7 | E15: 8.9 | F15: 1.3 | G15: 1.3 | H15: -15.7 | I15: 1.3 | J15: 0 | R15: 34.5 | S15: 0 | T15: 2.5 | U15: 0 | X15: -4.8 | Y15: 1.5 | Z15: -0.1 | AB15: -3.4 | AD15: -0.3 | AI15: 14.6 | AJ15: -14.1 | AK15: 0 | AN15: -1.7 | AO15: 21.3 | AP15: 8.2 | AQ15: 15.1 | AR15: 2.9 | AS15: 0.1 | AT15: 2.6 | AU15: 1.6 | AV15: 0 | AW15: -41.1 | AX15: -64.9 | AY15: 6.6 | AZ15: -3.4 | BA15: 0 | BB15: 1.2 | BC15: 0.3 | BD15: 3.3 | BG15: 2.5 | BH15: -10.2 | BJ15: 0 | BN15: 6.2 | BU15: 4.9 | BV15: -5.9 | BW15: -3.9 | BX15: 0 | CA15: 0 | CB15: 19.1 | CC15: 18.2 | CD15: -2.9 | CE15: 5.8 | CF15: 1.7 | CG15: 0 | CJ15: -2.6 | CN15: 0 | CO15: -1.5 | CP15: 0 | CQ15: 0 | CT15: -2 | CU15: -0.7 | CV15: 1.4 | CX15: -5.1 | CY15: 0 | CZ15: 0 | DB15: 0 | DC15: -0.1 | DD15: -1 | DE15: 0 | DF15: 0 | DH15: 0.2 | DI15: 1.3 | DJ15: 1.2 | DK15: -1.7 | DL15: 0.3 | DM15: 0.6 | DO15: 0 | DP15: 0 | DQ15: -2.1 | DR15: -8 | DS15: 0 | DT15: 0 | DU15: -1.3 | DV15: 0.7 | DY15: -4.6 | DZ15: 1 | EA15: 3.1 | EB15: 2.9 | EE15: 0 | EF15: -10.1 | EG15: -14.8 | EH15: 0 | EI15: 0 | EK15: 2.7 | EL15: -0.1 | EM15: 1.5 | EN15: 0.2 | EO15: 0.2 | EP15: 0.2 | ER15: 0 | ES15: 0 | ET15: 0 | EU15: -0.2 | EV15: 0 | EW15: 0 | EX15: 0 | EY15: 2 | EZ15: 0.8 | FA15: 0.4 | FB15: 0.5 | FC15: 0 | FD15: 0.4 | FE15: 2 | FF15: 1.6 | FH15: 0 | FI15: 0 | FJ15: 0 | FK15: 2.9 | FL15: 1.8 | FM15: 3.5 | FO15: 16.1 | FQ15: 2.18498 | FR15: 0.32 | FS15: 2.8 | FT15: 1.8 | FU15: 1.3 | FV15: 0.3 | FW15: -0.7 | FX15: 0.4 | FY15: 8.40498
A16: 04/03/2026 | B16: 03:00 | C16: 34.5 | D16: -8.1 | E16: 8 | F16: 1.3 | G16: 1.4 | H16: -14.8 | I16: 11.5 | J16: 0 | R16: 34.4 | S16: 0 | T16: 2.9 | U16: 0 | X16: -3.3 | Y16: 2 | Z16: 0.3 | AB16: -3.4 | AD16: -0.2 | AI16: 13.9 | AJ16: -16 | AK16: 0 | AN16: -1.7 | AO16: 19.9 | AP16: 7.9 | AQ16: 16 | AR16: 3.4 | AS16: 0.4 | AT16: 2.6 | AU16: 1.1 | AV16: 0 | AW16: -40.4 | AX16: -64 | AY16: 7.4 | AZ16: -4.8 | BA16: 0 | BB16: 1.2 | BC16: 0.1 | BD16: 1.3 | BG16: 2.5 | BH16: -10.2 | BJ16: 0 | BN16: 7.7 | BU16: 6.3 | BV16: -4.5 | BW16: -2.4 | BX16: 0 | CA16: -0.1 | CB16: 19.1 | CC16: 18.5 | CD16: -2.6 | CE16: 5.7 | CF16: 1.7 | CG16: 0 | CJ16: -2.4 | CN16: 0 | CO16: 0.5 | CP16: 2.2 | CQ16: 0 | CT16: 0 | CU16: -0.7 | CV16: 1.4 | CX16: -5.2 | CY16: 0 | CZ16: 0 | DB16: 0 | DC16: 0 | DD16: -1.1 | DE16: 0 | DF16: 0 | DH16: 0.2 | DI16: 1.3 | DJ16: 1.4 | DK16: -2 | DL16: 0.3 | DM16: 0.6 | DO16: 0 | DP16: 0 | DQ16: -1.9 | DR16: -7.1 | DS16: 0 | DT16: 0.2 | DU16: -1.3 | DV16: 0.7 | DY16: -4.6 | DZ16: 0.9 | EA16: 3 | EB16: 2.8 | EE16: 0 | EF16: -9.9 | EG16: -14.6 | EH16: 0 | EI16: 0 | EK16: 2.7 | EL16: -0.1 | EM16: 1.5 | EN16: 0.2 | EO16: 0.2 | EP16: 0.2 | ER16: 0 | ES16: 0 | ET16: 0 | EU16: -0.2 | EV16: 0 | EW16: 0 | EX16: 0 | EY16: 2 | EZ16: 0.8 | FA16: 0.4 | FB16: 1 | FC16: 0 | FD16: 0.4 | FE16: 1.9 | FF16: 1.6 | FH16: 0 | FI16: 0 | FJ16: 0 | FK16: 2.6 | FL16: 2.1 | FM16: 3.5 | FO16: 42 | FQ16: 2.14291 | FR16: 0.27 | FS16: 2.9 | FT16: 1.8 | FU16: 1.3 | FV16: 0.3 | FW16: -0.7 | FX16: 0.4 | FY16: 8.41291
A17: 04/03/2026 | B17: 03:30 | C17: 32.2 | D17: -6.5 | E17: 9 | F17: 1.3 | G17: 1.4 | H17: -15 | I17: 13.9 | J17: 0 | R17: 38 | S17: 0 | T17: 3.1 | U17: 0 | X17: -3.6 | Y17: 1.6 | Z17: 0 | AB17: -3.4 | AD17: -0.7 | AI17: 14.5 | AJ17: -16 | AK17: 0 | AN17: -1.7 | AO17: 19.2 | AP17: 7.9 | AQ17: 15.2 | AR17: 3.2 | AS17: 0.6 | AT17: 2.6 | AU17: 2 | AV17: 0 | AW17: -41.8 | AX17: -65.6 | AY17: 6.2 | AZ17: -3.3 | BA17: 0 | BB17: 1.2 | BC17: 0.2 | BD17: 5.8 | BG17: 2.5 | BH17: -9.8 | BJ17: 0 | BN17: 6 | BU17: 4.7 | BV17: -6.3 | BW17: -4 | BX17: 0 | CA17: 0 | CB17: 19.7 | CC17: 18.1 | CD17: -3.2 | CE17: 5.7 | CF17: 1.7 | CG17: 0 | CJ17: -3.6 | CN17: 0 | CO17: -4.4 | CP17: 0.5 | CQ17: 0 | CT17: 0 | CU17: -0.8 | CV17: 1.3 | CX17: -5 | CY17: 0 | CZ17: 0 | DB17: 0 | DC17: 0 | DD17: -1.1 | DE17: 0 | DF17: 0 | DH17: 0.2 | DI17: 1.3 | DJ17: 1.3 | DK17: -1.7 | DL17: 0.3 | DM17: 0.6 | DO17: 0 | DP17: 0 | DQ17: -1.9 | DR17: -7 | DS17: 0 | DT17: 0.1 | DU17: -1 | DV17: 0.7 | DY17: -4.6 | DZ17: 0.9 | EA17: 3.1 | EB17: 2.8 | EE17: 0 | EF17: -9.9 | EG17: -14.6 | EH17: 0 | EI17: 0 | EK17: 2.7 | EL17: 0 | EM17: 1.5 | EN17: 0.2 | EO17: 0.2 | EP17: 0.2 | ER17: 0 | ES17: 0 | ET17: 0 | EU17: -0.2 | EV17: -12.8 | EW17: 16 | EX17: 0 | EY17: 2 | EZ17: 0.8 | FA17: 0.4 | FB17: 1 | FC17: 0 | FD17: 0.4 | FE17: 1.8 | FF17: 1.5 | FH17: 0 | FI17: 0 | FJ17: 0 | FK17: 2.4 | FL17: 1.7 | FM17: 3.5 | FO17: 37.4 | FQ17: 2.16543 | FR17: 0.25 | FS17: 2.2 | FT17: 1.9 | FU17: 1.3 | FV17: 0.3 | FW17: -0.8 | FX17: 0.4 | FY17: 7.71543
A18: 04/03/2026 | B18: 04:00 | C18: 28.7 | D18: -14.5 | E18: 7.7 | F18: 1.3 | G18: 1.3 | H18: -17 | I18: -1.2 | J18: 0 | R18: 33.3 | S18: 0 | T18: 3.1 | U18: 0 | X18: -6 | Y18: 1.8 | Z18: 0.1 | AB18: -3.4 | AD18: -1.2 | AI18: 12.4 | AJ18: -17.5 | AK18: 0 | AN18: -1.8 | AO18: 18.2 | AP18: 7.3 | AQ18: 15.3 | AR18: 3 | AS18: 0.3 | AT18: 2.6 | AU18: 0.5 | AV18: 0 | AW18: -45.5 | AX18: -64 | AY18: 4.4 | AZ18: -5.3 | BA18: 0 | BB18: 1.2 | BC18: 0.3 | BD18: 1.7 | BG18: 0.8 | BH18: -9.7 | BJ18: 0 | BN18: 4.9 | BU18: 4.6 | BV18: -6.4 | BW18: -4.3 | BX18: 0 | CA18: -0.1 | CB18: 18.3 | CC18: 18.2 | CD18: -3 | CE18: 5.7 | CF18: 1.6 | CG18: 0 | CJ18: -6.9 | CN18: 0 | CO18: -5.8 | CP18: -1.1 | CQ18: 0 | CT18: 0 | CU18: -0.9 | CV18: 1.4 | CX18: -4.9 | CY18: 0 | CZ18: 0 | DB18: 0.1 | DC18: -0.1 | DD18: -1.1 | DE18: 0 | DF18: 0 | DH18: 0.2 | DI18: 1.3 | DJ18: 1.2 | DK18: -1.7 | DL18: 0.3 | DM18: 0.6 | DO18: 0 | DP18: 0 | DQ18: -2 | DR18: -6.8 | DS18: 0 | DT18: 0.1 | DU18: -1.4 | DV18: 0.8 | DY18: -4.6 | DZ18: 0.9 | EA18: 3.1 | EB18: 2.7 | EE18: 0 | EF18: -8.4 | EG18: -14.8 | EH18: 0 | EI18: 0 | EK18: 2.7 | EL18: 0 | EM18: 1.6 | EN18: 0.2 | EO18: 0.2 | EP18: 0.2 | ER18: 0 | ES18: 0 | ET18: 0 | EU18: -0.2 | EV18: -11.8 | EW18: 4.7 | EX18: 0 | EY18: 2 | EZ18: 0.8 | FA18: 0.4 | FB18: 1 | FC18: 0 | FD18: 0.4 | FE18: 1.8 | FF18: 1.4 | FH18: 0 | FI18: 0 | FJ18: 0 | FK18: 2.2 | FL18: 1.4 | FM18: 3.3 | FO18: -37.8 | FQ18: 1.83036 | FR18: 0.16 | FS18: 2 | FT18: 1.9 | FU18: 1.3 | FV18: 0.3 | FW18: -0.9 | FX18: 0.4 | FY18: 6.99036
A19: 04/03/2026 | B19: 04:30 | C19: 31 | D19: -7.9 | E19: 9 | F19: 1.3 | G19: 1.3 | H19: -16.1 | I19: 9 | J19: 0 | R19: 40.3 | S19: 0.1 | T19: 3.3 | U19: 0 | X19: -4.5 | Y19: 2.1 | Z19: 0.2 | AB19: -3.4 | AD19: 0.3 | AI19: 13.4 | AJ19: -14.6 | AK19: 0 | AN19: -1.7 | AO19: 20.2 | AP19: 5.7 | AQ19: 14.9 | AR19: 2.8 | AS19: -0.3 | AT19: 2.6 | AU19: 1.5 | AV19: 0 | AW19: -40 | AX19: -58.9 | AY19: 6.2 | AZ19: -3.9 | BA19: 0 | BB19: 1.2 | BC19: 0.2 | BD19: 4.5 | BG19: 2.8 | BH19: -10.2 | BJ19: 0 | BN19: 5.9 | BU19: 6.4 | BV19: -4.4 | BW19: -2.5 | BX19: 0 | CA19: 0 | CB19: 17.2 | CC19: 17.9 | CD19: -3.1 | CE19: 5.7 | CF19: 1.6 | CG19: 0 | CJ19: -2.2 | CN19: 0 | CO19: -5.4 | CP19: -0.7 | CQ19: 0 | CT19: 0 | CU19: -0.9 | CV19: 1.4 | CX19: -4.7 | CY19: 0 | CZ19: 0 | DB19: 0.1 | DC19: 0 | DD19: -1.1 | DE19: 0 | DF19: 0 | DH19: 0.2 | DI19: 1.2 | DJ19: 1.3 | DK19: -1.9 | DL19: 0.3 | DM19: 0.6 | DO19: 0 | DP19: 0 | DQ19: -1.4 | DR19: -5.2 | DS19: 0 | DT19: 0 | DU19: -1.3 | DV19: 0.8 | DY19: -4.6 | DZ19: 1 | EA19: 3.2 | EB19: 2.8 | EE19: 0 | EF19: -8 | EG19: -14.1 | EH19: 0 | EI19: 0 | EK19: 2.6 | EL19: -0.2 | EM19: 1.6 | EN19: 0.2 | EO19: 0.2 | EP19: 0.2 | ER19: 0 | ES19: 0 | ET19: 0 | EU19: -0.2 | EV19: -9.3 | EW19: -3.5 | EX19: 0 | EY19: 2 | EZ19: 0.8 | FA19: 0.4 | FB19: 1 | FC19: 0 | FD19: 0.4 | FE19: 1.8 | FF19: 1.5 | FH19: 0 | FI19: 0 | FJ19: 0 | FK19: 2.6 | FL19: 1.7 | FM19: 3.3 | FO19: 25.6 | FQ19: 2.21107 | FR19: 0.12 | FS19: 2 | FT19: 1.7 | FU19: 1.3 | FV19: 0.3 | FW19: -0.8 | FX19: 0.4 | FY19: 7.23107
A20: 04/03/2026 | B20: 05:00 | C20: 32.1 | D20: -9.3 | E20: 8.4 | F20: 1.4 | G20: 1.4 | H20: -15.9 | I20: -2.3 | J20: 0 | R20: 35.8 | S20: 0 | T20: 2.9 | U20: 0 | X20: -3.8 | Y20: 2.2 | Z20: 0.3 | AB20: -3.4 | AD20: 0.6 | AI20: 13.5 | AJ20: -14 | AK20: 0 | AN20: -1.7 | AO20: 19.2 | AP20: 7.3 | AQ20: 15.4 | AR20: 3.2 | AS20: 0.2 | AT20: 2.6 | AU20: 1.5 | AV20: 0 | AW20: -40.9 | AX20: -59.7 | AY20: 5.2 | AZ20: -4.7 | BA20: 0 | BB20: 1.2 | BC20: 0.3 | BD20: 4.1 | BG20: 2.5 | BH20: -9.9 | BJ20: 0 | BN20: 5.8 | BU20: 6.6 | BV20: -4.3 | BW20: -2.3 | BX20: 0 | CA20: 0 | CB20: 17.6 | CC20: 18.1 | CD20: -3.1 | CE20: 5.7 | CF20: 1.7 | CG20: 0 | CJ20: -2.8 | CN20: 0 | CO20: -3.2 | CP20: 1.8 | CQ20: 0 | CT20: 0 | CU20: -1 | CV20: 1.4 | CX20: -4.8 | CY20: 0 | CZ20: 0 | DB20: 0 | DC20: 0 | DD20: -1 | DE20: -0.2 | DF20: -0.05 | DH20: 0.2 | DI20: 1.2 | DJ20: 1.2 | DK20: -1.9 | DL20: 0.3 | DM20: 0.6 | DO20: 0 | DP20: 0 | DQ20: -1.4 | DR20: -5.1 | DS20: 0.2 | DT20: 0.1 | DU20: -1.3 | DV20: 0.7 | DY20: -4.6 | DZ20: 0.9 | EA20: 3.2 | EB20: 2.8 | EE20: 0.4 | EF20: -9.6 | EG20: -14.1 | EH20: 0 | EI20: 0 | EK20: 2.7 | EL20: 0 | EM20: 1.6 | EN20: 0.2 | EO20: 0.2 | EP20: 0.2 | ER20: 0 | ES20: 0.3 | ET20: 0 | EU20: -0.2 | EV20: -8.5 | EW20: -1.8 | EX20: 0 | EY20: 2 | EZ20: 0.8 | FA20: 0.4 | FB20: 1 | FC20: 0.3 | FD20: 0.4 | FE20: 1.8 | FF20: 1.5 | FH20: 0 | FI20: 0 | FJ20: 0 | FK20: 2.5 | FL20: 1.6 | FM20: 3.1 | FO20: 15.55 | FQ20: 2.33599 | FR20: 0.33 | FS20: 2.1 | FT20: 1.8 | FU20: 1.3 | FV20: 0.3 | FW20: -0.9 | FX20: 0.4 | FY20: 7.66599
A21: 04/03/2026 | B21: 05:30 | C21: 30.7 | D21: 8.2 | E21: 11.8 | F21: 1.3 | G21: 1.3 | H21: -13.2 | I21: 13.1 | J21: 0 | R21: 52 | S21: 0 | T21: 3.4 | U21: 0 | X21: -3.2 | Y21: 2.1 | Z21: 0.3 | AB21: -3.1 | AD21: 0.8 | AI21: 13.4 | AJ21: -2.9 | AK21: 0 | AN21: -1.5 | AO21: 39.5 | AP21: 8.5 | AQ21: 15 | AR21: 2.8 | AS21: -1 | AT21: 2.6 | AU21: 0.8 | AV21: 0 | AW21: -27.6 | AX21: -46.6 | AY21: 7.2 | AZ21: -3.3 | BA21: 0 | BB21: 1.2 | BC21: 0.3 | BD21: 4.7 | BG21: 4.7 | BH21: 0 | BJ21: 0 | BN21: 11.5 | BU21: 7.9 | BV21: -3 | BW21: -1.1 | BX21: 0 | CA21: 0 | CB21: 18.7 | CC21: 17.7 | CD21: -3.1 | CE21: 5.7 | CF21: 1.6 | CG21: 0 | CJ21: 10.6 | CN21: 0 | CO21: 0.8 | CP21: 2.3 | CQ21: 0 | CT21: 0 | CU21: -0.9 | CV21: 1.4 | CX21: -4.4 | CY21: 0 | CZ21: 0 | DB21: 0 | DC21: 0 | DD21: -1.1 | DE21: 0 | DF21: -0.07 | DH21: 0.2 | DI21: 1.2 | DJ21: 1.3 | DK21: 1.3 | DL21: 0.3 | DM21: 0.6 | DO21: 0 | DP21: 0 | DQ21: -1.2 | DR21: -4 | DS21: 0.4 | DT21: 0 | DU21: -1.2 | DV21: 0.7 | DY21: -4.6 | DZ21: 1.2 | EA21: 3.2 | EB21: 2.9 | EE21: 0.4 | EF21: -8 | EG21: -12.1 | EH21: 0 | EI21: 0 | EK21: 2.7 | EL21: 0 | EM21: 1.6 | EN21: 0.2 | EO21: 0.2 | EP21: 0.2 | ER21: 0 | ES21: 0.3 | ET21: 0 | EU21: -0.2 | EV21: -7.7 | EW21: -1.2 | EX21: 0 | EY21: 2 | EZ21: 0.8 | FA21: 0.3 | FB21: 1 | FC21: 0.3 | FD21: 0.4 | FE21: 1.8 | FF21: 1.5 | FH21: 0 | FI21: 0 | FJ21: 0 | FK21: 1.3 | FL21: 1.9 | FM21: 3.2 | FO21: 181.03 | FQ21: 2.54075 | FR21: 0.6 | FS21: 2.3 | FT21: 1.8 | FU21: 1.1 | FV21: 0.3 | FW21: -0.7 | FX21: 0.4 | FY21: 8.34075
A22: 04/03/2026 | B22: 06:00 | C22: 32.2 | D22: 4.5 | E22: 11.4 | F22: 1.3 | G22: 1.3 | H22: -12.6 | I22: 2.7 | J22: 0 | R22: 49.2 | S22: 0.1 | T22: 3.3 | U22: 0 | X22: -4.7 | Y22: 2.2 | Z22: 0.3 | AB22: -3.4 | AD22: -0.5 | AI22: 13.8 | AJ22: -4.6 | AK22: 0 | AN22: -1.6 | AO22: 27.7 | AP22: 8.7 | AQ22: 15 | AR22: 2.9 | AS22: -1.2 | AT22: 2.6 | AU22: 1.1 | AV22: 0 | AW22: -27.3 | AX22: -47.9 | AY22: 0.9 | AZ22: -2.3 | BA22: 0 | BB22: 1.2 | BC22: 0.3 | BD22: 5.6 | BG22: 6.1 | BH22: 0 | BJ22: -1.8 | BN22: 4.7 | BU22: 6.5 | BV22: -4.5 | BW22: -2.4 | BX22: 0 | CA22: 0 | CB22: 32.9 | CC22: 27.2 | CD22: -3.4 | CE22: 5.7 | CF22: 1.5 | CG22: 0 | CJ22: 8.7 | CN22: 0 | CO22: 0.5 | CP22: 2.1 | CQ22: 0 | CT22: 0 | CU22: -0.9 | CV22: 1.4 | CX22: -4.1 | CY22: 0 | CZ22: 0 | DB22: 0 | DC22: 0 | DD22: -1.1 | DE22: 0.1 | DF22: -0.08 | DH22: 0.2 | DI22: 1.2 | DJ22: 1.2 | DK22: 2 | DL22: 1.1 | DM22: 0.6 | DO22: 0 | DP22: 0 | DQ22: -1.6 | DR22: -5.2 | DS22: 0.4 | DT22: 0.1 | DU22: -0.6 | DV22: 0.8 | DY22: -4.7 | DZ22: 0.9 | EA22: 3.2 | EB22: 2.9 | EE22: 0.3 | EF22: -8.4 | EG22: -12.5 | EH22: 0 | EI22: 0 | EK22: 2.6 | EL22: 0 | EM22: 1.6 | EN22: 0.2 | EO22: 0.2 | EP22: 0.2 | ER22: 29.4 | ES22: 0.4 | ET22: -0.2 | EU22: -0.2 | EV22: -8.6 | EW22: 0.3 | EX22: -0.9 | EY22: 2 | EZ22: 0.8 | FA22: 0.3 | FB22: 1 | FC22: 1.1 | FD22: 0.4 | FE22: 1.8 | FF22: 1.5 | FH22: 0 | FI22: 0 | FJ22: 0 | FK22: 1.2 | FL22: 1.9 | FM22: 3.2 | FO22: 183.42 | FQ22: 2.5306 | FR22: 0.44 | FS22: 2 | FT22: 1.8 | FU22: 0.4 | FV22: 0.3 | FW22: -0.7 | FX22: 0.4 | FY22: 7.1706
... A58: 05/03/2026 | B58: 00:00 | C58: 34.3 | D58: -3.6 | E58: 15.2 | F58: 1.8 | G58: 1.8 | H58: -11.2 | I58: 19.2 | J58: 4.6 | R58: 25.7 | S58: 0.1 | T58: 1.6 | U58: 0 | X58: 6.3 | Y58: 2.6 | Z58: 0.5 | AB58: -3.4 | AD58: 5.7 | AI58: 16.5 | AJ58: -15.8 | AK58: 0 | AN58: -0.9 | AO58: 25.5 | AP58: 9.9 | AQ58: 21 | AR58: 2 | AS58: 0.6 | AT58: 2.6 | AU58: 1.9 | AV58: -33.2 | AW58: -45.5 | AX58: -54.8 | AY58: 7.8 | AZ58: -1.6 | BA58: 0 | BB58: 1.2 | BC58: 0.2 | BD58: -1 | BG58: 1.5 | BH58: 1.4 | BJ58: 3.2 | BN58: 0 | BU58: 0 | BV58: 0 | BW58: 0 | BX58: 0 | CA58: 0.1 | CB58: 19.9 | CC58: 21.2 | CD58: -0.5 | CE58: 1.8 | CF58: 0 | CG58: 0 | CJ58: 6 | CN58: 5.4 | CO58: 0 | CP58: 0 | CQ58: 0 | CT58: -2.2 | CU58: -0.9 | CV58: 1.4 | CX58: -4.3 | CY58: 0 | CZ58: 0 | DB58: 0.1 | DC58: -0.1 | DD58: -1.2 | DE58: 0 | DF58: 0 | DH58: 0.2 | DI58: 1.5 | DJ58: 1.2 | DK58: -1.7 | DL58: 0.3 | DM58: 0.6 | DO58: 0 | DP58: 0 | DQ58: 8.4 | DR58: 5.5 | DS58: 0 | DT58: 0.1 | DU58: -1.3 | DV58: 0.5 | DY58: -4.7 | DZ58: 1 | EA58: 3.1 | EB58: 3 | EE58: 0 | EF58: 0 | EG58: 0 | EH58: 0 | EI58: 0 | EK58: 2.6 | EL58: 0 | EM58: 1.6 | EN58: 0.2 | EO58: 0.2 | EP58: 0.2 | ER58: 0 | ES58: 0 | ET58: 0 | EU58: 0 | EV58: -3.8 | EW58: -0.3 | EX58: 0 | EY58: 2.1 | EZ58: 0.8 | FA58: 0.2 | FB58: 0.6 | FC58: 0 | FD58: 0.4 | FE58: 1.8 | FF58: 1.5 | FH58: 9 | FI58: 10.5 | FJ58: 3.2 | FK58: 0 | FL58: 2.4 | FM58: 3.3 | FO58: 144.6 | FQ58: 2.90927 | FR58: -0.12 | FS58: 2.1 | FT58: 1.6 | FU58: 0.2 | FV58: 0.4 | FW58: -1.5 | FX58: 3 | FY58: 8.58927
A59: EJEC | C59: 754.5 | D59: 1371.55 | E59: 608.8 | F59: 36.2 | G59: 34.75 | H59: -181.4 | I59: 348.2 | J59: 14.85 | K59: 0 | L59: 0 | M59: 0 | N59: 0 | O59: 0 | P59: 0 | Q59: 0 | R59: 998.3 | S59: 0.9 | T59: 70.4 | U59: 2.7 | V59: 0 | W59: 0 | X59: -16.2 | Y59: 43.05 | Z59: 5.7 | AA59: 0 | AB59: -76.5 | AC59: 0 | AD59: 194.9 | AE59: 0 | AF59: 0 | AG59: 0 | AH59: 0 | AI59: 415.75 | AJ59: 128.05 | AK59: -3.4 | AL59: 0 | AM59: 0 | AN59: -36.5 | AO59: 787.65 | AP59: 222.6 | AQ59: 546.4 | AR59: 126.45 | AS59: -3.7 | AT59: 62.4 | AU59: 29.95 | AV59: 345.6 | AW59: -273.25 | AX59: -150.7 | AY59: 191.4 | AZ59: -51.15 | BA59: 34.1 | BB59: 28.8 | BC59: 8.25 | BD59: 255.35 | BE59: 0 | BF59: 0 | BG59: 134.55 | BH59: -48.65 | BI59: 0 | BJ59: -6.8 | BK59: 0 | BL59: 0 | BM59: 0 | BN59: 215.25 | BO59: 0 | BP59: 0 | BQ59: 0 | BR59: 0 | BS59: 0 | BT59: 0 | BU59: 196.9 | BV59: -32.3 | BW59: -18.05 | BX59: -5.25 | BY59: 0 | BZ59: 0 | CA59: 1.5 | CB59: 1192.9 | CC59: 749.95 | CD59: 164.7 | CE59: 222 | CF59: 130.1 | CG59: 81.45 | CH59: 0 | CI59: 0 | CJ59: 705.35 | CK59: 0 | CL59: 0 | CM59: 0 | CN59: 59.95 | CO59: 43.7 | CP59: 128.35 | CQ59: 79.65 | CR59: 0 | CS59: 0 | CT59: -32.25 | CU59: -22.05 | CV59: 33.1 | CW59: 0 | CX59: 73.2 | CY59: 79 | CZ59: 8.95 | DA59: 0 | DB59: 0.95 | DC59: -0.6 | DD59: -26.1 | DE59: 256.55 | DF59: 88.285 | DG59: 0 | DH59: 3.5 | DI59: 36.15 | DJ59: 29.55 | DK59: -1.35 | DL59: 7.8 | DM59: 13.95 | DN59: 0 | DO59: 7.3 | DP59: 19.65 | DQ59: 124.85 | DR59: 113.05 | DS59: -29.4 | DT59: 0.6 | DU59: -3.2 | DV59: 14.9 | DW59: 0 | DX59: 0 | DY59: -112.3 | DZ59: 22.75 | EA59: 71.05 | EB59: 70.45 | EC59: 0 | ED59: 0 | EE59: 29.1 | EF59: -91.8 | EG59: -159.95 | EH59: 2.6 | EI59: 2.35 | EJ59: 0 | EK59: 63.2 | EL59: -2.7 | EM59: 41.05 | EN59: 4.8 | EO59: 4.8 | EP59: 4.8 | EQ59: 0 | ER59: 382.6 | ES59: -9.1 | ET59: 161.95 | EU59: -4.25 | EV59: 58.6 | EW59: 53.95 | EX59: -77.75 | EY59: 37.75 | EZ59: 18.1 | FA59: 6.65 | FB59: 22.55 | FC59: -7.8 | FD59: 9.6 | FE59: 45.2 | FF59: 38 | FG59: 0 | FH59: 78.8 | FI59: 127.95 | FJ59: 48.55 | FK59: 23.65 | FL59: 55.55 | FM59: 85.15 | FN59: 0 | FO59: 12772.285 | FQ59: 62.711865 | FR59: 1.045 | FS59: 50.85 | FT59: 28.35 | FU59: 28.1 | FV59: 7.4 | FW59: -8.25 | FX59: 45.35 | FY59: 215.55686

Sheet DEMANDA_AREAS
B3: miércoles, 4 de Marzo del 2026
B5: REPORTE DE LA DEMANDA POR ÁREAS Y SUBAREAS OPERATIVAS (MW)
B6: FECHA HORA | C6: DEMANDA | E6: AREA | H6: SUBAREAS
C7: INTERCAMBIOS INTERNACIONALES | D7: SEIN | E7: NORTE | F7: CENTRO | G7: SUR | H7: ELECTROANDES
B8: 00:30 | C8: 0 | D8: 6638.2 | E8: 1022.2843 | F8: 3768.7823 | G8: 1847.1334 | H8: 251.0975
B9: 01:00 | C9: 0 | D9: 6566.5 | E9: 1029.9073 | F9: 3718.9471 | G9: 1817.6456 | H9: 244.4023
B10: 01:30 | C10: 0 | D10: 6488.3 | E10: 1024.604 | F10: 3642.327 | G10: 1821.369 | H10: 253.6333
B11: 02:00 | C11: 0 | D11: 6343.5 | E11: 967.7979 | F11: 3562.4324 | G11: 1813.2697 | H11: 257.3511
B12: 02:30 | C12: 0 | D12: 6284.2 | E12: 963.5237 | F12: 3506.5713 | G12: 1814.105 | H12: 253.9255
B13: 03:00 | C13: 0 | D13: 6265.4 | E13: 991.1397 | F13: 3459.038 | G13: 1815.2223 | H13: 247.998
B14: 03:30 | C14: 0 | D14: 6254 | E14: 993.5321 | F14: 3459.4786 | G14: 1800.9893 | H14: 252.9838
B15: 04:00 | C15: 0 | D15: 6234.1 | E15: 954.8826 | F15: 3465.5262 | G15: 1813.6912 | H15: 260.1115
B16: 04:30 | C16: 0 | D16: 6273 | E16: 982.9209 | F16: 3470.4693 | G16: 1819.6098 | H16: 256.4514
B17: 05:00 | C17: 0 | D17: 6278.7 | E17: 957.9343 | F17: 3504.5889 | G17: 1816.1768 | H17: 247.8693
B18: 05:30 | C18: 0 | D18: 6443.7 | E18: 1015.1209 | F18: 3593.2509 | G18: 1835.3282 | H18: 251.78
B19: 06:00 | C19: 0 | D19: 6445.63 | E19: 997.5458 | F19: 3647.8019 | G19: 1800.2823 | H19: 240.8506
... B59: ENERGÍA | C59: 0 | D59: 174252.7 | E59: 27833.213 | F59: 103272.65 | G59: 43146.836 | H59: 6082.2353
B61: LEYENDA:
D63: Potencia recibida del Ecuador
D64: Potencia entregada al Ecuador

Sheet DEMANDA_UL
B3: miércoles, 4 de Marzo del 2026
B5: POTENCIA DE LOS GRANDES USUARIOS LIBRES (MW)
B6: FECHA HORA | C6: GRANDES USUARIOS LIBRES DEL ÁREA NORTE | X6: GRANDES USUARIOS LIBRES DEL ÁREA CENTRO | BP6: GRANDES USUARIOS LIBRES DEL ÁREA SUR
C7: ARCA CONTINENTAL LINDLEY S.A. | D7: AUSTRAL GROUP S.A.A | E7: CEMENTOS PACASMAYO | F7: CONSORCIO MINERO HORIZONTE S.R.L. | G7: CORPORACIÓN PESQUERA INCA S.A.C. | H7: CREDITEX: CIA IND.TEXTIL CREDISA | I7: HIPERMERCADOS TOTTUS S.A | J7: INDUSTRIA TEXTIL PIURA | K7: MINERA BOROO MISQUICHILCA S.A. | L7: MINERA GOLD FIELDS | M7: MINERA MARSA | N7: MINERA MISKY MAYO | O7: MINERA YANACOCHA | P7: OPEN PLAZA | Q7: PESQUERA DIAMANTE | R7: PETROPERU | S7: REAL PLAZA S.R.L. | T7: SIDER PERU | U7: SUPERMERCADOS PERUANOS S.A. | V7: TRUPAL S.A. | W7: UNIÓN DE CERVECERÍAS PERUANAS BACKUS Y JOHNSTON S. | X7: ACEROS AREQUIPA | Y7: ADMINISTRADORA JOCKEY PLAZA SHOPPING CENTER S.A. | Z7: ALICORP | AA7: ARCA CONTINENTAL LINDLEY S.A. | AB7: AUSTRAL GROUP S.A.A | AC7: COMPAÑIA MINERA CONDESTABLE | AD7: CORPORACIÓN PESQUERA INCA S.A.C. | AE7: CREDITEX: CIA IND.TEXTIL CREDISA | AF7: FUNDICION CHILCA S.A. | AG7: HIPERMERCADOS TOTTUS S.A | AH7: INMOBILIARIA KANPU S.A. | AI7: INMUEBLES PANAMERICANA S.A. | AJ7: KIMBERLY-CLARK PERU | AK7: LECHE GLORIA S.A. | AL7: MALL AVENTURA S.A. | AM7: MARCOBRE S.A.C. | AN7: MINERA ANTAMINA | AO7: MINERA ARES | AP7: MINERA BUENAVENTURA | AQ7: MINERA CHINALCO PERÚ S.A. | AR7: MINERA SHOUXIN PERU S.A. | AS7: MINERA VOLCAN | AT7: MINSUR | AU7: MOLYCOP-ADESUR | AV7: NEXA RESOURCES CAJAMARQUILLA S.A. | AW7: NEXA RESOURCES PERÚ S.A.A. | AX7: OPEN PLAZA | AY7: OPP FILM | AZ7: OWENS-ILLINOIS PERÚ S.A. | BA7: PAPELERA NACIONAL S.A. | BB7: PESQUERA DIAMANTE | BC7: QUIMPAC S.A. | BD7: REAL PLAZA S.R.L. | BE7: REFINERIA LA PAMPILLA S.A.A | BF7: SAGA FALABELLA | BG7: SAN MIGUEL INDUSTRIAS PET S.A. | BH7: SHOUGANG HIERRO PERU | BI7: SOFTYS PERU S.A.C. | BJ7: SUPERMERCADOS PERUANOS S.A. | BK7: TEJIDOS SAN JACINTO | BL7: TREN URBANO DE LIMA S.A. | BM7: TRUPAL S.A. | BN7: UNACEM PERU S.A. | BO7: UNIÓN DE CERVECERÍAS PERUANAS BACKUS Y JOHNSTON S. | BP7: ANGLO AMERICAN QUELLAVECO S.A. | BQ7: ARCA CONTINENTAL LINDLEY S.A. | BR7: CAL & CEMENTO SUR S.A. | BS7: COMPAÑIA MINERA ANTAPACCAY S.A. | BT7: COMPAÑÍA MINERA CHUNGAR SAC | BU7: COMPAÑIA MINERA SAN IGNACIO DE MOROCOCHA S.A.A. | BV7: EL BROCAL .S.A. | BW7: EMPRESA ADMINISTRADORA CERRO S.A.C. | BX7: EMPRESA MINERA LOS QUENUALES S.A.C. | BY7: HIPERMERCADOS TOTTUS S.A | BZ7: HUDBAY PERU S.A.C. | CA7: INDUSTRIA CACHIMAYO | CB7: MALL AVENTURA S.A. | CC7: MINERA ARES | CD7: MINERA BUENAVENTURA | CE7: MINERA CERRO VERDE | CF7: MINERA CORONA | CG7: MINERA LAS BAMBAS S.A. | CH7: MINERA VOLCAN | CI7: MINSUR | CJ7: MOLYCOP-ADESUR | CK7: NEXA RESOURCES PERÚ S.A.A. | CL7: OXIDOS DE PASCO S.A.C. | CM7: PESQUERA DIAMANTE | CN7: REAL PLAZA S.R.L. | CO7: SOBREANDES S.A.C. | CP7: SOUTHERN PERU CC | CQ7: SUPERMERCADOS PERUANOS S.A. | CR7: UNACEM PERU S.A. | CS7: UNIÓN DE CERVECERÍAS PERUANAS BACKUS Y JOHNSTON S. | CT7: YURA
B8: 00:30 | E8: 35.05768 | F8: 9.474 | L8: 26.922 | M8: 14.59 | N8: 4.42 | O8: 33.922 | R8: 50.829 | T8: 44.9682 | V8: 9.8 | X8: 16.70279 | Z8: 6.14698 | AC8: 15.13 | AJ8: 5.33786 | AM8: 51.77625 | AN8: 118.02619 | AO8: 26.2757 | AP8: 0.81 | AQ8: 164.37 | AS8: 39.73 | AT8: 35.605 | AV8: 196.46834 | AW8: 28.3603 | BA8: 2.7 | BC8: 20.95224 | BE8: 19.2 | BI8: 4.36969 | BK8: 3.93352 | BN8: 30.921 | BP8: 141.71332 | BR8: 4.94256 | BS8: 137.68041 | BT8: 14.13112 | BV8: 35.5864 | BW8: 3.85819 | BZ8: 88.56594 | CA8: 25.008 | CC8: 0.551 | CD8: 25.8911 | CE8: 432.43044 | CG8: 150.55492 | CH8: 17.445 | CL8: 4.83845 | CO8: 17.41887 | CP8: 290.86 | CR8: 34.418 | CT8: 34.269
B9: 01:00 | E9: 36.99493 | F9: 9.8 | L9: 26.6796 | M9: 14.783 | N9: 4.67 | O9: 33.972 | R9: 50.968 | T9: 39.2748 | V9: 9.8 | X9: 16.46055 | Z9: 5.89848 | AC9: 14.97 | AJ9: 5.33431 | AM9: 52.34327 | AN9: 119.05334 | AO9: 26.506 | AP9: 0.7 | AQ9: 164.5 | AS9: 38.737 | AT9: 36.155 | AV9: 197.67245 | AW9: 27.7176 | BA9: 2.5 | BC9: 20.93737 | BE9: 19.2 | BI9: 4.3461 | BK9: 3.81698 | BN9: 32.071 | BP9: 142.65703 | BR9: 4.59777 | BS9: 137.14905 | BT9: 14.71824 | BV9: 35.7916 | BW9: 3.96348 | BZ9: 88.0452 | CA9: 25.016 | CC9: 0.577 | CD9: 25.95295 | CE9: 432.14207 | CG9: 152.75532 | CH9: 17.44 | CL9: 4.85091 | CO9: 16.29886 | CP9: 291.04 | CR9: 34.597 | CT9: 35.176
B10: 01:30 | E10: 38.86981 | F10: 8.644 | L10: 26.3928 | M10: 15.241 | N10: 4.8 | O10: 33.396 | R10: 50.65 | T10: 36.0991 | V10: 9.7 | X10: 16.77221 | Z10: 5.81628 | AC10: 14.21 | AJ10: 5.31128 | AM10: 50.28037 | AN10: 119.09597 | AO10: 27.6402 | AP10: 0.64 | AQ10: 161.57 | AS10: 39.452 | AT10: 35.602 | AV10: 197.74895 | AW10: 27.5801 | BA10: 2.5 | BC10: 20.90918 | BE10: 19.2 | BI10: 4.39155 | BK10: 3.90189 | BN10: 31.508 | BP10: 140.57543 | BR10: 4.70016 | BS10: 135.5918 | BT10: 14.99411 | BV10: 36.6151 | BW10: 4.0073 | BZ10: 88.80811 | CA10: 25.024 | CC10: 0.54 | CD10: 27.96493 | CE10: 434.66737 | CG10: 153.85844 | CH10: 17.902 | CL10: 4.85511 | CO10: 16.4663 | CP10: 289.28 | CR10: 34.614 | CT10: 32.361
B11: 02:00 | E11: 39.26412 | F11: 9.438 | L11: 26.0665 | M11: 15.413 | N11: 4.89 | O11: 33.28 | R11: 50.494 | T11: 46.9425 | V11: 9.7 | X11: 16.68664 | Z11: 6.02502 | AC11: 13.22 | AJ11: 5.27359 | AM11: 51.24501 | AN11: 119.65951 | AO11: 28.4621 | AP11: 0.44 | AQ11: 160.35 | AS11: 38.892 | AT11: 35.52 | AV11: 197.25794 | AW11: 27.9158 | BA11: 2.7 | BC11: 20.84485 | BE11: 19.2 | BI11: 4.53909 | BK11: 3.84495 | BN11: 30.864 | BP11: 139.1653 | BR11: 4.70795 | BS11: 137.74882 | BT11: 13.78439 | BV11: 36.688 | BW11: 3.7307 | BZ11: 88.33678 | CA11: 25.012 | CC11: 0.542 | CD11: 26.22548 | CE11: 434.24215 | CG11: 154.09048 | CH11: 17.68 | CL11: 4.81952 | CO11: 16.09464 | CP11: 284.19 | CR11: 34.239 | CT11: 36.204
B12: 02:30 | E12: 39.302 | F12: 9.791 | L12: 26.1765 | M12: 15.346 | N12: 4.13 | O12: 33.258 | R12: 50.466 | T12: 44.7262 | V12: 9.6 | X12: 16.82076 | Z12: 5.8972 | AC12: 9.76 | AJ12: 5.22184 | AM12: 52.25204 | AN12: 119.69713 | AO12: 28.5236 | AP12: 0.41 | AQ12: 158.53 | AS12: 38.414 | AT12: 35.899 | AV12: 195.2822 | AW12: 28.5988 | BA12: 2.4 | BC12: 20.71567 | BE12: 19.2 | BI12: 4.46645 | BK12: 3.84661 | BN12: 30.892 | BP12: 141.02843 | BR12: 4.75807 | BS12: 137.94574 | BT12: 13.43901 | BV12: 36.9514 | BW12: 3.87202 | BZ12: 87.92013 | CA12: 24.954 | CC12: 0.532 | CD12: 26.22755 | CE12: 432.15736 | CG12: 158.41919 | CH12: 17.788 | CL12: 4.64957 | CO12: 17.06748 | CP12: 282.06 | CR12: 34.492 | CT12: 36.412
B13: 03:00 | E13: 39.29476 | F13: 9.861 | L13: 26.7115 | M13: 15.341 | N13: 4.24 | O13: 33.186 | R13: 50.443 | T13: 45.221 | V13: 9.6 | X13: 16.65716 | Z13: 5.99877 | AC13: 9.3 | AJ13: 4.81592 | AM13: 52.37927 | AN13: 120.99364 | AO13: 27.4279 | AP13: 0.67 | AQ13: 158.65 | AS13: 38.724 | AT13: 35.019 | AV13: 192.36361 | AW13: 30.5124 | BA13: 2.7 | BC13: 20.44618 | BE13: 19.2 | BI13: 4.35431 | BK13: 3.8183 | BN13: 30.767 | BP13: 142.34837 | BR13: 4.86015 | BS13: 135.34802 | BT13: 13.12729 | BV13: 36.0398 | BW13: 3.96593 | BZ13: 86.25255 | CA13: 24.964 | CC13: 0.533 | CD13: 25.6642 | CE13: 437.26128 | CG13: 152.0258 | CH13: 17.549 | CL13: 4.63842 | CO13: 17.80259 | CP13: 292.45 | CR13: 34.383 | CT13: 35.002
B14: 03:30 | E14: 39.39573 | F14: 10.197 | L14: 26.517 | M14: 14.807 | N14: 4.48 | O14: 33.134 | R14: 50.594 | T14: 37.2809 | V14: 9.5 | X14: 17.04969 | Z14: 5.86927 | AC14: 8.07 | AJ14: 5.05719 | AM14: 53.19527 | AN14: 122.18791 | AO14: 27.3853 | AP14: 0.48 | AQ14: 158.61 | AS14: 38.403 | AT14: 33.786 | AV14: 196.69516 | AW14: 31.1299 | BA14: 2.6 | BC14: 20.51173 | BE14: 19.2 | BI14: 4.50655 | BK14: 3.76897 | BN14: 30.771 | BP14: 139.60698 | BR14: 4.87886 | BS14: 137.17003 | BT14: 13.46388 | BV14: 35.6893 | BW14: 4.02736 | BZ14: 87.31435 | CA14: 25.029 | CC14: 0.541 | CD14: 26.77391 | CE14: 437.83278 | CG14: 152.58034 | CH14: 17.419 | CL14: 4.65728 | CO14: 17.59525 | CP14: 279.27 | CR14: 34.152 | CT14: 35.084
B15: 04:00 | E15: 39.79484 | F15: 9.576 | L15: 26.3973 | M15: 14.71 | N15: 4.49 | O15: 33.202 | R15: 50.465 | T15: 39.5823 | V15: 9.5 | X15: 16.85206 | Z15: 5.89628 | AC15: 6.33 | AJ15: 5.19055 | AM15: 53.21999 | AN15: 121.91105 | AO15: 27.1073 | AP15: 0.18 | AQ15: 156.74 | AS15: 37.788 | AT15: 34.098 | AV15: 194.40745 | AW15: 32.7345 | BA15: 2.5 | BC15: 20.627 | BE15: 19.2 | BI15: 4.69633 | BK15: 3.67619 | BN15: 30.706 | BP15: 141.33564 | BR15: 4.88227 | BS15: 136.96648 | BT15: 13.33465 | BV15: 35.8094 | BW15: 3.88656 | BZ15: 88.85436 | CA15: 25.009 | CC15: 0.524 | CD15: 26.28933 | CE15: 437.09204 | CG15: 149.71158 | CH15: 18.133 | CL15: 4.81996 | CO15: 17.88885 | CP15: 283.15 | CR15: 33.778 | CT15: 35.484
B16: 04:30 | E16: 39.79482 | F16: 9.703 | L16: 26.3316 | M16: 15.562 | N16: 4.8 | O16: 32.928 | R16: 50.219 | T16: 38.8956 | V16: 9.4 | X16: 16.94851 | Z16: 5.90848 | AC16: 5.32 | AJ16: 5.28152 | AM16: 53.40483 | AN16: 121.01748 | AO16: 27.2012 | AP16: 1.65 | AQ16: 159.82 | AS16: 37.663 | AT16: 33.203 | AV16: 195.79215 | AW16: 30.9759 | BA16: 2.63 | BC16: 20.4661 | BE16: 19.2 | BI16: 4.5203 | BK16: 3.6725 | BN16: 30.586 | BP16: 140.572 | BR16: 4.85739 | BS16: 137.63434 | BT16: 14.26543 | BV16: 36.45 | BW16: 3.90366 | BZ16: 89.5553 | CA16: 24.938 | CC16: 0.559 | CD16: 27.28062 | CE16: 432.84298 | CG16: 146.18728 | CH16: 18.253 | CL16: 4.83303 | CO16: 16.9578 | CP16: 290.51 | CR16: 34.546 | CT16: 35.774
B17: 05:00 | E17: 39.20811 | F17: 8.427 | L17: 26.2452 | M17: 15.899 | N17: 4.51 | O17: 33.382 | R17: 50.449 | T17: 45.4945 | V17: 9.4 | X17: 16.96454 | Z17: 5.89085 | AC17: 4.93 | AJ17: 5.03627 | AM17: 49.51298 | AN17: 122.28633 | AO17: 26.778 | AP17: 2.1 | AQ17: 159.15 | AS17: 37.077 | AT17: 32.554 | AV17: 193.30902 | AW17: 30.8737 | BA17: 2.5 | BC17: 20.48302 | BE17: 19.2 | BI17: 4.63508 | BK17: 3.63158 | BN17: 30.65 | BP17: 139.85859 | BR17: 4.60201 | BS17: 134.92117 | BT17: 13.40507 | BV17: 34.3868 | BW17: 4.37541 | BZ17: 90.15853 | CA17: 24.92 | CC17: 0.527 | CD17: 25.71726 | CE17: 441.30532 | CG17: 139.97101 | CH17: 18.392 | CL17: 4.81794 | CO17: 17.2987 | CP17: 290.61 | CR17: 40.226 | CT17: 36.566
B18: 05:30 | E18: 38.73156 | F18: 8.299 | L18: 26.8028 | M18: 15.987 | N18: 4.73 | O18: 33.946 | R18: 50.708 | T18: 53.0903 | V18: 9.2 | X18: 16.73083 | Z18: 5.94515 | AC18: 5.05 | AJ18: 5.08865 | AM18: 49.88019 | AN18: 120.44283 | AO18: 26.8226 | AP18: 1.93 | AQ18: 159.49 | AS18: 35.556 | AT18: 33.238 | AV18: 191.48508 | AW18: 29.9217 | BA18: 2.5 | BC18: 20.31086 | BE18: 19.2 | BI18: 4.70902 | BK18: 3.51671 | BN18: 30.637 | BP18: 140.19965 | BR18: 4.54522 | BS18: 134.59892 | BT18: 13.5407 | BV18: 35.4158 | BW18: 3.85894 | BZ18: 89.81625 | CA18: 24.914 | CC18: 0.489 | CD18: 25.66093 | CE18: 437.34361 | CG18: 145.61291 | CH18: 18.36 | CL18: 4.918 | CO18: 15.27484 | CP18: 291.26 | CR18: 39.868 | CT18: 36.694
B19: 06:00 | E19: 39.50944 | F19: 7.015 | L19: 27.645 | M19: 15.521 | N19: 4.78 | O19: 32.758 | R19: 50.703 | T19: 40.9209 | V19: 9 | X19: 16.53287 | Z19: 5.9811 | AC19: 5.38 | AJ19: 5.10208 | AM19: 48.66101 | AN19: 123.14469 | AO19: 22.8031 | AP19: 1.54 | AQ19: 163.02 | AS19: 34.851 | AT19: 33.238 | AV19: 193.57618 | AW19: 29.2103 | BA19: 2.5 | BC19: 20.3338 | BE19: 19.2 | BI19: 4.66293 | BK19: 3.44207 | BN19: 28.4 | BP19: 139.60774 | BR19: 4.54634 | BS19: 134.59679 | BT19: 13.07495 | BV19: 34.2808 | BW19: 3.65085 | BZ19: 90.24565 | CA19: 24.971 | CC19: 0.559 | CD19: 24.83623 | CE19: 429.94931 | CG19: 141.3707 | CH19: 18.102 | CL19: 4.67942 | CO19: 14.41463 | CP19: 289.22 | CR19: 40.318 | CT19: 34.442
... B55: 00:00 | E55: 28.88072 | F55: 10.615 | L55: 26.6791 | M55: 14.383 | N55: 5.49 | O55: 32.962 | R55: 51.019 | T55: 47.7982 | V55: 8.3 | X55: 17.63537 | Z55: 5.83353 | AC55: 5.68 | AJ55: 5.27586 | AM55: 40.93166 | AN55: 125.14945 | AO55: 27.9289 | AP55: 0.83 | AQ55: 161.15 | AS55: 38.312 | AT55: 35.341 | AV55: 120.58605 | AW55: 25.9341 | BA55: 0.9 | BC55: 20.19385 | BE55: 20 | BI55: 4.61053 | BK55: 5.31516 | BN55: 21.606 | BP55: 141.14657 | BR55: 5.04241 | BS55: 138.59068 | BT55: 14.38246 | BV55: 36.4117 | BW55: 3.83695 | BZ55: 88.93837 | CA55: 25.25 | CC55: 0.568 | CD55: 25.93958 | CE55: 392.78054 | CG55: 97.61451 | CH55: 18.278 | CL55: 4.73709 | CO55: 17.08708 | CP55: 271.07 | CR55: 40.171 | CT55: 37.309
B56: MWh | C56: 0 | D56: 0 | E56: 819.4081 | F56: 221.19375 | G56: 0 | H56: 0 | I56: 0 | J56: 0 | K56: 0 | L56: 654.3476 | M56: 332.2055 | N56: 109.48 | O56: 788.971 | P56: 0 | Q56: 0 | R56: 1203.8775 | S56: 0 | T56: 928.40045 | U56: 0 | V56: 212.3 | W56: 0 | X56: 389.6966 | Y56: 0 | Z56: 136.0846 | AA56: 0 | AB56: 0 | AC56: 156.245 | AD56: 0 | AE56: 0 | AF56: 0 | AG56: 0 | AH56: 0 | AI56: 0 | AJ56: 118.96792 | AK56: 0 | AL56: 0 | AM56: 1032.0617 | AN56: 2934.0803 | AO56: 642.70915 | AP56: 18.01 | AQ56: 3882.475 | AR56: 0 | AS56: 870.361 | AT56: 826.802 | AU56: 0 | AV56: 3914.3732 | AW56: 681.9913 | AX56: 0 | AY56: 0 | AZ56: 0 | BA56: 47.165 | BB56: 0 | BC56: 488.38627 | BD56: 0 | BE56: 474.4 | BF56: 0 | BG56: 0 | BH56: 0 | BI56: 106.6748 | BJ56: 0 | BK56: 97.09671 | BL56: 0 | BM56: 0 | BN56: 507.3295 | BO56: 0 | BP56: 3318.414 | BQ56: 0 | BR56: 112.8026 | BS56: 3264.1903 | BT56: 308.47477 | BU56: 0 | BV56: 837.0705 | BW56: 93.053 | BX56: 0 | BY56: 0 | BZ56: 2121.0497 | CA56: 499.672 | CB56: 0 | CC56: 12.88 | CD56: 625.90346 | CE56: 9380.1031 | CF56: 0 | CG56: 2705.5647 | CH56: 425.608 | CI56: 0 | CJ56: 0 | CK56: 0 | CL56: 112.94273 | CM56: 0 | CN56: 0 | CO56: 374.16301 | CP56: 6577.885 | CQ56: 0 | CR56: 885.0025 | CS56: 0 | CT56: 557.5325
B59: Nota :
B60: Información proporcionada por la empresas
C62: DATOS ESTIMADOS
C64: SIN DATOS

Sheet TIPO_RECURSO
B3: miércoles, 4 de Marzo del 2026
B5: REPORTE POTENCIA GENERADA POR TIPO DE RECURSO
B6: HORA | C6: H. PASADA | D6: H. REGULACION | E6: GAS DE CAMISEA | F6: GAS DE MALACAS | G6: GAS DE AGUAYTIA | H6: RESIDUAL | I6: NAFTA+GAS DE REFINERIA | J6: FLEXIGAS+GAS DE REFINERIA | K6: DIÉSEL | L6: BAGAZO | M6: BIOGÁS | N6: SOLAR | O6: EÓLICA | P6: TOTAL | U6: EMPRESA | V6: CENTRAL | W6: HIDROELECTRICA DE PASADA | X6: HIDROELECTRICA DE REGULACION
B7: 00:30 | C7: 1174.4 | D7: 3689.6 | F7: 34.8 | G7: 80.3 | H7: 19.2 | I7: =+DESPACHO_EJECUTADO!FH11+DESPACHO_EJECUTADO!FI11 -> 0 | K7: 1415.8 | L7: 47.3 | M7: 11 | N7: 0 | O7: 165.8 | P7: =+SUM(C7:O7) -> 6638.2 | U7: ANDEAN POWER S.A.C. | V7: C.H.CARHUAC | W7: 435.45
B8: 01:00 | C8: 1182.2 | D8: 3660.9 | F8: 30.7 | G8: 59.9 | H8: 13.5 | I8: =+DESPACHO_EJECUTADO!FH12+DESPACHO_EJECUTADO!FI12 -> 0 | K8: 1417.5 | L8: 46.9 | M8: 11 | N8: 0 | O8: 143.9 | P8: =+SUM(C8:O8) -> 6566.5 | U8: ASOCIACIÓN SANTA LUCIA DE CHACAS | V8: C.H. HUALLIN | W8: 76.8
B9: 01:30 | C9: 1184.5 | D9: 3560.5 | F9: 30.5 | G9: 60.7 | H9: 13.3 | I9: =+DESPACHO_EJECUTADO!FH13+DESPACHO_EJECUTADO!FI13 -> 0 | K9: 1423.4 | L9: 48.9 | M9: 11 | N9: 0 | O9: 155.5 | P9: =+SUM(C9:O9) -> 6488.3 | U9: CELARIS ENERGY S.A. | V9: C.H. MANTA I | W9: 474.35
B10: 02:00 | C10: 1187.2 | D10: 3562.5 | F10: 27.7 | G10: 59 | H10: 13.4 | I10: =+DESPACHO_EJECUTADO!FH14+DESPACHO_EJECUTADO!FI14 -> 0 | K10: 1275.2 | L10: 45.3 | M10: 11 | N10: 0 | O10: 162.2 | P10: =+SUM(C10:O10) -> 6343.5 | U10: CELEPSA | V10: C.H. EL PLATANAL | X10: 4657
B11: 02:30 | C11: 1171.2 | D11: 3569.4 | F11: 30.4 | G11: 60.1 | H11: 13.2 | I11: =+DESPACHO_EJECUTADO!FH15+DESPACHO_EJECUTADO!FI15 -> 0 | K11: 1243.5 | L11: 45.5 | M11: 9.8 | N11: 0 | O11: 141.1 | P11: =+SUM(C11:O11) -> 6284.2 | U11: CELEPSA RENOVABLES S.R.L. | V11: C.H. MARAÑON | W11: 453.6
B12: 03:00 | C12: 1165.6 | D12: 3557.8 | F12: 28.9 | G12: 61.1 | H12: 13.2 | I12: =+DESPACHO_EJECUTADO!FH16+DESPACHO_EJECUTADO!FI16 -> 0 | K12: 1248.4 | L12: 46.3 | M12: 11 | N12: 0 | O12: 133.1 | P12: =+SUM(C12:O12) -> 6265.4 | U12: CHINANGO S.A.C. | V12: C.H. CHIMAY | X12: 3607.9
B13: 03:30 | C13: 1166.4 | D13: 3602.8 | F13: 27.9 | G13: 59.9 | H13: 13.1 | I13: =+DESPACHO_EJECUTADO!FH17+DESPACHO_EJECUTADO!FI17 -> 0 | K13: 1167.6 | L13: 50.2 | M13: 10.9 | N13: 0 | O13: 155.2 | P13: =+SUM(C13:O13) -> 6254 | V13: C.H. YANANGO | W13: 1010.75
B14: 04:00 | C14: 1158.6 | D14: 3573.7 | F14: 29 | G14: 58.4 | H14: 13.4 | I14: =+DESPACHO_EJECUTADO!FH18+DESPACHO_EJECUTADO!FI18 -> 0 | K14: 1152.7 | L14: 48.2 | M14: 10.9 | N14: 0 | O14: 189.2 | P14: =+SUM(C14:O14) -> 6234.1 | U14: EGASA | V14: C.H. CHARCANI III | W14: 152.1
B15: 04:30 | C15: 1173.5 | D15: 3610.5 | F15: 28.3 | G15: 0 | H15: 14.1 | I15: =+DESPACHO_EJECUTADO!FH19+DESPACHO_EJECUTADO!FI19 -> 0 | K15: 1166.9 | L15: 48.9 | M15: 10.9 | N15: 0 | O15: 219.9 | P15: =+SUM(C15:O15) -> 6273 | V15: C.H. CHARCANI V | X15: 2742.85
B16: 05:00 | C16: 1183.1 | D16: 3598 | F16: 27.8 | G16: 0 | H16: 14.7 | I16: =+DESPACHO_EJECUTADO!FH20+DESPACHO_EJECUTADO!FI20 -> 0 | K16: 1164.5 | L16: 49.3 | M16: 10.9 | N16: 0 | O16: 230.4 | P16: =+SUM(C16:O16) -> 6278.7 | U16: EGEJUNIN | V16: C.H. HUASAHUASI I | W16: 475.3
B17: 05:30 | C17: 1170.8 | D17: 3716.8 | F17: 0 | G17: 0 | H17: 14.2 | I17: =+DESPACHO_EJECUTADO!FH21+DESPACHO_EJECUTADO!FI21 -> 0 | K17: 1241.5 | L17: 48.9 | M17: 10.4 | N17: 0 | O17: 241.1 | P17: =+SUM(C17:O17) -> 6443.7 | V17: C.H. RUNATULLO II | W17: 485.15
B18: 06:00 | C18: 1149.3 | D18: 3691 | F18: 20.2 | G18: 0 | H18: 14.2 | I18: =+DESPACHO_EJECUTADO!FH22+DESPACHO_EJECUTADO!FI22 -> 0 | K18: 1244.2 | L18: 49.1 | M18: 10.4 | N18: 15.73 | O18: 251.5 | P18: =+SUM(C18:O18) -> 6445.63 | V18: C.H. RUNATULLO III | W18: 484.65
B19: 06:30 | C19: 1142.8 | D19: 3632.7 | F19: 20.1 | G19: 0 | H19: 13.2 | I19: =+DESPACHO_EJECUTADO!FH23+DESPACHO_EJECUTADO!FI23 -> 0 | K19: 1240.7 | L19: 50.1 | M19: 10.4 | N19: 179.3 | O19: 244.6 | P19: =+SUM(C19:O19) -> 6533.9 | V19: C.H. SANTA CRUZ I | W19: 316.85
B20: 07:00 | C20: 1154.6 | D20: 3415.4 | F20: 18.1 | G20: 0 | H20: 14 | I20: =+DESPACHO_EJECUTADO!FH24+DESPACHO_EJECUTADO!FI24 -> 10 | K20: 1193.8 | L20: 45.7 | M20: 10.6 | N20: 462.6 | O20: 262.5 | P20: =+SUM(C20:O20) -> 6587.3 | U20: EGEMSA | V20: C.H. MACHUPICCHU | W20: 3979.55
B21: 07:30 | C21: 1157.5 | D21: 3555.1 | F21: 13 | G21: 0 | H21: 14.2 | I21: =+DESPACHO_EJECUTADO!FH25+DESPACHO_EJECUTADO!FI25 -> 11.1 | K21: 1039.3 | L21: 41.4 | M21: 10.6 | N21: 770.62 | O21: 206.4 | P21: =+SUM(C21:O21) -> 6819.22 | U21: EGESUR | V21: C.H. ARICOTA I | X21: 240.15
B22: 08:00 | C22: 1155.7 | D22: 3543.9 | F22: 12.8 | G22: 0 | H22: 14.2 | I22: =+DESPACHO_EJECUTADO!FH26+DESPACHO_EJECUTADO!FI26 -> 18.9 | K22: 1038 | L22: 45.7 | M22: 10.5 | N22: 889.97 | O22: 234 | P22: =+SUM(C22:O22) -> 6963.67 | V22: C.H. ARICOTA II | X22: 159.65
B23: 08:30 | C23: 1151.5 | D23: 3628.2 | F23: 13 | G23: 0 | H23: 14.1 | I23: =+DESPACHO_EJECUTADO!FH27+DESPACHO_EJECUTADO!FI27 -> 34.4 | K23: 1163.3 | L23: 45.7 | M23: 9.1 | N23: 1001.87 | O23: 221.4 | P23: =+SUM(C23:O23) -> 7282.57 | U23: ELECTRICA YANAPAMPA SAC | V23: C.H. YANAPAMPA | W23: 67.6
B24: 09:00 | C24: 1162.5 | D24: 3508.1 | F24: 13.4 | G24: 0 | H24: 14.2 | I24: =+DESPACHO_EJECUTADO!FH28+DESPACHO_EJECUTADO!FI28 -> 46.2 | K24: 1463 | L24: 55.8 | M24: 8.8 | N24: 1031.03 | O24: 226.6 | P24: =+SUM(C24:O24) -> 7529.63 | U24: ELECTROPERU | V24: C.H. MANTARO | X24: 15726.2
B25: 09:30 | C25: 1160.1 | D25: 3545.5 | F25: 13 | G25: 0 | H25: 14.2 | I25: =+DESPACHO_EJECUTADO!FH29+DESPACHO_EJECUTADO!FI29 -> 51.6 | K25: 1413 | L25: 55.6 | M25: 8.1 | N25: 1018.77 | O25: 326.2 | P25: =+SUM(C25:O25) -> 7606.07 | V25: C.H. RESTITUCION | W25: 5135.55
B26: 10:00 | C26: 1167 | D26: 3574.2 | F26: 13.2 | G26: 0 | H26: 14.2 | I26: =+DESPACHO_EJECUTADO!FH30+DESPACHO_EJECUTADO!FI30 -> 58.2 | K26: 1490.2 | L26: 60.5 | M26: 7.6 | N26: 1003.98 | O26: 337.5 | P26: =+SUM(C26:O26) -> 7726.58 | U26: EMPRESA DE GENERACION ELECTRICA CANCHAYLLO SAC | V26: C.H. CANCHAYLLO | W26: 120.95
B27: 10:30 | C27: 1177.8 | D27: 3622.8 | F27: 12.7 | G27: 0 | H27: 14.3 | I27: =+DESPACHO_EJECUTADO!FH31+DESPACHO_EJECUTADO!FI31 -> 59.9 | K27: 1445.8 | L27: 56 | M27: 7.7 | N27: 1065.42 | O27: 373.7 | P27: =+SUM(C27:O27) -> 7836.12 | U27: EMPRESA DE GENERACION ELECTRICA SANTA ANA S.A.C. | V27: C.H. RENOVANDES H1 | W27: 489.35
B28: 11:00 | C28: 1181.2 | D28: 3570.7 | F28: 14.7 | G28: 60.4 | H28: 14.3 | I28: =+DESPACHO_EJECUTADO!FH32+DESPACHO_EJECUTADO!FI32 -> 61.1 | K28: 1457.1 | L28: 59.2 | M28: 8.7 | N28: 1064.38 | O28: 422.7 | P28: =+SUM(C28:O28) -> 7914.48 | U28: EMPRESA DE GENERACION HUALLAGA | V28: C.H. CHAGLLA | X28: 9256.2
B29: 11:30 | C29: 1185.8 | D29: 3713.1 | F29: 16.9 | G29: 60.5 | H29: 12.8 | I29: =+DESPACHO_EJECUTADO!FH33+DESPACHO_EJECUTADO!FI33 -> 63.6 | K29: 1416.5 | L29: 60.1 | M29: 9 | N29: 1061.21 | O29: 408.9 | P29: =+SUM(C29:O29) -> 8008.41 | V29: P.C.H. CHAGLLA | W29: 156
B30: 12:00 | C30: 1181.9 | D30: 3655.9 | F30: 17.3 | G30: 60.5 | H30: 12.8 | I30: =+DESPACHO_EJECUTADO!FH34+DESPACHO_EJECUTADO!FI34 -> 68.8 | K30: 1454.6 | L30: 57.4 | M30: 8.9 | N30: 1060.07 | O30: 391.7 | P30: =+SUM(C30:O30) -> 7969.87 | U30: EMPRESA DE GENERACION HUANZA | V30: C.H. HUANZA | X30: 1803.65
B31: 12:30 | C31: 1200.1 | D31: 3593.9 | F31: 17 | G31: 59.6 | H31: 12.2 | I31: =+DESPACHO_EJECUTADO!FH35+DESPACHO_EJECUTADO!FI35 -> 68.7 | K31: 1364 | L31: 57.7 | M31: 8.9 | N31: 1051.13 | O31: 413.6 | P31: =+SUM(C31:O31) -> 7846.83 | U31: EMPRESA ELECTRICA AGUA AZUL | V31: C.H. POTRERO | W31: 296.4
B32: 13:00 | C32: 1227 | D32: 3471.7 | F32: 24.8 | G32: 61.1 | H32: 12.5 | I32: =+DESPACHO_EJECUTADO!FH36+DESPACHO_EJECUTADO!FI36 -> 69.1 | K32: 1301.6 | L32: 59 | M32: 8.8 | N32: 1046 | O32: 570.3 | P32: =+SUM(C32:O32) -> 7851.9 | U32: EMPRESA ELECTRICA RIO DOBLE | V32: C.H. LAS PIZARRAS | W32: 448.4
B33: 13:30 | C33: 1230.9 | D33: 3516.5 | F33: 25 | G33: 61.7 | H33: 12.3 | I33: =+DESPACHO_EJECUTADO!FH37+DESPACHO_EJECUTADO!FI37 -> 69.2 | K33: 1218.4 | L33: 58.4 | M33: 7.7 | N33: 1038.76 | O33: 608 | P33: =+SUM(C33:O33) -> 7846.86 | U33: ENGIE ENERGIA PERU S.A.A. | V33: C.H. QUITARACSA | X33: 458.315
B34: 14:00 | C34: 1227.7 | D34: 3555.8 | F34: 24.6 | G34: 61.2 | H34: 11.9 | I34: =+DESPACHO_EJECUTADO!FH38+DESPACHO_EJECUTADO!FI38 -> 67.1 | K34: 1168.3 | L34: 57.5 | M34: 7.7 | N34: 1050.35 | O34: 619.6 | P34: =+SUM(C34:O34) -> 7851.75 | V34: C.H. YUNCAN | X34: 3150.775
B35: 14:30 | C35: 1225 | D35: 3660.4 | F35: 24.9 | G35: 60.3 | H35: 11.9 | I35: =+DESPACHO_EJECUTADO!FH39+DESPACHO_EJECUTADO!FI39 -> 68.3 | K35: 1161 | L35: 58 | M35: 7.7 | N35: 1049.06 | O35: 651.9 | P35: =+SUM(C35:O35) -> 7978.46 | U35: GENERACIÓN ANDINA S.A.C. | V35: C.H. 8 DE AGOSTO | W35: 504
B36: 15:00 | C36: 1226.2 | D36: 3482 | F36: 25 | G36: 60.8 | H36: 11.6 | I36: =+DESPACHO_EJECUTADO!FH40+DESPACHO_EJECUTADO!FI40 -> 68.2 | K36: 1323.1 | L36: 60 | M36: 7.7 | N36: 1005 | O36: 658.6 | P36: =+SUM(C36:O36) -> 7928.2 | V36: C.H. EL CARMEN | W36: 177.3
B37: 15:30 | C37: 1211.3 | D37: 3658.6 | F37: 24.9 | G37: 59.3 | H37: 10.1 | I37: =+DESPACHO_EJECUTADO!FH41+DESPACHO_EJECUTADO!FI41 -> 67.5 | K37: 1189.2 | L37: 64.6 | M37: 7.9 | N37: 1013.38 | O37: 656.3 | P37: =+SUM(C37:O37) -> 7963.08 | U37: GENERADORA DE ENERGÍA DEL PERÚ | V37: C.H. ÁNGEL I | W37: 489.6
B38: 16:00 | C38: 1219.9 | D38: 3590.3 | F38: 29.9 | G38: 60.6 | H38: 11.2 | I38: =+DESPACHO_EJECUTADO!FH42+DESPACHO_EJECUTADO!FI42 -> 67.9 | K38: 1286.3 | L38: 65.8 | M38: 8 | N38: 956.25 | O38: 672.5 | P38: =+SUM(C38:O38) -> 7968.65 | V38: C.H. ÁNGEL II | W38: 489.6
B39: 16:30 | C39: 1224 | D39: 3586.7 | F39: 30 | G39: 60.3 | H39: 12.1 | I39: =+DESPACHO_EJECUTADO!FH43+DESPACHO_EJECUTADO!FI43 -> 71.4 | K39: 1336.6 | L39: 64 | M39: 8.3 | N39: 846.22 | O39: 670.8 | P39: =+SUM(C39:O39) -> 7910.42 | V39: C.H. ÁNGEL III | W39: 480
B40: 17:00 | C40: 1223.7 | D40: 3635.1 | F40: 31.1 | G40: 82.3 | H40: 11.7 | I40: =+DESPACHO_EJECUTADO!FH44+DESPACHO_EJECUTADO!FI44 -> 71.6 | K40: 1428.6 | L40: 69.2 | M40: 8.3 | N40: 578.85 | O40: 669.8 | P40: =+SUM(C40:O40) -> 7810.25 | V40: C.H. LA JOYA | W40: 176.65
B41: 17:30 | C41: 1221.4 | D41: 3506.3 | F41: 29.3 | G41: 81.8 | H41: 12.5 | I41: =+DESPACHO_EJECUTADO!FH45+DESPACHO_EJECUTADO!FI45 -> 73.1 | K41: 1654.5 | L41: 66.8 | M41: 8.7 | N41: 247.27 | O41: 692.8 | P41: =+SUM(C41:O41) -> 7594.47 | U41: HIDROCAÑETE S.A. | V41: C.H. IMPERIAL | W41: 84.6
B42: 18:00 | C42: 1221.1 | D42: 3463.6 | F42: 30 | G42: 80.8 | H42: 12.7 | I42: =+DESPACHO_EJECUTADO!FH46+DESPACHO_EJECUTADO!FI46 -> 74 | K42: 1787.1 | L42: 65.8 | M42: 8.2 | N42: 22.11 | O42: 683.5 | P42: =+SUM(C42:O42) -> 7448.91 | U42: HIDROELECTRICA HUANCHOR S.A.C. | V42: C.H. HUANCHOR | W42: 445.35
B43: 18:30 | C43: 1228.8 | D43: 3715.7 | F43: 29.9 | G43: 82.1 | H43: 14.3 | I43: =+DESPACHO_EJECUTADO!FH47+DESPACHO_EJECUTADO!FI47 -> 73.7 | K43: 1737.2 | L43: 68.8 | M43: 8 | N43: 4.1 | O43: 627.7 | P43: =+SUM(C43:O43) -> 7590.3 | U43: HUAURA POWER GROUP S.A. | V43: C.H. YARUCAYA | W43: 414.4
B44: 19:00 | C44: 1226.3 | D44: 3822.3 | F44: 81.9 | G44: 81.3 | H44: 14.6 | I44: =+DESPACHO_EJECUTADO!FH48+DESPACHO_EJECUTADO!FI48 -> 73.8 | K44: 1887.1 | L44: 68 | M44: 8 | N44: 0 | O44: 546.5 | P44: =+SUM(C44:O44) -> 7809.8 | U44: HYDRO GLOBAL PERÚ S.A.C. | V44: CH SAN GABAN III | X44: 4860.25
B45: 19:30 | C45: 1196 | D45: 3837.3 | F45: 81.9 | G45: 81.6 | H45: 14.4 | I45: =+DESPACHO_EJECUTADO!FH49+DESPACHO_EJECUTADO!FI49 -> 74.2 | K45: 1968.1 | L45: 69.3 | M45: 8 | N45: 0 | O45: 518.8 | P45: =+SUM(C45:O45) -> 7849.6 | U45: INLAND ENERGY SAC | V45: C.H. SANTA TERESA | W45: 2180.85
B46: 20:00 | C46: 1191.7 | D46: 3824.3 | F46: 112.6 | G46: 81.4 | H46: 14.3 | I46: =+DESPACHO_EJECUTADO!FH50+DESPACHO_EJECUTADO!FI50 -> 74.1 | K46: 1970.1 | L46: 67.9 | M46: 8.2 | N46: 0 | O46: 481 | P46: =+SUM(C46:O46) -> 7825.6 | U46: INVERSIONES SHAQSHA S.A.C. | V46: C.H. PARIAC | W46: 104.05
B47: 20:30 | C47: 1187.2 | D47: 3882.1 | F47: 125.3 | G47: 80.7 | H47: 14 | I47: =+DESPACHO_EJECUTADO!FH51+DESPACHO_EJECUTADO!FI51 -> 74.1 | K47: 1895.1 | L47: 68.3 | M47: 9 | N47: 0 | O47: 430 | P47: =+SUM(C47:O47) -> 7765.8 | U47: KALLPA GENERACION S.A. | V47: C.H. CERRO DEL AGUILA | X47: 12195.25
B48: 21:00 | C48: 1155.6 | D48: 3801.3 | F48: 125.7 | G48: 80.4 | H48: 14.3 | I48: =+DESPACHO_EJECUTADO!FH52+DESPACHO_EJECUTADO!FI52 -> 74.1 | K48: 2029 | L48: 67.8 | M48: 9.3 | N48: 0 | O48: 371.3 | P48: =+SUM(C48:O48) -> 7728.8 | V48: M.C.H. CERRO DEL AGUILA | W48: 245.3
B49: 21:30 | C49: 1166.4 | D49: 3601.61 | F49: 126.3 | G49: 80.9 | H49: 14.6 | I49: =+DESPACHO_EJECUTADO!FH53+DESPACHO_EJECUTADO!FI53 -> 74.2 | K49: 2129.6 | L49: 69.2 | M49: 9.3 | N49: 0 | O49: 364.2166 | P49: =+SUM(C49:O49) -> 7636.3266 | U49: LA VIRGEN | V49: C.H. LA VIRGEN | X49: 1974
B50: 22:00 | C50: 1175.5 | D50: 3518.73 | F50: 125.9 | G50: 81.8 | H50: 14.1 | I50: =+DESPACHO_EJECUTADO!FH54+DESPACHO_EJECUTADO!FI54 -> 74.1 | K50: 1951.67 | L50: 68.4 | M50: 9.3 | N50: 0 | O50: 384.4231 | P50: =+SUM(C50:O50) -> 7403.9231 | U50: MAJA ENERGIA S.A.C. | V50: C.H. RONCADOR | W50: 68.1
B51: 22:30 | C51: 1160.3 | D51: 3529.98 | F51: 125.9 | G51: 81.9 | H51: 13.7 | I51: =+DESPACHO_EJECUTADO!FH55+DESPACHO_EJECUTADO!FI55 -> 74.1 | K51: 1764.26 | L51: 67.6 | M51: 9.5 | N51: 0 | O51: 376.4965 | P51: =+SUM(C51:O51) -> 7203.7365 | U51: ORAZUL ENERGY PERÚ | V51: C.H. CAÑA BRAVA | W51: 134.75
B52: 23:00 | C52: 1153.9 | D52: 3642.66 | F52: 126.5 | G52: 82.5 | H52: 14.2 | I52: =+DESPACHO_EJECUTADO!FH56+DESPACHO_EJECUTADO!FI56 -> 74.2 | K52: 1436.27 | L52: 68.2 | M52: 9.4 | N52: 0 | O52: 357.8584 | P52: =+SUM(C52:O52) -> 6965.6884 | V52: C.H. CAÑON DEL PATO | X52: 5644.15
B53: 23:30 | C53: 1153.5 | D53: 3694.21 | F53: 82.2 | G53: 81.7 | H53: 14.4 | I53: =+DESPACHO_EJECUTADO!FH57+DESPACHO_EJECUTADO!FI57 -> 74 | K53: 1302.62 | L53: 67.2 | M53: 9.4 | N53: 0 | O53: 332.1413 | P53: =+SUM(C53:O53) -> 6811.3713 | V53: C.H. CARHUAQUERO | X53: 2224.05
B54: 00:00 | C54: 1156.4 | D54: 3632.69 | F54: 49.4 | G54: 81.8 | H54: 14.7 | I54: =+DESPACHO_EJECUTADO!FH58+DESPACHO_EJECUTADO!FI58 -> 74.1 | K54: 1237.88 | L54: 67.8 | M54: 9.4 | N54: 0 | O54: 297.4583 | P54: =+SUM(C54:O54) -> 6621.6283 | V54: C.H. CARHUAQUERO IV | W54: 243.7
B55: TOTAL MWh | C55: =SUM(C7:C54)/2 -> 28427.55 | D55: =SUM(D7:D54)/2 -> 86791.44 | E55: =SUM(E7:E54)/2 -> 0 | F55: =SUM(F7:F54)/2 -> 1002.2 | G55: =SUM(G7:G54)/2 -> 1224.35 | H55: =SUM(H7:H54)/2 -> 325.15 | I55: =SUM(I7:I54)/2 -> 1104.3 | J55: =SUM(J7:J54)/2 -> 0 | ... P55: =SUM(P7:P54)/2 -> 174252.7 | U55: ORYGEN PERU S.A.A. | V55: C.H. CALLAHUANCA | X55: 1871.9
B56: % | C56: =+C55/$P$55 -> 0.16313979 | D56: =+D55/$P$55 -> 0.49807802 | E56: =+E55/$P$55 -> 0 | F56: =+F55/$P$55 -> 0.0057514173 | G56: =+G55/$P$55 -> 0.0070262899 | H56: =+H55/$P$55 -> 0.0018659682 | I56: =+I55/$P$55 -> 0.0063373479 | J56: =+J55/$P$55 -> 0 | ... P56: =+P55/$P$55 -> 1 | V56: C.H. HER 1 | W56: 12.75
V57: C.H. HUAMPANI | W57: 677.75
V58: C.H. HUINCO | X58: 5313.9
V59: C.H. MATUCANA | X59: 2893.7
V60: C.H. MOYOPAMPA | W60: 1521.25
U61: SAN GABAN | V61: C.H. SAN GABAN II | X61: 2645.75
V62: PCH TUPURI | W62: 50.55
U63: SINERSA | V63: C.H. CHANCAY | W63: 479.75
V64: C.H. POECHOS II | W64: 152
V65: C.H. RUCUY | W65: 479.75
U66: STATKRAFT S.A | V66: C.H. ARCATA | W66: 91.2
V67: C.H. CAHUA | W67: 299.05
V68: C.H. CHEVES | X68: 3636.65
V69: C.H. GALLITO CIEGO | X69: 694.25
V70: C.H. MALPASO | X70: 1034.9
V71: C.H. YAUPI | W71: 2539.2
U72: TRANSMISION ANDINA DE GENERACION S.A.C. | V72: C.H. OROYA | W72: 124.8
V73: C.H. PACHACHACA | W73: 214.65
U74: VARI ENERGIA S.A.C. | V74: C.H. ANASHIRONI | W74: 487.8
U75: TOTAL MWh | W75: 28427.55 | X75: 86791.44

Sheet GENERACION RER
B3: miércoles, 4 de Marzo del 2026
B5: GENERACIÓN ELÉCTRICA DE LAS CENTRALES RER (MW)
B6: HORA | C6: ACCIONA ENERGIA PERU S.A.C | D6: AGRO INDUSTRIAL PARAMONGA S.A. | E6: AGROAURORA S.A.C. | F6: AGROINDUSTRIAS SAN JACINTO S.A.A. | G6: AGROLMOS SOCIEDAD ANONIMA - AGROLMOS S.A. | H6: ANDEAN POWER S.A.C. | I6: ASOCIACIÓN SANTA LUCIA DE CHACAS | J6: ATRIA ENERGIA S.A.C. | K6: BIOENERGIA DEL CHIRA S.A. | L6: CASA GRANDE S.A.A. | M6: CELARIS ENERGY S.A. | N6: COENERGY S.A.C. | O6: COLCA SOLAR S.A.C. | P6: EGEJUNIN | U6: ELECTRICA YANAPAMPA SAC | V6: EMPRESA DE GENERACION ELECTRICA CANCHAYLLO SAC | W6: EMPRESA DE GENERACION ELECTRICA SANTA ANA S.A.C. | X6: EMPRESA ELECTRICA AGUA AZUL | Y6: EMPRESA ELECTRICA RIO DOBLE | Z6: ENERGÍA EÓLICA S.A. | AB6: ENERGIA RENOVABLE DEL SUR S.A. | AC6: ENERGIA RENOVABLE LA JOYA S.A. | AE6: ENGIE ENERGIA PERU S.A.A. | AI6: GENERACIÓN ANDINA S.A.C. | AK6: GENERADORA DE ENERGÍA DEL PERÚ | AO6: GR CORTARRAMA SOCIEDAD ANONIMA CERRADA | AP6: GR PAINO SOCIEDAD ANONIMA CERRADA | AQ6: GR TARUCA SOCIEDAD ANONIMA CERRADA | AR6: GR VALE S.A.C. | AS6: HIDROCAÑETE S.A. | AT6: HUAURA POWER GROUP S.A. | AU6: HYDRO PATAPO S.A.C. | AV6: JOYA SOLAR S.A.C. | AW6: KALLPA GENERACION S.A. | AY6: KONDU SAC | AZ6: MAJA ENERGIA S.A.C. | BA6: MAJES ARCUS S.A.C. | BC6: MOQUEGUA FV S.A.C. | BD6: ORAZUL ENERGY PERÚ | BF6: ORYGEN PERU S.A.A. | BL6: PANAMERICANA SOLAR SAC. | BM6: PARQUE EOLICO MARCONA S.A.C. | BN6: PARQUE EOLICO TRES HERMANAS S.A.C. | BO6: PETRAMAS | BS6: REPARTICIÓN ARCUS S.A.C. | BT6: SAN GABAN | BU6: SINERSA | BX6: TACNA SOLAR SAC. | BY6: VARI ENERGIA S.A.C. | BZ6: TOTAL RER
C7: C.S. SAN JOSE | D7: C.T. PARAMONGA | E7: C.T. MAPLE | F7: C.T SAN JACINTO | G7: C.T. AGROLMOS | H7: C.H. CARHUAC | I7: C.H. HUALLIN | J7: C.H. PURMACANA | K7: C.T. CAÑA BRAVA | L7: C.T. CASA GRANDE | M7: C.H. MANTA | N7: CS COENERGY | O7: CS YARUCAYA | P7: C.H. HUASAHUASI I | Q7: C.H. HUASAHUASI II | R7: C.H. RUNATULLO II | S7: C.H. RUNATULLO III | T7: C.H. STA CRUZ I y II | U7: C.H. YANAPAMPA | V7: C.H. CANCHAYLLO | W7: C.H. RENOVANDES H1 | X7: C.H. POTRERO | Y7: C.H. LAS PIZARRAS | Z7: C.E. CUPISNIQUE | AA7: C.E. TALARA | AB7: CE SAN JUAN | AC7: C.S. ILLA 1 | AD7: C.S. ILLA 2 | AE7: C.E. P LOM EXPANSION | AF7: C.E. PUNTA LOMITAS | AG7: C.S. INTIPAMPA | AH7: CS EXPANSIÓN INTIPAMPA | AI7: C.H. 8 DE AGOSTO | AJ7: C.H. EL CARMEN | AK7: C.H. ANGEL I | AL7: C.H. ANGEL II | AM7: C.H. ANGEL III | AN7: C.H. LA JOYA | AO7: CS MATARANI | AP7: C.E. HUAMBOS | AQ7: C.E. DUNA | AR7: C.S. LUPI | AS7: C.H. NUEVAIMPERIAL | AT7: C.H. YARUCAYA | AU7: MCH PATAPO | AV7: CS SAN MARTIN SOLAR | AW7: CS SUNNY | AX7: CS SUNNY EXPANSION | AY7: CARHUAQUERO (CS) | AZ7: C.H. RONCADOR | BA7: C.S. MAJES | BB7: C.S. SOL DE VERANO | BC7: C.S. MOQUEGUA FV | BD7: C.H. CANA BRAVA | BE7: C.H. CARHUAQUERO4 | BF7: C.E. WAYRA EXTENSION | BG7: C.E. WAYRA I | BH7: C.H. HER 1 | BI7: C.S. CLEMESI | BJ7: C.S. RUBI | BK7: C.S. Wayra Solar | BL7: C.S. PANAMERICANA-SOLAR | BM7: C.E. MARCONA | BN7: C.E. 3 HERMANAS | BO7: C.T. HUAYCOLORO | BP7: C.T. LA GRINGA V | BQ7: CTB CALLAO | BR7: CTB. DONA CATALINA | BS7: C.S. REPARTICION | BT7: C.H. TUPURI | BU7: C.H. CHANCAY | BV7: C.H. POECHOS2 | BW7: C.H. RUCUY | BX7: C.S. TACNA-SOLAR | BY7: C.H. ANASHIRONI | BZ7: MW
B8: 0:30 | E8: 13.4 | F8: 7.3 | G8: 12 | H8: 20.4 | I8: 3.2 | L8: 14.6 | M8: 20 | P8: 19.8 | R8: 20.3 | S8: 20.2 | T8: 13.2 | U8: 2.8 | V8: 5.1 | W8: 20.1 | X8: 15.1 | Y8: 18.7 | AA8: 1.1 | AB8: 62.1 | AE8: 0.6 | AF8: 46.9 | AI8: 21 | AJ8: 7.7 | AK8: 20.4 | AL8: 20.4 | AM8: 20 | AN8: 7.3 | AS8: 3.5 | AT8: 18.4 | AZ8: 3.2 | BD8: 5.5 | BE8: 9.9 | BH8: 0.3 | BM8: 18.8 | BN8: 36.3 | BO8: 4.8 | BP8: 2.6 | BQ8: 2.4 | BR8: 1.2 | BT8: 2.2 | BU8: 20 | BV8: 6.1 | BW8: 20 | BY8: 20.3 | BZ8: 609.2
B9: 1:00 | E9: 13.2 | F9: 7 | G9: 11.7 | H9: 20.4 | I9: 3.2 | L9: 15 | M9: 19.9 | P9: 19.8 | R9: 20.3 | S9: 20.2 | T9: 13.2 | U9: 2.8 | V9: 5.1 | W9: 20.3 | X9: 15.1 | Y9: 18.7 | AA9: 1.4 | AB9: 63 | AF9: 31.8 | AI9: 21 | AJ9: 7.7 | AK9: 20.4 | AL9: 20.4 | AM9: 20 | AN9: 7.3 | AS9: 3.5 | AT9: 18.4 | AZ9: 3.2 | BD9: 5.6 | BE9: 10 | BH9: 0.3 | BM9: 17.7 | BN9: 30 | BO9: 4.8 | BP9: 2.6 | BQ9: 2.4 | BR9: 1.2 | BT9: 2.2 | BU9: 20 | BV9: 6.2 | BW9: 20 | BY9: 20.4 | BZ9: 587.4
B10: 1:30 | E10: 15 | F10: 7.2 | G10: 12 | H10: 20.4 | I10: 3.2 | L10: 14.7 | M10: 19.8 | P10: 19.8 | R10: 20.3 | S10: 20.2 | T10: 13.2 | U10: 2.7 | V10: 5.1 | W10: 20.4 | X10: 15.1 | Y10: 18.7 | AA10: 0.1 | AB10: 57.9 | AE10: 0.7 | AF10: 46.3 | AI10: 21 | AJ10: 7.6 | AK10: 20.4 | AL10: 20.4 | AM10: 20 | AN10: 7.3 | AS10: 3.6 | AT10: 18.4 | AZ10: 3.2 | BD10: 5.5 | BE10: 9.8 | BH10: 0.3 | BM10: 15.4 | BN10: 35.1 | BO10: 4.8 | BP10: 2.6 | BQ10: 2.4 | BR10: 1.2 | BT10: 2.2 | BU10: 20 | BV10: 6.2 | BW10: 20 | BY10: 20.3 | BZ10: 600.5
B11: 2:00 | E11: 13.1 | F11: 6.5 | G11: 11.7 | H11: 20.4 | I11: 3.2 | L11: 14 | M11: 19.8 | P11: 19.8 | R11: 20.2 | S11: 20.2 | T11: 13.2 | U11: 2.7 | V11: 5.1 | W11: 20.5 | X11: 15.1 | Y11: 18.8 | AA11: 0.2 | AB11: 63.4 | AE11: 0.7 | AF11: 41.8 | AI11: 21 | AJ11: 7.5 | AK11: 20.4 | AL11: 20.4 | AM11: 20 | AN11: 7.3 | AS11: 3.6 | AT11: 17.4 | AZ11: 3.2 | BD11: 5.6 | BE11: 9.8 | BH11: 0.6 | BM11: 14.8 | BN11: 41.3 | BO11: 4.8 | BP11: 2.6 | BQ11: 2.4 | BR11: 1.2 | BT11: 2.2 | BU11: 20 | BV11: 6.2 | BW11: 20 | BY11: 20.3 | BZ11: 603
B12: 2:30 | E12: 13.4 | F12: 6.5 | G12: 12 | H12: 20.4 | I12: 3.2 | L12: 13.6 | M12: 19.6 | P12: 19.8 | R12: 20.2 | S12: 20.2 | T12: 13.2 | U12: 2.9 | V12: 5.1 | W12: 20.3 | X12: 15.1 | Y12: 18.8 | AA12: 0.8 | AB12: 46 | AE12: 0.4 | AF12: 44 | AI12: 21 | AJ12: 7.5 | AK12: 20.4 | AL12: 20.4 | AM12: 20 | AN12: 7.3 | AS12: 3.6 | AT12: 8.5 | AZ12: 3.2 | BD12: 5.6 | BE12: 10 | BH12: 0.6 | BM12: 12.2 | BN12: 37.7 | BO12: 4.6 | BP12: 1.6 | BQ12: 2.4 | BR12: 1.2 | BT12: 2.2 | BU12: 20 | BV12: 6.2 | BW12: 20 | BY12: 20.3 | BZ12: 572
B13: 3:00 | E13: 14.3 | F13: 6.3 | G13: 12 | H13: 20.4 | I13: 3.2 | L13: 13.7 | M13: 19.6 | P13: 19.8 | R13: 20 | S13: 20.2 | T13: 13.2 | U13: 2.8 | V13: 5.1 | W13: 20.3 | X13: 15.1 | Y13: 18.8 | AA13: 0.4 | AB13: 44.2 | AE13: 1.2 | AF13: 42.7 | AI13: 21 | AJ13: 7.5 | AK13: 20.4 | AL13: 20.4 | AM13: 20 | AN13: 7.3 | AS13: 3.6 | AT13: 6 | AZ13: 3.2 | BD13: 5.6 | BE13: 9.9 | BF13: 1.4 | BH13: 0.6 | BM13: 11.9 | BN13: 31.3 | BO13: 4.8 | BP13: 2.6 | BQ13: 2.4 | BR13: 1.2 | BT13: 2.2 | BU13: 20 | BV13: 6.2 | BW13: 20 | BY13: 20.3 | BZ13: 563.1
B14: 3:30 | E14: 14.7 | F14: 7.6 | G14: 11.9 | H14: 20.4 | I14: 3.2 | L14: 16 | M14: 19.5 | P14: 19.8 | R14: 20.1 | S14: 20.2 | T14: 13.2 | U14: 2.7 | V14: 5.1 | W14: 20.4 | X14: 15.1 | Y14: 18.7 | AA14: 1.3 | AB14: 49.5 | AE14: 0.5 | AF14: 40.7 | AI14: 21 | AJ14: 7.4 | AK14: 20.4 | AL14: 20.4 | AM14: 20 | AN14: 7.3 | AS14: 3.6 | AT14: 6 | AZ14: 3.2 | BD14: 5.6 | BE14: 9.9 | BF14: 5.8 | BG14: 15.4 | BH14: 0.6 | BM14: 11.4 | BN14: 30.6 | BO14: 4.8 | BP14: 2.5 | BQ14: 2.4 | BR14: 1.2 | BT14: 2.2 | BU14: 20 | BV14: 6.2 | BW14: 20 | BY14: 20.3 | BZ14: 588.8
B15: 4:00 | E15: 14.7 | F15: 6.5 | G15: 11.5 | H15: 20.4 | I15: 3.2 | L15: 15.5 | M15: 20 | P15: 19.8 | R15: 20.1 | S15: 20.2 | T15: 13.2 | U15: 3 | V15: 5 | W15: 20.1 | X15: 15.1 | Y15: 18.8 | AA15: 1.6 | AB15: 53 | AF15: 47.8 | AI15: 21 | AJ15: 7.4 | AK15: 20.4 | AL15: 20.4 | AM15: 20 | AN15: 7.3 | AS15: 3.6 | AT15: 7.7 | AZ15: 3.2 | BD15: 5.7 | BE15: 10.1 | BF15: 12.5 | BG15: 30.5 | BH15: 0.6 | BM15: 12.8 | BN15: 31 | BO15: 4.8 | BP15: 2.5 | BQ15: 2.4 | BR15: 1.2 | BT15: 2.2 | BU15: 20 | BV15: 6.1 | BW15: 20 | BY15: 20.2 | BZ15: 623.1
B16: 4:30 | E16: 14.7 | F16: 7.2 | G16: 11.1 | H16: 20.4 | I16: 3.2 | L16: 15.9 | M16: 20 | P16: 19.8 | R16: 20 | S16: 20.2 | T16: 13.2 | U16: 3.1 | V16: 5 | W16: 20.5 | X16: 15.1 | Y16: 18.7 | AA16: 0.9 | AB16: 56.6 | AE16: 0.5 | AF16: 55.5 | AI16: 21 | AJ16: 7.4 | AK16: 20.4 | AL16: 20.4 | AM16: 20 | AN16: 7.3 | AS16: 3.6 | AT16: 10 | AZ16: 3.2 | BD16: 5.6 | BE16: 9.8 | BF16: 30.4 | BG16: 33.4 | BH16: 0.6 | BM16: 12.3 | BN16: 30.3 | BO16: 4.8 | BP16: 2.5 | BQ16: 2.4 | BR16: 1.2 | BT16: 2.2 | BU16: 20 | BV16: 6.2 | BW16: 20 | BY16: 20.4 | BZ16: 657
B17: 5:00 | E17: 14.7 | F17: 7.7 | G17: 11 | H17: 20.4 | I17: 3.2 | L17: 15.9 | M17: 20 | P17: 19.8 | R17: 20.1 | S17: 20.2 | T17: 13.2 | U17: 3 | V17: 5.2 | W17: 20.3 | X17: 15.1 | Y17: 18.7 | AA17: 0.1 | AB17: 53.5 | AE17: 1 | AF17: 65.3 | AI17: 21 | AJ17: 7.4 | AK17: 20.4 | AL17: 20.4 | AM17: 20 | AN17: 7.3 | AS17: 3.6 | AT17: 18.4 | AZ17: 3.2 | BD17: 5.5 | BE17: 10 | BF17: 29.4 | BG17: 37.6 | BH17: 0.6 | BM17: 12 | BN17: 31.5 | BO17: 4.8 | BP17: 2.5 | BQ17: 2.4 | BR17: 1.2 | BT17: 2.2 | BU17: 20 | BV17: 6.2 | BW17: 20 | BY17: 20.3 | BZ17: 676.3
B18: 5:30 | E18: 14.7 | F18: 6.5 | G18: 11.1 | H18: 20.4 | I18: 3.2 | L18: 16.6 | M18: 20 | P18: 19.8 | R18: 20 | S18: 20.2 | T18: 13.2 | U18: 3 | V18: 5.2 | W18: 20.3 | X18: 5.1 | Y18: 18.8 | AB18: 64.2 | AE18: 1 | AF18: 73 | AI18: 21 | AJ18: 7.2 | AK18: 20.4 | AL18: 20.4 | AM18: 20 | AN18: 7.3 | AS18: 3.5 | AT18: 18.4 | AZ18: 3.2 | BD18: 5.7 | BE18: 9.8 | BF18: 23.6 | BG18: 28.1 | BH18: 0.6 | BM18: 14.7 | BN18: 36.5 | BO18: 4.8 | BP18: 2.6 | BQ18: 2.4 | BR18: 0.6 | BT18: 2.2 | BU18: 20 | BV18: 6.2 | BW18: 20 | BY18: 20.4 | BZ18: 675.9
B19: 6:00 | E19: 14.6 | F19: 7.2 | G19: 11 | H19: 20.4 | I19: 3.2 | L19: 16.3 | M19: 20 | P19: 19.8 | R19: 20.3 | S19: 20.2 | T19: 13.2 | U19: 3 | V19: 5.1 | W19: 20.6 | X19: 5.1 | Y19: 18.7 | AB19: 72.3 | AE19: 1 | AF19: 85.4 | AG19: 0.4 | AH19: 0.6 | AI19: 21 | AJ19: 7.2 | AK19: 20.4 | AL19: 20.4 | AM19: 20 | AN19: 7.3 | AO19: 0.8 | AS19: 3.5 | AT19: 18.4 | AV19: 4.1 | AW19: 3 | AX19: 1.83 | AZ19: 3.2 | BA19: 0.1 | BC19: 0.1 | BD19: 5.7 | BE19: 9.9 | BF19: 15.1 | BG19: 20.5 | BH19: 0.6 | BI19: 1.9 | BJ19: 2.8 | BM19: 16.4 | BN19: 40.8 | BO19: 4.8 | BP19: 2.6 | BQ19: 2.4 | BR19: 0.6 | BT19: 2.2 | BU19: 20 | BV19: 6.2 | BW19: 20 | BX19: 0.1 | BY19: 20.4 | BZ19: 702.73
B20: 6:30 | E20: 14.5 | F20: 8.2 | G20: 11.6 | H20: 20.4 | I20: 3.2 | L20: 15.8 | M20: 20 | P20: 19.8 | R20: 20.2 | S20: 20.2 | T20: 13.2 | U20: 3 | V20: 5.1 | W20: 20.5 | X20: 5.1 | Y20: 18.7 | AA20: 0.8 | AB20: 74.2 | AE20: 0.4 | AF20: 71.8 | AG20: 7.3 | AH20: 6.4 | AI20: 21 | AJ20: 7.1 | AK20: 20.4 | AL20: 20.4 | AM20: 20 | AN20: 7.6 | AO20: 4.2 | AS20: 3.5 | AT20: 18.5 | AV20: 51.8 | AW20: 32.6 | AX20: 18.6 | AZ20: 3.3 | BA20: 1.2 | BC20: 1.3 | BD20: 5.5 | BE20: 9.9 | BF20: 11.2 | BG20: 18.7 | BH20: 0.6 | BI20: 21.6 | BJ20: 30.8 | BL20: 1.8 | BM20: 18.9 | BN20: 48.6 | BO20: 4.8 | BP20: 2.6 | BQ20: 2.4 | BR20: 0.6 | BS20: 1.1 | BT20: 2.2 | BU20: 20 | BV20: 6.2 | BW20: 20 | BX20: 0.6 | BY20: 20.4 | BZ20: 860.4
B21: 7:00 | E21: 13.3 | F21: 6.2 | G21: 11.2 | H21: 20.4 | I21: 3.2 | L21: 15 | M21: 20 | O21: 0.1 | P21: 19.8 | R21: 20.2 | S21: 20.2 | T21: 13.2 | U21: 3 | V21: 5 | W21: 20.6 | X21: 6.5 | Y21: 18.7 | Z21: 1.4 | AA21: 1.1 | AB21: 91 | AE21: 0.6 | AF21: 71.3 | AG21: 19.4 | AH21: 13.8 | AI21: 21 | AJ21: 7.1 | AK21: 20.4 | AL21: 20.4 | AM21: 20 | AN21: 7.6 | AO21: 10.8 | AS21: 3.5 | AT21: 18.5 | AV21: 137.5 | AW21: 75.6 | AX21: 41.8 | AZ21: 3.3 | BA21: 2.2 | BC21: 8.8 | BD21: 5.5 | BE21: 9.9 | BF21: 6.5 | BG21: 12.2 | BH21: 0.6 | BI21: 59.4 | BJ21: 79 | BL21: 9.8 | BM21: 21.1 | BN21: 57.3 | BO21: 4.8 | BP21: 2.8 | BQ21: 2.4 | BR21: 0.6 | BS21: 3.2 | BT21: 2.2 | BU21: 20 | BV21: 6.3 | BW21: 20 | BX21: 1.2 | BY21: 20.3 | BZ21: 1158.8
B22: 7:30 | E22: 14.1 | F22: 6.4 | G22: 7 | H22: 20.4 | I22: 3.2 | L22: 13.9 | M22: 20 | N22: 0.1 | O22: 0.1 | P22: 19.8 | R22: 20.2 | S22: 20.2 | T22: 13.2 | U22: 3 | V22: 5 | W22: 20.6 | X22: 7 | Y22: 18.7 | Z22: 0.5 | AA22: 1.4 | AB22: 82.4 | AF22: 40.4 | AG22: 21 | AH22: 20 | AI22: 21 | AJ22: 7.3 | AK22: 20.4 | AL22: 20.4 | AM22: 20 | AN22: 7.6 | AO22: 9.4 | AQ22: 0.1 | AS22: 3.5 | AT22: 18.4 | AV22: 215.4 | AW22: 166.5 | AX22: 82.82 | AZ22: 3.3 | BA22: 4.4 | BC22: 12.9 | BD22: 5.6 | BE22: 10 | BF22: 5.2 | BG22: 6.2 | BH22: 0.6 | BI22: 91.7 | BJ22: 122.5 | BL22: 15.6 | BM22: 16.5 | BN22: 53.7 | BO22: 4.8 | BP22: 2.8 | BQ22: 2.4 | BR22: 0.6 | BS22: 5.9 | BT22: 2.2 | BU22: 20 | BV22: 6.3 | BW22: 20 | BX22: 2.3 | BY22: 20.3 | BZ22: 1407.22
B23: 8:00 | D23: 1.9 | E23: 14.1 | F23: 6.9 | G23: 9.9 | H23: 20.4 | I23: 3.2 | L23: 12.9 | M23: 20 | N23: 0.2 | O23: 0.2 | P23: 19.8 | R23: 20.3 | S23: 20.2 | T23: 13.2 | U23: 3 | V23: 5 | W23: 20.6 | X23: 7 | Y23: 18.7 | Z23: 0.1 | AA23: 4.6 | AB23: 77.1 | AE23: 0.7 | AF23: 72.1 | AG23: 35.3 | AH23: 25 | AI23: 21 | AJ23: 7.3 | AK23: 20.4 | AL23: 20.4 | AM23: 20 | AN23: 7.4 | AO23: 21.1 | AP23: 0.4 | AQ23: 1.1 | AS23: 3.5 | AT23: 18.4 | AV23: 237.2 | AW23: 187.5 | AX23: 93.37 | AY23: 0.1 | AZ23: 3.3 | BA23: 8.7 | BC23: 14 | BD23: 5.5 | BE23: 9.9 | BF23: 4.9 | BG23: 5.4 | BH23: 0.6 | BI23: 100.1 | BJ23: 136.7 | BL23: 17 | BM23: 16.9 | BN23: 50.7 | BO23: 4.8 | BP23: 2.7 | BQ23: 2.4 | BR23: 0.6 | BS23: 8.5 | BU23: 20 | BV23: 6.3 | BW23: 20 | BX23: 5 | BY23: 20.4 | BZ23: 1555.97
B24: 8:30 | D24: 2.3 | E24: 12.4 | F24: 6.9 | G24: 11.3 | H24: 20.4 | I24: 3.2 | L24: 12.8 | M24: 20 | N24: 0.2 | O24: 0.3 | P24: 19.8 | R24: 20.2 | S24: 20.2 | T24: 13.2 | U24: 3 | V24: 4.9 | W24: 20.6 | X24: 7 | Y24: 18.7 | AA24: 1.9 | AB24: 85 | AE24: 0.9 | AF24: 75.4 | AG24: 36.2 | AH24: 24.7 | AI24: 21 | AJ24: 7.4 | AK24: 20.4 | AL24: 20.4 | AM24: 20 | AN24: 7.7 | AO24: 78 | AP24: 0.4 | AQ24: 1 | AS24: 3.6 | AT24: 18.4 | AV24: 250 | AW24: 199.9 | AX24: 99.67 | AY24: 0.1 | AZ24: 3.3 | BA24: 11.3 | BC24: 14.8 | BD24: 5.5 | BE24: 9.8 | BF24: 0.1 | BH24: 0.6 | BI24: 104.1 | BJ24: 141.8 | BL24: 18 | BM24: 13 | BN24: 43.7 | BO24: 3.2 | BP24: 2.4 | BQ24: 2.4 | BR24: 1.1 | BS24: 10.9 | BU24: 20 | BV24: 6.4 | BW24: 20 | BX24: 11.9 | BY24: 20.5 | BZ24: 1654.27
B25: 9:00 | D25: 12.5 | E25: 12 | F25: 7.4 | G25: 12 | H25: 20.3 | I25: 3.2 | L25: 11.9 | M25: 20 | N25: 0.3 | O25: 0.5 | P25: 19.8 | R25: 20.3 | S25: 20.2 | T25: 13.2 | U25: 3 | V25: 4.9 | W25: 20.7 | X25: 7 | Y25: 18.7 | AA25: 1.3 | AB25: 102.1 | AE25: 0.6 | AF25: 53.9 | AG25: 36.4 | AH25: 25.4 | AI25: 21 | AJ25: 7.3 | AK25: 20.4 | AL25: 20.4 | AM25: 20 | AN25: 7.5 | AO25: 79.9 | AP25: 0.8 | AQ25: 1.9 | AS25: 3.5 | AT25: 18.4 | AV25: 252.9 | AW25: 203.7 | AX25: 102.13 | AY25: 0.2 | AZ25: 3.3 | BA25: 13.3 | BC25: 15.1 | BD25: 5.7 | BE25: 10 | BH25: 0.6 | BI25: 106.3 | BJ25: 145 | BL25: 18.5 | BM25: 16.2 | BN25: 49.8 | BO25: 3.2 | BP25: 2.2 | BQ25: 2.3 | BR25: 1.1 | BS25: 13.1 | BT25: 2.1 | BU25: 20 | BV25: 6.4 | BW25: 20 | BX25: 18.3 | BY25: 20.4 | BZ25: 1700.53
B26: 9:30 | D26: 14 | E26: 11.1 | F26: 6.8 | G26: 10.9 | H26: 20.3 | I26: 3.2 | L26: 12.8 | M26: 20 | N26: 0.3 | O26: 0.7 | P26: 19.8 | R26: 20.2 | S26: 20.2 | T26: 13.2 | U26: 2.9 | V26: 5.1 | W26: 20.2 | X26: 7 | Y26: 18.7 | AA26: 1.7 | AB26: 107.1 | AE26: 3.6 | AF26: 116.1 | AG26: 33.2 | AH26: 25.1 | AI26: 21 | AJ26: 7.2 | AK26: 20.4 | AL26: 20.4 | AM26: 20 | AN26: 7.9 | AO26: 80.6 | AP26: 4.2 | AQ26: 5 | AS26: 3.6 | AT26: 18.4 | AV26: 245.3 | AW26: 197.6 | AX26: 99.67 | AY26: 0.2 | AZ26: 3.3 | BA26: 15 | BC26: 15.1 | BD26: 5.7 | BE26: 9.8 | BH26: 0.6 | BI26: 107.8 | BJ26: 146.5 | BL26: 18.6 | BM26: 20.6 | BN26: 67.9 | BO26: 2.8 | BP26: 1.9 | BQ26: 2.3 | BR26: 1.1 | BS26: 15.1 | BT26: 2.2 | BU26: 20 | BV26: 6.3 | BW26: 20 | BX26: 18 | BY26: 20.3 | BZ26: 1786.57
B27: 10:00 | D27: 15.2 | E27: 14.2 | F27: 6.8 | G27: 11.3 | H27: 20.3 | I27: 3.2 | L27: 13 | M27: 20 | N27: 0.3 | O27: 0.5 | P27: 19.8 | R27: 20.2 | S27: 20.2 | T27: 13.2 | U27: 3.1 | V27: 5.1 | W27: 20.4 | X27: 7 | Y27: 18.7 | AA27: 2.9 | AB27: 112.5 | AE27: 4.2 | AF27: 115.8 | AG27: 37.4 | AH27: 27 | AI27: 21 | AJ27: 7.2 | AK27: 20.4 | AL27: 20.4 | AM27: 20 | AN27: 7.8 | AO27: 80.3 | AP27: 3.5 | AQ27: 5.7 | AS27: 3.6 | AT27: 18.4 | AV27: 251.7 | AW27: 173.1 | AX27: 94.58 | AY27: 0.2 | AZ27: 3.3 | BA27: 16.4 | BC27: 15.1 | BD27: 5.6 | BE27: 9.9 | BH27: 0.6 | BI27: 108.1 | BJ27: 145.5 | BL27: 18.5 | BM27: 20.3 | BN27: 72.6 | BO27: 2.6 | BP27: 1.8 | BQ27: 2.3 | BR27: 0.9 | BS27: 16.9 | BT27: 2.2 | BU27: 20 | BV27: 6.4 | BW27: 20 | BX27: 18.4 | BY27: 20.3 | BZ27: 1787.88
B28: 10:30 | D28: 15 | E28: 13.6 | F28: 6 | G28: 12 | H28: 20.3 | I28: 3.2 | L28: 9.4 | M28: 20 | N28: 0.4 | O28: 0.5 | P28: 19.8 | R28: 20.2 | S28: 20.2 | T28: 13.2 | U28: 3.1 | V28: 5 | W28: 20.1 | X28: 6.6 | Y28: 18.7 | Z28: 2.4 | AA28: 4.9 | AB28: 113.2 | AE28: 7.6 | AF28: 136.7 | AG28: 38.6 | AH28: 27.3 | AI28: 21 | AJ28: 7.2 | AK28: 20.4 | AL28: 20.4 | AM28: 20 | AN28: 7.8 | AO28: 80.9 | AP28: 5.8 | AQ28: 7.4 | AS28: 3.6 | AT28: 18.4 | AV28: 252.8 | AW28: 214.7 | AX28: 107.62 | AY28: 0.4 | AZ28: 3.3 | BA28: 17.7 | BC28: 15 | BD28: 5.7 | BE28: 9.8 | BH28: 0.6 | BI28: 108.2 | BJ28: 146.1 | BL28: 18.5 | BM28: 19.5 | BN28: 76.2 | BO28: 2.6 | BP28: 1.9 | BQ28: 2.3 | BR28: 0.9 | BS28: 17.5 | BT28: 2.2 | BU28: 20 | BV28: 6.4 | BW28: 20 | BX28: 19.2 | BY28: 20.2 | BZ28: 1880.22
B29: 11:00 | D29: 15.3 | E29: 15 | F29: 6.2 | G29: 12 | H29: 20.4 | I29: 3.2 | L29: 10.7 | M29: 20 | N29: 0.4 | O29: 0.5 | P29: 19.8 | R29: 20.2 | S29: 20.2 | T29: 13.2 | U29: 3 | V29: 5 | W29: 20.4 | X29: 6.6 | Y29: 18.7 | Z29: 3.7 | AA29: 2.4 | AB29: 113.4 | AE29: 13.7 | AF29: 176.4 | AG29: 38.4 | AH29: 27.3 | AI29: 21 | AJ29: 7.2 | AK29: 20.4 | AL29: 20.4 | AM29: 20 | AN29: 7.6 | AO29: 80.9 | AP29: 7.5 | AS29: 3.6 | AT29: 18.4 | AV29: 252.9 | AW29: 213.8 | AX29: 106.48 | AY29: 0.5 | AZ29: 3.3 | BA29: 18.6 | BC29: 14.9 | BD29: 5.4 | BE29: 9.9 | BF29: 3.3 | BG29: 3.6 | BH29: 0.6 | BI29: 108.2 | BJ29: 145.5 | BL29: 18.5 | BM29: 19.8 | BN29: 78.9 | BO29: 3.2 | BP29: 2.1 | BQ29: 2.3 | BR29: 1.1 | BS29: 18.3 | BT29: 2.2 | BU29: 20 | BV29: 6.4 | BW29: 20 | BX29: 19.2 | BY29: 20.3 | BZ29: 1932.38
B30: 11:30 | D30: 16.6 | E30: 14.7 | F30: 6.3 | G30: 11.7 | H30: 20.4 | I30: 3.2 | L30: 10.8 | M30: 20 | N30: 0.4 | O30: 0.3 | P30: 19.8 | R30: 20.2 | S30: 20.2 | T30: 13.2 | U30: 2.3 | V30: 5.1 | W30: 20.5 | X30: 6.5 | Y30: 18.7 | Z30: 2.2 | AA30: 1.2 | AB30: 112.5 | AE30: 17.1 | AF30: 149.9 | AG30: 38.2 | AH30: 27.3 | AI30: 21 | AJ30: 7.2 | AK30: 20.4 | AL30: 20.4 | AM30: 20 | AN30: 7.6 | AO30: 80.1 | AP30: 9.4 | AQ30: 22 | AS30: 3.6 | AT30: 18.4 | AV30: 252.9 | AW30: 214.2 | AX30: 106.21 | AY30: 0.3 | AZ30: 3.3 | BA30: 19 | BC30: 14.8 | BD30: 5.6 | BE30: 9.9 | BG30: 0.6 | BH30: 0.6 | BI30: 107.5 | BJ30: 144 | BL30: 18.3 | BM30: 20.7 | BN30: 73.3 | BO30: 3.2 | BP30: 2.4 | BQ30: 2.3 | BR30: 1.1 | BS30: 18.8 | BT30: 2.2 | BU30: 20 | BV30: 6.4 | BW30: 20 | BX30: 18.9 | BY30: 20.4 | BZ30: 1916.31
B31: 12:00 | D31: 13.9 | E31: 14.6 | F31: 5.9 | G31: 11.6 | H31: 20.4 | I31: 3.2 | L31: 11.4 | M31: 20 | N31: 0.4 | O31: 0.3 | P31: 19.8 | R31: 20.2 | S31: 20.2 | T31: 13.2 | U31: 2.2 | V31: 5 | W31: 20.5 | X31: 6 | Y31: 18.7 | Z31: 1.4 | AA31: 3.9 | AB31: 109 | AE31: 19.2 | AF31: 147.7 | AG31: 37.8 | AH31: 27.1 | AI31: 21 | AJ31: 7.2 | AK31: 20.4 | AL31: 20.4 | AM31: 20 | AN31: 7.6 | AO31: 80.8 | AP31: 7.2 | AQ31: 10.5 | AS31: 3.6 | AT31: 18.4 | AV31: 252.9 | AW31: 214.5 | AX31: 106.67 | AY31: 0.1 | AZ31: 3.3 | BA31: 19.2 | BC31: 14.5 | BD31: 5.6 | BE31: 10.4 | BH31: 0.6 | BI31: 107.2 | BJ31: 142.8 | BL31: 18 | BM31: 19 | BN31: 73.8 | BO31: 3.2 | BP31: 2.3 | BQ31: 2.3 | BR31: 1.1 | BS31: 19.1 | BT31: 2.2 | BU31: 20 | BV31: 6.4 | BW31: 20 | BX31: 18.7 | BY31: 20.3 | BZ31: 1894.87
B32: 12:30 | D32: 15.6 | E32: 14.6 | F32: 7.2 | G32: 11.2 | H32: 20.3 | I32: 3.2 | L32: 9.1 | M32: 20 | N32: 0.4 | O32: 0.2 | P32: 19.8 | R32: 20.2 | S32: 20.2 | T32: 13.2 | U32: 2 | V32: 5 | W32: 20.3 | X32: 6 | Y32: 18.7 | Z32: 0.7 | AA32: 4.4 | AB32: 112.6 | AE32: 18.2 | AF32: 148.7 | AG32: 37.9 | AH32: 27.2 | AI32: 21 | AJ32: 7.2 | AK32: 20.4 | AL32: 20.4 | AM32: 20 | AN32: 7.6 | AO32: 80.7 | AP32: 8.8 | AQ32: 9 | AS32: 3.6 | AT32: 18.4 | AV32: 252.2 | AW32: 213.8 | AX32: 105.93 | AY32: 0.1 | AZ32: 3.3 | BA32: 19.1 | BC32: 14.4 | BD32: 5.7 | BE32: 10.4 | BF32: 16.2 | BH32: 0.6 | BI32: 107.2 | BJ32: 136.7 | BL32: 17.8 | BM32: 20.6 | BN32: 74.4 | BO32: 3.2 | BP32: 2.3 | BQ32: 2.3 | BR32: 1.1 | BS32: 18.9 | BT32: 2.2 | BU32: 20 | BV32: 6.4 | BW32: 20 | BX32: 18.6 | BY32: 20.3 | BZ32: 1907.73
B33: 13:00 | D33: 14.1 | E33: 14.6 | F33: 7.7 | G33: 11.1 | H33: 20.3 | I33: 3.2 | L33: 11.5 | M33: 20 | N33: 0.4 | O33: 0.2 | P33: 19.8 | R33: 20.2 | S33: 20.2 | T33: 13.2 | U33: 2.9 | V33: 5 | W33: 20.5 | X33: 6 | Y33: 18.7 | Z33: 1.5 | AA33: 1.4 | AB33: 109.7 | AE33: 18.8 | AF33: 166.3 | AG33: 38 | AH33: 27.1 | AI33: 21 | AJ33: 7.2 | AK33: 20.4 | AL33: 20.4 | AM33: 20 | AN33: 7.6 | AO33: 80.8 | AP33: 8.1 | AQ33: 8.2 | AS33: 3.5 | AT33: 18.4 | AV33: 251.9 | AW33: 211.9 | AX33: 107 | AY33: 0.1 | AZ33: 3.3 | BA33: 18.8 | BC33: 14.3 | BD33: 5.7 | BE33: 10.3 | BF33: 104 | BG33: 82.6 | BH33: 0.6 | BI33: 92.9 | BJ33: 146.8 | BL33: 17.9 | BM33: 18.9 | BN33: 50.8 | BO33: 3.2 | BP33: 2.2 | BQ33: 2.3 | BR33: 1.1 | BS33: 18.6 | BT33: 2.2 | BU33: 20 | BV33: 6.4 | BW33: 20 | BX33: 19.3 | BY33: 20.3 | BZ33: 2061.4
B34: 13:30 | D34: 15.1 | E34: 13.3 | F34: 6.7 | G34: 10.9 | H34: 20.4 | I34: 3.2 | L34: 12.4 | M34: 20 | N34: 0.4 | O34: 0.2 | P34: 19.8 | R34: 20.3 | S34: 20.2 | T34: 13.2 | U34: 2.9 | V34: 5 | W34: 20.7 | X34: 9 | Y34: 18.7 | Z34: 4.9 | AB34: 107.2 | AE34: 21.4 | AF34: 175.6 | AG34: 37.9 | AH34: 27.2 | AI34: 21 | AJ34: 7.1 | AK34: 20.4 | AL34: 20.4 | AM34: 20 | AN34: 7.6 | AO34: 80.8 | AP34: 6.3 | AQ34: 8 | AS34: 3.5 | AT34: 18.5 | AV34: 253.6 | AW34: 215 | AX34: 108.36 | AY34: 0.1 | AZ34: 1.7 | BA34: 18.2 | BC34: 14.4 | BD34: 5.8 | BE34: 10.4 | BF34: 112.4 | BG34: 104.3 | BH34: 0.6 | BI34: 105.2 | BJ34: 122.5 | BL34: 18.2 | BM34: 20.7 | BN34: 47.2 | BO34: 2.8 | BP34: 1.6 | BQ34: 2.3 | BR34: 1 | BS34: 17.8 | BT34: 2.2 | BU34: 20 | BV34: 6.5 | BW34: 20 | BX34: 18.9 | BY34: 20.4 | BZ34: 2092.36
B35: 14:00 | D35: 14.7 | E35: 12.4 | F35: 6.4 | G35: 11.5 | H35: 20.4 | I35: 3.2 | L35: 12.5 | M35: 20 | N35: 0.4 | O35: 0.1 | P35: 19.8 | R35: 20.2 | S35: 20.2 | T35: 13.2 | U35: 2.7 | V35: 5.1 | W35: 20.5 | X35: 11.3 | Y35: 18.7 | Z35: 7.2 | AB35: 99.5 | AE35: 23 | AF35: 173.6 | AG35: 38.2 | AH35: 27 | AI35: 21 | AJ35: 7.1 | AK35: 20.4 | AL35: 20.4 | AM35: 20 | AN35: 7.6 | AO35: 80.8 | AP35: 0.3 | AQ35: 0.1 | AS35: 3.5 | AT35: 18.5 | AV35: 253.3 | AW35: 213.1 | AX35: 107.95 | AY35: 0.1 | AZ35: 1.7 | BA35: 17 | BC35: 14.3 | BD35: 5.5 | BE35: 10.3 | BF35: 128.6 | BG35: 105 | BH35: 0.6 | BI35: 109.9 | BJ35: 134.8 | BL35: 18.1 | BM35: 18 | BN35: 64.3 | BO35: 2.8 | BP35: 1.6 | BQ35: 2.3 | BR35: 1 | BS35: 16.5 | BT35: 2.2 | BU35: 20 | BV35: 6.4 | BW35: 20 | BX35: 18.8 | BY35: 20.4 | BZ35: 2116.05
B36: 14:30 | D36: 15.6 | E36: 12.8 | F36: 7 | G36: 11.5 | H36: 20.3 | I36: 3.2 | L36: 11.1 | M36: 20 | N36: 0.4 | O36: 0.1 | P36: 19.8 | R36: 20.2 | S36: 20.2 | T36: 13.2 | U36: 3.1 | V36: 5 | W36: 20.4 | X36: 16 | Y36: 18.7 | Z36: 12.1 | AB36: 100 | AE36: 18.2 | AF36: 178.4 | AG36: 38.1 | AH36: 27 | AI36: 21 | AJ36: 7.1 | AK36: 20.4 | AL36: 20.4 | AM36: 20 | AN36: 7.6 | AO36: 80.8 | AP36: 1.9 | AQ36: 1.4 | AS36: 3.5 | AT36: 18.4 | AV36: 254.2 | AW36: 213.4 | AX36: 105.56 | AZ36: 1.7 | BA36: 15.4 | BC36: 14.3 | BD36: 5.8 | BE36: 10.4 | BF36: 143.8 | BG36: 117.9 | BH36: 0.6 | BI36: 105.3 | BJ36: 142.9 | BL36: 17.8 | BM36: 18.6 | BN36: 59.6 | BO36: 2.8 | BP36: 1.6 | BQ36: 2.3 | BR36: 1 | BS36: 15.1 | BT36: 2.2 | BU36: 20 | BV36: 6.4 | BW36: 20 | BX36: 18.7 | BY36: 20.4 | BZ36: 2152.66
B37: 15:00 | D37: 16.1 | E37: 13.6 | F37: 6.3 | G37: 11.7 | H37: 20.3 | I37: 3.2 | L37: 12.3 | M37: 20.1 | N37: 0.3 | O37: 0.1 | P37: 19.8 | R37: 20.2 | S37: 20.2 | T37: 13.2 | U37: 3.1 | V37: 5 | W37: 20.3 | X37: 16 | Y37: 18.7 | Z37: 13.3 | AB37: 98.2 | AE37: 17.6 | AF37: 181 | AG37: 37.7 | AH37: 26.8 | AI37: 21 | AJ37: 7.2 | AK37: 20.4 | AL37: 20.4 | AM37: 20 | AN37: 6.2 | AO37: 80.8 | AP37: 2.2 | AQ37: 1.7 | AS37: 3.5 | AT37: 18.4 | AV37: 223.8 | AW37: 208.7 | AX37: 103.6 | AZ37: 1.7 | BA37: 13.6 | BC37: 14.1 | BD37: 5.7 | BE37: 10.3 | BF37: 144.7 | BG37: 116.8 | BH37: 0.6 | BI37: 104.2 | BJ37: 141 | BL37: 17.8 | BM37: 20.4 | BN37: 62.7 | BO37: 2.7 | BP37: 1.6 | BQ37: 2.3 | BR37: 1.1 | BS37: 13.6 | BT37: 2.2 | BU37: 20 | BV37: 6.4 | BW37: 19.9 | BX37: 18.9 | BY37: 20.3 | BZ37: 2115.6
B38: 15:30 | D38: 16.7 | E38: 14 | F38: 6.5 | G38: 11.7 | H38: 20.4 | I38: 3.2 | L38: 15.7 | M38: 13.2 | N38: 0.3 | O38: 0.1 | P38: 19.8 | R38: 20.2 | S38: 20.2 | T38: 13.2 | U38: 3 | V38: 5.2 | W38: 20.2 | X38: 16 | Y38: 18.7 | Z38: 12.4 | AB38: 100.9 | AE38: 15.5 | AF38: 181.6 | AG38: 37.8 | AH38: 26.6 | AI38: 21 | AJ38: 7.2 | AK38: 20.4 | AL38: 20.4 | AM38: 20 | AN38: 6.9 | AO38: 79 | AP38: 2.4 | AQ38: 1.2 | AS38: 3.5 | AT38: 18.4 | AV38: 252.8 | AW38: 202.6 | AX38: 100.38 | AZ38: 1.7 | BA38: 11.6 | BC38: 13.9 | BD38: 5.5 | BE38: 10.5 | BF38: 144.6 | BG38: 119.5 | BH38: 0.6 | BI38: 102.1 | BJ38: 139.1 | BL38: 17.2 | BM38: 14.5 | BN38: 63.7 | BO38: 2.7 | BP38: 1.8 | BQ38: 2.3 | BR38: 1.1 | BS38: 11.6 | BT38: 2.2 | BU38: 20 | BV38: 6.4 | BW38: 20 | BX38: 18.3 | BY38: 20.3 | BZ38: 2120.48
B39: 16:00 | D39: 17 | E39: 14.1 | F39: 7.2 | G39: 11.7 | H39: 20.4 | I39: 3.2 | L39: 15.8 | M39: 15.6 | N39: 0.2 | O39: 0.1 | P39: 19.8 | R39: 20.1 | S39: 20.1 | T39: 13.3 | U39: 3.1 | V39: 5.1 | W39: 20.3 | X39: 16 | Y39: 18.6 | Z39: 5.6 | AA39: 0.5 | AB39: 106.8 | AE39: 11.8 | AF39: 181.6 | AG39: 28.5 | AH39: 18.2 | AI39: 21 | AJ39: 7.2 | AK39: 20.4 | AL39: 20.4 | AM39: 20 | AN39: 7.1 | AO39: 75.4 | AP39: 2.1 | AQ39: 1.1 | AS39: 3.5 | AT39: 18.4 | AV39: 245.1 | AW39: 193.9 | AX39: 95.85 | AZ39: 1.7 | BA39: 9.1 | BC39: 13.6 | BD39: 5.6 | BE39: 10.5 | BF39: 162.1 | BG39: 114.1 | BH39: 0.6 | BI39: 98.5 | BJ39: 134.6 | BL39: 16.8 | BM39: 23.1 | BN39: 63.7 | BO39: 2.8 | BP39: 1.8 | BQ39: 2.3 | BR39: 1.1 | BS39: 9.2 | BT39: 2.2 | BU39: 20 | BV39: 6.4 | BW39: 20 | BX39: 17.2 | BY39: 20.3 | BZ39: 2083.45
B40: 16:30 | D40: 16.1 | E40: 13.7 | F40: 6.5 | G40: 11.7 | H40: 20.4 | I40: 3.2 | L40: 16 | M40: 20.1 | N40: 0.2 | O40: 0.1 | P40: 19.8 | R40: 20.2 | S40: 20.2 | T40: 13.2 | U40: 3 | V40: 5 | W40: 20.2 | X40: 16 | Y40: 18.6 | Z40: 10.9 | AA40: 0.9 | AB40: 108.1 | AE40: 14.7 | AF40: 174.8 | AG40: 13.4 | AH40: 14.2 | AI40: 21 | AJ40: 7.2 | AK40: 20.4 | AL40: 20.4 | AM40: 20 | AN40: 7.2 | AO40: 65.6 | AP40: 2.3 | AQ40: 1.1 | AS40: 3.5 | AT40: 18.4 | AV40: 225 | AW40: 178.1 | AX40: 87.52 | AZ40: 1.7 | BA40: 6.5 | BC40: 12.6 | BD40: 5.4 | BE40: 10.4 | BF40: 166 | BG40: 118.2 | BH40: 0.6 | BI40: 90.8 | BJ40: 114.7 | BL40: 15.8 | BM40: 25 | BN40: 48.8 | BO40: 3.2 | BP40: 1.8 | BQ40: 2.3 | BR40: 1 | BS40: 6.7 | BT40: 2.2 | BU40: 20 | BV40: 6.4 | BW40: 20 | BX40: 15 | BY40: 20.2 | BZ40: 1974.22
B41: 17:00 | D41: 17 | E41: 14.1 | F41: 8.2 | G41: 12 | H41: 20.4 | I41: 3.2 | L41: 17.9 | M41: 20.3 | N41: 0.1 | O41: 0.1 | P41: 19.8 | R41: 20.2 | S41: 20.2 | T41: 13.2 | U41: 3 | V41: 5 | W41: 20.5 | X41: 16 | Y41: 18.7 | Z41: 11.9 | AA41: 0.1 | AB41: 109.6 | AE41: 12.9 | AF41: 170.9 | AG41: 12.4 | AH41: 12.8 | AI41: 21 | AJ41: 7.2 | AK41: 20.4 | AL41: 20.4 | AM41: 20 | AN41: 7.1 | AO41: 38.4 | AP41: 2.6 | AQ41: 0.9 | AS41: 3.5 | AT41: 18.4 | AV41: 160.9 | AW41: 120.2 | AX41: 57.25 | AZ41: 1.7 | BA41: 3.5 | BC41: 10.9 | BD41: 5.7 | BE41: 10.5 | BF41: 165.8 | BG41: 121.4 | BH41: 0.6 | BI41: 64.9 | BJ41: 71.2 | BL41: 13.7 | BM41: 25.1 | BN41: 48.6 | BO41: 3.2 | BP41: 1.8 | BQ41: 2.3 | BR41: 1 | BS41: 3.9 | BT41: 2.2 | BU41: 20 | BV41: 6.4 | BW41: 20 | BX41: 8.6 | BY41: 20.3 | BZ41: 1712.05
B42: 17:30 | D42: 17.5 | E42: 14.1 | F42: 6.6 | G42: 12 | H42: 20.4 | I42: 3.2 | L42: 16.6 | M42: 20.3 | N42: 0.1 | P42: 19.8 | R42: 20.2 | S42: 20.2 | T42: 13.2 | U42: 2.9 | V42: 5 | W42: 20.6 | X42: 16 | Y42: 18.8 | Z42: 12.5 | AB42: 111.3 | AE42: 10.8 | AF42: 191.4 | AG42: 7 | AH42: 5.8 | AI42: 21 | AJ42: 7.3 | AK42: 20.4 | AL42: 20.4 | AM42: 20 | AN42: 7.3 | AO42: 14.4 | AP42: 3.1 | AQ42: 3.1 | AS42: 3.5 | AT42: 18.4 | AV42: 73 | AW42: 53.1 | AX42: 23.77 | AZ42: 1.7 | BA42: 1.2 | BC42: 5.8 | BD42: 5.7 | BE42: 10.4 | BF42: 160.8 | BG42: 124.4 | BH42: 0.6 | BI42: 25.7 | BJ42: 26.8 | BL42: 7.5 | BM42: 26.8 | BN42: 48.6 | BO42: 3.2 | BP42: 2.2 | BQ42: 2.3 | BR42: 1 | BS42: 1.6 | BT42: 2.2 | BU42: 20 | BV42: 6.3 | BW42: 20 | BX42: 1.5 | BY42: 20.4 | BZ42: 1401.77
B43: 18:00 | D43: 16.8 | E43: 14.1 | F43: 4.9 | G43: 11.5 | H43: 20.4 | I43: 3.2 | L43: 18.5 | M43: 20.3 | P43: 19.8 | R43: 20.1 | S43: 20.1 | T43: 13.2 | U43: 2.9 | V43: 4.9 | W43: 20.3 | X43: 16 | Y43: 18.7 | Z43: 7.9 | AB43: 98.5 | AE43: 17.2 | AF43: 195.8 | AG43: 0.5 | AH43: 0.2 | AI43: 21 | AJ43: 7.5 | AK43: 20.4 | AL43: 20.4 | AM43: 20 | AN43: 7.3 | AO43: 1.2 | AP43: 4.7 | AQ43: 3.4 | AS43: 3.5 | AT43: 18.4 | AV43: 7 | AW43: 3.6 | AX43: 1.51 | AZ43: 1.7 | BA43: 0.2 | BC43: 0.8 | BD43: 5.8 | BE43: 10.4 | BF43: 154.4 | BG43: 123.3 | BH43: 0.6 | BI43: 1.6 | BJ43: 1.3 | BL43: 4.1 | BM43: 23.9 | BN43: 54.4 | BO43: 3.2 | BP43: 1.7 | BQ43: 2.3 | BR43: 1 | BS43: 0.1 | BT43: 2.2 | BU43: 20 | BV43: 6.4 | BW43: 20 | BY43: 20.3 | BZ43: 1165.41
B44: 18:30 | D44: 17.6 | E44: 14 | F44: 6.3 | G44: 12.2 | H44: 17.1 | I44: 3.2 | L44: 18.7 | M44: 20.3 | P44: 19.8 | R44: 20.4 | S44: 20.2 | T44: 13.2 | U44: 2.9 | V44: 4.9 | W44: 20.6 | X44: 16 | Y44: 18.7 | Z44: 4 | AB44: 82.6 | AE44: 16.3 | AF44: 184.9 | AI44: 21 | AJ44: 7.7 | AK44: 20.4 | AL44: 20.4 | AM44: 20 | AN44: 7.2 | AP44: 4.7 | AQ44: 3.2 | AS44: 3.4 | AT44: 18.4 | AZ44: 2.3 | BD44: 5.8 | BE44: 10.4 | BF44: 127.2 | BG44: 119.1 | BH44: 0.6 | BL44: 4.1 | BM44: 22 | BN44: 63.7 | BO44: 3.2 | BP44: 1.7 | BQ44: 2.3 | BR44: 0.8 | BT44: 2.2 | BU44: 20 | BV44: 6.4 | BW44: 20 | BY44: 20.4 | BZ44: 1092.5
B45: 19:00 | D45: 17.4 | E45: 13.6 | F45: 5.9 | G45: 12.3 | H45: 18.3 | I45: 3.2 | L45: 18.8 | M45: 20.3 | P45: 19.8 | R45: 20.2 | S45: 20.2 | T45: 13.2 | U45: 2.9 | V45: 5 | W45: 20.4 | X45: 16 | Y45: 18.7 | Z45: 3.8 | AB45: 68.3 | AE45: 11.2 | AF45: 167.8 | AI45: 21 | AJ45: 7.7 | AK45: 20.4 | AL45: 20.4 | AM45: 20 | AN45: 7.4 | AP45: 3.7 | AQ45: 3.3 | AS45: 3.4 | AT45: 18.4 | AZ45: 2.5 | BD45: 5.6 | BE45: 10.4 | BF45: 115.3 | BG45: 105.9 | BH45: 0.6 | BM45: 17 | BN45: 50.2 | BO45: 3.2 | BP45: 1.7 | BQ45: 2.3 | BR45: 0.8 | BT45: 2.2 | BU45: 20 | BV45: 6.4 | BW45: 20 | BY45: 20.3 | BZ45: 1007.4
B46: 19:30 | D46: 17.7 | E46: 14.1 | F46: 6.5 | G46: 12.2 | H46: 9 | I46: 3.2 | L46: 18.8 | M46: 20.2 | P46: 19.8 | R46: 20.3 | S46: 20.2 | T46: 13.2 | U46: 2.9 | V46: 5 | W46: 20.3 | X46: 16 | Y46: 18.7 | Z46: 0.9 | AB46: 57 | AE46: 10.2 | AF46: 180.8 | AI46: 21 | AJ46: 7.7 | AK46: 20.4 | AL46: 20.4 | AM46: 20 | AN46: 7.4 | AP46: 3.9 | AQ46: 2.6 | AS46: 3.4 | AT46: 18.4 | AZ46: 2.8 | BD46: 5.6 | BE46: 10.3 | BF46: 110.6 | BG46: 94.2 | BH46: 0.6 | BM46: 14.8 | BN46: 43.8 | BO46: 3.2 | BP46: 1.7 | BQ46: 2.3 | BR46: 0.8 | BT46: 2.2 | BU46: 20 | BV46: 6.4 | BW46: 20 | BY46: 20.3 | BZ46: 971.8
B47: 20:00 | D47: 17.1 | E47: 14.1 | F47: 5.7 | G47: 12.2 | I47: 3.2 | L47: 18.8 | M47: 20 | P47: 19.9 | R47: 20.2 | S47: 20.2 | T47: 13.2 | U47: 2.9 | V47: 5 | W47: 20.5 | X47: 16 | Y47: 18.7 | AB47: 53.9 | AE47: 12.9 | AF47: 194.8 | AI47: 21 | AJ47: 7.7 | AK47: 20.4 | AL47: 20.4 | AM47: 20 | AN47: 7.4 | AP47: 3.4 | AQ47: 1.7 | AS47: 3.4 | AT47: 18.4 | AZ47: 3 | BD47: 5.7 | BE47: 10.3 | BF47: 86.6 | BG47: 80.3 | BH47: 0.6 | BM47: 12.2 | BN47: 35.2 | BO47: 3.2 | BP47: 1.9 | BQ47: 2.3 | BR47: 0.8 | BT47: 2.2 | BU47: 20 | BV47: 6.4 | BW47: 20 | BY47: 20.3 | BZ47: 924.1
B48: 20:30 | D48: 16.7 | E48: 14.1 | F48: 6.8 | G48: 12 | I48: 3.2 | L48: 18.7 | M48: 19.4 | P48: 19.8 | R48: 20.3 | S48: 20.2 | T48: 13.2 | U48: 3 | V48: 5 | W48: 20.3 | X48: 16 | Y48: 18.7 | AB48: 41.2 | AE48: 10.7 | AF48: 184.5 | AI48: 21 | AJ48: 7.7 | AK48: 20.4 | AL48: 20.4 | AM48: 20 | AN48: 7.3 | AP48: 1.9 | AQ48: 1.4 | AS48: 3.5 | AT48: 18.4 | AZ48: 3 | BD48: 5.7 | BE48: 10.4 | BF48: 70.9 | BG48: 73.4 | BH48: 0.6 | BM48: 10.2 | BN48: 35.8 | BO48: 3.2 | BP48: 2.5 | BQ48: 2.3 | BR48: 1 | BT48: 2.2 | BU48: 20 | BV48: 6.4 | BW48: 20 | BY48: 20.3 | BZ48: 873.7
B49: 21:00 | D49: 17.3 | E49: 14.1 | F49: 6.3 | G49: 11.8 | I49: 3.2 | L49: 18.3 | M49: 19.1 | P49: 19.8 | R49: 20.3 | S49: 20.2 | T49: 13.2 | U49: 3 | V49: 4.9 | W49: 20.2 | X49: 16 | Y49: 18.6 | AB49: 37.2 | AE49: 9.1 | AF49: 179.4 | AI49: 21 | AJ49: 7.7 | AK49: 20.4 | AL49: 20.4 | AM49: 20 | AN49: 7.3 | AP49: 0.7 | AQ49: 0.2 | AS49: 3.5 | AT49: 18.4 | AZ49: 3 | BD49: 5.6 | BE49: 10.4 | BF49: 44.7 | BG49: 53.4 | BH49: 0.6 | BM49: 8.6 | BN49: 38 | BO49: 3.2 | BP49: 2.7 | BQ49: 2.3 | BR49: 1.1 | BT49: 2.2 | BU49: 20 | BV49: 6.4 | BW49: 20 | BY49: 20.3 | BZ49: 814.1
B50: 21:30 | D50: 17.4 | E50: 14.1 | F50: 7.6 | G50: 11.7 | I50: 3.2 | L50: 18.4 | M50: 20.1 | P50: 19.8 | R50: 20.3 | S50: 20.2 | T50: 13.2 | U50: 2.9 | V50: 4.9 | W50: 20.3 | X50: 16 | Y50: 18.6 | AB50: 37.5 | AE50: 10.3466 | AF50: 188.37 | AI50: 21 | AJ50: 7.6 | AK50: 20.4 | AL50: 20.4 | AM50: 20 | AN50: 7.3 | AQ50: 1 | AS50: 3.5 | AT50: 18.4 | AZ50: 3 | BD50: 5.5 | BE50: 10.4 | BF50: 35.6 | BG50: 45 | BH50: 0.6 | BM50: 10 | BN50: 36.4 | BO50: 3.2 | BP50: 2.7 | BQ50: 2.3 | BR50: 1.1 | BT50: 2.2 | BU50: 20 | BV50: 6.4 | BW50: 20 | BY50: 20.3 | BZ50: 809.2166
B51: 22:00 | D51: 17.3 | E51: 14.1 | F51: 6.7 | G51: 12.2 | H51: 11.4 | I51: 3.2 | L51: 18.1 | M51: 20.2 | P51: 19.8 | R51: 20.3 | S51: 20.2 | T51: 13.2 | U51: 2.7 | V51: 5 | W51: 20.2 | X51: 16 | Y51: 18.5 | Z51: 0.6 | AB51: 43.4 | AE51: 8.8931 | AF51: 206.13 | AI51: 21 | AJ51: 7.7 | AK51: 20.4 | AL51: 20.4 | AM51: 20 | AN51: 7.4 | AQ51: 0.9 | AS51: 3.5 | AT51: 18.4 | AZ51: 3 | BD51: 5.5 | BE51: 10.4 | BF51: 32.9 | BG51: 41.5 | BH51: 0.6 | BM51: 10.7 | BN51: 39.4 | BO51: 3.2 | BP51: 2.7 | BQ51: 2.3 | BR51: 1.1 | BT51: 2.2 | BU51: 19.8 | BV51: 6.4 | BW51: 19.8 | BY51: 20.3 | BZ51: 839.6231
B52: 22:30 | D52: 17.2 | E52: 14.1 | F52: 7.3 | G52: 11.8 | H52: 20.3 | I52: 3.2 | L52: 17.2 | M52: 20.3 | P52: 19.8 | R52: 20.3 | S52: 20.1 | T52: 13.2 | U52: 2.5 | V52: 5.2 | W52: 20 | X52: 16 | Y52: 18.5 | Z52: 1.5 | AA52: 0.3 | AB52: 51 | AE52: 9.4265 | AF52: 178.37 | AI52: 21 | AJ52: 7.7 | AK52: 20.4 | AL52: 20.4 | AM52: 20 | AN52: 7.4 | AS52: 3.5 | AT52: 18.4 | AZ52: 3 | BD52: 5.5 | BE52: 10.4 | BF52: 40.6 | BG52: 39.2 | BM52: 12.5 | BN52: 43.6 | BO52: 3.2 | BP52: 2.9 | BQ52: 2.3 | BR52: 1.1 | BT52: 2.2 | BU52: 19.7 | BV52: 6.4 | BW52: 19.8 | BY52: 20.2 | BZ52: 838.9965
B53: 23:00 | D53: 16.8 | E53: 14.1 | F53: 7.4 | G53: 11.3 | H53: 20.4 | I53: 3.2 | L53: 18.6 | M53: 20.3 | P53: 19.8 | R53: 20.3 | S53: 20.2 | T53: 13.2 | U53: 2.3 | V53: 5.2 | W53: 20.4 | X53: 16 | Y53: 18.5 | Z53: 0.7 | AA53: 0.3 | AB53: 60.1 | AE53: 5.6884 | AF53: 160.57 | AI53: 21 | AJ53: 7.6 | AK53: 20.4 | AL53: 20.4 | AM53: 20 | AN53: 7.3 | AS53: 3.5 | AT53: 18.4 | AZ53: 3 | BD53: 5.7 | BE53: 10.3 | BF53: 31.7 | BG53: 34.6 | BM53: 15.9 | BN53: 48.3 | BO53: 4 | BP53: 2.1 | BQ53: 2.3 | BR53: 1 | BT53: 2.2 | BU53: 20 | BV53: 6.4 | BW53: 20 | BY53: 20.3 | BZ53: 821.7584
B54: 23:30 | D54: 17.2 | E54: 14.1 | F54: 8 | G54: 11.6 | H54: 20.4 | I54: 3.2 | L54: 16.3 | M54: 20.2 | P54: 19.8 | R54: 20.3 | S54: 20.2 | T54: 13.2 | U54: 2 | V54: 5.1 | W54: 20.5 | X54: 16 | Y54: 18.5 | AA54: 0.8 | AB54: 63.7 | AE54: 9.2213 | AF54: 156.42 | AI54: 21 | AJ54: 7.6 | AK54: 20.4 | AL54: 20.4 | AM54: 20 | AN54: 6.3 | AQ54: 0.1 | AS54: 3.5 | AT54: 18.4 | AZ54: 3 | BD54: 5.6 | BE54: 10.3 | BF54: 19.8 | BG54: 27.3 | BM54: 14 | BN54: 40.8 | BO54: 4.8 | BP54: 1.6 | BQ54: 2.3 | BR54: 0.7 | BT54: 2.2 | BU54: 20 | BV54: 6.4 | BW54: 20 | BY54: 20.4 | BZ54: 793.6413
B55: 0:00 | D55: 16.8 | E55: 14.1 | F55: 6 | G55: 12.3 | H55: 20.4 | I55: 3.2 | L55: 18.6 | M55: 20.2 | P55: 19.9 | R55: 20.3 | S55: 20.2 | T55: 13.2 | U55: 1.5 | V55: 5 | W55: 20.4 | X55: 16 | Y55: 18.5 | AA55: 2.2 | AB55: 65 | AE55: 7.6283 | AF55: 135.93 | AI55: 21 | AJ55: 7.5 | AK55: 20.4 | AL55: 20.4 | AM55: 20 | AN55: 7.2 | AS55: 3.5 | AT55: 18.4 | AZ55: 3 | BD55: 5.7 | BE55: 10.5 | BF55: 15.4 | BG55: 18 | BM55: 14.4 | BN55: 38.9 | BO55: 4.8 | BP55: 1.6 | BQ55: 2.3 | BR55: 0.7 | BT55: 2.2 | BU55: 20 | BV55: 6.4 | BW55: 20 | BY55: 20.3 | BZ55: 759.9583
B56: EJEC MWh | C56: 0 | D56: 252.75 | E56: 334.05 | F56: 162.6 | G56: 276.8 | H56: 435.45 | I56: 76.8 | J56: 0 | K56: 0 | L56: 360.45 | M56: 474.35 | N56: 3.1 | O56: 2.65 | P56: 475.3 | Q56: 0 | R56: 485.15 | S56: 484.65 | T56: 316.85 | U56: 67.6 | V56: 120.95 | W56: 489.35 | X56: 296.4 | Y56: 448.4 | Z56: 62.05 | AA56: 23.45 | AB56: 1894.25 | AC56: 0 | AD56: 0 | AE56: 198.9521 | AF56: 3043.195 | AG56: 353.5 | AH56: 258.55 | AI56: 504 | AJ56: 177.3 | AK56: 489.6 | AL56: 489.6 | AM56: 480 | AN56: 176.65 | AO56: 723.25 | AP56: 51.15 | AQ56: 54.15 | AR56: 0 | AS56: 84.6 | AT56: 414.4 | AU56: 0 | AV56: 2555.1 | AW56: 2062.05 | AX56: 1033.065 | AY56: 1.25 | AZ56: 68.1 | BA56: 140.65 | BB56: 0 | BC56: 149.9 | BD56: 134.75 | BE56: 243.7 | BF56: 1242.05 | BG56: 1095.8 | BH56: 12.75 | BI56: 1070.2 | BJ56: 1420.7 | BK56: 0 | BL56: 188.95 | BM56: 405.4 | BN56: 1179.9 | BO56: 89.4 | BP56: 52.75 | BQ56: 56.05 | BR56: 23.75 | BS56: 141 | BT56: 50.55 | BU56: 479.75 | BV56: 152 | BW56: 479.75 | BX56: 162.8 | BY56: 487.8 | BZ56: 30222.212
L70: TERMOELÉCTRICA | M70: 1608.6 | N70: 5.3225753 | O70: #FFA975
L71: HIDROELÉCTRICA | M71: 9096.55 | N71: 30.098889 | O71: #98D2FF
L72: EÓLICA | M72: 9250.3471 | N72: 30.607776 | O72: #B9ACFF
L73: SOLAR | M73: 10266.715 | N73: 33.97076 | O73: #FFD272

Sheet COGENERACIÓN
B3: miércoles, 4 de Marzo del 2026
B5: CENTRALES DE COGENERACIÓN DEL SEIN
B6: HORA | C6: AGRO INDUSTRIAL PARAMONGA S.A. | D6: AGROAURORA S.A.C. | E6: AGROINDUSTRIAS SAN JACINTO S.A.A. | F6: AGROLMOS SOCIEDAD ANONIMA - AGROLMOS S.A. | G6: BIOENERGIA DEL CHIRA S.A. | H6: CASA GRANDE S.A.A. | I6: GM OPERACIONES S.A.C. | J6: TOTAL COGENERACION
C7: C.T. PARAMONGA | D7: C.T. MAPLE | E7: C.T SAN JACINTO | F7: C.T. AGROLMOS | G7: C.T. CAÑA BRAVA | H7: C.T. CASA GRANDE | I7: C.T. REFINERÍA TALARA | J7: MW
B8: 0:30 | D8: 13.4 | E8: 7.3 | F8: 12 | H8: 14.6 | J8: 47.3
B9: 1:00 | D9: 13.2 | E9: 7 | F9: 11.7 | H9: 15 | J9: 46.9
B10: 1:30 | D10: 15 | E10: 7.2 | F10: 12 | H10: 14.7 | J10: 48.9
B11: 2:00 | D11: 13.1 | E11: 6.5 | F11: 11.7 | H11: 14 | J11: 45.3
B12: 2:30 | D12: 13.4 | E12: 6.5 | F12: 12 | H12: 13.6 | J12: 45.5
B13: 3:00 | D13: 14.3 | E13: 6.3 | F13: 12 | H13: 13.7 | J13: 46.3
B14: 3:30 | D14: 14.7 | E14: 7.6 | F14: 11.9 | H14: 16 | J14: 50.2
B15: 4:00 | D15: 14.7 | E15: 6.5 | F15: 11.5 | H15: 15.5 | J15: 48.2
B16: 4:30 | D16: 14.7 | E16: 7.2 | F16: 11.1 | H16: 15.9 | J16: 48.9
B17: 5:00 | D17: 14.7 | E17: 7.7 | F17: 11 | H17: 15.9 | J17: 49.3
B18: 5:30 | D18: 14.7 | E18: 6.5 | F18: 11.1 | H18: 16.6 | J18: 48.9
B19: 6:00 | D19: 14.6 | E19: 7.2 | F19: 11 | H19: 16.3 | J19: 49.1
B20: 6:30 | D20: 14.5 | E20: 8.2 | F20: 11.6 | H20: 15.8 | J20: 50.1
B21: 7:00 | D21: 13.3 | E21: 6.2 | F21: 11.2 | H21: 15 | I21: 10 | J21: 55.7
B22: 7:30 | D22: 14.1 | E22: 6.4 | F22: 7 | H22: 13.9 | I22: 11.1 | J22: 52.5
B23: 8:00 | C23: 1.9 | D23: 14.1 | E23: 6.9 | F23: 9.9 | H23: 12.9 | I23: 18.9 | J23: 64.6
B24: 8:30 | C24: 2.3 | D24: 12.4 | E24: 6.9 | F24: 11.3 | H24: 12.8 | I24: 34.4 | J24: 80.1
B25: 9:00 | C25: 12.5 | D25: 12 | E25: 7.4 | F25: 12 | H25: 11.9 | I25: 46.2 | J25: 102
B26: 9:30 | C26: 14 | D26: 11.1 | E26: 6.8 | F26: 10.9 | H26: 12.8 | I26: 51.6 | J26: 107.2
B27: 10:00 | C27: 15.2 | D27: 14.2 | E27: 6.8 | F27: 11.3 | H27: 13 | I27: 58.2 | J27: 118.7
B28: 10:30 | C28: 15 | D28: 13.6 | E28: 6 | F28: 12 | H28: 9.4 | I28: 59.9 | J28: 115.9
B29: 11:00 | C29: 15.3 | D29: 15 | E29: 6.2 | F29: 12 | H29: 10.7 | I29: 61.1 | J29: 120.3
B30: 11:30 | C30: 16.6 | D30: 14.7 | E30: 6.3 | F30: 11.7 | H30: 10.8 | I30: 63.6 | J30: 123.7
B31: 12:00 | C31: 13.9 | D31: 14.6 | E31: 5.9 | F31: 11.6 | H31: 11.4 | I31: 68.8 | J31: 126.2
B32: 12:30 | C32: 15.6 | D32: 14.6 | E32: 7.2 | F32: 11.2 | H32: 9.1 | I32: 68.7 | J32: 126.4
B33: 13:00 | C33: 14.1 | D33: 14.6 | E33: 7.7 | F33: 11.1 | H33: 11.5 | I33: 69.1 | J33: 128.1
B34: 13:30 | C34: 15.1 | D34: 13.3 | E34: 6.7 | F34: 10.9 | H34: 12.4 | I34: 69.2 | J34: 127.6
... B55: 0:00 | C55: 16.8 | D55: 14.1 | E55: 6 | F55: 12.3 | H55: 18.6 | I55: 74.1 | J55: 141.9
B56: EJEC MWh | C56: 252.75 | D56: 334.05 | E56: 162.6 | F56: 276.8 | G56: 0 | H56: 360.45 | I56: 1104.3 | J56: 2490.95

Sheet EVO_PRO_ENE
B3: domingo, 1 de Marzo del 2026 - miércoles, 4 de Marzo del 2026
B5: EVOLUCIÓN DE LA PRODUCCIÓN DE LA ENERGÍA DIARIA DE LOS INTEGRANTES DEL COES (MWh)
B6: EMPRESA | C6: CENTRAL | D6: UNIDAD | E6: TIPO | F6: Marzo
F7: 1 | G7: 2 | H7: 3 | I7: 4 | J7: TOTAL
B8: AGRO INDUSTRIAL PARAMONGA S.A. | C8: C.T. PARAMONGA | D8: TV-01 | E8: TERMOELÉCTRICA | F8: 394.35 | I8: 252.75 | J8: 647.1
B9: AGROAURORA S.A.C. | C9: C.T. MAPLE ETANOL | D9: TV | E9: TERMOELÉCTRICA | F9: 335.2 | G9: 306.05 | H9: 339.8 | I9: 334.05 | J9: 1315.1
B10: AGROINDUSTRIAS SAN JACINTO S.A.A. | C10: C.T. SAN JACINTO | D10: CENTRAL | E10: TERMOELÉCTRICA | F10: 83.15 | H10: 45.9 | I10: 162.6 | J10: 291.65
B11: AGROLMOS SOCIEDAD ANONIMA - AGROLMOS S.A. | C11: C.T. AGROLMOS | D11: CENTRAL | E11: TERMOELÉCTRICA | F11: 255.15 | G11: 262.2 | H11: 274.8 | I11: 276.8 | J11: 1068.95
B12: ANDEAN POWER S.A.C. | C12: C.H.CARHUAC | D12: CENTRAL | E12: HIDROELÉCTRICA | F12: 460.15 | G12: 402.15 | H12: 487.65 | I12: 435.45 | J12: 1785.4
B13: ASOCIACIÓN SANTA LUCIA DE CHACAS | C13: C.H. HUALLIN | D13: CENTRAL | E13: HIDROELÉCTRICA | F13: 76.8 | G13: 75.92 | H13: 75.55 | I13: 76.8 | J13: 305.07
B14: ATRIA ENERGIA S.A.C. | C14: C.H. PURMACANA | D14: CENTRAL | E14: HIDROELÉCTRICA | J14: 0
B15: BIOENERGIA DEL CHIRA S.A. | C15: C.T. CAÑA BRAVA | D15: CENTRAL | E15: TERMOELÉCTRICA | J15: 0
B16: CASA GRANDE S.A.A. | C16: C.T. CASA GRANDE | D16: TV3 | E16: TERMOELÉCTRICA | F16: 443.6 | G16: 406.1 | H16: 401.665 | I16: 360.45 | J16: 1611.815
B17: CELARIS ENERGY S.A. | C17: C.H. MANTA I | D17: CENTRAL | E17: HIDROELÉCTRICA | F17: 447.9 | G17: 382.7 | H17: 473 | I17: 474.35 | J17: 1777.95
B18: CELEPSA | C18: C.H. EL PLATANAL | D18: CENTRAL | E18: HIDROELÉCTRICA | F18: 4638.2 | G18: 4391.55 | H18: 4518.3 | I18: 4657 | J18: 18205.05
B19: CELEPSA RENOVABLES S.R.L. | C19: C.H. MARAÑON | D19: CENTRAL | E19: HIDROELÉCTRICA | F19: 452.096 | G19: 453.6 | H19: 453.6 | I19: 453.6 | J19: 1812.896
B20: CENTRALES SANTA ROSA S.A.C. | C20: C.H. SANTA ROSA I | D20: CENTRAL | E20: HIDROELÉCTRICA | J20: 0
B21: CENTRALES SANTA ROSA S.A.C. | C21: C.H. SANTA ROSA II | D21: CENTRAL | E21: HIDROELÉCTRICA | J21: 0
B22: CHINANGO S.A.C. | C22: C.H. CHIMAY | D22: CENTRAL | E22: HIDROELÉCTRICA | F22: 3522.65 | G22: 3509.6 | H22: 3449.55 | I22: 3607.9 | J22: 14089.7
B23: CHINANGO S.A.C. | C23: C.H. YANANGO | D23: CENTRAL | E23: HIDROELÉCTRICA | F23: 1000.65 | G23: 1009.75 | H23: 1010.35 | I23: 1010.75 | J23: 4031.5
B24: COENERGY S.A.C. | C24: C.S. COENERGY | D24: CENTRAL | E24: SOLAR | F24: 2.9 | G24: 2.65 | H24: 3.25 | I24: 3.1 | J24: 11.9
B25: COLCA SOLAR S.A.C. | C25: C.S. YARUCAYA | D25: CENTRAL | E25: SOLAR | F25: 8.7 | G25: 8.45 | H25: 4.65 | I25: 2.65 | J25: 24.45
B26: EGASA | C26: C.H. CHARCANI III | D26: CENTRAL | E26: HIDROELÉCTRICA | F26: 139 | G26: 137.45 | H26: 147.3 | I26: 152.1 | J26: 575.85
B27: EGASA | C27: C.H. CHARCANI IV | D27: CENTRAL | E27: HIDROELÉCTRICA | J27: 0
B28: EGASA | C28: C.H. CHARCANI V | D28: CENTRAL | E28: HIDROELÉCTRICA | F28: 3412.75 | G28: 3419 | H28: 2782.3 | I28: 2742.85 | J28: 12356.9
B29: EGASA | C29: C.H. CHARCANI VI | D29: CENTRAL | E29: HIDROELÉCTRICA | J29: 0
B30: EGASA | C30: C.T. CHILINA DIESEL | D30: CENTRAL | E30: TERMOELÉCTRICA | F30: 31.35 | G30: 145.45 | H30: 45.5 | J30: 222.3
B31: EGASA | C31: C.T. CHILINA DIESEL | D31: TG | E31: TERMOELÉCTRICA | F31: 48.7 | G31: 165.65 | H31: 55.35 | J31: 269.7
B32: EGASA | C32: C.T. MOLLENDO DIESEL | D32: CENTRAL | E32: TERMOELÉCTRICA | F32: 91.65 | G32: 284.25 | H32: 133.4 | J32: 509.3
B33: EGEJUNIN | C33: C.H. HUASAHUASI I | D33: CENTRAL | E33: HIDROELÉCTRICA | F33: 475.4 | G33: 475.2 | H33: 475.25 | I33: 475.3 | J33: 1901.15
B34: EGEJUNIN | C34: C.H. RUNATULLO II | D34: CENTRAL | E34: HIDROELÉCTRICA | F34: 479.17445 | G34: 480.9 | H34: 484.5 | I34: 485.15 | J34: 1929.7244
B35: EGEJUNIN | C35: C.H. RUNATULLO III | D35: CENTRAL | E35: HIDROELÉCTRICA | F35: 477.74955 | G35: 484.5 | H35: 484.7 | I35: 484.65 | J35: 1931.5995
B36: EGEJUNIN | C36: C.H. SANTA CRUZ I | D36: CENTRAL | E36: HIDROELÉCTRICA | F36: 314.91645 | G36: 313 | H36: 316.8 | I36: 316.85 | J36: 1261.5665
B37: EGEMSA | C37: C.H. MACHUPICCHU | D37: CENTRAL | E37: HIDROELÉCTRICA | F37: 3883.75 | G37: 3985.6 | H37: 3974.7 | I37: 3979.55 | J37: 15823.6
B38: EGESUR | C38: C.H. ARICOTA I | D38: CENTRAL | E38: HIDROELÉCTRICA | F38: 194.3 | G38: 204.8 | H38: 236.6 | I38: 240.15 | J38: 875.85
B39: EGESUR | C39: C.H. ARICOTA II | D39: CENTRAL | E39: HIDROELÉCTRICA | F39: 130.65 | G39: 136.55 | H39: 158.55 | I39: 159.65 | J39: 585.4
B40: EGESUR | C40: C.T. INDEPENDENCIA | D40: CENTRAL | E40: TERMOELÉCTRICA | F40: 54.4 | J40: 54.4
B41: ELECTRICA YANAPAMPA SAC | C41: C.H. YANAPAMPA | D41: CENTRAL | E41: HIDROELÉCTRICA | F41: 75.75 | G41: 57 | H41: 63.45 | I41: 67.6 | J41: 263.8
B42: ELECTROPERU | C42: C.H. MANTARO | D42: CENTRAL | E42: HIDROELÉCTRICA | F42: 2566.9 | G42: 14892.065 | H42: 15452.85 | I42: 15726.2 | J42: 48638.015
B43: ELECTROPERU | C43: C.H. RESTITUCION | D43: CENTRAL | E43: HIDROELÉCTRICA | F43: 700.6 | G43: 4978.885 | H43: 5119.5 | I43: 5135.55 | J43: 15934.535
B44: ELECTROPERU | C44: C.T. TUMBES | D44: MAK1 | E44: TERMOELÉCTRICA | F44: 89.8 | G44: 116.35 | H44: 178.65 | I44: 183.55 | J44: 568.35
B45: ELECTROPERU | C45: C.T. TUMBES | D45: MAK2 | E45: TERMOELÉCTRICA | F45: 92.8 | G45: 116.1 | H45: 180.15 | I45: 183.8 | J45: 572.85
B46: EMPRESA DE GENERACION ELECTRICA CANCHAYLLO SAC | C46: C.H. CANCHAYLLO | D46: CENTRAL | E46: HIDROELÉCTRICA | F46: 37.7 | G46: 113.95 | H46: 120.55 | I46: 120.95 | J46: 393.15
B47: EMPRESA DE GENERACION ELECTRICA SANTA ANA S.A.C. | C47: C.H. RENOVANDES H1 | D47: CENTRAL | E47: HIDROELÉCTRICA | F47: 488 | G47: 488.6 | H47: 487.45 | I47: 489.35 | J47: 1953.4
B48: EMPRESA DE GENERACION HUALLAGA | C48: C.H. CHAGLLA | D48: CENTRAL | E48: HIDROELÉCTRICA | F48: 10655.8 | G48: 9722.05 | H48: 8821.05 | I48: 9256.2 | J48: 38455.1
B49: EMPRESA DE GENERACION HUALLAGA | C49: P.C.H. CHAGLLA | D49: CENTRAL | E49: HIDROELÉCTRICA | F49: 45.6 | G49: 156 | H49: 156 | I49: 156 | J49: 513.6
B50: EMPRESA DE GENERACION HUANZA | C50: C.H. HUANZA | D50: CENTRAL | E50: HIDROELÉCTRICA | F50: 2215.95 | G50: 1485.5 | H50: 1808.05 | I50: 1803.65 | J50: 7313.15
B51: EMPRESA ELECTRICA AGUA AZUL | C51: C.H. POTRERO | D51: CENTRAL | E51: HIDROELÉCTRICA | F51: 479.8 | G51: 479.2 | H51: 309.75 | I51: 296.4 | J51: 1565.15
B52: EMPRESA ELECTRICA RIO DOBLE | C52: C.H. LAS PIZARRAS | D52: CENTRAL | E52: HIDROELÉCTRICA | F52: 453.95 | G52: 454.05 | H52: 451.95 | I52: 448.4 | J52: 1808.35
B53: ENEL GENERACION PIURA S.A. | C53: C.T. MALACAS 1 | D53: TG6 | E53: TERMOELÉCTRICA | F53: 442.25 | H53: 211.85 | I53: 282.85 | J53: 936.95
B54: ENEL GENERACION PIURA S.A. | C54: C.T. MALACAS 2 | D54: TG4 | E54: TERMOELÉCTRICA | F54: 804.65 | G54: 576.8 | H54: 688.55 | I54: 719.35 | J54: 2789.35
B55: ENEL GENERACION PIURA S.A. | C55: C.T. RF DE GENERACION TALARA | D55: TG5 | E55: TERMOELÉCTRICA | J55: 0
B56: ENERGÍA EÓLICA S.A. | C56: C.E. CUPISNIQUE | D56: CENTRAL | E56: EÓLICA | F56: 470.95 | G56: 460.15 | H56: 384.6 | I56: 62.05 | J56: 1377.75
B57: ENERGÍA EÓLICA S.A. | C57: C.E. TALARA | D57: CENTRAL | E57: EÓLICA | F57: 87.9 | G57: 84.3 | H57: 59.25 | I57: 23.45 | J57: 254.9
B58: ENERGIA RENOVABLE DEL SUR S.A. | C58: C.E. SAN JUAN | D58: CENTRAL | E58: EÓLICA | F58: 2138.95 | G58: 1788.1 | H58: 2208.7 | I58: 1894.25 | J58: 8030
B59: ENGIE ENERGIA PERU S.A.A. | C59: C.E. PUNTA LOMITAS | D59: PL-BL1 | E59: EÓLICA | F59: 1146.1 | G59: 739.1 | H59: 1539.8 | I59: 1254.365 | J59: 4679.365
B60: ENGIE ENERGIA PERU S.A.A. | C60: C.E. PUNTA LOMITAS | D60: PL-BL2 | E60: EÓLICA | F60: 1793.65 | G60: 1372.8 | H60: 2299.25 | I60: 1788.83 | J60: 7254.53
B61: ENGIE ENERGIA PERU S.A.A. | C61: C.E. PUNTA LOMITAS_EXP | D61: PUN LOM_EXP-BL1 | E61: EÓLICA | F61: 154.65 | G61: 146.2 | H61: 196.1 | I61: 109.6793 | J61: 606.6293
B62: ENGIE ENERGIA PERU S.A.A. | C62: C.E. PUNTA LOMITAS_EXP | D62: PUN LOM_EXP-BL2 | E62: EÓLICA | F62: 117.15 | G62: 48.8 | H62: 151.55 | I62: 89.2728 | J62: 406.7728
B63: ENGIE ENERGIA PERU S.A.A. | C63: C.H. QUITARACSA | D63: CENTRAL | E63: HIDROELÉCTRICA | F63: 498.25 | G63: 475.85 | H63: 400.3 | I63: 458.315 | J63: 1832.715
B64: ENGIE ENERGIA PERU S.A.A. | C64: C.H. YUNCAN | D64: CENTRAL | E64: HIDROELÉCTRICA | F64: 2707.2 | G64: 2772.7 | H64: 3141.45 | I64: 3150.775 | J64: 11772.125
B65: ENGIE ENERGIA PERU S.A.A. | C65: C.S. EXPANSIÓN INTIPAMPA | D65: CENTRAL | E65: SOLAR | F65: 267.95 | G65: 270.4 | H65: 271.6 | I65: 258.55 | J65: 1068.5
B66: ENGIE ENERGIA PERU S.A.A. | C66: C.S. INTIPAMPA | D66: CENTRAL | E66: SOLAR | F66: 371.45 | G66: 376.3 | H66: 376.25 | I66: 353.5 | J66: 1477.5
B67: ENGIE ENERGIA PERU S.A.A. | C67: C.T. CHILCA 1 | D67: TG1 | E67: TERMOELÉCTRICA | F67: 810.65 | J67: 810.65
B68: ENGIE ENERGIA PERU S.A.A. | C68: C.T. CHILCA 1 | D68: TG2 | E68: TERMOELÉCTRICA | J68: 0
B69: ENGIE ENERGIA PERU S.A.A. | C69: C.T. CHILCA 1 | D69: TG3 | E69: TERMOELÉCTRICA | F69: 808.55 | J69: 808.55
B70: ENGIE ENERGIA PERU S.A.A. | C70: C.T. CHILCA 1 | D70: TV | E70: TERMOELÉCTRICA | F70: 282.4 | J70: 282.4
B71: ENGIE ENERGIA PERU S.A.A. | C71: C.T. CHILCA 2 | D71: TG41 | E71: TERMOELÉCTRICA | F71: 831.85 | J71: 831.85
B72: ENGIE ENERGIA PERU S.A.A. | C72: C.T. CHILCA 2 | D72: TV42 | E72: TERMOELÉCTRICA | F72: 491.25 | J72: 491.25
B73: ENGIE ENERGIA PERU S.A.A. | C73: C.T. NEPI | D73: TG41 | E73: TERMOELÉCTRICA | F73: 1503.1 | G73: 4672.15 | H73: 4666.5 | I73: 4676.27 | J73: 15518.02
B74: ENGIE ENERGIA PERU S.A.A. | C74: C.T. NEPI | D74: TG42 | E74: TERMOELÉCTRICA | F74: 1433.75 | G74: 4699 | H74: 4239.05 | I74: 4653.16 | J74: 15024.96
B75: ENGIE ENERGIA PERU S.A.A. | C75: C.T. NEPI | D75: TG43 | E75: TERMOELÉCTRICA | F75: 1352.2 | G75: 3685 | H75: 2698.25 | I75: 3865.67 | J75: 11601.12
B76: ENGIE ENERGIA PERU S.A.A. | C76: C.T. RF PLANTA ILO | D76: TG1 | E76: TERMOELÉCTRICA | F76: 777.1 | G76: 1879.05 | H76: 198.9 | J76: 2855.05
B77: ENGIE ENERGIA PERU S.A.A. | C77: C.T. RF PLANTA ILO | D77: TG2 | E77: TERMOELÉCTRICA | F77: 887 | G77: 2242.1 | H77: 669.45 | J77: 3798.55
B78: ENGIE ENERGIA PERU S.A.A. | C78: C.T. RF PLANTA ILO | D78: TG3 | E78: TERMOELÉCTRICA | F78: 839.35 | G78: 2120.35 | H78: 189.3 | J78: 3149
B79: FENIX POWER PERÚ | C79: C.T. FENIX | D79: GT11 | E79: TERMOELÉCTRICA | F79: 1354.2 | I79: 1734 | J79: 3088.2
B80: FENIX POWER PERÚ | C80: C.T. FENIX | D80: GT12 | E80: TERMOELÉCTRICA | F80: 1317.5 | G80: 945.3 | H80: 1747.6 | I80: 2500.5 | J80: 6510.9
B81: FENIX POWER PERÚ | C81: C.T. FENIX | D81: TV10 | E81: TERMOELÉCTRICA | F81: 1381.8 | G81: 530 | H81: 932.85 | I81: 2589.7 | J81: 5434.35
B82: GENERACIÓN ANDINA S.A.C. | C82: C.H. 8 DE AGOSTO | D82: CENTRAL | E82: HIDROELÉCTRICA | F82: 514.55 | G82: 513.95 | H82: 451.25 | I82: 504 | J82: 1983.75
B83: GENERACIÓN ANDINA S.A.C. | C83: C.H. EL CARMEN | D83: CENTRAL | E83: HIDROELÉCTRICA | F83: 191.2 | G83: 192.1 | H83: 186.4 | I83: 177.3 | J83: 747
B84: GENERADORA DE ENERGÍA DEL PERÚ | C84: C.H. ÁNGEL I | D84: CENTRAL | E84: HIDROELÉCTRICA | F84: 489.6 | G84: 489.6 | H84: 489.6 | I84: 489.6 | J84: 1958.4
B85: GENERADORA DE ENERGÍA DEL PERÚ | C85: C.H. ÁNGEL II | D85: CENTRAL | E85: HIDROELÉCTRICA | F85: 489.6 | G85: 489.6 | H85: 489.6 | I85: 489.6 | J85: 1958.4
B86: GENERADORA DE ENERGÍA DEL PERÚ | C86: C.H. ÁNGEL III | D86: CENTRAL | E86: HIDROELÉCTRICA | F86: 480 | G86: 480 | H86: 480 | I86: 480 | J86: 1920
B87: GENERADORA DE ENERGÍA DEL PERÚ | C87: C.H. LA JOYA | D87: CENTRAL | E87: HIDROELÉCTRICA | F87: 141.6 | G87: 170.85 | H87: 161.35 | I87: 176.65 | J87: 650.45
B88: GM OPERACIONES S.A.C. | C88: CT REFINERIA TALARA | D88: TV1 REF TALARA | E88: TERMOELÉCTRICA | I88: 629.25 | J88: 629.25
B89: GM OPERACIONES S.A.C. | C89: CT REFINERIA TALARA | D89: TV2 REF TALARA | E89: TERMOELÉCTRICA | I89: 475.05 | J89: 475.05
B90: GR CORTARRAMA SOCIEDAD ANONIMA CERRADA | C90: C.S. MATARANI | D90: C.S. MATARANI | E90: SOLAR | F90: 809.65 | G90: 819.15 | H90: 812.95 | I90: 723.25 | J90: 3165
B91: GR PAINO SOCIEDAD ANONIMA CERRADA | C91: C.E. HUAMBOS | D91: CENTRAL | E91: EÓLICA | F91: 209.5 | G91: 118.45 | H91: 129.15 | I91: 51.15 | J91: 508.25
B92: GR TARUCA SOCIEDAD ANONIMA CERRADA | C92: C.E. DUNA | D92: CENTRAL | E92: EÓLICA | F92: 256.3 | G92: 158.45 | H92: 163.5 | I92: 54.15 | J92: 632.4
B93: HIDROCAÑETE S.A. | C93: C.H. IMPERIAL | D93: CENTRAL | E93: HIDROELÉCTRICA | F93: 83.6 | G93: 84.35 | H93: 84.4 | I93: 84.6 | J93: 336.95
B94: HIDROELECTRICA HUANCHOR S.A.C. | C94: C.H. HUANCHOR | D94: CENTRAL | E94: HIDROELÉCTRICA | F94: 441.6 | G94: 442.9 | H94: 446.4 | I94: 445.35 | J94: 1776.25
B95: HUAURA POWER GROUP S.A. | C95: C.H. YARUCAYA | D95: CENTRAL | E95: HIDROELÉCTRICA | F95: 444 | G95: 403.65 | H95: 420.75 | I95: 414.4 | J95: 1682.8
B96: HYDRO GLOBAL PERÚ S.A.C. | C96: CH SAN GABAN III | D96: CENTRAL | E96: HIDROELÉCTRICA | F96: 4331.1 | G96: 4857 | H96: 4846.7 | I96: 4860.25 | J96: 18895.05
B97: INFRAESTRUCTURAS Y ENERGIAS DEL PERU S.A.C. | C97: C.T. RF PTO MALDONADO | D97: CENTRAL | E97: TERMOELÉCTRICA | F97: 48.45 | G97: 115.35 | H97: 0.9 | J97: 164.7
B98: INFRAESTRUCTURAS Y ENERGIAS DEL PERU S.A.C. | C98: C.T. RF PUCALLPA | D98: CENTRAL | E98: TERMOELÉCTRICA | F98: 112.85 | G98: 281.05 | J98: 393.9
B99: INLAND ENERGY SAC | C99: C.H. SANTA TERESA | D99: CENTRAL | E99: HIDROELÉCTRICA | F99: 2121.9 | G99: 2165.35 | H99: 2165.55 | I99: 2180.85 | J99: 8633.65
B100: INVERSIONES SHAQSHA S.A.C. | C100: C.H. PARIAC | D100: CENTRAL | E100: HIDROELÉCTRICA | F100: 84.1 | G100: 84.55 | H100: 92.45 | I100: 104.05 | J100: 365.15
B101: JOYA SOLAR S.A.C. | C101: C.S. SAN MARTIN SOLAR | D101: CENTRAL | E101: SOLAR | F101: 2600.85 | G101: 2607 | H101: 2600.85 | I101: 2555.1 | J101: 10363.8
B102: KALLPA GENERACION S.A. | C102: C.H. CERRO DEL AGUILA | D102: CENTRAL | E102: HIDROELÉCTRICA | F102: 12265.85 | G102: 11744.05 | H102: 11684.3 | I102: 12195.25 | J102: 47889.45
B103: KALLPA GENERACION S.A. | C103: C.S. SUNNY | D103: CENTRAL | E103: SOLAR | F103: 2105.2 | G103: 2140.35 | H103: 2146.95 | I103: 2062.05 | J103: 8454.55
...

Sheet G_AREAS
B3: miércoles, 4 de Marzo del 2026
B5: HORA | C5: RESUMEN DE GENERACIÓN POR ÁREAS DEL SEIN | D5: RESUMEN DE GENERACIÓN POR ÁREAS DEL SEIN | E5: RESUMEN DE GENERACIÓN POR ÁREAS DEL SEIN | F5: RESUMEN DE GENERACIÓN POR ÁREAS DEL SEIN | G5: RESUMEN DE GENERACIÓN POR ÁREAS DEL SEIN | H5: RESUMEN DE GENERACIÓN POR ÁREAS DEL SEIN | I5: RESUMEN DE GENERACIÓN POR ÁREAS DEL SEIN | J5: RESUMEN DE GENERACIÓN POR ÁREAS DEL SEIN | K5: RESUMEN DE GENERACIÓN POR ÁREAS DEL SEIN | L5: RESUMEN DE GENERACIÓN POR ÁREAS DEL SEIN | M5: RESUMEN DE GENERACIÓN POR ÁREAS DEL SEIN | N5: RESUMEN DE GENERACIÓN POR ÁREAS DEL SEIN | O5: RESUMEN DE GENERACIÓN POR ÁREAS DEL SEIN | P5: RESUMEN DE GENERACIÓN POR ÁREAS DEL SEIN | Q5: RESUMEN DE GENERACIÓN POR ÁREAS DEL SEIN | R5: RESUMEN DE GENERACIÓN POR ÁREAS DEL SEIN | S5: HORA | T5: GENERACIÓN POR TIPO DE GENERACIÓN | U5: GENERACIÓN POR TIPO DE GENERACIÓN | V5: GENERACIÓN POR TIPO DE GENERACIÓN | W5: GENERACIÓN POR TIPO DE GENERACIÓN | X5: GENERACIÓN POR TIPO DE GENERACIÓN | Y5: HORA | Z5: GENERACIÓN POR TIPO DE GENERACIÓN | AA5: GENERACIÓN POR TIPO DE GENERACIÓN | AB5: GENERACIÓN POR TIPO DE GENERACIÓN | AC5: GENERACIÓN POR TIPO DE GENERACIÓN | AD5: GENERACIÓN POR TIPO DE GENERACIÓN
C6: NORTE | D6: NORTE | E6: NORTE | F6: NORTE | G6: CENTRO | H6: CENTRO | I6: CENTRO | J6: CENTRO | K6: SUR | L6: SUR | M6: SUR | N6: SUR | O6: GENERACIÓN INTEGRANTES COES | P6: GENERACIÓN INTEGRANTES COES | Q6: GENERACIÓN INTEGRANTES COES | R6: GENERACIÓN INTEGRANTES COES | T6: INTEGRANTES COES | U6: INTEGRANTES COES | V6: INTEGRANTES COES | W6: INTEGRANTES COES | X6: INTEGRANTES COES | Z6: INTEGRANTES COES RER | AA6: INTEGRANTES COES RER | AB6: INTEGRANTES COES RER | AC6: INTEGRANTES COES RER | AD6: INTEGRANTES COES RER
C7: GENERACIÓN HIDROELÉCTRICA NORTE | D7: GENERACIÓN TERMOELÉCTRICA NORTE | E7: GENERACIÓN SOLAR NORTE | F7: GENERACIÓN EÓLICA NORTE | G7: GENERACIÓN HIDROELÉCTRICA CENTRO | H7: GENERACIÓN TERMOELÉCTRICA CENTRO | I7: GENERACIÓN SOLAR CENTRO | J7: GENERACIÓN EÓLICA CENTRO | K7: GENERACIÓN HIDROELÉCTRICA SUR | L7: GENERACIÓN TERMOELÉCTRICA SUR | M7: GENERACIÓN SOLAR SUR | N7: GENERACIÓN EÓLICA SUR | O7: GENERACIÓN COES NORTE | P7: GENERACIÓN COES CENTRO | Q7: GENERACIÓN COES SUR | R7: TOTAL GENERACION | T7: HIDROELÉCTRICA | U7: TERMOELÉCTRICA | V7: SOLAR | W7: EÓLICA | X7: TOTAL GENERACION | Z7: HIDROELÉCTRICA RER | AA7: TERMOELÉCTRICA RER | AB7: SOLAR RER | AC7: EÓLICA RER | AD7: TOTAL RER
B8: 00:30 | C8: 452.5 | D8: 97.3 | E8: 0 | F8: 1.1 | G8: 3665.2 | H8: 401.4 | I8: 0 | J8: 164.7 | K8: 746.3 | L8: 1109.7 | M8: 0 | N8: 0 | O8: 550.9 | P8: 4231.3 | Q8: 1856 | R8: 6638.2 | S8: 00:30 | T8: 4864 | U8: 1608.4 | V8: 0 | W8: 165.8 | X8: 6638.2 | Y8: 00:30 | Z8: 385.1 | AA8: 58.3 | AB8: 0 | AC8: 165.8 | AD8: 609.2
B9: 01:00 | C9: 451.5 | D9: 92.8 | E9: 0 | F9: 1.4 | G9: 3635.1 | H9: 373.9 | I9: 0 | J9: 142.5 | K9: 756.5 | L9: 1112.8 | M9: 0 | N9: 0 | O9: 545.7 | P9: 4151.5 | Q9: 1869.3 | R9: 6566.5 | S9: 01:00 | T9: 4843.1 | U9: 1579.5 | V9: 0 | W9: 143.9 | X9: 6566.5 | Y9: 01:00 | Z9: 385.6 | AA9: 57.9 | AB9: 0 | AC9: 143.9 | AD9: 587.4
B10: 01:30 | C10: 450.7 | D10: 94.7 | E10: 0 | F10: 0.1 | G10: 3538.2 | H10: 375.6 | I10: 0 | J10: 155.4 | K10: 756.1 | L10: 1117.5 | M10: 0 | N10: 0 | O10: 545.5 | P10: 4069.2 | Q10: 1873.6 | R10: 6488.3 | S10: 01:30 | T10: 4745 | U10: 1587.8 | V10: 0 | W10: 155.5 | X10: 6488.3 | Y10: 01:30 | Z10: 385.1 | AA10: 59.9 | AB10: 0 | AC10: 155.5 | AD10: 600.5
B11: 02:00 | C11: 451.6 | D11: 88.4 | E11: 0 | F11: 0.2 | G11: 3540.3 | H11: 373.6 | I11: 0 | J11: 162 | K11: 757.8 | L11: 969.6 | M11: 0 | N11: 0 | O11: 540.2 | P11: 4075.9 | Q11: 1727.4 | R11: 6343.5 | S11: 02:00 | T11: 4749.7 | U11: 1431.6 | V11: 0 | W11: 162.2 | X11: 6343.5 | Y11: 02:00 | Z11: 384.5 | AA11: 56.3 | AB11: 0 | AC11: 162.2 | AD11: 603
B12: 02:30 | C12: 451.4 | D12: 91.4 | E12: 0 | F12: 0.8 | G12: 3533.9 | H12: 374.1 | I12: 0 | J12: 140.3 | K12: 755.3 | L12: 937 | M12: 0 | N12: 0 | O12: 543.6 | P12: 4048.3 | Q12: 1692.3 | R12: 6284.2 | S12: 02:30 | T12: 4740.6 | U12: 1402.5 | V12: 0 | W12: 141.1 | X12: 6284.2 | Y12: 02:30 | Z12: 375.6 | AA12: 55.3 | AB12: 0 | AC12: 141.1 | AD12: 572
B13: 03:00 | C13: 452.1 | D13: 90.8 | E13: 0 | F13: 0.4 | G13: 3510.2 | H13: 378.2 | I13: 0 | J13: 132.7 | K13: 761.1 | L13: 939.9 | M13: 0 | N13: 0 | O13: 543.3 | P13: 4021.1 | Q13: 1701 | R13: 6265.4 | S13: 03:00 | T13: 4723.4 | U13: 1408.9 | V13: 0 | W13: 133.1 | X13: 6265.4 | Y13: 03:00 | Z13: 372.7 | AA13: 57.3 | AB13: 0 | AC13: 133.1 | AD13: 563.1
B14: 03:30 | C14: 452.5 | D14: 93.5 | E14: 0 | F14: 1.3 | G14: 3558.1 | H14: 375.4 | I14: 0 | J14: 153.9 | K14: 758.6 | L14: 860.7 | M14: 0 | N14: 0 | O14: 547.3 | P14: 4087.4 | Q14: 1619.3 | R14: 6254 | S14: 03:30 | T14: 4769.2 | U14: 1329.6 | V14: 0 | W14: 155.2 | X14: 6254 | Y14: 03:30 | Z14: 372.5 | AA14: 61.1 | AB14: 0 | AC14: 155.2 | AD14: 588.8
B15: 04:00 | C15: 450.1 | D15: 92.2 | E15: 0 | F15: 1.6 | G15: 3535.8 | H15: 370.3 | I15: 0 | J15: 187.6 | K15: 746.4 | L15: 850.1 | M15: 0 | N15: 0 | O15: 543.9 | P15: 4093.7 | Q15: 1596.5 | R15: 6234.1 | S15: 04:00 | T15: 4732.3 | U15: 1312.6 | V15: 0 | W15: 189.2 | X15: 6234.1 | Y15: 04:00 | Z15: 374.8 | AA15: 59.1 | AB15: 0 | AC15: 189.2 | AD15: 623.1
B16: 04:30 | C16: 452.5 | D16: 92.5 | E16: 0 | F16: 0.9 | G16: 3572.1 | H16: 316.9 | I16: 0 | J16: 219 | K16: 759.4 | L16: 859.7 | M16: 0 | N16: 0 | O16: 545.9 | P16: 4108 | Q16: 1619.1 | R16: 6273 | S16: 04:30 | T16: 4784 | U16: 1269.1 | V16: 0 | W16: 219.9 | X16: 6273 | Y16: 04:30 | Z16: 377.3 | AA16: 59.8 | AB16: 0 | AC16: 219.9 | AD16: 657
B17: 05:00 | C17: 452 | D17: 92.5 | E17: 0 | F17: 0.1 | G17: 3568.1 | H17: 315.7 | I17: 0 | J17: 230.3 | K17: 761 | L17: 859 | M17: 0 | N17: 0 | O17: 544.6 | P17: 4114.1 | Q17: 1620 | R17: 6278.7 | S17: 05:00 | T17: 4781.1 | U17: 1267.2 | V17: 0 | W17: 230.4 | X17: 6278.7 | Y17: 05:00 | Z17: 385.7 | AA17: 60.2 | AB17: 0 | AC17: 230.4 | AD17: 676.3
B18: 05:30 | C18: 440.8 | D18: 64.2 | E18: 0 | F18: 0 | G18: 3688.6 | H18: 314.9 | I18: 0 | J18: 241.1 | K18: 758.2 | L18: 935.9 | M18: 0 | N18: 0 | O18: 505 | P18: 4244.6 | Q18: 1694.1 | R18: 6443.7 | S18: 05:30 | T18: 4887.6 | U18: 1315 | V18: 0 | W18: 241.1 | X18: 6443.7 | Y18: 05:30 | Z18: 375.5 | AA18: 59.3 | AB18: 0 | AC18: 241.1 | AD18: 675.9
B19: 06:00 | C19: 442.3 | D19: 84.7 | E19: 0 | F19: 0 | G19: 3640.6 | H19: 315.7 | I19: 0 | J19: 251.5 | K19: 757.4 | L19: 937.7 | M19: 15.73 | N19: 0 | O19: 527 | P19: 4207.8 | Q19: 1710.83 | R19: 6445.63 | S19: 06:00 | T19: 4840.3 | U19: 1338.1 | V19: 15.73 | W19: 251.5 | X19: 6445.63 | Y19: 06:00 | Z19: 376 | AA19: 59.5 | AB19: 15.73 | AC19: 251.5 | AD19: 702.73
... B56: TOTAL MWh | C56: 11268.065 | D56: 4569.65 | E56: 1.25 | F56: 190.8 | G56: 85212.175 | H56: 12785.6 | I56: 5.75 | J56: 9059.5471 | K56: 18738.75 | L56: 22161.4 | M56: 10259.715 | N56: 0 | O56: 16029.765 | P56: 107063.07 | Q56: 51159.865 | R56: 174252.7 | S56: TOTAL MWh | T56: 115218.99 | U56: 39516.65 | V56: 10266.715 | W56: 9250.3471 | X56: 174252.7 | Y56: TOTAL MWh | Z56: 9096.55 | AA56: 1608.6 | AB56: 10266.715 | AC56: 9250.3471 | AD56: 30222.212

Sheet HOP
B3: miércoles, 4 de Marzo del 2026
B5: Reporte de Horas de Operación
B6: Empresa | C6: Central | D6: Grupo | E6: Modo de Operación | F6: Inicio | G6: Final | H6: O. Arranque | I6: O. Parada | J6: Tipo Operación | K6: Ensayo de Potencia Efectiva | L6: Ensayo de Potencia Mínima | M6: Sistema | N6: Lim. Transm. | O6: Causa | P6: Observación
B7: AGRO INDUSTRIAL PARAMONGA S.A. | C7: C.T. PARAMONGA | D7: CENTRAL | E7: PARAMONGA - BAGAZO | F7: 04/03/2026 07:59:00 | G7: 05/03/2026 00:00:00 | H7: 04/03/2026 07:49:00 | J7: POR COGENERACION | O7: ...
B8: AGROAURORA S.A.C. | C8: C.T. MAPLE ETANOL | D8: CENTRAL | E8: MAPLE- BAGAZO | F8: 04/03/2026 00:00:00 | G8: 05/03/2026 00:00:00 | J8: POR COGENERACION | O8: ...
B9: AGROINDUSTRIAS SAN JACINTO S.A.A. | C9: C.T. SAN JACINTO | D9: CENTRAL | E9: SAN_JACINTO - BAGAZO | F9: 04/03/2026 00:00:00 | G9: 05/03/2026 00:00:00 | J9: POR COGENERACION | O9: ...
B10: AGROLMOS SOCIEDAD ANONIMA - AGROLMOS S.A. | C10: C.T. AGROLMOS | D10: CENTRAL | E10: AGROLMOS TV1 & TV2 - BAGAZO | F10: 04/03/2026 00:00:00 | G10: 05/03/2026 00:00:00 | J10: POR COGENERACION | O10: ...
B11: CASA GRANDE S.A.A. | C11: C.T. CASA GRANDE | D11: CENTRAL | E11: CASA GRANDE TV1 & TV3 - BAGAZO | F11: 04/03/2026 00:00:00 | G11: 05/03/2026 00:00:00 | J11: POR COGENERACION | O11: ...
B12: ELECTROPERU | C12: C.T. TUMBES | D12: MAK1 | E12: TUMBES MAK 1 - D2 | F12: 04/03/2026 00:00:00 | G12: 05/03/2026 00:00:00 | J12: POR POTENCIA O ENERGIA | O12: ...
B13: ELECTROPERU | C13: C.T. TUMBES | D13: MAK2 | E13: TUMBES MAK 2 - D2 | F13: 04/03/2026 00:00:00 | G13: 05/03/2026 00:00:00 | J13: POR POTENCIA O ENERGIA | O13: ...
B14: ENEL GENERACION PIURA S.A. | C14: C.T. MALACAS 1 | D14: CENTRAL | E14: MALACAS1 TG6 - GAS | F14: 04/03/2026 05:41:00 | G14: 04/03/2026 12:36:00 | H14: 04/03/2026 05:28:00 | I14: 04/03/2026 12:30:00 | J14: POR PRUEBAS | O14: ...
B15: ENEL GENERACION PIURA S.A. | C15: C.T. MALACAS 1 | D15: CENTRAL | E15: MALACAS1 TG6 - D2 | F15: 04/03/2026 19:50:00 | G15: 05/03/2026 00:00:00 | H15: 04/03/2026 18:35:00 | I15: 04/03/2026 23:50:00 | J15: POR POTENCIA O ENERGIA | O15: ...
B16: ENEL GENERACION PIURA S.A. | C16: C.T. MALACAS 2 | D16: CENTRAL | E16: MALACAS2 TG4 - GAS | F16: 04/03/2026 00:00:00 | G16: 04/03/2026 05:19:00 | I16: 04/03/2026 05:06:00 | J16: POR POTENCIA O ENERGIA | O16: ...
B17: ENEL GENERACION PIURA S.A. | C17: C.T. MALACAS 2 | D17: CENTRAL | E17: MALACAS2 TG4 - GAS | F17: 04/03/2026 12:51:00 | G17: 05/03/2026 00:00:00 | H17: 04/03/2026 12:30:00 | J17: POR POTENCIA O ENERGIA | O17: ... | P17: Se coordinó subir a carga mínima de acuerdo al despacho programado según el volumen de gas informado. A las 23:12h se bajó a 35 MW por disponibilidad de gas.
B18: ENGIE ENERGIA PERU S.A.A. | C18: C.T. NEPI | D18: TG41 | E18: CTNEPI TG41 - D2 | F18: 04/03/2026 00:00:00 | G18: 05/03/2026 00:00:00 | J18: POR POTENCIA O ENERGIA | O18: ...
B19: ENGIE ENERGIA PERU S.A.A. | C19: C.T. NEPI | D19: TG42 | E19: CTNEPI TG42 - D2 | F19: 04/03/2026 00:00:00 | G19: 04/03/2026 18:05:00 | J19: POR POTENCIA O ENERGIA | O19: ...
B20: ENGIE ENERGIA PERU S.A.A. | C20: C.T. NEPI | D20: TG43 | E20: CTNEPI TG43 - D2 | F20: 04/03/2026 00:00:00 | G20: 04/03/2026 07:06:00 | J20: POR POTENCIA O ENERGIA | O20: ...
B21: ENGIE ENERGIA PERU S.A.A. | C21: C.T. NEPI | D21: TG43 | E21: CTNEPI TG43 - D2 | F21: 04/03/2026 07:06:00 | G21: 04/03/2026 08:23:00 | J21: A MINIMA CARGA | O21: ...
B22: ENGIE ENERGIA PERU S.A.A. | C22: C.T. NEPI | D22: TG43 | E22: CTNEPI TG43 - D2 | F22: 04/03/2026 08:23:00 | G22: 04/03/2026 08:55:00 | J22: POR POTENCIA O ENERGIA | O22: ...
B23: ENGIE ENERGIA PERU S.A.A. | C23: C.T. NEPI | D23: TG43 | E23: CTNEPI TG43 - D2 | F23: 04/03/2026 08:55:00 | G23: 04/03/2026 11:27:00 | J23: A MINIMA CARGA | O23: ...
B24: ENGIE ENERGIA PERU S.A.A. | C24: C.T. NEPI | D24: TG43 | E24: CTNEPI TG43 - D2 | F24: 04/03/2026 11:27:00 | G24: 04/03/2026 12:49:00 | J24: POR POTENCIA O ENERGIA | O24: ...
B25: ENGIE ENERGIA PERU S.A.A. | C25: C.T. NEPI | D25: TG43 | E25: CTNEPI TG43 - D2 | F25: 04/03/2026 12:49:00 | G25: 04/03/2026 14:38:00 | J25: A MINIMA CARGA | O25: ...
B26: ENGIE ENERGIA PERU S.A.A. | C26: C.T. NEPI | D26: TG43 | E26: CTNEPI TG43 - D2 | F26: 04/03/2026 14:38:00 | G26: 04/03/2026 14:58:00 | J26: POR POTENCIA O ENERGIA | O26: ...
B27: ENGIE ENERGIA PERU S.A.A. | C27: C.T. NEPI | D27: TG43 | E27: CTNEPI TG43 - D2 | F27: 04/03/2026 14:58:00 | G27: 04/03/2026 15:30:00 | J27: A MINIMA CARGA | O27: ...
B28: ENGIE ENERGIA PERU S.A.A. | C28: C.T. NEPI | D28: TG43 | E28: CTNEPI TG43 - D2 | F28: 04/03/2026 15:30:00 | G28: 04/03/2026 17:13:00 | J28: POR POTENCIA O ENERGIA | O28: ...
B29: ENGIE ENERGIA PERU S.A.A. | C29: C.T. NEPI | D29: TG43 | E29: CTNEPI TG43 - D2 | F29: 04/03/2026 17:13:00 | G29: 04/03/2026 20:52:00 | J29: A MINIMA CARGA | O29: ...
... B34: FENIX POWER PERÚ | C34: C.T. FENIX | D34: CENTRAL | E34: FENIX CCOMB GT12 - D2 | F34: 04/03/2026 00:00:00 | G34: 04/03/2026 09:37:00 | J34: POR POTENCIA O ENERGIA | O34: ...
B35: FENIX POWER PERÚ | C35: C.T. FENIX | D35: GT11 | E35: FENIX GT11 - D2 | F35: 04/03/2026 06:45:00 | G35: 04/03/2026 09:37:00 | H35: 04/03/2026 04:56:00 | J35: A MINIMA CARGA | O35: ... | P35: En proceso de acople al 2x1
B36: FENIX POWER PERÚ | C36: C.T. FENIX | D36: CENTRAL | E36: FENIX CCOMB GT11 & GT12 - D2 | F36: 04/03/2026 09:37:00 | G36: 05/03/2026 00:00:00 | J36: POR POTENCIA O ENERGIA | O36: ... | P36: Proceso de estabilización en 2x1, generando 300 MW 17:35h CC-Fenix informa que puede operar a maxima generación por disponibilidad de combustible. A las 23:47 h, S/C generar 400 MW de acuerdo a su disponibilidad de combustible.
B37: GM OPERACIONES S.A.C. | C37: CT REFINERIA TALARA | D37: TV1 REF TALARA | E37: REF_TALARA TV1 - NLH_RFG | F37: 04/03/2026 06:40:00 | G37: 05/03/2026 00:00:00 | H37: 04/03/2026 06:38:00 | J37: POR COGENERACION | O37: ...
B38: GM OPERACIONES S.A.C. | C38: CT REFINERIA TALARA | D38: TV2 REF TALARA | E38: REF_TALARA TV2 - NLH_RFG | F38: 04/03/2026 07:44:00 | G38: 05/03/2026 00:00:00 | J38: POR COGENERACION | O38: ...
B39: MINERA CERRO VERDE | C39: C.T. RECKA | D39: CENTRAL | E39: RECKA TG1 - D2 | F39: 04/03/2026 16:57:00 | G39: 04/03/2026 22:50:00 | H39: 04/03/2026 16:38:00 | I39: 04/03/2026 22:39:00 | J39: POR POTENCIA O ENERGIA | O39: ...
B40: ORYGEN PERU S.A.A. | C40: C.T. SANTA ROSA I | D40: TG7 | E40: STA ROSA WEST TG7 - D2 CON H2O | F40: 04/03/2026 00:00:00 | G40: 04/03/2026 00:10:00 | J40: A MINIMA CARGA | O40: ...
B41: ORYGEN PERU S.A.A. | C41: C.T. SANTA ROSA I | D41: TG7 | E41: STA ROSA WEST TG7 - D2 CON H2O | F41: 04/03/2026 10:43:00 | G41: 04/03/2026 20:18:00 | H41: 04/03/2026 08:48:00 | I41: 04/03/2026 20:04:00 | J41: A MINIMA CARGA | O41: ...
B42: ORYGEN PERU S.A.A. | C42: C.T. VENTANILLA | D42: TG3 | E42: VENTANILLA TG3 - D2 | F42: 04/03/2026 00:00:00 | G42: 05/03/2026 00:00:00 | J42: POR POTENCIA O ENERGIA | O42: ...
B43: PETRAMAS | C43: C.T. HUAYCOLORO | D43: CENTRAL | E43: HUAYCOLORO - BIOGAS | F43: 04/03/2026 00:00:00 | G43: 05/03/2026 00:00:00 | I43: 04/03/2026 08:01:00 | J43: POR POTENCIA O ENERGIA | O43: ...
B44: PETRAMAS | C44: C.T. HUAYCOLORO | D44: G2 | E44: HUAYCOLORO - BIOGAS | F44: 04/03/2026 22:42:00 | G44: 05/03/2026 00:00:00 | H44: 04/03/2026 22:39:00 | J44: POR POTENCIA O ENERGIA | O44: ...
B45: PETRAMAS | C45: C.T. LA GRINGA | D45: CENTRAL | E45: LA GRINGA V - BIOGAS | F45: 04/03/2026 00:00:00 | G45: 05/03/2026 00:00:00 | J45: POR POTENCIA O ENERGIA | O45: ...
B46: PETRAMAS | C46: C.T.B DOÑA CATALINA | D46: CENTRAL | E46: DONA CATALINA - BIOGAS | F46: 04/03/2026 00:00:00 | G46: 05/03/2026 00:00:00 | I46: 04/03/2026 05:11:00 | J46: POR POTENCIA O ENERGIA | O46: ...
B47: PETRAMAS | C47: C.T.B. CALLAO | D47: CENTRAL | E47: CALLAO - BIOGAS | F47: 04/03/2026 00:00:00 | G47: 05/03/2026 00:00:00 | J47: POR POTENCIA O ENERGIA | O47: ...
B48: SAMAY I S.A.C | C48: C.T. PUERTO BRAVO | D48: TG1 | E48: PTO BRAVO TG1 - D2 | F48: 04/03/2026 00:00:00 | G48: 04/03/2026 00:29:00 | I48: 04/03/2026 00:16:00 | J48: POR POTENCIA O ENERGIA | O48: ...
B49: SAMAY I S.A.C | C49: C.T. PUERTO BRAVO | D49: TG2 | E49: PTO BRAVO TG2 - D2 | F49: 04/03/2026 00:00:00 | G49: 04/03/2026 03:02:00 | J49: POR POTENCIA O ENERGIA | O49: ...
B50: SAMAY I S.A.C | C50: C.T. PUERTO BRAVO | D50: TG3 | E50: PTO BRAVO TG3 - D2 | F50: 04/03/2026 00:00:00 | G50: 04/03/2026 07:10:00 | J50: POR POTENCIA O ENERGIA | O50: ...
B51: SAMAY I S.A.C | C51: C.T. PUERTO BRAVO | D51: TG4 | E51: PTO BRAVO TG4 - D2 | F51: 04/03/2026 00:00:00 | G51: 04/03/2026 02:01:00 | I51: 04/03/2026 01:45:00 | J51: POR POTENCIA O ENERGIA | O51: ...
B52: SAMAY I S.A.C | C52: C.T. PUERTO BRAVO | D52: TG2 | E52: PTO BRAVO TG2 - D2 | F52: 04/03/2026 03:02:00 | G52: 04/03/2026 05:20:00 | J52: A MINIMA CARGA | O52: ...
B53: SAMAY I S.A.C | C53: C.T. PUERTO BRAVO | D53: TG2 | E53: PTO BRAVO TG2 - D2 | F53: 04/03/2026 05:20:00 | G53: 04/03/2026 06:48:00 | J53: POR POTENCIA O ENERGIA | O53: ...
B54: SAMAY I S.A.C | C54: C.T. PUERTO BRAVO | D54: TG2 | E54: PTO BRAVO TG2 - D2 | F54: 04/03/2026 06:48:00 | G54: 04/03/2026 11:49:00 | J54: A MINIMA CARGA | O54: ...
B55: SAMAY I S.A.C | C55: C.T. PUERTO BRAVO | D55: TG3 | E55: PTO BRAVO TG3 - D2 | F55: 04/03/2026 07:10:00 | G55: 04/03/2026 08:13:00 | J55: A MINIMA CARGA | O55: ...
B56: SAMAY I S.A.C | C56: C.T. PUERTO BRAVO | D56: TG3 | E56: PTO BRAVO TG3 - D2 | F56: 04/03/2026 08:13:00 | G56: 04/03/2026 13:30:00 | J56: POR POTENCIA O ENERGIA | O56: ...
B57: SAMAY I S.A.C | C57: C.T. PUERTO BRAVO | D57: TG1 | E57: PTO BRAVO TG1 - D2 | F57: 04/03/2026 08:41:00 | G57: 04/03/2026 11:03:00 | H57: 04/03/2026 08:18:00 | I57: 04/03/2026 10:50:00 | J57: POR POTENCIA O ENERGIA | O57: ...
B58: SAMAY I S.A.C | C58: C.T. PUERTO BRAVO | D58: TG4 | E58: PTO BRAVO TG4 - D2 | F58: 04/03/2026 08:48:00 | G58: 04/03/2026 13:06:00 | H58: 04/03/2026 08:24:00 | I58: 04/03/2026 12:58:00 | J58: A MINIMA CARGA | O58: ...
B59: SAMAY I S.A.C | C59: C.T. PUERTO BRAVO | D59: TG2 | E59: PTO BRAVO TG2 - D2 | F59: 04/03/2026 11:49:00 | G59: 04/03/2026 12:17:00 | J59: POR POTENCIA O ENERGIA | O59: ...
B60: SAMAY I S.A.C | C60: C.T. PUERTO BRAVO | D60: TG2 | E60: PTO BRAVO TG2 - D2 | F60: 04/03/2026 12:17:00 | G60: 04/03/2026 20:55:00 | J60: A MINIMA CARGA | O60: ...
B61: SAMAY I S.A.C | C61: C.T. PUERTO BRAVO | D61: TG3 | E61: PTO BRAVO TG3 - D2 | F61: 04/03/2026 13:30:00 | G61: 04/03/2026 14:14:00 | J61: A MINIMA CARGA | O61: ...
B62: SAMAY I S.A.C | C62: C.T. PUERTO BRAVO | D62: TG3 | E62: PTO BRAVO TG3 - D2 | F62: 04/03/2026 14:14:00 | G62: 04/03/2026 18:04:00 | J62: POR POTENCIA O ENERGIA | O62: ...
B63: SAMAY I S.A.C | C63: C.T. PUERTO BRAVO | D63: TG4 | E63: PTO BRAVO TG4 - D2 | F63: 04/03/2026 16:43:00 | G63: 04/03/2026 20:55:00 | H63: 04/03/2026 16:19:00 | J63: A MINIMA CARGA | O63: ...
B64: SAMAY I S.A.C | C64: C.T. PUERTO BRAVO | D64: TG1 | E64: PTO BRAVO TG1 - D2 | F64: 04/03/2026 17:06:00 | G64: 04/03/2026 19:07:00 | H64: 04/03/2026 16:40:00 | J64: A MINIMA CARGA | O64: ...
B65: SAMAY I S.A.C | C65: C.T. PUERTO BRAVO | D65: TG3 | E65: PTO BRAVO TG3 - D2 | F65: 04/03/2026 18:04:00 | G65: 04/03/2026 18:31:00 | J65: A MINIMA CARGA | O65: ...
B66: SAMAY I S.A.C | C66: C.T. PUERTO BRAVO | D66: TG3 | E66: PTO BRAVO TG3 - D2 | F66: 04/03/2026 18:31:00 | G66: 04/03/2026 22:40:00 | I66: 04/03/2026 22:23:00 | J66: POR POTENCIA O ENERGIA | O66: ...
B67: SAMAY I S.A.C | C67: C.T. PUERTO BRAVO | D67: TG1 | E67: PTO BRAVO TG1 - D2 | F67: 04/03/2026 19:07:00 | G67: 04/03/2026 23:25:00 | J67: POR POTENCIA O ENERGIA | O67: ...
B68: SAMAY I S.A.C | C68: C.T. PUERTO BRAVO | D68: TG2 | E68: PTO BRAVO TG2 - D2 | F68: 04/03/2026 20:55:00 | G68: 04/03/2026 22:11:00 | I68: 04/03/2026 21:59:00 | J68: POR POTENCIA O ENERGIA | O68: ...
B69: SAMAY I S.A.C | C69: C.T. PUERTO BRAVO | D69: TG4 | E69: PTO BRAVO TG4 - D2 | F69: 04/03/2026 20:55:00 | G69: 04/03/2026 21:40:00 | J69: POR POTENCIA O ENERGIA | O69: ...
B70: SAMAY I S.A.C | C70: C.T. PUERTO BRAVO | D70: TG4 | E70: PTO BRAVO TG4 - D2 | F70: 04/03/2026 21:40:00 | G70: 04/03/2026 21:59:00 | I70: 04/03/2026 21:51:00 | J70: A MINIMA CARGA | O70: ...
B71: SAMAY I S.A.C | C71: C.T. PUERTO BRAVO | D71: TG1 | E71: PTO BRAVO TG1 - D2 | F71: 04/03/2026 23:25:00 | G71: 05/03/2026 00:00:00 | J71: A MINIMA CARGA | O71: ...
B72: SHOUGESA | C72: C.T. SAN NICOLAS | D72: TV1 | E72: SAN NICOLAS TV1 - R500 | F72: 04/03/2026 00:00:00 | G72: 04/03/2026 11:06:00 | J72: POR POTENCIA O ENERGIA | O72: ...
B73: SHOUGESA | C73: C.T. SAN NICOLAS | D73: TV2 | E73: SAN NICOLAS TV2 - R500 | F73: 04/03/2026 00:00:00 | G73: 04/03/2026 00:33:00 | J73: POR POTENCIA O ENERGIA | O73: ... | P73: Paro por correctivo
B74: SHOUGESA | C74: C.T. SAN NICOLAS | D74: TV1 | E74: SAN NICOLAS TV1 - R500 | F74: 04/03/2026 11:06:00 | G74: 04/03/2026 18:17:00 | J74: A MINIMA CARGA | N74: xLT | O74: ...
B75: SHOUGESA | C75: C.T. SAN NICOLAS | D75: TV1 | E75: SAN NICOLAS TV1 - R500 | F75: 04/03/2026 18:17:00 | G75: 05/03/2026 00:00:00 | J75: POR POTENCIA O ENERGIA | O75: ...
B76: TERMOSELVA | C76: C.T. AGUAYTIA | D76: TG2 | E76: AGUAYTIA TG2 - GAS | F76: 04/03/2026 00:00:00 | G76: 04/03/2026 04:15:00 | I76: 04/03/2026 04:01:00 | J76: POR POTENCIA O ENERGIA | O76: ... | P76: A bajo a mínima para cumplir con volumen de 16 MMPC
B77: TERMOSELVA | C77: C.T. AGUAYTIA | D77: TG1 | E77: AGUAYTIA TG1 - GAS | F77: 04/03/2026 10:40:00 | G77: 05/03/2026 00:00:00 | H77: 04/03/2026 10:26:00 | J77: POR POTENCIA O ENERGIA | O77: ...

Sheet INDISP
B3: miércoles, 4 de Marzo del 2026
B5: Hora Inicio y Fin de Indisponibilidades de las Unidades de Generación SEIN
B6: Empresa | C6: Ubicación | D6: Equipo | E6: Inicio | F6: Final | G6: Descripción | H6: MW Indisp. | I6: Prog. | J6: Dispon | K6: Interrupc. | L6: Tipo | M6: CodEq | N6: TipoEq_Osinerg
B7: AGRO INDUSTRIAL PARAMONGA S.A. | C7: PARAMONGA | D7: TV-01 | E7: 04/03/2026 00:00 | F7: 04/03/2026 07:59 | G7: LIMPIEZA E INSPECCIÓN DE LA CALDERA CBS Y MANTENIMIENTO A SUS PERIFÉRICOS (CONDUCTORES, VENTILADORES, BOMBAS, MOTORES, ETC) | H7: 14 | I7: P | J7: F/S | K7: N | L7: PREV. | M7: 12664 | N7: G
B8: BIOENERGIA DEL CHIRA S.A. | C8: CAÑA BRAVA | D8: CENTRAL | E8: 04/03/2026 00:00 | F8: 05/03/2026 00:00 | G8: La C.T. Caña Brava para para mentenimiento anual programado. | H8: 11.9 | I8: P | J8: F/S | K8: N | L8: PREV. | M8: 20510 | N8: G
B9: EGASA | C9: CHARCANI IV | D9: CENTRAL | E9: 04/03/2026 00:00 | F9: 05/03/2026 00:00 | G9: FS Fuerza Mayor, Ingreso de huayco a la central. | H9: 15 | I9: F | J9: F/S | K9: N | L9: OTROS | M9: 1198 | N9: G
B10: EGASA | C10: CHILINA D | D10: SLZ1 | E10: 04/03/2026 00:00 | F10: 04/03/2026 09:20 | G10: Revisión y reparación del acople de excitación con generador | H10: 5 | I10: F | J10: F/S | K10: N | L10: CORR. | M10: 136 | N10: G
B11: EGESUR | C11: ARICOTA I | D11: G2 | E11: 04/03/2026 00:00 | F11: 05/03/2026 00:00 | G11: MANTENIMIENTO ELECTROMECÁNICO 3 / MODERNIZACIÓN DE EQUIPAMIENTO DE REGULADOR AUTOMÁTICO DE VOLTAJE / SISTEMA DE EXCITACIÓN UNIDAD DE GENERACIÓN 02 - CENTRAL HIDROELÉCTRICA ARICOTA I | H11: 0 | I11: P | J11: F/S | K11: N | L11: PREV. | M11: 125 | N11: G
B12: ENEL GENERACION PIURA S.A. | C12: RESERVA FRIA DE GENERACION TALARA | D12: TG5 | E12: 04/03/2026 00:00 | F12: 05/03/2026 00:00 | G12: Cambios de seguros y compresor axial. | H12: 0 | I12: P | J12: F/S | K12: N | L12: CORR. | M12: 13555 | N12: G
B13: GM OPERACIONES S.A.C. | C13: REFINERIA TALARA | D13: CENTRAL | E13: 04/03/2026 00:00 | F13: 05/03/2026 00:00 | G13: CENTRAL INDISPONIBLE POR FALLA | H13: 0 | I13: P | J13: F/S | K13: N | L13: CORR. | M13: 22187 | N13: G
B14: ORYGEN PERU S.A.A. | C14: CH HER 1 | D14: CENTRAL | E14: 04/03/2026 22:23 | F14: 05/03/2026 00:00 | G14: INDISPONIBLE POR ALTA CONCENTRACIÓN DE SÓLIDOS 86 M3/S Y 6.5 G/L | H14: 0.7 | I14: F | J14: F/S | K14: N | L14: OTROS | M14: 18790 | N14: G
B15: ORYGEN PERU S.A.A. | C15: HUAMPANÍ | D15: G2 | E15: 04/03/2026 00:00 | F15: 04/03/2026 00:07 | G15: TRIP DE UNIDAD CON 15.1 MW, CAUSAS EN INVESTIGACIÓN. | H15: 15 | I15: F | J15: F/S | K15: N | L15: CORR. | M15: 27 | N15: G
B16: ORYGEN PERU S.A.A. | C16: HUAMPANÍ | D16: CENTRAL | E16: 04/03/2026 22:38 | F16: 05/03/2026 00:00 | G16: INDISPONIBLE POR ALTA CONCENTRACIÓN DE SÓLIDOS 86 M3/S Y 6.5 G/L | H16: 30 | I16: F | J16: F/S | K16: N | L16: OTROS | M16: 270 | N16: G
B17: ORYGEN PERU S.A.A. | C17: SANTA ROSA | D17: TG7 | E17: 04/03/2026 09:08 | F17: 04/03/2026 10:43 | G17: mantenimiento correctivo, ajuste de los sensores de posición de la bleed valve HP. | H17: 0 | I17: F | J17: F/S | K17: N | L17: CORR. | M17: 33 | N17: G
B18: ORYGEN PERU S.A.A. | C18: VENTANILLA | D18: TG4 | E18: 04/03/2026 00:00 | F18: 05/03/2026 00:00 | G18: MANTENIMIENTO DE BESS | H18: 150 | I18: P | J18: F/S | K18: N | L18: PREV. | M18: 14 | N18: G
... B26: SHOUGESA | C26: SAN NICOLÁS | D26: TV3 | E26: 04/03/2026 00:00 | F26: 05/03/2026 00:00 | G26: Queda indisponible por falla en la celda N°3. | H26: 24.26 | I26: P | J26: F/S | K26: N | L26: CORR. | M26: 60 | N26: G

Sheet RESERVA_FRÍA
B3: 04/03/2026 | E3: EJECUTADO | L3: Miércoles 4 de Marzo del 2026 / SEM N° 9 | V3: EJECUTADO | AC3: Miércoles 4 de Marzo del 2026 / SEM N° 9 | EE3: ENERGIA RENOVABLES | GW3: COGENERACION | HF3: NO INTEGRANTES
B4: Miércoles | C4: HYDROG | D4: ELECTROPERU | H4: ORAZU | J4: TER | L4: KALLPA GENERACION S.A. | T4: SHOUGESA | X4: EGM | Y4: EGESUR | AB4: EGASA | AI4: SGB | AJ4: CELEP | AK4: MINCVE | AL4: ETEN | AN4: HUALLA | AP4: LAVI | AQ4: CHIN | AS4: HUANCH | AT4: CELER | AU4: INLD | AV4: FENIX POWER PERÚ | AY4: STATKRAFT S.A | BE4: STARO | BG4: HUANZA | BH4: ENEL GENERACION PIURA S.A. | BK4: ENGIE ENERGIA PERU S.A.A. | BY4: IYEP | CA4: SHAQSH | CB4: ORYGEN PERU S.A.A. | CN4: SAMAY I S.A.C | CR4: TCHILC | CT4: TADG | CV4: GENERACION | CY4: SALIDAS YUPANA | DC4: FLUJO EN LINEAS | DO4: COSTOS MARGINALES | DS4: RESERVA | DX4: DEMANDA POR AREAS | EE4: ACHI | EF4: PIEREN | EG4: COLCA | EH4: ERSUR | EI4: GRCOR | EJ4: TARU | EK4: KONDU | EL4: VARI | EM4: ORAZU | EO4: KALLPA | EQ4: SGB | ER4: AIPSA | ES4: MAJA | ET4: EGECSA | EU4: STANA | EV4: AGUAA | EW4: RDOBLE | EX4: HIDRO | EY4: HUARA | EZ4: MOQUE | FA4: PANAM | FB4: PARQU | FC4: PE3HER | FD4: TACNA | FE4: EYSAC | FF4: AURORA | FG4: AGROIN | FH4: AGROLM | FI4: ANDEA | FJ4: ASLC | FK4: ATRIA | FL4: CAGR | FM4: COENGY | FN4: EGEJUNIN | FR4: EOL | FT4: ENGIE ENERGIA PERU S.A.A. | FZ4: GENE | GB4: GENERADORA DE ENERGÍA DEL PERÚ | GF4: PAINO | GG4: JOYAS | GH4: SARCUS | GI4: ORYGEN PERU S.A.A. | GN4: PETRAMAS | GR4: RARCUS | GS4: SINERSA | GW4: ACHI | GX4: GM OP | GZ4: AIPSA | HA4: AURORA | HB4: AGROIN | HC4: AGROLM | HD4: CAGR | HF4: UNACEM | HG4: EOR | HH4: AYEP | HI4: ELZANA | HJ4: ENOSA | HK4: SDE | HL4: SINERS | HO4: RESERVA
