Workbook

Sheet EVENTOS
B3: lunes, 27 de Octubre del 2025
B5: INFORMACIÓN DE EVENTOS PRINCIPALES EN SUS INSTALACIONES
B6: TIPO DE EVENTO | C6: EMPRESA | D6: UBICACIÓN | E6: TIPO DE EQUIPO | F6: EQUIPO | G6: INICIO | H6: FINAL | I6: DESCRIPCIÓN | J6: MW INDISP. | K6: INTERRUPCIÓN (SI/NO) | L6: TENSIÓN DE FALLA (kV)
B7: FALLA | C7: CONCESIONARIA LINEA DE TRANSMISION CCNCM S.A.C. | D7: CACLIC - BELAUNDE TERRY | E7: LINEA DE TRANSMISION | F7: L-2194 | G7: 27/10/2025 18:27:50 | H7: 27/10/2025 18:32:24 | I7: DESCONEXIÓN DE LA LÍNEA L-2194 (CÁCLIC - BELAUNDE TERRY) DE 220 KV | J7: 57.81 | K7: SI | L7: 220
B8: EVENTO | C8: CONELSUR LT SAC | D8: PORTILLO | E8: SUBESTACION | F8: SS.EE. | G8: 27/10/2025 08:34:00 | H8: 28/10/2025 00:00:00 | I8: DECLARACIÓN DE SITUACIÓN EXCEPCIONAL EN LA S.E. PORTILLO 60 kV | K8: NO
B9: EVENTO | C9: ELECTRO ORIENTE | D9: BELAUNDE TERRY - TARAPOTO | E9: LINEA DE TRANSMISION | F9: L-1018 | G9: 27/10/2025 18:00:00 | H9: 27/10/2025 18:27:00 | I9: DECLARACIÓN DE SITUACIÓN EXCEPCIONAL EN LA LÍNEA L-1018 (BELAUNDE TERRY - TARAPOTO) DE 138 kV | K9: NO
B10: FALLA | C10: GENERACIÓN ANDINA S.A.C. | D10: TINGO MARÍA - 8 DE AGOSTO | E10: LINEA DE TRANSMISION | F10: L-1145 | G10: 27/10/2025 01:32:32 | H10: 27/10/2025 01:32:32 | I10: RECIERRE EXITOSO EN LA LÍNEA L-1145 (TINGO MARÍA - 8 DE AGOSTO) DE 138 KV | K10: NO | L10: 138
B11: FALLA | C11: INVERSIONES SHAQSHA S.A.C. | D11: COBRIZA I - COBRIZA II | E11: LINEA DE TRANSMISION | F11: L-6602 | G11: 27/10/2025 17:41:39 | H11: 27/10/2025 17:42:45 | I11: DESCONEXIÓN DE LA LÍNEA L-6602 (COBRIZA I – COBRIZA II) DE 69 KV | J11: 6.5 | K11: SI | L11: 0
B12: FALLA | C12: KALLPA GENERACION S.A. | D12: SAN JOSE - SUNNY | E12: LINEA DE TRANSMISION | F12: L-2070 | G12: 27/10/2025 08:21:00 | H12: 27/10/2025 10:40:00 | I12: DESCONEXIÓN DE LA LÍNEA L-2070 (SAN JOSÉ - SUNNY) DE 220 KV | K12: SI | L12: 220
B13: FALLA | C13: LINEAS ANDINAS SECUNDARIAS S.A.C. | D13: CARHUAMAYO - HUARÓN | E13: LINEA DE TRANSMISION | F13: L-6514 | G13: 27/10/2025 12:49:02 | H13: 27/10/2025 12:50:14 | I13: DESCONEXIÓN DE LAS LÍNEAS L-6514/L-6516 (CARHUAMAYO - HUARÓN - EXCELSIOR) DE 50 KV | J13: 8.49 | K13: SI | L13: 50
B14: EVENTO | C14: RED DE ENERGIA DEL PERU S.A. | D14: TINGO MARÍA - AUCAYACU | E14: LINEA DE TRANSMISION | F14: L-1122 | G14: 27/10/2025 18:48:00 | H14: 27/10/2025 21:20:00 | I14: DECLARACIÓN DE SITUACIÓN EXCEPCIONAL EN LA LÍNEA L-1122 (TINGO MARÍA - AUCAYACU) DE 138 kV | K14: NO
B15: FALLA | C15: RED DE ENERGIA DEL PERU S.A. | D15: PIURA OESTE | E15: REACTOR | F15: R-7 | G15: 27/10/2025 01:47:49 | H15: 27/10/2025 12:08:00 | I15: DESCONEXIÓN DEL REACTOR R-7 DE LA S.E. PIURA OESTE | K15: NO | L15: 220

Sheet RESTRIC_OPE
B3: lunes, 27 de Octubre del 2025
B5: RESTRICCIONES OPERATIVAS
B6: FECHA | C6: HORA INICIO | D6: HORA FINAL | E6: EMPRESA | F6: UBICACIÓN | G6: T.Eq. | H6: EQUIPO | I6: DESCRIPCIÓN
B7: 27/10/2025 | C7: 00:00 | D7: 24:00 | E7: EGASA | F7: S.E. CONVERTIDOR | G7: BARRA | H7: BARRA138KV | I7: EGASA limitó la capacidad del transformador 138 kV/33 kV a 50 MVA por deterioro del aislamiento.
B8: 27/10/2025 | C8: 00:00 | D8: 24:00 | E8: ELECTROPERU | F8: C.H. MANTARO | G8: CH | H8: CENTRAL | I8: De acuerdo con el correo del día 25.08.2025, la central tiene una limitación de potencia máxima de 650 MW por seguridad de la central.
B9: 27/10/2025 | C9: 00:00 | D9: 24:00 | E9: ENEL GENERACION PIURA S.A. | F9: C.T. MALACAS | G9: CT | H9: CENTRAL | I9: De acuerdo con la comunicación vía correo del día 24.10.2024. ENEL GENERACIÓN PIURA informa una restricción de potencia para alcanzar 105 MW en simultaneo (TG6+TGN4).
B10: 27/10/2025 | C10: 00:00 | D10: 24:00 | E10: ENEL GENERACION PIURA S.A. | F10: C.T. MALACAS | G10: GT | H10: TG4 | I10: De acuerdo a lo informado mediante correo electronico el día 04.07, la uniadTG4 puede operar a potencia efectiva durante 3 horas o con 80MW durante 4 horas, y el resto de los periodos a mínima generación.
B11: 27/10/2025 | C11: 00:00 | D11: 24:00 | E11: ENGIE ENERGIA PERU S.A.A. | F11: C.H. YUNCÁN | G11: GH | H11: G3 | I11: Según la carta N° ENG/ 198-2024 enviada por su representada, se opera de forma continua el G3 de la CH Yuncán, debido a la ejecución de mantenimientos necesarios para evitar daños en los sellos de seguridad de la válvula esférica del grupo.
B12: 27/10/2025 | C12: 00:00 | D12: 24:00 | E12: ENGIE ENERGIA PERU S.A.A. | F12: C.T. CHILCA 1 | G12: CT | H12: CENTRAL | I12: Restricción de temperatura de la C.T Chilca, ver valor en el modelo de despacho.
B13: 27/10/2025 | C13: 00:00 | D13: 24:00 | E13: ENGIE ENERGIA PERU S.A.A. | F13: C.T. CHILCA 1 | G13: CT | H13: CENTRAL | I13: Con carta ENG/971-2023, indica que no puede cumplir con las IO considerada en el PDO_17122023 dado que vulneran la seguridad de sus activos. Indican que se debe tomar TMO=168h.
B14: 27/10/2025 | C14: 00:00 | D14: 24:00 | E14: ENGIE ENERGIA PERU S.A.A. | F14: C.T. CHILCA 2 | G14: CT | H14: CENTRAL | I14: Con carta ENG/971-2023, indica que no puede cumplir con las IO considerada en el PDO_17122023 dado que vulneran la seguridad de sus activos. Indican que se debe tomar TMO=168h.
B15: 27/10/2025 | C15: 00:00 | D15: 24:00 | E15: FENIX POWER PERÚ | F15: C.T. FENIX | G15: CT | H15: CENTRAL | I15: De acuerdo con lo comunicado en el correo del día 06.05.2024, la CT Fenix cuenta con TMO de 168 hrs en todos su modos de operación.
B16: 27/10/2025 | C16: 00:00 | D16: 24:00 | E16: KALLPA GENERACION S.A. | F16: C.H. MINI CENTRAL CERRO DEL AGUILA | G16: CH | H16: CENTRAL | I16: Caudal ecológico de la Mini CH Cerro del Águila es de 6.1 m3/s correspondiente al mes de setiembre.
B17: 27/10/2025 | C17: 00:00 | D17: 24:00 | E17: KALLPA GENERACION S.A. | F17: C.H. MINI CENTRAL CERRO DEL AGUILA | G17: CH | H17: CENTRAL | I17: De acuerdo con lo informado por Kallpa el día 20.08.2025, la MCH Cerro del Águila tiene TA=0.07h, TMO=0.08h, TMA=0.16h.
... B47: 27/10/2025 | C47: 00:00 | D47: 24:00 | E47: UNACEM PERU S.A. | F47: S.E. CONDORCOCHA | G47: TRAFO3D | H47: T-3 138/44 kV | I47: De acuerdo con lo comunicado UNACEM mediante el informe INF_00142-2025, la transformador T3 de la SE Condorcocha esta limitado al 50% de su capacidad.

Sheet MANTENIMIENTO EJECUTADOS
B3: lunes, 27 de Octubre del 2025
B5: Mantenimiento Ejecutado
B6: Empresa | C6: Ubicación | D6: Equipo | E6: Inicio | F6: Final | G6: Descripción | H6: MW Indisp. | I6: Prog. | J6: Dispon | K6: Interrupc. | L6: Tipo | M6: CodEq | N6: TipoEq_Osinerg
B7: ATLANTICA TRANSMISION SUR S.A. | C7: CHILCA CTM - POROMA | D7: L-5032 | E7: 27/10/2025 07:33 | F7: 27/10/2025 17:20 | G7: Mejoramiento de PAT | H7: 0 | I7: P | J7: E/S | K7: N | L7: PREV. | M7: 13652 | N7: T
B8: ATLANTICA TRANSMISION SUR S.A. | C8: CHILCA CTM - POROMA | D8: L-5032 | E8: 27/10/2025 08:00 | F8: 27/10/2025 16:47 | G8: Mantenimiento de pedestales. | H8: 0 | I8: P | J8: E/S | K8: N | L8: PREV. | M8: 13652 | N8: T
B9: ATLANTICA TRANSMISION SUR S.A. | C9: OCONA | D9: INT-5450 | E9: 27/10/2025 00:00 | F9: 28/10/2025 00:00 | G9: Interruptor INT-5450 cerrado con restriccion operativa, REB-5450 en servicio y suministrando los SS.AA. de la S.E. Oco?a. | H9: 0 | I9: P | J9: E/S | K9: N | L9: OTROS | M9: 13761 | N9: T
B10: ATLANTICA TRANSMISION SUR S.A. | C10: POROMA | D10: INT-5371 | E10: 27/10/2025 00:00 | F10: 28/10/2025 00:00 | G10: Seccionador SBB-5371 fase T indisponible por problemas mecanicos, el seccionador permanece cerrado y bloqueado | H10: 0 | I10: P | J10: E/S | K10: N | L10: OTROS | M10: 13751 | N10: T
B11: ATLANTICA TRANSMISION SUR S.A. | C11: POROMA | D11: REB-5350 | E11: 27/10/2025 00:00 | F11: 28/10/2025 00:00 | G11: Fuera de servicio po falla en el equipo. | H11: 0 | I11: P | J11: F/S | K11: N | L11: OTROS | M11: 13771 | N11: T
B12: ATLANTICA TRANSMISION SUR S.A. | C12: POROMA | D12: AUT-5371 | E12: 27/10/2025 08:46 | F12: 27/10/2025 15:35 | G12: MANTENIMIENTO PREVENTIVO EN AUTOTRANSFORMADOR Y EQUIPOS DE CELDA | H12: 0 | I12: P | J12: F/S | K12: N | L12: PRUEBA | M12: 13783 | N12: T
B13: ATLANTICA TRANSMISION SUR S.A. | C13: POROMA | D13: BARRA A_220KV | E13: 27/10/2025 08:49 | F13: 27/10/2025 15:18 | G13: Mantenimiento en equipos del AUT5371 asociados a la barra A | H13: 0 | I13: P | J13: F/S | K13: N | L13: PREV. | M13: 13860 | N13: T
B14: ATLANTICA TRANSMISION SUR S.A. | C14: POROMA | D14: REL-5381 | E14: 27/10/2025 10:56 | F14: 27/10/2025 16:50 | G14: Extraccion de muestras de aceite. | H14: 0 | I14: P | J14: E/S | K14: N | L14: PREV. | M14: 13772 | N14: T
B15: ATN S.A. | C15: KIMAN AYLLU | D15: AUT-501 | E15: 27/10/2025 00:00 | F15: 28/10/2025 00:00 | G15: Restriccion Operativa en el circuito de control de cambiador de tap s del AUT-501 | H15: 0 | I15: P | J15: E/S | K15: N | L15: OTROS | M15: 13099 | N15: T
B16: CONCESIONARIA LINEA DE TRANSMISION LA NI?A S.A.C. | C16: ALIPIO ROSALES | D16: SS.EE. | E16: 27/10/2025 00:00 | F16: 28/10/2025 00:00 | G16: DIFERENCIAL DE BARRAS DESHABILITADO 220KV A SOLICITUD DE LA EMPRESA ACCIONA HASTA EL INICIO DE SU OPERACION EXPERIMENTAL POR LA INCORPORACION DE SU NUEVA BAHIA | H16: 0 | I16: P | J16: E/S | K16: N | L16: OTROS | M16: 24127 | N16: T
B17: CONCESIONARIA TRANSMISORA REQUE TUMBES S.A.C. | C17: ALIPIO ROSALES | D17: TR-2306 | E17: 27/10/2025 00:00 | F17: 28/10/2025 00:00 | G17: Pruebas previas a su integracion. | H17: 0 | I17: P | J17: E/S | K17: N | L17: P.ENERG | M17: 26657 | N17: T
B18: CONELSUR LT SAC | C18: CALLAHUANCA (CNS) | D18: S.E. | E18: 27/10/2025 00:00 | F18: 28/10/2025 00:00 | G18: RELE DIFERENCIAL DE BARRAS DE CALLAHUANCA 220KV INOPERATIVO | H18: 0 | I18: F | J18: E/S | K18: N | L18: OTROS | M18: 316 | N18: T
... B116: TRANSMANTARO | C116: YARABAMBA | D116: IN-5120 | E116: 27/10/2025 00:00 | F116: 28/10/2025 00:00 | G116: INTERRUPTOR INDISPONIBLE POR FALLA EN LOS MANDOS DE CONTROL DE N1, N2 Y N3. | H116: 0 | I116: P | J116: F/S | K116: N | L116: OTROS | M116: 17437 | N116: T

Sheet INGRESO OC
A3: lunes, 27 de Octubre del 2025
A5: INGRESO A OPERACIÓN COMERCIAL
A6: EMPRESA | B6: TIPO DE EQUIPO | C6: UBICACIÓN | D6: EQUIPO | E6: Fecha y hora de Ingreso a Operación Comercial

Sheet DESPACHO_EJECUTADO
B3: lunes, 27 de Octubre del 2025
A5: POTENCIA ACTIVA EJECUTADA DE LAS UNIDADES DE GENERACIÓN DEL SEIN (MW) | FM5: CENTRALES NO INTEGRANTES COES
A6: FECHA | B6: HORA | C6: 65333 | D6: 101 | E6: 102 | F6: 42667 | G6: 42668 | H6: 126 | I6: 127 | J6: 138 | K6: 139 | L6: 197 | M6: 203 | N6: 204 | O6: 230 | P6: 209 | Q6: 56677 | R6: 796 | S6: 2146 | T6: 142 | U6: 143 | V6: 125 | W6: 187 | X6: 163 | Y6: 298 | Z6: 299 | AA6: 219 | AB6: 151 | AC6: 152 | AD6: 153 | AE6: 154 | AF6: 756 | AG6: 156 | AH6: 155 | AI6: 182 | AJ6: 212 | AK6: 758 | AL6: 263 | AM6: 265 | AN6: 775 | AO6: 777 | AP6: 2154 | AQ6: 150 | AR6: 149 | AS6: 188 | AT6: 2131 | AU6: 755 | AV6: 252 | AW6: 249 | AX6: 250 | AY6: 117 | AZ6: 267 | BA6: 268 | BB6: 119 | BC6: 120 | BD6: 189 | BE6: 122 | BF6: 266 | BG6: 337 | BH6: 338 | BI6: 251 | BJ6: 115 | BK6: 239 | BL6: 288 | BM6: 240 | BN6: 241 | BO6: 242 | BP6: 191 | BQ6: 194 | BR6: 196 | BS6: 207 | BT6: 236 | BU6: 795 | BV6: 285 | BW6: 995 | BX6: 996 | BY6: 997 | BZ6: 766 | CA6: 926 | CB6: 924 | CC6: 121 | CD6: 103 | CE6: 104 | CF6: 106 | CG6: 105 | CH6: 107 | CI6: 110 | CJ6: 109 | CK6: 144 | CL6: 113 | CM6: 114 | CN6: 193 | CO6: 208 | CP6: 786 | CQ6: 787 | CR6: 788 | CS6: 789 | CT6: 248 | CU6: 2159 | CV6: 303 | CW6: 59715 | CX6: 62255 | CY6: 1263 | CZ6: 61800 | DA6: 2194 | DB6: 69125 | DC6: 216 | DD6: 198 | DE6: 70400 | DF6: 49607 | DG6: 214 | DH6: 260 | DI6: 2152 | DJ6: 2128 | DK6: 247 | DL6: 228 | DM6: 2135 | DN6: 261 | DO6: 237 | DP6: 253 | DQ6: 770 | DR6: 235 | DS6: 238 | DT6: 2184 | DU6: 61855 | DV6: 223 | DW6: 226 | DX6: 201 | DY6: 258 | DZ6: 259 | EA6: 920 | EB6: 257 | EC6: 256 | ED6: 2148 | EE6: 58288 | EF6: 58289 | EG6: 58839 | EH6: 58840 | EI6: 296 | EJ6: 297 | EK6: 211 | EL6: 2175 | EM6: 2178 | EN6: 2181 | EO6: 1262 | EP6: 63425 | EQ6: 233 | ER6: 2150 | ES6: 2165 | ET6: 2161 | EU6: 61197 | EV6: 58851 | EW6: 225 | EX6: 2201 | EY6: 2171 | EZ6: 760 | FA6: 234 | FB6: 215 | FC6: 917 | FD6: 289 | FE6: 58333 | FF6: 58336 | FG6: 213 | FH6: 232 | FI6: 2190 | FJ6: 69867 | FK6: TOTAL COES | FM6: 221 | FN6: 222 | FO6: 224 | FP6: 2187 | FQ6: 227 | FR6: 49400 | FS6: 199 | FT6: 200 | FU6: TOTAL NO COES
C7: SUR | D7: CENTRO | E7: CENTRO | F7: NORTE | G7: NORTE | H7: NORTE | I7: NORTE | J7: CENTRO | K7: CENTRO | L7: CENTRO | M7: CENTRO | N7: CENTRO | O7: CENTRO | P7: CENTRO | Q7: CENTRO | R7: CENTRO | S7: CENTRO | T7: CENTRO | U7: CENTRO | V7: CENTRO | W7: CENTRO | X7: SUR | Y7: SUR | Z7: SUR | AA7: CENTRO | AB7: SUR | AC7: SUR | AD7: SUR | AE7: SUR | AF7: SUR | AG7: SUR | AH7: SUR | AI7: SUR | AJ7: CENTRO | AK7: NORTE | AL7: NORTE | AM7: NORTE | AN7: CENTRO | AO7: CENTRO | AP7: CENTRO | AQ7: CENTRO | AR7: CENTRO | AS7: CENTRO | AT7: CENTRO | AU7: SUR | AV7: CENTRO | AW7: CENTRO | AX7: CENTRO | AY7: CENTRO | AZ7: CENTRO | BA7: CENTRO | BB7: CENTRO | BC7: CENTRO | BD7: SUR | BE7: NORTE | BF7: CENTRO | BG7: CENTRO | BH7: CENTRO | BI7: CENTRO | BJ7: NORTE | BK7: NORTE | BL7: NORTE | BM7: SUR | BN7: SUR | BO7: SUR | BP7: CENTRO | BQ7: CENTRO | BR7: CENTRO | BS7: CENTRO | BT7: CENTRO | BU7: CENTRO | BV7: CENTRO | BW7: SUR | BX7: SUR | BY7: SUR | BZ7: NORTE | CA7: SUR | CB7: CENTRO | CC7: NORTE | CD7: CENTRO | CE7: CENTRO | CF7: CENTRO | CG7: CENTRO | CH7: CENTRO | CI7: CENTRO | CJ7: CENTRO | CK7: CENTRO | CL7: CENTRO | CM7: CENTRO | CN7: CENTRO | CO7: CENTRO | CP7: SUR | CQ7: SUR | CR7: SUR | CS7: SUR | CT7: CENTRO | CU7: CENTRO | CV7: CENTRO | CW7: CENTRO | CX7: SUR | CY7: NORTE | CZ7: NORTE | DA7: NORTE | DB7: CENTRO | DC7: NORTE | DD7: NORTE | DE7: SUR | DF7: SUR | DG7: CENTRO | DH7: CENTRO | DI7: CENTRO | DJ7: NORTE | DK7: NORTE | DL7: CENTRO | DM7: CENTRO | DN7: SUR | DO7: SUR | DP7: CENTRO | DQ7: CENTRO | DR7: SUR | DS7: CENTRO | DT7: CENTRO | DU7: NORTE | DV7: CENTRO | DW7: CENTRO | DX7: NORTE | DY7: CENTRO | DZ7: CENTRO | EA7: CENTRO | EB7: NORTE | EC7: NORTE | ED7: SUR | EE7: CENTRO | EF7: CENTRO | EG7: CENTRO | EH7: CENTRO | EI7: CENTRO | EJ7: CENTRO | EK7: SUR | EL7: SUR | EM7: SUR | EN7: SUR | EO7: NORTE | EP7: SUR | EQ7: SUR | ER7: SUR | ES7: CENTRO | ET7: CENTRO | EU7: CENTRO | EV7: SUR | EW7: CENTRO | EX7: CENTRO | EY7: CENTRO | EZ7: CENTRO | FA7: SUR | FB7: NORTE | FC7: CENTRO | FD7: NORTE | FE7: NORTE | FF7: NORTE | FG7: CENTRO | FH7: NORTE | FI7: NORTE | FJ7: NORTE | FM7: NORTE | FN7: CENTRO | FO7: NORTE | FP7: NORTE | FQ7: NORTE | FR7: NORTE | FS7: NORTE | FT7: NORTE
C8: HIDROELÉCTRICA | D8: HIDROELÉCTRICA | E8: HIDROELÉCTRICA | F8: TERMOELÉCTRICA | G8: TERMOELÉCTRICA | H8: HIDROELÉCTRICA | I8: HIDROELÉCTRICA | J8: TERMOELÉCTRICA | K8: TERMOELÉCTRICA | L8: TERMOELÉCTRICA | M8: TERMOELÉCTRICA | N8: TERMOELÉCTRICA | O8: TERMOELÉCTRICA | P8: TERMOELÉCTRICA | Q8: TERMOELÉCTRICA | R8: HIDROELÉCTRICA | S8: HIDROELÉCTRICA | T8: TERMOELÉCTRICA | U8: TERMOELÉCTRICA | V8: TERMOELÉCTRICA | W8: TERMOELÉCTRICA | X8: HIDROELÉCTRICA | Y8: HIDROELÉCTRICA | Z8: HIDROELÉCTRICA | AA8: TERMOELÉCTRICA | AB8: HIDROELÉCTRICA | AC8: HIDROELÉCTRICA | AD8: HIDROELÉCTRICA | AE8: HIDROELÉCTRICA | AF8: TERMOELÉCTRICA | AG8: TERMOELÉCTRICA | AH8: TERMOELÉCTRICA | AI8: HIDROELÉCTRICA | AJ8: HIDROELÉCTRICA | AK8: TERMOELÉCTRICA | AL8: TERMOELÉCTRICA | AM8: TERMOELÉCTRICA | AN8: HIDROELÉCTRICA | AO8: HIDROELÉCTRICA | AP8: HIDROELÉCTRICA | AQ8: HIDROELÉCTRICA | AR8: HIDROELÉCTRICA | AS8: HIDROELÉCTRICA | AT8: HIDROELÉCTRICA | AU8: HIDROELÉCTRICA | AV8: TERMOELÉCTRICA | AW8: TERMOELÉCTRICA | AX8: TERMOELÉCTRICA | AY8: HIDROELÉCTRICA | AZ8: HIDROELÉCTRICA | BA8: HIDROELÉCTRICA | BB8: HIDROELÉCTRICA | BC8: HIDROELÉCTRICA | BD8: HIDROELÉCTRICA | BE8: HIDROELÉCTRICA | BF8: HIDROELÉCTRICA | BG8: HIDROELÉCTRICA | BH8: HIDROELÉCTRICA | BI8: HIDROELÉCTRICA | BJ8: TERMOELÉCTRICA | BK8: TERMOELÉCTRICA | BL8: TERMOELÉCTRICA | BM8: TERMOELÉCTRICA | BN8: TERMOELÉCTRICA | BO8: TERMOELÉCTRICA | BP8: HIDROELÉCTRICA | BQ8: TERMOELÉCTRICA | BR8: TERMOELÉCTRICA | BS8: TERMOELÉCTRICA | BT8: TERMOELÉCTRICA | BU8: TERMOELÉCTRICA | BV8: TERMOELÉCTRICA | BW8: TERMOELÉCTRICA | BX8: TERMOELÉCTRICA | BY8: TERMOELÉCTRICA | BZ8: HIDROELÉCTRICA | CA8: TERMOELÉCTRICA | CB8: TERMOELÉCTRICA | CC8: HIDROELÉCTRICA | CD8: HIDROELÉCTRICA | CE8: HIDROELÉCTRICA | CF8: HIDROELÉCTRICA | CG8: HIDROELÉCTRICA | CH8: HIDROELÉCTRICA | CI8: TERMOELÉCTRICA | CJ8: TERMOELÉCTRICA | CK8: TERMOELÉCTRICA | CL8: TERMOELÉCTRICA | CM8: TERMOELÉCTRICA | CN8: TERMOELÉCTRICA | CO8: TERMOELÉCTRICA | CP8: TERMOELÉCTRICA | CQ8: TERMOELÉCTRICA | CR8: TERMOELÉCTRICA | CS8: TERMOELÉCTRICA | CT8: TERMOELÉCTRICA | CU8: TERMOELÉCTRICA | CV8: SOLAR | CW8: EÓLICA | CX8: SOLAR | CY8: EÓLICA | CZ8: SOLAR | DA8: HIDROELÉCTRICA | DB8: HIDROELÉCTRICA | DC8: HIDROELÉCTRICA | DD8: HIDROELÉCTRICA | DE8: SOLAR | DF8: HIDROELÉCTRICA | DG8: HIDROELÉCTRICA | DH8: HIDROELÉCTRICA | DI8: HIDROELÉCTRICA | DJ8: HIDROELÉCTRICA | DK8: HIDROELÉCTRICA | DL8: HIDROELÉCTRICA | DM8: HIDROELÉCTRICA | DN8: SOLAR | DO8: SOLAR | DP8: EÓLICA | DQ8: EÓLICA | DR8: SOLAR | DS8: HIDROELÉCTRICA | DT8: HIDROELÉCTRICA | DU8: HIDROELÉCTRICA | DV8: HIDROELÉCTRICA | DW8: HIDROELÉCTRICA | DX8: HIDROELÉCTRICA | DY8: HIDROELÉCTRICA | DZ8: HIDROELÉCTRICA | EA8: HIDROELÉCTRICA | EB8: EÓLICA | EC8: EÓLICA | ED8: SOLAR | EE8: EÓLICA | EF8: EÓLICA | EG8: EÓLICA | EH8: EÓLICA | EI8: HIDROELÉCTRICA | EJ8: HIDROELÉCTRICA | EK8: HIDROELÉCTRICA | EL8: HIDROELÉCTRICA | EM8: HIDROELÉCTRICA | EN8: HIDROELÉCTRICA | EO8: EÓLICA | EP8: SOLAR | EQ8: SOLAR | ER8: SOLAR | ES8: HIDROELÉCTRICA | ET8: EÓLICA | EU8: EÓLICA | EV8: SOLAR | EW8: TERMOELÉCTRICA | EX8: TERMOELÉCTRICA | EY8: TERMOELÉCTRICA | EZ8: TERMOELÉCTRICA | FA8: SOLAR | FB8: HIDROELÉCTRICA | FC8: HIDROELÉCTRICA | FD8: TERMOELÉCTRICA | FE8: TERMOELÉCTRICA | FF8: TERMOELÉCTRICA | FG8: TERMOELÉCTRICA | FH8: TERMOELÉCTRICA | FI8: TERMOELÉCTRICA | FJ8: TERMOELÉCTRICA | FM8: HIDROELÉCTRICA | FN8: HIDROELÉCTRICA | FO8: HIDROELÉCTRICA | FP8: HIDROELÉCTRICA | FQ8: TERMOELÉCTRICA | FR8: TERMOELÉCTRICA | FS8: HIDROELÉCTRICA | FT8: HIDROELÉCTRICA
C9: HYDRO GLOBAL PERÚ S.A.C. | D9: ELECTROPERU | E9: ELECTROPERU | F9: ELECTROPERU | G9: ELECTROPERU | H9: ORAZUL ENERGY PERÚ | I9: ORAZUL ENERGY PERÚ | J9: TERMOSELVA | K9: TERMOSELVA | L9: KALLPA GENERACION S.A. | M9: KALLPA GENERACION S.A. | N9: KALLPA GENERACION S.A. | O9: KALLPA GENERACION S.A. | P9: KALLPA GENERACION S.A. | Q9: KALLPA GENERACION S.A. | R9: KALLPA GENERACION S.A. | S9: KALLPA GENERACION S.A. | T9: SHOUGESA | U9: SHOUGESA | V9: SHOUGESA | W9: SHOUGESA | X9: EGEMSA | Y9: EGESUR | Z9: EGESUR | AA9: EGESUR | AB9: EGASA | AC9: EGASA | AD9: EGASA | AE9: EGASA | AF9: EGASA | AG9: EGASA | AH9: EGASA | AI9: SAN GABAN | AJ9: CELEPSA | AK9: MINERA CERRO VERDE | AL9: PLANTA DE RESERVA FRIA DE GENERACION DE ETEN S.A. | AM9: PLANTA DE RESERVA FRIA DE GENERACION DE ETEN S.A. | AN9: EMPRESA DE GENERACION HUALLAGA | AO9: EMPRESA DE GENERACION HUALLAGA | AP9: LA VIRGEN | AQ9: CHINANGO S.A.C. | AR9: CHINANGO S.A.C. | AS9: HIDROELECTRICA HUANCHOR S.A.C. | AT9: CELEPSA RENOVABLES S.R.L. | AU9: INLAND ENERGY SAC | AV9: FENIX POWER PERÚ | AW9: FENIX POWER PERÚ | AX9: FENIX POWER PERÚ | AY9: STATKRAFT S.A | AZ9: STATKRAFT S.A | BA9: STATKRAFT S.A | BB9: STATKRAFT S.A | BC9: STATKRAFT S.A | BD9: STATKRAFT S.A | BE9: STATKRAFT S.A | BF9: STATKRAFT S.A | BG9: CENTRALES SANTA ROSA S.A.C. | BH9: CENTRALES SANTA ROSA S.A.C. | BI9: EMPRESA DE GENERACION HUANZA | BJ9: ENEL GENERACION PIURA S.A. | BK9: ENEL GENERACION PIURA S.A. | BL9: ENEL GENERACION PIURA S.A. | BM9: ENGIE ENERGIA PERU S.A.A. | BN9: ENGIE ENERGIA PERU S.A.A. | BO9: ENGIE ENERGIA PERU S.A.A. | BP9: ENGIE ENERGIA PERU S.A.A. | BQ9: ENGIE ENERGIA PERU S.A.A. | BR9: ENGIE ENERGIA PERU S.A.A. | BS9: ENGIE ENERGIA PERU S.A.A. | BT9: ENGIE ENERGIA PERU S.A.A. | BU9: ENGIE ENERGIA PERU S.A.A. | BV9: ENGIE ENERGIA PERU S.A.A. | BW9: ENGIE ENERGIA PERU S.A.A. | BX9: ENGIE ENERGIA PERU S.A.A. | BY9: ENGIE ENERGIA PERU S.A.A. | BZ9: ENGIE ENERGIA PERU S.A.A. | CA9: INFRAESTRUCTURAS Y ENERGIAS DEL PERU S.A.C. | CB9: INFRAESTRUCTURAS Y ENERGIAS DEL PERU S.A.C. | CC9: INVERSIONES SHAQSHA S.A.C. | CD9: ORYGEN PERU S.A.A. | CE9: ORYGEN PERU S.A.A. | CF9: ORYGEN PERU S.A.A. | CG9: ORYGEN PERU S.A.A. | CH9: ORYGEN PERU S.A.A. | CI9: ORYGEN PERU S.A.A. | CJ9: ORYGEN PERU S.A.A. | CK9: ORYGEN PERU S.A.A. | CL9: ORYGEN PERU S.A.A. | CM9: ORYGEN PERU S.A.A. | CN9: ORYGEN PERU S.A.A. | CO9: ORYGEN PERU S.A.A. | CP9: SAMAY I S.A.C | CQ9: SAMAY I S.A.C | CR9: SAMAY I S.A.C | CS9: SAMAY I S.A.C | CT9: TERMOCHILCA S.A.C. | CU9: TERMOCHILCA S.A.C. | CV9: COLCA SOLAR S.A.C. | CW9: ENERGIA RENOVABLE DEL SUR S.A. | CX9: GR CORTARRAMA SOCIEDAD ANONIMA CERRADA | CY9: GR TARUCA SOCIEDAD ANONIMA CERRADA | CZ9: KONDU SAC | DA9: PERUANA DE INVERSIONES EN ENERGIAS RENOVABLES S.A. | DB9: VARI ENERGIA S.A.C. | DC9: ORAZUL ENERGY PERÚ | DD9: ORAZUL ENERGY PERÚ | DE9: KALLPA GENERACION S.A. | DF9: SAN GABAN | DG9: MAJA ENERGIA S.A.C. | DH9: EMPRESA DE GENERACION ELECTRICA CANCHAYLLO SAC | DI9: EMPRESA DE GENERACION ELECTRICA SANTA ANA S.A.C. | DJ9: EMPRESA ELECTRICA AGUA AZUL | DK9: EMPRESA ELECTRICA RIO DOBLE | DL9: HIDROCAÑETE S.A. | DM9: HUAURA POWER GROUP S.A. | DN9: MOQUEGUA FV S.A.C. | DO9: PANAMERICANA SOLAR SAC. | DP9: PARQUE EOLICO MARCONA S.A.C. | DQ9: PARQUE EOLICO TRES HERMANAS S.A.C. | DR9: TACNA SOLAR SAC. | DS9: ELECTRICA YANAPAMPA SAC | DT9: ANDEAN POWER S.A.C. | DU9: ASOCIACIÓN SANTA LUCIA DE CHACAS | DV9: ATRIA ENERGIA S.A.C. | DW9: EGEJUNIN | DX9: EGEJUNIN | DY9: EGEJUNIN | DZ9: EGEJUNIN | EA9: EMPRESA DE GENERACION ELECTRICA RIO BAÑOS S.A.C. | EB9: ENERGÍA EÓLICA S.A. | EC9: ENERGÍA EÓLICA S.A. | ED9: ENGIE ENERGIA PERU S.A.A. | EE9: ENGIE ENERGIA PERU S.A.A. | EF9: ENGIE ENERGIA PERU S.A.A. | EG9: ENGIE ENERGIA PERU S.A.A. | EH9: ENGIE ENERGIA PERU S.A.A. | EI9: GENERACIÓN ANDINA S.A.C. | EJ9: GENERACIÓN ANDINA S.A.C. | EK9: GENERADORA DE ENERGÍA DEL PERÚ | EL9: GENERADORA DE ENERGÍA DEL PERÚ | EM9: GENERADORA DE ENERGÍA DEL PERÚ | EN9: GENERADORA DE ENERGÍA DEL PERÚ | EO9: GR PAINO SOCIEDAD ANONIMA CERRADA | EP9: JOYA SOLAR S.A.C. | EQ9: MAJES ARCUS S.A.C. | ER9: ORYGEN PERU S.A.A. | ES9: ORYGEN PERU S.A.A. | ET9: ORYGEN PERU S.A.A. | EU9: ORYGEN PERU S.A.A. | EV9: ORYGEN PERU S.A.A. | EW9: PETRAMAS | EX9: PETRAMAS | EY9: PETRAMAS | EZ9: PETRAMAS | FA9: REPARTICIÓN ARCUS S.A.C. | FB9: SINERSA | FC9: SINERSA | FD9: BIOENERGIA DEL CHIRA S.A. | FE9: GM OPERACIONES S.A.C. | FF9: GM OPERACIONES S.A.C. | FG9: AGRO INDUSTRIAL PARAMONGA S.A. | FH9: AGROAURORA S.A.C. | FI9: AGROINDUSTRIAS SAN JACINTO S.A.A. | FJ9: AGROLMOS SOCIEDAD ANONIMA - AGROLMOS S.A. | FM9: UNACEM PERU S.A. | FN9: ELECTRO ORIENTE | FO9: AGUAS Y ENERGIA PERU | FP9: ELECTRO ZAÑA S.A.C. | FQ9: ELECTRONOROESTE S.A. | FR9: SDE PIURA | FS9: SINERSA | FT9: SINERSA
C10: SAN GABAN III | D10: MANTARO | E10: RESTITUCION | F10: TUMBES MAK 1 | G10: TUMBES MAK 2 | H10: CARHUAQUERO | I10: CAÑON DEL PATO | J10: AGUAYTIA TG1 | K10: AGUAYTIA TG2 | L10: KALLPA TG1 | M10: KALLPA TG2 | N10: KALLPA TG3 | O10: KALLPA TV | P10: LFLORES TG1 | Q10: LFLORES TV | R10: CERRO DEL AGUILA | S10: CERRODELAGUILAG4 | T10: SHOUGESA TV1 | U10: SHOUGESA TV2 | V10: SHOUGESA TV3 | W10: SHOUGESA CUMMINS | X10: MACHUPICCHU | Y10: ARICOTA 1 | Z10: ARICOTA 2 | AA10: INDEPENDENCIA | AB10: CHARCANI I,II,III | AC10: CHARCANI IV | AD10: CHARCANI V | AE10: CHARCANI VI | AF10: CHILINA TG | AG10: MOLLENDO 1, 2, 3 | AH10: CHILINA (SULZ 1,2) | AI10: SAN GABAN II | AJ10: PLATANAL | AK10: RECKA | AL10: RF ETEN TG1 | AM10: RF ETEN TG2 | AN10: CHAGLLA GP1 | AO10: CHAGLLA | AP10: LA VIRGEN | AQ10: CHIMAY | AR10: YANANGO | AS10: HUANCHOR | AT10: MARAÑON | AU10: STA TERESA | AV10: FENIX GT11 | AW10: FENIX GT12 | AX10: FENIX TV10 | AY10: YAUPI | AZ10: OROYA | BA10: PACHACHACA | BB10: MALPASO | BC10: CAHUA | BD10: ARCATA | BE10: GALLITO CIEGO | BF10: CHEVES | BG10: SANTA ROSA 1 | BH10: SANTA ROSA 2 | BI10: HUANZA | BJ10: MALACAS2 TG4 | BK10: MALACAS3 TG 5 | BL10: MALACAS1 TG6 | BM10: RF ILO2 TG1 | BN10: RF ILO2 TG2 | BO10: RF ILO2 TG3 | BP10: YUNCAN | BQ10: CHILCA1 TG1 | BR10: CHILCA1 TG2 | BS10: CHILCA1 TG3 | BT10: CHILCA-TV | BU10: CHILCA2 TG41 | BV10: CHILCA2-TV | BW10: CTNEPI_TG41 | BX10: CTNEPI_TG42 | BY10: CTNEPI_TG43 | BZ10: QUITARACSA | CA10: RF PTO MALDONADO | CB10: RF PUCALLPA | CC10: PARIAC | CD10: HUINCO | CE10: MATUCANA | CF10: MOYOPAMPA | CG10: CALLAHUANCA | CH10: HUAMPANI | CI10: STA ROSA WEST TG7 | CJ10: UTI_5 | CK10: UTI_6 | CL10: VENTANILLA 3 | CM10: VENTANILLA 4 | CN10: VENTANILLA TV | CO10: STAROSA TG8 | CP10: PTO_BRVO TG1 | CQ10: PTO_BRVO TG2 | CR10: PTO_BRVO TG3 | CS10: PTO_BRVO TG4 | CT10: OLLEROS TG1 | CU10: OLLEROS TV | CV10: CS YARUCAYA | CW10: SAN JUAN | CX10: MATARANI | CY10: DUNA | CZ10: CARHUAQUERO (CS) | DA10: MANTA I | DB10: ANASHIRONI | DC10: CARHUAQUERO4 | DD10: CAÑA BRAVA | DE10: SUNNY | DF10: TUPURI | DG10: RONCADOR | DH10: CANCHAYLLO | DI10: RENOVANDESH1 | DJ10: POTRERO | DK10: PIZARRAS | DL10: NIMPERIAL | DM10: YARUCAYA | DN10: MOQUEGUA-SOLAR | DO10: PANAMERICANA-SOLAR | DP10: PQE-EOLICO-MARCONA | DQ10: PQE-EOLICO-3-HERMANAS | DR10: TACNA-SOLAR | DS10: YANAPAMPA | DT10: CARHUAC | DU10: HUALLIN | DV10: PURMACANA | DW10: HUASAHUASI | DX10: STACRUZ_1_2 | DY10: RUNATULLO_II | DZ10: RUNATULLO_III | EA10: RUCUY | EB10: PQE-EOLICO-TALARA | EC10: PQE-EOLICO-CUPISNIQUE | ED10: INTIPAMPA | EE10: PUNTA LOMITAS-BL1 | EF10: PUNTA LOMITAS-BL2 | EG10: PUN LOMITAS_EXP-BL1 | EH10: PUN LOMITAS_EXP-BL2 | EI10: 8AGOSTO | EJ10: EL CARMEN | EK10: LA JOYA | EL10: ANGEL_I | EM10: ANGEL_II | EN10: ANGEL_III | EO10: HUAMBOS | EP10: SAN MARTIN SOLAR | EQ10: MAJES | ER10: RUBI | ES10: CH_HER1 | ET10: WAYRA-I | EU10: WAYRA EXTENSION | EV10: CLEMESI | EW10: HUAYCOLORO | EX10: CALLAO | EY10: DONA_CATALINA | EZ10: LAGRINGAV | FA10: REPARTICION | FB10: POECHOS2 | FC10: CHANCAY | FD10: CANA BRAVA | FE10: REFINERIA TALARA TV1 | FF10: REFINERÍA TALARA TV2 | FG10: PARAMONGA | FH10: MAPLE | FI10: SAN_JACINTO | FJ10: AGROLMOS | FK10: MW | FM10: CARPAPATA | FN10: CENTRALES ELOR | FO10: PIAS1 | FP10: ZANA | FQ10: TABLAZO | FR10: TALLANCA | FS10: CURUMUY | FT10: POECHOS1 | FU10: MW
A11: 27/10/2025 | B11: 00:30 | C11: 144.8 | D11: 628.9 | E11: 213 | H11: 89.6 | I11: 207.1 | L11: 185.8 | M11: 192.8 | N11: 192.6 | O11: 284.4 | P11: 214.4 | Q11: 110.4 | R11: 366.4 | S11: 5.2 | X11: 165.4 | Y11: 7.2 | Z11: 5.7 | AB11: 6.9 | AC11: 11.6 | AD11: 71.9 | AI11: 79.7 | AJ11: 114.7 | AN11: 6.5 | AO11: 304.8 | AP11: 53.3 | AQ11: 76.5 | AR11: 27.5 | AS11: 18.2 | AT11: 18.8 | AU11: 91.4 | AY11: 105.8 | AZ11: 5.5 | BA11: 9.1 | BB11: 18.6 | BC11: 40.7 | BD11: 2 | BE11: 29.3 | BF11: 76.2 | BI11: 72.6 | BL11: 48 | BP11: 110.9 | BQ11: 62 | BR11: 11 | BS11: 200 | BT11: 87.4 | CC11: 4 | CD11: 128.5 | CE11: 83.4 | CF11: 64.2 | CG11: 48 | CH11: 29.9 | CL11: 145.9 | CM11: 147.1 | CN11: 149.5 | CT11: 0 | CU11: 0 | CV11: 0 | CW11: 34.7 | CX11: 0 | CY11: 0.8 | CZ11: 0 | DA11: 17.3 | DB11: 20.7 | DC11: 9.8 | DD11: 5.4 | DE11: 0 | DF11: 0.9 | DG11: 3.5 | DH11: 4.4 | DJ11: 16.5 | DK11: 18.9 | DL11: 3.6 | DM11: 18.6 | DN11: 0 | DO11: 0 | DP11: 9.2 | DQ11: 28.1 | DR11: 0 | DS11: 3.4 | DT11: 16.6 | DU11: 2.3 | DW11: 10.1 | DX11: 7.2 | DY11: 14.8 | DZ11: 20.2 | EA11: 20 | EB11: 11.9 | EC11: 22.1 | ED11: 0 | EE11: 85.3 | EF11: 81 | EG11: 7.3 | EH11: 4.6 | EI11: 20.9 | EJ11: 6.4 | EK11: 7.1 | EL11: 18 | EM11: 18.6 | EN11: 18.3 | EO11: 1.4 | EP11: 0 | EQ11: 0 | ER11: 0 | ES11: 0.6 | ET11: 30.7 | EU11: 18.7 | EV11: 0 | EW11: 2.9 | EX11: 1.1 | EY11: 2.4 | EZ11: 1.1 | FA11: 0 | FB11: 6.346 | FC11: 20.008 | FD11: 8.8 | FF11: 0 | FG11: 15.7 | FH11: 17.5 | FI11: 9.1 | FK11: 6299.954 | FM11: 21.4 | FN11: 0 | FO11: 5.9 | FP11: 13.2 | FQ11: 27.2 | FR11: 18 | FS11: 5.29 | FT11: 4.303 | FU11: 95.293
A12: 27/10/2025 | B12: 01:00 | C12: 91.5 | D12: 630.6 | E12: 214 | H12: 90.4 | I12: 207.3 | L12: 185.6 | M12: 189.4 | N12: 189.6 | O12: 280.3 | P12: 213.1 | Q12: 110.1 | R12: 369.6 | S12: 5.2 | X12: 168.1 | Y12: 8 | Z12: 5.8 | AB12: 6.9 | AC12: 11.6 | AD12: 72.4 | AI12: 80.4 | AJ12: 117.8 | AN12: 6.4 | AO12: 305 | AP12: 52.2 | AQ12: 76.5 | AR12: 28.1 | AS12: 18.2 | AT12: 18.8 | AU12: 91 | AY12: 106.1 | AZ12: 5.5 | BA12: 9.1 | BB12: 21.4 | BC12: 41 | BD12: 2 | BE12: 30.4 | BF12: 77.2 | BI12: 73.2 | BL12: 47.8 | BP12: 70.2 | BQ12: 61.6 | BR12: 10.4 | BS12: 200 | BT12: 86.7 | CC12: 4 | CD12: 164 | CE12: 84.4 | CF12: 64.5 | CG12: 47.7 | CH12: 30.1 | CL12: 145.5 | CM12: 146.5 | CN12: 148.7 | CT12: 0 | CU12: 0 | CV12: 0 | CW12: 39.5 | CX12: 0 | CY12: 0.8 | CZ12: 0 | DA12: 17.4 | DB12: 20.7 | DC12: 9.9 | DD12: 5.4 | DE12: 0 | DF12: 0.9 | DG12: 3.5 | DH12: 4.3 | DJ12: 16.5 | DK12: 18.9 | DL12: 3.6 | DM12: 18.6 | DN12: 0 | DO12: 0 | DP12: 12 | DQ12: 38.1 | DR12: 0 | DS12: 3.4 | DT12: 17.7 | DU12: 2.3 | DW12: 10.1 | DX12: 7.3 | DY12: 14.9 | DZ12: 20.2 | EA12: 20 | EB12: 10.3 | EC12: 14.1 | ED12: 0 | EE12: 76.9 | EF12: 71.7 | EG12: 6.8 | EH12: 3.5 | EI12: 20.9 | EJ12: 6.3 | EK12: 7.1 | EL12: 18 | EM12: 18 | EN12: 18.3 | EO12: 1.3 | EP12: 0 | EQ12: 0 | ER12: 0 | ES12: 0.6 | ET12: 25.7 | EU12: 19.9 | EV12: 0 | EW12: 2.9 | EX12: 1.1 | EY12: 2.4 | EZ12: 1.1 | FA12: 0 | FB12: 6.345 | FC12: 20.013 | FD12: 8.2 | FF12: 0 | FG12: 15.1 | FH12: 17.5 | FI12: 8.2 | FK12: 6230.158 | FM12: 21.4 | FN12: 0 | FO12: 5.9 | FP12: 13.2 | FQ12: 27.1 | FR12: 18.6 | FS12: 5.286 | FT12: 4.264 | FU12: 95.75
A13: 27/10/2025 | B13: 01:30 | C13: 150.7 | D13: 630.8 | E13: 214 | H13: 90.3 | I13: 210.6 | L13: 177.6 | M13: 178 | N13: 178.6 | O13: 269.5 | P13: 213.5 | Q13: 110.2 | R13: 369.5 | S13: 5.2 | X13: 164.5 | Y13: 7.7 | Z13: 6.2 | AB13: 7.1 | AC13: 11.6 | AD13: 72.4 | AI13: 79.8 | AJ13: 117.9 | AN13: 6.4 | AO13: 304.4 | AP13: 52.2 | AQ13: 76.6 | AR13: 26.7 | AS13: 18.2 | AT13: 18.8 | AU13: 89.8 | AY13: 106.7 | AZ13: 5.6 | BA13: 9.1 | BB13: 34.1 | BC13: 41 | BD13: 2 | BE13: 30.1 | BF13: 77 | BI13: 72.9 | BL13: 47.8 | BP13: 70.1 | BQ13: 62.1 | BR13: 45.2 | BS13: 200 | BT13: 86.5 | CC13: 4 | CD13: 134.8 | CE13: 84 | CF13: 64.3 | CG13: 47.9 | CH13: 30 | CL13: 145.8 | CM13: 146.9 | CN13: 149 | CT13: 0 | CU13: 0 | CV13: 0 | CW13: 39.1 | CX13: 0 | CY13: 0.5 | CZ13: 0 | DA13: 17.5 | DB13: 20.7 | DC13: 9.9 | DD13: 5.5 | DE13: 0 | DF13: 0.9 | DG13: 3.5 | DH13: 4.3 | DJ13: 16.5 | DK13: 18.9 | DL13: 3.6 | DM13: 18.6 | DN13: 0 | DO13: 0 | DP13: 9.8 | DQ13: 28.5 | DR13: 0 | DS13: 3.5 | DT13: 17.8 | DU13: 2.3 | DW13: 10.1 | DX13: 7.3 | DY13: 15 | DZ13: 20.2 | EA13: 20 | EB13: 10.1 | EC13: 15.3 | ED13: 0 | EE13: 64.3 | EF13: 55.7 | EG13: 5.1 | EH13: 3.6 | EI13: 20.9 | EJ13: 6.1 | EK13: 7.1 | EL13: 18 | EM13: 18.4 | EN13: 18.6 | EO13: 0.7 | EP13: 0 | EQ13: 0 | ER13: 0 | ES13: 0.6 | ET13: 26.1 | EU13: 19.4 | EV13: 0 | EW13: 2.9 | EX13: 1.1 | EY13: 2.4 | EZ13: 1.1 | FA13: 0 | FB13: 6.333 | FC13: 20.005 | FD13: 8.1 | FF13: 0 | FG13: 15.8 | FH13: 17.5 | FI13: 8.9 | FK13: 6223.838 | FM13: 21.5 | FN13: 0 | FO13: 5.9 | FP13: 13.2 | FQ13: 27.1 | FR13: 18.6 | FS13: 5.287 | FT13: 4.266 | FU13: 95.853
A14: 27/10/2025 | B14: 02:00 | C14: 153 | D14: 633.2 | E14: 215.5 | H14: 91.4 | I14: 213.1 | L14: 177.3 | M14: 176.9 | N14: 176.7 | O14: 260.4 | P14: 211.3 | Q14: 110.1 | R14: 370.9 | S14: 5.2 | X14: 159.6 | Y14: 8 | Z14: 6.3 | AB14: 6.9 | AC14: 11.6 | AD14: 51.5 | AI14: 80.6 | AJ14: 102.7 | AN14: 6.4 | AO14: 300.1 | AP14: 51.9 | AQ14: 77 | AR14: 27.8 | AS14: 18.3 | AT14: 18.8 | AU14: 94.2 | AY14: 106.8 | AZ14: 5.5 | BA14: 9.1 | BB14: 18.8 | BC14: 42.1 | BD14: 2 | BE14: 14.2 | BF14: 79.2 | BI14: 56.2 | BL14: 47.9 | BP14: 70.4 | BQ14: 61.5 | BR14: 79.4 | BS14: 200 | BT14: 86.8 | CC14: 4 | CD14: 112.6 | CE14: 85.3 | CF14: 64.7 | CG14: 47.8 | CH14: 30.1 | CL14: 145.3 | CM14: 146.1 | CN14: 148.7 | CT14: 0 | CU14: 0 | CV14: 0 | CW14: 37.5 | CX14: 0 | CY14: 0.1 | CZ14: 0 | DA14: 17.3 | DB14: 20.8 | DC14: 9.9 | DD14: 5.5 | DE14: 0 | DF14: 0.9 | DG14: 3.5 | DH14: 4.3 | DJ14: 16.5 | DK14: 18.8 | DL14: 3.6 | DM14: 18.6 | DN14: 0 | DO14: 0 | DP14: 9.8 | DQ14: 27.4 | DR14: 0 | DS14: 3.5 | DT14: 18.2 | DU14: 2.3 | DW14: 10.1 | DX14: 7.4 | DY14: 15.2 | DZ14: 20.2 | EA14: 20 | EB14: 10.4 | EC14: 30 | ED14: 0 | EE14: 57.9 | EF14: 55.7 | EG14: 5.4 | EH14: 3.6 | EI14: 20.9 | EJ14: 6 | EK14: 7.1 | EL14: 18.2 | EM14: 18.4 | EN14: 18.6 | EO14: 0.5 | EP14: 0 | EQ14: 0 | ER14: 0 | ES14: 0.6 | ET14: 27.2 | EU14: 19.2 | EV14: 0 | EW14: 2.9 | EX14: 1.1 | EY14: 2.4 | EZ14: 1.1 | FA14: 0 | FB14: 6.313 | FC14: 20.046 | FD14: 9.2 | FF14: 0 | FG14: 15.8 | FH14: 17.5 | FI14: 6.5 | FK14: 6155.159 | FM14: 21.5 | FN14: 0 | FO14: 5.9 | FP14: 13.2 | FQ14: 27.3 | FR14: 18.6 | FS14: 5.329 | FT14: 4.272 | FU14: 96.101
A15: 27/10/2025 | B15: 02:30 | C15: 149.9 | D15: 635.3 | E15: 216.5 | H15: 90.3 | I15: 212.5 | L15: 177.2 | M15: 176 | N15: 177.3 | O15: 272 | P15: 212.1 | Q15: 110.6 | R15: 377.1 | S15: 5.2 | X15: 170.3 | Y15: 8.1 | Z15: 6.2 | AB15: 6.9 | AC15: 11.6 | AD15: 51.5 | AI15: 100.6 | AJ15: 89.8 | AN15: 6.4 | AO15: 147.8 | AP15: 51.8 | AQ15: 76.8 | AR15: 29 | AS15: 18.3 | AT15: 18.8 | AU15: 91.7 | AY15: 106.2 | AZ15: 5.5 | BA15: 9.3 | BB15: 18.5 | BC15: 41.8 | BD15: 2 | BE15: 12 | BF15: 80.2 | BI15: 56.3 | BL15: 47.9 | BP15: 70.5 | BQ15: 10 | BR15: 115.9 | BS15: 200 | BT15: 149.5 | CC15: 4 | CD15: 98.7 | CE15: 85.1 | CF15: 64.8 | CG15: 47.9 | CH15: 30.1 | CL15: 145.9 | CM15: 147 | CN15: 149.1 | CT15: 0 | CU15: 0 | CV15: 0 | CW15: 41.8 | CX15: 0 | CY15: 0 | CZ15: 0 | DA15: 17.4 | DB15: 20.8 | DC15: 9.9 | DD15: 5.4 | DE15: 0 | DF15: 0.9 | DG15: 3.5 | DH15: 4.5 | DJ15: 16.8 | DK15: 18.9 | DL15: 3.6 | DM15: 18.6 | DN15: 0 | DO15: 0 | DP15: 11.2 | DQ15: 27 | DR15: 0 | DS15: 3.5 | DT15: 14.8 | DU15: 2.5 | DW15: 10.1 | DX15: 7.4 | DY15: 15 | DZ15: 20.2 | EA15: 20 | EB15: 10.1 | EC15: 28.9 | ED15: 0 | EE15: 55 | EF15: 51.3 | EG15: 4.2 | EH15: 3.3 | EI15: 20.7 | EJ15: 6 | EK15: 7.1 | EL15: 18.2 | EM15: 18.6 | EN15: 18.9 | EO15: 0 | EP15: 0 | EQ15: 0 | ER15: 0 | ES15: 0.6 | ET15: 34.5 | EU15: 24.5 | EV15: 0 | EW15: 2.9 | EX15: 1.1 | EY15: 2.4 | EZ15: 1.1 | FA15: 0 | FB15: 6.354 | FC15: 20.046 | FD15: 9.2 | FF15: 0 | FG15: 15.8 | FH15: 17.5 | FI15: 8.2 | FK15: 6076.1 | FM15: 21.6 | FN15: 0 | FO15: 5.9 | FP15: 13.2 | FQ15: 27.3 | FR15: 18.6 | FS15: 5.292 | FT15: 4.314 | FU15: 96.206
A16: 27/10/2025 | B16: 03:00 | C16: 143.8 | D16: 626 | E16: 212.2 | H16: 89.2 | I16: 73.2 | L16: 183.6 | M16: 185.2 | N16: 185.1 | O16: 277.9 | P16: 214 | Q16: 110.2 | R16: 364.5 | S16: 5.1 | X16: 161 | Y16: 7.2 | Z16: 6 | AB16: 6.9 | AC16: 11.6 | AD16: 49.6 | AI16: 99.1 | AJ16: 89.8 | AN16: 6.4 | AO16: 146.4 | AP16: 51.7 | AQ16: 75.9 | AR16: 27 | AS16: 18.2 | AT16: 18.8 | AU16: 86.9 | AY16: 105.3 | AZ16: 5.5 | BA16: 9.1 | BB16: 17.3 | BC16: 40.4 | BD16: 2 | BE16: 11.7 | BF16: 74.6 | BI16: 54 | BL16: 47.9 | BP16: 69.3 | BQ16: 10.1 | BR16: 172.6 | BS16: 200 | BT16: 180.5 | CC16: 4 | CD16: 100.9 | CE16: 81.9 | CF16: 63.5 | CG16: 43.4 | CH16: 29.8 | CL16: 146.4 | CM16: 147.2 | CN16: 149.5 | CT16: 0 | CU16: 0 | CV16: 0 | CW16: 46.7 | CX16: 0 | CY16: 0.9 | CZ16: 0 | DA16: 17.5 | DB16: 20.7 | DC16: 9.9 | DD16: 5.4 | DE16: 0 | DF16: 0.9 | DG16: 3.5 | DH16: 4.5 | DJ16: 17.2 | DK16: 18.9 | DL16: 3.6 | DM16: 18.6 | DN16: 0 | DO16: 0 | DP16: 10.7 | DQ16: 30.6 | DR16: 0 | DS16: 3.5 | DT16: 14.5 | DU16: 2.6 | DW16: 10 | DX16: 7.4 | DY16: 14.4 | DZ16: 20.1 | EA16: 20 | EB16: 7.9 | EC16: 15 | ED16: 0 | EE16: 48.8 | EF16: 47.6 | EG16: 3 | EH16: 4.6 | EI16: 20.5 | EJ16: 6 | EK16: 7.1 | EL16: 18.2 | EM16: 18.6 | EN16: 18.9 | EO16: 1.2 | EP16: 0 | EQ16: 0 | ER16: 0 | ES16: 0.6 | ET16: 38.7 | EU16: 27.5 | EV16: 0 | EW16: 2.9 | EX16: 1.1 | EY16: 2.4 | EZ16: 1.1 | FA16: 0 | FB16: 6.348 | FC16: 20.029 | FD16: 9.5 | FF16: 0 | FG16: 15 | FH16: 17.5 | FI16: 8.9 | FK16: 5970.477 | FM16: 21.8 | FN16: 0 | FO16: 5.9 | FP16: 13.2 | FQ16: 27.3 | FR16: 17.8 | FS16: 5.361 | FT16: 4.274 | FU16: 95.635
A17: 27/10/2025 | B17: 03:30 | C17: 152.8 | D17: 638 | E17: 215.9 | H17: 91.8 | I17: 160 | L17: 175.5 | M17: 175.5 | N17: 175.9 | O17: 261.5 | P17: 212.7 | Q17: 110 | R17: 384.4 | S17: 5.3 | X17: 170.9 | Y17: 8.4 | Z17: 6.3 | AB17: 6.9 | AC17: 10.8 | AD17: 51.5 | AI17: 103.7 | AJ17: 89.6 | AN17: 6.5 | AO17: 11.8 | AP17: 52 | AQ17: 105 | AR17: 29.3 | AS17: 18.2 | AT17: 18.8 | AU17: 89.6 | AY17: 109 | AZ17: 5.5 | BA17: 9.1 | BB17: 22.1 | BC17: 42.5 | BD17: 2 | BE17: 12.2 | BF17: 81.3 | BI17: 57.3 | BL17: 47.9 | BP17: 70.6 | BQ17: 9.8 | BR17: 172.9 | BS17: 200 | BT17: 181 | CC17: 4 | CD17: 154.9 | CE17: 91.1 | CF17: 65.5 | CG17: 42.2 | CH17: 30.7 | CL17: 145.7 | CM17: 146.7 | CN17: 148.4 | CT17: 0 | CU17: 0 | CV17: 0 | CW17: 45.9 | CX17: 0 | CY17: 0.8 | CZ17: 0 | DA17: 17.5 | DB17: 20.9 | DC17: 9.9 | DD17: 5.5 | DE17: 0 | DF17: 0.8 | DG17: 3.5 | DH17: 4.4 | DJ17: 17.9 | DK17: 18.9 | DL17: 3.6 | DM17: 18.6 | DN17: 0 | DO17: 0 | DP17: 9.5 | DQ17: 27 | DR17: 0 | DS17: 3.5 | DT17: 14.5 | DU17: 2.6 | DW17: 10.1 | DX17: 7.4 | DY17: 14.7 | DZ17: 20.2 | EA17: 20 | EB17: 9.3 | EC17: 11 | ED17: 0 | EE17: 52.2 | EF17: 52.7 | EG17: 5.7 | EH17: 2.6 | EI17: 20.5 | EJ17: 6 | EK17: 7.2 | EL17: 18.2 | EM17: 18.4 | EN17: 18.7 | EO17: 1.4 | EP17: 0 | EQ17: 0 | ER17: 0 | ES17: 0.6 | ET17: 35.2 | EU17: 23.9 | EV17: 0 | EW17: 2.9 | EX17: 1.1 | EY17: 2.4 | EZ17: 1.1 | FA17: 0 | FB17: 6.313 | FC17: 20.022 | FD17: 8.9 | FF17: 0 | FG17: 15 | FH17: 17.5 | FI17: 8.6 | FK17: 6056.135 | FM17: 21.9 | FN17: 0 | FO17: 5.9 | FP17: 13.2 | FQ17: 27.3 | FR17: 18.6 | FS17: 5.365 | FT17: 4.305 | FU17: 96.57
A18: 27/10/2025 | B18: 04:00 | C18: 145.2 | D18: 635.3 | E18: 215.7 | H18: 89.7 | I18: 218 | L18: 176.8 | M18: 176.8 | N18: 177.2 | O18: 264.5 | P18: 214.3 | Q18: 110.4 | R18: 379.3 | S18: 5.2 | X18: 168 | Y18: 7.8 | Z18: 6.2 | AB18: 6.9 | AC18: 11 | AD18: 51 | AI18: 102.5 | AJ18: 89.5 | AN18: 6.4 | AO18: 0 | AP18: 52.4 | AQ18: 134.7 | AR18: 29.3 | AS18: 18.2 | AT18: 18.8 | AU18: 90.8 | AY18: 106.2 | AZ18: 5.5 | BA18: 9.1 | BB18: 18.2 | BC18: 41.3 | BD18: 2 | BE18: 12 | BF18: 77 | BI18: 56 | BL18: 48.2 | BP18: 70.4 | BQ18: 10.7 | BR18: 174.7 | BS18: 200 | BT18: 180.9 | CC18: 4 | CD18: 118.1 | CE18: 88.9 | CF18: 64.7 | CG18: 42 | CH18: 30.4 | CL18: 147 | CM18: 147.7 | CN18: 150.2 | CT18: 0 | CU18: 0 | CV18: 0 | CW18: 43.3 | CX18: 0 | CY18: 0.3 | CZ18: 0 | DA18: 17.6 | DB18: 20.7 | DC18: 9.9 | DD18: 5.4 | DE18: 0 | DF18: 0.8 | DG18: 3.5 | DH18: 4.4 | DJ18: 18.3 | DK18: 18.9 | DL18: 3.6 | DM18: 18.6 | DN18: 0 | DO18: 0 | DP18: 10.7 | DQ18: 33.6 | DR18: 0 | DS18: 3.5 | DT18: 14.7 | DU18: 2.6 | DW18: 10.1 | DX18: 7.4 | DY18: 14.4 | DZ18: 20.2 | EA18: 20 | EB18: 11.9 | EC18: 12.6 | ED18: 0 | EE18: 59.2 | EF18: 52.6 | EG18: 7.1 | EH18: 3.4 | EI18: 20.5 | EJ18: 6 | EK18: 7.2 | EL18: 18.2 | EM18: 18.4 | EN18: 18.7 | EO18: 0.7 | EP18: 0 | EQ18: 0 | ER18: 0 | ES18: 0.6 | ET18: 27.3 | EU18: 24.3 | EV18: 0 | EW18: 2.9 | EX18: 1.1 | EY18: 2.4 | EZ18: 1.1 | FA18: 0 | FB18: 6.354 | FC18: 20.012 | FD18: 8.8 | FF18: 0 | FG18: 15 | FH18: 17.5 | FI18: 8.2 | FK18: 6081.666 | FM18: 22.1 | FN18: 0 | FO18: 5.9 | FP18: 13.2 | FQ18: 27.4 | FR18: 18.6 | FS18: 5.373 | FT18: 4.294 | FU18: 96.867
A19: 27/10/2025 | B19: 04:30 | C19: 148.7 | D19: 633.1 | E19: 215.3 | H19: 90.2 | I19: 214.5 | L19: 175.8 | M19: 175.2 | N19: 175.1 | O19: 266.5 | P19: 213.8 | Q19: 110.4 | R19: 378.1 | S19: 5.2 | X19: 167.7 | Y19: 7.8 | Z19: 6.1 | AB19: 6.9 | AC19: 11 | AD19: 51 | AI19: 102.3 | AJ19: 89.2 | AN19: 6.4 | AO19: 0 | AP19: 52.5 | AQ19: 142.3 | AR19: 29.6 | AS19: 18.2 | AT19: 18.8 | AU19: 92.3 | AY19: 106 | AZ19: 5.5 | BA19: 9.1 | BB19: 24.5 | BC19: 40.1 | BD19: 2 | BE19: 12 | BF19: 76.6 | BI19: 55.8 | BL19: 47.9 | BP19: 70.2 | BQ19: 10.1 | BR19: 174.2 | BS19: 200 | BT19: 181.5 | CC19: 4 | CD19: 119.8 | CE19: 88.9 | CF19: 62.5 | CG19: 46.7 | CH19: 30.3 | CL19: 146.4 | CM19: 147.5 | CN19: 149.2 | CT19: 0 | CU19: 0 | CV19: 0 | CW19: 30.1 | CX19: 0 | CY19: 0 | CZ19: 0 | DA19: 17.7 | DB19: 20.7 | DC19: 9.9 | DD19: 5.6 | DE19: 0 | DF19: 0.8 | DG19: 3.5 | DH19: 4.4 | DJ19: 18.5 | DK19: 18.9 | DL19: 3.6 | DM19: 18.6 | DN19: 0 | DO19: 0 | DP19: 12.6 | DQ19: 24.1 | DR19: 0 | DS19: 3.5 | DT19: 14.5 | DU19: 2.6 | DW19: 9.9 | DX19: 7.6 | DY19: 14.4 | DZ19: 19.8 | EA19: 20 | EB19: 12.7 | EC19: 9 | ED19: 0 | EE19: 53.8 | EF19: 49.1 | EG19: 5.2 | EH19: 2.6 | EI19: 20.4 | EJ19: 6 | EK19: 7.2 | EL19: 18.2 | EM19: 18.8 | EN19: 18.8 | EO19: 0 | EP19: 0 | EQ19: 0 | ER19: 0 | ES19: 0.6 | ET19: 19.3 | EU19: 16.1 | EV19: 0 | EW19: 2.9 | EX19: 1.1 | EY19: 2.4 | EZ19: 1.1 | FA19: 0 | FB19: 6.348 | FC19: 19.987 | FD19: 9.2 | FF19: 0 | FG19: 15.9 | FH19: 17.5 | FI19: 9 | FK19: 6039.335 | FM19: 22.1 | FN19: 0 | FO19: 5.9 | FP19: 13.2 | FQ19: 27.3 | FR19: 18.6 | FS19: 5.323 | FT19: 4.266 | FU19: 96.689
A20: 27/10/2025 | B20: 05:00 | C20: 201.8 | D20: 632.8 | E20: 215 | H20: 90.2 | I20: 215.2 | L20: 185.7 | M20: 192.4 | N20: 192.8 | O20: 280 | P20: 213 | Q20: 110.7 | R20: 378.2 | S20: 5.2 | X20: 166.5 | Y20: 7.8 | Z20: 6.1 | AB20: 7 | AC20: 11.1 | AD20: 59.4 | AI20: 102.3 | AJ20: 120.4 | AN20: 6.4 | AO20: 0 | AP20: 53.8 | AQ20: 145.6 | AR20: 29.3 | AS20: 18.2 | AT20: 18.8 | AU20: 92.2 | AY20: 106.5 | AZ20: 5.5 | BA20: 9.1 | BB20: 35.3 | BC20: 40.1 | BD20: 2 | BE20: 12 | BF20: 76.7 | BI20: 82.8 | BL20: 48 | BP20: 70.1 | BQ20: 10.4 | BR20: 174.3 | BS20: 200 | BT20: 182 | CC20: 4 | CD20: 197 | CE20: 88.9 | CF20: 62.5 | CG20: 47.2 | CH20: 30.2 | CL20: 146.7 | CM20: 147.6 | CN20: 149.6 | CT20: 0 | CU20: 0 | CV20: 0 | CW20: 30.8 | CX20: 0 | CY20: 0 | CZ20: 0 | DA20: 17.7 | DB20: 20.7 | DC20: 9.9 | DD20: 5.3 | DE20: 0 | DF20: 1 | DG20: 3.5 | DH20: 4.3 | DJ20: 18.5 | DK20: 18.9 | DL20: 3.6 | DM20: 18.6 | DN20: 0 | DO20: 0 | DP20: 10.9 | DQ20: 23.4 | DR20: 0 | DS20: 3.5 | DT20: 14.9 | DU20: 2.6 | DW20: 9.9 | DX20: 7.8 | DY20: 14.4 | DZ20: 19.4 | EA20: 20 | EB20: 13.5 | EC20: 9.5 | ED20: 0 | EE20: 23.4 | EF20: 30.8 | EG20: 2.7 | EH20: 1.3 | EI20: 20 | EJ20: 5.6 | EK20: 7.2 | EL20: 18.2 | EM20: 18.9 | EN20: 18.8 | EO20: 0 | EP20: 0 | EQ20: 0 | ER20: 0 | ES20: 0.6 | ET20: 12.7 | EU20: 11.9 | EV20: 0 | EW20: 2.9 | EX20: 1.1 | EY20: 2.4 | EZ20: 1.1 | FA20: 0 | FB20: 6.346 | FC20: 20.026 | FD20: 8.9 | FF20: 0 | FG20: 15.5 | FH20: 17.5 | FI20: 9.1 | FK20: 6245.972 | FM20: 22.1 | FN20: 0 | FO20: 5.8 | FP20: 13.2 | FQ20: 27.3 | FR20: 14.5 | FS20: 5.319 | FT20: 4.313 | FU20: 92.532
A21: 27/10/2025 | B21: 05:30 | C21: 202.5 | D21: 632.9 | E21: 215.4 | H21: 90.1 | I21: 216.1 | L21: 185.5 | M21: 201.5 | N21: 201.3 | O21: 284.9 | P21: 213.7 | Q21: 110.1 | R21: 378.7 | S21: 5.2 | X21: 166.1 | Y21: 7.9 | Z21: 5.9 | AB21: 6.9 | AC21: 11.2 | AD21: 90.6 | AI21: 102.5 | AJ21: 136.2 | AN21: 6.4 | AO21: 0 | AP21: 53.8 | AQ21: 147.4 | AR21: 29.4 | AS21: 18.2 | AT21: 18.8 | AU21: 91.3 | AY21: 106.1 | AZ21: 5.5 | BA21: 9.1 | BB21: 35.2 | BC21: 40.3 | BD21: 2 | BE21: 12 | BF21: 76.9 | BI21: 82.8 | BL21: 48 | BP21: 70.1 | BQ21: 30.3 | BR21: 174.5 | BS21: 200 | BT21: 182.6 | CC21: 4 | CD21: 231.2 | CE21: 88.8 | CF21: 62.5 | CG21: 47.2 | CH21: 30.2 | CL21: 146.7 | CM21: 147.6 | CN21: 149.5 | CT21: 10.303 | CU21: 0 | CV21: 0 | CW21: 26.1 | CX21: 1.4 | CY21: 0.2 | CZ21: 0 | DA21: 17.7 | DB21: 20.8 | DC21: 9.9 | DD21: 5.5 | DE21: 5.4 | DF21: 1.1 | DG21: 3.5 | DH21: 4.3 | DJ21: 18.6 | DK21: 18.8 | DL21: 3.6 | DM21: 18.6 | DN21: 0.5 | DO21: 0.4 | DP21: 9 | DQ21: 24.4 | DR21: 0.1 | DS21: 3.4 | DT21: 20.2 | DU21: 2.6 | DW21: 10.2 | DX21: 7.8 | DY21: 14.4 | DZ21: 19.4 | EA21: 20 | EB21: 17.5 | EC21: 9.3 | ED21: 1.1 | EE21: 18.3 | EF21: 18 | EG21: 2.1 | EH21: 0.9 | EI21: 20 | EJ21: 5.8 | EK21: 7.2 | EL21: 18.2 | EM21: 18.9 | EN21: 18.8 | EO21: 0.7 | EP21: 8 | EQ21: 0 | ER21: 5.9 | ES21: 0.6 | ET21: 6.2 | EU21: 3.5 | EV21: 5.4 | EW21: 2.9 | EX21: 1.1 | EY21: 2.4 | EZ21: 1.1 | FA21: 0 | FB21: 6.345 | FC21: 20.06 | FD21: 9.3 | FF21: 0 | FG21: 16 | FH21: 17.5 | FI21: 7.3 | FK21: 6382.208 | FM21: 22.1 | FN21: 0 | FO21: 5.8 | FP21: 13.2 | FQ21: 27.3 | FR21: 9.4 | FS21: 5.293 | FT21: 4.292 | FU21: 87.385
A22: 27/10/2025 | B22: 06:00 | C22: 199.2 | D22: 632.4 | E22: 215 | H22: 88.7 | I22: 217.6 | L22: 186.8 | M22: 190.4 | N22: 189.6 | O22: 280.9 | P22: 215 | Q22: 110.5 | R22: 377.2 | S22: 5.1 | X22: 164 | Y22: 7.6 | Z22: 5.8 | AB22: 6.9 | AC22: 11.8 | AD22: 90.3 | AI22: 109.9 | AJ22: 136.2 | AN22: 6.4 | AO22: 0 | AP22: 53.4 | AQ22: 136.1 | AR22: 30 | AS22: 18.3 | AT22: 18.8 | AU22: 90.2 | AY22: 105.5 | AZ22: 5.5 | BA22: 9.1 | BB22: 20.4 | BC22: 38.5 | BD22: 2 | BE22: 11.8 | BF22: 75.7 | BI22: 82.2 | BL22: 47.9 | BP22: 69.5 | BQ22: 53.7 | BR22: 175 | BS22: 200 | BT22: 181.4 | CC22: 4 | CD22: 152.3 | CE22: 87 | CF22: 61.5 | CG22: 47.3 | CH22: 30 | CL22: 147.1 | CM22: 148 | CN22: 149.9 | CT22: 10.268 | CU22: 0 | CV22: 0 | CW22: 33.9 | CX22: 6.6 | CY22: 0.5 | CZ22: 0 | DA22: 17.7 | DB22: 20.7 | DC22: 9.9 | DD22: 5.4 | DE22: 44.5 | DF22: 1.1 | DG22: 3.5 | DH22: 4.2 | DJ22: 19 | DK22: 18.9 | DL22: 3.6 | DM22: 18.6 | DN22: 1.4 | DO22: 1.4 | DP22: 9.2 | DQ22: 23 | DR22: 0.4 | DS22: 3.4 | DT22: 20.2 | DU22: 2.6 | DW22: 10.4 | DX22: 7.8 | DY22: 14.3 | DZ22: 19 | EA22: 20 | EB22: 18.6 | EC22: 10.7 | ED22: 9.9 | EE22: 15.3 | EF22: 17.8 | EG22: 1.7 | EH22: 0.6 | EI22: 19.9 | EJ22: 5.4 | EK22: 7.2 | EL22: 18.4 | EM22: 18.9 | EN22: 18.9 | EO22: 0.8 | EP22: 79 | EQ22: 0.8 | ER22: 44.4 | ES22: 0.6 | ET22: 5.2 | EU22: 5.1 | EV22: 38.4 | EW22: 2.9 | EX22: 1.1 | EY22: 2.4 | EZ22: 1.1 | FA22: 0.7 | FB22: 6.333 | FC22: 20.033 | FD22: 9.3 | FF22: 0 | FG22: 15.6 | FH22: 17.5 | FI22: 9.3 | FK22: 6474.734 | FM22: 22.1 | FN22: 0 | FO22: 5.8 | FP22: 13.2 | FQ22: 27.2 | FR22: 9.4 | FS22: 5.283 | FT22: 4.294 | FU22: 87.277
... A58: 28/10/2025 | B58: 00:00 | C58: 203.9 | D58: 625.7 | E58: 213.6 | H58: 89.9 | I58: 220.3 | L58: 131.7 | M58: 131.8 | N58: 131.7 | O58: 229.8 | P58: 215.3 | Q58: 110.3 | R58: 375.9 | S58: 10.4 | X58: 167.1 | Y58: 7.3 | Z58: 6 | AB58: 6.9 | AC58: 12.6 | AD58: 69.8 | AI58: 110.6 | AJ58: 153.8 | AN58: 6.5 | AO58: 150.7 | AP58: 50.5 | AQ58: 151.8 | AR58: 26.9 | AS58: 18.3 | AT58: 18.8 | AU58: 90.6 | AY58: 105.9 | AZ58: 5.7 | BA58: 8.4 | BB58: 17.6 | BC58: 41.3 | BD58: 2 | BE58: 25.6 | BF58: 80.8 | BI58: 59.5 | BL58: 0 | BP58: 127.1 | BQ58: 131.4 | BR58: 131.2 | BS58: 131 | BT58: 216.8 | CC58: 4 | CD58: 95 | CE58: 93 | CF58: 65.5 | CG58: 45.2 | CH58: 29.9 | CL58: 147.2 | CM58: 148.2 | CN58: 149.9 | CT58: 214.783 | CU58: 103.777 | CV58: 0 | CW58: 50.2 | CX58: 0 | CY58: 0 | CZ58: 0 | DA58: 20 | DB58: 20.7 | DC58: 9.9 | DD58: 5.3 | DE58: 0 | DF58: 1.1 | DG58: 3.5 | DH58: 4.2 | DJ58: 20 | DK58: 18.7 | DL58: 3.5 | DM58: 18.6 | DN58: 0 | DO58: 0 | DP58: 10 | DQ58: 26.2 | DR58: 0 | DS58: 2.9 | DT58: 17.2 | DU58: 2.8 | DW58: 11.8 | DX58: 8.8 | DY58: 13.4 | DZ58: 18.9 | EA58: 20 | EB58: 13 | EC58: 34.8 | ED58: 0 | EE58: 65.8 | EF58: 73.4 | EG58: 5.4 | EH58: 3.8 | EI58: 21 | EJ58: 7.2 | EK58: 7.3 | EL58: 20.4 | EM58: 20.4 | EN58: 20 | EO58: 0 | EP58: 0 | EQ58: 0 | ER58: 0 | ES58: 0.6 | ET58: 31.1 | EU58: 23 | EV58: 0 | EW58: 2.8 | EX58: 1.1 | EY58: 2.4 | EZ58: 1.1 | FA58: 0 | FB58: 6.315 | FC58: 20.012 | FD58: 8.9 | FF58: 34.4 | FG58: 14.8 | FH58: 13.1 | FI58: 8.1 | FK58: 6687.187 | FM58: 21.2 | FN58: 3.86 | FO58: 6 | FP58: 13.2 | FQ58: 27.2 | FR58: 9.4 | FS58: 4.635 | FT58: 7.207 | FU58: 92.702
A59: EJEC | C59: 4256.3 | D59: 15143.3 | E59: 5143 | F59: 0 | G59: 0 | H59: 2162.4 | I59: 4977.15 | J59: 0 | K59: 0 | L59: 3885.7 | M59: 3912.95 | N59: 3912.5 | O59: 6174.25 | P59: 5089 | Q59: 2639.05 | R59: 9016.85 | S59: 161 | T59: 0 | U59: 0 | V59: 0 | W59: 0 | X59: 3980.35 | Y59: 186.6 | Z59: 144.45 | AA59: 0 | AB59: 165.85 | AC59: 287.95 | AD59: 1898.05 | AE59: 0 | AF59: 0 | AG59: 0 | AH59: 0 | AI59: 2552.55 | AJ59: 3315.8 | AK59: 0 | AL59: 0 | AM59: 0 | AN59: 154.7 | AO59: 3015.35 | AP59: 1253.25 | AQ59: 3330.55 | AR59: 686.7 | AS59: 436.15 | AT59: 451.2 | AU59: 2163.1 | AV59: 0 | AW59: 0 | AX59: 0 | AY59: 2548.9 | AZ59: 133.1 | BA59: 216.7 | BB59: 508.55 | BC59: 992.7 | BD59: 48 | BE59: 392 | BF59: 1826.75 | BG59: 0 | BH59: 0 | BI59: 1595.1 | BJ59: 0 | BK59: 0 | BL59: 1067.75 | BM59: 0 | BN59: 0 | BO59: 0 | BP59: 2600.15 | BQ59: 2946.75 | BR59: 3547.25 | BS59: 4414.15 | BT59: 5333.4 | BU59: 0 | BV59: 0 | BW59: 0 | BX59: 0 | BY59: 0 | BZ59: 0 | CA59: 0 | CB59: 0 | CC59: 96 | CD59: 3666.05 | CE59: 2136.7 | CF59: 1535.85 | CG59: 1109.7 | CH59: 721.55 | CI59: 0 | CJ59: 0 | CK59: 0 | CL59: 3479.45 | CM59: 3496.95 | CN59: 3570.4 | CO59: 0 | CP59: 0 | CQ59: 0 | CR59: 0 | CS59: 0 | CT59: 3175.454 | CU59: 1423.6025 | CV59: 8.2 | CW59: 1277.1 | CX59: 814.75 | CY59: 20.65 | CZ59: 2.55 | DA59: 430.55 | DB59: 497.9 | DC59: 237.8 | DD59: 130.6 | DE59: 1348.95 | DF59: 26.45 | DG59: 84 | DH59: 105.15 | DI59: 0 | DJ59: 463.55 | DK59: 449.9 | DL59: 85.2 | DM59: 445.8 | DN59: 143.05 | DO59: 170.7 | DP59: 302.75 | DQ59: 915.7 | DR59: 147 | DS59: 79.25 | DT59: 385.55 | DU59: 62.7 | DV59: 0 | DW59: 285.15 | DX59: 190.25 | DY59: 336.75 | DZ59: 459.3 | EA59: 480.2 | EB59: 372.45 | EC59: 941.15 | ED59: 388.4 | EE59: 1395.7 | EF59: 1519.85 | EG59: 161.95 | EH59: 91.65 | EI59: 490.05 | EJ59: 163.8 | EK59: 172.6 | EL59: 475.4 | EM59: 477.95 | EN59: 470.9 | EO59: 35.25 | EP59: 2660.1 | EQ59: 142.2 | ER59: 1535.55 | ES59: 14.4 | ET59: 1134.15 | EU59: 1091.85 | EV59: 1145.5 | EW59: 66.05 | EX59: 14.45 | EY59: 55.75 | EZ59: 26.4 | FA59: 135.95 | FB59: 152.099 | FC59: 480.774 | FD59: 213.3 | FE59: 0 | FF59: 317.595 | FG59: 367.05 | FH59: 351.5 | FI59: 200 | FJ59: 0 | FK59: 170728.22 | FM59: 514.65 | FN59: 55.12 | FO59: 143.05 | FP59: 244.2 | FQ59: 644.3 | FR59: 268.85 | FS59: 113.7725 | FT59: 169.561 | FU59: 2153.5035

Sheet REACTIVA
B3: lunes, 27 de Octubre del 2025
A5: POTENCIA REACTIVA EJECUTADA DE LAS UNIDADES DE GENERACIÓN DEL COES (MVAR) | FM5: CENTRALES NO INTEGRANTES COES
A6: FECHA | B6: HORA | C6: 65333 | D6: 101 | E6: 102 | F6: 42667 | G6: 42668 | H6: 126 | I6: 127 | J6: 138 | K6: 139 | L6: 197 | M6: 203 | N6: 204 | O6: 230 | P6: 209 | Q6: 56677 | R6: 796 | S6: 2146 | T6: 142 | U6: 143 | V6: 125 | W6: 187 | X6: 163 | Y6: 298 | Z6: 299 | AA6: 219 | AB6: 151 | AC6: 152 | AD6: 153 | AE6: 154 | AF6: 756 | AG6: 156 | AH6: 155 | AI6: 182 | AJ6: 212 | AK6: 758 | AL6: 263 | AM6: 265 | AN6: 775 | AO6: 777 | AP6: 2154 | AQ6: 150 | AR6: 149 | AS6: 188 | AT6: 2131 | AU6: 755 | AV6: 252 | AW6: 249 | AX6: 250 | AY6: 117 | AZ6: 267 | BA6: 268 | BB6: 119 | BC6: 120 | BD6: 189 | BE6: 122 | BF6: 266 | BG6: 337 | BH6: 338 | BI6: 251 | BJ6: 115 | BK6: 239 | BL6: 288 | BM6: 240 | BN6: 241 | BO6: 242 | BP6: 191 | BQ6: 194 | BR6: 196 | BS6: 207 | BT6: 236 | BU6: 795 | BV6: 285 | BW6: 995 | BX6: 996 | BY6: 997 | BZ6: 766 | CA6: 926 | CB6: 924 | CC6: 121 | CD6: 103 | CE6: 104 | CF6: 106 | CG6: 105 | CH6: 107 | CI6: 110 | CJ6: 109 | CK6: 144 | CL6: 113 | CM6: 114 | CN6: 193 | CO6: 208 | CP6: 786 | CQ6: 787 | CR6: 788 | CS6: 789 | CT6: 248 | CU6: 2159 | CV6: 303 | CW6: 59715 | CX6: 62255 | CY6: 1263 | CZ6: 61800 | DA6: 2194 | DB6: 69125 | DC6: 216 | DD6: 198 | DE6: 70400 | DF6: 49607 | DG6: 214 | DH6: 260 | DI6: 2152 | DJ6: 2128 | DK6: 247 | DL6: 228 | DM6: 2135 | DN6: 261 | DO6: 237 | DP6: 253 | DQ6: 770 | DR6: 235 | DS6: 238 | DT6: 2184 | DU6: 61855 | DV6: 223 | DW6: 226 | DX6: 201 | DY6: 258 | DZ6: 259 | EA6: 920 | EB6: 257 | EC6: 256 | ED6: 2148 | EE6: 58288 | EF6: 58289 | EG6: 58839 | EH6: 58840 | EI6: 296 | EJ6: 297 | EK6: 211 | EL6: 2175 | EM6: 2178 | EN6: 2181 | EO6: 1262 | EP6: 63425 | EQ6: 233 | ER6: 2150 | ES6: 2165 | ET6: 2161 | EU6: 61197 | EV6: 58851 | EW6: 225 | EX6: 2201 | EY6: 2171 | EZ6: 760 | FA6: 234 | FB6: 215 | FC6: 917 | FD6: 289 | FE6: 58333 | FF6: 58336 | FG6: 213 | FH6: 232 | FI6: 2190 | FJ6: 69867 | FK6: TOTAL COES | FM6: 221 | FN6: 222 | FO6: 224 | FP6: 2187 | FQ6: 227 | FR6: 49400 | FS6: 199 | FT6: 200 | FU6: TOTAL NO COES
C7: SUR | D7: CENTRO | E7: CENTRO | F7: NORTE | G7: NORTE | H7: NORTE | I7: NORTE | J7: CENTRO | K7: CENTRO | L7: CENTRO | M7: CENTRO | N7: CENTRO | O7: CENTRO | P7: CENTRO | Q7: CENTRO | R7: CENTRO | S7: CENTRO | T7: CENTRO | U7: CENTRO | V7: CENTRO | W7: CENTRO | X7: SUR | Y7: SUR | Z7: SUR | AA7: CENTRO | AB7: SUR | AC7: SUR | AD7: SUR | AE7: SUR | AF7: SUR | AG7: SUR | AH7: SUR | AI7: SUR | AJ7: CENTRO | AK7: NORTE | AL7: NORTE | AM7: NORTE | AN7: CENTRO | AO7: CENTRO | AP7: CENTRO | AQ7: CENTRO | AR7: CENTRO | AS7: CENTRO | AT7: CENTRO | AU7: SUR | AV7: CENTRO | AW7: CENTRO | AX7: CENTRO | AY7: CENTRO | AZ7: CENTRO | BA7: CENTRO | BB7: CENTRO | BC7: CENTRO | BD7: SUR | BE7: NORTE | BF7: CENTRO | BG7: CENTRO | BH7: CENTRO | BI7: CENTRO | BJ7: NORTE | BK7: NORTE | BL7: NORTE | BM7: SUR | BN7: SUR | BO7: SUR | BP7: CENTRO | BQ7: CENTRO | BR7: CENTRO | BS7: CENTRO | BT7: CENTRO | BU7: CENTRO | BV7: CENTRO | BW7: SUR | BX7: SUR | BY7: SUR | BZ7: NORTE | CA7: SUR | CB7: CENTRO | CC7: NORTE | CD7: CENTRO | CE7: CENTRO | CF7: CENTRO | CG7: CENTRO | CH7: CENTRO | CI7: CENTRO | CJ7: CENTRO | CK7: CENTRO | CL7: CENTRO | CM7: CENTRO | CN7: CENTRO | CO7: CENTRO | CP7: SUR | CQ7: SUR | CR7: SUR | CS7: SUR | CT7: CENTRO | CU7: CENTRO | CV7: CENTRO | CW7: CENTRO | CX7: SUR | CY7: NORTE | CZ7: NORTE | DA7: NORTE | DB7: CENTRO | DC7: NORTE | DD7: NORTE | DE7: SUR | DF7: SUR | DG7: CENTRO | DH7: CENTRO | DI7: CENTRO | DJ7: NORTE | DK7: NORTE | DL7: CENTRO | DM7: CENTRO | DN7: SUR | DO7: SUR | DP7: CENTRO | DQ7: CENTRO | DR7: SUR | DS7: CENTRO | DT7: CENTRO | DU7: NORTE | DV7: CENTRO | DW7: CENTRO | DX7: NORTE | DY7: CENTRO | DZ7: CENTRO | EA7: CENTRO | EB7: NORTE | EC7: NORTE | ED7: SUR | EE7: CENTRO | EF7: CENTRO | EG7: CENTRO | EH7: CENTRO | EI7: CENTRO | EJ7: CENTRO | EK7: SUR | EL7: SUR | EM7: SUR | EN7: SUR | EO7: NORTE | EP7: SUR | EQ7: SUR | ER7: SUR | ES7: CENTRO | ET7: CENTRO | EU7: CENTRO | EV7: SUR | EW7: CENTRO | EX7: CENTRO | EY7: CENTRO | EZ7: CENTRO | FA7: SUR | FB7: NORTE | FC7: CENTRO | FD7: NORTE | FE7: NORTE | FF7: NORTE | FG7: CENTRO | FH7: NORTE | FI7: NORTE | FJ7: NORTE | FM7: NORTE | FN7: CENTRO | FO7: NORTE | FP7: NORTE | FQ7: NORTE | FR7: NORTE | FS7: NORTE | FT7: NORTE
C8: HIDROELÉCTRICA | D8: HIDROELÉCTRICA | E8: HIDROELÉCTRICA | F8: TERMOELÉCTRICA | G8: TERMOELÉCTRICA | H8: HIDROELÉCTRICA | I8: HIDROELÉCTRICA | J8: TERMOELÉCTRICA | K8: TERMOELÉCTRICA | L8: TERMOELÉCTRICA | M8: TERMOELÉCTRICA | N8: TERMOELÉCTRICA | O8: TERMOELÉCTRICA | P8: TERMOELÉCTRICA | Q8: TERMOELÉCTRICA | R8: HIDROELÉCTRICA | S8: HIDROELÉCTRICA | T8: TERMOELÉCTRICA | U8: TERMOELÉCTRICA | V8: TERMOELÉCTRICA | W8: TERMOELÉCTRICA | X8: HIDROELÉCTRICA | Y8: HIDROELÉCTRICA | Z8: HIDROELÉCTRICA | AA8: TERMOELÉCTRICA | AB8: HIDROELÉCTRICA | AC8: HIDROELÉCTRICA | AD8: HIDROELÉCTRICA | AE8: HIDROELÉCTRICA | AF8: TERMOELÉCTRICA | AG8: TERMOELÉCTRICA | AH8: TERMOELÉCTRICA | AI8: HIDROELÉCTRICA | AJ8: HIDROELÉCTRICA | AK8: TERMOELÉCTRICA | AL8: TERMOELÉCTRICA | AM8: TERMOELÉCTRICA | AN8: HIDROELÉCTRICA | AO8: HIDROELÉCTRICA | AP8: HIDROELÉCTRICA | AQ8: HIDROELÉCTRICA | AR8: HIDROELÉCTRICA | AS8: HIDROELÉCTRICA | AT8: HIDROELÉCTRICA | AU8: HIDROELÉCTRICA | AV8: TERMOELÉCTRICA | AW8: TERMOELÉCTRICA | AX8: TERMOELÉCTRICA | AY8: HIDROELÉCTRICA | AZ8: HIDROELÉCTRICA | BA8: HIDROELÉCTRICA | BB8: HIDROELÉCTRICA | BC8: HIDROELÉCTRICA | BD8: HIDROELÉCTRICA | BE8: HIDROELÉCTRICA | BF8: HIDROELÉCTRICA | BG8: HIDROELÉCTRICA | BH8: HIDROELÉCTRICA | BI8: HIDROELÉCTRICA | BJ8: TERMOELÉCTRICA | BK8: TERMOELÉCTRICA | BL8: TERMOELÉCTRICA | BM8: TERMOELÉCTRICA | BN8: TERMOELÉCTRICA | BO8: TERMOELÉCTRICA | BP8: HIDROELÉCTRICA | BQ8: TERMOELÉCTRICA | BR8: TERMOELÉCTRICA | BS8: TERMOELÉCTRICA | BT8: TERMOELÉCTRICA | BU8: TERMOELÉCTRICA | BV8: TERMOELÉCTRICA | BW8: TERMOELÉCTRICA | BX8: TERMOELÉCTRICA | BY8: TERMOELÉCTRICA | BZ8: HIDROELÉCTRICA | CA8: TERMOELÉCTRICA | CB8: TERMOELÉCTRICA | CC8: HIDROELÉCTRICA | CD8: HIDROELÉCTRICA | CE8: HIDROELÉCTRICA | CF8: HIDROELÉCTRICA | CG8: HIDROELÉCTRICA | CH8: HIDROELÉCTRICA | CI8: TERMOELÉCTRICA | CJ8: TERMOELÉCTRICA | CK8: TERMOELÉCTRICA | CL8: TERMOELÉCTRICA | CM8: TERMOELÉCTRICA | CN8: TERMOELÉCTRICA | CO8: TERMOELÉCTRICA | CP8: TERMOELÉCTRICA | CQ8: TERMOELÉCTRICA | CR8: TERMOELÉCTRICA | CS8: TERMOELÉCTRICA | CT8: TERMOELÉCTRICA | CU8: TERMOELÉCTRICA | CV8: SOLAR | CW8: EÓLICA | CX8: SOLAR | CY8: EÓLICA | CZ8: SOLAR | DA8: HIDROELÉCTRICA | DB8: HIDROELÉCTRICA | DC8: HIDROELÉCTRICA | DD8: HIDROELÉCTRICA | DE8: SOLAR | DF8: HIDROELÉCTRICA | DG8: HIDROELÉCTRICA | DH8: HIDROELÉCTRICA | DI8: HIDROELÉCTRICA | DJ8: HIDROELÉCTRICA | DK8: HIDROELÉCTRICA | DL8: HIDROELÉCTRICA | DM8: HIDROELÉCTRICA | DN8: SOLAR | DO8: SOLAR | DP8: EÓLICA | DQ8: EÓLICA | DR8: SOLAR | DS8: HIDROELÉCTRICA | DT8: HIDROELÉCTRICA | DU8: HIDROELÉCTRICA | DV8: HIDROELÉCTRICA | DW8: HIDROELÉCTRICA | DX8: HIDROELÉCTRICA | DY8: HIDROELÉCTRICA | DZ8: HIDROELÉCTRICA | EA8: HIDROELÉCTRICA | EB8: EÓLICA | EC8: EÓLICA | ED8: SOLAR | EE8: EÓLICA | EF8: EÓLICA | EG8: EÓLICA | EH8: EÓLICA | EI8: HIDROELÉCTRICA | EJ8: HIDROELÉCTRICA | EK8: HIDROELÉCTRICA | EL8: HIDROELÉCTRICA | EM8: HIDROELÉCTRICA | EN8: HIDROELÉCTRICA | EO8: EÓLICA | EP8: SOLAR | EQ8: SOLAR | ER8: SOLAR | ES8: HIDROELÉCTRICA | ET8: EÓLICA | EU8: EÓLICA | EV8: SOLAR | EW8: TERMOELÉCTRICA | EX8: TERMOELÉCTRICA | EY8: TERMOELÉCTRICA | EZ8: TERMOELÉCTRICA | FA8: SOLAR | FB8: HIDROELÉCTRICA | FC8: HIDROELÉCTRICA | FD8: TERMOELÉCTRICA | FE8: TERMOELÉCTRICA | FF8: TERMOELÉCTRICA | FG8: TERMOELÉCTRICA | FH8: TERMOELÉCTRICA | FI8: TERMOELÉCTRICA | FJ8: TERMOELÉCTRICA | FM8: HIDROELÉCTRICA | FN8: HIDROELÉCTRICA | FO8: HIDROELÉCTRICA | FP8: HIDROELÉCTRICA | FQ8: TERMOELÉCTRICA | FR8: TERMOELÉCTRICA | FS8: HIDROELÉCTRICA | FT8: HIDROELÉCTRICA
C9: HYDRO GLOBAL PERÚ S.A.C. | D9: ELECTROPERU | E9: ELECTROPERU | F9: ELECTROPERU | G9: ELECTROPERU | H9: ORAZUL ENERGY PERÚ | I9: ORAZUL ENERGY PERÚ | J9: TERMOSELVA | K9: TERMOSELVA | L9: KALLPA GENERACION S.A. | M9: KALLPA GENERACION S.A. | N9: KALLPA GENERACION S.A. | O9: KALLPA GENERACION S.A. | P9: KALLPA GENERACION S.A. | Q9: KALLPA GENERACION S.A. | R9: KALLPA GENERACION S.A. | S9: KALLPA GENERACION S.A. | T9: SHOUGESA | U9: SHOUGESA | V9: SHOUGESA | W9: SHOUGESA | X9: EGEMSA | Y9: EGESUR | Z9: EGESUR | AA9: EGESUR | AB9: EGASA | AC9: EGASA | AD9: EGASA | AE9: EGASA | AF9: EGASA | AG9: EGASA | AH9: EGASA | AI9: SAN GABAN | AJ9: CELEPSA | AK9: MINERA CERRO VERDE | AL9: PLANTA DE RESERVA FRIA DE GENERACION DE ETEN S.A. | AM9: PLANTA DE RESERVA FRIA DE GENERACION DE ETEN S.A. | AN9: EMPRESA DE GENERACION HUALLAGA | AO9: EMPRESA DE GENERACION HUALLAGA | AP9: LA VIRGEN | AQ9: CHINANGO S.A.C. | AR9: CHINANGO S.A.C. | AS9: HIDROELECTRICA HUANCHOR S.A.C. | AT9: CELEPSA RENOVABLES S.R.L. | AU9: INLAND ENERGY SAC | AV9: FENIX POWER PERÚ | AW9: FENIX POWER PERÚ | AX9: FENIX POWER PERÚ | AY9: STATKRAFT S.A | AZ9: STATKRAFT S.A | BA9: STATKRAFT S.A | BB9: STATKRAFT S.A | BC9: STATKRAFT S.A | BD9: STATKRAFT S.A | BE9: STATKRAFT S.A | BF9: STATKRAFT S.A | BG9: CENTRALES SANTA ROSA S.A.C. | BH9: CENTRALES SANTA ROSA S.A.C. | BI9: EMPRESA DE GENERACION HUANZA | BJ9: ENEL GENERACION PIURA S.A. | BK9: ENEL GENERACION PIURA S.A. | BL9: ENEL GENERACION PIURA S.A. | BM9: ENGIE ENERGIA PERU S.A.A. | BN9: ENGIE ENERGIA PERU S.A.A. | BO9: ENGIE ENERGIA PERU S.A.A. | BP9: ENGIE ENERGIA PERU S.A.A. | BQ9: ENGIE ENERGIA PERU S.A.A. | BR9: ENGIE ENERGIA PERU S.A.A. | BS9: ENGIE ENERGIA PERU S.A.A. | BT9: ENGIE ENERGIA PERU S.A.A. | BU9: ENGIE ENERGIA PERU S.A.A. | BV9: ENGIE ENERGIA PERU S.A.A. | BW9: ENGIE ENERGIA PERU S.A.A. | BX9: ENGIE ENERGIA PERU S.A.A. | BY9: ENGIE ENERGIA PERU S.A.A. | BZ9: ENGIE ENERGIA PERU S.A.A. | CA9: INFRAESTRUCTURAS Y ENERGIAS DEL PERU S.A.C. | CB9: INFRAESTRUCTURAS Y ENERGIAS DEL PERU S.A.C. | CC9: INVERSIONES SHAQSHA S.A.C. | CD9: ORYGEN PERU S.A.A. | CE9: ORYGEN PERU S.A.A. | CF9: ORYGEN PERU S.A.A. | CG9: ORYGEN PERU S.A.A. | CH9: ORYGEN PERU S.A.A. | CI9: ORYGEN PERU S.A.A. | CJ9: ORYGEN PERU S.A.A. | CK9: ORYGEN PERU S.A.A. | CL9: ORYGEN PERU S.A.A. | CM9: ORYGEN PERU S.A.A. | CN9: ORYGEN PERU S.A.A. | CO9: ORYGEN PERU S.A.A. | CP9: SAMAY I S.A.C | CQ9: SAMAY I S.A.C | CR9: SAMAY I S.A.C | CS9: SAMAY I S.A.C | CT9: TERMOCHILCA S.A.C. | CU9: TERMOCHILCA S.A.C. | CV9: COLCA SOLAR S.A.C. | CW9: ENERGIA RENOVABLE DEL SUR S.A. | CX9: GR CORTARRAMA SOCIEDAD ANONIMA CERRADA | CY9: GR TARUCA SOCIEDAD ANONIMA CERRADA | CZ9: KONDU SAC | DA9: PERUANA DE INVERSIONES EN ENERGIAS RENOVABLES S.A. | DB9: VARI ENERGIA S.A.C. | DC9: ORAZUL ENERGY PERÚ | DD9: ORAZUL ENERGY PERÚ | DE9: KALLPA GENERACION S.A. | DF9: SAN GABAN | DG9: MAJA ENERGIA S.A.C. | DH9: EMPRESA DE GENERACION ELECTRICA CANCHAYLLO SAC | DI9: EMPRESA DE GENERACION ELECTRICA SANTA ANA S.A.C. | DJ9: EMPRESA ELECTRICA AGUA AZUL | DK9: EMPRESA ELECTRICA RIO DOBLE | DL9: HIDROCAÑETE S.A. | DM9: HUAURA POWER GROUP S.A. | DN9: MOQUEGUA FV S.A.C. | DO9: PANAMERICANA SOLAR SAC. | DP9: PARQUE EOLICO MARCONA S.A.C. | DQ9: PARQUE EOLICO TRES HERMANAS S.A.C. | DR9: TACNA SOLAR SAC. | DS9: ELECTRICA YANAPAMPA SAC | DT9: ANDEAN POWER S.A.C. | DU9: ASOCIACIÓN SANTA LUCIA DE CHACAS | DV9: ATRIA ENERGIA S.A.C. | DW9: EGEJUNIN | DX9: EGEJUNIN | DY9: EGEJUNIN | DZ9: EGEJUNIN | EA9: EMPRESA DE GENERACION ELECTRICA RIO BAÑOS S.A.C. | EB9: ENERGÍA EÓLICA S.A. | EC9: ENERGÍA EÓLICA S.A. | ED9: ENGIE ENERGIA PERU S.A.A. | EE9: ENGIE ENERGIA PERU S.A.A. | EF9: ENGIE ENERGIA PERU S.A.A. | EG9: ENGIE ENERGIA PERU S.A.A. | EH9: ENGIE ENERGIA PERU S.A.A. | EI9: GENERACIÓN ANDINA S.A.C. | EJ9: GENERACIÓN ANDINA S.A.C. | EK9: GENERADORA DE ENERGÍA DEL PERÚ | EL9: GENERADORA DE ENERGÍA DEL PERÚ | EM9: GENERADORA DE ENERGÍA DEL PERÚ | EN9: GENERADORA DE ENERGÍA DEL PERÚ | EO9: GR PAINO SOCIEDAD ANONIMA CERRADA | EP9: JOYA SOLAR S.A.C. | EQ9: MAJES ARCUS S.A.C. | ER9: ORYGEN PERU S.A.A. | ES9: ORYGEN PERU S.A.A. | ET9: ORYGEN PERU S.A.A. | EU9: ORYGEN PERU S.A.A. | EV9: ORYGEN PERU S.A.A. | EW9: PETRAMAS | EX9: PETRAMAS | EY9: PETRAMAS | EZ9: PETRAMAS | FA9: REPARTICIÓN ARCUS S.A.C. | FB9: SINERSA | FC9: SINERSA | FD9: BIOENERGIA DEL CHIRA S.A. | FE9: GM OPERACIONES S.A.C. | FF9: GM OPERACIONES S.A.C. | FG9: AGRO INDUSTRIAL PARAMONGA S.A. | FH9: AGROAURORA S.A.C. | FI9: AGROINDUSTRIAS SAN JACINTO S.A.A. | FJ9: AGROLMOS SOCIEDAD ANONIMA - AGROLMOS S.A. | FM9: UNACEM PERU S.A. | FN9: ELECTRO ORIENTE | FO9: AGUAS Y ENERGIA PERU | FP9: ELECTRO ZAÑA S.A.C. | FQ9: ELECTRONOROESTE S.A. | FR9: SDE PIURA | FS9: SINERSA | FT9: SINERSA
C10: SAN GABAN III | D10: MANTARO | E10: RESTITUCION | F10: TUMBES MAK 1 | G10: TUMBES MAK 2 | H10: CARHUAQUERO | I10: CAÑON DEL PATO | J10: AGUAYTIA TG1 | K10: AGUAYTIA TG2 | L10: KALLPA TG1 | M10: KALLPA TG2 | N10: KALLPA TG3 | O10: KALLPA TV | P10: LFLORES TG1 | Q10: LFLORES TV | R10: CERRO DEL AGUILA | S10: CERRODELAGUILAG4 | T10: SHOUGESA TV1 | U10: SHOUGESA TV2 | V10: SHOUGESA TV3 | W10: SHOUGESA CUMMINS | X10: MACHUPICCHU | Y10: ARICOTA 1 | Z10: ARICOTA 2 | AA10: INDEPENDENCIA | AB10: CHARCANI I,II,III | AC10: CHARCANI IV | AD10: CHARCANI V | AE10: CHARCANI VI | AF10: CHILINA TG | AG10: MOLLENDO 1, 2, 3 | AH10: CHILINA (SULZ 1,2) | AI10: SAN GABAN II | AJ10: PLATANAL | AK10: RECKA | AL10: RF ETEN TG1 | AM10: RF ETEN TG2 | AN10: CHAGLLA GP1 | AO10: CHAGLLA | AP10: LA VIRGEN | AQ10: CHIMAY | AR10: YANANGO | AS10: HUANCHOR | AT10: MARAÑON | AU10: STA TERESA | AV10: FENIX GT11 | AW10: FENIX GT12 | AX10: FENIX TV10 | AY10: YAUPI | AZ10: OROYA | BA10: PACHACHACA | BB10: MALPASO | BC10: CAHUA | BD10: ARCATA | BE10: GALLITO CIEGO | BF10: CHEVES | BG10: SANTA ROSA 1 | BH10: SANTA ROSA 2 | BI10: HUANZA | BJ10: MALACAS2 TG4 | BK10: MALACAS3 TG 5 | BL10: MALACAS1 TG6 | BM10: RF ILO2 TG1 | BN10: RF ILO2 TG2 | BO10: RF ILO2 TG3 | BP10: YUNCAN | BQ10: CHILCA1 TG1 | BR10: CHILCA1 TG2 | BS10: CHILCA1 TG3 | BT10: CHILCA-TV | BU10: CHILCA2 TG41 | BV10: CHILCA2-TV | BW10: CTNEPI_TG41 | BX10: CTNEPI_TG42 | BY10: CTNEPI_TG43 | BZ10: QUITARACSA | CA10: RF PTO MALDONADO | CB10: RF PUCALLPA | CC10: PARIAC | CD10: HUINCO | CE10: MATUCANA | CF10: MOYOPAMPA | CG10: CALLAHUANCA | CH10: HUAMPANI | CI10: STA ROSA WEST TG7 | CJ10: UTI_5 | CK10: UTI_6 | CL10: VENTANILLA 3 | CM10: VENTANILLA 4 | CN10: VENTANILLA TV | CO10: STAROSA TG8 | CP10: PTO_BRVO TG1 | CQ10: PTO_BRVO TG2 | CR10: PTO_BRVO TG3 | CS10: PTO_BRVO TG4 | CT10: OLLEROS TG1 | CU10: OLLEROS TV | CV10: CS YARUCAYA | CW10: SAN JUAN | CX10: MATARANI | CY10: DUNA | CZ10: CARHUAQUERO (CS) | DA10: MANTA I | DB10: ANASHIRONI | DC10: CARHUAQUERO4 | DD10: CAÑA BRAVA | DE10: SUNNY | DF10: TUPURI | DG10: RONCADOR | DH10: CANCHAYLLO | DI10: RENOVANDESH1 | DJ10: POTRERO | DK10: PIZARRAS | DL10: NIMPERIAL | DM10: YARUCAYA | DN10: MOQUEGUA-SOLAR | DO10: PANAMERICANA-SOLAR | DP10: PQE-EOLICO-MARCONA | DQ10: PQE-EOLICO-3-HERMANAS | DR10: TACNA-SOLAR | DS10: YANAPAMPA | DT10: CARHUAC | DU10: HUALLIN | DV10: PURMACANA | DW10: HUASAHUASI | DX10: STACRUZ_1_2 | DY10: RUNATULLO_II | DZ10: RUNATULLO_III | EA10: RUCUY | EB10: PQE-EOLICO-TALARA | EC10: PQE-EOLICO-CUPISNIQUE | ED10: INTIPAMPA | EE10: PUNTA LOMITAS-BL1 | EF10: PUNTA LOMITAS-BL2 | EG10: PUN LOMITAS_EXP-BL1 | EH10: PUN LOMITAS_EXP-BL2 | EI10: 8AGOSTO | EJ10: EL CARMEN | EK10: LA JOYA | EL10: ANGEL_I | EM10: ANGEL_II | EN10: ANGEL_III | EO10: HUAMBOS | EP10: SAN MARTIN SOLAR | EQ10: MAJES | ER10: RUBI | ES10: CH_HER1 | ET10: WAYRA-I | EU10: WAYRA EXTENSION | EV10: CLEMESI | EW10: HUAYCOLORO | EX10: CALLAO | EY10: DONA_CATALINA | EZ10: LAGRINGAV | FA10: REPARTICION | FB10: POECHOS2 | FC10: CHANCAY | FD10: CANA BRAVA | FE10: REFINERIA TALARA TV1 | FF10: REFINERÍA TALARA TV2 | FG10: PARAMONGA | FH10: MAPLE | FI10: SAN_JACINTO | FJ10: AGROLMOS | FK10: MVAR | FM10: CARPAPATA | FN10: CENTRALES ELOR | FO10: PIAS1 | FP10: ZANA | FQ10: TABLAZO | FR10: TALLANCA | FS10: CURUMUY | FT10: POECHOS1 | FU10: MVAR
A11: 27/10/2025 | B11: 00:30 | C11: 2.7 | D11: -35.1 | E11: 3.9 | H11: -15.6 | I11: 12.6 | L11: -37.2 | M11: -42.6 | N11: -22.4 | O11: 13.8 | P11: -11.1 | Q11: -17.8 | R11: 18.4 | S11: -0.1 | X11: 5.5 | Y11: 0.2 | Z11: 0.2 | AB11: -3.4 | AC11: 3.5 | AD11: 1.4 | AI11: 0.7 | AJ11: -24.7 | AN11: -1.8 | AO11: -17.4 | AP11: 3.5 | AQ11: 2.6 | AR11: -1.8 | AS11: -0.5 | AT11: 2.6 | AU11: 1.2 | AY11: 2.2 | AZ11: -1.7 | BA11: 0.2 | BB11: -1.2 | BC11: 0.5 | BD11: 0.4 | BE11: 0.1 | BF11: -17.4 | BI11: -2.1 | BL11: -3.3 | BP11: -7.5 | BQ11: -42.8 | BR11: -2 | BS11: -2.4 | BT11: -71.3 | CC11: -0.5 | CD11: 22 | CE11: 13.5 | CF11: 0.7 | CG11: -0.1 | CH11: -0.1 | CL11: -19 | CM11: -13.9 | CN11: -34.2 | CT11: 0 | CU11: 0 | CW11: -7.3 | CX11: 0 | CY11: 0 | DA11: 1.2 | DB11: 0 | DC11: -0.1 | DD11: -0.9 | DE11: 0 | DG11: 0 | DH11: 1 | DJ11: -2.4 | DK11: 0.3 | DL11: 0.6 | DN11: 0 | DO11: 0 | DP11: 13.9 | DQ11: 17.4 | DR11: 0 | DS11: -0.1 | DT11: -0.6 | DU11: 0.4 | DW11: -2.7 | DX11: 0.2 | DY11: 1.3 | DZ11: 2.2 | EA11: 0.7 | EB11: 0 | EC11: 8.2 | ED11: 0 | EE11: -5.8 | EF11: -6.4 | EG11: 0 | EH11: 0 | EI11: 2.6 | EJ11: 0 | EK11: 1.5 | EL11: 0.2 | EM11: 0.2 | EN11: 0.2 | EO11: 0 | EP11: 0 | EQ11: 0 | ER11: 0 | ES11: -0.2 | ET11: -5.3 | EU11: 0 | EV11: 0 | EW11: 1.6 | EX11: 0.3 | EY11: 0.8 | EZ11: 0.6 | FA11: 0 | FB11: 0.4 | FC11: 1 | FD11: 1.9 | FF11: 0 | FG11: 1.9 | FH11: 0 | FI11: 2.5 | FK11: -307.3 | FM11: 1.8 | FN11: 0 | FO11: 1.2 | FP11: 1.8 | FQ11: 0.3 | FR11: 0.1 | FS11: -0.6 | FT11: 0.5 | FU11: 5.1
A12: 27/10/2025 | B12: 01:00 | C12: 4.7 | D12: -30.9 | E12: 4.1 | H12: -15.3 | I12: 11.3 | L12: -34.2 | M12: -37.7 | N12: -17.1 | O12: 15.5 | P12: -11.4 | Q12: -17.5 | R12: 15.6 | S12: 0 | X12: 5.1 | Y12: -0.1 | Z12: 0.1 | AB12: -3.5 | AC12: 3.5 | AD12: 1.1 | AI12: 0.5 | AJ12: -20.1 | AN12: -1.2 | AO12: -17.2 | AP12: 3.1 | AQ12: 3 | AR12: -2.2 | AS12: -1.2 | AT12: 2.6 | AU12: 1.1 | AY12: 1.4 | AZ12: -1.7 | BA12: 0.2 | BB12: -0.8 | BC12: 1 | BD12: 0.4 | BE12: 0.1 | BF12: -15.9 | BI12: -1.1 | BL12: -3 | BP12: -7.4 | BQ12: -43.3 | BR12: -2.7 | BS12: -3.2 | BT12: -71.8 | CC12: -0.5 | CD12: 15.9 | CE12: 13.8 | CF12: 1.4 | CG12: -0.1 | CH12: -0.2 | CL12: -17.2 | CM12: -12.1 | CN12: -31.7 | CT12: 0 | CU12: 0 | CW12: -8.1 | CX12: 0 | CY12: 0 | DA12: 1.2 | DB12: 0 | DC12: -0.1 | DD12: -0.9 | DE12: 0 | DG12: 0 | DH12: 1 | DJ12: -2.5 | DK12: 0.3 | DL12: 0.6 | DN12: 0 | DO12: 0 | DP12: 13.3 | DQ12: 15.6 | DR12: 0 | DS12: 0 | DT12: -0.6 | DU12: 0.4 | DW12: -2.7 | DX12: 0.1 | DY12: 1.3 | DZ12: 2.2 | EA12: 0.9 | EB12: 0 | EC12: 1.7 | ED12: 0 | EE12: -5 | EF12: -5.4 | EG12: 0 | EH12: 0 | EI12: 2.6 | EJ12: 0 | EK12: 1.5 | EL12: 0.2 | EM12: 0.2 | EN12: 0.2 | EO12: 0 | EP12: 0 | EQ12: 0 | ER12: 0 | ES12: -0.2 | ET12: -6.3 | EU12: 0 | EV12: 0 | EW12: 1.6 | EX12: 0.3 | EY12: 0.8 | EZ12: 0.6 | FA12: 0 | FB12: 0.4 | FC12: 1.2 | FD12: 1.8 | FF12: 0 | FG12: 2.4 | FH12: 0 | FI12: 3 | FK12: -293.2 | FM12: 1.8 | FN12: 0 | FO12: 1.1 | FP12: 1.7 | FQ12: 0.3 | FR12: 0.2 | FS12: -0.6 | FT12: 0.6 | FU12: 5.1
A13: 27/10/2025 | B13: 01:30 | C13: 4.9 | D13: -27.9 | E13: 4.8 | H13: -16.9 | I13: 10 | L13: -36.8 | M13: -37.6 | N13: -16.3 | O13: 12.7 | P13: -17.3 | Q13: -18.3 | R13: 14.7 | S13: 0.1 | X13: 3.7 | Y13: 0.5 | Z13: 0.5 | AB13: -3.6 | AC13: 3.3 | AD13: -0.1 | AI13: 0.8 | AJ13: -20.6 | AN13: -1.2 | AO13: -18.4 | AP13: 3.2 | AQ13: 2.4 | AR13: -1.9 | AS13: -1.6 | AT13: 2.6 | AU13: 1.8 | AY13: 2.6 | AZ13: -1.6 | BA13: 0.2 | BB13: 1.3 | BC13: 1.7 | BD13: 0.4 | BE13: 0.1 | BF13: -12.6 | BI13: -1.8 | BL13: -3.4 | BP13: -4.9 | BQ13: -43 | BR13: -2.4 | BS13: -3 | BT13: -71.3 | CC13: -0.5 | CD13: 15.8 | CE13: 14.1 | CF13: 0.7 | CG13: -0.1 | CH13: -0.1 | CL13: -19.2 | CM13: -14 | CN13: -34.6 | CT13: 0 | CU13: 0 | CW13: -8.6 | CX13: 0 | CY13: 0 | DA13: 1.2 | DB13: 0.2 | DC13: -0.1 | DD13: -1 | DE13: 0 | DG13: 0 | DH13: 1 | DJ13: -2.6 | DK13: 0.1 | DL13: 0.6 | DN13: 0 | DO13: 0 | DP13: 13.5 | DQ13: 16.1 | DR13: 0 | DS13: -0.1 | DT13: -0.7 | DU13: 0.4 | DW13: -2.7 | DX13: 0.2 | DY13: 1.3 | DZ13: 2.2 | EA13: 0.9 | EB13: 0 | EC13: 1.5 | ED13: 0 | EE13: -3.9 | EF13: -4.9 | EG13: 0 | EH13: 0 | EI13: 2.6 | EJ13: 0 | EK13: 1.5 | EL13: 0.2 | EM13: 0.2 | EN13: 0.2 | EO13: 0 | EP13: 0 | EQ13: 0 | ER13: 0 | ES13: -0.2 | ET13: -6.9 | EU13: 0 | EV13: 0 | EW13: 1.6 | EX13: 0.3 | EY13: 0.8 | EZ13: 0.6 | FA13: 0 | FB13: 0.4 | FC13: 1.2 | FD13: 1.8 | FF13: 0 | FG13: 2.2 | FH13: 0 | FI13: 2.6 | FK13: -304.4 | FM13: 1.9 | FN13: 0 | FO13: 1.5 | FP13: 1.7 | FQ13: 0.3 | FR13: 0.1 | FS13: -0.7 | FT13: 0.5 | FU13: 5.3
A14: 27/10/2025 | B14: 02:00 | C14: 6 | D14: -28.7 | E14: 4.7 | H14: -10.8 | I14: 20.8 | L14: -38.1 | M14: -39.3 | N14: -18.5 | O14: 8.9 | P14: -17.4 | Q14: -18.3 | R14: 13.9 | S14: 0.1 | X14: 4.4 | Y14: 0.2 | Z14: 0.3 | AB14: -3.4 | AC14: 3.3 | AD14: -1 | AI14: 1.1 | AJ14: -23.3 | AN14: -1.2 | AO14: -19.2 | AP14: 3 | AQ14: 2.7 | AR14: -2.3 | AS14: -1.6 | AT14: 2.6 | AU14: 1.5 | AY14: 2.7 | AZ14: -1.6 | BA14: 0.2 | BB14: 1 | BC14: 0.9 | BD14: 0.4 | BE14: 0.3 | BF14: -14.9 | BI14: -2.8 | BL14: -2.7 | BP14: -5.4 | BQ14: -43.8 | BR14: -2.4 | BS14: -3.5 | BT14: -70.3 | CC14: -0.5 | CD14: 15.5 | CE14: 13.5 | CF14: 1.3 | CG14: -0.2 | CH14: -0.2 | CL14: -19.9 | CM14: -14.7 | CN14: -35.8 | CT14: 0 | CU14: 0 | CW14: -9.2 | CX14: 0 | CY14: 0 | DA14: 1.2 | DB14: 0.1 | DC14: 0 | DD14: -1 | DE14: 0 | DG14: 0 | DH14: 1 | DJ14: -2 | DK14: 0.1 | DL14: 0.6 | DN14: 0 | DO14: 0 | DP14: 13 | DQ14: 19.8 | DR14: 0 | DS14: 0 | DT14: -0.7 | DU14: 0.3 | DW14: -2.7 | DX14: 0.2 | DY14: 1.3 | DZ14: 2.2 | EA14: 0.9 | EB14: 0 | EC14: 2.8 | ED14: 0 | EE14: -4.5 | EF14: -5.3 | EG14: 0 | EH14: 0 | EI14: 2.6 | EJ14: 0 | EK14: 1.6 | EL14: 0.2 | EM14: 0.2 | EN14: 0.2 | EO14: 0 | EP14: 0 | EQ14: 0 | ER14: 0 | ES14: -0.2 | ET14: -7.2 | EU14: 0 | EV14: 0 | EW14: 1.6 | EX14: 0.3 | EY14: 0.8 | EZ14: 0.6 | FA14: 0 | FB14: 0.4 | FC14: 1.2 | FD14: 2 | FF14: 0 | FG14: 3 | FH14: 0 | FI14: 3.5 | FK14: -303.6 | FM14: 1.8 | FN14: 0 | FO14: 1.7 | FP14: 1.7 | FQ14: 0.3 | FR14: 0.2 | FS14: -0.5 | FT14: 0.5 | FU14: 5.7
A15: 27/10/2025 | B15: 02:30 | C15: 5.4 | D15: -46.3 | E15: 2 | H15: -13 | I15: 18.7 | L15: -38 | M15: -46.8 | N15: -26.3 | O15: 11 | P15: -17 | Q15: -18.3 | R15: 14.3 | S15: -0.1 | X15: 3.1 | Y15: 0 | Z15: 0.2 | AB15: -3.4 | AC15: 3.3 | AD15: 0 | AI15: 4.3 | AJ15: -24.4 | AN15: -1.4 | AO15: -26.1 | AP15: 2.3 | AQ15: 2.9 | AR15: -1.9 | AS15: -1.4 | AT15: 2.6 | AU15: 0.8 | AY15: -0.3 | AZ15: -1.5 | BA15: 0.2 | BB15: -2.3 | BC15: 0.1 | BD15: 0.4 | BE15: 0.2 | BF15: -20.5 | BI15: -2.8 | BL15: -3.2 | BP15: -9.2 | BQ15: -43.3 | BR15: -0.1 | BS15: -3.1 | BT15: -66.5 | CC15: -0.5 | CD15: 16.6 | CE15: 13.8 | CF15: 1.3 | CG15: -0.1 | CH15: 0 | CL15: -20 | CM15: -14.9 | CN15: -36 | CT15: 0 | CU15: 0 | CW15: -9.4 | CX15: 0 | CY15: 0 | DA15: 1.2 | DB15: 0 | DC15: 0 | DD15: -0.8 | DE15: 0 | DG15: 0 | DH15: 1 | DJ15: -2.2 | DK15: 0.1 | DL15: 0.6 | DN15: 0 | DO15: 0 | DP15: 12.9 | DQ15: 19.6 | DR15: 0 | DS15: 0.1 | DT15: -0.5 | DU15: 0.4 | DW15: -2.7 | DX15: 0.1 | DY15: 1.2 | DZ15: 2.1 | EA15: 0.9 | EB15: 0 | EC15: 9.2 | ED15: 0 | EE15: -7.3 | EF15: -7.2 | EG15: 0 | EH15: 0 | EI15: 2.5 | EJ15: 0 | EK15: 1.6 | EL15: 0.2 | EM15: 0.2 | EN15: 0.2 | EO15: 0 | EP15: 0 | EQ15: 0 | ER15: 0 | ES15: -0.2 | ET15: -7.3 | EU15: 0 | EV15: 0 | EW15: 1.6 | EX15: 0.3 | EY15: 0.8 | EZ15: 0.6 | FA15: 0 | FB15: 0.4 | FC15: 1.2 | FD15: 2 | FF15: 0 | FG15: 3.7 | FH15: 0 | FI15: 3 | FK15: -355.1 | FM15: 1.4 | FN15: 0 | FO15: 1.7 | FP15: 1.8 | FQ15: 0.3 | FR15: 0.2 | FS15: -0.5 | FT15: 0.5 | FU15: 5.4
A16: 27/10/2025 | B16: 03:00 | C16: 4 | D16: -47.6 | E16: 1.8 | H16: -10.4 | I16: 13.2 | L16: -40.1 | M16: -40.4 | N16: -19.7 | O16: 8.9 | P16: -15.1 | Q16: -16.7 | R16: 10.1 | S16: 0.1 | X16: 2 | Y16: 0.6 | Z16: 0.4 | AB16: -3.6 | AC16: 3.4 | AD16: -0.3 | AI16: 4.4 | AJ16: -24 | AN16: -1.3 | AO16: -32.8 | AP16: 1.7 | AQ16: 2.4 | AR16: -2 | AS16: -1.4 | AT16: 2.6 | AU16: 1.4 | AY16: -0.2 | AZ16: -1.5 | BA16: 0.2 | BB16: -0.2 | BC16: 1.6 | BD16: 0.4 | BE16: 0.2 | BF16: -16.2 | BI16: -3.2 | BL16: -2.9 | BP16: -6.3 | BQ16: -41.6 | BR16: 0 | BS16: -1.1 | BT16: -61.4 | CC16: -0.5 | CD16: 16.4 | CE16: 13.3 | CF16: -3.1 | CG16: -0.1 | CH16: -0.1 | CL16: -20.3 | CM16: -15.2 | CN16: -36.5 | CT16: 0 | CU16: 0 | CW16: -9.5 | CX16: 0 | CY16: 0 | DA16: 1.2 | DB16: 0 | DC16: -0.1 | DD16: -0.8 | DE16: 0 | DG16: 0 | DH16: 1 | DJ16: -2.5 | DK16: 0.2 | DL16: 0.6 | DN16: 0 | DO16: 0 | DP16: 12.9 | DQ16: 19.3 | DR16: 0 | DS16: 0.2 | DT16: -0.5 | DU16: 0.4 | DW16: -2.7 | DX16: 0.1 | DY16: 1.1 | DZ16: 2 | EA16: 0.9 | EB16: 0 | EC16: 4.2 | ED16: 0 | EE16: -8.5 | EF16: -8.7 | EG16: 0 | EH16: 0 | EI16: 2.5 | EJ16: 0 | EK16: 1.6 | EL16: 0.2 | EM16: 0.2 | EN16: 0.2 | EO16: 0 | EP16: 0 | EQ16: 0 | ER16: 0 | ES16: -0.2 | ET16: -6.8 | EU16: 0 | EV16: 0 | EW16: 1.6 | EX16: 0.3 | EY16: 0.8 | EZ16: 0.6 | FA16: 0 | FB16: 0.4 | FC16: 1.2 | FD16: 2.1 | FF16: 0 | FG16: 2.8 | FH16: 0 | FI16: 3 | FK16: -355.4 | FM16: 1.4 | FN16: 0 | FO16: 1.6 | FP16: 1.8 | FQ16: 0.3 | FR16: 0.2 | FS16: -0.6 | FT16: 0.4 | FU16: 5.1
A17: 27/10/2025 | B17: 03:30 | C17: 8.9 | D17: -33.6 | E17: 4.1 | H17: -9.4 | I17: 15.5 | L17: -39.7 | M17: -37.4 | N17: -16.8 | O17: 9.6 | P17: -14.7 | Q17: -16.7 | R17: 14.5 | S17: 0.2 | X17: 4.5 | Y17: 0.6 | Z17: 0.6 | AB17: -3.5 | AC17: 3.6 | AD17: -1.3 | AI17: 6.4 | AJ17: -24 | AN17: -1.4 | AO17: -33.6 | AP17: 1.9 | AQ17: -1.6 | AR17: -5.2 | AS17: -1.4 | AT17: 2.6 | AU17: 1.4 | AY17: 0.2 | AZ17: -1.8 | BA17: 0.2 | BB17: 1.4 | BC17: 2.2 | BD17: 0.4 | BE17: 0.2 | BF17: -13 | BI17: -2.8 | BL17: -2 | BP17: -7 | BQ17: -41.8 | BR17: 0 | BS17: -0.9 | BT17: -60.4 | CC17: -0.5 | CD17: 14.8 | CE17: 13.2 | CF17: -3.7 | CG17: -0.1 | CH17: -4.3 | CL17: -19.9 | CM17: -14.5 | CN17: -35.8 | CT17: 0 | CU17: 0 | CW17: -7.1 | CX17: 0 | CY17: 0 | DA17: 1.2 | DB17: 0.1 | DC17: 0 | DD17: -0.9 | DE17: 0 | DG17: 0 | DH17: 1 | DJ17: -2.7 | DK17: 0.2 | DL17: 0.6 | DN17: 0 | DO17: 0 | DP17: 13 | DQ17: 19.9 | DR17: 0 | DS17: 0.3 | DT17: -0.4 | DU17: 0.4 | DW17: -2.7 | DX17: 0.1 | DY17: 1.3 | DZ17: 2.1 | EA17: 0.9 | EB17: 0 | EC17: 1.6 | ED17: 0 | EE17: -6.1 | EF17: -6.6 | EG17: 0 | EH17: 0 | EI17: 2.5 | EJ17: 0 | EK17: 1.5 | EL17: 0.2 | EM17: 0.2 | EN17: 0.2 | EO17: 0 | EP17: 0 | EQ17: 0 | ER17: 0 | ES17: -0.2 | ET17: -7 | EU17: 0 | EV17: 0 | EW17: 1.6 | EX17: 0.3 | EY17: 0.8 | EZ17: 0.6 | FA17: 0 | FB17: 0.4 | FC17: 1.2 | FD17: 1.9 | FF17: 0 | FG17: 2.2 | FH17: 0.7 | FI17: 2.8 | FK17: -315.7 | FM17: 1.4 | FN17: 0 | FO17: 1.7 | FP17: 1.7 | FQ17: 0.3 | FR17: 0.2 | FS17: -0.5 | FT17: 0.5 | FU17: 5.3
A18: 27/10/2025 | B18: 04:00 | C18: 8.3 | D18: -27.5 | E18: 5.3 | H18: -12.6 | I18: 20.1 | L18: -41.6 | M18: -44.5 | N18: -21.9 | O18: 14.1 | P18: -12.3 | Q18: -14.2 | R18: 24.8 | S18: -0.1 | X18: 20.4 | Y18: 1 | Z18: 0.8 | AB18: -3.4 | AC18: 3.7 | AD18: 2.5 | AI18: 6.1 | AJ18: -23.2 | AN18: -1.2 | AO18: 0 | AP18: 2.3 | AQ18: -2.8 | AR18: -4.6 | AS18: -1.3 | AT18: 2.6 | AU18: 1.5 | AY18: 0.6 | AZ18: -1.5 | BA18: 0.2 | BB18: -1.4 | BC18: 1.1 | BD18: 0.4 | BE18: 0.2 | BF18: -18.8 | BI18: -1.4 | BL18: -3.2 | BP18: -1.3 | BQ18: -38 | BR18: 0 | BS18: 0 | BT18: -58.8 | CC18: -0.5 | CD18: 17.5 | CE18: 13.8 | CF18: -3.6 | CG18: -0.1 | CH18: -4.1 | CL18: -16.4 | CM18: -11.3 | CN18: -30.3 | CT18: 0 | CU18: 0 | CW18: -2.4 | CX18: 0 | CY18: 0 | DA18: 1.3 | DB18: 0 | DC18: 0 | DD18: -0.8 | DE18: 0 | DG18: 0.1 | DH18: 1 | DJ18: -2.3 | DK18: 0.2 | DL18: 0.6 | DN18: 0 | DO18: 0 | DP18: 14 | DQ18: 22.2 | DR18: 0 | DS18: 0.1 | DT18: -0.3 | DU18: 0.4 | DW18: -2.8 | DX18: 0.2 | DY18: 1.1 | DZ18: 2.1 | EA18: 0.9 | EB18: 0 | EC18: 1.5 | ED18: 0 | EE18: -4.6 | EF18: -5.3 | EG18: 0 | EH18: 0 | EI18: 2.5 | EJ18: 0 | EK18: 1.5 | EL18: 0.2 | EM18: 0.2 | EN18: 0.2 | EO18: 0 | EP18: 0 | EQ18: 0 | ER18: 0 | ES18: -0.2 | ET18: -3 | EU18: 0 | EV18: 0 | EW18: 1.6 | EX18: 0.3 | EY18: 0.8 | EZ18: 0.6 | FA18: 0 | FB18: 0.4 | FC18: 1.2 | FD18: 1.9 | FF18: 0 | FG18: 1.7 | FH18: 0.7 | FI18: 2.8 | FK18: -214 | FM18: 1.6 | FN18: 0 | FO18: 1.6 | FP18: 1.8 | FQ18: 0.3 | FR18: 0.2 | FS18: -0.5 | FT18: 0.6 | FU18: 5.6
A19: 27/10/2025 | B19: 04:30 | C19: 8.6 | D19: -26 | E19: 5.5 | H19: -11.6 | I19: 23 | L19: -41.1 | M19: -43.2 | N19: -25.8 | O19: 13.9 | P19: -11.3 | Q19: -14.1 | R19: 24.6 | S19: -0.1 | X19: 20.3 | Y19: 0.9 | Z19: 0.7 | AB19: -3.4 | AC19: 3.9 | AD19: 3.6 | AI19: 6 | AJ19: -22.7 | AN19: -1.1 | AO19: 0 | AP19: 2.8 | AQ19: -2.5 | AR19: -4.9 | AS19: -1.7 | AT19: 2.6 | AU19: 1.8 | AY19: 0.4 | AZ19: -1.5 | BA19: 0.2 | BB19: -0.9 | BC19: 1.5 | BD19: 0.4 | BE19: 0.2 | BF19: -17.3 | BI19: -1.1 | BL19: -2.3 | BP19: -1.1 | BQ19: -37.7 | BR19: 0 | BS19: 0 | BT19: -57.1 | CC19: -0.5 | CD19: 16.6 | CE19: 14.7 | CF19: -3.2 | CG19: -0.1 | CH19: -4.2 | CL19: -15.6 | CM19: -10.4 | CN19: -29.4 | CT19: 0 | CU19: 0 | CW19: -1.3 | CX19: 0 | CY19: 0.2 | DA19: 1.3 | DB19: 0.1 | DC19: 0 | DD19: -0.9 | DE19: 0 | DG19: 0 | DH19: 1 | DJ19: -2.3 | DK19: 0.1 | DL19: 0.6 | DN19: 0 | DO19: 0 | DP19: 13.8 | DQ19: 23.1 | DR19: 0 | DS19: 0.1 | DT19: -0.2 | DU19: 0.4 | DW19: -2.8 | DX19: 0.2 | DY19: 1.1 | DZ19: 2 | EA19: 1.1 | EB19: 0 | EC19: 1.5 | ED19: 0 | EE19: -6.1 | EF19: -6.2 | EG19: 0 | EH19: 0 | EI19: 2.5 | EJ19: 0 | EK19: 1.5 | EL19: 0.2 | EM19: 0.2 | EN19: 0.2 | EO19: 0 | EP19: 0 | EQ19: 0 | ER19: 0 | ES19: -0.2 | ET19: -2.9 | EU19: 0 | EV19: 0 | EW19: 1.6 | EX19: 0.3 | EY19: 0.8 | EZ19: 0.6 | FA19: 0 | FB19: 0.4 | FC19: 1.4 | FD19: 2 | FF19: 0 | FG19: 2.9 | FH19: 0.6 | FI19: 3.8 | FK19: -197 | FM19: 1.7 | FN19: 0 | FO19: 2 | FP19: 1.8 | FQ19: 0.3 | FR19: 0.2 | FS19: -0.4 | FT19: 0.5 | FU19: 6.1
A20: 27/10/2025 | B20: 05:00 | C20: 34.4 | D20: -18.6 | E20: 6.8 | H20: -10.9 | I20: 24.4 | L20: -35.7 | M20: -35.2 | N20: -9.8 | O20: 21.1 | P20: -9.5 | Q20: -12.8 | R20: 25.4 | S20: 0.1 | X20: 21.3 | Y20: 1 | Z20: 0.8 | AB20: -3.4 | AC20: 4 | AD20: 4.5 | AI20: 9.3 | AJ20: -18 | AN20: -1.1 | AO20: 0 | AP20: 3.3 | AQ20: 5 | AR20: -4.9 | AS20: -1.4 | AT20: 2.6 | AU20: 1.5 | AY20: 2.2 | AZ20: -1.5 | BA20: 0.2 | BB20: -0.9 | BC20: 1.7 | BD20: 0.4 | BE20: 0.2 | BF20: -17.1 | BI20: 0.4 | BL20: -2 | BP20: -0.2 | BQ20: -36 | BR20: 0 | BS20: 0 | BT20: -56.2 | CC20: -0.5 | CD20: 16.4 | CE20: 14.2 | CF20: -2.9 | CG20: -0.1 | CH20: -4.2 | CL20: -12.6 | CM20: -7.6 | CN20: -25.2 | CT20: -0.3 | CU20: 0 | CW20: -3.7 | CX20: 0 | CY20: 0 | DA20: 1.3 | DB20: 0.1 | DC20: 0 | DD20: -0.7 | DE20: 5.8 | DG20: 0 | DH20: 1.2 | DJ20: -2.1 | DK20: 0.1 | DL20: 0.6 | DN20: 0 | DO20: 0 | DP20: 13.9 | DQ20: 22.2 | DR20: 0.4 | DS20: 0.1 | DT20: -0.2 | DU20: 0.4 | DW20: -2.8 | DX20: 0 | DY20: 1.1 | DZ20: 2 | EA20: 1.1 | EB20: 0 | EC20: 1.5 | ED20: 0.3 | EE20: -3.1 | EF20: -3.1 | EG20: 0 | EH20: 0 | EI20: 2.4 | EJ20: 0 | EK20: 1.5 | EL20: 0.2 | EM20: 0.2 | EN20: 0.2 | EO20: 0.3 | EP20: 0 | EQ20: 0 | ER20: 0 | ES20: -0.2 | ET20: -3.6 | EU20: 0 | EV20: 0 | EW20: 1.6 | EX20: 0.3 | EY20: 0.8 | EZ20: 0.6 | FA20: 0 | FB20: 0.4 | FC20: 1.4 | FD20: 2.1 | FF20: 0 | FG20: 3.3 | FH20: 0.7 | FI20: 3.1 | FK20: -75.7 | FM20: 1.8 | FN20: 0 | FO20: 1.8 | FP20: 1.8 | FQ20: 0.3 | FR20: 0.1 | FS20: -0.3 | FT20: 0.6 | FU20: 6.1
A21: 27/10/2025 | B21: 05:30 | C21: 33.8 | D21: -19.2 | E21: 6.9 | H21: -8.7 | I21: 24.5 | L21: -33.8 | M21: -29.2 | N21: -3.7 | O21: 30.4 | P21: -8.2 | Q21: -12.1 | R21: 24.1 | S21: 0.1 | X21: 18.4 | Y21: 1 | Z21: 0.8 | AB21: -3.6 | AC21: 3.7 | AD21: 3.8 | AI21: 8.9 | AJ21: -15.1 | AN21: -1 | AO21: 0 | AP21: 3.5 | AQ21: 4.9 | AR21: -4.9 | AS21: -1.5 | AT21: 2.6 | AU21: 0.6 | AY21: 2 | AZ21: -1.4 | BA21: 0.2 | BB21: -0.3 | BC21: 2.2 | BD21: 0.4 | BE21: 0.2 | BF21: -17.4 | BI21: 0.4 | BL21: -1.3 | BP21: -0.1 | BQ21: -35 | BR21: 0 | BS21: 0 | BT21: -53.4 | CC21: -0.5 | CD21: 16.4 | CE21: 12 | CF21: -3.4 | CG21: -0.1 | CH21: -4.2 | CL21: -10.2 | CM21: -5 | CN21: -21.5 | CT21: 6.2 | CU21: 0 | CW21: -7.1 | CX21: 0 | CY21: 0 | DA21: 1.3 | DB21: 0 | DC21: 0 | DD21: -0.8 | DE21: 3.1 | DG21: 0 | DH21: 1 | DJ21: -2.2 | DK21: 0.2 | DL21: 0.6 | DN21: 0 | DO21: 0 | DP21: 13.9 | DQ21: 22 | DR21: 0.5 | DS21: 0.1 | DT21: -0.3 | DU21: 0.4 | DW21: -2.8 | DX21: 0 | DY21: 1.1 | DZ21: 2 | EA21: 1.3 | EB21: 0 | EC21: 1.5 | ED21: 0.1 | EE21: -1.1 | EF21: -0.9 | EG21: 0 | EH21: 0 | EI21: 2.4 | EJ21: 0 | EK21: 1.6 | EL21: 0.2 | EM21: 0.2 | EN21: 0.2 | EO21: 0 | EP21: 19.4 | EQ21: 0 | ER21: 2.2 | ES21: -0.2 | ET21: -4.5 | EU21: 0 | EV21: 1.2 | EW21: 1.6 | EX21: 0.3 | EY21: 0.8 | EZ21: 0.6 | FA21: 0 | FB21: 0.4 | FC21: 1.6 | FD21: 2 | FF21: 0 | FG21: 3.8 | FH21: 1 | FI21: 3.9 | FK21: -14.2 | FM21: 1.9 | FN21: 0 | FO21: 1.6 | FP21: 1.8 | FQ21: 0.3 | FR21: 0 | FS21: -0.2 | FT21: 0.5 | FU21: 5.9
A22: 27/10/2025 | B22: 06:00 | C22: 32.7 | D22: -35.4 | E22: 3.9 | H22: -7.4 | I22: 26.9 | L22: -35.1 | M22: -34.4 | N22: -9.9 | O22: 28.9 | P22: -8.9 | Q22: -12.9 | R22: 19 | S22: 0 | X22: 16.1 | Y22: 0.6 | Z22: 0.5 | AB22: -3.5 | AC22: 3.7 | AD22: 2.7 | AI22: 11.2 | AJ22: -15.4 | AN22: -0.9 | AO22: 0 | AP22: 3.3 | AQ22: 5 | AR22: -4.7 | AS22: -1.6 | AT22: 2.6 | AU22: 0.8 | AY22: 0.9 | AZ22: -1.3 | BA22: 0.2 | BB22: 1.1 | BC22: 2.4 | BD22: 0.4 | BE22: 0.2 | BF22: -18.3 | BI22: 0.4 | BL22: -1.1 | BP22: -0.3 | BQ22: -35.7 | BR22: 0 | BS22: 0 | BT22: -55.3 | CC22: -0.5 | CD22: 16.3 | CE22: 12.2 | CF22: -3.3 | CG22: -0.1 | CH22: -4.3 | CL22: -11.4 | CM22: -6.2 | CN22: -22.9 | CT22: 4.8 | CU22: 0 | CW22: -10.4 | CX22: 0 | CY22: 0 | DA22: 1.3 | DB22: 0 | DC22: 0 | DD22: -0.9 | DE22: 1.2 | DG22: 0 | DH22: 1 | DJ22: -1.1 | DK22: 0.2 | DL22: 0.6 | DN22: 0 | DO22: 0 | DP22: 13.1 | DQ22: 20.2 | DR22: 0.3 | DS22: 0.1 | DT22: -0.3 | DU22: 0.4 | DW22: -3 | DX22: 0 | DY22: 1.1 | DZ22: 1.9 | EA22: 1.3 | EB22: 0 | EC22: 1.5 | ED22: 0.1 | EE22: -3.9 | EF22: -4 | EG22: 0 | EH22: 0 | EI22: 2.4 | EJ22: 0 | EK22: 1.6 | EL22: 0.2 | EM22: 0.2 | EN22: 0.2 | EO22: 0 | EP22: 19.5 | EQ22: 0 | ER22: 1.9 | ES22: -0.2 | ET22: -8.1 | EU22: 0 | EV22: 0.2 | EW22: 1.6 | EX22: 0.3 | EY22: 0.8 | EZ22: 0.6 | FA22: 0 | FB22: 0.4 | FC22: 1.6 | FD22: 1.9 | FF22: 0 | FG22: 4.2 | FH22: 1.5 | FI22: 2.8 | FK22: -79.7 | FM22: 1.8 | FN22: 0 | FO22: 1.5 | FP22: 1.8 | FQ22: 0.3 | FR22: 0 | FS22: 0 | FT22: 0.6 | FU22: 6
... A58: 28/10/2025 | B58: 00:00 | C58: 37.4 | D58: -7.2 | E58: 8.4 | H58: -16.5 | I58: 9.7 | L58: -42.9 | M58: -41.1 | N58: -15.5 | O58: 28.7 | P58: -3.5 | Q58: -8.9 | R58: 29.3 | S58: 0.1 | X58: 8 | Y58: 1.1 | Z58: 0.9 | AB58: -3.4 | AC58: 3.3 | AD58: -0.5 | AI58: 14.6 | AJ58: -4.1 | AN58: -1.4 | AO58: -11.3 | AP58: 2.7 | AQ58: 14.9 | AR58: 5 | AS58: 0 | AT58: 2.6 | AU58: 0.9 | AY58: 4.5 | AZ58: -0.8 | BA58: 0.3 | BB58: 1.2 | BC58: -4.8 | BD58: 0.4 | BE58: 0.1 | BF58: -0.1 | BI58: -8.3 | BL58: 0 | BP58: -6.5 | BQ58: -27.2 | BR58: 0 | BS58: 0 | BT58: -45.6 | CC58: -0.5 | CD58: 44 | CE58: 40.7 | CF58: 8.9 | CG58: -1 | CH58: 0.1 | CL58: -10.1 | CM58: -4.9 | CN58: -32.3 | CT58: 0 | CU58: 0 | CW58: -4.4 | CX58: 0 | CY58: 0 | DA58: 1.3 | DB58: 0.1 | DC58: -0.1 | DD58: -0.8 | DE58: 0 | DG58: 0.2 | DH58: 1.2 | DJ58: 0.1 | DK58: 0.2 | DL58: 0.6 | DN58: 0 | DO58: 0 | DP58: 0 | DQ58: 0 | DR58: 0 | DS58: 0.2 | DT58: 0.4 | DU58: 0.5 | DW58: -3.2 | DX58: 0 | DY58: 1.6 | DZ58: 1.6 | EA58: 0.9 | EB58: 0 | EC58: 6.1 | ED58: 0 | EE58: -7.6 | EF58: -8 | EG58: 0 | EH58: 0 | EI58: 2.6 | EJ58: 0 | EK58: 1.5 | EL58: 0.2 | EM58: 0.2 | EN58: 0.2 | EO58: 0 | EP58: 0 | EQ58: 0 | ER58: 0 | ES58: -0.2 | ET58: -5.8 | EU58: 0 | EV58: 0 | EW58: 1.6 | EX58: 0.3 | EY58: 0.8 | EZ58: 0.6 | FA58: 0 | FB58: 0 | FC58: 0 | FD58: 1.9 | FF58: 0.32 | FG58: 0.4 | FH58: 0 | FI58: 3.5 | FK58: -31.58 | FM58: 1.7 | FN58: -0.31 | FO58: 1.2 | FP58: 1.6 | FQ58: 1.3 | FR58: 1.3 | FS58: 0 | FT58: 0 | FU58: 6.79
A59: EJEC | C59: 592.25 | D59: 91.6 | E59: 256.85 | F59: 0 | G59: 0 | H59: -210 | I59: 521.85 | J59: 0 | K59: 0 | L59: -594.5 | M59: -539 | N59: 58.75 | O59: 1034.45 | P59: 119.6 | Q59: -75.75 | R59: 784.5 | S59: 1.2 | T59: 0 | U59: 0 | V59: 0 | W59: 0 | X59: 341.55 | Y59: 20.25 | Z59: 15.05 | AA59: 0 | AB59: -82.1 | AC59: 87.4 | AD59: 151.4 | AE59: 0 | AF59: 0 | AG59: 0 | AH59: 0 | AI59: 329.05 | AJ59: -169.45 | AK59: 0 | AL59: 0 | AM59: 0 | AN59: -30.75 | AO59: -136.9 | AP59: 91.8 | AQ59: 254.15 | AR59: 37.35 | AS59: -16.15 | AT59: 62.4 | AU59: 29.25 | AV59: 0 | AW59: 0 | AX59: 0 | AY59: 147 | AZ59: -30 | BA59: 4.85 | BB59: 63.6 | BC59: 34.6 | BD59: 9.6 | BE59: 6.1 | BF59: -177.05 | BG59: 0 | BH59: 0 | BI59: 70.65 | BJ59: 0 | BK59: 0 | BL59: -28.35 | BM59: 0 | BN59: 0 | BO59: 0 | BP59: 38.85 | BQ59: -443.7 | BR59: -4.8 | BS59: -8.6 | BT59: -836.4 | BU59: 0 | BV59: 0 | BW59: 0 | BX59: 0 | BY59: 0 | BZ59: 0 | CA59: 0 | CB59: 0 | CC59: -11.2 | CD59: 1039.35 | CE59: 616.4 | CF59: 169.2 | CG59: 31.45 | CH59: 64.5 | CI59: 0 | CJ59: 0 | CK59: 0 | CL59: 186.35 | CM59: 313.4 | CN59: -282.5 | CO59: 0 | CP59: 0 | CQ59: 0 | CR59: 0 | CS59: 0 | CT59: 118.05 | CU59: -3.75 | CV59: 0 | CW59: -46.5 | CX59: 82.9 | CY59: 0.15 | CZ59: 0 | DA59: 29.95 | DB59: 1.05 | DC59: -0.85 | DD59: -21.4 | DE59: 164.85 | DF59: 0 | DG59: 0.45 | DH59: 26.7 | DI59: 0 | DJ59: -8.9 | DK59: 4.35 | DL59: 14.3 | DM59: 0 | DN59: -7.35 | DO59: -18.4 | DP59: 110.5 | DQ59: 172.35 | DR59: -25.15 | DS59: 0.65 | DT59: 0.85 | DU59: 10.45 | DV59: 0 | DW59: -74 | DX59: 1.3 | DY59: 31.65 | DZ59: 47.9 | EA59: 32.55 | EB59: 3.5 | EC59: 70.85 | ED59: 33.45 | EE59: -82.4 | EF59: -88.35 | EG59: 1.9 | EH59: 2.35 | EI59: 60.45 | EJ59: -2.1 | EK59: 38.2 | EL59: 4.8 | EM59: 4.8 | EN59: 4.8 | EO59: 0.45 | EP59: 273.4 | EQ59: 19 | ER59: 208.55 | ES59: -4.8 | ET59: -12 | EU59: 20.55 | EV59: -63.55 | EW59: 37.1 | EX59: 3.9 | EY59: 17.95 | EZ59: 14.4 | FA59: 17.35 | FB59: 16.6 | FC59: 35.95 | FD59: 46.05 | FE59: 0 | FF59: 3.135 | FG59: 70.2 | FH59: 15.9 | FI59: 80.5 | FJ59: 0 | FK59: 5496.935 | FM59: 43.7 | FN59: -2.76 | FO59: 31.75 | FP59: 32 | FQ59: 21.15 | FR59: 18.9 | FS59: 8.95 | FT59: 31.35 | FU59: 185.04

Sheet DEMANDA_AREAS
B3: lunes, 27 de Octubre del 2025
B5: REPORTE DE LA DEMANDA POR ÁREAS Y SUBAREAS OPERATIVAS (MW)
B6: FECHA HORA | C6: DEMANDA | E6: AREA | H6: SUBAREAS
C7: INTERCAMBIOS INTERNACIONALES | D7: SEIN | E7: NORTE | F7: CENTRO | G7: SUR | H7: ELECTROANDES
B8: 00:30 | C8: 0 | D8: 6299.954 | E8: 900.2492 | F8: 3604.6073 | G8: 1795.0975 | H8: 222.487
B9: 01:00 | C9: 0 | D9: 6230.158 | E9: 872.7896 | F9: 3628.2698 | G9: 1729.0986 | H9: 224.0774
B10: 01:30 | C10: 0 | D10: 6223.838 | E10: 851.9267 | F10: 3602.1981 | G10: 1769.7132 | H10: 224.2114
B11: 02:00 | C11: 0 | D11: 6155.159 | E11: 841.9981 | F11: 3547.6088 | G11: 1765.5521 | H11: 226.763
B12: 02:30 | C12: 0 | D12: 6076.1 | E12: 849.8461 | F12: 3475.3694 | G12: 1750.8845 | H12: 219.9723
B13: 03:00 | C13: 0 | D13: 5970.477 | E13: 840.9786 | F13: 3365.2865 | G13: 1764.2119 | H13: 219.1293
B14: 03:30 | C14: 0 | D14: 6056.135 | E14: 853.2914 | F14: 3444.6313 | G14: 1758.2123 | H14: 215.7201
B15: 04:00 | C15: 0 | D15: 6081.666 | E15: 858.8608 | F15: 3452.8687 | G15: 1769.9365 | H15: 220.5693
B16: 04:30 | C16: 0 | D16: 6039.335 | E16: 875.1664 | F16: 3384.3337 | G16: 1779.8349 | H16: 217.3364
B17: 05:00 | C17: 0 | D17: 6245.972 | E17: 903.0637 | F17: 3541.3967 | G17: 1801.5116 | H17: 217.5013
B18: 05:30 | C18: 0 | D18: 6382.208 | E18: 929.6866 | F18: 3674.2607 | G18: 1778.2607 | H18: 209.7757
B19: 06:00 | C19: 0 | D19: 6474.734 | E19: 968.4647 | F19: 3708.5205 | G19: 1797.7488 | H19: 204.3275
... B59: ENERGÍA | C59: 0 | D59: 170728.22 | E59: 25991.561 | F59: 100325.26 | G59: 44411.399 | H59: 5151.8154
B61: LEYENDA:
D63: Potencia recibida del Ecuador
D64: Potencia entregada al Ecuador

Sheet DEMANDA_UL
B3: lunes, 27 de Octubre del 2025
B5: POTENCIA DE LOS GRANDES USUARIOS LIBRES (MW)
B6: FECHA HORA | C6: GRANDES USUARIOS LIBRES DEL ÁREA NORTE | X6: GRANDES USUARIOS LIBRES DEL ÁREA CENTRO | BP6: GRANDES USUARIOS LIBRES DEL ÁREA SUR
C7: ARCA CONTINENTAL LINDLEY S.A. | D7: AUSTRAL GROUP S.A.A | E7: CEMENTOS PACASMAYO | F7: CONSORCIO MINERO HORIZONTE S.R.L. | G7: CORPORACIÓN PESQUERA INCA S.A.C. | H7: CREDITEX: CIA IND.TEXTIL CREDISA | I7: HIPERMERCADOS TOTTUS S.A | J7: INDUSTRIA TEXTIL PIURA | K7: MINERA BOROO MISQUICHILCA S.A. | L7: MINERA GOLD FIELDS | M7: MINERA MARSA | N7: MINERA MISKY MAYO | O7: MINERA YANACOCHA | P7: OPEN PLAZA | Q7: PESQUERA DIAMANTE | R7: PETROPERU | S7: REAL PLAZA S.R.L. | T7: SIDER PERU | U7: SUPERMERCADOS PERUANOS S.A. | V7: TRUPAL S.A. | W7: UNIÓN DE CERVECERÍAS PERUANAS BACKUS Y JOHNSTON S. | X7: ACEROS AREQUIPA | Y7: ADMINISTRADORA JOCKEY PLAZA SHOPPING CENTER S.A. | Z7: ALICORP | AA7: ARCA CONTINENTAL LINDLEY S.A. | AB7: AUSTRAL GROUP S.A.A | AC7: COMPAÑIA MINERA CONDESTABLE | AD7: CORPORACIÓN PESQUERA INCA S.A.C. | AE7: CREDITEX: CIA IND.TEXTIL CREDISA | AF7: FUNDICION CHILCA S.A. | AG7: HIPERMERCADOS TOTTUS S.A | AH7: INMOBILIARIA KANPU S.A. | AI7: INMUEBLES PANAMERICANA S.A. | AJ7: KIMBERLY-CLARK PERU | AK7: LECHE GLORIA S.A. | AL7: MALL AVENTURA S.A. | AM7: MARCOBRE S.A.C. | AN7: MINERA ANTAMINA | AO7: MINERA ARES | AP7: MINERA BUENAVENTURA | AQ7: MINERA CHINALCO PERÚ S.A. | AR7: MINERA SHOUXIN PERU S.A. | AS7: MINERA VOLCAN | AT7: MINSUR | AU7: MOLYCOP-ADESUR | AV7: NEXA RESOURCES CAJAMARQUILLA S.A. | AW7: NEXA RESOURCES PERÚ S.A.A. | AX7: OPEN PLAZA | AY7: OPP FILM | AZ7: OWENS-ILLINOIS PERÚ S.A. | BA7: PAPELERA NACIONAL S.A. | BB7: PESQUERA DIAMANTE | BC7: QUIMPAC S.A. | BD7: REAL PLAZA S.R.L. | BE7: REFINERIA LA PAMPILLA S.A.A | BF7: SAGA FALABELLA | BG7: SAN MIGUEL INDUSTRIAS PET S.A. | BH7: SHOUGANG HIERRO PERU | BI7: SOFTYS PERU S.A.C. | BJ7: SUPERMERCADOS PERUANOS S.A. | BK7: TEJIDOS SAN JACINTO | BL7: TREN URBANO DE LIMA S.A. | BM7: TRUPAL S.A. | BN7: UNACEM PERU S.A. | BO7: UNIÓN DE CERVECERÍAS PERUANAS BACKUS Y JOHNSTON S. | BP7: ANGLO AMERICAN QUELLAVECO S.A. | BQ7: ARCA CONTINENTAL LINDLEY S.A. | BR7: CAL & CEMENTO SUR S.A. | BS7: COMPAÑIA MINERA ANTAPACCAY S.A. | BT7: COMPAÑÍA MINERA CHUNGAR SAC | BU7: COMPAÑIA MINERA SAN IGNACIO DE MOROCOCHA S.A.A. | BV7: EL BROCAL .S.A. | BW7: EMPRESA ADMINISTRADORA CERRO S.A.C. | BX7: EMPRESA MINERA LOS QUENUALES S.A.C. | BY7: HIPERMERCADOS TOTTUS S.A | BZ7: HUDBAY PERU S.A.C. | CA7: INDUSTRIA CACHIMAYO | CB7: MALL AVENTURA S.A. | CC7: MINERA ARES | CD7: MINERA BUENAVENTURA | CE7: MINERA CERRO VERDE | CF7: MINERA CORONA | CG7: MINERA LAS BAMBAS S.A. | CH7: MINERA VOLCAN | CI7: MINSUR | CJ7: MOLYCOP-ADESUR | CK7: NEXA RESOURCES PERÚ S.A.A. | CL7: OXIDOS DE PASCO S.A.C. | CM7: PESQUERA DIAMANTE | CN7: REAL PLAZA S.R.L. | CO7: SOBREANDES S.A.C. | CP7: SOUTHERN PERU CC | CQ7: SUPERMERCADOS PERUANOS S.A. | CR7: UNACEM PERU S.A. | CS7: UNIÓN DE CERVECERÍAS PERUANAS BACKUS Y JOHNSTON S. | CT7: YURA
B8: 00:30 | E8: 22.44506 | F8: 13.13 | H8: 4.224 | K8: 19.2533 | L8: 25.3955 | M8: 14.0561 | N8: 13.49 | O8: 33.144 | R8: 52.154 | T8: 15.7019 | V8: 9.2 | X8: 154.75358 | Z8: 3.14383 | AC8: 17 | AE8: 2.908 | AF8: 0.9 | AH8: 2.3127 | AJ8: 5.33786 | AK8: 0 | AL8: 1.0721 | AM8: 50.3343 | AN8: 114.01966 | AO8: 26.6262 | AP8: 0.81 | AQ8: 165.98 | AS8: 35.81775 | AT8: 35.06 | AV8: 193.60379 | AW8: 36.8524 | AY8: 0.24115 | BA8: 2.3 | BC8: 61.899 | BE8: 18.2 | BI8: 18.40663 | BK8: 4.0337 | BM8: 6.951 | BN8: 48.942 | BO8: 1.71 | BP8: 141.3804 | BR8: 5.2745 | BS8: 130.3426 | BT8: 11.37866 | BV8: 34.6346 | BW8: 3.85819 | BX8: 11.79 | BZ8: 91.6858 | CA8: 24.77911 | CB8: 0.3842 | CC8: 0.66 | CD8: 25.9211 | CE8: 466.94168 | CF8: 11.0608 | CG8: 158.6426 | CH8: 17.4981 | CK8: 16.3907 | CL8: 5.11897 | CO8: 12.13104 | CP8: 285.72 | CR8: 40.12 | CT8: 29.24
B9: 01:00 | E9: 22.42173 | F9: 12.77 | H9: 4.253 | K9: 18.8208 | L9: 25.1497 | M9: 14.2555 | N9: 13.5 | O9: 33.22 | R9: 51.94 | T9: 13.4988 | V9: 9.9 | X9: 146.06158 | Z9: 2.84407 | AC9: 16.94 | AE9: 2.962 | AF9: 0.9 | AH9: 4.3837 | AJ9: 5.33431 | AK9: 0 | AL9: 0.9379 | AM9: 48.312 | AN9: 112.00339 | AO9: 27.1331 | AP9: 0.7 | AQ9: 168.75 | AS9: 35.30208 | AT9: 35.09 | AV9: 194.8457 | AW9: 37.9361 | AY9: 0.2532 | BA9: 2.4 | BC9: 61.72858 | BE9: 18.2 | BI9: 18.19198 | BK9: 3.96947 | BM9: 6.261 | BN9: 49.469 | BO9: 1.55 | BP9: 142.0216 | BR9: 5.3387 | BS9: 129.9695 | BT9: 11.13515 | BV9: 35.0001 | BW9: 3.96348 | BX9: 11.58 | BZ9: 91.446 | CA9: 24.71401 | CB9: 0.3574 | CC9: 0.681 | CD9: 24.76295 | CE9: 465.68819 | CF9: 10.9872 | CG9: 158.9241 | CH9: 17.08131 | CK9: 16.3289 | CL9: 5.18565 | CO9: 11.52579 | CP9: 283.77 | CR9: 40.206 | CT9: 29.275
B10: 01:30 | E10: 22.42474 | F10: 12.827 | H10: 4.234 | K10: 18.6451 | L10: 24.8168 | M10: 14.0472 | N10: 13.53 | O10: 34.052 | R10: 52.044 | T10: 13.7215 | V10: 9.8 | X10: 142.98056 | Z10: 2.56726 | AC10: 16.92 | AE10: 2.946 | AF10: 0.7 | AH10: 4.4164 | AJ10: 5.31128 | AK10: 0 | AL10: 0.8494 | AM10: 48.7907 | AN10: 113.44223 | AO10: 27.6002 | AP10: 0.64 | AQ10: 173.14 | AS10: 35.7444 | AT10: 35.06 | AV10: 194.93786 | AW10: 38.1862 | AY10: 0.27502 | BA10: 2.4 | BC10: 61.72112 | BE10: 18.2 | BI10: 18.43103 | BK10: 3.88321 | BM10: 6.321 | BN10: 49.831 | BO10: 1.47 | BP10: 144.0365 | BR10: 5.5055 | BS10: 131.8795 | BT10: 11.25067 | BV10: 35.9433 | BW10: 4.0073 | BX10: 12.18 | BZ10: 91.73083 | CA10: 24.7502 | CB10: 0.345 | CC10: 0.657 | CD10: 25.18493 | CE10: 466.93725 | CF10: 10.9861 | CG10: 156.8621 | CH10: 17.67092 | CK10: 16.9059 | CL10: 4.93965 | CO10: 12.34563 | CP10: 282.58 | CR10: 40.139 | CT10: 29.427
B11: 02:00 | E11: 21.98114 | F11: 12.98 | H11: 4.25 | K11: 18.9879 | L11: 25.4027 | M11: 14.1016 | N11: 13.17 | O11: 32.928 | R11: 51.863 | T11: 14.5553 | V11: 9.7 | X11: 92.25349 | Z11: 2.6275 | AC11: 16.26 | AE11: 2.921 | AF11: 0.6 | AH11: 4.0517 | AJ11: 5.27359 | AK11: 0 | AL11: 0.8264 | AM11: 50.041 | AN11: 113.16265 | AO11: 27.7671 | AP11: 0.44 | AQ11: 169.34 | AS11: 36.87071 | AT11: 36.01 | AV11: 189.49491 | AW11: 38.2314 | AY11: 0.23792 | BA11: 2.4 | BC11: 61.80555 | BE11: 18.2 | BI11: 18.21926 | BK11: 3.92841 | BM11: 6.621 | BN11: 49.584 | BO11: 1.7 | BP11: 142.833 | BR11: 5.4312 | BS11: 128.4711 | BT11: 11.18296 | BV11: 35.9937 | BW11: 3.7307 | BX11: 11.89 | BZ11: 92.03186 | CA11: 24.74016 | CB11: 0.3349 | CC11: 0.702 | CD11: 25.61548 | CE11: 469.05608 | CF11: 11.1065 | CG11: 152.0514 | CH11: 17.602 | CK11: 16.7854 | CL11: 4.629 | CO11: 12.32219 | CP11: 276.96 | CR11: 40.17 | CT11: 24.616
B12: 02:30 | E12: 23.61608 | F12: 12.452 | H12: 4.298 | K12: 18.8776 | L12: 25.493 | M12: 14.4472 | N12: 13.55 | O12: 33.358 | R12: 51.955 | T12: 11.7771 | V12: 9.8 | X12: 108.80102 | Z12: 2.63856 | AC12: 15.68 | AE12: 2.849 | AF12: 0.6 | AH12: 3.8573 | AJ12: 5.22184 | AK12: 0 | AL12: 0.8019 | AM12: 49.5644 | AN12: 112.16429 | AO12: 27.8848 | AP12: 0.41 | AQ12: 164.04 | AS12: 36.93673 | AT12: 35.16 | AV12: 190.18987 | AW12: 38.0797 | AY12: 0.27413 | BA12: 2.3 | BC12: 61.85504 | BE12: 18.2 | BI12: 18.38825 | BK12: 3.89779 | BM12: 6.632 | BN12: 48.173 | BO12: 1.8 | BP12: 142.9598 | BR12: 5.446 | BS12: 126.2696 | BT12: 11.41776 | BV12: 33.2257 | BW12: 3.87202 | BX12: 12.08 | BZ12: 93.36364 | CA12: 24.70441 | CB12: 0.3225 | CC12: 0.66 | CD12: 25.63755 | CE12: 462.6581 | CF12: 11.38 | CG12: 150.5591 | CH12: 17.2438 | CK12: 17.0134 | CL12: 4.59748 | CO12: 12.09047 | CP12: 274.33 | CR12: 39.975 | CT12: 25.754
B13: 03:00 | E13: 25.62304 | F13: 12.422 | H13: 4.276 | K13: 18.9964 | L13: 25.7169 | M13: 14.0149 | N13: 13.5 | O13: 32.842 | R13: 52.045 | T13: 15.8586 | V13: 9.9 | X13: 157.34277 | Z13: 2.51834 | AC13: 14.57 | AE13: 2.807 | AF13: 0.6 | AH13: 2.4625 | AJ13: 4.81592 | AK13: 0 | AL13: 0.7929 | AM13: 50.0793 | AN13: 116.44474 | AO13: 27.0835 | AP13: 0.67 | AQ13: 165.05 | AS13: 36.8961 | AT13: 34.95 | AV13: 189.52173 | AW13: 37.3647 | AY13: 0.2617 | BA13: 2.4 | BC13: 61.71691 | BE13: 18.2 | BI13: 18.4178 | BK13: 3.98269 | BM13: 6.321 | BN13: 45.566 | BO13: 1.47 | BP13: 143.9482 | BR13: 5.632 | BS13: 129.0273 | BT13: 11.31911 | BV13: 33.2298 | BW13: 3.96593 | BX13: 11.95 | BZ13: 91.45458 | CA13: 24.72224 | CB13: 0.3215 | CC13: 0.654 | CD13: 25.8442 | CE13: 463.48751 | CF13: 11.3998 | CG13: 154.6006 | CH13: 17.44761 | CK13: 16.3319 | CL13: 4.60426 | CO13: 12.59713 | CP13: 282.08 | CR13: 40.122 | CT13: 29.369
B14: 03:30 | E14: 35.03193 | F14: 12.814 | H14: 4.308 | K14: 18.4345 | L14: 25.9712 | M14: 13.6875 | N14: 13.29 | O14: 33.516 | R14: 51.752 | T14: 16.5428 | V14: 9.9 | X14: 149.33627 | Z14: 2.49429 | AC14: 15.53 | AE14: 2.806 | AF14: 0.6 | AH14: 1.6997 | AJ14: 5.05719 | AK14: 0 | AL14: 0.7654 | AM14: 50.1409 | AN14: 107.26446 | AO14: 27.2117 | AP14: 0.48 | AQ14: 164.27 | AS14: 37.80803 | AT14: 34.34 | AV14: 189.07298 | AW14: 38.428 | AY14: 0.26913 | BA14: 2.4 | BC14: 61.74031 | BE14: 18.2 | BI14: 18.15459 | BK14: 3.94112 | BM14: 5.321 | BN14: 46.413 | BO14: 1.85 | BP14: 143.2119 | BR14: 5.6913 | BS14: 128.278 | BT14: 10.39896 | BV14: 33.1426 | BW14: 4.02736 | BX14: 12.01 | BZ14: 92.33371 | CA14: 24.76892 | CB14: 0.3054 | CC14: 0.704 | CD14: 25.40391 | CE14: 463.65375 | CF14: 11.2716 | CG14: 154.3894 | CH14: 18.08441 | CK14: 17.1212 | CL14: 4.58173 | CO14: 11.90005 | CP14: 277.29 | CR14: 38.658 | CT14: 26.503
B15: 04:00 | E15: 36.32589 | F15: 11.954 | H15: 4.24 | K15: 18.5102 | L15: 26.0587 | M15: 13.6944 | N15: 13.36 | O15: 33.68 | R15: 52.349 | T15: 16.659 | V15: 9.8 | X15: 143.51281 | Z15: 2.51657 | AC15: 15.54 | AE15: 2.846 | AF15: 0.6 | AH15: 6.3022 | AJ15: 5.19055 | AK15: 0 | AL15: 0.7762 | AM15: 49.5302 | AN15: 106.28975 | AO15: 27.9054 | AP15: 0.18 | AQ15: 164.03 | AS15: 37.57644 | AT15: 33.75 | AV15: 189.85791 | AW15: 37.1646 | AY15: 0.33006 | BA15: 2.3 | BC15: 61.37538 | BE15: 18.2 | BI15: 18.12552 | BK15: 4.07897 | BM15: 5.321 | BN15: 45.512 | BO15: 1.86 | BP15: 142.6635 | BR15: 5.7042 | BS15: 129.5154 | BT15: 11.08706 | BV15: 33.5858 | BW15: 3.88656 | BX15: 11.83 | BZ15: 91.99516 | CA15: 24.76409 | CB15: 0.2943 | CC15: 0.679 | CD15: 26.00933 | CE15: 464.94904 | CF15: 10.9605 | CG15: 153.8627 | CH15: 17.66871 | CK15: 16.2186 | CL15: 4.6411 | CO15: 11.98782 | CP15: 283.56 | CR15: 38.675 | CT15: 24.281
B16: 04:30 | E16: 34.31119 | F16: 12.938 | H16: 4.169 | K16: 18.056 | L16: 26.1465 | M16: 15.1271 | N16: 13.38 | O16: 34.192 | R16: 52.626 | T16: 16.1548 | V16: 9.8 | X16: 87.63566 | Z16: 2.48806 | AC16: 14.53 | AE16: 2.834 | AF16: 0.6 | AH16: 10.3473 | AJ16: 5.28152 | AK16: 0 | AL16: 0.756 | AM16: 50.1941 | AN16: 103.53479 | AO16: 28.2481 | AP16: 1.65 | AQ16: 163.48 | AS16: 36.39369 | AT16: 33.07 | AV16: 196.64282 | AW16: 37.5094 | AY16: 0.2917 | BA16: 2.32 | BC16: 60.86244 | BE16: 18.2 | BI16: 18.41841 | BK16: 3.96271 | BM16: 6.321 | BN16: 41.519 | BO16: 1.83 | BP16: 142.8321 | BR16: 5.7687 | BS16: 123.7284 | BT16: 10.38727 | BV16: 34.2893 | BW16: 3.90366 | BX16: 11.26 | BZ16: 91.47773 | CA16: 24.91635 | CB16: 0.2852 | CC16: 0.663 | CD16: 25.60062 | CE16: 470.21493 | CF16: 11.2295 | CG16: 156.5781 | CH16: 17.12087 | CK16: 16.608 | CL16: 4.87311 | CO16: 12.18956 | CP16: 283.72 | CR16: 38.435 | CT16: 26.64
B17: 05:00 | E17: 36.03745 | F17: 11.536 | H17: 4.057 | K17: 19.0448 | L17: 25.8546 | M17: 15.6924 | N17: 13.44 | O17: 34.142 | R17: 52.361 | T17: 15.8243 | V17: 9.8 | X17: 142.3595 | Z17: 2.46059 | AC17: 14.96 | AE17: 2.785 | AF17: 0.6 | AH17: 5.8536 | AJ17: 5.03627 | AK17: 0 | AL17: 0.7559 | AM17: 50.5205 | AN17: 114.4613 | AO17: 28.3464 | AP17: 2.1 | AQ17: 164.11 | AS17: 36.23251 | AT17: 33.17 | AV17: 198.28923 | AW17: 36.6178 | AY17: 0.28903 | BA17: 2.3 | BC17: 60.57703 | BE17: 18.2 | BI17: 18.31452 | BK17: 3.96551 | BM17: 6.321 | BN17: 41.332 | BO17: 1.93 | BP17: 141.0202 | BR17: 5.7719 | BS17: 127.4324 | BT17: 11.12928 | BV17: 33.8823 | BW17: 4.37541 | BX17: 10.83 | BZ17: 92.71307 | CA17: 25.07065 | CB17: 0.2813 | CC17: 0.669 | CD17: 25.22726 | CE17: 468.39458 | CF17: 10.8548 | CG17: 158.3059 | CH17: 17.53521 | CK17: 15.9753 | CL17: 4.83488 | CO17: 11.53021 | CP17: 284.07 | CR17: 38.423 | CT17: 29.141
B18: 05:30 | E18: 36.07933 | F18: 11.333 | H18: 4.194 | K18: 19.1025 | L18: 25.8992 | M18: 15.0206 | N18: 13.29 | O18: 35.022 | R18: 52.374 | T18: 16.2236 | V18: 9.7 | X18: 140.00155 | Z18: 2.48158 | AC18: 15.22 | AE18: 2.777 | AF18: 0.5 | AH18: 7.8831 | AJ18: 5.08865 | AK18: 0 | AL18: 0.7738 | AM18: 49.6334 | AN18: 111.61426 | AO18: 26.4669 | AP18: 1.93 | AQ18: 165.1 | AS18: 36.41634 | AT18: 32.74 | AV18: 197.23482 | AW18: 36.2281 | AY18: 0.26103 | BA18: 2.3 | BC18: 60.82856 | BE18: 18.2 | BI18: 17.88993 | BK18: 4.03977 | BM18: 6.512 | BN18: 41.707 | BO18: 1.97 | BP18: 142.5764 | BR18: 5.8805 | BS18: 125.8678 | BT18: 10.31658 | BV18: 35.0835 | BW18: 3.85894 | BX18: 10.53 | BZ18: 90.85884 | CA18: 25.03181 | CB18: 0.274 | CC18: 0.681 | CD18: 24.43093 | CE18: 468.62207 | CF18: 10.7245 | CG18: 141.7514 | CH18: 17.90178 | CK18: 15.9823 | CL18: 4.67108 | CO18: 10.48701 | CP18: 290.24 | CR18: 38.725 | CT18: 24.802
B19: 06:00 | E19: 35.21582 | F19: 10.339 | H19: 3.502 | K19: 19.2615 | L19: 26.4143 | M19: 14.568 | N19: 13.36 | O19: 34.608 | R19: 52.476 | T19: 15.7077 | V19: 9.7 | X19: 110.74703 | Z19: 2.4817 | AC19: 16.03 | AE19: 2.831 | AF19: 0.6 | AH19: 7.1698 | AJ19: 5.10208 | AK19: 0 | AL19: 0.8043 | AM19: 51.0539 | AN19: 115.2535 | AO19: 22.7489 | AP19: 1.54 | AQ19: 165.35 | AS19: 34.8159 | AT19: 32.42 | AV19: 198.28487 | AW19: 34.939 | AY19: 0.28818 | BA19: 2.2 | BC19: 61.81692 | BE19: 18.2 | BI19: 18.27186 | BK19: 4.0811 | BM19: 6.741 | BN19: 42.104 | BO19: 1.99 | BP19: 139.932 | BR19: 5.6339 | BS19: 122.989 | BT19: 10.64646 | BV19: 33.5786 | BW19: 3.65085 | BX19: 10.23 | BZ19: 91.0867 | CA19: 25.05768 | CB19: 0.2622 | CC19: 0.639 | CD19: 23.46623 | CE19: 465.59248 | CF19: 10.005 | CG19: 157.0863 | CH19: 17.70224 | CK19: 15.7605 | CL19: 4.5281 | CO19: 9.17436 | CP19: 289.01 | CR19: 38.964 | CT19: 22.399
... B55: 00:00 | E55: 27.59246 | F55: 13.556 | H55: 0 | K55: 19.156 | L55: 25.0099 | M55: 13.4921 | N55: 12.58 | O55: 33.68 | R55: 50.977 | T55: 16.0013 | V55: 8.6 | X55: 125.90525 | Z55: 3.21123 | AC55: 14.44 | AE55: 0 | AF55: 5.2 | AH55: 3.7606 | AJ55: 5.27586 | AK55: 0 | AL55: 1.2794 | AM55: 54.2654 | AN55: 112.15027 | AO55: 29.1212 | AP55: 0.83 | AQ55: 163.66 | AS55: 36.90007 | AT55: 30.8 | AV55: 195.0173 | AW55: 36.5369 | AY55: 0.25869 | BA55: 2.5 | BC55: 61.42652 | BE55: 18.3 | BI55: 16.47883 | BK55: 5.28922 | BM55: 6.521 | BN55: 50.206 | BO55: 1.83 | BP55: 139.7925 | BR55: 4.998 | BS55: 127.3405 | BT55: 11.54261 | BV55: 35.4717 | BW55: 3.83695 | BX55: 12.86 | BZ55: 91.8692 | CA55: 25.0104 | CB55: 0.4179 | CC55: 0.766 | CD55: 25.64958 | CE55: 450.1466 | CF55: 11.4223 | CG55: 158.1815 | CH55: 17.89699 | CK55: 19.7337 | CL55: 5.41738 | CO55: 16.30242 | CP55: 287.24 | CR55: 34.432 | CT55: 23.939
B56: MWh | C56: 0 | D56: 0 | E56: 625.31975 | F56: 296.284 | G56: 0 | H56: 84.3495 | I56: 0 | J56: 0 | K56: 451.98415 | L56: 634.29485 | M56: 311.11035 | N56: 300.275 | O56: 807.368 | P56: 0 | Q56: 0 | R56: 1223.186 | S56: 0 | T56: 362.5249 | U56: 0 | V56: 213.45 | W56: 0 | X56: 2519.7128 | Y56: 0 | Z56: 70.095635 | AA56: 0 | AB56: 0 | AC56: 383.325 | AD56: 0 | AE56: 87.3135 | AF56: 24.8 | AG56: 0 | AH56: 81.204 | AI56: 0 | AJ56: 118.96792 | AK56: 0 | AL56: 59.79345 | AM56: 1203.2117 | AN56: 2695.9671 | AO56: 643.6122 | AP56: 18.01 | AQ56: 3676.705 | AR56: 0 | AS56: 850.54481 | AT56: 787.735 | AU56: 0 | AV56: 4092.0765 | AW56: 868.67725 | AX56: 0 | AY56: 6.773585 | AZ56: 0 | BA56: 55.16 | BB56: 0 | BC56: 1347.0093 | BD56: 0 | BE56: 434.55 | BF56: 0 | BG56: 0 | BH56: 0 | BI56: 400.30413 | BJ56: 0 | BK56: 118.62703 | BL56: 0 | BM56: 154.5385 | BN56: 884.7955 | BO56: 45.255 | BP56: 3332.9949 | BQ56: 0 | BR56: 128.6986 | BS56: 3048.2991 | BT56: 259.91946 | BU56: 0 | BV56: 791.4495 | BW56: 93.445805 | BX56: 262.895 | BY56: 0 | BZ56: 2165.458 | CA56: 511.60436 | CB56: 21.9506 | CC56: 16.8405 | CD56: 584.46345 | CE56: 10951.867 | CF56: 255.6065 | CG56: 3681.2816 | CH56: 413.03458 | CI56: 0 | CJ56: 0 | CK56: 412.02615 | CL56: 114.62252 | CM56: 0 | CN56: 0 | CO56: 276.00209 | CP56: 6669.94 | CQ56: 0 | CR56: 815.903 | CS56: 0 | CT56: 364.727
B59: Nota :
B60: Información proporcionada por la empresas
C62: DATOS ESTIMADOS
C64: SIN DATOS

Sheet TIPO_RECURSO
B3: lunes, 27 de Octubre del 2025
B5: REPORTE POTENCIA GENERADA POR TIPO DE RECURSO
B6: HORA | C6: H. PASADA | D6: H. REGULACION | E6: GAS DE CAMISEA | F6: GAS DE MALACAS | G6: DIÉSEL | H6: RESIDUAL | I6: NAFTA+GAS DE REFINERIA | J6: FLEXIGAS+GAS DE REFINERIA | K6: BAGAZO | L6: BIOGÁS | M6: SOLAR | N6: EÓLICA | O6: TOTAL | T6: EMPRESA | U6: CENTRAL | V6: HIDROELECTRICA DE PASADA | W6: HIDROELECTRICA DE REGULACION
B7: 00:30 | C7: 1144.554 | D7: 2729.7 | E7: 1983.3 | F7: 48 | G7: 0 | H7: 0 | I7: =+DESPACHO_EJECUTADO!FF11 -> 0 | J7: 0 | K7: 51.1 | L7: 7.5 | M7: 0 | N7: 335.8 | O7: =+SUM(C7:N7) -> 6299.954 | T7: ANDEAN POWER S.A.C. | U7: C.H.CARHUAC | V7: 385.55
B8: 01:00 | C8: 1150.158 | D8: 2687.6 | E8: 1967.5 | F8: 47.8 | G8: 0 | H8: 0 | I8: =+DESPACHO_EJECUTADO!FF12 -> 0 | J8: 0 | K8: 49 | L8: 7.5 | M8: 0 | N8: 320.6 | O8: =+SUM(C8:N8) -> 6230.158 | T8: ASOCIACIÓN SANTA LUCIA DE CHACAS | U8: C.H. HUALLIN | V8: 62.7
B9: 01:30 | C9: 1145.538 | D9: 2731.6 | E9: 1962.9 | F9: 47.8 | G9: 0 | H9: 0 | I9: =+DESPACHO_EJECUTADO!FF13 -> 0 | J9: 0 | K9: 50.3 | L9: 7.5 | M9: 0 | N9: 278.2 | O9: =+SUM(C9:N9) -> 6223.838 | T9: CELEPSA | U9: C.H. EL PLATANAL | W9: 3315.8
B10: 02:00 | C10: 1149.759 | D10: 2635.8 | E10: 1980.5 | F10: 47.9 | G10: 0 | H10: 0 | I10: =+DESPACHO_EJECUTADO!FF14 -> 0 | J10: 0 | K10: 49 | L10: 7.5 | M10: 0 | N10: 284.7 | O10: =+SUM(C10:N10) -> 6155.159 | T10: CELEPSA RENOVABLES S.R.L. | U10: C.H. MARAÑON | V10: 451.2
B11: 02:30 | C11: 1157.1 | D11: 2478.5 | E11: 2042.6 | F11: 47.9 | G11: 0 | H11: 0 | I11: =+DESPACHO_EJECUTADO!FF15 -> 0 | J11: 0 | K11: 50.7 | L11: 7.5 | M11: 0 | N11: 291.8 | O11: =+SUM(C11:N11) -> 6076.1 | T11: CHINANGO S.A.C. | U11: C.H. CHIMAY | W11: 3330.55
B12: 03:00 | C12: 1131.577 | D12: 2287.1 | E12: 2162.3 | F12: 47.9 | G12: 0 | H12: 0 | I12: =+DESPACHO_EJECUTADO!FF16 -> 0 | J12: 0 | K12: 50.9 | L12: 7.5 | M12: 0 | N12: 283.2 | O12: =+SUM(C12:N12) -> 5970.477 | U12: C.H. YANANGO | V12: 686.7
B13: 03:30 | C13: 1160.135 | D13: 2397.8 | E13: 2115.6 | F13: 47.9 | G13: 0 | H13: 0 | I13: =+DESPACHO_EJECUTADO!FF17 -> 0 | J13: 0 | K13: 50 | L13: 7.5 | M13: 0 | N13: 277.2 | O13: =+SUM(C13:N13) -> 6056.135 | T13: EGASA | U13: C.H. CHARCANI III | V13: 165.85
B14: 04:00 | C14: 1153.066 | D14: 2405.2 | E14: 2131.2 | F14: 48.2 | G14: 0 | H14: 0 | I14: =+DESPACHO_EJECUTADO!FF18 -> 0 | J14: 0 | K14: 49.5 | L14: 7.5 | M14: 0 | N14: 287 | O14: =+SUM(C14:N14) -> 6081.666 | U14: C.H. CHARCANI IV | W14: 287.95
B15: 04:30 | C15: 1150.735 | D15: 2421.3 | E15: 2125.7 | F15: 47.9 | G15: 0 | H15: 0 | I15: =+DESPACHO_EJECUTADO!FF19 -> 0 | J15: 0 | K15: 51.6 | L15: 7.5 | M15: 0 | N15: 234.6 | O15: =+SUM(C15:N15) -> 6039.335 | U15: C.H. CHARCANI V | W15: 1898.05
B16: 05:00 | C16: 1148.672 | D16: 2634.7 | E16: 2185.2 | F16: 48 | G16: 0 | H16: 0 | I16: =+DESPACHO_EJECUTADO!FF20 -> 0 | J16: 0 | K16: 51 | L16: 7.5 | M16: 0 | N16: 170.9 | O16: =+SUM(C16:N16) -> 6245.972 | T16: EGEJUNIN | U16: C.H. HUASAHUASI I | V16: 285.15
B17: 05:30 | C17: 1153.705 | D17: 2720 | E17: 2238.503 | F17: 48 | G17: 0 | H17: 0 | I17: =+DESPACHO_EJECUTADO!FF21 -> 0 | J17: 0 | K17: 50.1 | L17: 7.5 | M17: 28.2 | N17: 136.2 | O17: =+SUM(C17:N17) -> 6382.208 | U17: C.H. RUNATULLO II | V17: 336.75
B18: 06:00 | C18: 1146.766 | D18: 2612.4 | E18: 2238.568 | F18: 47.9 | G18: 0 | H18: 0 | I18: =+DESPACHO_EJECUTADO!FF22 -> 0 | J18: 0 | K18: 51.7 | L18: 7.5 | M18: 227.5 | N18: 142.4 | O18: =+SUM(C18:N18) -> 6474.734 | U18: C.H. RUNATULLO III | V18: 459.3
B19: 06:30 | C19: 1154.395 | D19: 2579.4 | E19: 2225.701 | F19: 48 | G19: 0 | H19: 0 | I19: =+DESPACHO_EJECUTADO!FF23 -> 0 | J19: 0 | K19: 49.7 | L19: 7.5 | M19: 478.9 | N19: 135.9 | O19: =+SUM(C19:N19) -> 6679.496 | U19: C.H. SANTA CRUZ I | V19: 190.25
B20: 07:00 | C20: 1154.098 | D20: 2312.5 | E20: 2123.437 | F20: 47.6 | G20: 0 | H20: 0 | I20: =+DESPACHO_EJECUTADO!FF24 -> 0 | J20: 0 | K20: 52.2 | L20: 7.5 | M20: 787.9 | N20: 145.2 | O20: =+SUM(C20:N20) -> 6630.435 | T20: EGEMSA | U20: C.H. MACHUPICCHU | V20: 3980.35
B21: 07:30 | C21: 1134.202 | D21: 2339.7 | E21: 2239.64 | F21: 47.6 | G21: 0 | H21: 0 | I21: =+DESPACHO_EJECUTADO!FF25 -> 0 | J21: 0 | K21: 51.7 | L21: 6.4 | M21: 845.1 | N21: 151.1 | O21: =+SUM(C21:N21) -> 6815.442 | T21: EGESUR | U21: C.H. ARICOTA I | W21: 186.6
B22: 08:00 | C22: 1142.518 | D22: 2457.8 | E22: 2235.606 | F22: 47.4 | G22: 0 | H22: 0 | I22: =+DESPACHO_EJECUTADO!FF26 -> 0 | J22: 0 | K22: 50.4 | L22: 6.4 | M22: 883.8 | N22: 174.6 | O22: =+SUM(C22:N22) -> 6998.524 | U22: C.H. ARICOTA II | W22: 144.45
B23: 08:30 | C23: 1130.061 | D23: 2741.6 | E23: 2345.09 | F23: 47.2 | G23: 0 | H23: 0 | I23: =+DESPACHO_EJECUTADO!FF27 -> 0 | J23: 0 | K23: 52 | L23: 6.4 | M23: 697.9 | N23: 191.4 | O23: =+SUM(C23:N23) -> 7211.651 | T23: ELECTRICA YANAPAMPA SAC | U23: C.H. YANAPAMPA | V23: 79.25
B24: 09:00 | C24: 1143.462 | D24: 2790 | E24: 2381.83 | F24: 47.1 | G24: 0 | H24: 0 | I24: =+DESPACHO_EJECUTADO!FF28 -> 0 | J24: 0 | K24: 50.6 | L24: 6.4 | M24: 708.6 | N24: 230.1 | O24: =+SUM(C24:N24) -> 7358.092 | T24: ELECTROPERU | U24: C.H. MANTARO | W24: 15143.3
B25: 09:30 | C25: 1174.703 | D25: 2808 | E25: 2312.855 | F25: 46.9 | G25: 0 | H25: 0 | I25: =+DESPACHO_EJECUTADO!FF29 -> 0 | J25: 0 | K25: 50.4 | L25: 6.4 | M25: 720.2 | N25: 293.5 | O25: =+SUM(C25:N25) -> 7412.958 | U25: C.H. RESTITUCION | V25: 5143
B26: 10:00 | C26: 1164.437 | D26: 2807.8 | E26: 2381.989 | F26: 46.8 | G26: 0 | H26: 0 | I26: =+DESPACHO_EJECUTADO!FF30 -> 0 | J26: 0 | K26: 53.3 | L26: 6.4 | M26: 728.1 | N26: 342 | O26: =+SUM(C26:N26) -> 7530.826 | T26: EMPRESA DE GENERACION ELECTRICA CANCHAYLLO SAC | U26: C.H. CANCHAYLLO | V26: 105.15
B27: 10:30 | C27: 1171.862 | D27: 2754.7 | E27: 2427.485 | F27: 46.8 | G27: 0 | H27: 0 | I27: =+DESPACHO_EJECUTADO!FF31 -> 0 | J27: 0 | K27: 45.4 | L27: 6.4 | M27: 733.1 | N27: 372 | O27: =+SUM(C27:N27) -> 7557.747 | T27: EMPRESA DE GENERACION ELECTRICA RIO BAÑOS S.A.C. | U27: C.H. RUCUY | V27: 480.2
B28: 11:00 | C28: 1140.806 | D28: 2588.1 | E28: 2639.181 | F28: 46.4 | G28: 0 | H28: 0 | I28: =+DESPACHO_EJECUTADO!FF32 -> 0 | J28: 0 | K28: 45 | L28: 6.4 | M28: 734.2 | N28: 410.9 | O28: =+SUM(C28:N28) -> 7610.987 | T28: EMPRESA DE GENERACION HUALLAGA | U28: C.H. CHAGLLA | W28: 3015.35
B29: 11:30 | C29: 1142.827 | D29: 2570.1 | E29: 2654.964 | F29: 46.7 | G29: 0 | H29: 0 | I29: =+DESPACHO_EJECUTADO!FF33 -> 0 | J29: 0 | K29: 45.3 | L29: 6.4 | M29: 737.9 | N29: 462.5 | O29: =+SUM(C29:N29) -> 7666.691 | U29: P.C.H. CHAGLLA | V29: 154.7
B30: 12:00 | C30: 1160.726 | D30: 2540.7 | E30: 2593.973 | F30: 46.7 | G30: 0 | H30: 0 | I30: =+DESPACHO_EJECUTADO!FF34 -> 0 | J30: 0 | K30: 46.6 | L30: 6.4 | M30: 794.6 | N30: 506.1 | O30: =+SUM(C30:N30) -> 7695.799 | T30: EMPRESA DE GENERACION HUANZA | U30: C.H. HUANZA | W30: 1595.1
B31: 12:30 | C31: 1157.464 | D31: 2451.2 | E31: 2503.143 | F31: 46.3 | G31: 0 | H31: 0 | I31: =+DESPACHO_EJECUTADO!FF35 -> 0 | J31: 0 | K31: 46.4 | L31: 6.4 | M31: 923 | N31: 466 | O31: =+SUM(C31:N31) -> 7599.907 | T31: EMPRESA ELECTRICA AGUA AZUL | U31: C.H. POTRERO | V31: 463.55
B32: 13:00 | C32: 1147.571 | D32: 2403 | E32: 2328.081 | F32: 46.6 | G32: 0 | H32: 0 | I32: =+DESPACHO_EJECUTADO!FF36 -> 0 | J32: 0 | K32: 44.8 | L32: 6.4 | M32: 951.7 | N32: 460.6 | O32: =+SUM(C32:N32) -> 7388.752 | T32: EMPRESA ELECTRICA RIO DOBLE | U32: C.H. LAS PIZARRAS | V32: 449.9
B33: 13:30 | C33: 1160.128 | D33: 2557.7 | E33: 2217.732 | F33: 46.7 | G33: 0 | H33: 0 | I33: =+DESPACHO_EJECUTADO!FF37 -> 0 | J33: 0 | K33: 44 | L33: 6.4 | M33: 946 | N33: 483.4 | O33: =+SUM(C33:N33) -> 7462.06 | T33: ENGIE ENERGIA PERU S.A.A. | U33: C.H. YUNCAN | W33: 2600.15
B34: 14:00 | C34: 1158.264 | D34: 2690.2 | E34: 2178.049 | F34: 47.1 | G34: 0 | H34: 0 | I34: =+DESPACHO_EJECUTADO!FF38 -> 0 | J34: 0 | K34: 43.8 | L34: 6.4 | M34: 937.5 | N34: 469.9 | O34: =+SUM(C34:N34) -> 7531.213 | T34: GENERACIÓN ANDINA S.A.C. | U34: C.H. 8 DE AGOSTO | V34: 490.05
B35: 14:30 | C35: 1154.737 | D35: 2651.7 | E35: 2341.308 | F35: 46.9 | G35: 0 | H35: 0 | I35: =+DESPACHO_EJECUTADO!FF39 -> 10.02 | J35: 0 | K35: 42.7 | L35: 6.4 | M35: 915.8 | N35: 518.1 | O35: =+SUM(C35:N35) -> 7687.665 | U35: C.H. EL CARMEN | V35: 163.8
B36: 15:00 | C36: 1138.057 | D36: 2598.2 | E36: 2328.816 | F36: 47.1 | G36: 0 | H36: 0 | I36: =+DESPACHO_EJECUTADO!FF40 -> 16.2 | J36: 0 | K36: 44.6 | L36: 5.4 | M36: 909 | N36: 565.1 | O36: =+SUM(C36:N36) -> 7652.473 | T36: GENERADORA DE ENERGÍA DEL PERÚ | U36: C.H. ÁNGEL I | V36: 475.4
B37: 15:30 | C37: 1154.78 | D37: 2578.2 | E37: 2341.849 | F37: 46.9 | G37: 0 | H37: 0 | I37: =+DESPACHO_EJECUTADO!FF41 -> 26.04 | J37: 0 | K37: 39.6 | L37: 4.9 | M37: 835.2 | N37: 679.2 | O37: =+SUM(C37:N37) -> 7706.669 | U37: C.H. ÁNGEL II | V37: 477.95
B38: 16:00 | C38: 1151.892 | D38: 2584.3 | E38: 2228.343 | F38: 46.7 | G38: 0 | H38: 0 | I38: =+DESPACHO_EJECUTADO!FF42 -> 34.17 | J38: 0 | K38: 42.4 | L38: 4.9 | M38: 821.2 | N38: 701.8 | O38: =+SUM(C38:N38) -> 7615.705 | U38: C.H. ÁNGEL III | V38: 470.9
B39: 16:30 | C39: 1162.3 | D39: 2639.6 | E39: 2411.369 | F39: 47.3 | G39: 0 | H39: 0 | I39: =+DESPACHO_EJECUTADO!FF43 -> 34.64 | J39: 0 | K39: 40.9 | L39: 4.9 | M39: 572.7 | N39: 686.3 | O39: =+SUM(C39:N39) -> 7600.009 | U39: C.H. LA JOYA | V39: 172.6
B40: 17:00 | C40: 1168.729 | D40: 2691 | E40: 2557.952 | F40: 47 | G40: 0 | H40: 0 | I40: =+DESPACHO_EJECUTADO!FF44 -> 34.37 | J40: 0 | K40: 41.6 | L40: 4.9 | M40: 315.7 | N40: 654.4 | O40: =+SUM(C40:N40) -> 7515.651 | T40: HIDROCAÑETE S.A. | U40: C.H. IMPERIAL | V40: 85.2
B41: 17:30 | C41: 1165.565 | D41: 2834.5 | E41: 2645.995 | F41: 47.1 | G41: 0 | H41: 0 | I41: =+DESPACHO_EJECUTADO!FF45 -> 34.32 | J41: 0 | K41: 43.9 | L41: 4.9 | M41: 51.6 | N41: 656.1 | O41: =+SUM(C41:N41) -> 7483.98 | T41: HIDROELECTRICA HUANCHOR S.A.C. | U41: C.H. HUANCHOR | V41: 436.15
B42: 18:00 | C42: 1164.623 | D42: 2767.5 | E42: 2602.923 | F42: 47.4 | G42: 0 | H42: 0 | I42: =+DESPACHO_EJECUTADO!FF46 -> 34.18 | J42: 0 | K42: 45.3 | L42: 5.7 | M42: 0.4 | N42: 621.2 | O42: =+SUM(C42:N42) -> 7289.226 | T42: HUAURA POWER GROUP S.A. | U42: C.H. YARUCAYA | V42: 445.8
B43: 18:30 | C43: 1160.982 | D43: 3028.3 | E43: 2710.308 | F43: 47.7 | G43: 0 | H43: 0 | I43: =+DESPACHO_EJECUTADO!FF47 -> 34.1 | J43: 0 | K43: 45 | L43: 7.3 | M43: 0 | N43: 596.2 | O43: =+SUM(C43:N43) -> 7629.89 | T43: HYDRO GLOBAL PERÚ S.A.C. | U43: CH SAN GABAN III | W43: 4256.3
B44: 19:00 | C44: 1161.906 | D44: 3098.6 | E44: 2702.999 | F44: 47.8 | G44: 0 | H44: 0 | I44: =+DESPACHO_EJECUTADO!FF48 -> 34.42 | J44: 0 | K44: 45.3 | L44: 7.4 | M44: 0 | N44: 591.9 | O44: =+SUM(C44:N44) -> 7690.325 | T44: INLAND ENERGY SAC | U44: C.H. SANTA TERESA | V44: 2163.1
B45: 19:30 | C45: 1171.387 | D45: 3120.5 | E45: 2713.365 | F45: 48.1 | G45: 0 | H45: 0 | I45: =+DESPACHO_EJECUTADO!FF49 -> 34.4 | J45: 0 | K45: 46.7 | L45: 7.4 | M45: 0 | N45: 561.1 | O45: =+SUM(C45:N45) -> 7702.952 | T45: INVERSIONES SHAQSHA S.A.C. | U45: C.H. PARIAC | V45: 96
B46: 20:00 | C46: 1175.465 | D46: 3215 | E46: 2765.197 | F46: 48.1 | G46: 0 | H46: 0 | I46: =+DESPACHO_EJECUTADO!FF50 -> 34.32 | J46: 0 | K46: 45.3 | L46: 7.4 | M46: 0 | N46: 456.3 | O46: =+SUM(C46:N46) -> 7747.082 | T46: KALLPA GENERACION S.A. | U46: C.H. CERRO DEL AGUILA | W46: 9016.85
B47: 20:30 | C47: 1170.996 | D47: 3226 | E47: 2766.912 | F47: 48.1 | G47: 0 | H47: 0 | I47: =+DESPACHO_EJECUTADO!FF51 -> 34.25 | J47: 0 | K47: 44.9 | L47: 7.4 | M47: 0 | N47: 417.1 | O47: =+SUM(C47:N47) -> 7715.658 | U47: M.C.H. CERRO DEL AGUILA | V47: 161
B48: 21:00 | C48: 1171.098 | D48: 3246.8 | E48: 2723.19 | F48: 48.1 | G48: 0 | H48: 0 | I48: =+DESPACHO_EJECUTADO!FF52 -> 34.16 | J48: 0 | K48: 45.4 | L48: 7.4 | M48: 0 | N48: 361.8 | O48: =+SUM(C48:N48) -> 7637.948 | T48: LA VIRGEN | U48: C.H. LA VIRGEN | W48: 1253.25
B49: 21:30 | C49: 1172.958 | D49: 3168.1 | E49: 2712.637 | F49: 47.9 | G49: 0 | H49: 0 | I49: =+DESPACHO_EJECUTADO!FF53 -> 34.68 | J49: 0 | K49: 45.8 | L49: 7.4 | M49: 0 | N49: 365 | O49: =+SUM(C49:N49) -> 7554.475 | T49: MAJA ENERGIA S.A.C. | U49: C.H. RONCADOR | V49: 84
B50: 22:00 | C50: 1169.798 | D50: 3168.5 | E50: 2663.662 | F50: 48.1 | G50: 0 | H50: 0 | I50: =+DESPACHO_EJECUTADO!FF54 -> 33.57 | J50: 0 | K50: 46.7 | L50: 7.4 | M50: 0 | N50: 375.7 | O50: =+SUM(C50:N50) -> 7513.43 | T50: ORAZUL ENERGY PERÚ | U50: C.H. CAÑA BRAVA | V50: 130.6
B51: 22:30 | C51: 1176.436 | D51: 3115.4 | E51: 2673.27 | F51: 48.1 | G51: 0 | H51: 0 | I51: =+DESPACHO_EJECUTADO!FF55 -> 34.23 | J51: 0 | K51: 45.5 | L51: 7.4 | M51: 0 | N51: 349.8 | O51: =+SUM(C51:N51) -> 7450.136 | U51: C.H. CAÑON DEL PATO | W51: 4977.15
B52: 23:00 | C52: 1179.184 | D52: 3076.7 | E52: 2498.194 | F52: 0 | G52: 0 | H52: 0 | I52: =+DESPACHO_EJECUTADO!FF56 -> 34.34 | J52: 0 | K52: 44.8 | L52: 7.4 | M52: 0 | N52: 346.2 | O52: =+SUM(C52:N52) -> 7186.818 | U52: C.H. CARHUAQUERO | W52: 2162.4
B53: 23:30 | C53: 1171.237 | D53: 3035.4 | E53: 2365.937 | F53: 0 | G53: 0 | H53: 0 | I53: =+DESPACHO_EJECUTADO!FF57 -> 34.38 | J53: 0 | K53: 45.9 | L53: 7.4 | M53: 0 | N53: 342.6 | O53: =+SUM(C53:N53) -> 7002.854 | U53: C.H. CARHUAQUERO IV | V53: 237.8
B54: 00:00 | C54: 1166.327 | D54: 2772.6 | E54: 2324.86 | F54: 0 | G54: 0 | H54: 0 | I54: =+DESPACHO_EJECUTADO!FF58 -> 34.4 | J54: 0 | K54: 44.9 | L54: 7.4 | M54: 0 | N54: 336.7 | O54: =+SUM(C54:N54) -> 6687.187 | T54: ORYGEN PERU S.A.A. | U54: C.H. CALLAHUANCA | W54: 1109.7
B55: TOTAL MWh | C55: =SUM(C7:C54)/2 -> 27768.873 | D55: =SUM(D7:D54)/2 -> 65375.55 | E55: =SUM(E7:E54)/2 -> 57000.857 | F55: =SUM(F7:F54)/2 -> 1067.75 | G55: =SUM(G7:G54)/2 -> 0 | H55: =SUM(H7:H54)/2 -> 0 | I55: =SUM(I7:I54)/2 -> 317.595 | J55: =SUM(J7:J54)/2 -> 0 | ... O55: =SUM(O7:O54)/2 -> 170728.22 | U55: C.H. HER 1 | V55: 14.4
B56: % | C56: =+C55/$O$55 -> 0.16264957 | D56: =+D55/$O$55 -> 0.38292175 | E56: =+E55/$O$55 -> 0.33386897 | F56: =+F55/$O$55 -> 0.0062540919 | G56: =+G55/$O$55 -> 0 | H56: =+H55/$O$55 -> 0 | I56: =+I55/$O$55 -> 0.0018602372 | J56: =+J55/$O$55 -> 0 | ... O56: =+O55/$O$55 -> 1 | U56: C.H. HUAMPANI | V56: 721.55
U57: C.H. HUINCO | W57: 3666.05
U58: C.H. MATUCANA | W58: 2136.7
U59: C.H. MOYOPAMPA | V59: 1535.85
T60: PERUANA DE INVERSIONES EN ENERGIAS RENOVABLES S.A. | U60: C.H. MANTA I | V60: 430.55
T61: SAN GABAN | U61: C.H. SAN GABAN II | W61: 2552.55
U62: PCH TUPURI | V62: 26.45
T63: SINERSA | U63: C.H. CHANCAY | V63: 480.774
U64: C.H. POECHOS II | V64: 152.099
T65: STATKRAFT S.A | U65: C.H. ARCATA | V65: 48
U66: C.H. CAHUA | V66: 992.7
U67: C.H. CHEVES | W67: 1826.75
U68: C.H. GALLITO CIEGO | W68: 392
U69: C.H. MALPASO | W69: 508.55
U70: C.H. OROYA | V70: 133.1
U71: C.H. PACHACHACA | V71: 216.7
U72: C.H. YAUPI | V72: 2548.9
T73: VARI ENERGIA S.A.C. | U73: C.H. ANASHIRONI | V73: 497.9
T74: TOTAL MWh | V74: 27768.873 | W74: 65375.55

Sheet GENERACION RER
B3: lunes, 27 de Octubre del 2025
B5: GENERACIÓN ELÉCTRICA DE LAS CENTRALES RER (MW)
B6: HORA | C6: AGRO INDUSTRIAL PARAMONGA S.A. | D6: AGROAURORA S.A.C. | E6: AGROINDUSTRIAS SAN JACINTO S.A.A. | F6: AGROLMOS SOCIEDAD ANONIMA - AGROLMOS S.A. | G6: ANDEAN POWER S.A.C. | H6: ASOCIACIÓN SANTA LUCIA DE CHACAS | I6: ATRIA ENERGIA S.A.C. | J6: BIOENERGIA DEL CHIRA S.A. | K6: COLCA SOLAR S.A.C. | L6: EGEJUNIN | Q6: ELECTRICA YANAPAMPA SAC | R6: EMPRESA DE GENERACION ELECTRICA CANCHAYLLO SAC | S6: EMPRESA DE GENERACION ELECTRICA RIO BAÑOS S.A.C. | T6: EMPRESA DE GENERACION ELECTRICA SANTA ANA S.A.C. | U6: EMPRESA ELECTRICA AGUA AZUL | V6: EMPRESA ELECTRICA RIO DOBLE | W6: ENERGÍA EÓLICA S.A. | Y6: ENERGIA RENOVABLE DEL SUR S.A. | Z6: ENGIE ENERGIA PERU S.A.A. | AE6: GENERACIÓN ANDINA S.A.C. | AG6: GENERADORA DE ENERGÍA DEL PERÚ | AK6: GR CORTARRAMA SOCIEDAD ANONIMA CERRADA | AL6: GR PAINO SOCIEDAD ANONIMA CERRADA | AM6: GR TARUCA SOCIEDAD ANONIMA CERRADA | AN6: HIDROCAÑETE S.A. | AO6: HUAURA POWER GROUP S.A. | AP6: HYDRO PATAPO S.A.C. | AQ6: JOYA SOLAR S.A.C. | AR6: KALLPA GENERACION S.A. | AS6: KONDU SAC | AT6: MAJA ENERGIA S.A.C. | AU6: MAJES ARCUS S.A.C. | AV6: MOQUEGUA FV S.A.C. | AW6: ORAZUL ENERGY PERÚ | AY6: ORYGEN PERU S.A.A. | BD6: PANAMERICANA SOLAR SAC. | BE6: PARQUE EOLICO MARCONA S.A.C. | BF6: PARQUE EOLICO TRES HERMANAS S.A.C. | BG6: PERUANA DE INVERSIONES EN ENERGIAS RENOVABLES S.A. | BH6: PETRAMAS | BL6: REPARTICIÓN ARCUS S.A.C. | BM6: SAN GABAN | BN6: SINERSA | BP6: TACNA SOLAR SAC. | BQ6: VARI ENERGIA S.A.C. | BR6: TOTAL RER
C7: C.T. PARAMONGA | D7: C.T. MAPLE | E7: C.T SAN JACINTO | F7: C.T. AGROLMOS | G7: C.H. CARHUAC | H7: C.H. HUALLIN | I7: C.H. PURMACANA | J7: C.T. CAÑA BRAVA | L7: C.H. HUASAHUASI I | M7: C.H. HUASAHUASI II | N7: C.H. RUNATULLO II | O7: C.H. RUNATULLO III | P7: C.H. STA CRUZ I y II | Q7: C.H. YANAPAMPA | R7: C.H. CANCHAYLLO | S7: C.H. RUCUY | T7: C.H. RENOVANDES H1 | U7: C.H. POTRERO | V7: C.H. LAS PIZARRAS | AE7: C.H. 8 DE AGOSTO | AF7: C.H. EL CARMEN | AG7: C.H. ANGEL I | AH7: C.H. ANGEL II | AI7: C.H. ANGEL III | AJ7: C.H. LA JOYA | AN7: C.H. NUEVAIMPERIAL | AO7: C.H. YARUCAYA | AP7: MCH PATAPO | AT7: C.H. RONCADOR | AW7: C.H. CANA BRAVA | AX7: C.H. CARHUAQUERO4 | BC7: C.H. HER 1 | BG7: C.H. MANTA | BH7: C.T. HUAYCOLORO | BI7: C.T. LA GRINGA V | BJ7: CTB CALLAO | BK7: CTB. DONA CATALINA | BM7: C.H. TUPURI | BN7: C.H. CHANCAY | BO7: C.H. POECHOS2 | BQ7: C.H. ANASHIRONI | BR7: MW
B8: 0:30 | C8: 15.7 | D8: 17.5 | E8: 9.1 | G8: 16.6 | H8: 2.3 | J8: 8.8 | L8: 10.1 | N8: 14.8 | O8: 20.2 | P8: 7.2 | Q8: 3.4 | R8: 4.4 | S8: 20 | U8: 16.5 | V8: 18.9 | W8: 11.9 | X8: 22.1 | Y8: 34.7 | Z8: 85.3 | AA8: 81 | AC8: 7.3 | AD8: 4.6 | AE8: 20.9 | AF8: 6.4 | AG8: 18 | AH8: 18.6 | AI8: 18.3 | AJ8: 7.1 | AL8: 1.4 | AM8: 0.8 | AN8: 3.6 | AO8: 18.6 | AT8: 3.5 | AW8: 5.4 | AX8: 9.8 | AY8: 18.7 | BA8: 30.7 | BC8: 0.6 | BE8: 9.2 | BF8: 28.1 | BG8: 17.3 | BH8: 2.9 | BI8: 1.1 | BJ8: 1.1 | BK8: 2.4 | BM8: 0.9 | BN8: 20.008 | BO8: 6.346 | BQ8: 20.7 | BR8: 724.854
B9: 1:00 | C9: 15.1 | D9: 17.5 | E9: 8.2 | G9: 17.7 | H9: 2.3 | J9: 8.2 | L9: 10.1 | N9: 14.9 | O9: 20.2 | P9: 7.3 | Q9: 3.4 | R9: 4.3 | S9: 20 | U9: 16.5 | V9: 18.9 | W9: 10.3 | X9: 14.1 | Y9: 39.5 | Z9: 76.9 | AA9: 71.7 | AC9: 6.8 | AD9: 3.5 | AE9: 20.9 | AF9: 6.3 | AG9: 18 | AH9: 18 | AI9: 18.3 | AJ9: 7.1 | AL9: 1.3 | AM9: 0.8 | AN9: 3.6 | AO9: 18.6 | AT9: 3.5 | AW9: 5.4 | AX9: 9.9 | AY9: 19.9 | BA9: 25.7 | BC9: 0.6 | BE9: 12 | BF9: 38.1 | BG9: 17.4 | BH9: 2.9 | BI9: 1.1 | BJ9: 1.1 | BK9: 2.4 | BM9: 0.9 | BN9: 20.013 | BO9: 6.345 | BQ9: 20.7 | BR9: 708.258
B10: 1:30 | C10: 15.8 | D10: 17.5 | E10: 8.9 | G10: 17.8 | H10: 2.3 | J10: 8.1 | L10: 10.1 | N10: 15 | O10: 20.2 | P10: 7.3 | Q10: 3.5 | R10: 4.3 | S10: 20 | U10: 16.5 | V10: 18.9 | W10: 10.1 | X10: 15.3 | Y10: 39.1 | Z10: 64.3 | AA10: 55.7 | AC10: 5.1 | AD10: 3.6 | AE10: 20.9 | AF10: 6.1 | AG10: 18 | AH10: 18.4 | AI10: 18.6 | AJ10: 7.1 | AL10: 0.7 | AM10: 0.5 | AN10: 3.6 | AO10: 18.6 | AT10: 3.5 | AW10: 5.5 | AX10: 9.9 | AY10: 19.4 | BA10: 26.1 | BC10: 0.6 | BE10: 9.8 | BF10: 28.5 | BG10: 17.5 | BH10: 2.9 | BI10: 1.1 | BJ10: 1.1 | BK10: 2.4 | BM10: 0.9 | BN10: 20.005 | BO10: 6.333 | BQ10: 20.7 | BR10: 668.138
B11: 2:00 | C11: 15.8 | D11: 17.5 | E11: 6.5 | G11: 18.2 | H11: 2.3 | J11: 9.2 | L11: 10.1 | N11: 15.2 | O11: 20.2 | P11: 7.4 | Q11: 3.5 | R11: 4.3 | S11: 20 | U11: 16.5 | V11: 18.8 | W11: 10.4 | X11: 30 | Y11: 37.5 | Z11: 57.9 | AA11: 55.7 | AC11: 5.4 | AD11: 3.6 | AE11: 20.9 | AF11: 6 | AG11: 18.2 | AH11: 18.4 | AI11: 18.6 | AJ11: 7.1 | AL11: 0.5 | AM11: 0.1 | AN11: 3.6 | AO11: 18.6 | AT11: 3.5 | AW11: 5.5 | AX11: 9.9 | AY11: 19.2 | BA11: 27.2 | BC11: 0.6 | BE11: 9.8 | BF11: 27.4 | BG11: 17.3 | BH11: 2.9 | BI11: 1.1 | BJ11: 1.1 | BK11: 2.4 | BM11: 0.9 | BN11: 20.046 | BO11: 6.313 | BQ11: 20.8 | BR11: 673.959
B12: 2:30 | C12: 15.8 | D12: 17.5 | E12: 8.2 | G12: 14.8 | H12: 2.5 | J12: 9.2 | L12: 10.1 | N12: 15 | O12: 20.2 | P12: 7.4 | Q12: 3.5 | R12: 4.5 | S12: 20 | U12: 16.8 | V12: 18.9 | W12: 10.1 | X12: 28.9 | Y12: 41.8 | Z12: 55 | AA12: 51.3 | AC12: 4.2 | AD12: 3.3 | AE12: 20.7 | AF12: 6 | AG12: 18.2 | AH12: 18.6 | AI12: 18.9 | AJ12: 7.1 | AN12: 3.6 | AO12: 18.6 | AT12: 3.5 | AW12: 5.4 | AX12: 9.9 | AY12: 24.5 | BA12: 34.5 | BC12: 0.6 | BE12: 11.2 | BF12: 27 | BG12: 17.4 | BH12: 2.9 | BI12: 1.1 | BJ12: 1.1 | BK12: 2.4 | BM12: 0.9 | BN12: 20.046 | BO12: 6.354 | BQ12: 20.8 | BR12: 680.3
B13: 3:00 | C13: 15 | D13: 17.5 | E13: 8.9 | G13: 14.5 | H13: 2.6 | J13: 9.5 | L13: 10 | N13: 14.4 | O13: 20.1 | P13: 7.4 | Q13: 3.5 | R13: 4.5 | S13: 20 | U13: 17.2 | V13: 18.9 | W13: 7.9 | X13: 15 | Y13: 46.7 | Z13: 48.8 | AA13: 47.6 | AC13: 3 | AD13: 4.6 | AE13: 20.5 | AF13: 6 | AG13: 18.2 | AH13: 18.6 | AI13: 18.9 | AJ13: 7.1 | AL13: 1.2 | AM13: 0.9 | AN13: 3.6 | AO13: 18.6 | AT13: 3.5 | AW13: 5.4 | AX13: 9.9 | AY13: 27.5 | BA13: 38.7 | BC13: 0.6 | BE13: 10.7 | BF13: 30.6 | BG13: 17.5 | BH13: 2.9 | BI13: 1.1 | BJ13: 1.1 | BK13: 2.4 | BM13: 0.9 | BN13: 20.029 | BO13: 6.348 | BQ13: 20.7 | BR13: 671.077
B14: 3:30 | C14: 15 | D14: 17.5 | E14: 8.6 | G14: 14.5 | H14: 2.6 | J14: 8.9 | L14: 10.1 | N14: 14.7 | O14: 20.2 | P14: 7.4 | Q14: 3.5 | R14: 4.4 | S14: 20 | U14: 17.9 | V14: 18.9 | W14: 9.3 | X14: 11 | Y14: 45.9 | Z14: 52.2 | AA14: 52.7 | AC14: 5.7 | AD14: 2.6 | AE14: 20.5 | AF14: 6 | AG14: 18.2 | AH14: 18.4 | AI14: 18.7 | AJ14: 7.2 | AL14: 1.4 | AM14: 0.8 | AN14: 3.6 | AO14: 18.6 | AT14: 3.5 | AW14: 5.5 | AX14: 9.9 | AY14: 23.9 | BA14: 35.2 | BC14: 0.6 | BE14: 9.5 | BF14: 27 | BG14: 17.5 | BH14: 2.9 | BI14: 1.1 | BJ14: 1.1 | BK14: 2.4 | BM14: 0.8 | BN14: 20.022 | BO14: 6.313 | BQ14: 20.9 | BR14: 665.135
B15: 4:00 | C15: 15 | D15: 17.5 | E15: 8.2 | G15: 14.7 | H15: 2.6 | J15: 8.8 | L15: 10.1 | N15: 14.4 | O15: 20.2 | P15: 7.4 | Q15: 3.5 | R15: 4.4 | S15: 20 | U15: 18.3 | V15: 18.9 | W15: 11.9 | X15: 12.6 | Y15: 43.3 | Z15: 59.2 | AA15: 52.6 | AC15: 7.1 | AD15: 3.4 | AE15: 20.5 | AF15: 6 | AG15: 18.2 | AH15: 18.4 | AI15: 18.7 | AJ15: 7.2 | AL15: 0.7 | AM15: 0.3 | AN15: 3.6 | AO15: 18.6 | AT15: 3.5 | AW15: 5.4 | AX15: 9.9 | AY15: 24.3 | BA15: 27.3 | BC15: 0.6 | BE15: 10.7 | BF15: 33.6 | BG15: 17.6 | BH15: 2.9 | BI15: 1.1 | BJ15: 1.1 | BK15: 2.4 | BM15: 0.8 | BN15: 20.012 | BO15: 6.354 | BQ15: 20.7 | BR15: 674.566
B16: 4:30 | C16: 15.9 | D16: 17.5 | E16: 9 | G16: 14.5 | H16: 2.6 | J16: 9.2 | L16: 9.9 | N16: 14.4 | O16: 19.8 | P16: 7.6 | Q16: 3.5 | R16: 4.4 | S16: 20 | U16: 18.5 | V16: 18.9 | W16: 12.7 | X16: 9 | Y16: 30.1 | Z16: 53.8 | AA16: 49.1 | AC16: 5.2 | AD16: 2.6 | AE16: 20.4 | AF16: 6 | AG16: 18.2 | AH16: 18.8 | AI16: 18.8 | AJ16: 7.2 | AN16: 3.6 | AO16: 18.6 | AT16: 3.5 | AW16: 5.6 | AX16: 9.9 | AY16: 16.1 | BA16: 19.3 | BC16: 0.6 | BE16: 12.6 | BF16: 24.1 | BG16: 17.7 | BH16: 2.9 | BI16: 1.1 | BJ16: 1.1 | BK16: 2.4 | BM16: 0.8 | BN16: 19.987 | BO16: 6.348 | BQ16: 20.7 | BR16: 624.535
B17: 5:00 | C17: 15.5 | D17: 17.5 | E17: 9.1 | G17: 14.9 | H17: 2.6 | J17: 8.9 | L17: 9.9 | N17: 14.4 | O17: 19.4 | P17: 7.8 | Q17: 3.5 | R17: 4.3 | S17: 20 | U17: 18.5 | V17: 18.9 | W17: 13.5 | X17: 9.5 | Y17: 30.8 | Z17: 23.4 | AA17: 30.8 | AC17: 2.7 | AD17: 1.3 | AE17: 20 | AF17: 5.6 | AG17: 18.2 | AH17: 18.9 | AI17: 18.8 | AJ17: 7.2 | AN17: 3.6 | AO17: 18.6 | AT17: 3.5 | AW17: 5.3 | AX17: 9.9 | AY17: 11.9 | BA17: 12.7 | BC17: 0.6 | BE17: 10.9 | BF17: 23.4 | BG17: 17.7 | BH17: 2.9 | BI17: 1.1 | BJ17: 1.1 | BK17: 2.4 | BM17: 1 | BN17: 20.026 | BO17: 6.346 | BQ17: 20.7 | BR17: 559.572
B18: 5:30 | C18: 16 | D18: 17.5 | E18: 7.3 | G18: 20.2 | H18: 2.6 | J18: 9.3 | L18: 10.2 | N18: 14.4 | O18: 19.4 | P18: 7.8 | Q18: 3.4 | R18: 4.3 | S18: 20 | U18: 18.6 | V18: 18.8 | W18: 17.5 | X18: 9.3 | Y18: 26.1 | Z18: 18.3 | AA18: 18 | AB18: 1.1 | AC18: 2.1 | AD18: 0.9 | AE18: 20 | AF18: 5.8 | AG18: 18.2 | AH18: 18.9 | AI18: 18.8 | AJ18: 7.2 | AK18: 1.4 | AL18: 0.7 | AM18: 0.2 | AN18: 3.6 | AO18: 18.6 | AQ18: 8 | AR18: 5.4 | AT18: 3.5 | AV18: 0.5 | AW18: 5.5 | AX18: 9.9 | AY18: 3.5 | AZ18: 5.9 | BA18: 6.2 | BB18: 5.4 | BC18: 0.6 | BD18: 0.4 | BE18: 9 | BF18: 24.4 | BG18: 17.7 | BH18: 2.9 | BI18: 1.1 | BJ18: 1.1 | BK18: 2.4 | BM18: 1.1 | BN18: 20.06 | BO18: 6.345 | BP18: 0.1 | BQ18: 20.8 | BR18: 558.305
B19: 6:00 | C19: 15.6 | D19: 17.5 | E19: 9.3 | G19: 20.2 | H19: 2.6 | J19: 9.3 | L19: 10.4 | N19: 14.3 | O19: 19 | P19: 7.8 | Q19: 3.4 | R19: 4.2 | S19: 20 | U19: 19 | V19: 18.9 | W19: 18.6 | X19: 10.7 | Y19: 33.9 | Z19: 15.3 | AA19: 17.8 | AB19: 9.9 | AC19: 1.7 | AD19: 0.6 | AE19: 19.9 | AF19: 5.4 | AG19: 18.4 | AH19: 18.9 | AI19: 18.9 | AJ19: 7.2 | AK19: 6.6 | AL19: 0.8 | AM19: 0.5 | AN19: 3.6 | AO19: 18.6 | AQ19: 79 | AR19: 44.5 | AT19: 3.5 | AU19: 0.8 | AV19: 1.4 | AW19: 5.4 | AX19: 9.9 | AY19: 5.1 | AZ19: 44.4 | BA19: 5.2 | BB19: 38.4 | BC19: 0.6 | BD19: 1.4 | BE19: 9.2 | BF19: 23 | BG19: 17.7 | BH19: 2.9 | BI19: 1.1 | BJ19: 1.1 | BK19: 2.4 | BL19: 0.7 | BM19: 1.1 | BN19: 20.033 | BO19: 6.333 | BP19: 0.4 | BQ19: 20.7 | BR19: 765.066
B20: 6:30 | C20: 15 | D20: 17.5 | E20: 7.9 | G20: 20.2 | H20: 2.5 | J20: 9.3 | L20: 9.9 | N20: 14.6 | O20: 19.2 | P20: 7.8 | Q20: 3.4 | R20: 4.3 | S20: 20 | U20: 19.1 | V20: 18.7 | W20: 16.7 | X20: 11.2 | Y20: 28.9 | Z20: 15.2 | AA20: 16.5 | AB20: 21.8 | AC20: 1.6 | AD20: 0.9 | AE20: 19.5 | AF20: 5.4 | AG20: 18.8 | AH20: 19 | AI20: 18.9 | AJ20: 7.1 | AK20: 20.3 | AL20: 0.1 | AN20: 3.6 | AO20: 18.6 | AQ20: 168.3 | AR20: 88.8 | AT20: 3.5 | AU20: 2.8 | AV20: 2.4 | AW20: 5.6 | AX20: 10 | AY20: 10.2 | AZ20: 92.7 | BA20: 4.7 | BB20: 76.3 | BC20: 0.6 | BD20: 2.2 | BE20: 8.5 | BF20: 21.4 | BG20: 17.5 | BH20: 2.9 | BI20: 1.1 | BJ20: 1.1 | BK20: 2.4 | BL20: 2.5 | BM20: 1.1 | BN20: 20.047 | BO20: 6.348 | BP20: 0.8 | BQ20: 20.8 | BR20: 1008.095
B21: 7:00 | C21: 16 | D21: 17.5 | E21: 9.2 | G21: 18.8 | H21: 2.5 | J21: 9.5 | K21: 0.1 | L21: 9.9 | N21: 14.2 | O21: 19 | P21: 7.7 | Q21: 3.4 | R21: 4.6 | S21: 20 | U21: 19.4 | V21: 18.7 | W21: 13.7 | X21: 12.9 | Y21: 31 | Z21: 23.9 | AA21: 17.9 | AB21: 32.2 | AC21: 2.4 | AD21: 1.1 | AE21: 19.5 | AF21: 5.4 | AG21: 20.4 | AH21: 20.4 | AI21: 19.1 | AJ21: 7.1 | AK21: 77.2 | AL21: 0.2 | AN21: 3.6 | AO21: 18.6 | AQ21: 237.1 | AR21: 188.9 | AT21: 3.5 | AU21: 5.5 | AV21: 3.6 | AW21: 5.5 | AX21: 9.9 | AY21: 10.6 | AZ21: 135.9 | BA21: 4 | BB21: 98 | BC21: 0.6 | BD21: 3.2 | BE21: 6.8 | BF21: 20.7 | BG21: 17.5 | BH21: 2.9 | BI21: 1.1 | BJ21: 1.1 | BK21: 2.4 | BL21: 4.9 | BM21: 1.2 | BN21: 19.977 | BO21: 6.321 | BP21: 1.3 | BQ21: 20.7 | BR21: 1330.298
B22: 7:30 | C22: 15.6 | D22: 18.3 | E22: 8.5 | G22: 6 | H22: 2.4 | J22: 9.3 | K22: 0.1 | L22: 10.1 | N22: 14.2 | O22: 18.9 | P22: 7.8 | Q22: 3.3 | R22: 4.5 | S22: 20 | U22: 18.8 | V22: 18.7 | W22: 18.3 | X22: 14.1 | Y22: 32.1 | Z22: 19.5 | AA22: 16.4 | AB22: 36.1 | AC22: 2.5 | AD22: 2 | AE22: 19.5 | AF22: 5.4 | AG22: 20.4 | AH22: 20.4 | AI22: 19.5 | AJ22: 6.4 | AK22: 80.8 | AN22: 3.5 | AO22: 18.6 | AQ22: 251 | AR22: 201.2 | AS22: 0.1 | AT22: 3.5 | AU22: 8.2 | AV22: 5.5 | AW22: 5.5 | AX22: 9.9 | AY22: 13 | AZ22: 143.8 | BA22: 5.6 | BB22: 103.4 | BC22: 0.6 | BD22: 5.2 | BE22: 9.2 | BF22: 18.4 | BG22: 17.8 | BH22: 2.9 | BI22: 1.1 | BK22: 2.4 | BL22: 7.4 | BM22: 1.2 | BN22: 20.076 | BO22: 6.326 | BP22: 2.3 | BQ22: 20.7 | BR22: 1378.302
B23: 8:00 | C23: 15.4 | D23: 18.3 | E23: 7.8 | G23: 7.1 | H23: 2.4 | J23: 8.9 | K23: 0.1 | L23: 10.1 | N23: 14.5 | O23: 19.1 | P23: 7.8 | Q23: 3.4 | R23: 4.4 | S23: 20.1 | U23: 19.1 | V23: 18.7 | W23: 20.6 | X23: 15.7 | Y23: 28.7 | Z23: 27.8 | AA23: 36.8 | AB23: 36.9 | AC23: 2.3 | AD23: 0.6 | AE23: 19.1 | AF23: 5.4 | AG23: 20.4 | AH23: 20.4 | AI23: 20 | AJ23: 7.3 | AK23: 80.9 | AN23: 3.5 | AO23: 18.6 | AQ23: 253.1 | AR23: 207.3 | AS23: 0.1 | AT23: 3.5 | AU23: 10.8 | AV23: 11.2 | AW23: 5.4 | AX23: 9.9 | AY23: 12.2 | AZ23: 148.7 | BA23: 5.8 | BB23: 107.2 | BC23: 0.6 | BD23: 14.1 | BE23: 6.2 | BF23: 17.9 | BG23: 18 | BH23: 2.9 | BI23: 1.1 | BK23: 2.4 | BL23: 9.7 | BM23: 1.2 | BN23: 20.013 | BO23: 6.305 | BP23: 3.7 | BQ23: 21 | BR23: 1442.518
B24: 8:30 | C24: 15.5 | D24: 18.4 | E24: 9.6 | G24: 7.9 | H24: 2.4 | J24: 8.5 | K24: 0.5 | L24: 10.2 | N24: 14.4 | O24: 19.1 | P24: 7.8 | Q24: 3.5 | R24: 4.4 | S24: 20.3 | U24: 20 | V24: 18.7 | W24: 16.7 | X24: 20.7 | Y24: 33.7 | Z24: 40.8 | AA24: 43.9 | AB24: 37.9 | AC24: 2.4 | AD24: 1.2 | AE24: 19 | AF24: 5.4 | AG24: 20.4 | AH24: 20.4 | AI24: 20 | AJ24: 7.2 | AK24: 80.4 | AN24: 3.5 | AO24: 18.6 | AQ24: 253.1 | AS24: 0.2 | AT24: 3.5 | AU24: 12.7 | AV24: 15.6 | AW24: 5.5 | AX24: 9.9 | AY24: 4.8 | AZ24: 151.2 | BB24: 109.5 | BC24: 0.6 | BD24: 19 | BE24: 11.6 | BF24: 15.6 | BG24: 17 | BH24: 2.9 | BI24: 1.1 | BK24: 2.4 | BL24: 11.9 | BM24: 1.2 | BN24: 20.343 | BO24: 6.318 | BP24: 5.9 | BQ24: 20.8 | BR24: 1276.061
B25: 9:00 | C25: 15.5 | D25: 18.3 | E25: 7.9 | G25: 16 | H25: 2.4 | J25: 8.9 | K25: 0.7 | L25: 10.6 | N25: 14.6 | O25: 18.7 | P25: 7.9 | Q25: 3.5 | R25: 4.4 | S25: 19.7 | U25: 19.9 | V25: 18.7 | W25: 15.1 | X25: 21.9 | Y25: 42.9 | Z25: 53 | AA25: 46.8 | AB25: 38.5 | AC25: 5.9 | AD25: 3.3 | AE25: 19.2 | AF25: 5.4 | AG25: 20.4 | AH25: 20.4 | AI25: 20 | AJ25: 6.6 | AK25: 80.8 | AN25: 3.5 | AO25: 18.6 | AQ25: 252.7 | AS25: 0.3 | AT25: 3.5 | AU25: 14.3 | AV25: 15.8 | AW25: 5.2 | AX25: 9.9 | AY25: 1.8 | AZ25: 153.2 | BB25: 111.3 | BC25: 0.6 | BD25: 18.5 | BE25: 11.2 | BF25: 28.2 | BG25: 17.8 | BH25: 2.9 | BI25: 1.1 | BK25: 2.4 | BL25: 13.8 | BM25: 1.2 | BN25: 19.643 | BO25: 6.319 | BP25: 8.7 | BQ25: 20.7 | BR25: 1331.062
B26: 9:30 | C26: 15.5 | D26: 18.3 | E26: 7.3 | G26: 20.2 | H26: 2.3 | J26: 9.3 | K26: 0.9 | L26: 10.9 | N26: 14.5 | O26: 19 | P26: 7.9 | Q26: 3.6 | R26: 4.5 | S26: 20 | U26: 20 | V26: 18.7 | W26: 15.5 | X26: 29.2 | Y26: 54 | Z26: 65.5 | AA26: 55.7 | AB26: 38.4 | AC26: 7.7 | AD26: 2.3 | AE26: 19.5 | AF26: 5.4 | AG26: 20.4 | AH26: 20.4 | AI26: 20 | AJ26: 6.6 | AK26: 80.9 | AN26: 3.6 | AO26: 18.6 | AQ26: 252.6 | AS26: 0.4 | AT26: 3.5 | AU26: 15.8 | AV26: 15.7 | AW26: 5.4 | AX26: 9.9 | AY26: 8.7 | AZ26: 154.3 | BA26: 1.8 | BB26: 112.3 | BC26: 0.6 | BD26: 18.6 | BE26: 14.2 | BF26: 38.9 | BG26: 17.8 | BH26: 2.9 | BI26: 1.1 | BK26: 2.4 | BL26: 15.3 | BM26: 1.2 | BN26: 20.047 | BO26: 6.356 | BP26: 15 | BQ26: 20.8 | BR26: 1412.203
B27: 10:00 | C27: 16.6 | D27: 17.5 | E27: 10.2 | G27: 20.2 | H27: 2.3 | J27: 9 | K27: 1 | L27: 10.8 | N27: 14.2 | O27: 19 | P27: 7.9 | Q27: 3.4 | R27: 4.5 | S27: 20 | U27: 20 | V27: 18.7 | W27: 17.8 | X27: 42.7 | Y27: 55 | Z27: 63.4 | AA27: 61.7 | AB27: 39.4 | AC27: 10.5 | AD27: 4.4 | AE27: 19.5 | AF27: 6 | AG27: 20.4 | AH27: 20.4 | AI27: 20 | AJ27: 7 | AK27: 80.9 | AN27: 3.5 | AO27: 18.6 | AQ27: 252.9 | AS27: 0.4 | AT27: 3.5 | AU27: 17 | AV27: 16 | AW27: 5.4 | AX27: 9.9 | AY27: 15.9 | AZ27: 153.8 | BA27: 8.6 | BB27: 113.2 | BC27: 0.6 | BD27: 19 | BE27: 16.5 | BF27: 45.5 | BG27: 17.3 | BH27: 2.9 | BI27: 1.1 | BK27: 2.4 | BL27: 16.5 | BM27: 1.2 | BN27: 20.069 | BO27: 6.368 | BP27: 18 | BQ27: 20.7 | BR27: 1471.237
B28: 10:30 | C28: 15.8 | D28: 12.1 | E28: 8.2 | G28: 20.2 | H28: 2.3 | J28: 9.3 | K28: 1.1 | L28: 10.6 | N28: 14.4 | O28: 19 | P28: 7.9 | Q28: 3.4 | R28: 4.4 | S28: 20 | U28: 20 | V28: 18.7 | W28: 13.1 | X28: 45.7 | Y28: 54.9 | Z28: 64.6 | AA28: 74.8 | AB28: 39.2 | AC28: 12.8 | AD28: 3.5 | AE28: 19.5 | AF28: 6.2 | AG28: 20.4 | AH28: 20.4 | AI28: 20 | AJ28: 7 | AK28: 80.9 | AL28: 0.1 | AM28: 0.6 | AN28: 3.5 | AO28: 18.6 | AQ28: 253 | AS28: 0.3 | AT28: 3.5 | AU28: 18.5 | AV28: 15.9 | AW28: 5.5 | AX28: 9.9 | AY28: 24.1 | AZ28: 154.7 | BA28: 7.2 | BB28: 113.6 | BC28: 0.6 | BD28: 18.9 | BE28: 16.7 | BF28: 53.9 | BG28: 17.4 | BH28: 2.9 | BI28: 1.1 | BK28: 2.4 | BL28: 17.6 | BM28: 1.2 | BN28: 20.006 | BO28: 6.356 | BP28: 19.4 | BQ28: 20.8 | BR28: 1498.662
B29: 11:00 | C29: 15 | D29: 12.1 | E29: 9 | G29: 20.2 | H29: 2.2 | J29: 8.9 | K29: 1.2 | L29: 10.4 | N29: 13.9 | O29: 19.2 | P29: 7.9 | Q29: 3.4 | R29: 4.4 | S29: 20.2 | U29: 20 | V29: 18.7 | W29: 10.5 | X29: 55.5 | Y29: 54.8 | Z29: 69.7 | AA29: 77.6 | AB29: 39.6 | AC29: 11.7 | AD29: 4.6 | AE29: 19.7 | AF29: 6.5 | AG29: 20.4 | AH29: 20.4 | AI29: 20 | AJ29: 7 | AK29: 80.9 | AL29: 2.2 | AM29: 2.4 | AN29: 3.5 | AO29: 18.6 | AQ29: 253.1 | AS29: 0.5 | AT29: 3.5 | AU29: 18.8 | AV29: 16 | AW29: 5.5 | AX29: 9.9 | AY29: 31 | AZ29: 153.8 | BA29: 11.4 | BB29: 113.5 | BC29: 0.6 | BD29: 19 | BE29: 21.1 | BF29: 58.4 | BG29: 17.2 | BH29: 2.9 | BI29: 1.1 | BK29: 2.4 | BL29: 18.2 | BM29: 1.2 | BN29: 20.142 | BO29: 6.364 | BP29: 19.6 | BQ29: 20.6 | BR29: 1538.106
B30: 11:30 | C30: 15.4 | D30: 12.1 | E30: 8.3 | G30: 20.2 | H30: 2.2 | J30: 9.5 | K30: 1.1 | L30: 10.2 | N30: 13.7 | O30: 19.1 | P30: 7.9 | Q30: 3.2 | R30: 4.5 | S30: 20 | U30: 20 | V30: 18.7 | W30: 11.1 | X30: 55.3 | Y30: 54.8 | Z30: 86.2 | AA30: 85.9 | AB30: 39.5 | AC30: 13.1 | AD30: 6 | AE30: 19.8 | AF30: 6.8 | AG30: 20.4 | AH30: 20.4 | AI30: 20 | AJ30: 7.2 | AK30: 80.8 | AL30: 2.5 | AM30: 3.3 | AN30: 3.5 | AO30: 18.6 | AQ30: 254.9 | AS30: 0.5 | AT30: 3.5 | AU30: 19 | AV30: 16 | AW30: 5.5 | AX30: 10 | AY30: 42.4 | AZ30: 154.8 | BA30: 17.1 | BB30: 113.8 | BC30: 0.6 | BD30: 19.5 | BE30: 21.1 | BF30: 63.7 | BG30: 17.3 | BH30: 2.9 | BI30: 1.1 | BK30: 2.4 | BL30: 18.5 | BM30: 1.2 | BN30: 20.083 | BO30: 6.344 | BP30: 19.5 | BQ30: 20.5 | BR30: 1593.527
B31: 12:00 | C31: 15.9 | D31: 12.1 | E31: 9.4 | G31: 18.8 | H31: 2.3 | J31: 9.2 | K31: 1.2 | L31: 10.2 | N31: 14.3 | O31: 19.1 | P31: 7.9 | Q31: 3.3 | R31: 4.6 | S31: 20 | U31: 20 | V31: 18.7 | W31: 14.4 | X31: 63.1 | Y31: 55.1 | Z31: 86.8 | AA31: 86.2 | AB31: 38.9 | AC31: 14 | AD31: 7 | AE31: 19.9 | AF31: 7.3 | AG31: 20.4 | AH31: 20.4 | AI31: 20 | AJ31: 8.1 | AK31: 80.9 | AL31: 4.8 | AM31: 6.2 | AN31: 3.5 | AO31: 18.6 | AQ31: 246.5 | AR31: 67.7 | AS31: 0.3 | AT31: 3.5 | AU31: 19.1 | AV31: 16 | AW31: 5.5 | AX31: 9.9 | AY31: 48.2 | AZ31: 153.4 | BA31: 31.3 | BB31: 113.3 | BC31: 0.6 | BD31: 19.6 | BE31: 21.8 | BF31: 67.2 | BG31: 17.1 | BH31: 2.9 | BI31: 1.1 | BK31: 2.4 | BL31: 18.3 | BM31: 1.2 | BN31: 20.062 | BO31: 6.364 | BP31: 19.4 | BQ31: 20.8 | BR31: 1696.126
B32: 12:30 | C32: 15.4 | D32: 12.1 | E32: 9.5 | G32: 9.3 | H32: 2.2 | J32: 9.4 | K32: 1.2 | L32: 14.5 | N32: 14.1 | O32: 19.2 | P32: 7.8 | Q32: 3.3 | R32: 4.5 | S32: 19.8 | U32: 20 | V32: 18.7 | W32: 13.4 | X32: 65.3 | Y32: 55 | Z32: 86.9 | AA32: 82.2 | AB32: 38.6 | AC32: 11.4 | AD32: 5 | AE32: 20.4 | AF32: 7.5 | AG32: 20.4 | AH32: 20.4 | AI32: 20 | AJ32: 7.6 | AK32: 80.8 | AL32: 1.4 | AM32: 2.1 | AN32: 3.5 | AO32: 18.6 | AQ32: 252.8 | AR32: 191.4 | AS32: 0.3 | AT32: 3.5 | AU32: 18.9 | AV32: 15.9 | AW32: 5.4 | AX32: 9.9 | AY32: 45.8 | AZ32: 152.7 | BA32: 39.8 | BB32: 113 | BC32: 0.6 | BD32: 19.5 | BE32: 13.3 | BF32: 44.4 | BG32: 17.3 | BH32: 2.9 | BI32: 1.1 | BK32: 2.4 | BL32: 18.4 | BM32: 1.2 | BN32: 19.733 | BO32: 6.331 | BP32: 19.5 | BQ32: 20.7 | BR32: 1778.264
B33: 13:00 | C33: 15.6 | D33: 12 | E33: 7.8 | G33: 6.1 | H33: 2.3 | J33: 9.4 | K33: 1.1 | L33: 16.3 | N33: 14 | O33: 19.2 | P33: 7.8 | Q33: 3.4 | R33: 4.4 | S33: 20 | U33: 20 | V33: 18.7 | W33: 14.6 | X33: 67.8 | Y33: 54.5 | Z33: 80.5 | AA33: 82.7 | AB33: 37.8 | AC33: 9.3 | AD33: 4.6 | AE33: 20.2 | AF33: 7.5 | AG33: 20.4 | AH33: 20.4 | AI33: 20 | AJ33: 7.6 | AK33: 80.8 | AN33: 3.6 | AO33: 18.6 | AQ33: 253.1 | AR33: 223.3 | AS33: 0.3 | AT33: 3.5 | AU33: 18.3 | AV33: 15.8 | AW33: 5.5 | AX33: 9.9 | AY33: 47.6 | AZ33: 151.9 | BA33: 40 | BB33: 112.7 | BC33: 0.6 | BD33: 19.4 | BE33: 13.6 | BF33: 45.4 | BG33: 17.2 | BH33: 2.9 | BI33: 1.1 | BK33: 2.4 | BL33: 17.6 | BM33: 1.2 | BN33: 20.034 | BO33: 6.337 | BP33: 19.6 | BQ33: 20.7 | BR33: 1798.971
B34: 13:30 | C34: 15.4 | D34: 12 | E34: 7.2 | G34: 6.2 | H34: 2.4 | J34: 9.4 | K34: 1.1 | L34: 16.1 | N34: 14 | O34: 19.4 | P34: 7.7 | Q34: 3.3 | R34: 4.4 | S34: 20 | U34: 20 | V34: 18.7 | W34: 14.7 | X34: 71.1 | Y34: 54.4 | Z34: 81.3 | AA34: 81 | AB34: 38.2 | AC34: 8.2 | AD34: 4.2 | AE34: 20.7 | AF34: 7.5 | AG34: 20.4 | AH34: 20.4 | AI34: 20 | AJ34: 7.2 | AK34: 80.8 | AL34: 0.6 | AM34: 0.1 | AN34: 3.5 | AO34: 18.6 | AQ34: 252.8 | AR34: 220.9 | AS34: 0.2 | AT34: 3.5 | AU34: 17.3 | AV34: 15.8 | AW34: 5.3 | AX34: 9.9 | AY34: 49.6 | AZ34: 151.9 | BA34: 57.7 | BB34: 111.5 | BC34: 0.6 | BD34: 19.4 | BE34: 13.8 | BF34: 46.7 | BG34: 17.2 | BH34: 2.9 | BI34: 1.1 | BK34: 2.4 | BL34: 16.6 | BM34: 1.2 | BN34: 20.069 | BO34: 6.359 | BP34: 19.5 | BQ34: 20.7 | BR34: 1815.128
B35: 14:00 | C35: 14.9 | D35: 12 | E35: 7.4 | G35: 6.9 | H35: 2.4 | J35: 9.5 | K35: 1 | L35: 16.1 | N35: 12.3 | O35: 19.6 | P35: 7.6 | Q35: 3.4 | R35: 4.3 | S35: 20.2 | U35: 20 | V35: 18.7 | W35: 14.8 | X35: 70.8 | Y35: 54.8 | Z35: 74.2 | AA35: 77.2 | AB35: 38.2 | AC35: 7.2 | AD35: 5.2 | AE35: 20.9 | AF35: 7.6 | AG35: 20.4 | AH35: 20.4 | AI35: 20 | AJ35: 7 | AK35: 80.8 | AL35: 1.4 | AM35: 0.4 | AN35: 3.6 | AO35: 18.6 | AQ35: 253 | AR35: 217.9 | AS35: 0.1 | AT35: 3.5 | AU35: 15.9 | AV35: 15.7 | AW35: 5.4 | AX35: 9.9 | AY35: 50.6 | AZ35: 151 | BA35: 51 | BB35: 110.1 | BC35: 0.6 | BD35: 19.3 | BE35: 14.1 | BF35: 48.2 | BG35: 16.8 | BH35: 2.9 | BI35: 1.1 | BK35: 2.4 | BL35: 15.2 | BM35: 1.2 | BN35: 20.316 | BO35: 6.348 | BP35: 19.3 | BQ35: 21.2 | BR35: 1792.864
B36: 14:30 | C36: 15 | D36: 12 | E36: 7.9 | G36: 12.8 | H36: 2.4 | J36: 7.8 | K36: 0.9 | L36: 15.5 | N36: 13.1 | O36: 19.4 | P36: 7.6 | Q36: 3.4 | R36: 4.3 | S36: 20 | U36: 20 | V36: 18.7 | W36: 15.1 | X36: 73 | Y36: 77.6 | Z36: 72.9 | AA36: 78.3 | AB36: 27.3 | AC36: 9.2 | AD36: 5.4 | AE36: 20.9 | AF36: 8.1 | AG36: 20.4 | AH36: 20.4 | AI36: 20 | AJ36: 6.5 | AK36: 80.8 | AL36: 2.1 | AM36: 1.3 | AN36: 3.5 | AO36: 18.6 | AQ36: 252.8 | AR36: 213.6 | AS36: 0.3 | AT36: 3.5 | AU36: 14.2 | AV36: 15.2 | AW36: 5.5 | AX36: 9.9 | AY36: 49.4 | AZ36: 150.4 | BA36: 70.1 | BB36: 109.4 | BC36: 0.6 | BD36: 18.2 | BE36: 14.3 | BF36: 49.4 | BG36: 17 | BH36: 2.9 | BI36: 1.1 | BK36: 2.4 | BL36: 13.6 | BM36: 1.2 | BN36: 20.002 | BO36: 6.335 | BP36: 19.1 | BQ36: 20.7 | BR36: 1823.337
B37: 15:00 | C37: 15 | D37: 12 | E37: 8 | G37: 15.5 | H37: 2.5 | J37: 9.6 | K37: 0.9 | L37: 15.6 | N37: 13.2 | O37: 19.3 | P37: 7.7 | Q37: 3.3 | R37: 4.4 | S37: 20 | U37: 20 | V37: 18.7 | W37: 15.7 | X37: 74 | Y37: 109.7 | Z37: 75.3 | AA37: 82.3 | AB37: 36.4 | AC37: 8.4 | AD37: 4.6 | AE37: 20.9 | AF37: 8.2 | AG37: 20.4 | AH37: 20.4 | AI37: 20 | AJ37: 6.5 | AK37: 80.8 | AL37: 1.5 | AM37: 0.3 | AN37: 3.6 | AO37: 18.4 | AQ37: 252.9 | AR37: 207.6 | AS37: 0.2 | AT37: 3.5 | AU37: 12.2 | AV37: 14.8 | AW37: 5.5 | AX37: 9.9 | AY37: 48.2 | AZ37: 146.9 | BA37: 80.1 | BB37: 108.1 | BC37: 0.6 | BD37: 18 | BE37: 14.5 | BF37: 50.5 | BG37: 17 | BH37: 2 | BI37: 1.1 | BK37: 2.3 | BL37: 11.7 | BM37: 1.2 | BN37: 20.016 | BO37: 6.341 | BP37: 18.5 | BQ37: 20.6 | BR37: 1867.357
B38: 15:30 | C38: 14.5 | D38: 12 | E38: 7.2 | G38: 15.4 | H38: 2.8 | J38: 5.9 | K38: 0.7 | L38: 14.5 | N38: 13.6 | O38: 19.4 | P38: 7.8 | Q38: 3.3 | R38: 4.5 | S38: 20 | U38: 20 | V38: 18.7 | W38: 16.6 | X38: 78.6 | Y38: 103.1 | Z38: 80.9 | AA38: 83.6 | AB38: 36.2 | AC38: 9.4 | AD38: 6.8 | AE38: 20.9 | AF38: 8.2 | AG38: 20.4 | AH38: 20.4 | AI38: 20 | AJ38: 7.1 | AK38: 79.6 | AL38: 3.5 | AM38: 1.9 | AN38: 3.6 | AO38: 18.4 | AQ38: 246.4 | AR38: 198.8 | AS38: 0.1 | AT38: 3.5 | AU38: 9.8 | AV38: 13.8 | AW38: 5.5 | AX38: 10 | AY38: 114.5 | AZ38: 113.9 | BA38: 114.3 | BB38: 91.8 | BC38: 0.6 | BD38: 17.2 | BE38: 14.7 | BF38: 51.3 | BG38: 17.1 | BH38: 2 | BI38: 1.1 | BK38: 1.8 | BL38: 9.4 | BM38: 1.2 | BN38: 19.99 | BO38: 6.29 | BP38: 17.5 | BQ38: 20.7 | BR38: 1902.78
B39: 16:00 | C39: 15 | D39: 12 | E39: 8.4 | G39: 15.4 | H39: 3 | J39: 7 | K39: 0.5 | L39: 13.6 | N39: 13.4 | O39: 19.3 | P39: 7.8 | Q39: 3.3 | R39: 4.4 | S39: 20 | U39: 20 | V39: 18.7 | W39: 19.5 | X39: 76.9 | Y39: 102.5 | Z39: 72.7 | AA39: 78.2 | AB39: 34.1 | AC39: 6.9 | AD39: 5.2 | AE39: 20.9 | AF39: 8.2 | AG39: 20.4 | AH39: 20.4 | AI39: 20 | AJ39: 7.3 | AK39: 73.5 | AL39: 2.9 | AM39: 0.6 | AN39: 3.5 | AO39: 18.4 | AQ39: 232 | AR39: 188 | AS39: 0.2 | AT39: 3.5 | AU39: 7.3 | AV39: 12.9 | AW39: 5.4 | AX39: 9.9 | AY39: 137.9 | AZ39: 135.8 | BA39: 131.9 | BB39: 99.9 | BC39: 0.6 | BD39: 14.9 | BE39: 14.8 | BF39: 51.8 | BG39: 17.2 | BH39: 2 | BI39: 1.1 | BK39: 1.8 | BL39: 7 | BM39: 1.2 | BN39: 19.974 | BO39: 6.318 | BP39: 15.1 | BQ39: 20.7 | BR39: 1913.092
B40: 16:30 | C40: 14.8 | D40: 11.5 | E40: 7.6 | G40: 15.5 | H40: 3 | J40: 7 | K40: 0.5 | L40: 12.7 | N40: 13.6 | O40: 19.2 | P40: 7.8 | Q40: 3.2 | R40: 4.4 | S40: 20 | U40: 20 | V40: 18.7 | W40: 23 | X40: 74.3 | Y40: 92.8 | Z40: 65.3 | AA40: 70.1 | AB40: 25.8 | AC40: 7.3 | AD40: 7.4 | AE40: 20.9 | AF40: 8.2 | AG40: 20.4 | AH40: 20.4 | AI40: 20 | AJ40: 7.5 | AK40: 50.8 | AL40: 3.3 | AM40: 1.3 | AN40: 3.6 | AO40: 18.5 | AQ40: 189.3 | AR40: 150.2 | AS40: 0.1 | AT40: 3.5 | AU40: 4.6 | AV40: 10.2 | AW40: 5.4 | AX40: 9.9 | AY40: 144.1 | AZ40: 60.6 | BA40: 130.9 | BB40: 55.2 | BC40: 0.6 | BD40: 12 | BE40: 14.7 | BF40: 51.8 | BG40: 17.1 | BH40: 2 | BI40: 1.1 | BK40: 1.8 | BL40: 4.5 | BM40: 1.2 | BN40: 20.07 | BO40: 6.33 | BP40: 8.9 | BQ40: 20.7 | BR40: 1647.2
B41: 17:00 | C41: 15 | D41: 11.5 | E41: 6.7 | G41: 15.5 | H41: 3 | J41: 8.4 | K41: 0.3 | L41: 13.1 | N41: 13.4 | O41: 19 | P41: 7.8 | Q41: 3.3 | R41: 4.3 | S41: 20 | U41: 20 | V41: 18.7 | W41: 24.9 | X41: 67.1 | Y41: 84.3 | Z41: 53.7 | AA41: 64.4 | AB41: 12.1 | AC41: 9.1 | AD41: 4.6 | AE41: 20.9 | AF41: 8.2 | AG41: 20.4 | AH41: 20.4 | AI41: 20 | AJ41: 7.4 | AK41: 23.1 | AL41: 4.6 | AM41: 1.6 | AN41: 3.6 | AO41: 18.5 | AQ41: 101 | AR41: 75.3 | AS41: 0.1 | AT41: 3.5 | AU41: 2.1 | AV41: 4.1 | AW41: 5.5 | AX41: 9.9 | AY41: 142.5 | AZ41: 47.3 | BA41: 131.8 | BB41: 40.6 | BC41: 0.6 | BD41: 4.7 | BE41: 14.5 | BF41: 51.3 | BG41: 17.2 | BH41: 2 | BI41: 1.1 | BK41: 1.8 | BL41: 2.1 | BM41: 1.2 | BN41: 20.014 | BO41: 6.315 | BP41: 2.9 | BQ41: 20.8 | BR41: 1359.129
B42: 17:30 | C42: 15 | D42: 11.8 | E42: 7.6 | G42: 15.5 | H42: 3 | J42: 9.5 | K42: 0.1 | L42: 13.1 | N42: 13.6 | O42: 18.4 | P42: 7.9 | Q42: 3.3 | R42: 4.3 | S42: 20 | U42: 20 | V42: 18.7 | W42: 25.2 | X42: 68.8 | Y42: 81.4 | Z42: 50.9 | AA42: 64 | AB42: 2.7 | AC42: 6 | AD42: 5 | AE42: 20.9 | AF42: 8.2 | AG42: 20.4 | AH42: 20.4 | AI42: 20 | AJ42: 7.1 | AK42: 4 | AL42: 4.8 | AM42: 2.4 | AN42: 3.5 | AO42: 18.4 | AQ42: 18.5 | AR42: 7.1 | AS42: 0.1 | AT42: 3.5 | AU42: 0.5 | AV42: 0.3 | AW42: 5.5 | AX42: 9.9 | AY42: 151.7 | AZ42: 8.1 | BA42: 131.3 | BB42: 9.5 | BC42: 0.6 | BD42: 0.2 | BE42: 14.2 | BF42: 50.4 | BG42: 17.5 | BH42: 2 | BI42: 1.1 | BK42: 1.8 | BL42: 0.5 | BM42: 1.2 | BN42: 20.042 | BO42: 6.323 | BQ42: 20.7 | BR42: 1098.465
B43: 18:00 | C43: 15 | D43: 13 | E43: 8.3 | G43: 15.5 | H43: 3 | J43: 9 | K43: 0.1 | L43: 13.4 | N43: 13.4 | O43: 18 | P43: 8 | Q43: 3.3 | R43: 4.4 | S43: 20 | U43: 20 | V43: 18.7 | W43: 25 | X43: 70 | Y43: 68.4 | Z43: 53.1 | AA43: 67.3 | AC43: 6.3 | AD43: 4.9 | AE43: 20.9 | AF43: 8.2 | AG43: 20.4 | AH43: 20.4 | AI43: 20 | AJ43: 7.1 | AL43: 4.4 | AM43: 3.1 | AN43: 3.5 | AO43: 18.4 | AQ43: 0.3 | AT43: 3.5 | AW43: 5.5 | AX43: 9.9 | AY43: 124.1 | BA43: 131.5 | BC43: 0.6 | BE43: 13.9 | BF43: 49.2 | BG43: 17.8 | BH43: 2.4 | BI43: 1.1 | BJ43: 0.4 | BK43: 1.8 | BM43: 1.2 | BN43: 19.982 | BO43: 6.341 | BQ43: 20.7 | BR43: 1014.723
B44: 18:30 | C44: 15 | D44: 13 | E44: 8.4 | G44: 15.6 | H44: 3 | J44: 8.6 | L44: 13.4 | N44: 13.4 | O44: 18 | P44: 8 | Q44: 3.3 | R44: 4.4 | S44: 20 | U44: 20 | V44: 18.7 | W44: 24.7 | X44: 64.1 | Y44: 64.2 | Z44: 49.9 | AA44: 69.5 | AC44: 7.3 | AD44: 3.1 | AE44: 21 | AF44: 8.2 | AG44: 20.4 | AH44: 20.4 | AI44: 20 | AJ44: 7.5 | AL44: 5 | AM44: 2.7 | AN44: 3.5 | AO44: 18.6 | AT44: 3.5 | AW44: 5.4 | AX44: 10 | AY44: 116.5 | BA44: 127.9 | BC44: 0.6 | BE44: 13.6 | BF44: 47.7 | BG44: 18.3 | BH44: 2.8 | BI44: 1.1 | BJ44: 1 | BK44: 2.4 | BM44: 1.2 | BN44: 20.05 | BO44: 6.332 | BQ44: 20.7 | BR44: 991.982
B45: 19:00 | C45: 15 | D45: 13 | E45: 8.3 | G45: 15.5 | H45: 3 | J45: 9 | L45: 13.4 | N45: 13.5 | O45: 18 | P45: 8.1 | Q45: 3 | R45: 4.4 | S45: 20 | U45: 20 | V45: 18.7 | W45: 20.6 | X45: 52.3 | Y45: 67 | Z45: 53.7 | AA45: 71.5 | AC45: 6.4 | AD45: 3.3 | AE45: 20.9 | AF45: 8 | AG45: 20.4 | AH45: 20.4 | AI45: 20 | AJ45: 7.5 | AL45: 5.7 | AM45: 1.9 | AN45: 3.6 | AO45: 18.6 | AT45: 3.5 | AW45: 5.4 | AX45: 9.9 | AY45: 122.7 | BA45: 127.6 | BC45: 0.6 | BE45: 13.5 | BF45: 45.7 | BG45: 18.5 | BH45: 2.8 | BI45: 1.1 | BJ45: 1.1 | BK45: 2.4 | BM45: 1.1 | BN45: 20.054 | BO45: 6.352 | BQ45: 20.7 | BR45: 987.706
B46: 19:30 | C46: 14.8 | D46: 13 | E46: 9.6 | G46: 17.1 | H46: 3 | J46: 9.3 | L46: 13.4 | N46: 14 | O46: 18.1 | P46: 8.3 | Q46: 3.1 | R46: 4.3 | S46: 20 | U46: 20 | V46: 18.7 | W46: 20.1 | X46: 44.6 | Y46: 60.1 | Z46: 59.9 | AA46: 75.3 | AC46: 7.6 | AD46: 3.3 | AE46: 20.9 | AF46: 7.6 | AG46: 20.4 | AH46: 20.4 | AI46: 20 | AJ46: 7.4 | AL46: 4 | AM46: 1.5 | AN46: 3.6 | AO46: 18.6 | AT46: 3.5 | AW46: 5.5 | AX46: 9.9 | AY46: 109.6 | BA46: 117.9 | BC46: 0.6 | BE46: 13.2 | BF46: 44 | BG46: 18.8 | BH46: 2.8 | BI46: 1.1 | BJ46: 1.1 | BK46: 2.4 | BM46: 1.1 | BN46: 20.045 | BO46: 6.342 | BQ46: 20.8 | BR46: 960.687
B47: 20:00 | C47: 14.8 | D47: 13 | E47: 8.2 | G47: 20.3 | H47: 3 | J47: 9.3 | L47: 13.3 | N47: 14 | O47: 18.1 | P47: 8.6 | Q47: 3.1 | R47: 4.3 | S47: 20.1 | U47: 20 | V47: 18.7 | W47: 17 | X47: 40.9 | Y47: 50.5 | Z47: 48.4 | AA47: 67 | AC47: 6 | AD47: 4 | AE47: 20.9 | AF47: 7.5 | AG47: 20.4 | AH47: 20.4 | AI47: 20 | AJ47: 7.4 | AL47: 2.8 | AM47: 1.4 | AN47: 3.5 | AO47: 18.6 | AT47: 3.5 | AW47: 5.5 | AX47: 9.9 | AY47: 73.7 | BA47: 89.4 | BC47: 0.6 | BE47: 12.8 | BF47: 42.4 | BG47: 19.3 | BH47: 2.8 | BI47: 1.1 | BJ47: 1.1 | BK47: 2.4 | BM47: 1.1 | BN47: 20.115 | BO47: 6.35 | BQ47: 20.9 | BR47: 858.465
B48: 20:30 | C48: 15 | D48: 13 | E48: 7.7 | G48: 20.2 | H48: 3 | J48: 9.2 | L48: 13.3 | N48: 13.9 | O48: 18.1 | P48: 8.7 | Q48: 3.2 | R48: 4.2 | S48: 20 | U48: 20 | V48: 18.7 | W48: 13.7 | X48: 30.7 | Y48: 51.8 | Z48: 53.9 | AA48: 69.7 | AC48: 6 | AD48: 3.6 | AE48: 20.9 | AF48: 7.5 | AG48: 20.4 | AH48: 20.4 | AI48: 20 | AJ48: 7.4 | AL48: 3 | AM48: 1.3 | AN48: 3.5 | AO48: 18.6 | AT48: 3.5 | AW48: 5.5 | AX48: 9.9 | AY48: 51.7 | BA48: 78.4 | BC48: 0.6 | BE48: 12.5 | BF48: 40.8 | BG48: 19.8 | BH48: 2.8 | BI48: 1.1 | BJ48: 1.1 | BK48: 2.4 | BM48: 1.1 | BN48: 20.05 | BO48: 6.346 | BQ48: 20.8 | BR48: 818.996
B49: 21:00 | C49: 15 | D49: 13.1 | E49: 7.9 | G49: 20.2 | H49: 3 | J49: 9.4 | L49: 13.4 | N49: 14 | O49: 18.1 | P49: 8.7 | Q49: 3.1 | R49: 4.6 | S49: 20 | U49: 20 | V49: 18.7 | W49: 15.1 | X49: 24.5 | Y49: 53.3 | Z49: 52.7 | AA49: 65.3 | AC49: 6.4 | AD49: 4.6 | AE49: 20.9 | AF49: 7.5 | AG49: 20.4 | AH49: 20.4 | AI49: 20 | AJ49: 7.4 | AL49: 0.2 | AN49: 3.5 | AO49: 18.6 | AT49: 3.5 | AW49: 5.4 | AX49: 9.9 | AY49: 33.2 | BA49: 55 | BC49: 0.6 | BE49: 12.3 | BF49: 39.2 | BG49: 19.9 | BH49: 2.8 | BI49: 1.1 | BJ49: 1.1 | BK49: 2.4 | BM49: 1.1 | BN49: 20.023 | BO49: 6.375 | BQ49: 20.7 | BR49: 764.598
B50: 21:30 | C50: 15.9 | D50: 13 | E50: 8.6 | G50: 20.2 | H50: 3 | J50: 8.3 | L50: 11.9 | N50: 14 | O50: 18.8 | P50: 8.8 | Q50: 2.9 | R50: 4.4 | S50: 20 | U50: 20 | V50: 18.7 | W50: 14.3 | X50: 26.8 | Y50: 50.5 | Z50: 62.8 | AA50: 86 | AC50: 8.2 | AD50: 5 | AE50: 20.4 | AF50: 7.5 | AG50: 20.4 | AH50: 20.4 | AI50: 20 | AJ50: 7.4 | AL50: 0.3 | AN50: 3.5 | AO50: 18.6 | AT50: 3.5 | AW50: 5.4 | AX50: 9.9 | AY50: 26.8 | BA50: 34.3 | BC50: 0.6 | BE50: 12.2 | BF50: 37.8 | BG50: 20 | BH50: 2.8 | BI50: 1.1 | BJ50: 1.1 | BK50: 2.4 | BM50: 1.1 | BN50: 20.032 | BO50: 6.326 | BQ50: 20.7 | BR50: 766.658
B51: 22:00 | C51: 15.5 | D51: 13.1 | E51: 9.7 | G51: 20.2 | H51: 2.9 | J51: 8.4 | L51: 11.7 | N51: 13.5 | O51: 18.9 | P51: 8.8 | Q51: 2.9 | R51: 4.4 | S51: 20 | U51: 20 | V51: 18.7 | W51: 14.4 | X51: 30.2 | Y51: 46 | Z51: 72.5 | AA51: 90.3 | AC51: 6 | AD51: 4.7 | AE51: 21 | AF51: 7.2 | AG51: 20.4 | AH51: 20.4 | AI51: 20 | AJ51: 7.4 | AL51: 0.4 | AN51: 3.5 | AO51: 18.6 | AT51: 3.5 | AW51: 5.5 | AX51: 9.9 | AY51: 29.6 | BA51: 32.9 | BC51: 0.6 | BE51: 12.1 | BF51: 36.6 | BG51: 20 | BH51: 2.8 | BI51: 1.1 | BJ51: 1.1 | BK51: 2.4 | BM51: 1.1 | BN51: 20.05 | BO51: 6.348 | BQ51: 20.7 | BR51: 777.998
B52: 22:30 | C52: 15 | D52: 13.1 | E52: 8.1 | G52: 20.2 | H52: 2.9 | J52: 9.3 | L52: 11.7 | N52: 13.6 | O52: 18.9 | P52: 8.8 | Q52: 3 | R52: 4.3 | S52: 20 | U52: 20 | V52: 18.7 | W52: 13.5 | X52: 30.8 | Y52: 46.4 | Z52: 69.6 | AA52: 88.2 | AC52: 7.2 | AD52: 4.6 | AE52: 21 | AF52: 7.2 | AG52: 20.4 | AH52: 20.4 | AI52: 20 | AJ52: 7.4 | AN52: 3.5 | AO52: 18.6 | AT52: 3.5 | AW52: 5.4 | AX52: 9.9 | AY52: 17.4 | BA52: 25.8 | BC52: 0.6 | BE52: 11.7 | BF52: 34.6 | BG52: 20 | BH52: 2.8 | BI52: 1.1 | BJ52: 1.1 | BK52: 2.4 | BM52: 1 | BN52: 20.015 | BO52: 6.321 | BQ52: 20.8 | BR52: 750.836
B53: 23:00 | C53: 14 | D53: 13.1 | E53: 8.5 | G53: 20.2 | H53: 2.9 | J53: 9.2 | L53: 11.7 | N53: 13.6 | O53: 18.9 | P53: 8.8 | Q53: 2.9 | R53: 4.2 | S53: 20 | U53: 20 | V53: 18.7 | W53: 14.6 | X53: 34 | Y53: 50 | Z53: 64.6 | AA53: 86.9 | AC53: 8.7 | AD53: 3.6 | AE53: 21 | AF53: 7.2 | AG53: 20.4 | AH53: 20.4 | AI53: 20 | AJ53: 7.4 | AN53: 3.5 | AO53: 18.6 | AT53: 3.5 | AW53: 5.3 | AX53: 10 | AY53: 16.1 | BA53: 24.7 | BC53: 0.6 | BE53: 11.1 | BF53: 31.9 | BG53: 20.1 | BH53: 2.8 | BI53: 1.1 | BJ53: 1.1 | BK53: 2.4 | BM53: 1.1 | BN53: 19.965 | BO53: 6.319 | BQ53: 20.8 | BR53: 746.484
B54: 23:30 | C54: 15.3 | D54: 13.1 | E54: 8.7 | G54: 20.2 | H54: 2.8 | J54: 8.8 | L54: 11.8 | N54: 13.5 | O54: 18.9 | P54: 8.8 | Q54: 2.9 | R54: 4.2 | S54: 20 | U54: 20 | V54: 18.7 | W54: 13.7 | X54: 35.4 | Y54: 50.4 | Z54: 63.1 | AA54: 81.1 | AC54: 6.8 | AD54: 5.3 | AE54: 21 | AF54: 7.2 | AG54: 20.4 | AH54: 20.4 | AI54: 20 | AJ54: 7.4 | AN54: 3.6 | AO54: 18.6 | AT54: 3.5 | AW54: 5.4 | AX54: 9.9 | AY54: 20.5 | BA54: 26.6 | BC54: 0.6 | BE54: 10.6 | BF54: 29.1 | BG54: 20 | BH54: 2.8 | BI54: 1.1 | BJ54: 1.1 | BK54: 2.4 | BM54: 1.1 | BN54: 20.1 | BO54: 6.337 | BQ54: 20.8 | BR54: 744.037
B55: 0:00 | C55: 14.8 | D55: 13.1 | E55: 8.1 | G55: 17.2 | H55: 2.8 | J55: 8.9 | L55: 11.8 | N55: 13.4 | O55: 18.9 | P55: 8.8 | Q55: 2.9 | R55: 4.2 | S55: 20 | U55: 20 | V55: 18.7 | W55: 13 | X55: 34.8 | Y55: 50.2 | Z55: 65.8 | AA55: 73.4 | AC55: 5.4 | AD55: 3.8 | AE55: 21 | AF55: 7.2 | AG55: 20.4 | AH55: 20.4 | AI55: 20 | AJ55: 7.3 | AN55: 3.5 | AO55: 18.6 | AT55: 3.5 | AW55: 5.3 | AX55: 9.9 | AY55: 23 | BA55: 31.1 | BC55: 0.6 | BE55: 10 | BF55: 26.2 | BG55: 20 | BH55: 2.8 | BI55: 1.1 | BJ55: 1.1 | BK55: 2.4 | BM55: 1.1 | BN55: 20.012 | BO55: 6.315 | BQ55: 20.7 | BR55: 733.527
B56: EJEC MWh | C56: 367.05 | D56: 351.5 | E56: 200 | F56: 0 | G56: 385.55 | H56: 62.7 | I56: 0 | J56: 213.3 | K56: 8.2 | L56: 285.15 | M56: 0 | N56: 336.75 | O56: 459.3 | P56: 190.25 | Q56: 79.25 | R56: 105.15 | S56: 480.2 | T56: 0 | U56: 463.55 | V56: 449.9 | W56: 372.45 | X56: 941.15 | Y56: 1277.1 | Z56: 1395.7 | AA56: 1519.85 | AB56: 388.4 | AC56: 161.95 | AD56: 91.65 | AE56: 490.05 | AF56: 163.8 | AG56: 475.4 | AH56: 477.95 | AI56: 470.9 | AJ56: 172.6 | AK56: 814.75 | AL56: 35.25 | AM56: 20.65 | AN56: 85.2 | AO56: 445.8 | AP56: 0 | AQ56: 2660.1 | AR56: 1348.95 | AS56: 2.55 | AT56: 84 | AU56: 142.2 | AV56: 143.05 | AW56: 130.6 | AX56: 237.8 | AY56: 1091.85 | AZ56: 1535.55 | BA56: 1134.15 | BB56: 1145.5 | BC56: 14.4 | BD56: 170.7 | BE56: 302.75 | BF56: 915.7 | BG56: 430.55 | BH56: 66.05 | BI56: 26.4 | BJ56: 14.45 | BK56: 55.75 | BL56: 135.95 | BM56: 26.45 | BN56: 480.774 | BO56: 152.099 | BP56: 147 | BQ56: 497.9 | BR56: 27331.623
L70: TERMOELÉCTRICA | M70: 1294.5 | N70: 4.736272 | O70: #FFA975
L71: HIDROELÉCTRICA | M71: 8134.023 | N71: 29.760483 | O71: #98D2FF
L72: SOLAR | M72: 8642.9 | N72: 31.622345 | O72: #FFD272
L73: EÓLICA | M73: 9260.2 | N73: 33.880901 | O73: #B9ACFF

Sheet COGENERACIÓN
B3: lunes, 27 de Octubre del 2025
B5: CENTRALES DE COGENERACIÓN DEL SEIN
B6: HORA | C6: AGRO INDUSTRIAL PARAMONGA S.A. | D6: AGROAURORA S.A.C. | E6: AGROINDUSTRIAS SAN JACINTO S.A.A. | F6: AGROLMOS SOCIEDAD ANONIMA - AGROLMOS S.A. | G6: BIOENERGIA DEL CHIRA S.A. | H6: GM OPERACIONES S.A.C. | I6: TOTAL COGENERACION
C7: C.T. PARAMONGA | D7: C.T. MAPLE | E7: C.T SAN JACINTO | F7: C.T. AGROLMOS | G7: C.T. CAÑA BRAVA | H7: C.T. REFINERÍA TALARA | I7: MW
B8: 0:30 | C8: 15.7 | D8: 17.5 | E8: 9.1 | G8: 8.8 | I8: 51.1
B9: 1:00 | C9: 15.1 | D9: 17.5 | E9: 8.2 | G9: 8.2 | I9: 49
B10: 1:30 | C10: 15.8 | D10: 17.5 | E10: 8.9 | G10: 8.1 | I10: 50.3
B11: 2:00 | C11: 15.8 | D11: 17.5 | E11: 6.5 | G11: 9.2 | I11: 49
B12: 2:30 | C12: 15.8 | D12: 17.5 | E12: 8.2 | G12: 9.2 | I12: 50.7
B13: 3:00 | C13: 15 | D13: 17.5 | E13: 8.9 | G13: 9.5 | I13: 50.9
B14: 3:30 | C14: 15 | D14: 17.5 | E14: 8.6 | G14: 8.9 | I14: 50
B15: 4:00 | C15: 15 | D15: 17.5 | E15: 8.2 | G15: 8.8 | I15: 49.5
B16: 4:30 | C16: 15.9 | D16: 17.5 | E16: 9 | G16: 9.2 | I16: 51.6
B17: 5:00 | C17: 15.5 | D17: 17.5 | E17: 9.1 | G17: 8.9 | I17: 51
B18: 5:30 | C18: 16 | D18: 17.5 | E18: 7.3 | G18: 9.3 | I18: 50.1
B19: 6:00 | C19: 15.6 | D19: 17.5 | E19: 9.3 | G19: 9.3 | I19: 51.7
... B35: 14:00 | C35: 14.9 | D35: 12 | E35: 7.4 | G35: 9.5 | I35: 43.8
B36: 14:30 | C36: 15 | D36: 12 | E36: 7.9 | G36: 7.8 | H36: 10.02 | I36: 52.72
B37: 15:00 | C37: 15 | D37: 12 | E37: 8 | G37: 9.6 | H37: 16.2 | I37: 60.8
B38: 15:30 | C38: 14.5 | D38: 12 | E38: 7.2 | G38: 5.9 | H38: 26.04 | I38: 65.64
B39: 16:00 | C39: 15 | D39: 12 | E39: 8.4 | G39: 7 | H39: 34.17 | I39: 76.57
B40: 16:30 | C40: 14.8 | D40: 11.5 | E40: 7.6 | G40: 7 | H40: 34.64 | I40: 75.54
B41: 17:00 | C41: 15 | D41: 11.5 | E41: 6.7 | G41: 8.4 | H41: 34.37 | I41: 75.97
B42: 17:30 | C42: 15 | D42: 11.8 | E42: 7.6 | G42: 9.5 | H42: 34.32 | I42: 78.22
B43: 18:00 | C43: 15 | D43: 13 | E43: 8.3 | G43: 9 | H43: 34.18 | I43: 79.48
B44: 18:30 | C44: 15 | D44: 13 | E44: 8.4 | G44: 8.6 | H44: 34.1 | I44: 79.1
B45: 19:00 | C45: 15 | D45: 13 | E45: 8.3 | G45: 9 | H45: 34.42 | I45: 79.72
B46: 19:30 | C46: 14.8 | D46: 13 | E46: 9.6 | G46: 9.3 | H46: 34.4 | I46: 81.1
B47: 20:00 | C47: 14.8 | D47: 13 | E47: 8.2 | G47: 9.3 | H47: 34.32 | I47: 79.62
... B55: 0:00 | C55: 14.8 | D55: 13.1 | E55: 8.1 | G55: 8.9 | H55: 34.4 | I55: 79.3
B56: EJEC MWh | C56: 367.05 | D56: 351.5 | E56: 200 | F56: 0 | G56: 213.3 | H56: 317.595 | I56: 1449.445

Sheet EVO_PRO_ENE
B3: miércoles, 1 de Octubre del 2025 - lunes, 27 de Octubre del 2025
B5: EVOLUCIÓN DE LA PRODUCCIÓN DE LA ENERGÍA DIARIA DE LOS INTEGRANTES DEL COES (MWh)
B6: EMPRESA | C6: CENTRAL | D6: UNIDAD | E6: TIPO | F6: Octubre
F7: 1 | G7: 2 | H7: 3 | I7: 4 | J7: 5 | K7: 6 | L7: 7 | M7: 8 | N7: 9 | O7: 10 | P7: 11 | Q7: 12 | R7: 13 | S7: 14 | T7: 15 | U7: 16 | V7: 17 | W7: 18 | X7: 19 | Y7: 20 | Z7: 21 | AA7: 22 | AB7: 23 | AC7: 24 | AD7: 25 | AE7: 26 | AF7: 27 | AG7: TOTAL
B8: AGRO INDUSTRIAL PARAMONGA S.A. | C8: C.T. PARAMONGA | D8: TV-01 | E8: TERMOELÉCTRICA | H8: 170.35 | I8: 353.4 | J8: 378.6 | K8: 316.9 | L8: 381.15 | M8: 377 | N8: 377.5 | O8: 351.85 | P8: 356.25 | Q8: 366.45 | R8: 360 | S8: 359.5 | T8: 359.95 | U8: 360.45 | V8: 268.65 | W8: 309.85 | X8: 256.3 | Y8: 352.65 | Z8: 345.2 | AA8: 352.3 | AB8: 362.65 | AC8: 339.7 | AD8: 368.45 | AE8: 361.65 | AF8: 367.05 | AG8: 8553.8
B9: AGROAURORA S.A.C. | C9: C.T. MAPLE ETANOL | D9: TV | E9: TERMOELÉCTRICA | F9: 450.6 | G9: 441.4 | H9: 362.5 | I9: 292.65 | J9: 440.5 | K9: 431.95 | L9: 406.45 | M9: 448.05 | N9: 445.6 | O9: 441.35 | P9: 441.15 | Q9: 455.8 | R9: 454.8 | S9: 455.45 | T9: 454.55 | U9: 329.7 | V9: 338.55 | W9: 404.3 | X9: 313.15 | Y9: 395.65 | AA9: 316.85 | AB9: 440.6 | AC9: 392.1 | AD9: 409.5 | AE9: 441.15 | AF9: 351.5 | AG9: 10555.85
B10: AGROINDUSTRIAS SAN JACINTO S.A.A. | C10: C.T. SAN JACINTO | D10: CENTRAL | E10: TERMOELÉCTRICA | F10: 65 | G10: 182.75 | H10: 189.45 | I10: 192.6 | J10: 192.3 | K10: 195.4 | L10: 190.05 | M10: 191.07 | N10: 188.259 | O10: 188.35 | P10: 163.25 | Q10: 178.45 | R10: 181.2 | S10: 187.6 | T10: 187.63 | U10: 177.1 | V10: 178.9 | W10: 190.9 | X10: 190.1 | Y10: 189.505 | Z10: 176.3 | AA10: 190.18 | AB10: 185.9 | AC10: 190.95 | AD10: 194.9 | AE10: 201.15 | AF10: 200 | AG10: 4939.244
B11: AGROLMOS SOCIEDAD ANONIMA - AGROLMOS S.A. | C11: C.T. AGROLMOS | D11: CENTRAL | E11: TERMOELÉCTRICA | F11: 265.4 | G11: 262.9 | H11: 263.3 | I11: 263.25 | J11: 256.2 | K11: 217.7 | L11: 264.45 | M11: 260.7 | N11: 258.4329 | O11: 259.25 | P11: 247.11025 | Q11: 259.6 | R11: 253.75 | S11: 68.6 | T11: 207.03 | U11: 260.13855 | V11: 264.75 | W11: 263.57 | X11: 260.4 | Y11: 263.245 | Z11: 250.5 | AA11: 264.25 | AB11: 261.945 | AC11: 261.25 | AD11: 233.4 | AE11: 10 | AG11: 6201.1217
B12: ANDEAN POWER S.A.C. | C12: C.H.CARHUAC | D12: CENTRAL | E12: HIDROELÉCTRICA | F12: 367.55 | G12: 339.7 | H12: 358.95 | I12: 369.8 | J12: 342.05 | K12: 283.65 | L12: 355.65 | M12: 334 | N12: 317.15 | O12: 367.75 | P12: 363.55 | Q12: 369.95 | R12: 370.5 | S12: 389.45 | T12: 393.15 | U12: 412.55 | V12: 450.25 | W12: 456.8 | X12: 408.85 | Y12: 453.9 | Z12: 424.65 | AA12: 368.15 | AB12: 393.75 | AC12: 371.65 | AD12: 365.05 | AE12: 387.4 | AF12: 385.55 | AG12: 10201.4
B13: ASOCIACIÓN SANTA LUCIA DE CHACAS | C13: C.H. HUALLIN | D13: CENTRAL | E13: HIDROELÉCTRICA | F13: 33.45 | G13: 27.85 | H13: 35 | I13: 44.1 | J13: 33.1 | K13: 29.6 | L13: 31.75 | M13: 29.05 | N13: 27.9 | O13: 38.9 | P13: 42.95 | Q13: 23.2 | R13: 40.25 | S13: 37.5 | T13: 35.45 | U13: 33.45 | V13: 55.35 | W13: 63.55 | X13: 55.05 | Y13: 58.86 | Z13: 60.4 | AA13: 48 | AB13: 60 | AC13: 59.55 | AD13: 51.1 | AE13: 50.05 | AF13: 62.7 | AG13: 1168.11
B14: ATRIA ENERGIA S.A.C. | C14: C.H. PURMACANA | D14: CENTRAL | E14: HIDROELÉCTRICA | F14: 7.2 | G14: 8.9 | H14: 2.1 | L14: 4.55 | M14: 9.6 | N14: 9.6 | O14: 2.75 | S14: 6.55 | T14: 9.6 | U14: 9.5 | V14: 2.75 | Z14: 6.75 | AA14: 9.6 | AB14: 9.6 | AC14: 2.75 | AG14: 101.8
B15: BIOENERGIA DEL CHIRA S.A. | C15: C.T. CAÑA BRAVA | D15: CENTRAL | E15: TERMOELÉCTRICA | F15: 94.65 | G15: 162.7 | H15: 223.25 | I15: 234.55 | J15: 223.85 | K15: 164.3 | L15: 217 | M15: 224.35 | N15: 224.45 | O15: 223.65 | P15: 225.85 | Q15: 222.95 | R15: 213.05 | S15: 221.7 | T15: 199.4 | U15: 222.25 | V15: 222.2 | W15: 223.6 | X15: 222.5 | Y15: 211.65 | Z15: 217.8 | AA15: 230.2 | AB15: 216.75 | AC15: 178.65 | AD15: 221.15 | AE15: 221.45 | AF15: 213.3 | AG15: 5677.2
B16: CELEPSA | C16: C.H. EL PLATANAL | D16: CENTRAL | E16: HIDROELÉCTRICA | F16: 2674.85 | G16: 2542.3 | H16: 2536.1 | I16: 2631.65 | J16: 3175.4 | K16: 3261.8 | L16: 3113.4 | M16: 2920.2 | N16: 2747.55 | O16: 3272.3 | P16: 3714.2 | Q16: 3457 | R16: 3345.7 | S16: 3113.5 | T16: 3094.6 | U16: 2890 | V16: 3289.6 | W16: 3519.55 | X16: 3544.5 | Y16: 4032.55 | Z16: 3972.4 | AA16: 3683.15 | AB16: 3333.3 | AC16: 3798.1 | AD16: 3457.25 | AE16: 3230.6 | AF16: 3315.8 | AG16: 87667.35
B17: CELEPSA RENOVABLES S.R.L. | C17: C.H. MARAÑON | D17: CENTRAL | E17: HIDROELÉCTRICA | F17: 300.85 | G17: 290.1 | H17: 293.45 | I17: 292.8 | J17: 112.9 | K17: 292.8 | L17: 292.75 | M17: 286.1 | N17: 292.8 | O17: 292.8 | P17: 292.8 | Q17: 292.8 | R17: 292.8 | S17: 319.45 | T17: 372.05 | U17: 147.55 | V17: 290.4 | W17: 290.4 | X17: 344.95 | Y17: 446.4 | Z17: 446.1 | AA17: 443.2 | AB17: 445.30416 | AC17: 447.3 | AD17: 451.2 | AE17: 451.2 | AF17: 451.2 | AG17: 8972.4542
B18: CENTRALES SANTA ROSA S.A.C. | C18: C.H. SANTA ROSA I | D18: CENTRAL | E18: HIDROELÉCTRICA | AG18: 0
B19: CENTRALES SANTA ROSA S.A.C. | C19: C.H. SANTA ROSA II | D19: CENTRAL | E19: HIDROELÉCTRICA | AG19: 0
B20: CHINANGO S.A.C. | C20: C.H. CHIMAY | D20: CENTRAL | E20: HIDROELÉCTRICA | F20: 2784.45 | G20: 3406 | H20: 3550.95 | I20: 3331.35 | J20: 2767.95 | K20: 2249.75 | L20: 2232.975 | M20: 2605.55 | N20: 2207.1 | O20: 3315.95 | P20: 3202.35 | Q20: 3425.15 | R20: 2994.25 | S20: 3124.3 | T20: 2816.7 | U20: 3615.9 | V20: 3619.85 | W20: 3631.8 | X20: 3407.25 | Y20: 3634.9 | Z20: 3584.45 | AA20: 3551.045 | AB20: 3527.35 | AC20: 3300.85 | AD20: 3111.7 | AE20: 3234.7 | AF20: 3330.55 | AG20: 85565.12
B21: CHINANGO S.A.C. | C21: C.H. YANANGO | D21: CENTRAL | E21: HIDROELÉCTRICA | F21: 540.45 | G21: 351.05 | H21: 750 | I21: 684.9 | J21: 580.5 | K21: 433.2 | L21: 520.13 | M21: 575.35 | N21: 532.8 | O21: 737.35 | P21: 721.45 | Q21: 707.95 | R21: 658.4 | S21: 636.5 | T21: 458.7 | U21: 752.8 | V21: 710.65 | W21: 660.95 | X21: 742.5 | Y21: 733.65 | Z21: 724.25 | AA21: 689.03 | AB21: 896.15 | AC21: 790.3 | AD21: 703.65 | AE21: 712.8 | AF21: 686.7 | AG21: 17692.16
B22: COLCA SOLAR S.A.C. | C22: C.S. YARUCAYA | D22: CENTRAL | E22: SOLAR | F22: 7.5 | G22: 8.65 | H22: 6 | I22: 8.45 | J22: 7.85 | K22: 6.4 | L22: 9.35 | M22: 8.25 | N22: 7.35 | O22: 8.4 | P22: 8.4 | Q22: 9.5 | R22: 8.5 | S22: 9.2 | T22: 8.95 | U22: 9.1 | V22: 9.4 | W22: 8 | X22: 9.2 | Y22: 8.15 | Z22: 7.4 | AA22: 7.5 | AB22: 8.45 | AC22: 7.9 | AD22: 7.45 | AE22: 8.25 | AF22: 8.2 | AG22: 221.75
B23: EGASA | C23: C.H. CHARCANI III | D23: CENTRAL | E23: HIDROELÉCTRICA | F23: 166.35 | G23: 166.25 | H23: 165.95 | I23: 164.85 | J23: 163.65 | K23: 164.5 | L23: 163.55 | M23: 162.75 | N23: 163.2 | O23: 162.85 | P23: 162.1 | Q23: 160.7 | R23: 163.65 | S23: 164.65 | T23: 164.8 | U23: 164.3 | V23: 163.65 | W23: 164.3 | X23: 163.15 | Y23: 165.35 | Z23: 165.5 | AA23: 165.3 | AB23: 165.9 | AC23: 165.4 | AD23: 164.7 | AE23: 165.9 | AF23: 165.85 | AG23: 4439.1
B24: EGASA | C24: C.H. CHARCANI IV | D24: CENTRAL | E24: HIDROELÉCTRICA | F24: 297.2 | G24: 297 | H24: 288 | I24: 283.1 | J24: 301.6 | K24: 293.75 | L24: 290.85 | M24: 298.05 | N24: 298.9 | O24: 283 | P24: 281.3 | Q24: 277.6 | R24: 287.85 | S24: 290.3 | T24: 296.05 | U24: 297.45 | V24: 279 | W24: 290.3 | X24: 290.6 | Y24: 298.65 | Z24: 291.05 | AA24: 298.25 | AB24: 297.3 | AC24: 283.75 | AD24: 293.45 | AE24: 293.6 | AF24: 287.95 | AG24: 7865.9
B25: EGASA | C25: C.H. CHARCANI V | D25: CENTRAL | E25: HIDROELÉCTRICA | F25: 1889.7 | G25: 1892.05 | H25: 1906.2 | I25: 1888.55 | J25: 1905.7 | K25: 1892.1 | L25: 1891.8 | M25: 1893 | N25: 1899.65 | O25: 1897.45 | P25: 1885.9 | Q25: 1908.35 | R25: 1885.5 | S25: 1886.4 | T25: 1903.9 | U25: 1913.8 | V25: 1902.55 | W25: 1906.3 | X25: 1890.15 | Y25: 1909.35 | Z25: 1889.25 | AA25: 1900.85 | AB25: 1902.95 | AC25: 1892.95 | AD25: 1896.55 | AE25: 1890.95 | AF25: 1898.05 | AG25: 51219.95
B26: EGASA | C26: C.H. CHARCANI VI | D26: CENTRAL | E26: HIDROELÉCTRICA | AG26: 0
B27: EGASA | C27: C.T. CHILINA DIESEL | D27: CENTRAL | E27: TERMOELÉCTRICA | AG27: 0
B28: EGASA | C28: C.T. CHILINA DIESEL | D28: TG | E28: TERMOELÉCTRICA | AG28: 0
B29: EGASA | C29: C.T. MOLLENDO DIESEL | D29: CENTRAL | E29: TERMOELÉCTRICA | AG29: 0
B30: EGEJUNIN | C30: C.H. HUASAHUASI I | D30: CENTRAL | E30: HIDROELÉCTRICA | F30: 200.95 | G30: 190.45 | H30: 229.25 | I30: 237.9 | J30: 219.9 | K30: 189 | L30: 192.2 | M30: 232 | N30: 220.95 | O30: 249.95 | P30: 328.45 | Q30: 179.45 | R30: 277.65 | S30: 257.75 | T30: 259.2 | U30: 257.35 | V30: 251.5 | W30: 236.55 | X30: 237.3 | Y30: 237.05 | Z30: 237.6 | AA30: 236.85 | AB30: 314.65 | AC30: 308.5 | AD30: 257.65 | AE30: 249.95 | AF30: 285.15 | AG30: 6575.15
B31: EGEJUNIN | C31: C.H. RUNATULLO II | D31: CENTRAL | E31: HIDROELÉCTRICA | F31: 233.8 | G31: 279 | H31: 381.25 | I31: 422.5 | J31: 384.7 | K31: 376.2 | L31: 373.6 | M31: 361.4 | N31: 364.05 | O31: 403 | P31: 405.25 | Q31: 409.85 | R31: 423.65 | S31: 419.05 | T31: 418.9 | U31: 441.85 | V31: 441.1 | W31: 419.05 | X31: 458.45 | Y31: 479.15 | Z31: 479.4 | AA31: 454.26 | AB31: 436.45 | AC31: 376.25 | AD31: 355.2 | AE31: 353.5 | AF31: 336.75 | AG31: 10687.61
B32: EGEJUNIN | C32: C.H. RUNATULLO III | D32: CENTRAL | E32: HIDROELÉCTRICA | F32: 322.25 | G32: 377.25 | H32: 475.75 | I32: 484.55 | J32: 486.9 | K32: 475.7 | L32: 475.95 | M32: 474.7 | N32: 461.4 | O32: 486.1 | P32: 487.3 | Q32: 487.4 | R32: 487.1 | S32: 482.5 | T32: 484.95 | U32: 484.9 | V32: 485 | W32: 485 | X32: 484.45 | Y32: 485.25 | Z32: 485.05 | AA32: 483.56 | AB32: 486.1 | AC32: 486.05 | AD32: 477.65 | AE32: 484.4 | AF32: 459.3 | AG32: 12736.51
B33: EGEJUNIN | C33: C.H. SANTA CRUZ I | D33: CENTRAL | E33: HIDROELÉCTRICA | F33: 71.55 | G33: 62.5 | H33: 119.1 | I33: 154.75 | J33: 124.1 | K33: 112.55 | L33: 115.95 | M33: 118 | N33: 107.75 | O33: 112 | P33: 152.4 | Q33: 164.15 | R33: 178.05 | S33: 177.3 | T33: 144.55 | U33: 133.95 | V33: 133.65 | W33: 156 | X33: 150.05 | Y33: 155.15 | Z33: 163.2 | AA33: 158.75 | AB33: 163.2 | AC33: 189.7 | AD33: 181.05 | AE33: 164.35 | AF33: 190.25 | AG33: 3854
B34: EGEMSA | C34: C.H. MACHUPICCHU | D34: CENTRAL | E34: HIDROELÉCTRICA | F34: 3704.95 | G34: 3919.4 | H34: 3970.1 | I34: 3953.25 | J34: 628.3 | K34: 3894.2 | L34: 3968.15 | M34: 3978.5 | N34: 4006.65 | O34: 4003.25 | P34: 3883.65 | Q34: 3996.1 | R34: 3999 | S34: 3932.35 | T34: 3956.35 | U34: 4008.25 | V34: 3993.85 | W34: 3896.35 | X34: 2989.35 | Y34: 4016.05 | Z34: 3990.95 | AA34: 4011.6 | AB34: 3986.4 | AC34: 3965.8 | AD34: 3954.65 | AE34: 3874 | AF34: 3980.35 | AG34: 102461.8
B35: EGESUR | C35: C.H. ARICOTA I | D35: CENTRAL | E35: HIDROELÉCTRICA | F35: 183.05 | G35: 182.85 | H35: 183.8 | I35: 183.3 | J35: 187.5 | K35: 183.6 | L35: 183.3 | M35: 185.1 | N35: 184.3 | O35: 183.35 | P35: 185 | Q35: 183.95 | R35: 182.85 | S35: 180.5 | T35: 182.65 | U35: 182.95 | V35: 183.05 | W35: 184.1 | X35: 184.85 | Y35: 185.5 | Z35: 182.3 | AA35: 185.54 | AB35: 186.2 | AC35: 185.15 | AD35: 184.95 | AE35: 185.6 | AF35: 186.6 | AG35: 4971.89
B36: EGESUR | C36: C.H. ARICOTA II | D36: CENTRAL | E36: HIDROELÉCTRICA | F36: 144.9 | G36: 149.3 | H36: 150.45 | I36: 148.9 | J36: 149.75 | K36: 148.55 | L36: 147.05 | M36: 148.6 | N36: 148.5 | O36: 145.65 | P36: 143.4 | Q36: 143.6 | R36: 139.65 | S36: 137.5 | T36: 140 | U36: 141.85 | V36: 144.15 | W36: 146.95 | X36: 146.75 | Y36: 146.4 | Z36: 143.5 | AA36: 142.75 | AB36: 143.85 | AC36: 146.15 | AD36: 144.25 | AE36: 141.75 | AF36: 144.45 | AG36: 3918.6
B37: EGESUR | C37: C.T. INDEPENDENCIA | D37: CENTRAL | E37: TERMOELÉCTRICA | AG37: 0
B38: ELECTRICA YANAPAMPA SAC | C38: C.H. YANAPAMPA | D38: CENTRAL | E38: HIDROELÉCTRICA | F38: 59.75 | G38: 59.1 | H38: 60 | I38: 71.8 | J38: 79.85 | K38: 77.35 | L38: 77.45 | M38: 81.25 | N38: 81.35 | O38: 80.75 | P38: 81.8 | Q38: 81.7 | R38: 81.6 | S38: 82.7 | T38: 80 | U38: 74.1 | V38: 73.8 | W38: 80.2 | X38: 79.3 | Y38: 80.7 | Z38: 79.55 | AA38: 79.75 | AB38: 60.1 | AC38: 39.25 | AD38: 81.75 | AE38: 81.1 | AF38: 79.25 | AG38: 2025.3
B39: ELECTROPERU | C39: C.H. MANTARO | D39: CENTRAL | E39: HIDROELÉCTRICA | F39: 13007.55 | G39: 14243.5 | H39: 15012.5 | I39: 14590 | J39: 15187.5 | K39: 15165.05 | L39: 15203.2 | M39: 14963.6 | N39: 15205.3 | O39: 15163.3 | P39: 15080.2 | Q39: 15174.4 | R39: 15081.7 | S39: 14208.2 | T39: 15130.95 | U39: 14750.9 | V39: 15140.85 | W39: 15122.4 | X39: 14832.6 | Y39: 15173.35 | Z39: 15123.2 | AA39: 15153.1 | AB39: 15154.65 | AC39: 15147.45 | AD39: 15154.1 | AE39: 14341.7 | AF39: 15143.3 | AG39: 402654.55
B40: ELECTROPERU | C40: C.H. RESTITUCION | D40: CENTRAL | E40: HIDROELÉCTRICA | F40: 4287.8 | G40: 4844 | H40: 5148.95 | I40: 4446.1 | J40: 5214.05 | K40: 5222.9 | L40: 5197.2 | M40: 5124.4 | N40: 5217.1 | O40: 5195.2 | P40: 5153.75 | Q40: 5184.9 | R40: 5165.65 | S40: 4813.8 | T40: 5182.75 | U40: 5059.1 | V40: 5174.25 | W40: 5172.55 | X40: 5051.45 | Y40: 5181.1 | Z40: 5172.05 | AA40: 5182.6 | AB40: 5181.65 | AC40: 5180.55 | AD40: 5180.45 | AE40: 4860 | AF40: 5143 | AG40: 136937.3
B41: ELECTROPERU | C41: C.T. TUMBES | D41: MAK1 | E41: TERMOELÉCTRICA | M41: 10.9 | AG41: 10.9
B42: ELECTROPERU | C42: C.T. TUMBES | D42: MAK2 | E42: TERMOELÉCTRICA | AB42: 9.05 | AG42: 9.05
B43: EMPRESA DE GENERACION ELECTRICA CANCHAYLLO SAC | C43: C.H. CANCHAYLLO | D43: CENTRAL | E43: HIDROELÉCTRICA | F43: 109.6 | G43: 113.3 | H43: 111.3 | I43: 110.35 | J43: 109.95 | K43: 110.5 | L43: 112.15 | M43: 113.55 | N43: 114.605 | O43: 113.7 | P43: 116.65 | Q43: 113.75 | R43: 113.65 | S43: 111.05 | T43: 107.05 | U43: 109.2 | V43: 111.6 | W43: 117.45 | X43: 117.95 | Y43: 119.35 | Z43: 112.45 | AA43: 110.55 | AB43: 109.45 | AC43: 105.15 | AD43: 105.05 | AE43: 103.1 | AF43: 105.15 | AG43: 3007.605
B44: EMPRESA DE GENERACION ELECTRICA RIO BAÑOS S.A.C. | C44: C.H. RUCUY | D44: CENTRAL | E44: HIDROELÉCTRICA | F44: 355.2 | G44: 412.3 | H44: 457.5 | I44: 479.75 | J44: 479.8 | K44: 480.05 | L44: 479.85 | M44: 478.85 | N44: 479.95 | O44: 479.25 | P44: 479.35 | Q44: 479.25 | R44: 479.7 | S44: 479.8 | T44: 479.6 | U44: 477.5 | V44: 479.3 | W44: 480 | X44: 479.05 | Y44: 479.7 | Z44: 479.3 | AA44: 476.49 | AB44: 479.45 | AC44: 480.45 | AD44: 479.9 | AE44: 479.25 | AF44: 480.2 | AG44: 12730.79
B45: EMPRESA DE GENERACION ELECTRICA SANTA ANA S.A.C. | C45: C.H. RENOVANDES H1 | D45: CENTRAL | E45: HIDROELÉCTRICA | F45: 487.35 | G45: 487.6 | H45: 426.15 | I45: 488.35 | J45: 243.9 | K45: 12.65 | L45: 191.2 | M45: 362.8 | N45: 488 | O45: 482.5 | P45: 487.6 | Q45: 487.4 | R45: 486.3 | S45: 485.05 | T45: 487.75 | U45: 482.2 | V45: 488.3 | W45: 488.6 | X45: 458.3 | Y45: 150.05 | AG45: 8172.05
B46: EMPRESA DE GENERACION HUALLAGA | C46: C.H. CHAGLLA | D46: CENTRAL | E46: HIDROELÉCTRICA | F46: 2225.6 | G46: 2934.8 | H46: 4180.5 | I46: 4222.3 | J46: 3993.35 | K46: 2341.45 | L46: 3109.95 | M46: 4648.1 | N46: 3408.1 | O46: 3319.2 | P46: 4170.35 | Q46: 3169.6 | R46: 4433 | S46: 4329.4 | T46: 3057.15 | U46: 4117.05 | V46: 10353.55 | W46: 5885.75 | X46: 5561 | Y46: 6499.1 | Z46: 8030.75 | AA46: 6199.79 | AB46: 6407.3 | AC46: 4753.65 | AD46: 3087.5 | AE46: 3495.25 | AF46: 3015.35 | AG46: 120948.89
B47: EMPRESA DE GENERACION HUALLAGA | C47: P.C.H. CHAGLLA | D47: CENTRAL | E47: HIDROELÉCTRICA | F47: 156 | G47: 156 | H47: 156 | I47: 156 | J47: 156 | K47: 156 | L47: 156 | M47: 156 | N47: 50 | V47: 32.35 | W47: 155.75 | X47: 155.8 | Y47: 154.7 | Z47: 154.6 | AA47: 153.25 | AB47: 155 | AC47: 154.75 | AD47: 115.6 | AE47: 155.15 | AF47: 154.7 | AG47: 2839.65
B48: EMPRESA DE GENERACION HUANZA | C48: C.H. HUANZA | D48: CENTRAL | E48: HIDROELÉCTRICA | F48: 1564.15 | G48: 1467.25 | H48: 1459.9 | I48: 1541.65 | J48: 1327.45 | K48: 1180 | L48: 1422 | M48: 1324.05 | N48: 1331.45 | O48: 1468.9 | P48: 1411 | Q48: 1427.5 | R48: 1414.3 | S48: 1567.65 | T48: 1651.45 | U48: 1801.35 | V48: 1883.55 | W48: 1958.3 | X48: 1778.25 | Y48: 1912.4 | Z48: 1757.1 | AA48: 1477.45 | AB48: 1501.35 | AC48: 1512.25 | AD48: 1429 | AE48: 1605.05 | AF48: 1595.1 | AG48: 41769.85
B49: EMPRESA ELECTRICA AGUA AZUL | C49: C.H. POTRERO | D49: CENTRAL | E49: HIDROELÉCTRICA | F49: 126.05 | G49: 119.3 | H49: 134.3 | I49: 214.35 | J49: 232.8 | K49: 187.2 | L49: 167.4 | M49: 175.2 | N49: 233.45 | O49: 241.25 | P49: 421.26535 | Q49: 418.05 | R49: 479.95 | S49: 480 | T49: 450.9 | U49: 384.45 | V49: 399.45 | W49: 354.85 | X49: 322 | Y49: 281.6 | Z49: 370.05 | AA49: 467.95 | AB49: 479.55 | AC49: 480 | AD49: 471.05 | AE49: 427.95 | AF49: 463.55 | AG49: 8983.9153
B50: EMPRESA ELECTRICA RIO DOBLE | C50: C.H. LAS PIZARRAS | D50: CENTRAL | E50: HIDROELÉCTRICA | F50: 108.6 | G50: 124.75 | H50: 141.25 | I50: 178.2 | J50: 223.85 | K50: 158.2 | L50: 139.1 | M50: 123.65 | N50: 145.25 | O50: 196.75 | P50: 370.95 | Q50: 405.5 | R50: 374.7 | S50: 323.95 | T50: 292.905 | U50: 246.25 | V50: 234 | W50: 222.95 | X50: 196 | Y50: 228 | Z50: 231.25 | AA50: 415.055 | AB50: 424.85 | AC50: 446.95 | AD50: 450.65 | AE50: 447.1 | AF50: 449.9 | AG50: 7300.56
B51: ENEL GENERACION PIURA S.A. | C51: C.T. MALACAS 1 | D51: TG6 | E51: TERMOELÉCTRICA | G51: 534.7845 | K51: 750.05 | L51: 790.85 | M51: 321.55 | N51: 820 | O51: 59.85 | Q51: 703.3 | R51: 375.1 | S51: 547.8 | T51: 732.95 | U51: 544.1 | V51: 352.9 | W51: 277.3 | Y51: 585.3 | Z51: 644.3 | AA51: 625.425 | AB51: 280.5 | AC51: 631.35 | AD51: 618.55 | AE51: 683.8 | AF51: 1067.75 | AG51: 11947.51
B52: ENEL GENERACION PIURA S.A. | C52: C.T. MALACAS 2 | D52: TG4 | E52: TERMOELÉCTRICA | F52: 24.95 | G52: 24.7 | H52: 31.15 | I52: 25.55 | J52: 38.35 | K52: 125.8 | T52: 305.45 | X52: 719.1 | Y52: 37.3 | AG52: 1332.35
B53: ENEL GENERACION PIURA S.A. | C53: C.T. RF DE GENERACION TALARA | D53: TG5 | E53: TERMOELÉCTRICA | V53: 120.3 | Y53: 89.45 | Z53: 59.35 | AA53: 43.95 | AB53: 101.35 | AC53: 54.8 | AD53: 62.6 | AE53: 297.55 | AG53: 829.35
B54: ENERGÍA EÓLICA S.A. | C54: C.E. CUPISNIQUE | D54: CENTRAL | E54: EÓLICA | F54: 995.5 | G54: 507.95 | H54: 866.8 | I54: 1435.85 | J54: 1410.3 | K54: 1230.85 | L54: 1251.6 | M54: 1322.35 | N54: 1418.95 | O54: 1017.75 | P54: 1120.85 | Q54: 834.45 | R54: 892.7 | S54: 1071.65 | T54: 1014.9 | U54: 686.35 | V54: 839.3 | W54: 857.05 | X54: 859.35 | Y54: 654.65 | Z54: 671.25 | AA54: 1174.65 | AB54: 1296.8 | AC54: 1384.35 | AD54: 1573.3 | AE54: 1225.65 | AF54: 941.15 | AG54: 28556.3
B55: ENERGÍA EÓLICA S.A. | C55: C.E. TALARA | D55: CENTRAL | E55: EÓLICA | F55: 407.75 | G55: 93.5 | H55: 181.5 | I55: 434.75 | J55: 598.75 | K55: 501.35 | L55: 572.7 | M55: 557.15 | N55: 520.3 | O55: 341.3 | P55: 336.1 | Q55: 226.35 | R55: 208.2 | S55: 560.45 | T55: 535.4 | U55: 562.65 | V55: 558.3 | W55: 370.6 | X55: 358.2 | Y55: 260.8 | Z55: 201.75 | AA55: 387.3 | AB55: 368.25 | AC55: 390.75 | AD55: 496.2 | AE55: 566.9 | AF55: 372.45 | AG55: 10969.7
B56: ENERGIA RENOVABLE DEL SUR S.A. | C56: C.E. SAN JUAN | D56: CENTRAL | E56: EÓLICA | F56: 2501.15 | G56: 2088 | H56: 782.85 | I56: 2304.35 | J56: 2676.75 | K56: 2067.6 | L56: 2130.95 | M56: 2539.95 | N56: 2276 | O56: 2227.35 | P56: 1989.2 | Q56: 1801.45 | R56: 1366.85 | S56: 1493.15 | T56: 990.25 | U56: 1113.8 | V56: 1051.95 | W56: 1560.3 | X56: 1587.5 | Y56: 1207.55 | Z56: 1343.85 | AA56: 1934.05 | AB56: 1640.8 | AC56: 1572.8 | AD56: 2019.15 | AE56: 1785.25 | AF56: 1277.1 | AG56: 47329.95
B57: ENGIE ENERGIA PERU S.A.A. | C57: C.E. PUNTA LOMITAS | D57: PL-BL1 | E57: EÓLICA | F57: 1971.85 | G57: 1753.75 | H57: 509.2 | I57: 2268.6 | J57: 2392.65 | K57: 2328.65 | L57: 2154.4 | N57: 1268.45 | O57: 1281.95 | P57: 1419.65 | Q57: 939.6 | R57: 806.2 | S57: 1123.8 | T57: 919.05 | U57: 1241.25 | V57: 1068.7 | X57: 1726.95 | Y57: 1319.35 | Z57: 1101.2 | AA57: 1224.96 | AB57: 1649.25 | AC57: 2273.65 | AD57: 2269.6 | AE57: 2204.6 | AF57: 1395.7 | AG57: 38613.01
B58: ENGIE ENERGIA PERU S.A.A. | C58: C.E. PUNTA LOMITAS | D58: PL-BL2 | E58: EÓLICA | F58: 1975.25 | G58: 2014.7 | H58: 725.95 | I58: 2304.25 | J58: 2419.1 | K58: 2470.1 | L58: 2429.1 | N58: 1646.1 | O58: 1736.2 | P58: 1937.25 | Q58: 1434 | R58: 1216.05 | S58: 1511.25 | T58: 1163.95 | U58: 1393.4 | V58: 1223.1 | X58: 1994.7 | Y58: 1510.915 | Z58: 1483.65 | AA58: 1639.885 | AB58: 2001 | AC58: 2356.4 | AD58: 2301.1421 | AE58: 2159.65 | AF58: 1519.85 | AG58: 44566.942
B59: ENGIE ENERGIA PERU S.A.A. | C59: C.E. PUNTA LOMITAS_EXP | D59: PUN LOM_EXP-BL1 | E59: EÓLICA | F59: 266.3 | G59: 248.8 | H59: 63.8 | I59: 362.8 | J59: 434.75 | K59: 412.55 | L59: 348.5 | M59: 243.9 | N59: 204 | O59: 197.8 | P59: 231.3 | Q59: 153.15 | R59: 140.7 | S59: 169.65 | T59: 129.05 | U59: 166.15 | V59: 148.25 | W59: 163.25 | X59: 242.05 | Y59: 181.65 | Z59: 129.85 | AA59: 98.625 | AB59: 213.1 | AC59: 328.7 | AD59: 335.2 | AE59: 298.4 | AF59: 161.95 | AG59: 6074.225
B60: ENGIE ENERGIA PERU S.A.A. | C60: C.E. PUNTA LOMITAS_EXP | D60: PUN LOM_EXP-BL2 | E60: EÓLICA | F60: 115.85 | G60: 97.6 | H60: 30.2 | I60: 245.2 | J60: 254.15 | K60: 237.4 | L60: 163.1 | M60: 104.25 | N60: 100.6 | O60: 110.7 | P60: 146.75 | Q60: 88.45 | R60: 79.35 | S60: 100.1 | T60: 94.4 | U60: 127.65 | V60: 96.25 | W60: 109.2 | X60: 145.85 | Y60: 89.2 | Z60: 60.6 | AA60: 85.505 | AB60: 142.2 | AC60: 230.5 | AD60: 243.7 | AE60: 216.35 | AF60: 91.65 | AG60: 3606.755
B61: ENGIE ENERGIA PERU S.A.A. | C61: C.H. QUITARACSA | D61: CENTRAL | E61: HIDROELÉCTRICA | W61: 0.3 | AG61: 0.3
B62: ENGIE ENERGIA PERU S.A.A. | C62: C.H. YUNCAN | D62: CENTRAL | E62: HIDROELÉCTRICA | F62: 1618.15 | G62: 2173.25 | H62: 2895.2 | I62: 2464.8 | J62: 2530.05 | K62: 2109.1 | L62: 1422.7 | M62: 2525 | N62: 1940 | O62: 2321.2 | P62: 2678.2 | Q62: 2794.7 | R62: 2214.9 | S62: 2281.45 | T62: 2303.35 | U62: 2157.9 | V62: 2993.4 | W62: 2672.35 | X62: 2928.2 | Y62: 3067.9 | Z62: 2796.4 | AA62: 3031.525 | AB62: 2605.35 | AC62: 2374.15 | AD62: 2273.55 | AE62: 2080.45 | AF62: 2600.15 | AG62: 65853.375
B63: ENGIE ENERGIA PERU S.A.A. | C63: C.S. INTIPAMPA | D63: CENTRAL | E63: SOLAR | F63: 332.45 | G63: 370.3 | H63: 375.95 | I63: 375.35 | J63: 372.65 | K63: 360.6 | L63: 343.15 | M63: 360 | N63: 372.9 | O63: 378.1 | P63: 384.6 | Q63: 385.55 | R63: 366.65 | S63: 375.05 | T63: 352.4 | U63: 366.45 | V63: 375.35 | W63: 382.15 | X63: 386.9 | Y63: 390.6 | Z63: 392.05 | AA63: 392.75 | AB63: 379.8 | AC63: 297.25 | AD63: 361.55 | AE63: 384.65 | AF63: 388.4 | AG63: 10003.6
B64: ENGIE ENERGIA PERU S.A.A. | C64: C.T. CHILCA 1 | D64: TG1 | E64: TERMOELÉCTRICA | F64: 3795.8 | G64: 2734.05 | H64: 2867 | I64: 3935.1 | J64: 3821.35 | K64: 4237.75 | L64: 3930.85 | M64: 3098.6 | N64: 4065.25 | O64: 3623.75 | P64: 2804.15 | Q64: 2461.5 | R64: 2976.65 | S64: 855.4 | AE64: 980.1 | AF64: 2946.75 | AG64: 49134.05
B65: ENGIE ENERGIA PERU S.A.A. | C65: C.T. CHILCA 1 | D65: TG2 | E65: TERMOELÉCTRICA | F65: 3764.25 | G65: 2724.4 | H65: 2691.65 | K65: 1347.8 | L65: 3682.2 | M65: 3080.55 | N65: 4025.75 | O65: 3592.2 | P65: 2798.55 | Q65: 2456.45 | R65: 2976.35 | S65: 3871.4 | T65: 4177.4 | U65: 4054.05 | V65: 173.35 | W65: 740.5 | Y65: 353.1 | Z65: 840.4 | AA65: 914.97 | AD65: 395.75 | AE65: 726.6 | AF65: 3547.25 | AG65: 52934.92
B66: ENGIE ENERGIA PERU S.A.A. | C66: C.T. CHILCA 1 | D66: TG3 | E66: TERMOELÉCTRICA | F66: 4235.9 | G66: 2845.8 | H66: 2955.4 | I66: 1025.5 | J66: 1546.6 | K66: 4800 | L66: 4385.9 | M66: 3351 | N66: 4472.2 | O66: 4046.25 | P66: 2856.2 | Q66: 2479.15 | R66: 2974.85 | S66: 4461.55 | T66: 4800 | U66: 4788.05 | V66: 4752.7 | W66: 4971.75 | X66: 660.85 | Y66: 1977.7 | Z66: 4908.7 | AA66: 4803.49 | AB66: 4948.3 | AC66: 4956.65 | AD66: 4848.95 | AE66: 4957.7 | AF66: 4414.15 | AG66: 102225.29
B67: ENGIE ENERGIA PERU S.A.A. | C67: C.T. CHILCA 1 | D67: TV | E67: TERMOELÉCTRICA | F67: 5984.15 | G67: 4862.6 | H67: 4905.15 | I67: 2242.45 | J67: 2526.4 | K67: 4492.9 | L67: 5976.8 | M67: 5216.85 | N67: 6215.2 | O67: 5780.7 | P67: 4907.05 | Q67: 4485.65 | R67: 5011.3 | S67: 4568.75 | T67: 4435.5 | U67: 4329.7 | V67: 2193.6 | W67: 2149.45 | X67: 90.25 | Y67: 756.35 | Z67: 2099.8 | AA67: 2083.415 | AB67: 2091.65 | AC67: 2092.3 | AD67: 2094.85 | AE67: 2092.65 | AF67: 5333.4 | AG67: 99018.865
B68: ENGIE ENERGIA PERU S.A.A. | C68: C.T. CHILCA 2 | D68: TG41 | E68: TERMOELÉCTRICA | N68: 119.65 | AG68: 119.65
B69: ENGIE ENERGIA PERU S.A.A. | C69: C.T. CHILCA 2 | D69: TV42 | E69: TERMOELÉCTRICA | V69: 0.6 | AG69: 0.6
B70: ENGIE ENERGIA PERU S.A.A. | C70: C.T. NEPI | D70: TG41 | E70: TERMOELÉCTRICA | AG70: 0
B71: ENGIE ENERGIA PERU S.A.A. | C71: C.T. NEPI | D71: TG42 | E71: TERMOELÉCTRICA | AG71: 0
B72: ENGIE ENERGIA PERU S.A.A. | C72: C.T. NEPI | D72: TG43 | E72: TERMOELÉCTRICA | M72: 450.4 | AG72: 450.4
B73: ENGIE ENERGIA PERU S.A.A. | C73: C.T. RF PLANTA ILO | D73: TG1 | E73: TERMOELÉCTRICA | AG73: 0
B74: ENGIE ENERGIA PERU S.A.A. | C74: C.T. RF PLANTA ILO | D74: TG2 | E74: TERMOELÉCTRICA | AG74: 0
B75: ENGIE ENERGIA PERU S.A.A. | C75: C.T. RF PLANTA ILO | D75: TG3 | E75: TERMOELÉCTRICA | AG75: 0
B76: FENIX POWER PERÚ | C76: C.T. FENIX | D76: GT11 | E76: TERMOELÉCTRICA | F76: 3580.25 | G76: 3739.25 | H76: 3994.05 | I76: 4117 | J76: 3214.1 | K76: 4063.1 | L76: 4203.7 | M76: 3414.6 | N76: 4370.9 | O76: 4246.9 | P76: 3317.25 | Q76: 80.55 | R76: 3333.5 | S76: 4086.2 | T76: 4338.5 | U76: 3748.2 | V76: 3884.85 | W76: 4050.35 | X76: 3647.2 | Y76: 4113.15 | Z76: 3804.7 | AA76: 4249.465 | AB76: 4158.4 | AC76: 3774.1 | AD76: 3855.35 | AE76: 1080.6 | AG76: 94466.215
B77: FENIX POWER PERÚ | C77: C.T. FENIX | D77: GT12 | E77: TERMOELÉCTRICA | F77: 3588.25 | G77: 3744.6 | H77: 4002.35 | I77: 4127.4 | J77: 3222.6 | K77: 4071.45 | L77: 4213.25 | M77: 3422.9 | N77: 4382.25 | O77: 4256.9 | P77: 3324 | Q77: 3418.8 | R77: 3895.15 | S77: 4095.1 | T77: 4349.75 | U77: 3758.6 | V77: 3894.75 | W77: 4061.5 | X77: 3655.1 | Y77: 4120.75 | Z77: 3813.9 | AA77: 4246.855 | AB77: 4167.5 | AC77: 3780.45 | AD77: 3867.55 | AE77: 376.55 | AG77: 97858.255
B78: FENIX POWER PERÚ | C78: C.T. FENIX | D78: TV10 | E78: TERMOELÉCTRICA | F78: 4000.55 | G78: 4085.1 | H78: 4222.7 | I78: 4287.7 | J78: 3803.6 | K78: 4254.2 | L78: 4339.35 | M78: 3930.85 | N78: 4421.15 | O78: 4349.3 | P78: 3873.1 | Q78: 2004.55 | R78: 3727.55 | S78: 4266.95 | T78: 4403.75 | U78: 4090.95 | V78: 4173.2 | W78: 4254.15 | X78: 4036.25 | Y78: 4275.75 | Z78: 4121.35 | AA78: 4355.87 | AB78: 4313.95 | AC78: 4102.65 | AD78: 4147.75 | AE78: 785.4 | AG78: 102627.67
B79: GENERACIÓN ANDINA S.A.C. | C79: C.H. 8 DE AGOSTO | D79: CENTRAL | E79: HIDROELÉCTRICA | F79: 252 | G79: 252 | H79: 252 | I79: 251.85 | J79: 260.55 | K79: 252 | L79: 293.8 | M79: 313.2 | N79: 251.05 | O79: 354.3 | P79: 503.8 | Q79: 419.95 | R79: 455.75 | S79: 385.15 | T79: 356.05 | U79: 488.55 | V79: 502.3 | W79: 294.3 | X79: 250.05 | Y79: 250.25 | Z79: 251.45 | AA79: 241.895 | AB79: 249.6 | AC79: 304.95 | AD79: 454.95 | AE79: 480.2 | AF79: 490.05 | AG79: 9111.995
B80: GENERACIÓN ANDINA S.A.C. | C80: C.H. EL CARMEN | D80: CENTRAL | E80: HIDROELÉCTRICA | F80: 148.2 | G80: 144.2 | H80: 183.95 | I80: 119.5 | J80: 79.4 | K80: 67.7 | L80: 69.4 | M80: 85.5 | N80: 65.85 | O80: 162.55 | P80: 158.2 | Q80: 124.7 | R80: 145.25 | S80: 115.75 | T80: 85.9 | U80: 140.85 | V80: 161.5 | W80: 147.3 | X80: 177.5 | Y80: 168.95 | Z80: 154.15 | AA80: 181.235 | AB80: 175.25 | AC80: 182.35 | AD80: 106.95 | AE80: 156.35 | AF80: 163.8 | AG80: 3672.235
B81: GENERADORA DE ENERGÍA DEL PERÚ | C81: C.H. ÁNGEL I | D81: CENTRAL | E81: HIDROELÉCTRICA | F81: 124.4 | G81: 274.25 | H81: 424.65 | I81: 422 | J81: 345.9 | K81: 247.25 | L81: 244.95 | M81: 328.45 | N81: 397.45 | O81: 374.05 | P81: 316.05 | Q81: 263.5 | R81: 230.6 | S81: 226.8 | T81: 426.05 | U81: 487.4 | V81: 489.6 | W81: 488 | X81: 489 | Y81: 489.5 | Z81: 418.55 | AA81: 389.93 | AB81: 325.8 | AC81: 458.7 | AD81: 487.37 | AE81: 474.45 | AF81: 475.4 | AG81: 10120.05
B82: GENERADORA DE ENERGÍA DEL PERÚ | C82: C.H. ÁNGEL II | D82: CENTRAL | E82: HIDROELÉCTRICA | F82: 136.6 | G82: 183.35 | H82: 326.4 | I82: 429.45 | J82: 360.95 | K82: 259 | L82: 254.9 | M82: 337.7 | N82: 403.45 | O82: 388.75 | P82: 328.65 | Q82: 277.15 | R82: 241.5 | S82: 237.55 | T82: 433.65 | U82: 489.6 | V82: 489.6 | W82: 489.6 | X82: 489.6 | Y82: 489.6 | Z82: 432.6 | AA82: 400.31 | AB82: 338.5 | AC82: 459 | AD82: 487.32 | AE82: 483.2 | AF82: 477.95 | AG82: 10125.93
B83: GENERADORA DE ENERGÍA DEL PERÚ | C83: C.H. ÁNGEL III | D83: CENTRAL | E83: HIDROELÉCTRICA | F83: 140.05 | G83: 179.4 | H83: 286.9 | I83: 414.15 | J83: 364.45 | K83: 262.55 | L83: 250.35 | M83: 331.45 | N83: 397.2 | O83: 387.6 | P83: 334.15 | Q83: 282.05 | R83: 246.15 | S83: 240.1 | T83: 398.5 | U83: 470.4 | V83: 470.4 | W83: 468.15 | X83: 470.4 | Y83: 470.85 | Z83: 428.6 | AA83: 396.66 | AB83: 340.3 | AC83: 436 | AD83: 472.44 | AE83: 475.1 | AF83: 470.9 | AG83: 9885.25
B84: GENERADORA DE ENERGÍA DEL PERÚ | C84: C.H. LA JOYA | D84: CENTRAL | E84: HIDROELÉCTRICA | F84: 174.85 | G84: 176.2 | H84: 174.05 | I84: 174.85 | J84: 167.9 | K84: 174 | L84: 175.25 | M84: 171.5 | N84: 174.9 | O84: 177.45 | P84: 169.7 | Q84: 165.35 | R84: 172.2 | S84: 165.5 | T84: 185.4 | U84: 182.15 | V84: 173.35 | W84: 169.4 | X84: 167.25 | Y84: 173.25 | Z84: 166.6 | AA84: 169.35 | AB84: 169.4 | AC84: 172.3 | AD84: 170.85 | AE84: 82.4 | AF84: 172.6 | AG84: 4568
B85: GM OPERACIONES S.A.C. | C85: CT REFINERIA TALARA | D85: TV1 REF TALARA | E85: TERMOELÉCTRICA | F85: 697.05 | G85: 675.25 | H85: 670.7 | I85: 677.25 | J85: 690.95 | K85: 700.05 | L85: 678.55 | M85: 670.3 | N85: 667.5 | O85: 674.15 | P85: 383.75 | V85: 224.7 | W85: 642.85 | X85: 657.9 | Y85: 680.35 | Z85: 512.85 | AG85: 9904.15
B86: GM OPERACIONES S.A.C. | C86: CT REFINERIA TALARA | D86: TV2 REF TALARA | E86: TERMOELÉCTRICA | F86: 788.65 | G86: 783.15 | H86: 768.75 | I86: 777.4 | J86: 778.05 | K86: 766.9 | L86: 767.1 | M86: 768.45 | N86: 783.95 | O86: 790.05 | P86: 444.45 | S86: 2.45 | T86: 374.375 | U86: 761.4 | V86: 789.85 | W86: 779.15 | X86: 810.95 | Y86: 794.85 | Z86: 576.8 | AF86: 317.595 | AG86: 13424.32
B87: GR CORTARRAMA SOCIEDAD ANONIMA CERRADA | C87: C.S. MATARANI | D87: C.S. MATARANI | E87: SOLAR | F87: 793.15 | G87: 790.5 | H87: 812.4 | I87: 819.3 | J87: 812.65 | K87: 784.7 | L87: 702.55 | M87: 777.25 | N87: 787.8 | O87: 798.65 | P87: 812.85 | Q87: 776 | R87: 792.1 | S87: 797.9 | T87: 765.15 | U87: 803.1 | V87: 741.15 | W87: 802.55 | X87: 824.05 | Y87: 831.8 | Z87: 830.15 | AA87: 831.4 | AB87: 790.25 | AC87: 695.55 | AD87: 699.05 | AE87: 5 | AF87: 814.75 | AG87: 20491.75
B88: GR PAINO SOCIEDAD ANONIMA CERRADA | C88: C.E. HUAMBOS | D88: CENTRAL | E88: EÓLICA | F88: 169.2 | G88: 237.4 | H88: 130.9 | I88: 169.35 | J88: 193.8 | K88: 168.05 | L88: 228.85 | M88: 198.1 | N88: 60.15 | O88: 20.1 | P88: 57.1 | Q88: 29.1 | R88: 35.1 | S88: 60.05 | T88: 84.05 | U88: 118.05 | V88: 198.15 | W88: 225.05 | X88: 172.45 | Y88: 174.95 | Z88: 148.05 | AA88: 156.65 | AB88: 153.3 | AC88: 198.15 | AD88: 70.1 | AE88: 63.9 | AF88: 35.25 | AG88: 3555.35
B89: GR TARUCA SOCIEDAD ANONIMA CERRADA | C89: C.E. DUNA | D89: CENTRAL | E89: EÓLICA | F89: 203.5 | G89: 301.35 | H89: 164.1 | I89: 195.75 | J89: 213.25 | K89: 208.75 | L89: 242.9 | M89: 186.9 | N89: 54.25 | O89: 16.3 | P89: 60.9 | Q89: 25.3 | R89: 27.45 | S89: 61.45 | T89: 75.9 | U89: 135.85 | V89: 207.95 | W89: 241.45 | X89: 169.4 | Y89: 159.95 | Z89: 149.8 | AA89: 158.385 | AB89: 172.1 | AC89: 189.95 | AD89: 79.95 | AE89: 59.45 | AF89: 20.65 | AG89: 3782.935
B90: HIDROCAÑETE S.A. | C90: C.H. IMPERIAL | D90: CENTRAL | E90: HIDROELÉCTRICA | F90: 83.75 | G90: 44.3 | H90: 84.65 | I90: 84.75 | J90: 84.8 | K90: 84.15 | L90: 84.25 | M90: 84.15 | N90: 84.55 | O90: 83.85 | P90: 86.05 | Q90: 84.45 | R90: 84.1 | S90: 84 | T90: 86.15 | U90: 84.55 | V90: 85.7 | W90: 85.75 | X90: 84.55 | Y90: 81.35 | Z90: 79.6 | AA90: 81.9 | AB90: 81.9 | AC90: 84.05 | AD90: 84.15 | AE90: 85.6 | AF90: 85.2 | AG90: 2232.25
B91: HIDROELECTRICA HUANCHOR S.A.C. | C91: C.H. HUANCHOR | D91: CENTRAL | E91: HIDROELÉCTRICA | F91: 438.65 | G91: 436.75 | H91: 440.5 | I91: 442.2 | J91: 430.95 | K91: 431.1 | L91: 440.5 | M91: 435.3 | N91: 438.3 | O91: 439.65 | P91: 418.3966 | Q91: 218.6 | R91: 223.7595 | S91: 247.35 | T91: 340.55 | U91: 402.15 | V91: 424.25 | W91: 409.2 | X91: 404.65 | Y91: 410.45 | Z91: 401.2 | AA91: 406.73 | AB91: 418.1 | AC91: 428.65 | AD91: 430.4 | AE91: 438.95 | AF91: 436.15 | AG91: 10833.436
B92: HUAURA POWER GROUP S.A. | C92: C.H. YARUCAYA | D92: CENTRAL | E92: HIDROELÉCTRICA | F92: 444 | G92: 444 | H92: 443.95 | I92: 443.95 | J92: 444 | K92: 444 | L92: 444 | M92: 444 | N92: 443.95 | O92: 444 | P92: 444 | Q92: 444 | R92: 444 | S92: 424.85 | T92: 446.4 | U92: 436.8 | V92: 444.2 | W92: 446.3 | X92: 446.4 | Y92: 446.4 | Z92: 446.4 | AA92: 446.4 | AB92: 446.4 | AC92: 446.4 | AD92: 446.4 | AE92: 446.4 | AF92: 445.8 | AG92: 11987.4
B93: HYDRO GLOBAL PERÚ S.A.C. | C93: CH SAN GABAN III | D93: CENTRAL | E93: HIDROELÉCTRICA | F93: 2447.4 | G93: 2383.75 | H93: 3446.9 | I93: 3471.9 | J93: 3494.05 | K93: 2787.35 | L93: 2615.05 | M93: 2724.1 | N93: 3215.3 | O93: 3482.1 | P93: 3487.55 | Q93: 3471.35 | R93: 2833.9 | S93: 2878.9 | T93: 3271.95 | U93: 4236.65 | V93: 4788.4 | W93: 4853.05 | X93: 4855.05 | Y93: 4871.4 | Z93: 4864.1 | AA93: 4076.825 | AB93: 3443.8 | AC93: 4464.2 | AD93: 4907.65 | AE93: 4078.65 | AF93: 4256.3 | AG93: 99707.625
B94: INFRAESTRUCTURAS Y ENERGIAS DEL PERU S.A.C. | C94: C.T. RF PTO MALDONADO | D94: CENTRAL | E94: TERMOELÉCTRICA | V94: 0.7 | AD94: 0.9 | AG94: 1.6
B95: INFRAESTRUCTURAS Y ENERGIAS DEL PERU S.A.C. | C95: C.T. RF PUCALLPA | D95: CENTRAL | E95: TERMOELÉCTRICA | K95: 1.65 | AD95: 1.6 | AG95: 3.25
B96: INLAND ENERGY SAC | C96: C.H. SANTA TERESA | D96: CENTRAL | E96: HIDROELÉCTRICA | F96: 1968.2 | G96: 2129.7 | H96: 2165.95 | I96: 2141.25 | J96: 66.35 | K96: 2111.6 | L96: 2160.65 | M96: 2159.75 | N96: 2172.3 | O96: 2173.1 | P96: 2097.95 | Q96: 2174.6 | R96: 2164.9 | S96: 2118.5 | T96: 2113.25 | U96: 2188.55 | V96: 2166.5 | W96: 2090.7 | X96: 1677.95 | Y96: 2184.2 | Z96: 2181.25 | AA96: 2156.475 | AB96: 2157.3 | AC96: 2165.6 | AD96: 2157.8 | AE96: 2107.1 | AF96: 2163.1 | AG96: 55314.575
B97: INVERSIONES SHAQSHA S.A.C. | C97: C.H. PARIAC | D97: CENTRAL | E97: HIDROELÉCTRICA | L97: 12.8 | M97: 58.25 | N97: 51.4 | O97: 54.8 | P97: 60 | Q97: 58.75 | R97: 60 | S97: 57.75 | T97: 45.65 | U97: 36.365 | V97: 48.5 | W97: 60 | X97: 60 | Y97: 71.8 | Z97: 87.9 | AA97: 91.75 | AB97: 100.2 | AC97: 97 | AD97: 83.45 | AE97: 92 | AF97: 96 | AG97: 1384.365
B98: JOYA SOLAR S.A.C. | C98: C.S. SAN MARTIN SOLAR | D98: CENTRAL | E98: SOLAR | F98: 2569.3 | G98: 2598.1 | H98: 2600 | I98: 2608.25 | J98: 2599.45 | K98: 2602.25 | L98: 2354.95 | M98: 2503.9 | N98: 2562 | O98: 2591.25 | P98: 2598.2 | Q98: 2616.95 | R98: 2576.7 | S98: 2540.9 | T98: 2435.2 | U98: 2602.65 | V98: 2424.05 | W98: 2550.35 | X98: 2582 | Y98: 2655.45 | Z98: 2644.25 | AA98: 2651.9 | AB98: 2610.55 | AC98: 2243.38 | AD98: 2406.75 | AE98: 2653.75 | AF98: 2660.1 | AG98: 69042.58
B99: KALLPA GENERACION S.A. | C99: C.H. CERRO DEL AGUILA | D99: CENTRAL | E99: HIDROELÉCTRICA | F99: 4751.1 | G99: 6923.3 | H99: 7251.35 | I99: 6078.25 | J99: 7618.65 | K99: 7072.95 | L99: 7359.7 | M99: 6757.35 | N99: 7180.1 | O99: 7995.55 | P99: 8674 | Q99: 9434.3 | R99: 10385.75 | S99: 11732.9 | T99: 9360.75 | U99: 9476.75 | V99: 11978.65 | W99: 9513.85 | X99: 11190.3 | Y99: 13344 | Z99: 13285.3 | AA99: 13334.815 | AB99: 13330.65 | AC99: 13339 | AD99: 8961.5 | AE99: 8966.6 | AF99: 9016.85 | AG99: 254314.27
B100: KALLPA GENERACION S.A. | C100: C.S. SUNNY | D100: CENTRAL | E100: SOLAR | F100: 1919.2 | G100: 1953.5 | H100: 2020.1 | I100: 2035.3 | J100: 2146.2 | K100: 2164.25 | L100: 1264.2 | M100: 1750.6 | N100: 2039.45 | O100: 2141.1 | P100: 2166.8 | Q100: 2176.95 | R100: 2208.65 | S100: 2078 | T100: 1947.15 | U100: 2151.19 | V100: 1996.63 | W100: 2092.38 | X100: 2189.65 | Y100: 2210.5 | Z100: 2144.7 | AA100: 2191.7 | AB100: 2140.885 | AC100: 1870.28 | AD100: 2046.35 | AE100: 2212.3 | AF100: 1348.95 | AG100: 54606.965
B101: KALLPA GENERACION S.A. | C101: C.T. KALLPA | D101: TG1 | E101: TERMOELÉCTRICA | F101: 3356.05 | G101: 3095.7 | H101: 3106.45 | I101: 3571.4 | J101: 187.8 | S101: 2849.8 | T101: 3766.6 | U101: 3119.8 | V101: 3305.3 | W101: 3399.6 | X101: 3140.85 | Y101: 3299.9 | Z101: 3429.25 | AA101: 3551.82 | AB101: 3242.1 | AC101: 3318.05 | AD101: 3215.65 | AE101: 3411.35 | AF101: 3885.7 | AG101: 60253.17
B102: KALLPA GENERACION S.A. | C102: C.T. KALLPA | D102: TG2 | E102: TERMOELÉCTRICA | F102: 3378 | G102: 3093.25 | H102: 3091.9 | I102: 3661.05 | J102: 3660.05 | K102: 4916.6 | L102: 4952.45 | M102: 4699.35 | N102: 4948.15 | O102: 4947.7 | P102: 4847.35 | Q102: 4138.9 | R102: 4925.35 | S102: 3874.85 | T102: 3783.2 | U102: 3119.95 | V102: 3299.35 | W102: 3399.95 | X102: 3142.55 | Y102: 3322 | Z102: 3428.8 | AA102: 3561.435 | AB102: 3237.2 | AC102: 3318.4 | AD102: 3216 | AE102: 3413.2 | AF102: 3912.95 | AG102: 103289.93
B103: KALLPA GENERACION S.A. | C103: C.T. KALLPA | D103: TG3 | E103: TERMOELÉCTRICA | F103: 3378.15 | G103: 3094.9 | H103: 3096 | I103: 3675 | J103: 3676.25 | K103: 4977.55 | L103: 5006.7 | M103: 4740.1 | N103: 5018.4 | O103: 5015.1 | P103: 4898.45 | Q103: 4184.85 | R103: 4995.85 | S103: 3890.25 | T103: 3782.35 | U103: 3116.9 | V103: 3299.1 | W103: 3399.05 | X103: 3141.4 | Y103: 3321.45 | Z103: 3427.25 | AA103: 3560.085 | AB103: 3237.45 | AC103: 3315.1 | AD103: 3215.7 | AE103: 3415.25 | AF103: 3912.5 | AG103: 103791.13
...

Sheet G_AREAS
B3: lunes, 27 de Octubre del 2025
B5: HORA | C5: RESUMEN DE GENERACIÓN POR ÁREAS DEL SEIN | D5: RESUMEN DE GENERACIÓN POR ÁREAS DEL SEIN | E5: RESUMEN DE GENERACIÓN POR ÁREAS DEL SEIN | F5: RESUMEN DE GENERACIÓN POR ÁREAS DEL SEIN | G5: RESUMEN DE GENERACIÓN POR ÁREAS DEL SEIN | H5: RESUMEN DE GENERACIÓN POR ÁREAS DEL SEIN | I5: RESUMEN DE GENERACIÓN POR ÁREAS DEL SEIN | J5: RESUMEN DE GENERACIÓN POR ÁREAS DEL SEIN | K5: RESUMEN DE GENERACIÓN POR ÁREAS DEL SEIN | L5: RESUMEN DE GENERACIÓN POR ÁREAS DEL SEIN | M5: RESUMEN DE GENERACIÓN POR ÁREAS DEL SEIN | N5: RESUMEN DE GENERACIÓN POR ÁREAS DEL SEIN | O5: RESUMEN DE GENERACIÓN POR ÁREAS DEL SEIN | P5: RESUMEN DE GENERACIÓN POR ÁREAS DEL SEIN | Q5: RESUMEN DE GENERACIÓN POR ÁREAS DEL SEIN | R5: RESUMEN DE GENERACIÓN POR ÁREAS DEL SEIN | S5: HORA | T5: GENERACIÓN POR TIPO DE GENERACIÓN | U5: GENERACIÓN POR TIPO DE GENERACIÓN | V5: GENERACIÓN POR TIPO DE GENERACIÓN | W5: GENERACIÓN POR TIPO DE GENERACIÓN | X5: GENERACIÓN POR TIPO DE GENERACIÓN | Y5: HORA | Z5: GENERACIÓN POR TIPO DE GENERACIÓN | AA5: GENERACIÓN POR TIPO DE GENERACIÓN | AB5: GENERACIÓN POR TIPO DE GENERACIÓN | AC5: GENERACIÓN POR TIPO DE GENERACIÓN | AD5: GENERACIÓN POR TIPO DE GENERACIÓN
C6: NORTE | D6: NORTE | E6: NORTE | F6: NORTE | G6: CENTRO | H6: CENTRO | I6: CENTRO | J6: CENTRO | K6: SUR | L6: SUR | M6: SUR | N6: SUR | O6: GENERACIÓN INTEGRANTES COES | P6: GENERACIÓN INTEGRANTES COES | Q6: GENERACIÓN INTEGRANTES COES | R6: GENERACIÓN INTEGRANTES COES | T6: INTEGRANTES COES | U6: INTEGRANTES COES | V6: INTEGRANTES COES | W6: INTEGRANTES COES | X6: INTEGRANTES COES | Z6: INTEGRANTES COES RER | AA6: INTEGRANTES COES RER | AB6: INTEGRANTES COES RER | AC6: INTEGRANTES COES RER | AD6: INTEGRANTES COES RER
C7: GENERACIÓN HIDROELÉCTRICA NORTE | D7: GENERACIÓN TERMOELÉCTRICA NORTE | E7: GENERACIÓN SOLAR NORTE | F7: GENERACIÓN EÓLICA NORTE | G7: GENERACIÓN HIDROELÉCTRICA CENTRO | H7: GENERACIÓN TERMOELÉCTRICA CENTRO | I7: GENERACIÓN SOLAR CENTRO | J7: GENERACIÓN EÓLICA CENTRO | K7: GENERACIÓN HIDROELÉCTRICA SUR | L7: GENERACIÓN TERMOELÉCTRICA SUR | M7: GENERACIÓN SOLAR SUR | N7: GENERACIÓN EÓLICA SUR | O7: GENERACIÓN COES NORTE | P7: GENERACIÓN COES CENTRO | Q7: GENERACIÓN COES SUR | R7: TOTAL GENERACION | T7: HIDROELÉCTRICA | U7: TERMOELÉCTRICA | V7: SOLAR | W7: EÓLICA | X7: TOTAL GENERACION | Z7: HIDROELÉCTRICA RER | AA7: TERMOELÉCTRICA RER | AB7: SOLAR RER | AC7: EÓLICA RER | AD7: TOTAL RER
B8: 00:30 | C8: 413.746 | D8: 83.4 | E8: 0 | F8: 36.2 | G8: 2811.008 | H8: 2006.5 | I8: 0 | J8: 299.6 | K8: 649.5 | L8: 0 | M8: 0 | N8: 0 | O8: 533.346 | P8: 5117.108 | Q8: 649.5 | R8: 6299.954 | S8: 00:30 | T8: 3874.254 | U8: 2089.9 | V8: 0 | W8: 335.8 | X8: 6299.954 | Y8: 00:30 | Z8: 330.454 | AA8: 58.6 | AB8: 0 | AC8: 335.8 | AD8: 724.854
B9: 01:00 | C9: 416.145 | D9: 81.7 | E9: 0 | F9: 26.5 | G9: 2821.613 | H9: 1990.1 | I9: 0 | J9: 294.1 | K9: 600 | L9: 0 | M9: 0 | N9: 0 | O9: 524.345 | P9: 5105.813 | Q9: 600 | R9: 6230.158 | S9: 01:00 | T9: 3837.758 | U9: 2071.8 | V9: 0 | W9: 320.6 | X9: 6230.158 | Y9: 01:00 | Z9: 331.158 | AA9: 56.5 | AB9: 0 | AC9: 320.6 | AD9: 708.258
B10: 01:30 | C10: 419.233 | D10: 82.3 | E10: 0 | F10: 26.6 | G10: 2803.105 | H10: 1986.2 | I10: 0 | J10: 251.6 | K10: 654.8 | L10: 0 | M10: 0 | N10: 0 | O10: 528.133 | P10: 5040.905 | Q10: 654.8 | R10: 6223.838 | S10: 01:30 | T10: 3877.138 | U10: 2068.5 | V10: 0 | W10: 278.2 | X10: 6223.838 | Y10: 01:30 | Z10: 332.138 | AA10: 57.8 | AB10: 0 | AC10: 278.2 | AD10: 668.138
B11: 02:00 | C11: 406.713 | D11: 81.1 | E11: 0 | F11: 41 | G11: 2741.946 | H11: 2003.8 | I11: 0 | J11: 243.7 | K11: 636.9 | L11: 0 | M11: 0 | N11: 0 | O11: 528.813 | P11: 4989.446 | Q11: 636.9 | R11: 6155.159 | S11: 02:00 | T11: 3785.559 | U11: 2084.9 | V11: 0 | W11: 284.7 | X11: 6155.159 | Y11: 02:00 | Z11: 332.759 | AA11: 56.5 | AB11: 0 | AC11: 284.7 | AD11: 673.959
B12: 02:30 | C12: 403.454 | D12: 82.8 | E12: 0 | F12: 39 | G12: 2569.646 | H12: 2065.9 | I12: 0 | J12: 252.8 | K12: 662.5 | L12: 0 | M12: 0 | N12: 0 | O12: 525.254 | P12: 4888.346 | Q12: 662.5 | R12: 6076.1 | S12: 02:30 | T12: 3635.6 | U12: 2148.7 | V12: 0 | W12: 291.8 | X12: 6076.1 | Y12: 02:30 | Z12: 330.3 | AA12: 58.2 | AB12: 0 | AC12: 291.8 | AD12: 680.3
B13: 03:00 | C13: 263.348 | D13: 83.8 | E13: 0 | F13: 25 | G13: 2517.529 | H13: 2184.8 | I13: 0 | J13: 258.2 | K13: 637.8 | L13: 0 | M13: 0 | N13: 0 | O13: 372.148 | P13: 4960.529 | Q13: 637.8 | R13: 5970.477 | S13: 03:00 | T13: 3418.677 | U13: 2268.6 | V13: 0 | W13: 283.2 | X13: 5970.477 | Y13: 03:00 | Z13: 329.477 | AA13: 58.4 | AB13: 0 | AC13: 283.2 | AD13: 671.077
