Workbook

Sheet EVENTOS
B3: sábado, 26 de Abril del 2025
B5: INFORMACIÓN DE EVENTOS PRINCIPALES EN SUS INSTALACIONES
B6: TIPO DE EVENTO | C6: EMPRESA | D6: UBICACIÓN | E6: TIPO DE EQUIPO | F6: EQUIPO | G6: INICIO | H6: FINAL | I6: DESCRIPCIÓN | J6: MW INDISP. | K6: INTERRUPCIÓN (SI/NO) | L6: TENSIÓN DE FALLA (kV)
B7: EVENTO | C7: CONELSUR LT SAC | D7: PORTILLO | E7: SUBESTACION | F7: SS.EE. | G7: 26/04/2025 00:00:00 | H7: 27/04/2025 00:00:00 | I7: DECLARACIÓN DE SITUACIÓN EXCEPCIONAL EN LA S.E. PORTILLO DE 60 kV | K7: NO
B8: EVENTO | C8: ELECTRONOROESTE S.A. | D8: PIURA OESTE - SULLANA | E8: LINEA DE TRANSMISION | F8: L-6698 | G8: 26/04/2025 02:36:00 | H8: 26/04/2025 06:22:00 | I8: DESCONECTÓ LA LÍNEA L-6698 (PIURA OESTE - SULLANA) DE 60 KV | K8: NO
B9: FALLA | C9: KALLPA GENERACION S.A. | D9: MINI CENTRAL CERRO DEL AGUILA | E9: CENTRAL HIDROELÉCTRICA | F9: CENTRAL | G9: 26/04/2025 02:06:00 | H9: 26/04/2025 13:37:00 | I9: DESCONEXIÓN DE LA C.H. MINI CENTRAL CERRO DEL AGUILA POR FALLA | K9: NO | L9: 13.8
B10: EVENTO | C10: RED DE ENERGIA DEL PERU S.A. | D10: TINGO MARÍA - AUCAYACU | E10: LINEA DE TRANSMISION | F10: L-1122 | G10: 26/04/2025 08:40:00 | H10: 26/04/2025 15:45:00 | I10: DECLARACIÓN DE SITUACIÓN EXCEPCIONAL EN LA LÍNEA L-1122 (TINGO MARÍA - AUCAYACU) DE 138 kV | K10: NO
B11: EVENTO | C11: RED DE ENERGIA DEL PERU S.A. | D11: TINGO MARÍA - AUCAYACU | E11: LINEA DE TRANSMISION | F11: L-1122 | G11: 26/04/2025 18:20:00 | H11: 26/04/2025 20:57:00 | I11: DECLARACIÓN DE SITUACIÓN EXCEPCIONAL EN LA LÍNEA L-1122 (TINGO MARÍA - AUCAYACU) DE 138 kV | K11: NO
B12: FALLA | C12: STATKRAFT S.A | D12: MOROCOCHA - CARLOS FRANCISCO | E12: LINEA DE TRANSMISION | F12: L-6532 | G12: 26/04/2025 15:07:00 | H12: 26/04/2025 15:37:00 | I12: DESCONEXIÓN DE LAS LÍNEAS L-6532 Y L-6533 (NUEVA MOROCOCHA - CASAPALCA) DE 50 kV POR FALLA | K12: SI | L12: 50
B13: EVENTO | C13: ATLANTICA TRANSMISION SUR S.A. | D13: POROMA - OCONA | E13: LINEA DE TRANSMISION | F13: L-5034 | G13: 26/04/2025 11:20:00 | H13: 26/04/2025 16:12:00 | I13: DECLARACIÓN DE SITUACION EXCEPCIONAL EN EL ENLACE CENTRO - SUR | K13: NO

Sheet RESTRIC_OPE
B3: sábado, 26 de Abril del 2025
B5: RESTRICCIONES OPERATIVAS
B6: FECHA | C6: HORA INICIO | D6: HORA FINAL | E6: EMPRESA | F6: UBICACIÓN | G6: T.Eq. | H6: EQUIPO | I6: DESCRIPCIÓN
B7: 26/04/2025 | C7: 00:00 | D7: 24:00 | E7: CELEPSA | F7: C.H. EL PLATANAL | G7: CH | H7: CENTRAL | I7: Debido al incremento del caudal del rio cañete y establecimiento de la temporada de avenida, se declara la C.H. El Platanal como CENTRAL HIDRÁULICA DE PASADA (correo 03/01/2025).
B8: 26/04/2025 | C8: 00:00 | D8: 24:00 | E8: EGASA | F8: C.H. CHARCANI II | G8: GH | H8: G2 | I8: El Grupo N°02 esta operando con una potencia no mayor a 0.07MW en referencia a 0.18MW de su potencia efectiva, con el fin de no generar daños mayores hasta la reparación de su cojinete.
B9: 26/04/2025 | C9: 00:00 | D9: 24:00 | E9: EGASA | F9: S.E. CONVERTIDOR | G9: BARRA | H9: BARRA138KV | I9: EGASA limitó la capacidad del transformador 138 kV/33 kV a 50 MVA por deterioro del aislamiento.
B10: 26/04/2025 | C10: 00:00 | D10: 24:00 | E10: ENEL GENERACION PIURA S.A. | F10: C.T. MALACAS | G10: CT | H10: CENTRAL | I10: De acuerdo con la comunicación vía correo del día 24.10.2024. ENEL GENERACIÓN PIURA informa una restricción de potencia para alcanzar 105 MW en simultaneo (TG6+TGN4).
B11: 26/04/2025 | C11: 00:00 | D11: 24:00 | E11: ENEL GENERACION PIURA S.A. | F11: C.T. MALACAS | G11: CT | H11: CENTRAL | I11: La unidad TGN4 de la CT Malacas está limitada a 35 MW y no puede operar en conjunto con la TG6. Esto debido a que el ducto estará en mantenimiento, así como su compresor de GAS hasta el 05/05/2025.
B12: 26/04/2025 | C12: 00:00 | D12: 24:00 | E12: ENGIE | F12: C.E. PUNTA LOMITAS | G12: CE | H12: CENTRAL | I12: De acuerdo a la carta ENG/737-2024 (Exp:202400007555). Limitación de cables de media tensión a 100 MW de los transformadores PLT1 y PLT2 de la CE Punta Lomitas. Quedan limitados a 200 MW la generación de CE Punta Lomitas y Punta Lomitas Extensión.
B13: 26/04/2025 | C13: 00:00 | D13: 24:00 | E13: ENGIE | F13: C.H. QUITARACSA | G13: CH | H13: CENTRAL | I13: De acuerdo con el correo del 23.04 se considera la operación continua de la CH Quitaracsa debido a que el sistema de refrigeración de la CH Cañón del Pato se alimenta desde la descarga del caudal turbinado por la CH Quitaracsa.
B14: 26/04/2025 | C14: 00:00 | D14: 24:00 | E14: ENGIE | F14: C.H. YUNCÁN | G14: GH | H14: G3 | I14: Según la carta N° ENG/ 198-2024 enviada por su representada, se opera de forma continua el G3 de la CH Yuncán, debido a la ejecución de mantenimientos necesarios para evitar daños en los sellos de seguridad de la válvula esférica del grupo.
B15: 26/04/2025 | C15: 00:00 | D15: 24:00 | E15: ENGIE | F15: C.T. CHILCA 1 | G15: CT | H15: CENTRAL | I15: Con carta ENG/971-2023, indica que no puede cumplir con las IO considerada en el PDO_17122023 dado que vulneran la seguridad de sus activos. Indican que se debe tomar TMO=168h.
B16: 26/04/2025 | C16: 00:00 | D16: 24:00 | E16: ENGIE | F16: C.T. CHILCA 1 | G16: CT | H16: CENTRAL | I16: Restricción de temperatura de la C.T Chilca, ver valor en el modelo de despacho.
B17: 26/04/2025 | C17: 00:00 | D17: 24:00 | E17: ENGIE | F17: C.T. CHILCA 2 | G17: CT | H17: CENTRAL | I17: Restricción de temperatura de la C.T Chilca2, ver valor en el modelo de despacho.
... B48: 26/04/2025 | C48: 00:00 | D48: 24:00 | E48: TERMOSELVA | F48: C.T. AGUAYTÍA | G48: CT | H48: CENTRAL | I48: Restricción de 19 MMPCD de GN para la CT Aguaytía.

Sheet MANTENIMIENTO EJECUTADOS
B3: sábado, 26 de Abril del 2025
B5: Mantenimiento Ejecutado
B6: Empresa | C6: Ubicación | D6: Equipo | E6: Inicio | F6: Final | G6: Descripción | H6: MW Indisp. | I6: Prog. | J6: Dispon | K6: Interrupc. | L6: Tipo | M6: CodEq | N6: TipoEq_Osinerg
B7: AGROAURORA S.A.C. | C7: MAPLE ETANOL | D7: CENTRAL | E7: 26/04/2025 00:00 | F7: 27/04/2025 00:00 | G7: MANTENIMIENTO PREVENTIVO PROGRAMADO DE LA CENTRAL TERMOELECTRICA Y EQUIPOS AUXILIARES. | H7: 17 | I7: P | J7: F/S | K7: N | L7: OTROS | M7: 13417 | N7: G
B8: AGROAURORA S.A.C. | C8: MAPLE ETANOL | D8: CENTRAL | E8: 26/04/2025 00:00 | F8: 27/04/2025 00:00 | G8: CENTRAL TERMOELECTRICA FUERA DE SERVICIO POR FALTA DE MATERIA PRIMA PARA LOS REQUERIMIENTOS DE CALOR UTIL EN FABRICA | H8: 17 | I8: P | J8: F/S | K8: N | L8: OTROS | M8: 13417 | N8: G
B9: AGROINDUSTRIAS SAN JACINTO S.A.A. | C9: SAN JACINTO | D9: CENTRAL | E9: 26/04/2025 00:00 | F9: 27/04/2025 00:00 | G9: Mantenimiento Anual. | H9: 8.15 | I9: P | J9: F/S | K9: N | L9: PREV. | M9: 19865 | N9: G
B10: ATLANTICA TRANSMISION SUR S.A. | C10: CHILCA-CTM | D10: INT-5261 | E10: 26/04/2025 00:00 | F10: 27/04/2025 00:00 | G10: Seccionador SBB-5261 fase S indisponible para maniobras de apertura y cierre por anomalia en tapa de tanque de compresion, el seccionador permanece cerrado y bloqueado. | H10: 0 | I10: P | J10: E/S | K10: N | L10: OTROS | M10: 13854 | N10: T
B11: ATLANTICA TRANSMISION SUR S.A. | C11: MONTALVO | D11: ACOPLE 220 | E11: 26/04/2025 00:00 | F11: 27/04/2025 00:00 | G11: Proyecto Refuerzos: Reemplazo del HMI existente, Pruebas y Configuracion. No se contara con nivel 1 de operacion. | H11: 0 | I11: P | J11: E/S | K11: N | L11: P.ENERG | M11: 14767 | N11: T
B12: ATLANTICA TRANSMISION SUR S.A. | C12: MONTALVO | D12: BARRA A_220KV | E12: 26/04/2025 00:00 | F12: 27/04/2025 00:00 | G12: Proyecto Refuerzos: Indisponibilidad de la proteccion diferencial de barras 220 kV por Conexion de la nueva UB-87B hacia la UC existente,Configuracion y Pruebas. | H12: 0 | I12: P | J12: E/S | K12: N | L12: P.ENERG | M12: 13869 | N12: T
B13: ATLANTICA TRANSMISION SUR S.A. | C13: MONTALVO | D13: BARRA A_500KV | E13: 26/04/2025 00:00 | F13: 27/04/2025 00:00 | G13: Proyecto Refuerzos: Indisponibilidad de la proteccion diferencial de barras 500kV por conexion de nueva UB-87B hacia la UC existente, Configuracion y Pruebas. | H13: 0 | I13: P | J13: E/S | K13: N | L13: P.ENERG | M13: 13870 | N13: T
B14: ATLANTICA TRANSMISION SUR S.A. | C14: MONTALVO | D14: BARRA B_220kV | E14: 26/04/2025 00:00 | F14: 27/04/2025 00:00 | G14: Proyecto Refuerzos: Indisponibilidad de la proteccion diferencial de barras 220 kV por Conexion de la nueva UB-87B hacia la UC existente,Configuracion y Pruebas. | H14: 0 | I14: P | J14: E/S | K14: N | L14: P.ENERG | M14: 14765 | N14: T
B15: ATLANTICA TRANSMISION SUR S.A. | C15: MONTALVO | D15: BARRA B_500KV | E15: 26/04/2025 00:00 | F15: 27/04/2025 00:00 | G15: Proyecto Refuerzos: Indisponibilidad de la proteccion diferencial de barras 500kV por conexion de nueva UB-87B hacia la UC existente, Configuracion y Pruebas. | H15: 0 | I15: P | J15: E/S | K15: N | L15: P.ENERG | M15: 13871 | N15: T
B16: ATLANTICA TRANSMISION SUR S.A. | C16: MONTALVO | D16: CL-2057 | E16: 26/04/2025 00:00 | F16: 27/04/2025 00:00 | G16: Proyecto Refuerzos: Reemplazo del HMI existente, Pruebas y Configuracion. No se contara con nivel 1 de operacion. | H16: 0 | I16: P | J16: E/S | K16: N | L16: P.ENERG | M16: 13812 | N16: T
B17: ATLANTICA TRANSMISION SUR S.A. | C17: MONTALVO | D17: CL-AUT-5671_500 | E17: 26/04/2025 00:00 | F17: 27/04/2025 00:00 | G17: Proyecto Refuerzos: Reemplazo del HMI existente, Pruebas y Configuracion. No se contara con nivel 1 de operacion en INT-5671, INT-5652 y SAT-5671. | H17: 0 | I17: P | J17: E/S | K17: N | L17: P.ENERG | M17: 13809 | N17: T
B18: ATLANTICA TRANSMISION SUR S.A. | C18: MONTALVO | D18: INT-5652 | E18: 26/04/2025 00:00 | F18: 27/04/2025 00:00 | G18: Proyecto Refuerzos:Indisponible por Implementacion de conexion de corrientes, disparos, posiciones, enclavamientos hacia los equipos del nuevos Autotransformador. AUT-5671 en servicio solo por Barra A 500kV. | H18: 0 | I18: P | J18: F/S | K18: N | L18: P.ENERG | M18: 13765 | N18: T
... B163: TRANSMANTARO | C163: YARABAMBA | D163: IN-5120 | E163: 26/04/2025 00:00 | F163: 27/04/2025 00:00 | G163: INTERRUPTOR INDISPONIBLE POR FALLA EN LOS MANDOS DE CONTROL DE N1, N2 Y N3. | H163: 0 | I163: P | J163: F/S | K163: N | L163: OTROS | M163: 17437 | N163: T

Sheet INGRESO OC
A3: sábado, 26 de Abril del 2025
A5: INGRESO A OPERACIÓN COMERCIAL
A6: EMPRESA | B6: TIPO DE EQUIPO | C6: UBICACIÓN | D6: EQUIPO | E6: Fecha y hora de Ingreso a Operación Comercial

Sheet DESPACHO_EJECUTADO
B3: sábado, 26 de Abril del 2025
A5: POTENCIA ACTIVA EJECUTADA DE LAS UNIDADES DE GENERACIÓN DEL SEIN (MW) | FL5: CENTRALES NO INTEGRANTES COES
A6: FECHA | B6: HORA | C6: 337 | D6: 338 | E6: 65333 | F6: 101 | G6: 102 | H6: 42667 | I6: 42668 | J6: 126 | K6: 127 | L6: 138 | M6: 139 | N6: 197 | O6: 203 | P6: 204 | Q6: 230 | R6: 209 | S6: 56677 | T6: 796 | U6: 2146 | V6: 142 | W6: 143 | X6: 125 | Y6: 187 | Z6: 163 | AA6: 298 | AB6: 299 | AC6: 219 | AD6: 151 | AE6: 152 | AF6: 153 | AG6: 154 | AH6: 756 | AI6: 156 | AJ6: 155 | AK6: 182 | AL6: 212 | AM6: 758 | AN6: 263 | AO6: 265 | AP6: 775 | AQ6: 777 | AR6: 2154 | AS6: 150 | AT6: 149 | AU6: 188 | AV6: 2131 | AW6: 755 | AX6: 252 | AY6: 249 | AZ6: 250 | BA6: 117 | BB6: 267 | BC6: 268 | BD6: 119 | BE6: 120 | BF6: 189 | BG6: 122 | BH6: 266 | BI6: 251 | BJ6: 115 | BK6: 239 | BL6: 288 | BM6: 240 | BN6: 241 | BO6: 242 | BP6: 191 | BQ6: 194 | BR6: 196 | BS6: 207 | BT6: 236 | BU6: 795 | BV6: 285 | BW6: 995 | BX6: 996 | BY6: 997 | BZ6: 766 | CA6: 926 | CB6: 924 | CC6: 121 | CD6: 103 | CE6: 104 | CF6: 106 | CG6: 105 | CH6: 107 | CI6: 110 | CJ6: 109 | CK6: 144 | CL6: 113 | CM6: 114 | CN6: 193 | CO6: 208 | CP6: 786 | CQ6: 787 | CR6: 788 | CS6: 789 | CT6: 248 | CU6: 2159 | CV6: 303 | CW6: 59715 | CX6: 62255 | CY6: 1263 | CZ6: 61800 | DA6: 2194 | DB6: 216 | DC6: 198 | DD6: 49607 | DE6: 214 | DF6: 260 | DG6: 2152 | DH6: 2128 | DI6: 247 | DJ6: 228 | DK6: 2135 | DL6: 261 | DM6: 237 | DN6: 253 | DO6: 770 | DP6: 225 | DQ6: 2201 | DR6: 2171 | DS6: 760 | DT6: 235 | DU6: 238 | DV6: 2184 | DW6: 61855 | DX6: 223 | DY6: 226 | DZ6: 201 | EA6: 258 | EB6: 259 | EC6: 920 | ED6: 257 | EE6: 256 | EF6: 2148 | EG6: 58288 | EH6: 58289 | EI6: 58839 | EJ6: 58840 | EK6: 296 | EL6: 297 | EM6: 211 | EN6: 2175 | EO6: 2178 | EP6: 2181 | EQ6: 1262 | ER6: 63425 | ES6: 233 | ET6: 2150 | EU6: 2165 | EV6: 2161 | EW6: 61197 | EX6: 58851 | EY6: 234 | EZ6: 215 | FA6: 917 | FB6: 289 | FC6: 58333 | FD6: 58336 | FE6: 202 | FF6: 58487 | FG6: 213 | FH6: 232 | FI6: 2190 | FJ6: TOTAL COES | FL6: 221 | FM6: 222 | FN6: 224 | FO6: 2187 | FP6: 227 | FQ6: 49400 | FR6: 199 | FS6: 200 | FT6: TOTAL NO COES
C7: CENTRO | D7: CENTRO | E7: SUR | F7: CENTRO | G7: CENTRO | H7: NORTE | I7: NORTE | J7: NORTE | K7: NORTE | L7: CENTRO | M7: CENTRO | N7: CENTRO | O7: CENTRO | P7: CENTRO | Q7: CENTRO | R7: CENTRO | S7: CENTRO | T7: CENTRO | U7: CENTRO | V7: CENTRO | W7: CENTRO | X7: CENTRO | Y7: CENTRO | Z7: SUR | AA7: SUR | AB7: SUR | AC7: CENTRO | AD7: SUR | AE7: SUR | AF7: SUR | AG7: SUR | AH7: SUR | AI7: SUR | AJ7: SUR | AK7: SUR | AL7: CENTRO | AM7: NORTE | AN7: NORTE | AO7: NORTE | AP7: CENTRO | AQ7: CENTRO | AR7: CENTRO | AS7: CENTRO | AT7: CENTRO | AU7: CENTRO | AV7: CENTRO | AW7: SUR | AX7: CENTRO | AY7: CENTRO | AZ7: CENTRO | BA7: CENTRO | BB7: CENTRO | BC7: CENTRO | BD7: CENTRO | BE7: CENTRO | BF7: SUR | BG7: NORTE | BH7: CENTRO | BI7: CENTRO | BJ7: NORTE | BK7: NORTE | BL7: NORTE | BM7: SUR | BN7: SUR | BO7: SUR | BP7: CENTRO | BQ7: CENTRO | BR7: CENTRO | BS7: CENTRO | BT7: CENTRO | BU7: CENTRO | BV7: CENTRO | BW7: SUR | BX7: SUR | BY7: SUR | BZ7: NORTE | CA7: SUR | CB7: CENTRO | CC7: NORTE | CD7: CENTRO | CE7: CENTRO | CF7: CENTRO | CG7: CENTRO | CH7: CENTRO | CI7: CENTRO | CJ7: CENTRO | CK7: CENTRO | CL7: CENTRO | CM7: CENTRO | CN7: CENTRO | CO7: CENTRO | CP7: SUR | CQ7: SUR | CR7: SUR | CS7: SUR | CT7: CENTRO | CU7: CENTRO | CV7: CENTRO | CW7: CENTRO | CX7: SUR | CY7: NORTE | CZ7: NORTE | DA7: NORTE | DB7: NORTE | DC7: NORTE | DD7: SUR | DE7: CENTRO | DF7: CENTRO | DG7: CENTRO | DH7: NORTE | DI7: NORTE | DJ7: CENTRO | DK7: CENTRO | DL7: SUR | DM7: SUR | DN7: CENTRO | DO7: CENTRO | DP7: CENTRO | DQ7: CENTRO | DR7: CENTRO | DS7: CENTRO | DT7: SUR | DU7: CENTRO | DV7: CENTRO | DW7: NORTE | DX7: CENTRO | DY7: CENTRO | DZ7: NORTE | EA7: CENTRO | EB7: CENTRO | EC7: CENTRO | ED7: NORTE | EE7: NORTE | EF7: SUR | EG7: CENTRO | EH7: CENTRO | EI7: CENTRO | EJ7: CENTRO | EK7: CENTRO | EL7: CENTRO | EM7: SUR | EN7: SUR | EO7: SUR | EP7: SUR | EQ7: NORTE | ER7: SUR | ES7: SUR | ET7: SUR | EU7: CENTRO | EV7: CENTRO | EW7: CENTRO | EX7: SUR | EY7: SUR | EZ7: NORTE | FA7: CENTRO | FB7: NORTE | FC7: NORTE | FD7: NORTE | FE7: CENTRO | FF7: CENTRO | FG7: CENTRO | FH7: NORTE | FI7: NORTE | FL7: NORTE | FM7: CENTRO | FN7: NORTE | FO7: NORTE | FP7: NORTE | FQ7: NORTE | FR7: NORTE | FS7: NORTE
C8: HIDROELÉCTRICA | D8: HIDROELÉCTRICA | E8: HIDROELÉCTRICA | F8: HIDROELÉCTRICA | G8: HIDROELÉCTRICA | H8: TERMOELÉCTRICA | I8: TERMOELÉCTRICA | J8: HIDROELÉCTRICA | K8: HIDROELÉCTRICA | L8: TERMOELÉCTRICA | M8: TERMOELÉCTRICA | N8: TERMOELÉCTRICA | O8: TERMOELÉCTRICA | P8: TERMOELÉCTRICA | Q8: TERMOELÉCTRICA | R8: TERMOELÉCTRICA | S8: TERMOELÉCTRICA | T8: HIDROELÉCTRICA | U8: HIDROELÉCTRICA | V8: TERMOELÉCTRICA | W8: TERMOELÉCTRICA | X8: TERMOELÉCTRICA | Y8: TERMOELÉCTRICA | Z8: HIDROELÉCTRICA | AA8: HIDROELÉCTRICA | AB8: HIDROELÉCTRICA | AC8: TERMOELÉCTRICA | AD8: HIDROELÉCTRICA | AE8: HIDROELÉCTRICA | AF8: HIDROELÉCTRICA | AG8: HIDROELÉCTRICA | AH8: TERMOELÉCTRICA | AI8: TERMOELÉCTRICA | AJ8: TERMOELÉCTRICA | AK8: HIDROELÉCTRICA | AL8: HIDROELÉCTRICA | AM8: TERMOELÉCTRICA | AN8: TERMOELÉCTRICA | AO8: TERMOELÉCTRICA | AP8: HIDROELÉCTRICA | AQ8: HIDROELÉCTRICA | AR8: HIDROELÉCTRICA | AS8: HIDROELÉCTRICA | AT8: HIDROELÉCTRICA | AU8: HIDROELÉCTRICA | AV8: HIDROELÉCTRICA | AW8: HIDROELÉCTRICA | AX8: TERMOELÉCTRICA | AY8: TERMOELÉCTRICA | AZ8: TERMOELÉCTRICA | BA8: HIDROELÉCTRICA | BB8: HIDROELÉCTRICA | BC8: HIDROELÉCTRICA | BD8: HIDROELÉCTRICA | BE8: HIDROELÉCTRICA | BF8: HIDROELÉCTRICA | BG8: HIDROELÉCTRICA | BH8: HIDROELÉCTRICA | BI8: HIDROELÉCTRICA | BJ8: TERMOELÉCTRICA | BK8: TERMOELÉCTRICA | BL8: TERMOELÉCTRICA | BM8: TERMOELÉCTRICA | BN8: TERMOELÉCTRICA | BO8: TERMOELÉCTRICA | BP8: HIDROELÉCTRICA | BQ8: TERMOELÉCTRICA | BR8: TERMOELÉCTRICA | BS8: TERMOELÉCTRICA | BT8: TERMOELÉCTRICA | BU8: TERMOELÉCTRICA | BV8: TERMOELÉCTRICA | BW8: TERMOELÉCTRICA | BX8: TERMOELÉCTRICA | BY8: TERMOELÉCTRICA | BZ8: HIDROELÉCTRICA | CA8: TERMOELÉCTRICA | CB8: TERMOELÉCTRICA | CC8: HIDROELÉCTRICA | CD8: HIDROELÉCTRICA | CE8: HIDROELÉCTRICA | CF8: HIDROELÉCTRICA | CG8: HIDROELÉCTRICA | CH8: HIDROELÉCTRICA | CI8: TERMOELÉCTRICA | CJ8: TERMOELÉCTRICA | CK8: TERMOELÉCTRICA | CL8: TERMOELÉCTRICA | CM8: TERMOELÉCTRICA | CN8: TERMOELÉCTRICA | CO8: TERMOELÉCTRICA | CP8: TERMOELÉCTRICA | CQ8: TERMOELÉCTRICA | CR8: TERMOELÉCTRICA | CS8: TERMOELÉCTRICA | CT8: TERMOELÉCTRICA | CU8: TERMOELÉCTRICA | CV8: SOLAR | CW8: EÓLICA | CX8: SOLAR | CY8: EÓLICA | CZ8: SOLAR | DA8: HIDROELÉCTRICA | DB8: HIDROELÉCTRICA | DC8: HIDROELÉCTRICA | DD8: HIDROELÉCTRICA | DE8: HIDROELÉCTRICA | DF8: HIDROELÉCTRICA | DG8: HIDROELÉCTRICA | DH8: HIDROELÉCTRICA | DI8: HIDROELÉCTRICA | DJ8: HIDROELÉCTRICA | DK8: HIDROELÉCTRICA | DL8: SOLAR | DM8: SOLAR | DN8: EÓLICA | DO8: EÓLICA | DP8: TERMOELÉCTRICA | DQ8: TERMOELÉCTRICA | DR8: TERMOELÉCTRICA | DS8: TERMOELÉCTRICA | DT8: SOLAR | DU8: HIDROELÉCTRICA | DV8: HIDROELÉCTRICA | DW8: HIDROELÉCTRICA | DX8: HIDROELÉCTRICA | DY8: HIDROELÉCTRICA | DZ8: HIDROELÉCTRICA | EA8: HIDROELÉCTRICA | EB8: HIDROELÉCTRICA | EC8: HIDROELÉCTRICA | ED8: EÓLICA | EE8: EÓLICA | EF8: SOLAR | EG8: EÓLICA | EH8: EÓLICA | EI8: EÓLICA | EJ8: EÓLICA | EK8: HIDROELÉCTRICA | EL8: HIDROELÉCTRICA | EM8: HIDROELÉCTRICA | EN8: HIDROELÉCTRICA | EO8: HIDROELÉCTRICA | EP8: HIDROELÉCTRICA | EQ8: EÓLICA | ER8: SOLAR | ES8: SOLAR | ET8: SOLAR | EU8: HIDROELÉCTRICA | EV8: EÓLICA | EW8: EÓLICA | EX8: SOLAR | EY8: SOLAR | EZ8: HIDROELÉCTRICA | FA8: HIDROELÉCTRICA | FB8: TERMOELÉCTRICA | FC8: TERMOELÉCTRICA | FD8: TERMOELÉCTRICA | FE8: TERMOELÉCTRICA | FF8: TERMOELÉCTRICA | FG8: TERMOELÉCTRICA | FH8: TERMOELÉCTRICA | FI8: TERMOELÉCTRICA | FL8: HIDROELÉCTRICA | FM8: HIDROELÉCTRICA | FN8: HIDROELÉCTRICA | FO8: HIDROELÉCTRICA | FP8: TERMOELÉCTRICA | FQ8: TERMOELÉCTRICA | FR8: HIDROELÉCTRICA | FS8: HIDROELÉCTRICA
C9: CENTRALES SANTA ROSA S.A.C. | D9: CENTRALES SANTA ROSA S.A.C. | E9: HYDRO GLOBAL PERÚ S.A.C. | F9: ELECTROPERU | G9: ELECTROPERU | H9: ELECTROPERU | I9: ELECTROPERU | J9: ORAZUL ENERGY PERÚ | K9: ORAZUL ENERGY PERÚ | L9: TERMOSELVA | M9: TERMOSELVA | N9: KALLPA GENERACION S.A. | O9: KALLPA GENERACION S.A. | P9: KALLPA GENERACION S.A. | Q9: KALLPA GENERACION S.A. | R9: KALLPA GENERACION S.A. | S9: KALLPA GENERACION S.A. | T9: KALLPA GENERACION S.A. | U9: KALLPA GENERACION S.A. | V9: SHOUGESA | W9: SHOUGESA | X9: SHOUGESA | Y9: SHOUGESA | Z9: EGEMSA | AA9: EGESUR | AB9: EGESUR | AC9: EGESUR | AD9: EGASA | AE9: EGASA | AF9: EGASA | AG9: EGASA | AH9: EGASA | AI9: EGASA | AJ9: EGASA | AK9: SAN GABAN | AL9: CELEPSA | AM9: MINERA CERRO VERDE | AN9: PLANTA DE RESERVA FRIA DE GENERACION DE ETEN S.A. | AO9: PLANTA DE RESERVA FRIA DE GENERACION DE ETEN S.A. | AP9: EMPRESA DE GENERACION HUALLAGA | AQ9: EMPRESA DE GENERACION HUALLAGA | AR9: LA VIRGEN | AS9: CHINANGO S.A.C. | AT9: CHINANGO S.A.C. | AU9: HIDROELECTRICA HUANCHOR S.A.C. | AV9: CELEPSA RENOVABLES S.R.L. | AW9: INLAND ENERGY SAC | AX9: FENIX POWER PERÚ | AY9: FENIX POWER PERÚ | AZ9: FENIX POWER PERÚ | BA9: STATKRAFT S.A | BB9: STATKRAFT S.A | BC9: STATKRAFT S.A | BD9: STATKRAFT S.A | BE9: STATKRAFT S.A | BF9: STATKRAFT S.A | BG9: STATKRAFT S.A | BH9: STATKRAFT S.A | BI9: EMPRESA DE GENERACION HUANZA | BJ9: ENEL GENERACION PIURA S.A. | BK9: ENEL GENERACION PIURA S.A. | BL9: ENEL GENERACION PIURA S.A. | BM9: ENGIE | BN9: ENGIE | BO9: ENGIE | BP9: ENGIE | BQ9: ENGIE | BR9: ENGIE | BS9: ENGIE | BT9: ENGIE | BU9: ENGIE | BV9: ENGIE | BW9: ENGIE | BX9: ENGIE | BY9: ENGIE | BZ9: ENGIE | CA9: INFRAESTRUCTURAS Y ENERGIAS DEL PERU S.A.C. | CB9: INFRAESTRUCTURAS Y ENERGIAS DEL PERU S.A.C. | CC9: INVERSIONES SHAQSHA S.A.C. | CD9: ORYGEN PERU S.A.A. | CE9: ORYGEN PERU S.A.A. | CF9: ORYGEN PERU S.A.A. | CG9: ORYGEN PERU S.A.A. | CH9: ORYGEN PERU S.A.A. | CI9: ORYGEN PERU S.A.A. | CJ9: ORYGEN PERU S.A.A. | CK9: ORYGEN PERU S.A.A. | CL9: ORYGEN PERU S.A.A. | CM9: ORYGEN PERU S.A.A. | CN9: ORYGEN PERU S.A.A. | CO9: ORYGEN PERU S.A.A. | CP9: SAMAY I S.A.C | CQ9: SAMAY I S.A.C | CR9: SAMAY I S.A.C | CS9: SAMAY I S.A.C | CT9: TERMOCHILCA S.A.C. | CU9: TERMOCHILCA S.A.C. | CV9: COLCA SOLAR S.A.C. | CW9: ENERGIA RENOVABLE DEL SUR S.A. | CX9: GR CORTARRAMA SOCIEDAD ANONIMA CERRADA | CY9: GR TARUCA SOCIEDAD ANONIMA CERRADA | CZ9: KONDU SAC | DA9: PERUANA DE INVERSIONES EN ENERGIAS RENOVABLES S.A. | DB9: ORAZUL ENERGY PERÚ | DC9: ORAZUL ENERGY PERÚ | DD9: SAN GABAN | DE9: MAJA ENERGIA S.A.C. | DF9: EMPRESA DE GENERACION ELECTRICA CANCHAYLLO SAC | DG9: EMPRESA DE GENERACION ELECTRICA SANTA ANA S.A.C. | DH9: EMPRESA ELECTRICA AGUA AZUL | DI9: EMPRESA ELECTRICA RIO DOBLE | DJ9: HIDROCAÑETE S.A. | DK9: HUAURA POWER GROUP S.A. | DL9: MOQUEGUA FV S.A.C. | DM9: PANAMERICANA SOLAR SAC. | DN9: PARQUE EOLICO MARCONA S.A.C. | DO9: PARQUE EOLICO TRES HERMANAS S.A.C. | DP9: PETRAMAS | DQ9: PETRAMAS | DR9: PETRAMAS | DS9: PETRAMAS | DT9: TACNA SOLAR SAC. | DU9: ELECTRICA YANAPAMPA SAC | DV9: ANDEAN POWER S.A.C. | DW9: ASOCIACIÓN SANTA LUCIA DE CHACAS | DX9: ATRIA ENERGIA S.A.C. | DY9: EGEJUNIN | DZ9: EGEJUNIN | EA9: EGEJUNIN | EB9: EGEJUNIN | EC9: EMPRESA DE GENERACION ELECTRICA RIO BAÑOS S.A.C. | ED9: ENERGÍA EÓLICA S.A. | EE9: ENERGÍA EÓLICA S.A. | EF9: ENGIE | EG9: ENGIE | EH9: ENGIE | EI9: ENGIE | EJ9: ENGIE | EK9: GENERACIÓN ANDINA S.A.C. | EL9: GENERACIÓN ANDINA S.A.C. | EM9: GENERADORA DE ENERGÍA DEL PERÚ | EN9: GENERADORA DE ENERGÍA DEL PERÚ | EO9: GENERADORA DE ENERGÍA DEL PERÚ | EP9: GENERADORA DE ENERGÍA DEL PERÚ | EQ9: GR PAINO SOCIEDAD ANONIMA CERRADA | ER9: JOYA SOLAR S.A.C. | ES9: MAJES ARCUS S.A.C. | ET9: ORYGEN PERU S.A.A. | EU9: ORYGEN PERU S.A.A. | EV9: ORYGEN PERU S.A.A. | EW9: ORYGEN PERU S.A.A. | EX9: ORYGEN PERU S.A.A. | EY9: REPARTICIÓN ARCUS S.A.C. | EZ9: SINERSA | FA9: SINERSA | FB9: BIOENERGIA DEL CHIRA S.A. | FC9: GM OPERACIONES S.A.C. | FD9: GM OPERACIONES S.A.C. | FE9: SDF ENERGIA SAC | FF9: SDF ENERGIA SAC | FG9: AGRO INDUSTRIAL PARAMONGA S.A. | FH9: AGROAURORA S.A.C. | FI9: AGROINDUSTRIAS SAN JACINTO S.A.A. | FL9: UNACEM PERU S.A. | FM9: ELECTRO ORIENTE | FN9: AGUAS Y ENERGIA PERU | FO9: ELECTRO ZAÑA S.A.C. | FP9: ELECTRONOROESTE S.A. | FQ9: SDE PIURA | FR9: SINERSA | FS9: SINERSA
C10: SANTA ROSA 1 | D10: SANTA ROSA 2 | E10: SAN GABAN III | F10: MANTARO | G10: RESTITUCION | H10: TUMBES MAK 1 | I10: TUMBES MAK 2 | J10: CARHUAQUERO | K10: CAÑON DEL PATO | L10: AGUAYTIA TG1 | M10: AGUAYTIA TG2 | N10: KALLPA TG1 | O10: KALLPA TG2 | P10: KALLPA TG3 | Q10: KALLPA TV | R10: LFLORES TG1 | S10: LFLORES TV | T10: CERRO DEL AGUILA | U10: CERRODELAGUILAG4 | V10: SHOUGESA TV1 | W10: SHOUGESA TV2 | X10: SHOUGESA TV3 | Y10: SHOUGESA CUMMINS | Z10: MACHUPICCHU | AA10: ARICOTA 1 | AB10: ARICOTA 2 | AC10: INDEPENDENCIA | AD10: CHARCANI I,II,III | AE10: CHARCANI IV | AF10: CHARCANI V | AG10: CHARCANI VI | AH10: CHILINA TG | AI10: MOLLENDO 1, 2, 3 | AJ10: CHILINA (SULZ 1,2) | AK10: SAN GABAN II | AL10: PLATANAL | AM10: RECKA | AN10: RF ETEN TG1 | AO10: RF ETEN TG2 | AP10: CHAGLLA GP1 | AQ10: CHAGLLA | AR10: LA VIRGEN | AS10: CHIMAY | AT10: YANANGO | AU10: HUANCHOR | AV10: MARAÑON | AW10: STA TERESA | AX10: FENIX GT11 | AY10: FENIX GT12 | AZ10: FENIX TV10 | BA10: YAUPI | BB10: OROYA | BC10: PACHACHACA | BD10: MALPASO | BE10: CAHUA | BF10: ARCATA | BG10: GALLITO CIEGO | BH10: CHEVES | BI10: HUANZA | BJ10: MALACAS2 TG4 | BK10: MALACAS3 TG 5 | BL10: MALACAS1 TG6 | BM10: RF ILO2 TG1 | BN10: RF ILO2 TG2 | BO10: RF ILO2 TG3 | BP10: YUNCAN | BQ10: CHILCA1 TG1 | BR10: CHILCA1 TG2 | BS10: CHILCA1 TG3 | BT10: CHILCA-TV | BU10: CHILCA2 TG41 | BV10: CHILCA2-TV | BW10: CTNEPI_TG41 | BX10: CTNEPI_TG42 | BY10: CTNEPI_TG43 | BZ10: QUITARACSA | CA10: RF PTO MALDONADO | CB10: RF PUCALLPA | CC10: PARIAC | CD10: HUINCO | CE10: MATUCANA | CF10: MOYOPAMPA | CG10: CALLAHUANCA | CH10: HUAMPANI | CI10: STA ROSA WEST TG7 | CJ10: UTI_5 | CK10: UTI_6 | CL10: VENTANILLA 3 | CM10: VENTANILLA 4 | CN10: VENTANILLA TV | CO10: STAROSA TG8 | CP10: PTO_BRVO TG1 | CQ10: PTO_BRVO TG2 | CR10: PTO_BRVO TG3 | CS10: PTO_BRVO TG4 | CT10: OLLEROS TG1 | CU10: OLLEROS TV | CV10: CS YARUCAYA | CW10: SAN JUAN | CX10: MATARANI | CY10: DUNA | CZ10: CARHUAQUERO (CS) | DA10: MANTA I | DB10: CARHUAQUERO4 | DC10: CAÑA BRAVA | DD10: TUPURI | DE10: RONCADOR | DF10: CANCHAYLLO | DG10: RENOVANDESH1 | DH10: POTRERO | DI10: PIZARRAS | DJ10: NIMPERIAL | DK10: YARUCAYA | DL10: MOQUEGUA-SOLAR | DM10: PANAMERICANA-SOLAR | DN10: PQE-EOLICO-MARCONA | DO10: PQE-EOLICO-3-HERMANAS | DP10: HUAYCOLORO | DQ10: CALLAO | DR10: DONA_CATALINA | DS10: LAGRINGAV | DT10: TACNA-SOLAR | DU10: YANAPAMPA | DV10: CARHUAC | DW10: HUALLIN | DX10: PURMACANA | DY10: HUASAHUASI | DZ10: STACRUZ_1_2 | EA10: RUNATULLO_II | EB10: RUNATULLO_III | EC10: RUCUY | ED10: PQE-EOLICO-TALARA | EE10: PQE-EOLICO-CUPISNIQUE | EF10: INTIPAMPA | EG10: PUNTA LOMITAS-BL1 | EH10: PUNTA LOMITAS-BL2 | EI10: PUN LOMITAS_EXP-BL1 | EJ10: PUN LOMITAS_EXP-BL2 | EK10: 8AGOSTO | EL10: EL CARMEN | EM10: LA JOYA | EN10: ANGEL_I | EO10: ANGEL_II | EP10: ANGEL_III | EQ10: HUAMBOS | ER10: SAN MARTIN SOLAR | ES10: MAJES | ET10: RUBI | EU10: CH_HER1 | EV10: WAYRA-I | EW10: WAYRA EXTENSION | EX10: CLEMESI | EY10: REPARTICION | EZ10: POECHOS2 | FA10: CHANCAY | FB10: CANA BRAVA | FC10: REFINERIA TALARA TV1 | FD10: REFINERÍA TALARA TV2 | FE10: OQUENDO TG1 | FF10: OQUENDO TV1 | FG10: PARAMONGA | FH10: MAPLE | FI10: SAN_JACINTO | FJ10: MW | FL10: CARPAPATA | FM10: CENTRALES ELOR | FN10: PIAS1 | FO10: ZANA | FP10: TABLAZO | FQ10: TALLANCA | FR10: CURUMUY | FS10: POECHOS1 | FT10: MW
A11: 26/04/2025 | B11: 00:30 | E11: 102.55 | F11: 647.6 | G11: 214.9 | J11: 89.7 | K11: 167.3 | N11: 111.8 | O11: 111.7 | P11: 112.3 | Q11: 210.5 | R11: 110 | S11: 67.7 | T11: 559.5 | U11: 10.5 | Z11: 165.5 | AA11: 7.5 | AB11: 3.7 | AD11: 6.7 | AE11: 10.1 | AF11: 85 | AG11: 6.3 | AK11: 110.9 | AL11: 224.2 | AP11: 6.5 | AQ11: 466.5 | AR11: 76.6 | AS11: 148.6 | AT11: 42.4 | AU11: 18.7 | AV11: 19.7 | AW11: 89.6 | AX11: 0 | AZ11: 0 | BA11: 108.3 | BB11: 7.8 | BC11: 5.8 | BD11: 45.8 | BE11: 22.4 | BF11: 3.8 | BG11: 38.6 | BH11: 174.2 | BI11: 72.7 | BL11: 48.8 | BP11: 86.4 | BQ11: 92.6 | BR11: 0 | BS11: 101.3 | BT11: 125.1 | CC11: 4.6 | CD11: 218 | CE11: 129.5 | CF11: 65 | CG11: 80.4 | CH11: 30.1 | CL11: 103.8 | CM11: 103.9 | CN11: 121.4 | CV11: 0 | CW11: 95.8 | CX11: 0 | CY11: 0.8 | CZ11: 0 | DA11: 0 | DB11: 9.9 | DC11: 5.6 | DD11: 1.2 | DE11: 3.4 | DF11: 4.8 | DG11: 20.2 | DH11: 10.3 | DI11: 10.2 | DJ11: 3.6 | DK11: 9.3 | DL11: 0 | DM11: 0 | DN11: 25.2 | DO11: 68.6 | DP11: 4.4 | DQ11: 1.9 | DR11: 2.4 | DT11: 0 | DU11: 2.4 | DV11: 20.4 | DW11: 0 | DX11: 0 | DY11: 19.8 | DZ11: 9.7 | EA11: 16.1 | EB11: 20.3 | EC11: 20 | ED11: 4.9 | EE11: 36.7 | EF11: 0 | EG11: 66.2 | EH11: 90.5 | EI11: 9.6 | EJ11: 1.6 | EK11: 20.9 | EL11: 8.3 | EM11: 8.3 | EN11: 20.4 | EO11: 20.4 | EP11: 20.2 | EQ11: 1.2 | ER11: 0 | ES11: 0 | ET11: 0 | EU11: 0.6 | EV11: 40.5 | EW11: 29 | EX11: 0 | EY11: 0 | EZ11: 9.2 | FA11: 20 | FC11: 37.2 | FE11: 29.4 | FF11: 3.4 | FG11: 15 | FJ11: 6674.65 | FL11: 23.54426 | FM11: 0.631 | FO11: 13.16234 | FQ11: 18.91596 | FR11: 10.1 | FS11: 16.1 | FT11: 82.45356
A12: 26/04/2025 | B12: 01:00 | E12: 102.91 | F12: 647.3 | G12: 214.9 | J12: 75.4 | K12: 229.5 | N12: 99.8 | O12: 108 | P12: 108.2 | Q12: 207.8 | R12: 110.2 | S12: 67.2 | T12: 558.3 | U12: 10.5 | Z12: 163.7 | AA12: 7.4 | AB12: 3.7 | AD12: 6.7 | AE12: 10.1 | AF12: 85.5 | AG12: 6.3 | AK12: 111 | AL12: 223.5 | AP12: 6.5 | AQ12: 451.6 | AR12: 76 | AS12: 147 | AT12: 42.4 | AU12: 18.7 | AV12: 19.7 | AW12: 90 | AX12: 0 | AZ12: 0 | BA12: 108.6 | BB12: 7.5 | BC12: 5.8 | BD12: 45.8 | BE12: 22.4 | BF12: 3.8 | BG12: 38.4 | BH12: 174.5 | BI12: 22.5 | BL12: 48.7 | BP12: 86.5 | BQ12: 79.9 | BR12: 0 | BS12: 79.4 | BT12: 105.5 | CC12: 4.6 | CD12: 202.3 | CE12: 128.3 | CF12: 65 | CG12: 78.4 | CH12: 30.3 | CL12: 103.7 | CM12: 103.1 | CN12: 120.4 | CV12: 0 | CW12: 101.2 | CX12: 0 | CY12: 1.2 | CZ12: 0 | DA12: 0 | DB12: 9.9 | DC12: 5.4 | DD12: 1.2 | DE12: 3.4 | DF12: 5 | DG12: 20.4 | DH12: 10.9 | DI12: 10 | DJ12: 2.9 | DK12: 9.3 | DL12: 0 | DM12: 0 | DN12: 30.7 | DO12: 73.5 | DP12: 4.4 | DQ12: 1.9 | DR12: 2.4 | DT12: 0 | DU12: 2.4 | DV12: 16.8 | DW12: 0 | DX12: 0 | DY12: 19.8 | DZ12: 9.7 | EA12: 16.1 | EB12: 20.3 | EC12: 20 | ED12: 6.5 | EE12: 38.5 | EF12: 0 | EG12: 62.1 | EH12: 90.1 | EI12: 6.1 | EJ12: 0.2 | EK12: 20.9 | EL12: 8.3 | EM12: 8.3 | EN12: 20.4 | EO12: 20.4 | EP12: 20.2 | EQ12: 1 | ER12: 0 | ES12: 0 | ET12: 0 | EU12: 0.6 | EV12: 38.8 | EW12: 29.8 | EX12: 0 | EY12: 0 | EZ12: 9.2 | FA12: 20 | FC12: 38 | FE12: 29.4 | FF12: 3.4 | FG12: 15.1 | FJ12: 6561.31 | FL12: 23.54689 | FM12: 0 | FO12: 13.1761 | FQ12: 18.91529 | FR12: 10 | FS12: 16 | FT12: 81.63828
A13: 26/04/2025 | B13: 01:30 | E13: 104.04 | F13: 646.9 | G13: 214.5 | J13: 89.8 | K13: 229.6 | N13: 99.9 | O13: 108.8 | P13: 109 | Q13: 207.2 | R13: 109.1 | S13: 67.3 | T13: 558.6 | U13: 10.5 | Z13: 162.6 | AA13: 7.2 | AB13: 3.7 | AD13: 6.7 | AE13: 10.1 | AF13: 85.1 | AG13: 6.3 | AK13: 110.9 | AL13: 223.3 | AP13: 6.4 | AQ13: 368.4 | AR13: 76.5 | AS13: 134.8 | AT13: 42.5 | AU13: 18.7 | AV13: 19.7 | AW13: 89.3 | AX13: 0 | AZ13: 0 | BA13: 108.3 | BB13: 7.6 | BC13: 5.8 | BD13: 45.6 | BE13: 22.5 | BF13: 3.8 | BG13: 37.7 | BH13: 173.4 | BI13: 22.3 | BL13: 32.6 | BP13: 86.5 | BQ13: 85 | BR13: 0 | BS13: 84.4 | BT13: 107.5 | CC13: 4.6 | CD13: 186.4 | CE13: 117.5 | CF13: 65 | CG13: 78.4 | CH13: 30.2 | CL13: 104 | CM13: 104.3 | CN13: 120.8 | CV13: 0 | CW13: 107.7 | CX13: 0 | CY13: 0.5 | CZ13: 0 | DA13: 0 | DB13: 9.9 | DC13: 5.5 | DD13: 1.2 | DE13: 3.4 | DF13: 5 | DG13: 20.2 | DH13: 11.3 | DI13: 9.9 | DJ13: 3 | DK13: 9.3 | DL13: 0 | DM13: 0 | DN13: 30.4 | DO13: 75.5 | DP13: 0 | DQ13: 2 | DR13: 2.3 | DT13: 0 | DU13: 2.4 | DV13: 9.9 | DW13: 0 | DX13: 0 | DY13: 19.8 | DZ13: 9.7 | EA13: 16.1 | EB13: 20.3 | EC13: 20 | ED13: 13.7 | EE13: 48.2 | EF13: 0 | EG13: 58.7 | EH13: 93 | EI13: 6 | EJ13: 0.2 | EK13: 20.9 | EL13: 8.3 | EM13: 8.3 | EN13: 20.4 | EO13: 20.4 | EP13: 20.2 | EQ13: 0.1 | ER13: 0 | ES13: 0 | ET13: 0 | EU13: 0.6 | EV13: 35 | EW13: 24.2 | EX13: 0 | EY13: 0 | EZ13: 9.2 | FA13: 20 | FC13: 38.6 | FE13: 29.4 | FF13: 3.4 | FG13: 15 | FJ13: 6450.74 | FL13: 23.54199 | FM13: 0 | FO13: 13.17016 | FQ13: 18.91479 | FR13: 10.2 | FS13: 16 | FT13: 81.82694
A14: 26/04/2025 | B14: 02:00 | E14: 103.12 | F14: 647.3 | G14: 214.5 | J14: 90.6 | K14: 229.3 | N14: 99.7 | O14: 108.9 | P14: 108.7 | Q14: 207 | R14: 109.8 | S14: 67.6 | T14: 559.2 | U14: 10.5 | Z14: 165.7 | AA14: 7.4 | AB14: 3.7 | AD14: 6.7 | AE14: 10.1 | AF14: 85 | AG14: 6.3 | AK14: 111.1 | AL14: 223.5 | AP14: 6.4 | AQ14: 392.5 | AR14: 77 | AS14: 139.3 | AT14: 42.4 | AU14: 18.7 | AV14: 19.5 | AW14: 89.4 | AX14: 0 | AZ14: 0 | BA14: 109 | BB14: 7.6 | BC14: 5.8 | BD14: 46.3 | BE14: 22.6 | BF14: 3.8 | BG14: 38.1 | BH14: 174.5 | BI14: 22.6 | BL14: 25 | BP14: 86.5 | BQ14: 84.5 | BR14: 0 | BS14: 84.1 | BT14: 108.4 | CC14: 4.6 | CD14: 88.5 | CE14: 121.5 | CF14: 65.2 | CG14: 78.2 | CH14: 30.3 | CL14: 103.7 | CM14: 103.6 | CN14: 120.1 | CV14: 0 | CW14: 110 | CX14: 0 | CY14: 0.4 | CZ14: 0 | DA14: 0 | DB14: 9.9 | DC14: 5.5 | DD14: 1.2 | DE14: 3.4 | DF14: 4.9 | DG14: 20.4 | DH14: 12.8 | DI14: 9.9 | DJ14: 3.4 | DK14: 9.3 | DL14: 0 | DM14: 0 | DN14: 31 | DO14: 77.1 | DP14: 0 | DQ14: 2 | DR14: 2.3 | DT14: 0 | DU14: 2.4 | DV14: 10.2 | DW14: 0 | DX14: 0 | DY14: 19.8 | DZ14: 9.7 | EA14: 16 | EB14: 20.3 | EC14: 20 | ED14: 12.3 | EE14: 39.6 | EF14: 0 | EG14: 56.2 | EH14: 89 | EI14: 4.3 | EJ14: 1.2 | EK14: 20.9 | EL14: 8.3 | EM14: 8.5 | EN14: 20.4 | EO14: 20.4 | EP14: 20.2 | EQ14: 0.3 | ER14: 0 | ES14: 0 | ET14: 0 | EU14: 0.6 | EV14: 35.7 | EW14: 29 | EX14: 0 | EY14: 0 | EZ14: 9.2 | FA14: 20 | FC14: 38.7 | FE14: 29.4 | FF14: 3.4 | FG14: 15 | FJ14: 6379.92 | FL14: 23.54262 | FM14: 0 | FO14: 13.1715 | FQ14: 18.91437 | FR14: 10.2 | FS14: 15.9 | FT14: 81.72849
A15: 26/04/2025 | B15: 02:30 | E15: 103.47 | F15: 647.2 | G15: 214.7 | J15: 90.2 | K15: 229 | N15: 99.8 | O15: 109.3 | P15: 109.5 | Q15: 207 | R15: 109.9 | S15: 66.8 | T15: 560 | U15: 0 | Z15: 165.6 | AA15: 7.3 | AB15: 3.7 | AD15: 6.7 | AE15: 10.1 | AF15: 85.4 | AG15: 6.3 | AK15: 110.9 | AL15: 223.2 | AP15: 6.5 | AQ15: 305.6 | AR15: 77 | AS15: 126 | AT15: 42.5 | AU15: 18.7 | AV15: 19.1 | AW15: 91.4 | AX15: 0 | AZ15: 0 | BA15: 108.4 | BB15: 7.5 | BC15: 5.9 | BD15: 45.6 | BE15: 22.4 | BF15: 3.8 | BG15: 38 | BH15: 173.9 | BI15: 22.4 | BL15: 25.1 | BP15: 86.5 | BQ15: 85.1 | BR15: 0 | BS15: 85 | BT15: 108.6 | CC15: 4.6 | CD15: 120 | CE15: 110.2 | CF15: 65 | CG15: 78.4 | CH15: 30.2 | CL15: 104 | CM15: 104 | CN15: 120.8 | CV15: 0 | CW15: 110.3 | CX15: 0 | CY15: 0.7 | CZ15: 0 | DA15: 0 | DB15: 9.9 | DC15: 5.4 | DD15: 1.2 | DE15: 3.4 | DF15: 4.9 | DG15: 20.2 | DH15: 16.4 | DI15: 9.8 | DJ15: 3.5 | DK15: 9.3 | DL15: 0 | DM15: 0 | DN15: 31.5 | DO15: 78.6 | DP15: 0 | DQ15: 2 | DR15: 2.3 | DT15: 0 | DU15: 2.4 | DV15: 10.1 | DW15: 0 | DX15: 0 | DY15: 19.8 | DZ15: 9.7 | EA15: 16.1 | EB15: 20.3 | EC15: 20 | ED15: 10.5 | EE15: 48.2 | EF15: 0 | EG15: 52.9 | EH15: 82.1 | EI15: 4.6 | EJ15: 1.8 | EK15: 20.9 | EL15: 8.3 | EM15: 8.9 | EN15: 20.4 | EO15: 20.4 | EP15: 20.2 | EQ15: 0.6 | ER15: 0 | ES15: 0 | ET15: 0 | EU15: 0.6 | EV15: 46.1 | EW15: 36.5 | EX15: 0 | EY15: 0 | EZ15: 9.2 | FA15: 20 | FC15: 38.5 | FE15: 29.4 | FF15: 3.3 | FG15: 14.7 | FJ15: 6314.17 | FL15: 23.54305 | FM15: 0 | FO15: 13.1783 | FQ15: 18.91428 | FR15: 10.1 | FS15: 16 | FT15: 81.73563
A16: 26/04/2025 | B16: 03:00 | E16: 103.49 | F16: 647.3 | G16: 214.9 | J16: 88.4 | K16: 228.3 | N16: 110.4 | O16: 111.5 | P16: 110.5 | Q16: 212 | R16: 109.2 | S16: 68.2 | T16: 561.9 | U16: 0 | Z16: 165.4 | AA16: 7.2 | AB16: 3.7 | AD16: 6.7 | AE16: 10.1 | AF16: 85.5 | AG16: 6.3 | AK16: 110.8 | AL16: 223.9 | AP16: 6.4 | AQ16: 370.2 | AR16: 77.5 | AS16: 148.5 | AT16: 42.5 | AU16: 18.7 | AV16: 19 | AW16: 87.3 | AX16: 0 | AZ16: 0 | BA16: 108.5 | BB16: 7.5 | BC16: 5.9 | BD16: 45 | BE16: 45.9 | BF16: 3.8 | BG16: 37.2 | BH16: 173.5 | BI16: 22.2 | BL16: 25.2 | BP16: 86 | BQ16: 85.8 | BR16: 0 | BS16: 85.8 | BT16: 109.6 | CC16: 4.6 | CD16: 47.8 | CE16: 128.5 | CF16: 63.7 | CG16: 78.1 | CH16: 30.1 | CL16: 104.4 | CM16: 103.6 | CN16: 121.9 | CV16: 0 | CW16: 109.6 | CX16: 0 | CY16: 2.4 | CZ16: 0 | DA16: 0 | DB16: 9.9 | DC16: 5.5 | DD16: 1.2 | DE16: 3.4 | DF16: 4.9 | DG16: 20.3 | DH16: 18.3 | DI16: 9.8 | DJ16: 3.5 | DK16: 9.3 | DL16: 0 | DM16: 0 | DN16: 31.4 | DO16: 76 | DP16: 0 | DQ16: 2 | DR16: 2.3 | DT16: 0 | DU16: 2.4 | DV16: 10.1 | DW16: 0 | DX16: 0 | DY16: 19.8 | DZ16: 9.7 | EA16: 16 | EB16: 20.2 | EC16: 19.8 | ED16: 12.6 | EE16: 52 | EF16: 0 | EG16: 54.6 | EH16: 80.5 | EI16: 5 | EJ16: 1.3 | EK16: 20.9 | EL16: 8.3 | EM16: 8.9 | EN16: 20.4 | EO16: 20.4 | EP16: 20.2 | EQ16: 3.6 | ER16: 0 | ES16: 0 | ET16: 0 | EU16: 0.6 | EV16: 43.4 | EW16: 29.4 | EX16: 0 | EY16: 0 | EZ16: 9.2 | FA16: 19.8 | FC16: 38.7 | FE16: 29.4 | FF16: 3.3 | FG16: 14.8 | FJ16: 6385.49 | FL16: 23.54368 | FM16: 0 | FO16: 13.18072 | FQ16: 18.91448 | FR16: 0 | FS16: 16 | FT16: 71.63888
A17: 26/04/2025 | B17: 03:30 | E17: 103.37 | F17: 647.6 | G17: 214.8 | J17: 90.2 | K17: 229.3 | N17: 105.8 | O17: 106.9 | P17: 106.2 | Q17: 208 | R17: 110.4 | S17: 67.1 | T17: 559.6 | U17: 0 | Z17: 163 | AA17: 7.4 | AB17: 3.2 | AD17: 6.7 | AE17: 10.1 | AF17: 84.6 | AG17: 6.3 | AK17: 110.9 | AL17: 223.9 | AP17: 6.4 | AQ17: 397.7 | AR17: 77.4 | AS17: 138.8 | AT17: 42.4 | AU17: 18.7 | AV17: 19.4 | AW17: 91 | AX17: 29.9 | AZ17: 0 | BA17: 109.1 | BB17: 7.5 | BC17: 5.9 | BD17: 45.7 | BE17: 46 | BF17: 3.8 | BG17: 38 | BH17: 174 | BI17: 22.6 | BL17: 24.8 | BP17: 86.4 | BQ17: 85.2 | BR17: 0 | BS17: 84.7 | BT17: 107.9 | CC17: 4.6 | CD17: 37.1 | CE17: 121.6 | CF17: 63 | CG17: 78.2 | CH17: 30.2 | CL17: 104 | CM17: 104.3 | CN17: 121 | CV17: 0 | CW17: 111.2 | CX17: 0 | CY17: 3.7 | CZ17: 0 | DA17: 0 | DB17: 9.9 | DC17: 5.4 | DD17: 1.2 | DE17: 3.4 | DF17: 4.8 | DG17: 20.2 | DH17: 15.4 | DI17: 9.8 | DJ17: 3.4 | DK17: 9.3 | DL17: 0 | DM17: 0 | DN17: 31 | DO17: 75.4 | DP17: 0 | DQ17: 2 | DR17: 2.3 | DT17: 0 | DU17: 2.4 | DV17: 10.1 | DW17: 0 | DX17: 0 | DY17: 19.8 | DZ17: 9.7 | EA17: 16.1 | EB17: 20.3 | EC17: 20 | ED17: 11.7 | EE17: 51.7 | EF17: 0 | EG17: 53.2 | EH17: 79.3 | EI17: 4.7 | EJ17: 1.3 | EK17: 20.9 | EL17: 8.3 | EM17: 8.7 | EN17: 20.4 | EO17: 20.4 | EP17: 20.2 | EQ17: 4.8 | ER17: 0 | ES17: 0 | ET17: 0 | EU17: 0.6 | EV17: 45 | EW17: 35.6 | EX17: 0 | EY17: 0 | EZ17: 9.2 | FA17: 20 | FC17: 38.2 | FE17: 29.4 | FF17: 3.3 | FG17: 14.8 | FJ17: 6401.17 | FL17: 23.5429 | FM17: 0 | FO17: 13.1789 | FQ17: 18.91445 | FR17: 0 | FS17: 16 | FT17: 71.63625
A18: 26/04/2025 | B18: 04:00 | E18: 103.49 | F18: 649.2 | G18: 215 | J18: 92.4 | K18: 229.2 | N18: 105.5 | O18: 104.5 | P18: 104.2 | Q18: 205.6 | R18: 109.5 | S18: 66.2 | T18: 560.6 | U18: 0 | Z18: 165.5 | AA18: 7.6 | AB18: 3.6 | AD18: 6.7 | AE18: 10.1 | AF18: 85.5 | AG18: 6.2 | AK18: 111.1 | AL18: 224.1 | AP18: 6.5 | AQ18: 411.7 | AR18: 77.5 | AS18: 143.8 | AT18: 42.4 | AU18: 18.7 | AV18: 19.4 | AW18: 89 | AX18: 29.5 | AZ18: 0 | BA18: 109.7 | BB18: 7.6 | BC18: 5.9 | BD18: 46.1 | BE18: 46.2 | BF18: 3.8 | BG18: 39.2 | BH18: 174.2 | BI18: 22.9 | BL18: 25.1 | BP18: 86.9 | BQ18: 84.1 | BR18: 0 | BS18: 83.9 | BT18: 107.9 | CC18: 4.6 | CD18: 23.8 | CE18: 124.1 | CF18: 63.4 | CG18: 78.6 | CH18: 30.3 | CL18: 102.9 | CM18: 103.6 | CN18: 119.7 | CV18: 0 | CW18: 111.9 | CX18: 0 | CY18: 2.9 | CZ18: 0 | DA18: 0 | DB18: 10 | DC18: 5.5 | DD18: 1.2 | DE18: 3.4 | DF18: 4.8 | DG18: 20.1 | DH18: 16.8 | DI18: 9.8 | DJ18: 3.4 | DK18: 9.3 | DL18: 0 | DM18: 0 | DN18: 29.9 | DO18: 72.6 | DP18: 0 | DQ18: 2 | DR18: 2.3 | DT18: 0 | DU18: 2.4 | DV18: 10.1 | DW18: 0 | DX18: 0 | DY18: 19.7 | DZ18: 9.7 | EA18: 16 | EB18: 20.3 | EC18: 20 | ED18: 11.6 | EE18: 49.3 | EF18: 0 | EG18: 51.7 | EH18: 74.7 | EI18: 4.2 | EJ18: 0.9 | EK18: 20.9 | EL18: 8.3 | EM18: 8.7 | EN18: 20.4 | EO18: 20.4 | EP18: 20.2 | EQ18: 4.4 | ER18: 0 | ES18: 0 | ET18: 0 | EU18: 0.6 | EV18: 44.8 | EW18: 36.1 | EX18: 0 | EY18: 0 | EZ18: 9.2 | FA18: 20 | FC18: 38.2 | FE18: 29.4 | FF18: 3.3 | FG18: 15 | FJ18: 6395.19 | FL18: 23.54082 | FM18: 0 | FO18: 13.17978 | FQ18: 18.91436 | FR18: 0 | FS18: 16 | FT18: 71.63496
A19: 26/04/2025 | B19: 04:30 | E19: 103.23 | F19: 643.1 | G19: 214.7 | J19: 89.6 | K19: 227.9 | N19: 105.5 | O19: 105.7 | P19: 105.7 | Q19: 209 | R19: 109.9 | S19: 67.4 | T19: 554.1 | U19: 0 | Z19: 162.9 | AA19: 7.1 | AB19: 3.8 | AD19: 6.7 | AE19: 10.1 | AF19: 71 | AG19: 6.2 | AK19: 110.3 | AL19: 222.9 | AP19: 6.4 | AQ19: 389.2 | AR19: 77.5 | AS19: 142 | AT19: 42.4 | AU19: 18.7 | AV19: 19.3 | AW19: 89.7 | AX19: 29.4 | AZ19: 0 | BA19: 108.1 | BB19: 7.6 | BC19: 5.8 | BD19: 45.5 | BE19: 44.1 | BF19: 3.8 | BG19: 37.4 | BH19: 172.5 | BI19: 22.1 | BL19: 25 | BP19: 86.2 | BQ19: 84.9 | BR19: 0 | BS19: 84.6 | BT19: 107.6 | CC19: 4.6 | CD19: 48.9 | CE19: 120.2 | CF19: 62.6 | CG19: 78.2 | CH19: 29.9 | CL19: 104 | CM19: 103.8 | CN19: 120.9 | CV19: 0 | CW19: 111.1 | CX19: 0 | CY19: 2.9 | CZ19: 0 | DA19: 0 | DB19: 10 | DC19: 5.5 | DD19: 1.2 | DE19: 3.4 | DF19: 4.8 | DG19: 20 | DH19: 16.8 | DI19: 9.8 | DJ19: 3.3 | DK19: 9.3 | DL19: 0 | DM19: 0 | DN19: 30.4 | DO19: 71.2 | DP19: 0 | DQ19: 2 | DR19: 2.3 | DT19: 0 | DU19: 2.4 | DV19: 10.1 | DW19: 0 | DX19: 0 | DY19: 19.7 | DZ19: 9.7 | EA19: 15.8 | EB19: 20.2 | EC19: 20 | ED19: 12.5 | EE19: 57.6 | EF19: 0 | EG19: 35.1 | EH19: 63.9 | EI19: 2.7 | EJ19: 0.1 | EK19: 20.9 | EL19: 8.2 | EM19: 8.8 | EN19: 20.4 | EO19: 20.4 | EP19: 20.2 | EQ19: 3.6 | ER19: 0 | ES19: 0 | ET19: 0 | EU19: 0.6 | EV19: 43.5 | EW19: 38.3 | EX19: 0 | EY19: 0 | EZ19: 9.1 | FA19: 20 | FC19: 37.9 | FE19: 29.3 | FF19: 3.2 | FG19: 15 | FJ19: 6332.93 | FL19: 23.53726 | FM19: 0 | FO19: 13.14753 | FQ19: 18.9146 | FR19: 0 | FS19: 16 | FT19: 71.59939
A20: 26/04/2025 | B20: 05:00 | E20: 103.25 | F20: 651.7 | G20: 214.9 | J20: 90.2 | K20: 231.3 | N20: 120.7 | O20: 120.2 | P20: 120.4 | Q20: 209.9 | R20: 110.9 | S20: 66.8 | T20: 564.5 | U20: 0 | Z20: 166.6 | AA20: 7.9 | AB20: 4 | AD20: 6.7 | AE20: 10.1 | AF20: 69 | AG20: 6.3 | AK20: 110.8 | AL20: 224.1 | AP20: 6.4 | AQ20: 464.9 | AR20: 77.5 | AS20: 149.3 | AT20: 42.4 | AU20: 18.7 | AV20: 18.8 | AW20: 90 | AX20: 29.2 | AZ20: 0 | BA20: 109.5 | BB20: 7.5 | BC20: 5.8 | BD20: 46.6 | BE20: 35.4 | BF20: 3.8 | BG20: 38.7 | BH20: 175.5 | BI20: 22.9 | BL20: 0 | BP20: 86.6 | BQ20: 84.9 | BR20: 0 | BS20: 85.2 | BT20: 108.6 | CC20: 4.6 | CD20: 62 | CE20: 130.6 | CF20: 63.3 | CG20: 78.4 | CH20: 30.5 | CL20: 104.1 | CM20: 104.7 | CN20: 120.4 | CV20: 0 | CW20: 108.5 | CX20: 0 | CY20: 1.4 | CZ20: 0 | DA20: 0 | DB20: 9.9 | DC20: 5.5 | DD20: 1.2 | DE20: 3.4 | DF20: 4.9 | DG20: 20.5 | DH20: 16.8 | DI20: 9.9 | DJ20: 3.3 | DK20: 9.3 | DL20: 0 | DM20: 0 | DN20: 30.5 | DO20: 75.1 | DP20: 0 | DQ20: 2 | DR20: 2.3 | DT20: 0 | DU20: 2.4 | DV20: 10.1 | DW20: 0 | DX20: 0 | DY20: 19.7 | DZ20: 9.7 | EA20: 16.2 | EB20: 20.3 | EC20: 20 | ED20: 15.4 | EE20: 68.7 | EF20: 0 | EG20: 30.2 | EH20: 57.8 | EI20: 2 | EJ20: 0.7 | EK20: 20.9 | EL20: 8.1 | EM20: 8.7 | EN20: 20.4 | EO20: 20.4 | EP20: 20.2 | EQ20: 2.9 | ER20: 0 | ES20: 0 | ET20: 0 | EU20: 0.6 | EV20: 52.2 | EW20: 44.3 | EX20: 0 | EY20: 0 | EZ20: 9.2 | FA20: 20 | FC20: 36.9 | FE20: 29.3 | FF20: 3.3 | FG20: 14.5 | FJ20: 6506.65 | FL20: 23.53626 | FM20: 0 | FO20: 13.16941 | FQ20: 18.91436 | FR20: 0 | FS20: 16.1 | FT20: 71.72003
A21: 26/04/2025 | B21: 05:30 | E21: 103.25 | F21: 646.7 | G21: 215.7 | J21: 90.1 | K21: 229.1 | N21: 117.5 | O21: 118.1 | P21: 117.5 | Q21: 229.5 | R21: 110.9 | S21: 66.6 | T21: 549.4 | U21: 0 | Z21: 166 | AA21: 7.5 | AB21: 3.1 | AD21: 6.7 | AE21: 10.1 | AF21: 71 | AG21: 6.1 | AK21: 111 | AL21: 223.4 | AP21: 6.4 | AQ21: 465.6 | AR21: 77.4 | AS21: 148.2 | AT21: 42.7 | AU21: 18.7 | AV21: 18.9 | AW21: 92.7 | AX21: 35.8 | AZ21: 0 | BA21: 108.7 | BB21: 7.7 | BC21: 5.8 | BD21: 45.4 | BE21: 34.9 | BF21: 3.8 | BG21: 37.7 | BH21: 174.3 | BI21: 42 | BL21: 0 | BP21: 86.8 | BQ21: 85 | BR21: 0 | BS21: 84.6 | BT21: 107.1 | CC21: 4.6 | CD21: 46.3 | CE21: 130.2 | CF21: 63.3 | CG21: 78.3 | CH21: 30.3 | CL21: 103.4 | CM21: 104.1 | CN21: 120.8 | CV21: 0 | CW21: 112.1 | CX21: 0 | CY21: 2.4 | CZ21: 0 | DA21: 0 | DB21: 9.8 | DC21: 5.4 | DD21: 1.2 | DE21: 3.4 | DF21: 5 | DG21: 0 | DH21: 16.8 | DI21: 9.9 | DJ21: 3.2 | DK21: 9.3 | DL21: 0 | DM21: 0 | DN21: 31 | DO21: 73.4 | DP21: 0 | DQ21: 2 | DR21: 2.3 | DT21: 0 | DU21: 2.4 | DV21: 11.1 | DW21: 0 | DX21: 0 | DY21: 19.8 | DZ21: 9.7 | EA21: 15.9 | EB21: 20.3 | EC21: 19.9 | ED21: 14 | EE21: 63.3 | EF21: 0 | EG21: 26.2 | EH21: 51.7 | EI21: 1.3 | EJ21: 0.1 | EK21: 20.9 | EL21: 8.1 | EM21: 8.8 | EN21: 20.4 | EO21: 20.4 | EP21: 20.2 | EQ21: 4.1 | ER21: 0 | ES21: 0 | ET21: 0 | EU21: 0.6 | EV21: 53.8 | EW21: 44.5 | EX21: 0 | EY21: 0 | EZ21: 9.2 | FA21: 20 | FC21: 37.7 | FE21: 29.3 | FF21: 3.3 | FG21: 14.6 | FJ21: 6469.55 | FL21: 23.53595 | FM21: 0 | FO21: 13.19982 | FQ21: 18.91408 | FR21: 0 | FS21: 16 | FT21: 71.64985
A22: 26/04/2025 | B22: 06:00 | E22: 103.1 | F22: 651 | G22: 214.6 | J22: 90.9 | K22: 229.1 | N22: 118.6 | O22: 118.7 | P22: 117.9 | Q22: 211.1 | R22: 110 | S22: 66.9 | T22: 565.5 | U22: 0 | Z22: 170.4 | AA22: 7.8 | AB22: 4.1 | AD22: 6.7 | AE22: 10.1 | AF22: 85.6 | AG22: 6.1 | AK22: 111 | AL22: 221.7 | AP22: 6.4 | AQ22: 466.2 | AR22: 77.7 | AS22: 148.6 | AT22: 42.4 | AU22: 18.5 | AV22: 18.8 | AW22: 94 | AX22: 33 | AZ22: 0 | BA22: 109.2 | BB22: 7.6 | BC22: 5.9 | BD22: 46.4 | BE22: 32.3 | BF22: 3.8 | BG22: 38.3 | BH22: 175 | BI22: 42.1 | BL22: 0 | BP22: 86.7 | BQ22: 114.7 | BR22: 0 | BS22: 114.5 | BT22: 129.5 | CC22: 4.6 | CD22: 91 | CE22: 130.6 | CF22: 63.3 | CG22: 78.4 | CH22: 30.3 | CL22: 103.4 | CM22: 104.4 | CN22: 120.3 | CV22: 0 | CW22: 108.1 | CX22: 0 | CY22: 1.9 | CZ22: 0 | DA22: 9.3 | DB22: 9.9 | DC22: 5.4 | DD22: 1.2 | DE22: 3.4 | DF22: 4.9 | DG22: 0 | DH22: 16.8 | DI22: 9.9 | DJ22: 3.3 | DK22: 9.3 | DL22: 0.9 | DM22: 0.8 | DN22: 30.3 | DO22: 66.2 | DP22: 0 | DQ22: 2 | DR22: 2.3 | DT22: 0.1 | DU22: 2.4 | DV22: 13.8 | DW22: 0 | DX22: 0 | DY22: 19.7 | DZ22: 9.7 | EA22: 15.7 | EB22: 20.3 | EC22: 20 | ED22: 9 | EE22: 50.3 | EF22: 0 | EG22: 30.1 | EH22: 47.2 | EI22: 2.1 | EJ22: 0.3 | EK22: 20.9 | EL22: 7.8 | EM22: 8.9 | EN22: 20.4 | EO22: 20.4 | EP22: 20.2 | EQ22: 3 | ER22: 0.33 | ES22: 0 | ET22: 0.8 | EU22: 0.6 | EV22: 40.8 | EW22: 29.1 | EX22: 0.6 | EY22: 0 | EZ22: 9.2 | FA22: 20 | FC22: 38 | FE22: 29.3 | FF22: 3.3 | FG22: 14.6 | FJ22: 6573.63 | FL22: 23.53519 | FM22: 0 | FO22: 13.18044 | FQ22: 16.34249 | FR22: 0 | FS22: 16 | FT22: 69.05812
... A58: 27/04/2025 | B58: 00:00 | E58: 29.05 | F58: 639 | G58: 212.5 | J58: 88.1 | K58: 228.1 | N58: 106.3 | O58: 106.3 | P58: 106.3 | Q58: 208.1 | R58: 110.3 | S58: 67.9 | T58: 545.8 | U58: 10.2 | Z58: 161.5 | AA58: 7 | AB58: 2.9 | AD58: 6.7 | AE58: 10.1 | AF58: 86.2 | AG58: 7.2 | AK58: 109.5 | AL58: 173.6 | AP58: 6.5 | AQ58: 374.9 | AR58: 73.6 | AS58: 121.3 | AT58: 42.3 | AU58: 18.5 | AV58: 19.5 | AW58: 88.2 | AX58: 188.4 | AZ58: 93.1 | BA58: 107 | BB58: 8.3 | BC58: 7.6 | BD58: 44.2 | BE58: 13.8 | BF58: 3.8 | BG58: 37.3 | BH58: 170.9 | BI58: 93 | BL58: 0 | BP58: 85.2 | BQ58: 130.5 | BR58: 0 | BS58: 129.8 | BT58: 141.9 | CC58: 4.6 | CD58: 184.9 | CE58: 107.5 | CF58: 61.6 | CG58: 77.9 | CH58: 29.7 | CL58: 0 | CM58: 147.4 | CN58: 68.1 | CV58: 0 | CW58: 110.6 | CX58: 0 | CY58: 0 | CZ58: 0 | DA58: 20 | DB58: 9.9 | DC58: 5.5 | DD58: 1.2 | DE58: 3.4 | DF58: 4.9 | DG58: 20 | DH58: 20 | DI58: 18.6 | DJ58: 3.6 | DK58: 9.3 | DL58: 0 | DM58: 0 | DN58: 31.8 | DO58: 83.2 | DP58: 0 | DQ58: 2 | DR58: 2.2 | DT58: 0 | DU58: 2.4 | DV58: 20.2 | DW58: 3.1 | DX58: 0.3 | DY58: 19.8 | DZ58: 9.7 | EA58: 17.4 | EB58: 20.2 | EC58: 19.8 | ED58: 16.6 | EE58: 61.3 | EF58: 0 | EG58: 68.3 | EH58: 85.5 | EI58: 5 | EJ58: 0.5 | EK58: 20.9 | EL58: 7 | EM58: 8.6 | EN58: 20.4 | EO58: 20.4 | EP58: 20.2 | EQ58: 0 | ER58: 0 | ES58: 0 | ET58: 0 | EU58: 0.6 | EV58: 40.7 | EW58: 33.6 | EX58: 0 | EY58: 0 | EZ58: 9.4 | FA58: 19.9 | FC58: 37.3 | FE58: 29.3 | FF58: 3.2 | FG58: 14.2 | FJ58: 6685.95 | FL58: 23.11184 | FM58: 7.998 | FO58: 13.1707 | FQ58: 18.91797 | FR58: 10.3 | FS58: 15.9 | FT58: 89.39851
A59: EJEC | C59: 0 | D59: 0 | E59: 1762.195 | F59: 15458.05 | G59: 5129.95 | H59: 0 | I59: 0 | J59: 2149.85 | K59: 5441.8 | L59: 0 | M59: 0 | N59: 2753.4 | O59: 2770.45 | P59: 2767.7 | Q59: 5167.3 | R59: 3065.45 | S59: 1811.2 | T59: 13351.4 | U59: 130.55 | V59: 0 | W59: 0 | X59: 0 | Y59: 0 | Z59: 3945.35 | AA59: 175.85 | AB59: 85.5 | AC59: 0 | AD59: 160.5 | AE59: 242.55 | AF59: 2149.6 | AG59: 149.9 | AH59: 0 | AI59: 0 | AJ59: 0 | AK59: 2173.05 | AL59: 4968.3 | AM59: 0 | AN59: 0 | AO59: 0 | AP59: 153.95 | AQ59: 10595.55 | AR59: 1752.9 | AS59: 3353.1 | AT59: 1016.5 | AU59: 425.5 | AV59: 464.65 | AW59: 2150.85 | AX59: 2751.6 | AY59: 0 | AZ59: 1267.15 | BA59: 2563.55 | BB59: 192.25 | BC59: 140.35 | BD59: 1095.4 | BE59: 571.25 | BF59: 91.2 | BG59: 909.45 | BH59: 4153.7 | BI59: 1476.95 | BJ59: 0 | BK59: 0 | BL59: 140.15 | BM59: 0 | BN59: 0 | BO59: 0 | BP59: 2070.55 | BQ59: 2728.85 | BR59: 625.15 | BS59: 2885.05 | BT59: 3195.25 | BU59: 0 | BV59: 0 | BW59: 0 | BX59: 0 | BY59: 0 | BZ59: 0 | CA59: 0 | CB59: 0 | CC59: 110.25 | CD59: 3931.95 | CE59: 3037.9 | CF59: 1523.3 | CG59: 1892.05 | CH59: 723.7 | CI59: 0 | CJ59: 0 | CK59: 0 | CL59: 1342.3 | CM59: 2871.25 | CN59: 2282.1 | CO59: 0 | CP59: 0 | CQ59: 0 | CR59: 0 | CS59: 0 | CT59: 0 | CU59: 0 | CV59: 9.25 | CW59: 2633.2 | CX59: 658.3 | CY59: 62.45 | CZ59: 3 | DA59: 364.35 | DB59: 237.9 | DC59: 130.55 | DD59: 28.8 | DE59: 79.3 | DF59: 98.4 | DG59: 121.35 | DH59: 422.8 | DI59: 381.6 | DJ59: 81.85 | DK59: 223.2 | DL59: 131.4 | DM59: 155.55 | DN59: 724.5 | DO59: 1888.5 | DP59: 4.4 | DQ59: 47.9 | DR59: 54.85 | DS59: 0 | DT59: 158.75 | DU59: 56.9 | DV59: 390.8 | DW59: 14.15 | DX59: 5.2 | DY59: 471.85 | DZ59: 232.85 | EA59: 389.4 | EB59: 485.9 | EC59: 478.65 | ED59: 358.4 | EE59: 1411.55 | EF59: 298.7 | EG59: 1727.95 | EH59: 1984.4 | EI59: 211.35 | EJ59: 128.5 | EK59: 501.6 | EL59: 179.3 | EM59: 208.95 | EN59: 489.6 | EO59: 489.6 | EP59: 484.8 | EQ59: 82.6 | ER59: 2121.594 | ES59: 127.9 | ET59: 1194.95 | EU59: 14.4 | EV59: 1627.95 | EW59: 1719.2 | EX59: 883.5 | EY59: 122.95 | EZ59: 221.85 | FA59: 479.6 | FB59: 0 | FC59: 901.2 | FD59: 0 | FE59: 698.25 | FF59: 77.95 | FG59: 351.95 | FH59: 0 | FI59: 0 | FJ59: 170623.94 | FL59: 565.14932 | FM59: 93.3055 | FN59: 0 | FO59: 315.99723 | FP59: 0 | FQ59: 324.09025 | FR59: 198.9 | FS59: 384.9 | FT59: 1882.3423

Sheet REACTIVA
B3: sábado, 26 de Abril del 2025
A5: POTENCIA REACTIVA EJECUTADA DE LAS UNIDADES DE GENERACIÓN DEL COES (MVAR) | FK5: CENTRALES NO INTEGRANTES COES
A6: FECHA | B6: HORA | C6: 337 | D6: 338 | E6: 65333 | F6: 101 | G6: 102 | H6: 42667 | I6: 42668 | J6: 126 | K6: 127 | L6: 138 | M6: 139 | N6: 197 | O6: 203 | P6: 204 | Q6: 230 | R6: 209 | S6: 56677 | T6: 796 | U6: 2146 | V6: 142 | W6: 143 | X6: 125 | Y6: 187 | Z6: 163 | AA6: 298 | AB6: 219 | AC6: 151 | AD6: 152 | AE6: 153 | AF6: 154 | AG6: 756 | AH6: 156 | AI6: 155 | AJ6: 182 | AK6: 212 | AL6: 758 | AM6: 263 | AN6: 265 | AO6: 775 | AP6: 777 | AQ6: 2154 | AR6: 150 | AS6: 149 | AT6: 188 | AU6: 2131 | AV6: 755 | AW6: 252 | AX6: 249 | AY6: 250 | AZ6: 117 | BA6: 267 | BB6: 268 | BC6: 119 | BD6: 120 | BE6: 189 | BF6: 122 | BG6: 266 | BH6: 251 | BI6: 115 | BJ6: 239 | BK6: 288 | BL6: 240 | BM6: 241 | BN6: 242 | BO6: 191 | BP6: 194 | BQ6: 196 | BR6: 207 | BS6: 236 | BT6: 795 | BU6: 285 | BV6: 995 | BW6: 996 | BX6: 997 | BY6: 766 | BZ6: 926 | CA6: 924 | CB6: 121 | CC6: 103 | CD6: 104 | CE6: 106 | CF6: 105 | CG6: 107 | CH6: 110 | CI6: 109 | CJ6: 144 | CK6: 113 | CL6: 114 | CM6: 193 | CN6: 208 | CO6: 786 | CP6: 787 | CQ6: 788 | CR6: 789 | CS6: 248 | CT6: 2159 | CU6: 303 | CV6: 59715 | CW6: 62255 | CX6: 1263 | CY6: 61800 | CZ6: 2194 | DA6: 216 | DB6: 198 | DC6: 49607 | DD6: 214 | DE6: 260 | DF6: 2152 | DG6: 2128 | DH6: 247 | DI6: 228 | DJ6: 2135 | DK6: 261 | DL6: 237 | DM6: 253 | DN6: 770 | DO6: 225 | DP6: 2201 | DQ6: 2171 | DR6: 760 | DS6: 235 | DT6: 238 | DU6: 2184 | DV6: 61855 | DW6: 223 | DX6: 226 | DY6: 201 | DZ6: 258 | EA6: 259 | EB6: 920 | EC6: 257 | ED6: 256 | EE6: 2148 | EF6: 58288 | EG6: 58289 | EH6: 58839 | EI6: 58840 | EJ6: 296 | EK6: 297 | EL6: 211 | EM6: 2175 | EN6: 2178 | EO6: 2181 | EP6: 1262 | EQ6: 63425 | ER6: 233 | ES6: 2150 | ET6: 2165 | EU6: 2161 | EV6: 61197 | EW6: 58851 | EX6: 234 | EY6: 215 | EZ6: 917 | FA6: 289 | FB6: 58333 | FC6: 58336 | FD6: 202 | FE6: 58487 | FF6: 213 | FG6: 232 | FH6: 2190 | FI6: TOTAL COES | FK6: 221 | FL6: 222 | FM6: 224 | FN6: 2187 | FO6: 227 | FP6: 49400 | FQ6: 199 | FR6: 200 | FS6: TOTAL NO COES
C7: CENTRO | D7: CENTRO | E7: SUR | F7: CENTRO | G7: CENTRO | H7: NORTE | I7: NORTE | J7: NORTE | K7: NORTE | L7: CENTRO | M7: CENTRO | N7: CENTRO | O7: CENTRO | P7: CENTRO | Q7: CENTRO | R7: CENTRO | S7: CENTRO | T7: CENTRO | U7: CENTRO | V7: CENTRO | W7: CENTRO | X7: CENTRO | Y7: CENTRO | Z7: SUR | AA7: SUR | AB7: CENTRO | AC7: SUR | AD7: SUR | AE7: SUR | AF7: SUR | AG7: SUR | AH7: SUR | AI7: SUR | AJ7: SUR | AK7: CENTRO | AL7: NORTE | AM7: NORTE | AN7: NORTE | AO7: CENTRO | AP7: CENTRO | AQ7: CENTRO | AR7: CENTRO | AS7: CENTRO | AT7: CENTRO | AU7: CENTRO | AV7: SUR | AW7: CENTRO | AX7: CENTRO | AY7: CENTRO | AZ7: CENTRO | BA7: CENTRO | BB7: CENTRO | BC7: CENTRO | BD7: CENTRO | BE7: SUR | BF7: NORTE | BG7: CENTRO | BH7: CENTRO | BI7: NORTE | BJ7: NORTE | BK7: NORTE | BL7: SUR | BM7: SUR | BN7: SUR | BO7: CENTRO | BP7: CENTRO | BQ7: CENTRO | BR7: CENTRO | BS7: CENTRO | BT7: CENTRO | BU7: CENTRO | BV7: SUR | BW7: SUR | BX7: SUR | BY7: NORTE | BZ7: SUR | CA7: CENTRO | CB7: NORTE | CC7: CENTRO | CD7: CENTRO | CE7: CENTRO | CF7: CENTRO | CG7: CENTRO | CH7: CENTRO | CI7: CENTRO | CJ7: CENTRO | CK7: CENTRO | CL7: CENTRO | CM7: CENTRO | CN7: CENTRO | CO7: SUR | CP7: SUR | CQ7: SUR | CR7: SUR | CS7: CENTRO | CT7: CENTRO | CU7: CENTRO | CV7: CENTRO | CW7: SUR | CX7: NORTE | CY7: NORTE | CZ7: NORTE | DA7: NORTE | DB7: NORTE | DC7: SUR | DD7: CENTRO | DE7: CENTRO | DF7: CENTRO | DG7: NORTE | DH7: NORTE | DI7: CENTRO | DJ7: CENTRO | DK7: SUR | DL7: SUR | DM7: CENTRO | DN7: CENTRO | DO7: CENTRO | DP7: CENTRO | DQ7: CENTRO | DR7: CENTRO | DS7: SUR | DT7: CENTRO | DU7: CENTRO | DV7: NORTE | DW7: CENTRO | DX7: CENTRO | DY7: NORTE | DZ7: CENTRO | EA7: CENTRO | EB7: CENTRO | EC7: NORTE | ED7: NORTE | EE7: SUR | EF7: CENTRO | EG7: CENTRO | EH7: CENTRO | EI7: CENTRO | EJ7: CENTRO | EK7: CENTRO | EL7: SUR | EM7: SUR | EN7: SUR | EO7: SUR | EP7: NORTE | EQ7: SUR | ER7: SUR | ES7: SUR | ET7: CENTRO | EU7: CENTRO | EV7: CENTRO | EW7: SUR | EX7: SUR | EY7: NORTE | EZ7: CENTRO | FA7: NORTE | FB7: NORTE | FC7: NORTE | FD7: CENTRO | FE7: CENTRO | FF7: CENTRO | FG7: NORTE | FH7: NORTE | FK7: NORTE | FL7: CENTRO | FM7: NORTE | FN7: NORTE | FO7: NORTE | FP7: NORTE | FQ7: NORTE | FR7: NORTE
C8: HIDROELÉCTRICA | D8: HIDROELÉCTRICA | E8: HIDROELÉCTRICA | F8: HIDROELÉCTRICA | G8: HIDROELÉCTRICA | H8: TERMOELÉCTRICA | I8: TERMOELÉCTRICA | J8: HIDROELÉCTRICA | K8: HIDROELÉCTRICA | L8: TERMOELÉCTRICA | M8: TERMOELÉCTRICA | N8: TERMOELÉCTRICA | O8: TERMOELÉCTRICA | P8: TERMOELÉCTRICA | Q8: TERMOELÉCTRICA | R8: TERMOELÉCTRICA | S8: TERMOELÉCTRICA | T8: HIDROELÉCTRICA | U8: HIDROELÉCTRICA | V8: TERMOELÉCTRICA | W8: TERMOELÉCTRICA | X8: TERMOELÉCTRICA | Y8: TERMOELÉCTRICA | Z8: HIDROELÉCTRICA | AA8: HIDROELÉCTRICA | AB8: TERMOELÉCTRICA | AC8: HIDROELÉCTRICA | AD8: HIDROELÉCTRICA | AE8: HIDROELÉCTRICA | AF8: HIDROELÉCTRICA | AG8: TERMOELÉCTRICA | AH8: TERMOELÉCTRICA | AI8: TERMOELÉCTRICA | AJ8: HIDROELÉCTRICA | AK8: HIDROELÉCTRICA | AL8: TERMOELÉCTRICA | AM8: TERMOELÉCTRICA | AN8: TERMOELÉCTRICA | AO8: HIDROELÉCTRICA | AP8: HIDROELÉCTRICA | AQ8: HIDROELÉCTRICA | AR8: HIDROELÉCTRICA | AS8: HIDROELÉCTRICA | AT8: HIDROELÉCTRICA | AU8: HIDROELÉCTRICA | AV8: HIDROELÉCTRICA | AW8: TERMOELÉCTRICA | AX8: TERMOELÉCTRICA | AY8: TERMOELÉCTRICA | AZ8: HIDROELÉCTRICA | BA8: HIDROELÉCTRICA | BB8: HIDROELÉCTRICA | BC8: HIDROELÉCTRICA | BD8: HIDROELÉCTRICA | BE8: HIDROELÉCTRICA | BF8: HIDROELÉCTRICA | BG8: HIDROELÉCTRICA | BH8: HIDROELÉCTRICA | BI8: TERMOELÉCTRICA | BJ8: TERMOELÉCTRICA | BK8: TERMOELÉCTRICA | BL8: TERMOELÉCTRICA | BM8: TERMOELÉCTRICA | BN8: TERMOELÉCTRICA | BO8: HIDROELÉCTRICA | BP8: TERMOELÉCTRICA | BQ8: TERMOELÉCTRICA | BR8: TERMOELÉCTRICA | BS8: TERMOELÉCTRICA | BT8: TERMOELÉCTRICA | BU8: TERMOELÉCTRICA | BV8: TERMOELÉCTRICA | BW8: TERMOELÉCTRICA | BX8: TERMOELÉCTRICA | BY8: HIDROELÉCTRICA | BZ8: TERMOELÉCTRICA | CA8: TERMOELÉCTRICA | CB8: HIDROELÉCTRICA | CC8: HIDROELÉCTRICA | CD8: HIDROELÉCTRICA | CE8: HIDROELÉCTRICA | CF8: HIDROELÉCTRICA | CG8: HIDROELÉCTRICA | CH8: TERMOELÉCTRICA | CI8: TERMOELÉCTRICA | CJ8: TERMOELÉCTRICA | CK8: TERMOELÉCTRICA | CL8: TERMOELÉCTRICA | CM8: TERMOELÉCTRICA | CN8: TERMOELÉCTRICA | CO8: TERMOELÉCTRICA | CP8: TERMOELÉCTRICA | CQ8: TERMOELÉCTRICA | CR8: TERMOELÉCTRICA | CS8: TERMOELÉCTRICA | CT8: TERMOELÉCTRICA | CU8: SOLAR | CV8: EÓLICA | CW8: SOLAR | CX8: EÓLICA | CY8: SOLAR | CZ8: HIDROELÉCTRICA | DA8: HIDROELÉCTRICA | DB8: HIDROELÉCTRICA | DC8: HIDROELÉCTRICA | DD8: HIDROELÉCTRICA | DE8: HIDROELÉCTRICA | DF8: HIDROELÉCTRICA | DG8: HIDROELÉCTRICA | DH8: HIDROELÉCTRICA | DI8: HIDROELÉCTRICA | DJ8: HIDROELÉCTRICA | DK8: SOLAR | DL8: SOLAR | DM8: EÓLICA | DN8: EÓLICA | DO8: TERMOELÉCTRICA | DP8: TERMOELÉCTRICA | DQ8: TERMOELÉCTRICA | DR8: TERMOELÉCTRICA | DS8: SOLAR | DT8: HIDROELÉCTRICA | DU8: HIDROELÉCTRICA | DV8: HIDROELÉCTRICA | DW8: HIDROELÉCTRICA | DX8: HIDROELÉCTRICA | DY8: HIDROELÉCTRICA | DZ8: HIDROELÉCTRICA | EA8: HIDROELÉCTRICA | EB8: HIDROELÉCTRICA | EC8: EÓLICA | ED8: EÓLICA | EE8: SOLAR | EF8: EÓLICA | EG8: EÓLICA | EH8: EÓLICA | EI8: EÓLICA | EJ8: HIDROELÉCTRICA | EK8: HIDROELÉCTRICA | EL8: HIDROELÉCTRICA | EM8: HIDROELÉCTRICA | EN8: HIDROELÉCTRICA | EO8: HIDROELÉCTRICA | EP8: EÓLICA | EQ8: SOLAR | ER8: SOLAR | ES8: SOLAR | ET8: HIDROELÉCTRICA | EU8: EÓLICA | EV8: EÓLICA | EW8: SOLAR | EX8: SOLAR | EY8: HIDROELÉCTRICA | EZ8: HIDROELÉCTRICA | FA8: TERMOELÉCTRICA | FB8: TERMOELÉCTRICA | FC8: TERMOELÉCTRICA | FD8: TERMOELÉCTRICA | FE8: TERMOELÉCTRICA | FF8: TERMOELÉCTRICA | FG8: TERMOELÉCTRICA | FH8: TERMOELÉCTRICA | FK8: HIDROELÉCTRICA | FL8: HIDROELÉCTRICA | FM8: HIDROELÉCTRICA | FN8: HIDROELÉCTRICA | FO8: TERMOELÉCTRICA | FP8: TERMOELÉCTRICA | FQ8: HIDROELÉCTRICA | FR8: HIDROELÉCTRICA
C9: CENTRALES SANTA ROSA S.A.C. | D9: CENTRALES SANTA ROSA S.A.C. | E9: HYDRO GLOBAL PERÚ S.A.C. | F9: ELECTROPERU | G9: ELECTROPERU | H9: ELECTROPERU | I9: ELECTROPERU | J9: ORAZUL ENERGY PERÚ | K9: ORAZUL ENERGY PERÚ | L9: TERMOSELVA | M9: TERMOSELVA | N9: KALLPA GENERACION S.A. | O9: KALLPA GENERACION S.A. | P9: KALLPA GENERACION S.A. | Q9: KALLPA GENERACION S.A. | R9: KALLPA GENERACION S.A. | S9: KALLPA GENERACION S.A. | T9: KALLPA GENERACION S.A. | U9: KALLPA GENERACION S.A. | V9: SHOUGESA | W9: SHOUGESA | X9: SHOUGESA | Y9: SHOUGESA | Z9: EGEMSA | AA9: EGESUR | AB9: EGESUR | AC9: EGASA | AD9: EGASA | AE9: EGASA | AF9: EGASA | AG9: EGASA | AH9: EGASA | AI9: EGASA | AJ9: SAN GABAN | AK9: CELEPSA | AL9: MINERA CERRO VERDE | AM9: PLANTA DE RESERVA FRIA DE GENERACION DE ETEN S.A. | AN9: PLANTA DE RESERVA FRIA DE GENERACION DE ETEN S.A. | AO9: EMPRESA DE GENERACION HUALLAGA | AP9: EMPRESA DE GENERACION HUALLAGA | AQ9: LA VIRGEN | AR9: CHINANGO S.A.C. | AS9: CHINANGO S.A.C. | AT9: HIDROELECTRICA HUANCHOR S.A.C. | AU9: CELEPSA RENOVABLES S.R.L. | AV9: INLAND ENERGY SAC | AW9: FENIX POWER PERÚ | AX9: FENIX POWER PERÚ | AY9: FENIX POWER PERÚ | AZ9: STATKRAFT S.A | BA9: STATKRAFT S.A | BB9: STATKRAFT S.A | BC9: STATKRAFT S.A | BD9: STATKRAFT S.A | BE9: STATKRAFT S.A | BF9: STATKRAFT S.A | BG9: STATKRAFT S.A | BH9: EMPRESA DE GENERACION HUANZA | BI9: ENEL GENERACION PIURA S.A. | BJ9: ENEL GENERACION PIURA S.A. | BK9: ENEL GENERACION PIURA S.A. | BL9: ENGIE | BM9: ENGIE | BN9: ENGIE | BO9: ENGIE | BP9: ENGIE | BQ9: ENGIE | BR9: ENGIE | BS9: ENGIE | BT9: ENGIE | BU9: ENGIE | BV9: ENGIE | BW9: ENGIE | BX9: ENGIE | BY9: ENGIE | BZ9: INFRAESTRUCTURAS Y ENERGIAS DEL PERU S.A.C. | CA9: INFRAESTRUCTURAS Y ENERGIAS DEL PERU S.A.C. | CB9: INVERSIONES SHAQSHA S.A.C. | CC9: ORYGEN PERU S.A.A. | CD9: ORYGEN PERU S.A.A. | CE9: ORYGEN PERU S.A.A. | CF9: ORYGEN PERU S.A.A. | CG9: ORYGEN PERU S.A.A. | CH9: ORYGEN PERU S.A.A. | CI9: ORYGEN PERU S.A.A. | CJ9: ORYGEN PERU S.A.A. | CK9: ORYGEN PERU S.A.A. | CL9: ORYGEN PERU S.A.A. | CM9: ORYGEN PERU S.A.A. | CN9: ORYGEN PERU S.A.A. | CO9: SAMAY I S.A.C | CP9: SAMAY I S.A.C | CQ9: SAMAY I S.A.C | CR9: SAMAY I S.A.C | CS9: TERMOCHILCA S.A.C. | CT9: TERMOCHILCA S.A.C. | CU9: COLCA SOLAR S.A.C. | CV9: ENERGIA RENOVABLE DEL SUR S.A. | CW9: GR CORTARRAMA SOCIEDAD ANONIMA CERRADA | CX9: GR TARUCA SOCIEDAD ANONIMA CERRADA | CY9: KONDU SAC | CZ9: PERUANA DE INVERSIONES EN ENERGIAS RENOVABLES S.A. | DA9: ORAZUL ENERGY PERÚ | DB9: ORAZUL ENERGY PERÚ | DC9: SAN GABAN | DD9: MAJA ENERGIA S.A.C. | DE9: EMPRESA DE GENERACION ELECTRICA CANCHAYLLO SAC | DF9: EMPRESA DE GENERACION ELECTRICA SANTA ANA S.A.C. | DG9: EMPRESA ELECTRICA AGUA AZUL | DH9: EMPRESA ELECTRICA RIO DOBLE | DI9: HIDROCAÑETE S.A. | DJ9: HUAURA POWER GROUP S.A. | DK9: MOQUEGUA FV S.A.C. | DL9: PANAMERICANA SOLAR SAC. | DM9: PARQUE EOLICO MARCONA S.A.C. | DN9: PARQUE EOLICO TRES HERMANAS S.A.C. | DO9: PETRAMAS | DP9: PETRAMAS | DQ9: PETRAMAS | DR9: PETRAMAS | DS9: TACNA SOLAR SAC. | DT9: ELECTRICA YANAPAMPA SAC | DU9: ANDEAN POWER S.A.C. | DV9: ASOCIACIÓN SANTA LUCIA DE CHACAS | DW9: ATRIA ENERGIA S.A.C. | DX9: EGEJUNIN | DY9: EGEJUNIN | DZ9: EGEJUNIN | EA9: EGEJUNIN | EB9: EMPRESA DE GENERACION ELECTRICA RIO BAÑOS S.A.C. | EC9: ENERGÍA EÓLICA S.A. | ED9: ENERGÍA EÓLICA S.A. | EE9: ENGIE | EF9: ENGIE | EG9: ENGIE | EH9: ENGIE | EI9: ENGIE | EJ9: GENERACIÓN ANDINA S.A.C. | EK9: GENERACIÓN ANDINA S.A.C. | EL9: GENERADORA DE ENERGÍA DEL PERÚ | EM9: GENERADORA DE ENERGÍA DEL PERÚ | EN9: GENERADORA DE ENERGÍA DEL PERÚ | EO9: GENERADORA DE ENERGÍA DEL PERÚ | EP9: GR PAINO SOCIEDAD ANONIMA CERRADA | EQ9: JOYA SOLAR S.A.C. | ER9: MAJES ARCUS S.A.C. | ES9: ORYGEN PERU S.A.A. | ET9: ORYGEN PERU S.A.A. | EU9: ORYGEN PERU S.A.A. | EV9: ORYGEN PERU S.A.A. | EW9: ORYGEN PERU S.A.A. | EX9: REPARTICIÓN ARCUS S.A.C. | EY9: SINERSA | EZ9: SINERSA | FA9: BIOENERGIA DEL CHIRA S.A. | FB9: GM OPERACIONES S.A.C. | FC9: GM OPERACIONES S.A.C. | FD9: SDF ENERGIA SAC | FE9: SDF ENERGIA SAC | FF9: AGRO INDUSTRIAL PARAMONGA S.A. | FG9: AGROAURORA S.A.C. | FH9: AGROINDUSTRIAS SAN JACINTO S.A.A. | FK9: UNACEM PERU S.A. | FL9: ELECTRO ORIENTE | FM9: AGUAS Y ENERGIA PERU | FN9: ELECTRO ZAÑA S.A.C. | FO9: ELECTRONOROESTE S.A. | FP9: SDE PIURA | FQ9: SINERSA | FR9: SINERSA
C10: SANTA ROSA 1 | D10: SANTA ROSA 2 | E10: SAN GABAN III | F10: MANTARO | G10: RESTITUCION | H10: TUMBES MAK 1 | I10: TUMBES MAK 2 | J10: CARHUAQUERO | K10: CAÑON DEL PATO | L10: AGUAYTIA TG1 | M10: AGUAYTIA TG2 | N10: KALLPA TG1 | O10: KALLPA TG2 | P10: KALLPA TG3 | Q10: KALLPA TV | R10: LFLORES TG1 | S10: LFLORES TV | T10: CERRO DEL AGUILA | U10: CERRODELAGUILAG4 | V10: SHOUGESA TV1 | W10: SHOUGESA TV2 | X10: SHOUGESA TV3 | Y10: SHOUGESA CUMMINS | Z10: MACHUPICCHU | AA10: ARICOTA 1 | AB10: INDEPENDENCIA | AC10: CHARCANI I,II,III | AD10: CHARCANI IV | AE10: CHARCANI V | AF10: CHARCANI VI | AG10: CHILINA TG | AH10: MOLLENDO 1, 2, 3 | AI10: CHILINA (SULZ 1,2) | AJ10: SAN GABAN II | AK10: PLATANAL | AL10: RECKA | AM10: RF ETEN TG1 | AN10: RF ETEN TG2 | AO10: CHAGLLA GP1 | AP10: CHAGLLA | AQ10: LA VIRGEN | AR10: CHIMAY | AS10: YANANGO | AT10: HUANCHOR | AU10: MARAÑON | AV10: STA TERESA | AW10: FENIX GT11 | AX10: FENIX GT12 | AY10: FENIX TV10 | AZ10: YAUPI | BA10: OROYA | BB10: PACHACHACA | BC10: MALPASO | BD10: CAHUA | BE10: ARCATA | BF10: GALLITO CIEGO | BG10: CHEVES | BH10: HUANZA | BI10: MALACAS2 TG4 | BJ10: MALACAS3 TG 5 | BK10: MALACAS1 TG6 | BL10: RF ILO2 TG1 | BM10: RF ILO2 TG2 | BN10: RF ILO2 TG3 | BO10: YUNCAN | BP10: CHILCA1 TG1 | BQ10: CHILCA1 TG2 | BR10: CHILCA1 TG3 | BS10: CHILCA-TV | BT10: CHILCA2 TG41 | BU10: CHILCA2-TV | BV10: CTNEPI_TG41 | BW10: CTNEPI_TG42 | BX10: CTNEPI_TG43 | BY10: QUITARACSA | BZ10: RF PTO MALDONADO | CA10: RF PUCALLPA | CB10: PARIAC | CC10: HUINCO | CD10: MATUCANA | CE10: MOYOPAMPA | CF10: CALLAHUANCA | CG10: HUAMPANI | CH10: STA ROSA WEST TG7 | CI10: UTI_5 | CJ10: UTI_6 | CK10: VENTANILLA 3 | CL10: VENTANILLA 4 | CM10: VENTANILLA TV | CN10: STAROSA TG8 | CO10: PTO_BRVO TG1 | CP10: PTO_BRVO TG2 | CQ10: PTO_BRVO TG3 | CR10: PTO_BRVO TG4 | CS10: OLLEROS TG1 | CT10: OLLEROS TV | CU10: CS YARUCAYA | CV10: SAN JUAN | CW10: MATARANI | CX10: DUNA | CY10: CARHUAQUERO (CS) | CZ10: MANTA I | DA10: CARHUAQUERO4 | DB10: CAÑA BRAVA | DC10: TUPURI | DD10: RONCADOR | DE10: CANCHAYLLO | DF10: RENOVANDESH1 | DG10: POTRERO | DH10: PIZARRAS | DI10: NIMPERIAL | DJ10: YARUCAYA | DK10: MOQUEGUA-SOLAR | DL10: PANAMERICANA-SOLAR | DM10: PQE-EOLICO-MARCONA | DN10: PQE-EOLICO-3-HERMANAS | DO10: HUAYCOLORO | DP10: CALLAO | DQ10: DONA_CATALINA | DR10: LAGRINGAV | DS10: TACNA-SOLAR | DT10: YANAPAMPA | DU10: CARHUAC | DV10: HUALLIN | DW10: PURMACANA | DX10: HUASAHUASI | DY10: STACRUZ_1_2 | DZ10: RUNATULLO_II | EA10: RUNATULLO_III | EB10: RUCUY | EC10: PQE-EOLICO-TALARA | ED10: PQE-EOLICO-CUPISNIQUE | EE10: INTIPAMPA | EF10: PUNTA LOMITAS-BL1 | EG10: PUNTA LOMITAS-BL2 | EH10: PUN LOMITAS_EXP-BL1 | EI10: PUN LOMITAS_EXP-BL2 | EJ10: 8AGOSTO | EK10: EL CARMEN | EL10: LA JOYA | EM10: ANGEL_I | EN10: ANGEL_II | EO10: ANGEL_III | EP10: HUAMBOS | EQ10: SAN MARTIN SOLAR | ER10: MAJES | ES10: RUBI | ET10: CH_HER1 | EU10: WAYRA-I | EV10: WAYRA EXTENSION | EW10: CLEMESI | EX10: REPARTICION | EY10: POECHOS2 | EZ10: CHANCAY | FA10: CANA BRAVA | FB10: REFINERIA TALARA TV1 | FC10: REFINERÍA TALARA TV2 | FD10: OQUENDO TG1 | FE10: OQUENDO TV1 | FF10: PARAMONGA | FG10: MAPLE | FH10: SAN_JACINTO | FI10: MVAR | FK10: CARPAPATA | FL10: CENTRALES ELOR | FM10: PIAS1 | FN10: ZANA | FO10: TABLAZO | FP10: TALLANCA | FQ10: CURUMUY | FR10: POECHOS1 | FS10: MVAR
A11: 26/04/2025 | B11: 00:30 | E11: 8.78 | F11: 49.9 | G11: 21.1 | J11: -12.8 | K11: 1.4 | N11: -32.3 | O11: -44.8 | P11: -30.1 | Q11: 25.8 | R11: -6.9 | S11: 9.9 | T11: 56.8 | U11: 0 | Z11: 0.7 | AA11: 1.4 | AC11: -3.4 | AD11: 3.1 | AE11: 2.8 | AF11: 1 | AJ11: -1.9 | AK11: 15.4 | AO11: -1.7 | AP11: 49.9 | AQ11: 9.9 | AR11: 11.4 | AS11: 2 | AT11: 0 | AU11: 2.7 | AV11: 0.7 | AW11: 0 | AY11: 0 | AZ11: 8.3 | BA11: -0.5 | BB11: 0.6 | BC11: -1.3 | BD11: 3.8 | BE11: 1 | BF11: -0.1 | BG11: 2.3 | BH11: -1.2 | BK11: 3.8 | BO11: 9.4 | BP11: -40.4 | BQ11: 0 | BR11: -16 | BS11: -25.3 | CB11: -0.4 | CC11: 19.5 | CD11: 21.3 | CE11: 3.8 | CF11: 2.1 | CG11: 3.9 | CK11: 6.2 | CL11: 8.9 | CM11: -47.8 | CV11: -2.8 | CW11: 0 | CX11: 0 | CZ11: 0 | DA11: 0.1 | DB11: -1 | DD11: 0 | DE11: 1.5 | DF11: 1.8 | DG11: 1.1 | DH11: 0.1 | DI11: 0.6 | DJ11: 0 | DK11: 0 | DL11: 0 | DM11: -4.6 | DN11: -0.2 | DO11: 1.8 | DP11: 0.5 | DQ11: 0.8 | DS11: 0 | DT11: -0.1 | DU11: 0.7 | DV11: 0 | DX11: -4.8 | DY11: 0.7 | DZ11: 1.4 | EA11: 2.1 | EB11: 1.1 | EC11: 0.8 | ED11: 4 | EE11: 0 | EF11: -9.6 | EG11: -10 | EH11: 0 | EI11: 0 | EJ11: 2.6 | EK11: -0.1 | EL11: 1.7 | EM11: 0.2 | EN11: 0.2 | EO11: 0.2 | EQ11: 0 | ER11: 0 | ES11: 0 | ET11: -0.2 | EU11: -0.8 | EV11: 0 | EW11: 0 | EX11: 0 | EY11: 0.4 | EZ11: 1.4 | FB11: 6.5 | FD11: 1.8 | FE11: 1.7 | FF11: 2.3 | FI11: 106.58 | FK11: 2.50145 | FL11: 0.359 | FN11: 1.7332 | FP11: 2.68456 | FQ11: 0.2 | FR11: 0.2 | FS11: 7.67821
A12: 26/04/2025 | B12: 01:00 | E12: 9.49 | F12: 43.8 | G12: 20.6 | J12: -16.1 | K12: 2.1 | N12: -36.2 | O12: -46.9 | P12: -32.1 | Q12: 21.8 | R12: -10.7 | S12: 7.3 | T12: 54.7 | U12: 0 | Z12: -0.3 | AA12: 1.7 | AC12: -3.4 | AD12: 3.1 | AE12: 2.8 | AF12: 1 | AJ12: -2.2 | AK12: 14 | AO12: -1.8 | AP12: 50.9 | AQ12: 9.8 | AR12: 11.1 | AS12: 1.9 | AT12: 0 | AU12: 2.7 | AV12: 1.1 | AW12: 0 | AY12: 0 | AZ12: 9.2 | BA12: -0.4 | BB12: 0.5 | BC12: -2.2 | BD12: 3 | BE12: 1 | BF12: -0.1 | BG12: 0.7 | BH12: -4.8 | BK12: 1.9 | BO12: 7.4 | BP12: -44.5 | BQ12: 0 | BR12: -20.7 | BS12: -30.1 | CB12: -0.4 | CC12: 18.9 | CD12: 18.7 | CE12: 3.2 | CF12: 4.5 | CG12: -0.1 | CK12: 1.1 | CL12: 4 | CM12: -54.9 | CV12: -2.4 | CW12: 0 | CX12: 0 | CZ12: 0 | DA12: 0.1 | DB12: -0.9 | DD12: 0.2 | DE12: 1.5 | DF12: 1.9 | DG12: 0.9 | DH12: 0.1 | DI12: 0.5 | DJ12: 0 | DK12: 0 | DL12: 0 | DM12: -4.6 | DN12: 0.2 | DO12: 1.8 | DP12: 0.5 | DQ12: 0.8 | DS12: 0 | DT12: -0.3 | DU12: 0.7 | DV12: 0 | DX12: -4.7 | DY12: 0.9 | DZ12: 1.3 | EA12: 2 | EB12: 1.1 | EC12: 0.8 | ED12: 4 | EE12: 0 | EF12: -9.9 | EG12: -10.3 | EH12: 0 | EI12: 0 | EJ12: 2.6 | EK12: -0.1 | EL12: 1.7 | EM12: 0.2 | EN12: 0.2 | EO12: 0.2 | EQ12: 0 | ER12: 0 | ES12: 0 | ET12: -0.2 | EU12: -0.5 | EV12: 0 | EW12: 0 | EX12: 0 | EY12: 0.4 | EZ12: 1.4 | FB12: 5.3 | FD12: 1.8 | FE12: 2.2 | FF12: 2 | FI12: 29.49 | FK12: 2.47653 | FL12: 0 | FN12: 1.664 | FP12: 2.69377 | FQ12: -0.1 | FR12: 0.3 | FS12: 7.0343
A13: 26/04/2025 | B13: 01:30 | E13: 8.74 | F13: 34.5 | G13: 18.5 | J13: -18.6 | K13: -3 | N13: -39.1 | O13: -49.9 | P13: -35.1 | Q13: 18.4 | R13: -13.4 | S13: 5.1 | T13: 50.7 | U13: 0 | Z13: -2 | AA13: 1.4 | AC13: -3.3 | AD13: 3.4 | AE13: 2.3 | AF13: 1.2 | AJ13: -2.6 | AK13: 12.7 | AO13: -1.4 | AP13: 15.9 | AQ13: 9.6 | AR13: 8.6 | AS13: -0.9 | AT13: 0.2 | AU13: 2.7 | AV13: 1 | AW13: 0 | AY13: 0 | AZ13: 6.7 | BA13: -0.5 | BB13: 0.5 | BC13: -3.6 | BD13: 2.7 | BE13: 1 | BF13: -0.1 | BG13: 0.8 | BH13: -6.3 | BK13: 0.3 | BO13: -0.3 | BP13: -47.2 | BQ13: 0 | BR13: -23.7 | BS13: -33 | CB13: -0.4 | CC13: 19.1 | CD13: 17.7 | CE13: 4 | CF13: 2.1 | CG13: 0.1 | CK13: -4.4 | CL13: -1.6 | CM13: -52.2 | CV13: -2 | CW13: 0 | CX13: 0 | CZ13: 0 | DA13: 0.1 | DB13: -0.9 | DD13: 0.2 | DE13: 1.5 | DF13: 1.9 | DG13: 0.3 | DH13: 0.1 | DI13: 0.5 | DJ13: 0 | DK13: 0 | DL13: 0 | DM13: -4.9 | DN13: -0.6 | DO13: 0 | DP13: 0.5 | DQ13: 0.7 | DS13: 0 | DT13: 0.2 | DU13: 0.3 | DV13: 0 | DX13: -4.7 | DY13: 1 | DZ13: 1.3 | EA13: 2.1 | EB13: 1.1 | EC13: 0.8 | ED13: 4 | EE13: 0 | EF13: -10.5 | EG13: -10.9 | EH13: 0 | EI13: 0 | EJ13: 2.6 | EK13: -0.1 | EL13: 1.7 | EM13: 0.2 | EN13: 0.2 | EO13: 0.2 | EQ13: 0 | ER13: 0 | ES13: 0 | ET13: -0.2 | EU13: -1.7 | EV13: 0 | EW13: 0 | EX13: 0 | EY13: 0.4 | EZ13: 1.4 | FB13: 4.6 | FD13: 1.8 | FE13: 1.9 | FF13: 0.1 | FI13: -97.46 | FK13: 2.34983 | FL13: 0 | FN13: 1.65264 | FP13: 2.69665 | FQ13: -0.5 | FR13: 0.6 | FS13: 6.79912
A14: 26/04/2025 | B14: 02:00 | E14: 8.64 | F14: 37.4 | G14: 19.6 | J14: -18.8 | K14: -1.9 | N14: -39.5 | O14: -48.9 | P14: -34 | Q14: 17.2 | R14: -14.1 | S14: 5.1 | T14: 48.9 | U14: 0.2 | Z14: -1.8 | AA14: 1 | AC14: -3.3 | AD14: 3.2 | AE14: 1.6 | AF14: 1.1 | AJ14: -2 | AK14: 12.3 | AO14: -1.4 | AP14: 18.1 | AQ14: 9.6 | AR14: 8.5 | AS14: -1.1 | AT14: 0 | AU14: 2.7 | AV14: 1.3 | AW14: 0 | AY14: 0 | AZ14: 7.7 | BA14: -0.5 | BB14: 0.5 | BC14: -2.3 | BD14: 2.7 | BE14: 1 | BF14: -0.1 | BG14: 2.6 | BH14: -6.5 | BK14: 1.1 | BO14: 1.1 | BP14: -47.8 | BQ14: 0 | BR14: -24.2 | BS14: -33.8 | CB14: -0.4 | CC14: 14.2 | CD14: 17.5 | CE14: 3.5 | CF14: 2.1 | CG14: 0 | CK14: -5.8 | CL14: -2.8 | CM14: -54 | CV14: -1.8 | CW14: 0 | CX14: 0 | CZ14: 0 | DA14: 0.1 | DB14: -1 | DD14: 0.2 | DE14: 1.3 | DF14: 1.8 | DG14: -0.4 | DH14: 0.1 | DI14: 0.5 | DJ14: 0 | DK14: 0 | DL14: 0 | DM14: -5.1 | DN14: -0.9 | DO14: 0 | DP14: 0.5 | DQ14: 0.7 | DS14: 0 | DT14: 0.1 | DU14: 0.3 | DV14: 0 | DX14: -4.7 | DY14: 1 | DZ14: 1.4 | EA14: 2 | EB14: 1 | EC14: 0.8 | ED14: 4 | EE14: 0 | EF14: -10.8 | EG14: -10.8 | EH14: 0 | EI14: 0 | EJ14: 2.6 | EK14: -0.1 | EL14: 1.7 | EM14: 0.2 | EN14: 0.2 | EO14: 0.2 | EQ14: 0 | ER14: 0 | ES14: 0 | ET14: -0.2 | EU14: -1.9 | EV14: 0 | EW14: 0 | EX14: 0 | EY14: 0.4 | EZ14: 1.3 | FB14: 4.7 | FD14: 1.8 | FE14: 2.5 | FF14: 1.7 | FI14: -99.16 | FK14: 2.34833 | FL14: 0 | FN14: 1.59882 | FP14: 2.68957 | FQ14: -0.5 | FR14: 0.3 | FS14: 6.43672
A15: 26/04/2025 | B15: 02:30 | E15: 8.75 | F15: 34.1 | G15: 18.4 | J15: -19 | K15: -2.8 | N15: -38.2 | O15: -49.8 | P15: -35.3 | Q15: 19.6 | R15: -9.3 | S15: 7.8 | T15: 45.8 | U15: 0 | Z15: -2 | AA15: 1.7 | AC15: -3.3 | AD15: 3.2 | AE15: 0.7 | AF15: 1.1 | AJ15: 3.9 | AK15: 12.9 | AO15: -1.6 | AP15: -1.3 | AQ15: 9 | AR15: 9 | AS15: -1.2 | AT15: -0.2 | AU15: 2.6 | AV15: 1.1 | AW15: 0 | AY15: 0 | AZ15: 6.2 | BA15: -0.5 | BB15: 0.5 | BC15: -3.4 | BD15: 2.5 | BE15: 1 | BF15: -0.2 | BG15: 1.2 | BH15: -5.4 | BK15: 0.2 | BO15: -3.1 | BP15: -43.1 | BQ15: 0 | BR15: -19.3 | BS15: -29.2 | CB15: -0.4 | CC15: 14.4 | CD15: 17.8 | CE15: 4.1 | CF15: 2.7 | CG15: -0.1 | CK15: -2.1 | CL15: 0.7 | CM15: -48.8 | CV15: -1.8 | CW15: 0 | CX15: 0 | CZ15: 0 | DA15: 0 | DB15: -0.9 | DD15: -0.2 | DE15: 1.5 | DF15: 1.9 | DG15: -1.2 | DH15: 0.1 | DI15: 0.6 | DJ15: 0 | DK15: 0 | DL15: 0 | DM15: -5 | DN15: -0.7 | DO15: 0 | DP15: 0.5 | DQ15: 0.7 | DS15: 0 | DT15: 0.1 | DU15: 0.3 | DV15: 0 | DX15: -4.6 | DY15: 0.9 | DZ15: 1.5 | EA15: 2 | EB15: 1.3 | EC15: 0.8 | ED15: 4 | EE15: 0 | EF15: -10.9 | EG15: -11 | EH15: 0 | EI15: 0 | EJ15: 2.6 | EK15: -0.1 | EL15: 1.9 | EM15: 0.2 | EN15: 0.2 | EO15: 0.2 | EQ15: 0 | ER15: 0 | ES15: 0 | ET15: -0.2 | EU15: -0.8 | EV15: 0 | EW15: 0 | EX15: 0 | EY15: 0.4 | EZ15: 1.6 | FB15: 4.2 | FD15: 1.8 | FE15: 2.7 | FF15: 2.1 | FI15: -91.95 | FK15: 2.20995 | FL15: 0 | FN15: 1.73116 | FP15: 2.682 | FQ15: -0.6 | FR15: 0.4 | FS15: 6.42311
A16: 26/04/2025 | B16: 03:00 | E16: 9.16 | F16: 40.4 | G16: 20.6 | J16: -17.9 | K16: -1.3 | N16: -36.7 | O16: -45.9 | P16: -31.7 | Q16: 21.2 | R16: -9.8 | S16: 8 | T16: 48.8 | U16: 0 | Z16: -2.2 | AA16: 1.4 | AC16: -3.3 | AD16: 3.2 | AE16: 1.4 | AF16: 1 | AJ16: 4.9 | AK16: 14 | AO16: -1.5 | AP16: 15.9 | AQ16: 9 | AR16: 6.9 | AS16: -1 | AT16: 0.1 | AU16: 2.6 | AV16: 0 | AW16: 0 | AY16: 0 | AZ16: 8.9 | BA16: -0.2 | BB16: 0.7 | BC16: -1.8 | BD16: 1.5 | BE16: 1 | BF16: -0.1 | BG16: 1.4 | BH16: -5.2 | BK16: 1.3 | BO16: 0.5 | BP16: -42.1 | BQ16: 0 | BR16: -18.4 | BS16: -28.3 | CB16: -0.4 | CC16: 8.9 | CD16: 17.2 | CE16: 3.1 | CF16: 2.3 | CG16: -0.2 | CK16: -0.6 | CL16: 2 | CM16: -46.8 | CV16: -1.9 | CW16: 0 | CX16: 0 | CZ16: 0 | DA16: 0.1 | DB16: -0.9 | DD16: 0 | DE16: 1.5 | DF16: 1.9 | DG16: -1.5 | DH16: 0.1 | DI16: 0.5 | DJ16: 0 | DK16: 0 | DL16: 0 | DM16: -5.1 | DN16: -1.2 | DO16: 0 | DP16: 0.5 | DQ16: 0.7 | DS16: 0 | DT16: 0.1 | DU16: 0.3 | DV16: 0 | DX16: -4.9 | DY16: 0.8 | DZ16: 1.4 | EA16: 2 | EB16: 1.3 | EC16: 0.8 | ED16: 4 | EE16: 0 | EF16: -8.2 | EG16: -9.2 | EH16: 0 | EI16: 0 | EJ16: 2.6 | EK16: -0.1 | EL16: 1.9 | EM16: 0.2 | EN16: 0.2 | EO16: 0.2 | EQ16: 0 | ER16: 0 | ES16: 0 | ET16: -0.2 | EU16: -1.8 | EV16: 0 | EW16: 0 | EX16: 0 | EY16: 0.4 | EZ16: 1.6 | FB16: 5.4 | FD16: 1.8 | FE16: 2.8 | FF16: 2.9 | FI16: -37.04 | FK16: 2.42005 | FL16: 0 | FN16: 1.68875 | FP16: 2.67102 | FQ16: 0 | FR16: 2 | FS16: 8.77982
A17: 26/04/2025 | B17: 03:30 | E17: 9.13 | F17: 46 | G17: 20.5 | J17: -14.6 | K17: 12.2 | N17: -36 | O17: -48.2 | P17: -33.7 | Q17: 22 | R17: -8.7 | S17: 8.4 | T17: 46.7 | U17: 0 | Z17: -2.2 | AA17: 1.2 | AC17: -3.3 | AD17: 3 | AE17: 1.1 | AF17: 1 | AJ17: 4.4 | AK17: 13.4 | AO17: -1.5 | AP17: 15 | AQ17: 9.1 | AR17: 8.6 | AS17: -0.7 | AT17: 0.1 | AU17: 2.7 | AV17: 0.5 | AW17: 8.3 | AY17: 0 | AZ17: 3.9 | BA17: -0.2 | BB17: 0.6 | BC17: -2.4 | BD17: 2.5 | BE17: 1 | BF17: -0.1 | BG17: 0.5 | BH17: -5 | BK17: 3.2 | BO17: 2.8 | BP17: -42.3 | BQ17: 0 | BR17: -18.4 | BS17: -27.9 | CB17: -0.3 | CC17: 2.7 | CD17: 19.3 | CE17: 3.9 | CF17: 2.2 | CG17: -0.2 | CK17: -0.5 | CL17: 2.2 | CM17: -46.9 | CV17: -1.8 | CW17: 0 | CX17: 0 | CZ17: 0 | DA17: 0.1 | DB17: -0.9 | DD17: 0 | DE17: 1.5 | DF17: 1.9 | DG17: -0.8 | DH17: 0 | DI17: 0.6 | DJ17: 0 | DK17: 0 | DL17: 0 | DM17: -5 | DN17: -0.9 | DO17: 0 | DP17: 0.5 | DQ17: 0.7 | DS17: 0 | DT17: 0.3 | DU17: 0.2 | DV17: 0 | DX17: -4.6 | DY17: 0.6 | DZ17: 1.4 | EA17: 2.1 | EB17: 1.3 | EC17: 0.8 | ED17: 4 | EE17: 0 | EF17: -7.8 | EG17: -8.7 | EH17: 0 | EI17: 0 | EJ17: 2.6 | EK17: -0.1 | EL17: 1.9 | EM17: 0.2 | EN17: 0.2 | EO17: 0.2 | EQ17: 0 | ER17: 0 | ES17: 0 | ET17: -0.2 | EU17: -1.5 | EV17: 0 | EW17: 0 | EX17: 0 | EY17: 0.4 | EZ17: 1.6 | FB17: 6 | FD17: 1.8 | FE17: 2.8 | FF17: 2.5 | FI17: -11.07 | FK17: 2.35941 | FL17: 0 | FN17: 1.7495 | FP17: 2.68814 | FQ17: 0 | FR17: 2 | FS17: 8.79705
A18: 26/04/2025 | B18: 04:00 | E18: 9.04 | F18: 59.6 | G18: 22.3 | J18: -12.8 | K18: 12.9 | N18: -34.3 | O18: -48.4 | P18: -35.4 | Q18: 22.2 | R18: -9.4 | S18: 10.2 | T18: 48.7 | U18: 0 | Z18: 0 | AA18: 1.4 | AC18: -3.4 | AD18: 3.2 | AE18: 1.1 | AF18: 1.1 | AJ18: 4.4 | AK18: 13.1 | AO18: -1.5 | AP18: 9.7 | AQ18: 9.4 | AR18: 10.5 | AS18: -1 | AT18: 0 | AU18: 2.7 | AV18: 0.9 | AW18: 10.6 | AY18: 0 | AZ18: 2.8 | BA18: -0.3 | BB18: 0.6 | BC18: -1.3 | BD18: 3.6 | BE18: 1 | BF18: -0.2 | BG18: 3.8 | BH18: -5.2 | BK18: 3.8 | BO18: 3.3 | BP18: -42.3 | BQ18: 0 | BR18: -18.2 | BS18: -27.2 | CB18: -0.3 | CC18: 2.2 | CD18: 19.2 | CE18: 4.2 | CF18: 3.5 | CG18: -0.1 | CK18: -0.9 | CL18: 2.7 | CM18: -47.4 | CV18: -1.7 | CW18: 0 | CX18: 0 | CZ18: 0 | DA18: 0.1 | DB18: -0.9 | DD18: 0 | DE18: 1.5 | DF18: 1.8 | DG18: -1.2 | DH18: 0.1 | DI18: 0.5 | DJ18: 0 | DK18: 0 | DL18: 0 | DM18: -4.9 | DN18: -0.3 | DO18: 0 | DP18: 0.5 | DQ18: 0.7 | DS18: 0 | DT18: 0.2 | DU18: 0.3 | DV18: 0 | DX18: -4.6 | DY18: 0.7 | DZ18: 1.5 | EA18: 2.1 | EB18: 1.4 | EC18: 0.8 | ED18: 4 | EE18: 0 | EF18: -6.6 | EG18: -7.5 | EH18: 0 | EI18: 0 | EJ18: 2.6 | EK18: -0.1 | EL18: 1.9 | EM18: 0.2 | EN18: 0.2 | EO18: 0.2 | EQ18: 0 | ER18: 0 | ES18: 0 | ET18: -0.2 | EU18: 0.3 | EV18: 0 | EW18: 0 | EX18: 0 | EY18: 1.2 | EZ18: 1.6 | FB18: 6.8 | FD18: 1.8 | FE18: 2.8 | FF18: 3.2 | FI18: 25.14 | FK18: 2.31525 | FL18: 0 | FN18: 1.73607 | FP18: 2.68481 | FQ18: 0 | FR18: 2 | FS18: 8.73613
A19: 26/04/2025 | B19: 04:30 | E19: 8.36 | F19: 41.8 | G19: 19.9 | J19: -15.1 | K19: 5.7 | N19: -37.2 | O19: -48.7 | P19: -33.8 | Q19: 20 | R19: -9 | S19: 8.4 | T19: 47.7 | U19: 0 | Z19: -2 | AA19: 1.8 | AC19: -3.4 | AD19: 3.2 | AE19: 1.6 | AF19: 1.1 | AJ19: 4 | AK19: 13.7 | AO19: -1.3 | AP19: 40.7 | AQ19: 10.2 | AR19: 8.2 | AS19: -1.5 | AT19: 0 | AU19: 2.6 | AV19: 1 | AW19: 7.5 | AY19: 0 | AZ19: 5.2 | BA19: -0.3 | BB19: 0.5 | BC19: -2.4 | BD19: 2.6 | BE19: 1 | BF19: -0.1 | BG19: 2.9 | BH19: -4.9 | BK19: 3 | BO19: 1.3 | BP19: -42.6 | BQ19: 0 | BR19: -18.6 | BS19: -28.6 | CB19: -0.3 | CC19: 3 | CD19: 17.7 | CE19: 3.6 | CF19: 3.3 | CG19: -0.2 | CK19: -0.8 | CL19: 1.9 | CM19: -47.4 | CV19: -1.7 | CW19: 0 | CX19: 0 | CZ19: 0 | DA19: 0.1 | DB19: -0.9 | DD19: 0 | DE19: 1.6 | DF19: 1.8 | DG19: -1.5 | DH19: 0.1 | DI19: 0.5 | DJ19: 0.1 | DK19: 0 | DL19: 0 | DM19: -4.9 | DN19: -0.2 | DO19: 0 | DP19: 0.5 | DQ19: 0.7 | DS19: 0 | DT19: 0.2 | DU19: 0.3 | DV19: 0 | DX19: -4.7 | DY19: 0.8 | DZ19: 1.4 | EA19: 2.1 | EB19: 1.4 | EC19: 0.8 | ED19: 4 | EE19: 0 | EF19: -6.7 | EG19: -10.6 | EH19: 0 | EI19: 0 | EJ19: 2.6 | EK19: -0.1 | EL19: 1.9 | EM19: 0.2 | EN19: 0.2 | EO19: 0.2 | EQ19: 0 | ER19: 0 | ES19: 0 | ET19: -0.2 | EU19: -0.8 | EV19: 0 | EW19: 0 | EX19: 0 | EY19: 1.2 | EZ19: 1.7 | FB19: 6 | FD19: 1.8 | FE19: 2.9 | FF19: 2.4 | FI19: 0.46 | FK19: 2.48019 | FL19: 0 | FN19: 1.63735 | FP19: 2.68048 | FQ19: 0 | FR19: 1.9 | FS19: 8.69802
A20: 26/04/2025 | B20: 05:00 | E20: 9.09 | F20: 61.3 | G20: 23.1 | J20: -11.4 | K20: 13.4 | N20: -34.8 | O20: -41.9 | P20: -26.9 | Q20: 22.7 | R20: -6.6 | S20: 9.6 | T20: 53.5 | U20: 0 | Z20: 1.8 | AA20: 2 | AC20: -3.3 | AD20: 3.2 | AE20: 1.9 | AF20: 1.1 | AJ20: 4.5 | AK20: 14.7 | AO20: -1.3 | AP20: 49.7 | AQ20: 9.4 | AR20: 7.7 | AS20: -1.3 | AT20: 0 | AU20: 2.6 | AV20: 1.6 | AW20: 11.8 | AY20: 0 | AZ20: 9.1 | BA20: -0.3 | BB20: 0.5 | BC20: -0.6 | BD20: 4.4 | BE20: 0.9 | BF20: -0.2 | BG20: 5.2 | BH20: -4 | BK20: 0 | BO20: 6.9 | BP20: -40.6 | BQ20: 0 | BR20: -16.3 | BS20: -25.8 | CB20: -0.3 | CC20: 2.7 | CD20: 17.3 | CE20: 3.4 | CF20: 2.2 | CG20: -0.2 | CK20: 2.7 | CL20: 5.3 | CM20: -42.6 | CV20: -1.9 | CW20: 0 | CX20: 0 | CZ20: 0 | DA20: 0.1 | DB20: -0.9 | DD20: 0 | DE20: 1.5 | DF20: 1.9 | DG20: -1.6 | DH20: 0 | DI20: 0.5 | DJ20: 0 | DK20: 0 | DL20: 0 | DM20: -4.7 | DN20: -0.2 | DO20: 0 | DP20: 0.5 | DQ20: 0.7 | DS20: 0.2 | DT20: 0.4 | DU20: 0.3 | DV20: 0 | DX20: -4.6 | DY20: 1.1 | DZ20: 1.5 | EA20: 2.2 | EB20: 1.4 | EC20: 0.8 | ED20: 4 | EE20: 0.4 | EF20: -4.3 | EG20: -6.7 | EH20: 0 | EI20: 0 | EJ20: 2.6 | EK20: -0.1 | EL20: 1.8 | EM20: 0.2 | EN20: 0.2 | EO20: 0.2 | EQ20: 0 | ER20: 0 | ES20: 0 | ET20: -0.2 | EU20: 0.4 | EV20: 0 | EW20: 0 | EX20: 0 | EY20: 1.2 | EZ20: 1.8 | FB20: 10.5 | FD20: 1.8 | FE20: 2.3 | FF20: 2.9 | FI20: 125.09 | FK20: 2.34174 | FL20: 0 | FN20: 1.67972 | FP20: 2.68236 | FQ20: 0 | FR20: 2 | FS20: 8.70382
A21: 26/04/2025 | B21: 05:30 | E21: 9.59 | F21: 53 | G21: 21.7 | J21: -13.7 | K21: 3.6 | N21: -30.9 | O21: -48.5 | P21: -34.3 | Q21: 29.4 | R21: -6 | S21: 10.7 | T21: 51.5 | U21: 0 | Z21: 1.2 | AA21: 1.8 | AC21: -3.4 | AD21: 3.3 | AE21: 2.6 | AF21: 1.2 | AJ21: 4.1 | AK21: 14.9 | AO21: -1.5 | AP21: 49.1 | AQ21: 5.1 | AR21: 8.4 | AS21: -1.3 | AT21: 0.3 | AU21: 2.6 | AV21: 0.7 | AW21: 12.1 | AY21: 0 | AZ21: 8.3 | BA21: -0.4 | BB21: 0.4 | BC21: -4.7 | BD21: 2.3 | BE21: 1 | BF21: -0.1 | BG21: 0.7 | BH21: -4.5 | BK21: 0 | BO21: 6.9 | BP21: -39.4 | BQ21: 0 | BR21: -15.7 | BS21: -26.1 | CB21: -0.3 | CC21: 3 | CD21: 20 | CE21: 4.6 | CF21: 2.2 | CG21: -0.1 | CK21: 3.4 | CL21: 6.4 | CM21: -40.8 | CV21: -1.7 | CW21: 0 | CX21: 0 | CZ21: 0 | DA21: 0.1 | DB21: -0.9 | DD21: -0.2 | DE21: 1.4 | DF21: 0 | DG21: -1.3 | DH21: 0.1 | DI21: 0.5 | DJ21: 0 | DK21: 0 | DL21: 0 | DM21: -4.4 | DN21: 0.8 | DO21: 0 | DP21: 0.5 | DQ21: 0.7 | DS21: 0.3 | DT21: 0.2 | DU21: 0.3 | DV21: 0 | DX21: -4.6 | DY21: 0.6 | DZ21: 1.3 | EA21: 2.2 | EB21: 1.5 | EC21: 0.8 | ED21: 4 | EE21: 0.4 | EF21: -5.6 | EG21: -6.2 | EH21: 0 | EI21: 0 | EJ21: 2.6 | EK21: -0.1 | EL21: 2 | EM21: 0.2 | EN21: 0.2 | EO21: 0.2 | EQ21: 0 | ER21: 0 | ES21: 0 | ET21: -0.2 | EU21: 1.2 | EV21: 0 | EW21: 0 | EX21: 0 | EY21: 1.2 | EZ21: 1.8 | FB21: 6.7 | FD21: 1.8 | FE21: 2.5 | FF21: 2.7 | FI21: 87.99 | FK21: 1.74257 | FL21: 0 | FN21: 1.75843 | FP21: 2.67225 | FQ21: 0 | FR21: 2.2 | FS21: 8.37325
A22: 26/04/2025 | B22: 06:00 | E22: 10.22 | F22: 56.7 | G22: 22.2 | J22: -10 | K22: 16.2 | N22: -31.2 | O22: -46.5 | P22: -31.7 | Q22: 27.3 | R22: -3.6 | S22: 12 | T22: 55.4 | U22: 0 | Z22: 2.8 | AA22: 1.7 | AC22: -3.4 | AD22: 3.4 | AE22: 2.5 | AF22: 1.3 | AJ22: 4.4 | AK22: 13.9 | AO22: -1.7 | AP22: 45.8 | AQ22: 4.7 | AR22: 8.6 | AS22: -0.3 | AT22: 0.1 | AU22: 2.6 | AV22: 1.1 | AW22: 16.2 | AY22: 0 | AZ22: 8.5 | BA22: -0.6 | BB22: 0.2 | BC22: -4.9 | BD22: 3.8 | BE22: 1 | BF22: -0.1 | BG22: 0.6 | BH22: -3.3 | BK22: 0 | BO22: 6.6 | BP22: -36.2 | BQ22: 0 | BR22: -12.1 | BS22: -22.2 | CB22: -0.4 | CC22: 8.2 | CD22: 24.2 | CE22: 3.8 | CF22: 2.1 | CG22: 0 | CK22: 5.3 | CL22: 8.2 | CM22: -38 | CV22: -1.9 | CW22: 0 | CX22: 0 | CZ22: 0.8 | DA22: 0.1 | DB22: -0.8 | DD22: 0 | DE22: 1.3 | DF22: 0 | DG22: -0.9 | DH22: 0.1 | DI22: 0.6 | DJ22: 0 | DK22: 0 | DL22: 0.8 | DM22: -4.6 | DN22: 1.4 | DO22: 0 | DP22: 0.5 | DQ22: 0.7 | DS22: 0.3 | DT22: 0.2 | DU22: 0.3 | DV22: 0 | DX22: -4.7 | DY22: 0.5 | DZ22: 1.4 | EA22: 2.3 | EB22: 1.5 | EC22: 0.8 | ED22: 4 | EE22: 0.3 | EF22: -6 | EG22: -7.4 | EH22: 0 | EI22: 0 | EJ22: 2.6 | EK22: 0 | EL22: 1.8 | EM22: 0.2 | EN22: 0.2 | EO22: 0.2 | EQ22: 17.93 | ER22: 0 | ES22: 2.2 | ET22: -0.2 | EU22: -0.1 | EV22: 0 | EW22: 0 | EX22: 0 | EY22: 1.2 | EZ22: 1.8 | FB22: 9.7 | FD22: 1.8 | FE22: 0.8 | FF22: 3.2 | FI22: 170.35 | FK22: 1.6158 | FL22: 0 | FN22: 1.74713 | FP22: 1.78889 | FQ22: 0 | FR22: 2 | FS22: 7.15182
... A58: 27/04/2025 | B58: 00:00 | E58: 0 | F58: 19.5 | G58: 15.6 | J58: -22.9 | K58: -6.7 | N58: -35.8 | O58: -29.6 | P58: -31.3 | Q58: 4.7 | R58: -31.4 | S58: -32.9 | T58: 57 | U58: 0.1 | Z58: -2.8 | AA58: 0.9 | AC58: -3.3 | AD58: 2.2 | AE58: 4.6 | AF58: 1.1 | AJ58: 10 | AK58: 0.9 | AO58: -1.8 | AP58: 17.3 | AQ58: 9.9 | AR58: 9.2 | AS58: -0.2 | AT58: -0.3 | AU58: 2.7 | AV58: 1.2 | AW58: 5.1 | AY58: -57.2 | AZ58: 6.4 | BA58: -1.2 | BB58: 0.2 | BC58: -0.7 | BD58: -0.2 | BE58: 1 | BF58: -0.1 | BG58: 1 | BH58: -3.4 | BK58: 0 | BO58: 2.6 | BP58: -46.2 | BQ58: 0 | BR58: -7.7 | BS58: -21.7 | CB58: -0.3 | CC58: 17.1 | CD58: 23.6 | CE58: 7.2 | CF58: 11.2 | CG58: 1.9 | CK58: 0 | CL58: -6.6 | CM58: -56.9 | CV58: -1.8 | CW58: 0 | CX58: 0 | CZ58: 1.5 | DA58: 0 | DB58: -0.9 | DD58: 0.2 | DE58: 1.1 | DF58: 1.3 | DG58: -1.9 | DH58: 0.1 | DI58: 0.6 | DJ58: 0.1 | DK58: 0 | DL58: 0 | DM58: 0.9 | DN58: 2.5 | DO58: 0 | DP58: 0.5 | DQ58: 0.7 | DS58: 0 | DT58: 0.1 | DU58: 0.7 | DV58: 0.5 | DX58: -4.8 | DY58: 0.1 | DZ58: 1.7 | EA58: 2.5 | EB58: 1.1 | EC58: 0.8 | ED58: 17.3 | EE58: 0 | EF58: -12.7 | EG58: -13 | EH58: 0 | EI58: 0 | EJ58: 2.6 | EK58: -0.4 | EL58: 1.8 | EM58: 0.2 | EN58: 0.2 | EO58: 0.2 | EQ58: 0 | ER58: 0 | ES58: 0 | ET58: -0.2 | EU58: -0.5 | EV58: 0 | EW58: 0 | EX58: 0 | EY58: 0.4 | EZ58: 1.3 | FB58: 12.4 | FD58: 1.9 | FE58: 2.2 | FF58: 2.7 | FI58: -143 | FK58: 2.27545 | FL58: -0.366 | FN58: 1.79453 | FP58: 4.0989 | FQ58: 0 | FR58: 2 | FS58: 9.80288
A59: EJEC | C59: 0 | D59: 0 | E59: 129.15 | F59: 2045.6 | G59: 694.15 | H59: 0 | I59: 0 | J59: -212.45 | K59: 359.6 | L59: 0 | M59: 0 | N59: -377.5 | O59: -575.1 | P59: -229.35 | Q59: 723.8 | R59: -156.1 | S59: 55.35 | T59: 1054.55 | U59: 1.25 | V59: 0 | W59: 0 | X59: 0 | Y59: 0 | Z59: 51.8 | AA59: 33.45 | AB59: 0 | AC59: -79.65 | AD59: 84.5 | AE59: 217.75 | AF59: 45.1 | AG59: 0 | AH59: 0 | AI59: 0 | AJ59: 187.35 | AK59: 328.45 | AL59: 0 | AM59: 0 | AN59: 0 | AO59: -31.05 | AP59: 1110.7 | AQ59: 159 | AR59: 251.55 | AS59: 20.75 | AT59: -6.95 | AU59: 63.85 | AV59: 22.9 | AW59: 518.2 | AX59: 0 | AY59: -126.7 | AZ59: 211.25 | BA59: -30.4 | BB59: 7.45 | BC59: -45.4 | BD59: 58.8 | BE59: 23.65 | BF59: -1.1 | BG59: 45.9 | BH59: 26.75 | BI59: 0 | BJ59: 0 | BK59: 9.3 | BL59: 0 | BM59: 0 | BN59: 0 | BO59: 225.15 | BP59: -857.7 | BQ59: -0.25 | BR59: -208 | BS59: -420.1 | BT59: 0 | BU59: 0 | BV59: 0 | BW59: 0 | BX59: 0 | BY59: 0 | BZ59: 0 | CA59: 0 | CB59: -7.55 | CC59: 1258.8 | CD59: 897.05 | CE59: 232.5 | CF59: 246.3 | CG59: 71 | CH59: 0 | CI59: 0 | CJ59: 0 | CK59: 251.45 | CL59: 559.25 | CM59: -260.3 | CN59: 0 | CO59: 0 | CP59: 0 | CQ59: 0 | CR59: 0 | CS59: 0 | CT59: 0 | CU59: 0 | CV59: -41.95 | CW59: 65.7 | CX59: 0.1 | CY59: 0 | CZ59: 27.1 | DA59: 0.4 | DB59: -21.9 | DC59: 0 | DD59: -1.65 | DE59: 26.7 | DF59: 10.55 | DG59: -13.05 | DH59: 2.25 | DI59: 13.45 | DJ59: 1.05 | DK59: -6.95 | DL59: 155.55 | DM59: -69.55 | DN59: 62.55 | DO59: 1.8 | DP59: 12 | DQ59: 16.9 | DR59: 0 | DS59: -26.25 | DT59: 0.85 | DU59: 13.15 | DV59: 2.1 | DW59: 0 | DX59: -111.85 | DY59: 17.85 | DZ59: 38.6 | EA59: 59.7 | EB59: 36.25 | EC59: 19.2 | ED59: 115.4 | EE59: 21.85 | EF59: -123.55 | EG59: -150 | EH59: 1.3 | EI59: 1.6 | EJ59: 62.4 | EK59: -1 | EL59: 45.8 | EM59: 4.8 | EN59: 4.8 | EO59: 4.8 | EP59: 0 | EQ59: 237.609 | ER59: 16.3 | ES59: 132.4 | ET59: -4.8 | EU59: 178.7 | EV59: 116.95 | EW59: 82.95 | EX59: 13.3 | EY59: 17 | EZ59: 43.8 | FA59: 0 | FB59: 204.85 | FC59: 0 | FD59: 44.1 | FE59: 45.4 | FF59: 61.9 | FG59: 0 | FH59: 0 | FI59: 10127.059 | FK59: 51.26404 | FL59: -6.478 | FM59: 0 | FN59: 41.234945 | FO59: 0 | FP59: 68.78758 | FQ59: -0.2 | FR59: 48.55 | FS59: 203.15857

Sheet DEMANDA_AREAS
B3: sábado, 26 de Abril del 2025
B5: REPORTE DE LA DEMANDA POR ÁREAS Y SUBAREAS OPERATIVAS (MW)
B6: FECHA HORA | C6: DEMANDA | E6: AREA | H6: SUBAREAS
C7: INTERCAMBIOS INTERNACIONALES | D7: SEIN | E7: NORTE | F7: CENTRO | G7: SUR | H7: ELECTROANDES
B8: 00:30 | C8: 0 | D8: 6674.65 | E8: 977.4535 | F8: 3885.1107 | G8: 1812.0858 | H8: 225.7243
B9: 01:00 | C9: 0 | D9: 6561.31 | E9: 945.7261 | F9: 3810.7282 | G9: 1804.8557 | H9: 227.1589
B10: 01:30 | C10: 0 | D10: 6450.74 | E10: 947.1882 | F10: 3723.0555 | G10: 1780.4963 | H10: 217.725
B11: 02:00 | C11: 0 | D11: 6379.92 | E11: 932.7172 | F11: 3673.4366 | G11: 1773.7662 | H11: 222.4967
B12: 02:30 | C12: 0 | D12: 6314.17 | E12: 932.7484 | F12: 3608.8152 | G12: 1772.6064 | H12: 219.4224
B13: 03:00 | C13: 0 | D13: 6385.49 | E13: 919.8269 | F13: 3716.1798 | G13: 1749.4833 | H13: 224.6323
B14: 03:30 | C14: 0 | D14: 6401.17 | E14: 964.8677 | F14: 3682.5316 | G14: 1753.7707 | H14: 223.027
B15: 04:00 | C15: 0 | D15: 6395.19 | E15: 958.498 | F15: 3659.0952 | G15: 1777.5968 | H15: 223.455
B16: 04:30 | C16: 0 | D16: 6332.93 | E16: 954.3525 | F16: 3603.427 | G16: 1775.1505 | H16: 219.3789
B17: 05:00 | C17: 0 | D17: 6506.65 | E17: 975.0516 | F17: 3726.4383 | G17: 1805.1601 | H17: 223.0187
B18: 05:30 | C18: 0 | D18: 6469.55 | E18: 961.9121 | F18: 3717.1466 | G18: 1790.4913 | H18: 207.7377
B19: 06:00 | C19: 0 | D19: 6573.63 | E19: 1027.0311 | F19: 3747.1595 | G19: 1799.4394 | H19: 202.0125
... B59: ENERGÍA | C59: 0 | D59: 170623.94 | E59: 26628.75 | F59: 99954.306 | G59: 44040.883 | H59: 5028.2173
B61: LEYENDA:
D63: Potencia recibida del Ecuador
D64: Potencia entregada al Ecuador

Sheet DEMANDA_UL
B3: sábado, 26 de Abril del 2025
B5: POTENCIA DE LOS GRANDES USUARIOS LIBRES (MW)
B6: FECHA HORA | C6: GRANDES USUARIOS LIBRES DEL ÁREA NORTE | X6: GRANDES USUARIOS LIBRES DEL ÁREA CENTRO | BP6: GRANDES USUARIOS LIBRES DEL ÁREA SUR
C7: ARCA CONTINENTAL LINDLEY S.A. | D7: AUSTRAL GROUP S.A.A | E7: CEMENTOS PACASMAYO | F7: CONSORCIO MINERO HORIZONTE S.R.L. | G7: CORPORACIÓN PESQUERA INCA S.A.C. | H7: CREDITEX: CIA IND.TEXTIL CREDISA | I7: HIPERMERCADOS TOTTUS S.A | J7: INDUSTRIA TEXTIL PIURA | K7: MINERA BOROO MISQUICHILCA S.A. | L7: MINERA GOLD FIELDS | M7: MINERA MARSA | N7: MINERA MISKY MAYO | O7: MINERA YANACOCHA | P7: OPEN PLAZA | Q7: PESQUERA DIAMANTE | R7: PETROPERU | S7: REAL PLAZA S.R.L. | T7: SIDER PERU | U7: SUPERMERCADOS PERUANOS S.A. | V7: TRUPAL S.A. | W7: UNIÓN DE CERVECERÍAS PERUANAS BACKUS Y JOHNSTON S. | X7: ACEROS AREQUIPA | Y7: ADMINISTRADORA JOCKEY PLAZA SHOPPING CENTER S.A. | Z7: ALICORP | AA7: ARCA CONTINENTAL LINDLEY S.A. | AB7: AUSTRAL GROUP S.A.A | AC7: COMPAÑIA MINERA CONDESTABLE | AD7: CORPORACIÓN PESQUERA INCA S.A.C. | AE7: CREDITEX: CIA IND.TEXTIL CREDISA | AF7: FUNDICION CHILCA S.A. | AG7: HIPERMERCADOS TOTTUS S.A | AH7: INMOBILIARIA KANPU S.A. | AI7: INMUEBLES PANAMERICANA S.A. | AJ7: KIMBERLY-CLARK PERU | AK7: LECHE GLORIA S.A. | AL7: MALL AVENTURA S.A. | AM7: MARCOBRE S.A.C. | AN7: MINERA ANTAMINA | AO7: MINERA ARES | AP7: MINERA BUENAVENTURA | AQ7: MINERA CHINALCO PERÚ S.A. | AR7: MINERA SHOUXIN PERU S.A. | AS7: MINERA VOLCAN | AT7: MINSUR | AU7: MOLYCOP-ADESUR | AV7: NEXA RESOURCES CAJAMARQUILLA S.A. | AW7: NEXA RESOURCES PERÚ S.A.A. | AX7: OPEN PLAZA | AY7: OPP FILM | AZ7: OWENS-ILLINOIS PERÚ S.A. | BA7: PAPELERA NACIONAL S.A. | BB7: PESQUERA DIAMANTE | BC7: QUIMPAC S.A. | BD7: REAL PLAZA S.R.L. | BE7: REFINERIA LA PAMPILLA S.A.A | BF7: SAGA FALABELLA | BG7: SAN MIGUEL INDUSTRIAS PET S.A. | BH7: SHOUGANG HIERRO PERU | BI7: SOFTYS PERU S.A.C. | BJ7: SUPERMERCADOS PERUANOS S.A. | BK7: TEJIDOS SAN JACINTO | BL7: TREN URBANO DE LIMA S.A. | BM7: TRUPAL S.A. | BN7: UNACEM PERU S.A. | BO7: UNIÓN DE CERVECERÍAS PERUANAS BACKUS Y JOHNSTON S. | BP7: ANGLO AMERICAN QUELLAVECO S.A. | BQ7: ARCA CONTINENTAL LINDLEY S.A. | BR7: CAL & CEMENTO SUR S.A. | BS7: COMPAÑIA MINERA ANTAPACCAY S.A. | BT7: COMPAÑÍA MINERA CHUNGAR SAC | BU7: COMPAÑIA MINERA SAN IGNACIO DE MOROCOCHA S.A.A. | BV7: EL BROCAL .S.A. | BW7: EMPRESA ADMINISTRADORA CERRO S.A.C. | BX7: EMPRESA MINERA LOS QUENUALES S.A.C. | BY7: HIPERMERCADOS TOTTUS S.A | BZ7: HUDBAY PERU S.A.C. | CA7: INDUSTRIA CACHIMAYO | CB7: MALL AVENTURA S.A. | CC7: MINERA ARES | CD7: MINERA BUENAVENTURA | CE7: MINERA CERRO VERDE | CF7: MINERA CORONA | CG7: MINERA LAS BAMBAS S.A. | CH7: MINERA VOLCAN | CI7: MINSUR | CJ7: MOLYCOP-ADESUR | CK7: NEXA RESOURCES PERÚ S.A.A. | CL7: OXIDOS DE PASCO S.A.C. | CM7: PESQUERA DIAMANTE | CN7: REAL PLAZA S.R.L. | CO7: SOBREANDES S.A.C. | CP7: SOUTHERN PERU CC | CQ7: SUPERMERCADOS PERUANOS S.A. | CR7: UNACEM PERU S.A. | CS7: UNIÓN DE CERVECERÍAS PERUANAS BACKUS Y JOHNSTON S. | CT7: YURA
B8: 00:30 | E8: 33.30741 | F8: 12.67 | K8: 19.915 | L8: 27.5491 | M8: 13.1998 | N8: 13.18 | O8: 31.64 | R8: 46.745 | T8: 12.3363 | V8: 9.4 | X8: 36.26837 | Z8: 6.67095 | AF8: 2.7 | AJ8: 5.33786 | AK8: 0 | AL8: 1.1634 | AM8: 51.5373 | AN8: 23.73336 | AO8: 29.6189 | AP8: 0.81 | AQ8: 163 | AS8: 37.26185 | AT8: 32.26 | AV8: 194.6738 | AW8: 38.4602 | BA8: 5.3 | BC8: 70.60463 | BE8: 19.02 | BI8: 15.98149 | BK8: 5.50124 | BN8: 59.08 | BO8: 2.39 | BP8: 153.88088 | BR8: 4.70197 | BS8: 111.99692 | BT8: 15.01297 | BV8: 32.6214 | BW8: 3.85819 | BZ8: 87.42944 | CA8: 22.628 | CB8: 0.3323 | CC8: 0.669 | CD8: 27.7011 | CE8: 469.05984 | CF8: 11.135 | CG8: 159.242 | CH8: 18.047 | CK8: 15.581 | CL8: 5.05326 | CO8: 14.49044 | CP8: 293.96 | CR8: 38.433 | CT8: 12.74333
B9: 01:00 | E9: 31.87867 | F9: 13.212 | K9: 19.8732 | L9: 27.6967 | M9: 13.4278 | N9: 13.76 | O9: 31.064 | R9: 46.607 | T9: 11.9633 | V9: 9.5 | X9: 34.45499 | Z9: 7.01915 | AF9: 3.2 | AJ9: 5.33431 | AK9: 0 | AL9: 1.0619 | AM9: 50.3964 | AN9: 23.6654 | AO9: 28.9997 | AP9: 0.7 | AQ9: 162.91 | AS9: 36.27383 | AT9: 32.37 | AV9: 197.80451 | AW9: 38.926 | BA9: 5.1 | BC9: 70.76434 | BE9: 19.02 | BI9: 15.70607 | BK9: 5.62551 | BN9: 58.47 | BO9: 2.27 | BP9: 152.09854 | BR9: 4.68022 | BS9: 110.29839 | BT9: 14.82365 | BV9: 32.325 | BW9: 3.96348 | BZ9: 87.56466 | CA9: 22.706 | CB9: 0.315 | CC9: 0.7 | CD9: 26.45295 | CE9: 468.7223 | CF9: 10.9824 | CG9: 154.5187 | CH9: 17.9718 | CK9: 15.7088 | CL9: 5.09391 | CO9: 14.6518 | CP9: 295.32 | CR9: 39.213 | CT9: 14.74158
B10: 01:30 | E10: 30.87913 | F10: 13.424 | K10: 19.9714 | L10: 27.4225 | M10: 13.773 | N10: 13.22 | O10: 29.964 | R10: 46.61 | T10: 9.5742 | V10: 9.5 | X10: 34.22214 | Z10: 8.23074 | AF10: 5.6 | AJ10: 5.31128 | AK10: 0 | AL10: 0.972 | AM10: 51.0576 | AN10: 23.5413 | AO10: 29.2239 | AP10: 0.64 | AQ10: 162.37 | AS10: 35.072 | AT10: 32.25 | AV10: 197.40896 | AW10: 39.4726 | BA10: 5.2 | BC10: 70.60113 | BE10: 19.02 | BI10: 16.0557 | BK10: 5.652 | BN10: 57.93 | BO10: 2.39 | BP10: 152.42272 | BR10: 4.64027 | BS10: 109.88705 | BT10: 14.95703 | BV10: 32.7976 | BW10: 4.0073 | BZ10: 87.17741 | CA10: 22.796 | CB10: 0.307 | CC10: 0.676 | CD10: 26.39493 | CE10: 462.14029 | CF10: 10.9754 | CG10: 155.1982 | CH10: 18.01368 | CK10: 15.0196 | CL10: 4.91373 | CO10: 14.20658 | CP10: 293.38 | CR10: 39.433 | CT10: 16.11471
B11: 02:00 | E11: 31.46839 | F11: 13.179 | K11: 19.8968 | L11: 27.5765 | M11: 14.4418 | N11: 13.26 | O11: 30.444 | R11: 46.887 | T11: 11.8238 | V11: 9.6 | X11: 41.04491 | Z11: 8.59473 | AF11: 4.7 | AJ11: 5.27359 | AK11: 0 | AL11: 0.9678 | AM11: 49.3972 | AN11: 23.54924 | AO11: 29.0068 | AP11: 0.44 | AQ11: 163.92 | AS11: 36.69367 | AT11: 31.82 | AV11: 196.84119 | AW11: 39.45 | BA11: 4.9 | BC11: 70.53856 | BE11: 19.02 | BI11: 15.97139 | BK11: 5.65372 | BN11: 58.4 | BO11: 2.42 | BP11: 152.30295 | BR11: 4.70379 | BS11: 111.02216 | BT11: 14.68728 | BV11: 32.6223 | BW11: 3.7307 | BZ11: 88.09409 | CA11: 22.792 | CB11: 0.3282 | CC11: 0.672 | CD11: 25.59548 | CE11: 467.8458 | CF11: 10.9122 | CG11: 158.5263 | CH11: 17.57039 | CK11: 14.5297 | CL11: 5.0786 | CO11: 14.43571 | CP11: 288.21 | CR11: 39.939 | CT11: 16.08862
B12: 02:30 | E12: 28.19988 | F12: 13.473 | K12: 19.8428 | L12: 27.6995 | M12: 14.7161 | N12: 13.57 | O12: 30.33 | R12: 46.706 | T12: 12.2769 | V12: 9.6 | X12: 40.5061 | Z12: 9.1159 | AF12: 2.9 | AJ12: 5.22184 | AK12: 0 | AL12: 0.9744 | AM12: 49.1199 | AN12: 23.48752 | AO12: 29.636 | AP12: 0.41 | AQ12: 160.25 | AS12: 37.18803 | AT12: 31.74 | AV12: 196.52254 | AW12: 39.6956 | BA12: 4.9 | BC12: 70.60992 | BE12: 19.02 | BI12: 15.90777 | BK12: 5.53429 | BN12: 58.5 | BO12: 2.51 | BP12: 153.00999 | BR12: 4.60566 | BS12: 109.96771 | BT12: 15.19436 | BV12: 32.0398 | BW12: 3.87202 | BZ12: 88.21885 | CA12: 22.719 | CB12: 0.3299 | CC12: 0.693 | CD12: 25.85755 | CE12: 466.84385 | CF12: 11.3591 | CG12: 154.3371 | CH12: 17.63476 | CK12: 14.7372 | CL12: 5.10519 | CO12: 14.73664 | CP12: 282.37 | CR12: 40.279 | CT12: 16.63273
B13: 03:00 | E13: 32.36573 | F13: 13.572 | K13: 19.9777 | L13: 27.7883 | M13: 14.4598 | N13: 13.92 | O13: 29.99 | R13: 46.84 | T13: 20.301 | V13: 9.5 | X13: 134.02422 | Z13: 9.11258 | AF13: 2.3 | AJ13: 4.81592 | AK13: 0 | AL13: 0.939 | AM13: 49.7339 | AN13: 23.21119 | AO13: 30.4157 | AP13: 0.67 | AQ13: 162.78 | AS13: 36.18672 | AT13: 32.59 | AV13: 196.98659 | AW13: 40.0757 | BA13: 5 | BC13: 70.586 | BE13: 19.02 | BI13: 15.98348 | BK13: 5.47038 | BN13: 58.53 | BO13: 2.45 | BP13: 151.05569 | BR13: 4.59217 | BS13: 110.41693 | BT13: 15.42498 | BV13: 31.559 | BW13: 3.96593 | BZ13: 88.90854 | CA13: 22.705 | CB13: 0.3507 | CC13: 0.657 | CD13: 25.9442 | CE13: 443.87222 | CF13: 11.3935 | CG13: 155.3351 | CH13: 17.72104 | CK13: 15.1141 | CL13: 4.86089 | CO13: 14.98729 | CP13: 290.91 | CR13: 40.409 | CT13: 18.25563
B14: 03:30 | E14: 32.38383 | F14: 13.282 | K14: 19.5292 | L14: 26.7418 | M14: 14.4281 | N14: 13.94 | O14: 29.812 | R14: 46.65 | T14: 42.789 | V14: 9.5 | X14: 115.41394 | Z14: 9.04062 | AF14: 1.6 | AJ14: 5.05719 | AK14: 0 | AL14: 0.9246 | AM14: 47.8366 | AN14: 23.31652 | AO14: 29.5951 | AP14: 0.48 | AQ14: 161.25 | AS14: 36.90605 | AT14: 32.03 | AV14: 194.64528 | AW14: 39.2406 | BA14: 4.8 | BC14: 70.55926 | BE14: 19.02 | BI14: 15.52302 | BK14: 5.4637 | BN14: 57.06 | BO14: 2.4 | BP14: 150.62161 | BR14: 4.55352 | BS14: 111.15864 | BT14: 15.02381 | BV14: 30.9982 | BW14: 4.02736 | BZ14: 89.82623 | CA14: 22.709 | CB14: 0.3455 | CC14: 0.675 | CD14: 27.08391 | CE14: 452.9545 | CF14: 11.8186 | CG14: 153.6388 | CH14: 17.97521 | CK14: 14.6064 | CL14: 4.85921 | CO14: 14.96095 | CP14: 280.18 | CR14: 39.934 | CT14: 18.18008
B15: 04:00 | E15: 32.72561 | F15: 13.006 | K15: 19.9028 | L15: 27.4435 | M15: 14.1352 | N15: 13.81 | O15: 30.092 | R15: 46.871 | T15: 36.8013 | V15: 9.6 | X15: 78.5627 | Z15: 9.08259 | AF15: 1.2 | AJ15: 5.19055 | AK15: 0 | AL15: 0.8982 | AM15: 49.6843 | AN15: 23.43187 | AO15: 29.6032 | AP15: 0.18 | AQ15: 161.05 | AS15: 36.69402 | AT15: 30.71 | AV15: 194.34895 | AW15: 39.0047 | BA15: 5.1 | BC15: 70.70165 | BE15: 19.02 | BI15: 15.74977 | BK15: 5.58246 | BN15: 56.96 | BO15: 2.31 | BP15: 150.39748 | BR15: 4.55294 | BS15: 111.78126 | BT15: 14.00592 | BV15: 31.5921 | BW15: 3.88656 | BZ15: 89.10463 | CA15: 22.725 | CB15: 0.3265 | CC15: 0.704 | CD15: 26.78933 | CE15: 465.30266 | CF15: 11.6964 | CG15: 147.7255 | CH15: 18.16363 | CK15: 14.8306 | CL15: 4.87244 | CO15: 14.76168 | CP15: 288.2 | CR15: 39.721 | CT15: 16.00355
B16: 04:30 | E16: 33.28526 | F16: 13.153 | K16: 18.0406 | L16: 27.0456 | M16: 15.03 | N16: 13.02 | O16: 29.868 | R16: 47.324 | T16: 33.3706 | V16: 9.5 | X16: 147.12419 | Z16: 9.07058 | AF16: 1.1 | AJ16: 5.28152 | AK16: 0 | AL16: 0.8734 | AM16: 50.8401 | AN16: 23.383 | AO16: 29.4065 | AP16: 1.65 | AQ16: 161.04 | AS16: 36.21584 | AT16: 30.12 | AV16: 195.38792 | AW16: 39.1412 | BA16: 5 | BC16: 70.64064 | BE16: 19.02 | BI16: 15.7021 | BK16: 5.60246 | BN16: 57.92 | BO16: 2.14 | BP16: 154.24491 | BR16: 4.41284 | BS16: 112.51785 | BT16: 14.34526 | BV16: 32.3707 | BW16: 3.90366 | BZ16: 87.91823 | CA16: 22.757 | CB16: 0.3072 | CC16: 0.694 | CD16: 25.96062 | CE16: 464.26435 | CF16: 11.5456 | CG16: 145.0448 | CH16: 18.14967 | CK16: 13.9696 | CL16: 4.86408 | CO16: 14.38153 | CP16: 298.28 | CR16: 37.59 | CT16: 15.77678
B17: 05:00 | E17: 33.54326 | F17: 12.727 | K17: 19.5039 | L17: 27.1701 | M17: 14.7988 | N17: 13.38 | O17: 29.752 | R17: 47.002 | T17: 38.6732 | V17: 9.4 | X17: 143.94722 | Z17: 8.90092 | AF17: 0.9 | AJ17: 5.03627 | AK17: 0 | AL17: 0.8653 | AM17: 51.9288 | AN17: 23.52017 | AO17: 28.8206 | AP17: 2.1 | AQ17: 162.8 | AS17: 35.29329 | AT17: 29.81 | AV17: 198.28043 | AW17: 37.3666 | BA17: 5.1 | BC17: 69.96611 | BE17: 19.02 | BI17: 15.63546 | BK17: 5.5286 | BN17: 58.42 | BO17: 2.02 | BP17: 155.32879 | BR17: 4.46714 | BS17: 112.73093 | BT17: 14.27683 | BV17: 31.4779 | BW17: 4.37541 | BZ17: 88.36884 | CA17: 23.043 | CB17: 0.2773 | CC17: 0.688 | CD17: 23.96726 | CE17: 454.76392 | CF17: 11.1099 | CG17: 161.4887 | CH17: 17.84553 | CK17: 14.1307 | CL17: 4.84772 | CO17: 14.17105 | CP17: 298.03 | CR17: 34.34 | CT17: 16.09391
B18: 05:30 | E18: 33.66896 | F18: 11.646 | K18: 19.5046 | L18: 28.0913 | M18: 15.9317 | N18: 13.89 | O18: 30.2 | R18: 46.577 | T18: 46.7571 | V18: 9.1 | X18: 123.30006 | Z18: 8.69607 | AF18: 0.8 | AJ18: 5.08865 | AK18: 0 | AL18: 0.8541 | AM18: 51.5019 | AN18: 23.73239 | AO18: 28.2693 | AP18: 1.93 | AQ18: 161.59 | AS18: 34.69981 | AT18: 29.56 | AV18: 198.42784 | AW18: 37.2227 | BA18: 5 | BC18: 69.97547 | BE18: 19.02 | BI18: 15.43081 | BK18: 5.59991 | BN18: 56 | BO18: 1.98 | BP18: 155.15447 | BR18: 4.31466 | BS18: 113.45915 | BT18: 13.68914 | BV18: 29.2402 | BW18: 3.85894 | BZ18: 90.1727 | CA18: 23.081 | CB18: 0.2654 | CC18: 0.667 | CD18: 23.70093 | CE18: 461.55142 | CF18: 11.0373 | CG18: 157.4309 | CH18: 18.66621 | CK18: 14.4129 | CL18: 4.82673 | CO18: 13.27766 | CP18: 297.58 | CR18: 34.392 | CT18: 16.00152
B19: 06:00 | E19: 32.83198 | F19: 10.949 | K19: 19.477 | L19: 28.3005 | M19: 15.0424 | N19: 13.63 | O19: 30.622 | R19: 46.384 | T19: 45.4745 | V19: 8.9 | X19: 97.0046 | Z19: 8.84771 | AF19: 0.8 | AJ19: 5.10208 | AK19: 0 | AL19: 0.8697 | AM19: 51.6576 | AN19: 23.54967 | AO19: 26.8742 | AP19: 1.54 | AQ19: 160.56 | AS19: 34.09063 | AT19: 31.53 | AV19: 198.50663 | AW19: 35.602 | BA19: 4.9 | BC19: 69.84922 | BE19: 19.02 | BI19: 15.76215 | BK19: 5.66291 | BN19: 54.85 | BO19: 1.95 | BP19: 154.98341 | BR19: 4.36595 | BS19: 114.31829 | BT19: 13.65733 | BV19: 29.9612 | BW19: 3.65085 | BZ19: 90.96202 | CA19: 23.049 | CB19: 0.2688 | CC19: 0.644 | CD19: 22.31623 | CE19: 465.20042 | CF19: 10.6068 | CG19: 153.8137 | CH19: 18.81619 | CK19: 13.4882 | CL19: 4.72527 | CO19: 11.79393 | CP19: 297.32 | CR19: 34.819 | CT19: 16.14825
... B55: 00:00 | E55: 33.14625 | F55: 12.554 | K55: 20.9329 | L55: 27.9936 | M55: 13.5744 | N55: 10.48 | O55: 31.732 | R55: 51.12 | T55: 36.8467 | V55: 8.5 | X55: 135.42497 | Z55: 8.02648 | AF55: 1.2 | AJ55: 5.27586 | AK55: 0 | AL55: 1.4259 | AM55: 50.5673 | AN55: 23.93966 | AO55: 28.3973 | AP55: 0.83 | AQ55: 162.6 | AS55: 37.7045 | AT55: 31.82 | AV55: 192.9521 | AW55: 36.2361 | BA55: 5.2 | BC55: 72.80754 | BE55: 18.61 | BI55: 12.15011 | BK55: 5.44423 | BN55: 56.05 | BO55: 1.99 | BP55: 148.67454 | BR55: 4.55844 | BS55: 122.99435 | BT55: 15.48799 | BV55: 34.5871 | BW55: 3.83695 | BZ55: 90.27816 | CA55: 6.837 | CB55: 0.3698 | CC55: 0.666 | CD55: 22.05958 | CE55: 458.85607 | CF55: 11.6536 | CG55: 141.8494 | CH55: 17.7678 | CK55: 16.4183 | CL55: 5.07086 | CO55: 8.80217 | CP55: 299.22 | CR55: 36.56 | CT55: 15.3913
B56: MWh | C56: 0 | D56: 0 | E56: 693.26051 | F56: 293.078 | G56: 0 | H56: 0 | I56: 0 | J56: 0 | K56: 476.3413 | L56: 672.8717 | M56: 313.61945 | N56: 314.89 | O56: 738.946 | P56: 0 | Q56: 0 | R56: 1166.1485 | S56: 0 | T56: 741.23515 | U56: 0 | V56: 208.35 | W56: 0 | X56: 2315.5332 | Y56: 0 | Z56: 213.15559 | AA56: 0 | AB56: 0 | AC56: 0 | AD56: 0 | AE56: 0 | AF56: 32.95 | AG56: 0 | AH56: 0 | AI56: 0 | AJ56: 118.96792 | AK56: 0 | AL56: 77.1353 | AM56: 1192.7812 | AN56: 562.91282 | AO56: 673.9206 | AP56: 18.01 | AQ56: 3850.51 | AR56: 0 | AS56: 840.55644 | AT56: 763.805 | AU56: 0 | AV56: 4395.9288 | AW56: 883.15125 | AX56: 0 | AY56: 0 | AZ56: 0 | BA56: 124.5 | BB56: 0 | BC56: 1569.0448 | BD56: 0 | BE56: 451.43 | BF56: 0 | BG56: 0 | BH56: 0 | BI56: 342.27945 | BJ56: 0 | BK56: 134.74774 | BL56: 0 | BM56: 0 | BN56: 1088.56 | BO56: 50.68 | BP56: 3560.2893 | BQ56: 0 | BR56: 108.77188 | BS56: 2768.0757 | BT56: 343.07328 | BU56: 0 | BV56: 738.97175 | BW56: 93.491925 | BX56: 0 | BY56: 0 | BZ56: 2130.2671 | CA56: 432.042 | CB56: 20.33465 | CC56: 16.1275 | CD56: 588.37846 | CE56: 10969.374 | CF56: 264.0481 | CG56: 3666.3942 | CH56: 401.34366 | CI56: 0 | CJ56: 0 | CK56: 354.8136 | CL56: 114.98707 | CM56: 0 | CN56: 0 | CO56: 241.00709 | CP56: 6839.78 | CQ56: 0 | CR56: 887.2505 | CS56: 0 | CT56: 343.34127
B59: Nota :
B60: Información proporcionada por la empresas
C62: DATOS ESTIMADOS
C64: SIN DATOS

Sheet TIPO_RECURSO
B3: sábado, 26 de Abril del 2025
B5: REPORTE POTENCIA GENERADA POR TIPO DE RECURSO
B6: HORA | C6: H. PASADA | D6: H. REGULACION | E6: GAS DE CAMISEA | F6: GAS DE MALACAS | G6: GAS DE AGUAYTIA | H6: DIESEL | I6: RESIDUAL | J6: NAFTA+GAS DE REFINERIA | K6: FLEXIGAS+GAS DE REFINERIA | L6: BAGAZO | M6: BIOGÁS | N6: SOLAR | O6: EÓLICA | P6: TOTAL | U6: EMPRESA | V6: CENTRAL | W6: HIDROELECTRICA DE PASADA | X6: HIDROELECTRICA DE REGULACION
B7: 00:30 | C7: 1137.8 | D7: 3551.65 | E7: 1404.9 | F7: 48.8 | J7: =DESPACHO_EJECUTADO!FC11 -> 37.2 | L7: 15 | M7: 8.7 | N7: 0 | O7: 470.6 | P7: =SUM(C7:O7) -> 6674.65 | U7: ANDEAN POWER S.A.C. | V7: C.H.CARHUAC | W7: 390.8
B8: 01:00 | C8: 1132.9 | D8: 3512.21 | E8: 1326 | F8: 48.7 | J8: =DESPACHO_EJECUTADO!FC12 -> 38 | L8: 15.1 | M8: 8.7 | N8: 0 | O8: 479.7 | P8: =SUM(C8:O8) -> 6561.31 | U8: ASOCIACIÓN SANTA LUCIA DE CHACAS | V8: C.H. HUALLIN | W8: 14.15
B9: 01:30 | C9: 1123.9 | D9: 3403.04 | E9: 1340.1 | F9: 32.6 | J9: =DESPACHO_EJECUTADO!FC13 -> 38.6 | L9: 15 | M9: 4.3 | N9: 0 | O9: 493.2 | P9: =SUM(C9:O9) -> 6450.74 | U9: ATRIA ENERGIA S.A.C. | V9: C.H. PURMACANA | W9: 5.2
B10: 02:00 | C10: 1130.3 | D10: 3341.62 | E10: 1338.9 | F10: 25 | J10: =DESPACHO_EJECUTADO!FC14 -> 38.7 | L10: 15 | M10: 4.3 | N10: 0 | O10: 486.1 | P10: =SUM(C10:O10) -> 6379.92 | U10: CELEPSA | V10: C.H. EL PLATANAL | X10: 4968.3
B11: 02:30 | C11: 1124.3 | D11: 3260.37 | E11: 1342.5 | F11: 25.1 | J11: =DESPACHO_EJECUTADO!FC15 -> 38.5 | L11: 14.7 | M11: 4.3 | N11: 0 | O11: 504.4 | P11: =SUM(C11:O11) -> 6314.17 | U11: CELEPSA RENOVABLES S.R.L. | V11: C.H. MARAÑON | W11: 464.65
B12: 03:00 | C12: 1143.7 | D12: 3291.39 | E12: 1365.6 | F12: 25.2 | J12: =DESPACHO_EJECUTADO!FC16 -> 38.7 | L12: 14.8 | M12: 4.3 | N12: 0 | O12: 501.8 | P12: =SUM(C12:O12) -> 6385.49 | U12: CHINANGO S.A.C. | V12: C.H. CHIMAY | X12: 3353.1
B13: 03:30 | C13: 1142.4 | D13: 3293.97 | E13: 1374.1 | F13: 24.8 | J13: =DESPACHO_EJECUTADO!FC17 -> 38.2 | L13: 14.8 | M13: 4.3 | N13: 0 | O13: 508.6 | P13: =SUM(C13:O13) -> 6401.17 | V13: C.H. YANANGO | W13: 1016.5
B14: 04:00 | C14: 1145.9 | D14: 3311.89 | E14: 1359.8 | F14: 25.1 | J14: =DESPACHO_EJECUTADO!FC18 -> 38.2 | L14: 15 | M14: 4.3 | N14: 0 | O14: 495 | P14: =SUM(C14:O14) -> 6395.19 | U14: EGASA | V14: C.H. CHARCANI III | W14: 160.5
B15: 04:30 | C15: 1137.9 | D15: 3269.03 | E15: 1370.9 | F15: 25 | J15: =DESPACHO_EJECUTADO!FC19 -> 37.9 | L15: 15 | M15: 4.3 | N15: 0 | O15: 472.9 | P15: =SUM(C15:O15) -> 6332.93 | V15: C.H. CHARCANI IV | X15: 242.55
B16: 05:00 | C16: 1136.5 | D16: 3406.15 | E16: 1418.6 | F16: 0 | J16: =DESPACHO_EJECUTADO!FC20 -> 36.9 | L16: 14.5 | M16: 4.3 | N16: 0 | O16: 489.7 | P16: =SUM(C16:O16) -> 6506.65 | V16: C.H. CHARCANI V | X16: 2149.6
B17: 05:30 | C17: 1118.6 | D17: 3382.95 | E17: 1433.5 | F17: 0 | J17: =DESPACHO_EJECUTADO!FC21 -> 37.7 | L17: 14.6 | M17: 4.3 | N17: 0 | O17: 477.9 | P17: =SUM(C17:O17) -> 6469.55 | V17: C.H. CHARCANI VI | X17: 149.9
B18: 06:00 | C18: 1132.2 | D18: 3467 | E18: 1495.6 | F18: 0 | J18: =DESPACHO_EJECUTADO!FC22 -> 38 | L18: 14.6 | M18: 4.3 | N18: 3.53 | O18: 418.4 | P18: =SUM(C18:O18) -> 6573.63 | U18: EGEJUNIN | V18: C.H. HUASAHUASI I | W18: 471.85
B19: 06:30 | C19: 1127 | D19: 3320.6 | E19: 1455.2 | F19: 0 | J19: =DESPACHO_EJECUTADO!FC23 -> 37.8 | L19: 15.1 | M19: 4.3 | N19: 79.94 | O19: 422.7 | P19: =SUM(C19:O19) -> 6462.64 | V19: C.H. RUNATULLO II | W19: 389.4
B20: 07:00 | C20: 1127.9 | D20: 3273.37 | E20: 1371.8 | F20: 0 | J20: =DESPACHO_EJECUTADO!FC24 -> 37.9 | L20: 14.8 | M20: 4.3 | N20: 299.039 | O20: 389.1 | P20: =SUM(C20:O20) -> 6518.209 | V20: C.H. RUNATULLO III | W20: 485.9
B21: 07:30 | C21: 1129 | D21: 3330.48 | E21: 1386.4 | F21: 0 | J21: =DESPACHO_EJECUTADO!FC25 -> 37.6 | L21: 14.6 | M21: 4.3 | N21: 481.155 | O21: 344.5 | P21: =SUM(C21:O21) -> 6728.035 | V21: C.H. SANTA CRUZ I | W21: 232.85
B22: 08:00 | C22: 1127.8 | D22: 3431.81 | E22: 1378.6 | F22: 0 | J22: =DESPACHO_EJECUTADO!FC26 -> 38 | L22: 15 | M22: 4.3 | N22: 594.145 | O22: 290.3 | P22: =SUM(C22:O22) -> 6879.955 | U22: EGEMSA | V22: C.H. MACHUPICCHU | W22: 3945.35
B23: 08:30 | C23: 1124.1 | D23: 3436.89 | E23: 1559.7 | F23: 0 | J23: =DESPACHO_EJECUTADO!FC27 -> 37.8 | L23: 15.1 | M23: 4.3 | N23: 616.284 | O23: 304.2 | P23: =SUM(C23:O23) -> 7098.374 | U23: EGESUR | V23: C.H. ARICOTA I | X23: 175.85
B24: 09:00 | C24: 1122.3 | D24: 3556.93 | E24: 1660 | F24: 0 | J24: =DESPACHO_EJECUTADO!FC28 -> 37.2 | L24: 14 | M24: 4.3 | N24: 632.374 | O24: 317.8 | P24: =SUM(C24:O24) -> 7344.904 | V24: C.H. ARICOTA II | X24: 85.5
B25: 09:30 | C25: 1121.5 | D25: 3502.44 | E25: 1678.8 | F25: 0 | J25: =DESPACHO_EJECUTADO!FC29 -> 36.9 | L25: 14.6 | M25: 4.3 | N25: 633.897 | O25: 336.6 | P25: =SUM(C25:O25) -> 7329.037 | U25: ELECTRICA YANAPAMPA SAC | V25: C.H. YANAPAMPA | W25: 56.9
B26: 10:00 | C26: 1135.7 | D26: 3561.19 | E26: 1750.5 | F26: 0 | J26: =DESPACHO_EJECUTADO!FC30 -> 36.3 | L26: 14.9 | M26: 4.3 | N26: 619.274 | O26: 401 | P26: =SUM(C26:O26) -> 7523.164 | U26: ELECTROPERU | V26: C.H. MANTARO | X26: 15458.05
B27: 10:30 | C27: 1138.9 | D27: 3426.34 | E27: 1790.2 | F27: 0 | J27: =DESPACHO_EJECUTADO!FC31 -> 36.1 | L27: 14.8 | M27: 4.3 | N27: 648.394 | O27: 479.4 | P27: =SUM(C27:O27) -> 7538.434 | V27: C.H. RESTITUCION | W27: 5129.95
B28: 11:00 | C28: 1143.4 | D28: 3501.48 | E28: 1837.2 | F28: 0 | J28: =DESPACHO_EJECUTADO!FC32 -> 37 | L28: 15.1 | M28: 4.3 | N28: 647.14 | O28: 519.7 | P28: =SUM(C28:O28) -> 7705.32 | U28: EMPRESA DE GENERACION ELECTRICA CANCHAYLLO SAC | V28: C.H. CANCHAYLLO | W28: 98.4
B29: 11:30 | C29: 1147.5 | D29: 3506.03 | E29: 1752.8 | F29: 0 | J29: =DESPACHO_EJECUTADO!FC33 -> 37 | L29: 15.1 | M29: 4.3 | N29: 653.273 | O29: 558.7 | P29: =SUM(C29:O29) -> 7674.703 | U29: EMPRESA DE GENERACION ELECTRICA RIO BAÑOS S.A.C. | V29: C.H. RUCUY | W29: 478.65
B30: 12:00 | C30: 1136.1 | D30: 3480.7 | E30: 1703.7 | F30: 0 | J30: =DESPACHO_EJECUTADO!FC34 -> 38.5 | L30: 14.6 | M30: 4.3 | N30: 652.059 | O30: 687.1 | P30: =SUM(C30:O30) -> 7717.059 | U30: EMPRESA DE GENERACION ELECTRICA SANTA ANA S.A.C. | V30: C.H. RENOVANDES H1 | W30: 121.35
B31: 12:30 | C31: 1105.4 | D31: 3155.47 | E31: 1842.7 | F31: 0 | J31: =DESPACHO_EJECUTADO!FC35 -> 38.6 | L31: 14.2 | M31: 4.3 | N31: 656.168 | O31: 744.8 | P31: =SUM(C31:O31) -> 7561.638 | U31: EMPRESA DE GENERACION HUALLAGA | V31: C.H. CHAGLLA | X31: 10595.55
B32: 13:00 | C32: 1119.9 | D32: 3309.25 | E32: 1597.3 | F32: 0 | J32: =DESPACHO_EJECUTADO!FC36 -> 38.7 | L32: 14.6 | M32: 4.3 | N32: 661.203 | O32: 804.9 | P32: =SUM(C32:O32) -> 7550.153 | V32: P.C.H. CHAGLLA | W32: 153.95
B33: 13:30 | C33: 1110.3 | D33: 3395.79 | E33: 1482.4 | F33: 0 | J33: =DESPACHO_EJECUTADO!FC37 -> 38.7 | L33: 14.3 | M33: 4.3 | N33: 657.78 | O33: 831.7 | P33: =SUM(C33:O33) -> 7535.27 | U33: EMPRESA DE GENERACION HUANZA | V33: C.H. HUANZA | X33: 1476.95
B34: 14:00 | C34: 1149.1 | D34: 3354.07 | E34: 1475.7 | F34: 0 | J34: =DESPACHO_EJECUTADO!FC38 -> 38.5 | L34: 14.6 | M34: 4.3 | N34: 636.961 | O34: 856.9 | P34: =SUM(C34:O34) -> 7530.131 | U34: EMPRESA ELECTRICA AGUA AZUL | V34: C.H. POTRERO | W34: 422.8
B35: 14:30 | C35: 1132 | D35: 3305.12 | E35: 1469.5 | F35: 0 | J35: =DESPACHO_EJECUTADO!FC39 -> 36.2 | L35: 14.5 | M35: 4.3 | N35: 650.923 | O35: 866.5 | P35: =SUM(C35:O35) -> 7479.043 | U35: EMPRESA ELECTRICA RIO DOBLE | V35: C.H. LAS PIZARRAS | W35: 381.6
B36: 15:00 | C36: 1124.7 | D36: 3296.13 | E36: 1573.7 | F36: 0 | J36: =DESPACHO_EJECUTADO!FC40 -> 36 | L36: 14.1 | M36: 4.3 | N36: 623.817 | O36: 883 | P36: =SUM(C36:O36) -> 7555.747 | U36: ENGIE | V36: C.H. YUNCAN | X36: 2070.55
B37: 15:30 | C37: 1090.7 | D37: 3297.81 | E37: 1550 | F37: 0 | J37: =DESPACHO_EJECUTADO!FC41 -> 36.3 | L37: 15.3 | M37: 4.3 | N37: 579.422 | O37: 887.1 | P37: =SUM(C37:O37) -> 7460.932 | U37: GENERACIÓN ANDINA S.A.C. | V37: C.H. 8 DE AGOSTO | W37: 501.6
B38: 16:00 | C38: 1117.4 | D38: 3412.16 | E38: 1502 | F38: 0 | J38: =DESPACHO_EJECUTADO!FC42 -> 36.3 | L38: 15.1 | M38: 4.3 | N38: 448.188 | O38: 892.4 | P38: =SUM(C38:O38) -> 7427.848 | V38: C.H. EL CARMEN | W38: 179.3
B39: 16:30 | C39: 1125.1 | D39: 3458.79 | E39: 1626.4 | F39: 0 | J39: =DESPACHO_EJECUTADO!FC43 -> 36.2 | L39: 15.2 | M39: 4.3 | N39: 189.461 | O39: 890.3 | P39: =SUM(C39:O39) -> 7345.751 | U39: GENERADORA DE ENERGÍA DEL PERÚ | V39: C.H. ÁNGEL I | W39: 489.6
B40: 17:00 | C40: 1137.1 | D40: 3512.07 | E40: 1658.8 | F40: 0 | J40: =DESPACHO_EJECUTADO!FC44 -> 36.4 | L40: 15.3 | M40: 4.3 | N40: 65.189 | O40: 888.5 | P40: =SUM(C40:O40) -> 7317.659 | V40: C.H. ÁNGEL II | W40: 489.6
B41: 17:30 | C41: 1152.5 | D41: 3547.94 | E41: 1612.5 | F41: 0 | J41: =DESPACHO_EJECUTADO!FC45 -> 36.4 | L41: 14.6 | M41: 4.3 | N41: 2.072 | O41: 876.9 | P41: =SUM(C41:O41) -> 7247.212 | V41: C.H. ÁNGEL III | W41: 484.8
B42: 18:00 | C42: 1145.9 | D42: 3511.5 | E42: 1776.7 | F42: 0 | J42: =DESPACHO_EJECUTADO!FC46 -> 37.3 | L42: 14.3 | M42: 4.3 | N42: 0 | O42: 841.4 | P42: =SUM(C42:O42) -> 7331.4 | V42: C.H. LA JOYA | W42: 208.95
B43: 18:30 | C43: 1146.1 | D43: 3540.1 | E43: 2014.1 | F43: 0 | J43: =DESPACHO_EJECUTADO!FC47 -> 37.8 | L43: 14 | M43: 4.3 | N43: 0 | O43: 814.8 | P43: =SUM(C43:O43) -> 7571.2 | U43: HIDROCAÑETE S.A. | V43: C.H. IMPERIAL | W43: 81.85
B44: 19:00 | C44: 1148.4 | D44: 3599.8 | E44: 2050.3 | F44: 0 | J44: =DESPACHO_EJECUTADO!FC48 -> 37.8 | L44: 13 | M44: 4.3 | N44: 0 | O44: 718.5 | P44: =SUM(C44:O44) -> 7572.1 | U44: HIDROELECTRICA HUANCHOR S.A.C. | V44: C.H. HUANCHOR | W44: 425.5
B45: 19:30 | C45: 1148.1 | D45: 3587.6 | E45: 2065.2 | F45: 0 | J45: =DESPACHO_EJECUTADO!FC49 -> 37.8 | L45: 14.5 | M45: 4.3 | N45: 0 | O45: 717.5 | P45: =SUM(C45:O45) -> 7575 | U45: HUAURA POWER GROUP S.A. | V45: C.H. YARUCAYA | W45: 223.2
B46: 20:00 | C46: 1147.4 | D46: 3560.6 | E46: 2047.8 | F46: 0 | J46: =DESPACHO_EJECUTADO!FC50 -> 37.3 | L46: 14.3 | M46: 4.2 | N46: 0 | O46: 717.9 | P46: =SUM(C46:O46) -> 7529.5 | U46: HYDRO GLOBAL PERÚ S.A.C. | V46: CH SAN GABAN III | X46: 1762.195
B47: 20:30 | C47: 1156.7 | D47: 3566.5 | E47: 1979.6 | F47: 0 | J47: =DESPACHO_EJECUTADO!FC51 -> 37.7 | L47: 14.6 | M47: 4.2 | N47: 0 | O47: 722 | P47: =SUM(C47:O47) -> 7481.3 | U47: INLAND ENERGY SAC | V47: C.H. SANTA TERESA | W47: 2150.85
B48: 21:00 | C48: 1134.2 | D48: 3521.69 | E48: 1992.8 | F48: 0 | J48: =DESPACHO_EJECUTADO!FC52 -> 38.1 | L48: 14.7 | M48: 4.2 | N48: 0 | O48: 707 | P48: =SUM(C48:O48) -> 7412.69 | U48: INVERSIONES SHAQSHA S.A.C. | V48: C.H. PARIAC | W48: 110.25
B49: 21:30 | C49: 1148.6 | D49: 3619.77 | E49: 1873.3 | F49: 0 | J49: =DESPACHO_EJECUTADO!FC53 -> 37.8 | L49: 14.8 | M49: 4.2 | N49: 0 | O49: 693.8 | P49: =SUM(C49:O49) -> 7392.27 | U49: KALLPA GENERACION S.A. | V49: C.H. CERRO DEL AGUILA | X49: 13351.4
B50: 22:00 | C50: 1152.8 | D50: 3560.4 | E50: 1934.9 | F50: 0 | J50: =DESPACHO_EJECUTADO!FC54 -> 37.5 | L50: 14.5 | M50: 4.2 | N50: 0 | O50: 659.7 | P50: =SUM(C50:O50) -> 7364 | V50: M.C.H. CERRO DEL AGUILA | W50: 130.55
B51: 22:30 | C51: 1144.2 | D51: 3600.4 | E51: 1978.3 | F51: 0 | J51: =DESPACHO_EJECUTADO!FC55 -> 37.7 | L51: 14.5 | M51: 4.2 | N51: 0 | O51: 597.7 | P51: =SUM(C51:O51) -> 7377 | U51: LA VIRGEN | V51: C.H. LA VIRGEN | X51: 1752.9
B52: 23:00 | C52: 1157.2 | D52: 3417.61 | E52: 1870.6 | F52: 0 | J52: =DESPACHO_EJECUTADO!FC56 -> 37.5 | L52: 14.5 | M52: 4.2 | N52: 0 | O52: 567.3 | P52: =SUM(C52:O52) -> 7068.91 | U52: MAJA ENERGIA S.A.C. | V52: C.H. RONCADOR | W52: 79.3
B53: 23:30 | C53: 1177.9 | D53: 3507.74 | E53: 1613.9 | F53: 0 | J53: =DESPACHO_EJECUTADO!FC57 -> 37.8 | L53: 14.4 | M53: 4.2 | N53: 0 | O53: 554 | P53: =SUM(C53:O53) -> 6909.94 | U53: ORAZUL ENERGY PERÚ | V53: C.H. CAÑA BRAVA | W53: 130.55
B54: 00:00 | C54: 1159 | D54: 3297.25 | E54: 1636.9 | F54: 0 | J54: =DESPACHO_EJECUTADO!FC58 -> 37.3 | L54: 14.2 | M54: 4.2 | N54: 0 | O54: 537.1 | P54: =SUM(C54:O54) -> 6685.95 | V54: C.H. CAÑON DEL PATO | X54: 5441.8
B55: TOTAL MWh | C55: =+SUM(C7:C54)/2 -> 27259.15 | D55: =+SUM(D7:D54)/2 -> 82377.545 | E55: =+SUM(E7:E54)/2 -> 39060.4 | F55: =+SUM(F7:F54)/2 -> 140.15 | G55: =+SUM(G7:G54)/2 -> 0 | H55: =+SUM(H7:H54)/2 -> 0 | I55: =+SUM(I7:I54)/2 -> 0 | J55: =+SUM(J7:J54)/2 -> 901.2 | ... O55: =+SUM(O7:O54)/2 -> 14560.55 | P55: =SUM(C55:O55) -> 170623.94 | V55: C.H. CARHUAQUERO | X55: 2149.85
B56: % | C56: =+C55*100/$P$55 -> 15.976158 | D56: =+D55*100/$P$55 -> 48.28018 | E56: =+E55*100/$P$55 -> 22.892684 | F56: =+F55*100/$P$55 -> 0.082139705 | G56: =+G55*100/$P$55 -> 0 | H56: =+H55*100/$P$55 -> 0 | I56: =+I55*100/$P$55 -> 0 | J56: =+J55*100/$P$55 -> 0.52817911 | ... O56: =+O55*100/$P$55 -> 8.5337087 | P56: 100.00 | V56: C.H. CARHUAQUERO IV | W56: 237.9
U57: ORYGEN PERU S.A.A. | V57: C.H. CALLAHUANCA | X57: 1892.05
V58: C.H. HER 1 | W58: 14.4
V59: C.H. HUAMPANI | W59: 723.7
V60: C.H. HUINCO | X60: 3931.95
V61: C.H. MATUCANA | X61: 3037.9
V62: C.H. MOYOPAMPA | W62: 1523.3
U63: PERUANA DE INVERSIONES EN ENERGIAS RENOVABLES S.A. | V63: C.H. MANTA I | W63: 364.35
U64: SAN GABAN | V64: C.H. SAN GABAN II | X64: 2173.05
V65: MCH TUPURI | W65: 28.8
U66: SINERSA | V66: C.H. CHANCAY | W66: 479.6
V67: C.H. POECHOS II | W67: 221.85
U68: STATKRAFT S.A | V68: C.H. ARCATA | W68: 91.2
V69: C.H. CAHUA | W69: 571.25
V70: C.H. CHEVES | X70: 4153.7
V71: C.H. GALLITO CIEGO | X71: 909.45
V72: C.H. MALPASO | X72: 1095.4
V73: C.H. OROYA | W73: 192.25
V74: C.H. PACHACHACA | W74: 140.35
V75: C.H. YAUPI | W75: 2563.55
U76: TOTAL MWh | W76: 27259.15 | X76: 82377.545

Sheet GENERACION RER
B3: sábado, 26 de Abril del 2025
B5: GENERACIÓN ELÉCTRICA DE LAS CENTRALES RER (MW)
B6: HORA | C6: AGRO INDUSTRIAL PARAMONGA S.A. | D6: AGROAURORA S.A.C. | E6: AGROINDUSTRIAS SAN JACINTO S.A.A. | F6: ANDEAN POWER S.A.C. | G6: ASOCIACIÓN SANTA LUCIA DE CHACAS | H6: ATRIA ENERGIA S.A.C. | I6: BIOENERGIA DEL CHIRA S.A. | J6: COLCA SOLAR S.A.C. | K6: EGEJUNIN | P6: ELECTRICA YANAPAMPA SAC | Q6: EMPRESA DE GENERACION ELECTRICA CANCHAYLLO SAC | R6: EMPRESA DE GENERACION ELECTRICA RIO BAÑOS S.A.C. | S6: EMPRESA DE GENERACION ELECTRICA SANTA ANA S.A.C. | T6: EMPRESA ELECTRICA AGUA AZUL | U6: EMPRESA ELECTRICA RIO DOBLE | V6: ENERGÍA EÓLICA S.A. | X6: ENERGIA RENOVABLE DEL SUR S.A. | Y6: ENGIE | AD6: GENERACIÓN ANDINA S.A.C. | AF6: GENERADORA DE ENERGÍA DEL PERÚ | AJ6: GR CORTARRAMA SOCIEDAD ANONIMA CERRADA | AK6: GR PAINO SOCIEDAD ANONIMA CERRADA | AL6: GR TARUCA SOCIEDAD ANONIMA CERRADA | AM6: HIDROCAÑETE S.A. | AN6: HUAURA POWER GROUP S.A. | AO6: HYDRO PATAPO S.A.C. | AP6: JOYA SOLAR S.A.C. | AQ6: KONDU SAC | AR6: MAJA ENERGIA S.A.C. | AS6: MAJES ARCUS S.A.C. | AT6: MOQUEGUA FV S.A.C. | AU6: ORAZUL ENERGY PERÚ | AW6: ORYGEN PERU S.A.A. | BB6: PANAMERICANA SOLAR SAC. | BC6: PARQUE EOLICO MARCONA S.A.C. | BD6: PARQUE EOLICO TRES HERMANAS S.A.C. | BE6: PERUANA DE INVERSIONES EN ENERGIAS RENOVABLES S.A. | BF6: PETRAMAS | BJ6: REPARTICIÓN ARCUS S.A.C. | BK6: SAN GABAN | BL6: SDF ENERGIA SAC | BM6: SINERSA | BO6: TACNA SOLAR SAC. | BP6: TOTAL RER
C7: C.T. PARAMONGA | D7: C.T. MAPLE | E7: C.T SAN JACINTO | F7: C.H. CARHUAC | G7: C.H. HUALLIN | H7: C.H. PURMACANA | I7: C.T. CAÑA BRAVA | K7: C.H. HUASAHUASI I | L7: C.H. HUASAHUASI II | M7: C.H. RUNATULLO II | N7: C.H. RUNATULLO III | O7: C.H. STA CRUZ I y II | P7: C.H. YANAPAMPA | Q7: C.H. CANCHAYLLO | R7: C.H. RUCUY | S7: C.H. RENOVANDES H1 | T7: C.H. POTRERO | U7: C.H. LAS PIZARRAS | AD7: C.H. 8 DE AGOSTO | AE7: C.H. EL CARMEN | AF7: C.H. ANGEL I | AG7: C.H. ANGEL II | AH7: C.H. ANGEL III | AI7: C.H. LA JOYA | AM7: C.H. NUEVAIMPERIAL | AN7: C.H. YARUCAYA | AO7: MCH PATAPO | AR7: C.H. RONCADOR | AU7: C.H. CANA BRAVA | AV7: C.H. CARHUAQUERO4 | BA7: C.H. HER 1 | BE7: C.H. MANTA | BF7: C.T. HUAYCOLORO | BG7: C.T. LA GRINGA V | BH7: CTB CALLAO | BI7: CTB. DONA CATALINA | BK7: C.H. TUPURI | BL7: C.T. OQUENDO | BM7: C.H. CHANCAY | BN7: C.H. POECHOS2 | BP7: MW
B8: 0:30 | C8: 15 | F8: 20.4 | K8: 19.8 | M8: 16.1 | N8: 20.3 | O8: 9.7 | P8: 2.4 | Q8: 4.8 | R8: 20 | S8: 20.2 | T8: 10.3 | U8: 10.2 | V8: 4.9 | W8: 36.7 | X8: 95.8 | Y8: 66.2 | Z8: 90.5 | AB8: 9.6 | AC8: 1.6 | AD8: 20.9 | AE8: 8.3 | AF8: 20.4 | AG8: 20.4 | AH8: 20.2 | AI8: 8.3 | AK8: 1.2 | AL8: 0.8 | AM8: 3.6 | AN8: 9.3 | AR8: 3.4 | AU8: 5.6 | AV8: 9.9 | AW8: 29 | AY8: 40.5 | BA8: 0.6 | BC8: 25.2 | BD8: 68.6 | BF8: 4.4 | BH8: 1.9 | BI8: 2.4 | BK8: 1.2 | BM8: 20 | BN8: 9.2 | BP8: 809.8
B9: 1:00 | C9: 15.1 | F9: 16.8 | K9: 19.8 | M9: 16.1 | N9: 20.3 | O9: 9.7 | P9: 2.4 | Q9: 5 | R9: 20 | S9: 20.4 | T9: 10.9 | U9: 10 | V9: 6.5 | W9: 38.5 | X9: 101.2 | Y9: 62.1 | Z9: 90.1 | AB9: 6.1 | AC9: 0.2 | AD9: 20.9 | AE9: 8.3 | AF9: 20.4 | AG9: 20.4 | AH9: 20.2 | AI9: 8.3 | AK9: 1 | AL9: 1.2 | AM9: 2.9 | AN9: 9.3 | AR9: 3.4 | AU9: 5.4 | AV9: 9.9 | AW9: 29.8 | AY9: 38.8 | BA9: 0.6 | BC9: 30.7 | BD9: 73.5 | BF9: 4.4 | BH9: 1.9 | BI9: 2.4 | BK9: 1.2 | BM9: 20 | BN9: 9.2 | BP9: 815.3
B10: 1:30 | C10: 15 | F10: 9.9 | K10: 19.8 | M10: 16.1 | N10: 20.3 | O10: 9.7 | P10: 2.4 | Q10: 5 | R10: 20 | S10: 20.2 | T10: 11.3 | U10: 9.9 | V10: 13.7 | W10: 48.2 | X10: 107.7 | Y10: 58.7 | Z10: 93 | AB10: 6 | AC10: 0.2 | AD10: 20.9 | AE10: 8.3 | AF10: 20.4 | AG10: 20.4 | AH10: 20.2 | AI10: 8.3 | AK10: 0.1 | AL10: 0.5 | AM10: 3 | AN10: 9.3 | AR10: 3.4 | AU10: 5.5 | AV10: 9.9 | AW10: 24.2 | AY10: 35 | BA10: 0.6 | BC10: 30.4 | BD10: 75.5 | BH10: 2 | BI10: 2.3 | BK10: 1.2 | BM10: 20 | BN10: 9.2 | BP10: 817.7
B11: 2:00 | C11: 15 | F11: 10.2 | K11: 19.8 | M11: 16 | N11: 20.3 | O11: 9.7 | P11: 2.4 | Q11: 4.9 | R11: 20 | S11: 20.4 | T11: 12.8 | U11: 9.9 | V11: 12.3 | W11: 39.6 | X11: 110 | Y11: 56.2 | Z11: 89 | AB11: 4.3 | AC11: 1.2 | AD11: 20.9 | AE11: 8.3 | AF11: 20.4 | AG11: 20.4 | AH11: 20.2 | AI11: 8.5 | AK11: 0.3 | AL11: 0.4 | AM11: 3.4 | AN11: 9.3 | AR11: 3.4 | AU11: 5.5 | AV11: 9.9 | AW11: 29 | AY11: 35.7 | BA11: 0.6 | BC11: 31 | BD11: 77.1 | BH11: 2 | BI11: 2.3 | BK11: 1.2 | BM11: 20 | BN11: 9.2 | BP11: 813
B12: 2:30 | C12: 14.7 | F12: 10.1 | K12: 19.8 | M12: 16.1 | N12: 20.3 | O12: 9.7 | P12: 2.4 | Q12: 4.9 | R12: 20 | S12: 20.2 | T12: 16.4 | U12: 9.8 | V12: 10.5 | W12: 48.2 | X12: 110.3 | Y12: 52.9 | Z12: 82.1 | AB12: 4.6 | AC12: 1.8 | AD12: 20.9 | AE12: 8.3 | AF12: 20.4 | AG12: 20.4 | AH12: 20.2 | AI12: 8.9 | AK12: 0.6 | AL12: 0.7 | AM12: 3.5 | AN12: 9.3 | AR12: 3.4 | AU12: 5.4 | AV12: 9.9 | AW12: 36.5 | AY12: 46.1 | BA12: 0.6 | BC12: 31.5 | BD12: 78.6 | BH12: 2 | BI12: 2.3 | BK12: 1.2 | BM12: 20 | BN12: 9.2 | BP12: 834.7
B13: 3:00 | C13: 14.8 | F13: 10.1 | K13: 19.8 | M13: 16 | N13: 20.2 | O13: 9.7 | P13: 2.4 | Q13: 4.9 | R13: 19.8 | S13: 20.3 | T13: 18.3 | U13: 9.8 | V13: 12.6 | W13: 52 | X13: 109.6 | Y13: 54.6 | Z13: 80.5 | AB13: 5 | AC13: 1.3 | AD13: 20.9 | AE13: 8.3 | AF13: 20.4 | AG13: 20.4 | AH13: 20.2 | AI13: 8.9 | AK13: 3.6 | AL13: 2.4 | AM13: 3.5 | AN13: 9.3 | AR13: 3.4 | AU13: 5.5 | AV13: 9.9 | AW13: 29.4 | AY13: 43.4 | BA13: 0.6 | BC13: 31.4 | BD13: 76 | BH13: 2 | BI13: 2.3 | BK13: 1.2 | BM13: 19.8 | BN13: 9.2 | BP13: 833.7
B14: 3:30 | C14: 14.8 | F14: 10.1 | K14: 19.8 | M14: 16.1 | N14: 20.3 | O14: 9.7 | P14: 2.4 | Q14: 4.8 | R14: 20 | S14: 20.2 | T14: 15.4 | U14: 9.8 | V14: 11.7 | W14: 51.7 | X14: 111.2 | Y14: 53.2 | Z14: 79.3 | AB14: 4.7 | AC14: 1.3 | AD14: 20.9 | AE14: 8.3 | AF14: 20.4 | AG14: 20.4 | AH14: 20.2 | AI14: 8.7 | AK14: 4.8 | AL14: 3.7 | AM14: 3.4 | AN14: 9.3 | AR14: 3.4 | AU14: 5.4 | AV14: 9.9 | AW14: 35.6 | AY14: 45 | BA14: 0.6 | BC14: 31 | BD14: 75.4 | BH14: 2 | BI14: 2.3 | BK14: 1.2 | BM14: 20 | BN14: 9.2 | BP14: 837.6
B15: 4:00 | C15: 15 | F15: 10.1 | K15: 19.7 | M15: 16 | N15: 20.3 | O15: 9.7 | P15: 2.4 | Q15: 4.8 | R15: 20 | S15: 20.1 | T15: 16.8 | U15: 9.8 | V15: 11.6 | W15: 49.3 | X15: 111.9 | Y15: 51.7 | Z15: 74.7 | AB15: 4.2 | AC15: 0.9 | AD15: 20.9 | AE15: 8.3 | AF15: 20.4 | AG15: 20.4 | AH15: 20.2 | AI15: 8.7 | AK15: 4.4 | AL15: 2.9 | AM15: 3.4 | AN15: 9.3 | AR15: 3.4 | AU15: 5.5 | AV15: 10 | AW15: 36.1 | AY15: 44.8 | BA15: 0.6 | BC15: 29.9 | BD15: 72.6 | BH15: 2 | BI15: 2.3 | BK15: 1.2 | BM15: 20 | BN15: 9.2 | BP15: 825.5
B16: 4:30 | C16: 15 | F16: 10.1 | K16: 19.7 | M16: 15.8 | N16: 20.2 | O16: 9.7 | P16: 2.4 | Q16: 4.8 | R16: 20 | S16: 20 | T16: 16.8 | U16: 9.8 | V16: 12.5 | W16: 57.6 | X16: 111.1 | Y16: 35.1 | Z16: 63.9 | AB16: 2.7 | AC16: 0.1 | AD16: 20.9 | AE16: 8.2 | AF16: 20.4 | AG16: 20.4 | AH16: 20.2 | AI16: 8.8 | AK16: 3.6 | AL16: 2.9 | AM16: 3.3 | AN16: 9.3 | AR16: 3.4 | AU16: 5.5 | AV16: 10 | AW16: 38.3 | AY16: 43.5 | BA16: 0.6 | BC16: 30.4 | BD16: 71.2 | BH16: 2 | BI16: 2.3 | BK16: 1.2 | BM16: 20 | BN16: 9.1 | BP16: 802.8
B17: 5:00 | C17: 14.5 | F17: 10.1 | K17: 19.7 | M17: 16.2 | N17: 20.3 | O17: 9.7 | P17: 2.4 | Q17: 4.9 | R17: 20 | S17: 20.5 | T17: 16.8 | U17: 9.9 | V17: 15.4 | W17: 68.7 | X17: 108.5 | Y17: 30.2 | Z17: 57.8 | AB17: 2 | AC17: 0.7 | AD17: 20.9 | AE17: 8.1 | AF17: 20.4 | AG17: 20.4 | AH17: 20.2 | AI17: 8.7 | AK17: 2.9 | AL17: 1.4 | AM17: 3.3 | AN17: 9.3 | AR17: 3.4 | AU17: 5.5 | AV17: 9.9 | AW17: 44.3 | AY17: 52.2 | BA17: 0.6 | BC17: 30.5 | BD17: 75.1 | BH17: 2 | BI17: 2.3 | BK17: 1.2 | BM17: 20 | BN17: 9.2 | BP17: 820.1
B18: 5:30 | C18: 14.6 | F18: 11.1 | K18: 19.8 | M18: 15.9 | N18: 20.3 | O18: 9.7 | P18: 2.4 | Q18: 5 | R18: 19.9 | T18: 16.8 | U18: 9.9 | V18: 14 | W18: 63.3 | X18: 112.1 | Y18: 26.2 | Z18: 51.7 | AB18: 1.3 | AC18: 0.1 | AD18: 20.9 | AE18: 8.1 | AF18: 20.4 | AG18: 20.4 | AH18: 20.2 | AI18: 8.8 | AK18: 4.1 | AL18: 2.4 | AM18: 3.2 | AN18: 9.3 | AR18: 3.4 | AU18: 5.4 | AV18: 9.8 | AW18: 44.5 | AY18: 53.8 | BA18: 0.6 | BC18: 31 | BD18: 73.4 | BH18: 2 | BI18: 2.3 | BK18: 1.2 | BM18: 20 | BN18: 9.2 | BP18: 788.5
B19: 6:00 | C19: 14.6 | F19: 13.8 | K19: 19.7 | M19: 15.7 | N19: 20.3 | O19: 9.7 | P19: 2.4 | Q19: 4.9 | R19: 20 | T19: 16.8 | U19: 9.9 | V19: 9 | W19: 50.3 | X19: 108.1 | Y19: 30.1 | Z19: 47.2 | AB19: 2.1 | AC19: 0.3 | AD19: 20.9 | AE19: 7.8 | AF19: 20.4 | AG19: 20.4 | AH19: 20.2 | AI19: 8.9 | AK19: 3 | AL19: 1.9 | AM19: 3.3 | AN19: 9.3 | AP19: 0.33 | AR19: 3.4 | AT19: 0.9 | AU19: 5.4 | AV19: 9.9 | AW19: 29.1 | AX19: 0.8 | AY19: 40.8 | AZ19: 0.6 | BA19: 0.6 | BB19: 0.8 | BC19: 30.3 | BD19: 66.2 | BE19: 9.3 | BH19: 2 | BI19: 2.3 | BK19: 1.2 | BM19: 20 | BN19: 9.2 | BO19: 0.1 | BP19: 744.23
B20: 6:30 | C20: 15.1 | F20: 13.9 | K20: 19.6 | M20: 15.1 | N20: 20.2 | O20: 9.8 | P20: 2.4 | Q20: 4.9 | R20: 20 | T20: 17.5 | U20: 9.9 | V20: 8.7 | W20: 47.4 | X20: 108.6 | Y20: 22.9 | Z20: 48.1 | AA20: 3.2 | AB20: 2.1 | AD20: 20.9 | AE20: 7.8 | AF20: 20.4 | AG20: 20.4 | AH20: 20.2 | AI20: 8.9 | AJ20: 7.9 | AK20: 2.5 | AL20: 1.5 | AM20: 3.3 | AN20: 9.3 | AP20: 19.44 | AR20: 3.4 | AS20: 0.8 | AT20: 5.8 | AU20: 5.4 | AV20: 9.9 | AW20: 33.2 | AX20: 17 | AY20: 40.9 | AZ20: 12.7 | BA20: 0.6 | BB20: 6 | BC20: 31.2 | BD20: 75.6 | BE20: 19.8 | BH20: 2 | BI20: 2.3 | BJ20: 0.5 | BK20: 1.2 | BM20: 20 | BN20: 9.1 | BO20: 6.6 | BP20: 835.94
B21: 7:00 | C21: 14.8 | F21: 11 | H21: 0.2 | K21: 19.6 | M21: 15.8 | N21: 20.3 | O21: 9.7 | P21: 2.4 | Q21: 4.9 | R21: 20 | T21: 16.6 | U21: 9.9 | V21: 6.1 | W21: 37.5 | X21: 109.6 | Y21: 23.4 | Z21: 45.2 | AA21: 13.3 | AB21: 1.2 | AD21: 20.9 | AE21: 7.8 | AF21: 20.4 | AG21: 20.4 | AH21: 20.2 | AI21: 8.9 | AJ21: 31.2 | AK21: 2.8 | AL21: 2.2 | AM21: 3.2 | AN21: 9.3 | AP21: 101.839 | AR21: 3.3 | AS21: 3.3 | AT21: 11.3 | AU21: 5.5 | AV21: 9.9 | AW21: 25.4 | AX21: 61.7 | AY21: 33.8 | AZ21: 47.7 | BA21: 0.6 | BB21: 12.6 | BC21: 31.4 | BD21: 70.5 | BE21: 20 | BH21: 2 | BI21: 2.3 | BJ21: 3.1 | BK21: 1.2 | BM21: 20 | BN21: 9.2 | BO21: 13 | BP21: 1018.439
B22: 7:30 | C22: 14.6 | F22: 7.2 | H22: 0.3 | J22: 0.1 | K22: 19.6 | M22: 16 | N22: 20.3 | O22: 9.6 | P22: 2.4 | Q22: 4.9 | R22: 20 | T22: 17.1 | U22: 9.9 | V22: 5.9 | W22: 27.1 | X22: 99.4 | Y22: 21.5 | Z22: 39.6 | AA22: 24.2 | AB22: 0.4 | AD22: 20.9 | AE22: 7.8 | AF22: 20.4 | AG22: 20.4 | AH22: 20.2 | AI22: 8.9 | AJ22: 29.4 | AK22: 2.7 | AL22: 2.3 | AM22: 3.2 | AN22: 9.3 | AP22: 189.855 | AR22: 3.3 | AS22: 6 | AT22: 12.8 | AU22: 5.5 | AV22: 9.9 | AW22: 21 | AX22: 103.5 | AY22: 30 | AZ22: 80.3 | BA22: 0.6 | BB22: 14.6 | BC22: 26.8 | BD22: 67.8 | BE22: 20 | BH22: 2 | BI22: 2.3 | BJ22: 5.6 | BK22: 1.2 | BM22: 20 | BN22: 9.2 | BO22: 14.8 | BP22: 1152.655
B23: 8:00 | C23: 15 | F23: 7.3 | H23: 0.3 | J23: 0.2 | K23: 19.6 | M23: 15.8 | N23: 20.3 | O23: 9.6 | P23: 2.4 | Q23: 4.8 | R23: 20 | T23: 17 | U23: 18.6 | V23: 6.8 | W23: 23.7 | X23: 95.4 | Y23: 19.9 | Z23: 33.9 | AA23: 32.1 | AB23: 0.6 | AC23: 0.1 | AD23: 20.9 | AE23: 7.7 | AF23: 20.4 | AG23: 20.4 | AH23: 20.2 | AI23: 8.9 | AJ23: 69.2 | AK23: 0.9 | AL23: 0.6 | AM23: 3.3 | AN23: 9.3 | AP23: 213.345 | AQ23: 0.1 | AR23: 3.3 | AS23: 8.5 | AT23: 13.4 | AU23: 5.4 | AV23: 9.8 | AW23: 12.7 | AX23: 127.3 | AY23: 13.6 | AZ23: 91 | BA23: 0.6 | BB23: 15.3 | BC23: 25.9 | BD23: 56.2 | BE23: 20 | BH23: 2 | BI23: 2.3 | BJ23: 7.9 | BK23: 1.2 | BM23: 20 | BN23: 9.2 | BO23: 15.8 | BP23: 1220.045
B24: 8:30 | C24: 15.1 | F24: 16.4 | H24: 0.3 | J24: 0.7 | K24: 19.7 | M24: 15.5 | N24: 20.2 | O24: 9.8 | P24: 2.4 | Q24: 4.9 | R24: 20 | T24: 17 | U24: 18.5 | V24: 10.1 | W24: 30.3 | X24: 91.7 | Y24: 22.9 | Z24: 36.6 | AA24: 32.6 | AB24: 1.5 | AC24: 0.9 | AD24: 20.9 | AE24: 7.6 | AF24: 20.4 | AG24: 20.4 | AH24: 20.2 | AI24: 8.9 | AJ24: 72.3 | AK24: 0.6 | AL24: 0.1 | AM24: 3.2 | AN24: 9.3 | AP24: 220.884 | AQ24: 0.2 | AR24: 3.3 | AS24: 10.9 | AT24: 13.6 | AU24: 5.4 | AV24: 9.9 | AW24: 8 | AX24: 130.1 | AY24: 8.1 | AZ24: 93.3 | BA24: 0.6 | BB24: 15.4 | BC24: 28.2 | BD24: 65.2 | BE24: 20 | BH24: 2 | BI24: 2.3 | BJ24: 10.1 | BK24: 1.2 | BM24: 20 | BN24: 9.2 | BO24: 16.2 | BP24: 1265.084
B25: 9:00 | C25: 14 | F25: 20.2 | H25: 0.3 | J25: 0.9 | K25: 19.7 | M25: 15.8 | N25: 20.3 | O25: 9.8 | P25: 2.4 | Q25: 4.9 | R25: 19.9 | T25: 17 | U25: 18.5 | V25: 15.2 | W25: 22.2 | X25: 108.7 | Y25: 25.2 | Z25: 38 | AA25: 33 | AB25: 2.1 | AC25: 1.3 | AD25: 20.9 | AE25: 7.6 | AF25: 20.4 | AG25: 20.4 | AH25: 20.2 | AI25: 8.5 | AJ25: 73.8 | AK25: 1 | AL25: 0.7 | AM25: 3.3 | AN25: 9.3 | AP25: 227.874 | AQ25: 0.3 | AR25: 3.3 | AS25: 12.5 | AT25: 13.7 | AU25: 5.4 | AV25: 9.9 | AW25: 1.4 | AX25: 131.5 | AY25: 0.1 | AZ25: 95 | BA25: 0.6 | BB25: 15.6 | BC25: 26.4 | BD25: 75.5 | BE25: 20 | BH25: 2 | BI25: 2.3 | BJ25: 11.9 | BK25: 1.2 | BM25: 20 | BN25: 9.2 | BO25: 16.3 | BP25: 1297.474
B26: 9:30 | C26: 14.6 | F26: 20.2 | H26: 0.3 | J26: 1 | K26: 19.7 | M26: 15.4 | N26: 20.2 | O26: 9.8 | P26: 2.4 | Q26: 2.5 | R26: 20 | T26: 17.3 | U26: 18.6 | V26: 18.7 | W26: 26.3 | X26: 116.4 | Y26: 23.6 | Z26: 40.9 | AA26: 32.9 | AB26: 2.4 | AC26: 0.8 | AD26: 20.9 | AE26: 7.5 | AF26: 20.4 | AG26: 20.4 | AH26: 20.2 | AI26: 8.5 | AJ26: 73.9 | AK26: 0.2 | AL26: 0.1 | AM26: 3.4 | AN26: 9.3 | AP26: 230.397 | AQ26: 0.3 | AR26: 3.2 | AS26: 14.1 | AT26: 13.7 | AU26: 5.4 | AV26: 9.9 | AW26: 0.6 | AX26: 126.7 | AZ26: 94.8 | BA26: 0.6 | BB26: 16.1 | BC26: 29 | BD26: 77.6 | BE26: 20 | BH26: 2 | BI26: 2.3 | BJ26: 13.7 | BK26: 1.2 | BM26: 20 | BN26: 9.3 | BO26: 16.3 | BP26: 1315.997
B27: 10:00 | C27: 14.9 | F27: 20.2 | H27: 0.3 | J27: 1.1 | K27: 19.7 | M27: 15.6 | N27: 20.3 | O27: 9.8 | P27: 2.4 | Q27: 0.2 | R27: 20 | T27: 17 | U27: 18.5 | V27: 18.7 | W27: 46.1 | X27: 122.5 | Y27: 36.5 | Z27: 57.9 | AA27: 33.1 | AB27: 2.5 | AC27: 2.2 | AD27: 20.9 | AE27: 7.5 | AF27: 20.4 | AG27: 20.4 | AH27: 20.2 | AI27: 8.5 | AJ27: 75.5 | AK27: 1.2 | AL27: 0.7 | AM27: 3.5 | AN27: 9.3 | AP27: 204.474 | AQ27: 0.4 | AR27: 3.1 | AS27: 15.8 | AT27: 13.8 | AU27: 5.5 | AV27: 9.8 | AW27: 9.4 | AX27: 131.3 | AZ27: 96.1 | BA27: 0.6 | BB27: 16.9 | BC27: 29.7 | BD27: 73.6 | BE27: 20 | BH27: 2 | BI27: 2.3 | BJ27: 15 | BK27: 1.2 | BM27: 20 | BN27: 9.2 | BO27: 15.8 | BP27: 1363.574
B28: 10:30 | C28: 14.8 | F28: 20.2 | H28: 0.3 | J28: 1.2 | K28: 19.7 | M28: 15.5 | N28: 20.2 | O28: 9.8 | P28: 2.4 | R28: 19.8 | T28: 18 | U28: 18.6 | V28: 14.1 | W28: 57.8 | X28: 123.8 | Y28: 55.7 | Z28: 74.7 | AA28: 32.8 | AB28: 7 | AC28: 3.2 | AD28: 20.9 | AE28: 7.4 | AF28: 20.4 | AG28: 20.4 | AH28: 20.2 | AI28: 8.9 | AJ28: 74.7 | AK28: 2.3 | AL28: 0.8 | AM28: 3.5 | AN28: 9.3 | AP28: 232.694 | AQ28: 0.4 | AR28: 3.1 | AS28: 16.6 | AT28: 13.8 | AU28: 5.4 | AV28: 10 | AW28: 24.4 | AX28: 131.4 | AY28: 6.3 | AZ28: 95.6 | BA28: 0.6 | BB28: 16.8 | BC28: 30.7 | BD28: 78.6 | BE28: 20 | BH28: 2 | BI28: 2.3 | BJ28: 16 | BK28: 1.2 | BM28: 20 | BN28: 9.2 | BO28: 16.4 | BP28: 1471.894
B29: 11:00 | C29: 15.1 | F29: 20.2 | H29: 0.3 | J29: 1.3 | K29: 19.7 | M29: 15.5 | N29: 20.3 | O29: 9.8 | P29: 2.4 | R29: 19.9 | T29: 18 | U29: 18.6 | V29: 15 | W29: 61.9 | X29: 122.4 | Y29: 60.1 | Z29: 72.3 | AA29: 33.2 | AB29: 12.4 | AC29: 6.1 | AD29: 20.9 | AE29: 3.3 | AF29: 20.4 | AG29: 20.4 | AH29: 20.2 | AI29: 8.9 | AJ29: 73.6 | AK29: 1.3 | AL29: 1.1 | AM29: 3.5 | AN29: 9.3 | AP29: 229.94 | AQ29: 0.4 | AR29: 3.2 | AS29: 17.4 | AT29: 13.6 | AU29: 5.5 | AV29: 9.8 | AW29: 44.6 | AX29: 131 | AY29: 11.7 | AZ29: 96.2 | BA29: 0.6 | BB29: 16.4 | BC29: 30.7 | BD29: 80.1 | BE29: 19.9 | BH29: 2 | BI29: 2.3 | BJ29: 16.8 | BK29: 1.2 | BM29: 20 | BN29: 9.2 | BO29: 17.3 | BP29: 1507.24
B30: 11:30 | C30: 15.1 | F30: 20.2 | H30: 0.3 | J30: 1.3 | K30: 19.6 | M30: 15.6 | N30: 20.3 | O30: 9.8 | P30: 2.2 | R30: 19.8 | T30: 18.4 | U30: 18.6 | V30: 13.3 | W30: 61.2 | X30: 85.4 | Y30: 76.3 | Z30: 82.1 | AA30: 32.8 | AB30: 12.5 | AC30: 7 | AD30: 20.9 | AE30: 7.4 | AF30: 20.4 | AG30: 20.4 | AH30: 20.2 | AI30: 8.6 | AJ30: 73.4 | AK30: 1.1 | AL30: 0.9 | AM30: 3.6 | AN30: 9.3 | AP30: 233.473 | AQ30: 0.4 | AR30: 3.1 | AS30: 17.8 | AT30: 13.8 | AU30: 5.4 | AV30: 9.9 | AW30: 73.7 | AX30: 132.1 | AY30: 33.4 | AZ30: 97.2 | BA30: 0.6 | BB30: 16.5 | BC30: 30.8 | BD30: 81 | BE30: 20 | BH30: 2 | BI30: 2.3 | BJ30: 17.2 | BK30: 1.2 | BM30: 19.8 | BN30: 9.2 | BO30: 17.3 | BP30: 1556.173
B31: 12:00 | C31: 14.6 | F31: 20.2 | H31: 0.3 | J31: 1.3 | K31: 19.6 | M31: 15.5 | N31: 20.2 | O31: 9.7 | P31: 2.3 | R31: 19.9 | T31: 18.7 | U31: 18.6 | V31: 9.8 | W31: 74.4 | X31: 113.1 | Y31: 73.5 | Z31: 89.2 | AA31: 31.9 | AB31: 13.3 | AC31: 7.6 | AD31: 20.9 | AE31: 7.4 | AF31: 20.4 | AG31: 20.4 | AH31: 20.2 | AI31: 8.6 | AJ31: 77.6 | AK31: 3.2 | AL31: 2.3 | AM31: 3.5 | AN31: 9.3 | AP31: 234.659 | AQ31: 0.5 | AR31: 3.1 | AS31: 18.4 | AT31: 13.7 | AU31: 5.4 | AV31: 9.8 | AW31: 103.6 | AX31: 129.5 | AY31: 82.7 | AZ31: 94.5 | BA31: 0.6 | BB31: 16.6 | BC31: 31.8 | BD31: 82.6 | BE31: 19.6 | BH31: 2 | BI31: 2.3 | BJ31: 17.5 | BK31: 1.2 | BM31: 20 | BN31: 9.2 | BO31: 15.9 | BP31: 1682.659
B32: 12:30 | C32: 14.2 | F32: 20 | H32: 0.3 | J32: 1.3 | K32: 19.5 | M32: 14.3 | N32: 20.1 | O32: 9.7 | P32: 2.4 | R32: 19.6 | T32: 19.3 | U32: 18.6 | V32: 11.8 | W32: 76.8 | X32: 124 | Y32: 90.8 | Z32: 97.7 | AA32: 32.5 | AB32: 17.7 | AC32: 11 | AD32: 20.9 | AE32: 7.4 | AF32: 20.4 | AG32: 20.4 | AH32: 20.2 | AI32: 8.9 | AJ32: 77.2 | AK32: 4.5 | AL32: 2.7 | AM32: 3.5 | AN32: 9.3 | AP32: 237.268 | AQ32: 0.5 | AR32: 3.2 | AS32: 18.3 | AT32: 13.6 | AU32: 5.3 | AV32: 9.9 | AW32: 100.3 | AX32: 129.6 | AY32: 94.9 | AZ32: 94.8 | BA32: 0.6 | BB32: 16.5 | BC32: 31.4 | BD32: 81.2 | BE32: 20 | BH32: 2 | BI32: 2.3 | BJ32: 17.4 | BK32: 1.2 | BM32: 19.6 | BN32: 9.2 | BO32: 17.2 | BP32: 1743.268
B33: 13:00 | C33: 14.6 | F33: 13.6 | H33: 0.3 | J33: 1.3 | K33: 19.4 | M33: 15.5 | N33: 20.2 | O33: 9.6 | P33: 2.4 | R33: 19.9 | T33: 18.2 | U33: 18.6 | V33: 17.7 | W33: 80.3 | X33: 124.5 | Y33: 92.8 | Z33: 106.9 | AA33: 32.8 | AB33: 16.9 | AC33: 10.1 | AD33: 20.9 | AE33: 7.3 | AF33: 20.4 | AG33: 20.4 | AH33: 20.2 | AI33: 9 | AJ33: 78.9 | AK33: 3.8 | AL33: 3.6 | AM33: 3.5 | AN33: 9.3 | AP33: 241.503 | AQ33: 0.4 | AR33: 3.2 | AS33: 17.8 | AT33: 13.5 | AU33: 5.4 | AV33: 9.9 | AW33: 121.5 | AX33: 129.7 | AY33: 112 | AZ33: 94.6 | BA33: 0.6 | BB33: 16.5 | BC33: 31.8 | BD33: 83 | BE33: 20 | BH33: 2 | BI33: 2.3 | BJ33: 16.7 | BK33: 1.2 | BM33: 20 | BN33: 9.2 | BO33: 17.5 | BP33: 1803.203
B34: 13:30 | C34: 14.3 | F34: 12.2 | H34: 0.3 | J34: 1.3 | K34: 19.4 | M34: 15.5 | N34: 20.2 | O34: 9.6 | P34: 2.4 | Q34: 1 | R34: 19.9 | T34: 19 | U34: 18.5 | V34: 18 | W34: 79.7 | X34: 124.8 | Y34: 95.4 | Z34: 106.7 | AA34: 31.3 | AB34: 19.1 | AC34: 12.9 | AD34: 20.9 | AE34: 7.3 | AF34: 20.4 | AG34: 20.4 | AH34: 20.2 | AI34: 9.1 | AJ34: 77.9 | AK34: 8.4 | AL34: 7.5 | AM34: 3.5 | AN34: 9.3 | AP34: 242.58 | AQ34: 0.4 | AR34: 3.2 | AS34: 17.1 | AT34: 13.7 | AU34: 5.4 | AV34: 10 | AW34: 125.4 | AX34: 128.8 | AY34: 118.2 | AZ34: 94.3 | BA34: 0.6 | BB34: 16.9 | BC34: 31.8 | BD34: 83.8 | BE34: 20 | BH34: 2 | BI34: 2.3 | BJ34: 16.3 | BK34: 1.2 | BM34: 20 | BN34: 9.2 | BO34: 17.2 | BP34: 1826.78
B35: 14:00 | C35: 14.6 | F35: 12.4 | H35: 0.3 | J35: 1.2 | K35: 19.5 | M35: 15.5 | N35: 20.2 | O35: 9.6 | P35: 1.8 | Q35: 5 | R35: 19.9 | T35: 19.1 | U35: 18.5 | V35: 22.6 | W35: 78.7 | X35: 122.7 | Y35: 101.1 | Z35: 106.6 | AA35: 32.8 | AB35: 17.9 | AC35: 13.4 | AD35: 20.9 | AE35: 7.3 | AF35: 20.4 | AG35: 20.4 | AH35: 20.2 | AI35: 9.1 | AJ35: 75.5 | AK35: 8.1 | AL35: 5.9 | AM35: 3.5 | AN35: 9.3 | AP35: 231.661 | AQ35: 0.4 | AR35: 3.2 | AS35: 16 | AT35: 13.7 | AU35: 5.4 | AV35: 10 | AW35: 137.7 | AX35: 125.6 | AY35: 124.8 | AZ35: 91.5 | BA35: 0.6 | BB35: 16.8 | BC35: 32.1 | BD35: 85.3 | BE35: 20 | BH35: 2 | BI35: 2.3 | BJ35: 14.4 | BK35: 1.2 | BM35: 20 | BN35: 9.2 | BO35: 17.4 | BP35: 1835.261
B36: 14:30 | C36: 14.5 | F36: 12.3 | H36: 0.3 | J36: 1.1 | K36: 19.5 | M36: 15.2 | N36: 20.1 | O36: 9.6 | P36: 1.9 | Q36: 5 | R36: 20 | T36: 18.7 | U36: 18.5 | V36: 25.3 | W36: 78.1 | X36: 123.9 | Y36: 98.2 | Z36: 102.2 | AA36: 32.6 | AB36: 18 | AC36: 13.7 | AD36: 20.9 | AE36: 7.3 | AF36: 20.4 | AG36: 20.4 | AH36: 20.2 | AI36: 9.1 | AJ36: 77.7 | AK36: 7.7 | AL36: 5.8 | AM36: 3.5 | AN36: 9.3 | AP36: 238.923 | AQ36: 0.4 | AR36: 3.2 | AS36: 13.6 | AT36: 13.9 | AU36: 5.4 | AV36: 10 | AW36: 146.5 | AX36: 130.7 | AY36: 127.8 | AZ36: 94.9 | BA36: 0.6 | BB36: 16.6 | BC36: 31.6 | BD36: 87.7 | BE36: 20 | BH36: 2 | BI36: 2.3 | BJ36: 13.5 | BK36: 1.2 | BM36: 20 | BN36: 9.2 | BO36: 17 | BP36: 1858.023
B37: 15:00 | C37: 14.1 | F37: 11.8 | H37: 0.3 | J37: 1 | K37: 19.4 | M37: 15.7 | N37: 20.2 | O37: 9.6 | P37: 2.4 | Q37: 5 | R37: 19.8 | T37: 18.8 | U37: 18.5 | V37: 28.4 | W37: 79.7 | X37: 123.2 | Y37: 104.7 | Z37: 105.9 | AA37: 32.8 | AB37: 18.9 | AC37: 13.1 | AD37: 20.9 | AE37: 7.2 | AF37: 20.4 | AG37: 20.4 | AH37: 20.2 | AI37: 9.1 | AJ37: 73.9 | AK37: 9.9 | AL37: 4.9 | AM37: 3.4 | AN37: 9.3 | AP37: 225.217 | AQ37: 0.1 | AR37: 3.1 | AS37: 11.3 | AT37: 13.5 | AU37: 5.5 | AV37: 10 | AW37: 147.6 | AX37: 128.8 | AY37: 127.2 | AZ37: 92.5 | BA37: 0.6 | BB37: 16.1 | BC37: 31.9 | BD37: 87.6 | BE37: 20 | BH37: 2 | BI37: 2.3 | BJ37: 12 | BK37: 1.2 | BM37: 19.8 | BN37: 9.2 | BO37: 16.6 | BP37: 1847.017
B38: 15:30 | C38: 15.3 | F38: 16.7 | H38: 0.3 | J38: 0.9 | K38: 19.4 | M38: 15.7 | N38: 20.3 | O38: 9.7 | P38: 2.4 | Q38: 5.1 | R38: 20 | T38: 15.2 | U38: 18.5 | V38: 28.2 | W38: 81.2 | X38: 119 | Y38: 106.7 | Z38: 101.3 | AA38: 29.6 | AB38: 17.6 | AC38: 14.7 | AD38: 20.9 | AE38: 7.2 | AF38: 20.4 | AG38: 20.4 | AH38: 20.2 | AI38: 9.1 | AJ38: 67.1 | AK38: 10.4 | AL38: 7.8 | AM38: 3.2 | AN38: 9.3 | AP38: 204.822 | AQ38: 0.2 | AR38: 3.2 | AS38: 9.2 | AT38: 12.5 | AU38: 5.5 | AV38: 9.8 | AW38: 153.7 | AX38: 125.1 | AY38: 128.4 | AZ38: 90.3 | BA38: 0.6 | BB38: 15 | BC38: 31.5 | BD38: 86.6 | BE38: 20 | BH38: 2 | BI38: 2.3 | BJ38: 9.3 | BK38: 1.2 | BM38: 20 | BN38: 9.2 | BO38: 15.4 | BP38: 1809.622
B39: 16:00 | C39: 15.1 | F39: 18.8 | H39: 0.3 | J39: 0.5 | K39: 19.5 | M39: 15.5 | N39: 20.2 | O39: 9.7 | P39: 2.4 | Q39: 5 | R39: 19.9 | T39: 10.9 | U39: 18.8 | V39: 27.4 | W39: 81.6 | X39: 115 | Y39: 108.3 | Z39: 105.8 | AA39: 22.6 | AB39: 17.8 | AC39: 14 | AD39: 20.9 | AE39: 7.2 | AF39: 20.4 | AG39: 20.4 | AH39: 20.2 | AI39: 9.1 | AJ39: 28.5 | AK39: 12.8 | AL39: 11.2 | AM39: 3 | AN39: 9.3 | AP39: 179.288 | AQ39: 0.3 | AR39: 3.1 | AS39: 4.6 | AT39: 10.5 | AU39: 5.4 | AV39: 9.9 | AW39: 155.2 | AX39: 93.7 | AY39: 128.4 | AZ39: 77.1 | BA39: 0.6 | BB39: 12.6 | BC39: 29.5 | BD39: 85.4 | BE39: 20 | BH39: 2 | BI39: 2.3 | BJ39: 6.3 | BK39: 1.2 | BM39: 20 | BN39: 9.2 | BO39: 12.2 | BP39: 1680.888
B40: 16:30 | C40: 15.2 | F40: 18.8 | H40: 0.3 | J40: 0.5 | K40: 19.5 | M40: 15.4 | N40: 20.2 | O40: 9.7 | P40: 2.4 | Q40: 5.1 | R40: 20 | T40: 20 | U40: 18.8 | V40: 26.2 | W40: 81.1 | X40: 113.9 | Y40: 107.2 | Z40: 105.8 | AA40: 13.5 | AB40: 17.2 | AC40: 10.8 | AD40: 20.9 | AE40: 7.2 | AF40: 20.4 | AG40: 20.4 | AH40: 20.2 | AI40: 9.1 | AJ40: 16.6 | AK40: 9.9 | AL40: 10.6 | AM40: 3.2 | AN40: 9.3 | AP40: 64.561 | AQ40: 0.2 | AR40: 3.1 | AS40: 3 | AT40: 3.7 | AU40: 5.5 | AV40: 10.1 | AW40: 161.2 | AX40: 38.7 | AY40: 129.3 | AZ40: 36.9 | BA40: 0.6 | BB40: 4.2 | BC40: 30.7 | BD40: 86.4 | BE40: 20 | BH40: 2 | BI40: 2.3 | BJ40: 2.5 | BK40: 1.2 | BM40: 20 | BN40: 9.2 | BO40: 5.1 | BP40: 1429.861
B41: 17:00 | C41: 15.3 | F41: 20.2 | H41: 0.3 | J41: 0.2 | K41: 19.4 | M41: 15.3 | N41: 20.2 | O41: 9.7 | P41: 2.4 | Q41: 5.1 | R41: 19.9 | T41: 19.6 | U41: 18.8 | V41: 22.8 | W41: 81.8 | X41: 109.3 | Y41: 110.7 | Z41: 105.4 | AA41: 1.8 | AB41: 16.3 | AC41: 10.2 | AD41: 20.9 | AE41: 7.4 | AF41: 20.4 | AG41: 20.4 | AH41: 20.2 | AI41: 9.1 | AJ41: 10.8 | AK41: 10.8 | AL41: 9.4 | AM41: 3.4 | AN41: 9.3 | AP41: 36.689 | AQ41: 0.1 | AR41: 3.3 | AS41: 2.6 | AT41: 0.3 | AU41: 5.5 | AV41: 9.9 | AW41: 164.3 | AX41: 5.3 | AY41: 129.1 | AZ41: 5 | BA41: 0.6 | BB41: 0.3 | BC41: 30.5 | BD41: 87.9 | BE41: 20 | BH41: 2 | BI41: 2.3 | BJ41: 2 | BK41: 1.2 | BM41: 20 | BN41: 9.1 | BO41: 0.1 | BP41: 1304.889
B42: 17:30 | C42: 14.6 | F42: 20.4 | H42: 0.3 | J42: 0.1 | K42: 19.5 | M42: 16.3 | N42: 20.2 | O42: 9.7 | P42: 2.4 | Q42: 5.1 | R42: 20 | T42: 19.8 | U42: 18.8 | V42: 20 | W42: 81.8 | X42: 107.6 | Y42: 108.5 | Z42: 104.6 | AB42: 17.1 | AC42: 9.4 | AD42: 20.9 | AE42: 7.4 | AF42: 20.4 | AG42: 20.4 | AH42: 20.2 | AI42: 9 | AK42: 10.5 | AL42: 9 | AM42: 3.5 | AN42: 9.3 | AP42: 1.472 | AR42: 3.3 | AS42: 0.2 | AU42: 5.4 | AV42: 10 | AW42: 163.3 | AY42: 129 | AZ42: 0.1 | BA42: 0.6 | BC42: 29.3 | BD42: 86.8 | BE42: 20 | BH42: 2 | BI42: 2.3 | BJ42: 0.2 | BK42: 1.2 | BM42: 20 | BN42: 9.2 | BP42: 1231.172
B43: 18:00 | C43: 14.3 | F43: 20.4 | H43: 0.3 | K43: 19.5 | M43: 17.5 | N43: 20.2 | O43: 9.7 | P43: 2.4 | Q43: 5.1 | R43: 20 | T43: 20 | U43: 18.8 | V43: 16.7 | W43: 81.8 | X43: 107.3 | Y43: 103.5 | Z43: 105.7 | AB43: 12.5 | AC43: 11.3 | AD43: 20.9 | AE43: 7.2 | AF43: 20.4 | AG43: 20.4 | AH43: 20.2 | AI43: 9.1 | AK43: 6.9 | AL43: 3.9 | AM43: 3.5 | AN43: 9.3 | AR43: 3.4 | AU43: 5.5 | AV43: 10 | AW43: 149.9 | AY43: 129.1 | BA43: 0.6 | BC43: 29.4 | BD43: 83.4 | BE43: 20.1 | BH43: 2 | BI43: 2.3 | BK43: 1.2 | BM43: 20.2 | BN43: 9.3 | BP43: 1195.2
B44: 18:30 | C44: 14 | F44: 20.4 | H44: 0.3 | K44: 19.5 | M44: 17.8 | N44: 20.3 | O44: 9.7 | P44: 2.4 | Q44: 5 | R44: 20 | T44: 19.7 | U44: 18.8 | V44: 13.5 | W44: 81.1 | X44: 103.9 | Y44: 106.5 | Z44: 104.3 | AB44: 14.4 | AC44: 8.5 | AD44: 20.9 | AE44: 7.2 | AF44: 20.4 | AG44: 20.4 | AH44: 20.2 | AI44: 8.9 | AK44: 4.1 | AL44: 1.8 | AM44: 3.5 | AN44: 9.3 | AR44: 3.3 | AU44: 5.4 | AV44: 9.9 | AW44: 140.4 | AY44: 127.3 | BA44: 0.6 | BC44: 28 | BD44: 81 | BE44: 20 | BH44: 2 | BI44: 2.3 | BK44: 1.2 | BM44: 20.1 | BN44: 9.4 | BP44: 1167.7
B45: 19:00 | C45: 13 | F45: 20.4 | H45: 0.3 | K45: 19.7 | M45: 17.8 | N45: 20.3 | O45: 9.7 | P45: 2.4 | Q45: 5 | R45: 20 | T45: 19.6 | U45: 18.7 | V45: 14.7 | W45: 73.7 | X45: 95 | Y45: 96.8 | Z45: 100.6 | AB45: 8.8 | AC45: 6.1 | AD45: 20.9 | AE45: 7.2 | AF45: 20.4 | AG45: 20.4 | AH45: 20.2 | AI45: 8.3 | AK45: 1.9 | AL45: 0.5 | AM45: 3.5 | AN45: 9.3 | AR45: 3.4 | AU45: 5.4 | AV45: 9.9 | AW45: 101.2 | AY45: 111 | BA45: 0.6 | BC45: 29.2 | BD45: 79 | BE45: 20 | BH45: 2 | BI45: 2.3 | BK45: 1.2 | BM45: 20 | BN45: 9.4 | BP45: 1069.8
B46: 19:30 | C46: 14.5 | F46: 20.4 | G46: 0.5 | H46: 0.3 | K46: 19.8 | M46: 17.8 | N46: 20.3 | O46: 9.7 | P46: 2.4 | Q46: 5 | R46: 20 | T46: 20 | U46: 18.8 | V46: 14 | W46: 64.8 | X46: 97 | Y46: 112.5 | Z46: 100.7 | AB46: 10 | AC46: 6.9 | AD46: 20.9 | AE46: 7.2 | AF46: 20.4 | AG46: 20.4 | AH46: 20.2 | AI46: 7.9 | AK46: 1.6 | AL46: 1.5 | AM46: 3.5 | AN46: 9.3 | AR46: 3.4 | AU46: 5.4 | AV46: 9.9 | AW46: 95.1 | AY46: 105.8 | BA46: 0.6 | BC46: 30.1 | BD46: 77.5 | BE46: 20 | BH46: 2 | BI46: 2.3 | BK46: 1.2 | BM46: 20 | BN46: 9.3 | BP46: 1070.9
B47: 20:00 | C47: 14.3 | F47: 20.4 | G47: 3.1 | H47: 0.3 | K47: 19.8 | M47: 17.7 | N47: 20.2 | O47: 9.7 | P47: 2.4 | Q47: 4.9 | R47: 20 | T47: 20 | U47: 18.8 | V47: 12 | W47: 68.8 | X47: 94.2 | Y47: 113.5 | Z47: 100.8 | AB47: 9.8 | AC47: 9 | AD47: 20.9 | AE47: 7.2 | AF47: 20.4 | AG47: 20.4 | AH47: 20.2 | AI47: 7.9 | AK47: 1 | AL47: 0.6 | AM47: 3.6 | AN47: 9.3 | AR47: 3.4 | AU47: 5.4 | AV47: 9.9 | AW47: 93.1 | AY47: 106.8 | BA47: 0.6 | BC47: 28.9 | BD47: 79.4 | BE47: 20 | BH47: 2 | BI47: 2.2 | BK47: 1.2 | BM47: 20 | BN47: 9.3 | BP47: 1073.4
B48: 20:30 | C48: 14.6 | F48: 20.4 | G48: 3.1 | H48: 0.3 | K48: 19.8 | M48: 17.8 | N48: 20.3 | O48: 9.7 | P48: 2.4 | Q48: 4.9 | R48: 20 | T48: 20 | U48: 18.7 | V48: 10.5 | W48: 64.6 | X48: 87.5 | Y48: 105.4 | Z48: 98.1 | AB48: 10.2 | AC48: 6.6 | AD48: 20.9 | AE48: 7.2 | AF48: 20.4 | AG48: 20.4 | AH48: 20.2 | AI48: 7.9 | AK48: 1.2 | AL48: 0.8 | AM48: 3.6 | AN48: 9.3 | AR48: 3.4 | AU48: 5.4 | AV48: 9.9 | AW48: 105.7 | AY48: 120.8 | BA48: 0.6 | BC48: 29.7 | BD48: 80.9 | BE48: 20 | BH48: 2 | BI48: 2.2 | BK48: 1.2 | BM48: 20 | BN48: 9.4 | BP48: 1078
B49: 21:00 | C49: 14.7 | F49: 20.4 | G49: 3.1 | H49: 0.3 | K49: 19.8 | M49: 17.5 | N49: 20.2 | O49: 9.7 | P49: 2.4 | Q49: 4.9 | R49: 19.8 | T49: 20 | U49: 18.6 | V49: 13.6 | W49: 59.6 | X49: 91.1 | Y49: 114.7 | Z49: 97.7 | AB49: 11.3 | AC49: 11.4 | AD49: 20.9 | AE49: 7.2 | AF49: 20.4 | AG49: 20.4 | AH49: 20.2 | AI49: 7.9 | AK49: 0.7 | AL49: 0.6 | AM49: 3.6 | AN49: 9.3 | AR49: 3.4 | AU49: 5.4 | AV49: 10 | AW49: 94.2 | AY49: 106.1 | BA49: 0.6 | BC49: 27.9 | BD49: 78.1 | BE49: 20 | BH49: 2 | BI49: 2.2 | BK49: 1.2 | BM49: 19.9 | BN49: 9.4 | BP49: 1062.4
B50: 21:30 | C50: 14.8 | F50: 20.4 | G50: 3.1 | H50: 0.3 | K50: 19.8 | M50: 17.7 | N50: 20.3 | O50: 9.7 | P50: 2.4 | Q50: 5.1 | R50: 20 | T50: 20 | U50: 18.6 | V50: 16.7 | W50: 56.9 | X50: 107.1 | Y50: 113.2 | Z50: 97.8 | AB50: 11.9 | AC50: 10.5 | AD50: 20.9 | AE50: 7.2 | AF50: 20.4 | AG50: 20.4 | AH50: 20.2 | AI50: 7.9 | AK50: 1.1 | AL50: 1.5 | AM50: 3.5 | AN50: 9.3 | AR50: 3.4 | AU50: 5.4 | AV50: 9.8 | AW50: 79 | AY50: 85.6 | BA50: 0.6 | BC50: 30.3 | BD50: 82.2 | BE50: 20 | BH50: 2 | BI50: 2.2 | BK50: 1.2 | BM50: 20 | BN50: 9.4 | BP50: 1049.8
B51: 22:00 | C51: 14.5 | F51: 20.3 | G51: 3.1 | H51: 0.3 | K51: 19.8 | M51: 17.6 | N51: 20.2 | O51: 9.7 | P51: 2.4 | Q51: 5 | R51: 19.9 | T51: 20 | U51: 18.6 | V51: 13.7 | W51: 58.9 | X51: 116.8 | Y51: 110.2 | Z51: 94.2 | AB51: 9.1 | AC51: 6.8 | AD51: 20.9 | AE51: 7.1 | AF51: 20.4 | AG51: 20.4 | AH51: 20.2 | AI51: 8.8 | AK51: 0.3 | AL51: 0.5 | AM51: 3.6 | AN51: 9.3 | AR51: 3.4 | AU51: 5.4 | AV51: 9.9 | AW51: 67.5 | AY51: 61.6 | BA51: 0.6 | BC51: 31.5 | BD51: 88.6 | BE51: 20 | BH51: 2 | BI51: 2.2 | BK51: 1.2 | BM51: 20 | BN51: 9.4 | BP51: 1015.9
B52: 22:30 | C52: 14.5 | F52: 20.2 | G52: 3 | H52: 0.3 | K52: 19.8 | M52: 17.8 | N52: 20.2 | O52: 9.7 | P52: 2.4 | Q52: 5 | R52: 20 | T52: 20 | U52: 18.6 | V52: 11.1 | W52: 57.1 | X52: 117.5 | Y52: 90.8 | Z52: 95.7 | AB52: 5 | AC52: 3.2 | AD52: 20.9 | AE52: 7.1 | AF52: 20.4 | AG52: 20.4 | AH52: 20.2 | AI52: 8.8 | AK52: 0.2 | AM52: 3.5 | AN52: 9.3 | AR52: 3.4 | AU52: 5.5 | AV52: 9.9 | AW52: 52.9 | AY52: 47.4 | BA52: 0.6 | BC52: 31.2 | BD52: 85.6 | BE52: 20 | BH52: 2 | BI52: 2.2 | BK52: 1.2 | BM52: 20.1 | BN52: 9.4 | BP52: 954.1
B53: 23:00 | C53: 14.5 | F53: 20.2 | G53: 3.1 | H53: 0.3 | K53: 19.8 | M53: 17.6 | N53: 20.3 | O53: 9.7 | P53: 2.4 | Q53: 5 | R53: 19.9 | T53: 20 | U53: 18.6 | V53: 20.6 | W53: 49.7 | X53: 119.5 | Y53: 82.8 | Z53: 91.8 | AB53: 4.7 | AC53: 1.5 | AD53: 20.9 | AE53: 7.1 | AF53: 20.4 | AG53: 20.4 | AH53: 20.2 | AI53: 8.8 | AM53: 3.6 | AN53: 9.3 | AR53: 3.4 | AU53: 5.5 | AV53: 9.9 | AW53: 43.5 | AY53: 39.6 | BA53: 0.6 | BC53: 31.1 | BD53: 82.5 | BE53: 20 | BH53: 2 | BI53: 2.2 | BK53: 1.2 | BM53: 20 | BN53: 9.4 | BP53: 923.6
B54: 23:30 | C54: 14.4 | F54: 20.3 | G54: 3.1 | H54: 0.3 | K54: 19.8 | M54: 17.7 | N54: 20.2 | O54: 9.7 | P54: 2.4 | Q54: 4.9 | R54: 20 | S54: 20.2 | T54: 18.7 | U54: 18.6 | V54: 17.6 | W54: 44 | X54: 116.5 | Y54: 74.6 | Z54: 88.7 | AB54: 4.9 | AC54: 2.5 | AD54: 20.9 | AE54: 7.1 | AF54: 20.4 | AG54: 20.4 | AH54: 20.2 | AI54: 8.6 | AL54: 0.3 | AM54: 3.6 | AN54: 9.3 | AR54: 3.3 | AU54: 5.4 | AV54: 10 | AW54: 41.8 | AY54: 44.8 | BA54: 0.6 | BC54: 31.9 | BD54: 86.4 | BE54: 20 | BH54: 2 | BI54: 2.2 | BK54: 1.2 | BM54: 20 | BN54: 9.4 | BP54: 928.9
B55: 0:00 | C55: 14.2 | F55: 20.2 | G55: 3.1 | H55: 0.3 | K55: 19.8 | M55: 17.4 | N55: 20.2 | O55: 9.7 | P55: 2.4 | Q55: 4.9 | R55: 19.8 | S55: 20 | T55: 20 | U55: 18.6 | V55: 16.6 | W55: 61.3 | X55: 110.6 | Y55: 68.3 | Z55: 85.5 | AB55: 5 | AC55: 0.5 | AD55: 20.9 | AE55: 7 | AF55: 20.4 | AG55: 20.4 | AH55: 20.2 | AI55: 8.6 | AM55: 3.6 | AN55: 9.3 | AR55: 3.4 | AU55: 5.5 | AV55: 9.9 | AW55: 33.6 | AY55: 40.7 | BA55: 0.6 | BC55: 31.8 | BD55: 83.2 | BE55: 20 | BH55: 2 | BI55: 2.2 | BK55: 1.2 | BM55: 19.9 | BN55: 9.4 | BP55: 912.2
B56: EJEC MWh | C56: 351.95 | D56: 0 | E56: 0 | F56: 390.8 | G56: 14.15 | H56: 5.2 | I56: 0 | J56: 9.25 | K56: 471.85 | L56: 0 | M56: 389.4 | N56: 485.9 | O56: 232.85 | P56: 56.9 | Q56: 98.4 | R56: 478.65 | S56: 121.35 | T56: 422.8 | U56: 381.6 | V56: 358.4 | W56: 1411.55 | X56: 2633.2 | Y56: 1727.95 | Z56: 1984.4 | AA56: 298.7 | AB56: 211.35 | AC56: 128.5 | AD56: 501.6 | AE56: 179.3 | AF56: 489.6 | AG56: 489.6 | AH56: 484.8 | AI56: 208.95 | AJ56: 658.3 | AK56: 82.6 | AL56: 62.45 | AM56: 81.85 | AN56: 223.2 | AO56: 0 | AP56: 2121.594 | AQ56: 3 | AR56: 79.3 | AS56: 127.9 | AT56: 131.4 | AU56: 130.55 | AV56: 237.9 | AW56: 1719.2 | AX56: 1194.95 | AY56: 1627.95 | AZ56: 883.5 | BA56: 14.4 | BB56: 155.55 | BC56: 724.5 | BD56: 1888.5 | BE56: 364.35 | BF56: 4.4 | BG56: 0 | BH56: 47.9 | BI56: 54.85 | BJ56: 122.95 | BK56: 28.8 | BL56: 0 | BM56: 479.6 | BN56: 221.85 | BO56: 158.75 | BP56: 28650.994
L70: TERMOELÉCTRICA | M70: 459.1 | N70: 1.6023877 | O70: #FF0000
L71: SOLAR | M71: 5865.844 | N71: 20.47344 | O71: #FBFB00
L72: HIDROELÉCTRICA | M72: 7765.5 | N72: 27.103772 | O72: #00B0F0
L73: EÓLICA | M73: 14560.55 | N73: 50.820401 | O73: #FBBD00

Sheet COGENERACIÓN
B3: sábado, 26 de Abril del 2025
B5: CENTRALES DE COGENERACIÓN DEL SEIN
B6: HORA | C6: AGRO INDUSTRIAL PARAMONGA S.A. | D6: AGROAURORA S.A.C. | E6: AGROINDUSTRIAS SAN JACINTO S.A.A. | F6: BIOENERGIA DEL CHIRA S.A. | G6: GM OPERACIONES S.A.C. | H6: SDF ENERGIA SAC | I6: TOTAL COGENERACION
C7: C.T. PARAMONGA | D7: C.T. MAPLE | E7: C.T SAN JACINTO | F7: C.T. CAÑA BRAVA | G7: C.T. REFINERÍA TALARA | H7: C.T. OQUENDO | I7: MW
B8: 0:30 | C8: 15 | G8: 37.2 | H8: 32.8 | I8: 85
B9: 1:00 | C9: 15.1 | G9: 38 | H9: 32.8 | I9: 85.9
B10: 1:30 | C10: 15 | G10: 38.6 | H10: 32.8 | I10: 86.4
B11: 2:00 | C11: 15 | G11: 38.7 | H11: 32.8 | I11: 86.5
B12: 2:30 | C12: 14.7 | G12: 38.5 | H12: 32.7 | I12: 85.9
B13: 3:00 | C13: 14.8 | G13: 38.7 | H13: 32.7 | I13: 86.2
B14: 3:30 | C14: 14.8 | G14: 38.2 | H14: 32.7 | I14: 85.7
B15: 4:00 | C15: 15 | G15: 38.2 | H15: 32.7 | I15: 85.9
B16: 4:30 | C16: 15 | G16: 37.9 | H16: 32.5 | I16: 85.4
B17: 5:00 | C17: 14.5 | G17: 36.9 | H17: 32.6 | I17: 84
B18: 5:30 | C18: 14.6 | G18: 37.7 | H18: 32.6 | I18: 84.9
B19: 6:00 | C19: 14.6 | G19: 38 | H19: 32.6 | I19: 85.2
... B55: 0:00 | C55: 14.2 | G55: 37.3 | H55: 32.5 | I55: 84
B56: EJEC MWh | C56: 351.95 | D56: 0 | E56: 0 | F56: 0 | G56: 901.2 | H56: 776.2 | I56: 2029.35

Sheet EVO_PRO_ENE
B3: martes, 1 de Abril del 2025 - sábado, 26 de Abril del 2025
B5: EVOLUCIÓN DE LA PRODUCCIÓN DE LA ENERGÍA DIARIA DE LOS INTEGRANTES DEL COES (MWh)
B6: EMPRESA | C6: CENTRAL | D6: UNIDAD | E6: TIPO | F6: Abril
F7: 1 | G7: 2 | H7: 3 | I7: 4 | J7: 5 | K7: 6 | L7: 7 | M7: 8 | N7: 9 | O7: 10 | P7: 11 | Q7: 12 | R7: 13 | S7: 14 | T7: 15 | U7: 16 | V7: 17 | W7: 18 | X7: 19 | Y7: 20 | Z7: 21 | AA7: 22 | AB7: 23 | AC7: 24 | AD7: 25 | AE7: 26 | AF7: TOTAL
B8: AGRO INDUSTRIAL PARAMONGA S.A. | C8: C.T. PARAMONGA | D8: TV-01 | E8: TERMOELÉCTRICA | F8: 169.5 | G8: 245.7 | H8: 400.2 | I8: 407.05 | J8: 368.75 | K8: 335.9 | L8: 386.5 | M8: 390.9 | N8: 397 | O8: 404.2 | P8: 409.9 | Q8: 377.85 | R8: 212.4 | S8: 293.4 | T8: 323.2 | U8: 347.1 | V8: 360.45 | W8: 338.55 | X8: 267 | Y8: 390.9 | Z8: 398.15 | AA8: 359.3 | AB8: 385.5 | AC8: 371 | AD8: 358.5 | AE8: 351.95 | AF8: 9050.85
B9: AGROAURORA S.A.C. | C9: C.T. MAPLE ETANOL | D9: TV | E9: TERMOELÉCTRICA | AF9: 0
B10: AGROINDUSTRIAS SAN JACINTO S.A.A. | C10: C.T. SAN JACINTO | D10: CENTRAL | E10: TERMOELÉCTRICA | F10: 120.97 | G10: 109.3 | H10: 25.6 | AF10: 255.87
B11: ANDEAN POWER S.A.C. | C11: C.H.CARHUAC | D11: CENTRAL | E11: HIDROELÉCTRICA | F11: 488.5 | G11: 480.45 | H11: 486.9 | I11: 484.9 | J11: 483.9 | K11: 480.35 | L11: 485.6 | M11: 486.15 | N11: 486.95 | O11: 483.35 | P11: 485.85 | Q11: 485.7 | R11: 457.1 | S11: 475.5 | T11: 487.15 | U11: 483.65 | V11: 470.35 | W11: 485.5 | X11: 483.55 | Y11: 458.1 | Z11: 402.6 | AA11: 283.4 | AB11: 291.3 | AC11: 271.9 | AD11: 369.8 | AE11: 390.8 | AF11: 11629.3
B12: ASOCIACIÓN SANTA LUCIA DE CHACAS | C12: C.H. HUALLIN | D12: CENTRAL | E12: HIDROELÉCTRICA | F12: 71.9 | G12: 70.3 | H12: 71.4 | I12: 71.5 | J12: 72 | K12: 72 | L12: 72 | M12: 71.95 | N12: 71.35 | O12: 71.35 | P12: 70.45 | Q12: 71.95 | R12: 72 | S12: 71.2 | T12: 71.5 | U12: 63.8 | V12: 72 | W12: 71.5 | X12: 72 | Y12: 72 | Z12: 72 | AA12: 74 | AB12: 72.8 | AC12: 50 | AD12: 1 | AE12: 14.15 | AF12: 1708.1
B13: ATRIA ENERGIA S.A.C. | C13: C.H. PURMACANA | D13: CENTRAL | E13: HIDROELÉCTRICA | F13: 1.95 | G13: 1.2 | H13: 1.9 | I13: 2.5 | J13: 1.7 | Y13: 4.1 | Z13: 1.75 | AD13: 2.35 | AE13: 5.2 | AF13: 22.65
B14: BIOENERGIA DEL CHIRA S.A. | C14: C.T. CAÑA BRAVA | D14: CENTRAL | E14: TERMOELÉCTRICA | AF14: 0
B15: CELEPSA | C15: C.H. EL PLATANAL | D15: CENTRAL | E15: HIDROELÉCTRICA | F15: 5347.15 | G15: 5339.95 | H15: 1378.3 | I15: 5218.2 | J15: 5088.55 | K15: 4928.1 | L15: 4820.1 | M15: 4611.65 | N15: 4963.3 | O15: 5002.8 | P15: 5166.75 | Q15: 5150.4 | R15: 4786.25 | S15: 4891.35 | T15: 4742.75 | U15: 4977.4 | V15: 5033 | W15: 4936.15 | X15: 5341.55 | Y15: 5423.95 | Z15: 4666.15 | AA15: 4993.45 | AB15: 5102.45 | AC15: 5358.55 | AD15: 3079.85 | AE15: 4968.3 | AF15: 125316.4
B16: CELEPSA RENOVABLES S.R.L. | C16: C.H. MARAÑON | D16: CENTRAL | E16: HIDROELÉCTRICA | F16: 473.53848 | G16: 472.8 | H16: 470.1 | I16: 472.4 | J16: 472.8 | K16: 472.8 | L16: 472.8 | M16: 472.8 | N16: 472.8 | O16: 472.8 | P16: 465.3 | Q16: 466.9 | R16: 472.8 | S16: 472.8 | T16: 472.8 | U16: 472.8 | V16: 472.8 | W16: 472.8 | X16: 472.8 | Y16: 472.8 | Z16: 472.8 | AA16: 472.8 | AB16: 472.8 | AC16: 472.95 | AD16: 468.955 | AE16: 464.65 | AF16: 12265.193
B17: CENTRALES SANTA ROSA S.A.C. | C17: C.H. SANTA ROSA I | D17: CENTRAL | E17: HIDROELÉCTRICA | AF17: 0
B18: CENTRALES SANTA ROSA S.A.C. | C18: C.H. SANTA ROSA II | D18: CENTRAL | E18: HIDROELÉCTRICA | AF18: 0
B19: CHINANGO S.A.C. | C19: C.H. CHIMAY | D19: CENTRAL | E19: HIDROELÉCTRICA | F19: 3355.35 | G19: 3375.8 | H19: 3482.65 | I19: 3415.15 | J19: 3427.9 | K19: 3416.3 | L19: 3380.6 | M19: 3331.3 | N19: 3419.15 | O19: 3435.35 | P19: 3466.6 | Q19: 3463.25 | R19: 3144.9 | S19: 3401.05 | T19: 3363.95 | U19: 3386.15 | V19: 3547.25 | W19: 3479.4 | X19: 3473.7 | Y19: 3416.8 | Z19: 3490.05 | AA19: 3392 | AB19: 3368.75 | AC19: 3486.55 | AD19: 3386.95 | AE19: 3353.1 | AF19: 88660
B20: CHINANGO S.A.C. | C20: C.H. YANANGO | D20: CENTRAL | E20: HIDROELÉCTRICA | F20: 1016.7 | G20: 1013.95 | H20: 1013.6 | I20: 1009.2 | J20: 186.5 | K20: 678.65 | L20: 1017.15 | M20: 1016.6 | N20: 1016.6 | O20: 1016.3 | P20: 1016.3 | Q20: 1011.55 | R20: 1015.5 | S20: 1014.75 | T20: 1013.45 | U20: 1014 | V20: 1013.9 | W20: 1013.6 | X20: 1012.25 | Y20: 1012.1 | Z20: 1011.95 | AA20: 1011.55 | AB20: 1011.25 | AC20: 886.75 | AD20: 1017.65 | AE20: 1016.5 | AF20: 25078.3
B21: COLCA SOLAR S.A.C. | C21: C.S. YARUCAYA | D21: CENTRAL | E21: SOLAR | F21: 5.2 | G21: 4.6 | H21: 5.55 | I21: 7.85 | J21: 5.6 | K21: 6.8 | L21: 8.05 | M21: 6.95 | N21: 7.3 | O21: 8.2 | P21: 9.05 | Q21: 9.2 | R21: 8.8 | S21: 8.7 | T21: 8.75 | U21: 9.05 | V21: 6.15 | W21: 8.4 | X21: 7.05 | Y21: 5.3 | Z21: 7 | AA21: 9.05 | AB21: 8.9 | AC21: 6.95 | AD21: 8.6 | AE21: 9.25 | AF21: 196.3
B22: EGASA | C22: C.H. CHARCANI III | D22: CENTRAL | E22: HIDROELÉCTRICA | F22: 156 | G22: 157.75 | H22: 158.4 | I22: 158.6 | J22: 157.05 | K22: 159.75 | L22: 158.4 | M22: 156.4 | N22: 154.5 | O22: 108.7 | P22: 154.85 | Q22: 151.3 | R22: 99.8 | S22: 143.55 | T22: 145.25 | U22: 158.9 | V22: 160.15 | W22: 158.7 | X22: 159.15 | Y22: 161.4 | Z22: 158.35 | AA22: 160.6 | AB22: 159.215 | AC22: 160.8 | AD22: 159.28 | AE22: 160.5 | AF22: 3977.345
B23: EGASA | C23: C.H. CHARCANI IV | D23: CENTRAL | E23: HIDROELÉCTRICA | F23: 242.5 | G23: 242.5 | H23: 242.45 | I23: 242.85 | J23: 242.9 | K23: 243.1 | L23: 242.5 | M23: 242.9 | N23: 242.45 | O23: 242.85 | P23: 242.485 | Q23: 243.15 | R23: 161.45 | S23: 170.2 | T23: 240.2 | U23: 243.6 | V23: 244.75 | W23: 244.75 | X23: 244.7 | Y23: 244.6 | Z23: 244.55 | AA23: 244.35 | AB23: 242.6 | AC23: 242.25 | AD23: 242.235 | AE23: 242.55 | AF23: 6165.42
B24: EGASA | C24: C.H. CHARCANI V | D24: CENTRAL | E24: HIDROELÉCTRICA | F24: 3149.6 | G24: 3430.2 | H24: 3438.15 | I24: 3168.35 | J24: 3422.5 | K24: 3434.9 | L24: 3434.9 | M24: 3050 | N24: 3197.05 | O24: 3439.3 | P24: 3441.475 | Q24: 3439.2 | R24: 3433.8 | S24: 3439 | T24: 3435.2 | U24: 3435.1 | V24: 3434.5 | W24: 3430.95 | X24: 3441.1 | Y24: 3436.45 | Z24: 2856.75 | AA24: 2156.8 | AB24: 2152.615 | AC24: 2154.3 | AD24: 2148.47 | AE24: 2149.6 | AF24: 81150.26
B25: EGASA | C25: C.H. CHARCANI VI | D25: CENTRAL | E25: HIDROELÉCTRICA | F25: 210.05 | G25: 214.55 | H25: 215.4 | I25: 211.45 | J25: 214.7 | K25: 214.85 | L25: 215.25 | M25: 215.6 | N25: 215.15 | O25: 215.8 | P25: 209.39 | Q25: 208 | R25: 199.45 | S25: 196.1 | T25: 139.45 | U25: 180.9 | V25: 181.9 | W25: 182.45 | X25: 182.8 | Y25: 182.95 | Z25: 166.6 | AA25: 141.6 | AB25: 141.095 | AC25: 144.65 | AD25: 150.605 | AE25: 149.9 | AF25: 4900.64
B26: EGASA | C26: C.T. CHILINA DIESEL | D26: CENTRAL | E26: TERMOELÉCTRICA | F26: 9 | P26: 10.8 | AB26: 13.05 | AF26: 32.85
B27: EGASA | C27: C.T. CHILINA DIESEL | D27: TG | E27: TERMOELÉCTRICA | AF27: 0
B28: EGASA | C28: C.T. MOLLENDO DIESEL | D28: CENTRAL | E28: TERMOELÉCTRICA | AF28: 0
B29: EGEJUNIN | C29: C.H. HUASAHUASI I | D29: CENTRAL | E29: HIDROELÉCTRICA | F29: 475.4 | G29: 476.1 | H29: 475.8 | I29: 474.55 | J29: 471.75 | K29: 475.3 | L29: 474.1 | M29: 449.65 | N29: 407.15 | O29: 380.25 | P29: 370.65 | Q29: 360.15 | R29: 413.7 | S29: 437.15 | T29: 424.8 | U29: 475.3 | V29: 475.2 | W29: 475.45 | X29: 475.2 | Y29: 475.25 | Z29: 475.35 | AA29: 475.3 | AB29: 475.45 | AC29: 475.25 | AD29: 475.2 | AE29: 471.85 | AF29: 11791.3
B30: EGEJUNIN | C30: C.H. RUNATULLO II | D30: CENTRAL | E30: HIDROELÉCTRICA | F30: 483.85 | G30: 481.95 | H30: 482.9 | I30: 482.15 | J30: 473.65 | K30: 479.9 | L30: 480.75 | M30: 482.15 | N30: 484.4 | O30: 484.55 | P30: 484.7 | Q30: 483.5 | R30: 483.15 | S30: 483.95 | T30: 482.5 | U30: 483.5 | V30: 482.9 | W30: 478.55 | X30: 464.55 | Y30: 458.35 | Z30: 471.75 | AA30: 437 | AB30: 409.75 | AC30: 381.25 | AD30: 386.4 | AE30: 389.4 | AF30: 12077.45
B31: EGEJUNIN | C31: C.H. RUNATULLO III | D31: CENTRAL | E31: HIDROELÉCTRICA | F31: 486.55 | G31: 486.55 | H31: 486.6 | I31: 486.45 | J31: 486.4 | K31: 486.85 | L31: 486.85 | M31: 486.6 | N31: 486.6 | O31: 486.45 | P31: 486.6 | Q31: 486.45 | R31: 486.45 | S31: 486.5 | T31: 486.2 | U31: 486.45 | V31: 486.2 | W31: 485.65 | X31: 486.15 | Y31: 485.8 | Z31: 485.8 | AA31: 486.5 | AB31: 486.15 | AC31: 486.15 | AD31: 486.05 | AE31: 485.9 | AF31: 12644.9
B32: EGEJUNIN | C32: C.H. SANTA CRUZ I | D32: CENTRAL | E32: HIDROELÉCTRICA | F32: 235.65 | G32: 235.2 | H32: 237.35 | I32: 229.55 | J32: 235.75 | K32: 235.05 | L32: 234.25 | M32: 234.05 | N32: 234.05 | O32: 233.55 | P32: 233.15 | Q32: 232.7 | R32: 232.45 | S32: 232.4 | T32: 231.15 | U32: 229.3 | V32: 232.85 | W32: 223.4 | X32: 230.2 | Y32: 216.65 | Z32: 231.5 | AA32: 225.25 | AB32: 227.3 | AC32: 229.45 | AD32: 231.45 | AE32: 232.85 | AF32: 6016.5
B33: EGEMSA | C33: C.H. MACHUPICCHU | D33: CENTRAL | E33: HIDROELÉCTRICA | F33: 3962.35 | G33: 3952.55 | H33: 3937.9 | I33: 3946.1 | J33: 3906.6 | K33: 3890.85 | L33: 3968.85 | M33: 3960.7 | N33: 3928.15 | O33: 3971.1 | P33: 3962.75 | Q33: 3932.8 | R33: 3167.45 | S33: 3998.25 | T33: 3972.2 | U33: 3950.05 | V33: 3954.3 | W33: 3959.45 | X33: 3959.1 | Y33: 3952.9 | Z33: 3970.25 | AA33: 3955.4 | AB33: 3968.95 | AC33: 3952.85 | AD33: 3970.45 | AE33: 3945.35 | AF33: 101997.65
B34: EGESUR | C34: C.H. ARICOTA I | D34: CENTRAL | E34: HIDROELÉCTRICA | F34: 178.75 | G34: 179.35 | H34: 180.65 | I34: 180.3 | J34: 177.6 | K34: 180.65 | L34: 180.45 | M34: 178.55 | N34: 181.05 | O34: 179.25 | P34: 180.5 | Q34: 181 | R34: 180.2 | S34: 181.6 | T34: 178.5 | U34: 180 | V34: 179.5 | W34: 181 | X34: 178.1 | Y34: 174.75 | Z34: 176.5 | AA34: 177.6 | AB34: 177.3 | AC34: 175.2 | AD34: 177.05 | AE34: 175.85 | AF34: 4651.25
B35: EGESUR | C35: C.H. ARICOTA II | D35: CENTRAL | E35: HIDROELÉCTRICA | F35: 78.25 | G35: 79.15 | H35: 78.25 | I35: 80.4 | J35: 79.6 | K35: 79.7 | L35: 79.65 | M35: 78.5 | N35: 78.7 | O35: 78.9 | P35: 81.05 | Q35: 80.8 | R35: 81.6 | S35: 84.9 | T35: 82.25 | U35: 82.7 | V35: 80.6 | W35: 80 | X35: 82.4 | Y35: 81 | Z35: 81.45 | AA35: 83.4 | AB35: 83.7 | AC35: 84.5 | AD35: 85.4 | AE35: 85.5 | AF35: 2112.35
B36: EGESUR | C36: C.T. INDEPENDENCIA | D36: CENTRAL | E36: TERMOELÉCTRICA | F36: 6.95 | G36: 31.25 | H36: 237 | I36: 126.85 | J36: 55.15 | K36: 46.35 | N36: 131.95 | O36: 74.3 | P36: 183.15 | Q36: 37.6 | R36: 80.55 | S36: 40.85 | U36: 55.2 | V36: 110.6 | W36: 101.4 | X36: 99.3 | Y36: 333.45 | Z36: 118.45 | AB36: 2.55 | AF36: 1872.9
B37: ELECTRICA YANAPAMPA SAC | C37: C.H. YANAPAMPA | D37: CENTRAL | E37: HIDROELÉCTRICA | F37: 74.5 | G37: 69.1 | H37: 73.75 | I37: 67.1 | J37: 72.45 | K37: 70.3 | L37: 73.4 | M37: 73.4 | N37: 65.8 | O37: 66.2 | P37: 60.3 | Q37: 17.65 | R37: 37.85 | S37: 71.7 | T37: 71.3 | U37: 74.8 | V37: 73.55 | W37: 77.2 | X37: 77 | Y37: 76.3 | Z37: 76.3 | AA37: 75.5 | AB37: 73.85 | AC37: 76.25 | AD37: 73.8 | AE37: 56.9 | AF37: 1776.25
B38: ELECTROPERU | C38: C.H. MANTARO | D38: CENTRAL | E38: HIDROELÉCTRICA | F38: 15574.5 | G38: 15381 | H38: 15127.05 | I38: 14878.9 | J38: 15509.65 | K38: 14698.4 | L38: 14679.5 | M38: 14286.7 | N38: 14716.15 | O38: 15539.05 | P38: 15554.9 | Q38: 15541 | R38: 14942.7 | S38: 15295.05 | T38: 13798.95 | U38: 15072.05 | V38: 15261.5 | W38: 15388.05 | X38: 15556.25 | Y38: 15524.85 | Z38: 15534.35 | AA38: 15029.5 | AB38: 15535.9 | AC38: 15531.965 | AD38: 15539.65 | AE38: 15458.05 | AF38: 394955.61
B39: ELECTROPERU | C39: C.H. RESTITUCION | D39: CENTRAL | E39: HIDROELÉCTRICA | F39: 4479.45 | G39: 4692.25 | H39: 4788.4 | I39: 4812.75 | J39: 3560 | K39: 3195.95 | L39: 3320.5 | M39: 3487.05 | N39: 4891.8 | O39: 5178 | P39: 5187.05 | Q39: 5179.9 | R39: 4364.85 | S39: 5083.05 | T39: 4574.55 | U39: 5038 | V39: 5100.15 | W39: 5134.15 | X39: 5157.7 | Y39: 4473.9 | Z39: 5156.8 | AA39: 5001.4 | AB39: 5157.25 | AC39: 5149.545 | AD39: 5154.1 | AE39: 5129.95 | AF39: 122448.49
B40: ELECTROPERU | C40: C.T. TUMBES | D40: MAK1 | E40: TERMOELÉCTRICA | Y40: 41.95 | AF40: 41.95
B41: ELECTROPERU | C41: C.T. TUMBES | D41: MAK2 | E41: TERMOELÉCTRICA | Y41: 43.95 | AF41: 43.95
B42: EMPRESA DE GENERACION ELECTRICA CANCHAYLLO SAC | C42: C.H. CANCHAYLLO | D42: CENTRAL | E42: HIDROELÉCTRICA | F42: 120.25 | G42: 96.8 | H42: 112.6 | I42: 117.35 | J42: 121 | K42: 120.05 | L42: 117.95 | M42: 116.65 | N42: 114.2 | O42: 110.8 | P42: 100.55 | Q42: 97.5 | R42: 98.3 | S42: 100.6 | T42: 95.6 | U42: 98.95 | V42: 120.2 | W42: 118.95 | X42: 113.45 | Y42: 115.75 | Z42: 119.25 | AA42: 118 | AB42: 115.75 | AC42: 114.35 | AD42: 114.8 | AE42: 98.4 | AF42: 2888.05
B43: EMPRESA DE GENERACION ELECTRICA RIO BAÑOS S.A.C. | C43: C.H. RUCUY | D43: CENTRAL | E43: HIDROELÉCTRICA | F43: 478.8 | G43: 360.9 | H43: 393 | I43: 246.75 | J43: 478.65 | K43: 478.7 | L43: 478 | M43: 478.8 | N43: 478.95 | O43: 479.65 | P43: 479.55 | Q43: 479.65 | R43: 479.55 | S43: 479.15 | T43: 478.85 | U43: 479.1 | V43: 479.1 | W43: 479.15 | X43: 479.7 | Y43: 479.8 | Z43: 478.85 | AA43: 478.45 | AB43: 479.05 | AC43: 479.25 | AD43: 479.35 | AE43: 478.65 | AF43: 12019.4
B44: EMPRESA DE GENERACION ELECTRICA SANTA ANA S.A.C. | C44: C.H. RENOVANDES H1 | D44: CENTRAL | E44: HIDROELÉCTRICA | F44: 487.75 | G44: 487.05 | H44: 487.75 | I44: 486.95 | J44: 417.7 | K44: 487.15 | L44: 486.95 | M44: 485.1 | N44: 485.4 | O44: 484.95 | P44: 485.6 | Q44: 485.5 | R44: 484.8 | S44: 485.85 | T44: 482.55 | U44: 484.35 | V44: 484.45 | W44: 484.15 | X44: 486.45 | Y44: 447.15 | Z44: 487 | AA44: 486.85 | AB44: 486.15 | AC44: 485.35 | AD44: 486.85 | AE44: 121.35 | AF44: 12161.15
B45: EMPRESA DE GENERACION HUALLAGA | C45: C.H. CHAGLLA | D45: CENTRAL | E45: HIDROELÉCTRICA | F45: 10661.95 | G45: 10629.55 | H45: 10754.5 | I45: 10970.9 | J45: 10660.45 | K45: 9385.5 | L45: 9964.75 | M45: 9993.5 | N45: 9951.85 | O45: 10263.55 | P45: 10272.3 | Q45: 10718.05 | R45: 8555.1 | S45: 9969.1 | T45: 9530.35 | U45: 10263.4 | V45: 9810.65 | W45: 9204.95 | X45: 10209 | Y45: 9341.75 | Z45: 10752.3 | AA45: 10824.75 | AB45: 10467.55 | AC45: 10930.15 | AD45: 10975.4 | AE45: 10595.55 | AF45: 265656.85
B46: EMPRESA DE GENERACION HUALLAGA | C46: P.C.H. CHAGLLA | D46: CENTRAL | E46: HIDROELÉCTRICA | F46: 154.85 | G46: 154.95 | H46: 154.55 | I46: 155.55 | J46: 155.3 | K46: 155.05 | L46: 154.75 | M46: 154.35 | N46: 154.7 | O46: 154.95 | P46: 155.65 | Q46: 155.65 | R46: 155.55 | S46: 155.5 | T46: 155.45 | U46: 155.5 | V46: 154.85 | W46: 155.3 | X46: 155.45 | Y46: 155.6 | Z46: 155.55 | AA46: 155.3 | AB46: 153.7 | AC46: 154 | AD46: 146.95 | AE46: 153.95 | AF46: 4022.95
B47: EMPRESA DE GENERACION HUANZA | C47: C.H. HUANZA | D47: CENTRAL | E47: HIDROELÉCTRICA | F47: 2125.9 | G47: 2037.7 | H47: 2140 | I47: 2192.2 | J47: 2288.2 | K47: 2285.95 | L47: 2192.55 | M47: 2215.3 | N47: 2165.15 | O47: 2118.6 | P47: 2233.4 | Q47: 2191.25 | R47: 1916.75 | S47: 1846.35 | T47: 2141.6 | U47: 1950.45 | V47: 1828.45 | W47: 1992.4 | X47: 2084.85 | Y47: 1988.65 | Z47: 1351.75 | AA47: 822.85 | AB47: 883.8 | AC47: 900.3 | AD47: 1261.05 | AE47: 1476.95 | AF47: 48632.4
B48: EMPRESA ELECTRICA AGUA AZUL | C48: C.H. POTRERO | D48: CENTRAL | E48: HIDROELÉCTRICA | F48: 410.7 | G48: 458.1 | H48: 469.4 | I48: 431.05 | J48: 479.7 | K48: 474.6 | L48: 480 | M48: 480 | N48: 476.75 | O48: 468.45 | P48: 475.1 | Q48: 462.75 | R48: 479.15 | S48: 480 | T48: 439.65 | U48: 419.1 | V48: 479.9 | W48: 479.85 | X48: 479.8 | Y48: 479.95 | Z48: 480 | AA48: 480 | AB48: 480 | AC48: 422.9 | AD48: 462 | AE48: 422.8 | AF48: 12051.7
B49: EMPRESA ELECTRICA RIO DOBLE | C49: C.H. LAS PIZARRAS | D49: CENTRAL | E49: HIDROELÉCTRICA | G49: 198.25 | H49: 391.95 | I49: 457.5 | J49: 456.1 | K49: 455.35 | L49: 454.5 | M49: 453.9 | N49: 423.35 | O49: 424.3 | P49: 453 | Q49: 453.5 | R49: 451.1 | S49: 452 | T49: 441.55 | U49: 455.4 | V49: 455.75 | W49: 455.65 | X49: 455.55 | Y49: 431.15 | Z49: 458.35 | AA49: 458.25 | AB49: 458.4 | AC49: 456.2 | AD49: 405.8 | AE49: 381.6 | AF49: 10838.45
B50: ENEL GENERACION PIURA S.A. | C50: C.T. MALACAS 1 | D50: TG6 | E50: TERMOELÉCTRICA | F50: 1019 | G50: 814.1 | H50: 813.8 | I50: 823.7 | J50: 747.2 | K50: 34.7 | L50: 649.9 | M50: 669.5 | N50: 694.8 | O50: 767.6 | P50: 807.35 | Q50: 810.15 | R50: 570.2 | S50: 659.65 | U50: 737.4 | V50: 376.65 | W50: 682.05 | X50: 682.7 | Y50: 1106.2 | Z50: 1107.45 | AA50: 968.4 | AB50: 722.45 | AC50: 717.9 | AD50: 378.85 | AE50: 140.15 | AF50: 17501.85
B51: ENEL GENERACION PIURA S.A. | C51: C.T. MALACAS 2 | D51: TG4 | E51: TERMOELÉCTRICA | AF51: 0
B52: ENEL GENERACION PIURA S.A. | C52: C.T. RF DE GENERACION TALARA | D52: TG5 | E52: TERMOELÉCTRICA | AF52: 0
B53: ENERGÍA EÓLICA S.A. | C53: C.E. CUPISNIQUE | D53: CENTRAL | E53: EÓLICA | F53: 1063.95 | G53: 1005.35 | H53: 861.2 | I53: 769 | J53: 801.95 | K53: 1122.55 | L53: 1183.5 | M53: 976.95 | N53: 796.15 | O53: 976.8 | P53: 851.5 | Q53: 957.4 | R53: 1196.5 | S53: 1444.65 | T53: 1784.75 | U53: 1304.25 | V53: 1235.05 | W53: 1101.05 | X53: 957 | Y53: 843.9 | Z53: 1077.45 | AA53: 1254.4 | AB53: 1302.55 | AC53: 1106.7 | AD53: 1362.6 | AE53: 1411.55 | AF53: 28748.7
B54: ENERGÍA EÓLICA S.A. | C54: C.E. TALARA | D54: CENTRAL | E54: EÓLICA | F54: 108.95 | G54: 206.5 | H54: 105.4 | I54: 241.5 | J54: 166.2 | K54: 297.3 | L54: 419.35 | M54: 198.75 | N54: 317.55 | O54: 370.55 | P54: 133.7 | Q54: 286.65 | R54: 507.5 | S54: 504.2 | T54: 700.3 | U54: 654.4 | V54: 314.05 | W54: 424.05 | X54: 398 | Y54: 381.45 | Z54: 437.5 | AA54: 562.45 | AB54: 366.65 | AC54: 436.85 | AD54: 445.2 | AE54: 358.4 | AF54: 9343.4
B55: ENERGIA RENOVABLE DEL SUR S.A. | C55: C.E. SAN JUAN | D55: CENTRAL | E55: EÓLICA | F55: 2690.05 | G55: 2781.75 | H55: 2483.9 | I55: 1829.25 | J55: 1028.15 | K55: 2249 | L55: 2083.9 | M55: 2008.95 | N55: 1750.95 | O55: 1563.5 | P55: 1767.4 | Q55: 2368.65 | R55: 2339.75 | S55: 2693.7 | T55: 2380.05 | U55: 2190.95 | V55: 2040.8 | W55: 2440.75 | X55: 2477.5 | Y55: 1356.8 | Z55: 1699.75 | AA55: 2367.55 | AB55: 2420.6 | AC55: 1863.25 | AD55: 2339.3 | AE55: 2633.2 | AF55: 55849.4
B56: ENGIE | C56: C.E. PUNTA LOMITAS | D56: PL-BL1 | E56: EÓLICA | F56: 1634.25 | G56: 1352.8 | H56: 1500.95 | I56: 1406.8 | J56: 1156 | K56: 1529.45 | L56: 1744.1 | M56: 1646.8 | N56: 1026.85 | O56: 1293.6 | P56: 1009.05 | Q56: 1090.65 | R56: 1872.95 | S56: 1819.65 | T56: 1991.35 | U56: 1751.1 | V56: 1249.05 | W56: 732.25 | X56: 955.65 | Y56: 642.05 | Z56: 654.95 | AA56: 1747.4 | AB56: 1571 | AC56: 1256.55 | AD56: 1202.5 | AE56: 1727.95 | AF56: 35565.7
B57: ENGIE | C57: C.E. PUNTA LOMITAS | D57: PL-BL2 | E57: EÓLICA | F57: 2042.2 | G57: 1773.95 | H57: 1973.35 | I57: 1691.25 | J57: 1734.7 | K57: 1740.05 | L57: 1825.15 | M57: 2006.15 | N57: 1441.65 | O57: 1662.3 | P57: 1504.35 | Q57: 1551 | R57: 2156.05 | S57: 1975.45 | T57: 2121.1 | U57: 1929 | V57: 1631.65 | W57: 1132.15 | X57: 1313.95 | Y57: 1048.35 | Z57: 957.25 | AA57: 1985.75 | AB57: 1926.05 | AC57: 1659.55 | AD57: 1716.15 | AE57: 1984.4 | AF57: 44482.95
B58: ENGIE | C58: C.E. PUNTA LOMITAS_EXP | D58: PUN LOM_EXP-BL1 | E58: EÓLICA | F58: 274.2 | G58: 191.35 | H58: 214.25 | I58: 233.5 | J58: 115.7 | K58: 171.2 | L58: 249.45 | M58: 277.2 | N58: 138.35 | O58: 196.45 | P58: 106.75 | Q58: 116.05 | R58: 259.8 | S58: 276.85 | T58: 340.9 | U58: 274.45 | V58: 193.8 | W58: 91.4 | X58: 137.75 | Y58: 84.1 | Z58: 87.6 | AA58: 244.55 | AB58: 176.75 | AC58: 158.3 | AD58: 138.15 | AE58: 211.35 | AF58: 4960.2
B59: ENGIE | C59: C.E. PUNTA LOMITAS_EXP | D59: PUN LOM_EXP-BL2 | E59: EÓLICA | F59: 142.75 | G59: 106.7 | H59: 127.9 | I59: 155 | J59: 130.95 | K59: 165.8 | L59: 211.9 | M59: 164.1 | N59: 92.7 | O59: 140.3 | P59: 76.7 | Q59: 79.15 | R59: 169.9 | S59: 198.15 | T59: 253.75 | U59: 212.25 | V59: 111.1 | W59: 36.1 | X59: 40.9 | Y59: 40.2 | Z59: 25.2 | AA59: 136.55 | AB59: 125.75 | AC59: 90.45 | AD59: 78.9 | AE59: 128.5 | AF59: 3241.65
B60: ENGIE | C60: C.H. QUITARACSA | D60: CENTRAL | E60: HIDROELÉCTRICA | AF60: 0
B61: ENGIE | C61: C.H. YUNCAN | D61: CENTRAL | E61: HIDROELÉCTRICA | F61: 2071.75 | G61: 2068.6 | H61: 2071.6 | I61: 2070.9 | J61: 2071.95 | K61: 2071.7 | L61: 2073.7 | M61: 2070.35 | N61: 2074.6 | O61: 1983.2 | P61: 2074 | Q61: 2072.15 | R61: 2067.9 | S61: 1979.45 | T61: 2052.2 | U61: 2080.5 | V61: 2077.1 | W61: 2070.45 | X61: 2074.85 | Y61: 2066.75 | Z61: 2071.9 | AA61: 2071.25 | AB61: 2074.3 | AC61: 2072.15 | AD61: 2071.8 | AE61: 2070.55 | AF61: 53675.65
B62: ENGIE | C62: C.S. INTIPAMPA | D62: CENTRAL | E62: SOLAR | F62: 277.95 | G62: 208.65 | H62: 294.3 | I62: 307.75 | J62: 328.15 | K62: 296.25 | L62: 328 | M62: 325.65 | N62: 328.5 | O62: 320.9 | P62: 317.25 | Q62: 327.45 | R62: 325.95 | S62: 326.2 | T62: 320.3 | U62: 322.8 | V62: 321.4 | W62: 312.75 | X62: 248.95 | Y62: 259.05 | Z62: 81.05 | AA62: 303.9 | AB62: 309.05 | AC62: 306 | AD62: 286.15 | AE62: 298.7 | AF62: 7683.05
B63: ENGIE | C63: C.T. CHILCA 1 | D63: TG1 | E63: TERMOELÉCTRICA | F63: 3436.15 | G63: 3474.7 | H63: 3658.45 | I63: 3920.3 | J63: 3531.45 | K63: 2517.7 | L63: 3192.3 | M63: 3117.85 | N63: 230 | O63: 2589.95 | P63: 3535.7 | Q63: 3838.55 | R63: 3855.9 | S63: 3834.55 | T63: 3864.55 | U63: 3856.45 | V63: 2060.5 | W63: 662.35 | X63: 1030.5 | Y63: 2102.65 | Z63: 3981.4 | AA63: 3586.1 | AB63: 2993.65 | AC63: 3290 | AD63: 4098.6 | AE63: 2728.85 | AF63: 78989.15
B64: ENGIE | C64: C.T. CHILCA 1 | D64: TG2 | E64: TERMOELÉCTRICA | AE64: 625.15 | AF64: 625.15
B65: ENGIE | C65: C.T. CHILCA 1 | D65: TG3 | E65: TERMOELÉCTRICA | F65: 3042.95 | G65: 3618.95 | H65: 4172 | I65: 4513.65 | J65: 3512.8 | K65: 2669.6 | L65: 3571.05 | M65: 3665.75 | N65: 4027.9 | O65: 4129.05 | P65: 4037.75 | Q65: 249.65 | R65: 760.45 | S65: 159.55 | U65: 493.5 | V65: 399.15 | Z65: 3554.8 | AA65: 4035 | AB65: 3207.6 | AC65: 3585.9 | AD65: 4726.4 | AE65: 2885.05 | AF65: 65018.5
B66: ENGIE | C66: C.T. CHILCA 1 | D66: TV | E66: TERMOELÉCTRICA | F66: 3048.95 | G66: 3682.95 | H66: 3961.4 | I66: 4167.25 | J66: 3614.7 | K66: 3011.9 | L66: 3559.1 | M66: 3503.35 | N66: 1841.3 | O66: 3226.15 | P66: 3748.15 | Q66: 1652.25 | R66: 1659.95 | S66: 1642.55 | T66: 1656.85 | U66: 1654.5 | V66: 639.45 | Y66: 722.95 | Z66: 3570.5 | AA66: 3889.4 | AB66: 3376.1 | AC66: 3623.4 | AD66: 4362.15 | AE66: 3195.25 | AF66: 69010.5
B67: ENGIE | C67: C.T. CHILCA 2 | D67: TG41 | E67: TERMOELÉCTRICA | I67: 273.8 | N67: 168.7 | P67: 457.9 | Q67: 482.85 | U67: 181.25 | V67: 236.2 | W67: 235.55 | X67: 238.25 | Y67: 352.95 | Z67: 421.5 | AC67: 284.75 | AF67: 3333.7
B68: ENGIE | C68: C.T. CHILCA 2 | D68: TV42 | E68: TERMOELÉCTRICA | AF68: 0
B69: ENGIE | C69: C.T. NEPI | D69: TG41 | E69: TERMOELÉCTRICA | AF69: 0
B70: ENGIE | C70: C.T. NEPI | D70: TG42 | E70: TERMOELÉCTRICA | AF70: 0
B71: ENGIE | C71: C.T. NEPI | D71: TG43 | E71: TERMOELÉCTRICA | AF71: 0
B72: ENGIE | C72: C.T. RF PLANTA ILO | D72: TG1 | E72: TERMOELÉCTRICA | J72: 216.2 | V72: 1208.35 | W72: 442.6 | AF72: 1867.15
B73: ENGIE | C73: C.T. RF PLANTA ILO | D73: TG2 | E73: TERMOELÉCTRICA | V73: 1109.7 | X73: 496.8 | AF73: 1606.5
B74: ENGIE | C74: C.T. RF PLANTA ILO | D74: TG3 | E74: TERMOELÉCTRICA | V74: 1037.15 | X74: 515 | AF74: 1552.15
B75: FENIX POWER PERÚ | C75: C.T. FENIX | D75: GT11 | E75: TERMOELÉCTRICA | F75: 3186.75 | G75: 3118.65 | AA75: 1681.25 | AE75: 2751.6 | AF75: 10738.25
B76: FENIX POWER PERÚ | C76: C.T. FENIX | D76: GT12 | E76: TERMOELÉCTRICA | F76: 3191.9 | G76: 3310.45 | H76: 3701 | Z76: 2807.25 | AA76: 164.85 | AF76: 13175.45
B77: FENIX POWER PERÚ | C77: C.T. FENIX | D77: TV10 | E77: TERMOELÉCTRICA | F77: 3798.4 | G77: 3735.75 | H77: 1934.9 | AE77: 1267.15 | AF77: 10736.2
B78: GENERACIÓN ANDINA S.A.C. | C78: C.H. 8 DE AGOSTO | D78: CENTRAL | E78: HIDROELÉCTRICA | F78: 503.5 | G78: 502.5 | H78: 503.8 | I78: 465.4 | J78: 504 | K78: 504 | L78: 504 | M78: 504 | N78: 504 | O78: 503.25 | P78: 471.5 | Q78: 501.65 | R78: 501.7 | S78: 453.5 | T78: 497.25 | U78: 482.3 | V78: 499.3 | W78: 502.4 | X78: 502.1 | Y78: 475.95 | Z78: 293.1 | AA78: 504 | AB78: 503.2 | AC78: 502.05 | AD78: 464.2 | AE78: 501.6 | AF78: 12654.25
B79: GENERACIÓN ANDINA S.A.C. | C79: C.H. EL CARMEN | D79: CENTRAL | E79: HIDROELÉCTRICA | F79: 200.85 | G79: 201.6 | H79: 201.45 | I79: 194.05 | J79: 201.35 | K79: 193.85 | L79: 182.4 | M79: 170.5 | N79: 166.9 | O79: 164.8 | P79: 179.6 | Q79: 176.6 | R79: 198 | S79: 189.65 | T79: 184.95 | U79: 172.9 | V79: 180.4 | W79: 171 | X79: 168.3 | Y79: 195.4 | Z79: 179.15 | AA79: 187.35 | AB79: 171.25 | AC79: 162.4 | AD79: 181.7 | AE79: 179.3 | AF79: 4755.7
B80: GENERADORA DE ENERGÍA DEL PERÚ | C80: C.H. ÁNGEL I | D80: CENTRAL | E80: HIDROELÉCTRICA | F80: 489.6 | G80: 489.6 | H80: 489.6 | I80: 489.6 | J80: 489.6 | K80: 489.6 | L80: 489.6 | M80: 489.6 | N80: 489.6 | O80: 489.6 | P80: 489.6 | Q80: 450.55 | R80: 489.6 | S80: 489.6 | T80: 489.6 | U80: 489.6 | V80: 489.6 | W80: 489.6 | X80: 489.6 | Y80: 489.6 | Z80: 489.6 | AA80: 489.6 | AB80: 489.6 | AC80: 489.6 | AD80: 489.6 | AE80: 489.6 | AF80: 12690.55
B81: GENERADORA DE ENERGÍA DEL PERÚ | C81: C.H. ÁNGEL II | D81: CENTRAL | E81: HIDROELÉCTRICA | F81: 489.6 | G81: 489.6 | H81: 489.6 | I81: 489.6 | J81: 489.6 | K81: 489.6 | L81: 489.6 | M81: 489.6 | N81: 489.6 | O81: 489.6 | P81: 489.6 | Q81: 446.6 | R81: 489.6 | S81: 489.6 | T81: 489.6 | U81: 489.6 | V81: 489.6 | W81: 489.6 | X81: 489.6 | Y81: 489.6 | Z81: 489.6 | AA81: 489.6 | AB81: 489.6 | AC81: 489.6 | AD81: 489.6 | AE81: 489.6 | AF81: 12686.6
B82: GENERADORA DE ENERGÍA DEL PERÚ | C82: C.H. ÁNGEL III | D82: CENTRAL | E82: HIDROELÉCTRICA | F82: 484.8 | G82: 484.8 | H82: 484.8 | I82: 484.8 | J82: 484.8 | K82: 484.8 | L82: 484.8 | M82: 484.8 | N82: 484.8 | O82: 484.8 | P82: 484.8 | Q82: 433.5 | R82: 480 | S82: 480 | T82: 480 | U82: 483 | V82: 484.8 | W82: 484.8 | X82: 484.8 | Y82: 484.8 | Z82: 484.8 | AA82: 484.8 | AB82: 484.8 | AC82: 484.8 | AD82: 484.8 | AE82: 484.8 | AF82: 12537.3
B83: GENERADORA DE ENERGÍA DEL PERÚ | C83: C.H. LA JOYA | D83: CENTRAL | E83: HIDROELÉCTRICA | F83: 184.05 | G83: 162.95 | H83: 194.25 | I83: 201.35 | J83: 218.05 | K83: 126.45 | L83: 225.25 | M83: 205.5 | N83: 185.35 | O83: 198.15 | P83: 187.4 | Q83: 201.45 | R83: 205.9 | S83: 198.85 | T83: 209.5 | U83: 209.15 | V83: 210.25 | W83: 208.05 | X83: 208.95 | Y83: 209.05 | Z83: 199.7 | AA83: 171.5 | AB83: 189.8 | AC83: 201.75 | AD83: 200.3 | AE83: 208.95 | AF83: 5121.9
B84: GM OPERACIONES S.A.C. | C84: CT REFINERIA TALARA | D84: TV1 REF TALARA | E84: TERMOELÉCTRICA | F84: 114.1 | G84: 432.7 | H84: 590.8 | I84: 789.4 | J84: 936.7 | K84: 1033.1 | L84: 1058.9 | M84: 1053.25 | N84: 1042.8 | O84: 1045.35 | P84: 1048.2 | Q84: 1048.875 | R84: 1021.57 | S84: 1013.9 | T84: 971.415 | U84: 1044.35 | V84: 1037.2 | W84: 1006.05 | X84: 1016.05 | Y84: 903.2 | Z84: 1004.6 | AA84: 1020.2 | AB84: 1017.15 | AC84: 934.85 | AD84: 721.55 | AE84: 901.2 | AF84: 23807.46
B85: GM OPERACIONES S.A.C. | C85: CT REFINERIA TALARA | D85: TV2 REF TALARA | E85: TERMOELÉCTRICA | N85: 115.2 | O85: 448.3 | P85: 485.8 | Q85: 592.58 | R85: 745.865 | S85: 582.3 | T85: 619.79 | U85: 711.25 | V85: 720.45 | W85: 412.75 | X85: 22.75 | Y85: 632.25 | Z85: 740.05 | AA85: 758.7 | AB85: 788.9 | AC85: 776.4 | AD85: 409.4 | AF85: 9562.735
B86: GR CORTARRAMA SOCIEDAD ANONIMA CERRADA | C86: C.S. MATARANI | D86: C.S. MATARANI | E86: SOLAR | F86: 618.9 | G86: 610.2 | H86: 579.2 | I86: 677.1 | J86: 676.1 | K86: 10.9 | L86: 671.2 | M86: 679.3 | N86: 692.7 | O86: 701.9 | P86: 607.05 | Q86: 696.05 | R86: 697.4 | S86: 634 | T86: 688.2 | U86: 692.3 | V86: 700.95 | W86: 675.75 | X86: 484.05 | Y86: 508 | Z86: 258.85 | AA86: 575.8 | AB86: 724.3 | AC86: 711 | AD86: 678.5 | AE86: 658.3 | AF86: 15908
B87: GR PAINO SOCIEDAD ANONIMA CERRADA | C87: C.E. HUAMBOS | D87: CENTRAL | E87: EÓLICA | F87: 33.05 | G87: 79.4 | H87: 72.7 | I87: 186.65 | J87: 242.8 | K87: 230.25 | L87: 201.1 | M87: 146 | N87: 192.65 | O87: 36.75 | P87: 17.9 | Q87: 23.05 | R87: 185.15 | S87: 265.2 | T87: 238.15 | U87: 159.75 | V87: 263.6 | W87: 285.3 | X87: 243.7 | Y87: 136.35 | Z87: 79.75 | AA87: 20.25 | AB87: 37.5 | AC87: 100.65 | AD87: 52.4 | AE87: 82.6 | AF87: 3612.65
B88: GR TARUCA SOCIEDAD ANONIMA CERRADA | C88: C.E. DUNA | D88: CENTRAL | E88: EÓLICA | F88: 53.2 | G88: 103.5 | H88: 102 | I88: 241.35 | J88: 307.25 | K88: 285.6 | L88: 264.25 | M88: 198.1 | N88: 201.25 | O88: 40.4 | P88: 23.6 | Q88: 28.5 | R88: 248.5 | S88: 318.95 | T88: 297.6 | U88: 194.65 | V88: 334.7 | W88: 352.4 | X88: 333 | Y88: 204.3 | Z88: 92.4 | AA88: 22.8 | AB88: 40.6 | AC88: 122.25 | AD88: 50.6 | AE88: 62.45 | AF88: 4524.2
B89: HIDROCAÑETE S.A. | C89: C.H. IMPERIAL | D89: CENTRAL | E89: HIDROELÉCTRICA | F89: 84.85 | G89: 85.55 | H89: 86 | I89: 85.1 | J89: 87.1 | K89: 88.45 | L89: 87.1 | M89: 85.75 | N89: 75.9 | O89: 87.45 | P89: 88 | Q89: 86 | R89: 87.75 | S89: 89.35 | T89: 88.7 | U89: 87.2 | V89: 85.3 | W89: 87.1 | X89: 85.55 | Y89: 85.7 | Z89: 84.45 | AA89: 85.95 | AB89: 86.4 | AC89: 84.9 | AD89: 79.45 | AE89: 81.85 | AF89: 2226.9
B90: HIDROELECTRICA HUANCHOR S.A.C. | C90: C.H. HUANCHOR | D90: CENTRAL | E90: HIDROELÉCTRICA | F90: 444.3032 | G90: 440.55 | H90: 442.15 | I90: 398.3 | J90: 437.4 | K90: 445.05 | L90: 443.95 | M90: 444.6 | N90: 444.6 | O90: 445.2 | P90: 444.35 | Q90: 444 | R90: 445.1 | S90: 443.4 | T90: 443.5 | U90: 444.65 | V90: 444 | W90: 444.2 | X90: 446.05 | Y90: 445.78156 | Z90: 445.75 | AA90: 448.05 | AB90: 448.25 | AC90: 448.35 | AD90: 448 | AE90: 425.5 | AF90: 11495.035
B91: HUAURA POWER GROUP S.A. | C91: C.H. YARUCAYA | D91: CENTRAL | E91: HIDROELÉCTRICA | F91: 444.35 | G91: 228.25 | H91: 94.55 | I91: 119.7 | J91: 221.3 | K91: 223.2 | L91: 223.2 | M91: 223.2 | N91: 223.2 | O91: 222.6 | P91: 223.2 | Q91: 223.15 | R91: 223.2 | S91: 223.2 | T91: 222.95 | U91: 223.2 | V91: 223.2 | W91: 223.2 | X91: 223.2 | Y91: 223.2 | Z91: 223.2 | AA91: 222.75 | AB91: 223.2 | AC91: 223.2 | AD91: 223.2 | AE91: 223.2 | AF91: 5794
B92: HYDRO GLOBAL PERÚ S.A.C. | C92: CH SAN GABAN III | D92: CHSAN GABAN III | E92: HIDROELÉCTRICA | V92: 185.935 | W92: 223.256 | X92: 421.894 | Y92: 125.155 | AA92: 679.245 | AB92: 1622.9734 | AC92: 2521.0765 | AD92: 2700.955 | AE92: 1762.195 | AF92: 10242.685
B93: INFRAESTRUCTURAS Y ENERGIAS DEL PERU S.A.C. | C93: C.T. RF PTO MALDONADO | D93: CENTRAL | E93: TERMOELÉCTRICA | K93: 86.8 | L93: 32.15 | AF93: 118.95
B94: INFRAESTRUCTURAS Y ENERGIAS DEL PERU S.A.C. | C94: C.T. RF PUCALLPA | D94: CENTRAL | E94: TERMOELÉCTRICA | K94: 131.5 | O94: 17.65 | AF94: 149.15
B95: INLAND ENERGY SAC | C95: C.H. SANTA TERESA | D95: CENTRAL | E95: HIDROELÉCTRICA | F95: 2165.05 | G95: 2166.25 | H95: 2155.3 | I95: 2162.95 | J95: 2125.4 | K95: 2133.9 | L95: 2177.15 | M95: 2161.6 | N95: 2137.5 | O95: 2157.5 | P95: 2156.65 | Q95: 2138.15 | R95: 1601.725 | S95: 2177.1 | T95: 2172.35 | U95: 2155.15 | V95: 2151.15 | W95: 2172.35 | X95: 2174.15 | Y95: 2158.4 | Z95: 2163.75 | AA95: 2169.55 | AB95: 2159.85 | AC95: 2165.5 | AD95: 2161.15 | AE95: 2150.85 | AF95: 55570.425
B96: INVERSIONES SHAQSHA S.A.C. | C96: C.H. PARIAC | D96: CENTRAL | E96: HIDROELÉCTRICA | F96: 104.7 | G96: 103.2 | H96: 98.15 | I96: 105.6 | J96: 107.85 | K96: 108.45 | L96: 108.85 | M96: 110.4 | N96: 110.4 | O96: 110.1 | P96: 111.6 | Q96: 110.8 | R96: 106.89 | S96: 111.5 | T96: 111.3 | U96: 112.15 | V96: 111.7 | W96: 112.8 | X96: 111.7 | Y96: 112.65 | Z96: 111.55 | AA96: 110.4 | AB96: 110.4 | AC96: 110.3 | AD96: 110.2 | AE96: 110.25 | AF96: 2843.89
B97: JOYA SOLAR S.A.C. | C97: C.S. SAN MARTIN SOLAR | D97: CENTRAL | E97: SOLAR | O97: 27.405 | P97: 447.54 | Q97: 1100.3 | R97: 1063.415 | S97: 1293.545 | T97: 708.18 | U97: 1532.245 | V97: 1946.61 | W97: 1974.185 | X97: 1540.6515 | Y97: 1578.02 | Z97: 903.515 | AA97: 1783.075 | AB97: 2262.605 | AC97: 2244.81 | AD97: 2079.5305 | AE97: 2121.594 | AF97: 24607.226
B98: KALLPA GENERACION S.A. | C98: C.H. CERRO DEL AGUILA | D98: CENTRAL | E98: HIDROELÉCTRICA | F98: 13408.8 | G98: 13394.55 | H98: 11308.8 | I98: 12224.1 | J98: 13304.26 | K98: 13006.1 | L98: 13406.05 | M98: 13384.85 | N98: 13430.55 | O98: 13418.25 | P98: 10633.3 | Q98: 11389.05 | R98: 13350.95 | S98: 13423.9 | T98: 13399.8 | U98: 12845.75 | V98: 12932 | W98: 13361.2 | X98: 13448.8 | Y98: 13449.9 | Z98: 13410.15 | AA98: 13420.95 | AB98: 13398.8 | AC98: 13433.3 | AD98: 13440.85 | AE98: 13351.4 | AF98: 338976.41
B99: KALLPA GENERACION S.A. | C99: C.T. KALLPA | D99: TG1 | E99: TERMOELÉCTRICA | F99: 2961.8 | G99: 3023.25 | H99: 3288.05 | I99: 3169.85 | J99: 2972.61 | K99: 2797.85 | L99: 2792.7 | M99: 2742 | N99: 3021.95 | O99: 2936.8 | P99: 3082.85 | Q99: 2978.55 | R99: 2863 | S99: 2815.15 | T99: 2838.15 | U99: 2953.55 | V99: 2996.2 | W99: 2910 | X99: 3235.75 | Y99: 3178.5 | Z99: 3394.8 | AA99: 2795.45 | AB99: 2858.1 | AC99: 3277.2 | AD99: 3050.95 | AE99: 2753.4 | AF99: 77688.46
B100: KALLPA GENERACION S.A. | C100: C.T. KALLPA | D100: TG2 | E100: TERMOELÉCTRICA | F100: 2959.1 | G100: 3018.55 | H100: 3285.95 | I100: 3170.8 | J100: 2968.27 | K100: 2795.35 | L100: 2779.1 | M100: 2737.2 | N100: 3023.4 | O100: 2931.85 | P100: 3085.45 | Q100: 2977.3 | R100: 2859.75 | S100: 2809.2 | T100: 2832.85 | U100: 2948.9 | V100: 3009.85 | W100: 2900.7 | X100: 3266.45 | Y100: 3204.9 | Z100: 3399.45 | AA100: 2789.75 | AB100: 2854.4 | AC100: 3283.95 | AD100: 3051.75 | AE100: 2770.45 | AF100: 77714.67
B101: KALLPA GENERACION S.A. | C101: C.T. KALLPA | D101: TG3 | E101: TERMOELÉCTRICA | F101: 2957.85 | G101: 3016.15 | H101: 3287.2 | I101: 3171.45 | J101: 2968.445 | K101: 2793.95 | L101: 2779.95 | M101: 2740.55 | N101: 3023.5 | O101: 2933.4 | P101: 3087.65 | Q101: 2972.5 | R101: 1856.6 | S101: 2811.95 | T101: 2833.95 | U101: 2950.95 | V101: 3011.8 | W101: 2906 | X101: 3265.25 | Y101: 3209.8 | Z101: 3402.4 | AA101: 2792.45 | AB101: 2852.65 | AC101: 3286 | AD101: 3053.15 | AE101: 2767.7 | AF101: 76733.245
B102: KALLPA GENERACION S.A. | C102: C.T. KALLPA | D102: TV | E102: TERMOELÉCTRICA | F102: 5369.05 | G102: 5402.15 | H102: 5621.85 | I102: 5538.9 | J102: 5386.72 | K102: 5219.1 | L102: 5197.2 | M102: 5143.1 | N102: 5411.45 | O102: 5344.05 | P102: 5471.15 | Q102: 5370.1 | R102: 4509.55 | S102: 5230 | T102: 5245.4 | U102: 5349.65 | V102: 5375.75 | W102: 5298.6 | X102: 5602.55 | Y102: 5549.4 | Z102: 5761.25 | AA102: 5172.1 | AB102: 5259.35 | AC102: 5618.9 | AD102: 5434.45 | AE102: 5167.3 | AF102: 139049.07
B103: KALLPA GENERACION S.A. | C103: C.T. LAS FLORES | D103: TG1 | E103: TERMOELÉCTRICA | F103: 3812.95 | G103: 3553.5 | H103: 4147.65 | I103: 3984.75 | J103: 3519.735 | K103: 2961.75 | L103: 3331.55 | M103: 3351.35 | N103: 3776.4 | O103: 4115.4 | P103: 4148.8 | Q103: 4721.1 | R103: 3475.15 | S103: 3665.15 | T103: 3772.1 | U103: 4052.2 | V103: 54.95 | Z103: 3795 | AA103: 3933.35 | AB103: 3191 | AC103: 3329.3 | AD103: 4409 | AE103: 3065.45 | AF103: 82167.585
...

Sheet G_AREAS
B3: sábado, 26 de Abril del 2025
B5: HORA | C5: RESUMEN DE GENERACIÓN POR ÁREAS DEL SEIN | D5: RESUMEN DE GENERACIÓN POR ÁREAS DEL SEIN | E5: RESUMEN DE GENERACIÓN POR ÁREAS DEL SEIN | F5: RESUMEN DE GENERACIÓN POR ÁREAS DEL SEIN | G5: RESUMEN DE GENERACIÓN POR ÁREAS DEL SEIN | H5: RESUMEN DE GENERACIÓN POR ÁREAS DEL SEIN | I5: RESUMEN DE GENERACIÓN POR ÁREAS DEL SEIN | J5: RESUMEN DE GENERACIÓN POR ÁREAS DEL SEIN | K5: RESUMEN DE GENERACIÓN POR ÁREAS DEL SEIN | L5: RESUMEN DE GENERACIÓN POR ÁREAS DEL SEIN | M5: RESUMEN DE GENERACIÓN POR ÁREAS DEL SEIN | N5: RESUMEN DE GENERACIÓN POR ÁREAS DEL SEIN | O5: RESUMEN DE GENERACIÓN POR ÁREAS DEL SEIN | P5: RESUMEN DE GENERACIÓN POR ÁREAS DEL SEIN | Q5: RESUMEN DE GENERACIÓN POR ÁREAS DEL SEIN | R5: RESUMEN DE GENERACIÓN POR ÁREAS DEL SEIN | S5: HORA | T5: GENERACIÓN POR TIPO DE GENERACIÓN | U5: GENERACIÓN POR TIPO DE GENERACIÓN | V5: GENERACIÓN POR TIPO DE GENERACIÓN | W5: GENERACIÓN POR TIPO DE GENERACIÓN | X5: GENERACIÓN POR TIPO DE GENERACIÓN | Y5: HORA | Z5: GENERACIÓN POR TIPO DE GENERACIÓN | AA5: GENERACIÓN POR TIPO DE GENERACIÓN | AB5: GENERACIÓN POR TIPO DE GENERACIÓN | AC5: GENERACIÓN POR TIPO DE GENERACIÓN | AD5: GENERACIÓN POR TIPO DE GENERACIÓN
C6: NORTE | D6: NORTE | E6: NORTE | F6: NORTE | G6: CENTRO | H6: CENTRO | I6: CENTRO | J6: CENTRO | K6: SUR | L6: SUR | M6: SUR | N6: SUR | O6: GENERACIÓN INTEGRANTES COES | P6: GENERACIÓN INTEGRANTES COES | Q6: GENERACIÓN INTEGRANTES COES | R6: GENERACIÓN INTEGRANTES COES | T6: INTEGRANTES COES | U6: INTEGRANTES COES | V6: INTEGRANTES COES | W6: INTEGRANTES COES | X6: INTEGRANTES COES | Z6: INTEGRANTES COES RER | AA6: INTEGRANTES COES RER | AB6: INTEGRANTES COES RER | AC6: INTEGRANTES COES RER | AD6: INTEGRANTES COES RER
C7: GENERACIÓN HIDROELÉCTRICA NORTE | D7: GENERACIÓN TERMOELÉCTRICA NORTE | E7: GENERACIÓN SOLAR NORTE | F7: GENERACIÓN EÓLICA NORTE | G7: GENERACIÓN HIDROELÉCTRICA CENTRO | H7: GENERACIÓN TERMOELÉCTRICA CENTRO | I7: GENERACIÓN SOLAR CENTRO | J7: GENERACIÓN EÓLICA CENTRO | K7: GENERACIÓN HIDROELÉCTRICA SUR | L7: GENERACIÓN TERMOELÉCTRICA SUR | M7: GENERACIÓN SOLAR SUR | N7: GENERACIÓN EÓLICA SUR | O7: GENERACIÓN COES NORTE | P7: GENERACIÓN COES CENTRO | Q7: GENERACIÓN COES SUR | R7: TOTAL GENERACION | T7: HIDROELÉCTRICA | U7: TERMOELÉCTRICA | V7: SOLAR | W7: EÓLICA | X7: TOTAL GENERACION | Z7: HIDROELÉCTRICA RER | AA7: TERMOELÉCTRICA RER | AB7: SOLAR RER | AC7: EÓLICA RER | AD7: TOTAL RER
B8: 00:30 | C8: 355.1 | D8: 86 | E8: 0 | F8: 43.6 | G8: 3672.2 | H8: 1428.6 | I8: 0 | J8: 427 | K8: 662.15 | L8: 0 | M8: 0 | N8: 0 | O8: 484.7 | P8: 5527.8 | Q8: 662.15 | R8: 6674.65 | S8: 00:30 | T8: 4689.45 | U8: 1514.6 | V8: 0 | W8: 470.6 | X8: 6674.65 | Y8: 00:30 | Z8: 315.5 | AA8: 23.7 | AB8: 0 | AC8: 470.6 | AD8: 809.8
B9: 01:00 | C9: 403 | D9: 86.7 | E9: 0 | F9: 47.2 | G9: 3580.5 | H9: 1349.8 | I9: 0 | J9: 432.5 | K9: 661.61 | L9: 0 | M9: 0 | N9: 0 | O9: 536.9 | P9: 5362.8 | Q9: 661.61 | R9: 6561.31 | S9: 01:00 | T9: 4645.11 | U9: 1436.5 | V9: 0 | W9: 479.7 | X9: 6561.31 | Y9: 01:00 | Z9: 311.8 | AA9: 23.8 | AB9: 0 | AC9: 479.7 | AD9: 815.3
B10: 01:30 | C10: 417.2 | D10: 71.2 | E10: 0 | F10: 62.5 | G10: 3449.5 | H10: 1359.4 | I10: 0 | J10: 430.7 | K10: 660.24 | L10: 0 | M10: 0 | N10: 0 | O10: 550.9 | P10: 5239.6 | Q10: 660.24 | R10: 6450.74 | S10: 01:30 | T10: 4526.94 | U10: 1430.6 | V10: 0 | W10: 493.2 | X10: 6450.74 | Y10: 01:30 | Z10: 305.2 | AA10: 19.3 | AB10: 0 | AC10: 493.2 | AD10: 817.7
B11: 02:00 | C11: 419.6 | D11: 63.7 | E11: 0 | F11: 52.6 | G11: 3389.3 | H11: 1358.2 | I11: 0 | J11: 433.5 | K11: 663.02 | L11: 0 | M11: 0 | N11: 0 | O11: 535.9 | P11: 5181 | Q11: 663.02 | R11: 6379.92 | S11: 02:00 | T11: 4471.92 | U11: 1421.9 | V11: 0 | W11: 486.1 | X11: 6379.92 | Y11: 02:00 | Z11: 307.6 | AA11: 19.3 | AB11: 0 | AC11: 486.1 | AD11: 813
B12: 02:30 | C12: 422.2 | D12: 63.6 | E12: 0 | F12: 60 | G12: 3296.7 | H12: 1361.5 | I12: 0 | J12: 444.4 | K12: 665.77 | L12: 0 | M12: 0 | N12: 0 | O12: 545.8 | P12: 5102.6 | Q12: 665.77 | R12: 6314.17 | S12: 02:30 | T12: 4384.67 | U12: 1425.1 | V12: 0 | W12: 504.4 | X12: 6314.17 | Y12: 02:30 | Z12: 311.3 | AA12: 19 | AB12: 0 | AC12: 504.4 | AD12: 834.7
B13: 03:00 | C13: 420.9 | D13: 63.9 | E13: 0 | F13: 70.6 | G13: 3352.8 | H13: 1384.7 | I13: 0 | J13: 431.2 | K13: 661.39 | L13: 0 | M13: 0 | N13: 0 | O13: 555.4 | P13: 5168.7 | Q13: 661.39 | R13: 6385.49 | S13: 03:00 | T13: 4435.09 | U13: 1448.6 | V13: 0 | W13: 501.8 | X13: 6385.49 | Y13: 03:00 | Z13: 312.8 | AA13: 19.1 | AB13: 0 | AC13: 501.8 | AD13: 833.7
B14: 03:30 | C14: 421.5 | D14: 63 | E14: 0 | F14: 71.9 | G14: 3353.6 | H14: 1393.2 | I14: 0 | J14: 436.7 | K14: 661.27 | L14: 0 | M14: 0 | N14: 0 | O14: 556.4 | P14: 5183.5 | Q14: 661.27 | R14: 6401.17 | S14: 03:30 | T14: 4436.37 | U14: 1456.2 | V14: 0 | W14: 508.6 | X14: 6401.17 | Y14: 03:30 | Z14: 309.9 | AA14: 19.1 | AB14: 0 | AC14: 508.6 | AD14: 837.6
B15: 04:00 | C15: 426.4 | D15: 63.3 | E15: 0 | F15: 68.2 | G15: 3367.9 | H15: 1379.1 | I15: 0 | J15: 426.8 | K15: 663.49 | L15: 0 | M15: 0 | N15: 0 | O15: 557.9 | P15: 5173.8 | Q15: 663.49 | R15: 6395.19 | S15: 04:00 | T15: 4457.79 | U15: 1442.4 | V15: 0 | W15: 495 | X15: 6395.19 | Y15: 04:00 | Z15: 311.2 | AA15: 19.3 | AB15: 0 | AC15: 495 | AD15: 825.5
B16: 04:30 | C16: 420.4 | D16: 62.9 | E16: 0 | F16: 76.6 | G16: 3340.7 | H16: 1390.2 | I16: 0 | J16: 396.3 | K16: 645.83 | L16: 0 | M16: 0 | N16: 0 | O16: 559.9 | P16: 5127.2 | Q16: 645.83 | R16: 6332.93 | S16: 04:30 | T16: 4406.93 | U16: 1453.1 | V16: 0 | W16: 472.9 | X16: 6332.93 | Y16: 04:30 | Z16: 310.6 | AA16: 19.3 | AB16: 0 | AC16: 472.9 | AD16: 802.8
B17: 05:00 | C17: 425.8 | D17: 36.9 | E17: 0 | F17: 88.4 | G17: 3467.5 | H17: 1437.4 | I17: 0 | J17: 401.3 | K17: 649.35 | L17: 0 | M17: 0 | N17: 0 | O17: 551.1 | P17: 5306.2 | Q17: 649.35 | R17: 6506.65 | S17: 05:00 | T17: 4542.65 | U17: 1474.3 | V17: 0 | W17: 489.7 | X17: 6506.65 | Y17: 05:00 | Z17: 311.6 | AA17: 18.8 | AB17: 0 | AC17: 489.7 | AD17: 820.1
B18: 05:30 | C18: 422.3 | D18: 37.7 | E18: 0 | F18: 83.8 | G18: 3427 | H18: 1452.4 | I18: 0 | J18: 394.1 | K18: 652.25 | L18: 0 | M18: 0 | N18: 0 | O18: 543.8 | P18: 5273.5 | Q18: 652.25 | R18: 6469.55 | S18: 05:30 | T18: 4501.55 | U18: 1490.1 | V18: 0 | W18: 477.9 | X18: 6469.55 | Y18: 05:30 | Z18: 291.7 | AA18: 18.9 | AB18: 0 | AC18: 477.9 | AD18: 788.5
B19: 06:00 | C19: 433.1 | D19: 38 | E19: 0 | F19: 64.2 | G19: 3492.3 | H19: 1514.5 | I19: 0 | J19: 354.2 | K19: 673.8 | L19: 0 | M19: 3.53 | N19: 0 | O19: 535.3 | P19: 5361 | Q19: 677.33 | R19: 6573.63 | S19: 06:00 | T19: 4599.2 | U19: 1552.5 | V19: 3.53 | W19: 418.4 | X19: 6573.63 | Y19: 06:00 | Z19: 303.4 | AA19: 18.9 | AB19: 3.53 | AC19: 418.4 | AD19: 744.23
... B56: TOTAL MWh | C56: 10617.4 | D56: 1041.35 | E56: 3 | F56: 1915 | G56: 84231 | H56: 39519.5 | I56: 9.25 | J56: 12645.55 | K56: 14788.295 | L56: 0 | M56: 5853.594 | N56: 0 | O56: 13576.75 | P56: 136405.3 | Q56: 20641.889 | R56: 170623.94 | S56: TOTAL MWh | T56: 109636.7 | U56: 40560.85 | V56: 5865.844 | W56: 14560.55 | X56: 170623.94 | Y56: TOTAL MWh | Z56: 7765.5 | AA56: 459.1 | AB56: 5865.844 | AC56: 14560.55 | AD56: 28650.994

Sheet HOP
B3: sábado, 26 de Abril del 2025
B5: Reporte de Horas de Operación
B6: Empresa | C6: Central | D6: Grupo | E6: Modo de Operación | F6: Inicio | G6: Final | H6: O. Arranque | I6: O. Parada | J6: Tipo Operación | K6: Ensayo de Potencia Efectiva | L6: Ensayo de Potencia Mínima | M6: Sistema | N6: Lim. Transm. | O6: Causa | P6: Observación
B7: AGRO INDUSTRIAL PARAMONGA S.A. | C7: C.T. PARAMONGA | D7: CENTRAL | E7: PARAMONGA - BAGAZO | F7: 26/04/2025 00:00:00 | G7: 27/04/2025 00:00:00 | J7: POR COGENERACION | O7: ...
B8: ENEL GENERACION PIURA S.A. | C8: C.T. MALACAS 1 | D8: CENTRAL | E8: MALACAS1 TG6 - GAS | F8: 26/04/2025 00:00:00 | G8: 26/04/2025 01:24:00 | J8: POR POTENCIA O ENERGIA | O8: ...
B9: ENEL GENERACION PIURA S.A. | C9: C.T. MALACAS 1 | D9: CENTRAL | E9: MALACAS1 TG6 - GAS | F9: 26/04/2025 01:24:00 | G9: 26/04/2025 04:53:00 | I9: 26/04/2025 04:44:00 | J9: A MINIMA CARGA | O9: ...
B10: ENGIE | C10: C.T. CHILCA 1 | D10: CENTRAL | E10: CHILCA1 CCOMB TG1 & TG3 - GAS | F10: 26/04/2025 00:00:00 | G10: 26/04/2025 00:12:00 | J10: POR POTENCIA O ENERGIA | O10: ...
B11: ENGIE | C11: C.T. CHILCA 1 | D11: CENTRAL | E11: CHILCA1 CCOMB TG1 & TG3 - GAS | F11: 26/04/2025 00:12:00 | G11: 26/04/2025 05:44:00 | J11: A MINIMA CARGA | O11: ...
B12: ENGIE | C12: C.T. CHILCA 1 | D12: CENTRAL | E12: CHILCA1 CCOMB TG1 & TG3 - GAS | F12: 26/04/2025 05:44:00 | G12: 26/04/2025 06:31:00 | J12: POR POTENCIA O ENERGIA | O12: ... | P12: S/C generar a 350 MW
B13: ENGIE | C13: C.T. CHILCA 1 | D13: CENTRAL | E13: CHILCA1 CCOMB TG1 & TG3 - GAS | F13: 26/04/2025 06:31:00 | G13: 26/04/2025 08:17:00 | J13: A MINIMA CARGA | O13: ...
B14: ENGIE | C14: C.T. CHILCA 1 | D14: CENTRAL | E14: CHILCA1 CCOMB TG1 & TG3 - GAS | F14: 26/04/2025 08:17:00 | G14: 26/04/2025 12:22:00 | J14: POR POTENCIA O ENERGIA | O14: ... | P14: S/C geneara a 350 MW. A las 08:37 h, S/C generar a máxima generación. A las 11:19 h, S/C generar a 400 MW. A las 12:01 h, S/C generar a plena carga.
B15: ENGIE | C15: C.T. CHILCA 1 | D15: CENTRAL | E15: CHILCA1 CCOMB TG1 & TG3 - GAS | F15: 26/04/2025 12:22:00 | G15: 26/04/2025 16:27:00 | J15: A MINIMA CARGA | O15: ...
B16: ENGIE | C16: C.T. CHILCA 1 | D16: CENTRAL | E16: CHILCA1 CCOMB TG1 & TG3 - GAS | F16: 26/04/2025 16:27:00 | G16: 27/04/2025 00:00:00 | J16: POR POTENCIA O ENERGIA | O16: ... | P16: S/C generar a 380 MW. A las 17:28 h, S/C generar a mínimo por pruebas de la TG2. A las 17:52 h, S/C generar a máxima generación en conjunto con la TG2. A las 21:16 h, S/C generar a máxima generación. A las 22:51 h, S/C generar a 400 MW.
B17: ENGIE | C17: C.T. CHILCA 1 | D17: TG2 | E17: CHILCA1 TG2 - GAS | F17: 26/04/2025 16:56:00 | G17: 26/04/2025 21:15:00 | J17: POR PRUEBAS | O17: REQ. PROPIO
B18: FENIX POWER PERÚ | C18: C.T. FENIX | D18: GT11 | E18: FENIX GT11 - GAS | F18: 26/04/2025 03:17:00 | G18: 26/04/2025 09:13:00 | J18: POR PRUEBAS | O18: REQ. PROPIO
B19: FENIX POWER PERÚ | C19: C.T. FENIX | D19: CENTRAL | E19: FENIX CCOMB GT11 - GAS | F19: 26/04/2025 09:13:00 | G19: 27/04/2025 00:00:00 | J19: POR PRUEBAS | O19: REQ. PROPIO
B20: GM OPERACIONES S.A.C. | C20: CT REFINERIA TALARA | D20: TV1 REF TALARA | E20: REF_TALARA TV1 - NLH_RFG | F20: 26/04/2025 00:00:00 | G20: 27/04/2025 00:00:00 | J20: POR COGENERACION | O20: ...
B21: KALLPA GENERACION S.A. | C21: C.T. KALLPA | D21: CENTRAL | E21: KALLPA CCOMB TG1 & TG2 & TG3 - GAS | F21: 26/04/2025 00:00:00 | G21: 26/04/2025 18:30:00 | J21: POR RSF | O21: ...
B22: KALLPA GENERACION S.A. | C22: C.T. KALLPA | D22: CENTRAL | E22: KALLPA CCOMB TG1 & TG2 & TG3 - GAS | F22: 26/04/2025 18:30:00 | G22: 26/04/2025 21:00:00 | J22: POR POTENCIA O ENERGIA | O22: ...
B23: KALLPA GENERACION S.A. | C23: C.T. KALLPA | D23: CENTRAL | E23: KALLPA CCOMB TG1 & TG2 & TG3 - GAS | F23: 26/04/2025 21:00:00 | G23: 27/04/2025 00:00:00 | J23: POR RSF | O23: ...
B24: KALLPA GENERACION S.A. | C24: C.T. LAS FLORES | D24: CENTRAL | E24: LAS FLORES CCOMB TG1 - GAS | F24: 26/04/2025 00:00:00 | G24: 26/04/2025 18:28:00 | J24: A MINIMA CARGA | O24: ...
B25: KALLPA GENERACION S.A. | C25: C.T. LAS FLORES | D25: CENTRAL | E25: LAS FLORES CCOMB TG1 - GAS | F25: 26/04/2025 18:28:00 | G25: 26/04/2025 22:51:00 | J25: POR POTENCIA O ENERGIA | O25: ...
B26: KALLPA GENERACION S.A. | C26: C.T. LAS FLORES | D26: CENTRAL | E26: LAS FLORES CCOMB TG1 - GAS | F26: 26/04/2025 22:51:00 | G26: 27/04/2025 00:00:00 | J26: A MINIMA CARGA | O26: ...
B27: ORYGEN PERU S.A.A. | C27: C.T. VENTANILLA | D27: CENTRAL | E27: VENTANILLA CCOMB TG3 & TG4 - GAS | F27: 26/04/2025 00:00:00 | G27: 26/04/2025 13:28:00 | I27: 26/04/2025 12:23:00 | J27: A MINIMA CARGA | O27: ... | P27: F/S TG3
B28: ORYGEN PERU S.A.A. | C28: C.T. VENTANILLA | D28: CENTRAL | E28: VENTANILLA CCOMB TG4 - GAS | F28: 26/04/2025 13:28:00 | G28: 26/04/2025 16:26:00 | J28: A MINIMA CARGA | O28: ...
B29: ORYGEN PERU S.A.A. | C29: C.T. VENTANILLA | D29: CENTRAL | E29: VENTANILLA CCOMB TG4 - GAS | F29: 26/04/2025 16:26:00 | G29: 27/04/2025 00:00:00 | J29: POR POTENCIA O ENERGIA | O29: ...
B30: PETRAMAS | C30: C.T. HUAYCOLORO | D30: CENTRAL | E30: HUAYCOLORO - BIOGAS | F30: 26/04/2025 00:00:00 | G30: 26/04/2025 01:24:00 | I30: 26/04/2025 01:03:00 | J30: POR POTENCIA O ENERGIA | O30: ...
B31: PETRAMAS | C31: C.T.B DOÑA CATALINA | D31: CENTRAL | E31: DONA CATALINA - BIOGAS | F31: 26/04/2025 00:00:00 | G31: 27/04/2025 00:00:00 | J31: POR POTENCIA O ENERGIA | O31: ...
B32: PETRAMAS | C32: C.T.B. CALLAO | D32: CENTRAL | E32: CALLAO - BIOGAS | F32: 26/04/2025 00:00:00 | G32: 27/04/2025 00:00:00 | J32: POR POTENCIA O ENERGIA | O32: ...
B33: SDF ENERGIA SAC | C33: C.T. OQUENDO | D33: CENTRAL | E33: OQUENDO CCOMB TG1 - GAS | F33: 26/04/2025 00:00:00 | G33: 27/04/2025 00:00:00 | J33: POR COGENERACION | O33: ...

Sheet INDISP
B3: sábado, 26 de Abril del 2025
B5: Hora Inicio y Fin de Indisponibilidades de las Unidades de Generación SEIN
B6: Empresa | C6: Ubicación | D6: Equipo | E6: Inicio | F6: Final | G6: Descripción | H6: MW Indisp. | I6: Prog. | J6: Dispon | K6: Interrupc. | L6: Tipo | M6: CodEq | N6: TipoEq_Osinerg
B7: AGROAURORA S.A.C. | C7: MAPLE ETANOL | D7: CENTRAL | E7: 26/04/2025 00:00 | F7: 27/04/2025 00:00 | G7: MANTENIMIENTO PREVENTIVO PROGRAMADO DE LA CENTRAL TERMOELECTRICA Y EQUIPOS AUXILIARES. | H7: 17 | I7: P | J7: F/S | K7: N | L7: OTROS | M7: 13417 | N7: G
B8: AGROAURORA S.A.C. | C8: MAPLE ETANOL | D8: CENTRAL | E8: 26/04/2025 00:00 | F8: 27/04/2025 00:00 | G8: CENTRAL TERMOELECTRICA FUERA DE SERVICIO POR FALTA DE MATERIA PRIMA PARA LOS REQUERIMIENTOS DE CALOR ÚTIL EN FÁBRICA | H8: 17 | I8: P | J8: F/S | K8: N | L8: OTROS | M8: 13417 | N8: G
B9: AGROINDUSTRIAS SAN JACINTO S.A.A. | C9: SAN JACINTO | D9: CENTRAL | E9: 26/04/2025 00:00 | F9: 27/04/2025 00:00 | G9: Mantenimiento Anual. | H9: 8.15 | I9: P | J9: F/S | K9: N | L9: PREV. | M9: 19865 | N9: G
B10: BIOENERGIA DEL CHIRA S.A. | C10: CAÑA BRAVA | D10: CENTRAL | E10: 26/04/2025 00:00 | F10: 27/04/2025 00:00 | G10: La C.T. Caña Brava retrasará su arranque post para anual de mantenimiento debido a un retraso en el reinicio de la molienda de caña. | H10: 11.63 | I10: P | J10: F/S | K10: N | L10: PREV. | M10: 20510 | N10: G
B11: EGASA | C11: CHARCANI IV | D11: G3 | E11: 26/04/2025 00:00 | F11: 27/04/2025 00:00 | G11: Mantenimiento Generador | H11: 5.1 | I11: P | J11: F/S | K11: N | L11: PREV. | M11: 120 | N11: G
B12: EGEJUNIN | C12: SANTA CRUZ II | D12: G2 | E12: 26/04/2025 00:00 | F12: 27/04/2025 00:00 | G12: Mantenimiento correctivo mayor de turbina del G2. | H12: 3.15 | I12: P | J12: F/S | K12: N | L12: CORR. | M12: 12651 | N12: G
B13: EMPRESA DE GENERACION ELECTRICA SANTA ANA S.A.C. | C13: RENOVANDES H1 | D13: G1 | E13: 26/04/2025 05:03 | F13: 26/04/2025 23:23 | G13: Vaciado de Tubería Forzada, para Instalación de sensores de Presión y manómetro de tubería Forzada del grupo de la CH. ANASHIRONI | H13: 20 | I13: P | J13: F/S | K13: S | L13: SEG.PER | M13: 18265 | N13: G
B14: EMPRESA DE GENERACION ELECTRICA SANTA ANA S.A.C. | C14: RENOVANDES H1 | D14: G1 | E14: 26/04/2025 05:03 | F14: 26/04/2025 23:23 | G14: Desconexión de Grupo Generador H1, para Instalación de sensores de presión y manómetro de tubería Forzada del grupo de la CH. ANASHIRONI | H14: 20 | I14: P | J14: F/S | K14: N | L14: SEG.PER | M14: 18265 | N14: G
B15: ENGIE | C15: CHILCA 1 | D15: TG2 | E15: 26/04/2025 00:00 | F15: 27/04/2025 00:00 | G15: INSPECCION DE 33000 EOH (HOT GAS PATH) | H15: 170 | I15: P | J15: F/S | K15: N | L15: PREV. | M15: 198 | N15: G
B16: ENGIE | C16: QUITARACSA | D16: CENTRAL | E16: 26/04/2025 00:00 | F16: 27/04/2025 00:00 | G16: FUERA DE SERVICIO DEBIDO A INDISPONIBILIDAD BOCATOMA QUITARACSA Y SAN MATEO POR CAIDA DE ROCAS EN LA ZONA. NO SE PUEDE CAPTAR AGUA EN LA CONDICION PRESENTADA | H16: 110 | I16: P | J16: F/S | K16: N | L16: CORR. | M16: 14448 | N16: G
B17: ENGIE | C17: YUNCÁN | D17: G2 | E17: 26/04/2025 00:00 | F17: 27/04/2025 00:00 | G17: MANTENIMIENTO CORRECTIVO DEL GENERADOR | H17: 45.5 | I17: P | J17: F/S | K17: N | L17: CORR. | M17: 200 | N17: G
B18: FENIX POWER PERÚ | C18: FENIX | D18: CENTRAL | E18: 26/04/2025 00:00 | F18: 27/04/2025 00:00 | G18: Indisponible debido a su mantenimiento anual. | H18: 0 | I18: P | J18: F/S | K18: N | L18: PREV. | M18: 13601 | N18: G
... B35: TERMOCHILCA S.A.C. | C35: SANTO DOMINGO DE LOS OLLEROS | D35: TG1 | E35: 26/04/2025 00:00 | F35: 27/04/2025 00:00 | G35: Inspección mayor de la unidad TG1 (55000 horas)**************************** | H35: 296.3 | I35: P | J35: F/S | K35: N | L35: PREV. | M35: 13657 | N35: G

Sheet RESERVA_FRÍA
B3: 26/04/2025 | E3: EJECUTADO | L3: Sábado 26 de Abril del 2025 / SEM N° 17 | V3: EJECUTADO | AC3: Sábado 26 de Abril del 2025 / SEM N° 17 | EE3: ENERGIA RENOVABLES | GP3: COGENERACION | GY3: NO INTEGRANTES
