Workbook

Sheet EVENTOS
B3: miércoles, 5 de Noviembre del 2025
B5: INFORMACIÓN DE EVENTOS PRINCIPALES EN SUS INSTALACIONES
B6: TIPO DE EVENTO | C6: EMPRESA | D6: UBICACIÓN | E6: TIPO DE EQUIPO | F6: EQUIPO | G6: INICIO | H6: FINAL | I6: DESCRIPCIÓN | J6: MW INDISP. | K6: INTERRUPCIÓN (SI/NO) | L6: TENSIÓN DE FALLA (kV)
B7: FALLA | C7: ATN S.A. | D7: RAMADA - PAMPA HONDA | E7: LINEA DE TRANSMISION | F7: L-2275 | G7: 05/11/2025 17:56:00 | H7: 05/11/2025 17:56:00 | I7: RECIERRE EXITOSO DE LA S LINEAS L-2273/L-2275 (LA RAMADA - PAMPA HONDA) DE 220 KV | K7: NO | L7: 220
B8: EVENTO | C8: CONELSUR LT SAC | D8: PORTILLO | E8: SUBESTACION | F8: SS.EE. | G8: 05/11/2025 00:00:00 | H8: 06/11/2025 00:00:00 | I8: DECLARACIÓN DE SITUACIÓN EXCEPCIONAL EN LA S.E. PORTILLO 60 kV | K8: NO
B9: EVENTO | C9: ELECTRO ORIENTE | D9: BELAUNDE TERRY - TARAPOTO | E9: LINEA DE TRANSMISION | F9: L-1018 | G9: 05/11/2025 18:18:00 | H9: 05/11/2025 19:59:00 | I9: DECLARACIÓN DE SITUACIÓN EXCEPCIONAL EN LA LÍNEA L-1018 (BELAUNDE TERRY - TARAPOTO) DE 138 kV | K9: NO
B10: FALLA | C10: VARI ENERGIA S.A.C. | D10: ANASHIRONI | E10: GENERADOR HIDROELÉCTRICO | F10: G1 | G10: 05/11/2025 05:40:11 | H10: 05/11/2025 08:59:00 | I10: DESCONEXIÓN DE LA C.H. ANASHIRONI | K10: NO | L10: 13.8

Sheet RESTRIC_OPE
B3: miércoles, 5 de Noviembre del 2025
B5: RESTRICCIONES OPERATIVAS
B6: FECHA | C6: HORA INICIO | D6: HORA FINAL | E6: EMPRESA | F6: UBICACIÓN | G6: T.Eq. | H6: EQUIPO | I6: DESCRIPCIÓN
B7: 05/11/2025 | C7: 00:00 | D7: 24:00 | E7: CELEPSA | F7: C.H. EL PLATANAL | G7: CH | H7: CENTRAL | I7: De acuerdo con el correo del 13/10/2025. Debido a problemas en el control de la compuerta de bocatoma, informaron que el servicio de RSF queda indisponible.
B8: 05/11/2025 | C8: 00:00 | D8: 24:00 | E8: EGASA | F8: S.E. CONVERTIDOR | G8: BARRA | H8: BARRA138KV | I8: EGASA limitó la capacidad del transformador 138 kV/33 kV a 50 MVA por deterioro del aislamiento.
B9: 05/11/2025 | C9: 00:00 | D9: 24:00 | E9: ELECTROPERU | F9: C.H. MANTARO | G9: CH | H9: CENTRAL | I9: De acuerdo con el correo del día 25.08.2025, la central tiene una limitación de potencia máxima de 650 MW por seguridad de la central.
B10: 05/11/2025 | C10: 00:00 | D10: 24:00 | E10: ENEL GENERACION PIURA S.A. | F10: C.T. MALACAS | G10: CT | H10: CENTRAL | I10: De acuerdo con la comunicación vía correo del día 24.10.2024. ENEL GENERACIÓN PIURA informa una restricción de potencia para alcanzar 105 MW en simultaneo (TG6+TGN4).
B11: 05/11/2025 | C11: 00:00 | D11: 24:00 | E11: ENEL GENERACION PIURA S.A. | F11: C.T. MALACAS | G11: GT | H11: TG4 | I11: De acuerdo a lo informado mediante correo electrónico el día 25.10, con la disponibilidad actual de aproximadamente 13 MMPCD (368.12 Mm³) la unidad TG4 puede con una generación de 80 MW durante 5 horas, y a potencia mínima durante el resto de los periodos
B12: 05/11/2025 | C12: 00:00 | D12: 24:00 | E12: ENGIE ENERGIA PERU S.A.A. | F12: C.H. YUNCÁN | G12: GH | H12: G3 | I12: Según la carta N° ENG/ 198-2024 enviada por su representada, se opera de forma continua el G3 de la CH Yuncán, debido a la ejecución de mantenimientos necesarios para evitar daños en los sellos de seguridad de la válvula esférica del grupo.
B13: 05/11/2025 | C13: 00:00 | D13: 24:00 | E13: ENGIE ENERGIA PERU S.A.A. | F13: C.T. CHILCA 1 | G13: CT | H13: CENTRAL | I13: Restricción de temperatura de la C.T Chilca, ver valor en el modelo de despacho.
B14: 05/11/2025 | C14: 00:00 | D14: 24:00 | E14: ENGIE ENERGIA PERU S.A.A. | F14: C.T. CHILCA 1 | G14: CT | H14: CENTRAL | I14: Con carta ENG/971-2023, indica que no puede cumplir con las IO considerada en el PDO_17122023 dado que vulneran la seguridad de sus activos. Indican que se debe tomar TMO=168h.
B15: 05/11/2025 | C15: 00:00 | D15: 24:00 | E15: ENGIE ENERGIA PERU S.A.A. | F15: C.T. CHILCA 2 | G15: CT | H15: CENTRAL | I15: Con carta ENG/971-2023, indica que no puede cumplir con las IO considerada en el PDO_17122023 dado que vulneran la seguridad de sus activos. Indican que se debe tomar TMO=168h.
B16: 05/11/2025 | C16: 00:00 | D16: 24:00 | E16: FENIX POWER PERÚ | F16: C.T. FENIX | G16: CT | H16: CENTRAL | I16: De acuerdo con lo comunicado en el correo del día 06.05.2025, la CT Fenix cuenta con TMO de 168 hrs en todos sus modos de operación.
B17: 05/11/2025 | C17: 00:00 | D17: 24:00 | E17: KALLPA GENERACION S.A. | F17: C.H. MINI CENTRAL CERRO DEL AGUILA | G17: CH | H17: CENTRAL | I17: Caudal ecológico de la Mini CH Cerro del Águila es de 10.6 m3/s correspondiente al mes de noviembre.
... B47: 05/11/2025 | C47: 00:00 | D47: 24:00 | E47: TERMOSELVA | F47: C.T. AGUAYTÍA | G47: CT | H47: CENTRAL | I47: Disponibilidad de 23.5 MMSCF para la CT Aguaytía.

Sheet MANTENIMIENTO EJECUTADOS
B3: miércoles, 5 de Noviembre del 2025
B5: Mantenimiento Ejecutado
B6: Empresa | C6: Ubicación | D6: Equipo | E6: Inicio | F6: Final | G6: Descripción | H6: MW Indisp. | I6: Prog. | J6: Dispon | K6: Interrupc. | L6: Tipo | M6: CodEq | N6: TipoEq_Osinerg
B7: ACEROS AREQUIPA | C7: INDEPENDENCIA - ACEROS AREQUIPA | D7: L-2217 | E7: 05/11/2025 14:00 | F7: 05/11/2025 17:00 | G7: Se requiere cambiar densimetro del interruptor de la fase S | H7: 150 | I7: P | J7: F/S | K7: N | L7: CORR. | M7: 748 | N7: T
B8: ANGLO AMERICAN QUELLAVECO S.A. | C8: MOQUEGUA | D8: CL-2067 | E8: 05/11/2025 10:30 | F8: 05/11/2025 16:00 | G8: MP 1A TERMOGRAFIA A EQUIPOS DE PATIO 220 KV DE LAS CELDAS CL-2067 Y CL-2068, ACTIVIDAD CON CAMBIO DE BARRAS. (R0114508) | H8: 0 | I8: P | J8: E/S | K8: N | L8: PREV. | M8: 21361 | N8: T
B9: ANGLO AMERICAN QUELLAVECO S.A. | C9: MOQUEGUA | D9: CL-2068 | E9: 05/11/2025 10:30 | F9: 05/11/2025 16:00 | G9: MP 1A TERMOGRAFIA A EQUIPOS DE PATIO 220 KV DE LAS CELDAS CL-2067 Y CL-2068, ACTIVIDAD CON CAMBIO DE BARRAS. (R0114508) | H9: 0 | I9: P | J9: E/S | K9: N | L9: PREV. | M9: 21362 | N9: T
B10: ATLANTICA TRANSMISION SUR S.A. | C10: CHILCA CTM - POROMA | D10: L-5032 | E10: 05/11/2025 07:25 | F10: 05/11/2025 16:52 | G10: Mejoramiento de PAT | H10: 0 | I10: P | J10: E/S | K10: N | L10: PREV. | M10: 13652 | N10: T
B11: ATLANTICA TRANSMISION SUR S.A. | C11: CHILCA CTM - POROMA | D11: L-5032 | E11: 05/11/2025 08:27 | F11: 05/11/2025 17:44 | G11: Mantenimiento de pedestales. | H11: 0 | I11: P | J11: E/S | K11: N | L11: PREV. | M11: 13652 | N11: T
B12: ATLANTICA TRANSMISION SUR S.A. | C12: OCONA | D12: INT-5450 | E12: 05/11/2025 00:00 | F12: 06/11/2025 00:00 | G12: Interruptor INT-5450 cerrado con restriccion operativa, REB-5450 en servicio y suministrando los SS.AA. de la S.E. Oco?a. | H12: 0 | I12: P | J12: E/S | K12: N | L12: OTROS | M12: 13761 | N12: T
B13: ATLANTICA TRANSMISION SUR S.A. | C13: POROMA | D13: INT-5371 | E13: 05/11/2025 00:00 | F13: 06/11/2025 00:00 | G13: Seccionador SBB-5371 fase T indisponible por problemas mecanicos, el seccionador permanece cerrado y bloqueado | H13: 0 | I13: P | J13: E/S | K13: N | L13: OTROS | M13: 13751 | N13: T
B14: ATLANTICA TRANSMISION SUR S.A. | C14: POROMA | D14: REB-5350 | E14: 05/11/2025 00:00 | F14: 06/11/2025 00:00 | G14: Fuera de servicio po falla en el equipo. | H14: 0 | I14: P | J14: F/S | K14: N | L14: OTROS | M14: 13771 | N14: T
B15: ATN S.A. | C15: KIMAN AYLLU | D15: AUT-501 | E15: 05/11/2025 00:00 | F15: 06/11/2025 00:00 | G15: Restriccion Operativa en el circuito de control de cambiador de tap s del AUT-501 | H15: 0 | I15: P | J15: E/S | K15: N | L15: OTROS | M15: 13099 | N15: T
B16: ATRIA ENERGIA S.A.C. | C16: PURMACANA | D16: CENTRAL | E16: 05/11/2025 00:00 | F16: 06/11/2025 00:00 | G16: MANTENIMIENTO DE CANAL DE CONDUCCION, COMPUERTAS, SISTEMA DE LUBRICACION DE COJINETES, SISTEMA DE REFRIGERACION Y VALVULAS | H16: 0.4 | I16: P | J16: F/S | K16: N | L16: PREV. | M16: 13132 | N16: G
B17: CONELSUR LT SAC | C17: CALLAHUANCA (CNS) | D17: S.E. | E17: 05/11/2025 00:00 | F17: 06/11/2025 00:00 | G17: RELE DIFERENCIAL DE BARRAS DE CALLAHUANCA 220KV INOPERATIVO | H17: 0 | I17: F | J17: E/S | K17: N | L17: OTROS | M17: 316 | N17: T
B18: EGASA | C18: SANTUARIO | D18: ACOPLE 138 | E18: 05/11/2025 00:00 | F18: 06/11/2025 00:00 | G18: En servicio barra 2,uso en grupo N1 Charcani V con interruptor de acoplamiento, por falla | H18: 0 | I18: P | J18: E/S | K18: N | L18: OTROS | M18: 11052 | N18: T
... B156: TRANSMANTARO | C156: YARABAMBA | D156: CL-R-30 | E156: 05/11/2025 00:00 | F156: 06/11/2025 00:00 | G156: CL-R30 CON MANDO SINCRONIZADO ASOCIADO AL INTERRUPTOR IN-5147 INDISPONIBLE. EL SABADO 19.04.25 NO PUDO SER AJUSTADO DEBIDO A FALTA DE EQUIPOS DE PARTE DE LA CONTRATISTA HITACHI. | H156: 0 | I156: P | J156: E/S | K156: N | L156: OTROS | M156: 17424 | N156: T

Sheet INGRESO OC
A3: miércoles, 5 de Noviembre del 2025
A5: INGRESO A OPERACIÓN COMERCIAL
A6: EMPRESA | B6: TIPO DE EQUIPO | C6: UBICACIÓN | D6: EQUIPO | E6: Fecha y hora de Ingreso a Operación Comercial

Sheet DESPACHO_EJECUTADO
B3: miércoles, 5 de Noviembre del 2025
A5: POTENCIA ACTIVA EJECUTADA DE LAS UNIDADES DE GENERACIÓN DEL SEIN (MW) | FM5: CENTRALES NO INTEGRANTES COES
A6: FECHA | B6: HORA | C6: 65333 | D6: 101 | E6: 102 | F6: 42667 | G6: 42668 | H6: 126 | I6: 127 | J6: 138 | K6: 139 | L6: 197 | M6: 203 | N6: 204 | O6: 230 | P6: 209 | Q6: 56677 | R6: 796 | S6: 2146 | T6: 142 | U6: 143 | V6: 125 | W6: 187 | X6: 163 | Y6: 298 | Z6: 299 | AA6: 219 | AB6: 151 | AC6: 152 | AD6: 153 | AE6: 154 | AF6: 756 | AG6: 156 | AH6: 155 | AI6: 182 | AJ6: 212 | AK6: 758 | AL6: 263 | AM6: 265 | AN6: 775 | AO6: 777 | AP6: 2154 | AQ6: 150 | AR6: 149 | AS6: 188 | AT6: 2131 | AU6: 755 | AV6: 252 | AW6: 249 | AX6: 250 | AY6: 117 | AZ6: 267 | BA6: 268 | BB6: 119 | BC6: 120 | BD6: 189 | BE6: 122 | BF6: 266 | BG6: 337 | BH6: 338 | BI6: 251 | BJ6: 115 | BK6: 239 | BL6: 288 | BM6: 240 | BN6: 241 | BO6: 242 | BP6: 191 | BQ6: 194 | BR6: 196 | BS6: 207 | BT6: 236 | BU6: 795 | BV6: 285 | BW6: 995 | BX6: 996 | BY6: 997 | BZ6: 766 | CA6: 926 | CB6: 924 | CC6: 121 | CD6: 103 | CE6: 104 | CF6: 106 | CG6: 105 | CH6: 107 | CI6: 110 | CJ6: 109 | CK6: 144 | CL6: 113 | CM6: 114 | CN6: 193 | CO6: 208 | CP6: 786 | CQ6: 787 | CR6: 788 | CS6: 789 | CT6: 248 | CU6: 2159 | CV6: 303 | CW6: 59715 | CX6: 62255 | CY6: 1263 | CZ6: 61800 | DA6: 2194 | DB6: 69125 | DC6: 216 | DD6: 198 | DE6: 70400 | DF6: 49607 | DG6: 214 | DH6: 260 | DI6: 2152 | DJ6: 2128 | DK6: 247 | DL6: 228 | DM6: 2135 | DN6: 261 | DO6: 237 | DP6: 253 | DQ6: 770 | DR6: 235 | DS6: 238 | DT6: 2184 | DU6: 61855 | DV6: 223 | DW6: 226 | DX6: 201 | DY6: 258 | DZ6: 259 | EA6: 920 | EB6: 257 | EC6: 256 | ED6: 2148 | EE6: 58288 | EF6: 58289 | EG6: 58839 | EH6: 58840 | EI6: 296 | EJ6: 297 | EK6: 211 | EL6: 2175 | EM6: 2178 | EN6: 2181 | EO6: 1262 | EP6: 63425 | EQ6: 233 | ER6: 2150 | ES6: 2165 | ET6: 2161 | EU6: 61197 | EV6: 58851 | EW6: 225 | EX6: 2201 | EY6: 2171 | EZ6: 760 | FA6: 234 | FB6: 215 | FC6: 917 | FD6: 289 | FE6: 58333 | FF6: 58336 | FG6: 213 | FH6: 232 | FI6: 2190 | FJ6: 69867 | FK6: TOTAL COES | FM6: 221 | FN6: 222 | FO6: 224 | FP6: 2187 | FQ6: 227 | FR6: 49400 | FS6: 199 | FT6: 200 | FU6: TOTAL NO COES
C7: SUR | D7: CENTRO | E7: CENTRO | F7: NORTE | G7: NORTE | H7: NORTE | I7: NORTE | J7: CENTRO | K7: CENTRO | L7: CENTRO | M7: CENTRO | N7: CENTRO | O7: CENTRO | P7: CENTRO | Q7: CENTRO | R7: CENTRO | S7: CENTRO | T7: CENTRO | U7: CENTRO | V7: CENTRO | W7: CENTRO | X7: SUR | Y7: SUR | Z7: SUR | AA7: CENTRO | AB7: SUR | AC7: SUR | AD7: SUR | AE7: SUR | AF7: SUR | AG7: SUR | AH7: SUR | AI7: SUR | AJ7: CENTRO | AK7: NORTE | AL7: NORTE | AM7: NORTE | AN7: CENTRO | AO7: CENTRO | AP7: CENTRO | AQ7: CENTRO | AR7: CENTRO | AS7: CENTRO | AT7: CENTRO | AU7: SUR | AV7: CENTRO | AW7: CENTRO | AX7: CENTRO | AY7: CENTRO | AZ7: CENTRO | BA7: CENTRO | BB7: CENTRO | BC7: CENTRO | BD7: SUR | BE7: NORTE | BF7: CENTRO | BG7: CENTRO | BH7: CENTRO | BI7: CENTRO | BJ7: NORTE | BK7: NORTE | BL7: NORTE | BM7: SUR | BN7: SUR | BO7: SUR | BP7: CENTRO | BQ7: CENTRO | BR7: CENTRO | BS7: CENTRO | BT7: CENTRO | BU7: CENTRO | BV7: CENTRO | BW7: SUR | BX7: SUR | BY7: SUR | BZ7: NORTE | CA7: SUR | CB7: CENTRO | CC7: NORTE | CD7: CENTRO | CE7: CENTRO | CF7: CENTRO | CG7: CENTRO | CH7: CENTRO | CI7: CENTRO | CJ7: CENTRO | CK7: CENTRO | CL7: CENTRO | CM7: CENTRO | CN7: CENTRO | CO7: CENTRO | CP7: SUR | CQ7: SUR | CR7: SUR | CS7: SUR | CT7: CENTRO | CU7: CENTRO | CV7: CENTRO | CW7: CENTRO | CX7: SUR | CY7: NORTE | CZ7: NORTE | DA7: NORTE | DB7: CENTRO | DC7: NORTE | DD7: NORTE | DE7: SUR | DF7: SUR | DG7: CENTRO | DH7: CENTRO | DI7: CENTRO | DJ7: NORTE | DK7: NORTE | DL7: CENTRO | DM7: CENTRO | DN7: SUR | DO7: SUR | DP7: CENTRO | DQ7: CENTRO | DR7: SUR | DS7: CENTRO | DT7: CENTRO | DU7: NORTE | DV7: CENTRO | DW7: CENTRO | DX7: NORTE | DY7: CENTRO | DZ7: CENTRO | EA7: CENTRO | EB7: NORTE | EC7: NORTE | ED7: SUR | EE7: CENTRO | EF7: CENTRO | EG7: CENTRO | EH7: CENTRO | EI7: CENTRO | EJ7: CENTRO | EK7: SUR | EL7: SUR | EM7: SUR | EN7: SUR | EO7: NORTE | EP7: SUR | EQ7: SUR | ER7: SUR | ES7: CENTRO | ET7: CENTRO | EU7: CENTRO | EV7: SUR | EW7: CENTRO | EX7: CENTRO | EY7: CENTRO | EZ7: CENTRO | FA7: SUR | FB7: NORTE | FC7: CENTRO | FD7: NORTE | FE7: NORTE | FF7: NORTE | FG7: CENTRO | FH7: NORTE | FI7: NORTE | FJ7: NORTE | FM7: NORTE | FN7: CENTRO | FO7: NORTE | FP7: NORTE | FQ7: NORTE | FR7: NORTE | FS7: NORTE | FT7: NORTE
C8: HIDROELÉCTRICA | D8: HIDROELÉCTRICA | E8: HIDROELÉCTRICA | F8: TERMOELÉCTRICA | G8: TERMOELÉCTRICA | H8: HIDROELÉCTRICA | I8: HIDROELÉCTRICA | J8: TERMOELÉCTRICA | K8: TERMOELÉCTRICA | L8: TERMOELÉCTRICA | M8: TERMOELÉCTRICA | N8: TERMOELÉCTRICA | O8: TERMOELÉCTRICA | P8: TERMOELÉCTRICA | Q8: TERMOELÉCTRICA | R8: HIDROELÉCTRICA | S8: HIDROELÉCTRICA | T8: TERMOELÉCTRICA | U8: TERMOELÉCTRICA | V8: TERMOELÉCTRICA | W8: TERMOELÉCTRICA | X8: HIDROELÉCTRICA | Y8: HIDROELÉCTRICA | Z8: HIDROELÉCTRICA | AA8: TERMOELÉCTRICA | AB8: HIDROELÉCTRICA | AC8: HIDROELÉCTRICA | AD8: HIDROELÉCTRICA | AE8: HIDROELÉCTRICA | AF8: TERMOELÉCTRICA | AG8: TERMOELÉCTRICA | AH8: TERMOELÉCTRICA | AI8: HIDROELÉCTRICA | AJ8: HIDROELÉCTRICA | AK8: TERMOELÉCTRICA | AL8: TERMOELÉCTRICA | AM8: TERMOELÉCTRICA | AN8: HIDROELÉCTRICA | AO8: HIDROELÉCTRICA | AP8: HIDROELÉCTRICA | AQ8: HIDROELÉCTRICA | AR8: HIDROELÉCTRICA | AS8: HIDROELÉCTRICA | AT8: HIDROELÉCTRICA | AU8: HIDROELÉCTRICA | AV8: TERMOELÉCTRICA | AW8: TERMOELÉCTRICA | AX8: TERMOELÉCTRICA | AY8: HIDROELÉCTRICA | AZ8: HIDROELÉCTRICA | BA8: HIDROELÉCTRICA | BB8: HIDROELÉCTRICA | BC8: HIDROELÉCTRICA | BD8: HIDROELÉCTRICA | BE8: HIDROELÉCTRICA | BF8: HIDROELÉCTRICA | BG8: HIDROELÉCTRICA | BH8: HIDROELÉCTRICA | BI8: HIDROELÉCTRICA | BJ8: TERMOELÉCTRICA | BK8: TERMOELÉCTRICA | BL8: TERMOELÉCTRICA | BM8: TERMOELÉCTRICA | BN8: TERMOELÉCTRICA | BO8: TERMOELÉCTRICA | BP8: HIDROELÉCTRICA | BQ8: TERMOELÉCTRICA | BR8: TERMOELÉCTRICA | BS8: TERMOELÉCTRICA | BT8: TERMOELÉCTRICA | BU8: TERMOELÉCTRICA | BV8: TERMOELÉCTRICA | BW8: TERMOELÉCTRICA | BX8: TERMOELÉCTRICA | BY8: TERMOELÉCTRICA | BZ8: HIDROELÉCTRICA | CA8: TERMOELÉCTRICA | CB8: TERMOELÉCTRICA | CC8: HIDROELÉCTRICA | CD8: HIDROELÉCTRICA | CE8: HIDROELÉCTRICA | CF8: HIDROELÉCTRICA | CG8: HIDROELÉCTRICA | CH8: HIDROELÉCTRICA | CI8: TERMOELÉCTRICA | CJ8: TERMOELÉCTRICA | CK8: TERMOELÉCTRICA | CL8: TERMOELÉCTRICA | CM8: TERMOELÉCTRICA | CN8: TERMOELÉCTRICA | CO8: TERMOELÉCTRICA | CP8: TERMOELÉCTRICA | CQ8: TERMOELÉCTRICA | CR8: TERMOELÉCTRICA | CS8: TERMOELÉCTRICA | CT8: TERMOELÉCTRICA | CU8: TERMOELÉCTRICA | CV8: SOLAR | CW8: EÓLICA | CX8: SOLAR | CY8: EÓLICA | CZ8: SOLAR | DA8: HIDROELÉCTRICA | DB8: HIDROELÉCTRICA | DC8: HIDROELÉCTRICA | DD8: HIDROELÉCTRICA | DE8: SOLAR | DF8: HIDROELÉCTRICA | DG8: HIDROELÉCTRICA | DH8: HIDROELÉCTRICA | DI8: HIDROELÉCTRICA | DJ8: HIDROELÉCTRICA | DK8: HIDROELÉCTRICA | DL8: HIDROELÉCTRICA | DM8: HIDROELÉCTRICA | DN8: SOLAR | DO8: SOLAR | DP8: EÓLICA | DQ8: EÓLICA | DR8: SOLAR | DS8: HIDROELÉCTRICA | DT8: HIDROELÉCTRICA | DU8: HIDROELÉCTRICA | DV8: HIDROELÉCTRICA | DW8: HIDROELÉCTRICA | DX8: HIDROELÉCTRICA | DY8: HIDROELÉCTRICA | DZ8: HIDROELÉCTRICA | EA8: HIDROELÉCTRICA | EB8: EÓLICA | EC8: EÓLICA | ED8: SOLAR | EE8: EÓLICA | EF8: EÓLICA | EG8: EÓLICA | EH8: EÓLICA | EI8: HIDROELÉCTRICA | EJ8: HIDROELÉCTRICA | EK8: HIDROELÉCTRICA | EL8: HIDROELÉCTRICA | EM8: HIDROELÉCTRICA | EN8: HIDROELÉCTRICA | EO8: EÓLICA | EP8: SOLAR | EQ8: SOLAR | ER8: SOLAR | ES8: HIDROELÉCTRICA | ET8: EÓLICA | EU8: EÓLICA | EV8: SOLAR | EW8: TERMOELÉCTRICA | EX8: TERMOELÉCTRICA | EY8: TERMOELÉCTRICA | EZ8: TERMOELÉCTRICA | FA8: SOLAR | FB8: HIDROELÉCTRICA | FC8: HIDROELÉCTRICA | FD8: TERMOELÉCTRICA | FE8: TERMOELÉCTRICA | FF8: TERMOELÉCTRICA | FG8: TERMOELÉCTRICA | FH8: TERMOELÉCTRICA | FI8: TERMOELÉCTRICA | FJ8: TERMOELÉCTRICA | FM8: HIDROELÉCTRICA | FN8: HIDROELÉCTRICA | FO8: HIDROELÉCTRICA | FP8: HIDROELÉCTRICA | FQ8: TERMOELÉCTRICA | FR8: TERMOELÉCTRICA | FS8: HIDROELÉCTRICA | FT8: HIDROELÉCTRICA
C9: HYDRO GLOBAL PERÚ S.A.C. | D9: ELECTROPERU | E9: ELECTROPERU | F9: ELECTROPERU | G9: ELECTROPERU | H9: ORAZUL ENERGY PERÚ | I9: ORAZUL ENERGY PERÚ | J9: TERMOSELVA | K9: TERMOSELVA | L9: KALLPA GENERACION S.A. | M9: KALLPA GENERACION S.A. | N9: KALLPA GENERACION S.A. | O9: KALLPA GENERACION S.A. | P9: KALLPA GENERACION S.A. | Q9: KALLPA GENERACION S.A. | R9: KALLPA GENERACION S.A. | S9: KALLPA GENERACION S.A. | T9: SHOUGESA | U9: SHOUGESA | V9: SHOUGESA | W9: SHOUGESA | X9: EGEMSA | Y9: EGESUR | Z9: EGESUR | AA9: EGESUR | AB9: EGASA | AC9: EGASA | AD9: EGASA | AE9: EGASA | AF9: EGASA | AG9: EGASA | AH9: EGASA | AI9: SAN GABAN | AJ9: CELEPSA | AK9: MINERA CERRO VERDE | AL9: PLANTA DE RESERVA FRIA DE GENERACION DE ETEN S.A. | AM9: PLANTA DE RESERVA FRIA DE GENERACION DE ETEN S.A. | AN9: EMPRESA DE GENERACION HUALLAGA | AO9: EMPRESA DE GENERACION HUALLAGA | AP9: LA VIRGEN | AQ9: CHINANGO S.A.C. | AR9: CHINANGO S.A.C. | AS9: HIDROELECTRICA HUANCHOR S.A.C. | AT9: CELEPSA RENOVABLES S.R.L. | AU9: INLAND ENERGY SAC | AV9: FENIX POWER PERÚ | AW9: FENIX POWER PERÚ | AX9: FENIX POWER PERÚ | AY9: STATKRAFT S.A | AZ9: STATKRAFT S.A | BA9: STATKRAFT S.A | BB9: STATKRAFT S.A | BC9: STATKRAFT S.A | BD9: STATKRAFT S.A | BE9: STATKRAFT S.A | BF9: STATKRAFT S.A | BG9: CENTRALES SANTA ROSA S.A.C. | BH9: CENTRALES SANTA ROSA S.A.C. | BI9: EMPRESA DE GENERACION HUANZA | BJ9: ENEL GENERACION PIURA S.A. | BK9: ENEL GENERACION PIURA S.A. | BL9: ENEL GENERACION PIURA S.A. | BM9: ENGIE ENERGIA PERU S.A.A. | BN9: ENGIE ENERGIA PERU S.A.A. | BO9: ENGIE ENERGIA PERU S.A.A. | BP9: ENGIE ENERGIA PERU S.A.A. | BQ9: ENGIE ENERGIA PERU S.A.A. | BR9: ENGIE ENERGIA PERU S.A.A. | BS9: ENGIE ENERGIA PERU S.A.A. | BT9: ENGIE ENERGIA PERU S.A.A. | BU9: ENGIE ENERGIA PERU S.A.A. | BV9: ENGIE ENERGIA PERU S.A.A. | BW9: ENGIE ENERGIA PERU S.A.A. | BX9: ENGIE ENERGIA PERU S.A.A. | BY9: ENGIE ENERGIA PERU S.A.A. | BZ9: ENGIE ENERGIA PERU S.A.A. | CA9: INFRAESTRUCTURAS Y ENERGIAS DEL PERU S.A.C. | CB9: INFRAESTRUCTURAS Y ENERGIAS DEL PERU S.A.C. | CC9: INVERSIONES SHAQSHA S.A.C. | CD9: ORYGEN PERU S.A.A. | CE9: ORYGEN PERU S.A.A. | CF9: ORYGEN PERU S.A.A. | CG9: ORYGEN PERU S.A.A. | CH9: ORYGEN PERU S.A.A. | CI9: ORYGEN PERU S.A.A. | CJ9: ORYGEN PERU S.A.A. | CK9: ORYGEN PERU S.A.A. | CL9: ORYGEN PERU S.A.A. | CM9: ORYGEN PERU S.A.A. | CN9: ORYGEN PERU S.A.A. | CO9: ORYGEN PERU S.A.A. | CP9: SAMAY I S.A.C | CQ9: SAMAY I S.A.C | CR9: SAMAY I S.A.C | CS9: SAMAY I S.A.C | CT9: TERMOCHILCA S.A.C. | CU9: TERMOCHILCA S.A.C. | CV9: COLCA SOLAR S.A.C. | CW9: ENERGIA RENOVABLE DEL SUR S.A. | CX9: GR CORTARRAMA SOCIEDAD ANONIMA CERRADA | CY9: GR TARUCA SOCIEDAD ANONIMA CERRADA | CZ9: KONDU SAC | DA9: PERUANA DE INVERSIONES EN ENERGIAS RENOVABLES S.A. | DB9: VARI ENERGIA S.A.C. | DC9: ORAZUL ENERGY PERÚ | DD9: ORAZUL ENERGY PERÚ | DE9: KALLPA GENERACION S.A. | DF9: SAN GABAN | DG9: MAJA ENERGIA S.A.C. | DH9: EMPRESA DE GENERACION ELECTRICA CANCHAYLLO SAC | DI9: EMPRESA DE GENERACION ELECTRICA SANTA ANA S.A.C. | DJ9: EMPRESA ELECTRICA AGUA AZUL | DK9: EMPRESA ELECTRICA RIO DOBLE | DL9: HIDROCAÑETE S.A. | DM9: HUAURA POWER GROUP S.A. | DN9: MOQUEGUA FV S.A.C. | DO9: PANAMERICANA SOLAR SAC. | DP9: PARQUE EOLICO MARCONA S.A.C. | DQ9: PARQUE EOLICO TRES HERMANAS S.A.C. | DR9: TACNA SOLAR SAC. | DS9: ELECTRICA YANAPAMPA SAC | DT9: ANDEAN POWER S.A.C. | DU9: ASOCIACIÓN SANTA LUCIA DE CHACAS | DV9: ATRIA ENERGIA S.A.C. | DW9: EGEJUNIN | DX9: EGEJUNIN | DY9: EGEJUNIN | DZ9: EGEJUNIN | EA9: EMPRESA DE GENERACION ELECTRICA RIO BAÑOS S.A.C. | EB9: ENERGÍA EÓLICA S.A. | EC9: ENERGÍA EÓLICA S.A. | ED9: ENGIE ENERGIA PERU S.A.A. | EE9: ENGIE ENERGIA PERU S.A.A. | EF9: ENGIE ENERGIA PERU S.A.A. | EG9: ENGIE ENERGIA PERU S.A.A. | EH9: ENGIE ENERGIA PERU S.A.A. | EI9: GENERACIÓN ANDINA S.A.C. | EJ9: GENERACIÓN ANDINA S.A.C. | EK9: GENERADORA DE ENERGÍA DEL PERÚ | EL9: GENERADORA DE ENERGÍA DEL PERÚ | EM9: GENERADORA DE ENERGÍA DEL PERÚ | EN9: GENERADORA DE ENERGÍA DEL PERÚ | EO9: GR PAINO SOCIEDAD ANONIMA CERRADA | EP9: JOYA SOLAR S.A.C. | EQ9: MAJES ARCUS S.A.C. | ER9: ORYGEN PERU S.A.A. | ES9: ORYGEN PERU S.A.A. | ET9: ORYGEN PERU S.A.A. | EU9: ORYGEN PERU S.A.A. | EV9: ORYGEN PERU S.A.A. | EW9: PETRAMAS | EX9: PETRAMAS | EY9: PETRAMAS | EZ9: PETRAMAS | FA9: REPARTICIÓN ARCUS S.A.C. | FB9: SINERSA | FC9: SINERSA | FD9: BIOENERGIA DEL CHIRA S.A. | FE9: GM OPERACIONES S.A.C. | FF9: GM OPERACIONES S.A.C. | FG9: AGRO INDUSTRIAL PARAMONGA S.A. | FH9: AGROAURORA S.A.C. | FI9: AGROINDUSTRIAS SAN JACINTO S.A.A. | FJ9: AGROLMOS SOCIEDAD ANONIMA - AGROLMOS S.A. | FM9: UNACEM PERU S.A. | FN9: ELECTRO ORIENTE | FO9: AGUAS Y ENERGIA PERU | FP9: ELECTRO ZAÑA S.A.C. | FQ9: ELECTRONOROESTE S.A. | FR9: SDE PIURA | FS9: SINERSA | FT9: SINERSA
C10: SAN GABAN III | D10: MANTARO | E10: RESTITUCION | F10: TUMBES MAK 1 | G10: TUMBES MAK 2 | H10: CARHUAQUERO | I10: CAÑON DEL PATO | J10: AGUAYTIA TG1 | K10: AGUAYTIA TG2 | L10: KALLPA TG1 | M10: KALLPA TG2 | N10: KALLPA TG3 | O10: KALLPA TV | P10: LFLORES TG1 | Q10: LFLORES TV | R10: CERRO DEL AGUILA | S10: CERRODELAGUILAG4 | T10: SHOUGESA TV1 | U10: SHOUGESA TV2 | V10: SHOUGESA TV3 | W10: SHOUGESA CUMMINS | X10: MACHUPICCHU | Y10: ARICOTA 1 | Z10: ARICOTA 2 | AA10: INDEPENDENCIA | AB10: CHARCANI I,II,III | AC10: CHARCANI IV | AD10: CHARCANI V | AE10: CHARCANI VI | AF10: CHILINA TG | AG10: MOLLENDO 1, 2, 3 | AH10: CHILINA (SULZ 1,2) | AI10: SAN GABAN II | AJ10: PLATANAL | AK10: RECKA | AL10: RF ETEN TG1 | AM10: RF ETEN TG2 | AN10: CHAGLLA GP1 | AO10: CHAGLLA | AP10: LA VIRGEN | AQ10: CHIMAY | AR10: YANANGO | AS10: HUANCHOR | AT10: MARAÑON | AU10: STA TERESA | AV10: FENIX GT11 | AW10: FENIX GT12 | AX10: FENIX TV10 | AY10: YAUPI | AZ10: OROYA | BA10: PACHACHACA | BB10: MALPASO | BC10: CAHUA | BD10: ARCATA | BE10: GALLITO CIEGO | BF10: CHEVES | BG10: SANTA ROSA 1 | BH10: SANTA ROSA 2 | BI10: HUANZA | BJ10: MALACAS2 TG4 | BK10: MALACAS3 TG 5 | BL10: MALACAS1 TG6 | BM10: RF ILO2 TG1 | BN10: RF ILO2 TG2 | BO10: RF ILO2 TG3 | BP10: YUNCAN | BQ10: CHILCA1 TG1 | BR10: CHILCA1 TG2 | BS10: CHILCA1 TG3 | BT10: CHILCA-TV | BU10: CHILCA2 TG41 | BV10: CHILCA2-TV | BW10: CTNEPI_TG41 | BX10: CTNEPI_TG42 | BY10: CTNEPI_TG43 | BZ10: QUITARACSA | CA10: RF PTO MALDONADO | CB10: RF PUCALLPA | CC10: PARIAC | CD10: HUINCO | CE10: MATUCANA | CF10: MOYOPAMPA | CG10: CALLAHUANCA | CH10: HUAMPANI | CI10: STA ROSA WEST TG7 | CJ10: UTI_5 | CK10: UTI_6 | CL10: VENTANILLA 3 | CM10: VENTANILLA 4 | CN10: VENTANILLA TV | CO10: STAROSA TG8 | CP10: PTO_BRVO TG1 | CQ10: PTO_BRVO TG2 | CR10: PTO_BRVO TG3 | CS10: PTO_BRVO TG4 | CT10: OLLEROS TG1 | CU10: OLLEROS TV | CV10: CS YARUCAYA | CW10: SAN JUAN | CX10: MATARANI | CY10: DUNA | CZ10: CARHUAQUERO (CS) | DA10: MANTA I | DB10: ANASHIRONI | DC10: CARHUAQUERO4 | DD10: CAÑA BRAVA | DE10: SUNNY | DF10: TUPURI | DG10: RONCADOR | DH10: CANCHAYLLO | DI10: RENOVANDESH1 | DJ10: POTRERO | DK10: PIZARRAS | DL10: NIMPERIAL | DM10: YARUCAYA | DN10: MOQUEGUA-SOLAR | DO10: PANAMERICANA-SOLAR | DP10: PQE-EOLICO-MARCONA | DQ10: PQE-EOLICO-3-HERMANAS | DR10: TACNA-SOLAR | DS10: YANAPAMPA | DT10: CARHUAC | DU10: HUALLIN | DV10: PURMACANA | DW10: HUASAHUASI | DX10: STACRUZ_1_2 | DY10: RUNATULLO_II | DZ10: RUNATULLO_III | EA10: RUCUY | EB10: PQE-EOLICO-TALARA | EC10: PQE-EOLICO-CUPISNIQUE | ED10: INTIPAMPA | EE10: PUNTA LOMITAS-BL1 | EF10: PUNTA LOMITAS-BL2 | EG10: PUN LOMITAS_EXP-BL1 | EH10: PUN LOMITAS_EXP-BL2 | EI10: 8AGOSTO | EJ10: EL CARMEN | EK10: LA JOYA | EL10: ANGEL_I | EM10: ANGEL_II | EN10: ANGEL_III | EO10: HUAMBOS | EP10: SAN MARTIN SOLAR | EQ10: MAJES | ER10: RUBI | ES10: CH_HER1 | ET10: WAYRA-I | EU10: WAYRA EXTENSION | EV10: CLEMESI | EW10: HUAYCOLORO | EX10: CALLAO | EY10: DONA_CATALINA | EZ10: LAGRINGAV | FA10: REPARTICION | FB10: POECHOS2 | FC10: CHANCAY | FD10: CANA BRAVA | FE10: REFINERIA TALARA TV1 | FF10: REFINERÍA TALARA TV2 | FG10: PARAMONGA | FH10: MAPLE | FI10: SAN_JACINTO | FJ10: AGROLMOS | FK10: MW | FM10: CARPAPATA | FN10: CENTRALES ELOR | FO10: PIAS1 | FP10: ZANA | FQ10: TABLAZO | FR10: TALLANCA | FS10: CURUMUY | FT10: POECHOS1 | FU10: MW
A11: 05/11/2025 | B11: 00:30 | C11: 200.5 | D11: 619.1 | E11: 212.5 | H11: 90.9 | I11: 190 | L11: 133 | M11: 133.2 | N11: 133.1 | O11: 233.5 | P11: 0 | R11: 346.8 | S11: 5.5 | X11: 147 | Y11: 7.1 | Z11: 5.7 | AA11: 5.7 | AB11: 6.9 | AC11: 14.4 | AD11: 89.4 | AI11: 109.6 | AJ11: 51.2 | AN11: 6.4 | AO11: 145.8 | AP11: 53 | AQ11: 118.2 | AR11: 26.8 | AS11: 18.4 | AT11: 18.8 | AU11: 79.3 | AY11: 107.6 | AZ11: 7.4 | BA11: 6 | BB11: 25 | BC11: 42.5 | BD11: 2 | BE11: 11.7 | BF11: 64.8 | BI11: 66.7 | BL11: 0 | BP11: 82.7 | BQ11: 153.5 | BR11: 153.2 | BS11: 153.5 | BT11: 239.6 | CC11: 4 | CD11: 151 | CE11: 61.8 | CF11: 62.5 | CG11: 46.8 | CH11: 28.4 | CL11: 146 | CM11: 147.8 | CN11: 148.6 | CT11: 216.3 | CU11: 103.7 | CV11: 0 | CW11: 85.3 | CX11: 0 | CY11: 0 | CZ11: 0 | DA11: 20 | DB11: 20.2 | DF11: 1 | DG11: 3.3 | DH11: 3 | DJ11: 18.4 | DK11: 19 | DL11: 3.5 | DM11: 18.6 | DN11: 0 | DO11: 0 | DP11: 30.4 | DQ11: 84.3 | DR11: 0 | DS11: 3.1 | DT11: 18.4 | DU11: 2.7 | DW11: 10.4 | DX11: 9.3 | DY11: 10.4 | DZ11: 13.7 | EA11: 15.5 | EB11: 11.4 | EC11: 61 | ED11: 0 | EE11: 52.4 | EF11: 84.9 | EG11: 4 | EH11: 2.8 | EI11: 20.9 | EJ11: 7.6 | EK11: 7.9 | EL11: 18.9 | EM11: 19.8 | EN11: 19.8 | EO11: 0 | EQ11: 0 | ER11: 0 | ES11: 0.6 | ET11: 12.4 | EU11: 14.4 | EV11: 0 | EW11: 1.1 | EY11: 1.8 | EZ11: 1 | FA11: 0 | FB11: 6.1 | FC11: 18.6 | FD11: 8.7 | FE11: 26.9 | FF11: 33.1 | FG11: 15 | FH11: 0 | FI11: 7.1 | FJ11: 11 | FK11: 6294.6 | FM11: 11.4614 | FN11: 7.96 | FO11: 6 | FP11: 13.2 | FQ11: 27.1 | FR11: 18.9 | FS11: 4.3 | FT11: 5.3 | FU11: 94.2214
A12: 05/11/2025 | B12: 01:00 | C12: 199 | D12: 625.6 | E12: 214.7 | H12: 87.9 | I12: 196.2 | L12: 119.8 | M12: 119.7 | N12: 119.4 | O12: 221.4 | P12: 0 | R12: 350.4 | S12: 5.6 | X12: 146.7 | Y12: 7.2 | Z12: 5.5 | AA12: 5.7 | AB12: 6.9 | AC12: 13.1 | AD12: 70 | AI12: 110.4 | AJ12: 51.1 | AN12: 6.4 | AO12: 148.4 | AP12: 52.2 | AQ12: 114.5 | AR12: 27.3 | AS12: 18.4 | AT12: 18.8 | AU12: 78.1 | AY12: 108.3 | AZ12: 7.5 | BA12: 6 | BB12: 24.1 | BC12: 43.1 | BD12: 2 | BE12: 11.7 | BF12: 67.2 | BI12: 65.6 | BL12: 0 | BP12: 83.6 | BQ12: 154.6 | BR12: 154.6 | BS12: 153.9 | BT12: 239.4 | CC12: 3.9 | CD12: 129.4 | CE12: 66.5 | CF12: 63.5 | CG12: 47.2 | CH12: 29.1 | CL12: 147.4 | CM12: 148.5 | CN12: 150.4 | CT12: 216.3 | CU12: 103.6 | CV12: 0 | CW12: 81.3 | CX12: 0 | CY12: 0.3 | CZ12: 0 | DA12: 20 | DB12: 20.6 | DF12: 1 | DG12: 3.3 | DH12: 2.8 | DJ12: 20 | DK12: 19 | DL12: 3.5 | DM12: 18.6 | DN12: 0 | DO12: 0 | DP12: 29.6 | DQ12: 79.6 | DR12: 0 | DS12: 3.1 | DT12: 16 | DU12: 2.7 | DW12: 10 | DX12: 9.3 | DY12: 10.4 | DZ12: 13.9 | EA12: 15.5 | EB12: 11.5 | EC12: 52.4 | ED12: 0 | EE12: 65.4 | EF12: 90 | EG12: 8.2 | EH12: 3.9 | EI12: 20.9 | EJ12: 7.5 | EK12: 8 | EL12: 18.5 | EM12: 19.8 | EN12: 19.8 | EO12: 0 | EQ12: 0 | ER12: 0 | ES12: 0.6 | ET12: 8 | EU12: 8.4 | EV12: 0 | EW12: 1.1 | EY12: 1.8 | EZ12: 1 | FA12: 0 | FB12: 6.2 | FC12: 18.6 | FD12: 8 | FE12: 26.5 | FF12: 33.2 | FG12: 15 | FH12: 0 | FI12: 7 | FJ12: 10.5 | FK12: 6220.1 | FM12: 11.47448 | FN12: 0.74 | FO12: 6 | FP12: 13.2 | FQ12: 27.1 | FR12: 18.9 | FS12: 4.4 | FT12: 5.3 | FU12: 87.11448
A13: 05/11/2025 | B13: 01:30 | C13: 203.5 | D13: 628.7 | E13: 213.6 | H13: 90.6 | I13: 198.1 | L13: 121.1 | M13: 122 | N13: 120.7 | O13: 219.9 | P13: 0 | R13: 352.6 | S13: 5.8 | X13: 148.4 | Y13: 7.6 | Z13: 5.7 | AA13: 5.6 | AB13: 6.9 | AC13: 11.5 | AD13: 70.5 | AI13: 110.6 | AJ13: 51.2 | AN13: 6.4 | AO13: 149.3 | AP13: 52 | AQ13: 126.3 | AR13: 27.2 | AS13: 18.4 | AT13: 18.8 | AU13: 80.8 | AY13: 108.3 | AZ13: 7.5 | BA13: 6.1 | BB13: 22.1 | BC13: 44.3 | BD13: 2 | BE13: 12 | BF13: 69.8 | BI13: 66.7 | BL13: 0 | BP13: 84.4 | BQ13: 137 | BR13: 137 | BS13: 136.8 | BT13: 221.1 | CC13: 4 | CD13: 152.4 | CE13: 66.1 | CF13: 64.3 | CG13: 47.4 | CH13: 29.6 | CL13: 147.2 | CM13: 148.4 | CN13: 150 | CT13: 215.9 | CU13: 103.4 | CV13: 0 | CW13: 78.8 | CX13: 0 | CY13: 0.7 | CZ13: 0 | DA13: 20 | DB13: 20.8 | DF13: 1 | DG13: 3.3 | DH13: 2.8 | DJ13: 19.8 | DK13: 18.9 | DL13: 3.5 | DM13: 18.6 | DN13: 0 | DO13: 0 | DP13: 25.6 | DQ13: 59.7 | DR13: 0 | DS13: 3.2 | DT13: 15.8 | DU13: 2.7 | DW13: 10 | DX13: 9.3 | DY13: 10.6 | DZ13: 14.2 | EA13: 15.5 | EB13: 16.2 | EC13: 53.5 | ED13: 0 | EE13: 57 | EF13: 73.8 | EG13: 4.5 | EH13: 1.1 | EI13: 20.9 | EJ13: 7.5 | EK13: 7.9 | EL13: 18.5 | EM13: 19.8 | EN13: 19.8 | EO13: 0 | EQ13: 0 | ER13: 0 | ES13: 0.6 | ET13: 2.7 | EU13: 1.5 | EV13: 0 | EW13: 1.1 | EY13: 1.8 | EZ13: 1 | FA13: 0 | FB13: 6.1 | FC13: 18.6 | FD13: 8.5 | FE13: 27.1 | FF13: 32 | FG13: 14.8 | FH13: 0 | FI13: 6.9 | FJ13: 10 | FK13: 6145.6 | FM13: 11.67608 | FN13: 0 | FO13: 6 | FP13: 13.2 | FQ13: 27.1 | FR13: 18.9 | FS13: 4.3 | FT13: 5.3 | FU13: 86.47608
A14: 05/11/2025 | B14: 02:00 | C14: 203.7 | D14: 627.7 | E14: 213.9 | H14: 90.1 | I14: 205 | L14: 129.7 | M14: 129.3 | N14: 130 | O14: 227.1 | P14: 0 | R14: 349.7 | S14: 5.7 | X14: 148.5 | Y14: 7.5 | Z14: 5.7 | AA14: 5.6 | AB14: 6.9 | AC14: 10 | AD14: 70.5 | AI14: 110.5 | AJ14: 51.5 | AN14: 6.4 | AO14: 148.5 | AP14: 52 | AQ14: 106.3 | AR14: 27.9 | AS14: 18.4 | AT14: 18.8 | AU14: 79.5 | AY14: 108.3 | AZ14: 7.5 | BA14: 6 | BB14: 22.8 | BC14: 44 | BD14: 2 | BE14: 12 | BF14: 68.4 | BI14: 66.6 | BL14: 0 | BP14: 84.3 | BQ14: 140.4 | BR14: 140.2 | BS14: 140.1 | BT14: 225.9 | CC14: 3.9 | CD14: 133.9 | CE14: 60.6 | CF14: 64 | CG14: 46.9 | CH14: 29.5 | CL14: 146.9 | CM14: 148.5 | CN14: 149.2 | CT14: 215.9 | CU14: 103.8 | CV14: 0 | CW14: 94.5 | CX14: 0 | CY14: 0 | CZ14: 0 | DA14: 20 | DB14: 20.7 | DF14: 1 | DG14: 3.2 | DH14: 2.8 | DJ14: 19.6 | DK14: 18.9 | DL14: 3.5 | DM14: 18.6 | DN14: 0 | DO14: 0 | DP14: 29.3 | DQ14: 47.9 | DR14: 0 | DS14: 3.2 | DT14: 15.9 | DU14: 2.8 | DW14: 10 | DX14: 9.2 | DY14: 10.6 | DZ14: 14.1 | EA14: 15.6 | EB14: 19.4 | EC14: 48.9 | ED14: 0 | EE14: 29.3 | EF14: 42.5 | EG14: 1.6 | EH14: 1.1 | EI14: 20.9 | EJ14: 7.5 | EK14: 7.9 | EL14: 18.5 | EM14: 19.8 | EN14: 19.8 | EO14: 0 | EQ14: 0 | ER14: 0 | ES14: 0.6 | ET14: 6.4 | EU14: 0.9 | EV14: 0 | EW14: 1.1 | EY14: 1.8 | EZ14: 1 | FA14: 0 | FB14: 6.1 | FC14: 18.7 | FD14: 9.3 | FE14: 27.4 | FF14: 31.9 | FG14: 15.4 | FH14: 0 | FI14: 7 | FJ14: 10 | FK14: 6094.2 | FM14: 11.67979 | FN14: 0 | FO14: 6 | FP14: 13.2 | FQ14: 27 | FR14: 18.9 | FS14: 4.2 | FT14: 5.4 | FU14: 86.37979
A15: 05/11/2025 | B15: 02:30 | C15: 203.2 | D15: 618.6 | E15: 213.4 | H15: 90.2 | I15: 209.2 | L15: 119.7 | M15: 119 | N15: 119 | O15: 227.5 | P15: 0 | R15: 339.2 | S15: 5.8 | X15: 144.7 | Y15: 7.2 | Z15: 5.9 | AA15: 5.7 | AB15: 6.9 | AC15: 12.3 | AD15: 69.5 | AI15: 110.5 | AJ15: 51.1 | AN15: 6.4 | AO15: 147.3 | AP15: 52.1 | AQ15: 30.7 | AR15: 28.8 | AS15: 18.2 | AT15: 18.8 | AU15: 80.7 | AY15: 107.8 | AZ15: 7.5 | BA15: 6 | BB15: 28.4 | BC15: 43.8 | BD15: 2 | BE15: 11.9 | BF15: 66.1 | BI15: 65.6 | BL15: 0 | BP15: 84 | BQ15: 139.4 | BR15: 139.2 | BS15: 139.1 | BT15: 225 | CC15: 3.9 | CD15: 122.3 | CE15: 65.3 | CF15: 63.6 | CG15: 46.8 | CH15: 29.8 | CL15: 146.3 | CM15: 147.8 | CN15: 148.6 | CT15: 215.9 | CU15: 103.6 | CV15: 0 | CW15: 103.8 | CX15: 0 | CY15: 0 | CZ15: 0 | DA15: 20 | DB15: 20.7 | DF15: 1 | DG15: 3.3 | DH15: 2.8 | DJ15: 20 | DK15: 18.9 | DL15: 3.5 | DM15: 18.6 | DN15: 0 | DO15: 0 | DP15: 29.8 | DQ15: 64.3 | DR15: 0 | DS15: 3.2 | DT15: 15.9 | DU15: 2.9 | DW15: 10 | DX15: 9.2 | DY15: 10.1 | DZ15: 13.7 | EA15: 15.7 | EB15: 20.5 | EC15: 44.4 | ED15: 0 | EE15: 19.9 | EF15: 28.2 | EG15: 1 | EH15: 0.8 | EI15: 20.9 | EJ15: 7.5 | EK15: 7.9 | EL15: 18.5 | EM15: 19.3 | EN15: 19.8 | EO15: 0 | EQ15: 0 | ER15: 0 | ES15: 0.6 | ET15: 0.3 | EU15: 0.1 | EV15: 0 | EW15: 1.1 | EY15: 1.8 | EZ15: 1 | FA15: 0 | FB15: 6.1 | FC15: 18.7 | FD15: 9.2 | FE15: 27.3 | FF15: 32.2 | FG15: 15.2 | FH15: 0 | FI15: 7.7 | FJ15: 10 | FK15: 5948.7 | FM15: 11.67687 | FN15: 0 | FO15: 6 | FP15: 13.2 | FQ15: 27 | FR15: 18.9 | FS15: 4.2 | FT15: 5.3 | FU15: 86.27687
A16: 05/11/2025 | B16: 03:00 | C16: 199.4 | D16: 613.6 | E16: 213.5 | H16: 89.3 | I16: 207.8 | L16: 128.6 | M16: 128 | N16: 128.5 | O16: 232 | P16: 0 | R16: 288.5 | S16: 5.6 | X16: 138.5 | Y16: 6.7 | Z16: 5.8 | AA16: 5.6 | AB16: 6.9 | AC16: 12.3 | AD16: 69.3 | AI16: 109.1 | AJ16: 51.2 | AN16: 6.4 | AO16: 145.8 | AP16: 52.3 | AQ16: 29.7 | AR16: 26.6 | AS16: 18.4 | AT16: 18.8 | AU16: 78.3 | AY16: 106 | AZ16: 7.5 | BA16: 6 | BB16: 26.8 | BC16: 42.9 | BD16: 2 | BE16: 11.5 | BF16: 63 | BI16: 64.2 | BL16: 0 | BP16: 83.2 | BQ16: 136.9 | BR16: 137 | BS16: 137.9 | BT16: 224.6 | CC16: 3.9 | CD16: 153.1 | CE16: 70 | CF16: 62.4 | CG16: 46.5 | CH16: 29.3 | CL16: 146 | CM16: 147.3 | CN16: 148.1 | CT16: 216.2 | CU16: 103.6 | CV16: 0 | CW16: 98.2 | CX16: 0 | CY16: 0 | CZ16: 0 | DA16: 20 | DB16: 20.4 | DF16: 1 | DG16: 3.3 | DH16: 2.9 | DJ16: 19.5 | DK16: 18.9 | DL16: 3.5 | DM16: 18.6 | DN16: 0 | DO16: 0 | DP16: 27.1 | DQ16: 70.7 | DR16: 0 | DS16: 3.2 | DT16: 15.8 | DU16: 3 | DW16: 10 | DX16: 9.2 | DY16: 9.8 | DZ16: 13.5 | EA16: 15.7 | EB16: 19.7 | EC16: 41.7 | ED16: 0 | EE16: 25.9 | EF16: 46.6 | EG16: 1.3 | EH16: 1.4 | EI16: 20.9 | EJ16: 7.5 | EK16: 8.3 | EL16: 18.5 | EM16: 19.3 | EN16: 19.3 | EO16: 0 | EQ16: 0 | ER16: 0 | ES16: 0.6 | ET16: 0 | EU16: 3.2 | EV16: 0 | EW16: 1.1 | EY16: 1.8 | EZ16: 1 | FA16: 0 | FB16: 6.1 | FC16: 18.8 | FD16: 9 | FE16: 26.6 | FF16: 32.2 | FG16: 15.5 | FH16: 0 | FI16: 7.1 | FJ16: 10.8 | FK16: 5940.9 | FM16: 11.68189 | FN16: 0 | FO16: 6 | FP16: 13.2 | FQ16: 27.1 | FR16: 18.9 | FS16: 4.1 | FT16: 5.4 | FU16: 86.38189
A17: 05/11/2025 | B17: 03:30 | C17: 204.6 | D17: 624.9 | E17: 214 | H17: 90.1 | I17: 210.5 | L17: 125.6 | M17: 126.1 | N17: 125.7 | O17: 225.9 | P17: 0 | R17: 360.4 | S17: 5.8 | X17: 145.8 | Y17: 7.4 | Z17: 6 | AA17: 5.6 | AB17: 6.9 | AC17: 12.3 | AD17: 70.3 | AI17: 110.5 | AJ17: 51.1 | AN17: 6.4 | AO17: 183 | AP17: 52.3 | AQ17: 66 | AR17: 27.7 | AS17: 18.4 | AT17: 18.8 | AU17: 79.9 | AY17: 108.2 | AZ17: 7.5 | BA17: 6 | BB17: 3.1 | BC17: 44 | BD17: 2 | BE17: 12 | BF17: 67.4 | BI17: 41.8 | BL17: 0 | BP17: 84.1 | BQ17: 120.5 | BR17: 120.6 | BS17: 121.2 | BT17: 208.9 | CC17: 3.9 | CD17: 159 | CE17: 69.9 | CF17: 64 | CG17: 47 | CH17: 29.9 | CL17: 146.7 | CM17: 148.3 | CN17: 149.4 | CT17: 215.7 | CU17: 103.5 | CV17: 0 | CW17: 96 | CX17: 0 | CY17: 0 | CZ17: 0 | DA17: 20.1 | DB17: 20.7 | DF17: 1 | DG17: 3.3 | DH17: 2.9 | DJ17: 20 | DK17: 18.9 | DL17: 3.5 | DM17: 18.6 | DN17: 0 | DO17: 0 | DP17: 23.5 | DQ17: 56 | DR17: 0 | DS17: 2.9 | DT17: 12.5 | DU17: 3 | DW17: 10.6 | DX17: 9.2 | DY17: 10.3 | DZ17: 14.1 | EA17: 15.7 | EB17: 14.3 | EC17: 32 | ED17: 0 | EE17: 39 | EF17: 57.4 | EG17: 2.5 | EH17: 0.6 | EI17: 20.9 | EJ17: 7.5 | EK17: 8.1 | EL17: 18.5 | EM17: 19.3 | EN17: 19.3 | EO17: 0 | EQ17: 0 | ER17: 0 | ES17: 0.6 | ET17: 0 | EU17: 4.2 | EV17: 0 | EW17: 1.1 | EY17: 1.8 | EZ17: 1 | FA17: 0 | FB17: 6.2 | FC17: 18.7 | FD17: 9.4 | FE17: 26.7 | FF17: 32.1 | FG17: 15.5 | FH17: 0 | FI17: 7.9 | FJ17: 11 | FK17: 6005 | FM17: 11.68257 | FN17: 0 | FO17: 6 | FP17: 13.2 | FQ17: 27.1 | FR17: 18.9 | FS17: 4.1 | FT17: 5.3 | FU17: 86.28257
A18: 05/11/2025 | B18: 04:00 | C18: 202 | D18: 626.2 | E18: 214.5 | H18: 89.5 | I18: 211.3 | L18: 121.8 | M18: 122.2 | N18: 122.4 | O18: 220.4 | P18: 0 | R18: 362.3 | S18: 5.8 | X18: 147.8 | Y18: 7.4 | Z18: 5.8 | AA18: 5.6 | AB18: 6.9 | AC18: 12.3 | AD18: 70.3 | AI18: 110.7 | AJ18: 51.5 | AN18: 6.4 | AO18: 184.8 | AP18: 52.2 | AQ18: 76.4 | AR18: 27.5 | AS18: 18.4 | AT18: 18.8 | AU18: 73.8 | AY18: 107.7 | AZ18: 7.5 | BA18: 6 | BB18: 2.9 | BC18: 43.8 | BD18: 2 | BE18: 11.9 | BF18: 67.5 | BI18: 41.6 | BL18: 0 | BP18: 84.1 | BQ18: 127.2 | BR18: 127.4 | BS18: 127.1 | BT18: 209.9 | CC18: 3.9 | CD18: 96.2 | CE18: 74.2 | CF18: 63.9 | CG18: 47 | CH18: 29.9 | CL18: 147 | CM18: 148.6 | CN18: 149.6 | CT18: 216 | CU18: 103.6 | CV18: 0 | CW18: 79.6 | CX18: 0 | CY18: 0 | CZ18: 0 | DA18: 20.2 | DB18: 20.7 | DF18: 1 | DG18: 3.3 | DH18: 2.8 | DJ18: 20 | DK18: 18.8 | DL18: 3.5 | DM18: 18.6 | DN18: 0 | DO18: 0 | DP18: 21.5 | DQ18: 51.9 | DR18: 0 | DS18: 3.1 | DT18: 9.9 | DU18: 2.9 | DW18: 10.6 | DX18: 9.2 | DY18: 10.4 | DZ18: 14 | EA18: 15.8 | EB18: 15.3 | EC18: 38.8 | ED18: 0 | EE18: 64.3 | EF18: 94.9 | EG18: 4.9 | EH18: 2.9 | EI18: 20.9 | EJ18: 7.5 | EK18: 8.1 | EL18: 18.5 | EM18: 19.3 | EN18: 19.3 | EO18: 0 | EQ18: 0 | ER18: 0 | ES18: 0.6 | ET18: 0 | EU18: 0 | EV18: 0 | EW18: 1.1 | EY18: 1.8 | EZ18: 1 | FA18: 0 | FB18: 6.1 | FC18: 18.7 | FD18: 9.2 | FE18: 27 | FF18: 31.8 | FG18: 15.5 | FH18: 0 | FI18: 6.7 | FJ18: 11 | FK18: 6004.5 | FM18: 11.68196 | FN18: 0 | FO18: 6 | FP18: 13.2 | FQ18: 27 | FR18: 18.9 | FS18: 4.1 | FT18: 5.4 | FU18: 86.28196
A19: 05/11/2025 | B19: 04:30 | C19: 205.7 | D19: 635.2 | E19: 216.3 | H19: 91 | I19: 213.2 | L19: 117.4 | M19: 117.6 | N19: 117.9 | O19: 216.6 | P19: 0 | R19: 371.5 | S19: 5.8 | X19: 148.5 | Y19: 8.2 | Z19: 5.9 | AA19: 5.7 | AB19: 6.9 | AC19: 12.4 | AD19: 71.6 | AI19: 110.4 | AJ19: 52.4 | AN19: 6.4 | AO19: 184.3 | AP19: 52.2 | AQ19: 77.5 | AR19: 28.7 | AS19: 18.6 | AT19: 18.8 | AU19: 72.9 | AY19: 111 | AZ19: 7.5 | BA19: 6.2 | BB19: 4.2 | BC19: 45.3 | BD19: 2 | BE19: 12.3 | BF19: 72.2 | BI19: 43.8 | BL19: 0 | BP19: 84.8 | BQ19: 125.5 | BR19: 125.4 | BS19: 124.2 | BT19: 210.8 | CC19: 3.7 | CD19: 112.5 | CE19: 101.9 | CF19: 65.2 | CG19: 47.1 | CH19: 30.6 | CL19: 147.3 | CM19: 148.6 | CN19: 149.8 | CT19: 216.2 | CU19: 103.5 | CV19: 0 | CW19: 96.6 | CX19: 0 | CY19: 0 | CZ19: 0 | DA19: 20.2 | DB19: 21 | DF19: 1 | DG19: 3.3 | DH19: 2.8 | DJ19: 20 | DK19: 18.9 | DL19: 3.5 | DM19: 18.6 | DN19: 0 | DO19: 0 | DP19: 26.2 | DQ19: 58.6 | DR19: 0 | DS19: 2.9 | DT19: 9.8 | DU19: 2.9 | DW19: 10.6 | DX19: 9.2 | DY19: 10.9 | DZ19: 14.4 | EA19: 15.6 | EB19: 18 | EC19: 39 | ED19: 0 | EE19: 63.3 | EF19: 96.7 | EG19: 5.3 | EH19: 1.9 | EI19: 20.9 | EJ19: 7.4 | EK19: 7.6 | EL19: 18.5 | EM19: 19.3 | EN19: 19.3 | EO19: 0 | EQ19: 0 | ER19: 0 | ES19: 0.6 | ET19: 0 | EU19: 0.3 | EV19: 0 | EW19: 1.1 | EY19: 1.8 | EZ19: 1 | FA19: 0 | FB19: 6.1 | FC19: 18.7 | FD19: 8.8 | FE19: 26.5 | FF19: 32 | FG19: 15 | FH19: 0 | FI19: 5.5 | FJ19: 11 | FK19: 6103.8 | FM19: 11.68548 | FN19: 0 | FO19: 6 | FP19: 13.2 | FQ19: 27.1 | FR19: 18.9 | FS19: 4.1 | FT19: 5.4 | FU19: 86.38548
A20: 05/11/2025 | B20: 05:00 | C20: 202.9 | D20: 625.7 | E20: 214.2 | H20: 90.2 | I20: 211 | L20: 126.2 | M20: 126.1 | N20: 125.9 | O20: 224.5 | P20: 0 | R20: 360.9 | S20: 5.8 | X20: 145.9 | Y20: 7.7 | Z20: 5.7 | AA20: 5.7 | AB20: 6.9 | AC20: 12.4 | AD20: 70.3 | AI20: 110.5 | AJ20: 50.8 | AN20: 6.4 | AO20: 183.3 | AP20: 52.3 | AQ20: 101.6 | AR20: 29.1 | AS20: 18.2 | AT20: 18.8 | AU20: 80.5 | AY20: 108.7 | AZ20: 7.5 | BA20: 6 | BB20: 3.2 | BC20: 44.3 | BD20: 2 | BE20: 12.2 | BF20: 68.9 | BI20: 42 | BL20: 0 | BP20: 84.2 | BQ20: 122 | BR20: 121.7 | BS20: 121.2 | BT20: 209.3 | CC20: 3.7 | CD20: 74.4 | CE20: 78.3 | CF20: 64 | CG20: 46.9 | CH20: 30.1 | CL20: 146.6 | CM20: 147.7 | CN20: 149.1 | CT20: 216 | CU20: 103.6 | CV20: 0 | CW20: 106.7 | CX20: 0 | CY20: 0 | CZ20: 0 | DA20: 20.1 | DB20: 20.7 | DF20: 1 | DG20: 3.3 | DH20: 2.9 | DJ20: 20 | DK20: 18.8 | DL20: 3.5 | DM20: 18.6 | DN20: 0.4 | DO20: 0.5 | DP20: 28.8 | DQ20: 68.4 | DR20: 0.1 | DS20: 3 | DT20: 10.4 | DU20: 2.9 | DW20: 10.6 | DX20: 9.2 | DY20: 10.4 | DZ20: 14 | EA20: 15.5 | EB20: 16.4 | EC20: 37.2 | ED20: 0 | EE20: 58.6 | EF20: 88.7 | EG20: 5.4 | EH20: 1.5 | EI20: 20.9 | EJ20: 7.4 | EK20: 7.7 | EL20: 18.5 | EM20: 19.3 | EN20: 19.3 | EO20: 0 | EQ20: 0 | ER20: 0 | ES20: 0.6 | ET20: 0 | EU20: 0 | EV20: 0.1 | EW20: 1.1 | EY20: 1.8 | EZ20: 1 | FA20: 0 | FB20: 6.1 | FC20: 18.6 | FD20: 9.2 | FE20: 25.7 | FF20: 31.9 | FG20: 14.8 | FH20: 0 | FI20: 5.3 | FJ20: 11 | FK20: 6051 | FM20: 11.677 | FN20: 0 | FO20: 6 | FP20: 13.2 | FQ20: 27.1 | FR20: 16.9 | FS20: 4.1 | FT20: 5.4 | FU20: 84.377
A21: 05/11/2025 | B21: 05:30 | C21: 202.9 | D21: 623.5 | E21: 213 | H21: 89.9 | I21: 210.8 | L21: 139 | M21: 138.6 | N21: 139 | O21: 235 | P21: 0 | R21: 360.4 | S21: 5.8 | X21: 147.3 | Y21: 7.3 | Z21: 5.7 | AA21: 5.6 | AB21: 6.9 | AC21: 11.9 | AD21: 70.4 | AI21: 110.3 | AJ21: 51.2 | AN21: 6.4 | AO21: 182.9 | AP21: 53 | AQ21: 142.8 | AR21: 28.4 | AS21: 18.6 | AT21: 18.8 | AU21: 78.5 | AY21: 107.8 | AZ21: 7.5 | BA21: 6.2 | BB21: 11.7 | BC21: 44.4 | BD21: 2 | BE21: 11.8 | BF21: 66.8 | BI21: 41.6 | BL21: 0 | BP21: 83.9 | BQ21: 130.5 | BR21: 130.4 | BS21: 130.4 | BT21: 217 | CC21: 3.7 | CD21: 108 | CE21: 88.9 | CF21: 63.7 | CG21: 46.9 | CH21: 29.9 | CL21: 146.4 | CM21: 147.8 | CN21: 148.4 | CT21: 215.9 | CU21: 103.6 | CV21: 0 | CW21: 106.2 | CX21: 3.9 | CY21: 0 | CZ21: 0 | DA21: 20 | DB21: 20.6 | DF21: 1 | DG21: 3.3 | DH21: 2.9 | DJ21: 20 | DK21: 18.8 | DL21: 3.5 | DM21: 18.6 | DN21: 2.5 | DO21: 3.2 | DP21: 29.5 | DQ21: 74.4 | DR21: 0.8 | DS21: 3 | DT21: 10.4 | DU21: 2.9 | DW21: 10.6 | DX21: 9.1 | DY21: 10.4 | DZ21: 13.9 | EA21: 15.4 | EB21: 15.2 | EC21: 22.3 | ED21: 1.7 | EE21: 72.8 | EF21: 81.2 | EG21: 9 | EH21: 3.6 | EI21: 20.9 | EJ21: 7.4 | EK21: 7.8 | EL21: 18 | EM21: 19.3 | EN21: 19.3 | EO21: 0 | EQ21: 0 | ER21: 8.7 | ES21: 0.6 | ET21: 0 | EU21: 0 | EV21: 7.9 | EW21: 1.1 | EY21: 1.8 | EZ21: 1 | FA21: 0 | FB21: 6.2 | FC21: 18.6 | FD21: 8.5 | FE21: 25.9 | FF21: 31.9 | FG21: 15.2 | FH21: 0 | FI21: 6.1 | FJ21: 11 | FK21: 6247 | FM21: 11.67519 | FN21: 0 | FO21: 6 | FP21: 13.2 | FQ21: 27.1 | FR21: 9.5 | FS21: 4.1 | FT21: 5.4 | FU21: 76.97519
A22: 05/11/2025 | B22: 06:00 | C22: 202.9 | D22: 621 | E22: 212.3 | H22: 89.7 | I22: 210.6 | L22: 112.6 | M22: 112.3 | N22: 112.7 | O22: 216.7 | P22: 0 | R22: 356.1 | S22: 5.7 | X22: 144.9 | Y22: 7.1 | Z22: 5.9 | AA22: 5.6 | AB22: 6.9 | AC22: 12 | AD22: 70 | AI22: 110.4 | AJ22: 51.1 | AN22: 6.4 | AO22: 227.9 | AP22: 52.9 | AQ22: 142.9 | AR22: 28.2 | AS22: 18.4 | AT22: 18.8 | AU22: 70.7 | AY22: 107.7 | AZ22: 7.5 | BA22: 6 | BB22: 11.6 | BC22: 44.8 | BD22: 2 | BE22: 11.7 | BF22: 66.1 | BI22: 40.8 | BL22: 0 | BP22: 83.9 | BQ22: 112.2 | BR22: 112.1 | BS22: 112.1 | BT22: 205 | CC22: 3.7 | CD22: 113.8 | CE22: 70.8 | CF22: 63.7 | CG22: 46.9 | CH22: 29.9 | CL22: 145.3 | CM22: 147 | CN22: 147.3 | CT22: 216.2 | CU22: 103.8 | CV22: 0 | CW22: 99.7 | CX22: 27.2 | CY22: 2.5 | CZ22: 0 | DA22: 20.1 | DB22: 0 | DF22: 0.9 | DG22: 3.3 | DH22: 2.8 | DJ22: 20 | DK22: 18.8 | DL22: 3.5 | DM22: 18.6 | DN22: 6.9 | DO22: 6.8 | DP22: 27.8 | DQ22: 73.2 | DR22: 0.8 | DS22: 3.1 | DT22: 10.3 | DU22: 2.9 | DW22: 10.6 | DX22: 9 | DY22: 10.2 | DZ22: 14 | EA22: 15.5 | EB22: 16.7 | EC22: 16.4 | ED22: 11.3 | EE22: 67.3 | EF22: 80 | EG22: 5.9 | EH22: 2.7 | EI22: 20.9 | EJ22: 7.4 | EK22: 7.9 | EL22: 18 | EM22: 19.3 | EN22: 19.3 | EO22: 1.2 | EQ22: 1.2 | ER22: 50.1 | ES22: 0.6 | ET22: 2.9 | EU22: 6.3 | EV22: 43.4 | EW22: 1.1 | EY22: 1.8 | EZ22: 1 | FA22: 0.9 | FB22: 6.1 | FC22: 18.6 | FD22: 9.2 | FE22: 25.6 | FF22: 31.6 | FG22: 15.3 | FH22: 0 | FI22: 5.1 | FJ22: 11 | FK22: 6179.2 | FM22: 11.67897 | FN22: 5.05 | FO22: 6 | FP22: 13.2 | FQ22: 27.2 | FR22: 9.5 | FS22: 4.1 | FT22: 5.3 | FU22: 82.02897
... A58: 06/11/2025 | B58: 00:00 | C58: 179.5 | D58: 629.2 | E58: 214 | H58: 30.1 | I58: 195 | L58: 128.3 | M58: 128.3 | N58: 127.9 | O58: 227 | P58: 104.6 | R58: 295.3 | S58: 5.7 | X58: 142.2 | Y58: 7.4 | Z58: 5.8 | AA58: 0 | AB58: 7.1 | AC58: 13.4 | AD58: 87.7 | AI58: 110.4 | AJ58: 60 | AN58: 6.4 | AO58: 0 | AP58: 45.8 | AQ58: 121 | AR58: 23.8 | AS58: 18.6 | AT58: 18.8 | AU58: 75.4 | AY58: 108.8 | AZ58: 7.5 | BA58: 5.8 | BB58: 35.1 | BC58: 44.5 | BD58: 2 | BE58: 32 | BF58: 69.3 | BI58: 57.4 | BL58: 42.9 | BP58: 114.9 | BQ58: 175.9 | BR58: 173.5 | BS58: 200 | BT58: 269.3 | CC58: 3.6 | CD58: 140.2 | CE58: 79.6 | CF58: 70.1 | CG58: 46.6 | CH58: 30 | CL58: 146.7 | CM58: 148.3 | CN58: 150 | CT58: 216 | CU58: 103.4 | CV58: 0 | CW58: 120.8 | CX58: 0 | CY58: 0.1 | CZ58: 0 | DA58: 0 | DB58: 20.7 | DF58: 0.8 | DG58: 3.5 | DH58: 2.7 | DJ58: 20 | DK58: 18.7 | DL58: 3.4 | DM58: 18.6 | DN58: 0 | DO58: 0 | DP58: 30.3 | DQ58: 88.6 | DR58: 0 | DS58: 3.5 | DT58: 13.5 | DU58: 2.6 | DW58: 9.5 | DX58: 9.7 | DY58: 9.8 | DZ58: 13 | EA58: 16.2 | EB58: 18.3 | EC58: 35 | ED58: 0 | EE58: 61.1 | EF58: 90.7 | EG58: 5.8 | EH58: 3.3 | EI58: 19.4 | EJ58: 6.8 | EK58: 8.2 | EL58: 16 | EM58: 17 | EN58: 16.7 | EO58: 0 | EQ58: 0 | ER58: 0 | ES58: 0.6 | ET58: 73.8 | EU58: 79.9 | EV58: 0 | EW58: 1.1 | EY58: 2.4 | EZ58: 1.1 | FA58: 0 | FB58: 6.2 | FC58: 18.8 | FD58: 8.2 | FE58: 26.3 | FF58: 32.8 | FG58: 15.3 | FH58: 20.2 | FI58: 7.1 | FJ58: 11 | FK58: 6491.2 | FM58: 10.85544 | FN58: 7.98 | FO58: 6.1 | FP58: 13.2 | FQ58: 27 | FR58: 9.5 | FS58: 4 | FT58: 7.9 | FU58: 86.53544
A59: EJEC | C59: 4031.8 | D59: 15037 | E59: 5148.9 | F59: 0 | G59: 0 | H59: 2084.45 | I59: 4845.7 | J59: 0 | K59: 0 | L59: 3643.05 | M59: 3705.2 | N59: 3704 | O59: 5965.65 | P59: 1372.75 | Q59: 0 | R59: 7573.55 | S59: 137.6 | T59: 0 | U59: 0 | V59: 0 | W59: 0 | X59: 3412.15 | Y59: 178.5 | Z59: 138.85 | AA59: 306.3 | AB59: 166.1 | AC59: 301.5 | AD59: 1900.55 | AE59: 0 | AF59: 0 | AG59: 0 | AH59: 0 | AI59: 2387.35 | AJ59: 2729.25 | AK59: 0 | AL59: 0 | AM59: 0 | AN59: 154.8 | AO59: 4789.45 | AP59: 1174.3 | AQ59: 2823.4 | AR59: 615.95 | AS59: 442.4 | AT59: 451.2 | AU59: 1823.05 | AV59: 0 | AW59: 0 | AX59: 0 | AY59: 2584.55 | AZ59: 179.95 | BA59: 144.45 | BB59: 554.85 | BC59: 1068.8 | BD59: 48 | BE59: 417.4 | BF59: 1626.3 | BG59: 0 | BH59: 0 | BI59: 1565.9 | BJ59: 0 | BK59: 0 | BL59: 678.7 | BM59: 0 | BN59: 0 | BO59: 0 | BP59: 2224.3 | BQ59: 3876.8 | BR59: 3841.7 | BS59: 4305.95 | BT59: 6067.85 | BU59: 0 | BV59: 0 | BW59: 0 | BX59: 0 | BY59: 0 | BZ59: 0 | CA59: 0 | CB59: 0 | CC59: 88.15 | CD59: 3362.45 | CE59: 2075.1 | CF59: 1532.5 | CG59: 1120.05 | CH59: 717.7 | CI59: 0 | CJ59: 0 | CK59: 0 | CL59: 3493.2 | CM59: 3524.1 | CN59: 3818.6 | CO59: 0 | CP59: 0 | CQ59: 0 | CR59: 0 | CS59: 0 | CT59: 5141.4 | CU59: 2461.9 | CV59: 5.65 | CW59: 2735.55 | CX59: 742.6 | CY59: 99.65 | CZ59: 2.4 | DA59: 293.65 | DB59: 426.05 | DC59: 0 | DD59: 0 | DE59: 0 | DF59: 21.75 | DG59: 73.85 | DH59: 67.45 | DI59: 0 | DJ59: 477.05 | DK59: 424.65 | DL59: 83.1 | DM59: 446.4 | DN59: 137.7 | DO59: 166.45 | DP59: 697.55 | DQ59: 1933.4 | DR59: 137.05 | DS59: 77.2 | DT59: 368.2 | DU59: 65.55 | DV59: 0 | DW59: 229.8 | DX59: 212.6 | DY59: 242.05 | DZ59: 336.55 | EA59: 369.15 | EB59: 399.3 | EC59: 1244.65 | ED59: 357.8 | EE59: 841.1 | EF59: 2079.4 | EG59: 75.05 | EH59: 143.3 | EI59: 493.6 | EJ59: 171.15 | EK59: 189.95 | EL59: 413.85 | EM59: 436.1 | EN59: 438.15 | EO59: 75.75 | EP59: 0 | EQ59: 118.35 | ER59: 1369.95 | ES59: 14.4 | ET59: 1682.6 | EU59: 1839.55 | EV59: 1021.45 | EW59: 26.4 | EX59: 0 | EY59: 45.4 | EZ59: 24 | FA59: 120.6 | FB59: 148.15 | FC59: 445.9 | FD59: 206 | FE59: 631.6 | FF59: 785.35 | FG59: 359.25 | FH59: 328.7 | FI59: 170.15 | FJ59: 261.9 | FK59: 165397.3 | FM59: 123.55436 | FN59: 146.865 | FO59: 145.8 | FP59: 316.8 | FQ59: 638.7 | FR59: 274 | FS59: 92.6 | FT59: 193.35 | FU59: 1931.6694

Sheet REACTIVA
B3: miércoles, 5 de Noviembre del 2025
A5: POTENCIA REACTIVA EJECUTADA DE LAS UNIDADES DE GENERACIÓN DEL COES (MVAR) | FM5: CENTRALES NO INTEGRANTES COES
A6: FECHA | B6: HORA | C6: 65333 | D6: 101 | E6: 102 | F6: 42667 | G6: 42668 | H6: 126 | I6: 127 | J6: 138 | K6: 139 | L6: 197 | M6: 203 | N6: 204 | O6: 230 | P6: 209 | Q6: 56677 | R6: 796 | S6: 2146 | T6: 142 | U6: 143 | V6: 125 | W6: 187 | X6: 163 | Y6: 298 | Z6: 299 | AA6: 219 | AB6: 151 | AC6: 152 | AD6: 153 | AE6: 154 | AF6: 756 | AG6: 156 | AH6: 155 | AI6: 182 | AJ6: 212 | AK6: 758 | AL6: 263 | AM6: 265 | AN6: 775 | AO6: 777 | AP6: 2154 | AQ6: 150 | AR6: 149 | AS6: 188 | AT6: 2131 | AU6: 755 | AV6: 252 | AW6: 249 | AX6: 250 | AY6: 117 | AZ6: 267 | BA6: 268 | BB6: 119 | BC6: 120 | BD6: 189 | BE6: 122 | BF6: 266 | BG6: 337 | BH6: 338 | BI6: 251 | BJ6: 115 | BK6: 239 | BL6: 288 | BM6: 240 | BN6: 241 | BO6: 242 | BP6: 191 | BQ6: 194 | BR6: 196 | BS6: 207 | BT6: 236 | BU6: 795 | BV6: 285 | BW6: 995 | BX6: 996 | BY6: 997 | BZ6: 766 | CA6: 926 | CB6: 924 | CC6: 121 | CD6: 103 | CE6: 104 | CF6: 106 | CG6: 105 | CH6: 107 | CI6: 110 | CJ6: 109 | CK6: 144 | CL6: 113 | CM6: 114 | CN6: 193 | CO6: 208 | CP6: 786 | CQ6: 787 | CR6: 788 | CS6: 789 | CT6: 248 | CU6: 2159 | CV6: 303 | CW6: 59715 | CX6: 62255 | CY6: 1263 | CZ6: 61800 | DA6: 2194 | DB6: 69125 | DC6: 216 | DD6: 198 | DE6: 70400 | DF6: 49607 | DG6: 214 | DH6: 260 | DI6: 2152 | DJ6: 2128 | DK6: 247 | DL6: 228 | DM6: 2135 | DN6: 261 | DO6: 237 | DP6: 253 | DQ6: 770 | DR6: 235 | DS6: 238 | DT6: 2184 | DU6: 61855 | DV6: 223 | DW6: 226 | DX6: 201 | DY6: 258 | DZ6: 259 | EA6: 920 | EB6: 257 | EC6: 256 | ED6: 2148 | EE6: 58288 | EF6: 58289 | EG6: 58839 | EH6: 58840 | EI6: 296 | EJ6: 297 | EK6: 211 | EL6: 2175 | EM6: 2178 | EN6: 2181 | EO6: 1262 | EP6: 63425 | EQ6: 233 | ER6: 2150 | ES6: 2165 | ET6: 2161 | EU6: 61197 | EV6: 58851 | EW6: 225 | EX6: 2201 | EY6: 2171 | EZ6: 760 | FA6: 234 | FB6: 215 | FC6: 917 | FD6: 289 | FE6: 58333 | FF6: 58336 | FG6: 213 | FH6: 232 | FI6: 2190 | FJ6: 69867 | FK6: TOTAL COES | FM6: 221 | FN6: 222 | FO6: 224 | FP6: 2187 | FQ6: 227 | FR6: 49400 | FS6: 199 | FT6: 200 | FU6: TOTAL NO COES
C7: SUR | D7: CENTRO | E7: CENTRO | F7: NORTE | G7: NORTE | H7: NORTE | I7: NORTE | J7: CENTRO | K7: CENTRO | L7: CENTRO | M7: CENTRO | N7: CENTRO | O7: CENTRO | P7: CENTRO | Q7: CENTRO | R7: CENTRO | S7: CENTRO | T7: CENTRO | U7: CENTRO | V7: CENTRO | W7: CENTRO | X7: SUR | Y7: SUR | Z7: SUR | AA7: CENTRO | AB7: SUR | AC7: SUR | AD7: SUR | AE7: SUR | AF7: SUR | AG7: SUR | AH7: SUR | AI7: SUR | AJ7: CENTRO | AK7: NORTE | AL7: NORTE | AM7: NORTE | AN7: CENTRO | AO7: CENTRO | AP7: CENTRO | AQ7: CENTRO | AR7: CENTRO | AS7: CENTRO | AT7: CENTRO | AU7: SUR | AV7: CENTRO | AW7: CENTRO | AX7: CENTRO | AY7: CENTRO | AZ7: CENTRO | BA7: CENTRO | BB7: CENTRO | BC7: CENTRO | BD7: SUR | BE7: NORTE | BF7: CENTRO | BG7: CENTRO | BH7: CENTRO | BI7: CENTRO | BJ7: NORTE | BK7: NORTE | BL7: NORTE | BM7: SUR | BN7: SUR | BO7: SUR | BP7: CENTRO | BQ7: CENTRO | BR7: CENTRO | BS7: CENTRO | BT7: CENTRO | BU7: CENTRO | BV7: CENTRO | BW7: SUR | BX7: SUR | BY7: SUR | BZ7: NORTE | CA7: SUR | CB7: CENTRO | CC7: NORTE | CD7: CENTRO | CE7: CENTRO | CF7: CENTRO | CG7: CENTRO | CH7: CENTRO | CI7: CENTRO | CJ7: CENTRO | CK7: CENTRO | CL7: CENTRO | CM7: CENTRO | CN7: CENTRO | CO7: CENTRO | CP7: SUR | CQ7: SUR | CR7: SUR | CS7: SUR | CT7: CENTRO | CU7: CENTRO | CV7: CENTRO | CW7: CENTRO | CX7: SUR | CY7: NORTE | CZ7: NORTE | DA7: NORTE | DB7: CENTRO | DC7: NORTE | DD7: NORTE | DE7: SUR | DF7: SUR | DG7: CENTRO | DH7: CENTRO | DI7: CENTRO | DJ7: NORTE | DK7: NORTE | DL7: CENTRO | DM7: CENTRO | DN7: SUR | DO7: SUR | DP7: CENTRO | DQ7: CENTRO | DR7: SUR | DS7: CENTRO | DT7: CENTRO | DU7: NORTE | DV7: CENTRO | DW7: CENTRO | DX7: NORTE | DY7: CENTRO | DZ7: CENTRO | EA7: CENTRO | EB7: NORTE | EC7: NORTE | ED7: SUR | EE7: CENTRO | EF7: CENTRO | EG7: CENTRO | EH7: CENTRO | EI7: CENTRO | EJ7: CENTRO | EK7: SUR | EL7: SUR | EM7: SUR | EN7: SUR | EO7: NORTE | EP7: SUR | EQ7: SUR | ER7: SUR | ES7: CENTRO | ET7: CENTRO | EU7: CENTRO | EV7: SUR | EW7: CENTRO | EX7: CENTRO | EY7: CENTRO | EZ7: CENTRO | FA7: SUR | FB7: NORTE | FC7: CENTRO | FD7: NORTE | FE7: NORTE | FF7: NORTE | FG7: CENTRO | FH7: NORTE | FI7: NORTE | FJ7: NORTE | FM7: NORTE | FN7: CENTRO | FO7: NORTE | FP7: NORTE | FQ7: NORTE | FR7: NORTE | FS7: NORTE | FT7: NORTE
C8: HIDROELÉCTRICA | D8: HIDROELÉCTRICA | E8: HIDROELÉCTRICA | F8: TERMOELÉCTRICA | G8: TERMOELÉCTRICA | H8: HIDROELÉCTRICA | I8: HIDROELÉCTRICA | J8: TERMOELÉCTRICA | K8: TERMOELÉCTRICA | L8: TERMOELÉCTRICA | M8: TERMOELÉCTRICA | N8: TERMOELÉCTRICA | O8: TERMOELÉCTRICA | P8: TERMOELÉCTRICA | Q8: TERMOELÉCTRICA | R8: HIDROELÉCTRICA | S8: HIDROELÉCTRICA | T8: TERMOELÉCTRICA | U8: TERMOELÉCTRICA | V8: TERMOELÉCTRICA | W8: TERMOELÉCTRICA | X8: HIDROELÉCTRICA | Y8: HIDROELÉCTRICA | Z8: HIDROELÉCTRICA | AA8: TERMOELÉCTRICA | AB8: HIDROELÉCTRICA | AC8: HIDROELÉCTRICA | AD8: HIDROELÉCTRICA | AE8: HIDROELÉCTRICA | AF8: TERMOELÉCTRICA | AG8: TERMOELÉCTRICA | AH8: TERMOELÉCTRICA | AI8: HIDROELÉCTRICA | AJ8: HIDROELÉCTRICA | AK8: TERMOELÉCTRICA | AL8: TERMOELÉCTRICA | AM8: TERMOELÉCTRICA | AN8: HIDROELÉCTRICA | AO8: HIDROELÉCTRICA | AP8: HIDROELÉCTRICA | AQ8: HIDROELÉCTRICA | AR8: HIDROELÉCTRICA | AS8: HIDROELÉCTRICA | AT8: HIDROELÉCTRICA | AU8: HIDROELÉCTRICA | AV8: TERMOELÉCTRICA | AW8: TERMOELÉCTRICA | AX8: TERMOELÉCTRICA | AY8: HIDROELÉCTRICA | AZ8: HIDROELÉCTRICA | BA8: HIDROELÉCTRICA | BB8: HIDROELÉCTRICA | BC8: HIDROELÉCTRICA | BD8: HIDROELÉCTRICA | BE8: HIDROELÉCTRICA | BF8: HIDROELÉCTRICA | BG8: HIDROELÉCTRICA | BH8: HIDROELÉCTRICA | BI8: HIDROELÉCTRICA | BJ8: TERMOELÉCTRICA | BK8: TERMOELÉCTRICA | BL8: TERMOELÉCTRICA | BM8: TERMOELÉCTRICA | BN8: TERMOELÉCTRICA | BO8: TERMOELÉCTRICA | BP8: HIDROELÉCTRICA | BQ8: TERMOELÉCTRICA | BR8: TERMOELÉCTRICA | BS8: TERMOELÉCTRICA | BT8: TERMOELÉCTRICA | BU8: TERMOELÉCTRICA | BV8: TERMOELÉCTRICA | BW8: TERMOELÉCTRICA | BX8: TERMOELÉCTRICA | BY8: TERMOELÉCTRICA | BZ8: HIDROELÉCTRICA | CA8: TERMOELÉCTRICA | CB8: TERMOELÉCTRICA | CC8: HIDROELÉCTRICA | CD8: HIDROELÉCTRICA | CE8: HIDROELÉCTRICA | CF8: HIDROELÉCTRICA | CG8: HIDROELÉCTRICA | CH8: HIDROELÉCTRICA | CI8: TERMOELÉCTRICA | CJ8: TERMOELÉCTRICA | CK8: TERMOELÉCTRICA | CL8: TERMOELÉCTRICA | CM8: TERMOELÉCTRICA | CN8: TERMOELÉCTRICA | CO8: TERMOELÉCTRICA | CP8: TERMOELÉCTRICA | CQ8: TERMOELÉCTRICA | CR8: TERMOELÉCTRICA | CS8: TERMOELÉCTRICA | CT8: TERMOELÉCTRICA | CU8: TERMOELÉCTRICA | CV8: SOLAR | CW8: EÓLICA | CX8: SOLAR | CY8: EÓLICA | CZ8: SOLAR | DA8: HIDROELÉCTRICA | DB8: HIDROELÉCTRICA | DC8: HIDROELÉCTRICA | DD8: HIDROELÉCTRICA | DE8: SOLAR | DF8: HIDROELÉCTRICA | DG8: HIDROELÉCTRICA | DH8: HIDROELÉCTRICA | DI8: HIDROELÉCTRICA | DJ8: HIDROELÉCTRICA | DK8: HIDROELÉCTRICA | DL8: HIDROELÉCTRICA | DM8: HIDROELÉCTRICA | DN8: SOLAR | DO8: SOLAR | DP8: EÓLICA | DQ8: EÓLICA | DR8: SOLAR | DS8: HIDROELÉCTRICA | DT8: HIDROELÉCTRICA | DU8: HIDROELÉCTRICA | DV8: HIDROELÉCTRICA | DW8: HIDROELÉCTRICA | DX8: HIDROELÉCTRICA | DY8: HIDROELÉCTRICA | DZ8: HIDROELÉCTRICA | EA8: HIDROELÉCTRICA | EB8: EÓLICA | EC8: EÓLICA | ED8: SOLAR | EE8: EÓLICA | EF8: EÓLICA | EG8: EÓLICA | EH8: EÓLICA | EI8: HIDROELÉCTRICA | EJ8: HIDROELÉCTRICA | EK8: HIDROELÉCTRICA | EL8: HIDROELÉCTRICA | EM8: HIDROELÉCTRICA | EN8: HIDROELÉCTRICA | EO8: EÓLICA | EP8: SOLAR | EQ8: SOLAR | ER8: SOLAR | ES8: HIDROELÉCTRICA | ET8: EÓLICA | EU8: EÓLICA | EV8: SOLAR | EW8: TERMOELÉCTRICA | EX8: TERMOELÉCTRICA | EY8: TERMOELÉCTRICA | EZ8: TERMOELÉCTRICA | FA8: SOLAR | FB8: HIDROELÉCTRICA | FC8: HIDROELÉCTRICA | FD8: TERMOELÉCTRICA | FE8: TERMOELÉCTRICA | FF8: TERMOELÉCTRICA | FG8: TERMOELÉCTRICA | FH8: TERMOELÉCTRICA | FI8: TERMOELÉCTRICA | FJ8: TERMOELÉCTRICA | FM8: HIDROELÉCTRICA | FN8: HIDROELÉCTRICA | FO8: HIDROELÉCTRICA | FP8: HIDROELÉCTRICA | FQ8: TERMOELÉCTRICA | FR8: TERMOELÉCTRICA | FS8: HIDROELÉCTRICA | FT8: HIDROELÉCTRICA
C9: HYDRO GLOBAL PERÚ S.A.C. | D9: ELECTROPERU | E9: ELECTROPERU | F9: ELECTROPERU | G9: ELECTROPERU | H9: ORAZUL ENERGY PERÚ | I9: ORAZUL ENERGY PERÚ | J9: TERMOSELVA | K9: TERMOSELVA | L9: KALLPA GENERACION S.A. | M9: KALLPA GENERACION S.A. | N9: KALLPA GENERACION S.A. | O9: KALLPA GENERACION S.A. | P9: KALLPA GENERACION S.A. | Q9: KALLPA GENERACION S.A. | R9: KALLPA GENERACION S.A. | S9: KALLPA GENERACION S.A. | T9: SHOUGESA | U9: SHOUGESA | V9: SHOUGESA | W9: SHOUGESA | X9: EGEMSA | Y9: EGESUR | Z9: EGESUR | AA9: EGESUR | AB9: EGASA | AC9: EGASA | AD9: EGASA | AE9: EGASA | AF9: EGASA | AG9: EGASA | AH9: EGASA | AI9: SAN GABAN | AJ9: CELEPSA | AK9: MINERA CERRO VERDE | AL9: PLANTA DE RESERVA FRIA DE GENERACION DE ETEN S.A. | AM9: PLANTA DE RESERVA FRIA DE GENERACION DE ETEN S.A. | AN9: EMPRESA DE GENERACION HUALLAGA | AO9: EMPRESA DE GENERACION HUALLAGA | AP9: LA VIRGEN | AQ9: CHINANGO S.A.C. | AR9: CHINANGO S.A.C. | AS9: HIDROELECTRICA HUANCHOR S.A.C. | AT9: CELEPSA RENOVABLES S.R.L. | AU9: INLAND ENERGY SAC | AV9: FENIX POWER PERÚ | AW9: FENIX POWER PERÚ | AX9: FENIX POWER PERÚ | AY9: STATKRAFT S.A | AZ9: STATKRAFT S.A | BA9: STATKRAFT S.A | BB9: STATKRAFT S.A | BC9: STATKRAFT S.A | BD9: STATKRAFT S.A | BE9: STATKRAFT S.A | BF9: STATKRAFT S.A | BG9: CENTRALES SANTA ROSA S.A.C. | BH9: CENTRALES SANTA ROSA S.A.C. | BI9: EMPRESA DE GENERACION HUANZA | BJ9: ENEL GENERACION PIURA S.A. | BK9: ENEL GENERACION PIURA S.A. | BL9: ENEL GENERACION PIURA S.A. | BM9: ENGIE ENERGIA PERU S.A.A. | BN9: ENGIE ENERGIA PERU S.A.A. | BO9: ENGIE ENERGIA PERU S.A.A. | BP9: ENGIE ENERGIA PERU S.A.A. | BQ9: ENGIE ENERGIA PERU S.A.A. | BR9: ENGIE ENERGIA PERU S.A.A. | BS9: ENGIE ENERGIA PERU S.A.A. | BT9: ENGIE ENERGIA PERU S.A.A. | BU9: ENGIE ENERGIA PERU S.A.A. | BV9: ENGIE ENERGIA PERU S.A.A. | BW9: ENGIE ENERGIA PERU S.A.A. | BX9: ENGIE ENERGIA PERU S.A.A. | BY9: ENGIE ENERGIA PERU S.A.A. | BZ9: ENGIE ENERGIA PERU S.A.A. | CA9: INFRAESTRUCTURAS Y ENERGIAS DEL PERU S.A.C. | CB9: INFRAESTRUCTURAS Y ENERGIAS DEL PERU S.A.C. | CC9: INVERSIONES SHAQSHA S.A.C. | CD9: ORYGEN PERU S.A.A. | CE9: ORYGEN PERU S.A.A. | CF9: ORYGEN PERU S.A.A. | CG9: ORYGEN PERU S.A.A. | CH9: ORYGEN PERU S.A.A. | CI9: ORYGEN PERU S.A.A. | CJ9: ORYGEN PERU S.A.A. | CK9: ORYGEN PERU S.A.A. | CL9: ORYGEN PERU S.A.A. | CM9: ORYGEN PERU S.A.A. | CN9: ORYGEN PERU S.A.A. | CO9: ORYGEN PERU S.A.A. | CP9: SAMAY I S.A.C | CQ9: SAMAY I S.A.C | CR9: SAMAY I S.A.C | CS9: SAMAY I S.A.C | CT9: TERMOCHILCA S.A.C. | CU9: TERMOCHILCA S.A.C. | CV9: COLCA SOLAR S.A.C. | CW9: ENERGIA RENOVABLE DEL SUR S.A. | CX9: GR CORTARRAMA SOCIEDAD ANONIMA CERRADA | CY9: GR TARUCA SOCIEDAD ANONIMA CERRADA | CZ9: KONDU SAC | DA9: PERUANA DE INVERSIONES EN ENERGIAS RENOVABLES S.A. | DB9: VARI ENERGIA S.A.C. | DC9: ORAZUL ENERGY PERÚ | DD9: ORAZUL ENERGY PERÚ | DE9: KALLPA GENERACION S.A. | DF9: SAN GABAN | DG9: MAJA ENERGIA S.A.C. | DH9: EMPRESA DE GENERACION ELECTRICA CANCHAYLLO SAC | DI9: EMPRESA DE GENERACION ELECTRICA SANTA ANA S.A.C. | DJ9: EMPRESA ELECTRICA AGUA AZUL | DK9: EMPRESA ELECTRICA RIO DOBLE | DL9: HIDROCAÑETE S.A. | DM9: HUAURA POWER GROUP S.A. | DN9: MOQUEGUA FV S.A.C. | DO9: PANAMERICANA SOLAR SAC. | DP9: PARQUE EOLICO MARCONA S.A.C. | DQ9: PARQUE EOLICO TRES HERMANAS S.A.C. | DR9: TACNA SOLAR SAC. | DS9: ELECTRICA YANAPAMPA SAC | DT9: ANDEAN POWER S.A.C. | DU9: ASOCIACIÓN SANTA LUCIA DE CHACAS | DV9: ATRIA ENERGIA S.A.C. | DW9: EGEJUNIN | DX9: EGEJUNIN | DY9: EGEJUNIN | DZ9: EGEJUNIN | EA9: EMPRESA DE GENERACION ELECTRICA RIO BAÑOS S.A.C. | EB9: ENERGÍA EÓLICA S.A. | EC9: ENERGÍA EÓLICA S.A. | ED9: ENGIE ENERGIA PERU S.A.A. | EE9: ENGIE ENERGIA PERU S.A.A. | EF9: ENGIE ENERGIA PERU S.A.A. | EG9: ENGIE ENERGIA PERU S.A.A. | EH9: ENGIE ENERGIA PERU S.A.A. | EI9: GENERACIÓN ANDINA S.A.C. | EJ9: GENERACIÓN ANDINA S.A.C. | EK9: GENERADORA DE ENERGÍA DEL PERÚ | EL9: GENERADORA DE ENERGÍA DEL PERÚ | EM9: GENERADORA DE ENERGÍA DEL PERÚ | EN9: GENERADORA DE ENERGÍA DEL PERÚ | EO9: GR PAINO SOCIEDAD ANONIMA CERRADA | EP9: JOYA SOLAR S.A.C. | EQ9: MAJES ARCUS S.A.C. | ER9: ORYGEN PERU S.A.A. | ES9: ORYGEN PERU S.A.A. | ET9: ORYGEN PERU S.A.A. | EU9: ORYGEN PERU S.A.A. | EV9: ORYGEN PERU S.A.A. | EW9: PETRAMAS | EX9: PETRAMAS | EY9: PETRAMAS | EZ9: PETRAMAS | FA9: REPARTICIÓN ARCUS S.A.C. | FB9: SINERSA | FC9: SINERSA | FD9: BIOENERGIA DEL CHIRA S.A. | FE9: GM OPERACIONES S.A.C. | FF9: GM OPERACIONES S.A.C. | FG9: AGRO INDUSTRIAL PARAMONGA S.A. | FH9: AGROAURORA S.A.C. | FI9: AGROINDUSTRIAS SAN JACINTO S.A.A. | FJ9: AGROLMOS SOCIEDAD ANONIMA - AGROLMOS S.A. | FM9: UNACEM PERU S.A. | FN9: ELECTRO ORIENTE | FO9: AGUAS Y ENERGIA PERU | FP9: ELECTRO ZAÑA S.A.C. | FQ9: ELECTRONOROESTE S.A. | FR9: SDE PIURA | FS9: SINERSA | FT9: SINERSA
C10: SAN GABAN III | D10: MANTARO | E10: RESTITUCION | F10: TUMBES MAK 1 | G10: TUMBES MAK 2 | H10: CARHUAQUERO | I10: CAÑON DEL PATO | J10: AGUAYTIA TG1 | K10: AGUAYTIA TG2 | L10: KALLPA TG1 | M10: KALLPA TG2 | N10: KALLPA TG3 | O10: KALLPA TV | P10: LFLORES TG1 | Q10: LFLORES TV | R10: CERRO DEL AGUILA | S10: CERRODELAGUILAG4 | T10: SHOUGESA TV1 | U10: SHOUGESA TV2 | V10: SHOUGESA TV3 | W10: SHOUGESA CUMMINS | X10: MACHUPICCHU | Y10: ARICOTA 1 | Z10: ARICOTA 2 | AA10: INDEPENDENCIA | AB10: CHARCANI I,II,III | AC10: CHARCANI IV | AD10: CHARCANI V | AE10: CHARCANI VI | AF10: CHILINA TG | AG10: MOLLENDO 1, 2, 3 | AH10: CHILINA (SULZ 1,2) | AI10: SAN GABAN II | AJ10: PLATANAL | AK10: RECKA | AL10: RF ETEN TG1 | AM10: RF ETEN TG2 | AN10: CHAGLLA GP1 | AO10: CHAGLLA | AP10: LA VIRGEN | AQ10: CHIMAY | AR10: YANANGO | AS10: HUANCHOR | AT10: MARAÑON | AU10: STA TERESA | AV10: FENIX GT11 | AW10: FENIX GT12 | AX10: FENIX TV10 | AY10: YAUPI | AZ10: OROYA | BA10: PACHACHACA | BB10: MALPASO | BC10: CAHUA | BD10: ARCATA | BE10: GALLITO CIEGO | BF10: CHEVES | BG10: SANTA ROSA 1 | BH10: SANTA ROSA 2 | BI10: HUANZA | BJ10: MALACAS2 TG4 | BK10: MALACAS3 TG 5 | BL10: MALACAS1 TG6 | BM10: RF ILO2 TG1 | BN10: RF ILO2 TG2 | BO10: RF ILO2 TG3 | BP10: YUNCAN | BQ10: CHILCA1 TG1 | BR10: CHILCA1 TG2 | BS10: CHILCA1 TG3 | BT10: CHILCA-TV | BU10: CHILCA2 TG41 | BV10: CHILCA2-TV | BW10: CTNEPI_TG41 | BX10: CTNEPI_TG42 | BY10: CTNEPI_TG43 | BZ10: QUITARACSA | CA10: RF PTO MALDONADO | CB10: RF PUCALLPA | CC10: PARIAC | CD10: HUINCO | CE10: MATUCANA | CF10: MOYOPAMPA | CG10: CALLAHUANCA | CH10: HUAMPANI | CI10: STA ROSA WEST TG7 | CJ10: UTI_5 | CK10: UTI_6 | CL10: VENTANILLA 3 | CM10: VENTANILLA 4 | CN10: VENTANILLA TV | CO10: STAROSA TG8 | CP10: PTO_BRVO TG1 | CQ10: PTO_BRVO TG2 | CR10: PTO_BRVO TG3 | CS10: PTO_BRVO TG4 | CT10: OLLEROS TG1 | CU10: OLLEROS TV | CV10: CS YARUCAYA | CW10: SAN JUAN | CX10: MATARANI | CY10: DUNA | CZ10: CARHUAQUERO (CS) | DA10: MANTA I | DB10: ANASHIRONI | DC10: CARHUAQUERO4 | DD10: CAÑA BRAVA | DE10: SUNNY | DF10: TUPURI | DG10: RONCADOR | DH10: CANCHAYLLO | DI10: RENOVANDESH1 | DJ10: POTRERO | DK10: PIZARRAS | DL10: NIMPERIAL | DM10: YARUCAYA | DN10: MOQUEGUA-SOLAR | DO10: PANAMERICANA-SOLAR | DP10: PQE-EOLICO-MARCONA | DQ10: PQE-EOLICO-3-HERMANAS | DR10: TACNA-SOLAR | DS10: YANAPAMPA | DT10: CARHUAC | DU10: HUALLIN | DV10: PURMACANA | DW10: HUASAHUASI | DX10: STACRUZ_1_2 | DY10: RUNATULLO_II | DZ10: RUNATULLO_III | EA10: RUCUY | EB10: PQE-EOLICO-TALARA | EC10: PQE-EOLICO-CUPISNIQUE | ED10: INTIPAMPA | EE10: PUNTA LOMITAS-BL1 | EF10: PUNTA LOMITAS-BL2 | EG10: PUN LOMITAS_EXP-BL1 | EH10: PUN LOMITAS_EXP-BL2 | EI10: 8AGOSTO | EJ10: EL CARMEN | EK10: LA JOYA | EL10: ANGEL_I | EM10: ANGEL_II | EN10: ANGEL_III | EO10: HUAMBOS | EP10: SAN MARTIN SOLAR | EQ10: MAJES | ER10: RUBI | ES10: CH_HER1 | ET10: WAYRA-I | EU10: WAYRA EXTENSION | EV10: CLEMESI | EW10: HUAYCOLORO | EX10: CALLAO | EY10: DONA_CATALINA | EZ10: LAGRINGAV | FA10: REPARTICION | FB10: POECHOS2 | FC10: CHANCAY | FD10: CANA BRAVA | FE10: REFINERIA TALARA TV1 | FF10: REFINERÍA TALARA TV2 | FG10: PARAMONGA | FH10: MAPLE | FI10: SAN_JACINTO | FJ10: AGROLMOS | FK10: MVAR | FM10: CARPAPATA | FN10: CENTRALES ELOR | FO10: PIAS1 | FP10: ZANA | FQ10: TABLAZO | FR10: TALLANCA | FS10: CURUMUY | FT10: POECHOS1 | FU10: MVAR
A11: 05/11/2025 | B11: 00:30 | C11: 34.1 | D11: -30.5 | E11: 2.3 | H11: -11.2 | I11: 9.4 | L11: -18.5 | M11: -17.8 | N11: 3.7 | O11: 33.3 | P11: 0 | R11: 18.7 | S11: 0.4 | X11: 0.8 | Y11: 0.9 | Z11: 0.1 | AA11: 0.8 | AB11: -3.3 | AC11: 2.8 | AD11: 15.9 | AI11: 8.5 | AJ11: -21.9 | AN11: -1.4 | AO11: -21.9 | AP11: 2.7 | AQ11: 12.8 | AR11: -2 | AS11: 0.6 | AT11: 2.6 | AU11: 0.9 | AY11: 2.6 | AZ11: -0.8 | BA11: -0.1 | BB11: 1 | BC11: 1.1 | BD11: 0.4 | BE11: 0.2 | BF11: 4.6 | BI11: -16 | BL11: 0 | BP11: -2.7 | BQ11: -47.5 | BR11: -48.9 | BS11: 0 | BT11: -36 | CC11: -0.3 | CD11: 22.4 | CE11: 14.9 | CF11: 3.7 | CG11: 0.8 | CH11: 2.2 | CL11: -6.4 | CM11: -4.5 | CN11: -42.9 | CT11: -32.5 | CU11: -20.9 | CW11: -20.4 | CX11: 0 | CY11: 0 | DA11: 1.3 | DB11: 0.1 | DG11: 0 | DH11: 0.7 | DJ11: -0.5 | DK11: 0.2 | DL11: 0.5 | DN11: 0 | DO11: 0 | DP11: 4.9 | DQ11: -3.3 | DR11: 0 | DS11: 0 | DT11: 0.5 | DU11: 0.3 | DW11: -2.8 | DX11: 0.1 | DY11: 0.6 | DZ11: 0.3 | EA11: 0.3 | EB11: 0 | EC11: 16.1 | ED11: 0 | EE11: -0.2 | EF11: -2.4 | EG11: 0.5 | EH11: 0.5 | EI11: 2.6 | EJ11: -0.1 | EK11: 1.7 | EL11: 0.2 | EM11: 0.2 | EN11: 0.2 | EO11: 0 | EQ11: 0 | ER11: 0 | ES11: -0.2 | ET11: -15 | EU11: 0 | EV11: 0 | EW11: 0.6 | EY11: 0.6 | EZ11: 0.6 | FA11: 0 | FB11: 0.4 | FC11: 0.6 | FD11: 2 | FE11: 8.5 | FF11: 0 | FG11: 1.2 | FH11: 0 | FI11: 2.8 | FJ11: 4.1 | FK11: -174.5 | FM11: 1.86545 | FN11: -0.4 | FO11: 1.2 | FP11: 1.5 | FQ11: 0.3 | FR11: 0.2 | FS11: -0.2 | FT11: 0.3 | FU11: 4.76545
A12: 05/11/2025 | B12: 01:00 | C12: 32.7 | D12: -35.8 | E12: 2.4 | H12: -15.2 | I12: 6.4 | L12: -18.2 | M12: -24.8 | N12: -2.9 | O12: 36.3 | P12: 0 | R12: 27.1 | S12: -0.3 | X12: 0 | Y12: 0.6 | Z12: 0 | AA12: 0.8 | AB12: -3.4 | AC12: 2.8 | AD12: 14.2 | AI12: 7.3 | AJ12: -22.7 | AN12: -1.3 | AO12: -22.7 | AP12: 2.6 | AQ12: 8.1 | AR12: -3.5 | AS12: 0.9 | AT12: 2.6 | AU12: 0.1 | AY12: 3.6 | AZ12: -0.8 | BA12: -0.2 | BB12: -3.1 | BC12: 0.2 | BD12: 0.4 | BE12: 0.1 | BF12: -3.7 | BI12: -16.3 | BL12: 0 | BP12: -0.5 | BQ12: -45.5 | BR12: -46.9 | BS12: 0 | BT12: -36 | CC12: -0.3 | CD12: 16.7 | CE12: 13.4 | CF12: -1.5 | CG12: 0.8 | CH12: 0 | CL12: -5.9 | CM12: -3.6 | CN12: -41.7 | CT12: -34.3 | CU12: -21.9 | CW12: -21 | CX12: 0 | CY12: 0 | DA12: 1.3 | DB12: 0 | DG12: 0 | DH12: 0.7 | DJ12: -1.2 | DK12: 0.2 | DL12: 0.6 | DN12: 0 | DO12: 0 | DP12: 4.4 | DQ12: -4.2 | DR12: 0 | DS12: 0 | DT12: 0.5 | DU12: 0.3 | DW12: -2.6 | DX12: 0.2 | DY12: 0.5 | DZ12: 0.3 | EA12: 0.5 | EB12: 0 | EC12: 17.6 | ED12: 0 | EE12: 0.4 | EF12: -1.3 | EG12: 0.4 | EH12: 0.6 | EI12: 2.6 | EJ12: -0.1 | EK12: 1.6 | EL12: 0.2 | EM12: 0.2 | EN12: 0.2 | EO12: 0 | EQ12: 0 | ER12: 0 | ES12: -0.2 | ET12: -15.5 | EU12: 0.4 | EV12: 0 | EW12: 0.6 | EY12: 0.6 | EZ12: 0.6 | FA12: 0 | FB12: 0.4 | FC12: 0.6 | FD12: 1.7 | FE12: 8.5 | FF12: 0.3 | FG12: 1.4 | FH12: 0 | FI12: 3.1 | FJ12: 3.7 | FK12: -223.8 | FM12: 1.79566 | FN12: -0.15 | FO12: 1.2 | FP12: 1.6 | FQ12: 0.3 | FR12: 0.2 | FS12: -0.1 | FT12: 0.4 | FU12: 5.24566
A13: 05/11/2025 | B13: 01:30 | C13: 36 | D13: -37.1 | E13: 2.4 | H13: -14.1 | I13: 7.9 | L13: -17.6 | M13: -22.5 | N13: -1.1 | O13: 37.1 | P13: 0 | R13: 26.2 | S13: -0.1 | X13: 0.9 | Y13: 1.4 | Z13: 0.7 | AA13: 0.8 | AB13: -3.4 | AC13: 3 | AD13: 14.7 | AI13: 7.9 | AJ13: -23.5 | AN13: -1.4 | AO13: -23.4 | AP13: 2.5 | AQ13: 7.4 | AR13: -3.6 | AS13: 0.8 | AT13: 2.6 | AU13: 0.2 | AY13: 3 | AZ13: -0.8 | BA13: -0.2 | BB13: -2.6 | BC13: -0.9 | BD13: 0.4 | BE13: 0.1 | BF13: -0.7 | BI13: -16.6 | BL13: 0 | BP13: -1.5 | BQ13: -49 | BR13: -50.4 | BS13: 0 | BT13: -40.9 | CC13: -0.3 | CD13: 17.6 | CE13: 12.6 | CF13: -1.4 | CG13: 0.8 | CH13: -2 | CL13: -7.4 | CM13: -5.1 | CN13: -44 | CT13: -37.1 | CU13: -23.6 | CW13: -22.2 | CX13: 0 | CY13: 0 | DA13: 1.3 | DB13: 0.1 | DG13: 0 | DH13: 0.7 | DJ13: -1.1 | DK13: 0.2 | DL13: 0.6 | DN13: 0 | DO13: 0 | DP13: 4.5 | DQ13: -3.7 | DR13: 0 | DS13: 0 | DT13: 0.5 | DU13: 0.3 | DW13: -2.6 | DX13: 0.2 | DY13: 0.6 | DZ13: 0.4 | EA13: 0.3 | EB13: 0 | EC13: 20.9 | ED13: 0 | EE13: -0.7 | EF13: -0.8 | EG13: 0.5 | EH13: 0.5 | EI13: 2.6 | EJ13: -0.1 | EK13: 1.6 | EL13: 0.2 | EM13: 0.2 | EN13: 0.2 | EO13: 0 | EQ13: 0 | ER13: 0 | ES13: -0.2 | ET13: -15.5 | EU13: 0 | EV13: 0 | EW13: 0.6 | EY13: 0.6 | EZ13: 0.6 | FA13: 0 | FB13: 0.4 | FC13: 0.6 | FD13: 1.9 | FE13: 8.5 | FF13: 0.2 | FG13: 1.7 | FH13: 0 | FI13: 3.5 | FJ13: 3.4 | FK13: -233.8 | FM13: 1.90563 | FN13: 0 | FO13: 1.4 | FP13: 1.6 | FQ13: 0.3 | FR13: 0.2 | FS13: -0.1 | FT13: 0.4 | FU13: 5.70563
A14: 05/11/2025 | B14: 02:00 | C14: 35.2 | D14: -41 | E14: 1.6 | H14: -15.1 | I14: 8.3 | L14: -19 | M14: -23.8 | N14: -2.1 | O14: 33.3 | P14: 0 | R14: 21.6 | S14: 0.1 | X14: 0 | Y14: 0.9 | Z14: 0.3 | AA14: 0.8 | AB14: -3.4 | AC14: 3.3 | AD14: 12.9 | AI14: 7.6 | AJ14: -23.7 | AN14: -1.3 | AO14: -24.3 | AP14: 2.8 | AQ14: 8.7 | AR14: -3.7 | AS14: 1.3 | AT14: 2.6 | AU14: 1.4 | AY14: 2.3 | AZ14: -0.8 | BA14: -0.2 | BB14: -1.9 | BC14: -0.4 | BD14: 0.4 | BE14: 0.1 | BF14: -0.6 | BI14: -16.7 | BL14: 0 | BP14: -2 | BQ14: -50.9 | BR14: -52.3 | BS14: 0 | BT14: -39.9 | CC14: -0.3 | CD14: 15.8 | CE14: 12.8 | CF14: -1.5 | CG14: 0.8 | CH14: -1.9 | CL14: -10.7 | CM14: -8.4 | CN14: -48.8 | CT14: -39.5 | CU14: -19 | CW14: -22.3 | CX14: 0 | CY14: 0.2 | DA14: 1.3 | DB14: 0.1 | DG14: 0 | DH14: 0.6 | DJ14: -1.1 | DK14: 0.2 | DL14: 0.5 | DN14: 0 | DO14: 0 | DP14: 1.8 | DQ14: -3.5 | DR14: 0 | DS14: 0.1 | DT14: 0.5 | DU14: 0.3 | DW14: -2.6 | DX14: 0.1 | DY14: 0.5 | DZ14: 0.2 | EA14: 0.3 | EB14: 0 | EC14: 22.1 | ED14: 0 | EE14: -5.4 | EF14: -5.4 | EG14: 0 | EH14: 0 | EI14: 2.6 | EJ14: -0.1 | EK14: 1.9 | EL14: 0.2 | EM14: 0.2 | EN14: 0.2 | EO14: 0 | EQ14: 0 | ER14: 0 | ES14: -0.2 | ET14: -17 | EU14: 0 | EV14: 0 | EW14: 0.6 | EY14: 0.6 | EZ14: 0.6 | FA14: 0 | FB14: 0.4 | FC14: 0.5 | FD14: 2 | FE14: 8.6 | FF14: 0.5 | FG14: 1 | FH14: 0 | FI14: 2.6 | FJ14: 3 | FK14: -281.6 | FM14: 1.9974 | FN14: 0 | FO14: 1.4 | FP14: 1.6 | FQ14: 0.3 | FR14: 0.3 | FS14: -0.1 | FT14: 0.4 | FU14: 5.8974
A15: 05/11/2025 | B15: 02:30 | C15: 35.3 | D15: -42.1 | E15: 0.8 | H15: -13.2 | I15: 10.2 | L15: -21.7 | M15: -25.7 | N15: -4.4 | O15: 30.4 | P15: 0 | R15: 17.1 | S15: 0.1 | X15: -0.9 | Y15: 1.1 | Z15: 0.4 | AA15: 0.8 | AB15: -3.3 | AC15: 2.4 | AD15: 13.7 | AI15: 7.9 | AJ15: -24.5 | AN15: -1.4 | AO15: -25.2 | AP15: 2.8 | AQ15: 1.9 | AR15: -4.1 | AS15: 0.5 | AT15: 2.6 | AU15: 0.8 | AY15: 1.4 | AZ15: -1.1 | BA15: -0.3 | BB15: -2 | BC15: 0 | BD15: 0.4 | BE15: 0.1 | BF15: -0.1 | BI15: -17.3 | BL15: 0 | BP15: -1.6 | BQ15: -52.5 | BR15: -54 | BS15: 0 | BT15: -42.8 | CC15: -0.3 | CD15: 15.1 | CE15: 12.8 | CF15: -0.9 | CG15: 0.6 | CH15: -2 | CL15: -12.2 | CM15: -10.3 | CN15: -51.4 | CT15: -41.4 | CU15: -20.2 | CW15: -22.2 | CX15: 0 | CY15: 0 | DA15: 1.3 | DB15: 0 | DG15: 0 | DH15: 0.6 | DJ15: -0.9 | DK15: 0.2 | DL15: 0.5 | DN15: 0 | DO15: 0 | DP15: 1.9 | DQ15: -4.8 | DR15: 0 | DS15: 0.1 | DT15: 0.5 | DU15: 0.3 | DW15: -2.6 | DX15: 0 | DY15: 0.4 | DZ15: -0.1 | EA15: 0.3 | EB15: 0 | EC15: 19.7 | ED15: 0 | EE15: -6.2 | EF15: -5.8 | EG15: 0 | EH15: 0 | EI15: 2.6 | EJ15: -0.1 | EK15: 1.7 | EL15: 0.2 | EM15: 0.2 | EN15: 0.2 | EO15: 0 | EQ15: 0 | ER15: 0 | ES15: -0.2 | ET15: -16.6 | EU15: 0 | EV15: 0 | EW15: 0.6 | EY15: 0.6 | EZ15: 0.6 | FA15: 0 | FB15: 0.4 | FC15: 0.4 | FD15: 2 | FE15: 8.2 | FF15: 0.5 | FG15: 1.8 | FH15: 0 | FI15: 2.2 | FJ15: 3.5 | FK15: -325.7 | FM15: 1.92361 | FN15: 0 | FO15: 1.4 | FP15: 1.6 | FQ15: 0.3 | FR15: 0.3 | FS15: -0.1 | FT15: 0.4 | FU15: 5.82361
A16: 05/11/2025 | B16: 03:00 | C16: 32.2 | D16: -53.2 | E16: -1.2 | H16: -12.6 | I16: 9.4 | L16: -23.2 | M16: -26.1 | N16: -5.7 | O16: 28.4 | P16: 0 | R16: 5.9 | S16: 0.1 | X16: -1.9 | Y16: 1.3 | Z16: 0.4 | AA16: 0.8 | AB16: -3.3 | AC16: 2.3 | AD16: 12.8 | AI16: 6.9 | AJ16: -24.2 | AN16: -1.4 | AO16: -25.7 | AP16: 2.5 | AQ16: 1.8 | AR16: -4.3 | AS16: 0.5 | AT16: 2.6 | AU16: 0.9 | AY16: -0.1 | AZ16: -1 | BA16: -0.3 | BB16: -2.8 | BC16: -1.5 | BD16: 0.4 | BE16: 0.1 | BF16: -0.9 | BI16: -16.6 | BL16: 0 | BP16: -2.5 | BQ16: -54.9 | BR16: -56.4 | BS16: -1.5 | BT16: -45.9 | CC16: -0.3 | CD16: 15.1 | CE16: 13.2 | CF16: -0.3 | CG16: 0.6 | CH16: -2 | CL16: -14.7 | CM16: -13.1 | CN16: -55.1 | CT16: -30 | CU16: -21.8 | CW16: -22.8 | CX16: 0 | CY16: 0 | DA16: 1.3 | DB16: 0.1 | DG16: 0 | DH16: 0.6 | DJ16: -0.9 | DK16: 0.2 | DL16: 0.6 | DN16: 0 | DO16: 0 | DP16: 2.1 | DQ16: -5.5 | DR16: 0 | DS16: 0.1 | DT16: 0.5 | DU16: 0.3 | DW16: -2.6 | DX16: 0 | DY16: 0.4 | DZ16: -0.3 | EA16: 0.3 | EB16: 0 | EC16: 20.1 | ED16: 0 | EE16: -6.5 | EF16: -6.9 | EG16: 0 | EH16: 0 | EI16: 2.6 | EJ16: -0.1 | EK16: 1.9 | EL16: 0.2 | EM16: 0.2 | EN16: 0.2 | EO16: 0 | EQ16: 0 | ER16: 0 | ES16: -0.2 | ET16: 0 | EU16: 0 | EV16: 0 | EW16: 0.6 | EY16: 0.6 | EZ16: 0.6 | FA16: 0 | FB16: 0.4 | FC16: 0.4 | FD16: 2 | FE16: 8.2 | FF16: 0.5 | FG16: 1.6 | FH16: 0 | FI16: 2.4 | FJ16: 3.5 | FK16: -359.6 | FM16: 1.89896 | FN16: 0 | FO16: 1.4 | FP16: 1.6 | FQ16: 0.3 | FR16: 0.3 | FS16: -0.2 | FT16: 0.3 | FU16: 5.59896
A17: 05/11/2025 | B17: 03:30 | C17: 35.7 | D17: -44.3 | E17: 0.8 | H17: -14.9 | I17: 9.3 | L17: -21.9 | M17: -27.9 | N17: -6.7 | O17: 30.3 | P17: 0 | R17: 20.7 | S17: -0.1 | X17: -1.1 | Y17: 0.8 | Z17: 0.3 | AA17: 0.8 | AB17: -3.3 | AC17: 2.5 | AD17: 13.7 | AI17: 7 | AJ17: -24.8 | AN17: -1.4 | AO17: -20.7 | AP17: 2.5 | AQ17: 1 | AR17: -3.8 | AS17: 0.5 | AT17: 2.6 | AU17: 0.9 | AY17: 1.7 | AZ17: -1.1 | BA17: -0.3 | BB17: 0.2 | BC17: -0.8 | BD17: 0.4 | BE17: 0.1 | BF17: -0.8 | BI17: -16.6 | BL17: 0 | BP17: -0.7 | BQ17: -55.7 | BR17: -57.1 | BS17: -2.5 | BT17: -46.1 | CC17: -0.3 | CD17: 15.6 | CE17: 13.3 | CF17: -1 | CG17: 0.7 | CH17: -1.8 | CL17: -13.2 | CM17: -11.1 | CN17: -52.8 | CT17: -30.7 | CU17: -22.1 | CW17: -22.9 | CX17: 0 | CY17: 0 | DA17: 1.3 | DB17: 0 | DG17: 0 | DH17: 0.8 | DJ17: -1 | DK17: 0.2 | DL17: 0.6 | DN17: 0 | DO17: 0 | DP17: 2.1 | DQ17: -5 | DR17: 0 | DS17: 0.1 | DT17: 0.4 | DU17: 0.3 | DW17: -2.8 | DX17: 0.1 | DY17: 0.4 | DZ17: -0.1 | EA17: 0.5 | EB17: 0 | EC17: 16.9 | ED17: 0 | EE17: -2.9 | EF17: -3.3 | EG17: 0 | EH17: 0 | EI17: 2.6 | EJ17: -0.1 | EK17: 1.9 | EL17: 0.2 | EM17: 0.2 | EN17: 0.2 | EO17: 0 | EQ17: 0 | ER17: 0 | ES17: -0.2 | ET17: 0 | EU17: 0 | EV17: 0 | EW17: 0.6 | EY17: 0.6 | EZ17: 0.6 | FA17: 0 | FB17: 0.4 | FC17: 0.6 | FD17: 2 | FE17: 8.4 | FF17: 0.1 | FG17: 1.2 | FH17: 0 | FI17: 2.1 | FJ17: 3.8 | FK17: -313.3 | FM17: 1.86632 | FN17: 0 | FO17: 1.6 | FP17: 1.6 | FQ17: 0.3 | FR17: 0.3 | FS17: -0.2 | FT17: 0.5 | FU17: 5.96632
A18: 05/11/2025 | B18: 04:00 | C18: 35.1 | D18: -46.4 | E18: 1.1 | H18: -16.5 | I18: 8.8 | L18: -21.7 | M18: -29.1 | N18: -7.7 | O18: 30.7 | P18: 0 | R18: 24.3 | S18: -0.1 | X18: -0.7 | Y18: 1 | Z18: 0.6 | AA18: 0.8 | AB18: -3.3 | AC18: 2.5 | AD18: 14.2 | AI18: 6.7 | AJ18: -24.9 | AN18: -1.4 | AO18: -21 | AP18: 2.5 | AQ18: 0.5 | AR18: -3.7 | AS18: 1 | AT18: 2.6 | AU18: 1.9 | AY18: 0.6 | AZ18: -1 | BA18: -0.2 | BB18: 0.5 | BC18: -1.4 | BD18: 0.4 | BE18: 0.1 | BF18: -3.1 | BI18: -16.6 | BL18: 0 | BP18: -1.3 | BQ18: -54.4 | BR18: -55.7 | BS18: -1.6 | BT18: -46.4 | CC18: -0.3 | CD18: 16.3 | CE18: 12.5 | CF18: -1.4 | CG18: 0.7 | CH18: -2 | CL18: -12.9 | CM18: -10.7 | CN18: -51.9 | CT18: -30.4 | CU18: -22 | CW18: -21.1 | CX18: 0 | CY18: 0 | DA18: 1.3 | DB18: 0 | DG18: 0.1 | DH18: 0.8 | DJ18: -0.5 | DK18: 0.2 | DL18: 0.6 | DN18: 0 | DO18: 0 | DP18: 2.5 | DQ18: -3.9 | DR18: 0 | DS18: 0.1 | DT18: 0.5 | DU18: 0.3 | DW18: -2.7 | DX18: 0.2 | DY18: 0.4 | DZ18: 0 | EA18: 0.5 | EB18: 0 | EC18: 16.4 | ED18: 0 | EE18: 1.1 | EF18: -0.7 | EG18: 0.8 | EH18: 0.8 | EI18: 2.6 | EJ18: -0.1 | EK18: 1.8 | EL18: 0.2 | EM18: 0.2 | EN18: 0.2 | EO18: 0 | EQ18: 0 | ER18: 0 | ES18: -0.2 | ET18: 0 | EU18: 0 | EV18: 0 | EW18: 0.6 | EY18: 0.6 | EZ18: 0.6 | FA18: 0 | FB18: 0.4 | FC18: 0.6 | FD18: 2 | FE18: 8.5 | FF18: 0.1 | FG18: 1 | FH18: 0 | FI18: 2.1 | FJ18: 3.9 | FK18: -301.6 | FM18: 1.83421 | FN18: 0 | FO18: 1.6 | FP18: 1.6 | FQ18: 0.3 | FR18: 0.2 | FS18: -0.1 | FT18: 0.3 | FU18: 5.73421
A19: 05/11/2025 | B19: 04:30 | C19: 39.3 | D19: -27.9 | E19: 3.8 | H19: -15 | I19: 10.4 | L19: -19.9 | M19: -21.5 | N19: -0.6 | O19: 31.6 | P19: 0 | R19: 29.9 | S19: 0.1 | X19: 3 | Y19: 1.4 | Z19: 0.9 | AA19: 0.8 | AB19: -3.3 | AC19: 2.8 | AD19: 16.5 | AI19: 8.4 | AJ19: -24.6 | AN19: -1.3 | AO19: -20.3 | AP19: 2.7 | AQ19: -0.1 | AR19: -3.4 | AS19: 1 | AT19: 2.6 | AU19: 0.1 | AY19: 4.2 | AZ19: -1 | BA19: -0.3 | BB19: 0.2 | BC19: 0.8 | BD19: 0.4 | BE19: 0.1 | BF19: 1 | BI19: -16.6 | BL19: 0 | BP19: -2.2 | BQ19: -53.2 | BR19: -54.5 | BS19: 0 | BT19: -44.6 | CC19: -0.2 | CD19: 16 | CE19: 12.2 | CF19: -1.7 | CG19: 0.8 | CH19: -1.9 | CL19: -10.9 | CM19: -8.3 | CN19: -49.2 | CT19: -28.1 | CU19: -20.6 | CW19: -19.7 | CX19: 0 | CY19: 0 | DA19: 1.3 | DB19: 0 | DG19: 0 | DH19: 0.8 | DJ19: -0.9 | DK19: 0.1 | DL19: 0.6 | DN19: 0 | DO19: 0 | DP19: 2.6 | DQ19: -3 | DR19: 0 | DS19: 0.1 | DT19: 0.3 | DU19: 0.2 | DW19: -2.8 | DX19: 0.3 | DY19: 0.6 | DZ19: 0.3 | EA19: 0.5 | EB19: 0 | EC19: 14.5 | ED19: 0 | EE19: 1.8 | EF19: -0.4 | EG19: 0.8 | EH19: 0.9 | EI19: 2.6 | EJ19: -0.1 | EK19: 1.8 | EL19: 0.2 | EM19: 0.2 | EN19: 0.2 | EO19: 0 | EQ19: 0 | ER19: 0 | ES19: -0.2 | ET19: 0 | EU19: 0 | EV19: 0 | EW19: 0.6 | EY19: 0.6 | EZ19: 0.6 | FA19: 0 | FB19: 0.4 | FC19: 0.8 | FD19: 1.9 | FE19: 8.8 | FF19: 0.3 | FG19: 1.2 | FH19: 0 | FI19: 1.9 | FJ19: 3.5 | FK19: -216 | FM19: 1.93096 | FN19: 0 | FO19: 1.7 | FP19: 1.6 | FQ19: 0.3 | FR19: 0.2 | FS19: -0.1 | FT19: 0.4 | FU19: 6.03096
A20: 05/11/2025 | B20: 05:00 | C20: 38.3 | D20: -39.6 | E20: 1.4 | H20: -13.6 | I20: 11.4 | L20: -22.3 | M20: -25.1 | N20: -3.9 | O20: 29.2 | P20: 0 | R20: 24.8 | S20: 0.1 | X20: 3.2 | Y20: 1.3 | Z20: 0.8 | AA20: 0.8 | AB20: -3.3 | AC20: 2.8 | AD20: 16.7 | AI20: 7.9 | AJ20: -24.9 | AN20: -1.3 | AO20: -21.2 | AP20: 2.6 | AQ20: 2.6 | AR20: -4.1 | AS20: -0.4 | AT20: 2.6 | AU20: 0.8 | AY20: 2.6 | AZ20: -1.1 | BA20: -0.3 | BB20: 0 | BC20: -0.2 | BD20: 0.4 | BE20: 0.1 | BF20: -0.5 | BI20: -16.6 | BL20: 0 | BP20: -1.3 | BQ20: -54.3 | BR20: -55.6 | BS20: -0.9 | BT20: -45.9 | CC20: -0.3 | CD20: 14.7 | CE20: 12.8 | CF20: -1.2 | CG20: 0.7 | CH20: -2 | CL20: -10.5 | CM20: -8.6 | CN20: -48.6 | CT20: -27 | CU20: -20 | CW20: -19.4 | CX20: 0 | CY20: 0 | DA20: 1.3 | DB20: 0.1 | DG20: 0 | DH20: 0.7 | DJ20: -1 | DK20: 0.2 | DL20: 0.6 | DN20: 0 | DO20: 0 | DP20: 2.6 | DQ20: -3.2 | DR20: 0.4 | DS20: 0.1 | DT20: 0.3 | DU20: 0.3 | DW20: -2.8 | DX20: 0.3 | DY20: 0.4 | DZ20: 0 | EA20: 0.5 | EB20: 0 | EC20: 12.5 | ED20: 0.3 | EE20: -1.7 | EF20: -3.5 | EG20: 0.3 | EH20: 0.4 | EI20: 2.6 | EJ20: -0.1 | EK20: 1.8 | EL20: 0.2 | EM20: 0.2 | EN20: 0.2 | EO20: 0 | EQ20: 0 | ER20: 0 | ES20: -0.2 | ET20: 0 | EU20: 0 | EV20: 1.2 | EW20: 0.6 | EY20: 0.6 | EZ20: 0.6 | FA20: 0 | FB20: 0.4 | FC20: 0.8 | FD20: 2 | FE20: 8.7 | FF20: 0.4 | FG20: 1 | FH20: 0 | FI20: 2.1 | FJ20: 3.4 | FK20: -259.8 | FM20: 1.89979 | FN20: 0 | FO20: 1.6 | FP20: 1.6 | FQ20: 0.3 | FR20: 0.2 | FS20: -0.1 | FT20: 0.4 | FU20: 5.89979
A21: 05/11/2025 | B21: 05:30 | C21: 38.3 | D21: -29.9 | E21: 2.6 | H21: -11.2 | I21: 14 | L21: -16.5 | M21: -20 | N21: 0.9 | O21: 36.5 | P21: 0 | R21: 26.8 | S21: 0.1 | X21: 3.1 | Y21: 1.5 | Z21: 0.8 | AA21: 0.8 | AB21: -3.2 | AC21: 3 | AD21: 16.5 | AI21: 7.8 | AJ21: -23.1 | AN21: -1.2 | AO21: -19.8 | AP21: 2.8 | AQ21: 2 | AR21: -4.2 | AS21: -1.4 | AT21: 2.6 | AU21: 1.1 | AY21: 1.1 | AZ21: -0.8 | BA21: -0.3 | BB21: -0.8 | BC21: 0.4 | BD21: 0.4 | BE21: 0.1 | BF21: -0.2 | BI21: -16.4 | BL21: 0 | BP21: -0.1 | BQ21: -50.6 | BR21: -51.9 | BS21: 0 | BT21: -40.8 | CC21: -0.3 | CD21: 14.7 | CE21: 13.1 | CF21: -0.5 | CG21: 0.6 | CH21: -2 | CL21: -7.3 | CM21: -5.5 | CN21: -44.1 | CT21: -22.6 | CU21: -17.3 | CW21: -20.3 | CX21: 0.1 | CY21: 0 | DA21: 1.3 | DB21: 0 | DG21: 0 | DH21: 0.7 | DJ21: -1 | DK21: 0.1 | DL21: 0.6 | DN21: -0.1 | DO21: 0 | DP21: 2.8 | DQ21: -2.8 | DR21: 0.2 | DS21: 0.1 | DT21: 0.3 | DU21: 0.2 | DW21: -2.8 | DX21: 0.2 | DY21: 0.4 | DZ21: 0 | EA21: 0.5 | EB21: 0 | EC21: 4.5 | ED21: -0.1 | EE21: 0.4 | EF21: 0.6 | EG21: 0.4 | EH21: 0.8 | EI21: 2.6 | EJ21: -0.1 | EK21: 1.7 | EL21: 0.2 | EM21: 0.2 | EN21: 0.2 | EO21: 0 | EQ21: 0 | ER21: 2.2 | ES21: -0.2 | ET21: 0 | EU21: 0 | EV21: 1.2 | EW21: 0.6 | EY21: 0.6 | EZ21: 0.6 | FA21: 0 | FB21: 0.4 | FC21: 0.8 | FD21: 1.8 | FE21: 9.2 | FF21: 0.5 | FG21: 0.9 | FH21: 0 | FI21: 1.9 | FJ21: 3.8 | FK21: -184.2 | FM21: 1.97895 | FN21: 0 | FO21: 1.4 | FP21: 1.7 | FQ21: 0.3 | FR21: 0.3 | FS21: 0.1 | FT21: 0.4 | FU21: 6.17895
A22: 05/11/2025 | B22: 06:00 | C22: 35.9 | D22: -38.4 | E22: 1.1 | H22: -8.5 | I22: 14.1 | L22: -24 | M22: -23.8 | N22: -2.9 | O22: 26.8 | P22: 0 | R22: 17.2 | S22: 0.3 | X22: 1 | Y22: 1.2 | Z22: 0.5 | AA22: 0.8 | AB22: -3.2 | AC22: 3.5 | AD22: 14.7 | AI22: 7.2 | AJ22: -23.7 | AN22: -1.1 | AO22: -12.7 | AP22: 2.8 | AQ22: 2.1 | AR22: -4.6 | AS22: -1.5 | AT22: 2.6 | AU22: 1.1 | AY22: 2.1 | AZ22: -0.8 | BA22: -0.2 | BB22: 1.2 | BC22: -0.4 | BD22: 0.4 | BE22: 0.2 | BF22: 4.3 | BI22: -16.4 | BL22: 0 | BP22: -1.7 | BQ22: -56.6 | BR22: -58 | BS22: -2.7 | BT22: -45.5 | CC22: -0.3 | CD22: 13.4 | CE22: 12.7 | CF22: -0.3 | CG22: 0.6 | CH22: -2.3 | CL22: -11 | CM22: -9.2 | CN22: -49.8 | CT22: -18.8 | CU22: -18.8 | CW22: -22 | CX22: 0.8 | CY22: 0 | DA22: 1.3 | DB22: 0 | DG22: 0 | DH22: 0.7 | DJ22: -0.1 | DK22: 0.1 | DL22: 0.7 | DN22: -0.3 | DO22: -0.2 | DP22: 1.8 | DQ22: -6.1 | DR22: 0.3 | DS22: 0.1 | DT22: 0.3 | DU22: 0.3 | DW22: -2.8 | DX22: 0.2 | DY22: 0.4 | DZ22: 0 | EA22: 0.5 | EB22: 0 | EC22: 0.3 | ED22: 0.1 | EE22: -1.7 | EF22: -2.3 | EG22: 0.3 | EH22: 0.5 | EI22: 2.6 | EJ22: -0.1 | EK22: 1.6 | EL22: 0.2 | EM22: 0.2 | EN22: 0.2 | EO22: 0 | EQ22: 0 | ER22: 1.7 | ES22: -0.2 | ET22: -16.3 | EU22: 0 | EV22: 0 | EW22: 0.6 | EY22: 0.6 | EZ22: 0.6 | FA22: 0 | FB22: 0.4 | FC22: 0.8 | FD22: 2 | FE22: 9.5 | FF22: 0.5 | FG22: 2 | FH22: 0 | FI22: 2 | FJ22: 3.5 | FK22: -283.8 | FM22: 1.93344 | FN22: -0.11 | FO22: 1.5 | FP22: 1.7 | FQ22: 0.3 | FR22: 0.2 | FS22: 0.1 | FT22: 0.4 | FU22: 6.02344
... A58: 06/11/2025 | B58: 00:00 | C58: 24.4 | D58: -44.2 | E58: 3.6 | H58: -19.7 | I58: -5.5 | L58: -39.4 | M58: -46.3 | N58: -16.6 | O58: 22.1 | P58: 6.8 | R58: 16.7 | S58: 0 | X58: 3.7 | Y58: 1 | Z58: 0.3 | AA58: 0 | AB58: -3.5 | AC58: 4 | AD58: -1.7 | AI58: 6 | AJ58: -7.3 | AN58: -0.8 | AO58: 0 | AP58: 3.1 | AQ58: 12.1 | AR58: 2.1 | AS58: 0.2 | AT58: 2.6 | AU58: 1.2 | AY58: 3.7 | AZ58: -0.8 | BA58: 0.2 | BB58: -3.9 | BC58: -1.3 | BD58: 0.4 | BE58: 0 | BF58: -3.1 | BI58: -4.9 | BL58: -5.7 | BP58: 6.7 | BQ58: -46.6 | BR58: -48.2 | BS58: -0.9 | BT58: 5.5 | CC58: -0.3 | CD58: 47.6 | CE58: 20.5 | CF58: 8.8 | CG58: 0.6 | CH58: -1.1 | CL58: -3.7 | CM58: -1.5 | CN58: -38.3 | CT58: -19.3 | CU58: -14.6 | CW58: -17.6 | CX58: 0 | CY58: 0 | DA58: 0 | DB58: 0 | DG58: 0.2 | DH58: 0.8 | DJ58: 0.2 | DK58: 0.2 | DL58: 0.6 | DN58: 0 | DO58: 0 | DP58: 6.7 | DQ58: 1.7 | DR58: 0 | DS58: -0.2 | DT58: 0.6 | DU58: 0.2 | DW58: -3.1 | DX58: 0 | DY58: 0.3 | DZ58: -0.4 | EA58: 0.5 | EB58: 0 | EC58: 14.1 | ED58: 0 | EE58: -0.1 | EF58: -1.9 | EG58: 0.5 | EH58: 0.6 | EI58: 2.4 | EJ58: 0 | EK58: 1.7 | EL58: 0.2 | EM58: 0.2 | EN58: 0.2 | EO58: 0.3 | EQ58: 0 | ER58: 0 | ES58: -0.2 | ET58: -5.5 | EU58: 0 | EV58: 0 | EW58: 0.7 | EY58: 0.8 | EZ58: 0.6 | FA58: 0 | FB58: 0.8 | FC58: 0.8 | FD58: 1.8 | FE58: 9.1 | FF58: 0.1 | FG58: 3 | FH58: 0 | FI58: 3.2 | FJ58: 4 | FK58: -147.2 | FM58: 1.68389 | FN58: -0.54 | FO58: 1.6 | FP58: 1.7 | FQ58: 0.3 | FR58: 0.2 | FS58: 0.1 | FT58: 0.4 | FU58: 5.44389
A59: EJEC | C59: 605.5 | D59: 363.95 | E59: 427.35 | F59: 0 | G59: 0 | H59: -198 | I59: 216.75 | J59: 0 | K59: 0 | L59: -95.45 | M59: -173.35 | N59: 368.05 | O59: 1259.4 | P59: 170.8 | Q59: 0 | R59: 476.45 | S59: 0.9 | T59: 0 | U59: 0 | V59: 0 | W59: 0 | X59: 177.8 | Y59: 29.25 | Z59: 13 | AA59: 38.3 | AB59: -80.6 | AC59: 101.35 | AD59: 264.35 | AE59: 0 | AF59: 0 | AG59: 0 | AH59: 0 | AI59: 204.55 | AJ59: -154.85 | AK59: 0 | AL59: 0 | AM59: 0 | AN59: -30.25 | AO59: -348.4 | AP59: 81.75 | AQ59: 284.65 | AR59: 2.4 | AS59: -21.5 | AT59: 62.4 | AU59: 23.95 | AV59: 0 | AW59: 0 | AX59: 0 | AY59: 118.2 | AZ59: -25.85 | BA59: -2.1 | BB59: -33.35 | BC59: 18.85 | BD59: 9.6 | BE59: 4.2 | BF59: -8.2 | BG59: 0 | BH59: 0 | BI59: -69.65 | BJ59: 0 | BK59: 0 | BL59: -38.3 | BM59: 0 | BN59: 0 | BO59: 0 | BP59: 72.75 | BQ59: -832.25 | BR59: -865.65 | BS59: -7.3 | BT59: -441.1 | BU59: 0 | BV59: 0 | BW59: 0 | BX59: 0 | BY59: 0 | BZ59: 0 | CA59: 0 | CB59: 0 | CC59: -6.25 | CD59: 934.25 | CE59: 795.4 | CF59: 190.25 | CG59: 16.55 | CH59: 41.6 | CI59: 0 | CJ59: 0 | CK59: 0 | CL59: 282.4 | CM59: 334.45 | CN59: -358.4 | CO59: 0 | CP59: 0 | CQ59: 0 | CR59: 0 | CS59: 0 | CT59: -142 | CU59: -217.95 | CV59: 0 | CW59: -407.1 | CX59: 71.1 | CY59: 0.1 | CZ59: 0 | DA59: 19.95 | DB59: 0.9 | DC59: 0 | DD59: 0 | DE59: 0 | DF59: 0 | DG59: 0.45 | DH59: 17.95 | DI59: 0 | DJ59: -0.05 | DK59: 3.6 | DL59: 14.1 | DM59: 0 | DN59: -6.9 | DO59: -16.35 | DP59: 99.6 | DQ59: -23.15 | DR59: -21.85 | DS59: -0.15 | DT59: 12.75 | DU59: 6.6 | DV59: 0 | DW59: -61.85 | DX59: 5.8 | DY59: 10.2 | DZ59: 4.85 | EA59: 19.85 | EB59: 11.65 | EC59: 194.05 | ED59: 27.75 | EE59: -17.55 | EF59: -35.95 | EG59: 6.1 | EH59: 8.9 | EI59: 61.25 | EJ59: -1.1 | EK59: 42.3 | EL59: 4.8 | EM59: 4.8 | EN59: 4.8 | EO59: 0.25 | EP59: 0 | EQ59: 13.45 | ER59: 124.7 | ES59: -4.7 | ET59: -36.15 | EU59: 1.4 | EV59: -46.45 | EW59: 14.9 | EX59: 0 | EY59: 14.75 | EZ59: 14.5 | FA59: 12.1 | FB59: 23.35 | FC59: 25.8 | FD59: 44.7 | FE59: 249.8 | FF59: 6.3 | FG59: 56.35 | FH59: 18.55 | FI59: 73.05 | FJ59: 94.1 | FK59: 4603.6 | FM59: 19.97615 | FN59: -16.45 | FO59: 34.85 | FP59: 40.7 | FQ59: 7.2 | FR59: 6.5 | FS59: 14.8 | FT59: 31.3 | FU59: 138.87615

Sheet DEMANDA_AREAS
B3: miércoles, 5 de Noviembre del 2025
B5: REPORTE DE LA DEMANDA POR ÁREAS Y SUBAREAS OPERATIVAS (MW)
B6: FECHA HORA | C6: DEMANDA | E6: AREA | H6: SUBAREAS
C7: INTERCAMBIOS INTERNACIONALES | D7: SEIN | E7: NORTE | F7: CENTRO | G7: SUR | H7: ELECTROANDES
B8: 00:30 | C8: 0 | D8: 6294.6 | E8: 936.2163 | F8: 3890.1027 | G8: 1468.281 | H8: 250.1858
B9: 01:00 | C9: 0 | D9: 6220.1 | E9: 903.8255 | F9: 3881.1519 | G9: 1435.1226 | H9: 238.6436
B10: 01:30 | C10: 0 | D10: 6145.6 | E10: 897.7716 | F10: 3811.0383 | G10: 1436.7901 | H10: 241.5613
B11: 02:00 | C11: 0 | D11: 6094.2 | E11: 899.9735 | F11: 3764.4926 | G11: 1429.7339 | H11: 239.5154
B12: 02:30 | C12: 0 | D12: 5948.7 | E12: 895.5982 | F12: 3634.197 | G12: 1418.9048 | H12: 239.0029
B13: 03:00 | C13: 0 | D13: 5940.9 | E13: 892.3638 | F13: 3628.7403 | G13: 1419.7959 | H13: 235.7295
B14: 03:30 | C14: 0 | D14: 6005 | E14: 890.7175 | F14: 3692.0969 | G14: 1422.1856 | H14: 243.2042
B15: 04:00 | C15: 0 | D15: 6004.5 | E15: 888.1588 | F15: 3676.5713 | G15: 1439.7699 | H15: 238.6242
B16: 04:30 | C16: 0 | D16: 6103.8 | E16: 918.0058 | F16: 3717.1607 | G16: 1468.6335 | H16: 239.3969
B17: 05:00 | C17: 0 | D17: 6051 | E17: 916.8575 | F17: 3655.6611 | G17: 1478.4814 | H17: 233.5444
B18: 05:30 | C18: 0 | D18: 6247 | E18: 940.9858 | F18: 3807.9988 | G18: 1498.0154 | H18: 236.2577
B19: 06:00 | C19: 0 | D19: 6179.2 | E19: 968.1471 | F19: 3651.7142 | G19: 1559.3387 | H19: 226.5358
... B59: ENERGÍA | C59: 0 | D59: 165397.3 | E59: 25533.552 | F59: 102723.87 | G59: 37139.876 | H59: 5644.6913
B61: LEYENDA:
D63: Potencia recibida del Ecuador
D64: Potencia entregada al Ecuador

Sheet TIPO_RECURSO
B3: miércoles, 5 de Noviembre del 2025
B5: REPORTE POTENCIA GENERADA POR TIPO DE RECURSO
B6: HORA | C6: H. PASADA | D6: H. REGULACION | E6: GAS DE CAMISEA | F6: GAS DE MALACAS | G6: RESIDUAL | H6: NAFTA+GAS DE REFINERIA | I6: FLEXIGAS+GAS DE REFINERIA | J6: BAGAZO | K6: BIOGÁS | L6: SOLAR | M6: EÓLICA | N6: TOTAL | S6: EMPRESA | T6: CENTRAL | U6: HIDROELECTRICA DE PASADA | V6: HIDROELECTRICA DE REGULACION
B7: 00:30 | C7: 1092.7 | D7: 2552.2 | E7: 2100.7 | F7: 0 | H7: =+DESPACHO_EJECUTADO!FE11+DESPACHO_EJECUTADO!FF11 -> 60 | J7: 41.8 | K7: 3.9 | L7: 0 | M7: 443.3 | N7: =+SUM(C7:M7) -> 6294.6 | S7: ANDEAN POWER S.A.C. | T7: C.H.CARHUAC | U7: 368.2
B8: 01:00 | C8: 1095.9 | D8: 2526.8 | E8: 2054.7 | F8: 0 | H8: =+DESPACHO_EJECUTADO!FE12+DESPACHO_EJECUTADO!FF12 -> 59.7 | J8: 40.5 | K8: 3.9 | L8: 0 | M8: 438.6 | N8: =+SUM(C8:M8) -> 6220.1 | S8: ASOCIACIÓN SANTA LUCIA DE CHACAS | T8: C.H. HUALLIN | U8: 65.55
B9: 01:30 | C9: 1102.1 | D9: 2579.1 | E9: 1986.1 | F9: 0 | H9: =+DESPACHO_EJECUTADO!FE13+DESPACHO_EJECUTADO!FF13 -> 59.1 | J9: 40.2 | K9: 3.9 | L9: 0 | M9: 375.1 | N9: =+SUM(C9:M9) -> 6145.6 | S9: CELEPSA | T9: C.H. EL PLATANAL | V9: 2729.25
B10: 02:00 | C10: 1100.7 | D10: 2534.2 | E10: 2032.6 | F10: 0 | H10: =+DESPACHO_EJECUTADO!FE14+DESPACHO_EJECUTADO!FF14 -> 59.3 | J10: 41.7 | K10: 3.9 | L10: 0 | M10: 321.8 | N10: =+SUM(C10:M10) -> 6094.2 | S10: CELEPSA RENOVABLES S.R.L. | T10: C.H. MARAÑON | U10: 451.2
B11: 02:30 | C11: 1096.9 | D11: 2437.4 | E11: 1995.8 | F11: 0 | H11: =+DESPACHO_EJECUTADO!FE15+DESPACHO_EJECUTADO!FF15 -> 59.5 | J11: 42.1 | K11: 3.9 | L11: 0 | M11: 313.1 | N11: =+SUM(C11:M11) -> 5948.7 | S11: CHINANGO S.A.C. | T11: C.H. CHIMAY | V11: 2823.4
B12: 03:00 | C12: 1080.6 | D12: 2399.1 | E12: 2020.3 | F12: 0 | H12: =+DESPACHO_EJECUTADO!FE16+DESPACHO_EJECUTADO!FF16 -> 58.8 | J12: 42.4 | K12: 3.9 | L12: 0 | M12: 335.8 | N12: =+SUM(C12:M12) -> 5940.9 | T12: C.H. YANANGO | U12: 615.95
B13: 03:30 | C13: 1095.6 | D13: 2533.7 | E13: 1943.7 | F13: 0 | H13: =+DESPACHO_EJECUTADO!FE17+DESPACHO_EJECUTADO!FF17 -> 58.8 | J13: 43.8 | K13: 3.9 | L13: 0 | M13: 325.5 | N13: =+SUM(C13:M13) -> 6005 | S13: EGASA | T13: C.H. CHARCANI III | U13: 166.1
B14: 04:00 | C14: 1088.4 | D14: 2488.1 | E14: 1948.8 | F14: 0 | H14: =+DESPACHO_EJECUTADO!FE18+DESPACHO_EJECUTADO!FF18 -> 58.8 | J14: 42.4 | K14: 3.9 | L14: 0 | M14: 374.1 | N14: =+SUM(C14:M14) -> 6004.5 | T14: C.H. CHARCANI IV | V14: 301.5
B15: 04:30 | C15: 1098.4 | D15: 2570.3 | E15: 1926.5 | F15: 0 | H15: =+DESPACHO_EJECUTADO!FE19+DESPACHO_EJECUTADO!FF19 -> 58.5 | J15: 40.3 | K15: 3.9 | L15: 0 | M15: 405.9 | N15: =+SUM(C15:M15) -> 6103.8 | T15: C.H. CHARCANI V | V15: 1900.55
B16: 05:00 | C16: 1095.4 | D16: 2495.4 | E16: 1945.6 | F16: 0 | H16: =+DESPACHO_EJECUTADO!FE20+DESPACHO_EJECUTADO!FF20 -> 57.6 | J16: 40.3 | K16: 3.9 | L16: 1.1 | M16: 411.7 | N16: =+SUM(C16:M16) -> 6051 | S16: EGEJUNIN | T16: C.H. HUASAHUASI I | U16: 229.8
B17: 05:30 | C17: 1091.4 | D17: 2582.6 | E17: 2027.6 | F17: 0 | H17: =+DESPACHO_EJECUTADO!FE21+DESPACHO_EJECUTADO!FF21 -> 57.8 | J17: 40.8 | K17: 3.9 | L17: 28.7 | M17: 414.2 | N17: =+SUM(C17:M17) -> 6247 | T17: C.H. RUNATULLO II | U17: 242.05
B18: 06:00 | C18: 1059.3 | D18: 2606.1 | E18: 1860.9 | F18: 0 | H18: =+DESPACHO_EJECUTADO!FE22+DESPACHO_EJECUTADO!FF22 -> 57.2 | J18: 40.6 | K18: 3.9 | L18: 148.6 | M18: 402.6 | N18: =+SUM(C18:M18) -> 6179.2 | T18: C.H. RUNATULLO III | U18: 336.55
B19: 06:30 | C19: 1070.8 | D19: 2579.1 | E19: 2010.7 | F19: 0 | H19: =+DESPACHO_EJECUTADO!FE23+DESPACHO_EJECUTADO!FF23 -> 58.3 | J19: 43.7 | K19: 3.9 | L19: 287.8 | M19: 447.1 | N19: =+SUM(C19:M19) -> 6501.4 | T19: C.H. SANTA CRUZ I | U19: 212.6
B20: 07:00 | C20: 1069.5 | D20: 2427.2 | E20: 1937.3 | F20: 0 | H20: =+DESPACHO_EJECUTADO!FE24+DESPACHO_EJECUTADO!FF24 -> 58.6 | J20: 44.8 | K20: 3.9 | L20: 383.2 | M20: 453.7 | N20: =+SUM(C20:M20) -> 6378.2 | S20: EGEMSA | T20: C.H. MACHUPICCHU | U20: 3412.15
B21: 07:30 | C21: 1058.6 | D21: 2357.5 | E21: 2247.5 | F21: 0 | H21: =+DESPACHO_EJECUTADO!FE25+DESPACHO_EJECUTADO!FF25 -> 59 | J21: 48.5 | K21: 3.9 | L21: 413.4 | M21: 434.8 | N21: =+SUM(C21:M21) -> 6623.2 | S21: EGESUR | T21: C.H. ARICOTA I | V21: 178.5
B22: 08:00 | C22: 1025.6 | D22: 2385.3 | E22: 2359.5 | F22: 0 | H22: =+DESPACHO_EJECUTADO!FE26+DESPACHO_EJECUTADO!FF26 -> 59 | J22: 56.4 | K22: 3.9 | L22: 413.4 | M22: 403.3 | N22: =+SUM(C22:M22) -> 6706.4 | T22: C.H. ARICOTA II | V22: 138.85
B23: 08:30 | C23: 1063.9 | D23: 2583.6 | E23: 2278.6 | F23: 0 | H23: =+DESPACHO_EJECUTADO!FE27+DESPACHO_EJECUTADO!FF27 -> 59.1 | J23: 55.6 | K23: 3.9 | L23: 437.9 | M23: 411.4 | N23: =+SUM(C23:M23) -> 6894 | S23: ELECTRICA YANAPAMPA SAC | T23: C.H. YANAPAMPA | U23: 77.2
B24: 09:00 | C24: 1055.6 | D24: 2744 | E24: 2291.6 | F24: 0 | H24: =+DESPACHO_EJECUTADO!FE28+DESPACHO_EJECUTADO!FF28 -> 59.2 | J24: 58.5 | K24: 3.9 | L24: 454.9 | M24: 417.2 | N24: =+SUM(C24:M24) -> 7084.9 | S24: ELECTROPERU | T24: C.H. MANTARO | V24: 15037
B25: 09:30 | C25: 1074.5 | D25: 2769 | E25: 2233.2 | F25: 0 | H25: =+DESPACHO_EJECUTADO!FE29+DESPACHO_EJECUTADO!FF29 -> 59 | J25: 59.3 | K25: 3.9 | L25: 458.7 | M25: 467.3 | N25: =+SUM(C25:M25) -> 7124.9 | T25: C.H. RESTITUCION | U25: 5148.9
B26: 10:00 | C26: 1086.6 | D26: 2787.8 | E26: 2138.2 | F26: 44.7 | H26: =+DESPACHO_EJECUTADO!FE30+DESPACHO_EJECUTADO!FF30 -> 58.7 | J26: 60.3 | K26: 3.9 | L26: 466.2 | M26: 633.5 | N26: =+SUM(C26:M26) -> 7279.9 | S26: EMPRESA DE GENERACION ELECTRICA CANCHAYLLO SAC | T26: C.H. CANCHAYLLO | U26: 67.45
B27: 10:30 | C27: 1080.9 | D27: 2660.2 | E27: 2391.8 | F27: 46.1 | H27: =+DESPACHO_EJECUTADO!FE31+DESPACHO_EJECUTADO!FF31 -> 57.2 | J27: 61.9 | K27: 3.9 | L27: 451.3 | M27: 658.5 | N27: =+SUM(C27:M27) -> 7411.8 | S27: EMPRESA DE GENERACION ELECTRICA RIO BAÑOS S.A.C. | T27: C.H. RUCUY | U27: 369.15
B28: 11:00 | C28: 1075.2 | D28: 2686 | E28: 2411.2 | F28: 45.8 | H28: =+DESPACHO_EJECUTADO!FE32+DESPACHO_EJECUTADO!FF32 -> 58.1 | J28: 60.9 | K28: 3.9 | L28: 460.5 | M28: 692.3 | N28: =+SUM(C28:M28) -> 7493.9 | S28: EMPRESA DE GENERACION HUALLAGA | T28: C.H. CHAGLLA | V28: 4789.45
B29: 11:30 | C29: 1080.6 | D29: 2763.3 | E29: 2454.5 | F29: 46 | H29: =+DESPACHO_EJECUTADO!FE33+DESPACHO_EJECUTADO!FF33 -> 58.3 | J29: 61.2 | K29: 3.9 | L29: 418.7 | M29: 700.8 | N29: =+SUM(C29:M29) -> 7587.3 | T29: P.C.H. CHAGLLA | U29: 154.8
B30: 12:00 | C30: 1074.1 | D30: 2718.1 | E30: 2280 | F30: 46 | H30: =+DESPACHO_EJECUTADO!FE34+DESPACHO_EJECUTADO!FF34 -> 59 | J30: 61.4 | K30: 3.7 | L30: 446.3 | M30: 691.3 | N30: =+SUM(C30:M30) -> 7379.9 | S30: EMPRESA DE GENERACION HUANZA | T30: C.H. HUANZA | V30: 1565.9
B31: 12:30 | C31: 1070.4 | D31: 2623.4 | E31: 2369.6 | F31: 46 | H31: =+DESPACHO_EJECUTADO!FE35+DESPACHO_EJECUTADO!FF35 -> 61 | J31: 61.6 | K31: 3.7 | L31: 408.5 | M31: 687.4 | N31: =+SUM(C31:M31) -> 7331.6 | S31: EMPRESA ELECTRICA AGUA AZUL | T31: C.H. POTRERO | U31: 477.05
B32: 13:00 | C32: 1069.4 | D32: 2562 | E32: 2379.7 | F32: 46.1 | H32: =+DESPACHO_EJECUTADO!FE36+DESPACHO_EJECUTADO!FF36 -> 60.7 | J32: 60.8 | K32: 3.7 | L32: 385.1 | M32: 691 | N32: =+SUM(C32:M32) -> 7258.5 | S32: EMPRESA ELECTRICA RIO DOBLE | T32: C.H. LAS PIZARRAS | U32: 424.65
B33: 13:30 | C33: 1065.7 | D33: 2541.3 | E33: 2350.6 | F33: 46.3 | H33: =+DESPACHO_EJECUTADO!FE37+DESPACHO_EJECUTADO!FF37 -> 60.9 | J33: 62.9 | K33: 3.7 | L33: 376.1 | M33: 702.1 | N33: =+SUM(C33:M33) -> 7209.6 | S33: ENGIE ENERGIA PERU S.A.A. | T33: C.H. YUNCAN | V33: 2224.3
B34: 14:00 | C34: 1066.8 | D34: 2549.8 | E34: 2428.9 | F34: 46.3 | H34: =+DESPACHO_EJECUTADO!FE38+DESPACHO_EJECUTADO!FF38 -> 60.5 | J34: 63 | K34: 3.7 | L34: 304.6 | M34: 706.4 | N34: =+SUM(C34:M34) -> 7230 | S34: GENERACIÓN ANDINA S.A.C. | T34: C.H. 8 DE AGOSTO | U34: 493.6
B35: 14:30 | C35: 1067.4 | D35: 2644.3 | E35: 2449.1 | F35: 46.8 | H35: =+DESPACHO_EJECUTADO!FE39+DESPACHO_EJECUTADO!FF39 -> 60.4 | J35: 63.4 | K35: 3.7 | L35: 306.2 | M35: 705.2 | N35: =+SUM(C35:M35) -> 7346.5 | T35: C.H. EL CARMEN | U35: 171.15
B36: 15:00 | C36: 1068 | D36: 2743.9 | E36: 2291.5 | F36: 46.8 | H36: =+DESPACHO_EJECUTADO!FE40+DESPACHO_EJECUTADO!FF40 -> 62.6 | J36: 64.1 | K36: 3.7 | L36: 362 | M36: 699 | N36: =+SUM(C36:M36) -> 7341.6 | S36: GENERADORA DE ENERGÍA DEL PERÚ | T36: C.H. ÁNGEL I | U36: 413.85
B37: 15:30 | C37: 1062.6 | D37: 2734.1 | E37: 2415.1 | F37: 47 | H37: =+DESPACHO_EJECUTADO!FE41+DESPACHO_EJECUTADO!FF41 -> 60.8 | J37: 60.4 | K37: 3.7 | L37: 283 | M37: 682.5 | N37: =+SUM(C37:M37) -> 7349.2 | T37: C.H. ÁNGEL II | U37: 436.1
B38: 16:00 | C38: 1063.5 | D38: 2685.6 | E38: 2393.1 | F38: 47 | H38: =+DESPACHO_EJECUTADO!FE42+DESPACHO_EJECUTADO!FF42 -> 59.6 | J38: 61.8 | K38: 3.7 | L38: 318 | M38: 701 | N38: =+SUM(C38:M38) -> 7333.3 | T38: C.H. ÁNGEL III | U38: 438.15
B39: 16:30 | C39: 1057.6 | D39: 2709.2 | E39: 2399.9 | F39: 47.3 | H39: =+DESPACHO_EJECUTADO!FE43+DESPACHO_EJECUTADO!FF43 -> 49.8 | J39: 62.8 | K39: 3.7 | L39: 235.6 | M39: 739.8 | N39: =+SUM(C39:M39) -> 7305.7 | T39: C.H. LA JOYA | U39: 189.95
B40: 17:00 | C40: 1060.7 | D40: 2898 | E40: 2326.7 | F40: 47.2 | H40: =+DESPACHO_EJECUTADO!FE44+DESPACHO_EJECUTADO!FF44 -> 60.3 | J40: 64.2 | K40: 3.7 | L40: 73.1 | M40: 728.1 | N40: =+SUM(C40:M40) -> 7262 | S40: HIDROCAÑETE S.A. | T40: C.H. IMPERIAL | U40: 83.1
B41: 17:30 | C41: 1072.4 | D41: 2840.6 | E41: 2335.2 | F41: 47.4 | H41: =+DESPACHO_EJECUTADO!FE45+DESPACHO_EJECUTADO!FF45 -> 60.1 | J41: 64.6 | K41: 3.9 | L41: 37.1 | M41: 774.5 | N41: =+SUM(C41:M41) -> 7235.8 | S41: HIDROELECTRICA HUANCHOR S.A.C. | T41: C.H. HUANCHOR | U41: 442.4
B42: 18:00 | C42: 1059.8 | D42: 2578.4 | E42: 2497.4 | F42: 47.5 | H42: =+DESPACHO_EJECUTADO!FE46+DESPACHO_EJECUTADO!FF46 -> 60.5 | J42: 63.6 | K42: 3.9 | L42: 0 | M42: 767.2 | N42: =+SUM(C42:M42) -> 7078.3 | S42: HUAURA POWER GROUP S.A. | T42: C.H. YARUCAYA | U42: 446.4
B43: 18:30 | C43: 1072 | D43: 2784.7 | E43: 2695.2 | F43: 47.5 | H43: =+DESPACHO_EJECUTADO!FE47+DESPACHO_EJECUTADO!FF47 -> 60.3 | J43: 63.99 | K43: 3.9 | L43: 0 | M43: 765.4 | N43: =+SUM(C43:M43) -> 7492.99 | S43: HYDRO GLOBAL PERÚ S.A.C. | T43: CH SAN GABAN III | V43: 4031.8
B44: 19:00 | C44: 1067.5 | D44: 2856.1 | E44: 2619.2 | F44: 47.6 | H44: =+DESPACHO_EJECUTADO!FE48+DESPACHO_EJECUTADO!FF48 -> 60.2 | J44: 61.62 | K44: 4.1 | L44: 0 | M44: 731.8 | N44: =+SUM(C44:M44) -> 7448.12 | S44: INLAND ENERGY SAC | T44: C.H. SANTA TERESA | U44: 1823.05
B45: 19:30 | C45: 1073.2 | D45: 2849.4 | E45: 2648.8 | F45: 47.3 | H45: =+DESPACHO_EJECUTADO!FE49+DESPACHO_EJECUTADO!FF49 -> 60 | J45: 62.18 | K45: 3.9 | L45: 0 | M45: 692 | N45: =+SUM(C45:M45) -> 7436.78 | S45: INVERSIONES SHAQSHA S.A.C. | T45: C.H. PARIAC | U45: 88.15
B46: 20:00 | C46: 1065 | D46: 2876.6 | E46: 2646.2 | F46: 47.6 | H46: =+DESPACHO_EJECUTADO!FE50+DESPACHO_EJECUTADO!FF50 -> 58.6 | J46: 61.71 | K46: 4.5 | L46: 0 | M46: 656.5 | N46: =+SUM(C46:M46) -> 7416.71 | S46: KALLPA GENERACION S.A. | T46: C.H. CERRO DEL AGUILA | V46: 7573.55
B47: 20:30 | C47: 1065.3 | D47: 2850.5 | E47: 2608.2 | F47: 47.6 | H47: =+DESPACHO_EJECUTADO!FE51+DESPACHO_EJECUTADO!FF51 -> 59 | J47: 59.84 | K47: 4.7 | L47: 0 | M47: 691.2 | N47: =+SUM(C47:M47) -> 7386.34 | T47: M.C.H. CERRO DEL AGUILA | U47: 137.6
B48: 21:00 | C48: 1066.5 | D48: 2822.3 | E48: 2567.4 | F48: 47.7 | H48: =+DESPACHO_EJECUTADO!FE52+DESPACHO_EJECUTADO!FF52 -> 57.8 | J48: 59.85 | K48: 4.7 | L48: 0 | M48: 676.6 | N48: =+SUM(C48:M48) -> 7302.85 | S48: LA VIRGEN | T48: C.H. LA VIRGEN | V48: 1174.3
B49: 21:30 | C49: 1060.8 | D49: 2666 | E49: 2645.9 | F49: 47.8 | H49: =+DESPACHO_EJECUTADO!FE53+DESPACHO_EJECUTADO!FF53 -> 58.9 | J49: 61.26 | K49: 4.6 | L49: 0 | M49: 692.9 | N49: =+SUM(C49:M49) -> 7238.16 | S49: MAJA ENERGIA S.A.C. | T49: C.H. RONCADOR | U49: 73.85
B50: 22:00 | C50: 1059 | D50: 2678.1 | E50: 2541.5 | F50: 47.7 | H50: =+DESPACHO_EJECUTADO!FE54+DESPACHO_EJECUTADO!FF54 -> 58.4 | J50: 51.91 | K50: 4.6 | L50: 0 | M50: 696.9 | N50: =+SUM(C50:M50) -> 7138.11 | S50: ORAZUL ENERGY PERÚ | T50: C.H. CAÑON DEL PATO | V50: 4845.7
B51: 22:30 | C51: 1017.2 | D51: 2590.8 | E51: 2546.1 | F51: 47.9 | H51: =+DESPACHO_EJECUTADO!FE55+DESPACHO_EJECUTADO!FF55 -> 58.4 | J51: 60.7 | K51: 4.6 | L51: 0 | M51: 691.9 | N51: =+SUM(C51:M51) -> 7017.6 | T51: C.H. CARHUAQUERO | V51: 2084.45
B52: 23:00 | C52: 1006.7 | D52: 2361.2 | E52: 2593.6 | F52: 47.8 | H52: =+DESPACHO_EJECUTADO!FE56+DESPACHO_EJECUTADO!FF56 -> 58.5 | J52: 62.32 | K52: 4.6 | L52: 0 | M52: 635.6 | N52: =+SUM(C52:M52) -> 6770.32 | S52: ORYGEN PERU S.A.A. | T52: C.H. CALLAHUANCA | V52: 1120.05
B53: 23:30 | C53: 1054.1 | D53: 2315.9 | E53: 2531.4 | F53: 47.7 | H53: =+DESPACHO_EJECUTADO!FE57+DESPACHO_EJECUTADO!FF57 -> 58.9 | J53: 62.22 | K53: 4.6 | L53: 0 | M53: 598.1 | N53: =+SUM(C53:M53) -> 6672.92 | T53: C.H. HER 1 | U53: 14.4
B54: 00:00 | C54: 1060.2 | D54: 2355.7 | E54: 2299.2 | F54: 42.9 | H54: =+DESPACHO_EJECUTADO!FE58+DESPACHO_EJECUTADO!FF58 -> 59.1 | J54: 61.8 | K54: 4.6 | L54: 0 | M54: 607.7 | N54: =+SUM(C54:M54) -> 6491.2 | T54: C.H. HUAMPANI | U54: 717.7
B55: TOTAL MWh | C55: =SUM(C7:C54)/2 -> 25682.55 | D55: =SUM(D7:D54)/2 -> 62942 | E55: =SUM(E7:E54)/2 -> 55228.45 | F55: =SUM(F7:F54)/2 -> 678.7 | G55: =SUM(G7:G54)/2 -> 0 | H55: =SUM(H7:H54)/2 -> 1416.95 | I55: =SUM(I7:I54)/2 -> 0 | J55: =SUM(J7:J54)/2 -> 1326 | ... N55: =SUM(N7:N54)/2 -> 165397.3 | T55: C.H. HUINCO | V55: 3362.45
B56: % | C56: =+C55/$N$55 -> 0.15527793 | D56: =+D55/$N$55 -> 0.38055035 | E56: =+E55/$N$55 -> 0.33391385 | F56: =+F55/$N$55 -> 0.0041034527 | G56: =+G55/$N$55 -> 0 | H56: =+H55/$N$55 -> 0.0085669476 | I56: =+I55/$N$55 -> 0 | J56: =+J55/$N$55 -> 0.0080170595 | ... N56: =+N55/$N$55 -> 1 | T56: C.H. MATUCANA | V56: 2075.1
T57: C.H. MOYOPAMPA | U57: 1532.5
S58: PERUANA DE INVERSIONES EN ENERGIAS RENOVABLES S.A. | T58: C.H. MANTA I | U58: 293.65
S59: SAN GABAN | T59: C.H. SAN GABAN II | V59: 2387.35
T60: PCH TUPURI | U60: 21.75
S61: SINERSA | T61: C.H. CHANCAY | U61: 445.9
T62: C.H. POECHOS II | U62: 148.15
S63: STATKRAFT S.A | T63: C.H. ARCATA | U63: 48
T64: C.H. CAHUA | U64: 1068.8
T65: C.H. CHEVES | V65: 1626.3
T66: C.H. GALLITO CIEGO | V66: 417.4
T67: C.H. MALPASO | V67: 554.85
T68: C.H. OROYA | U68: 179.95
T69: C.H. PACHACHACA | U69: 144.45
T70: C.H. YAUPI | U70: 2584.55
S71: VARI ENERGIA S.A.C. | T71: C.H. ANASHIRONI | U71: 426.05
S72: TOTAL MWh | U72: 25682.55 | V72: 62942

Sheet DEMANDA_UL
B3: miércoles, 5 de Noviembre del 2025
B5: POTENCIA DE LOS GRANDES USUARIOS LIBRES (MW)
B6: FECHA HORA | C6: GRANDES USUARIOS LIBRES DEL ÁREA NORTE | X6: GRANDES USUARIOS LIBRES DEL ÁREA CENTRO | BP6: GRANDES USUARIOS LIBRES DEL ÁREA SUR
C7: ARCA CONTINENTAL LINDLEY S.A. | D7: AUSTRAL GROUP S.A.A | E7: CEMENTOS PACASMAYO | F7: CONSORCIO MINERO HORIZONTE S.R.L. | G7: CORPORACIÓN PESQUERA INCA S.A.C. | H7: CREDITEX: CIA IND.TEXTIL CREDISA | I7: HIPERMERCADOS TOTTUS S.A | J7: INDUSTRIA TEXTIL PIURA | K7: MINERA BOROO MISQUICHILCA S.A. | L7: MINERA GOLD FIELDS | M7: MINERA MARSA | N7: MINERA MISKY MAYO | O7: MINERA YANACOCHA | P7: OPEN PLAZA | Q7: PESQUERA DIAMANTE | R7: PETROPERU | S7: REAL PLAZA S.R.L. | T7: SIDER PERU | U7: SUPERMERCADOS PERUANOS S.A. | V7: TRUPAL S.A. | W7: UNIÓN DE CERVECERÍAS PERUANAS BACKUS Y JOHNSTON S. | X7: ACEROS AREQUIPA | Y7: ADMINISTRADORA JOCKEY PLAZA SHOPPING CENTER S.A. | Z7: ALICORP | AA7: ARCA CONTINENTAL LINDLEY S.A. | AB7: AUSTRAL GROUP S.A.A | AC7: COMPAÑIA MINERA CONDESTABLE | AD7: CORPORACIÓN PESQUERA INCA S.A.C. | AE7: CREDITEX: CIA IND.TEXTIL CREDISA | AF7: FUNDICION CHILCA S.A. | AG7: HIPERMERCADOS TOTTUS S.A | AH7: INMOBILIARIA KANPU S.A. | AI7: INMUEBLES PANAMERICANA S.A. | AJ7: KIMBERLY-CLARK PERU | AK7: LECHE GLORIA S.A. | AL7: MALL AVENTURA S.A. | AM7: MARCOBRE S.A.C. | AN7: MINERA ANTAMINA | AO7: MINERA ARES | AP7: MINERA BUENAVENTURA | AQ7: MINERA CHINALCO PERÚ S.A. | AR7: MINERA SHOUXIN PERU S.A. | AS7: MINERA VOLCAN | AT7: MINSUR | AU7: MOLYCOP-ADESUR | AV7: NEXA RESOURCES CAJAMARQUILLA S.A. | AW7: NEXA RESOURCES PERÚ S.A.A. | AX7: OPEN PLAZA | AY7: OPP FILM | AZ7: OWENS-ILLINOIS PERÚ S.A. | BA7: PAPELERA NACIONAL S.A. | BB7: PESQUERA DIAMANTE | BC7: QUIMPAC S.A. | BD7: REAL PLAZA S.R.L. | BE7: REFINERIA LA PAMPILLA S.A.A | BF7: SAGA FALABELLA | BG7: SAN MIGUEL INDUSTRIAS PET S.A. | BH7: SHOUGANG HIERRO PERU | BI7: SOFTYS PERU S.A.C. | BJ7: SUPERMERCADOS PERUANOS S.A. | BK7: TEJIDOS SAN JACINTO | BL7: TREN URBANO DE LIMA S.A. | BM7: TRUPAL S.A. | BN7: UNACEM PERU S.A. | BO7: UNIÓN DE CERVECERÍAS PERUANAS BACKUS Y JOHNSTON S. | BP7: ANGLO AMERICAN QUELLAVECO S.A. | BQ7: ARCA CONTINENTAL LINDLEY S.A. | BR7: CAL & CEMENTO SUR S.A. | BS7: COMPAÑIA MINERA ANTAPACCAY S.A. | BT7: COMPAÑÍA MINERA CHUNGAR SAC | BU7: COMPAÑIA MINERA SAN IGNACIO DE MOROCOCHA S.A.A. | BV7: EL BROCAL .S.A. | BW7: EMPRESA ADMINISTRADORA CERRO S.A.C. | BX7: EMPRESA MINERA LOS QUENUALES S.A.C. | BY7: HIPERMERCADOS TOTTUS S.A | BZ7: HUDBAY PERU S.A.C. | CA7: INDUSTRIA CACHIMAYO | CB7: MALL AVENTURA S.A. | CC7: MINERA ARES | CD7: MINERA BUENAVENTURA | CE7: MINERA CERRO VERDE | CF7: MINERA CORONA | CG7: MINERA LAS BAMBAS S.A. | CH7: MINERA VOLCAN | CI7: MINSUR | CJ7: MOLYCOP-ADESUR | CK7: NEXA RESOURCES PERÚ S.A.A. | CL7: OXIDOS DE PASCO S.A.C. | CM7: PESQUERA DIAMANTE | CN7: REAL PLAZA S.R.L. | CO7: SOBREANDES S.A.C. | CP7: SOUTHERN PERU CC | CQ7: SUPERMERCADOS PERUANOS S.A. | CR7: UNACEM PERU S.A. | CS7: UNIÓN DE CERVECERÍAS PERUANAS BACKUS Y JOHNSTON S. | CT7: YURA
B8: 00:30 | E8: 24.672 | F8: 13.497 | H8: 4.146 | L8: 28.4327 | M8: 13.7114 | N8: 12.94 | O8: 36.542 | R8: 51.588 | T8: 15.5233 | V8: 4.4 | X8: 157.84058 | Z8: 7.5682 | AC8: 10.89 | AE8: 4.587 | AF8: 5.2 | AH8: 5.8124 | AJ8: 5.33786 | AK8: 0 | AM8: 50.85897 | AN8: 118.6779 | AO8: 28.02538 | AP8: 0.81 | AQ8: 171.8514 | AS8: 38.38059 | AT8: 32.21138 | AV8: 194.67666 | AW8: 34.10349 | BA8: 2.5 | BC8: 72.69053 | BI8: 16.76176 | BK8: 5.54332 | BM8: 6.521 | BN8: 54.474 | BO8: 2.04 | BP8: 88.08872 | BR8: 3.5871 | BS8: 127.57793 | BT8: 12.15707 | BW8: 3.85819 | BZ8: 89.8562 | CA8: 24.96377 | CC8: 0.678 | CD8: 25.69221 | CE8: 169.21348 | CG8: 153.09806 | CH8: 18.05011 | CK8: 16.2705 | CL8: 4.8157 | CO8: 16.64781 | CP8: 285.44 | CR8: 33.572 | CT8: 29.213
B9: 01:00 | E9: 24.691 | F9: 13.212 | H9: 4.085 | L9: 28.6558 | M9: 13.8272 | N9: 12.99 | O9: 36.076 | R9: 51.167 | T9: 15.3699 | V9: 4.6 | X9: 142.47313 | Z9: 7.71888 | AC9: 11.66 | AE9: 4.642 | AF9: 7.2 | AH9: 4.5476 | AJ9: 5.33431 | AK9: 0 | AM9: 50.90679 | AN9: 119.50257 | AO9: 27.71667 | AP9: 0.7 | AQ9: 171.3009 | AS9: 37.92826 | AT9: 34.99022 | AV9: 191.61268 | AW9: 34.13692 | BA9: 2.4 | BC9: 72.00168 | BI9: 17.00525 | BK9: 5.62236 | BM9: 6.362 | BN9: 51.271 | BO9: 2.33 | BP9: 88.09992 | BR9: 3.638 | BS9: 128.03722 | BT9: 12.06734 | BW9: 3.96348 | BZ9: 90.67838 | CA9: 24.97743 | CC9: 0.669 | CD9: 23.51185 | CE9: 167.95986 | CG9: 153.35667 | CH9: 17.61171 | CK9: 17.1147 | CL9: 4.76425 | CO9: 16.35368 | CP9: 283.54 | CR9: 33.503 | CT9: 30.079
B10: 01:30 | E10: 23.9 | F10: 13.067 | H10: 4.15 | L10: 28.2481 | M10: 14.2097 | N10: 12.99 | O10: 36.034 | R10: 51.021 | T10: 18.4589 | V10: 5 | X10: 142.51603 | Z10: 7.43111 | AC10: 11.71 | AE10: 4.541 | AF10: 4 | AH10: 3.4672 | AJ10: 5.31128 | AK10: 0 | AM10: 50.00916 | AN10: 119.43528 | AO10: 27.79475 | AP10: 0.64 | AQ10: 169.8961 | AS10: 38.20058 | AT10: 34.52905 | AV10: 189.72474 | AW10: 33.33833 | BA10: 2.4 | BC10: 72.06862 | BI10: 16.76422 | BK10: 5.53169 | BM10: 6.362 | BN10: 52.183 | BO10: 2.26 | BP10: 89.84274 | BR10: 3.7376 | BS10: 128.02598 | BT10: 12.03021 | BW10: 4.0073 | BZ10: 90.6258 | CA10: 24.97212 | CC10: 0.653 | CD10: 24.2492 | CE10: 170.62604 | CG10: 149.66437 | CH10: 17.9441 | CK10: 18.2366 | CL10: 4.74491 | CO10: 15.97262 | CP10: 282.22 | CR10: 34.353 | CT10: 29.982
B11: 02:00 | E11: 23.413 | F11: 13.601 | H11: 4.114 | L11: 28.0594 | M11: 13.852 | N11: 12.92 | O11: 35.772 | R11: 51.331 | T11: 18.7917 | V11: 5.4 | X11: 139.90195 | Z11: 7.72617 | AC11: 11.03 | AE11: 4.503 | AF11: 3.3 | AH11: 4.7291 | AJ11: 5.27359 | AK11: 0 | AM11: 50.4936 | AN11: 121.32222 | AO11: 27.09637 | AP11: 0.44 | AQ11: 171.2569 | AS11: 38.34046 | AT11: 35.43743 | AV11: 191.95137 | AW11: 33.50528 | BA11: 2.5 | BC11: 71.83893 | BI11: 16.7064 | BK11: 5.37297 | BM11: 6.213 | BN11: 51.894 | BO11: 2.11 | BP11: 89.65375 | BR11: 3.6615 | BS11: 127.20191 | BT11: 11.92649 | BW11: 3.7307 | BZ11: 91.10491 | CA11: 24.96261 | CC11: 0.659 | CD11: 24.9907 | CE11: 168.84548 | CG11: 151.26621 | CH11: 17.54141 | CK11: 17.373 | CL11: 4.79454 | CO11: 16.18373 | CP11: 274.33 | CR11: 34.491 | CT11: 29.63
B12: 02:30 | E12: 24.112 | F12: 13.112 | H12: 3.99 | L12: 28.3518 | M12: 13.8819 | N12: 12.93 | O12: 35.746 | R12: 51.515 | T12: 18.5288 | V12: 6.2 | X12: 100.6883 | Z12: 7.78389 | AC12: 10.69 | AE12: 4.344 | AF12: 4.1 | AH12: 1.2703 | AJ12: 5.22184 | AK12: 0 | AM12: 50.02575 | AN12: 121.64146 | AO12: 27.27865 | AP12: 0.41 | AQ12: 169.3369 | AS12: 38.43971 | AT12: 35.29674 | AV12: 191.72174 | AW12: 34.33378 | BA12: 2.4 | BC12: 71.90233 | BI12: 17.0633 | BK12: 5.36358 | BM12: 6.321 | BN12: 52.078 | BO12: 2.14 | BP12: 91.54737 | BR12: 3.6746 | BS12: 127.2348 | BT12: 12.44524 | BW12: 3.87202 | BZ12: 91.40419 | CA12: 24.97083 | CC12: 0.703 | CD12: 26.06163 | CE12: 172.51193 | CG12: 154.86497 | CH12: 17.0782 | CK12: 17.0851 | CL12: 4.69194 | CO12: 15.99962 | CP12: 273.37 | CR12: 34.199 | CT12: 29.807
B13: 03:00 | E13: 23.337 | F13: 12.752 | H13: 3.999 | L13: 28.1772 | M13: 14.0841 | N13: 12.84 | O13: 35.544 | R13: 51.46 | T13: 18.4443 | V13: 6.9 | X13: 168.11144 | Z13: 8.01934 | AC13: 10.59 | AE13: 4.28 | AF13: 2.7 | AH13: 1.1936 | AJ13: 4.81592 | AK13: 0 | AM13: 51.19666 | AN13: 121.08886 | AO13: 27.01355 | AP13: 0.67 | AQ13: 167.6807 | AS13: 38.31366 | AT13: 34.68703 | AV13: 192.70316 | AW13: 34.50588 | BA13: 2.5 | BC13: 71.07842 | BI13: 16.84639 | BK13: 5.34542 | BM13: 6.521 | BN13: 51.243 | BO13: 2.19 | BP13: 92.13255 | BR13: 3.6669 | BS13: 124.06486 | BT13: 12.57967 | BW13: 3.96593 | BZ13: 93.37712 | CA13: 24.96309 | CC13: 0.66 | CD13: 25.02669 | CE13: 173.09561 | CG13: 155.15318 | CH13: 16.72562 | CK13: 17.829 | CL13: 4.77718 | CO13: 16.19517 | CP13: 284.15 | CR13: 34.46 | CT13: 29.843
B14: 03:30 | E14: 24.186 | F14: 13.346 | H14: 4.099 | L14: 27.7942 | M14: 14.2124 | N14: 12.84 | O14: 35.356 | R14: 51.34 | T14: 16.3768 | V14: 7.1 | X14: 153.31872 | Z14: 7.82946 | AC14: 10.8 | AE14: 4.201 | AF14: 3.6 | AH14: 4.8985 | AJ14: 5.05719 | AK14: 0 | AM14: 52.27218 | AN14: 121.70819 | AO14: 26.78053 | AP14: 0.48 | AQ14: 171.0518 | AS14: 37.96752 | AT14: 33.52248 | AV14: 194.48884 | AW14: 33.99988 | BA14: 2.4 | BC14: 71.39723 | BI14: 16.87625 | BK14: 5.30877 | BM14: 6.851 | BN14: 48.758 | BO14: 2.18 | BP14: 89.71489 | BR14: 3.6746 | BS14: 126.95901 | BT14: 12.48856 | BW14: 4.02736 | BZ14: 90.76081 | CA14: 25.01624 | CC14: 0.665 | CD14: 25.00222 | CE14: 173.63688 | CG14: 154.06229 | CH14: 17.41063 | CK14: 17.7951 | CL14: 4.70158 | CO14: 16.43922 | CP14: 270.71 | CR14: 33.222 | CT14: 30.016
B15: 04:00 | E15: 24.554 | F15: 13.105 | H15: 4.143 | L15: 27.9259 | M15: 14.2726 | N15: 12.78 | O15: 34.736 | R15: 51.349 | T15: 18.4588 | V15: 7.2 | X15: 145.35795 | Z15: 8.04424 | AC15: 10.97 | AE15: 4.124 | AF15: 3.4 | AH15: 4.8159 | AJ15: 5.19055 | AK15: 0 | AM15: 52.64581 | AN15: 123.02359 | AO15: 27.4216 | AP15: 0.18 | AQ15: 168.7591 | AS15: 37.75796 | AT15: 33.36664 | AV15: 194.7397 | AW15: 34.67265 | BA15: 2.4 | BC15: 70.98615 | BI15: 16.95914 | BK15: 5.26811 | BM15: 6.253 | BN15: 48.485 | BO15: 2.09 | BP15: 89.97242 | BR15: 3.6039 | BS15: 124.66546 | BT15: 12.55996 | BW15: 3.88656 | BZ15: 92.91903 | CA15: 25.0267 | CC15: 0.655 | CD15: 25.24264 | CE15: 172.33422 | CG15: 156.66148 | CH15: 17.56693 | CK15: 17.2922 | CL15: 4.43531 | CO15: 16.42487 | CP15: 275.36 | CR15: 33.047 | CT15: 30.032
B16: 04:30 | E16: 25.188 | F16: 12.586 | H16: 3.862 | L16: 27.9929 | M16: 15.0825 | N16: 13.2 | O16: 34.582 | R16: 51.432 | T16: 18.873 | V16: 7.3 | X16: 140.22758 | Z16: 8.3767 | AC16: 12.05 | AE16: 4.162 | AF16: 5.3 | AH16: 3.5025 | AJ16: 5.28152 | AK16: 0 | AM16: 52.86536 | AN16: 123.76224 | AO16: 27.16124 | AP16: 1.65 | AQ16: 170.9128 | AS16: 37.66299 | AT16: 32.45563 | AV16: 193.97352 | AW16: 34.75961 | BA16: 2.33 | BC16: 70.99266 | BI16: 17.03582 | BK16: 5.33964 | BM16: 6.475 | BN16: 48.124 | BO16: 1.72 | BP16: 99.64661 | BR16: 3.6445 | BS16: 128.18703 | BT16: 12.14232 | BW16: 3.90366 | BZ16: 92.29965 | CA16: 25.07299 | CC16: 0.669 | CD16: 25.65747 | CE16: 170.44718 | CG16: 154.67528 | CH16: 17.85675 | CK16: 16.8133 | CL16: 4.45259 | CO16: 16.22624 | CP16: 276.17 | CR16: 33.407 | CT16: 30.166
B17: 05:00 | E17: 25.338 | F17: 12.524 | H17: 4.086 | L17: 28.031 | M17: 15.4361 | N17: 13.42 | O17: 34.756 | R17: 51.363 | T17: 18.92 | V17: 7.4 | X17: 49.09073 | Z17: 8.52332 | AC17: 12.22 | AE17: 4.363 | AF17: 4.2 | AH17: 4.8393 | AJ17: 5.03627 | AK17: 0 | AM17: 53.15004 | AN17: 124.38642 | AO17: 26.984 | AP17: 2.1 | AQ17: 168.3303 | AS17: 36.21948 | AT17: 31.78671 | AV17: 193.61265 | AW17: 33.79777 | BA17: 2.2 | BC17: 71.4568 | BI17: 16.91788 | BK17: 5.38035 | BM17: 6.2651 | BN17: 46.349 | BO17: 1.95 | BP17: 124.39647 | BR17: 3.6313 | BS17: 128.21294 | BT17: 11.02862 | BW17: 4.37541 | BZ17: 92.13941 | CA17: 25.29761 | CC17: 0.69 | CD17: 24.21093 | CE17: 173.85333 | CG17: 154.12975 | CH17: 17.68666 | CK17: 16.9341 | CL17: 4.51662 | CO17: 16.04969 | CP17: 279.89 | CR17: 33.818 | CT17: 30.094
B18: 05:30 | E18: 29.218 | F18: 11.201 | H18: 4.097 | L18: 28.5882 | M18: 15.0197 | N18: 13.49 | O18: 35.472 | R18: 51.462 | T18: 18.6116 | V18: 7.4 | X18: 138.31039 | Z18: 8.33678 | AC18: 12.77 | AE18: 4.353 | AF18: 3.6 | AH18: 4.7799 | AJ18: 5.08865 | AK18: 0 | AM18: 52.98912 | AN18: 121.69547 | AO18: 25.52436 | AP18: 1.93 | AQ18: 140.1214 | AS18: 35.51138 | AT18: 31.72384 | AV18: 193.34565 | AW18: 33.36045 | BA18: 2 | BC18: 71.32728 | BI18: 16.90191 | BK18: 5.33356 | BM18: 6.4151 | BN18: 47.198 | BO18: 1.92 | BP18: 132.19732 | BR18: 3.6946 | BS18: 131.34237 | BT18: 11.17149 | BW18: 3.85894 | BZ18: 91.11005 | CA18: 25.28001 | CC18: 0.637 | CD18: 24.03434 | CE18: 173.89467 | CG18: 151.53844 | CH18: 17.97406 | CK18: 16.6023 | CL18: 4.49691 | CO18: 15.11419 | CP18: 280.61 | CR18: 36.642 | CT18: 29.598
B19: 06:00 | E19: 29.837 | F19: 10.648 | H19: 4.056 | L19: 28.4863 | M19: 14.3221 | N19: 13.48 | O19: 35.354 | R19: 51.34 | T19: 18.0331 | V19: 7.3 | X19: 147.50717 | Z19: 8.47523 | AC19: 11.55 | AE19: 4.456 | AF19: 3.5 | AH19: 5.04 | AJ19: 5.10208 | AK19: 0 | AM19: 53.00816 | AN19: 122.12586 | AO19: 21.9883 | AP19: 1.54 | AQ19: 114.1494 | AS19: 34.54472 | AT19: 32.28817 | AV19: 194.05522 | AW19: 32.28338 | BA19: 2.2 | BC19: 71.60836 | BI19: 16.85179 | BK19: 5.38394 | BM19: 6.565 | BN19: 46.88 | BO19: 1.81 | BP19: 138.39069 | BR19: 3.5849 | BS19: 129.73916 | BT19: 11.13025 | BW19: 3.65085 | BZ19: 91.91646 | CA19: 25.27532 | CC19: 0.707 | CD19: 22.48353 | CE19: 164.03894 | CG19: 156.20921 | CH19: 17.6502 | CK19: 16.8856 | CL19: 4.48658 | CO19: 13.55981 | CP19: 286.27 | CR19: 40.682 | CT19: 27.146
... B55: 00:00 | E55: 31.873 | F55: 12.338 | H55: 0 | L55: 27.055 | M55: 13.371 | N55: 10.11 | O55: 34.082 | R55: 50.624 | T55: 19.1303 | V55: 8.2 | X55: 103.76179 | Z55: 8.86095 | AC55: 10.96 | AE55: 0 | AF55: 2.9 | AH55: 5.1719 | AJ55: 5.27586 | AK55: 0 | AM55: 53.07166 | AN55: 124.65416 | AO55: 28.76855 | AP55: 0.83 | AQ55: 74.2872 | AS55: 37.28432 | AT55: 31.3933 | AV55: 195.75296 | AW55: 33.55881 | BA55: 1.3 | BC55: 72.87532 | BI55: 17.70148 | BK55: 5.38158 | BM55: 6.521 | BN55: 48.684 | BO55: 2.16 | BP55: 144.43687 | BR55: 4.3582 | BS55: 128.01188 | BT55: 10.20781 | BW55: 3.83695 | BZ55: 91.87649 | CA55: 24.8654 | CC55: 0.648 | CD55: 25.08017 | CE55: 174.34962 | CG55: 154.85477 | CH55: 17.69945 | CK55: 18.7104 | CL55: 5.05923 | CO55: 16.03971 | CP55: 276.37 | CR55: 38.756 | CT55: 24.128
B56: MWh | C56: 0 | D56: 0 | E56: 737.0045 | F56: 291.35175 | G56: 0 | H56: 83.3145 | I56: 0 | J56: 0 | K56: 0 | L56: 681.2004 | M56: 315.6126 | N56: 298.165 | O56: 818.436 | P56: 0 | Q56: 0 | R56: 1203.0035 | S56: 0 | T56: 414.459 | U56: 0 | V56: 193.8 | W56: 0 | X56: 1896.508 | Y56: 0 | Z56: 196.31434 | AA56: 0 | AB56: 0 | AC56: 276.58 | AD56: 0 | AE56: 105.0705 | AF56: 86.05 | AG56: 0 | AH56: 57.61 | AI56: 0 | AJ56: 118.96792 | AK56: 0 | AL56: 0 | AM56: 1208.8994 | AN56: 2899.0707 | AO56: 635.21354 | AP56: 18.01 | AQ56: 2380.9497 | AR56: 0 | AS56: 868.12472 | AT56: 751.4709 | AU56: 0 | AV56: 4237.4572 | AW56: 805.28067 | AX56: 0 | AY56: 0 | AZ56: 0 | BA56: 38.565 | BB56: 0 | BC56: 1527.9928 | BD56: 0 | BE56: 0 | BF56: 0 | BG56: 0 | BH56: 0 | BI56: 413.45836 | BJ56: 0 | BK56: 130.57305 | BL56: 0 | BM56: 154.3993 | BN56: 922.0135 | BO56: 51.44 | BP56: 3115.7006 | BQ56: 0 | BR56: 45.8424 | BS56: 3020.7734 | BT56: 277.74296 | BU56: 0 | BV56: 0 | BW56: 93.445805 | BX56: 0 | BY56: 0 | BZ56: 2174.709 | CA56: 528.686 | CB56: 0 | CC56: 15.7395 | CD56: 578.84127 | CE56: 4021.3494 | CF56: 0 | CG56: 3661.492 | CH56: 416.49257 | CI56: 0 | CJ56: 0 | CK56: 420.0116 | CL56: 107.82695 | CM56: 0 | CN56: 0 | CO56: 363.34796 | CP56: 6518.95 | CQ56: 0 | CR56: 886.0005 | CS56: 0 | CT56: 448.58
B59: Nota :
B60: Información proporcionada por la empresas
C62: DATOS ESTIMADOS
C64: SIN DATOS

Sheet GENERACION RER
B3: miércoles, 5 de Noviembre del 2025
B5: GENERACIÓN ELÉCTRICA DE LAS CENTRALES RER (MW)
B6: HORA | C6: AGRO INDUSTRIAL PARAMONGA S.A. | D6: AGROAURORA S.A.C. | E6: AGROINDUSTRIAS SAN JACINTO S.A.A. | F6: AGROLMOS SOCIEDAD ANONIMA - AGROLMOS S.A. | G6: ANDEAN POWER S.A.C. | H6: ASOCIACIÓN SANTA LUCIA DE CHACAS | I6: ATRIA ENERGIA S.A.C. | J6: BIOENERGIA DEL CHIRA S.A. | K6: COLCA SOLAR S.A.C. | L6: EGEJUNIN | Q6: ELECTRICA YANAPAMPA SAC | R6: EMPRESA DE GENERACION ELECTRICA CANCHAYLLO SAC | S6: EMPRESA DE GENERACION ELECTRICA RIO BAÑOS S.A.C. | T6: EMPRESA DE GENERACION ELECTRICA SANTA ANA S.A.C. | U6: EMPRESA ELECTRICA AGUA AZUL | V6: EMPRESA ELECTRICA RIO DOBLE | W6: ENERGÍA EÓLICA S.A. | Y6: ENERGIA RENOVABLE DEL SUR S.A. | Z6: ENGIE ENERGIA PERU S.A.A. | AE6: GENERACIÓN ANDINA S.A.C. | AG6: GENERADORA DE ENERGÍA DEL PERÚ | AK6: GR CORTARRAMA SOCIEDAD ANONIMA CERRADA | AL6: GR PAINO SOCIEDAD ANONIMA CERRADA | AM6: GR TARUCA SOCIEDAD ANONIMA CERRADA | AN6: HIDROCAÑETE S.A. | AO6: HUAURA POWER GROUP S.A. | AP6: HYDRO PATAPO S.A.C. | AQ6: KONDU SAC | AR6: MAJA ENERGIA S.A.C. | AS6: MAJES ARCUS S.A.C. | AT6: MOQUEGUA FV S.A.C. | AU6: ORAZUL ENERGY PERÚ | AW6: ORYGEN PERU S.A.A. | BB6: PANAMERICANA SOLAR SAC. | BC6: PARQUE EOLICO MARCONA S.A.C. | BD6: PARQUE EOLICO TRES HERMANAS S.A.C. | BE6: PERUANA DE INVERSIONES EN ENERGIAS RENOVABLES S.A. | BF6: PETRAMAS | BJ6: REPARTICIÓN ARCUS S.A.C. | BK6: SAN GABAN | BL6: SINERSA | BN6: TACNA SOLAR SAC. | BO6: VARI ENERGIA S.A.C. | BP6: TOTAL RER
C7: C.T. PARAMONGA | D7: C.T. MAPLE | E7: C.T SAN JACINTO | F7: C.T. AGROLMOS | G7: C.H. CARHUAC | H7: C.H. HUALLIN | I7: C.H. PURMACANA | J7: C.T. CAÑA BRAVA | L7: C.H. HUASAHUASI I | M7: C.H. HUASAHUASI II | N7: C.H. RUNATULLO II | O7: C.H. RUNATULLO III | P7: C.H. STA CRUZ I y II | Q7: C.H. YANAPAMPA | R7: C.H. CANCHAYLLO | S7: C.H. RUCUY | T7: C.H. RENOVANDES H1 | U7: C.H. POTRERO | V7: C.H. LAS PIZARRAS | AE7: C.H. 8 DE AGOSTO | AF7: C.H. EL CARMEN | AG7: C.H. ANGEL I | AH7: C.H. ANGEL II | AI7: C.H. ANGEL III | AJ7: C.H. LA JOYA | AN7: C.H. NUEVAIMPERIAL | AO7: C.H. YARUCAYA | AP7: MCH PATAPO | AR7: C.H. RONCADOR | AU7: C.H. CANA BRAVA | AV7: C.H. CARHUAQUERO4 | BA7: C.H. HER 1 | BE7: C.H. MANTA | BF7: C.T. HUAYCOLORO | BG7: C.T. LA GRINGA V | BH7: CTB CALLAO | BI7: CTB. DONA CATALINA | BK7: C.H. TUPURI | BL7: C.H. CHANCAY | BM7: C.H. POECHOS2 | BO7: C.H. ANASHIRONI | BP7: MW
B8: 0:30 | C8: 15 | E8: 7.1 | F8: 11 | G8: 18.4 | H8: 2.7 | J8: 8.7 | L8: 10.4 | N8: 10.4 | O8: 13.7 | P8: 9.3 | Q8: 3.1 | R8: 3 | S8: 15.5 | U8: 18.4 | V8: 19 | W8: 11.4 | X8: 61 | Y8: 85.3 | Z8: 52.4 | AA8: 84.9 | AC8: 4 | AD8: 2.8 | AE8: 20.9 | AF8: 7.6 | AG8: 18.9 | AH8: 19.8 | AI8: 19.8 | AJ8: 7.9 | AN8: 3.5 | AO8: 18.6 | AR8: 3.3 | AW8: 14.4 | AY8: 12.4 | BA8: 0.6 | BC8: 30.4 | BD8: 84.3 | BE8: 20 | BF8: 1.1 | BG8: 1 | BI8: 1.8 | BK8: 1 | BL8: 18.6 | BM8: 6.1 | BO8: 20.2 | BP8: 799.7
B9: 1:00 | C9: 15 | E9: 7 | F9: 10.5 | G9: 16 | H9: 2.7 | J9: 8 | L9: 10 | N9: 10.4 | O9: 13.9 | P9: 9.3 | Q9: 3.1 | R9: 2.8 | S9: 15.5 | U9: 20 | V9: 19 | W9: 11.5 | X9: 52.4 | Y9: 81.3 | Z9: 65.4 | AA9: 90 | AC9: 8.2 | AD9: 3.9 | AE9: 20.9 | AF9: 7.5 | AG9: 18.5 | AH9: 19.8 | AI9: 19.8 | AJ9: 8 | AM9: 0.3 | AN9: 3.5 | AO9: 18.6 | AR9: 3.3 | AW9: 8.4 | AY9: 8 | BA9: 0.6 | BC9: 29.6 | BD9: 79.6 | BE9: 20 | BF9: 1.1 | BG9: 1 | BI9: 1.8 | BK9: 1 | BL9: 18.6 | BM9: 6.2 | BO9: 20.6 | BP9: 792.6
B10: 1:30 | C10: 14.8 | E10: 6.9 | F10: 10 | G10: 15.8 | H10: 2.7 | J10: 8.5 | L10: 10 | N10: 10.6 | O10: 14.2 | P10: 9.3 | Q10: 3.2 | R10: 2.8 | S10: 15.5 | U10: 19.8 | V10: 18.9 | W10: 16.2 | X10: 53.5 | Y10: 78.8 | Z10: 57 | AA10: 73.8 | AC10: 4.5 | AD10: 1.1 | AE10: 20.9 | AF10: 7.5 | AG10: 18.5 | AH10: 19.8 | AI10: 19.8 | AJ10: 7.9 | AM10: 0.7 | AN10: 3.5 | AO10: 18.6 | AR10: 3.3 | AW10: 1.5 | AY10: 2.7 | BA10: 0.6 | BC10: 25.6 | BD10: 59.7 | BE10: 20 | BF10: 1.1 | BG10: 1 | BI10: 1.8 | BK10: 1 | BL10: 18.6 | BM10: 6.1 | BO10: 20.8 | BP10: 728.9
B11: 2:00 | C11: 15.4 | E11: 7 | F11: 10 | G11: 15.9 | H11: 2.8 | J11: 9.3 | L11: 10 | N11: 10.6 | O11: 14.1 | P11: 9.2 | Q11: 3.2 | R11: 2.8 | S11: 15.6 | U11: 19.6 | V11: 18.9 | W11: 19.4 | X11: 48.9 | Y11: 94.5 | Z11: 29.3 | AA11: 42.5 | AC11: 1.6 | AD11: 1.1 | AE11: 20.9 | AF11: 7.5 | AG11: 18.5 | AH11: 19.8 | AI11: 19.8 | AJ11: 7.9 | AN11: 3.5 | AO11: 18.6 | AR11: 3.2 | AW11: 0.9 | AY11: 6.4 | BA11: 0.6 | BC11: 29.3 | BD11: 47.9 | BE11: 20 | BF11: 1.1 | BG11: 1 | BI11: 1.8 | BK11: 1 | BL11: 18.7 | BM11: 6.1 | BO11: 20.7 | BP11: 676.9
B12: 2:30 | C12: 15.2 | E12: 7.7 | F12: 10 | G12: 15.9 | H12: 2.9 | J12: 9.2 | L12: 10 | N12: 10.1 | O12: 13.7 | P12: 9.2 | Q12: 3.2 | R12: 2.8 | S12: 15.7 | U12: 20 | V12: 18.9 | W12: 20.5 | X12: 44.4 | Y12: 103.8 | Z12: 19.9 | AA12: 28.2 | AC12: 1 | AD12: 0.8 | AE12: 20.9 | AF12: 7.5 | AG12: 18.5 | AH12: 19.3 | AI12: 19.8 | AJ12: 7.9 | AN12: 3.5 | AO12: 18.6 | AR12: 3.3 | AW12: 0.1 | AY12: 0.3 | BA12: 0.6 | BC12: 29.8 | BD12: 64.3 | BE12: 20 | BF12: 1.1 | BG12: 1 | BI12: 1.8 | BK12: 1 | BL12: 18.7 | BM12: 6.1 | BO12: 20.7 | BP12: 667.9
B13: 3:00 | C13: 15.5 | E13: 7.1 | F13: 10.8 | G13: 15.8 | H13: 3 | J13: 9 | L13: 10 | N13: 9.8 | O13: 13.5 | P13: 9.2 | Q13: 3.2 | R13: 2.9 | S13: 15.7 | U13: 19.5 | V13: 18.9 | W13: 19.7 | X13: 41.7 | Y13: 98.2 | Z13: 25.9 | AA13: 46.6 | AC13: 1.3 | AD13: 1.4 | AE13: 20.9 | AF13: 7.5 | AG13: 18.5 | AH13: 19.3 | AI13: 19.3 | AJ13: 8.3 | AN13: 3.5 | AO13: 18.6 | AR13: 3.3 | AW13: 3.2 | BA13: 0.6 | BC13: 27.1 | BD13: 70.7 | BE13: 20 | BF13: 1.1 | BG13: 1 | BI13: 1.8 | BK13: 1 | BL13: 18.8 | BM13: 6.1 | BO13: 20.4 | BP13: 689.7
B14: 3:30 | C14: 15.5 | E14: 7.9 | F14: 11 | G14: 12.5 | H14: 3 | J14: 9.4 | L14: 10.6 | N14: 10.3 | O14: 14.1 | P14: 9.2 | Q14: 2.9 | R14: 2.9 | S14: 15.7 | U14: 20 | V14: 18.9 | W14: 14.3 | X14: 32 | Y14: 96 | Z14: 39 | AA14: 57.4 | AC14: 2.5 | AD14: 0.6 | AE14: 20.9 | AF14: 7.5 | AG14: 18.5 | AH14: 19.3 | AI14: 19.3 | AJ14: 8.1 | AN14: 3.5 | AO14: 18.6 | AR14: 3.3 | AW14: 4.2 | BA14: 0.6 | BC14: 23.5 | BD14: 56 | BE14: 20.1 | BF14: 1.1 | BG14: 1 | BI14: 1.8 | BK14: 1 | BL14: 18.7 | BM14: 6.2 | BO14: 20.7 | BP14: 679.6
B15: 4:00 | C15: 15.5 | E15: 6.7 | F15: 11 | G15: 9.9 | H15: 2.9 | J15: 9.2 | L15: 10.6 | N15: 10.4 | O15: 14 | P15: 9.2 | Q15: 3.1 | R15: 2.8 | S15: 15.8 | U15: 20 | V15: 18.8 | W15: 15.3 | X15: 38.8 | Y15: 79.6 | Z15: 64.3 | AA15: 94.9 | AC15: 4.9 | AD15: 2.9 | AE15: 20.9 | AF15: 7.5 | AG15: 18.5 | AH15: 19.3 | AI15: 19.3 | AJ15: 8.1 | AN15: 3.5 | AO15: 18.6 | AR15: 3.3 | BA15: 0.6 | BC15: 21.5 | BD15: 51.9 | BE15: 20.2 | BF15: 1.1 | BG15: 1 | BI15: 1.8 | BK15: 1 | BL15: 18.7 | BM15: 6.1 | BO15: 20.7 | BP15: 724.2
B16: 4:30 | C16: 15 | E16: 5.5 | F16: 11 | G16: 9.8 | H16: 2.9 | J16: 8.8 | L16: 10.6 | N16: 10.9 | O16: 14.4 | P16: 9.2 | Q16: 2.9 | R16: 2.8 | S16: 15.6 | U16: 20 | V16: 18.9 | W16: 18 | X16: 39 | Y16: 96.6 | Z16: 63.3 | AA16: 96.7 | AC16: 5.3 | AD16: 1.9 | AE16: 20.9 | AF16: 7.4 | AG16: 18.5 | AH16: 19.3 | AI16: 19.3 | AJ16: 7.6 | AN16: 3.5 | AO16: 18.6 | AR16: 3.3 | AW16: 0.3 | BA16: 0.6 | BC16: 26.2 | BD16: 58.6 | BE16: 20.2 | BF16: 1.1 | BG16: 1 | BI16: 1.8 | BK16: 1 | BL16: 18.7 | BM16: 6.1 | BO16: 21 | BP16: 754.1
B17: 5:00 | C17: 14.8 | E17: 5.3 | F17: 11 | G17: 10.4 | H17: 2.9 | J17: 9.2 | L17: 10.6 | N17: 10.4 | O17: 14 | P17: 9.2 | Q17: 3 | R17: 2.9 | S17: 15.5 | U17: 20 | V17: 18.8 | W17: 16.4 | X17: 37.2 | Y17: 106.7 | Z17: 58.6 | AA17: 88.7 | AC17: 5.4 | AD17: 1.5 | AE17: 20.9 | AF17: 7.4 | AG17: 18.5 | AH17: 19.3 | AI17: 19.3 | AJ17: 7.7 | AN17: 3.5 | AO17: 18.6 | AR17: 3.3 | AT17: 0.4 | AZ17: 0.1 | BA17: 0.6 | BB17: 0.5 | BC17: 28.8 | BD17: 68.4 | BE17: 20.1 | BF17: 1.1 | BG17: 1 | BI17: 1.8 | BK17: 1 | BL17: 18.6 | BM17: 6.1 | BN17: 0.1 | BO17: 20.7 | BP17: 760.3
B18: 5:30 | C18: 15.2 | E18: 6.1 | F18: 11 | G18: 10.4 | H18: 2.9 | J18: 8.5 | L18: 10.6 | N18: 10.4 | O18: 13.9 | P18: 9.1 | Q18: 3 | R18: 2.9 | S18: 15.4 | U18: 20 | V18: 18.8 | W18: 15.2 | X18: 22.3 | Y18: 106.2 | Z18: 72.8 | AA18: 81.2 | AB18: 1.7 | AC18: 9 | AD18: 3.6 | AE18: 20.9 | AF18: 7.4 | AG18: 18 | AH18: 19.3 | AI18: 19.3 | AJ18: 7.8 | AK18: 3.9 | AN18: 3.5 | AO18: 18.6 | AR18: 3.3 | AT18: 2.5 | AX18: 8.7 | AZ18: 7.9 | BA18: 0.6 | BB18: 3.2 | BC18: 29.5 | BD18: 74.4 | BE18: 20 | BF18: 1.1 | BG18: 1 | BI18: 1.8 | BK18: 1 | BL18: 18.6 | BM18: 6.2 | BN18: 0.8 | BO18: 20.6 | BP18: 790.1
B19: 6:00 | C19: 15.3 | E19: 5.1 | F19: 11 | G19: 10.3 | H19: 2.9 | J19: 9.2 | L19: 10.6 | N19: 10.2 | O19: 14 | P19: 9 | Q19: 3.1 | R19: 2.8 | S19: 15.5 | U19: 20 | V19: 18.8 | W19: 16.7 | X19: 16.4 | Y19: 99.7 | Z19: 67.3 | AA19: 80 | AB19: 11.3 | AC19: 5.9 | AD19: 2.7 | AE19: 20.9 | AF19: 7.4 | AG19: 18 | AH19: 19.3 | AI19: 19.3 | AJ19: 7.9 | AK19: 27.2 | AL19: 1.2 | AM19: 2.5 | AN19: 3.5 | AO19: 18.6 | AR19: 3.3 | AS19: 1.2 | AT19: 6.9 | AW19: 6.3 | AX19: 50.1 | AY19: 2.9 | AZ19: 43.4 | BA19: 0.6 | BB19: 6.8 | BC19: 27.8 | BD19: 73.2 | BE19: 20.1 | BF19: 1.1 | BG19: 1 | BI19: 1.8 | BJ19: 0.9 | BK19: 0.9 | BL19: 18.6 | BM19: 6.1 | BN19: 0.8 | BP19: 877.4
B20: 6:30 | C20: 14 | D20: 5.1 | E20: 4.6 | F20: 11 | G20: 10.4 | H20: 2.9 | J20: 9 | K20: 0.1 | L20: 10.6 | N20: 10.6 | O20: 14.1 | P20: 8.9 | Q20: 3.2 | R20: 2.8 | S20: 15.7 | U20: 20 | V20: 18.8 | W20: 17.2 | X20: 16.6 | Y20: 98.7 | Z20: 67.7 | AA20: 80.6 | AB20: 23 | AC20: 6 | AD20: 2.4 | AE20: 20.9 | AF20: 7.4 | AG20: 18.3 | AH20: 19.3 | AI20: 19.3 | AJ20: 7.3 | AK20: 52 | AL20: 3 | AM20: 5.1 | AN20: 3.5 | AO20: 18.6 | AR20: 3.3 | AS20: 2.8 | AT20: 12.6 | AW20: 25 | AX20: 97.5 | AY20: 19.6 | AZ20: 80.4 | BA20: 0.6 | BB20: 15.1 | BC20: 27.2 | BD20: 78 | BE20: 19 | BF20: 1.1 | BG20: 1 | BI20: 1.8 | BJ20: 2.8 | BK20: 0.9 | BL20: 18.7 | BM20: 6.1 | BN20: 1.5 | BP20: 1063.7
B21: 7:00 | C21: 14.8 | D21: 5.2 | E21: 4.9 | F21: 11 | G21: 9.2 | H21: 2.8 | J21: 8.9 | K21: 0.1 | L21: 10.6 | N21: 10.4 | O21: 14.2 | P21: 8.9 | Q21: 3.1 | R21: 2.8 | S21: 15.6 | U21: 20 | V21: 18.9 | W21: 18.4 | X21: 9.7 | Y21: 95.9 | Z21: 63.1 | AA21: 84 | AB21: 32.2 | AC21: 5 | AD21: 0.8 | AE21: 20.9 | AF21: 7.4 | AG21: 18.3 | AH21: 19.1 | AI21: 19.3 | AJ21: 7.2 | AK21: 71.3 | AL21: 2.7 | AM21: 6.7 | AN21: 3.5 | AO21: 18.6 | AR21: 3.2 | AS21: 4.2 | AT21: 15 | AW21: 35.3 | AX21: 136.5 | AY21: 25.3 | AZ21: 98.5 | BA21: 0.6 | BB21: 18.1 | BC21: 26.6 | BD21: 80.2 | BE21: 19.2 | BF21: 1.1 | BG21: 1 | BI21: 1.8 | BJ21: 4.7 | BK21: 0.9 | BL21: 18.6 | BM21: 6.1 | BN21: 2.6 | BP21: 1165
B22: 7:30 | C22: 15.3 | D22: 7.2 | E22: 5.8 | F22: 11 | G22: 8.3 | H22: 2.8 | J22: 9.2 | K22: 0.2 | L22: 10.6 | N22: 10.4 | O22: 14.1 | P22: 8.8 | Q22: 3.2 | R22: 2.9 | S22: 15.7 | U22: 20 | V22: 18.9 | W22: 20.5 | X22: 6.6 | Y22: 105.2 | Z22: 43.3 | AA22: 84.8 | AB22: 34.8 | AC22: 1.9 | AD22: 0.4 | AE22: 20.9 | AF22: 7.3 | AG22: 18.3 | AH22: 19.1 | AI22: 19.3 | AJ22: 7.5 | AK22: 79 | AL22: 3.7 | AM22: 5.8 | AN22: 3.5 | AO22: 18.6 | AQ22: 0.1 | AR22: 1.9 | AS22: 8 | AT22: 13.6 | AW22: 29.2 | AX22: 145.1 | AY22: 23.9 | AZ22: 105.5 | BA22: 0.6 | BB22: 16.4 | BC22: 28.5 | BD22: 81 | BE22: 14.1 | BF22: 1.1 | BG22: 1 | BI22: 1.8 | BJ22: 6.9 | BK22: 0.9 | BL22: 18.8 | BM22: 6.1 | BN22: 3.8 | BP22: 1173.2
B23: 8:00 | C23: 15 | D23: 16 | E23: 5.1 | F23: 11 | G23: 13 | H23: 2.8 | J23: 9.3 | K23: 0.3 | L23: 10.6 | N23: 9.8 | O23: 13.7 | P23: 8.4 | Q23: 3.2 | R23: 3 | S23: 15.7 | U23: 20 | V23: 18.9 | W23: 13.6 | X23: 6.9 | Y23: 115.8 | AA23: 101.7 | AB23: 29 | AD23: 7.7 | AE23: 20.9 | AF23: 7.3 | AG23: 18.3 | AH23: 19.1 | AI23: 19.1 | AJ23: 7.5 | AK23: 80.5 | AL23: 3.3 | AM23: 5.9 | AN23: 3.5 | AO23: 18.6 | AQ23: 0.1 | AR23: 1.9 | AS23: 10.1 | AT23: 14.3 | AW23: 27.5 | AX23: 142.3 | AY23: 21.7 | AZ23: 105.8 | BA23: 0.6 | BB23: 17.1 | BC23: 25.8 | BD23: 73.4 | BE23: 10 | BF23: 1.1 | BG23: 1 | BI23: 1.8 | BJ23: 9.3 | BK23: 0.9 | BL23: 18.6 | BM23: 6.2 | BN23: 4.6 | BP23: 1148.6
B24: 8:30 | C24: 15 | D24: 17.3 | E24: 4.6 | F24: 11 | G24: 17.4 | H24: 2.8 | J24: 7.7 | K24: 0.8 | L24: 10.2 | N24: 10.3 | O24: 14.2 | P24: 8.4 | Q24: 2.4 | R24: 2.9 | S24: 15.6 | U24: 20 | V24: 18.9 | W24: 9.7 | X24: 10.6 | Y24: 119.4 | AA24: 109.4 | AB24: 35.4 | AD24: 6.9 | AE24: 20.9 | AF24: 7.3 | AG24: 18 | AH24: 19 | AI24: 19 | AJ24: 7.5 | AK24: 80.9 | AL24: 3 | AM24: 4.7 | AN24: 3.5 | AO24: 18.6 | AQ24: 0.3 | AR24: 1.9 | AS24: 12.4 | AT24: 15.7 | AW24: 20.9 | AX24: 147.2 | AY24: 17.4 | AZ24: 107 | BA24: 0.6 | BB24: 19.1 | BC24: 27.8 | BD24: 81.6 | BE24: 10 | BF24: 1.1 | BG24: 1 | BI24: 1.8 | BJ24: 11.9 | BK24: 0.9 | BL24: 18.6 | BM24: 6.2 | BN24: 7.2 | BP24: 1183.9
B25: 9:00 | C25: 15 | D25: 17.9 | E25: 6.2 | F25: 11 | G25: 18.4 | H25: 2.7 | J25: 8.4 | K25: 0.9 | L25: 10.2 | N25: 10.2 | O25: 14.1 | P25: 5 | Q25: 2.4 | R25: 3 | S25: 15.6 | U25: 20 | V25: 18.8 | W25: 7 | X25: 14.6 | Y25: 121.8 | AA25: 103.3 | AB25: 40 | AD25: 10.1 | AE25: 20.9 | AF25: 7.3 | AG25: 17.8 | AH25: 19 | AI25: 19 | AJ25: 7.5 | AK25: 80.9 | AL25: 3.6 | AM25: 2.7 | AN25: 3.5 | AO25: 18.6 | AQ25: 0.2 | AR25: 1.9 | AS25: 14.3 | AT25: 15.5 | AW25: 23.9 | AX25: 149 | AY25: 13.3 | AZ25: 109.9 | BA25: 0.6 | BB25: 19 | BC25: 29.3 | BD25: 87.6 | BE25: 10 | BF25: 1.1 | BG25: 1 | BI25: 1.8 | BJ25: 13.8 | BK25: 0.9 | BL25: 18.6 | BM25: 6.2 | BN25: 11.4 | BO25: 4 | BP25: 1210.7
B26: 9:30 | C26: 15 | D26: 18 | E26: 7 | F26: 11 | G26: 19.8 | H26: 2.7 | J26: 8.3 | K26: 0.8 | L26: 10 | N26: 9.7 | O26: 13.7 | P26: 5.7 | Q26: 2.4 | R26: 3 | S26: 15.3 | U26: 20 | V26: 18.7 | W26: 5.7 | X26: 18.1 | Y26: 124.4 | AA26: 98.5 | AB26: 39.7 | AD26: 9.9 | AE26: 20.9 | AF26: 7.3 | AG26: 17.8 | AH26: 18.8 | AI26: 18.8 | AJ26: 7.3 | AK26: 80.8 | AL26: 4.5 | AM26: 3.3 | AN26: 3.5 | AO26: 18.6 | AQ26: 0.4 | AR26: 1.9 | AS26: 15.7 | AT26: 15.8 | AW26: 56.6 | AX26: 146.5 | AY26: 32.1 | AZ26: 107.2 | BA26: 0.6 | BB26: 19.7 | BC26: 29.4 | BD26: 84.8 | BE26: 10 | BF26: 1.1 | BG26: 1 | BI26: 1.8 | BJ26: 15.3 | BK26: 0.9 | BL26: 18.5 | BM26: 6.2 | BN26: 16.8 | BO26: 20.6 | BP26: 1281.9
B27: 10:00 | C27: 15 | D27: 18.6 | E27: 7.2 | F27: 11 | G27: 20 | H27: 2.7 | J27: 8.5 | K27: 1.1 | L27: 9.8 | N27: 10.1 | O27: 14 | P27: 8.7 | Q27: 2.4 | R27: 2.9 | S27: 15.2 | U27: 20 | V27: 18.7 | W27: 7.2 | X27: 29.6 | Y27: 125.8 | AA27: 98.6 | AB27: 38.8 | AD27: 9.9 | AE27: 20.9 | AF27: 7.3 | AG27: 17.8 | AH27: 18.8 | AI27: 18.8 | AJ27: 7 | AK27: 80.8 | AL27: 4.8 | AM27: 6.4 | AN27: 3.5 | AO27: 18.6 | AQ27: 0.3 | AR27: 1.9 | AS27: 16.9 | AT27: 15.1 | AW27: 131 | AX27: 149.3 | AY27: 105.7 | AZ27: 109.8 | BA27: 0.6 | BB27: 18.9 | BC27: 29.6 | BD27: 84.9 | BE27: 10 | BF27: 1.1 | BG27: 1 | BI27: 1.8 | BJ27: 16.5 | BK27: 0.9 | BL27: 18.5 | BM27: 6.2 | BN27: 18.7 | BO27: 20.7 | BP27: 1459.9
B28: 10:30 | C28: 15.1 | D28: 19 | E28: 8 | F28: 11 | G28: 20.1 | H28: 2.7 | J28: 8.8 | K28: 1 | L28: 9.8 | N28: 10.6 | O28: 14.3 | P28: 8.8 | Q28: 2.4 | R28: 3 | S28: 15.2 | U28: 19.6 | V28: 18.7 | W28: 8 | X28: 49.6 | Y28: 126.1 | AA28: 98.1 | AB28: 38.7 | AD28: 10.1 | AE28: 20.9 | AF28: 7.3 | AG28: 17.8 | AH28: 18.8 | AI28: 18.8 | AJ28: 7.3 | AK28: 52.6 | AL28: 4.4 | AM28: 6.2 | AN28: 3.5 | AO28: 18.6 | AQ28: 0.4 | AR28: 1.8 | AS28: 18.2 | AT28: 15 | AW28: 132.1 | AX28: 155.1 | AY28: 108.4 | AZ28: 114.6 | BA28: 0.6 | BB28: 18.7 | BC28: 30.1 | BD28: 85.4 | BE28: 10 | BF28: 1.1 | BG28: 1 | BI28: 1.8 | BJ28: 17.5 | BK28: 0.9 | BL28: 18.5 | BM28: 6.2 | BN28: 19.5 | BO28: 20.7 | BP28: 1472.5
B29: 11:00 | C29: 15 | D29: 19 | E29: 7.4 | F29: 11 | G29: 20.2 | H29: 2.7 | J29: 8.5 | K29: 0.6 | L29: 9.8 | N29: 10.4 | O29: 14.1 | P29: 8.8 | Q29: 2.7 | R29: 2.9 | S29: 14.9 | U29: 19.6 | V29: 18.7 | W29: 7.3 | X29: 65.8 | Y29: 125.7 | AA29: 91.8 | AB29: 39.9 | AD29: 9.2 | AE29: 20.9 | AF29: 7 | AG29: 17.8 | AH29: 18.8 | AI29: 18.8 | AJ29: 7.6 | AK29: 80.9 | AL29: 4.6 | AM29: 5.5 | AN29: 3.5 | AO29: 18.6 | AQ29: 0.4 | AR29: 1.9 | AS29: 19.3 | AT29: 14.7 | AW29: 150.1 | AX29: 140.1 | AY29: 116.6 | AZ29: 108.2 | BA29: 0.6 | BB29: 18.4 | BC29: 30.1 | BD29: 85.6 | BE29: 10 | BF29: 1.1 | BG29: 1 | BI29: 1.8 | BJ29: 18.4 | BK29: 0.9 | BL29: 18.5 | BM29: 6.2 | BN29: 19.6 | BO29: 20.7 | BP29: 1514.2
B30: 11:30 | C30: 15 | D30: 19 | E30: 7.5 | F30: 11 | G30: 20.1 | H30: 2.6 | J30: 8.7 | K30: 0.5 | L30: 9.5 | N30: 9.9 | O30: 14 | P30: 9 | Q30: 3.4 | R30: 2.8 | S30: 14.3 | U30: 19.6 | V30: 18.7 | W30: 16.1 | X30: 74.2 | Y30: 125.9 | AA30: 88.8 | AB30: 40 | AD30: 9.9 | AE30: 20.9 | AF30: 7 | AG30: 17.6 | AH30: 18.8 | AI30: 18.8 | AJ30: 8 | AK30: 80.9 | AL30: 5 | AM30: 7.3 | AN30: 3.5 | AO30: 18.6 | AQ30: 0.5 | AR30: 1.9 | AS30: 15.8 | AT30: 15.2 | AW30: 142.6 | AX30: 122.8 | AY30: 116.4 | AZ30: 86.6 | BA30: 0.6 | BB30: 18.3 | BC30: 29.8 | BD30: 84.8 | BE30: 10 | BF30: 1.1 | BG30: 1 | BI30: 1.8 | BJ30: 18.9 | BK30: 0.9 | BL30: 18.1 | BM30: 6.1 | BN30: 19.2 | BO30: 20.7 | BP30: 1480
B31: 12:00 | C31: 14.8 | D31: 19 | E31: 7.3 | F31: 11 | G31: 19.6 | H31: 2.6 | J31: 9.3 | K31: 0.9 | L31: 9.4 | N31: 10.1 | O31: 14.1 | P31: 9 | Q31: 3.4 | R31: 2.7 | S31: 14.3 | U31: 19.6 | V31: 18.7 | W31: 16 | X31: 76.6 | Y31: 125.7 | AA31: 89.6 | AB31: 40.5 | AD31: 7.6 | AE31: 20.9 | AF31: 7 | AG31: 17.6 | AH31: 18.6 | AI31: 18.6 | AJ31: 8 | AK31: 77.5 | AL31: 6 | AM31: 7.7 | AN31: 3.5 | AO31: 18.6 | AQ31: 0.5 | AR31: 1.9 | AS31: 18.3 | AT31: 14.4 | AW31: 130.1 | AX31: 141.7 | AY31: 116.3 | AZ31: 104.9 | BA31: 0.6 | BB31: 17 | BC31: 29.8 | BD31: 85.9 | BE31: 10 | BF31: 1.1 | BG31: 0.9 | BI31: 1.7 | BJ31: 14.6 | BK31: 0.9 | BL31: 18.2 | BM31: 6.2 | BN31: 16 | BO31: 20.6 | BP31: 1497.4
B32: 12:30 | C32: 15.2 | D32: 19 | E32: 7.2 | F32: 11 | G32: 12.4 | H32: 2.6 | J32: 9.2 | K32: 0.6 | L32: 9.1 | N32: 10.2 | O32: 14 | P32: 9 | Q32: 3.4 | R32: 2.8 | S32: 14.4 | U32: 19.6 | V32: 18.4 | W32: 16.4 | X32: 79.8 | Y32: 125.8 | AA32: 93.4 | AB32: 40.1 | AD32: 9.5 | AE32: 20.9 | AF32: 7 | AG32: 17.6 | AH32: 18.4 | AI32: 18.4 | AJ32: 8.4 | AK32: 80.6 | AL32: 6.5 | AM32: 8.1 | AN32: 3.4 | AO32: 18.6 | AQ32: 0.3 | AR32: 3.4 | AS32: 14.2 | AT32: 13.4 | AW32: 118.3 | AX32: 120.4 | AY32: 115 | AZ32: 87.9 | BA32: 0.6 | BB32: 16.1 | BC32: 29.8 | BD32: 84.8 | BE32: 10 | BF32: 1.1 | BG32: 0.9 | BI32: 1.7 | BJ32: 15.4 | BK32: 0.9 | BL32: 18.3 | BM32: 6.2 | BN32: 19.5 | BO32: 20.8 | BP32: 1450
B33: 13:00 | C33: 15 | D33: 19.4 | E33: 7.3 | F33: 11 | G33: 12.6 | H33: 2.6 | J33: 8.1 | K33: 0.8 | L33: 9 | N33: 10.2 | O33: 14 | P33: 8.9 | Q33: 3.4 | R33: 2.8 | S33: 14.3 | U33: 19.6 | V33: 18.7 | W33: 19.8 | X33: 79.8 | Y33: 125.1 | AA33: 97 | AB33: 32 | AD33: 13.6 | AE33: 20.9 | AF33: 7 | AG33: 17.6 | AH33: 18.2 | AI33: 18.2 | AJ33: 8.4 | AK33: 75.3 | AL33: 8 | AM33: 9.2 | AN33: 3.4 | AO33: 18.6 | AQ33: 0.5 | AR33: 3.4 | AS33: 9.6 | AT33: 12.7 | AW33: 110.2 | AX33: 115.2 | AY33: 113.8 | AZ33: 86.4 | BA33: 0.6 | BB33: 15.4 | BC33: 29.8 | BD33: 84.7 | BE33: 10 | BF33: 1.1 | BG33: 0.9 | BI33: 1.7 | BJ33: 17.8 | BK33: 0.9 | BL33: 18.3 | BM33: 6.2 | BN33: 19.4 | BO33: 20.8 | BP33: 1429.2
B34: 13:30 | C34: 15.5 | D34: 19.8 | E34: 7.2 | F34: 11 | G34: 12.7 | H34: 2.6 | J34: 9.4 | K34: 0.6 | L34: 8.7 | N34: 10.1 | O34: 13.9 | P34: 8.8 | Q34: 3.4 | R34: 2.7 | S34: 14.1 | U34: 19.6 | V34: 18.9 | W34: 19.9 | X34: 79.8 | Y34: 123.3 | AA34: 98.5 | AB34: 26.2 | AD34: 13.9 | AE34: 20.9 | AF34: 7 | AG34: 17.4 | AH34: 18.2 | AI34: 18.2 | AJ34: 8.4 | AK34: 69.4 | AL34: 6.6 | AM34: 6.5 | AN34: 3.4 | AO34: 18.6 | AQ34: 0.2 | AR34: 3.4 | AS34: 12 | AT34: 12.3 | AW34: 122.2 | AX34: 123.2 | AY34: 116.9 | AZ34: 88 | BA34: 0.6 | BB34: 14.7 | BC34: 29.7 | BD34: 84.8 | BE34: 10 | BF34: 1.1 | BG34: 0.9 | BI34: 1.7 | BJ34: 10.8 | BK34: 0.9 | BL34: 18.2 | BM34: 6.2 | BN34: 18.7 | BO34: 20.7 | BP34: 1432.4
B35: 14:00 | C35: 15.7 | D35: 19.9 | E35: 7.7 | F35: 11 | G35: 12.9 | H35: 2.6 | J35: 8.7 | K35: 0.6 | L35: 8.7 | N35: 10.2 | O35: 15 | P35: 8.8 | Q35: 3.5 | R35: 2.7 | S35: 14 | U35: 19.6 | V35: 18.9 | W35: 22.1 | X35: 79.4 | Y35: 122.6 | AA35: 92.7 | AB35: 29.2 | AD35: 15.1 | AE35: 20.9 | AF35: 7 | AG35: 17.2 | AH35: 18.2 | AI35: 18.2 | AJ35: 8.4 | AK35: 50.9 | AL35: 2.6 | AM35: 3.7 | AN35: 3.4 | AO35: 18.6 | AQ35: 0.2 | AR35: 3.4 | AS35: 12 | AT35: 11.8 | AW35: 137.5 | AX35: 93.6 | AY35: 116.5 | AZ35: 67.3 | BA35: 0.6 | BB35: 14.2 | BC35: 30.1 | BD35: 84.1 | BE35: 10 | BF35: 1.1 | BG35: 0.9 | BI35: 1.7 | BJ35: 8.5 | BK35: 0.9 | BL35: 18.2 | BM35: 6.2 | BN35: 16.3 | BO35: 20.7 | BP35: 1366.5
B36: 14:30 | C36: 16 | D36: 19.9 | E36: 7.8 | F36: 11 | G36: 13.1 | H36: 2.6 | J36: 8.7 | K36: 0.5 | L36: 8.7 | N36: 10.3 | O36: 15.1 | P36: 8.8 | Q36: 3.5 | R36: 2.8 | S36: 13.9 | U36: 20 | V36: 18.7 | W36: 21.3 | X36: 79.7 | Y36: 117.7 | AA36: 93.3 | AB36: 30.3 | AD36: 14.6 | AE36: 20.8 | AF36: 7 | AG36: 17.2 | AH36: 18.2 | AI36: 18.2 | AJ36: 8.3 | AK36: 45.2 | AL36: 1.8 | AM36: 1.9 | AN36: 3.4 | AO36: 18.6 | AQ36: 0.1 | AR36: 3.4 | AS36: 7.2 | AT36: 10 | AW36: 139.9 | AX36: 103.1 | AY36: 116.8 | AZ36: 74.7 | BA36: 0.6 | BB36: 11.9 | BC36: 30 | BD36: 88.2 | BE36: 10 | BF36: 1.1 | BG36: 0.9 | BI36: 1.7 | BJ36: 6.8 | BK36: 0.9 | BL36: 18.1 | BM36: 6.2 | BN36: 16.4 | BO36: 20.9 | BP36: 1367.8
... B39: 16:00 | C39: 15.2 | D39: 19.9 | E39: 7.6 | F39: 11 | G39: 12.8 | H39: 2.6 | J39: 8.1 | K39: 0.1 | L39: 8.7 | N39: 9.8 | O39: 14.8 | P39: 8.6 | Q39: 3.5 | R39: 2.8 | S39: 14.9 | U39: 20 | V39: 18.7 | W39: 26 | X39: 81.1 | Y39: 118.8 | AA39: 103.2 | AB39: 25.5 | AD39: 14 | AE39: 20.5 | AF39: 7 | AG39: 15.4 | AH39: 17.4 | AI39: 17.4 | AJ39: 8.3 | AK39: 69.1 | AL39: 3.4 | AM39: 5.5 | AN39: 3.4 | AO39: 18.6 | AQ39: 0.1 | AR39: 3.5 | AS39: 5.4 | AT39: 6.2 | AW39: 117.5 | AX39: 110.5 | AY39: 119.5 | AZ39: 79.5 | BA39: 0.6 | BB39: 6.8 | BC39: 28.9 | BD39: 83.1 | BE39: 10 | BF39: 1.1 | BG39: 0.9 | BI39: 1.7 | BJ39: 6.2 | BK39: 0.9 | BL39: 18.4 | BM39: 6.2 | BN39: 8.6 | BO39: 20.7 | BP39: 1370
B40: 16:30 | C40: 15 | D40: 19.9 | E40: 8 | F40: 10.5 | G40: 12.8 | H40: 2.7 | J40: 9.4 | K40: 0.1 | L40: 8.7 | N40: 9.7 | O40: 14.8 | P40: 8.6 | Q40: 3.4 | R40: 2.8 | S40: 14.4 | U40: 20 | V40: 18.7 | W40: 24.3 | X40: 81.3 | Y40: 123.4 | AA40: 103.4 | AB40: 15.5 | AD40: 13.9 | AE40: 20.5 | AF40: 7 | AG40: 16.2 | AH40: 17.4 | AI40: 17.5 | AJ40: 8.3 | AK40: 24.3 | AL40: 3.7 | AM40: 5.3 | AN40: 3.4 | AO40: 18.6 | AR40: 3.5 | AS40: 2.8 | AT40: 3.1 | AW40: 150.1 | AX40: 94.4 | AY40: 120.1 | AZ40: 78.6 | BA40: 0.6 | BB40: 4 | BC40: 28.2 | BD40: 86.1 | BE40: 9.9 | BF40: 1.1 | BG40: 0.9 | BI40: 1.7 | BJ40: 6 | BK40: 0.9 | BL40: 18.3 | BM40: 6.2 | BN40: 6.8 | BO40: 20.7 | BP40: 1327.5
B41: 17:00 | C41: 15.5 | D41: 19.9 | E41: 9.3 | F41: 11 | G41: 15.1 | H41: 2.7 | J41: 8.5 | K41: 0.1 | L41: 8.7 | N41: 9.9 | O41: 15 | P41: 8.6 | Q41: 3.5 | R41: 2.8 | S41: 14.5 | U41: 20 | V41: 18.7 | W41: 22 | X41: 80.9 | Y41: 125.5 | AA41: 108.4 | AB41: 14.7 | AD41: 9.2 | AE41: 20.5 | AF41: 7 | AG41: 16.6 | AH41: 17.4 | AI41: 17.5 | AJ41: 8 | AK41: 13 | AL41: 4.7 | AM41: 7.7 | AN41: 3.4 | AO41: 18.6 | AR41: 3.5 | AS41: 1.4 | AT41: 2.5 | AW41: 138.2 | AX41: 17.1 | AY41: 119 | AZ41: 16 | BA41: 0.6 | BB41: 3.5 | BC41: 29.7 | BD41: 82.8 | BE41: 10 | BF41: 1.1 | BG41: 0.9 | BI41: 1.7 | BJ41: 2.4 | BK41: 0.9 | BL41: 18.3 | BM41: 6.2 | BN41: 2.4 | BO41: 20.7 | BP41: 1157.8
B42: 17:30 | C42: 15 | D42: 19.9 | E42: 9.5 | F42: 11 | G42: 20.2 | H42: 2.7 | J42: 9.2 | L42: 8.6 | N42: 9.9 | O42: 14.9 | P42: 8.5 | Q42: 3.4 | R42: 2.8 | S42: 15.1 | U42: 20 | V42: 18.7 | W42: 23.2 | X42: 81.4 | Y42: 126.5 | Z42: 71.5 | AA42: 75.4 | AB42: 3.8 | AC42: 7.9 | AD42: 5.1 | AE42: 20.5 | AF42: 7 | AG42: 16.6 | AH42: 17.4 | AI42: 17.5 | AJ42: 8 | AK42: 5.7 | AL42: 5.4 | AM42: 9.7 | AN42: 3.4 | AO42: 18.6 | AR42: 3.5 | AS42: 0.2 | AT42: 0.3 | AW42: 133.6 | AX42: 12.9 | AY42: 117.2 | AZ42: 13.2 | BA42: 0.6 | BB42: 0.2 | BC42: 30 | BD42: 87.6 | BE42: 10 | BF42: 1.1 | BG42: 1 | BI42: 1.8 | BJ42: 0.8 | BK42: 0.9 | BL42: 18.5 | BM42: 6.2 | BO42: 20.8 | BP42: 1174.4
B43: 18:00 | C43: 15.5 | D43: 19.9 | E43: 8 | F43: 11 | G43: 20.2 | H43: 2.8 | J43: 9.2 | L43: 7.9 | N43: 9.4 | O43: 13.7 | P43: 8.6 | Q43: 3.5 | R43: 2.8 | S43: 15.2 | U43: 20 | V43: 18.8 | W43: 24.5 | X43: 81.2 | Y43: 126 | Z43: 68.6 | AA43: 77.6 | AC43: 9.3 | AD43: 5.5 | AE43: 20.5 | AF43: 7 | AG43: 16.4 | AH43: 17 | AI43: 17.3 | AJ43: 7.8 | AL43: 9.3 | AM43: 8.4 | AN43: 3.5 | AO43: 18.6 | AR43: 3.5 | AW43: 115.5 | AY43: 122.8 | BA43: 0.6 | BC43: 30.3 | BD43: 88.2 | BE43: 10 | BF43: 1.1 | BG43: 1 | BI43: 1.8 | BK43: 0.9 | BL43: 18.5 | BM43: 6.2 | BO43: 20.6 | BP43: 1126
B44: 18:30 | C44: 15.2 | D44: 19.79 | E44: 8.8 | F44: 11 | G44: 20.2 | H44: 2.8 | J44: 9.2 | L44: 8 | N44: 10.1 | O44: 14.2 | P44: 8.7 | Q44: 3.4 | R44: 2.8 | S44: 15.1 | U44: 20 | V44: 18.8 | W44: 21.9 | X44: 81 | Y44: 125.5 | Z44: 66.1 | AA44: 83 | AC44: 9 | AD44: 2.5 | AE44: 20.4 | AF44: 6.9 | AG44: 16.4 | AH44: 17 | AI44: 17.3 | AJ44: 7.8 | AL44: 12.4 | AM44: 11.9 | AN44: 3.5 | AO44: 18.6 | AR44: 3.4 | AW44: 116.8 | AY44: 118.5 | BA44: 0.6 | BC44: 30.5 | BD44: 86.3 | BE44: 10 | BF44: 1.1 | BG44: 1 | BI44: 1.8 | BK44: 0.9 | BL44: 18.5 | BM44: 6.2 | BO44: 20.8 | BP44: 1125.69
B45: 19:00 | C45: 15.2 | D45: 20.12 | E45: 6.8 | F45: 11 | G45: 20.2 | H45: 2.8 | J45: 8.5 | L45: 9.1 | N45: 9.8 | O45: 14 | P45: 8.9 | Q45: 3.5 | R45: 2.7 | S45: 15.8 | U45: 20 | V45: 18.7 | W45: 15.9 | X45: 75.4 | Y45: 123.7 | Z45: 68.8 | AA45: 84.5 | AC45: 5.6 | AD45: 0.7 | AE45: 20 | AF45: 6.8 | AG45: 16.2 | AH45: 16.8 | AI45: 17.2 | AJ45: 8.1 | AL45: 8.8 | AM45: 10.7 | AN45: 3.5 | AO45: 18.6 | AR45: 3.4 | AW45: 107.3 | AY45: 113.1 | BA45: 0.6 | BC45: 29.9 | BD45: 87.4 | BE45: 10 | BF45: 1.1 | BG45: 1 | BI45: 2 | BK45: 0.9 | BL45: 18.7 | BM45: 6.2 | BO45: 20.7 | BP45: 1090.72
B46: 19:30 | C46: 15 | D46: 19.58 | E46: 7.3 | F46: 11 | G46: 20.2 | H46: 2.7 | J46: 9.3 | L46: 9.2 | N46: 9.9 | O46: 14 | P46: 9.1 | Q46: 3.5 | R46: 2.6 | S46: 16.4 | U46: 20 | V46: 18.7 | W46: 17.1 | X46: 63.1 | Y46: 121.6 | Z46: 67.7 | AA46: 85.5 | AC46: 6.5 | AD46: 0.6 | AE46: 20 | AF46: 6.8 | AG46: 16 | AH46: 16.6 | AI46: 16.8 | AJ46: 8.2 | AL46: 9.9 | AM46: 10.9 | AN46: 3.5 | AO46: 18.6 | AR46: 3.4 | AW46: 89.9 | AY46: 100.6 | BA46: 0.6 | BC46: 30.5 | BD46: 88.1 | BE46: 10 | BF46: 1.1 | BG46: 1 | BI46: 1.8 | BK46: 0.9 | BL46: 18.9 | BM46: 6.2 | BO46: 20.8 | BP46: 1051.68
B47: 20:00 | C47: 15.2 | D47: 19.81 | E47: 7.8 | F47: 11 | G47: 20.2 | H47: 2.7 | J47: 7.9 | L47: 9.2 | N47: 9.8 | O47: 14 | P47: 9.2 | Q47: 3.4 | R47: 2.5 | S47: 16.4 | U47: 20 | V47: 18.5 | W47: 16.8 | X47: 61.5 | Y47: 122.3 | Z47: 63.8 | AA47: 89.1 | AC47: 3.3 | AD47: 4 | AE47: 20 | AF47: 6.8 | AG47: 15.8 | AH47: 16.4 | AI47: 16.5 | AJ47: 8.2 | AL47: 7.5 | AM47: 9.9 | AN47: 3.5 | AO47: 18.6 | AR47: 3.4 | AW47: 79.1 | AY47: 80.5 | BA47: 0.6 | BC47: 30.6 | BD47: 88.1 | BE47: 10 | BF47: 1.1 | BG47: 1.1 | BI47: 2.3 | BK47: 0.9 | BL47: 18.9 | BM47: 6.2 | BO47: 20.7 | BP47: 1015.11
B48: 20:30 | C48: 15.2 | D48: 19.84 | E48: 7.6 | F48: 11 | G48: 20.2 | H48: 2.7 | J48: 6.2 | L48: 9.1 | N48: 9.9 | O48: 14 | P48: 9.2 | Q48: 3.4 | R48: 2.8 | S48: 16.4 | U48: 20 | V48: 18.5 | W48: 13.7 | X48: 61.3 | Y48: 120.4 | Z48: 67.9 | AA48: 85.7 | AC48: 4.6 | AD48: 2.5 | AE48: 20 | AF48: 6.8 | AG48: 15.5 | AH48: 16.4 | AI48: 16.5 | AJ48: 8.2 | AL48: 5.1 | AM48: 6.8 | AN48: 3.5 | AO48: 18.6 | AR48: 3.4 | AW48: 101.9 | AY48: 102.6 | BA48: 0.6 | BC48: 30.5 | BD48: 88.2 | BE48: 10 | BF48: 1.1 | BG48: 1.2 | BI48: 2.4 | BK48: 0.8 | BL48: 18.9 | BM48: 6.2 | BO48: 20.7 | BP48: 1048.04
B49: 21:00 | C49: 15.5 | D49: 19.45 | E49: 7.7 | F49: 11 | G49: 20.2 | H49: 2.7 | J49: 6.2 | L49: 9.1 | N49: 9.8 | O49: 14 | P49: 9.4 | Q49: 3.5 | R49: 2.7 | S49: 16.7 | U49: 20 | V49: 18.4 | W49: 13.7 | X49: 57.3 | Y49: 123.2 | Z49: 64.1 | AA49: 86.4 | AC49: 6.1 | AD49: 4.2 | AE49: 20 | AF49: 6.8 | AG49: 15 | AH49: 16.4 | AI49: 16.5 | AJ49: 8.2 | AL49: 2.6 | AM49: 5 | AN49: 3.4 | AO49: 18.6 | AR49: 3.4 | AW49: 95.2 | AY49: 100.2 | BA49: 0.6 | BC49: 30.6 | BD49: 88 | BE49: 10 | BF49: 1.1 | BG49: 1.2 | BI49: 2.4 | BK49: 0.8 | BL49: 19 | BM49: 6.2 | BO49: 20.7 | BP49: 1033.25
B50: 21:30 | C50: 15.5 | D50: 19.76 | E50: 7 | F50: 11 | G50: 18.9 | H50: 2.7 | J50: 8 | L50: 9.2 | N50: 9.7 | O50: 13.6 | P50: 9.4 | Q50: 3.5 | R50: 2.7 | S50: 16.7 | U50: 20 | V50: 18.5 | W50: 14.3 | X50: 59.4 | Y50: 122.7 | Z50: 66.2 | AA50: 80.6 | AC50: 7.4 | AD50: 6.1 | AE50: 19.7 | AF50: 6.8 | AG50: 15 | AH50: 16.2 | AI50: 16.5 | AJ50: 7.9 | AL50: 0.7 | AM50: 1.1 | AN50: 3.4 | AO50: 18.6 | AR50: 3.5 | AW50: 107.3 | AY50: 108.1 | BA50: 0.6 | BC50: 30.5 | BD50: 88.5 | BE50: 10 | BF50: 1.1 | BG50: 1.1 | BI50: 2.4 | BK50: 0.8 | BL50: 19.1 | BM50: 6.2 | BO50: 20.6 | BP50: 1048.56
B51: 22:00 | C51: 5.5 | D51: 19.61 | E51: 8.5 | F51: 11 | G51: 13.7 | H51: 2.7 | J51: 7.3 | L51: 9.4 | N51: 10.1 | O51: 13.2 | P51: 9.5 | Q51: 3.5 | R51: 2.7 | S51: 16.5 | U51: 20 | V51: 14.1 | W51: 16.5 | X51: 45.2 | Y51: 120.7 | Z51: 69.4 | AA51: 80.7 | AC51: 6.6 | AD51: 3.8 | AE51: 19.7 | AF51: 6.8 | AG51: 15.4 | AH51: 16 | AI51: 16.5 | AJ51: 7.8 | AL51: 0.3 | AM51: 1.2 | AN51: 3.4 | AO51: 18.6 | AR51: 3.5 | AW51: 118 | AY51: 115.6 | BA51: 0.6 | BC51: 30.6 | BD51: 88.3 | BE51: 9.9 | BF51: 1.1 | BG51: 1.1 | BI51: 2.4 | BK51: 0.8 | BL51: 18.9 | BM51: 6.2 | BO51: 20.9 | BP51: 1033.81
B52: 22:30 | C52: 14 | D52: 19.8 | E52: 8.3 | F52: 11 | G52: 13.7 | H52: 2.7 | J52: 7.6 | L52: 9.5 | N52: 9.3 | O52: 12.5 | P52: 9.6 | Q52: 3.5 | R52: 2.8 | S52: 16.3 | U52: 20 | W52: 14.1 | X52: 41.9 | Y52: 123.3 | Z52: 59.2 | AA52: 90 | AC52: 6.1 | AD52: 4.4 | AE52: 19.6 | AF52: 6.8 | AG52: 15.6 | AH52: 16 | AI52: 16.5 | AJ52: 7.8 | AM52: 0.1 | AN52: 3.4 | AO52: 18.6 | AR52: 3.5 | AW52: 120.4 | AY52: 113.3 | BA52: 0.6 | BC52: 30.6 | BD52: 88.5 | BE52: 4.5 | BF52: 1.1 | BG52: 1.1 | BI52: 2.4 | BK52: 0.8 | BL52: 18.9 | BM52: 6.2 | BO52: 20.4 | BP52: 1016.3
B53: 23:00 | C53: 15.8 | D53: 20.42 | E53: 6.5 | F53: 11 | G53: 13.7 | H53: 2.6 | J53: 8.6 | L53: 9.5 | N53: 9.3 | O53: 12.6 | P53: 9.6 | Q53: 3.5 | R53: 2.8 | S53: 16.3 | U53: 20 | W53: 12.8 | X53: 40.4 | Y53: 122.8 | Z53: 45 | AA53: 87.1 | AC53: 2.3 | AD53: 2.8 | AE53: 19.5 | AF53: 6.8 | AG53: 16 | AH53: 16 | AI53: 16.5 | AJ53: 7.8 | AL53: 0.2 | AM53: 0.4 | AN53: 3.4 | AO53: 18.6 | AR53: 3.5 | AW53: 102.7 | AY53: 100.4 | BA53: 0.6 | BC53: 30.7 | BD53: 88 | BF53: 1.1 | BG53: 1.1 | BI53: 2.4 | BK53: 0.8 | BL53: 18.9 | BM53: 6.2 | BO53: 20.5 | BP53: 957.52
B54: 23:30 | C54: 15.5 | D54: 20.42 | E54: 7.1 | F54: 11 | G54: 13.6 | H54: 2.6 | J54: 8.2 | L54: 9.5 | N54: 9.9 | O54: 12.9 | P54: 9.7 | Q54: 3.5 | R54: 2.8 | S54: 16.2 | U54: 20 | V54: 9.8 | W54: 15.8 | X54: 35.4 | Y54: 121 | Z54: 53.5 | AA54: 86.7 | AC54: 3.1 | AD54: 3 | AE54: 19.4 | AF54: 6.8 | AG54: 16 | AH54: 16.8 | AI54: 16.7 | AJ54: 8 | AM54: 0.1 | AN54: 3.4 | AO54: 18.6 | AR54: 3.5 | AW54: 83.1 | AY54: 78.2 | BA54: 0.6 | BC54: 30.4 | BD54: 87.8 | BF54: 1.1 | BG54: 1.1 | BI54: 2.4 | BK54: 0.8 | BL54: 18.8 | BM54: 6.2 | BO54: 20.7 | BP54: 931.72
B55: 0:00 | C55: 15.3 | D55: 20.2 | E55: 7.1 | F55: 11 | G55: 13.5 | H55: 2.6 | J55: 8.2 | L55: 9.5 | N55: 9.8 | O55: 13 | P55: 9.7 | Q55: 3.5 | R55: 2.7 | S55: 16.2 | U55: 20 | V55: 18.7 | W55: 18.3 | X55: 35 | Y55: 120.8 | Z55: 61.1 | AA55: 90.7 | AC55: 5.8 | AD55: 3.3 | AE55: 19.4 | AF55: 6.8 | AG55: 16 | AH55: 17 | AI55: 16.7 | AJ55: 8.2 | AM55: 0.1 | AN55: 3.4 | AO55: 18.6 | AR55: 3.5 | AW55: 79.9 | AY55: 73.8 | BA55: 0.6 | BC55: 30.3 | BD55: 88.6 | BF55: 1.1 | BG55: 1.1 | BI55: 2.4 | BK55: 0.8 | BL55: 18.8 | BM55: 6.2 | BO55: 20.7 | BP55: 950
B56: EJEC MWh | C56: 359.25 | D56: 328.7 | E56: 170.15 | F56: 261.9 | G56: 368.2 | H56: 65.55 | I56: 0 | J56: 206 | K56: 5.65 | L56: 229.8 | M56: 0 | N56: 242.05 | O56: 336.55 | P56: 212.6 | Q56: 77.2 | R56: 67.45 | S56: 369.15 | T56: 0 | U56: 477.05 | V56: 424.65 | W56: 399.3 | X56: 1244.65 | Y56: 2735.55 | Z56: 841.1 | AA56: 2079.4 | AB56: 357.8 | AC56: 75.05 | AD56: 143.3 | AE56: 493.6 | AF56: 171.15 | AG56: 413.85 | AH56: 436.1 | AI56: 438.15 | AJ56: 189.95 | AK56: 742.6 | AL56: 75.75 | AM56: 99.65 | AN56: 83.1 | AO56: 446.4 | AP56: 0 | AQ56: 2.4 | AR56: 73.85 | AS56: 118.35 | AT56: 137.7 | AU56: 0 | AV56: 0 | AW56: 1839.55 | AX56: 1369.95 | AY56: 1682.6 | AZ56: 1021.45 | BA56: 14.4 | BB56: 166.45 | BC56: 697.55 | BD56: 1933.4 | BE56: 293.65 | BF56: 26.4 | BG56: 24 | BH56: 0 | BI56: 45.4 | BJ56: 120.6 | BK56: 21.75 | BL56: 445.9 | BM56: 148.15 | BN56: 137.05 | BO56: 426.05 | BP56: 26414.95
L70: TERMOELÉCTRICA | M70: 1421.8 | N70: 5.382558 | O70: #FFA975
L71: SOLAR | M71: 4180 | N71: 15.824372 | O71: #FFD272
L72: HIDROELÉCTRICA | M72: 6966.3 | N72: 26.372566 | O72: #98D2FF
L73: EÓLICA | M73: 13846.85 | N73: 52.420504 | O73: #B9ACFF

Sheet COGENERACIÓN
B3: miércoles, 5 de Noviembre del 2025
B5: CENTRALES DE COGENERACIÓN DEL SEIN
B6: HORA | C6: AGRO INDUSTRIAL PARAMONGA S.A. | D6: AGROAURORA S.A.C. | E6: AGROINDUSTRIAS SAN JACINTO S.A.A. | F6: AGROLMOS SOCIEDAD ANONIMA - AGROLMOS S.A. | G6: BIOENERGIA DEL CHIRA S.A. | H6: GM OPERACIONES S.A.C. | I6: TOTAL COGENERACION
C7: C.T. PARAMONGA | D7: C.T. MAPLE | E7: C.T SAN JACINTO | F7: C.T. AGROLMOS | G7: C.T. CAÑA BRAVA | H7: C.T. REFINERÍA TALARA | I7: MW
B8: 0:30 | C8: 15 | E8: 7.1 | F8: 11 | G8: 8.7 | H8: 60 | I8: 101.8
B9: 1:00 | C9: 15 | E9: 7 | F9: 10.5 | G9: 8 | H9: 59.7 | I9: 100.2
B10: 1:30 | C10: 14.8 | E10: 6.9 | F10: 10 | G10: 8.5 | H10: 59.1 | I10: 99.3
B11: 2:00 | C11: 15.4 | E11: 7 | F11: 10 | G11: 9.3 | H11: 59.3 | I11: 101
B12: 2:30 | C12: 15.2 | E12: 7.7 | F12: 10 | G12: 9.2 | H12: 59.5 | I12: 101.6
B13: 3:00 | C13: 15.5 | E13: 7.1 | F13: 10.8 | G13: 9 | H13: 58.8 | I13: 101.2
B14: 3:30 | C14: 15.5 | E14: 7.9 | F14: 11 | G14: 9.4 | H14: 58.8 | I14: 102.6
B15: 4:00 | C15: 15.5 | E15: 6.7 | F15: 11 | G15: 9.2 | H15: 58.8 | I15: 101.2
B16: 4:30 | C16: 15 | E16: 5.5 | F16: 11 | G16: 8.8 | H16: 58.5 | I16: 98.8
B17: 5:00 | C17: 14.8 | E17: 5.3 | F17: 11 | G17: 9.2 | H17: 57.6 | I17: 97.9
B18: 5:30 | C18: 15.2 | E18: 6.1 | F18: 11 | G18: 8.5 | H18: 57.8 | I18: 98.6
B19: 6:00 | C19: 15.3 | E19: 5.1 | F19: 11 | G19: 9.2 | H19: 57.2 | I19: 97.8
B20: 6:30 | C20: 14 | D20: 5.1 | E20: 4.6 | F20: 11 | G20: 9 | H20: 58.3 | I20: 102
B21: 7:00 | C21: 14.8 | D21: 5.2 | E21: 4.9 | F21: 11 | G21: 8.9 | H21: 58.6 | I21: 103.4
B22: 7:30 | C22: 15.3 | D22: 7.2 | E22: 5.8 | F22: 11 | G22: 9.2 | H22: 59 | I22: 107.5
B23: 8:00 | C23: 15 | D23: 16 | E23: 5.1 | F23: 11 | G23: 9.3 | H23: 59 | I23: 115.4
B24: 8:30 | C24: 15 | D24: 17.3 | E24: 4.6 | F24: 11 | G24: 7.7 | H24: 59.1 | I24: 114.7
B25: 9:00 | C25: 15 | D25: 17.9 | E25: 6.2 | F25: 11 | G25: 8.4 | H25: 59.2 | I25: 117.7
B26: 9:30 | C26: 15 | D26: 18 | E26: 7 | F26: 11 | G26: 8.3 | H26: 59 | I26: 118.3
B27: 10:00 | C27: 15 | D27: 18.6 | E27: 7.2 | F27: 11 | G27: 8.5 | H27: 58.7 | I27: 119
B28: 10:30 | C28: 15.1 | D28: 19 | E28: 8 | F28: 11 | G28: 8.8 | H28: 57.2 | I28: 119.1
B29: 11:00 | C29: 15 | D29: 19 | E29: 7.4 | F29: 11 | G29: 8.5 | H29: 58.1 | I29: 119
B30: 11:30 | C30: 15 | D30: 19 | E30: 7.5 | F30: 11 | G30: 8.7 | H30: 58.3 | I30: 119.5
B31: 12:00 | C31: 14.8 | D31: 19 | E31: 7.3 | F31: 11 | G31: 9.3 | H31: 59 | I31: 120.4
... B56: EJEC MWh | C56: 359.25 | D56: 328.7 | E56: 170.15 | F56: 261.9 | G56: 206 | H56: 1416.95 | I56: 2742.95

Sheet EVO_PRO_ENE
B3: sábado, 1 de Noviembre del 2025 - miércoles, 5 de Noviembre del 2025
B5: EVOLUCIÓN DE LA PRODUCCIÓN DE LA ENERGÍA DIARIA DE LOS INTEGRANTES DEL COES (MWh)
B6: EMPRESA | C6: CENTRAL | D6: UNIDAD | E6: TIPO | F6: Noviembre
F7: 1 | G7: 2 | H7: 3 | I7: 4 | J7: 5 | K7: TOTAL
B8: AGRO INDUSTRIAL PARAMONGA S.A. | C8: C.T. PARAMONGA | D8: TV-01 | E8: TERMOELÉCTRICA | H8: 195.15 | I8: 342.3 | J8: 359.25 | K8: 896.7
B9: AGROAURORA S.A.C. | C9: C.T. MAPLE ETANOL | D9: TV | E9: TERMOELÉCTRICA | F9: 414.9 | G9: 359.75 | H9: 314.05 | I9: 386.35 | J9: 328.7 | K9: 1803.75
B10: AGROINDUSTRIAS SAN JACINTO S.A.A. | C10: C.T. SAN JACINTO | D10: CENTRAL | E10: TERMOELÉCTRICA | F10: 182 | G10: 157.2 | H10: 49.75 | I10: 70.95 | J10: 170.15 | K10: 630.05
B11: AGROLMOS SOCIEDAD ANONIMA - AGROLMOS S.A. | C11: C.T. AGROLMOS | D11: CENTRAL | E11: TERMOELÉCTRICA | F11: 265.35 | G11: 264.3 | H11: 263.9 | I11: 261.35 | J11: 261.9 | K11: 1316.8
B12: ANDEAN POWER S.A.C. | C12: C.H.CARHUAC | D12: CENTRAL | E12: HIDROELÉCTRICA | F12: 347.95 | G12: 359.35 | H12: 364.1 | I12: 373.4 | J12: 368.2 | K12: 1813
B13: ASOCIACIÓN SANTA LUCIA DE CHACAS | C13: C.H. HUALLIN | D13: CENTRAL | E13: HIDROELÉCTRICA | F13: 55.85 | G13: 59.1 | H13: 60.15 | I13: 57.1 | J13: 65.55 | K13: 297.75
B14: ATRIA ENERGIA S.A.C. | C14: C.H. PURMACANA | D14: CENTRAL | E14: HIDROELÉCTRICA | K14: 0
B15: BIOENERGIA DEL CHIRA S.A. | C15: C.T. CAÑA BRAVA | D15: CENTRAL | E15: TERMOELÉCTRICA | F15: 190.6 | G15: 212.4 | H15: 215.65 | I15: 203.35 | J15: 206 | K15: 1028
B16: CELEPSA | C16: C.H. EL PLATANAL | D16: CENTRAL | E16: HIDROELÉCTRICA | F16: 2830 | G16: 2899.6 | H16: 2724.65 | I16: 2741.65 | J16: 2729.25 | K16: 13925.15
B17: CELEPSA RENOVABLES S.R.L. | C17: C.H. MARAÑON | D17: CENTRAL | E17: HIDROELÉCTRICA | F17: 451.2 | G17: 451.2 | H17: 451.2 | I17: 451.2 | J17: 451.2 | K17: 2256
B18: CENTRALES SANTA ROSA S.A.C. | C18: C.H. SANTA ROSA I | D18: CENTRAL | E18: HIDROELÉCTRICA | K18: 0
B19: CENTRALES SANTA ROSA S.A.C. | C19: C.H. SANTA ROSA II | D19: CENTRAL | E19: HIDROELÉCTRICA | K19: 0
B20: CHINANGO S.A.C. | C20: C.H. CHIMAY | D20: CENTRAL | E20: HIDROELÉCTRICA | F20: 3626.05 | G20: 3629.35 | H20: 3621.5 | I20: 3360.35 | J20: 2823.4 | K20: 17060.65
B21: CHINANGO S.A.C. | C21: C.H. YANANGO | D21: CENTRAL | E21: HIDROELÉCTRICA | F21: 692 | G21: 656.35 | H21: 790.7 | I21: 694.2 | J21: 615.95 | K21: 3449.2
B22: COLCA SOLAR S.A.C. | C22: C.S. YARUCAYA | D22: CENTRAL | E22: SOLAR | F22: 9.1 | G22: 8.85 | H22: 8.45 | I22: 6.75 | J22: 5.65 | K22: 38.8
B23: EGASA | C23: C.H. CHARCANI III | D23: CENTRAL | E23: HIDROELÉCTRICA | F23: 165.6 | G23: 165.85 | H23: 165.95 | I23: 165.7 | J23: 166.1 | K23: 829.2
B24: EGASA | C24: C.H. CHARCANI IV | D24: CENTRAL | E24: HIDROELÉCTRICA | F24: 298.75 | G24: 295.95 | H24: 296.05 | I24: 271.55 | J24: 301.5 | K24: 1463.8
B25: EGASA | C25: C.H. CHARCANI V | D25: CENTRAL | E25: HIDROELÉCTRICA | F25: 1876.1 | G25: 1890.55 | H25: 1880.33 | I25: 1917.15 | J25: 1900.55 | K25: 9464.68
B26: EGASA | C26: C.H. CHARCANI VI | D26: CENTRAL | E26: HIDROELÉCTRICA | K26: 0
B27: EGASA | C27: C.T. CHILINA DIESEL | D27: CENTRAL | E27: TERMOELÉCTRICA | K27: 0
B28: EGASA | C28: C.T. CHILINA DIESEL | D28: TG | E28: TERMOELÉCTRICA | K28: 0
B29: EGASA | C29: C.T. MOLLENDO DIESEL | D29: CENTRAL | E29: TERMOELÉCTRICA | K29: 0
B30: EGEJUNIN | C30: C.H. HUASAHUASI I | D30: CENTRAL | E30: HIDROELÉCTRICA | F30: 287.25 | G30: 255.5 | H30: 321.7 | I30: 281.55 | J30: 229.8 | K30: 1375.8
B31: EGEJUNIN | C31: C.H. RUNATULLO II | D31: CENTRAL | E31: HIDROELÉCTRICA | F31: 285.65 | G31: 256.65 | H31: 258.75 | I31: 225.5 | J31: 242.05 | K31: 1268.6
B32: EGEJUNIN | C32: C.H. RUNATULLO III | D32: CENTRAL | E32: HIDROELÉCTRICA | F32: 396.5 | G32: 363.2 | H32: 367.05 | I32: 355.55 | J32: 336.55 | K32: 1818.85
B33: EGEJUNIN | C33: C.H. SANTA CRUZ I | D33: CENTRAL | E33: HIDROELÉCTRICA | F33: 165.3 | G33: 158.95 | H33: 162.55 | I33: 174.35 | J33: 212.6 | K33: 873.75
B34: EGEMSA | C34: C.H. MACHUPICCHU | D34: CENTRAL | E34: HIDROELÉCTRICA | F34: 3987.6 | G34: 3950.3 | H34: 3681.9 | I34: 3689.8 | J34: 3412.15 | K34: 18721.75
B35: EGESUR | C35: C.H. ARICOTA I | D35: CENTRAL | E35: HIDROELÉCTRICA | F35: 178.9 | G35: 178.15 | H35: 178.25 | I35: 178.55 | J35: 178.5 | K35: 892.35
B36: EGESUR | C36: C.H. ARICOTA II | D36: CENTRAL | E36: HIDROELÉCTRICA | F36: 137.15 | G36: 139.25 | H36: 140.7 | I36: 140.75 | J36: 138.85 | K36: 696.7
B37: EGESUR | C37: C.T. INDEPENDENCIA | D37: CENTRAL | E37: TERMOELÉCTRICA | F37: 132.95 | G37: 75.2 | H37: 161.2 | I37: 134.8 | J37: 306.3 | K37: 810.45
B38: ELECTRICA YANAPAMPA SAC | C38: C.H. YANAPAMPA | D38: CENTRAL | E38: HIDROELÉCTRICA | F38: 62.2 | G38: 76 | H38: 73.15 | I38: 77.25 | J38: 77.2 | K38: 365.8
B39: ELECTROPERU | C39: C.H. MANTARO | D39: CENTRAL | E39: HIDROELÉCTRICA | F39: 14611.8 | G39: 14679.565 | H39: 15064.885 | I39: 14980.1 | J39: 15037 | K39: 74373.35
B40: ELECTROPERU | C40: C.H. RESTITUCION | D40: CENTRAL | E40: HIDROELÉCTRICA | F40: 4974.55 | G40: 5001.895 | H40: 5155.88 | I40: 5131.35 | J40: 5148.9 | K40: 25412.575
B41: ELECTROPERU | C41: C.T. TUMBES | D41: MAK1 | E41: TERMOELÉCTRICA | K41: 0
B42: ELECTROPERU | C42: C.T. TUMBES | D42: MAK2 | E42: TERMOELÉCTRICA | K42: 0
B43: EMPRESA DE GENERACION ELECTRICA CANCHAYLLO SAC | C43: C.H. CANCHAYLLO | D43: CENTRAL | E43: HIDROELÉCTRICA | F43: 69.8 | G43: 69.5 | H43: 70.6 | I43: 68.7 | J43: 67.45 | K43: 346.05
B44: EMPRESA DE GENERACION ELECTRICA RIO BAÑOS S.A.C. | C44: C.H. RUCUY | D44: CENTRAL | E44: HIDROELÉCTRICA | F44: 372.9 | G44: 358.75 | H44: 351.65 | I44: 372.15 | J44: 369.15 | K44: 1824.6
B45: EMPRESA DE GENERACION ELECTRICA SANTA ANA S.A.C. | C45: C.H. RENOVANDES H1 | D45: CENTRAL | E45: HIDROELÉCTRICA | K45: 0
B46: EMPRESA DE GENERACION HUALLAGA | C46: C.H. CHAGLLA | D46: CENTRAL | E46: HIDROELÉCTRICA | F46: 6248.45 | G46: 3546.8 | H46: 5184.7 | I46: 4484.55 | J46: 4789.45 | K46: 24253.95
B47: EMPRESA DE GENERACION HUALLAGA | C47: P.C.H. CHAGLLA | D47: CENTRAL | E47: HIDROELÉCTRICA | F47: 155.5 | G47: 155.8 | H47: 155.75 | I47: 155.65 | J47: 154.8 | K47: 777.5
B48: EMPRESA DE GENERACION HUANZA | C48: C.H. HUANZA | D48: CENTRAL | E48: HIDROELÉCTRICA | F48: 1506.4 | G48: 1559.1 | H48: 1572.4 | I48: 1579.75 | J48: 1565.9 | K48: 7783.55
B49: EMPRESA ELECTRICA AGUA AZUL | C49: C.H. POTRERO | D49: CENTRAL | E49: HIDROELÉCTRICA | F49: 480 | G49: 480 | H49: 479.95 | I49: 480 | J49: 477.05 | K49: 2397
B50: EMPRESA ELECTRICA RIO DOBLE | C50: C.H. LAS PIZARRAS | D50: CENTRAL | E50: HIDROELÉCTRICA | F50: 454.15 | G50: 453.95 | H50: 453.75 | I50: 451.35 | J50: 424.65 | K50: 2237.85
B51: ENEL GENERACION PIURA S.A. | C51: C.T. MALACAS 1 | D51: TG6 | E51: TERMOELÉCTRICA | F51: 842.4 | G51: 2.65 | H51: 650.45 | I51: 641.6 | J51: 678.7 | K51: 2815.8
B52: ENEL GENERACION PIURA S.A. | C52: C.T. MALACAS 2 | D52: TG4 | E52: TERMOELÉCTRICA | K52: 0
B53: ENEL GENERACION PIURA S.A. | C53: C.T. RF DE GENERACION TALARA | D53: TG5 | E53: TERMOELÉCTRICA | G53: 352.45 | K53: 352.45
B54: ENERGÍA EÓLICA S.A. | C54: C.E. CUPISNIQUE | D54: CENTRAL | E54: EÓLICA | F54: 1077.35 | G54: 1198.25 | H54: 1245.05 | I54: 1370.75 | J54: 1244.65 | K54: 6136.05
B55: ENERGÍA EÓLICA S.A. | C55: C.E. TALARA | D55: CENTRAL | E55: EÓLICA | F55: 535.15 | G55: 406.2 | H55: 393.4 | I55: 389.35 | J55: 399.3 | K55: 2123.4
B56: ENERGIA RENOVABLE DEL SUR S.A. | C56: C.E. SAN JUAN | D56: CENTRAL | E56: EÓLICA | F56: 1591.15 | G56: 1841.4 | H56: 1519.1 | I56: 2469.25 | J56: 2735.55 | K56: 10156.45
B57: ENGIE ENERGIA PERU S.A.A. | C57: C.E. PUNTA LOMITAS | D57: PL-BL1 | E57: EÓLICA | F57: 1829.35 | G57: 1871.65 | H57: 869.2 | I57: 915.95 | J57: 841.1 | K57: 6327.25
B58: ENGIE ENERGIA PERU S.A.A. | C58: C.E. PUNTA LOMITAS | D58: PL-BL2 | E58: EÓLICA | F58: 2010 | G58: 2056.25 | H58: 1660.65 | I58: 2000.05 | J58: 2079.4 | K58: 9806.35
B59: ENGIE ENERGIA PERU S.A.A. | C59: C.E. PUNTA LOMITAS_EXP | D59: PUN LOM_EXP-BL1 | E59: EÓLICA | F59: 261.55 | G59: 269.3 | H59: 84.95 | I59: 77.45 | J59: 75.05 | K59: 768.3
B60: ENGIE ENERGIA PERU S.A.A. | C60: C.E. PUNTA LOMITAS_EXP | D60: PUN LOM_EXP-BL2 | E60: EÓLICA | F60: 125 | G60: 124.35 | H60: 138.75 | I60: 181.45 | J60: 143.3 | K60: 712.85
B61: ENGIE ENERGIA PERU S.A.A. | C61: C.H. QUITARACSA | D61: CENTRAL | E61: HIDROELÉCTRICA | K61: 0
B62: ENGIE ENERGIA PERU S.A.A. | C62: C.H. YUNCAN | D62: CENTRAL | E62: HIDROELÉCTRICA | F62: 2508.7 | G62: 2185.1 | H62: 2033.35 | I62: 2021.7 | J62: 2224.3 | K62: 10973.15
B63: ENGIE ENERGIA PERU S.A.A. | C63: C.S. INTIPAMPA | D63: CENTRAL | E63: SOLAR | F63: 406.15 | G63: 406.55 | H63: 405.95 | I63: 309.55 | J63: 357.8 | K63: 1886
B64: ENGIE ENERGIA PERU S.A.A. | C64: C.T. CHILCA 1 | D64: TG1 | E64: TERMOELÉCTRICA | F64: 3319.4 | G64: 3164.6 | H64: 3722.3 | I64: 4160.55 | J64: 3876.8 | K64: 18243.65
B65: ENGIE ENERGIA PERU S.A.A. | C65: C.T. CHILCA 1 | D65: TG2 | E65: TERMOELÉCTRICA | F65: 3288.9 | G65: 3148.7 | H65: 3685.15 | I65: 4109.8 | J65: 3841.7 | K65: 18074.25
B66: ENGIE ENERGIA PERU S.A.A. | C66: C.T. CHILCA 1 | D66: TG3 | E66: TERMOELÉCTRICA | F66: 3707.7 | G66: 3324.8 | H66: 4163.95 | I66: 4767.8 | J66: 4305.95 | K66: 20270.2
B67: ENGIE ENERGIA PERU S.A.A. | C67: C.T. CHILCA 1 | D67: TV | E67: TERMOELÉCTRICA | F67: 5457.75 | G67: 5248.05 | H67: 5927.9 | I67: 6429.85 | J67: 6067.85 | K67: 29131.4
B68: ENGIE ENERGIA PERU S.A.A. | C68: C.T. CHILCA 2 | D68: TG41 | E68: TERMOELÉCTRICA | K68: 0
B69: ENGIE ENERGIA PERU S.A.A. | C69: C.T. CHILCA 2 | D69: TV42 | E69: TERMOELÉCTRICA | K69: 0
B70: ENGIE ENERGIA PERU S.A.A. | C70: C.T. NEPI | D70: TG41 | E70: TERMOELÉCTRICA | K70: 0
B71: ENGIE ENERGIA PERU S.A.A. | C71: C.T. NEPI | D71: TG42 | E71: TERMOELÉCTRICA | K71: 0
B72: ENGIE ENERGIA PERU S.A.A. | C72: C.T. NEPI | D72: TG43 | E72: TERMOELÉCTRICA | K72: 0
B73: ENGIE ENERGIA PERU S.A.A. | C73: C.T. RF PLANTA ILO | D73: TG1 | E73: TERMOELÉCTRICA | K73: 0
B74: ENGIE ENERGIA PERU S.A.A. | C74: C.T. RF PLANTA ILO | D74: TG2 | E74: TERMOELÉCTRICA | G74: 354.4 | K74: 354.4
B75: ENGIE ENERGIA PERU S.A.A. | C75: C.T. RF PLANTA ILO | D75: TG3 | E75: TERMOELÉCTRICA | K75: 0
B76: FENIX POWER PERÚ | C76: C.T. FENIX | D76: GT11 | E76: TERMOELÉCTRICA | K76: 0
B77: FENIX POWER PERÚ | C77: C.T. FENIX | D77: GT12 | E77: TERMOELÉCTRICA | K77: 0
B78: FENIX POWER PERÚ | C78: C.T. FENIX | D78: TV10 | E78: TERMOELÉCTRICA | K78: 0
B79: GENERACIÓN ANDINA S.A.C. | C79: C.H. 8 DE AGOSTO | D79: CENTRAL | E79: HIDROELÉCTRICA | F79: 501.4 | G79: 485.75 | H79: 365.3 | I79: 492.5 | J79: 493.6 | K79: 2338.55
B80: GENERACIÓN ANDINA S.A.C. | C80: C.H. EL CARMEN | D80: CENTRAL | E80: HIDROELÉCTRICA | F80: 190.5 | G80: 183.35 | H80: 174.55 | I80: 181.9 | J80: 171.15 | K80: 901.45
B81: GENERADORA DE ENERGÍA DEL PERÚ | C81: C.H. ÁNGEL I | D81: CENTRAL | E81: HIDROELÉCTRICA | F81: 489.6 | G81: 489 | H81: 475.75 | I81: 479.85 | J81: 413.85 | K81: 2348.05
B82: GENERADORA DE ENERGÍA DEL PERÚ | C82: C.H. ÁNGEL II | D82: CENTRAL | E82: HIDROELÉCTRICA | F82: 489.6 | G82: 489.6 | H82: 484.45 | I82: 486.95 | J82: 436.1 | K82: 2386.7
B83: GENERADORA DE ENERGÍA DEL PERÚ | C83: C.H. ÁNGEL III | D83: CENTRAL | E83: HIDROELÉCTRICA | F83: 481.2 | G83: 480.85 | H83: 479.15 | I83: 478.4 | J83: 438.15 | K83: 2357.75
B84: GENERADORA DE ENERGÍA DEL PERÚ | C84: C.H. LA JOYA | D84: CENTRAL | E84: HIDROELÉCTRICA | F84: 162.6 | G84: 161.2 | H84: 173.7 | I84: 175.5 | J84: 189.95 | K84: 862.95
B85: GM OPERACIONES S.A.C. | C85: CT REFINERIA TALARA | D85: TV1 REF TALARA | E85: TERMOELÉCTRICA | F85: 658.2 | G85: 646.4 | H85: 664.7 | I85: 666.535 | J85: 631.6 | K85: 3267.435
B86: GM OPERACIONES S.A.C. | C86: CT REFINERIA TALARA | D86: TV2 REF TALARA | E86: TERMOELÉCTRICA | F86: 824.05 | G86: 813.1 | H86: 833 | I86: 832.73 | J86: 785.35 | K86: 4088.23
B87: GR CORTARRAMA SOCIEDAD ANONIMA CERRADA | C87: C.S. MATARANI | D87: C.S. MATARANI | E87: SOLAR | F87: 851.1 | G87: 853.5 | H87: 849.75 | I87: 755 | J87: 742.6 | K87: 4051.95
B88: GR PAINO SOCIEDAD ANONIMA CERRADA | C88: C.E. HUAMBOS | D88: CENTRAL | E88: EÓLICA | F88: 145.55 | G88: 180.9 | H88: 74.1 | I88: 29.2 | J88: 75.75 | K88: 505.5
B89: GR TARUCA SOCIEDAD ANONIMA CERRADA | C89: C.E. DUNA | D89: CENTRAL | E89: EÓLICA | F89: 150.7 | G89: 169.4 | H89: 76.05 | I89: 21.35 | J89: 99.65 | K89: 517.15
B90: HIDROCAÑETE S.A. | C90: C.H. IMPERIAL | D90: CENTRAL | E90: HIDROELÉCTRICA | F90: 86.6 | G90: 85.1 | H90: 82.8 | I90: 81.75 | J90: 83.1 | K90: 419.35
... B93: HYDRO GLOBAL PERÚ S.A.C. | C93: CH SAN GABAN III | D93: CENTRAL | E93: HIDROELÉCTRICA | F93: 4862.15 | G93: 4875.75 | H93: 4695.45 | I93: 4879.05 | J93: 4031.8 | K93: 23344.2
B94: INFRAESTRUCTURAS Y ENERGIAS DEL PERU S.A.C. | C94: C.T. RF PTO MALDONADO | D94: CENTRAL | E94: TERMOELÉCTRICA | I94: 0.9 | K94: 0.9
B95: INFRAESTRUCTURAS Y ENERGIAS DEL PERU S.A.C. | C95: C.T. RF PUCALLPA | D95: CENTRAL | E95: TERMOELÉCTRICA | F95: 1.65 | K95: 1.65
B96: INLAND ENERGY SAC | C96: C.H. SANTA TERESA | D96: CENTRAL | E96: HIDROELÉCTRICA | F96: 2166.95 | G96: 2157.8 | H96: 1991.55 | I96: 2005.55 | J96: 1823.05 | K96: 10144.9
B97: INVERSIONES SHAQSHA S.A.C. | C97: C.H. PARIAC | D97: CENTRAL | E97: HIDROELÉCTRICA | F97: 88 | G97: 86.15 | H97: 85.8 | I97: 87.7 | J97: 88.15 | K97: 435.8
B98: JOYA SOLAR S.A.C. | C98: C.S. SAN MARTIN SOLAR | D98: CENTRAL | E98: SOLAR | F98: 2689.25 | G98: 2713.85 | H98: 357 | K98: 5760.1
B99: KALLPA GENERACION S.A. | C99: C.H. CERRO DEL AGUILA | D99: CENTRAL | E99: HIDROELÉCTRICA | F99: 9013 | G99: 5717.2 | H99: 8506.85 | I99: 7358.5 | J99: 7573.55 | K99: 38169.1
B100: KALLPA GENERACION S.A. | C100: C.S. SUNNY | D100: CENTRAL | E100: SOLAR | F100: 2296.7 | G100: 2300.2 | H100: 263.15 | K100: 4860.05
B101: KALLPA GENERACION S.A. | C101: C.T. KALLPA | D101: TG1 | E101: TERMOELÉCTRICA | F101: 3408.4 | G101: 3010.7 | H101: 3755.1 | I101: 3636.15 | J101: 3643.05 | K101: 17453.4
B102: KALLPA GENERACION S.A. | C102: C.T. KALLPA | D102: TG2 | E102: TERMOELÉCTRICA | F102: 3435.85 | G102: 3009.35 | H102: 3788.05 | I102: 3634.65 | J102: 3705.2 | K102: 17573.1
B103: KALLPA GENERACION S.A. | C103: C.T. KALLPA | D103: TG3 | E103: TERMOELÉCTRICA | F103: 3436.45 | G103: 3009.65 | H103: 3787.85 | I103: 3632.35 | J103: 3704 | K103: 17570.3
B104: KALLPA GENERACION S.A. | C104: C.T. KALLPA | D104: TV | E104: TERMOELÉCTRICA | F104: 5742.25 | G104: 5379.1 | H104: 5941.9 | I104: 5904 | J104: 5965.65 | K104: 28932.9
B105: KALLPA GENERACION S.A. | C105: C.T. LAS FLORES | D105: TG1 | E105: TERMOELÉCTRICA | F105: 927.2 | G105: 297.85 | H105: 1604.55 | I105: 173.4 | J105: 1372.75 | K105: 4375.75
...

Sheet G_AREAS
B3: miércoles, 5 de Noviembre del 2025
B5: HORA | C5: RESUMEN DE GENERACIÓN POR ÁREAS DEL SEIN | D5: RESUMEN DE GENERACIÓN POR ÁREAS DEL SEIN | E5: RESUMEN DE GENERACIÓN POR ÁREAS DEL SEIN | F5: RESUMEN DE GENERACIÓN POR ÁREAS DEL SEIN | G5: RESUMEN DE GENERACIÓN POR ÁREAS DEL SEIN | H5: RESUMEN DE GENERACIÓN POR ÁREAS DEL SEIN | I5: RESUMEN DE GENERACIÓN POR ÁREAS DEL SEIN | J5: RESUMEN DE GENERACIÓN POR ÁREAS DEL SEIN | K5: RESUMEN DE GENERACIÓN POR ÁREAS DEL SEIN | L5: RESUMEN DE GENERACIÓN POR ÁREAS DEL SEIN | M5: RESUMEN DE GENERACIÓN POR ÁREAS DEL SEIN | N5: RESUMEN DE GENERACIÓN POR ÁREAS DEL SEIN | O5: RESUMEN DE GENERACIÓN POR ÁREAS DEL SEIN | P5: RESUMEN DE GENERACIÓN POR ÁREAS DEL SEIN | Q5: RESUMEN DE GENERACIÓN POR ÁREAS DEL SEIN | R5: RESUMEN DE GENERACIÓN POR ÁREAS DEL SEIN | S5: HORA | T5: GENERACIÓN POR TIPO DE GENERACIÓN | U5: GENERACIÓN POR TIPO DE GENERACIÓN | V5: GENERACIÓN POR TIPO DE GENERACIÓN | W5: GENERACIÓN POR TIPO DE GENERACIÓN | X5: GENERACIÓN POR TIPO DE GENERACIÓN | Y5: HORA | Z5: GENERACIÓN POR TIPO DE GENERACIÓN | AA5: GENERACIÓN POR TIPO DE GENERACIÓN | AB5: GENERACIÓN POR TIPO DE GENERACIÓN | AC5: GENERACIÓN POR TIPO DE GENERACIÓN | AD5: GENERACIÓN POR TIPO DE GENERACIÓN
C6: NORTE | D6: NORTE | E6: NORTE | F6: NORTE | G6: CENTRO | H6: CENTRO | I6: CENTRO | J6: CENTRO | K6: SUR | L6: SUR | M6: SUR | N6: SUR | O6: GENERACIÓN INTEGRANTES COES | P6: GENERACIÓN INTEGRANTES COES | Q6: GENERACIÓN INTEGRANTES COES | R6: GENERACIÓN INTEGRANTES COES | T6: INTEGRANTES COES | U6: INTEGRANTES COES | V6: INTEGRANTES COES | W6: INTEGRANTES COES | X6: INTEGRANTES COES | Z6: INTEGRANTES COES RER | AA6: INTEGRANTES COES RER | AB6: INTEGRANTES COES RER | AC6: INTEGRANTES COES RER | AD6: INTEGRANTES COES RER
C7: GENERACIÓN HIDROELÉCTRICA NORTE | D7: GENERACIÓN TERMOELÉCTRICA NORTE | E7: GENERACIÓN SOLAR NORTE | F7: GENERACIÓN EÓLICA NORTE | G7: GENERACIÓN HIDROELÉCTRICA CENTRO | H7: GENERACIÓN TERMOELÉCTRICA CENTRO | I7: GENERACIÓN SOLAR CENTRO | J7: GENERACIÓN EÓLICA CENTRO | K7: GENERACIÓN HIDROELÉCTRICA SUR | L7: GENERACIÓN TERMOELÉCTRICA SUR | M7: GENERACIÓN SOLAR SUR | N7: GENERACIÓN EÓLICA SUR | O7: GENERACIÓN COES NORTE | P7: GENERACIÓN COES CENTRO | Q7: GENERACIÓN COES SUR | R7: TOTAL GENERACION | T7: HIDROELÉCTRICA | U7: TERMOELÉCTRICA | V7: SOLAR | W7: EÓLICA | X7: TOTAL GENERACION | Z7: HIDROELÉCTRICA RER | AA7: TERMOELÉCTRICA RER | AB7: SOLAR RER | AC7: EÓLICA RER | AD7: TOTAL RER
B8: 00:30 | C8: 372.1 | D8: 86.8 | E8: 0 | F8: 72.4 | G8: 2543.5 | H8: 2119.6 | I8: 0 | J8: 370.9 | K8: 729.3 | L8: 0 | M8: 0 | N8: 0 | O8: 531.3 | P8: 5034 | Q8: 729.3 | R8: 6294.6 | S8: 00:30 | T8: 3644.9 | U8: 2206.4 | V8: 0 | W8: 443.3 | X8: 6294.6 | Y8: 00:30 | Z8: 310.7 | AA8: 45.7 | AB8: 0 | AC8: 443.3 | AD8: 799.7
B9: 01:00 | C9: 376.9 | D9: 85.2 | E9: 0 | F9: 64.2 | G9: 2539.8 | H9: 2073.6 | I9: 0 | J9: 374.4 | K9: 706 | L9: 0 | M9: 0 | N9: 0 | O9: 526.3 | P9: 4987.8 | Q9: 706 | R9: 6220.1 | S9: 01:00 | T9: 3622.7 | U9: 2158.8 | V9: 0 | W9: 438.6 | X9: 6220.1 | Y9: 01:00 | Z9: 309.6 | AA9: 44.4 | AB9: 0 | AC9: 438.6 | AD9: 792.6
B10: 01:30 | C10: 381.5 | D10: 84.5 | E10: 0 | F10: 70.4 | G10: 2585.2 | H10: 2004.8 | I10: 0 | J10: 304.7 | K10: 714.5 | L10: 0 | M10: 0 | N10: 0 | O10: 536.4 | P10: 4894.7 | Q10: 714.5 | R10: 6145.6 | S10: 01:30 | T10: 3681.2 | U10: 2089.3 | V10: 0 | W10: 375.1 | X10: 6145.6 | Y10: 01:30 | Z10: 309.7 | AA10: 44.1 | AB10: 0 | AC10: 375.1 | AD10: 728.9
B11: 02:00 | C11: 387.6 | D11: 85.6 | E11: 0 | F11: 68.3 | G11: 2535.5 | H11: 2051.9 | I11: 0 | J11: 253.5 | K11: 711.8 | L11: 0 | M11: 0 | N11: 0 | O11: 541.5 | P11: 4840.9 | Q11: 711.8 | R11: 6094.2 | S11: 02:00 | T11: 3634.9 | U11: 2137.5 | V11: 0 | W11: 321.8 | X11: 6094.2 | Y11: 02:00 | Z11: 309.5 | AA11: 45.6 | AB11: 0 | AC11: 321.8 | AD11: 676.9
B12: 02:30 | C12: 392.3 | D12: 86.4 | E12: 0 | F12: 64.9 | G12: 2432.6 | H12: 2014.9 | I12: 0 | J12: 248.2 | K12: 709.4 | L12: 0 | M12: 0 | N12: 0 | O12: 543.6 | P12: 4695.7 | Q12: 709.4 | R12: 5948.7 | S12: 02:30 | T12: 3534.3 | U12: 2101.3 | V12: 0 | W12: 313.1 | X12: 5948.7 | Y12: 02:30 | Z12: 308.8 | AA12: 46 | AB12: 0 | AC12: 313.1 | AD12: 667.9
B13: 03:00 | C13: 389.2 | D13: 85.7 | E13: 0 | F13: 61.4 | G13: 2395.8 | H13: 2039.7 | I13: 0 | J13: 274.4 | K13: 694.7 | L13: 0 | M13: 0 | N13: 0 | O13: 536.3 | P13: 4709.9 | Q13: 694.7 | R13: 5940.9 | S13: 03:00 | T13: 3479.7 | U13: 2125.4 | V13: 0 | W13: 335.8 | X13: 5940.9 | Y13: 03:00 | Z13: 307.6 | AA13: 46.3 | AB13: 0 | AC13: 335.8 | AD13: 689.7
B14: 03:30 | C14: 393.9 | D14: 87.1 | E14: 0 | F14: 46.3 | G14: 2523.5 | H14: 1963.1 | I14: 0 | J14: 279.2 | K14: 711.9 | L14: 0 | M14: 0 | N14: 0 | O14: 527.3 | P14: 4765.8 | Q14: 711.9 | R14: 6005 | S14: 03:30 | T14: 3629.3 | U14: 2050.2 | V14: 0 | W14: 325.5 | X14: 6005 | Y14: 03:30 | Z14: 306.4 | AA14: 47.7 | AB14: 0 | AC14: 325.5 | AD14: 679.6
B15: 04:00 | C15: 393.8 | D15: 85.7 | E15: 0 | F15: 54.1 | G15: 2477.5 | H15: 1968.2 | I15: 0 | J15: 320 | K15: 705.2 | L15: 0 | M15: 0 | N15: 0 | O15: 533.6 | P15: 4765.7 | Q15: 705.2 | R15: 6004.5 | S15: 04:00 | T15: 3576.5 | U15: 2053.9 | V15: 0 | W15: 374.1 | X15: 6004.5 | Y15: 04:00 | Z15: 303.8 | AA15: 46.3 | AB15: 0 | AC15: 374.1 | AD15: 724.2
B16: 04:30 | C16: 397.5 | D16: 83.8 | E16: 0 | F16: 57 | G16: 2561 | H16: 1945.4 | I16: 0 | J16: 348.9 | K16: 710.2 | L16: 0 | M16: 0 | N16: 0 | O16: 538.3 | P16: 4855.3 | Q16: 710.2 | R16: 6103.8 | S16: 04:30 | T16: 3668.7 | U16: 2029.2 | V16: 0 | W16: 405.9 | X16: 6103.8 | Y16: 04:30 | Z16: 304 | AA16: 44.2 | AB16: 0 | AC16: 405.9 | AD16: 754.1
B17: 05:00 | C17: 394.2 | D17: 83.1 | E17: 0 | F17: 53.6 | G17: 2486 | H17: 1964.3 | I17: 0 | J17: 358.1 | K17: 710.6 | L17: 0 | M17: 1.1 | N17: 0 | O17: 530.9 | P17: 4808.4 | Q17: 711.7 | R17: 6051 | S17: 05:00 | T17: 3590.8 | U17: 2047.4 | V17: 1.1 | W17: 411.7 | X17: 6051 | Y17: 05:00 | Z17: 303.3 | AA17: 44.2 | AB17: 1.1 | AC17: 411.7 | AD17: 760.3
B18: 05:30 | C18: 393.2 | D18: 83.4 | E18: 0 | F18: 37.5 | G18: 2572.2 | H18: 2046.7 | I18: 0 | J18: 376.7 | K18: 708.6 | L18: 0 | M18: 28.7 | N18: 0 | O18: 514.1 | P18: 4995.6 | Q18: 737.3 | R18: 6247 | S18: 05:30 | T18: 3674 | U18: 2130.1 | V18: 28.7 | W18: 414.2 | X18: 6247 | Y18: 05:30 | Z18: 302.5 | AA18: 44.7 | AB18: 28.7 | AC18: 414.2 | AD18: 790.1
B19: 06:00 | C19: 392.6 | D19: 82.5 | E19: 0 | F19: 36.8 | G19: 2574.6 | H19: 1880.1 | I19: 0 | J19: 365.8 | K19: 698.2 | L19: 0 | M19: 148.6 | N19: 0 | O19: 511.9 | P19: 4820.5 | Q19: 846.8 | R19: 6179.2 | S19: 06:00 | T19: 3665.4 | U19: 1962.6 | V19: 148.6 | W19: 402.6 | X19: 6179.2 | Y19: 06:00 | Z19: 281.7 | AA19: 44.5 | AB19: 148.6 | AC19: 402.6 | AD19: 877.4
... B56: TOTAL MWh | C56: 9057.35 | D56: 3062.4 | E56: 2.4 | F56: 1819.35 | G56: 63679.55 | H56: 55683.5 | I56: 5.65 | J56: 12027.5 | K56: 15887.65 | L56: 0 | M56: 4171.95 | N56: 0 | O56: 13941.5 | P56: 131396.2 | Q56: 20059.6 | R56: 165397.3 | S56: TOTAL MWh | T56: 88624.55 | U56: 58745.9 | V56: 4180 | W56: 13846.85 | X56: 165397.3 | Y56: TOTAL MWh | Z56: 6966.3 | AA56: 1421.8 | AB56: 4180 | AC56: 13846.85 | AD56: 26414.95

Sheet HOP
B3: miércoles, 5 de Noviembre del 2025
B5: Reporte de Horas de Operación
B6: Empresa | C6: Central | D6: Grupo | E6: Modo de Operación | F6: Inicio | G6: Final | H6: O. Arranque | I6: O. Parada | J6: Tipo Operación | K6: Ensayo de Potencia Efectiva | L6: Ensayo de Potencia Mínima | M6: Sistema | N6: Lim. Transm. | O6: Causa | P6: Observación
B7: AGRO INDUSTRIAL PARAMONGA S.A. | C7: C.T. PARAMONGA | D7: CENTRAL | E7: PARAMONGA - BAGAZO | F7: 05/11/2025 00:00:00 | G7: 06/11/2025 00:00:00 | J7: NO IDENTIFICADO | O7: ...
B8: AGROAURORA S.A.C. | C8: C.T. MAPLE ETANOL | D8: CENTRAL | E8: MAPLE- BAGAZO | F8: 05/11/2025 05:55:00 | G8: 06/11/2025 00:00:00 | J8: POR COGENERACION | O8: ...
B9: AGROINDUSTRIAS SAN JACINTO S.A.A. | C9: C.T. SAN JACINTO | D9: CENTRAL | E9: SAN_JACINTO - BAGAZO | F9: 05/11/2025 00:00:00 | G9: 06/11/2025 00:00:00 | J9: NO IDENTIFICADO | O9: ...
B10: AGROLMOS SOCIEDAD ANONIMA - AGROLMOS S.A. | C10: C.T. AGROLMOS | D10: CENTRAL | E10: AGROLMOS TV1 & TV2 - BAGAZO | F10: 05/11/2025 00:00:00 | G10: 06/11/2025 00:00:00 | J10: NO IDENTIFICADO | O10: ...
B11: BIOENERGIA DEL CHIRA S.A. | C11: C.T. CAÑA BRAVA | D11: G-1 | E11: CANA BRAVA TV1 - BAGAZO | F11: 05/11/2025 00:00:00 | G11: 06/11/2025 00:00:00 | J11: NO IDENTIFICADO | O11: ...
B12: EGESUR | C12: C.T. INDEPENDENCIA | D12: INDEP_G4 | E12: INDEPENDENCIA GAS | F12: 05/11/2025 00:00:00 | G12: 05/11/2025 08:35:00 | J12: POR PRUEBAS | O12: ...
B13: EGESUR | C13: C.T. INDEPENDENCIA | D13: CENTRAL | E13: INDEPENDENCIA GAS | F13: 05/11/2025 10:18:00 | G13: 05/11/2025 23:32:00 | H13: 05/11/2025 10:14:00 | J13: POR POTENCIA O ENERGIA | O13: ...
B14: EGESUR | C14: C.T. INDEPENDENCIA | D14: INDEP_G4 | E14: INDEPENDENCIA GAS | F14: 05/11/2025 17:07:00 | G14: 05/11/2025 17:36:00 | H14: 05/11/2025 17:02:00 | J14: POR PRUEBAS | O14: ...
B15: EGESUR | C15: C.T. INDEPENDENCIA | D15: CENTRAL | E15: INDEPENDENCIA GAS | F15: 05/11/2025 23:32:00 | G15: 05/11/2025 23:43:00 | I15: 05/11/2025 23:32:15 | J15: A MINIMA CARGA | O15: ...
B16: ENEL GENERACION PIURA S.A. | C16: C.T. MALACAS 1 | D16: CENTRAL | E16: MALACAS1 TG6 - GAS | F16: 05/11/2025 09:41:00 | G16: 05/11/2025 23:58:00 | H16: 05/11/2025 09:27:00 | I16: 05/11/2025 23:57:00 | J16: POR POTENCIA O ENERGIA | O16: ...
B17: ENGIE ENERGIA PERU S.A.A. | C17: C.T. CHILCA 1 | D17: CENTRAL | E17: CHILCA1 CCOMB TG1 & TG2 & TG3 - GAS | F17: 05/11/2025 00:00:00 | G17: 06/11/2025 00:00:00 | J17: POR POTENCIA O ENERGIA | O17: ... | P17: A las 00:00 h S/C bajar a 700 MW. A las 01:30 h S/C bajar a 640 MW.
B18: GM OPERACIONES S.A.C. | C18: CT REFINERIA TALARA | D18: TV1 REF TALARA | E18: REF_TALARA TV1 - NLH_RFG | F18: 05/11/2025 00:00:00 | G18: 06/11/2025 00:00:00 | J18: POR COGENERACION | O18: ...
B19: GM OPERACIONES S.A.C. | C19: CT REFINERIA TALARA | D19: TV2 REF TALARA | E19: REF_TALARA TV2 - NLH_RFG | F19: 05/11/2025 00:00:00 | G19: 06/11/2025 00:00:00 | J19: POR COGENERACION | O19: ...
B20: KALLPA GENERACION S.A. | C20: C.T. KALLPA | D20: CENTRAL | E20: KALLPA CCOMB TG1 & TG2 & TG3 - GAS | F20: 05/11/2025 00:00:00 | G20: 06/11/2025 00:00:00 | J20: POR POTENCIA O ENERGIA | O20: ...
B21: KALLPA GENERACION S.A. | C21: C.T. LAS FLORES | D21: TG1 | E21: LAS FLORES TG1 - GAS | F21: 05/11/2025 17:18:00 | G21: 05/11/2025 23:38:00 | H21: 05/11/2025 16:43:00 | J21: POR POTENCIA O ENERGIA | O21: ...
B22: KALLPA GENERACION S.A. | C22: C.T. LAS FLORES | D22: TG1 | E22: LAS FLORES TG1 - GAS | F22: 05/11/2025 23:38:00 | G22: 06/11/2025 00:00:00 | J22: A MINIMA CARGA | O22: ...
B23: ORYGEN PERU S.A.A. | C23: C.T. VENTANILLA | D23: CENTRAL | E23: VENTANILLA CCOMB TG3 & TG4 - GAS | F23: 05/11/2025 00:00:00 | G23: 05/11/2025 10:22:00 | J23: POR POTENCIA O ENERGIA | O23: ...
B24: ORYGEN PERU S.A.A. | C24: C.T. VENTANILLA | D24: CENTRAL | E24: VENTANILLA CCOMB TG3 & TG4 - GAS F.DIRECTO | F24: 05/11/2025 10:22:00 | G24: 05/11/2025 22:33:00 | J24: POR POTENCIA O ENERGIA | O24: ...
B25: ORYGEN PERU S.A.A. | C25: C.T. VENTANILLA | D25: CENTRAL | E25: VENTANILLA CCOMB TG3 & TG4 - GAS | F25: 05/11/2025 22:33:00 | G25: 06/11/2025 00:00:00 | J25: POR POTENCIA O ENERGIA | O25: ...
B26: PETRAMAS | C26: C.T. HUAYCOLORO | D26: G1 | E26: HUAYCOLORO - BIOGAS | F26: 05/11/2025 00:00:00 | G26: 06/11/2025 00:00:00 | J26: NO IDENTIFICADO | O26: ...
B27: PETRAMAS | C27: C.T. LA GRINGA | D27: G2 | E27: LA GRINGA V - BIOGAS | F27: 05/11/2025 00:00:00 | G27: 06/11/2025 00:00:00 | J27: NO IDENTIFICADO | O27: ...
B28: PETRAMAS | C28: C.T.B DOÑA CATALINA | D28: CENTRAL | E28: DONA CATALINA - BIOGAS | F28: 05/11/2025 00:00:00 | G28: 06/11/2025 00:00:00 | J28: NO IDENTIFICADO | O28: ...
B29: TERMOCHILCA S.A.C. | C29: C.T. OLLEROS | D29: CENTRAL | E29: OLLEROS CCOMB TG1 - GAS | F29: 05/11/2025 00:00:00 | G29: 06/11/2025 00:00:00 | J29: POR POTENCIA O ENERGIA | O29: ...

Sheet INDISP
B3: miércoles, 5 de Noviembre del 2025
B5: Hora Inicio y Fin de Indisponibilidades de las Unidades de Generación SEIN
B6: Empresa | C6: Ubicación | D6: Equipo | E6: Inicio | F6: Final | G6: Descripción | H6: MW Indisp. | I6: Prog. | J6: Dispon | K6: Interrupc. | L6: Tipo | M6: CodEq | N6: TipoEq_Osinerg
B7: ATRIA ENERGIA S.A.C. | C7: PURMACANA | D7: CENTRAL | E7: 05/11/2025 00:00 | F7: 06/11/2025 00:00 | G7: MANTENIMIENTO DE CANAL DE CONDUCCIÓN, COMPUERTAS, SISTEMA DE LUBRICACIÓN DE COJINETES, SISTEMA DE REFRIGERACIÓN Y VÁLVULAS | H7: 0.4 | I7: P | J7: F/S | K7: N | L7: PREV. | M7: 13132 | N7: G
B8: EGESUR | C8: INDEPENDENCIA | D8: INDEP_G4 | E8: 05/11/2025 08:35 | F8: 05/11/2025 17:07 | G8: Verificación de ajuste de espárragos de biela y cojinete principal como parte de su Mantenimiento por 32,000 horas de operación | H8: 5.732 | I8: P | J8: F/S | K8: N | L8: PREV. | M8: 12780 | N8: G
B9: EMPRESA DE GENERACION ELECTRICA SANTA ANA S.A.C. | C9: RENOVANDES H1 | D9: G1 | E9: 05/11/2025 00:00 | F9: 06/11/2025 00:00 | G9: Reemplazo del estator del grupo generador en la Central Hidroeléctrica Renovandes H1 | H9: 20 | I9: P | J9: F/S | K9: N | L9: PREV. | M9: 18265 | N9: G
B10: ENGIE ENERGIA PERU S.A.A. | C10: PUNTA LOMITAS | D10: PL-BL1 | E10: 05/11/2025 08:09 | F10: 05/11/2025 16:47 | G10: BARRA A 33KV F/S POR REPARACION DE CABLE DE ALIMENTACIÓN 33kV TRANSFORMADOR PRINCIPAL TP-1 SE PUNTA LOMITAS | H10: 0 | I10: P | J10: F/S | K10: N | L10: CORR. | M10: 22377 | N10: G
B11: ENGIE ENERGIA PERU S.A.A. | C11: YUNCÁN | D11: G3 | E11: 05/11/2025 00:00 | F11: 05/11/2025 18:12 | G11: APLICACIÓN DE RESINA EN PUNTOS DE DESCARGAS PARCIALES Y PRUEBAS OFFLINE | H11: 45.5 | I11: P | J11: F/S | K11: N | L11: PREV. | M11: 201 | N11: G
B12: FENIX POWER PERÚ | C12: FENIX | D12: TV10 | E12: 05/11/2025 00:00 | F12: 06/11/2025 00:00 | G12: Unidad fuera de servicio por mantenimiento correctivo del Transformador TR-TV10. | H12: 0 | I12: P | J12: F/S | K12: N | L12: OTROS | M12: 13602 | N12: G
B13: JOYA SOLAR S.A.C. | C13: SAN MARTIN SOLAR | D13: CENTRAL | E13: 05/11/2025 00:00 | F13: 06/11/2025 00:00 | G13: INDISPONIBLE POR MANTENIMIENTO DE LA BARRA A Y B DE SE SAN JOSE 220 KV | H13: 0 | I13: P | J13: F/S | K13: N | L13: OTROS | M13: 24345 | N13: G
B14: KALLPA GENERACION S.A. | C14: CERRO DEL AGUILA | D14: G2 | E14: 05/11/2025 00:00 | F14: 05/11/2025 20:47 | G14: MANTENIMIENTO PREVENTIVO SEMESTRAL E INSPECCIONES MENORES. | H14: 189.761 | I14: P | J14: F/S | K14: N | L14: PREV. | M14: 15212 | N14: G
B15: KALLPA GENERACION S.A. | C15: CERRO DEL AGUILA | D15: G2 | E15: 05/11/2025 21:21 | F15: 05/11/2025 21:23 | G15: Unidad indisponible por mantto | H15: 0 | I15: P | J15: F/S | K15: N | L15: CORR. | M15: 15212 | N15: G
B16: KALLPA GENERACION S.A. | C16: LAS FLORES | D16: TV | E16: 05/11/2025 00:00 | F16: 06/11/2025 00:00 | G16: Unidad indisponible para realizar mantenimiento correctivo | H16: 0 | I16: P | J16: F/S | K16: N | L16: CORR. | M16: 22082 | N16: G
B17: KALLPA GENERACION S.A. | C17: SUNNY | D17: CENTRAL | E17: 05/11/2025 00:00 | F17: 06/11/2025 00:00 | G17: INDISPONIBLE POR MANTENIMIENTO DE LA BARRA A Y B DE SE SAN JOSE 220 KV | H17: 0 | I17: P | J17: F/S | K17: N | L17: OTROS | M17: 24346 | N17: G
B18: ORAZUL ENERGY PERÚ | C18: CAÑA BRAVA | D18: G1 | E18: 05/11/2025 00:00 | F18: 06/11/2025 00:00 | G18: Inspección preventiva de sistemas de unidad, Inspección a distribuidor, rótulas, Barras 10KV, Barra SSAA 380V (TAC4), Tablero de distribución TCC4, Tableros de protecciones y control (TPU5/TCU5/TPTU5), Servicio de prueba integral de protecciones eléctricas, Inspección de equipos, etc | H18: 5.67 | I18: P | J18: F/S | K18: N | L18: PREV. | M18: 205 | N18: G
... B35: STATKRAFT S.A | C35: PACHACHACA | D35: G1 | E35: 05/11/2025 00:00 | F35: 06/11/2025 00:00 | G35: MANTENIMIENTO MAYOR UG1 + Mantenimiento Sistema de Control UG1 + Prueba de protecciones T1 | H35: 3 | I35: P | J35: F/S | K35: N | L35: PREV. | M35: 46 | N35: G

Sheet RESERVA_FRÍA
B3: 05/11/2025 | E3: EJECUTADO | L3: Miércoles 5 de Noviembre del 2025 / SEM N° 44 | V3: EJECUTADO | AC3: Miércoles 5 de Noviembre del 2025 / SEM N° 44 | EE3: ENERGIA RENOVABLES | GS3: COGENERACION | HA3: NO INTEGRANTES
B4: Miércoles | C4: HYDROG | D4: ELECTROPERU | H4: ORAZU | J4: TER | L4: KALLPA GENERACION S.A. | T4: SHOUGESA | X4: EGM | Y4: EGESUR | AB4: EGASA | AI4: SGB | AJ4: CELEP | AK4: MINCVE | AL4: ETEN | AN4: HUALLA | AP4: LAVI | AQ4: CHIN | AS4: HUANCH | AT4: CELER | AU4: INLD | AV4: FENIX POWER PERÚ | AY4: STATKRAFT S.A | BG4: STARO | BI4: HUANZA | BJ4: ENEL GENERACION PIURA S.A. | BM4: ENGIE ENERGIA PERU S.A.A. | CA4: IYEP | CC4: SHAQSH | CD4: ORYGEN PERU S.A.A. | CP4: SAMAY I S.A.C | CT4: TCHILC | CV4: GENERACION | CY4: SALIDAS YUPANA | DC4: FLUJO EN LINEAS | DO4: COSTOS MARGINALES | DS4: RESERVA | DX4: DEMANDA POR AREAS | EE4: ACHI | EF4: COLCA | EG4: ERSUR | EH4: GRCOR | EI4: TARU | EJ4: KONDU | EK4: PIEREN | EL4: VARI | EM4: ORAZU | EO4: KALLPA | EP4: SGB | EQ4: AIPSA | ER4: MAJA | ES4: EGECSA | ET4: STANA | EU4: AGUAA | EV4: RDOBLE | EW4: HIDRO | EX4: HUARA | EY4: MOQUE | EZ4: PANAM | FA4: PARQU | FB4: PE3HER | FC4: TACNA | FD4: EYSAC | FE4: AURORA | FF4: AGROIN | FG4: AGROLM | FH4: ANDEA | FI4: ASLC | FJ4: ATRIA | FK4: EGEJUNIN | FO4: EGERBA | FP4: EOL | FR4: ENGIE ENERGIA PERU S.A.A. | FW4: GENE | FY4: GENERADORA DE ENERGÍA DEL PERÚ | GC4: PAINO | GD4: JOYAS | GE4: SARCUS | GF4: ORYGEN PERU S.A.A. | GK4: PETRAMAS | GO4: RARCUS | GP4: SINERS | GS4: ACHI | GT4: GM OP | GV4: AIPSA | GW4: AURORA | GX4: AGROIN | GY4: AGROLM | HA4: UNACEM | HB4: EOR | HC4: AYEP | HD4: ELZANA | HE4: ENOSA | HF4: SDE | HG4: SINERS
C5: 65333 | D5: 101 | E5: 102 | F5: 42667 | G5: 42668 | H5: 126 | I5: 127 | J5: 138 | K5: 139 | L5: 197 | M5: 203 | N5: 204 | O5: 230 | P5: 209 | Q5: 56677 | R5: 796 | S5: 2146 | T5: 142 | U5: 143 | V5: 125 | W5: 187 | X5: 163 | Y5: 298 | Z5: 299 | AA5: 219 | AB5: 151 | AC5: 152 | AD5: 153 | AE5: 154 | AF5: 756 | AG5: 156 | AH5: 155 | AI5: 182 | AJ5: 212 | AK5: 758 | AL5: 263 | AM5: 265 | AN5: 775 | AO5: 777 | AP5: 2154 | AQ5: 150 | AR5: 149 | AS5: 188 | AT5: 2131 | AU5: 755 | AV5: 252 | AW5: 249 | AX5: 250 | AY5: 117 | AZ5: 267 | BA5: 268 | BB5: 119 | BC5: 120 | BD5: 189 | BE5: 122 | BF5: 266 | BG5: 337 | BH5: 338 | BI5: 251 | BJ5: 115 | BK5: 239 | BL5: 288 | BM5: 240 | BN5: 241 | BO5: 242 | BP5: 191 | BQ5: 194 | BR5: 196 | BS5: 207 | BT5: 236 | BU5: 795 | BV5: 285 | BW5: 995 | BX5: 996 | BY5: 997 | BZ5: 766 | CA5: 926 | CB5: 924 | CC5: 121 | CD5: 103 | CE5: 104 | CF5: 106 | CG5: 105 | CH5: 107 | CI5: 110 | CJ5: 109 | CK5: 144 | CL5: 113 | CM5: 114 | CN5: 193 | CO5: 208 | CP5: 786 | CQ5: 787 | CR5: 788 | CS5: 789 | CT5: 248 | CU5: 2159 | CV5: -1222 | CW5: -1223 | CX5: -1224 | CY5: 1221 | CZ5: 1222 | DA5: 1223 | DB5: 1224 | DC5: 1250 | DD5: 1251 | DE5: 1252 | DF5: 1253 | DG5: 1254 | DH5: 1255 | DI5: 1256 | DJ5: 1257 | DK5: 1258 | DL5: 1259 | DM5: 1260 | DN5: 1261 | DO5: 1226 | DP5: 1219 | DQ5: 1220 | DR5: -1203 | DS5: 1227 | DT5: 1205 | DU5: 1207 | DV5: 1206 | DW5: 1218 | DX5: 1211 | DY5: 1212 | DZ5: 1213 | EA5: 1214 | EB5: 1229 | EC5: -1221 | EE5: 289 | EF5: 303 | EG5: 59715 | EH5: 62255 | EI5: 1263 | EJ5: 61800 | EK5: 2194 | EL5: 69125 | EM5: 216 | EN5: 198 | EO5: 70400 | EP5: 49607 | EQ5: 213 | ER5: 214 | ES5: 260 | ET5: 2152 | EU5: 2128 | EV5: 247 | EW5: 228 | EX5: 2135 | EY5: 261 | EZ5: 237 | FA5: 253 | FB5: 770 | FC5: 235 | FD5: 238 | FE5: 232 | FF5: 2190 | FG5: 69867 | FH5: 2184 | FI5: 61855 | FJ5: 223 | FK5: 226 | FL5: 201 | FM5: 258 | FN5: 259 | FO5: 920 | FP5: 257 | FQ5: 256 | FR5: 2148 | FS5: 58288 | FT5: 58289 | FU5: 58839 | FV5: 58840 | FW5: 296 | FX5: 297 | FY5: 211 | FZ5: 2175 | GA5: 2178 | GB5: 2181 | GC5: 1262 | GD5: 63425 | GE5: 233 | GF5: 2150 | GG5: 2165 | GH5: 2161 | GI5: 61197 | GJ5: 58851 | GK5: 225 | GL5: 2201 | GM5: 2171 | GN5: 760 | GO5: 234 | GP5: 215 | GQ5: 917 | GS5: 289 | GT5: 58333 | GU5: 58336 | GV5: 213 | GW5: 232 | GX5: 2190 | GY5: 69867 | HA5: 221 | HB5: 222 | HC5: 224 | HD5: 2187 | HE5: 227 | HF5: 49400 | HG5: 199 | HH5: 200 | HJ5: 7000 | HK5: 7001 | HL5: 7002
B6: Día Hora | C6: SAN GABAN III | D6: MANTARO | E6: RESTITUCION | F6: TUMBES MAK 1 | G6: TUMBES MAK 2 | H6: CARHUAQUERO | I6: CAÑON DEL PATO | J6: AGUAYTIA TG1 | K6: AGUAYTIA TG2 | L6: KALLPA TG1 | M6: KALLPA TG2 | N6: KALLPA TG3 | O6: KALLPA TV | P6: LFLORES TG1 | Q6: LFLORES TV | R6: CERRO DEL AGUILA | S6: CERRODELAGUILAG4 | T6: SHOUGESA TV1 | U6: SHOUGESA TV2 | V6: SHOUGESA TV3 | W6: SHOUGESA CUMMINS | X6: MACHUPICCHU | Y6: ARICOTA 1 | Z6: ARICOTA 2 | AA6: INDEPENDENCIA | AB6: CHARCANI I,II,III | AC6: CHARCANI IV | AD6: CHARCANI V | AE6: CHARCANI VI | AF6: CHILINA TG | AG6: MOLLENDO 1, 2, 3 | AH6: CHILINA (SULZ 1,2) | AI6: SAN GABAN II | AJ6: PLATANAL | AK6: RECKA | AL6: RF ETEN TG1 | AM6: RF ETEN TG2 | AN6: CHAGLLA GP1 | AO6: CHAGLLA | AP6: LA VIRGEN | AQ6: CHIMAY | AR6: YANANGO | AS6: HUANCHOR | AT6: MARAÑON | AU6: STA TERESA | AV6: FENIX GT11 | AW6: FENIX GT12 | AX6: FENIX TV10 | AY6: YAUPI | AZ6: OROYA | BA6: PACHACHACA | BB6: MALPASO | BC6: CAHUA | BD6: ARCATA | BE6: GALLITO CIEGO | BF6: CHEVES | BG6: SANTA ROSA 1 | BH6: SANTA ROSA 2 | BI6: HUANZA | BJ6: MALACAS2 TG4 | BK6: MALACAS3 TG 5 | BL6: MALACAS1 TG6 | BM6: RF ILO2 TG1 | BN6: RF ILO2 TG2 | BO6: RF ILO2 TG3 | BP6: YUNCAN | BQ6: CHILCA1 TG1 | BR6: CHILCA1 TG2 | BS6: CHILCA1 TG3 | BT6: CHILCA-TV | BU6: CHILCA2 TG41 | BV6: CHILCA2-TV | BW6: CTNEPI_TG41 | BX6: CTNEPI_TG42 | BY6: CTNEPI_TG43 | BZ6: QUITARACSA | CA6: RF PTO MALDONADO | CB6: RF PUCALLPA | CC6: PARIAC | CD6: HUINCO | CE6: MATUCANA | CF6: MOYOPAMPA | CG6: CALLAHUANCA | CH6: HUAMPANI | CI6: STA ROSA WEST TG7 | CJ6: UTI_5 | CK6: UTI_6 | CL6: VENTANILLA 3 | CM6: VENTANILLA 4 | CN6: VENTANILLA TV | CO6: STAROSA TG8 | CP6: PTO_BRVO TG1 | CQ6: PTO_BRVO TG2 | CR6: PTO_BRVO TG3 | CS6: PTO_BRVO TG4 | CT6: OLLEROS TG1 | CU6: OLLEROS TV | CV6: Total CoGeneracion | CW6: Total Renovables | CX6: Total Generación COES | CY6: Demanda YUPANA | CZ6: Oferta | DA6: Perdidas YUPANA | DB6: Deficit YUPANA | DC6: FLUJO ENLACE CENTRO - SUR | DD6: FLUJO CHILCA CARAPONGO 500 KV | DE6: FLUJO CARAPONGO CARABAYLLO 500 KV | DF6: FLUJO CHIMBOTE TRUJILLO 500 KV | DG6: FLUJO TRUJILLO LA NIÑA 500 KV | DH6: FLUJO COLCABAMBA POROMA 500 KV | DI6: FLUJO CHILCA POROMA 500 KV | DJ6: FLUJO POROMA YARABAMBA 500 KV | DK6: FLUJO POROMA OCOÑA 500 KV | DL6: FLUJO YARABAMBA MOLTALVO 500 KV | DM6: FLUJO HUANCAVELICA - INDEPENDENCIA 220 KV | DN6: FLUJO CHILCA - SAN JUAN 220 KV | DO6: Cmg Santa Rosa YUPANA(US$/MWh) | DP6: Cmg Trujillo YUPANA(US$/MWh) | DQ6: Cmg Socabaya YUPANA(US$/MWh) | DR6: Nivel de Demanda | DS6: Reserva Fría Térmica | DT6: Reserva Eficiente | DU6: Reserva Eficiente Gas | DV6: Reserva Eficiente Carbón | DW6: Nivel Tablachaca | DX6: Demanda Centro | DY6: Demanda Norte | DZ6: Demanda Sur | EA6: Demanda Electroandes | EB6: Demanda Ecuador | EC6: Demanda COES | EE6: CANA BRAVA | EF6: CS YARUCAYA | EG6: SAN JUAN | EH6: MATARANI | EI6: DUNA | EJ6: CARHUAQUERO (CS) | EK6: MANTA I | EL6: ANASHIRONI | EM6: CARHUAQUERO4 | EN6: CAÑA BRAVA | EO6: SUNNY | EP6: TUPURI | EQ6: PARAMONGA | ER6: RONCADOR | ES6: CANCHAYLLO | ET6: RENOVANDESH1 | EU6: POTRERO | EV6: PIZARRAS | EW6: NIMPERIAL | EX6: YARUCAYA | EY6: MOQUEGUA-SOLAR | EZ6: PANAMERICANA-SOLAR | FA6: PQE-EOLICO-MARCONA | FB6: PQE-EOLICO-3-HERMANAS | FC6: TACNA-SOLAR | FD6: YANAPAMPA | FE6: MAPLE | FF6: SAN_JACINTO | FG6: AGROLMOS | FH6: CARHUAC | FI6: HUALLIN | FJ6: PURMACANA | FK6: HUASAHUASI | FL6: STACRUZ_1_2 | FM6: RUNATULLO_II | FN6: RUNATULLO_III | FO6: RUCUY | FP6: PQE-EOLICO-TALARA | FQ6: PQE-EOLICO-CUPISNIQUE | FR6: INTIPAMPA | FS6: PUNTA LOMITAS-BL1 | FT6: PUNTA LOMITAS-BL2 | FU6: PUN LOMITAS_EXP-BL1 | FV6: PUN LOMITAS_EXP-BL2 | FW6: 8AGOSTO | FX6: EL CARMEN | FY6: LA JOYA | FZ6: ANGEL_I | GA6: ANGEL_II | GB6: ANGEL_III | GC6: HUAMBOS | GD6: SAN MARTIN SOLAR | GE6: MAJES | GF6: RUBI | GG6: CH_HER1 | GH6: WAYRA-I | GI6: WAYRA EXTENSION | GJ6: CLEMESI | GK6: HUAYCOLORO | GL6: CALLAO | GM6: DONA_CATALINA | GN6: LAGRINGAV | GO6: REPARTICION | GP6: POECHOS2 | GQ6: CHANCAY | GS6: CANA BRAVA | GT6: REFINERIA TALARA TV1 | GU6: REFINERÍA TALARA TV2 | GV6: PARAMONGA | GW6: MAPLE | GX6: SAN_JACINTO | GY6: AGROLMOS | HA6: CARPAPATA | HB6: CENTRALES ELOR | HC6: PIAS1 | HD6: ZANA | HE6: TABLAZO | HF6: TALLANCA | HG6: CURUMUY | HH6: POECHOS1 | HJ6: ReservaFriaTermica | HK6: ReservaFria Rapida Termica | HL6: ReservaFria Termica xMantenimiento
B7: 00:30 | F7: 8.82587 | G7: 8.51669 | J7: 81.0961 | Q7: 211.16728 | T7: 18.14123 | U7: 19.19196 | V7: 24.42536 | W7: 1.06127 | AA7: 17.29572 | AF7: 12.23925 | AG7: 24.4617 | AH7: 10.27692 | AK7: 179.37322 | AM7: 7.93273 | AX7: 355.93154 | BK7: 184.87493 | BL7: 46.578 | BM7: 164.44227 | BN7: 165.47058 | BO7: 165.59853 | BV7: 110.49702 | BW7: 206.49456 | BX7: 206.11549 | BY7: 205.99003 | CA7: 17.41583 | CB7: 44.05367 | CI7: 118.14735 | CJ7: 52.41851 | CK7: 53.71012 | CO7: 191.19621 | CP7: 180.55348 | CQ7: 180.52451 | CR7: 181.33356 | CS7: 181.02912 | HJ7: 3636.3806 | HK7: 3574.6221 | HL7: 542.18261
B8: 01:00 | F8: 8.82587 | G8: 8.51669 | J8: 81.0961 | Q8: 211.16728 | T8: 18.14123 | U8: 19.19196 | V8: 24.42536 | W8: 1.06127 | AA8: 17.29572 | AF8: 12.23925 | AG8: 24.4617 | AH8: 10.27692 | AK8: 179.37322 | AM8: 7.93273 | AX8: 355.93154 | BK8: 184.87493 | BL8: 46.578 | BM8: 164.44227 | BN8: 165.47058 | BO8: 165.59853 | BV8: 110.49702 | BW8: 206.49456 | BX8: 206.11549 | BY8: 205.99003 | CA8: 17.41583 | CB8: 44.05367 | CI8: 118.14735 | CJ8: 52.41851 | CK8: 53.71012 | CO8: 191.19621 | CP8: 180.55348 | CQ8: 180.52451 | CR8: 181.33356 | CS8: 181.02912 | HJ8: 3636.3806 | HK8: 3574.6221 | HL8: 542.18261
B9: 01:30 | F9: 8.82587 | G9: 8.51669 | J9: 81.0961 | Q9: 211.16728 | T9: 18.14123 | U9: 19.19196 | V9: 24.42536 | W9: 1.06127 | AA9: 17.29572 | AF9: 12.23925 | AG9: 24.4617 | AH9: 10.27692 | AK9: 179.37322 | AM9: 7.93273 | AX9: 355.93154 | BK9: 184.87493 | BL9: 46.578 | BM9: 164.44227 | BN9: 165.47058 | BO9: 165.59853 | BV9: 110.49702 | BW9: 206.49456 | BX9: 206.11549 | BY9: 205.99003 | CA9: 17.41583 | CB9: 44.05367 | CI9: 118.14735 | CJ9: 52.41851 | CK9: 53.71012 | CO9: 191.19621 | CP9: 180.55348 | CQ9: 180.52451 | CR9: 181.33356 | CS9: 181.02912 | HJ9: 3636.3806 | HK9: 3574.6221 | HL9: 542.18261
B10: 02:00 | F10: 8.82587 | G10: 8.51669 | J10: 81.0961 | Q10: 211.16728 | T10: 18.14123 | U10: 19.19196 | V10: 24.42536 | W10: 1.06127 | AA10: 17.29572 | AF10: 12.23925 | AG10: 24.4617 | AH10: 10.27692 | AK10: 179.37322 | AM10: 7.93273 | AX10: 355.93154 | BK10: 184.87493 | BL10: 46.578 | BM10: 164.44227 | BN10: 165.47058 | BO10: 165.59853 | BV10: 110.49702 | BW10: 206.49456 | BX10: 206.11549 | BY10: 205.99003 | CA10: 17.41583 | CB10: 44.05367 | CI10: 118.14735 | CJ10: 52.41851 | CK10: 53.71012 | CO10: 191.19621 | CP10: 180.55348 | CQ10: 180.52451 | CR10: 181.33356 | CS10: 181.02912 | HJ10: 3636.3806 | HK10: 3574.6221 | HL10: 542.18261
B11: 02:30 | F11: 8.82587 | G11: 8.51669 | J11: 81.0961 | Q11: 211.16728 | T11: 18.14123 | U11: 19.19196 | V11: 24.42536 | W11: 1.06127 | AA11: 17.29572 | AF11: 12.23925 | AG11: 24.4617 | AH11: 10.27692 | AK11: 179.37322 | AM11: 7.93273 | AX11: 355.93154 | BK11: 184.87493 | BL11: 46.578 | BM11: 164.44227 | BN11: 165.47058 | BO11: 165.59853 | BV11: 110.49702 | BW11: 206.49456 | BX11: 206.11549 | BY11: 205.99003 | CA11: 17.41583 | CB11: 44.05367 | CI11: 118.14735 | CJ11: 52.41851 | CK11: 53.71012 | CO11: 191.19621 | CP11: 180.55348 | CQ11: 180.52451 | CR11: 181.33356 | CS11: 181.02912 | HJ11: 3636.3806 | HK11: 3574.6221 | HL11: 542.18261
B12: 03:00 | F12: 8.82587 | G12: 8.51669 | J12: 81.0961 | Q12: 211.16728 | T12: 18.14123 | U12: 19.19196 | V12: 24.42536 | W12: 1.06127 | AA12: 17.29572 | AF12: 12.23925 | AG12: 24.4617 | AH12: 10.27692 | AK12: 179.37322 | AM12: 7.93273 | AX12: 355.93154 | BK12: 184.87493 | BL12: 46.578 | BM12: 164.44227 | BN12: 165.47058 | BO12: 165.59853 | BV12: 110.49702 | BW12: 206.49456 | BX12: 206.11549 | BY12: 205.99003 | CA12: 17.41583 | CB12: 44.05367 | CI12: 118.14735 | CJ12: 52.41851 | CK12: 53.71012 | CO12: 191.19621 | CP12: 180.55348 | CQ12: 180.52451 | CR12: 181.33356 | CS12: 181.02912 | HJ12: 3636.3806 | HK12: 3574.6221 | HL12: 542.18261
B13: 03:30 | F13: 8.82587 | G13: 8.51669 | J13: 81.0961 | Q13: 211.16728 | T13: 18.14123 | U13: 19.19196 | V13: 24.42536 | W13: 1.06127 | AA13: 17.29572 | AF13: 12.23925 | AG13: 24.4617 | AH13: 10.27692 | AK13: 179.37322 | AM13: 7.93273 | AX13: 355.93154 | BK13: 184.87493 | BL13: 46.578 | BM13: 164.44227 | BN13: 165.47058 | BO13: 165.59853 | BV13: 110.49702 | BW13: 206.49456 | BX13: 206.11549 | BY13: 205.99003 | CA13: 17.41583 | CB13: 44.05367 | CI13: 118.14735 | CJ13: 52.41851 | CK13: 53.71012 | CO13: 191.19621 | CP13: 180.55348 | CQ13: 180.52451 | CR13: 181.33356 | CS13: 181.02912 | HJ13: 3636.3806 | HK13: 3574.6221 | HL13: 542.18261
B14: 04:00 | F14: 8.82587 | G14: 8.51669 | J14: 81.0961 | Q14: 211.16728 | T14: 18.14123 | U14: 19.19196 | V14: 24.42536 | W14: 1.06127 | AA14: 17.29572 | AF14: 12.23925 | AG14: 24.4617 | AH14: 10.27692 | AK14: 179.37322 | AM14: 7.93273 | AX14: 355.93154 | BK14: 184.87493 | BL14: 46.578 | BM14: 164.44227 | BN14: 165.47058 | BO14: 165.59853 | BV14: 110.49702 | BW14: 206.49456 | BX14: 206.11549 | BY14: 205.99003 | CA14: 17.41583 | CB14: 44.05367 | CI14: 118.14735 | CJ14: 52.41851 | CK14: 53.71012 | CO14: 191.19621 | CP14: 180.55348 | CQ14: 180.52451 | CR14: 181.33356 | CS14: 181.02912 | HJ14: 3636.3806 | HK14: 3574.6221 | HL14: 542.18261
B15: 04:30 | F15: 8.82587 | G15: 8.51669 | J15: 81.0961 | Q15: 211.16728 | T15: 18.14123 | U15: 19.19196 | V15: 24.42536 | W15: 1.06127 | AA15: 17.29572 | AF15: 12.23925 | AG15: 24.4617 | AH15: 10.27692 | AK15: 179.37322 | AM15: 7.93273 | AX15: 355.93154 | BK15: 184.87493 | BL15: 46.578 | BM15: 164.44227 | BN15: 165.47058 | BO15: 165.59853 | BV15: 110.49702 | BW15: 206.49456 | BX15: 206.11549 | BY15: 205.99003 | CA15: 17.41583 | CB15: 44.05367 | CI15: 118.14735 | CJ15: 52.41851 | CK15: 53.71012 | CO15: 191.19621 | CP15: 180.55348 | CQ15: 180.52451 | CR15: 181.33356 | CS15: 181.02912 | HJ15: 3636.3806 | HK15: 3574.6221 | HL15: 542.18261
B16: 05:00 | F16: 8.82587 | G16: 8.51669 | J16: 81.0961 | Q16: 211.16728 | T16: 18.14123 | U16: 19.19196 | V16: 24.42536 | W16: 1.06127 | AA16: 17.29572 | AF16: 12.23925 | AG16: 24.4617 | AH16: 10.27692 | AK16: 179.37322 | AM16: 7.93273 | AX16: 355.93154 | BK16: 184.87493 | BL16: 46.578 | BM16: 164.44227 | BN16: 165.47058 | BO16: 165.59853 | BV16: 110.49702 | BW16: 206.49456 | BX16: 206.11549 | BY16: 205.99003 | CA16: 17.41583 | CB16: 44.05367 | CI16: 118.14735 | CJ16: 52.41851 | CK16: 53.71012 | CO16: 191.19621 | CP16: 180.55348 | CQ16: 180.52451 | CR16: 181.33356 | CS16: 181.02912 | HJ16: 3636.3806 | HK16: 3574.6221 | HL16: 542.18261
B17: 05:30 | F17: 8.82587 | G17: 8.51669 | J17: 81.0961 | Q17: 211.16728 | T17: 18.14123 | U17: 19.19196 | V17: 24.42536 | W17: 1.06127 | AA17: 17.29572 | AF17: 12.23925 | AG17: 24.4617 | AH17: 10.27692 | AK17: 179.37322 | AM17: 7.93273 | AX17: 355.93154 | BK17: 184.87493 | BL17: 46.578 | BM17: 164.44227 | BN17: 165.47058 | BO17: 165.59853 | BV17: 110.49702 | BW17: 206.49456 | BX17: 206.11549 | BY17: 205.99003 | CA17: 17.41583 | CB17: 44.05367 | CI17: 118.14735 | CJ17: 52.41851 | CK17: 53.71012 | CO17: 191.19621 | CP17: 180.55348 | CQ17: 180.52451 | CR17: 181.33356 | CS17: 181.02912 | HJ17: 3636.3806 | HK17: 3574.6221 | HL17: 542.18261
B18: 06:00 | F18: 8.82587 | G18: 8.51669 | J18: 81.0961 | Q18: 211.16728 | T18: 18.14123 | U18: 19.19196 | V18: 24.42536 | W18: 1.06127 | AA18: 17.29572 | AF18: 12.23925 | AG18: 24.4617 | AH18: 10.27692 | AK18: 179.37322 | AM18: 7.93273 | AX18: 355.93154 | BK18: 184.87493 | BL18: 46.578 | BM18: 164.44227 | BN18: 165.47058 | BO18: 165.59853 | BV18: 110.49702 | BW18: 206.49456 | BX18: 206.11549 | BY18: 205.99003 | CA18: 17.41583 | CB18: 44.05367 | CI18: 118.14735 | CJ18: 52.41851 | CK18: 53.71012 | CO18: 191.19621 | CP18: 180.55348 | CQ18: 180.52451 | CR18: 181.33356 | CS18: 181.02912 | HJ18: 3636.3806 | HK18: 3574.6221 | HL18: 542.18261
... B25: 09:30 | F25: 8.82587 | G25: 8.51669 | J25: 81.0961 | Q25: 211.16728 | T25: 18.14123 | U25: 19.19196 | V25: 24.42536 | W25: 1.06127 | AA25: 17.29572 | AF25: 12.23925 | AG25: 24.4617 | AH25: 10.27692 | AK25: 179.37322 | AM25: 7.93273 | AX25: 355.93154 | BK25: 184.87493 | BL25: 46.578 | BM25: 164.44227 | BN25: 165.47058 | BO25: 165.59853 | BV25: 110.49702 | BW25: 206.49456 | BX25: 206.11549 | BY25: 205.99003 | CA25: 17.41583 | CB25: 44.05367 | CI25: 118.14735 | CJ25: 52.41851 | CK25: 53.71012 | CO25: 191.19621 | CP25: 180.55348 | CQ25: 180.52451 | CR25: 181.33356 | CS25: 181.02912 | HJ25: 3636.3806 | HK25: 3574.6221 | HL25: 547.94757
B26: 10:00 | F26: 8.82587 | G26: 8.51669 | J26: 81.0961 | Q26: 211.16728 | T26: 18.14123 | U26: 19.19196 | V26: 24.42536 | W26: 1.06127 | AA26: 17.29572 | AF26: 12.23925 | AG26: 24.4617 | AH26: 10.27692 | AK26: 179.37322 | AM26: 7.93273 | AX26: 355.93154 | BK26: 184.87493 | BM26: 164.44227 | BN26: 165.47058 | BO26: 165.59853 | BV26: 110.49702 | BW26: 206.49456 | BX26: 206.11549 | BY26: 205.99003 | CA26: 17.41583 | CB26: 44.05367 | CI26: 118.14735 | CJ26: 52.41851 | CK26: 53.71012 | CO26: 191.19621 | CP26: 180.55348 | CQ26: 180.52451 | CR26: 181.33356 | CS26: 181.02912 | HJ26: 3589.8026 | HK26: 3528.0441 | HL26: 547.94757
B27: 10:30 | F27: 8.82587 | G27: 8.51669 | J27: 81.0961 | Q27: 211.16728 | T27: 18.14123 | U27: 19.19196 | V27: 24.42536 | W27: 1.06127 | AF27: 12.23925 | AG27: 24.4617 | AH27: 10.27692 | AK27: 179.37322 | AM27: 7.93273 | AX27: 355.93154 | BK27: 184.87493 | BM27: 164.44227 | BN27: 165.47058 | BO27: 165.59853 | BV27: 110.49702 | BW27: 206.49456 | BX27: 206.11549 | BY27: 205.99003 | CA27: 17.41583 | CB27: 44.05367 | CI27: 118.14735 | CJ27: 52.41851 | CK27: 53.71012 | CO27: 191.19621 | CP27: 180.55348 | CQ27: 180.52451 | CR27: 181.33356 | CS27: 181.02912 | HJ27: 3572.5069 | HK27: 3510.7483 | HL27: 547.94757
B28: 11:00 | F28: 8.82587 | G28: 8.51669 | J28: 81.0961 | Q28: 211.16728 | T28: 18.14123 | U28: 19.19196 | V28: 24.42536 | W28: 1.06127 | AF28: 12.23925 | AG28: 24.4617 | AH28: 10.27692 | AK28: 179.37322 | AM28: 7.93273 | AX28: 355.93154 | BK28: 184.87493 | BM28: 164.44227 | BN28: 165.47058 | BO28: 165.59853 | BV28: 110.49702 | BW28: 206.49456 | BX28: 206.11549 | BY28: 205.99003 | CA28: 17.41583 | CB28: 44.05367 | CI28: 118.14735 | CJ28: 52.41851 | CK28: 53.71012 | CO28: 191.19621 | CP28: 180.55348 | CQ28: 180.52451 | CR28: 181.33356 | CS28: 181.02912 | HJ28: 3572.5069 | HK28: 3510.7483 | HL28: 547.94757
