Workbook

Sheet EVENTOS
B3: martes, 4 de Noviembre del 2025
B5: INFORMACIÓN DE EVENTOS PRINCIPALES EN SUS INSTALACIONES
B6: TIPO DE EVENTO | C6: EMPRESA | D6: UBICACIÓN | E6: TIPO DE EQUIPO | F6: EQUIPO | G6: INICIO | H6: FINAL | I6: DESCRIPCIÓN | J6: MW INDISP. | K6: INTERRUPCIÓN (SI/NO) | L6: TENSIÓN DE FALLA (kV)
B7: FALLA | C7: AGRO INDUSTRIAL PARAMONGA S.A. | D7: PARAMONGA | E7: CENTRAL TERMOELÉCTRICA | F7: CENTRAL | G7: 04/11/2025 10:27:00 | H7: 04/11/2025 11:43:00 | I7: DESCONEXIÓN DE LA C.T. PARAMONGA POR FALLA | K7: NO | L7: 13.8
B8: FALLA | C8: AGROAURORA S.A.C. | D8: MAPLE ETANOL | E8: CENTRAL TERMOELÉCTRICA | F8: CENTRAL | G8: 04/11/2025 21:35:00 | H8: 05/11/2025 05:55:00 | I8: DESCONEXIÓN DE LA LINEA L-6699 (PIURA OESTE - PLANTA ETANOL) EN 60 KV | K8: NO | L8: 0
B9: EVENTO | C9: CONELSUR LT SAC | D9: PORTILLO | E9: SUBESTACION | F9: SS.EE. | G9: 04/11/2025 00:00:00 | H9: 05/11/2025 00:00:00 | I9: DECLARACIÓN DE SITUACIÓN EXCEPCIONAL EN LA S.E. PORTILLO 60 kV | K9: NO
B10: FALLA | C10: EGASA | D10: CHARCANI IV | E10: GENERADOR HIDROELÉCTRICO | F10: G3 | G10: 04/11/2025 08:44:00 | H10: 04/11/2025 11:53:00 | I10: DESCONEXIÓN DEL GENERADOR G3 DE LA C.H. CHARCANI IV | K10: NO | L10: 5.25
B11: FALLA | C11: EMPRESA DE GENERACION ELECTRICA SANTA ANA S.A.C. | D11: LA VIRGEN | E11: TRANSFORMADOR 2D | F11: TE4 | G11: 04/11/2025 21:33:00 | H11: 04/11/2025 22:20:00 | I11: DESCONEXIÓN DEL TRANSFORMADOR TE4 138/60 KV DE LA S.E. LA VIRGEN | K11: NO | L11: 138
B12: FALLA | C12: MINERA CERRO VERDE | D12: SAN JOSE | E12: BANCO DE CONDENSADORES SERIE | F12: BCS-5982 | G12: 04/11/2025 11:04:00 | H12: 04/11/2025 11:43:00 | I12: DESCONEXIÓN DEL BANCO DE CONDENSADORES SERIE BCS-5982 DE 500 KV DE LA S.E. SAN JOSÉ | K12: NO | L12: 500
B13: FALLA | C13: ORYGEN PERU S.A.A. | D13: CALLAHUANCA | E13: GENERADOR HIDROELÉCTRICO | F13: G1 | G13: 04/11/2025 08:31:00 | H13: 04/11/2025 09:08:00 | I13: DESCONEXIÓN DEL GENERADOR G1 DE LA C.H. CALLAHUANCA | K13: NO | L13: 6.5
B14: EVENTO | C14: RED DE ENERGIA DEL PERU S.A. | D14: TINGO MARÍA - AUCAYACU | E14: LINEA DE TRANSMISION | F14: L-1122 | G14: 04/11/2025 18:20:00 | H14: 04/11/2025 20:05:00 | I14: DECLARACION DE SITUACION EXCEPCIONAL EN LA LINEA L-1122 (TINGO MARÍA - AUCAYACU) DE 138 KV, POR SOBRECARGA | K14: NO

Sheet RESTRIC_OPE
B3: martes, 4 de Noviembre del 2025
B5: RESTRICCIONES OPERATIVAS
B6: FECHA | C6: HORA INICIO | D6: HORA FINAL | E6: EMPRESA | F6: UBICACIÓN | G6: T.Eq. | H6: EQUIPO | I6: DESCRIPCIÓN
B7: 04/11/2025 | C7: 00:00 | D7: 24:00 | E7: CELEPSA | F7: C.H. EL PLATANAL | G7: CH | H7: CENTRAL | I7: De acuerdo con el correo del 13/10/2025. Debido a problemas en el control de la compuerta de bocatoma, informaron que el servicio de RSF queda indisponible.
B8: 04/11/2025 | C8: 00:00 | D8: 24:00 | E8: EGASA | F8: S.E. CONVERTIDOR | G8: BARRA | H8: BARRA138KV | I8: EGASA limitó la capacidad del transformador 138 kV/33 kV a 50 MVA por deterioro del aislamiento.
B9: 04/11/2025 | C9: 00:00 | D9: 24:00 | E9: ELECTROPERU | F9: C.H. MANTARO | G9: CH | H9: CENTRAL | I9: De acuerdo con el correo del día 25.08.2025, la central tiene una limitación de potencia máxima de 650 MW por seguridad de la central.
B10: 04/11/2025 | C10: 00:00 | D10: 24:00 | E10: ENEL GENERACION PIURA S.A. | F10: C.T. MALACAS | G10: CT | H10: CENTRAL | I10: De acuerdo con la comunicación vía correo del día 24.10.2024. ENEL GENERACIÓN PIURA informa una restricción de potencia para alcanzar 105 MW en simultaneo (TG6+TGN4).
B11: 04/11/2025 | C11: 00:00 | D11: 24:00 | E11: ENEL GENERACION PIURA S.A. | F11: C.T. MALACAS | G11: GT | H11: TG4 | I11: De acuerdo a lo informado mediante correo electrónico el día 25.10, con la disponibilidad actual de aproximadamente 13 MMPCD (368.12 Mm³) la unidad TG4 puede con una generación de 80 MW durante 5 horas, y a potencia mínima durante el resto de los periodos
B12: 04/11/2025 | C12: 00:00 | D12: 24:00 | E12: ENGIE ENERGIA PERU S.A.A. | F12: C.H. YUNCÁN | G12: GH | H12: G3 | I12: Según la carta N° ENG/ 198-2024 enviada por su representada, se opera de forma continua el G3 de la CH Yuncán, debido a la ejecución de mantenimientos necesarios para evitar daños en los sellos de seguridad de la válvula esférica del grupo.
B13: 04/11/2025 | C13: 00:00 | D13: 24:00 | E13: ENGIE ENERGIA PERU S.A.A. | F13: C.T. CHILCA 1 | G13: CT | H13: CENTRAL | I13: Restricción de temperatura de la C.T Chilca, ver valor en el modelo de despacho.
B14: 04/11/2025 | C14: 00:00 | D14: 24:00 | E14: ENGIE ENERGIA PERU S.A.A. | F14: C.T. CHILCA 1 | G14: CT | H14: CENTRAL | I14: Con carta ENG/971-2023, indica que no puede cumplir con las IO considerada en el PDO_17122023 dado que vulneran la seguridad de sus activos. Indican que se debe tomar TMO=168h.
B15: 04/11/2025 | C15: 00:00 | D15: 24:00 | E15: ENGIE ENERGIA PERU S.A.A. | F15: C.T. CHILCA 2 | G15: CT | H15: CENTRAL | I15: Con carta ENG/971-2023, indica que no puede cumplir con las IO considerada en el PDO_17122023 dado que vulneran la seguridad de sus activos. Indican que se debe tomar TMO=168h.
B16: 04/11/2025 | C16: 00:00 | D16: 24:00 | E16: FENIX POWER PERÚ | F16: C.T. FENIX | G16: CT | H16: CENTRAL | I16: De acuerdo con lo comunicado en el correo del día 06.05.2025, la CT Fenix cuenta con TMO de 168 hrs en todos sus modos de operación.
B17: 04/11/2025 | C17: 00:00 | D17: 24:00 | E17: KALLPA GENERACION S.A. | F17: C.H. MINI CENTRAL CERRO DEL AGUILA | G17: CH | H17: CENTRAL | I17: Caudal ecológico de la Mini CH Cerro del Águila es de 10.6 m3/s correspondiente al mes de noviembre.
... B47: 04/11/2025 | C47: 00:00 | D47: 24:00 | E47: TERMOSELVA | F47: C.T. AGUAYTÍA | G47: CT | H47: CENTRAL | I47: Disponibilidad de 23.5 MMSCF para la CT Aguaytía.

Sheet MANTENIMIENTO EJECUTADOS
B3: martes, 4 de Noviembre del 2025
B5: Mantenimiento Ejecutado
B6: Empresa | C6: Ubicación | D6: Equipo | E6: Inicio | F6: Final | G6: Descripción | H6: MW Indisp. | I6: Prog. | J6: Dispon | K6: Interrupc. | L6: Tipo | M6: CodEq | N6: TipoEq_Osinerg
B7: AGROINDUSTRIAS SAN JACINTO S.A.A. | C7: SAN JACINTO | D7: CENTRAL | E7: 04/11/2025 00:00 | F7: 05/11/2025 00:00 | G7: Mantenimiento Mensual | H7: 8.15 | I7: P | J7: F/S | K7: N | L7: PREV. | M7: 19865 | N7: G
B8: ATLANTICA TRANSMISION SUR S.A. | C8: CHILCA CTM - POROMA | D8: L-5032 | E8: 04/11/2025 07:15 | F8: 04/11/2025 16:49 | G8: Mejoramiento de PAT | H8: 0 | I8: P | J8: E/S | K8: N | L8: PREV. | M8: 13652 | N8: T
B9: ATLANTICA TRANSMISION SUR S.A. | C9: MONTALVO | D9: CL-2057 | E9: 04/11/2025 07:57 | F9: 04/11/2025 13:17 | G9: Reemplazo de transformador de corriente TCL-5601 de fase R | H9: 0 | I9: P | J9: F/S | K9: N | L9: CORR. | M9: 13812 | N9: T
B10: ATLANTICA TRANSMISION SUR S.A. | C10: MONTALVO - MOQUEGUA | D10: L-2057 | E10: 04/11/2025 07:59 | F10: 04/11/2025 13:17 | G10: Desconexion por seguridad debido a reemplazo de transformador de corriente TCL-5601 de fase R en CL-2057 SE Montalvo | H10: 0 | I10: P | J10: F/S | K10: N | L10: OTROS | M10: 13815 | N10: T
B11: ATLANTICA TRANSMISION SUR S.A. | C11: OCONA | D11: INT-5450 | E11: 04/11/2025 00:00 | F11: 05/11/2025 00:00 | G11: Interruptor INT-5450 cerrado con restriccion operativa, REB-5450 en servicio y suministrando los SS.AA. de la S.E. Oco?a. | H11: 0 | I11: P | J11: E/S | K11: N | L11: OTROS | M11: 13761 | N11: T
B12: ATLANTICA TRANSMISION SUR S.A. | C12: POROMA | D12: INT-5371 | E12: 04/11/2025 00:00 | F12: 05/11/2025 00:00 | G12: Seccionador SBB-5371 fase T indisponible por problemas mecanicos, el seccionador permanece cerrado y bloqueado | H12: 0 | I12: P | J12: E/S | K12: N | L12: OTROS | M12: 13751 | N12: T
B13: ATLANTICA TRANSMISION SUR S.A. | C13: POROMA | D13: REB-5350 | E13: 04/11/2025 00:00 | F13: 05/11/2025 00:00 | G13: Fuera de servicio po falla en el equipo. | H13: 0 | I13: P | J13: F/S | K13: N | L13: OTROS | M13: 13771 | N13: T
B14: ATN S.A. | C14: KIMAN AYLLU | D14: AUT-501 | E14: 04/11/2025 00:00 | F14: 05/11/2025 00:00 | G14: Restriccion Operativa en el circuito de control de cambiador de tap s del AUT-501 | H14: 0 | I14: P | J14: E/S | K14: N | L14: OTROS | M14: 13099 | N14: T
B15: ATRIA ENERGIA S.A.C. | C15: PURMACANA | D15: CENTRAL | E15: 04/11/2025 00:00 | F15: 05/11/2025 00:00 | G15: MANTENIMIENTO DE CANAL DE CONDUCCION, COMPUERTAS, SISTEMA DE LUBRICACION DE COJINETES, SISTEMA DE REFRIGERACION Y VALVULAS | H15: 0.4 | I15: P | J15: F/S | K15: N | L15: PREV. | M15: 13132 | N15: G
B16: CONELSUR LT SAC | C16: CALLAHUANCA (CNS) | D16: S.E. | E16: 04/11/2025 00:00 | F16: 05/11/2025 00:00 | G16: RELE DIFERENCIAL DE BARRAS DE CALLAHUANCA 220KV INOPERATIVO | H16: 0 | I16: F | J16: E/S | K16: N | L16: OTROS | M16: 316 | N16: T
B17: CONELSUR LT SAC | C17: YANANGO - PACHACHACA | D17: L-2256 | E17: 04/11/2025 07:07 | F17: 04/11/2025 15:48 | G17: CAMBIO DE PARARRAYOS | H17: 0 | I17: P | J17: F/S | K17: N | L17: PREV. | M17: 1074 | N17: T
B18: CONENHUA | C18: CHILOTA | D18: CL-2331 | E18: 04/11/2025 00:00 | F18: 05/11/2025 00:00 | G18: Energizacion Bahia CL-1331 en 220KV Subestacion Chilota de propiedad de CONENHUA | H18: 0 | I18: P | J18: E/S | K18: N | L18: P.ENERG | M18: 26710 | N18: T
... B152: TRANSMANTARO | C152: YARABAMBA | D152: CL-R-30 | E152: 04/11/2025 00:00 | F152: 05/11/2025 00:00 | G152: CL-R30 CON MANDO SINCRONIZADO ASOCIADO AL INTERRUPTOR IN-5147 INDISPONIBLE. EL SABADO 19.04.25 NO PUDO SER AJUSTADO DEBIDO A FALTA DE EQUIPOS DE PARTE DE LA CONTRATISTA HITACHI. | H152: 0 | I152: P | J152: E/S | K152: N | L152: OTROS | M152: 17424 | N152: T

Sheet INGRESO OC
A3: martes, 4 de Noviembre del 2025
A5: INGRESO A OPERACIÓN COMERCIAL
A6: EMPRESA | B6: TIPO DE EQUIPO | C6: UBICACIÓN | D6: EQUIPO | E6: Fecha y hora de Ingreso a Operación Comercial

Sheet DESPACHO_EJECUTADO
B3: martes, 4 de Noviembre del 2025
A5: POTENCIA ACTIVA EJECUTADA DE LAS UNIDADES DE GENERACIÓN DEL SEIN (MW) | FM5: CENTRALES NO INTEGRANTES COES
A6: FECHA | B6: HORA | C6: 65333 | D6: 101 | E6: 102 | F6: 42667 | G6: 42668 | H6: 126 | I6: 127 | J6: 138 | K6: 139 | L6: 197 | M6: 203 | N6: 204 | O6: 230 | P6: 209 | Q6: 56677 | R6: 796 | S6: 2146 | T6: 142 | U6: 143 | V6: 125 | W6: 187 | X6: 163 | Y6: 298 | Z6: 299 | AA6: 219 | AB6: 151 | AC6: 152 | AD6: 153 | AE6: 154 | AF6: 756 | AG6: 156 | AH6: 155 | AI6: 182 | AJ6: 212 | AK6: 758 | AL6: 263 | AM6: 265 | AN6: 775 | AO6: 777 | AP6: 2154 | AQ6: 150 | AR6: 149 | AS6: 188 | AT6: 2131 | AU6: 755 | AV6: 252 | AW6: 249 | AX6: 250 | AY6: 117 | AZ6: 267 | BA6: 268 | BB6: 119 | BC6: 120 | BD6: 189 | BE6: 122 | BF6: 266 | BG6: 337 | BH6: 338 | BI6: 251 | BJ6: 115 | BK6: 239 | BL6: 288 | BM6: 240 | BN6: 241 | BO6: 242 | BP6: 191 | BQ6: 194 | BR6: 196 | BS6: 207 | BT6: 236 | BU6: 795 | BV6: 285 | BW6: 995 | BX6: 996 | BY6: 997 | BZ6: 766 | CA6: 926 | CB6: 924 | CC6: 121 | CD6: 103 | CE6: 104 | CF6: 106 | CG6: 105 | CH6: 107 | CI6: 110 | CJ6: 109 | CK6: 144 | CL6: 113 | CM6: 114 | CN6: 193 | CO6: 208 | CP6: 786 | CQ6: 787 | CR6: 788 | CS6: 789 | CT6: 248 | CU6: 2159 | CV6: 303 | CW6: 59715 | CX6: 62255 | CY6: 1263 | CZ6: 61800 | DA6: 2194 | DB6: 69125 | DC6: 216 | DD6: 198 | DE6: 70400 | DF6: 49607 | DG6: 214 | DH6: 260 | DI6: 2152 | DJ6: 2128 | DK6: 247 | DL6: 228 | DM6: 2135 | DN6: 261 | DO6: 237 | DP6: 253 | DQ6: 770 | DR6: 235 | DS6: 238 | DT6: 2184 | DU6: 61855 | DV6: 223 | DW6: 226 | DX6: 201 | DY6: 258 | DZ6: 259 | EA6: 920 | EB6: 257 | EC6: 256 | ED6: 2148 | EE6: 58288 | EF6: 58289 | EG6: 58839 | EH6: 58840 | EI6: 296 | EJ6: 297 | EK6: 211 | EL6: 2175 | EM6: 2178 | EN6: 2181 | EO6: 1262 | EP6: 63425 | EQ6: 233 | ER6: 2150 | ES6: 2165 | ET6: 2161 | EU6: 61197 | EV6: 58851 | EW6: 225 | EX6: 2201 | EY6: 2171 | EZ6: 760 | FA6: 234 | FB6: 215 | FC6: 917 | FD6: 289 | FE6: 58333 | FF6: 58336 | FG6: 213 | FH6: 232 | FI6: 2190 | FJ6: 69867 | FK6: TOTAL COES | FM6: 221 | FN6: 222 | FO6: 224 | FP6: 2187 | FQ6: 227 | FR6: 49400 | FS6: 199 | FT6: 200 | FU6: TOTAL NO COES
C7: SUR | D7: CENTRO | E7: CENTRO | F7: NORTE | G7: NORTE | H7: NORTE | I7: NORTE | J7: CENTRO | K7: CENTRO | L7: CENTRO | M7: CENTRO | N7: CENTRO | O7: CENTRO | P7: CENTRO | Q7: CENTRO | R7: CENTRO | S7: CENTRO | T7: CENTRO | U7: CENTRO | V7: CENTRO | W7: CENTRO | X7: SUR | Y7: SUR | Z7: SUR | AA7: CENTRO | AB7: SUR | AC7: SUR | AD7: SUR | AE7: SUR | AF7: SUR | AG7: SUR | AH7: SUR | AI7: SUR | AJ7: CENTRO | AK7: NORTE | AL7: NORTE | AM7: NORTE | AN7: CENTRO | AO7: CENTRO | AP7: CENTRO | AQ7: CENTRO | AR7: CENTRO | AS7: CENTRO | AT7: CENTRO | AU7: SUR | AV7: CENTRO | AW7: CENTRO | AX7: CENTRO | AY7: CENTRO | AZ7: CENTRO | BA7: CENTRO | BB7: CENTRO | BC7: CENTRO | BD7: SUR | BE7: NORTE | BF7: CENTRO | BG7: CENTRO | BH7: CENTRO | BI7: CENTRO | BJ7: NORTE | BK7: NORTE | BL7: NORTE | BM7: SUR | BN7: SUR | BO7: SUR | BP7: CENTRO | BQ7: CENTRO | BR7: CENTRO | BS7: CENTRO | BT7: CENTRO | BU7: CENTRO | BV7: CENTRO | BW7: SUR | BX7: SUR | BY7: SUR | BZ7: NORTE | CA7: SUR | CB7: CENTRO | CC7: NORTE | CD7: CENTRO | CE7: CENTRO | CF7: CENTRO | CG7: CENTRO | CH7: CENTRO | CI7: CENTRO | CJ7: CENTRO | CK7: CENTRO | CL7: CENTRO | CM7: CENTRO | CN7: CENTRO | CO7: CENTRO | CP7: SUR | CQ7: SUR | CR7: SUR | CS7: SUR | CT7: CENTRO | CU7: CENTRO | CV7: CENTRO | CW7: CENTRO | CX7: SUR | CY7: NORTE | CZ7: NORTE | DA7: NORTE | DB7: CENTRO | DC7: NORTE | DD7: NORTE | DE7: SUR | DF7: SUR | DG7: CENTRO | DH7: CENTRO | DI7: CENTRO | DJ7: NORTE | DK7: NORTE | DL7: CENTRO | DM7: CENTRO | DN7: SUR | DO7: SUR | DP7: CENTRO | DQ7: CENTRO | DR7: SUR | DS7: CENTRO | DT7: CENTRO | DU7: NORTE | DV7: CENTRO | DW7: CENTRO | DX7: NORTE | DY7: CENTRO | DZ7: CENTRO | EA7: CENTRO | EB7: NORTE | EC7: NORTE | ED7: SUR | EE7: CENTRO | EF7: CENTRO | EG7: CENTRO | EH7: CENTRO | EI7: CENTRO | EJ7: CENTRO | EK7: SUR | EL7: SUR | EM7: SUR | EN7: SUR | EO7: NORTE | EP7: SUR | EQ7: SUR | ER7: SUR | ES7: CENTRO | ET7: CENTRO | EU7: CENTRO | EV7: SUR | EW7: CENTRO | EX7: CENTRO | EY7: CENTRO | EZ7: CENTRO | FA7: SUR | FB7: NORTE | FC7: CENTRO | FD7: NORTE | FE7: NORTE | FF7: NORTE | FG7: CENTRO | FH7: NORTE | FI7: NORTE | FJ7: NORTE | FM7: NORTE | FN7: CENTRO | FO7: NORTE | FP7: NORTE | FQ7: NORTE | FR7: NORTE | FS7: NORTE | FT7: NORTE
C8: HIDROELÉCTRICA | D8: HIDROELÉCTRICA | E8: HIDROELÉCTRICA | F8: TERMOELÉCTRICA | G8: TERMOELÉCTRICA | H8: HIDROELÉCTRICA | I8: HIDROELÉCTRICA | J8: TERMOELÉCTRICA | K8: TERMOELÉCTRICA | L8: TERMOELÉCTRICA | M8: TERMOELÉCTRICA | N8: TERMOELÉCTRICA | O8: TERMOELÉCTRICA | P8: TERMOELÉCTRICA | Q8: TERMOELÉCTRICA | R8: HIDROELÉCTRICA | S8: HIDROELÉCTRICA | T8: TERMOELÉCTRICA | U8: TERMOELÉCTRICA | V8: TERMOELÉCTRICA | W8: TERMOELÉCTRICA | X8: HIDROELÉCTRICA | Y8: HIDROELÉCTRICA | Z8: HIDROELÉCTRICA | AA8: TERMOELÉCTRICA | AB8: HIDROELÉCTRICA | AC8: HIDROELÉCTRICA | AD8: HIDROELÉCTRICA | AE8: HIDROELÉCTRICA | AF8: TERMOELÉCTRICA | AG8: TERMOELÉCTRICA | AH8: TERMOELÉCTRICA | AI8: HIDROELÉCTRICA | AJ8: HIDROELÉCTRICA | AK8: TERMOELÉCTRICA | AL8: TERMOELÉCTRICA | AM8: TERMOELÉCTRICA | AN8: HIDROELÉCTRICA | AO8: HIDROELÉCTRICA | AP8: HIDROELÉCTRICA | AQ8: HIDROELÉCTRICA | AR8: HIDROELÉCTRICA | AS8: HIDROELÉCTRICA | AT8: HIDROELÉCTRICA | AU8: HIDROELÉCTRICA | AV8: TERMOELÉCTRICA | AW8: TERMOELÉCTRICA | AX8: TERMOELÉCTRICA | AY8: HIDROELÉCTRICA | AZ8: HIDROELÉCTRICA | BA8: HIDROELÉCTRICA | BB8: HIDROELÉCTRICA | BC8: HIDROELÉCTRICA | BD8: HIDROELÉCTRICA | BE8: HIDROELÉCTRICA | BF8: HIDROELÉCTRICA | BG8: HIDROELÉCTRICA | BH8: HIDROELÉCTRICA | BI8: HIDROELÉCTRICA | BJ8: TERMOELÉCTRICA | BK8: TERMOELÉCTRICA | BL8: TERMOELÉCTRICA | BM8: TERMOELÉCTRICA | BN8: TERMOELÉCTRICA | BO8: TERMOELÉCTRICA | BP8: HIDROELÉCTRICA | BQ8: TERMOELÉCTRICA | BR8: TERMOELÉCTRICA | BS8: TERMOELÉCTRICA | BT8: TERMOELÉCTRICA | BU8: TERMOELÉCTRICA | BV8: TERMOELÉCTRICA | BW8: TERMOELÉCTRICA | BX8: TERMOELÉCTRICA | BY8: TERMOELÉCTRICA | BZ8: HIDROELÉCTRICA | CA8: TERMOELÉCTRICA | CB8: TERMOELÉCTRICA | CC8: HIDROELÉCTRICA | CD8: HIDROELÉCTRICA | CE8: HIDROELÉCTRICA | CF8: HIDROELÉCTRICA | CG8: HIDROELÉCTRICA | CH8: HIDROELÉCTRICA | CI8: TERMOELÉCTRICA | CJ8: TERMOELÉCTRICA | CK8: TERMOELÉCTRICA | CL8: TERMOELÉCTRICA | CM8: TERMOELÉCTRICA | CN8: TERMOELÉCTRICA | CO8: TERMOELÉCTRICA | CP8: TERMOELÉCTRICA | CQ8: TERMOELÉCTRICA | CR8: TERMOELÉCTRICA | CS8: TERMOELÉCTRICA | CT8: TERMOELÉCTRICA | CU8: TERMOELÉCTRICA | CV8: SOLAR | CW8: EÓLICA | CX8: SOLAR | CY8: EÓLICA | CZ8: SOLAR | DA8: HIDROELÉCTRICA | DB8: HIDROELÉCTRICA | DC8: HIDROELÉCTRICA | DD8: HIDROELÉCTRICA | DE8: SOLAR | DF8: HIDROELÉCTRICA | DG8: HIDROELÉCTRICA | DH8: HIDROELÉCTRICA | DI8: HIDROELÉCTRICA | DJ8: HIDROELÉCTRICA | DK8: HIDROELÉCTRICA | DL8: HIDROELÉCTRICA | DM8: HIDROELÉCTRICA | DN8: SOLAR | DO8: SOLAR | DP8: EÓLICA | DQ8: EÓLICA | DR8: SOLAR | DS8: HIDROELÉCTRICA | DT8: HIDROELÉCTRICA | DU8: HIDROELÉCTRICA | DV8: HIDROELÉCTRICA | DW8: HIDROELÉCTRICA | DX8: HIDROELÉCTRICA | DY8: HIDROELÉCTRICA | DZ8: HIDROELÉCTRICA | EA8: HIDROELÉCTRICA | EB8: EÓLICA | EC8: EÓLICA | ED8: SOLAR | EE8: EÓLICA | EF8: EÓLICA | EG8: EÓLICA | EH8: EÓLICA | EI8: HIDROELÉCTRICA | EJ8: HIDROELÉCTRICA | EK8: HIDROELÉCTRICA | EL8: HIDROELÉCTRICA | EM8: HIDROELÉCTRICA | EN8: HIDROELÉCTRICA | EO8: EÓLICA | EP8: SOLAR | EQ8: SOLAR | ER8: SOLAR | ES8: HIDROELÉCTRICA | ET8: EÓLICA | EU8: EÓLICA | EV8: SOLAR | EW8: TERMOELÉCTRICA | EX8: TERMOELÉCTRICA | EY8: TERMOELÉCTRICA | EZ8: TERMOELÉCTRICA | FA8: SOLAR | FB8: HIDROELÉCTRICA | FC8: HIDROELÉCTRICA | FD8: TERMOELÉCTRICA | FE8: TERMOELÉCTRICA | FF8: TERMOELÉCTRICA | FG8: TERMOELÉCTRICA | FH8: TERMOELÉCTRICA | FI8: TERMOELÉCTRICA | FJ8: TERMOELÉCTRICA | FM8: HIDROELÉCTRICA | FN8: HIDROELÉCTRICA | FO8: HIDROELÉCTRICA | FP8: HIDROELÉCTRICA | FQ8: TERMOELÉCTRICA | FR8: TERMOELÉCTRICA | FS8: HIDROELÉCTRICA | FT8: HIDROELÉCTRICA
C9: HYDRO GLOBAL PERÚ S.A.C. | D9: ELECTROPERU | E9: ELECTROPERU | F9: ELECTROPERU | G9: ELECTROPERU | H9: ORAZUL ENERGY PERÚ | I9: ORAZUL ENERGY PERÚ | J9: TERMOSELVA | K9: TERMOSELVA | L9: KALLPA GENERACION S.A. | M9: KALLPA GENERACION S.A. | N9: KALLPA GENERACION S.A. | O9: KALLPA GENERACION S.A. | P9: KALLPA GENERACION S.A. | Q9: KALLPA GENERACION S.A. | R9: KALLPA GENERACION S.A. | S9: KALLPA GENERACION S.A. | T9: SHOUGESA | U9: SHOUGESA | V9: SHOUGESA | W9: SHOUGESA | X9: EGEMSA | Y9: EGESUR | Z9: EGESUR | AA9: EGESUR | AB9: EGASA | AC9: EGASA | AD9: EGASA | AE9: EGASA | AF9: EGASA | AG9: EGASA | AH9: EGASA | AI9: SAN GABAN | AJ9: CELEPSA | AK9: MINERA CERRO VERDE | AL9: PLANTA DE RESERVA FRIA DE GENERACION DE ETEN S.A. | AM9: PLANTA DE RESERVA FRIA DE GENERACION DE ETEN S.A. | AN9: EMPRESA DE GENERACION HUALLAGA | AO9: EMPRESA DE GENERACION HUALLAGA | AP9: LA VIRGEN | AQ9: CHINANGO S.A.C. | AR9: CHINANGO S.A.C. | AS9: HIDROELECTRICA HUANCHOR S.A.C. | AT9: CELEPSA RENOVABLES S.R.L. | AU9: INLAND ENERGY SAC | AV9: FENIX POWER PERÚ | AW9: FENIX POWER PERÚ | AX9: FENIX POWER PERÚ | AY9: STATKRAFT S.A | AZ9: STATKRAFT S.A | BA9: STATKRAFT S.A | BB9: STATKRAFT S.A | BC9: STATKRAFT S.A | BD9: STATKRAFT S.A | BE9: STATKRAFT S.A | BF9: STATKRAFT S.A | BG9: CENTRALES SANTA ROSA S.A.C. | BH9: CENTRALES SANTA ROSA S.A.C. | BI9: EMPRESA DE GENERACION HUANZA | BJ9: ENEL GENERACION PIURA S.A. | BK9: ENEL GENERACION PIURA S.A. | BL9: ENEL GENERACION PIURA S.A. | BM9: ENGIE ENERGIA PERU S.A.A. | BN9: ENGIE ENERGIA PERU S.A.A. | BO9: ENGIE ENERGIA PERU S.A.A. | BP9: ENGIE ENERGIA PERU S.A.A. | BQ9: ENGIE ENERGIA PERU S.A.A. | BR9: ENGIE ENERGIA PERU S.A.A. | BS9: ENGIE ENERGIA PERU S.A.A. | BT9: ENGIE ENERGIA PERU S.A.A. | BU9: ENGIE ENERGIA PERU S.A.A. | BV9: ENGIE ENERGIA PERU S.A.A. | BW9: ENGIE ENERGIA PERU S.A.A. | BX9: ENGIE ENERGIA PERU S.A.A. | BY9: ENGIE ENERGIA PERU S.A.A. | BZ9: ENGIE ENERGIA PERU S.A.A. | CA9: INFRAESTRUCTURAS Y ENERGIAS DEL PERU S.A.C. | CB9: INFRAESTRUCTURAS Y ENERGIAS DEL PERU S.A.C. | CC9: INVERSIONES SHAQSHA S.A.C. | CD9: ORYGEN PERU S.A.A. | CE9: ORYGEN PERU S.A.A. | CF9: ORYGEN PERU S.A.A. | CG9: ORYGEN PERU S.A.A. | CH9: ORYGEN PERU S.A.A. | CI9: ORYGEN PERU S.A.A. | CJ9: ORYGEN PERU S.A.A. | CK9: ORYGEN PERU S.A.A. | CL9: ORYGEN PERU S.A.A. | CM9: ORYGEN PERU S.A.A. | CN9: ORYGEN PERU S.A.A. | CO9: ORYGEN PERU S.A.A. | CP9: SAMAY I S.A.C | CQ9: SAMAY I S.A.C | CR9: SAMAY I S.A.C | CS9: SAMAY I S.A.C | CT9: TERMOCHILCA S.A.C. | CU9: TERMOCHILCA S.A.C. | CV9: COLCA SOLAR S.A.C. | CW9: ENERGIA RENOVABLE DEL SUR S.A. | CX9: GR CORTARRAMA SOCIEDAD ANONIMA CERRADA | CY9: GR TARUCA SOCIEDAD ANONIMA CERRADA | CZ9: KONDU SAC | DA9: PERUANA DE INVERSIONES EN ENERGIAS RENOVABLES S.A. | DB9: VARI ENERGIA S.A.C. | DC9: ORAZUL ENERGY PERÚ | DD9: ORAZUL ENERGY PERÚ | DE9: KALLPA GENERACION S.A. | DF9: SAN GABAN | DG9: MAJA ENERGIA S.A.C. | DH9: EMPRESA DE GENERACION ELECTRICA CANCHAYLLO SAC | DI9: EMPRESA DE GENERACION ELECTRICA SANTA ANA S.A.C. | DJ9: EMPRESA ELECTRICA AGUA AZUL | DK9: EMPRESA ELECTRICA RIO DOBLE | DL9: HIDROCAÑETE S.A. | DM9: HUAURA POWER GROUP S.A. | DN9: MOQUEGUA FV S.A.C. | DO9: PANAMERICANA SOLAR SAC. | DP9: PARQUE EOLICO MARCONA S.A.C. | DQ9: PARQUE EOLICO TRES HERMANAS S.A.C. | DR9: TACNA SOLAR SAC. | DS9: ELECTRICA YANAPAMPA SAC | DT9: ANDEAN POWER S.A.C. | DU9: ASOCIACIÓN SANTA LUCIA DE CHACAS | DV9: ATRIA ENERGIA S.A.C. | DW9: EGEJUNIN | DX9: EGEJUNIN | DY9: EGEJUNIN | DZ9: EGEJUNIN | EA9: EMPRESA DE GENERACION ELECTRICA RIO BAÑOS S.A.C. | EB9: ENERGÍA EÓLICA S.A. | EC9: ENERGÍA EÓLICA S.A. | ED9: ENGIE ENERGIA PERU S.A.A. | EE9: ENGIE ENERGIA PERU S.A.A. | EF9: ENGIE ENERGIA PERU S.A.A. | EG9: ENGIE ENERGIA PERU S.A.A. | EH9: ENGIE ENERGIA PERU S.A.A. | EI9: GENERACIÓN ANDINA S.A.C. | EJ9: GENERACIÓN ANDINA S.A.C. | EK9: GENERADORA DE ENERGÍA DEL PERÚ | EL9: GENERADORA DE ENERGÍA DEL PERÚ | EM9: GENERADORA DE ENERGÍA DEL PERÚ | EN9: GENERADORA DE ENERGÍA DEL PERÚ | EO9: GR PAINO SOCIEDAD ANONIMA CERRADA | EP9: JOYA SOLAR S.A.C. | EQ9: MAJES ARCUS S.A.C. | ER9: ORYGEN PERU S.A.A. | ES9: ORYGEN PERU S.A.A. | ET9: ORYGEN PERU S.A.A. | EU9: ORYGEN PERU S.A.A. | EV9: ORYGEN PERU S.A.A. | EW9: PETRAMAS | EX9: PETRAMAS | EY9: PETRAMAS | EZ9: PETRAMAS | FA9: REPARTICIÓN ARCUS S.A.C. | FB9: SINERSA | FC9: SINERSA | FD9: BIOENERGIA DEL CHIRA S.A. | FE9: GM OPERACIONES S.A.C. | FF9: GM OPERACIONES S.A.C. | FG9: AGRO INDUSTRIAL PARAMONGA S.A. | FH9: AGROAURORA S.A.C. | FI9: AGROINDUSTRIAS SAN JACINTO S.A.A. | FJ9: AGROLMOS SOCIEDAD ANONIMA - AGROLMOS S.A. | FM9: UNACEM PERU S.A. | FN9: ELECTRO ORIENTE | FO9: AGUAS Y ENERGIA PERU | FP9: ELECTRO ZAÑA S.A.C. | FQ9: ELECTRONOROESTE S.A. | FR9: SDE PIURA | FS9: SINERSA | FT9: SINERSA
C10: SAN GABAN III | D10: MANTARO | E10: RESTITUCION | F10: TUMBES MAK 1 | G10: TUMBES MAK 2 | H10: CARHUAQUERO | I10: CAÑON DEL PATO | J10: AGUAYTIA TG1 | K10: AGUAYTIA TG2 | L10: KALLPA TG1 | M10: KALLPA TG2 | N10: KALLPA TG3 | O10: KALLPA TV | P10: LFLORES TG1 | Q10: LFLORES TV | R10: CERRO DEL AGUILA | S10: CERRODELAGUILAG4 | T10: SHOUGESA TV1 | U10: SHOUGESA TV2 | V10: SHOUGESA TV3 | W10: SHOUGESA CUMMINS | X10: MACHUPICCHU | Y10: ARICOTA 1 | Z10: ARICOTA 2 | AA10: INDEPENDENCIA | AB10: CHARCANI I,II,III | AC10: CHARCANI IV | AD10: CHARCANI V | AE10: CHARCANI VI | AF10: CHILINA TG | AG10: MOLLENDO 1, 2, 3 | AH10: CHILINA (SULZ 1,2) | AI10: SAN GABAN II | AJ10: PLATANAL | AK10: RECKA | AL10: RF ETEN TG1 | AM10: RF ETEN TG2 | AN10: CHAGLLA GP1 | AO10: CHAGLLA | AP10: LA VIRGEN | AQ10: CHIMAY | AR10: YANANGO | AS10: HUANCHOR | AT10: MARAÑON | AU10: STA TERESA | AV10: FENIX GT11 | AW10: FENIX GT12 | AX10: FENIX TV10 | AY10: YAUPI | AZ10: OROYA | BA10: PACHACHACA | BB10: MALPASO | BC10: CAHUA | BD10: ARCATA | BE10: GALLITO CIEGO | BF10: CHEVES | BG10: SANTA ROSA 1 | BH10: SANTA ROSA 2 | BI10: HUANZA | BJ10: MALACAS2 TG4 | BK10: MALACAS3 TG 5 | BL10: MALACAS1 TG6 | BM10: RF ILO2 TG1 | BN10: RF ILO2 TG2 | BO10: RF ILO2 TG3 | BP10: YUNCAN | BQ10: CHILCA1 TG1 | BR10: CHILCA1 TG2 | BS10: CHILCA1 TG3 | BT10: CHILCA-TV | BU10: CHILCA2 TG41 | BV10: CHILCA2-TV | BW10: CTNEPI_TG41 | BX10: CTNEPI_TG42 | BY10: CTNEPI_TG43 | BZ10: QUITARACSA | CA10: RF PTO MALDONADO | CB10: RF PUCALLPA | CC10: PARIAC | CD10: HUINCO | CE10: MATUCANA | CF10: MOYOPAMPA | CG10: CALLAHUANCA | CH10: HUAMPANI | CI10: STA ROSA WEST TG7 | CJ10: UTI_5 | CK10: UTI_6 | CL10: VENTANILLA 3 | CM10: VENTANILLA 4 | CN10: VENTANILLA TV | CO10: STAROSA TG8 | CP10: PTO_BRVO TG1 | CQ10: PTO_BRVO TG2 | CR10: PTO_BRVO TG3 | CS10: PTO_BRVO TG4 | CT10: OLLEROS TG1 | CU10: OLLEROS TV | CV10: CS YARUCAYA | CW10: SAN JUAN | CX10: MATARANI | CY10: DUNA | CZ10: CARHUAQUERO (CS) | DA10: MANTA I | DB10: ANASHIRONI | DC10: CARHUAQUERO4 | DD10: CAÑA BRAVA | DE10: SUNNY | DF10: TUPURI | DG10: RONCADOR | DH10: CANCHAYLLO | DI10: RENOVANDESH1 | DJ10: POTRERO | DK10: PIZARRAS | DL10: NIMPERIAL | DM10: YARUCAYA | DN10: MOQUEGUA-SOLAR | DO10: PANAMERICANA-SOLAR | DP10: PQE-EOLICO-MARCONA | DQ10: PQE-EOLICO-3-HERMANAS | DR10: TACNA-SOLAR | DS10: YANAPAMPA | DT10: CARHUAC | DU10: HUALLIN | DV10: PURMACANA | DW10: HUASAHUASI | DX10: STACRUZ_1_2 | DY10: RUNATULLO_II | DZ10: RUNATULLO_III | EA10: RUCUY | EB10: PQE-EOLICO-TALARA | EC10: PQE-EOLICO-CUPISNIQUE | ED10: INTIPAMPA | EE10: PUNTA LOMITAS-BL1 | EF10: PUNTA LOMITAS-BL2 | EG10: PUN LOMITAS_EXP-BL1 | EH10: PUN LOMITAS_EXP-BL2 | EI10: 8AGOSTO | EJ10: EL CARMEN | EK10: LA JOYA | EL10: ANGEL_I | EM10: ANGEL_II | EN10: ANGEL_III | EO10: HUAMBOS | EP10: SAN MARTIN SOLAR | EQ10: MAJES | ER10: RUBI | ES10: CH_HER1 | ET10: WAYRA-I | EU10: WAYRA EXTENSION | EV10: CLEMESI | EW10: HUAYCOLORO | EX10: CALLAO | EY10: DONA_CATALINA | EZ10: LAGRINGAV | FA10: REPARTICION | FB10: POECHOS2 | FC10: CHANCAY | FD10: CANA BRAVA | FE10: REFINERIA TALARA TV1 | FF10: REFINERÍA TALARA TV2 | FG10: PARAMONGA | FH10: MAPLE | FI10: SAN_JACINTO | FJ10: AGROLMOS | FK10: MW | FM10: CARPAPATA | FN10: CENTRALES ELOR | FO10: PIAS1 | FP10: ZANA | FQ10: TABLAZO | FR10: TALLANCA | FS10: CURUMUY | FT10: POECHOS1 | FU10: MW
A11: 04/11/2025 | B11: 00:30 | C11: 203.5 | D11: 628.9 | E11: 215.5 | H11: 89.7 | I11: 187.5 | L11: 155.2 | M11: 155.6 | N11: 155.6 | O11: 251.3 | P11: 212.6 | R11: 359.4 | S11: 10.4 | X11: 147.7 | Y11: 7.5 | Z11: 5.8 | AA11: 5.6 | AB11: 6.9 | AC11: 13.6 | AD11: 84.1 | AI11: 110.7 | AJ11: 58.5 | AN11: 6.5 | AO11: 0 | AP11: 59.6 | AQ11: 151.5 | AR11: 31.1 | AS11: 17.2 | AT11: 18.8 | AU11: 79 | AY11: 108.3 | AZ11: 7.5 | BA11: 6.3 | BB11: 34.6 | BC11: 41.2 | BD11: 2 | BE11: 11.9 | BF11: 66.5 | BI11: 46.7 | BL11: 48.3 | BP11: 83.9 | BQ11: 175.6 | BR11: 173.4 | BS11: 200 | BT11: 270.8 | CA11: 0 | CC11: 3.6 | CD11: 160.2 | CE11: 85.5 | CF11: 63 | CG11: 47.8 | CH11: 30.1 | CL11: 0 | CM11: 0 | CN11: 0 | CS11: 0 | CT11: 215.9 | CU11: 103.5 | CV11: 0 | CW11: 78.3 | CX11: 0 | CY11: 0 | CZ11: 0 | DA11: 20 | DB11: 20.7 | DD11: 4.7 | DF11: 1 | DG11: 2.5 | DH11: 2.8 | DJ11: 20 | DK11: 18.9 | DL11: 3.4 | DM11: 18.6 | DN11: 0 | DO11: 0 | DP11: 28.9 | DQ11: 76.8 | DR11: 0 | DS11: 3.1 | DT11: 10.5 | DU11: 2.4 | DW11: 13.7 | DX11: 6.8 | DY11: 9.8 | DZ11: 13.9 | EA11: 16.6 | EB11: 21.4 | EC11: 44.5 | ED11: 0 | EE11: 76.5 | EF11: 75.1 | EG11: 7.1 | EH11: 7.8 | EI11: 20.7 | EJ11: 7.7 | EK11: 7.4 | EL11: 18.4 | EM11: 19.8 | EN11: 19.7 | EO11: 0 | EQ11: 0 | ER11: 0 | ES11: 0.6 | ET11: 56.7 | EU11: 59.4 | EV11: 0 | EW11: 1.1 | EY11: 1.8 | EZ11: 1 | FA11: 0 | FB11: 6.4 | FC11: 18.9 | FD11: 9 | FE11: 28.4 | FF11: 35.2 | FG11: 14.9 | FH11: 15.9 | FI11: 0 | FJ11: 11 | FK11: 6375.7 | FM11: 21.3 | FN11: 7.95 | FO11: 0 | FP11: 13.2 | FQ11: 0 | FR11: 18.9 | FS11: 4.9 | FT11: 5.3 | FU11: 71.55
A12: 04/11/2025 | B12: 01:00 | C12: 203.8 | D12: 630.5 | E12: 215.8 | H12: 90.1 | I12: 186.6 | L12: 163.5 | M12: 163.1 | N12: 163.5 | O12: 254.4 | P12: 108.8 | R12: 359.8 | S12: 10.4 | X12: 139.7 | Y12: 7.5 | Z12: 5.9 | AA12: 5.6 | AB12: 6.9 | AC12: 13.6 | AD12: 84.5 | AI12: 110.6 | AJ12: 59.4 | AN12: 6.5 | AO12: 0 | AP12: 59.2 | AQ12: 151.6 | AR12: 31.6 | AS12: 17.4 | AT12: 18.8 | AU12: 71.7 | AY12: 108.3 | AZ12: 7.5 | BA12: 6.3 | BB12: 35.4 | BC12: 41.1 | BD12: 2 | BE12: 11.8 | BF12: 66 | BI12: 46.8 | BL12: 48.5 | BP12: 84 | BQ12: 175.4 | BR12: 173 | BS12: 200 | BT12: 272 | CA12: 0 | CC12: 3.6 | CD12: 98.4 | CE12: 84.8 | CF12: 63 | CG12: 47.4 | CH12: 30.1 | CL12: 0 | CM12: 0 | CN12: 0 | CS12: 0 | CT12: 215.9 | CU12: 103.3 | CV12: 0 | CW12: 75.6 | CX12: 0 | CY12: 0 | CZ12: 0 | DA12: 20 | DB12: 20.7 | DD12: 0 | DF12: 1 | DG12: 2.5 | DH12: 3 | DJ12: 20 | DK12: 18.9 | DL12: 3.4 | DM12: 18.6 | DN12: 0 | DO12: 0 | DP12: 28 | DQ12: 77.4 | DR12: 0 | DS12: 3.1 | DT12: 10.9 | DU12: 2.4 | DW12: 13.7 | DX12: 6.8 | DY12: 10.3 | DZ12: 14 | EA12: 18.9 | EB12: 26.8 | EC12: 55 | ED12: 0 | EE12: 73.8 | EF12: 77.8 | EG12: 6.7 | EH12: 8.7 | EI12: 20.7 | EJ12: 7.7 | EK12: 7.1 | EL12: 19.7 | EM12: 19.8 | EN12: 19.7 | EO12: 0 | EQ12: 0 | ER12: 0 | ES12: 0.6 | ET12: 69.7 | EU12: 73.9 | EV12: 0 | EW12: 1.1 | EY12: 1.8 | EZ12: 1 | FA12: 0 | FB12: 6.4 | FC12: 19.7 | FD12: 8.6 | FE12: 27.8 | FF12: 35.1 | FG12: 15 | FH12: 19.2 | FI12: 0 | FJ12: 11 | FK12: 6269 | FM12: 21.6 | FN12: 7.92 | FO12: 0 | FP12: 13.2 | FQ12: 0 | FR12: 18.9 | FS12: 4.8 | FT12: 5.2 | FU12: 71.62
A13: 04/11/2025 | B13: 01:30 | C13: 205 | D13: 630.3 | E13: 215.8 | H13: 89.9 | I13: 187.5 | L13: 176.6 | M13: 177.3 | N13: 176.1 | O13: 261.7 | P13: 25.4 | R13: 360.9 | S13: 10.4 | X13: 147.3 | Y13: 7.7 | Z13: 6 | AA13: 5.6 | AB13: 6.9 | AC13: 13.6 | AD13: 50.5 | AI13: 110.8 | AJ13: 59.2 | AN13: 6.5 | AO13: 0 | AP13: 59 | AQ13: 151.8 | AR13: 31.2 | AS13: 17.4 | AT13: 18.8 | AU13: 82.2 | AY13: 109.2 | AZ13: 7.5 | BA13: 6.3 | BB13: 35.2 | BC13: 41.3 | BD13: 2 | BE13: 12.1 | BF13: 66.9 | BI13: 46.9 | BL13: 48.5 | BP13: 84.1 | BQ13: 175.9 | BR13: 173.6 | BS13: 200 | BT13: 270.7 | CA13: 0 | CC13: 3.6 | CD13: 111.1 | CE13: 87.3 | CF13: 63.1 | CG13: 47.6 | CH13: 30.1 | CL13: 0 | CM13: 0 | CN13: 0 | CS13: 0 | CT13: 215.7 | CU13: 103.4 | CV13: 0 | CW13: 74.7 | CX13: 0 | CY13: 0 | CZ13: 0 | DA13: 20 | DB13: 20.7 | DD13: 0 | DF13: 1 | DG13: 2.5 | DH13: 2.9 | DJ13: 20 | DK13: 18.9 | DL13: 3.4 | DM13: 18.6 | DN13: 0 | DO13: 0 | DP13: 28.7 | DQ13: 76.6 | DR13: 0 | DS13: 3 | DT13: 11 | DU13: 2.3 | DW13: 12.8 | DX13: 6.8 | DY13: 10.5 | DZ13: 14.1 | EA13: 17.3 | EB13: 27.2 | EC13: 44.5 | ED13: 0 | EE13: 73.8 | EF13: 77 | EG13: 7.6 | EH13: 7.6 | EI13: 20.6 | EJ13: 7.7 | EK13: 7.3 | EL13: 19.7 | EM13: 20.4 | EN13: 19.7 | EO13: 0 | EQ13: 0 | ER13: 0 | ES13: 0.6 | ET13: 73 | EU13: 80.5 | EV13: 0 | EW13: 1.1 | EY13: 1.8 | EZ13: 1 | FA13: 0 | FB13: 6.4 | FC13: 19.2 | FD13: 8.8 | FE13: 28.1 | FF13: 35.1 | FG13: 15 | FH13: 19.3 | FI13: 0 | FJ13: 11 | FK13: 6233.3 | FM13: 21.8 | FN13: 7.94 | FO13: 0 | FP13: 13.2 | FQ13: 0 | FR13: 18.9 | FS13: 5 | FT13: 5.3 | FU13: 72.14
A14: 04/11/2025 | B14: 02:00 | C14: 204 | D14: 631.5 | E14: 215.3 | H14: 90.1 | I14: 191.5 | L14: 168 | M14: 167 | N14: 166.9 | O14: 250.9 | P14: 0 | R14: 366.5 | S14: 10.4 | X14: 150.1 | Y14: 7.5 | Z14: 6 | AA14: 5.7 | AB14: 6.9 | AC14: 13.6 | AD14: 50.7 | AI14: 110.8 | AJ14: 58.7 | AN14: 6.5 | AO14: 0 | AP14: 59 | AQ14: 151.7 | AR14: 29.9 | AS14: 17.2 | AT14: 18.8 | AU14: 80.9 | AY14: 108.5 | AZ14: 7.5 | BA14: 6.2 | BB14: 35.3 | BC14: 43.1 | BD14: 2 | BE14: 11.8 | BF14: 66.6 | BI14: 46.9 | BL14: 48.5 | BP14: 84.1 | BQ14: 175.9 | BR14: 173.8 | BS14: 200 | BT14: 271.2 | CA14: 0 | CC14: 3.6 | CD14: 97.3 | CE14: 88 | CF14: 63.1 | CG14: 47.5 | CH14: 30.1 | CL14: 0 | CM14: 0 | CN14: 0 | CS14: 0 | CT14: 216 | CU14: 103.4 | CV14: 0 | CW14: 78.8 | CX14: 0 | CY14: 0 | CZ14: 0 | DA14: 20 | DB14: 20.7 | DD14: 0 | DF14: 1 | DG14: 2.3 | DH14: 3 | DJ14: 20 | DK14: 19 | DL14: 3.4 | DM14: 18.6 | DN14: 0 | DO14: 0 | DP14: 26.5 | DQ14: 76.7 | DR14: 0 | DS14: 3 | DT14: 10.8 | DU14: 2.3 | DW14: 12.8 | DX14: 6.8 | DY14: 10.5 | DZ14: 14.1 | EA14: 16 | EB14: 27.6 | EC14: 35.3 | ED14: 0 | EE14: 74 | EF14: 76.6 | EG14: 8.6 | EH14: 8.1 | EI14: 20.3 | EJ14: 7.7 | EK14: 7.5 | EL14: 19.7 | EM14: 20.4 | EN14: 19.7 | EO14: 0 | EQ14: 0 | ER14: 0 | ES14: 0.6 | ET14: 65.9 | EU14: 81.7 | EV14: 0 | EW14: 1.1 | EY14: 1.8 | EZ14: 1 | FA14: 0 | FB14: 6.4 | FC14: 18.7 | FD14: 8.8 | FE14: 28.4 | FF14: 35.1 | FG14: 15 | FH14: 19.3 | FI14: 0 | FJ14: 10.1 | FK14: 6152.2 | FM14: 22 | FN14: 7.94 | FO14: 0 | FP14: 13.2 | FQ14: 0 | FR14: 18.9 | FS14: 5 | FT14: 5.3 | FU14: 72.34
A15: 04/11/2025 | B15: 02:30 | C15: 203.1 | D15: 625.5 | E15: 215.3 | H15: 90.5 | I15: 194.7 | L15: 145.2 | M15: 145.4 | N15: 144.9 | O15: 255.3 | P15: 0 | R15: 352.9 | S15: 10.4 | X15: 149.1 | Y15: 7.3 | Z15: 5.8 | AA15: 5.6 | AB15: 6.9 | AC15: 13.6 | AD15: 49.8 | AI15: 110.8 | AJ15: 58.5 | AN15: 6.4 | AO15: 0 | AP15: 59 | AQ15: 151.3 | AR15: 32.7 | AS15: 17.2 | AT15: 18.8 | AU15: 77.3 | AY15: 107.9 | AZ15: 7.5 | BA15: 6.2 | BB15: 15.5 | BC15: 42.9 | BD15: 2 | BE15: 12.1 | BF15: 65.1 | BI15: 46.8 | BL15: 48.7 | BP15: 83.9 | BQ15: 175.8 | BR15: 173.8 | BS15: 200 | BT15: 271.8 | CA15: 0 | CC15: 3.6 | CD15: 99.5 | CE15: 82.4 | CF15: 63.8 | CG15: 47.4 | CH15: 30 | CL15: 0 | CM15: 0 | CN15: 0 | CS15: 0 | CT15: 216.2 | CU15: 103.5 | CV15: 0 | CW15: 82.1 | CX15: 0 | CY15: 0 | CZ15: 0 | DA15: 20 | DB15: 20.7 | DD15: 0 | DF15: 1 | DG15: 2.2 | DH15: 3 | DJ15: 20 | DK15: 18.9 | DL15: 3.4 | DM15: 18.6 | DN15: 0 | DO15: 0 | DP15: 28.3 | DQ15: 76 | DR15: 0 | DS15: 3.2 | DT15: 10.9 | DU15: 2.3 | DW15: 12 | DX15: 6.8 | DY15: 10.2 | DZ15: 13.8 | EA15: 15.8 | EB15: 27.3 | EC15: 26.6 | ED15: 0 | EE15: 71.6 | EF15: 79 | EG15: 6.6 | EH15: 8.9 | EI15: 20.5 | EJ15: 7.7 | EK15: 7.4 | EL15: 19.7 | EM15: 20.4 | EN15: 20 | EO15: 0 | EQ15: 0 | ER15: 0 | ES15: 0.6 | ET15: 50.9 | EU15: 58.2 | EV15: 0 | EW15: 1.1 | EY15: 1.8 | EZ15: 1 | FA15: 0 | FB15: 6.4 | FC15: 18.7 | FD15: 8.8 | FE15: 27.7 | FF15: 34.6 | FG15: 15.3 | FH15: 18.9 | FI15: 0 | FJ15: 11.1 | FK15: 5999.7 | FM15: 22.1 | FN15: 7.94 | FO15: 0 | FP15: 13.2 | FQ15: 0 | FR15: 18.9 | FS15: 4.9 | FT15: 5.3 | FU15: 72.34
A16: 04/11/2025 | B16: 03:00 | C16: 201.9 | D16: 627.9 | E16: 215.3 | H16: 89 | I16: 195.1 | L16: 145.7 | M16: 145.8 | N16: 145.4 | O16: 247 | P16: 0 | R16: 360.4 | S16: 10.4 | X16: 145.7 | Y16: 7.1 | Z16: 5.7 | AA16: 5.7 | AB16: 6.9 | AC16: 13.9 | AD16: 49.7 | AI16: 110.5 | AJ16: 59 | AN16: 6.5 | AO16: 0 | AP16: 59 | AQ16: 150.9 | AR16: 31.4 | AS16: 17.2 | AT16: 18.8 | AU16: 80.1 | AY16: 108.2 | AZ16: 7.5 | BA16: 6.2 | BB16: 31.4 | BC16: 42.7 | BD16: 2 | BE16: 11.8 | BF16: 64.2 | BI16: 46.6 | BL16: 48.6 | BP16: 83.7 | BQ16: 177.1 | BR16: 174.7 | BS16: 200 | BT16: 271.9 | CA16: 0 | CC16: 3.6 | CD16: 116.7 | CE16: 79.4 | CF16: 63.7 | CG16: 47.4 | CH16: 29.7 | CL16: 30.2 | CM16: 0 | CN16: 0 | CS16: 0 | CT16: 216.2 | CU16: 103.7 | CV16: 0 | CW16: 79.8 | CX16: 0 | CY16: 0 | CZ16: 0 | DA16: 20 | DB16: 20.6 | DD16: 0 | DF16: 1 | DG16: 2.3 | DH16: 3 | DJ16: 20 | DK16: 19 | DL16: 3.4 | DM16: 18.6 | DN16: 0 | DO16: 0 | DP16: 27.1 | DQ16: 74.7 | DR16: 0 | DS16: 3.2 | DT16: 10.9 | DU16: 2.2 | DW16: 12 | DX16: 6.8 | DY16: 10.1 | DZ16: 13.9 | EA16: 16 | EB16: 26.9 | EC16: 24 | ED16: 0 | EE16: 75.5 | EF16: 75.9 | EG16: 6.9 | EH16: 8.6 | EI16: 20.6 | EJ16: 7.6 | EK16: 7.5 | EL16: 20.4 | EM16: 20.4 | EN16: 20 | EO16: 0 | EQ16: 0 | ER16: 0 | ES16: 0.6 | ET16: 56.5 | EU16: 77.7 | EV16: 0 | EW16: 1.1 | EY16: 1.8 | EZ16: 1 | FA16: 0 | FB16: 6.4 | FC16: 18.8 | FD16: 8.8 | FE16: 27.2 | FF16: 34.1 | FG16: 16 | FH16: 19.4 | FI16: 0 | FJ16: 11.1 | FK16: 6078.6 | FM16: 22.3 | FN16: 7.94 | FO16: 0 | FP16: 13.2 | FQ16: 0 | FR16: 18.9 | FS16: 5 | FT16: 5.2 | FU16: 72.54
A17: 04/11/2025 | B17: 03:30 | C17: 201.2 | D17: 626 | E17: 215.3 | H17: 88.2 | I17: 195.2 | L17: 148 | M17: 147.8 | N17: 147.6 | O17: 255.7 | P17: 0 | R17: 259.1 | S17: 10.3 | X17: 139.9 | Y17: 7.1 | Z17: 5.6 | AA17: 5.6 | AB17: 6.9 | AC17: 13.8 | AD17: 48.9 | AI17: 110.3 | AJ17: 58.3 | AN17: 6.4 | AO17: 0 | AP17: 58.5 | AQ17: 150.6 | AR17: 30.5 | AS17: 17.2 | AT17: 18.8 | AU17: 78.5 | AY17: 107.9 | AZ17: 7.5 | BA17: 6.2 | BB17: 24 | BC17: 43.4 | BD17: 2 | BE17: 11.8 | BF17: 65.9 | BI17: 46.6 | BL17: 48.4 | BP17: 83.4 | BQ17: 177.5 | BR17: 175.3 | BS17: 200 | BT17: 271.8 | CA17: 0 | CC17: 3.6 | CD17: 83.2 | CE17: 93 | CF17: 63.4 | CG17: 47.5 | CH17: 29.7 | CL17: 30.7 | CM17: 0 | CN17: 0 | CS17: 0 | CT17: 216.2 | CU17: 103.8 | CV17: 0 | CW17: 90.1 | CX17: 0 | CY17: 0 | CZ17: 0 | DA17: 20.1 | DB17: 20.7 | DD17: 0 | DF17: 1 | DG17: 2.4 | DH17: 3 | DJ17: 20 | DK17: 18.9 | DL17: 3.4 | DM17: 18.6 | DN17: 0 | DO17: 0 | DP17: 27.5 | DQ17: 76.4 | DR17: 0 | DS17: 3.2 | DT17: 10.9 | DU17: 2.2 | DW17: 12.1 | DX17: 6.8 | DY17: 10.3 | DZ17: 13.7 | EA17: 16 | EB17: 28 | EC17: 28 | ED17: 0 | EE17: 72.7 | EF17: 75.6 | EG17: 8.5 | EH17: 9.7 | EI17: 20.6 | EJ17: 7.6 | EK17: 7.5 | EL17: 20.4 | EM17: 20.4 | EN17: 20 | EO17: 0 | EQ17: 0 | ER17: 0 | ES17: 0.6 | ET17: 64 | EU17: 71.9 | EV17: 0 | EW17: 1.1 | EY17: 1.8 | EZ17: 1 | FA17: 0 | FB17: 6.4 | FC17: 18.8 | FD17: 8 | FE17: 28.8 | FF17: 35.7 | FG17: 16 | FH17: 19.4 | FI17: 0 | FJ17: 11.1 | FK17: 5975 | FM17: 22.2 | FN17: 7.95 | FO17: 0 | FP17: 13.2 | FQ17: 0 | FR17: 18.9 | FS17: 5 | FT17: 5.3 | FU17: 72.55
A18: 04/11/2025 | B18: 04:00 | C18: 204.8 | D18: 630.5 | E18: 216.7 | H18: 89.9 | I18: 195.6 | L18: 176.9 | M18: 177.3 | N18: 176.5 | O18: 258.2 | P18: 0 | R18: 273.7 | S18: 10.4 | X18: 148.2 | Y18: 7.6 | Z18: 5.9 | AA18: 5.6 | AB18: 6.9 | AC18: 13.8 | AD18: 50.5 | AI18: 110.8 | AJ18: 59.2 | AN18: 6.4 | AO18: 0 | AP18: 57.4 | AQ18: 151.3 | AR18: 29.8 | AS18: 17.2 | AT18: 18.8 | AU18: 80.8 | AY18: 109.2 | AZ18: 7.5 | BA18: 6.3 | BB18: 35 | BC18: 44.1 | BD18: 2 | BE18: 11.9 | BF18: 68.8 | BI18: 46.9 | BL18: 48.3 | BP18: 84.1 | BQ18: 176.3 | BR18: 174 | BS18: 200 | BT18: 269.9 | CA18: 0 | CC18: 3.6 | CD18: 94.4 | CE18: 91.6 | CF18: 64.1 | CG18: 47.4 | CH18: 30.1 | CL18: 30 | CM18: 0 | CN18: 0 | CS18: 0 | CT18: 216.5 | CU18: 103.8 | CV18: 0 | CW18: 85.3 | CX18: 0 | CY18: 0 | CZ18: 0 | DA18: 20 | DB18: 20.7 | DD18: 0 | DF18: 1 | DG18: 2.5 | DH18: 2.8 | DJ18: 20 | DK18: 19.1 | DL18: 3.4 | DM18: 18.6 | DN18: 0 | DO18: 0 | DP18: 30 | DQ18: 78.4 | DR18: 0 | DS18: 3.3 | DT18: 11 | DU18: 2.2 | DW18: 12.1 | DX18: 6.8 | DY18: 10.8 | DZ18: 14 | EA18: 16 | EB18: 28.4 | EC18: 26.8 | ED18: 0 | EE18: 71.2 | EF18: 82.5 | EG18: 6.6 | EH18: 6 | EI18: 20.3 | EJ18: 7.6 | EK18: 7.2 | EL18: 20.4 | EM18: 20.4 | EN18: 20 | EO18: 0 | EQ18: 0 | ER18: 0 | ES18: 0.6 | ET18: 58.2 | EU18: 58.5 | EV18: 0 | EW18: 1.1 | EY18: 1.8 | EZ18: 1 | FA18: 0 | FB18: 6.4 | FC18: 18.8 | FD18: 8.1 | FE18: 27.9 | FF18: 34.7 | FG18: 15.6 | FH18: 19.4 | FI18: 0 | FJ18: 11 | FK18: 6105 | FM18: 22.3 | FN18: 7.95 | FO18: 0 | FP18: 13.2 | FQ18: 0 | FR18: 18.9 | FS18: 5 | FT18: 5.3 | FU18: 72.65
A19: 04/11/2025 | B19: 04:30 | C19: 204.2 | D19: 594.9 | E19: 201 | H19: 89.9 | I19: 195.4 | L19: 147.1 | M19: 147.3 | N19: 147.1 | O19: 247 | P19: 0 | R19: 264.5 | S19: 10.5 | X19: 152.7 | Y19: 7.4 | Z19: 6 | AA19: 5.6 | AB19: 6.9 | AC19: 13.8 | AD19: 50.1 | AI19: 110.6 | AJ19: 58.4 | AN19: 6.5 | AO19: 0 | AP19: 57.6 | AQ19: 151 | AR19: 30.2 | AS19: 17.2 | AT19: 18.8 | AU19: 81.1 | AY19: 108.3 | AZ19: 7.5 | BA19: 6.1 | BB19: 24.5 | BC19: 43.8 | BD19: 2 | BE19: 11.7 | BF19: 68.2 | BI19: 66.6 | BL19: 48.2 | BP19: 83.9 | BQ19: 176.3 | BR19: 174 | BS19: 200 | BT19: 271.8 | CA19: 0 | CC19: 3.6 | CD19: 85.6 | CE19: 96.1 | CF19: 63.9 | CG19: 47.8 | CH19: 29.9 | CL19: 89.7 | CM19: 0 | CN19: 12.1 | CS19: 0 | CT19: 216.2 | CU19: 103.7 | CV19: 0 | CW19: 90.1 | CX19: 0 | CY19: 0 | CZ19: 0 | DA19: 20 | DB19: 20.6 | DD19: 0 | DF19: 1 | DG19: 2.3 | DH19: 2.8 | DJ19: 20 | DK19: 19.1 | DL19: 3.4 | DM19: 18.6 | DN19: 0 | DO19: 0 | DP19: 29.1 | DQ19: 75.7 | DR19: 0 | DS19: 3.3 | DT19: 14 | DU19: 2.2 | DW19: 12.2 | DX19: 6.8 | DY19: 11.1 | DZ19: 13.9 | EA19: 15.8 | EB19: 27.7 | EC19: 26.3 | ED19: 0 | EE19: 67.7 | EF19: 89.7 | EG19: 5.1 | EH19: 3.8 | EI19: 20.2 | EJ19: 7.6 | EK19: 6.8 | EL19: 20.4 | EM19: 20.4 | EN19: 20 | EO19: 0 | EQ19: 0 | ER19: 0 | ES19: 0.6 | ET19: 47.1 | EU19: 51 | EV19: 0 | EW19: 0.9 | EY19: 1.8 | EZ19: 1 | FA19: 0 | FB19: 6.4 | FC19: 18.7 | FD19: 7.3 | FE19: 28.1 | FF19: 35.1 | FG19: 15.8 | FH19: 18.5 | FI19: 0 | FJ19: 11.1 | FK19: 6005.4 | FM19: 22.3 | FN19: 7.94 | FO19: 0 | FP19: 13.2 | FQ19: 0 | FR19: 18.9 | FS19: 5 | FT19: 5.2 | FU19: 72.54
A20: 04/11/2025 | B20: 05:00 | C20: 203.8 | D20: 596.8 | E20: 204.7 | H20: 90.1 | I20: 195.1 | L20: 177.5 | M20: 176.9 | N20: 178.3 | O20: 266 | P20: 0 | R20: 266.4 | S20: 10.4 | X20: 154.2 | Y20: 7.6 | Z20: 6 | AA20: 5.7 | AB20: 7 | AC20: 13.8 | AD20: 50.3 | AI20: 110.9 | AJ20: 58.9 | AN20: 6.5 | AO20: 0 | AP20: 56.8 | AQ20: 141.5 | AR20: 29.6 | AS20: 17.4 | AT20: 18.8 | AU20: 83.6 | AY20: 108.7 | AZ20: 7.5 | BA20: 6.1 | BB20: 33.7 | BC20: 44.2 | BD20: 2 | BE20: 12 | BF20: 69.8 | BI20: 43 | BL20: 48.5 | BP20: 84 | BQ20: 176.7 | BR20: 174.4 | BS20: 200 | BT20: 272 | CA20: 0 | CC20: 3.6 | CD20: 110 | CE20: 78.8 | CF20: 64 | CG20: 47.7 | CH20: 30.1 | CL20: 116.9 | CM20: 0 | CN20: 54.2 | CS20: 0 | CT20: 216.5 | CU20: 103.9 | CV20: 0 | CW20: 88.3 | CX20: 0 | CY20: 0 | CZ20: 0 | DA20: 20 | DB20: 20.7 | DD20: 0 | DF20: 1 | DG20: 2.4 | DH20: 2.7 | DJ20: 20 | DK20: 19.1 | DL20: 3.4 | DM20: 18.6 | DN20: 0.1 | DO20: 0 | DP20: 27.5 | DQ20: 68.3 | DR20: 0 | DS20: 3.4 | DT20: 12.1 | DU20: 2.2 | DW20: 12.4 | DX20: 6.8 | DY20: 11.9 | DZ20: 14.1 | EA20: 15.8 | EB20: 26.8 | EC20: 28.9 | ED20: 0 | EE20: 73.7 | EF20: 82.3 | EG20: 4.8 | EH20: 6 | EI20: 20 | EJ20: 7.6 | EK20: 7.2 | EL20: 20.4 | EM20: 20.4 | EN20: 20 | EO20: 0 | EQ20: 0 | ER20: 0 | ES20: 0.6 | ET20: 50.6 | EU20: 58.8 | EV20: 0 | EW20: 0.7 | EY20: 1 | EZ20: 0.7 | FA20: 0 | FB20: 6.4 | FC20: 18.7 | FD20: 7.5 | FE20: 28.3 | FF20: 35.3 | FG20: 16 | FH20: 18 | FI20: 0 | FJ20: 11.1 | FK20: 6185.5 | FM20: 22.3 | FN20: 7.94 | FO20: 0 | FP20: 13.2 | FQ20: 0 | FR20: 18.9 | FS20: 4.9 | FT20: 5.3 | FU20: 72.54
A21: 04/11/2025 | B21: 05:30 | C21: 203.5 | D21: 599.5 | E21: 210.4 | H21: 90 | I21: 195.4 | L21: 173.6 | M21: 174.3 | N21: 174.1 | O21: 259.9 | P21: 0 | R21: 358.6 | S21: 10.4 | X21: 154.7 | Y21: 7.4 | Z21: 5.9 | AA21: 5.6 | AB21: 6.9 | AC21: 12.6 | AD21: 50.7 | AI21: 110.8 | AJ21: 59.4 | AN21: 6.5 | AO21: 0 | AP21: 57 | AQ21: 141 | AR21: 29.4 | AS21: 17.4 | AT21: 18.8 | AU21: 84.7 | AY21: 108.3 | AZ21: 7.5 | BA21: 6.2 | BB21: 32.3 | BC21: 45.1 | BD21: 2 | BE21: 11.9 | BF21: 69.1 | BI21: 42.5 | BL21: 48.5 | BP21: 84 | BQ21: 176.6 | BR21: 174.4 | BS21: 200 | BT21: 271.6 | CA21: 0 | CC21: 3.6 | CD21: 104.2 | CE21: 83.9 | CF21: 63.9 | CG21: 47.5 | CH21: 29.9 | CL21: 116.9 | CM21: 30 | CN21: 57.7 | CS21: 0 | CT21: 216.2 | CU21: 103.6 | CV21: 0 | CW21: 92.8 | CX21: 3.5 | CY21: 0 | CZ21: 0 | DA21: 20 | DB21: 20.7 | DD21: 0 | DF21: 1 | DG21: 2.4 | DH21: 2.8 | DJ21: 20 | DK21: 18.9 | DL21: 3.4 | DM21: 18.6 | DN21: 0.5 | DO21: 0.9 | DP21: 29.1 | DQ21: 59.3 | DR21: 0.1 | DS21: 3.3 | DT21: 10.1 | DU21: 2.2 | DW21: 12.4 | DX21: 6.8 | DY21: 12 | DZ21: 14 | EA21: 15.8 | EB21: 24.8 | EC21: 33.2 | ED21: 1 | EE21: 76.3 | EF21: 74 | EG21: 5.7 | EH21: 6.4 | EI21: 19.7 | EJ21: 7.5 | EK21: 7.3 | EL21: 20.4 | EM21: 20.4 | EN21: 20 | EO21: 0 | EQ21: 0 | ER21: 5.8 | ES21: 0.6 | ET21: 42.6 | EU21: 49.7 | EV21: 5 | EW21: 0.7 | EY21: 1 | EZ21: 0.7 | FA21: 0 | FB21: 6.4 | FC21: 18.7 | FD21: 8.1 | FE21: 28.3 | FF21: 35.3 | FG21: 16 | FH21: 19.1 | FI21: 0 | FJ21: 11 | FK21: 6292.2 | FM21: 22.3 | FN21: 7.95 | FO21: 0 | FP21: 13.2 | FQ21: 0 | FR21: 18.9 | FS21: 4.9 | FT21: 5.2 | FU21: 72.45
A22: 04/11/2025 | B22: 06:00 | C22: 206.4 | D22: 631.4 | E22: 216.5 | H22: 91.5 | I22: 205.2 | L22: 142 | M22: 141.6 | N22: 141.9 | O22: 237.4 | P22: 0 | R22: 263.9 | S22: 10.5 | X22: 167 | Y22: 7.9 | Z22: 5.8 | AA22: 5.6 | AB22: 6.9 | AC22: 12.5 | AD22: 50.1 | AI22: 110.8 | AJ22: 51.4 | AN22: 6.4 | AO22: 0 | AP22: 56.9 | AQ22: 143.1 | AR22: 33.8 | AS22: 17.2 | AT22: 18.8 | AU22: 88.3 | AY22: 109.1 | AZ22: 7.5 | BA22: 6 | BB22: 24.3 | BC22: 45.1 | BD22: 2 | BE22: 12.3 | BF22: 72.6 | BI22: 44 | BL22: 48.4 | BP22: 84.8 | BQ22: 175.5 | BR22: 173.2 | BS22: 200 | BT22: 271.8 | CA22: 0 | CC22: 3.6 | CD22: 85.5 | CE22: 81.6 | CF22: 64.9 | CG22: 47.4 | CH22: 30.4 | CL22: 116.4 | CM22: 29.4 | CN22: 57.2 | CS22: 0 | CT22: 216.4 | CU22: 103.8 | CV22: 0 | CW22: 97.1 | CX22: 26.4 | CY22: 0 | CZ22: 0 | DA22: 20 | DB22: 20.9 | DD22: 0 | DF22: 1.1 | DG22: 2.4 | DH22: 3 | DJ22: 20 | DK22: 18.9 | DL22: 3.4 | DM22: 18.6 | DN22: 1.2 | DO22: 1.3 | DP22: 28.8 | DQ22: 75.3 | DR22: 0.8 | DS22: 3.3 | DT22: 9.9 | DU22: 2.1 | DW22: 12.4 | DX22: 6.8 | DY22: 11.8 | DZ22: 14.2 | EA22: 15.5 | EB22: 25.8 | EC22: 24.6 | ED22: 6.2 | EE22: 58.4 | EF22: 69.3 | EG22: 5.5 | EH22: 4.6 | EI22: 19.7 | EJ22: 7.5 | EK22: 7.3 | EL22: 20.4 | EM22: 20.4 | EN22: 20 | EO22: 0 | EQ22: 1 | ER22: 42.1 | ES22: 0.6 | ET22: 41.1 | EU22: 50.6 | EV22: 35.4 | EW22: 0.7 | EY22: 1 | EZ22: 0.7 | FA22: 1 | FB22: 6.4 | FC22: 18.4 | FD22: 8.2 | FE22: 28.2 | FF22: 35.2 | FG22: 16.1 | FH22: 19.4 | FI22: 0 | FJ22: 11 | FK22: 6206 | FM22: 22.3 | FN22: 7.95 | FO22: 0 | FP22: 13.2 | FQ22: 0 | FR22: 18.3 | FS22: 4.8 | FT22: 5.2 | FU22: 71.75
... A58: 05/11/2025 | B58: 00:00 | C58: 200.7 | D58: 615.5 | E58: 212.1 | H58: 90.2 | I58: 191 | L58: 108.3 | M58: 108.7 | N58: 108.7 | O58: 214.5 | P58: 0 | R58: 337.4 | S58: 5.9 | X58: 147.9 | Y58: 6.9 | Z58: 6 | AA58: 5.6 | AB58: 6.9 | AC58: 14.4 | AD58: 88.4 | AI58: 109.9 | AJ58: 50.6 | AN58: 6.4 | AO58: 146.1 | AP58: 52.1 | AQ58: 149.6 | AR58: 27.7 | AS58: 18.4 | AT58: 18.8 | AU58: 79.1 | AY58: 106.6 | AZ58: 7.4 | BA58: 6 | BB58: 33.5 | BC58: 42.6 | BD58: 2 | BE58: 11.7 | BF58: 64.1 | BI58: 76.7 | BL58: 0 | BP58: 83.6 | BQ58: 175.3 | BR58: 173.1 | BS58: 200 | BT58: 271.8 | CA58: 0 | CC58: 3.9 | CD58: 122.2 | CE58: 67.6 | CF58: 63.1 | CG58: 47.1 | CH58: 29.6 | CL58: 145.3 | CM58: 146.9 | CN58: 148.1 | CS58: 0 | CT58: 216.4 | CU58: 103.6 | CV58: 0 | CW58: 90.8 | CX58: 0 | CY58: 0 | CZ58: 0 | DA58: 17.4 | DB58: 20.5 | DD58: 0 | DF58: 1 | DG58: 3.3 | DH58: 2.8 | DJ58: 20 | DK58: 18.9 | DL58: 3.5 | DM58: 18.6 | DN58: 0 | DO58: 0 | DP58: 30.2 | DQ58: 84.4 | DR58: 0 | DS58: 3.2 | DT58: 18.9 | DU58: 2.7 | DW58: 10.9 | DX58: 9.2 | DY58: 10.1 | DZ58: 14.6 | EA58: 15.7 | EB58: 12.9 | EC58: 68.2 | ED58: 0 | EE58: 47.8 | EF58: 90.1 | EG58: 4 | EH58: 2.5 | EI58: 20.9 | EJ58: 7.6 | EK58: 7.6 | EL58: 18.9 | EM58: 19.8 | EN58: 19.8 | EO58: 0 | EQ58: 0 | ER58: 0 | ES58: 0.6 | ET58: 8.7 | EU58: 7 | EV58: 0 | EW58: 1.1 | EY58: 1.8 | EZ58: 1 | FA58: 0 | FB58: 6 | FC58: 18.6 | FD58: 8.6 | FE58: 26.93 | FF58: 33.39 | FG58: 15 | FH58: 0 | FI58: 7 | FJ58: 11 | FK58: 6339.52 | FM58: 11.4 | FN58: 7.96 | FO58: 5.2 | FP58: 13.2 | FQ58: 27 | FR58: 18.9 | FS58: 4.2 | FT58: 5.3 | FU58: 93.16
A59: EJEC | C59: 4879.05 | D59: 14980.1 | E59: 5131.35 | F59: 0 | G59: 0 | H59: 2161.5 | I59: 4588.85 | J59: 0 | K59: 0 | L59: 3636.15 | M59: 3634.65 | N59: 3632.35 | O59: 5904 | P59: 173.4 | Q59: 0 | R59: 7358.5 | S59: 170.8 | T59: 0 | U59: 0 | V59: 0 | W59: 0 | X59: 3689.8 | Y59: 178.55 | Z59: 140.75 | AA59: 134.8 | AB59: 165.7 | AC59: 271.55 | AD59: 1917.15 | AE59: 0 | AF59: 0 | AG59: 0 | AH59: 0 | AI59: 2653.55 | AJ59: 2741.65 | AK59: 0 | AL59: 0 | AM59: 0 | AN59: 155.65 | AO59: 4484.55 | AP59: 1199.85 | AQ59: 3360.35 | AR59: 694.2 | AS59: 404.4 | AT59: 451.2 | AU59: 2005.55 | AV59: 0 | AW59: 0 | AX59: 0 | AY59: 2594 | AZ59: 179.85 | BA59: 145.9 | BB59: 698.8 | BC59: 1047.55 | BD59: 48 | BE59: 424.55 | BF59: 1668.7 | BG59: 0 | BH59: 0 | BI59: 1579.75 | BJ59: 0 | BK59: 0 | BL59: 641.6 | BM59: 0 | BN59: 0 | BO59: 0 | BP59: 2021.7 | BQ59: 4160.55 | BR59: 4109.8 | BS59: 4767.8 | BT59: 6429.85 | BU59: 0 | BV59: 0 | BW59: 0 | BX59: 0 | BY59: 0 | BZ59: 0 | CA59: 0.9 | CB59: 0 | CC59: 87.7 | CD59: 3330.6 | CE59: 1738.05 | CF59: 1537.65 | CG59: 1106.65 | CH59: 710.25 | CI59: 0 | CJ59: 0 | CK59: 0 | CL59: 2839.9 | CM59: 2575.5 | CN59: 2687.15 | CO59: 0 | CP59: 0 | CQ59: 0 | CR59: 0 | CS59: 370.8 | CT59: 5157.55 | CU59: 2466.6 | CV59: 6.75 | CW59: 2469.25 | CX59: 755 | CY59: 21.35 | CZ59: 2.9 | DA59: 478.3 | DB59: 496.65 | DC59: 0 | DD59: 2.35 | DE59: 0 | DF59: 26.75 | DG59: 70.65 | DH59: 68.7 | DI59: 0 | DJ59: 480 | DK59: 451.35 | DL59: 81.75 | DM59: 446.4 | DN59: 139.45 | DO59: 172.9 | DP59: 712.2 | DQ59: 1987.9 | DR59: 160.55 | DS59: 77.25 | DT59: 373.4 | DU59: 57.1 | DV59: 0 | DW59: 281.55 | DX59: 174.35 | DY59: 225.5 | DZ59: 355.55 | EA59: 372.15 | EB59: 389.35 | EC59: 1370.75 | ED59: 309.55 | EE59: 915.95 | EF59: 2000.05 | EG59: 77.45 | EH59: 181.45 | EI59: 492.5 | EJ59: 181.9 | EK59: 175.5 | EL59: 479.85 | EM59: 486.95 | EN59: 478.4 | EO59: 29.2 | EP59: 0 | EQ59: 130.85 | ER59: 1431.4 | ES59: 14.4 | ET59: 1974.8 | EU59: 2393.15 | EV59: 1061.8 | EW59: 23.95 | EX59: 0 | EY59: 40.45 | EZ59: 22.5 | FA59: 125.25 | FB59: 150.25 | FC59: 446.75 | FD59: 203.35 | FE59: 666.535 | FF59: 832.73 | FG59: 342.3 | FH59: 386.35 | FI59: 70.95 | FJ59: 261.35 | FK59: 165123.61 | FM59: 335.45 | FN59: 166.98 | FO59: 2.6 | FP59: 316.8 | FQ59: 399.25 | FR59: 453.3 | FS59: 102.15 | FT59: 190.55 | FU59: 1967.08

Sheet REACTIVA
B3: martes, 4 de Noviembre del 2025
A5: POTENCIA REACTIVA EJECUTADA DE LAS UNIDADES DE GENERACIÓN DEL COES (MVAR) | FM5: CENTRALES NO INTEGRANTES COES
A6: FECHA | B6: HORA | C6: 65333 | D6: 101 | E6: 102 | F6: 42667 | G6: 42668 | H6: 126 | I6: 127 | J6: 138 | K6: 139 | L6: 197 | M6: 203 | N6: 204 | O6: 230 | P6: 209 | Q6: 56677 | R6: 796 | S6: 2146 | T6: 142 | U6: 143 | V6: 125 | W6: 187 | X6: 163 | Y6: 298 | Z6: 299 | AA6: 219 | AB6: 151 | AC6: 152 | AD6: 153 | AE6: 154 | AF6: 756 | AG6: 156 | AH6: 155 | AI6: 182 | AJ6: 212 | AK6: 758 | AL6: 263 | AM6: 265 | AN6: 775 | AO6: 777 | AP6: 2154 | AQ6: 150 | AR6: 149 | AS6: 188 | AT6: 2131 | AU6: 755 | AV6: 252 | AW6: 249 | AX6: 250 | AY6: 117 | AZ6: 267 | BA6: 268 | BB6: 119 | BC6: 120 | BD6: 189 | BE6: 122 | BF6: 266 | BG6: 337 | BH6: 338 | BI6: 251 | BJ6: 115 | BK6: 239 | BL6: 288 | BM6: 240 | BN6: 241 | BO6: 242 | BP6: 191 | BQ6: 194 | BR6: 196 | BS6: 207 | BT6: 236 | BU6: 795 | BV6: 285 | BW6: 995 | BX6: 996 | BY6: 997 | BZ6: 766 | CA6: 926 | CB6: 924 | CC6: 121 | CD6: 103 | CE6: 104 | CF6: 106 | CG6: 105 | CH6: 107 | CI6: 110 | CJ6: 109 | CK6: 144 | CL6: 113 | CM6: 114 | CN6: 193 | CO6: 208 | CP6: 786 | CQ6: 787 | CR6: 788 | CS6: 789 | CT6: 248 | CU6: 2159 | CV6: 303 | CW6: 59715 | CX6: 62255 | CY6: 1263 | CZ6: 61800 | DA6: 2194 | DB6: 69125 | DC6: 216 | DD6: 198 | DE6: 70400 | DF6: 49607 | DG6: 214 | DH6: 260 | DI6: 2152 | DJ6: 2128 | DK6: 247 | DL6: 228 | DM6: 2135 | DN6: 261 | DO6: 237 | DP6: 253 | DQ6: 770 | DR6: 235 | DS6: 238 | DT6: 2184 | DU6: 61855 | DV6: 223 | DW6: 226 | DX6: 201 | DY6: 258 | DZ6: 259 | EA6: 920 | EB6: 257 | EC6: 256 | ED6: 2148 | EE6: 58288 | EF6: 58289 | EG6: 58839 | EH6: 58840 | EI6: 296 | EJ6: 297 | EK6: 211 | EL6: 2175 | EM6: 2178 | EN6: 2181 | EO6: 1262 | EP6: 63425 | EQ6: 233 | ER6: 2150 | ES6: 2165 | ET6: 2161 | EU6: 61197 | EV6: 58851 | EW6: 225 | EX6: 2201 | EY6: 2171 | EZ6: 760 | FA6: 234 | FB6: 215 | FC6: 917 | FD6: 289 | FE6: 58333 | FF6: 58336 | FG6: 213 | FH6: 232 | FI6: 2190 | FJ6: 69867 | FK6: TOTAL COES | FM6: 221 | FN6: 222 | FO6: 224 | FP6: 2187 | FQ6: 227 | FR6: 49400 | FS6: 199 | FT6: 200 | FU6: TOTAL NO COES
C7: SUR | D7: CENTRO | E7: CENTRO | F7: NORTE | G7: NORTE | H7: NORTE | I7: NORTE | J7: CENTRO | K7: CENTRO | L7: CENTRO | M7: CENTRO | N7: CENTRO | O7: CENTRO | P7: CENTRO | Q7: CENTRO | R7: CENTRO | S7: CENTRO | T7: CENTRO | U7: CENTRO | V7: CENTRO | W7: CENTRO | X7: SUR | Y7: SUR | Z7: SUR | AA7: CENTRO | AB7: SUR | AC7: SUR | AD7: SUR | AE7: SUR | AF7: SUR | AG7: SUR | AH7: SUR | AI7: SUR | AJ7: CENTRO | AK7: NORTE | AL7: NORTE | AM7: NORTE | AN7: CENTRO | AO7: CENTRO | AP7: CENTRO | AQ7: CENTRO | AR7: CENTRO | AS7: CENTRO | AT7: CENTRO | AU7: SUR | AV7: CENTRO | AW7: CENTRO | AX7: CENTRO | AY7: CENTRO | AZ7: CENTRO | BA7: CENTRO | BB7: CENTRO | BC7: CENTRO | BD7: SUR | BE7: NORTE | BF7: CENTRO | BG7: CENTRO | BH7: CENTRO | BI7: CENTRO | BJ7: NORTE | BK7: NORTE | BL7: NORTE | BM7: SUR | BN7: SUR | BO7: SUR | BP7: CENTRO | BQ7: CENTRO | BR7: CENTRO | BS7: CENTRO | BT7: CENTRO | BU7: CENTRO | BV7: CENTRO | BW7: SUR | BX7: SUR | BY7: SUR | BZ7: NORTE | CA7: SUR | CB7: CENTRO | CC7: NORTE | CD7: CENTRO | CE7: CENTRO | CF7: CENTRO | CG7: CENTRO | CH7: CENTRO | CI7: CENTRO | CJ7: CENTRO | CK7: CENTRO | CL7: CENTRO | CM7: CENTRO | CN7: CENTRO | CO7: CENTRO | CP7: SUR | CQ7: SUR | CR7: SUR | CS7: SUR | CT7: CENTRO | CU7: CENTRO | CV7: CENTRO | CW7: CENTRO | CX7: SUR | CY7: NORTE | CZ7: NORTE | DA7: NORTE | DB7: CENTRO | DC7: NORTE | DD7: NORTE | DE7: SUR | DF7: SUR | DG7: CENTRO | DH7: CENTRO | DI7: CENTRO | DJ7: NORTE | DK7: NORTE | DL7: CENTRO | DM7: CENTRO | DN7: SUR | DO7: SUR | DP7: CENTRO | DQ7: CENTRO | DR7: SUR | DS7: CENTRO | DT7: CENTRO | DU7: NORTE | DV7: CENTRO | DW7: CENTRO | DX7: NORTE | DY7: CENTRO | DZ7: CENTRO | EA7: CENTRO | EB7: NORTE | EC7: NORTE | ED7: SUR | EE7: CENTRO | EF7: CENTRO | EG7: CENTRO | EH7: CENTRO | EI7: CENTRO | EJ7: CENTRO | EK7: SUR | EL7: SUR | EM7: SUR | EN7: SUR | EO7: NORTE | EP7: SUR | EQ7: SUR | ER7: SUR | ES7: CENTRO | ET7: CENTRO | EU7: CENTRO | EV7: SUR | EW7: CENTRO | EX7: CENTRO | EY7: CENTRO | EZ7: CENTRO | FA7: SUR | FB7: NORTE | FC7: CENTRO | FD7: NORTE | FE7: NORTE | FF7: NORTE | FG7: CENTRO | FH7: NORTE | FI7: NORTE | FJ7: NORTE | FM7: NORTE | FN7: CENTRO | FO7: NORTE | FP7: NORTE | FQ7: NORTE | FR7: NORTE | FS7: NORTE | FT7: NORTE
C8: HIDROELÉCTRICA | D8: HIDROELÉCTRICA | E8: HIDROELÉCTRICA | F8: TERMOELÉCTRICA | G8: TERMOELÉCTRICA | H8: HIDROELÉCTRICA | I8: HIDROELÉCTRICA | J8: TERMOELÉCTRICA | K8: TERMOELÉCTRICA | L8: TERMOELÉCTRICA | M8: TERMOELÉCTRICA | N8: TERMOELÉCTRICA | O8: TERMOELÉCTRICA | P8: TERMOELÉCTRICA | Q8: TERMOELÉCTRICA | R8: HIDROELÉCTRICA | S8: HIDROELÉCTRICA | T8: TERMOELÉCTRICA | U8: TERMOELÉCTRICA | V8: TERMOELÉCTRICA | W8: TERMOELÉCTRICA | X8: HIDROELÉCTRICA | Y8: HIDROELÉCTRICA | Z8: HIDROELÉCTRICA | AA8: TERMOELÉCTRICA | AB8: HIDROELÉCTRICA | AC8: HIDROELÉCTRICA | AD8: HIDROELÉCTRICA | AE8: HIDROELÉCTRICA | AF8: TERMOELÉCTRICA | AG8: TERMOELÉCTRICA | AH8: TERMOELÉCTRICA | AI8: HIDROELÉCTRICA | AJ8: HIDROELÉCTRICA | AK8: TERMOELÉCTRICA | AL8: TERMOELÉCTRICA | AM8: TERMOELÉCTRICA | AN8: HIDROELÉCTRICA | AO8: HIDROELÉCTRICA | AP8: HIDROELÉCTRICA | AQ8: HIDROELÉCTRICA | AR8: HIDROELÉCTRICA | AS8: HIDROELÉCTRICA | AT8: HIDROELÉCTRICA | AU8: HIDROELÉCTRICA | AV8: TERMOELÉCTRICA | AW8: TERMOELÉCTRICA | AX8: TERMOELÉCTRICA | AY8: HIDROELÉCTRICA | AZ8: HIDROELÉCTRICA | BA8: HIDROELÉCTRICA | BB8: HIDROELÉCTRICA | BC8: HIDROELÉCTRICA | BD8: HIDROELÉCTRICA | BE8: HIDROELÉCTRICA | BF8: HIDROELÉCTRICA | BG8: HIDROELÉCTRICA | BH8: HIDROELÉCTRICA | BI8: HIDROELÉCTRICA | BJ8: TERMOELÉCTRICA | BK8: TERMOELÉCTRICA | BL8: TERMOELÉCTRICA | BM8: TERMOELÉCTRICA | BN8: TERMOELÉCTRICA | BO8: TERMOELÉCTRICA | BP8: HIDROELÉCTRICA | BQ8: TERMOELÉCTRICA | BR8: TERMOELÉCTRICA | BS8: TERMOELÉCTRICA | BT8: TERMOELÉCTRICA | BU8: TERMOELÉCTRICA | BV8: TERMOELÉCTRICA | BW8: TERMOELÉCTRICA | BX8: TERMOELÉCTRICA | BY8: TERMOELÉCTRICA | BZ8: HIDROELÉCTRICA | CA8: TERMOELÉCTRICA | CB8: TERMOELÉCTRICA | CC8: HIDROELÉCTRICA | CD8: HIDROELÉCTRICA | CE8: HIDROELÉCTRICA | CF8: HIDROELÉCTRICA | CG8: HIDROELÉCTRICA | CH8: HIDROELÉCTRICA | CI8: TERMOELÉCTRICA | CJ8: TERMOELÉCTRICA | CK8: TERMOELÉCTRICA | CL8: TERMOELÉCTRICA | CM8: TERMOELÉCTRICA | CN8: TERMOELÉCTRICA | CO8: TERMOELÉCTRICA | CP8: TERMOELÉCTRICA | CQ8: TERMOELÉCTRICA | CR8: TERMOELÉCTRICA | CS8: TERMOELÉCTRICA | CT8: TERMOELÉCTRICA | CU8: TERMOELÉCTRICA | CV8: SOLAR | CW8: EÓLICA | CX8: SOLAR | CY8: EÓLICA | CZ8: SOLAR | DA8: HIDROELÉCTRICA | DB8: HIDROELÉCTRICA | DC8: HIDROELÉCTRICA | DD8: HIDROELÉCTRICA | DE8: SOLAR | DF8: HIDROELÉCTRICA | DG8: HIDROELÉCTRICA | DH8: HIDROELÉCTRICA | DI8: HIDROELÉCTRICA | DJ8: HIDROELÉCTRICA | DK8: HIDROELÉCTRICA | DL8: HIDROELÉCTRICA | DM8: HIDROELÉCTRICA | DN8: SOLAR | DO8: SOLAR | DP8: EÓLICA | DQ8: EÓLICA | DR8: SOLAR | DS8: HIDROELÉCTRICA | DT8: HIDROELÉCTRICA | DU8: HIDROELÉCTRICA | DV8: HIDROELÉCTRICA | DW8: HIDROELÉCTRICA | DX8: HIDROELÉCTRICA | DY8: HIDROELÉCTRICA | DZ8: HIDROELÉCTRICA | EA8: HIDROELÉCTRICA | EB8: EÓLICA | EC8: EÓLICA | ED8: SOLAR | EE8: EÓLICA | EF8: EÓLICA | EG8: EÓLICA | EH8: EÓLICA | EI8: HIDROELÉCTRICA | EJ8: HIDROELÉCTRICA | EK8: HIDROELÉCTRICA | EL8: HIDROELÉCTRICA | EM8: HIDROELÉCTRICA | EN8: HIDROELÉCTRICA | EO8: EÓLICA | EP8: SOLAR | EQ8: SOLAR | ER8: SOLAR | ES8: HIDROELÉCTRICA | ET8: EÓLICA | EU8: EÓLICA | EV8: SOLAR | EW8: TERMOELÉCTRICA | EX8: TERMOELÉCTRICA | EY8: TERMOELÉCTRICA | EZ8: TERMOELÉCTRICA | FA8: SOLAR | FB8: HIDROELÉCTRICA | FC8: HIDROELÉCTRICA | FD8: TERMOELÉCTRICA | FE8: TERMOELÉCTRICA | FF8: TERMOELÉCTRICA | FG8: TERMOELÉCTRICA | FH8: TERMOELÉCTRICA | FI8: TERMOELÉCTRICA | FJ8: TERMOELÉCTRICA | FM8: HIDROELÉCTRICA | FN8: HIDROELÉCTRICA | FO8: HIDROELÉCTRICA | FP8: HIDROELÉCTRICA | FQ8: TERMOELÉCTRICA | FR8: TERMOELÉCTRICA | FS8: HIDROELÉCTRICA | FT8: HIDROELÉCTRICA
C9: HYDRO GLOBAL PERÚ S.A.C. | D9: ELECTROPERU | E9: ELECTROPERU | F9: ELECTROPERU | G9: ELECTROPERU | H9: ORAZUL ENERGY PERÚ | I9: ORAZUL ENERGY PERÚ | J9: TERMOSELVA | K9: TERMOSELVA | L9: KALLPA GENERACION S.A. | M9: KALLPA GENERACION S.A. | N9: KALLPA GENERACION S.A. | O9: KALLPA GENERACION S.A. | P9: KALLPA GENERACION S.A. | Q9: KALLPA GENERACION S.A. | R9: KALLPA GENERACION S.A. | S9: KALLPA GENERACION S.A. | T9: SHOUGESA | U9: SHOUGESA | V9: SHOUGESA | W9: SHOUGESA | X9: EGEMSA | Y9: EGESUR | Z9: EGESUR | AA9: EGESUR | AB9: EGASA | AC9: EGASA | AD9: EGASA | AE9: EGASA | AF9: EGASA | AG9: EGASA | AH9: EGASA | AI9: SAN GABAN | AJ9: CELEPSA | AK9: MINERA CERRO VERDE | AL9: PLANTA DE RESERVA FRIA DE GENERACION DE ETEN S.A. | AM9: PLANTA DE RESERVA FRIA DE GENERACION DE ETEN S.A. | AN9: EMPRESA DE GENERACION HUALLAGA | AO9: EMPRESA DE GENERACION HUALLAGA | AP9: LA VIRGEN | AQ9: CHINANGO S.A.C. | AR9: CHINANGO S.A.C. | AS9: HIDROELECTRICA HUANCHOR S.A.C. | AT9: CELEPSA RENOVABLES S.R.L. | AU9: INLAND ENERGY SAC | AV9: FENIX POWER PERÚ | AW9: FENIX POWER PERÚ | AX9: FENIX POWER PERÚ | AY9: STATKRAFT S.A | AZ9: STATKRAFT S.A | BA9: STATKRAFT S.A | BB9: STATKRAFT S.A | BC9: STATKRAFT S.A | BD9: STATKRAFT S.A | BE9: STATKRAFT S.A | BF9: STATKRAFT S.A | BG9: CENTRALES SANTA ROSA S.A.C. | BH9: CENTRALES SANTA ROSA S.A.C. | BI9: EMPRESA DE GENERACION HUANZA | BJ9: ENEL GENERACION PIURA S.A. | BK9: ENEL GENERACION PIURA S.A. | BL9: ENEL GENERACION PIURA S.A. | BM9: ENGIE ENERGIA PERU S.A.A. | BN9: ENGIE ENERGIA PERU S.A.A. | BO9: ENGIE ENERGIA PERU S.A.A. | BP9: ENGIE ENERGIA PERU S.A.A. | BQ9: ENGIE ENERGIA PERU S.A.A. | BR9: ENGIE ENERGIA PERU S.A.A. | BS9: ENGIE ENERGIA PERU S.A.A. | BT9: ENGIE ENERGIA PERU S.A.A. | BU9: ENGIE ENERGIA PERU S.A.A. | BV9: ENGIE ENERGIA PERU S.A.A. | BW9: ENGIE ENERGIA PERU S.A.A. | BX9: ENGIE ENERGIA PERU S.A.A. | BY9: ENGIE ENERGIA PERU S.A.A. | BZ9: ENGIE ENERGIA PERU S.A.A. | CA9: INFRAESTRUCTURAS Y ENERGIAS DEL PERU S.A.C. | CB9: INFRAESTRUCTURAS Y ENERGIAS DEL PERU S.A.C. | CC9: INVERSIONES SHAQSHA S.A.C. | CD9: ORYGEN PERU S.A.A. | CE9: ORYGEN PERU S.A.A. | CF9: ORYGEN PERU S.A.A. | CG9: ORYGEN PERU S.A.A. | CH9: ORYGEN PERU S.A.A. | CI9: ORYGEN PERU S.A.A. | CJ9: ORYGEN PERU S.A.A. | CK9: ORYGEN PERU S.A.A. | CL9: ORYGEN PERU S.A.A. | CM9: ORYGEN PERU S.A.A. | CN9: ORYGEN PERU S.A.A. | CO9: ORYGEN PERU S.A.A. | CP9: SAMAY I S.A.C | CQ9: SAMAY I S.A.C | CR9: SAMAY I S.A.C | CS9: SAMAY I S.A.C | CT9: TERMOCHILCA S.A.C. | CU9: TERMOCHILCA S.A.C. | CV9: COLCA SOLAR S.A.C. | CW9: ENERGIA RENOVABLE DEL SUR S.A. | CX9: GR CORTARRAMA SOCIEDAD ANONIMA CERRADA | CY9: GR TARUCA SOCIEDAD ANONIMA CERRADA | CZ9: KONDU SAC | DA9: PERUANA DE INVERSIONES EN ENERGIAS RENOVABLES S.A. | DB9: VARI ENERGIA S.A.C. | DC9: ORAZUL ENERGY PERÚ | DD9: ORAZUL ENERGY PERÚ | DE9: KALLPA GENERACION S.A. | DF9: SAN GABAN | DG9: MAJA ENERGIA S.A.C. | DH9: EMPRESA DE GENERACION ELECTRICA CANCHAYLLO SAC | DI9: EMPRESA DE GENERACION ELECTRICA SANTA ANA S.A.C. | DJ9: EMPRESA ELECTRICA AGUA AZUL | DK9: EMPRESA ELECTRICA RIO DOBLE | DL9: HIDROCAÑETE S.A. | DM9: HUAURA POWER GROUP S.A. | DN9: MOQUEGUA FV S.A.C. | DO9: PANAMERICANA SOLAR SAC. | DP9: PARQUE EOLICO MARCONA S.A.C. | DQ9: PARQUE EOLICO TRES HERMANAS S.A.C. | DR9: TACNA SOLAR SAC. | DS9: ELECTRICA YANAPAMPA SAC | DT9: ANDEAN POWER S.A.C. | DU9: ASOCIACIÓN SANTA LUCIA DE CHACAS | DV9: ATRIA ENERGIA S.A.C. | DW9: EGEJUNIN | DX9: EGEJUNIN | DY9: EGEJUNIN | DZ9: EGEJUNIN | EA9: EMPRESA DE GENERACION ELECTRICA RIO BAÑOS S.A.C. | EB9: ENERGÍA EÓLICA S.A. | EC9: ENERGÍA EÓLICA S.A. | ED9: ENGIE ENERGIA PERU S.A.A. | EE9: ENGIE ENERGIA PERU S.A.A. | EF9: ENGIE ENERGIA PERU S.A.A. | EG9: ENGIE ENERGIA PERU S.A.A. | EH9: ENGIE ENERGIA PERU S.A.A. | EI9: GENERACIÓN ANDINA S.A.C. | EJ9: GENERACIÓN ANDINA S.A.C. | EK9: GENERADORA DE ENERGÍA DEL PERÚ | EL9: GENERADORA DE ENERGÍA DEL PERÚ | EM9: GENERADORA DE ENERGÍA DEL PERÚ | EN9: GENERADORA DE ENERGÍA DEL PERÚ | EO9: GR PAINO SOCIEDAD ANONIMA CERRADA | EP9: JOYA SOLAR S.A.C. | EQ9: MAJES ARCUS S.A.C. | ER9: ORYGEN PERU S.A.A. | ES9: ORYGEN PERU S.A.A. | ET9: ORYGEN PERU S.A.A. | EU9: ORYGEN PERU S.A.A. | EV9: ORYGEN PERU S.A.A. | EW9: PETRAMAS | EX9: PETRAMAS | EY9: PETRAMAS | EZ9: PETRAMAS | FA9: REPARTICIÓN ARCUS S.A.C. | FB9: SINERSA | FC9: SINERSA | FD9: BIOENERGIA DEL CHIRA S.A. | FE9: GM OPERACIONES S.A.C. | FF9: GM OPERACIONES S.A.C. | FG9: AGRO INDUSTRIAL PARAMONGA S.A. | FH9: AGROAURORA S.A.C. | FI9: AGROINDUSTRIAS SAN JACINTO S.A.A. | FJ9: AGROLMOS SOCIEDAD ANONIMA - AGROLMOS S.A. | FM9: UNACEM PERU S.A. | FN9: ELECTRO ORIENTE | FO9: AGUAS Y ENERGIA PERU | FP9: ELECTRO ZAÑA S.A.C. | FQ9: ELECTRONOROESTE S.A. | FR9: SDE PIURA | FS9: SINERSA | FT9: SINERSA
C10: SAN GABAN III | D10: MANTARO | E10: RESTITUCION | F10: TUMBES MAK 1 | G10: TUMBES MAK 2 | H10: CARHUAQUERO | I10: CAÑON DEL PATO | J10: AGUAYTIA TG1 | K10: AGUAYTIA TG2 | L10: KALLPA TG1 | M10: KALLPA TG2 | N10: KALLPA TG3 | O10: KALLPA TV | P10: LFLORES TG1 | Q10: LFLORES TV | R10: CERRO DEL AGUILA | S10: CERRODELAGUILAG4 | T10: SHOUGESA TV1 | U10: SHOUGESA TV2 | V10: SHOUGESA TV3 | W10: SHOUGESA CUMMINS | X10: MACHUPICCHU | Y10: ARICOTA 1 | Z10: ARICOTA 2 | AA10: INDEPENDENCIA | AB10: CHARCANI I,II,III | AC10: CHARCANI IV | AD10: CHARCANI V | AE10: CHARCANI VI | AF10: CHILINA TG | AG10: MOLLENDO 1, 2, 3 | AH10: CHILINA (SULZ 1,2) | AI10: SAN GABAN II | AJ10: PLATANAL | AK10: RECKA | AL10: RF ETEN TG1 | AM10: RF ETEN TG2 | AN10: CHAGLLA GP1 | AO10: CHAGLLA | AP10: LA VIRGEN | AQ10: CHIMAY | AR10: YANANGO | AS10: HUANCHOR | AT10: MARAÑON | AU10: STA TERESA | AV10: FENIX GT11 | AW10: FENIX GT12 | AX10: FENIX TV10 | AY10: YAUPI | AZ10: OROYA | BA10: PACHACHACA | BB10: MALPASO | BC10: CAHUA | BD10: ARCATA | BE10: GALLITO CIEGO | BF10: CHEVES | BG10: SANTA ROSA 1 | BH10: SANTA ROSA 2 | BI10: HUANZA | BJ10: MALACAS2 TG4 | BK10: MALACAS3 TG 5 | BL10: MALACAS1 TG6 | BM10: RF ILO2 TG1 | BN10: RF ILO2 TG2 | BO10: RF ILO2 TG3 | BP10: YUNCAN | BQ10: CHILCA1 TG1 | BR10: CHILCA1 TG2 | BS10: CHILCA1 TG3 | BT10: CHILCA-TV | BU10: CHILCA2 TG41 | BV10: CHILCA2-TV | BW10: CTNEPI_TG41 | BX10: CTNEPI_TG42 | BY10: CTNEPI_TG43 | BZ10: QUITARACSA | CA10: RF PTO MALDONADO | CB10: RF PUCALLPA | CC10: PARIAC | CD10: HUINCO | CE10: MATUCANA | CF10: MOYOPAMPA | CG10: CALLAHUANCA | CH10: HUAMPANI | CI10: STA ROSA WEST TG7 | CJ10: UTI_5 | CK10: UTI_6 | CL10: VENTANILLA 3 | CM10: VENTANILLA 4 | CN10: VENTANILLA TV | CO10: STAROSA TG8 | CP10: PTO_BRVO TG1 | CQ10: PTO_BRVO TG2 | CR10: PTO_BRVO TG3 | CS10: PTO_BRVO TG4 | CT10: OLLEROS TG1 | CU10: OLLEROS TV | CV10: CS YARUCAYA | CW10: SAN JUAN | CX10: MATARANI | CY10: DUNA | CZ10: CARHUAQUERO (CS) | DA10: MANTA I | DB10: ANASHIRONI | DC10: CARHUAQUERO4 | DD10: CAÑA BRAVA | DE10: SUNNY | DF10: TUPURI | DG10: RONCADOR | DH10: CANCHAYLLO | DI10: RENOVANDESH1 | DJ10: POTRERO | DK10: PIZARRAS | DL10: NIMPERIAL | DM10: YARUCAYA | DN10: MOQUEGUA-SOLAR | DO10: PANAMERICANA-SOLAR | DP10: PQE-EOLICO-MARCONA | DQ10: PQE-EOLICO-3-HERMANAS | DR10: TACNA-SOLAR | DS10: YANAPAMPA | DT10: CARHUAC | DU10: HUALLIN | DV10: PURMACANA | DW10: HUASAHUASI | DX10: STACRUZ_1_2 | DY10: RUNATULLO_II | DZ10: RUNATULLO_III | EA10: RUCUY | EB10: PQE-EOLICO-TALARA | EC10: PQE-EOLICO-CUPISNIQUE | ED10: INTIPAMPA | EE10: PUNTA LOMITAS-BL1 | EF10: PUNTA LOMITAS-BL2 | EG10: PUN LOMITAS_EXP-BL1 | EH10: PUN LOMITAS_EXP-BL2 | EI10: 8AGOSTO | EJ10: EL CARMEN | EK10: LA JOYA | EL10: ANGEL_I | EM10: ANGEL_II | EN10: ANGEL_III | EO10: HUAMBOS | EP10: SAN MARTIN SOLAR | EQ10: MAJES | ER10: RUBI | ES10: CH_HER1 | ET10: WAYRA-I | EU10: WAYRA EXTENSION | EV10: CLEMESI | EW10: HUAYCOLORO | EX10: CALLAO | EY10: DONA_CATALINA | EZ10: LAGRINGAV | FA10: REPARTICION | FB10: POECHOS2 | FC10: CHANCAY | FD10: CANA BRAVA | FE10: REFINERIA TALARA TV1 | FF10: REFINERÍA TALARA TV2 | FG10: PARAMONGA | FH10: MAPLE | FI10: SAN_JACINTO | FJ10: AGROLMOS | FK10: MVAR | FM10: CARPAPATA | FN10: CENTRALES ELOR | FO10: PIAS1 | FP10: ZANA | FQ10: TABLAZO | FR10: TALLANCA | FS10: CURUMUY | FT10: POECHOS1 | FU10: MVAR
A11: 04/11/2025 | B11: 00:30 | C11: 37.9 | D11: -25.7 | E11: 6.3 | H11: -13.9 | I11: 8.1 | L11: -28 | M11: -38.3 | N11: -27.4 | O11: 30.7 | P11: -5.5 | R11: 32.5 | S11: 0.1 | X11: -4 | Y11: 1.1 | Z11: 0.7 | AA11: 0.8 | AB11: -3.4 | AC11: 3.7 | AD11: 10.1 | AI11: 8.7 | AJ11: -4 | AN11: -0.8 | AO11: 0 | AP11: 4.9 | AQ11: 13.4 | AR11: 1.1 | AS11: 0.5 | AT11: 2.6 | AU11: 0 | AY11: 6.6 | AZ11: -0.7 | BA11: -0.1 | BB11: -1 | BC11: -0.1 | BD11: 0.4 | BE11: 0.1 | BF11: -6.1 | BI11: -2.4 | BL11: 7.3 | BP11: 5 | BQ11: -30.1 | BR11: -31.6 | BT11: -11.4 | CA11: 0 | CC11: -0.3 | CD11: 26.8 | CE11: 12.2 | CF11: -0.6 | CG11: -1 | CH11: 0 | CL11: 0 | CM11: 0 | CN11: 0 | CS11: 0 | CT11: -18.1 | CU11: -14.7 | CW11: -16.2 | CX11: 0 | CY11: 0 | DA11: 1.3 | DB11: 0 | DD11: -0.2 | DG11: 0 | DH11: 0.9 | DJ11: -0.9 | DK11: 0.4 | DL11: 0.5 | DN11: 0 | DO11: 0 | DP11: 4.1 | DQ11: -5.6 | DR11: 0 | DS11: 0 | DT11: 0.3 | DU11: 0.3 | DW11: -3.4 | DX11: 0 | DY11: 0.2 | DZ11: 0.4 | EA11: 0.7 | EC11: 3.4 | ED11: 0 | EE11: 0.5 | EF11: 1.6 | EG11: 0.6 | EH11: 0.4 | EI11: 2.5 | EJ11: -0.1 | EK11: 1.6 | EL11: 0.2 | EM11: 0.2 | EN11: 0.2 | EQ11: 0 | ER11: 0 | ES11: -0.2 | ET11: -8 | EU11: 0 | EV11: 0 | EW11: 0.7 | EY11: 0.6 | EZ11: 0.6 | FA11: 0 | FB11: 0.4 | FC11: 0.8 | FD11: 2 | FE11: 12.4 | FF11: 0.4 | FG11: 3.9 | FH11: 1.1 | FI11: 0 | FJ11: 4.4 | FK11: -34.6 | FP11: 1.7 | FS11: 0.4 | FT11: 2 | FU11: 4.1
A12: 04/11/2025 | B12: 01:00 | C12: 37.5 | D12: -25.2 | E12: 5.6 | H12: -13.2 | I12: 7.1 | L12: -28.2 | M12: -41.5 | N12: -31.6 | O12: 28.6 | P12: -18.2 | R12: 29.5 | S12: 0 | X12: -1.9 | Y12: 0.9 | Z12: 0.6 | AA12: 0.8 | AB12: -3.4 | AC12: 3.5 | AD12: 9.9 | AI12: 9.2 | AJ12: -4.9 | AN12: -0.9 | AO12: 0 | AP12: 4.5 | AQ12: 14.2 | AR12: 0.8 | AS12: 0.8 | AT12: 2.6 | AU12: 0.4 | AY12: 4.9 | AZ12: -0.7 | BA12: -0.2 | BB12: -1.8 | BC12: -0.4 | BD12: 0.4 | BE12: 0.1 | BF12: -5.6 | BI12: -3.8 | BL12: 7.2 | BP12: 4.6 | BQ12: -34.2 | BR12: -35.4 | BT12: -14.2 | CA12: 0 | CC12: -0.3 | CD12: 18.9 | CE12: 12.7 | CF12: -0.1 | CG12: -1.1 | CH12: 0.1 | CL12: 0 | CM12: 0 | CN12: 0 | CS12: 0 | CT12: -23.1 | CU12: -17.6 | CW12: -16.3 | CX12: 0 | CY12: 0 | DA12: 1.3 | DB12: 0 | DD12: 0 | DG12: 0.1 | DH12: 0.7 | DJ12: -1.2 | DK12: 0.3 | DL12: 0.5 | DN12: 0 | DO12: 0 | DP12: 4 | DQ12: -6.1 | DR12: 0 | DS12: -0.1 | DT12: 0.3 | DU12: 0.2 | DW12: -3.5 | DX12: 0 | DY12: 0.3 | DZ12: 0.4 | EA12: 0.7 | EC12: 7.8 | ED12: 0 | EE12: 0.9 | EF12: 1.3 | EG12: 0.6 | EH12: 0.4 | EI12: 2.5 | EJ12: -0.1 | EK12: 1.5 | EL12: 0.2 | EM12: 0.2 | EN12: 0.2 | EQ12: 0 | ER12: 0 | ES12: -0.2 | ET12: -6.5 | EU12: 0 | EV12: 0 | EW12: 0.7 | EY12: 0.6 | EZ12: 0.6 | FA12: 0 | FB12: 0.4 | FC12: 1 | FD12: 1.9 | FE12: 11.7 | FF12: 0.3 | FG12: 4 | FH12: 0 | FI12: 0 | FJ12: 4.1 | FK12: -86.4 | FP12: 1.7 | FS12: -0.1 | FT12: 2 | FU12: 3.6
A13: 04/11/2025 | B13: 01:30 | C13: 39.8 | D13: -27.7 | E13: 5.4 | H13: -14.5 | I13: 4.7 | L13: -30.8 | M13: -42.1 | N13: -24.6 | O13: 26.7 | P13: -22.3 | R13: 31.4 | S13: 0 | X13: 0.8 | Y13: 1.2 | Z13: 0.8 | AA13: 0.7 | AB13: -3.4 | AC13: 3.5 | AD13: 9.8 | AI13: 10 | AJ13: -5.8 | AN13: -1 | AO13: 0 | AP13: 4.2 | AQ13: 8.7 | AR13: 1.3 | AS13: 0.7 | AT13: 2.6 | AU13: 1.5 | AY13: 6 | AZ13: -0.8 | BA13: -0.2 | BB13: -2.1 | BC13: -0.9 | BD13: 0.4 | BE13: 0.1 | BF13: -5 | BI13: -5 | BL13: 6.8 | BP13: 4.4 | BQ13: -35.8 | BR13: -37.2 | BT13: -18.1 | CA13: 0 | CC13: -0.4 | CD13: 20.3 | CE13: 12.3 | CF13: -0.3 | CG13: -1 | CH13: 0.2 | CL13: 0 | CM13: 0 | CN13: 0 | CS13: 0 | CT13: -25.9 | CU13: -19.2 | CW13: -16.6 | CX13: 0 | CY13: 0 | DA13: 1.3 | DB13: 0.1 | DD13: 0 | DG13: 0 | DH13: 0.7 | DJ13: -0.9 | DK13: 0.3 | DL13: 0.6 | DN13: 0 | DO13: 0 | DP13: 4 | DQ13: -5.6 | DR13: 0 | DS13: -0.1 | DT13: 0.3 | DU13: 0.2 | DW13: -3.1 | DX13: 0.1 | DY13: 0.2 | DZ13: 0.4 | EA13: 0.5 | EC13: 8.2 | ED13: 0 | EE13: 0.5 | EF13: 0.9 | EG13: 0.5 | EH13: 0.4 | EI13: 2.5 | EJ13: -0.1 | EK13: 1.6 | EL13: 0.2 | EM13: 0.2 | EN13: 0.2 | EQ13: 0 | ER13: 0 | ES13: -0.2 | ET13: -6 | EU13: 0 | EV13: 0 | EW13: 0.7 | EY13: 0.6 | EZ13: 0.6 | FA13: 0 | FB13: 0.4 | FC13: 0.8 | FD13: 1.9 | FE13: 12.1 | FF13: 0.4 | FG13: 3.1 | FH13: 0.5 | FI13: 0 | FJ13: 4 | FK13: -103.4 | FP13: 1.7 | FS13: 0.1 | FT13: 2 | FU13: 3.8
A14: 04/11/2025 | B14: 02:00 | C14: 38.4 | D14: -39.8 | E14: 3 | H14: -15.1 | I14: 3.6 | L14: -35.1 | M14: -51.5 | N14: -34 | O14: 21.1 | P14: 0 | R14: 28.3 | S14: -0.1 | X14: 1.6 | Y14: 0.6 | Z14: 0.4 | AA14: 0.9 | AB14: -3.4 | AC14: 3.2 | AD14: 9 | AI14: 9.3 | AJ14: -7 | AN14: -1 | AO14: 0 | AP14: 4 | AQ14: 9 | AR14: 1.2 | AS14: 0 | AT14: 2.6 | AU14: 1.1 | AY14: 3.9 | AZ14: -0.7 | BA14: -0.2 | BB14: -3.2 | BC14: -2 | BD14: 0.4 | BE14: 0.1 | BF14: -2.7 | BI14: -6.9 | BL14: 6.5 | BP14: 3.6 | BQ14: -41.6 | BR14: -43.2 | BT14: -24.5 | CA14: 0 | CC14: -0.4 | CD14: 21.2 | CE14: 12.1 | CF14: 0.1 | CG14: -1 | CH14: -0.1 | CL14: 0 | CM14: 0 | CN14: 0 | CS14: 0 | CT14: -25.4 | CU14: -19.5 | CW14: -17.7 | CX14: 0 | CY14: 0 | DA14: 1.3 | DB14: 0 | DD14: 0 | DG14: 0 | DH14: 0.7 | DJ14: -1.2 | DK14: 0.4 | DL14: 0.5 | DN14: 0 | DO14: 0 | DP14: 3.9 | DQ14: -6.4 | DR14: 0 | DS14: 0 | DT14: 0.3 | DU14: 0.2 | DW14: -3.1 | DX14: 0 | DY14: 0.2 | DZ14: 0.5 | EA14: 0.3 | EC14: 9.9 | ED14: 0 | EE14: -0.8 | EF14: -0.3 | EG14: 0.2 | EH14: 0.2 | EI14: 2.5 | EJ14: -0.1 | EK14: 1.5 | EL14: 0.2 | EM14: 0.2 | EN14: 0.2 | EQ14: 0 | ER14: 0 | ES14: -0.2 | ET14: -7.9 | EU14: 0 | EV14: 0 | EW14: 0.7 | EY14: 0.6 | EZ14: 0.6 | FA14: 0 | FB14: 0.4 | FC14: 0.6 | FD14: 1.9 | FE14: 11.9 | FF14: 0.1 | FG14: 5.7 | FH14: 0.6 | FI14: 0 | FJ14: 4.1 | FK14: -160.5 | FP14: 1.7 | FS14: 0.1 | FT14: 2 | FU14: 3.8
A15: 04/11/2025 | B15: 02:30 | C15: 37 | D15: -40.6 | E15: 2.6 | H15: -14.3 | I15: 5.4 | L15: -38.7 | M15: -52.7 | N15: -34.9 | O15: 18.6 | P15: 0 | R15: 21.4 | S15: 0.1 | X15: 1 | Y15: 0.8 | Z15: 0.3 | AA15: 0.8 | AB15: -3.4 | AC15: 3.2 | AD15: 8.6 | AI15: 9.7 | AJ15: -7.4 | AN15: -1.1 | AO15: 0 | AP15: 3.3 | AQ15: 9.7 | AR15: 0.8 | AS15: -0.4 | AT15: 2.6 | AU15: 1.1 | AY15: 3.7 | AZ15: -0.7 | BA15: -0.2 | BB15: -0.5 | BC15: -1.8 | BD15: 0.4 | BE15: 0.1 | BF15: 0.1 | BI15: -7.9 | BL15: 7.5 | BP15: 2.4 | BQ15: -43.5 | BR15: -45.1 | BT15: -25.9 | CA15: 0 | CC15: -0.3 | CD15: 19.9 | CE15: 12.7 | CF15: -5.9 | CG15: -1.1 | CH15: -0.2 | CL15: -1.3 | CM15: 0 | CN15: 0 | CS15: 0 | CT15: -22.3 | CU15: -18.7 | CW15: -18.2 | CX15: 0 | CY15: 0 | DA15: 1.3 | DB15: 0.1 | DD15: 0 | DG15: 0 | DH15: 0.6 | DJ15: -1.2 | DK15: 0.3 | DL15: 0.5 | DN15: 0 | DO15: 0 | DP15: 3.4 | DQ15: -7.5 | DR15: 0 | DS15: 0.1 | DT15: 0.3 | DU15: 0.2 | DW15: -3 | DX15: 0 | DY15: 0.2 | DZ15: 0.4 | EA15: 0.3 | EC15: 10.5 | ED15: 0 | EE15: -1.4 | EF15: -1.4 | EG15: 0.3 | EH15: 0 | EI15: 2.6 | EJ15: -0.1 | EK15: 1.6 | EL15: 0.2 | EM15: 0.2 | EN15: 0.2 | EQ15: 0 | ER15: 0 | ES15: -0.2 | ET15: -10.8 | EU15: 0 | EV15: 0 | EW15: 0.7 | EY15: 0.6 | EZ15: 0.6 | FA15: 0 | FB15: 0.4 | FC15: 0.4 | FD15: 1.9 | FE15: 11.9 | FF15: 0.1 | FG15: 2.3 | FH15: 0.7 | FI15: 0 | FJ15: 4.5 | FK15: -191.5 | FP15: 1.7 | FS15: 0.1 | FT15: 2.1 | FU15: 3.9
A16: 04/11/2025 | B16: 03:00 | C16: 37.6 | D16: -32.3 | E16: 4.7 | H16: -16.6 | I16: 4.3 | L16: -36.5 | M16: -50.4 | N16: -32.7 | O16: 20.6 | P16: 0 | R16: 28.4 | S16: 0 | X16: 1.9 | Y16: 1.6 | Z16: 0.9 | AA16: 0.8 | AB16: -3.4 | AC16: 3.2 | AD16: 10.3 | AI16: 10.2 | AJ16: -7.3 | AN16: -1.1 | AO16: 0 | AP16: 3.6 | AQ16: 8.7 | AR16: 1.2 | AS16: 0.4 | AT16: 2.6 | AU16: 1.4 | AY16: 4.6 | AZ16: -0.5 | BA16: 0 | BB16: -1.8 | BC16: -0.8 | BD16: 0.4 | BE16: 0.1 | BF16: -1.9 | BI16: -4.4 | BL16: 6.3 | BP16: 4.1 | BQ16: -40 | BR16: -41.6 | BT16: -22.9 | CA16: 0 | CC16: -0.4 | CD16: 14.7 | CE16: 4.8 | CF16: -6.4 | CG16: -1 | CH16: 0 | CL16: -1.1 | CM16: 0 | CN16: 0 | CS16: 0 | CT16: -20.8 | CU16: -17.8 | CW16: -17.5 | CX16: 0 | CY16: 0 | DA16: 1.3 | DB16: 0 | DD16: 0 | DG16: 0 | DH16: 0.7 | DJ16: -1.1 | DK16: 0.3 | DL16: 0.5 | DN16: 0 | DO16: 0 | DP16: 3.9 | DQ16: -6.4 | DR16: 0 | DS16: 0 | DT16: 0.3 | DU16: 0.2 | DW16: -2.9 | DX16: 0 | DY16: 0.3 | DZ16: 0.5 | EA16: 0.5 | EC16: 4.5 | ED16: 0 | EE16: -0.5 | EF16: 0.2 | EG16: 0.4 | EH16: 0.2 | EI16: 2.6 | EJ16: -0.1 | EK16: 1.7 | EL16: 0.2 | EM16: 0.2 | EN16: 0.2 | EQ16: 0 | ER16: 0 | ES16: -0.2 | ET16: -8.9 | EU16: 0 | EV16: 0 | EW16: 0.7 | EY16: 0.6 | EZ16: 0.6 | FA16: 0 | FB16: 0.4 | FC16: 0.6 | FD16: 1.9 | FE16: 11.7 | FF16: 0.1 | FG16: 3.6 | FH16: 0.6 | FI16: 0 | FJ16: 4.4 | FK16: -158 | FP16: 1.6 | FS16: 0.1 | FT16: 2 | FU16: 3.7
A17: 04/11/2025 | B17: 03:30 | C17: 36.4 | D17: -41.4 | E17: 2.8 | H17: -18.8 | I17: 1.3 | L17: -37.4 | M17: -51.2 | N17: -33.2 | O17: 20.9 | P17: 0 | R17: 14.6 | S17: 0 | X17: -1 | Y17: 1.3 | Z17: 0.8 | AA17: 0.8 | AB17: -3.4 | AC17: 3.2 | AD17: 9.8 | AI17: 9.4 | AJ17: -6.9 | AN17: -1.1 | AO17: 0 | AP17: 3.5 | AQ17: 8.2 | AR17: 1.6 | AS17: 0.6 | AT17: 2.6 | AU17: 0.8 | AY17: 4.5 | AZ17: -0.7 | BA17: 0 | BB17: -2.1 | BC17: -2.2 | BD17: 0.4 | BE17: 0.1 | BF17: -0.9 | BI17: -4.9 | BL17: 6.1 | BP17: 2.7 | BQ17: -40.3 | BR17: -41.8 | BT17: -24.1 | CA17: 0 | CC17: -0.4 | CD17: 15.1 | CE17: 5.1 | CF17: -3.6 | CG17: -1 | CH17: 0.1 | CL17: -2.1 | CM17: 0 | CN17: 0 | CS17: 0 | CT17: -17.9 | CU17: -16 | CW17: -17.2 | CX17: 0 | CY17: 0 | DA17: 1.3 | DB17: 0.1 | DD17: 0 | DG17: 0.1 | DH17: 0.6 | DJ17: -1.1 | DK17: 0.3 | DL17: 0.5 | DN17: 0 | DO17: 0 | DP17: 4 | DQ17: -6 | DR17: 0 | DS17: 0 | DT17: 0.2 | DU17: 0.2 | DW17: -3 | DX17: 0.1 | DY17: 0.3 | DZ17: 0.5 | EA17: 0.7 | EC17: 1.5 | ED17: 0 | EE17: -0.6 | EF17: 0 | EG17: 0.3 | EH17: 0 | EI17: 2.6 | EJ17: -0.1 | EK17: 1.7 | EL17: 0.2 | EM17: 0.2 | EN17: 0.2 | EQ17: 0 | ER17: 0 | ES17: -0.2 | ET17: -8.9 | EU17: 0 | EV17: 0 | EW17: 0.7 | EY17: 0.6 | EZ17: 0.6 | FA17: 0 | FB17: 0.4 | FC17: 0.8 | FD17: 1.8 | FE17: 11.9 | FF17: 0.5 | FG17: 2.8 | FH17: 0.8 | FI17: 0 | FJ17: 4.4 | FK17: -195.9 | FP17: 1.5 | FS17: 0.1 | FT17: 2 | FU17: 3.6
A18: 04/11/2025 | B18: 04:00 | C18: 40.3 | D18: -33 | E18: 4.2 | H18: -17.3 | I18: 5.6 | L18: -30.9 | M18: -46.2 | N18: -28 | O18: 24.9 | P18: 0 | R18: 17.1 | S18: 0 | X18: 3.3 | Y18: 1.7 | Z18: 1.5 | AA18: 0.8 | AB18: -3.4 | AC18: 3.4 | AD18: 11.2 | AI18: 10 | AJ18: -7.1 | AN18: -1.1 | AO18: 0 | AP18: 3.4 | AQ18: 9.5 | AR18: 0.9 | AS18: 0.8 | AT18: 2.6 | AU18: 0.7 | AY18: 5.3 | AZ18: -0.5 | BA18: 0 | BB18: -3.5 | BC18: -1.5 | BD18: 0.4 | BE18: 0.1 | BF18: -3.9 | BI18: -4.7 | BL18: 6.6 | BP18: 3.6 | BQ18: -39.4 | BR18: -40.9 | BT18: -21 | CA18: 0 | CC18: -0.3 | CD18: 15.1 | CE18: 5.5 | CF18: -2.8 | CG18: -1 | CH18: 0 | CL18: -0.2 | CM18: 0 | CN18: 0 | CS18: 0 | CT18: -17.5 | CU18: -15.9 | CW18: -17 | CX18: 0 | CY18: 0 | DA18: 1.3 | DB18: 0.1 | DD18: 0 | DG18: 0.1 | DH18: 0.7 | DJ18: -0.9 | DK18: 0.2 | DL18: 0.5 | DN18: 0 | DO18: 0 | DP18: 3.8 | DQ18: -6.3 | DR18: 0 | DS18: -0.1 | DT18: 0.3 | DU18: 0.2 | DW18: -3 | DX18: 0.1 | DY18: 0.4 | DZ18: 0.5 | EA18: 0.7 | EC18: 1.5 | ED18: 0 | EE18: 1.1 | EF18: 0.8 | EG18: 0.6 | EH18: 0.6 | EI18: 2.6 | EJ18: -0.1 | EK18: 1.7 | EL18: 0.2 | EM18: 0.2 | EN18: 0.2 | EQ18: 0 | ER18: 0 | ES18: -0.2 | ET18: -8.3 | EU18: 0 | EV18: 0 | EW18: 0.7 | EY18: 0.6 | EZ18: 0.6 | FA18: 0 | FB18: 0.4 | FC18: 1 | FD18: 1.8 | FE18: 11.3 | FF18: 0.2 | FG18: 3.6 | FH18: 0.7 | FI18: 0 | FJ18: 4.5 | FK18: -133.7 | FP18: 1.6 | FS18: 0.1 | FT18: 2 | FU18: 3.7
A19: 04/11/2025 | B19: 04:30 | C19: 39.5 | D19: -39.2 | E19: 0.1 | H19: -16.3 | I19: 5.9 | L19: -37.9 | M19: -51.3 | N19: -33.5 | O19: 18.3 | P19: 0 | R19: 12.1 | S19: 0.1 | X19: 3.1 | Y19: 1.2 | Z19: 1 | AA19: 0.8 | AB19: -3.4 | AC19: 3.4 | AD19: 11.2 | AI19: 9.4 | AJ19: -7.4 | AN19: -1.1 | AO19: 0 | AP19: 3.2 | AQ19: 9.1 | AR19: 1 | AS19: 0.7 | AT19: 2.6 | AU19: 0.2 | AY19: 4.4 | AZ19: -0.8 | BA19: -0.2 | BB19: -1.2 | BC19: -0.9 | BD19: 0.4 | BE19: 0.1 | BF19: 0.2 | BI19: -3.5 | BL19: 6.7 | BP19: 2.3 | BQ19: -41.2 | BR19: -42.8 | BT19: -24 | CA19: 0 | CC19: -0.4 | CD19: 13.7 | CE19: 5.3 | CF19: -3.5 | CG19: -1 | CH19: -0.1 | CL19: 1.2 | CM19: 0 | CN19: -10.3 | CS19: 0 | CT19: -18.1 | CU19: -16.2 | CW19: -17.1 | CX19: 0 | CY19: 0 | DA19: 1.3 | DB19: 0.1 | DD19: 0 | DG19: 0 | DH19: 0.6 | DJ19: -1 | DK19: 0.2 | DL19: 0.5 | DN19: 0 | DO19: 0 | DP19: 3.7 | DQ19: -6.5 | DR19: 0 | DS19: 0.1 | DT19: 0.3 | DU19: 0.2 | DW19: -3 | DX19: 0 | DY19: 0.3 | DZ19: 0.5 | EA19: 0.7 | EC19: 1.5 | ED19: 0 | EE19: -0.6 | EF19: -2.2 | EG19: 0.5 | EH19: 0.5 | EI19: 2.6 | EJ19: -0.1 | EK19: 1.7 | EL19: 0.2 | EM19: 0.2 | EN19: 0.2 | EQ19: 0 | ER19: 0 | ES19: -0.2 | ET19: -10.2 | EU19: 0 | EV19: 0 | EW19: 0.6 | EY19: 0.6 | EZ19: 0.6 | FA19: 0 | FB19: 0.4 | FC19: 1 | FD19: 1.5 | FE19: 11.4 | FF19: 0.1 | FG19: 4 | FH19: 0.4 | FI19: 0 | FJ19: 4.5 | FK19: -197 | FP19: 1.6 | FS19: 0.1 | FT19: 2 | FU19: 3.7
A20: 04/11/2025 | B20: 05:00 | C20: 39.7 | D20: -33.7 | E20: 1.5 | H20: -16.9 | I20: 5.8 | L20: -31.1 | M20: -45.4 | N20: -27.2 | O20: 26.7 | P20: 0 | R20: 15.1 | S20: 0 | X20: 4.2 | Y20: 1.3 | Z20: 1.1 | AA20: 0.8 | AB20: -3.4 | AC20: 3.6 | AD20: 12.4 | AI20: 9.7 | AJ20: -6.6 | AN20: -1 | AO20: 0 | AP20: 3.2 | AQ20: 9.4 | AR20: 1.1 | AS20: 0.4 | AT20: 2.6 | AU20: 1.2 | AY20: 3.7 | AZ20: -0.7 | BA20: -0.2 | BB20: -3.1 | BC20: -1.5 | BD20: 0.4 | BE20: 0.1 | BF20: -2.6 | BI20: -12 | BL20: 6.7 | BP20: 2.9 | BQ20: -39 | BR20: -40.5 | BT20: -20.8 | CA20: 0 | CC20: -0.3 | CD20: 14.2 | CE20: 5.2 | CF20: -3 | CG20: -1 | CH20: -0.1 | CL20: 5.1 | CM20: -0.8 | CN20: -7.6 | CS20: 0 | CT20: -16.7 | CU20: -15.4 | CW20: -17.3 | CX20: 0 | CY20: 0 | DA20: 1.3 | DB20: 0.1 | DD20: 0 | DG20: 0 | DH20: 0.6 | DJ20: -1.2 | DK20: 0.2 | DL20: 0.6 | DN20: 0 | DO20: 0 | DP20: 4 | DQ20: -5.6 | DR20: 0.6 | DS20: 0.1 | DT20: 0.3 | DU20: 0.2 | DW20: -3.1 | DX20: 0 | DY20: 0.4 | DZ20: 0.6 | EA20: 0.7 | EC20: 1.5 | ED20: 0.3 | EE20: 0.8 | EF20: 0.8 | EG20: 0.7 | EH20: 0.6 | EI20: 2.5 | EJ20: -0.1 | EK20: 1.7 | EL20: 0.2 | EM20: 0.2 | EN20: 0.2 | EQ20: 0 | ER20: 0 | ES20: -0.2 | ET20: -9.2 | EU20: 0 | EV20: 0 | EW20: 0.4 | EY20: 0.2 | EZ20: 0.4 | FA20: 0 | FB20: 0.4 | FC20: 1 | FD20: 1.6 | FE20: 11.6 | FF20: 0.2 | FG20: 2.5 | FH20: 0.9 | FI20: 0 | FJ20: 4.6 | FK20: -146.2 | FP20: 1.6 | FS20: 0.1 | FT20: 2 | FU20: 3.7
A21: 04/11/2025 | B21: 05:30 | C21: 40.4 | D21: -26.3 | E21: 2.9 | H21: -15.8 | I21: 6 | L21: -29.7 | M21: -46 | N21: -28.3 | O21: 27.7 | P21: 0 | R21: 28.9 | S21: -0.1 | X21: 4.9 | Y21: 1.6 | Z21: 1.2 | AA21: 0.9 | AB21: -3.4 | AC21: 3.8 | AD21: 11.9 | AI21: 10.1 | AJ21: -6.7 | AN21: -0.9 | AO21: 0 | AP21: 3.4 | AQ21: 9.6 | AR21: 1.1 | AS21: -0.8 | AT21: 2.6 | AU21: 0.8 | AY21: 3.5 | AZ21: -0.7 | BA21: -0.2 | BB21: -2.5 | BC21: -0.9 | BD21: 0.4 | BE21: 0.2 | BF21: -2 | BI21: -4.3 | BL21: 7 | BP21: 4.4 | BQ21: -38.2 | BR21: -39.7 | BT21: -21.4 | CA21: 0 | CC21: -0.3 | CD21: 14.2 | CE21: 5.5 | CF21: -3 | CG21: -1 | CH21: 0 | CL21: 4.1 | CM21: 20.9 | CN21: -9 | CS21: 0 | CT21: -15.9 | CU21: -14.9 | CW21: -19.1 | CX21: 0.2 | CY21: 0 | DA21: 1.3 | DB21: 0 | DD21: 0 | DG21: 0 | DH21: 0.6 | DJ21: -0.9 | DK21: 0.2 | DL21: 0.5 | DN21: 0 | DO21: 0 | DP21: 3.4 | DQ21: -0.4 | DR21: 0.5 | DS21: 0.1 | DT21: 0.3 | DU21: 0.2 | DW21: -3.1 | DX21: 0 | DY21: 0.4 | DZ21: 0.5 | EA21: 0.7 | EC21: 1.5 | ED21: 0.1 | EE21: 0.1 | EF21: 1.3 | EG21: 0.6 | EH21: 0.5 | EI21: 2.5 | EJ21: -0.1 | EK21: 1.5 | EL21: 0.2 | EM21: 0.2 | EN21: 0.2 | EQ21: 0 | ER21: 2.2 | ES21: -0.2 | ET21: -9.8 | EU21: 0 | EV21: 1.2 | EW21: 0.4 | EY21: 0.2 | EZ21: 0.4 | FA21: 0 | FB21: 0.4 | FC21: 1 | FD21: 1.7 | FE21: 11.5 | FF21: 0.1 | FG21: 3 | FH21: 0.9 | FI21: 0 | FJ21: 4.3 | FK21: -82.7 | FP21: 1.5 | FS21: 0.1 | FT21: 2 | FU21: 3.6
A22: 04/11/2025 | B22: 06:00 | C22: 41.5 | D22: -47.3 | E22: 0.3 | H22: -14.8 | I22: 5.3 | L22: -38.5 | M22: -52.7 | N22: -34.7 | O22: 17.9 | P22: 0 | R22: 8.6 | S22: 0 | X22: 5.4 | Y22: 1.1 | Z22: 0.9 | AA22: 0.8 | AB22: -3.4 | AC22: 4 | AD22: 10.6 | AI22: 9.7 | AJ22: -7.6 | AN22: -1 | AO22: 0 | AP22: 2.9 | AQ22: 9.8 | AR22: 0.9 | AS22: -1.6 | AT22: 2.6 | AU22: 1.4 | AY22: 3.4 | AZ22: -1 | BA22: -0.4 | BB22: -3.5 | BC22: -1.5 | BD22: 0.4 | BE22: 0.1 | BF22: -1 | BI22: -3.8 | BL22: 7.3 | BP22: 0.6 | BQ22: -42.4 | BR22: -44 | BT22: -23.6 | CA22: 0 | CC22: -0.3 | CD22: 14.4 | CE22: 5.6 | CF22: -2.9 | CG22: -1.1 | CH22: -0.2 | CL22: -0.4 | CM22: 16.1 | CN22: -15.8 | CS22: 0 | CT22: -19.3 | CU22: -16.9 | CW22: -20.3 | CX22: 1.2 | CY22: 0 | DA22: 1.3 | DB22: 0.1 | DD22: 0 | DG22: 0 | DH22: 0.6 | DJ22: -0.9 | DK22: 0.2 | DL22: 0.6 | DN22: 0 | DO22: 0 | DP22: 2.7 | DQ22: -4.1 | DR22: 0.2 | DS22: 0.1 | DT22: 0.2 | DU22: 0.2 | DW22: -3.1 | DX22: 0 | DY22: 0.3 | DZ22: 0.5 | EA22: 0.6 | EC22: 1.5 | ED22: -0.1 | EE22: -2.6 | EF22: -2.4 | EG22: 0.1 | EH22: 0.1 | EI22: 2.5 | EJ22: -0.1 | EK22: 1.4 | EL22: 0.2 | EM22: 0.2 | EN22: 0.2 | EQ22: 0 | ER22: 1.9 | ES22: -0.2 | ET22: -13.4 | EU22: 0 | EV22: 0.4 | EW22: 0.4 | EY22: 0.2 | EZ22: 0.4 | FA22: 0 | FB22: 0.4 | FC22: 0.8 | FD22: 1.8 | FE22: 11.5 | FF22: 0.5 | FG22: 2.7 | FH22: 0.9 | FI22: 0 | FJ22: 3.6 | FK22: -214.8 | FP22: 1.6 | FS22: 0 | FT22: 2 | FU22: 3.6
... A58: 05/11/2025 | B58: 00:00 | C58: 34.6 | D58: -32.4 | E58: 2.4 | H58: -10.1 | I58: 14.5 | L58: -14.9 | M58: -17.8 | N58: -11.1 | O58: 37.8 | P58: 0 | R58: 21.3 | S58: 0.2 | X58: 0.8 | Y58: 1 | Z58: 0.2 | AA58: 0.8 | AB58: -3.2 | AC58: 2.8 | AD58: 16.1 | AI58: 8.4 | AJ58: -21.1 | AN58: -1.2 | AO58: -19.4 | AP58: 3.2 | AQ58: 12.5 | AR58: -2.4 | AS58: 1 | AT58: 2.6 | AU58: 1.1 | AY58: 1.6 | AZ58: -0.6 | BA58: -0.1 | BB58: -1.5 | BC58: 0.6 | BD58: 0.4 | BE58: 0.1 | BF58: -1.7 | BI58: -13.8 | BL58: 0 | BP58: -0.2 | BQ58: -39.7 | BR58: -41.3 | BT58: -22.4 | CA58: 0 | CC58: -0.3 | CD58: 23.7 | CE58: 15.1 | CF58: 3.6 | CG58: 0.6 | CH58: 1.9 | CL58: -1.3 | CM58: 0.6 | CN58: -35.1 | CS58: 0 | CT58: -26.4 | CU58: -20.7 | CW58: -19.4 | CX58: 0 | CY58: 0 | DA58: 1.3 | DB58: 0 | DD58: 0 | DG58: 0.2 | DH58: 0.9 | DJ58: -0.9 | DK58: 0.2 | DL58: 0.6 | DN58: 0 | DO58: 0 | DP58: 3.4 | DQ58: -1.7 | DR58: 0 | DS58: 0 | DT58: 0.5 | DU58: 0.3 | DW58: -3 | DX58: 0 | DY58: 0.6 | DZ58: 0.3 | EA58: 0.5 | EC58: 14.6 | ED58: 0 | EE58: -0.1 | EF58: -3.8 | EG58: 0.4 | EH58: 0.4 | EI58: 2.6 | EJ58: -0.1 | EK58: 1.8 | EL58: 0.2 | EM58: 0.2 | EN58: 0.2 | EQ58: 0 | ER58: 0 | ES58: -0.2 | ET58: -13.5 | EU58: 0.7 | EV58: 0 | EW58: 0.6 | EY58: 0.6 | EZ58: 0.6 | FA58: 0 | FB58: 0.4 | FC58: 0.6 | FD58: 2.1 | FE58: 0 | FF58: 0 | FG58: 2.3 | FH58: 0 | FI58: 3.3 | FJ58: 4.1 | FK58: -127.4 | FP58: 1.6 | FS58: -0.2 | FT58: 0.4 | FU58: 1.8
A59: EJEC | C59: 924.6 | D59: -248.6 | E59: 165.7 | F59: 0 | G59: 0 | H59: -218.5 | I59: 270.7 | J59: 0 | K59: 0 | L59: -207.55 | M59: -378 | N59: -312 | O59: 1272.55 | P59: -23 | Q59: 0 | R59: 665.4 | S59: 1 | T59: 0 | U59: 0 | V59: 0 | W59: 0 | X59: 143.5 | Y59: 35.65 | Z59: 18 | AA59: 19.35 | AB59: -80.9 | AC59: 85.75 | AD59: 266.2 | AE59: 0 | AF59: 0 | AG59: 0 | AH59: 0 | AI59: 310.65 | AJ59: 78.1 | AK59: 0 | AL59: 0 | AM59: 0 | AN59: -30.15 | AO59: 79.15 | AP59: 83.3 | AQ59: 333.1 | AR59: 48.85 | AS59: -6.25 | AT59: 62.4 | AU59: 24.6 | AV59: 0 | AW59: 0 | AX59: 0 | AY59: 169.7 | AZ59: -19.7 | BA59: -4.5 | BB59: -35.6 | BC59: -57.85 | BD59: 9.8 | BE59: 4.4 | BF59: -12.75 | BG59: 0 | BH59: 0 | BI59: 38.35 | BJ59: 0 | BK59: 0 | BL59: 110.5 | BM59: 0 | BN59: 0 | BO59: 0 | BP59: 114.45 | BQ59: -721.8 | BR59: -754.05 | BS59: 0 | BT59: -282.15 | BU59: 0 | BV59: 0 | BW59: 0 | BX59: 0 | BY59: 0 | BZ59: 0 | CA59: 0.1 | CB59: 0 | CC59: -7.85 | CD59: 1101.45 | CE59: 389.55 | CF59: 189.8 | CG59: 9.7 | CH59: 84.4 | CI59: 0 | CJ59: 0 | CK59: 0 | CL59: 595.3 | CM59: 670.8 | CN59: 236 | CO59: 0 | CP59: 0 | CQ59: 0 | CR59: 0 | CS59: 3.45 | CT59: -260.8 | CU59: -249.65 | CV59: 0 | CW59: -391.25 | CX59: 73.35 | CY59: 0.1 | CZ59: 0 | DA59: 31.2 | DB59: 1.1 | DC59: 0 | DD59: -0.1 | DE59: 0 | DF59: 0 | DG59: 0.35 | DH59: 18.4 | DI59: 0 | DJ59: -10.2 | DK59: 6.85 | DL59: 13.45 | DM59: 0 | DN59: -7.2 | DO59: -18.3 | DP59: 102.4 | DQ59: -91.6 | DR59: -27.3 | DS59: 0.2 | DT59: 11.2 | DU59: 5.6 | DV59: 0 | DW59: -70.75 | DX59: -0.7 | DY59: 8.25 | DZ59: 20.1 | EA59: 19.9 | EB59: 0 | EC59: 93.6 | ED59: 21.45 | EE59: -5.05 | EF59: -66.9 | EG59: 6.7 | EH59: 4.55 | EI59: 61.5 | EJ59: -2.2 | EK59: 38.75 | EL59: 4.8 | EM59: 4.8 | EN59: 4.8 | EO59: 0 | EP59: 0 | EQ59: 15.85 | ER59: 247 | ES59: -4.75 | ET59: -72.35 | EU59: 0.35 | EV59: -53.65 | EW59: 14.25 | EX59: 0 | EY59: 13.35 | EZ59: 13.1 | FA59: 13.35 | FB59: 16.6 | FC59: 25.75 | FD59: 44.2 | FE59: 219.05 | FF59: 5.1 | FG59: 63.65 | FH59: 24.5 | FI59: 30.85 | FJ59: 87.35 | FK59: 5270.05 | FM59: 0 | FN59: 0 | FO59: 0 | FP59: 40.45 | FQ59: 0 | FR59: 0 | FS59: 3.3 | FT59: 50.25 | FU59: 94

Sheet DEMANDA_AREAS
B3: martes, 4 de Noviembre del 2025
B5: REPORTE DE LA DEMANDA POR ÁREAS Y SUBAREAS OPERATIVAS (MW)
B6: FECHA HORA | C6: DEMANDA | E6: AREA | H6: SUBAREAS
C7: INTERCAMBIOS INTERNACIONALES | D7: SEIN | E7: NORTE | F7: CENTRO | G7: SUR | H7: ELECTROANDES
B8: 00:30 | C8: 0 | D8: 6375.7 | E8: 919.6766 | F8: 3948.6968 | G8: 1507.3266 | H8: 230.591
B9: 01:00 | C9: 0 | D9: 6269 | E9: 915.0747 | F9: 3859.1034 | G9: 1494.8219 | H9: 235.0154
B10: 01:30 | C10: 0 | D10: 6233.3 | E10: 911.2273 | F10: 3815.4842 | G10: 1506.5885 | H10: 232.6505
B11: 02:00 | C11: 0 | D11: 6152.2 | E11: 904.3828 | F11: 3750.0532 | G11: 1497.764 | H11: 229.1852
B12: 02:30 | C12: 0 | D12: 5999.7 | E12: 906.9181 | F12: 3615.216 | G12: 1477.5659 | H12: 236.1474
B13: 03:00 | C13: 0 | D13: 6078.6 | E13: 892.1283 | F13: 3683.4949 | G13: 1502.9768 | H13: 238.2001
B14: 03:30 | C14: 0 | D14: 5975 | E14: 895.2615 | F14: 3597.0188 | G14: 1482.7197 | H14: 234.6091
B15: 04:00 | C15: 0 | D15: 6105 | E15: 900.9855 | F15: 3697.8823 | G15: 1506.1322 | H15: 231.8258
B16: 04:30 | C16: 0 | D16: 6005.4 | E16: 897.5246 | F16: 3591.1052 | G16: 1516.7702 | H16: 234.1507
B17: 05:00 | C17: 0 | D17: 6185.5 | E17: 897.1179 | F17: 3766.8128 | G17: 1521.5693 | H17: 231.3923
B18: 05:30 | C18: 0 | D18: 6292.2 | E18: 925.0975 | F18: 3840.3054 | G18: 1526.7971 | H18: 232.4049
B19: 06:00 | C19: 0 | D19: 6206 | E19: 927.8264 | F19: 3761.885 | G19: 1516.2886 | H19: 214.8403
... B59: ENERGÍA | C59: 0 | D59: 165123.61 | E59: 24573.764 | F59: 103629.98 | G59: 36919.871 | H59: 5625.9816
B61: LEYENDA:
D63: Potencia recibida del Ecuador
D64: Potencia entregada al Ecuador

Sheet DEMANDA_UL
B3: martes, 4 de Noviembre del 2025
B5: POTENCIA DE LOS GRANDES USUARIOS LIBRES (MW)
B6: FECHA HORA | C6: GRANDES USUARIOS LIBRES DEL ÁREA NORTE | X6: GRANDES USUARIOS LIBRES DEL ÁREA CENTRO | BP6: GRANDES USUARIOS LIBRES DEL ÁREA SUR
C7: ARCA CONTINENTAL LINDLEY S.A. | D7: AUSTRAL GROUP S.A.A | E7: CEMENTOS PACASMAYO | F7: CONSORCIO MINERO HORIZONTE S.R.L. | G7: CORPORACIÓN PESQUERA INCA S.A.C. | H7: CREDITEX: CIA IND.TEXTIL CREDISA | I7: HIPERMERCADOS TOTTUS S.A | J7: INDUSTRIA TEXTIL PIURA | K7: MINERA BOROO MISQUICHILCA S.A. | L7: MINERA GOLD FIELDS | M7: MINERA MARSA | N7: MINERA MISKY MAYO | O7: MINERA YANACOCHA | P7: OPEN PLAZA | Q7: PESQUERA DIAMANTE | R7: PETROPERU | S7: REAL PLAZA S.R.L. | T7: SIDER PERU | U7: SUPERMERCADOS PERUANOS S.A. | V7: TRUPAL S.A. | W7: UNIÓN DE CERVECERÍAS PERUANAS BACKUS Y JOHNSTON S. | X7: ACEROS AREQUIPA | Y7: ADMINISTRADORA JOCKEY PLAZA SHOPPING CENTER S.A. | Z7: ALICORP | AA7: ARCA CONTINENTAL LINDLEY S.A. | AB7: AUSTRAL GROUP S.A.A | AC7: COMPAÑIA MINERA CONDESTABLE | AD7: CORPORACIÓN PESQUERA INCA S.A.C. | AE7: CREDITEX: CIA IND.TEXTIL CREDISA | AF7: FUNDICION CHILCA S.A. | AG7: HIPERMERCADOS TOTTUS S.A | AH7: INMOBILIARIA KANPU S.A. | AI7: INMUEBLES PANAMERICANA S.A. | AJ7: KIMBERLY-CLARK PERU | AK7: LECHE GLORIA S.A. | AL7: MALL AVENTURA S.A. | AM7: MARCOBRE S.A.C. | AN7: MINERA ANTAMINA | AO7: MINERA ARES | AP7: MINERA BUENAVENTURA | AQ7: MINERA CHINALCO PERÚ S.A. | AR7: MINERA SHOUXIN PERU S.A. | AS7: MINERA VOLCAN | AT7: MINSUR | AU7: MOLYCOP-ADESUR | AV7: NEXA RESOURCES CAJAMARQUILLA S.A. | AW7: NEXA RESOURCES PERÚ S.A.A. | AX7: OPEN PLAZA | AY7: OPP FILM | AZ7: OWENS-ILLINOIS PERÚ S.A. | BA7: PAPELERA NACIONAL S.A. | BB7: PESQUERA DIAMANTE | BC7: QUIMPAC S.A. | BD7: REAL PLAZA S.R.L. | BE7: REFINERIA LA PAMPILLA S.A.A | BF7: SAGA FALABELLA | BG7: SAN MIGUEL INDUSTRIAS PET S.A. | BH7: SHOUGANG HIERRO PERU | BI7: SOFTYS PERU S.A.C. | BJ7: SUPERMERCADOS PERUANOS S.A. | BK7: TEJIDOS SAN JACINTO | BL7: TREN URBANO DE LIMA S.A. | BM7: TRUPAL S.A. | BN7: UNACEM PERU S.A. | BO7: UNIÓN DE CERVECERÍAS PERUANAS BACKUS Y JOHNSTON S. | BP7: ANGLO AMERICAN QUELLAVECO S.A. | BQ7: ARCA CONTINENTAL LINDLEY S.A. | BR7: CAL & CEMENTO SUR S.A. | BS7: COMPAÑIA MINERA ANTAPACCAY S.A. | BT7: COMPAÑÍA MINERA CHUNGAR SAC | BU7: COMPAÑIA MINERA SAN IGNACIO DE MOROCOCHA S.A.A. | BV7: EL BROCAL .S.A. | BW7: EMPRESA ADMINISTRADORA CERRO S.A.C. | BX7: EMPRESA MINERA LOS QUENUALES S.A.C. | BY7: HIPERMERCADOS TOTTUS S.A | BZ7: HUDBAY PERU S.A.C. | CA7: INDUSTRIA CACHIMAYO | CB7: MALL AVENTURA S.A. | CC7: MINERA ARES | CD7: MINERA BUENAVENTURA | CE7: MINERA CERRO VERDE | CF7: MINERA CORONA | CG7: MINERA LAS BAMBAS S.A. | CH7: MINERA VOLCAN | CI7: MINSUR | CJ7: MOLYCOP-ADESUR | CK7: NEXA RESOURCES PERÚ S.A.A. | CL7: OXIDOS DE PASCO S.A.C. | CM7: PESQUERA DIAMANTE | CN7: REAL PLAZA S.R.L. | CO7: SOBREANDES S.A.C. | CP7: SOUTHERN PERU CC | CQ7: SUPERMERCADOS PERUANOS S.A. | CR7: UNACEM PERU S.A. | CS7: UNIÓN DE CERVECERÍAS PERUANAS BACKUS Y JOHNSTON S. | CT7: YURA
B8: 00:30 | E8: 26.13408 | F8: 13.232 | H8: 4.193 | L8: 26.9077 | M8: 12.6368 | N8: 13.5 | O8: 35.024 | R8: 50.909 | T8: 13.9483 | V8: 0.9 | X8: 138.92145 | Z8: 5.68047 | AC8: 12.24 | AE8: 4.375 | AF8: 2.2 | AH8: 3.538 | AJ8: 5.33786 | AK8: 0 | AM8: 50.66585 | AN8: 120.35625 | AO8: 18.30106 | AP8: 0.81 | AQ8: 168.30725 | AS8: 38.32331 | AT8: 31.6995 | AV8: 195.63909 | AW8: 36.4543 | BA8: 2.3 | BC8: 72.63675 | BE8: 17.1 | BI8: 17.84612 | BK8: 5.66739 | BM8: 6.212 | BN8: 52.719 | BO8: 1.56 | BP8: 140.55042 | BR8: 3.8086 | BS8: 127.77545 | BT8: 11.18742 | BV8: 36.4312 | BW8: 3.85819 | BZ8: 92.01696 | CA8: 6.65996 | CC8: 0.664 | CD8: 25.84515 | CE8: 182.12323 | CG8: 155.02859 | CH8: 17.55413 | CK8: 17.2578 | CL8: 4.862 | CO8: 16.33508 | CP8: 291.58 | CR8: 33.572 | CT8: 30.438
B9: 01:00 | E9: 26.06807 | F9: 12.805 | H9: 4.237 | L9: 26.8546 | M9: 12.6288 | N9: 13.66 | O9: 34.528 | R9: 51.265 | T9: 15.5747 | V9: 0.9 | X9: 134.65756 | Z9: 5.19237 | AC9: 12.6 | AE9: 4.495 | AF9: 3.6 | AH9: 1.7033 | AJ9: 5.33431 | AK9: 0 | AM9: 48.26761 | AN9: 119.37643 | AO9: 18.48444 | AP9: 0.7 | AQ9: 169.73758 | AS9: 37.97877 | AT9: 34.37152 | AV9: 193.07509 | AW9: 35.914 | BA9: 2.3 | BC9: 73.49432 | BE9: 17.1 | BI9: 17.55457 | BK9: 5.54993 | BM9: 6.6321 | BN9: 50.435 | BO9: 1.56 | BP9: 139.0403 | BR9: 3.6457 | BS9: 126.79755 | BT9: 12.78942 | BV9: 37.2484 | BW9: 3.96348 | BZ9: 91.01101 | CA9: 19.2251 | CC9: 0.672 | CD9: 25.4921 | CE9: 183.54381 | CG9: 147.61275 | CH9: 17.55214 | CK9: 17.1155 | CL9: 4.84195 | CO9: 16.16208 | CP9: 292.6 | CR9: 33.503 | CT9: 32.381
B10: 01:30 | E10: 29.15175 | F10: 12.239 | H10: 4.109 | L10: 26.9616 | M10: 13.3086 | N10: 13.64 | O10: 33.974 | R10: 51.919 | T10: 16.0525 | V10: 0.9 | X10: 115.38087 | Z10: 5.05744 | AC10: 12.43 | AE10: 4.584 | AF10: 5.5 | AH10: 3.6573 | AJ10: 5.31128 | AK10: 0 | AM10: 48.65412 | AN10: 118.97739 | AO10: 19.25075 | AP10: 0.64 | AQ10: 169.78548 | AS10: 38.59252 | AT10: 34.84366 | AV10: 195.2114 | AW10: 34.307 | BA10: 2.3 | BC10: 72.18532 | BE10: 17.1 | BI10: 17.69613 | BK10: 5.52769 | BM10: 6.251 | BN10: 50.417 | BO10: 1.56 | BP10: 141.53158 | BR10: 3.7385 | BS10: 126.93488 | BT10: 13.10978 | BV10: 38.0452 | BW10: 4.0073 | BZ10: 90.75775 | CA10: 19.43782 | CC10: 0.655 | CD10: 25.64587 | CE10: 183.73985 | CG10: 153.92132 | CH10: 17.59392 | CK10: 16.6648 | CL10: 4.86091 | CO10: 13.122 | CP10: 291.52 | CR10: 34.353 | CT10: 32.49
B11: 02:00 | E11: 29.33228 | F11: 12.694 | H11: 4.17 | L11: 26.5974 | M11: 13.54 | N11: 13.66 | O11: 34.358 | R11: 50.847 | T11: 15.8294 | V11: 0.9 | X11: 116.617 | Z11: 5.01955 | AC11: 12.11 | AE11: 4.538 | AF11: 7.2 | AH11: 4.0189 | AJ11: 5.27359 | AK11: 0 | AM11: 48.5924 | AN11: 119.23879 | AO11: 19.12878 | AP11: 0.44 | AQ11: 170.9264 | AS11: 39.07043 | AT11: 34.79268 | AV11: 195.06983 | AW11: 35.2176 | BA11: 2.4 | BC11: 71.1536 | BE11: 17.1 | BI11: 17.80105 | BK11: 5.48646 | BM11: 6.623 | BN11: 50.917 | BO11: 1.45 | BP11: 138.66532 | BR11: 3.7324 | BS11: 129.58264 | BT11: 14.47291 | BV11: 35.7693 | BW11: 3.7307 | BZ11: 89.88217 | CA11: 20.62111 | CC11: 0.69 | CD11: 25.46547 | CE11: 185.79855 | CG11: 152.6548 | CH11: 17.80637 | CK11: 16.3972 | CL11: 4.85859 | CO11: 11.19295 | CP11: 280.8 | CR11: 34.491 | CT11: 32.859
B12: 02:30 | E12: 33.22542 | F12: 13.177 | H12: 4.067 | L12: 26.243 | M12: 13.6376 | N12: 13.46 | O12: 34.218 | R12: 51.172 | T12: 16.0706 | V12: 0.9 | X12: 140.83638 | Z12: 5.04159 | AC12: 10.86 | AE12: 4.367 | AF12: 3.6 | AH12: 1.5774 | AJ12: 5.22184 | AK12: 0 | AM12: 49.67039 | AN12: 119.23304 | AO12: 19.47857 | AP12: 0.41 | AQ12: 169.65027 | AS12: 38.36458 | AT12: 35.13392 | AV12: 194.82273 | AW12: 36.6935 | BA12: 2.5 | BC12: 71.54913 | BE12: 17.1 | BI12: 17.61339 | BK12: 5.51315 | BM12: 6.321 | BN12: 50.912 | BO12: 1.58 | BP12: 136.53427 | BR12: 3.5962 | BS12: 128.86564 | BT12: 14.98542 | BV12: 36.0478 | BW12: 3.87202 | BZ12: 91.19838 | CA12: 24.74202 | CC12: 0.65 | CD12: 24.9503 | CE12: 183.04085 | CG12: 154.41405 | CH12: 17.35201 | CK12: 16.6346 | CL12: 4.5072 | CO12: 14.02576 | CP12: 272.27 | CR12: 34.199 | CT12: 34.789
B13: 03:00 | E13: 34.36945 | F13: 13.129 | H13: 4.219 | L13: 26.182 | M13: 13.8015 | N13: 13.5 | O13: 34.562 | R13: 50.96 | T13: 15.7312 | V13: 0.9 | X13: 162.59314 | Z13: 5.56628 | AC13: 9.94 | AE13: 4.367 | AF13: 2.2 | AH13: 2.7805 | AJ13: 4.81592 | AK13: 0 | AM13: 50.07286 | AN13: 118.94694 | AO13: 19.84646 | AP13: 0.67 | AQ13: 168.04667 | AS13: 37.38664 | AT13: 34.62476 | AV13: 194.65987 | AW13: 36.427 | BA13: 2.4 | BC13: 71.33136 | BE13: 17.1 | BI13: 17.75493 | BK13: 5.41222 | BM13: 6.3621 | BN13: 50.933 | BO13: 1.66 | BP13: 138.30563 | BR13: 3.5267 | BS13: 129.50984 | BT13: 14.6603 | BV13: 35.163 | BW13: 3.96593 | BZ13: 89.95233 | CA13: 24.81353 | CC13: 0.684 | CD13: 25.80117 | CE13: 186.08007 | CG13: 156.31644 | CH13: 17.71751 | CK13: 16.9647 | CL13: 4.49687 | CO13: 16.45146 | CP13: 279.51 | CR13: 34.46 | CT13: 36.349
B14: 03:30 | E14: 33.61875 | F14: 13.085 | H14: 4.151 | L14: 26.214 | M14: 13.4677 | N14: 13.47 | O14: 33.786 | R14: 51.463 | T14: 15.8234 | V14: 0.9 | X14: 132.10972 | Z14: 5.59154 | AC14: 9.71 | AE14: 4.427 | AF14: 3.7 | AH14: 3.0615 | AJ14: 5.05719 | AK14: 0 | AM14: 49.21887 | AN14: 120.02193 | AO14: 20.34543 | AP14: 0.48 | AQ14: 169.72042 | AS14: 38.10109 | AT14: 34.20714 | AV14: 192.61913 | AW14: 36.4494 | BA14: 2.4 | BC14: 71.23619 | BE14: 17.1 | BI14: 17.53321 | BK14: 5.3717 | BM14: 6.452 | BN14: 50.635 | BO14: 1.62 | BP14: 138.27175 | BR14: 3.6784 | BS14: 129.77606 | BT14: 14.42599 | BV14: 36.4934 | BW14: 4.02736 | BZ14: 91.10771 | CA14: 24.80936 | CC14: 0.647 | CD14: 24.81471 | CE14: 182.87373 | CG14: 151.49361 | CH14: 17.69751 | CK14: 17.5173 | CL14: 4.69209 | CO14: 16.83653 | CP14: 270.78 | CR14: 33.222 | CT14: 36.518
B15: 04:00 | E15: 33.40483 | F15: 13.735 | H15: 4.209 | L15: 25.9168 | M15: 13.4865 | N15: 13.3 | O15: 34.434 | R15: 50.256 | T15: 18.5474 | V15: 0.9 | X15: 112.46701 | Z15: 6.02183 | AC15: 10.19 | AE15: 4.235 | AF15: 4 | AH15: 4.0623 | AJ15: 5.19055 | AK15: 0 | AM15: 49.70015 | AN15: 121.33951 | AO15: 20.26479 | AP15: 0.18 | AQ15: 170.25802 | AS15: 38.22283 | AT15: 33.5296 | AV15: 194.57324 | AW15: 36.5072 | BA15: 2.5 | BC15: 71.76408 | BE15: 17.1 | BI15: 17.55149 | BK15: 5.36795 | BM15: 6.325 | BN15: 50.749 | BO15: 1.49 | BP15: 138.12899 | BR15: 3.6811 | BS15: 130.27891 | BT15: 14.61096 | BV15: 36.8982 | BW15: 3.88656 | BZ15: 88.43823 | CA15: 24.80466 | CC15: 0.666 | CD15: 25.37812 | CE15: 184.18633 | CG15: 155.72179 | CH15: 17.3439 | CK15: 17.7908 | CL15: 4.55193 | CO15: 16.86131 | CP15: 278.73 | CR15: 33.047 | CT15: 36.428
B16: 04:30 | E16: 33.41217 | F16: 13.122 | H16: 4.158 | L16: 26.394 | M16: 14.6036 | N16: 13.39 | O16: 35.048 | R16: 50.393 | T16: 17.0245 | V16: 0.8 | X16: 114.01172 | Z16: 6.00302 | AC16: 10.65 | AE16: 4.23 | AF16: 5 | AH16: 3.3286 | AJ16: 5.28152 | AK16: 0 | AM16: 50.32979 | AN16: 121.92154 | AO16: 19.86248 | AP16: 1.65 | AQ16: 168.11682 | AS16: 37.64241 | AT16: 32.67359 | AV16: 193.42863 | AW16: 32.246 | BA16: 2.33 | BC16: 71.90394 | BE16: 17.1 | BI16: 17.54097 | BK16: 5.44005 | BM16: 6.326 | BN16: 51.301 | BO16: 1.47 | BP16: 140.82312 | BR16: 3.5389 | BS16: 128.96262 | BT16: 13.68715 | BV16: 37.0048 | BW16: 3.90366 | BZ16: 90.21667 | CA16: 25.06918 | CC16: 0.654 | CD16: 25.66767 | CE16: 184.0425 | CG16: 152.25137 | CH16: 17.05689 | CK16: 17.3281 | CL16: 4.58666 | CO16: 17.20849 | CP16: 288.18 | CR16: 33.407 | CT16: 36.627
B17: 05:00 | E17: 34.52188 | F17: 12.326 | H17: 4.195 | L17: 26.8458 | M17: 15.8716 | N17: 13.62 | O17: 35.594 | R17: 50.305 | T17: 18.9575 | V17: 0.8 | X17: 150.84214 | Z17: 6.03116 | AC17: 10.77 | AE17: 4.243 | AF17: 4.7 | AH17: 2.2275 | AJ17: 5.03627 | AK17: 0 | AM17: 49.35217 | AN17: 122.40135 | AO17: 18.42354 | AP17: 2.1 | AQ17: 170.22295 | AS17: 37.13748 | AT17: 32.48219 | AV17: 194.43546 | AW17: 27.9892 | BA17: 2.4 | BC17: 71.84569 | BE17: 17.1 | BI17: 17.68519 | BK17: 5.44914 | BM17: 6.3261 | BN17: 52.419 | BO17: 1.65 | BP17: 141.71555 | BR17: 3.6424 | BS17: 130.16936 | BT17: 13.60793 | BV17: 36.515 | BW17: 4.37541 | BZ17: 89.55865 | CA17: 25.07353 | CC17: 0.656 | CD17: 25.19689 | CE17: 184.38091 | CG17: 154.74581 | CH17: 17.70088 | CK17: 17.0397 | CL17: 4.87405 | CO17: 16.51934 | CP17: 287.12 | CR17: 33.818 | CT17: 36.702
B18: 05:30 | E18: 34.50273 | F18: 11.18 | H18: 4.169 | L18: 27.3246 | M18: 15.4078 | N18: 12.59 | O18: 35.446 | R18: 50.468 | T18: 19.0807 | V18: 0.8 | X18: 84.80641 | Z18: 6.04217 | AC18: 10.64 | AE18: 4.197 | AF18: 5 | AH18: 1.181 | AJ18: 5.08865 | AK18: 0 | AM18: 49.53025 | AN18: 120.49467 | AO18: 17.50586 | AP18: 1.93 | AQ18: 172.99773 | AS18: 35.35603 | AT18: 32.17821 | AV18: 194.65463 | AW18: 27.6822 | BA18: 2.4 | BC18: 71.86001 | BE18: 17.1 | BI18: 17.65763 | BK18: 5.37781 | BM18: 3.21 | BN18: 53.045 | BO18: 1.69 | BP18: 140.08443 | BR18: 3.6667 | BS18: 130.99378 | BT18: 13.09389 | BV18: 36.4027 | BW18: 3.85894 | BZ18: 90.13628 | CA18: 25.08224 | CC18: 0.614 | CD18: 24.39177 | CE18: 184.45982 | CG18: 154.04634 | CH18: 17.76466 | CK18: 16.8216 | CL18: 4.63112 | CO18: 14.43532 | CP18: 286.79 | CR18: 36.642 | CT18: 36.549
B19: 06:00 | E19: 34.47131 | F19: 10.818 | H19: 4.103 | L19: 27.4996 | M19: 14.7154 | N19: 12.25 | O19: 34.44 | R19: 50.4 | T19: 15.7153 | V19: 0.8 | X19: 123.3425 | Z19: 6.14387 | AC19: 11.36 | AE19: 4.179 | AF19: 4.1 | AH19: 1.0796 | AJ19: 5.10208 | AK19: 0 | AM19: 49.79216 | AN19: 126.31536 | AO19: 14.22842 | AP19: 1.54 | AQ19: 170.0568 | AS19: 34.59016 | AT19: 32.23734 | AV19: 195.00534 | AW19: 25.9484 | BA19: 2.5 | BC19: 71.5752 | BE19: 17.1 | BI19: 17.7833 | BK19: 5.23813 | BM19: 3.362 | BN19: 51.073 | BO19: 1.55 | BP19: 140.14015 | BR19: 3.6401 | BS19: 129.92813 | BT19: 12.36701 | BV19: 35.8718 | BW19: 3.65085 | BZ19: 89.79863 | CA19: 25.07727 | CC19: 0.698 | CD19: 22.78194 | CE19: 183.21439 | CG19: 152.27081 | CH19: 17.9422 | CK19: 15.7381 | CL19: 4.79223 | CO19: 13.55714 | CP19: 289.49 | CR19: 40.682 | CT19: 35.257
... B55: 00:00 | E55: 23.87934 | F55: 13.412 | H55: 0 | L55: 27.9977 | M55: 14.1854 | N55: 12.99 | O55: 36.836 | R55: 51.772 | T55: 16.7208 | V55: 4.2 | X55: 121.06423 | Z55: 6.81425 | AC55: 15.93 | AE55: 0 | AF55: 4.9 | AH55: 5.257 | AJ55: 5.27586 | AK55: 0 | AM55: 51.76558 | AN55: 121.99495 | AO55: 27.81689 | AP55: 0.83 | AQ55: 172.80734 | AS55: 39.29264 | AT55: 31.44841 | AV55: 191.94745 | AW55: 33.7407 | BA55: 2.5 | BC55: 73.88961 | BE55: 18 | BI55: 16.70967 | BK55: 5.49222 | BM55: 6.261 | BN55: 55.222 | BO55: 1.95 | BP55: 87.27408 | BR55: 3.6357 | BS55: 128.77224 | BT55: 13.15286 | BV55: 36.4726 | BW55: 3.83695 | BZ55: 91.39805 | CA55: 24.93209 | CC55: 0.574 | CD55: 25.87818 | CE55: 169.56384 | CG55: 149.99553 | CH55: 17.54547 | CK55: 19.1817 | CL55: 4.9131 | CO55: 16.74932 | CP55: 284.72 | CR55: 38.756 | CT55: 24.449
B56: MWh | C56: 0 | D56: 0 | E56: 690.43421 | F56: 297.82 | G56: 0 | H56: 84.658 | I56: 0 | J56: 0 | K56: 0 | L56: 661.81955 | M56: 311.3564 | N56: 298.46 | O56: 843.111 | P56: 0 | Q56: 0 | R56: 1211.3115 | S56: 0 | T56: 366.73465 | U56: 0 | V56: 47.15 | W56: 0 | X56: 2417.7015 | Y56: 0 | Z56: 160.14747 | AA56: 0 | AB56: 0 | AC56: 330.8 | AD56: 0 | AE56: 104.79 | AF56: 84.35 | AG56: 0 | AH56: 44.443 | AI56: 0 | AJ56: 118.96792 | AK56: 0 | AL56: 0 | AM56: 1122.7409 | AN56: 2924.6628 | AO56: 502.85772 | AP56: 18.01 | AQ56: 4013.0786 | AR56: 0 | AS56: 878.93095 | AT56: 782.30339 | AU56: 0 | AV56: 4063.9643 | AW56: 726.9585 | AX56: 0 | AY56: 0 | AZ56: 0 | BA56: 57.665 | BB56: 0 | BC56: 1560.5949 | BD56: 0 | BE56: 417.35 | BF56: 0 | BG56: 0 | BH56: 0 | BI56: 419.66942 | BJ56: 0 | BK56: 130.38057 | BL56: 0 | BM56: 119.5667 | BN56: 966.7045 | BO56: 43.44 | BP56: 2605.223 | BQ56: 0 | BR56: 85.45875 | BS56: 3059.1409 | BT56: 290.35239 | BU56: 0 | BV56: 853.0144 | BW56: 93.445805 | BX56: 0 | BY56: 0 | BZ56: 2172.4001 | CA56: 510.45742 | CB56: 0 | CC56: 15.885 | CD56: 584.81174 | CE56: 4224.064 | CF56: 0 | CG56: 3628.1485 | CH56: 416.73674 | CI56: 0 | CJ56: 0 | CK56: 413.78615 | CL56: 111.97851 | CM56: 0 | CN56: 0 | CO56: 360.26117 | CP56: 6502.085 | CQ56: 0 | CR56: 886.0005 | CS56: 0 | CT56: 563.7785
B59: Nota :
B60: Información proporcionada por la empresas
C62: DATOS ESTIMADOS
C64: SIN DATOS

Sheet TIPO_RECURSO
B3: martes, 4 de Noviembre del 2025
B5: REPORTE POTENCIA GENERADA POR TIPO DE RECURSO
B6: HORA | C6: H. PASADA | D6: H. REGULACION | E6: GAS DE CAMISEA | F6: GAS DE MALACAS | G6: DIÉSEL | H6: RESIDUAL | I6: NAFTA+GAS DE REFINERIA | J6: FLEXIGAS+GAS DE REFINERIA | K6: BAGAZO | L6: BIOGÁS | M6: SOLAR | N6: EÓLICA | O6: TOTAL | T6: EMPRESA | U6: CENTRAL | V6: HIDROELECTRICA DE PASADA | W6: HIDROELECTRICA DE REGULACION
B7: 00:30 | C7: 1104.1 | D7: 2497.4 | E7: 2075.1 | F7: 48.3 | G7: 0 | I7: =+DESPACHO_EJECUTADO!FE11+DESPACHO_EJECUTADO!FF11 -> 63.6 | K7: 50.8 | L7: 3.9 | M7: 0 | N7: 532.5 | O7: =+SUM(C7:N7) -> 6375.7 | T7: ANDEAN POWER S.A.C. | U7: C.H.CARHUAC | V7: 373.4
B8: 01:00 | C8: 1090.3 | D8: 2437.7 | E8: 1998.5 | F8: 48.5 | G8: 0 | I8: =+DESPACHO_EJECUTADO!FE12+DESPACHO_EJECUTADO!FF12 -> 62.9 | K8: 53.8 | L8: 3.9 | M8: 0 | N8: 573.4 | O8: =+SUM(C8:N8) -> 6269 | T8: ASOCIACIÓN SANTA LUCIA DE CHACAS | U8: C.H. HUALLIN | V8: 57.1
B9: 01:30 | C9: 1107 | D9: 2423.4 | E9: 1962 | F9: 48.5 | G9: 0 | I9: =+DESPACHO_EJECUTADO!FE13+DESPACHO_EJECUTADO!FF13 -> 63.2 | K9: 54.1 | L9: 3.9 | M9: 0 | N9: 571.2 | O9: =+SUM(C9:N9) -> 6233.3 | T9: CELEPSA | U9: C.H. EL PLATANAL | W9: 2741.65
B10: 02:00 | C10: 1105.4 | D10: 2419.1 | E10: 1898.8 | F10: 48.5 | G10: 0 | I10: =+DESPACHO_EJECUTADO!FE14+DESPACHO_EJECUTADO!FF14 -> 63.5 | K10: 53.2 | L10: 3.9 | M10: 0 | N10: 559.8 | O10: =+SUM(C10:N10) -> 6152.2 | T10: CELEPSA RENOVABLES S.R.L. | U10: C.H. MARAÑON | V10: 451.2
B11: 02:30 | C11: 1102.2 | D11: 2375.5 | E11: 1837.5 | F11: 48.7 | G11: 0 | I11: =+DESPACHO_EJECUTADO!FE15+DESPACHO_EJECUTADO!FF15 -> 62.3 | K11: 54.1 | L11: 3.9 | M11: 0 | N11: 515.5 | O11: =+SUM(C11:N11) -> 5999.7 | T11: CHINANGO S.A.C. | U11: C.H. CHIMAY | W11: 3360.35
B12: 03:00 | C12: 1101.2 | D12: 2411.3 | E12: 1863.4 | F12: 48.6 | G12: 0 | I12: =+DESPACHO_EJECUTADO!FE16+DESPACHO_EJECUTADO!FF16 -> 61.3 | K12: 55.3 | L12: 3.9 | M12: 0 | N12: 533.6 | O12: =+SUM(C12:N12) -> 6078.6 | U12: C.H. YANANGO | V12: 694.2
B13: 03:30 | C13: 1093.1 | D13: 2278.2 | E13: 1880 | F13: 48.4 | G13: 0 | I13: =+DESPACHO_EJECUTADO!FE17+DESPACHO_EJECUTADO!FF17 -> 64.5 | K13: 54.5 | L13: 3.9 | M13: 0 | N13: 552.4 | O13: =+SUM(C13:N13) -> 5975 | T13: EGASA | U13: C.H. CHARCANI III | V13: 165.7
B14: 04:00 | C14: 1108.1 | D14: 2331.1 | E14: 1965 | F14: 48.3 | G14: 0 | I14: =+DESPACHO_EJECUTADO!FE18+DESPACHO_EJECUTADO!FF18 -> 62.6 | K14: 54.1 | L14: 3.9 | M14: 0 | N14: 531.9 | O14: =+SUM(C14:N14) -> 6105 | U14: C.H. CHARCANI IV | W14: 271.55
B15: 04:30 | C15: 1098.2 | D15: 2288.2 | E15: 1937.9 | F15: 48.2 | G15: 0 | I15: =+DESPACHO_EJECUTADO!FE19+DESPACHO_EJECUTADO!FF19 -> 63.2 | K15: 52.7 | L15: 3.7 | M15: 0 | N15: 513.3 | O15: =+SUM(C15:N15) -> 6005.4 | U15: C.H. CHARCANI V | W15: 1917.15
B16: 05:00 | C16: 1106.3 | D16: 2277 | E16: 2119 | F16: 48.5 | G16: 0 | I16: =+DESPACHO_EJECUTADO!FE20+DESPACHO_EJECUTADO!FF20 -> 63.6 | K16: 52.6 | L16: 2.4 | M16: 0.1 | N16: 516 | O16: =+SUM(C16:N16) -> 6185.5 | T16: EGEJUNIN | U16: C.H. HUASAHUASI I | V16: 281.55
B17: 05:30 | C17: 1111.1 | D17: 2367.2 | E17: 2134.5 | F17: 48.5 | G17: 0 | I17: =+DESPACHO_EJECUTADO!FE21+DESPACHO_EJECUTADO!FF21 -> 63.6 | K17: 54.2 | L17: 2.4 | M17: 16.8 | N17: 493.9 | O17: =+SUM(C17:N17) -> 6292.2 | U17: C.H. RUNATULLO II | V17: 225.5
B18: 06:00 | C18: 1139 | D18: 2289.4 | E18: 2012.2 | F18: 48.4 | G18: 0 | I18: =+DESPACHO_EJECUTADO!FE22+DESPACHO_EJECUTADO!FF22 -> 63.4 | K18: 54.7 | L18: 2.4 | M18: 115.4 | N18: 481.1 | O18: =+SUM(C18:N18) -> 6206 | U18: C.H. RUNATULLO III | V18: 355.55
B19: 06:30 | C19: 1115.9 | D19: 2130.7 | E19: 2080.8 | F19: 48.1 | G19: 0 | I19: =+DESPACHO_EJECUTADO!FE23+DESPACHO_EJECUTADO!FF23 -> 63 | K19: 55.2 | L19: 2.4 | M19: 251.1 | N19: 554.5 | O19: =+SUM(C19:N19) -> 6301.7 | U19: C.H. SANTA CRUZ I | V19: 174.35
B20: 07:00 | C20: 1122.2 | D20: 2179.5 | E20: 2137 | F20: 47.2 | G20: 0 | I20: =+DESPACHO_EJECUTADO!FE24+DESPACHO_EJECUTADO!FF24 -> 62.6 | K20: 49.9 | L20: 2.4 | M20: 257.4 | N20: 619.5 | O20: =+SUM(C20:N20) -> 6477.7 | T20: EGEMSA | U20: C.H. MACHUPICCHU | V20: 3689.8
B21: 07:30 | C21: 1130.4 | D21: 2183 | E21: 2114 | F21: 47.3 | G21: 0 | I21: =+DESPACHO_EJECUTADO!FE25+DESPACHO_EJECUTADO!FF25 -> 62.2 | K21: 54.3 | L21: 3.1 | M21: 347.8 | N21: 660 | O21: =+SUM(C21:N21) -> 6602.1 | T21: EGESUR | U21: C.H. ARICOTA I | W21: 178.55
B22: 08:00 | C22: 1127.8 | D22: 2283.5 | E22: 2128.5 | F22: 47.7 | G22: 0 | I22: =+DESPACHO_EJECUTADO!FE26+DESPACHO_EJECUTADO!FF26 -> 62.3 | K22: 52.3 | L22: 3.8 | M22: 445.2 | N22: 593.4 | O22: =+SUM(C22:N22) -> 6744.5 | U22: C.H. ARICOTA II | W22: 140.75
B23: 08:30 | C23: 1127.1 | D23: 2381.7 | E23: 2239.1 | F23: 47.4 | G23: 0 | I23: =+DESPACHO_EJECUTADO!FE27+DESPACHO_EJECUTADO!FF27 -> 62.7 | K23: 53.4 | L23: 3.8 | M23: 444.5 | N23: 546.6 | O23: =+SUM(C23:N23) -> 6906.3 | T23: ELECTRICA YANAPAMPA SAC | U23: C.H. YANAPAMPA | V23: 77.25
B24: 09:00 | C24: 1125.2 | D24: 2410.4 | E24: 2274 | F24: 47.6 | G24: 0 | I24: =+DESPACHO_EJECUTADO!FE28+DESPACHO_EJECUTADO!FF28 -> 62.3 | K24: 50.7 | L24: 3.8 | M24: 449.4 | N24: 524.2 | O24: =+SUM(C24:N24) -> 6947.6 | T24: ELECTROPERU | U24: C.H. MANTARO | W24: 14980.1
B25: 09:30 | C25: 1130.9 | D25: 2566.2 | E25: 2216 | F25: 47 | G25: 1.8 | I25: =+DESPACHO_EJECUTADO!FE29+DESPACHO_EJECUTADO!FF29 -> 62 | K25: 52.2 | L25: 3.8 | M25: 442.7 | N25: 598.4 | O25: =+SUM(C25:N25) -> 7121 | U25: C.H. RESTITUCION | V25: 5131.35
B26: 10:00 | C26: 1130.5 | D26: 2513.5 | E26: 2191.7 | F26: 46.8 | G26: 0 | I26: =+DESPACHO_EJECUTADO!FE30+DESPACHO_EJECUTADO!FF30 -> 62 | K26: 52.5 | L26: 3.6 | M26: 463.7 | N26: 628.1 | O26: =+SUM(C26:N26) -> 7092.4 | T26: EMPRESA DE GENERACION ELECTRICA CANCHAYLLO SAC | U26: C.H. CANCHAYLLO | V26: 68.7
B27: 10:30 | C27: 1113.1 | D27: 2659.6 | E27: 2299.7 | F27: 46.3 | G27: 0 | I27: =+DESPACHO_EJECUTADO!FE31+DESPACHO_EJECUTADO!FF31 -> 61.7 | K27: 36.8 | L27: 3.6 | M27: 471.2 | N27: 625.7 | O27: =+SUM(C27:N27) -> 7317.7 | T27: EMPRESA DE GENERACION ELECTRICA RIO BAÑOS S.A.C. | U27: C.H. RUCUY | V27: 372.15
B28: 11:00 | C28: 1122.4 | D28: 2692 | E28: 2357.3 | F28: 45.8 | G28: 0 | I28: =+DESPACHO_EJECUTADO!FE32+DESPACHO_EJECUTADO!FF32 -> 62.1 | K28: 34.7 | L28: 3.6 | M28: 461.9 | N28: 643.1 | O28: =+SUM(C28:N28) -> 7422.9 | T28: EMPRESA DE GENERACION HUALLAGA | U28: C.H. CHAGLLA | W28: 4484.55
B29: 11:30 | C29: 1122.5 | D29: 2812.8 | E29: 2308.3 | F29: 45.7 | G29: 0 | I29: =+DESPACHO_EJECUTADO!FE33+DESPACHO_EJECUTADO!FF33 -> 61.9 | K29: 36.4 | L29: 3.6 | M29: 448.1 | N29: 661.7 | O29: =+SUM(C29:N29) -> 7501 | U29: P.C.H. CHAGLLA | V29: 155.65
B30: 12:00 | C30: 1109.7 | D30: 2684.1 | E30: 2276.5 | F30: 45.9 | G30: 0 | I30: =+DESPACHO_EJECUTADO!FE34+DESPACHO_EJECUTADO!FF34 -> 61.2 | K30: 44.1 | L30: 3.6 | M30: 453.2 | N30: 688.8 | O30: =+SUM(C30:N30) -> 7367.1 | T30: EMPRESA DE GENERACION HUANZA | U30: C.H. HUANZA | W30: 1579.75
B31: 12:30 | C31: 1133.6 | D31: 2782 | E31: 2203.2 | F31: 46.2 | G31: 0 | I31: =+DESPACHO_EJECUTADO!FE35+DESPACHO_EJECUTADO!FF35 -> 61.5 | K31: 51.6 | L31: 3.6 | M31: 430.9 | N31: 680.1 | O31: =+SUM(C31:N31) -> 7392.7 | T31: EMPRESA ELECTRICA AGUA AZUL | U31: C.H. POTRERO | V31: 480
B32: 13:00 | C32: 1121.3 | D32: 2733.1 | E32: 2234.4 | F32: 46.5 | G32: 0 | I32: =+DESPACHO_EJECUTADO!FE36+DESPACHO_EJECUTADO!FF36 -> 61.8 | K32: 56.3 | L32: 3.6 | M32: 414.4 | N32: 674.9 | O32: =+SUM(C32:N32) -> 7346.3 | T32: EMPRESA ELECTRICA RIO DOBLE | U32: C.H. LAS PIZARRAS | V32: 451.35
B33: 13:30 | C33: 1117.7 | D33: 2676 | E33: 2110 | F33: 46.3 | G33: 0 | I33: =+DESPACHO_EJECUTADO!FE37+DESPACHO_EJECUTADO!FF37 -> 62 | K33: 57.3 | L33: 3.6 | M33: 457.7 | N33: 655.6 | O33: =+SUM(C33:N33) -> 7186.2 | T33: ENGIE ENERGIA PERU S.A.A. | U33: C.H. YUNCAN | W33: 2021.7
B34: 14:00 | C34: 1106.2 | D34: 2705.3 | E34: 2312.1 | F34: 0 | G34: 0 | I34: =+DESPACHO_EJECUTADO!FE38+DESPACHO_EJECUTADO!FF38 -> 62.8 | K34: 56.9 | L34: 3.6 | M34: 420.5 | N34: 672 | O34: =+SUM(C34:N34) -> 7339.4 | T34: GENERACIÓN ANDINA S.A.C. | U34: C.H. 8 DE AGOSTO | V34: 492.5
B35: 14:30 | C35: 1087.1 | D35: 2781.4 | E35: 2334.3 | F35: 0 | G35: 0 | I35: =+DESPACHO_EJECUTADO!FE39+DESPACHO_EJECUTADO!FF39 -> 63.9 | K35: 56.9 | L35: 3.6 | M35: 455.3 | N35: 664.3 | O35: =+SUM(C35:N35) -> 7446.8 | U35: C.H. EL CARMEN | V35: 181.9
B36: 15:00 | C36: 1078.3 | D36: 2921.7 | E36: 2202 | F36: 0 | G36: 0 | I36: =+DESPACHO_EJECUTADO!FE40+DESPACHO_EJECUTADO!FF40 -> 63 | K36: 59.5 | L36: 3.6 | M36: 375.1 | N36: 663.7 | O36: =+SUM(C36:N36) -> 7366.9 | T36: GENERADORA DE ENERGÍA DEL PERÚ | U36: C.H. ÁNGEL I | V36: 479.85
B37: 15:30 | C37: 1116.9 | D37: 2916.4 | E37: 2237.3 | F37: 0 | G37: 0 | I37: =+DESPACHO_EJECUTADO!FE41+DESPACHO_EJECUTADO!FF41 -> 62.8 | K37: 58.9 | L37: 3.6 | M37: 376.2 | N37: 701.9 | O37: =+SUM(C37:N37) -> 7474 | U37: C.H. ÁNGEL II | V37: 486.95
B38: 16:00 | C38: 1077.4 | D38: 2798.8 | E38: 2345.9 | F38: 0 | G38: 0 | I38: =+DESPACHO_EJECUTADO!FE42+DESPACHO_EJECUTADO!FF42 -> 55.3 | K38: 57.7 | L38: 3.6 | M38: 308.4 | N38: 715 | O38: =+SUM(C38:N38) -> 7362.1 | U38: C.H. ÁNGEL III | V38: 478.4
B39: 16:30 | C39: 1097.7 | D39: 2889.8 | E39: 2306.1 | F39: 0 | G39: 0 | I39: =+DESPACHO_EJECUTADO!FE43+DESPACHO_EJECUTADO!FF43 -> 63.9 | K39: 57.9 | L39: 3.6 | M39: 151.4 | N39: 708.3 | O39: =+SUM(C39:N39) -> 7278.7 | U39: C.H. LA JOYA | V39: 175.5
B40: 17:00 | C40: 1095.8 | D40: 2857.5 | E40: 2281 | F40: 0 | G40: 0 | I40: =+DESPACHO_EJECUTADO!FE44+DESPACHO_EJECUTADO!FF44 -> 62.4 | K40: 59 | L40: 3.6 | M40: 117.7 | N40: 686 | O40: =+SUM(C40:N40) -> 7163 | T40: HIDROCAÑETE S.A. | U40: C.H. IMPERIAL | V40: 81.75
B41: 17:30 | C41: 1105.6 | D41: 2880.2 | E41: 2338.5 | F41: 0 | G41: 0 | I41: =+DESPACHO_EJECUTADO!FE45+DESPACHO_EJECUTADO!FF45 -> 62.3 | K41: 57.2 | L41: 3.8 | M41: 16.5 | N41: 669.5 | O41: =+SUM(C41:N41) -> 7133.6 | T41: HIDROELECTRICA HUANCHOR S.A.C. | U41: C.H. HUANCHOR | V41: 404.4
B42: 18:00 | C42: 1107.9 | D42: 2846.4 | E42: 2169 | F42: 0 | G42: 44.6 | I42: =+DESPACHO_EJECUTADO!FE46+DESPACHO_EJECUTADO!FF46 -> 62.3 | K42: 59.9 | L42: 4.1 | M42: 0.2 | N42: 729 | O42: =+SUM(C42:N42) -> 7023.4 | T42: HUAURA POWER GROUP S.A. | U42: C.H. YARUCAYA | V42: 446.4
B43: 18:30 | C43: 1107.5 | D43: 2819.9 | E43: 2381.8 | F43: 0 | G43: 174.4 | I43: =+DESPACHO_EJECUTADO!FE47+DESPACHO_EJECUTADO!FF47 -> 63.56 | K43: 58.9 | L43: 3.8 | M43: 0 | N43: 709.3 | O43: =+SUM(C43:N43) -> 7319.16 | T43: HYDRO GLOBAL PERÚ S.A.C. | U43: CH SAN GABAN III | W43: 4879.05
B44: 19:00 | C44: 1111.3 | D44: 3001.2 | E44: 2304.1 | F44: 0 | G44: 174.3 | I44: =+DESPACHO_EJECUTADO!FE48+DESPACHO_EJECUTADO!FF48 -> 63.64 | K44: 57 | L44: 3.9 | M44: 0 | N44: 696.6 | O44: =+SUM(C44:N44) -> 7412.04 | T44: INLAND ENERGY SAC | U44: C.H. SANTA TERESA | V44: 2005.55
B45: 19:30 | C45: 1109.4 | D45: 2990.3 | E45: 2313.8 | F45: 0 | G45: 173.6 | I45: =+DESPACHO_EJECUTADO!FE49+DESPACHO_EJECUTADO!FF49 -> 63.55 | K45: 58.4 | L45: 3.9 | M45: 0 | N45: 686.7 | O45: =+SUM(C45:N45) -> 7399.65 | T45: INVERSIONES SHAQSHA S.A.C. | U45: C.H. PARIAC | V45: 87.7
B46: 20:00 | C46: 1113.9 | D46: 3019.9 | E46: 2303.4 | F46: 0 | G46: 174.7 | I46: =+DESPACHO_EJECUTADO!FE50+DESPACHO_EJECUTADO!FF50 -> 63.2 | K46: 60.2 | L46: 3.9 | M46: 0 | N46: 644.1 | O46: =+SUM(C46:N46) -> 7383.3 | T46: KALLPA GENERACION S.A. | U46: C.H. CERRO DEL AGUILA | W46: 7358.5
B47: 20:30 | C47: 1120.9 | D47: 3076.5 | E47: 2322.7 | F47: 0 | G47: 0 | I47: =+DESPACHO_EJECUTADO!FE51+DESPACHO_EJECUTADO!FF51 -> 62.97 | K47: 58.5 | L47: 3.9 | M47: 0 | N47: 624.2 | O47: =+SUM(C47:N47) -> 7269.67 | U47: M.C.H. CERRO DEL AGUILA | V47: 170.8
B48: 21:00 | C48: 1115.8 | D48: 3121.4 | E48: 2301.2 | F48: 0 | G48: 0 | I48: =+DESPACHO_EJECUTADO!FE52+DESPACHO_EJECUTADO!FF52 -> 62.01 | K48: 59.7 | L48: 3.9 | M48: 0 | N48: 604.3 | O48: =+SUM(C48:N48) -> 7268.31 | T48: LA VIRGEN | U48: C.H. LA VIRGEN | W48: 1199.85
B49: 21:30 | C49: 1108 | D49: 3137.7 | E49: 2287.7 | F49: 0 | G49: 0 | I49: =+DESPACHO_EJECUTADO!FE53+DESPACHO_EJECUTADO!FF53 -> 63.31 | K49: 61.5 | L49: 3.9 | M49: 0 | N49: 534.7 | O49: =+SUM(C49:N49) -> 7196.81 | T49: MAJA ENERGIA S.A.C. | U49: C.H. RONCADOR | V49: 70.65
B50: 22:00 | C50: 1102.2 | D50: 3058.5 | E50: 2259 | F50: 0 | G50: 0 | I50: =+DESPACHO_EJECUTADO!FE54+DESPACHO_EJECUTADO!FF54 -> 62.42 | K50: 42.4 | L50: 3.9 | M50: 0 | N50: 552.6 | O50: =+SUM(C50:N50) -> 7081.02 | T50: ORAZUL ENERGY PERÚ | U50: C.H. CAÑA BRAVA | V50: 2.35
B51: 22:30 | C51: 1101 | D51: 3048.1 | E51: 2238 | F51: 0 | G51: 0 | I51: =+DESPACHO_EJECUTADO!FE55+DESPACHO_EJECUTADO!FF55 -> 62.34 | K51: 40.8 | L51: 3.9 | M51: 0 | N51: 557.6 | O51: =+SUM(C51:N51) -> 7051.74 | U51: C.H. CAÑON DEL PATO | W51: 4588.85
B52: 23:00 | C52: 1112.9 | D52: 2788.5 | E52: 2234.2 | F52: 0 | G52: 0 | I52: =+DESPACHO_EJECUTADO!FE56+DESPACHO_EJECUTADO!FF56 -> 61.77 | K52: 43.1 | L52: 3.9 | M52: 0 | N52: 534.3 | O52: =+SUM(C52:N52) -> 6778.67 | U52: C.H. CARHUAQUERO | W52: 2161.5
B53: 23:30 | C53: 1104 | D53: 2661.1 | E53: 2167.3 | F53: 0 | G53: 0 | I53: =+DESPACHO_EJECUTADO!FE57+DESPACHO_EJECUTADO!FF57 -> 61.74 | K53: 40.8 | L53: 3.9 | M53: 0 | N53: 515.8 | O53: =+SUM(C53:N53) -> 6554.64 | T53: ORYGEN PERU S.A.A. | U53: C.H. CALLAHUANCA | W53: 1106.65
B54: 00:00 | C54: 1095.5 | D54: 2565.3 | E54: 2126.3 | F54: 0 | G54: 0 | I54: =+DESPACHO_EJECUTADO!FE58+DESPACHO_EJECUTADO!FF58 -> 60.32 | K54: 41.6 | L54: 3.9 | M54: 0 | N54: 446.6 | O54: =+SUM(C54:N54) -> 6339.52 | U54: C.H. HER 1 | V54: 14.4
B55: TOTAL MWh | C55: =SUM(C7:C54)/2 -> 26645.8 | D55: =SUM(D7:D54)/2 -> 63484.75 | E55: =SUM(E7:E54)/2 -> 52310.05 | F55: =SUM(F7:F54)/2 -> 641.6 | G55: =SUM(G7:G54)/2 -> 371.7 | H55: =SUM(H7:H54)/2 -> 0 | I55: =SUM(I7:I54)/2 -> 1499.265 | J55: =SUM(J7:J54)/2 -> 0 | ... O55: =SUM(O7:O54)/2 -> 165123.62 | U55: C.H. HUAMPANI | V55: 710.25
B56: % | C56: =+C55/$O$55 -> 0.1613688 | D56: =+D55/$O$55 -> 0.38446802 | E56: =+E55/$O$55 -> 0.31679327 | F56: =+F55/$O$55 -> 0.0038855738 | G56: =+G55/$O$55 -> 0.0022510408 | H56: =+H55/$O$55 -> 0 | I56: =+I55/$O$55 -> 0.0090796522 | J56: =+J55/$O$55 -> 0 | ... O56: =+O55/$O$55 -> 1 | U56: C.H. HUINCO | W56: 3330.6
U57: C.H. MATUCANA | W57: 1738.05
U58: C.H. MOYOPAMPA | V58: 1537.65
T59: PERUANA DE INVERSIONES EN ENERGIAS RENOVABLES S.A. | U59: C.H. MANTA I | V59: 478.3
T60: SAN GABAN | U60: C.H. SAN GABAN II | W60: 2653.55
U61: PCH TUPURI | V61: 26.75
T62: SINERSA | U62: C.H. CHANCAY | V62: 446.75
U63: C.H. POECHOS II | V63: 150.25
T64: STATKRAFT S.A | U64: C.H. ARCATA | V64: 48
U65: C.H. CAHUA | V65: 1047.55
U66: C.H. CHEVES | W66: 1668.7
U67: C.H. GALLITO CIEGO | W67: 424.55
U68: C.H. MALPASO | W68: 698.8
U69: C.H. OROYA | V69: 179.85
U70: C.H. PACHACHACA | V70: 145.9
U71: C.H. YAUPI | V71: 2594
T72: VARI ENERGIA S.A.C. | U72: C.H. ANASHIRONI | V72: 496.65
T73: TOTAL MWh | V73: 26645.8 | W73: 63484.75

Sheet GENERACION RER
B3: martes, 4 de Noviembre del 2025
B5: GENERACIÓN ELÉCTRICA DE LAS CENTRALES RER (MW)
B6: HORA | C6: AGRO INDUSTRIAL PARAMONGA S.A. | D6: AGROAURORA S.A.C. | E6: AGROINDUSTRIAS SAN JACINTO S.A.A. | F6: AGROLMOS SOCIEDAD ANONIMA - AGROLMOS S.A. | G6: ANDEAN POWER S.A.C. | H6: ASOCIACIÓN SANTA LUCIA DE CHACAS | I6: ATRIA ENERGIA S.A.C. | J6: BIOENERGIA DEL CHIRA S.A. | K6: COLCA SOLAR S.A.C. | L6: EGEJUNIN | Q6: ELECTRICA YANAPAMPA SAC | R6: EMPRESA DE GENERACION ELECTRICA CANCHAYLLO SAC | S6: EMPRESA DE GENERACION ELECTRICA RIO BAÑOS S.A.C. | T6: EMPRESA DE GENERACION ELECTRICA SANTA ANA S.A.C. | U6: EMPRESA ELECTRICA AGUA AZUL | V6: EMPRESA ELECTRICA RIO DOBLE | W6: ENERGÍA EÓLICA S.A. | Y6: ENERGIA RENOVABLE DEL SUR S.A. | Z6: ENGIE ENERGIA PERU S.A.A. | AE6: GENERACIÓN ANDINA S.A.C. | AG6: GENERADORA DE ENERGÍA DEL PERÚ | AK6: GR CORTARRAMA SOCIEDAD ANONIMA CERRADA | AL6: GR PAINO SOCIEDAD ANONIMA CERRADA | AM6: GR TARUCA SOCIEDAD ANONIMA CERRADA | AN6: HIDROCAÑETE S.A. | AO6: HUAURA POWER GROUP S.A. | AP6: HYDRO PATAPO S.A.C. | AQ6: KONDU SAC | AR6: MAJA ENERGIA S.A.C. | AS6: MAJES ARCUS S.A.C. | AT6: MOQUEGUA FV S.A.C. | AU6: ORAZUL ENERGY PERÚ | AW6: ORYGEN PERU S.A.A. | BB6: PANAMERICANA SOLAR SAC. | BC6: PARQUE EOLICO MARCONA S.A.C. | BD6: PARQUE EOLICO TRES HERMANAS S.A.C. | BE6: PERUANA DE INVERSIONES EN ENERGIAS RENOVABLES S.A. | BF6: PETRAMAS | BJ6: REPARTICIÓN ARCUS S.A.C. | BK6: SAN GABAN | BL6: SINERSA | BN6: TACNA SOLAR SAC. | BO6: VARI ENERGIA S.A.C. | BP6: TOTAL RER
C7: C.T. PARAMONGA | D7: C.T. MAPLE | E7: C.T SAN JACINTO | F7: C.T. AGROLMOS | G7: C.H. CARHUAC | H7: C.H. HUALLIN | I7: C.H. PURMACANA | J7: C.T. CAÑA BRAVA | L7: C.H. HUASAHUASI I | M7: C.H. HUASAHUASI II | N7: C.H. RUNATULLO II | O7: C.H. RUNATULLO III | P7: C.H. STA CRUZ I y II | Q7: C.H. YANAPAMPA | R7: C.H. CANCHAYLLO | S7: C.H. RUCUY | T7: C.H. RENOVANDES H1 | U7: C.H. POTRERO | V7: C.H. LAS PIZARRAS | AE7: C.H. 8 DE AGOSTO | AF7: C.H. EL CARMEN | AG7: C.H. ANGEL I | AH7: C.H. ANGEL II | AI7: C.H. ANGEL III | AJ7: C.H. LA JOYA | AN7: C.H. NUEVAIMPERIAL | AO7: C.H. YARUCAYA | AP7: MCH PATAPO | AR7: C.H. RONCADOR | AU7: C.H. CANA BRAVA | AV7: C.H. CARHUAQUERO4 | BA7: C.H. HER 1 | BE7: C.H. MANTA | BF7: C.T. HUAYCOLORO | BG7: C.T. LA GRINGA V | BH7: CTB CALLAO | BI7: CTB. DONA CATALINA | BK7: C.H. TUPURI | BL7: C.H. CHANCAY | BM7: C.H. POECHOS2 | BO7: C.H. ANASHIRONI | BP7: MW
B8: 0:30 | C8: 14.9 | D8: 15.9 | F8: 11 | G8: 10.5 | H8: 2.4 | J8: 9 | L8: 13.7 | N8: 9.8 | O8: 13.9 | P8: 6.8 | Q8: 3.1 | R8: 2.8 | S8: 16.6 | U8: 20 | V8: 18.9 | W8: 21.4 | X8: 44.5 | Y8: 78.3 | Z8: 76.5 | AA8: 75.1 | AC8: 7.1 | AD8: 7.8 | AE8: 20.7 | AF8: 7.7 | AG8: 18.4 | AH8: 19.8 | AI8: 19.7 | AJ8: 7.4 | AN8: 3.4 | AO8: 18.6 | AR8: 2.5 | AU8: 4.7 | AW8: 59.4 | AY8: 56.7 | BA8: 0.6 | BC8: 28.9 | BD8: 76.8 | BE8: 20 | BF8: 1.1 | BG8: 1 | BI8: 1.8 | BK8: 1 | BL8: 18.9 | BM8: 6.4 | BO8: 20.7 | BP8: 896.2
B9: 1:00 | C9: 15 | D9: 19.2 | F9: 11 | G9: 10.9 | H9: 2.4 | J9: 8.6 | L9: 13.7 | N9: 10.3 | O9: 14 | P9: 6.8 | Q9: 3.1 | R9: 3 | S9: 18.9 | U9: 20 | V9: 18.9 | W9: 26.8 | X9: 55 | Y9: 75.6 | Z9: 73.8 | AA9: 77.8 | AC9: 6.7 | AD9: 8.7 | AE9: 20.7 | AF9: 7.7 | AG9: 19.7 | AH9: 19.8 | AI9: 19.7 | AJ9: 7.1 | AN9: 3.4 | AO9: 18.6 | AR9: 2.5 | AW9: 73.9 | AY9: 69.7 | BA9: 0.6 | BC9: 28 | BD9: 77.4 | BE9: 20 | BF9: 1.1 | BG9: 1 | BI9: 1.8 | BK9: 1 | BL9: 19.7 | BM9: 6.4 | BO9: 20.7 | BP9: 940.7
B10: 1:30 | C10: 15 | D10: 19.3 | F10: 11 | G10: 11 | H10: 2.3 | J10: 8.8 | L10: 12.8 | N10: 10.5 | O10: 14.1 | P10: 6.8 | Q10: 3 | R10: 2.9 | S10: 17.3 | U10: 20 | V10: 18.9 | W10: 27.2 | X10: 44.5 | Y10: 74.7 | Z10: 73.8 | AA10: 77 | AC10: 7.6 | AD10: 7.6 | AE10: 20.6 | AF10: 7.7 | AG10: 19.7 | AH10: 20.4 | AI10: 19.7 | AJ10: 7.3 | AN10: 3.4 | AO10: 18.6 | AR10: 2.5 | AW10: 80.5 | AY10: 73 | BA10: 0.6 | BC10: 28.7 | BD10: 76.6 | BE10: 20 | BF10: 1.1 | BG10: 1 | BI10: 1.8 | BK10: 1 | BL10: 19.2 | BM10: 6.4 | BO10: 20.7 | BP10: 936.6
B11: 2:00 | C11: 15 | D11: 19.3 | F11: 10.1 | G11: 10.8 | H11: 2.3 | J11: 8.8 | L11: 12.8 | N11: 10.5 | O11: 14.1 | P11: 6.8 | Q11: 3 | R11: 3 | S11: 16 | U11: 20 | V11: 19 | W11: 27.6 | X11: 35.3 | Y11: 78.8 | Z11: 74 | AA11: 76.6 | AC11: 8.6 | AD11: 8.1 | AE11: 20.3 | AF11: 7.7 | AG11: 19.7 | AH11: 20.4 | AI11: 19.7 | AJ11: 7.5 | AN11: 3.4 | AO11: 18.6 | AR11: 2.3 | AW11: 81.7 | AY11: 65.9 | BA11: 0.6 | BC11: 26.5 | BD11: 76.7 | BE11: 20 | BF11: 1.1 | BG11: 1 | BI11: 1.8 | BK11: 1 | BL11: 18.7 | BM11: 6.4 | BO11: 20.7 | BP11: 922.2
B12: 2:30 | C12: 15.3 | D12: 18.9 | F12: 11.1 | G12: 10.9 | H12: 2.3 | J12: 8.8 | L12: 12 | N12: 10.2 | O12: 13.8 | P12: 6.8 | Q12: 3.2 | R12: 3 | S12: 15.8 | U12: 20 | V12: 18.9 | W12: 27.3 | X12: 26.6 | Y12: 82.1 | Z12: 71.6 | AA12: 79 | AC12: 6.6 | AD12: 8.9 | AE12: 20.5 | AF12: 7.7 | AG12: 19.7 | AH12: 20.4 | AI12: 20 | AJ12: 7.4 | AN12: 3.4 | AO12: 18.6 | AR12: 2.2 | AW12: 58.2 | AY12: 50.9 | BA12: 0.6 | BC12: 28.3 | BD12: 76 | BE12: 20 | BF12: 1.1 | BG12: 1 | BI12: 1.8 | BK12: 1 | BL12: 18.7 | BM12: 6.4 | BO12: 20.7 | BP12: 877.7
B13: 3:00 | C13: 16 | D13: 19.4 | F13: 11.1 | G13: 10.9 | H13: 2.2 | J13: 8.8 | L13: 12 | N13: 10.1 | O13: 13.9 | P13: 6.8 | Q13: 3.2 | R13: 3 | S13: 16 | U13: 20 | V13: 19 | W13: 26.9 | X13: 24 | Y13: 79.8 | Z13: 75.5 | AA13: 75.9 | AC13: 6.9 | AD13: 8.6 | AE13: 20.6 | AF13: 7.6 | AG13: 20.4 | AH13: 20.4 | AI13: 20 | AJ13: 7.5 | AN13: 3.4 | AO13: 18.6 | AR13: 2.3 | AW13: 77.7 | AY13: 56.5 | BA13: 0.6 | BC13: 27.1 | BD13: 74.7 | BE13: 20 | BF13: 1.1 | BG13: 1 | BI13: 1.8 | BK13: 1 | BL13: 18.8 | BM13: 6.4 | BO13: 20.6 | BP13: 898.1
B14: 3:30 | C14: 16 | D14: 19.4 | F14: 11.1 | G14: 10.9 | H14: 2.2 | J14: 8 | L14: 12.1 | N14: 10.3 | O14: 13.7 | P14: 6.8 | Q14: 3.2 | R14: 3 | S14: 16 | U14: 20 | V14: 18.9 | W14: 28 | X14: 28 | Y14: 90.1 | Z14: 72.7 | AA14: 75.6 | AC14: 8.5 | AD14: 9.7 | AE14: 20.6 | AF14: 7.6 | AG14: 20.4 | AH14: 20.4 | AI14: 20 | AJ14: 7.5 | AN14: 3.4 | AO14: 18.6 | AR14: 2.4 | AW14: 71.9 | AY14: 64 | BA14: 0.6 | BC14: 27.5 | BD14: 76.4 | BE14: 20.1 | BF14: 1.1 | BG14: 1 | BI14: 1.8 | BK14: 1 | BL14: 18.8 | BM14: 6.4 | BO14: 20.7 | BP14: 916.4
B15: 4:00 | C15: 15.6 | D15: 19.4 | F15: 11 | G15: 11 | H15: 2.2 | J15: 8.1 | L15: 12.1 | N15: 10.8 | O15: 14 | P15: 6.8 | Q15: 3.3 | R15: 2.8 | S15: 16 | U15: 20 | V15: 19.1 | W15: 28.4 | X15: 26.8 | Y15: 85.3 | Z15: 71.2 | AA15: 82.5 | AC15: 6.6 | AD15: 6 | AE15: 20.3 | AF15: 7.6 | AG15: 20.4 | AH15: 20.4 | AI15: 20 | AJ15: 7.2 | AN15: 3.4 | AO15: 18.6 | AR15: 2.5 | AW15: 58.5 | AY15: 58.2 | BA15: 0.6 | BC15: 30 | BD15: 78.4 | BE15: 20 | BF15: 1.1 | BG15: 1 | BI15: 1.8 | BK15: 1 | BL15: 18.8 | BM15: 6.4 | BO15: 20.7 | BP15: 895.9
B16: 4:30 | C16: 15.8 | D16: 18.5 | F16: 11.1 | G16: 14 | H16: 2.2 | J16: 7.3 | L16: 12.2 | N16: 11.1 | O16: 13.9 | P16: 6.8 | Q16: 3.3 | R16: 2.8 | S16: 15.8 | U16: 20 | V16: 19.1 | W16: 27.7 | X16: 26.3 | Y16: 90.1 | Z16: 67.7 | AA16: 89.7 | AC16: 5.1 | AD16: 3.8 | AE16: 20.2 | AF16: 7.6 | AG16: 20.4 | AH16: 20.4 | AI16: 20 | AJ16: 6.8 | AN16: 3.4 | AO16: 18.6 | AR16: 2.3 | AW16: 51 | AY16: 47.1 | BA16: 0.6 | BC16: 29.1 | BD16: 75.7 | BE16: 20 | BF16: 0.9 | BG16: 1 | BI16: 1.8 | BK16: 1 | BL16: 18.7 | BM16: 6.4 | BO16: 20.6 | BP16: 877.9
B17: 5:00 | C17: 16 | D17: 18 | F17: 11.1 | G17: 12.1 | H17: 2.2 | J17: 7.5 | L17: 12.4 | N17: 11.9 | O17: 14.1 | P17: 6.8 | Q17: 3.4 | R17: 2.7 | S17: 15.8 | U17: 20 | V17: 19.1 | W17: 26.8 | X17: 28.9 | Y17: 88.3 | Z17: 73.7 | AA17: 82.3 | AC17: 4.8 | AD17: 6 | AE17: 20 | AF17: 7.6 | AG17: 20.4 | AH17: 20.4 | AI17: 20 | AJ17: 7.2 | AN17: 3.4 | AO17: 18.6 | AR17: 2.4 | AT17: 0.1 | AW17: 58.8 | AY17: 50.6 | BA17: 0.6 | BC17: 27.5 | BD17: 68.3 | BE17: 20 | BF17: 0.7 | BG17: 0.7 | BI17: 1 | BK17: 1 | BL17: 18.7 | BM17: 6.4 | BO17: 20.7 | BP17: 879
B18: 5:30 | C18: 16 | D18: 19.1 | F18: 11 | G18: 10.1 | H18: 2.2 | J18: 8.1 | L18: 12.4 | N18: 12 | O18: 14 | P18: 6.8 | Q18: 3.3 | R18: 2.8 | S18: 15.8 | U18: 20 | V18: 18.9 | W18: 24.8 | X18: 33.2 | Y18: 92.8 | Z18: 76.3 | AA18: 74 | AB18: 1 | AC18: 5.7 | AD18: 6.4 | AE18: 19.7 | AF18: 7.5 | AG18: 20.4 | AH18: 20.4 | AI18: 20 | AJ18: 7.3 | AK18: 3.5 | AN18: 3.4 | AO18: 18.6 | AR18: 2.4 | AT18: 0.5 | AW18: 49.7 | AX18: 5.8 | AY18: 42.6 | AZ18: 5 | BA18: 0.6 | BB18: 0.9 | BC18: 29.1 | BD18: 59.3 | BE18: 20 | BF18: 0.7 | BG18: 0.7 | BI18: 1 | BK18: 1 | BL18: 18.7 | BM18: 6.4 | BN18: 0.1 | BO18: 20.7 | BP18: 872.7
B19: 6:00 | C19: 16.1 | D19: 19.4 | F19: 11 | G19: 9.9 | H19: 2.1 | J19: 8.2 | L19: 12.4 | N19: 11.8 | O19: 14.2 | P19: 6.8 | Q19: 3.3 | R19: 3 | S19: 15.5 | U19: 20 | V19: 18.9 | W19: 25.8 | X19: 24.6 | Y19: 97.1 | Z19: 58.4 | AA19: 69.3 | AB19: 6.2 | AC19: 5.5 | AD19: 4.6 | AE19: 19.7 | AF19: 7.5 | AG19: 20.4 | AH19: 20.4 | AI19: 20 | AJ19: 7.3 | AK19: 26.4 | AN19: 3.4 | AO19: 18.6 | AR19: 2.4 | AS19: 1 | AT19: 1.2 | AW19: 50.6 | AX19: 42.1 | AY19: 41.1 | AZ19: 35.4 | BA19: 0.6 | BB19: 1.3 | BC19: 28.8 | BD19: 75.3 | BE19: 20 | BF19: 0.7 | BG19: 0.7 | BI19: 1 | BJ19: 1 | BK19: 1.1 | BL19: 18.4 | BM19: 6.4 | BN19: 0.8 | BO19: 20.9 | BP19: 958.6
B20: 6:30 | C20: 16 | D20: 19.4 | F20: 11.1 | G20: 10 | H20: 2.1 | J20: 8.7 | K20: 0.1 | L20: 12.4 | N20: 10.3 | O20: 14.6 | P20: 6.8 | Q20: 3.4 | R20: 2.8 | S20: 15.6 | U20: 20 | V20: 18.9 | W20: 19.5 | X20: 20.3 | Y20: 102.9 | Z20: 74.7 | AA20: 75.6 | AB20: 13.7 | AC20: 6.6 | AD20: 8.9 | AE20: 19.5 | AF20: 7.4 | AG20: 20.4 | AH20: 20.4 | AI20: 20 | AJ20: 7.1 | AK20: 39.1 | AN20: 3.4 | AO20: 18.6 | AR20: 2.6 | AS20: 2.4 | AT20: 2.6 | AW20: 73.7 | AX20: 102.6 | AY20: 57.2 | AZ20: 83.9 | BA20: 0.6 | BB20: 2.8 | BC20: 30.6 | BD20: 84.5 | BE20: 20 | BF20: 0.7 | BG20: 0.7 | BI20: 1 | BJ20: 2.2 | BK20: 1.1 | BL20: 18.6 | BM20: 6.3 | BN20: 1.7 | BO20: 20.6 | BP20: 1166.7
B21: 7:00 | C21: 16 | D21: 19.4 | F21: 6.5 | G21: 10 | H21: 2.1 | J21: 8 | K21: 0.1 | L21: 12.4 | N21: 10.8 | O21: 14.8 | P21: 6.8 | Q21: 3.4 | R21: 2.8 | S21: 15.8 | U21: 20 | V21: 18.8 | W21: 18.7 | X21: 19.1 | Y21: 111.3 | Z21: 75.2 | AA21: 73.9 | AB21: 18.3 | AC21: 8 | AD21: 8.9 | AE21: 19.4 | AF21: 7.5 | AG21: 20.4 | AH21: 20.4 | AI21: 20 | AJ21: 7.2 | AK21: 71.7 | AN21: 3.4 | AO21: 18.6 | AR21: 2.6 | AS21: 5.3 | AT21: 4.5 | AW21: 108.2 | AX21: 78.7 | AY21: 78.3 | AZ21: 61.1 | BA21: 0.6 | BB21: 8.9 | BC21: 30.2 | BD21: 87.7 | BE21: 20 | BF21: 0.6 | BG21: 0.6 | BI21: 1.2 | BJ21: 5.1 | BK21: 1.2 | BL21: 18.7 | BM21: 6.4 | BN21: 3.7 | BO21: 20.6 | BP21: 1233.9
B22: 7:30 | C22: 15.5 | D22: 19.4 | F22: 10.8 | G22: 15.6 | H22: 2.1 | J22: 8.6 | K22: 0.2 | L22: 12.4 | N22: 10.1 | O22: 15 | P22: 6.8 | Q22: 3.4 | R22: 2.8 | S22: 15.8 | U22: 20 | V22: 18.9 | W22: 17.1 | X22: 25.1 | Y22: 117.5 | Z22: 74.6 | AA22: 73.2 | AB22: 25 | AC22: 9.4 | AD22: 9.2 | AE22: 19.1 | AF22: 7.5 | AG22: 20.4 | AH22: 20.4 | AI22: 20 | AJ22: 7 | AK22: 57.5 | AN22: 3.4 | AO22: 18.6 | AQ22: 0.1 | AR22: 2.6 | AS22: 7.9 | AT22: 12.2 | AW22: 128.9 | AX22: 123.1 | AY22: 86.9 | AZ22: 88.8 | BA22: 0.6 | BB22: 18 | BC22: 30.7 | BD22: 87.4 | BE22: 20.2 | BF22: 0.7 | BG22: 0.8 | BI22: 1.6 | BJ22: 7.7 | BK22: 1.2 | BL22: 18.6 | BM22: 6.4 | BN22: 7.3 | BO22: 20.8 | BP22: 1374.9
B23: 8:00 | C23: 15.6 | D23: 18.8 | F23: 11 | G23: 17.7 | H23: 2.1 | J23: 6.9 | K23: 0.3 | L23: 12.4 | N23: 10.1 | O23: 15 | P23: 6.8 | Q23: 3.3 | R23: 2.9 | S23: 16.1 | U23: 20 | V23: 18.8 | W23: 17.3 | X23: 23 | Y23: 116 | AA23: 108.9 | AB23: 31.2 | AD23: 9.9 | AE23: 17.7 | AF23: 7.5 | AG23: 20.4 | AH23: 20.4 | AI23: 20 | AJ23: 7 | AK23: 80.9 | AN23: 3.4 | AO23: 18.6 | AQ23: 0.1 | AR23: 2.6 | AS23: 9.7 | AT23: 15.8 | AW23: 110.6 | AX23: 149.9 | AY23: 88.7 | AZ23: 110.4 | BA23: 0.6 | BB23: 19.1 | BC23: 30.8 | BD23: 88.2 | BE23: 20 | BF23: 1 | BG23: 1 | BI23: 1.8 | BJ23: 10.4 | BK23: 1.2 | BL23: 18.8 | BM23: 6.4 | BN23: 17.4 | BO23: 20.6 | BP23: 1405.1
B24: 8:30 | C24: 15 | D24: 18.5 | F24: 11 | G24: 17.6 | H24: 2.1 | J24: 8.9 | K24: 0.5 | L24: 12.1 | N24: 10.1 | O24: 15 | P24: 6.8 | Q24: 3.4 | R24: 3 | S24: 16 | U24: 20 | V24: 18.8 | W24: 18.8 | X24: 22 | Y24: 117.7 | AA24: 96.6 | AB24: 35.2 | AD24: 10.1 | AE24: 17.5 | AF24: 7.5 | AG24: 20.4 | AH24: 20.4 | AI24: 20 | AJ24: 7.1 | AK24: 65.1 | AN24: 3.4 | AO24: 18.6 | AQ24: 0.2 | AR24: 2.9 | AS24: 11.8 | AT24: 15.5 | AW24: 87.4 | AX24: 153.1 | AY24: 75.2 | AZ24: 113.2 | BA24: 0.6 | BB24: 18.8 | BC24: 30.7 | BD24: 88.1 | BE24: 20 | BF24: 1 | BG24: 1 | BI24: 1.8 | BJ24: 12.8 | BK24: 1.2 | BL24: 18.7 | BM24: 6.4 | BN24: 18.3 | BO24: 20.6 | BP24: 1358.5
B25: 9:00 | C25: 15 | D25: 16.5 | F25: 11 | G25: 16.6 | H25: 2 | J25: 8.2 | K25: 0.5 | L25: 11.8 | N25: 9.9 | O25: 14.9 | P25: 6.8 | Q25: 3.3 | R25: 2.9 | S25: 15.6 | U25: 20 | V25: 18.7 | W25: 14.5 | X25: 26.2 | Y25: 120.7 | AA25: 81.8 | AB25: 35.2 | AD25: 7.7 | AE25: 20.9 | AF25: 7.4 | AG25: 20.4 | AH25: 20.4 | AI25: 20 | AJ25: 7.1 | AK25: 80.9 | AN25: 3.4 | AO25: 18.6 | AQ25: 0.4 | AR25: 2.9 | AS25: 14.5 | AT25: 15.7 | AW25: 88.3 | AX25: 148.6 | AY25: 67.1 | AZ25: 101.3 | BA25: 0.6 | BB25: 19 | BC25: 30.5 | BD25: 87.4 | BE25: 20 | BF25: 1 | BG25: 1 | BI25: 1.8 | BJ25: 14.4 | BK25: 1.2 | BL25: 18.7 | BM25: 6.4 | BN25: 18.9 | BO25: 20.8 | BP25: 1339.4
B26: 9:30 | C26: 15.2 | D26: 16.7 | F26: 11 | G26: 16.8 | H26: 2 | J26: 9.3 | K26: 0.4 | L26: 11.4 | N26: 10.3 | O26: 15 | P26: 6.8 | Q26: 3.3 | R26: 2.9 | S26: 15 | U26: 20 | V26: 18.7 | W26: 8.7 | X26: 51.1 | Y26: 120.6 | AA26: 65 | AB26: 35.6 | AD26: 7.4 | AE26: 20.9 | AF26: 7.4 | AG26: 20.4 | AH26: 20.4 | AI26: 20 | AJ26: 7.1 | AK26: 80.8 | AN26: 3.4 | AO26: 18.6 | AQ26: 0.2 | AR26: 2.9 | AS26: 14.6 | AT26: 15.8 | AW26: 138.8 | AX26: 141.2 | AY26: 90.8 | AZ26: 100.7 | BA26: 0.6 | BB26: 19.2 | BC26: 30.7 | BD26: 85.3 | BE26: 20 | BF26: 1 | BG26: 1 | BI26: 1.8 | BJ26: 15.1 | BK26: 1.2 | BL26: 18.5 | BM26: 6.4 | BN26: 19.1 | BO26: 20.7 | BP26: 1407.8
B27: 10:00 | C27: 15.2 | D27: 16.7 | F27: 11 | G27: 17.3 | H27: 2 | J27: 9.6 | K27: 0.8 | L27: 11.5 | N27: 10.1 | O27: 15 | P27: 6.8 | Q27: 3.2 | R27: 2.8 | S27: 15.2 | U27: 20 | V27: 18.7 | W27: 3 | X27: 75.9 | Y27: 120.8 | AA27: 71.6 | AB27: 29.7 | AD27: 8.6 | AE27: 20.9 | AF27: 7.5 | AG27: 20.4 | AH27: 20.4 | AI27: 20 | AJ27: 7 | AK27: 80.8 | AN27: 3.4 | AO27: 18.6 | AQ27: 0.2 | AR27: 2.8 | AS27: 16.7 | AT27: 15.8 | AW27: 136.4 | AX27: 152 | AY27: 95.6 | AZ27: 113.1 | BA27: 0.6 | BB27: 19.2 | BC27: 30.7 | BD27: 85.5 | BE27: 20.2 | BF27: 1 | BG27: 0.9 | BI27: 1.7 | BJ27: 17.1 | BK27: 1.2 | BL27: 18.5 | BM27: 6.4 | BN27: 18.3 | BO27: 20.7 | BP27: 1459.1
B28: 10:30 | D28: 16.7 | F28: 11 | G28: 17.5 | H28: 2 | J28: 9.1 | K28: 1.1 | L28: 11.5 | N28: 10.3 | O28: 14.9 | P28: 6.8 | Q28: 3.2 | R28: 3 | S28: 15.6 | U28: 20 | V28: 18.7 | W28: 1.4 | X28: 78.1 | Y28: 120.7 | AA28: 86.6 | AB28: 38.2 | AD28: 7.6 | AE28: 20.9 | AF28: 7.5 | AG28: 20.4 | AH28: 20.4 | AI28: 20 | AJ28: 7 | AK28: 80.8 | AN28: 3.4 | AO28: 18.6 | AQ28: 0.3 | AR28: 2.8 | AS28: 14.5 | AT28: 16.1 | AW28: 124.6 | AX28: 152.1 | AY28: 90.5 | AZ28: 114.7 | BA28: 0.6 | BB28: 19.3 | BC28: 30.5 | BD28: 85.7 | BE28: 20 | BF28: 1 | BG28: 0.9 | BI28: 1.7 | BJ28: 16.1 | BK28: 1.2 | BL28: 18.7 | BM28: 6.2 | BN28: 18 | BO28: 20.7 | BP28: 1449.2
B29: 11:00 | D29: 14.6 | F29: 11 | G29: 17.6 | H29: 2 | J29: 9.1 | K29: 1.1 | L29: 11.3 | N29: 10.5 | O29: 15 | P29: 6.8 | Q29: 3.3 | R29: 3 | S29: 15.4 | U29: 20 | V29: 18.7 | W29: 0.6 | X29: 78.2 | Y29: 120 | AA29: 90.2 | AB29: 28 | AD29: 10.1 | AE29: 20.9 | AF29: 7.6 | AG29: 20.4 | AH29: 20.4 | AI29: 20 | AJ29: 7 | AK29: 79.3 | AN29: 3.4 | AO29: 18.6 | AQ29: 0.4 | AR29: 3.1 | AS29: 19 | AT29: 16.1 | AW29: 135.8 | AX29: 152.1 | AY29: 93.1 | AZ29: 114.3 | BA29: 0.6 | BB29: 19.4 | BC29: 30.3 | BD29: 84.8 | BE29: 20 | BF29: 1 | BG29: 0.9 | BI29: 1.7 | BJ29: 13.6 | BK29: 1.2 | BL29: 18.5 | BM29: 6.2 | BN29: 18.6 | BO29: 20.8 | BP29: 1455.6
B30: 11:30 | D30: 16.8 | F30: 11 | G30: 17.7 | H30: 2 | J30: 8.6 | K30: 1 | L30: 11.2 | N30: 10.7 | O30: 14.9 | P30: 6.8 | Q30: 3.3 | R30: 2.9 | S30: 15 | U30: 20 | V30: 18.7 | W30: 1.1 | X30: 78.2 | Y30: 119.2 | AA30: 91.9 | AB30: 28 | AD30: 10.3 | AE30: 20.9 | AF30: 7.6 | AG30: 20.4 | AH30: 20.4 | AI30: 20 | AJ30: 7.3 | AK30: 73.8 | AN30: 3.4 | AO30: 18.6 | AQ30: 0.3 | AR30: 3.1 | AS30: 17.4 | AT30: 14.5 | AW30: 148.4 | AX30: 151.8 | AY30: 97.3 | AZ30: 109.4 | BA30: 0.6 | BB30: 17.6 | BC30: 30.4 | BD30: 84.9 | BE30: 20 | BF30: 1 | BG30: 0.9 | BI30: 1.7 | BJ30: 14.7 | BK30: 1.2 | BL30: 18.5 | BM30: 6.2 | BN30: 19.6 | BO30: 20.7 | BP30: 1461.9
B31: 12:00 | C31: 7 | D31: 16.8 | F31: 11 | G31: 17.6 | H31: 2 | J31: 9.3 | K31: 1 | L31: 11.2 | N31: 10.4 | O31: 14.6 | P31: 6.8 | Q31: 3.2 | R31: 2.8 | S31: 15 | U31: 20 | V31: 18.7 | W31: 2 | X31: 78.2 | Y31: 123.4 | AA31: 94.1 | AB31: 33.2 | AD31: 10.2 | AE31: 20.9 | AF31: 7.6 | AG31: 20.4 | AH31: 20.4 | AI31: 20 | AJ31: 7.6 | AK31: 80.8 | AN31: 3.4 | AO31: 18.6 | AQ31: 0.5 | AR31: 3.1 | AS31: 16.7 | AT31: 15.6 | AW31: 152.5 | AX31: 140.1 | AY31: 112.9 | AZ31: 111.2 | BA31: 0.6 | BB31: 19.4 | BC31: 30.6 | BD31: 84.9 | BE31: 20 | BF31: 1 | BG31: 0.9 | BI31: 1.7 | BJ31: 16 | BK31: 1.2 | BL31: 18.4 | BM31: 6.1 | BN31: 18.7 | BO31: 20.5 | BP31: 1500.8
B32: 12:30 | C32: 15 | D32: 16.8 | F32: 11 | G32: 17.6 | H32: 1.9 | J32: 8.8 | K32: 0.9 | L32: 11.1 | N32: 11 | O32: 15 | P32: 6.8 | Q32: 3.3 | R32: 3 | S32: 15 | U32: 20 | V32: 18.5 | W32: 2.5 | X32: 78.2 | Y32: 122.9 | AA32: 88.9 | AB32: 37.5 | AD32: 10.1 | AE32: 20.9 | AF32: 7.6 | AG32: 20.4 | AH32: 20.4 | AI32: 20 | AJ32: 7.9 | AK32: 81 | AM32: 0.2 | AN32: 3.4 | AO32: 18.6 | AQ32: 0.5 | AR32: 3.1 | AS32: 17.3 | AT32: 15.2 | AW32: 144.8 | AX32: 134.1 | AY32: 116.9 | AZ32: 92.5 | BA32: 0.6 | BB32: 18.5 | BC32: 30.8 | BD32: 84.8 | BE32: 20 | BF32: 1 | BG32: 0.9 | BI32: 1.7 | BJ32: 15.6 | BK32: 1.2 | BL32: 18.5 | BM32: 6.1 | BN32: 17.8 | BO32: 20.8 | BP32: 1478.9
B33: 13:00 | C33: 15 | D33: 16.8 | E33: 4.7 | F33: 10.9 | G33: 17 | H33: 2 | J33: 8.9 | K33: 0.8 | L33: 11.1 | N33: 11.3 | O33: 15 | P33: 6.8 | Q33: 3.4 | R33: 3 | S33: 15 | U33: 20 | V33: 18.5 | W33: 11.8 | X33: 78.6 | Y33: 121.7 | AA33: 86.8 | AB33: 34.6 | AD33: 9.3 | AE33: 20.9 | AF33: 7.6 | AG33: 20.4 | AH33: 20.4 | AI33: 20 | AJ33: 7.9 | AK33: 78.4 | AN33: 3.4 | AO33: 18.6 | AQ33: 0.5 | AR33: 3.1 | AS33: 18.8 | AT33: 14.3 | AW33: 133.8 | AX33: 129.9 | AY33: 116.4 | AZ33: 89.9 | BA33: 0.6 | BB33: 17.6 | BC33: 30.5 | BD33: 86 | BE33: 20 | BF33: 1 | BG33: 0.9 | BI33: 1.7 | BJ33: 13.2 | BK33: 1.2 | BL33: 18.5 | BM33: 6.2 | BN33: 16.4 | BO33: 20.9 | BP33: 1462
B34: 13:30 | C34: 16 | D34: 16.8 | E34: 4.5 | F34: 11 | G34: 12 | H34: 2 | J34: 9 | K34: 1.3 | L34: 11.1 | N34: 10.8 | O34: 14.9 | P34: 6.8 | Q34: 3.1 | R34: 2.8 | S34: 15 | U34: 20 | V34: 18.7 | W34: 13 | X34: 78.4 | Y34: 117.4 | AA34: 82.3 | AB34: 26 | AD34: 9.9 | AE34: 20.9 | AF34: 7.6 | AG34: 20.4 | AH34: 20.4 | AI34: 20 | AJ34: 7.6 | AK34: 81 | AN34: 3.4 | AO34: 18.6 | AQ34: 0.5 | AR34: 3.1 | AS34: 14.7 | AT34: 14.3 | AW34: 122.3 | AX34: 155.1 | AY34: 116.6 | AZ34: 114.5 | BA34: 0.6 | BB34: 17.6 | BC34: 30.5 | BD34: 85.2 | BE34: 20.2 | BF34: 1 | BG34: 0.9 | BI34: 1.7 | BJ34: 15.9 | BK34: 1.2 | BL34: 18.4 | BM34: 6.2 | BN34: 16.8 | BO34: 20.8 | BP34: 1480.8
B35: 14:00 | C35: 15.9 | D35: 16.8 | E35: 4.7 | F35: 11 | G35: 12 | H35: 2 | J35: 8.5 | K35: 1.2 | L35: 11.1 | N35: 11.7 | O35: 14.6 | P35: 6.8 | Q35: 3.3 | R35: 2.8 | S35: 14.9 | U35: 20 | V35: 18.7 | W35: 16 | X35: 79 | Y35: 113.7 | AA35: 75.3 | AB35: 32.3 | AD35: 10.3 | AE35: 20.9 | AF35: 7.6 | AG35: 20.4 | AH35: 20.4 | AI35: 20 | AJ35: 7.4 | AK35: 69 | AL35: 1.2 | AM35: 1.8 | AN35: 3.4 | AO35: 18.6 | AQ35: 0.4 | AR35: 3.1 | AS35: 14.4 | AT35: 13.1 | AW35: 144.1 | AX35: 135.2 | AY35: 116.2 | AZ35: 106.1 | BA35: 0.6 | BB35: 16.6 | BC35: 30.1 | BD35: 84.3 | BE35: 20 | BF35: 1 | BG35: 0.9 | BI35: 1.7 | BJ35: 14.8 | BK35: 1.2 | BL35: 18.5 | BM35: 6.1 | BN35: 17.4 | BO35: 20.5 | BP35: 1459.6
B36: 14:30 | C36: 15.6 | D36: 17.2 | E36: 4.1 | F36: 11 | G36: 12.1 | H36: 2 | J36: 9 | K36: 1.1 | L36: 11.2 | O36: 13.4 | P36: 6.8 | Q36: 3.2 | R36: 2.8 | S36: 14.7 | U36: 20 | V36: 18.7 | W36: 14.7 | X36: 78.1 | Y36: 112.9 | AA36: 74.6 | AB36: 38.3 | AD36: 10.3 | AE36: 20.9 | AF36: 7.6 | AG36: 20.4 | AH36: 20.4 | AI36: 20 | AJ36: 7.4 | AK36: 78.9 | AL36: 1.4 | AM36: 1.3 | AN36: 3.4 | AO36: 18.6 | AQ36: 0.3 | AR36: 3.1 | AS36: 12.2 | AT36: 15.2 | AW36: 141.4 | AX36: 150.1 | AY36: 116.5 | AZ36: 110.4 | BA36: 0.6 | BB36: 18.2 | BC36: 28 | BD36: 85.1 | BE36: 20 | BF36: 1 | BG36: 0.9 | BI36: 1.7 | BJ36: 13.3 | BK36: 1.2 | BL36: 18.3 | BM36: 6.2 | BN36: 17.3 | BO36: 20.7 | BP36: 1473.8
B37: 15:00 | C37: 16.1 | D37: 17.2 | E37: 6.2 | F37: 11 | G37: 12.5 | H37: 2.1 | J37: 9 | K37: 0.4 | L37: 11.2 | O37: 13.4 | P37: 6.8 | Q37: 3.2 | R37: 2.8 | S37: 14.7 | U37: 20 | V37: 18.7 | W37: 16.5 | X37: 78.2 | Y37: 116 | AA37: 79.3 | AB37: 25.2 | AD37: 13.6 | AE37: 20.9 | AF37: 7.6 | AG37: 20.4 | AH37: 20.4 | AI37: 20 | AJ37: 7.2 | AK37: 51.6 | AL37: 3.6 | AM37: 4.2 | AN37: 3.4 | AO37: 18.6 | AQ37: 0.4 | AR37: 3.1 | AS37: 12.6 | AT37: 13.4 | AW37: 116.9 | AX37: 131.7 | AY37: 119.8 | AZ37: 97.9 | BA37: 0.6 | BB37: 16.3 | BC37: 30 | BD37: 85.6 | BE37: 20 | BF37: 1 | BG37: 0.9 | BI37: 1.7 | BJ37: 11.1 | BK37: 1.2 | BL37: 18.3 | BM37: 6.1 | BN37: 14.5 | BO37: 20.6 | BP37: 1395.7
B38: 15:30 | C38: 15.6 | D38: 17.5 | E38: 5.6 | F38: 11 | G38: 18.3 | H38: 2.2 | J38: 9.2 | K38: 0.3 | L38: 11.2 | O38: 14.8 | P38: 6.8 | Q38: 3.1 | R38: 3 | S38: 14.7 | U38: 20 | V38: 18.7 | W38: 17.9 | X38: 81.4 | Y38: 117 | AA38: 81.3 | AB38: 22.9 | AD38: 11.4 | AE38: 20.9 | AF38: 7.6 | AG38: 20.4 | AH38: 20.4 | AI38: 20 | AJ38: 7.2 | AK38: 58.8 | AL38: 6.3 | AM38: 3.6 | AN38: 3.4 | AO38: 18.6 | AQ38: 0.2 | AR38: 3.4 | AS38: 7.6 | AT38: 13.5 | AW38: 145.3 | AX38: 137.2 | AY38: 123 | AZ38: 98.8 | BA38: 0.6 | BB38: 16 | BC38: 30.1 | BD38: 84.6 | BE38: 20 | BF38: 1 | BG38: 0.9 | BI38: 1.7 | BJ38: 7.4 | BK38: 1.2 | BL38: 18.4 | BM38: 6.1 | BN38: 13.5 | BO38: 20.7 | BP38: 1442.3
B39: 16:00 | C39: 15.7 | D39: 17.5 | E39: 4.5 | F39: 11 | G39: 18.5 | H39: 2.3 | J39: 9 | K39: 0.2 | L39: 11.4 | O39: 14.2 | P39: 6.8 | Q39: 3.2 | R39: 2.9 | S39: 14.7 | U39: 20 | V39: 18.7 | W39: 14.3 | X39: 81.9 | Y39: 111.7 | AA39: 91.9 | AB39: 24.5 | AD39: 10.3 | AE39: 20.9 | AF39: 7.6 | AG39: 20.4 | AH39: 20.4 | AI39: 20 | AJ39: 6.7 | AK39: 60.9 | AL39: 7.3 | AM39: 4.7 | AN39: 3.4 | AO39: 18.6 | AQ39: 0.1 | AR39: 3.4 | AS39: 6.1 | AT39: 8.3 | AW39: 154.1 | AX39: 104.3 | AY39: 123.3 | AZ39: 73.9 | BA39: 0.6 | BB39: 9.7 | BC39: 30.6 | BD39: 84.9 | BE39: 20 | BF39: 1 | BG39: 0.9 | BI39: 1.7 | BJ39: 6.4 | BK39: 1.2 | BL39: 18.4 | BM39: 6.2 | BN39: 14 | BO39: 20.4 | BP39: 1385.6
B40: 16:30 | C40: 15.3 | D40: 17.5 | E40: 5.3 | F40: 11 | G40: 18.6 | H40: 2.5 | J40: 8.8 | K40: 0.1 | L40: 11.4 | O40: 14.8 | P40: 6.8 | Q40: 3.2 | R40: 2.8 | S40: 14.7 | U40: 20 | V40: 18.7 | W40: 15.8 | X40: 81.8 | Y40: 100.6 | AA40: 91.3 | AB40: 11.8 | AD40: 12.7 | AE40: 20.9 | AF40: 7.6 | AG40: 20.4 | AH40: 20.4 | AI40: 20 | AJ40: 6.7 | AK40: 25.1 | AL40: 7.8 | AM40: 5.2 | AN40: 3.4 | AO40: 18.6 | AQ40: 0.1 | AR40: 3.4 | AS40: 3.3 | AT40: 6.9 | AW40: 159 | AX40: 44.6 | AY40: 123.1 | AZ40: 36.4 | BA40: 0.6 | BB40: 9.2 | BC40: 28.5 | BD40: 82.5 | BE40: 20 | BF40: 1 | BG40: 0.9 | BI40: 1.7 | BJ40: 4.2 | BK40: 1.2 | BL40: 18.4 | BM40: 6.2 | BN40: 9.7 | BO40: 20.8 | BP40: 1223.3
B41: 17:00 | C41: 15.3 | D41: 17.6 | E41: 6.3 | F41: 11 | G41: 18.6 | H41: 2.8 | J41: 8.8 | K41: 0.1 | L41: 11.5 | O41: 14.7 | P41: 6.8 | Q41: 3.1 | R41: 2.9 | S41: 14.5 | U41: 20 | V41: 18.7 | W41: 19.6 | X41: 81.7 | Y41: 93.7 | AA41: 88.3 | AB41: 5.7 | AD41: 7.4 | AE41: 20.9 | AF41: 7.6 | AG41: 20.4 | AH41: 20.4 | AI41: 20 | AJ41: 7.6 | AK41: 19.8 | AL41: 7.7 | AM41: 6.2 | AN41: 3.4 | AO41: 18.6 | AQ41: 0.1 | AR41: 3.2 | AS41: 2.4 | AT41: 2.5 | AW41: 145.3 | AX41: 42.9 | AY41: 123.1 | AZ41: 36.3 | BA41: 0.6 | BB41: 3.1 | BC41: 27.6 | BD41: 85.4 | BE41: 20 | BF41: 1 | BG41: 0.9 | BI41: 1.7 | BJ41: 1.7 | BK41: 1.2 | BL41: 18.3 | BM41: 6.1 | BN41: 3.1 | BO41: 20.7 | BP41: 1168.9
B42: 17:30 | C42: 15.5 | D42: 17.6 | E42: 6.8 | F42: 11 | G42: 18.6 | H42: 3 | J42: 6.3 | L42: 11.8 | N42: 11.5 | O42: 14.6 | P42: 6.8 | Q42: 3.2 | R42: 2.8 | S42: 14.4 | U42: 20 | V42: 18.7 | W42: 21.4 | X42: 81.8 | Y42: 91.4 | AA42: 100.3 | AB42: 1.8 | AD42: 6.1 | AE42: 20.9 | AF42: 7.6 | AG42: 20.2 | AH42: 20.4 | AI42: 20 | AJ42: 7.3 | AK42: 4.1 | AL42: 5.7 | AM42: 5.8 | AN42: 3.4 | AO42: 18.6 | AR42: 3.2 | AS42: 0.8 | AT42: 0.2 | AW42: 132 | AX42: 4.5 | AY42: 114.4 | AZ42: 4.2 | BA42: 0.6 | BB42: 0.1 | BC42: 28.5 | BD42: 82.1 | BE42: 20 | BF42: 1 | BG42: 1 | BI42: 1.8 | BJ42: 0.7 | BK42: 1.2 | BL42: 18.3 | BM42: 6.2 | BN42: 0.1 | BO42: 20.7 | BP42: 1061
B43: 18:00 | C43: 15.5 | D43: 17.7 | E43: 7.2 | F43: 11 | G43: 18.6 | H43: 3 | J43: 8.5 | L43: 11.8 | N43: 12.2 | O43: 14.3 | P43: 6.8 | Q43: 3.2 | R43: 2.8 | S43: 14.3 | U43: 20 | V43: 18.7 | W43: 17.8 | X43: 81.4 | Y43: 108.9 | Z43: 57.8 | AA43: 96.3 | AD43: 5.8 | AE43: 20.9 | AF43: 7.5 | AG43: 20.2 | AH43: 20.4 | AI43: 20 | AJ43: 7 | AL43: 4.4 | AM43: 3.4 | AN43: 3.4 | AO43: 18.6 | AR43: 3.2 | AW43: 126.4 | AY43: 110.9 | AZ43: 0.2 | BA43: 0.6 | BC43: 29.5 | BD43: 86.4 | BE43: 20 | BF43: 1 | BG43: 1.3 | BI43: 1.8 | BK43: 1.2 | BL43: 18.2 | BM43: 6.1 | BO43: 20.7 | BP43: 1106.9
B44: 18:30 | C44: 14.7 | D44: 19 | E44: 7.1 | F44: 10.8 | G44: 18.9 | H44: 3 | J44: 7.3 | L44: 11.7 | N44: 12.2 | O44: 16.6 | P44: 6.8 | Q44: 3.2 | R44: 2.8 | S44: 15.6 | U44: 20 | V44: 18.7 | W44: 15.2 | X44: 80.9 | Y44: 107.1 | Z44: 50.5 | AA44: 96 | AC44: 3.8 | AD44: 5.1 | AE44: 20.9 | AF44: 7.6 | AG44: 20 | AH44: 20.4 | AI44: 20 | AJ44: 7.1 | AL44: 3.7 | AM44: 1.9 | AN44: 3.4 | AO44: 18.6 | AR44: 3.3 | AW44: 120.8 | AY44: 107.5 | BA44: 0.6 | BC44: 29.9 | BD44: 86.9 | BE44: 20 | BF44: 1 | BG44: 1 | BI44: 1.8 | BK44: 1.1 | BL44: 18.7 | BM44: 6.2 | BO44: 20.7 | BP44: 1090.1
B45: 19:00 | C45: 14.4 | D45: 17.4 | E45: 7.2 | F45: 11 | G45: 18.9 | H45: 3 | J45: 7 | L45: 11.6 | N45: 12.3 | O45: 16.8 | P45: 8.3 | Q45: 3.2 | R45: 2.8 | S45: 15.7 | U45: 20 | V45: 18.5 | W45: 15.6 | X45: 78.6 | Y45: 100.8 | Z45: 58.9 | AA45: 87.9 | AC45: 3.4 | AD45: 5.2 | AE45: 20.9 | AF45: 7.6 | AG45: 20 | AH45: 20.4 | AI45: 20 | AJ45: 7.2 | AL45: 2.7 | AM45: 1.7 | AN45: 3.4 | AO45: 18.6 | AR45: 3.3 | AW45: 120.1 | AY45: 103.3 | BA45: 0.6 | BC45: 30.7 | BD45: 87.7 | BE45: 20 | BF45: 1.1 | BG45: 1 | BI45: 1.8 | BK45: 1.1 | BL45: 18.7 | BM45: 6.2 | BO45: 20.7 | BP45: 1077.3
B46: 19:30 | C46: 14.7 | D46: 19 | E46: 7.2 | F46: 11 | G46: 18.9 | H46: 3 | J46: 6.5 | L46: 11.5 | N46: 10.6 | O46: 16.7 | P46: 8.4 | Q46: 3.2 | R46: 2.8 | S46: 15.3 | U46: 20 | V46: 18.7 | W46: 15.9 | X46: 75.7 | Y46: 94.1 | Z46: 58.9 | AA46: 88.1 | AC46: 4 | AD46: 6.8 | AE46: 20.9 | AF46: 7.6 | AG46: 19.8 | AH46: 20.4 | AI46: 20 | AJ46: 7.2 | AL46: 0.5 | AN46: 3.4 | AO46: 18.6 | AR46: 3.3 | AW46: 119.9 | AY46: 104.2 | BA46: 0.6 | BC46: 30.8 | BD46: 87.8 | BE46: 20 | BF46: 1.1 | BG46: 1 | BI46: 1.8 | BK46: 1.1 | BL46: 18.6 | BM46: 6.2 | BO46: 20.6 | BP46: 1066.4
B47: 20:00 | C47: 14.7 | D47: 19 | E47: 6.6 | F47: 11 | G47: 18.9 | H47: 3 | J47: 8.9 | L47: 11.5 | N47: 10.5 | O47: 17.1 | P47: 8.5 | Q47: 3.1 | R47: 2.6 | S47: 14.2 | U47: 20 | V47: 18.9 | W47: 13.3 | X47: 70.3 | Y47: 92.7 | Z47: 59.5 | AA47: 80.2 | AC47: 5.9 | AD47: 4.6 | AE47: 20.9 | AF47: 7.6 | AG47: 19.8 | AH47: 20.4 | AI47: 20 | AJ47: 7.7 | AL47: 0.2 | AN47: 3.4 | AO47: 18.6 | AR47: 3.4 | AW47: 110.4 | AY47: 93.5 | BA47: 0.6 | BC47: 29.6 | BD47: 83.9 | BE47: 20.2 | BF47: 1.1 | BG47: 1 | BI47: 1.8 | BK47: 1.1 | BL47: 18.2 | BM47: 6.2 | BO47: 20.8 | BP47: 1025.4
B48: 20:30 | C48: 14.9 | D48: 17.4 | E48: 7 | F48: 11 | G48: 19.1 | H48: 3 | J48: 8.2 | L48: 11.3 | N48: 11.3 | O48: 17.5 | P48: 8.8 | Q48: 3.1 | R48: 2.8 | S48: 15 | U48: 20 | V48: 18.9 | W48: 13 | X48: 65.2 | Y48: 100.9 | Z48: 65.5 | AA48: 81.8 | AC48: 6.4 | AD48: 5.1 | AE48: 20.9 | AF48: 7.6 | AG48: 19.4 | AH48: 20.4 | AI48: 20 | AJ48: 7.7 | AL48: 1.8 | AM48: 0.7 | AN48: 3.4 | AO48: 18.6 | AR48: 3.5 | AW48: 92.2 | AY48: 78.9 | BA48: 0.6 | BC48: 29.2 | BD48: 83.5 | BE48: 18.9 | BF48: 1.1 | BG48: 1 | BI48: 1.8 | BK48: 1.1 | BL48: 18.6 | BM48: 6.2 | BO48: 20.9 | BP48: 1005.2
B49: 21:00 | C49: 15.2 | D49: 18.7 | E49: 6.3 | F49: 11 | G49: 19.1 | H49: 3 | J49: 8.5 | L49: 11.3 | N49: 10.5 | O49: 17 | P49: 8.7 | Q49: 3.2 | R49: 2.9 | S49: 15.7 | U49: 20 | V49: 18.9 | W49: 10.9 | X49: 64.6 | Y49: 103.5 | Z49: 51.4 | AA49: 74.5 | AC49: 4.5 | AD49: 4.1 | AE49: 20.9 | AF49: 7.6 | AG49: 19 | AH49: 20.4 | AI49: 20 | AJ49: 7.7 | AL49: 1.1 | AN49: 3.4 | AO49: 18.6 | AR49: 3.5 | AW49: 87 | AY49: 85.2 | BA49: 0.6 | BC49: 30.6 | BD49: 86.9 | BE49: 20 | BF49: 1.1 | BG49: 1 | BI49: 1.8 | BK49: 1.1 | BL49: 18.8 | BM49: 6.2 | BO49: 20.7 | BP49: 986.7
B50: 21:30 | C50: 16 | D50: 19.1 | E50: 7 | F50: 11 | G50: 19.1 | H50: 3 | J50: 8.4 | L50: 11.1 | N50: 10.5 | O50: 15.4 | P50: 8.8 | Q50: 3.1 | R50: 2.8 | S50: 15.5 | U50: 20 | V50: 18.9 | W50: 13.2 | X50: 60.2 | Y50: 94.7 | Z50: 51.9 | AA50: 71.3 | AC50: 3.2 | AD50: 3.3 | AE50: 20.9 | AF50: 7.6 | AG50: 18.6 | AH50: 20 | AI50: 19.7 | AJ50: 7.4 | AL50: 1.7 | AM50: 0.7 | AN50: 3.4 | AO50: 18.6 | AR50: 3.3 | AW50: 58.7 | AY50: 59.8 | BA50: 0.6 | BC50: 30.6 | BD50: 85.4 | BE50: 20 | BF50: 1.1 | BG50: 1 | BI50: 1.8 | BK50: 1.1 | BL50: 18.6 | BM50: 6.2 | BO50: 20.7 | BP50: 915
B51: 22:00 | C51: 16 | E51: 6.2 | F51: 11 | G51: 18.9 | H51: 2.9 | J51: 9.2 | L51: 11.1 | N51: 10.5 | O51: 14.8 | P51: 8.9 | Q51: 3.1 | R51: 2.8 | S51: 15.4 | U51: 20 | V51: 18.9 | W51: 13.6 | X51: 50.3 | Y51: 98.1 | Z51: 53.1 | AA51: 83.8 | AC51: 3.5 | AD51: 2.7 | AE51: 20.9 | AF51: 7.6 | AG51: 18.6 | AH51: 19.6 | AI51: 19.6 | AJ51: 7.4 | AL51: 0.7 | AM51: 0.9 | AN51: 3.4 | AO51: 18.6 | AR51: 3.4 | AW51: 66.7 | AY51: 62.6 | BA51: 0.6 | BC51: 30.6 | BD51: 86 | BE51: 19.8 | BF51: 1.1 | BG51: 1 | BI51: 1.8 | BK51: 1 | BL51: 18.6 | BM51: 6.2 | BO51: 20.7 | BP51: 912.2
B52: 22:30 | C52: 15 | E52: 5.9 | F52: 11 | G52: 18.9 | H52: 2.8 | J52: 8.9 | L52: 11.1 | N52: 10.4 | O52: 14.9 | P52: 9.1 | Q52: 3.1 | R52: 2.9 | S52: 15.9 | U52: 20 | V52: 18.9 | W52: 11.5 | X52: 56.2 | Y52: 104.5 | Z52: 57.8 | AA52: 88.7 | AC52: 3.8 | AD52: 4.8 | AE52: 20.9 | AF52: 7.6 | AG52: 18.6 | AH52: 19.6 | AI52: 19.6 | AJ52: 7.6 | AL52: 0.5 | AM52: 0.4 | AN52: 3.4 | AO52: 18.6 | AR52: 3.3 | AW52: 57 | AY52: 55.2 | BA52: 0.6 | BC52: 30.5 | BD52: 86.7 | BE52: 19.6 | BF52: 1.1 | BG52: 1 | BI52: 1.8 | BK52: 1 | BL52: 18.8 | BM52: 6.2 | BO52: 20.7 | BP52: 916.4
B53: 23:00 | C53: 15 | E53: 7.8 | F53: 11 | G53: 18.9 | H53: 2.8 | J53: 9.3 | L53: 11 | N53: 10.3 | O53: 14.7 | P53: 9.2 | Q53: 3.2 | R53: 2.9 | S53: 16.1 | U53: 20 | V53: 18.9 | W53: 10.4 | X53: 68.8 | Y53: 103.5 | Z53: 61.2 | AA53: 89 | AC53: 3.1 | AD53: 2.1 | AE53: 20.9 | AF53: 7.6 | AG53: 18.9 | AH53: 19.6 | AI53: 19.6 | AJ53: 7.8 | AL53: 0.1 | AN53: 3.5 | AO53: 18.6 | AR53: 3.3 | AW53: 43.7 | AY53: 34.7 | BA53: 0.6 | BC53: 30.7 | BD53: 87 | BE53: 20 | BF53: 1.1 | BG53: 1 | BI53: 1.8 | BK53: 1 | BL53: 18.7 | BM53: 6.2 | BO53: 20.9 | BP53: 896.5
B54: 23:30 | C54: 15.3 | E54: 6.7 | F54: 11 | G54: 18.9 | H54: 2.7 | J54: 7.8 | L54: 10.9 | N54: 10.4 | O54: 14.9 | P54: 9.2 | Q54: 3.2 | R54: 2.7 | S54: 16 | U54: 20 | V54: 18.9 | W54: 10.5 | X54: 68.9 | Y54: 96.1 | Z54: 67.9 | AA54: 87.9 | AC54: 5.6 | AD54: 4.3 | AE54: 20.9 | AF54: 7.6 | AG54: 18.9 | AH54: 19.7 | AI54: 19.7 | AJ54: 7.7 | AN54: 3.5 | AO54: 18.6 | AR54: 3.3 | AW54: 31.9 | AY54: 25.9 | BA54: 0.6 | BC54: 30.1 | BD54: 86.7 | BE54: 20 | BF54: 1.1 | BG54: 1 | BI54: 1.8 | BK54: 1 | BL54: 18.8 | BM54: 6.1 | BO54: 20.6 | BP54: 875.3
B55: 0:00 | C55: 15 | E55: 7 | F55: 11 | G55: 18.9 | H55: 2.7 | J55: 8.6 | L55: 10.9 | N55: 10.1 | O55: 14.6 | P55: 9.2 | Q55: 3.2 | R55: 2.8 | S55: 15.7 | U55: 20 | V55: 18.9 | W55: 12.9 | X55: 68.2 | Y55: 90.8 | Z55: 47.8 | AA55: 90.1 | AC55: 4 | AD55: 2.5 | AE55: 20.9 | AF55: 7.6 | AG55: 18.9 | AH55: 19.8 | AI55: 19.8 | AJ55: 7.6 | AN55: 3.5 | AO55: 18.6 | AR55: 3.3 | AW55: 7 | AY55: 8.7 | BA55: 0.6 | BC55: 30.2 | BD55: 84.4 | BE55: 17.4 | BF55: 1.1 | BG55: 1 | BI55: 1.8 | BK55: 1 | BL55: 18.6 | BM55: 6 | BO55: 20.5 | BP55: 803.2
B56: EJEC MWh | C56: 342.3 | D56: 386.35 | E56: 70.95 | F56: 261.35 | G56: 373.4 | H56: 57.1 | I56: 0 | J56: 203.35 | K56: 6.75 | L56: 281.55 | M56: 0 | N56: 225.5 | O56: 355.55 | P56: 174.35 | Q56: 77.25 | R56: 68.7 | S56: 372.15 | T56: 0 | U56: 480 | V56: 451.35 | W56: 389.35 | X56: 1370.75 | Y56: 2469.25 | Z56: 915.95 | AA56: 2000.05 | AB56: 309.55 | AC56: 77.45 | AD56: 181.45 | AE56: 492.5 | AF56: 181.9 | AG56: 479.85 | AH56: 486.95 | AI56: 478.4 | AJ56: 175.5 | AK56: 755 | AL56: 29.2 | AM56: 21.35 | AN56: 81.75 | AO56: 446.4 | AP56: 0 | AQ56: 2.9 | AR56: 70.65 | AS56: 130.85 | AT56: 139.45 | AU56: 2.35 | AV56: 0 | AW56: 2393.15 | AX56: 1431.4 | AY56: 1974.8 | AZ56: 1061.8 | BA56: 14.4 | BB56: 172.9 | BC56: 712.2 | BD56: 1987.9 | BE56: 478.3 | BF56: 23.95 | BG56: 22.5 | BH56: 0 | BI56: 40.45 | BJ56: 125.25 | BK56: 26.75 | BL56: 446.75 | BM56: 150.25 | BN56: 160.55 | BO56: 496.65 | BP56: 27596.7
L70: TERMOELÉCTRICA | M70: 1351.2 | N70: 4.8962376 | O70: #FFA975
L71: SOLAR | M71: 4296.4 | N71: 15.568528 | O71: #FFD272
L72: HIDROELÉCTRICA | M72: 7426.25 | N72: 26.90992 | O72: #98D2FF
L73: EÓLICA | M73: 14522.85 | N73: 52.625314 | O73: #B9ACFF

Sheet COGENERACIÓN
B3: martes, 4 de Noviembre del 2025
B5: CENTRALES DE COGENERACIÓN DEL SEIN
B6: HORA | C6: AGRO INDUSTRIAL PARAMONGA S.A. | D6: AGROAURORA S.A.C. | E6: AGROINDUSTRIAS SAN JACINTO S.A.A. | F6: AGROLMOS SOCIEDAD ANONIMA - AGROLMOS S.A. | G6: BIOENERGIA DEL CHIRA S.A. | H6: GM OPERACIONES S.A.C. | I6: TOTAL COGENERACION
C7: C.T. PARAMONGA | D7: C.T. MAPLE | E7: C.T SAN JACINTO | F7: C.T. AGROLMOS | G7: C.T. CAÑA BRAVA | H7: C.T. REFINERÍA TALARA | I7: MW
B8: 0:30 | C8: 14.9 | D8: 15.9 | F8: 11 | G8: 9 | H8: 63.6 | I8: 114.4
B9: 1:00 | C9: 15 | D9: 19.2 | F9: 11 | G9: 8.6 | H9: 62.9 | I9: 116.7
B10: 1:30 | C10: 15 | D10: 19.3 | F10: 11 | G10: 8.8 | H10: 63.2 | I10: 117.3
B11: 2:00 | C11: 15 | D11: 19.3 | F11: 10.1 | G11: 8.8 | H11: 63.5 | I11: 116.7
B12: 2:30 | C12: 15.3 | D12: 18.9 | F12: 11.1 | G12: 8.8 | H12: 62.3 | I12: 116.4
B13: 3:00 | C13: 16 | D13: 19.4 | F13: 11.1 | G13: 8.8 | H13: 61.3 | I13: 116.6
B14: 3:30 | C14: 16 | D14: 19.4 | F14: 11.1 | G14: 8 | H14: 64.5 | I14: 119
B15: 4:00 | C15: 15.6 | D15: 19.4 | F15: 11 | G15: 8.1 | H15: 62.6 | I15: 116.7
B16: 4:30 | C16: 15.8 | D16: 18.5 | F16: 11.1 | G16: 7.3 | H16: 63.2 | I16: 115.9
B17: 5:00 | C17: 16 | D17: 18 | F17: 11.1 | G17: 7.5 | H17: 63.6 | I17: 116.2
B18: 5:30 | C18: 16 | D18: 19.1 | F18: 11 | G18: 8.1 | H18: 63.6 | I18: 117.8
B19: 6:00 | C19: 16.1 | D19: 19.4 | F19: 11 | G19: 8.2 | H19: 63.4 | I19: 118.1
... B27: 10:00 | C27: 15.2 | D27: 16.7 | F27: 11 | G27: 9.6 | H27: 62 | I27: 114.5
B28: 10:30 | D28: 16.7 | F28: 11 | G28: 9.1 | H28: 61.7 | I28: 98.5
B29: 11:00 | D29: 14.6 | F29: 11 | G29: 9.1 | H29: 62.1 | I29: 96.8
B30: 11:30 | D30: 16.8 | F30: 11 | G30: 8.6 | H30: 61.9 | I30: 98.3
B31: 12:00 | C31: 7 | D31: 16.8 | F31: 11 | G31: 9.3 | H31: 61.2 | I31: 105.3
B32: 12:30 | C32: 15 | D32: 16.8 | F32: 11 | G32: 8.8 | H32: 61.5 | I32: 113.1
B33: 13:00 | C33: 15 | D33: 16.8 | E33: 4.7 | F33: 10.9 | G33: 8.9 | H33: 61.8 | I33: 118.1
B34: 13:30 | C34: 16 | D34: 16.8 | E34: 4.5 | F34: 11 | G34: 9 | H34: 62 | I34: 119.3
B35: 14:00 | C35: 15.9 | D35: 16.8 | E35: 4.7 | F35: 11 | G35: 8.5 | H35: 62.8 | I35: 119.7
B36: 14:30 | C36: 15.6 | D36: 17.2 | E36: 4.1 | F36: 11 | G36: 9 | H36: 63.9 | I36: 120.8
B37: 15:00 | C37: 16.1 | D37: 17.2 | E37: 6.2 | F37: 11 | G37: 9 | H37: 63 | I37: 122.5
B38: 15:30 | C38: 15.6 | D38: 17.5 | E38: 5.6 | F38: 11 | G38: 9.2 | H38: 62.8 | I38: 121.7
B39: 16:00 | C39: 15.7 | D39: 17.5 | E39: 4.5 | F39: 11 | G39: 9 | H39: 55.3 | I39: 113
B40: 16:30 | C40: 15.3 | D40: 17.5 | E40: 5.3 | F40: 11 | G40: 8.8 | H40: 63.9 | I40: 121.8
B41: 17:00 | C41: 15.3 | D41: 17.6 | E41: 6.3 | F41: 11 | G41: 8.8 | H41: 62.4 | I41: 121.4
B42: 17:30 | C42: 15.5 | D42: 17.6 | E42: 6.8 | F42: 11 | G42: 6.3 | H42: 62.3 | I42: 119.5
B43: 18:00 | C43: 15.5 | D43: 17.7 | E43: 7.2 | F43: 11 | G43: 8.5 | H43: 62.3 | I43: 122.2
B44: 18:30 | C44: 14.7 | D44: 19 | E44: 7.1 | F44: 10.8 | G44: 7.3 | H44: 63.56 | I44: 122.46
... B50: 21:30 | C50: 16 | D50: 19.1 | E50: 7 | F50: 11 | G50: 8.4 | H50: 63.31 | I50: 124.81
B51: 22:00 | C51: 16 | E51: 6.2 | F51: 11 | G51: 9.2 | H51: 62.42 | I51: 104.82
B52: 22:30 | C52: 15 | E52: 5.9 | F52: 11 | G52: 8.9 | H52: 62.34 | I52: 103.14
B53: 23:00 | C53: 15 | E53: 7.8 | F53: 11 | G53: 9.3 | H53: 61.77 | I53: 104.87
B54: 23:30 | C54: 15.3 | E54: 6.7 | F54: 11 | G54: 7.8 | H54: 61.74 | I54: 102.54
B55: 0:00 | C55: 15 | E55: 7 | F55: 11 | G55: 8.6 | H55: 60.32 | I55: 101.92
B56: EJEC MWh | C56: 342.3 | D56: 386.35 | E56: 70.95 | F56: 261.35 | G56: 203.35 | H56: 1499.265 | I56: 2763.565

Sheet EVO_PRO_ENE
B3: sábado, 1 de Noviembre del 2025 - martes, 4 de Noviembre del 2025
B5: EVOLUCIÓN DE LA PRODUCCIÓN DE LA ENERGÍA DIARIA DE LOS INTEGRANTES DEL COES (MWh)
B6: EMPRESA | C6: CENTRAL | D6: UNIDAD | E6: TIPO | F6: Noviembre
F7: 1 | G7: 2 | H7: 3 | I7: 4 | J7: TOTAL
B8: AGRO INDUSTRIAL PARAMONGA S.A. | C8: C.T. PARAMONGA | D8: TV-01 | E8: TERMOELÉCTRICA | H8: 195.15 | I8: 342.3 | J8: 537.45
B9: AGROAURORA S.A.C. | C9: C.T. MAPLE ETANOL | D9: TV | E9: TERMOELÉCTRICA | F9: 414.9 | G9: 359.75 | H9: 314.05 | I9: 386.35 | J9: 1475.05
B10: AGROINDUSTRIAS SAN JACINTO S.A.A. | C10: C.T. SAN JACINTO | D10: CENTRAL | E10: TERMOELÉCTRICA | F10: 182 | G10: 157.2 | H10: 49.75 | I10: 70.95 | J10: 459.9
B11: AGROLMOS SOCIEDAD ANONIMA - AGROLMOS S.A. | C11: C.T. AGROLMOS | D11: CENTRAL | E11: TERMOELÉCTRICA | F11: 265.35 | G11: 264.3 | H11: 263.9 | I11: 261.35 | J11: 1054.9
B12: ANDEAN POWER S.A.C. | C12: C.H.CARHUAC | D12: CENTRAL | E12: HIDROELÉCTRICA | F12: 347.95 | G12: 359.35 | H12: 364.1 | I12: 373.4 | J12: 1444.8
B13: ASOCIACIÓN SANTA LUCIA DE CHACAS | C13: C.H. HUALLIN | D13: CENTRAL | E13: HIDROELÉCTRICA | F13: 55.85 | G13: 59.1 | H13: 60.15 | I13: 57.1 | J13: 232.2
B14: ATRIA ENERGIA S.A.C. | C14: C.H. PURMACANA | D14: CENTRAL | E14: HIDROELÉCTRICA | J14: 0
B15: BIOENERGIA DEL CHIRA S.A. | C15: C.T. CAÑA BRAVA | D15: CENTRAL | E15: TERMOELÉCTRICA | F15: 190.6 | G15: 212.4 | H15: 215.65 | I15: 203.35 | J15: 822
B16: CELEPSA | C16: C.H. EL PLATANAL | D16: CENTRAL | E16: HIDROELÉCTRICA | F16: 2830 | G16: 2899.6 | H16: 2724.65 | I16: 2741.65 | J16: 11195.9
B17: CELEPSA RENOVABLES S.R.L. | C17: C.H. MARAÑON | D17: CENTRAL | E17: HIDROELÉCTRICA | F17: 451.2 | G17: 451.2 | H17: 451.2 | I17: 451.2 | J17: 1804.8
B18: CENTRALES SANTA ROSA S.A.C. | C18: C.H. SANTA ROSA I | D18: CENTRAL | E18: HIDROELÉCTRICA | J18: 0
B19: CENTRALES SANTA ROSA S.A.C. | C19: C.H. SANTA ROSA II | D19: CENTRAL | E19: HIDROELÉCTRICA | J19: 0
B20: CHINANGO S.A.C. | C20: C.H. CHIMAY | D20: CENTRAL | E20: HIDROELÉCTRICA | F20: 3626.05 | G20: 3629.35 | H20: 3621.5 | I20: 3360.35 | J20: 14237.25
B21: CHINANGO S.A.C. | C21: C.H. YANANGO | D21: CENTRAL | E21: HIDROELÉCTRICA | F21: 692 | G21: 656.35 | H21: 790.7 | I21: 694.2 | J21: 2833.25
B22: COLCA SOLAR S.A.C. | C22: C.S. YARUCAYA | D22: CENTRAL | E22: SOLAR | F22: 9.1 | G22: 8.85 | H22: 8.45 | I22: 6.75 | J22: 33.15
B23: EGASA | C23: C.H. CHARCANI III | D23: CENTRAL | E23: HIDROELÉCTRICA | F23: 165.6 | G23: 165.85 | H23: 165.95 | I23: 165.7 | J23: 663.1
B24: EGASA | C24: C.H. CHARCANI IV | D24: CENTRAL | E24: HIDROELÉCTRICA | F24: 298.75 | G24: 295.95 | H24: 296.05 | I24: 271.55 | J24: 1162.3
B25: EGASA | C25: C.H. CHARCANI V | D25: CENTRAL | E25: HIDROELÉCTRICA | F25: 1876.1 | G25: 1890.55 | H25: 1880.33 | I25: 1917.15 | J25: 7564.13
B26: EGASA | C26: C.H. CHARCANI VI | D26: CENTRAL | E26: HIDROELÉCTRICA | J26: 0
B27: EGASA | C27: C.T. CHILINA DIESEL | D27: CENTRAL | E27: TERMOELÉCTRICA | J27: 0
B28: EGASA | C28: C.T. CHILINA DIESEL | D28: TG | E28: TERMOELÉCTRICA | J28: 0
B29: EGASA | C29: C.T. MOLLENDO DIESEL | D29: CENTRAL | E29: TERMOELÉCTRICA | J29: 0
B30: EGEJUNIN | C30: C.H. HUASAHUASI I | D30: CENTRAL | E30: HIDROELÉCTRICA | F30: 287.25 | G30: 255.5 | H30: 321.7 | I30: 281.55 | J30: 1146
B31: EGEJUNIN | C31: C.H. RUNATULLO II | D31: CENTRAL | E31: HIDROELÉCTRICA | F31: 285.65 | G31: 256.65 | H31: 258.75 | I31: 225.5 | J31: 1026.55
B32: EGEJUNIN | C32: C.H. RUNATULLO III | D32: CENTRAL | E32: HIDROELÉCTRICA | F32: 396.5 | G32: 363.2 | H32: 367.05 | I32: 355.55 | J32: 1482.3
B33: EGEJUNIN | C33: C.H. SANTA CRUZ I | D33: CENTRAL | E33: HIDROELÉCTRICA | F33: 165.3 | G33: 158.95 | H33: 162.55 | I33: 174.35 | J33: 661.15
B34: EGEMSA | C34: C.H. MACHUPICCHU | D34: CENTRAL | E34: HIDROELÉCTRICA | F34: 3987.6 | G34: 3950.3 | H34: 3681.9 | I34: 3689.8 | J34: 15309.6
B35: EGESUR | C35: C.H. ARICOTA I | D35: CENTRAL | E35: HIDROELÉCTRICA | F35: 178.9 | G35: 178.15 | H35: 178.25 | I35: 178.55 | J35: 713.85
B36: EGESUR | C36: C.H. ARICOTA II | D36: CENTRAL | E36: HIDROELÉCTRICA | F36: 137.15 | G36: 139.25 | H36: 140.7 | I36: 140.75 | J36: 557.85
B37: EGESUR | C37: C.T. INDEPENDENCIA | D37: CENTRAL | E37: TERMOELÉCTRICA | F37: 132.95 | G37: 75.2 | H37: 161.2 | I37: 134.8 | J37: 504.15
B38: ELECTRICA YANAPAMPA SAC | C38: C.H. YANAPAMPA | D38: CENTRAL | E38: HIDROELÉCTRICA | F38: 62.2 | G38: 76 | H38: 73.15 | I38: 77.25 | J38: 288.6
B39: ELECTROPERU | C39: C.H. MANTARO | D39: CENTRAL | E39: HIDROELÉCTRICA | F39: 14611.8 | G39: 14679.565 | H39: 15064.885 | I39: 14980.1 | J39: 59336.35
B40: ELECTROPERU | C40: C.H. RESTITUCION | D40: CENTRAL | E40: HIDROELÉCTRICA | F40: 4974.55 | G40: 5001.895 | H40: 5155.88 | I40: 5131.35 | J40: 20263.675
B41: ELECTROPERU | C41: C.T. TUMBES | D41: MAK1 | E41: TERMOELÉCTRICA | J41: 0
B42: ELECTROPERU | C42: C.T. TUMBES | D42: MAK2 | E42: TERMOELÉCTRICA | J42: 0
B43: EMPRESA DE GENERACION ELECTRICA CANCHAYLLO SAC | C43: C.H. CANCHAYLLO | D43: CENTRAL | E43: HIDROELÉCTRICA | F43: 69.8 | G43: 69.5 | H43: 70.6 | I43: 68.7 | J43: 278.6
B44: EMPRESA DE GENERACION ELECTRICA RIO BAÑOS S.A.C. | C44: C.H. RUCUY | D44: CENTRAL | E44: HIDROELÉCTRICA | F44: 372.9 | G44: 358.75 | H44: 351.65 | I44: 372.15 | J44: 1455.45
B45: EMPRESA DE GENERACION ELECTRICA SANTA ANA S.A.C. | C45: C.H. RENOVANDES H1 | D45: CENTRAL | E45: HIDROELÉCTRICA | J45: 0
B46: EMPRESA DE GENERACION HUALLAGA | C46: C.H. CHAGLLA | D46: CENTRAL | E46: HIDROELÉCTRICA | F46: 6248.45 | G46: 3546.8 | H46: 5184.7 | I46: 4484.55 | J46: 19464.5
B47: EMPRESA DE GENERACION HUALLAGA | C47: P.C.H. CHAGLLA | D47: CENTRAL | E47: HIDROELÉCTRICA | F47: 155.5 | G47: 155.8 | H47: 155.75 | I47: 155.65 | J47: 622.7
B48: EMPRESA DE GENERACION HUANZA | C48: C.H. HUANZA | D48: CENTRAL | E48: HIDROELÉCTRICA | F48: 1506.4 | G48: 1559.1 | H48: 1572.4 | I48: 1579.75 | J48: 6217.65
B49: EMPRESA ELECTRICA AGUA AZUL | C49: C.H. POTRERO | D49: CENTRAL | E49: HIDROELÉCTRICA | F49: 480 | G49: 480 | H49: 479.95 | I49: 480 | J49: 1919.95
B50: EMPRESA ELECTRICA RIO DOBLE | C50: C.H. LAS PIZARRAS | D50: CENTRAL | E50: HIDROELÉCTRICA | F50: 454.15 | G50: 453.95 | H50: 453.75 | I50: 451.35 | J50: 1813.2
B51: ENEL GENERACION PIURA S.A. | C51: C.T. MALACAS 1 | D51: TG6 | E51: TERMOELÉCTRICA | F51: 842.4 | G51: 2.65 | H51: 650.45 | I51: 641.6 | J51: 2137.1
B52: ENEL GENERACION PIURA S.A. | C52: C.T. MALACAS 2 | D52: TG4 | E52: TERMOELÉCTRICA | J52: 0
B53: ENEL GENERACION PIURA S.A. | C53: C.T. RF DE GENERACION TALARA | D53: TG5 | E53: TERMOELÉCTRICA | G53: 352.45 | J53: 352.45
B54: ENERGÍA EÓLICA S.A. | C54: C.E. CUPISNIQUE | D54: CENTRAL | E54: EÓLICA | F54: 1077.35 | G54: 1198.25 | H54: 1245.05 | I54: 1370.75 | J54: 4891.4
B55: ENERGÍA EÓLICA S.A. | C55: C.E. TALARA | D55: CENTRAL | E55: EÓLICA | F55: 535.15 | G55: 406.2 | H55: 393.4 | I55: 389.35 | J55: 1724.1
B56: ENERGIA RENOVABLE DEL SUR S.A. | C56: C.E. SAN JUAN | D56: CENTRAL | E56: EÓLICA | F56: 1591.15 | G56: 1841.4 | H56: 1519.1 | I56: 2469.25 | J56: 7420.9
B57: ENGIE ENERGIA PERU S.A.A. | C57: C.E. PUNTA LOMITAS | D57: PL-BL1 | E57: EÓLICA | F57: 1829.35 | G57: 1871.65 | H57: 869.2 | I57: 915.95 | J57: 5486.15
B58: ENGIE ENERGIA PERU S.A.A. | C58: C.E. PUNTA LOMITAS | D58: PL-BL2 | E58: EÓLICA | F58: 2010 | G58: 2056.25 | H58: 1660.65 | I58: 2000.05 | J58: 7726.95
B59: ENGIE ENERGIA PERU S.A.A. | C59: C.E. PUNTA LOMITAS_EXP | D59: PUN LOM_EXP-BL1 | E59: EÓLICA | F59: 261.55 | G59: 269.3 | H59: 84.95 | I59: 77.45 | J59: 693.25
B60: ENGIE ENERGIA PERU S.A.A. | C60: C.E. PUNTA LOMITAS_EXP | D60: PUN LOM_EXP-BL2 | E60: EÓLICA | F60: 125 | G60: 124.35 | H60: 138.75 | I60: 181.45 | J60: 569.55
B61: ENGIE ENERGIA PERU S.A.A. | C61: C.H. QUITARACSA | D61: CENTRAL | E61: HIDROELÉCTRICA | J61: 0
B62: ENGIE ENERGIA PERU S.A.A. | C62: C.H. YUNCAN | D62: CENTRAL | E62: HIDROELÉCTRICA | F62: 2508.7 | G62: 2185.1 | H62: 2033.35 | I62: 2021.7 | J62: 8748.85
B63: ENGIE ENERGIA PERU S.A.A. | C63: C.S. INTIPAMPA | D63: CENTRAL | E63: SOLAR | F63: 406.15 | G63: 406.55 | H63: 405.95 | I63: 309.55 | J63: 1528.2
B64: ENGIE ENERGIA PERU S.A.A. | C64: C.T. CHILCA 1 | D64: TG1 | E64: TERMOELÉCTRICA | F64: 3319.4 | G64: 3164.6 | H64: 3722.3 | I64: 4160.55 | J64: 14366.85
B65: ENGIE ENERGIA PERU S.A.A. | C65: C.T. CHILCA 1 | D65: TG2 | E65: TERMOELÉCTRICA | F65: 3288.9 | G65: 3148.7 | H65: 3685.15 | I65: 4109.8 | J65: 14232.55
B66: ENGIE ENERGIA PERU S.A.A. | C66: C.T. CHILCA 1 | D66: TG3 | E66: TERMOELÉCTRICA | F66: 3707.7 | G66: 3324.8 | H66: 4163.95 | I66: 4767.8 | J66: 15964.25
B67: ENGIE ENERGIA PERU S.A.A. | C67: C.T. CHILCA 1 | D67: TV | E67: TERMOELÉCTRICA | F67: 5457.75 | G67: 5248.05 | H67: 5927.9 | I67: 6429.85 | J67: 23063.55
B68: ENGIE ENERGIA PERU S.A.A. | C68: C.T. CHILCA 2 | D68: TG41 | E68: TERMOELÉCTRICA | J68: 0
B69: ENGIE ENERGIA PERU S.A.A. | C69: C.T. CHILCA 2 | D69: TV42 | E69: TERMOELÉCTRICA | J69: 0
B70: ENGIE ENERGIA PERU S.A.A. | C70: C.T. NEPI | D70: TG41 | E70: TERMOELÉCTRICA | J70: 0
B71: ENGIE ENERGIA PERU S.A.A. | C71: C.T. NEPI | D71: TG42 | E71: TERMOELÉCTRICA | J71: 0
B72: ENGIE ENERGIA PERU S.A.A. | C72: C.T. NEPI | D72: TG43 | E72: TERMOELÉCTRICA | J72: 0
B73: ENGIE ENERGIA PERU S.A.A. | C73: C.T. RF PLANTA ILO | D73: TG1 | E73: TERMOELÉCTRICA | J73: 0
B74: ENGIE ENERGIA PERU S.A.A. | C74: C.T. RF PLANTA ILO | D74: TG2 | E74: TERMOELÉCTRICA | G74: 354.4 | J74: 354.4
B75: ENGIE ENERGIA PERU S.A.A. | C75: C.T. RF PLANTA ILO | D75: TG3 | E75: TERMOELÉCTRICA | J75: 0
B76: FENIX POWER PERÚ | C76: C.T. FENIX | D76: GT11 | E76: TERMOELÉCTRICA | J76: 0
B77: FENIX POWER PERÚ | C77: C.T. FENIX | D77: GT12 | E77: TERMOELÉCTRICA | J77: 0
B78: FENIX POWER PERÚ | C78: C.T. FENIX | D78: TV10 | E78: TERMOELÉCTRICA | J78: 0
B79: GENERACIÓN ANDINA S.A.C. | C79: C.H. 8 DE AGOSTO | D79: CENTRAL | E79: HIDROELÉCTRICA | F79: 501.4 | G79: 485.75 | H79: 365.3 | I79: 492.5 | J79: 1844.95
B80: GENERACIÓN ANDINA S.A.C. | C80: C.H. EL CARMEN | D80: CENTRAL | E80: HIDROELÉCTRICA | F80: 190.5 | G80: 183.35 | H80: 174.55 | I80: 181.9 | J80: 730.3
B81: GENERADORA DE ENERGÍA DEL PERÚ | C81: C.H. ÁNGEL I | D81: CENTRAL | E81: HIDROELÉCTRICA | F81: 489.6 | G81: 489 | H81: 475.75 | I81: 479.85 | J81: 1934.2
B82: GENERADORA DE ENERGÍA DEL PERÚ | C82: C.H. ÁNGEL II | D82: CENTRAL | E82: HIDROELÉCTRICA | F82: 489.6 | G82: 489.6 | H82: 484.45 | I82: 486.95 | J82: 1950.6
B83: GENERADORA DE ENERGÍA DEL PERÚ | C83: C.H. ÁNGEL III | D83: CENTRAL | E83: HIDROELÉCTRICA | F83: 481.2 | G83: 480.85 | H83: 479.15 | I83: 478.4 | J83: 1919.6
B84: GENERADORA DE ENERGÍA DEL PERÚ | C84: C.H. LA JOYA | D84: CENTRAL | E84: HIDROELÉCTRICA | F84: 162.6 | G84: 161.2 | H84: 173.7 | I84: 175.5 | J84: 673
B85: GM OPERACIONES S.A.C. | C85: CT REFINERIA TALARA | D85: TV1 REF TALARA | E85: TERMOELÉCTRICA | F85: 658.2 | G85: 646.4 | H85: 664.7 | I85: 666.535 | J85: 2635.835
B86: GM OPERACIONES S.A.C. | C86: CT REFINERIA TALARA | D86: TV2 REF TALARA | E86: TERMOELÉCTRICA | F86: 824.05 | G86: 813.1 | H86: 833 | I86: 832.73 | J86: 3302.88
B87: GR CORTARRAMA SOCIEDAD ANONIMA CERRADA | C87: C.S. MATARANI | D87: C.S. MATARANI | E87: SOLAR | F87: 851.1 | G87: 853.5 | H87: 849.75 | I87: 755 | J87: 3309.35
B88: GR PAINO SOCIEDAD ANONIMA CERRADA | C88: C.E. HUAMBOS | D88: CENTRAL | E88: EÓLICA | F88: 145.55 | G88: 180.9 | H88: 74.1 | I88: 29.2 | J88: 429.75
B89: GR TARUCA SOCIEDAD ANONIMA CERRADA | C89: C.E. DUNA | D89: CENTRAL | E89: EÓLICA | F89: 150.7 | G89: 169.4 | H89: 76.05 | I89: 21.35 | J89: 417.5
B90: HIDROCAÑETE S.A. | C90: C.H. IMPERIAL | D90: CENTRAL | E90: HIDROELÉCTRICA | F90: 86.6 | G90: 85.1 | H90: 82.8 | I90: 81.75 | J90: 336.25
... B93: HYDRO GLOBAL PERÚ S.A.C. | C93: CH SAN GABAN III | D93: CENTRAL | E93: HIDROELÉCTRICA | F93: 4862.15 | G93: 4875.75 | H93: 4695.45 | I93: 4879.05 | J93: 19312.4
B94: INFRAESTRUCTURAS Y ENERGIAS DEL PERU S.A.C. | C94: C.T. RF PTO MALDONADO | D94: CENTRAL | E94: TERMOELÉCTRICA | I94: 0.9 | J94: 0.9
B95: INFRAESTRUCTURAS Y ENERGIAS DEL PERU S.A.C. | C95: C.T. RF PUCALLPA | D95: CENTRAL | E95: TERMOELÉCTRICA | F95: 1.65 | J95: 1.65
B96: INLAND ENERGY SAC | C96: C.H. SANTA TERESA | D96: CENTRAL | E96: HIDROELÉCTRICA | F96: 2166.95 | G96: 2157.8 | H96: 1991.55 | I96: 2005.55 | J96: 8321.85
B97: INVERSIONES SHAQSHA S.A.C. | C97: C.H. PARIAC | D97: CENTRAL | E97: HIDROELÉCTRICA | F97: 88 | G97: 86.15 | H97: 85.8 | I97: 87.7 | J97: 347.65
B98: JOYA SOLAR S.A.C. | C98: C.S. SAN MARTIN SOLAR | D98: CENTRAL | E98: SOLAR | F98: 2689.25 | G98: 2713.85 | H98: 357 | J98: 5760.1
B99: KALLPA GENERACION S.A. | C99: C.H. CERRO DEL AGUILA | D99: CENTRAL | E99: HIDROELÉCTRICA | F99: 9013 | G99: 5717.2 | H99: 8506.85 | I99: 7358.5 | J99: 30595.55
B100: KALLPA GENERACION S.A. | C100: C.S. SUNNY | D100: CENTRAL | E100: SOLAR | F100: 2296.7 | G100: 2300.2 | H100: 263.15 | J100: 4860.05
B101: KALLPA GENERACION S.A. | C101: C.T. KALLPA | D101: TG1 | E101: TERMOELÉCTRICA | F101: 3408.4 | G101: 3010.7 | H101: 3755.1 | I101: 3636.15 | J101: 13810.35
B102: KALLPA GENERACION S.A. | C102: C.T. KALLPA | D102: TG2 | E102: TERMOELÉCTRICA | F102: 3435.85 | G102: 3009.35 | H102: 3788.05 | I102: 3634.65 | J102: 13867.9
B103: KALLPA GENERACION S.A. | C103: C.T. KALLPA | D103: TG3 | E103: TERMOELÉCTRICA | F103: 3436.45 | G103: 3009.65 | H103: 3787.85 | I103: 3632.35 | J103: 13866.3
B104: KALLPA GENERACION S.A. | C104: C.T. KALLPA | D104: TV | E104: TERMOELÉCTRICA | F104: 5742.25 | G104: 5379.1 | H104: 5941.9 | I104: 5904 | J104: 22967.25
B105: KALLPA GENERACION S.A. | C105: C.T. LAS FLORES | D105: TG1 | E105: TERMOELÉCTRICA | F105: 927.2 | G105: 297.85 | H105: 1604.55 | I105: 173.4 | J105: 3003
...

Sheet G_AREAS
B3: martes, 4 de Noviembre del 2025
B5: HORA | C5: RESUMEN DE GENERACIÓN POR ÁREAS DEL SEIN | D5: RESUMEN DE GENERACIÓN POR ÁREAS DEL SEIN | E5: RESUMEN DE GENERACIÓN POR ÁREAS DEL SEIN | F5: RESUMEN DE GENERACIÓN POR ÁREAS DEL SEIN | G5: RESUMEN DE GENERACIÓN POR ÁREAS DEL SEIN | H5: RESUMEN DE GENERACIÓN POR ÁREAS DEL SEIN | I5: RESUMEN DE GENERACIÓN POR ÁREAS DEL SEIN | J5: RESUMEN DE GENERACIÓN POR ÁREAS DEL SEIN | K5: RESUMEN DE GENERACIÓN POR ÁREAS DEL SEIN | L5: RESUMEN DE GENERACIÓN POR ÁREAS DEL SEIN | M5: RESUMEN DE GENERACIÓN POR ÁREAS DEL SEIN | N5: RESUMEN DE GENERACIÓN POR ÁREAS DEL SEIN | O5: RESUMEN DE GENERACIÓN POR ÁREAS DEL SEIN | P5: RESUMEN DE GENERACIÓN POR ÁREAS DEL SEIN | Q5: RESUMEN DE GENERACIÓN POR ÁREAS DEL SEIN | R5: RESUMEN DE GENERACIÓN POR ÁREAS DEL SEIN | S5: HORA | T5: GENERACIÓN POR TIPO DE GENERACIÓN | U5: GENERACIÓN POR TIPO DE GENERACIÓN | V5: GENERACIÓN POR TIPO DE GENERACIÓN | W5: GENERACIÓN POR TIPO DE GENERACIÓN | X5: GENERACIÓN POR TIPO DE GENERACIÓN | Y5: HORA | Z5: GENERACIÓN POR TIPO DE GENERACIÓN | AA5: GENERACIÓN POR TIPO DE GENERACIÓN | AB5: GENERACIÓN POR TIPO DE GENERACIÓN | AC5: GENERACIÓN POR TIPO DE GENERACIÓN | AD5: GENERACIÓN POR TIPO DE GENERACIÓN
C6: NORTE | D6: NORTE | E6: NORTE | F6: NORTE | G6: CENTRO | H6: CENTRO | I6: CENTRO | J6: CENTRO | K6: SUR | L6: SUR | M6: SUR | N6: SUR | O6: GENERACIÓN INTEGRANTES COES | P6: GENERACIÓN INTEGRANTES COES | Q6: GENERACIÓN INTEGRANTES COES | R6: GENERACIÓN INTEGRANTES COES | T6: INTEGRANTES COES | U6: INTEGRANTES COES | V6: INTEGRANTES COES | W6: INTEGRANTES COES | X6: INTEGRANTES COES | Z6: INTEGRANTES COES RER | AA6: INTEGRANTES COES RER | AB6: INTEGRANTES COES RER | AC6: INTEGRANTES COES RER | AD6: INTEGRANTES COES RER
C7: GENERACIÓN HIDROELÉCTRICA NORTE | D7: GENERACIÓN TERMOELÉCTRICA NORTE | E7: GENERACIÓN SOLAR NORTE | F7: GENERACIÓN EÓLICA NORTE | G7: GENERACIÓN HIDROELÉCTRICA CENTRO | H7: GENERACIÓN TERMOELÉCTRICA CENTRO | I7: GENERACIÓN SOLAR CENTRO | J7: GENERACIÓN EÓLICA CENTRO | K7: GENERACIÓN HIDROELÉCTRICA SUR | L7: GENERACIÓN TERMOELÉCTRICA SUR | M7: GENERACIÓN SOLAR SUR | N7: GENERACIÓN EÓLICA SUR | O7: GENERACIÓN COES NORTE | P7: GENERACIÓN COES CENTRO | Q7: GENERACIÓN COES SUR | R7: TOTAL GENERACION | T7: HIDROELÉCTRICA | U7: TERMOELÉCTRICA | V7: SOLAR | W7: EÓLICA | X7: TOTAL GENERACION | Z7: HIDROELÉCTRICA RER | AA7: TERMOELÉCTRICA RER | AB7: SOLAR RER | AC7: EÓLICA RER | AD7: TOTAL RER
B8: 00:30 | C8: 371.9 | D8: 147.8 | E8: 0 | F8: 65.9 | G8: 2502.5 | H8: 2093.9 | I8: 0 | J8: 466.6 | K8: 727.1 | L8: 0 | M8: 0 | N8: 0 | O8: 585.6 | P8: 5063 | Q8: 727.1 | R8: 6375.7 | S8: 00:30 | T8: 3601.5 | U8: 2241.7 | V8: 0 | W8: 532.5 | X8: 6375.7 | Y8: 00:30 | Z8: 309 | AA8: 54.7 | AB8: 0 | AC8: 532.5 | AD8: 896.2
B9: 01:00 | C9: 366.6 | D9: 150.2 | E9: 0 | F9: 81.8 | G9: 2447.9 | H9: 2017.4 | I9: 0 | J9: 491.6 | K9: 713.5 | L9: 0 | M9: 0 | N9: 0 | O9: 598.6 | P9: 4956.9 | Q9: 713.5 | R9: 6269 | S9: 01:00 | T9: 3528 | U9: 2167.6 | V9: 0 | W9: 573.4 | X9: 6269 | Y9: 01:00 | Z9: 309.6 | AA9: 57.7 | AB9: 0 | AC9: 573.4 | AD9: 940.7
B10: 01:30 | C10: 367.5 | D10: 150.8 | E10: 0 | F10: 71.7 | G10: 2462.8 | H10: 1980.9 | I10: 0 | J10: 499.5 | K10: 700.1 | L10: 0 | M10: 0 | N10: 0 | O10: 590 | P10: 4943.2 | Q10: 700.1 | R10: 6233.3 | S10: 01:30 | T10: 3530.4 | U10: 2131.7 | V10: 0 | W10: 571.2 | X10: 6233.3 | Y10: 01:30 | Z10: 307.4 | AA10: 58 | AB10: 0 | AC10: 571.2 | AD10: 936.6
B11: 02:00 | C11: 371.5 | D11: 150.2 | E11: 0 | F11: 62.9 | G11: 2452.2 | H11: 1917.7 | I11: 0 | J11: 496.9 | K11: 700.8 | L11: 0 | M11: 0 | N11: 0 | O11: 584.6 | P11: 4866.8 | Q11: 700.8 | R11: 6152.2 | S11: 02:00 | T11: 3524.5 | U11: 2067.9 | V11: 0 | W11: 559.8 | X11: 6152.2 | Y11: 02:00 | Z11: 305.3 | AA11: 57.1 | AB11: 0 | AC11: 559.8 | AD11: 922.2
B12: 02:30 | C12: 375.3 | D12: 149.8 | E12: 0 | F12: 53.9 | G12: 2408.2 | H12: 1856.7 | I12: 0 | J12: 461.6 | K12: 694.2 | L12: 0 | M12: 0 | N12: 0 | O12: 579 | P12: 4726.5 | Q12: 694.2 | R12: 5999.7 | S12: 02:30 | T12: 3477.7 | U12: 2006.5 | V12: 0 | W12: 515.5 | X12: 5999.7 | Y12: 02:30 | Z12: 304.2 | AA12: 58 | AB12: 0 | AC12: 515.5 | AD12: 877.7
B13: 03:00 | C13: 373.9 | D13: 149.2 | E13: 0 | F13: 50.9 | G13: 2445.8 | H13: 1883.3 | I13: 0 | J13: 482.7 | K13: 692.8 | L13: 0 | M13: 0 | N13: 0 | O13: 574 | P13: 4811.8 | Q13: 692.8 | R13: 6078.6 | S13: 03:00 | T13: 3512.5 | U13: 2032.5 | V13: 0 | W13: 533.6 | X13: 6078.6 | Y13: 03:00 | Z13: 305.3 | AA13: 59.2 | AB13: 0 | AC13: 533.6 | AD13: 898.1
B14: 03:30 | C14: 373.2 | D14: 151.4 | E14: 0 | F14: 56 | G14: 2314.6 | H14: 1899.9 | I14: 0 | J14: 496.4 | K14: 683.5 | L14: 0 | M14: 0 | N14: 0 | O14: 580.6 | P14: 4710.9 | Q14: 683.5 | R14: 5975 | S14: 03:30 | T14: 3371.3 | U14: 2051.3 | V14: 0 | W14: 552.4 | X14: 5975 | Y14: 03:30 | Z14: 305.6 | AA14: 58.4 | AB14: 0 | AC14: 552.4 | AD14: 916.4
B15: 04:00 | C15: 375.5 | D15: 149.4 | E15: 0 | F15: 55.2 | G15: 2363.4 | H15: 1984.5 | I15: 0 | J15: 476.7 | K15: 700.3 | L15: 0 | M15: 0 | N15: 0 | O15: 580.1 | P15: 4824.6 | Q15: 700.3 | R15: 6105 | S15: 04:00 | T15: 3439.2 | U15: 2133.9 | V15: 0 | W15: 531.9 | X15: 6105 | Y15: 04:00 | Z15: 306 | AA15: 58 | AB15: 0 | AC15: 531.9 | AD15: 895.9
B16: 04:30 | C16: 375.1 | D16: 148.3 | E16: 0 | F16: 54 | G16: 2307.9 | H16: 1957.4 | I16: 0 | J16: 459.3 | K16: 703.4 | L16: 0 | M16: 0 | N16: 0 | O16: 577.4 | P16: 4724.6 | Q16: 703.4 | R16: 6005.4 | S16: 04:30 | T16: 3386.4 | U16: 2105.7 | V16: 0 | W16: 513.3 | X16: 6005.4 | Y16: 04:30 | Z16: 308.2 | AA16: 56.4 | AB16: 0 | AC16: 513.3 | AD16: 877.9
B17: 05:00 | C17: 375.3 | D17: 148.7 | E17: 0 | F17: 55.7 | G17: 2299.8 | H17: 2137.4 | I17: 0 | J17: 460.3 | K17: 708.2 | L17: 0 | M17: 0.1 | N17: 0 | O17: 579.7 | P17: 4897.5 | Q17: 708.3 | R17: 6185.5 | S17: 05:00 | T17: 3383.3 | U17: 2286.1 | V17: 0.1 | W17: 516 | X17: 6185.5 | Y17: 05:00 | Z17: 307.9 | AA17: 55 | AB17: 0.1 | AC17: 516 | AD17: 879
B18: 05:30 | C18: 375.2 | D18: 150.3 | E18: 0 | F18: 58 | G18: 2394.8 | H18: 2152.9 | I18: 0 | J18: 435.9 | K18: 708.3 | L18: 0 | M18: 16.8 | N18: 0 | O18: 583.5 | P18: 4983.6 | Q18: 725.1 | R18: 6292.2 | S18: 05:30 | T18: 3478.3 | U18: 2303.2 | V18: 16.8 | W18: 493.9 | X18: 6292.2 | Y18: 05:30 | Z18: 305.4 | AA18: 56.6 | AB18: 16.8 | AC18: 493.9 | AD18: 872.7
B19: 06:00 | C19: 386.8 | D19: 150.4 | E19: 0 | F19: 50.4 | G19: 2314.7 | H19: 2030.7 | I19: 0 | J19: 430.7 | K19: 726.9 | L19: 0 | M19: 115.4 | N19: 0 | O19: 587.6 | P19: 4776.1 | Q19: 842.3 | R19: 6206 | S19: 06:00 | T19: 3428.4 | U19: 2181.1 | V19: 115.4 | W19: 481.1 | X19: 6206 | Y19: 06:00 | Z19: 305 | AA19: 57.1 | AB19: 115.4 | AC19: 481.1 | AD19: 958.6
... B56: TOTAL MWh | C56: 9056.3 | D56: 3062.865 | E56: 2.9 | F56: 1810.65 | G56: 63477.15 | H56: 52739.25 | I56: 6.75 | J56: 12712.2 | K56: 17597.1 | L56: 371.7 | M56: 4286.75 | N56: 0 | O56: 13932.715 | P56: 128935.35 | Q56: 22255.55 | R56: 165123.61 | S56: TOTAL MWh | T56: 90130.55 | U56: 56173.815 | V56: 4296.4 | W56: 14522.85 | X56: 165123.61 | Y56: TOTAL MWh | Z56: 7426.25 | AA56: 1351.2 | AB56: 4296.4 | AC56: 14522.85 | AD56: 27596.7

Sheet HOP
B3: martes, 4 de Noviembre del 2025
B5: Reporte de Horas de Operación
B6: Empresa | C6: Central | D6: Grupo | E6: Modo de Operación | F6: Inicio | G6: Final | H6: O. Arranque | I6: O. Parada | J6: Tipo Operación | K6: Ensayo de Potencia Efectiva | L6: Ensayo de Potencia Mínima | M6: Sistema | N6: Lim. Transm. | O6: Causa | P6: Observación
B7: AGRO INDUSTRIAL PARAMONGA S.A. | C7: C.T. PARAMONGA | D7: CENTRAL | E7: PARAMONGA - BAGAZO | F7: 04/11/2025 00:00:00 | G7: 04/11/2025 10:27:00 | J7: POR COGENERACION | O7: ...
B8: AGRO INDUSTRIAL PARAMONGA S.A. | C8: C.T. PARAMONGA | D8: CENTRAL | E8: PARAMONGA - BAGAZO | F8: 04/11/2025 11:43:00 | G8: 05/11/2025 00:00:00 | H8: 04/11/2025 11:07:00 | J8: POR COGENERACION | O8: ...
B9: AGROAURORA S.A.C. | C9: C.T. MAPLE ETANOL | D9: CENTRAL | E9: MAPLE- BAGAZO | F9: 04/11/2025 00:00:00 | G9: 04/11/2025 21:47:00 | J9: POR COGENERACION | O9: ...
B10: AGROINDUSTRIAS SAN JACINTO S.A.A. | C10: C.T. SAN JACINTO | D10: CENTRAL | E10: SAN_JACINTO - BAGAZO | F10: 04/11/2025 12:42:00 | G10: 05/11/2025 00:00:00 | H10: 04/11/2025 12:35:00 | J10: POR COGENERACION | O10: ...
B11: AGROLMOS SOCIEDAD ANONIMA - AGROLMOS S.A. | C11: C.T. AGROLMOS | D11: CENTRAL | E11: AGROLMOS TV1 & TV2 - BAGAZO | F11: 04/11/2025 00:00:00 | G11: 05/11/2025 00:00:00 | H11: 04/11/2025 07:09:00 | J11: POR COGENERACION | O11: ...
B12: BIOENERGIA DEL CHIRA S.A. | C12: C.T. CAÑA BRAVA | D12: G-1 | E12: CANA BRAVA TV1 - BAGAZO | F12: 04/11/2025 00:00:00 | G12: 05/11/2025 00:00:00 | J12: POR COGENERACION | O12: ...
B13: EGESUR | C13: C.T. INDEPENDENCIA | D13: INDEP_G4 | E13: INDEPENDENCIA GAS | F13: 04/11/2025 00:00:00 | G13: 05/11/2025 00:00:00 | J13: POR PRUEBAS | O13: ...
B14: ENEL GENERACION PIURA S.A. | C14: C.T. MALACAS 1 | D14: CENTRAL | E14: MALACAS1 TG6 - GAS | F14: 04/11/2025 00:00:00 | G14: 04/11/2025 13:49:00 | I14: 04/11/2025 13:29:00 | J14: POR POTENCIA O ENERGIA | O14: ...
B15: ENGIE ENERGIA PERU S.A.A. | C15: C.T. CHILCA 1 | D15: CENTRAL | E15: CHILCA1 CCOMB TG1 & TG2 & TG3 - GAS | F15: 04/11/2025 00:00:00 | G15: 05/11/2025 00:00:00 | J15: POR POTENCIA O ENERGIA | O15: ... | P15: A las 07:26 h, S/C generar a 730 MW. A las 07:43 h, S/C generar a 630 MW. A las 08:01 h, S/C generar a 730 MW. A las 08:04 h, S/C generar a máxima generación.
B16: GM OPERACIONES S.A.C. | C16: CT REFINERIA TALARA | D16: TV1 REF TALARA | E16: REF_TALARA TV1 - NLH_RFG | F16: 04/11/2025 00:00:00 | G16: 05/11/2025 00:00:00 | J16: POR COGENERACION | O16: ...
B17: GM OPERACIONES S.A.C. | C17: CT REFINERIA TALARA | D17: TV2 REF TALARA | E17: REF_TALARA TV2 - NLH_RFG | F17: 04/11/2025 00:00:00 | G17: 05/11/2025 00:00:00 | J17: POR COGENERACION | O17: ...
B18: INFRAESTRUCTURAS Y ENERGIAS DEL PERU S.A.C. | C18: C.T. RF PTO MALDONADO | D18: CENTRAL | E18: RF PTO MALDONADO - D2 | F18: 04/11/2025 09:01:00 | G18: 04/11/2025 09:57:00 | H18: 04/11/2025 08:58:00 | I18: 04/11/2025 09:56:00 | J18: POR PRUEBAS | O18: ... | P18: Opero el grupo G4
B19: KALLPA GENERACION S.A. | C19: C.T. KALLPA | D19: CENTRAL | E19: KALLPA CCOMB TG1 & TG2 & TG3 - GAS | F19: 04/11/2025 00:00:00 | G19: 05/11/2025 00:00:00 | J19: POR POTENCIA O ENERGIA | O19: ...
B20: KALLPA GENERACION S.A. | C20: C.T. LAS FLORES | D20: TG1 | E20: LAS FLORES TG1 - GAS | F20: 04/11/2025 00:00:00 | G20: 04/11/2025 00:40:00 | J20: POR POTENCIA O ENERGIA | O20: ...
B21: KALLPA GENERACION S.A. | C21: C.T. LAS FLORES | D21: TG1 | E21: LAS FLORES TG1 - GAS | F21: 04/11/2025 00:40:00 | G21: 04/11/2025 01:33:00 | I21: 04/11/2025 01:18:00 | J21: A MINIMA CARGA | O21: ...
B22: ORYGEN PERU S.A.A. | C22: C.T. VENTANILLA | D22: TG3 | E22: VENTANILLA TG3 - GAS | F22: 04/11/2025 02:37:00 | G22: 04/11/2025 04:26:00 | H22: 04/11/2025 02:14:00 | J22: A MINIMA CARGA | O22: ... | P22: En proceso de acople en modo CC
B23: ORYGEN PERU S.A.A. | C23: C.T. VENTANILLA | D23: CENTRAL | E23: VENTANILLA CCOMB TG3 - GAS | F23: 04/11/2025 04:26:00 | G23: 04/11/2025 06:41:00 | J23: POR POTENCIA O ENERGIA | O23: ... | P23: En proceso de acople en modo 2X1
B24: ORYGEN PERU S.A.A. | C24: C.T. VENTANILLA | D24: TG4 | E24: VENTANILLA TG4 - GAS | F24: 04/11/2025 05:11:00 | G24: 04/11/2025 07:01:00 | H24: 04/11/2025 04:40:00 | J24: A MINIMA CARGA | O24: ...
B25: ORYGEN PERU S.A.A. | C25: C.T. VENTANILLA | D25: CENTRAL | E25: VENTANILLA CCOMB TG3 - GAS | F25: 04/11/2025 06:41:00 | G25: 04/11/2025 07:01:00 | J25: A MINIMA CARGA | O25: ... | P25: En proceso de acople en modo 2X1
B26: ORYGEN PERU S.A.A. | C26: C.T. VENTANILLA | D26: CENTRAL | E26: VENTANILLA CCOMB TG3 & TG4 - GAS | F26: 04/11/2025 07:01:00 | G26: 05/11/2025 00:00:00 | J26: POR POTENCIA O ENERGIA | O26: ...
B27: PETRAMAS | C27: C.T. HUAYCOLORO | D27: G1 | E27: HUAYCOLORO - BIOGAS | F27: 04/11/2025 00:00:00 | G27: 05/11/2025 00:00:00 | J27: POR POTENCIA O ENERGIA | O27: ...
B28: PETRAMAS | C28: C.T. LA GRINGA | D28: G2 | E28: LA GRINGA V - BIOGAS | F28: 04/11/2025 00:00:00 | G28: 05/11/2025 00:00:00 | J28: POR POTENCIA O ENERGIA | O28: ...
B29: PETRAMAS | C29: C.T.B DOÑA CATALINA | D29: CENTRAL | E29: DONA CATALINA - BIOGAS | F29: 04/11/2025 00:00:00 | G29: 05/11/2025 00:00:00 | J29: POR POTENCIA O ENERGIA | O29: ...
B30: SAMAY I S.A.C | C30: C.T. PUERTO BRAVO | D30: TG4 | E30: PTO BRAVO TG4 - D2 | F30: 04/11/2025 17:51:00 | G30: 04/11/2025 20:24:00 | H30: 04/11/2025 17:27:00 | I30: 04/11/2025 20:11:00 | J30: POR PRUEBAS ALEATORIAS PR-25 | O30: ... | P30: A las 18:10 h, alcanzó su máxima generación
B31: TERMOCHILCA S.A.C. | C31: C.T. OLLEROS | D31: CENTRAL | E31: OLLEROS CCOMB TG1 - GAS | F31: 04/11/2025 00:00:00 | G31: 05/11/2025 00:00:00 | J31: POR POTENCIA O ENERGIA | O31: ...

Sheet INDISP
B3: martes, 4 de Noviembre del 2025
B5: Hora Inicio y Fin de Indisponibilidades de las Unidades de Generación SEIN
B6: Empresa | C6: Ubicación | D6: Equipo | E6: Inicio | F6: Final | G6: Descripción | H6: MW Indisp. | I6: Prog. | J6: Dispon | K6: Interrupc. | L6: Tipo | M6: CodEq | N6: TipoEq_Osinerg
B7: AGROINDUSTRIAS SAN JACINTO S.A.A. | C7: SAN JACINTO | D7: CENTRAL | E7: 04/11/2025 00:00 | F7: 05/11/2025 00:00 | G7: Mantenimiento Mensual | H7: 8.15 | I7: P | J7: F/S | K7: N | L7: PREV. | M7: 19865 | N7: G
B8: ATRIA ENERGIA S.A.C. | C8: PURMACANA | D8: CENTRAL | E8: 04/11/2025 00:00 | F8: 05/11/2025 00:00 | G8: MANTENIMIENTO DE CANAL DE CONDUCCIÓN, COMPUERTAS, SISTEMA DE LUBRICACIÓN DE COJINETES, SISTEMA DE REFRIGERACIÓN Y VÁLVULAS | H8: 0.4 | I8: P | J8: F/S | K8: N | L8: PREV. | M8: 13132 | N8: G
B9: EGASA | C9: CHARCANI IV | D9: G2 | E9: 04/11/2025 07:19 | F9: 04/11/2025 18:43 | G9: Cambio tuberias sistema refrigeracion | H9: 5.136 | I9: P | J9: F/S | K9: N | L9: PREV. | M9: 119 | N9: G
B10: EGASA | C10: CHARCANI IV | D10: G3 | E10: 04/11/2025 08:44 | F10: 04/11/2025 11:53 | G10: Desconexión intempestiva por falla en investigación | H10: 5.2 | I10: F | J10: F/S | K10: N | L10: OTROS | M10: 120 | N10: G
B11: EGESUR | C11: INDEPENDENCIA | D11: INDEP_G4 | E11: 04/11/2025 00:00 | F11: 05/11/2025 00:00 | G11: Mantenimiento por 32,000 horas de operación | H11: 5.732 | I11: P | J11: F/S | K11: N | L11: PREV. | M11: 12780 | N11: G
B12: ELECTROPERU | C12: MANTARO | D12: G1 | E12: 04/11/2025 04:07 | F12: 04/11/2025 05:26 | G12: MANTT. CORRECTIVO.CAMBIO REG. VELOCIDAD. | H12: 101 | I12: P | J12: F/S | K12: N | L12: CORR. | M12: 1 | N12: G
B13: EMPRESA DE GENERACION ELECTRICA SANTA ANA S.A.C. | C13: RENOVANDES H1 | D13: G1 | E13: 04/11/2025 00:00 | F13: 05/11/2025 00:00 | G13: Reemplazo del estator del grupo generador en la Central Hidroeléctrica Renovandes H1 | H13: 20 | I13: P | J13: F/S | K13: N | L13: PREV. | M13: 18265 | N13: G
B14: ENGIE ENERGIA PERU S.A.A. | C14: PUNTA LOMITAS | D14: PL-BL1 | E14: 04/11/2025 08:16 | F14: 04/11/2025 17:14 | G14: BARRA A 33KV F/S POR REPARACION DE CABLE DE ALIMENTACIÓN 33kV TRANSFORMADOR PRINCIPAL TP-1 SE PUNTA LOMITAS | H14: 0 | I14: P | J14: F/S | K14: N | L14: CORR. | M14: 22377 | N14: G
B15: ENGIE ENERGIA PERU S.A.A. | C15: YUNCÁN | D15: G1 | E15: 04/11/2025 00:00 | F15: 04/11/2025 13:59 | G15: APLICACIÓN DE RESINA EN PUNTOS DE DESCARGAS PARCIALES Y PRUEBAS OFFLINE | H15: 45.5 | I15: P | J15: F/S | K15: N | L15: PREV. | M15: 199 | N15: G
B16: ENGIE ENERGIA PERU S.A.A. | C16: YUNCÁN | D16: G3 | E16: 04/11/2025 12:00 | F16: 04/11/2025 21:00 | G16: PRUEBA DE DESCARGAS PARCIALES OFFLINE G3 | H16: 45.5 | I16: P | J16: F/S | K16: N | L16: PREV. | M16: 201 | N16: G
B17: ENGIE ENERGIA PERU S.A.A. | C17: YUNCÁN | D17: G3 | E17: 04/11/2025 21:00 | F17: 05/11/2025 00:00 | G17: APLICACIÓN DE RESINA EN PUNTOS DE DESCARGAS PARCIALES Y PRUEBAS OFFLINE | H17: 45.5 | I17: P | J17: F/S | K17: N | L17: PREV. | M17: 201 | N17: G
B18: FENIX POWER PERÚ | C18: FENIX | D18: TV10 | E18: 04/11/2025 00:00 | F18: 05/11/2025 00:00 | G18: Unidad fuera de servicio por mantenimiento correctivo del Transformador TR-TV10. | H18: 0 | I18: P | J18: F/S | K18: N | L18: OTROS | M18: 13602 | N18: G
... B41: STATKRAFT S.A | C41: PACHACHACA | D41: G1 | E41: 04/11/2025 00:00 | F41: 05/11/2025 00:00 | G41: MANTENIMIENTO MAYOR UG1 + Mantenimiento Sistema de Control UG1 + Prueba de protecciones T1 | H41: 3 | I41: P | J41: F/S | K41: N | L41: PREV. | M41: 46 | N41: G

Sheet RESERVA_FRÍA
B3: 04/11/2025 | E3: EJECUTADO | L3: Martes 4 de Noviembre del 2025 / SEM N° 44 | V3: EJECUTADO | AC3: Martes 4 de Noviembre del 2025 / SEM N° 44 | EE3: ENERGIA RENOVABLES | GS3: COGENERACION | HA3: NO INTEGRANTES
B4: Martes | C4: HYDROG | D4: ELECTROPERU | H4: ORAZU | J4: TER | L4: KALLPA GENERACION S.A. | T4: SHOUGESA | X4: EGM | Y4: EGESUR | AB4: EGASA | AI4: SGB | AJ4: CELEP | AK4: MINCVE | AL4: ETEN | AN4: HUALLA | AP4: LAVI | AQ4: CHIN | AS4: HUANCH | AT4: CELER | AU4: INLD | AV4: FENIX POWER PERÚ | AY4: STATKRAFT S.A | BG4: STARO | BI4: HUANZA | BJ4: ENEL GENERACION PIURA S.A. | BM4: ENGIE ENERGIA PERU S.A.A. | CA4: IYEP | CC4: SHAQSH | CD4: ORYGEN PERU S.A.A. | CP4: SAMAY I S.A.C | CT4: TCHILC | CV4: GENERACION | CY4: SALIDAS YUPANA | DC4: FLUJO EN LINEAS | DO4: COSTOS MARGINALES | DS4: RESERVA | DX4: DEMANDA POR AREAS | EE4: ACHI | EF4: COLCA | EG4: ERSUR | EH4: GRCOR | EI4: TARU | EJ4: KONDU | EK4: PIEREN | EL4: VARI | EM4: ORAZU | EO4: KALLPA | EP4: SGB | EQ4: AIPSA | ER4: MAJA | ES4: EGECSA | ET4: STANA | EU4: AGUAA | EV4: RDOBLE | EW4: HIDRO | EX4: HUARA | EY4: MOQUE | EZ4: PANAM | FA4: PARQU | FB4: PE3HER | FC4: TACNA | FD4: EYSAC | FE4: AURORA | FF4: AGROIN | FG4: AGROLM | FH4: ANDEA | FI4: ASLC | FJ4: ATRIA | FK4: EGEJUNIN | FO4: EGERBA | FP4: EOL | FR4: ENGIE ENERGIA PERU S.A.A. | FW4: GENE | FY4: GENERADORA DE ENERGÍA DEL PERÚ | GC4: PAINO | GD4: JOYAS | GE4: SARCUS | GF4: ORYGEN PERU S.A.A. | GK4: PETRAMAS | GO4: RARCUS | GP4: SINERS | GS4: ACHI | GT4: GM OP | GV4: AIPSA | GW4: AURORA | GX4: AGROIN | GY4: AGROLM | HA4: UNACEM | HB4: EOR | HC4: AYEP | HD4: ELZANA | HE4: ENOSA | HF4: SDE | HG4: SINERS
C5: #### | D5: 101 | E5: 102 | F5: #### | G5: 42668 | H5: 126 | I5: 127 | J5: 138 | K5: 139 | L5: 197 | M5: 203 | N5: 204 | O5: 230 | P5: 209 | Q5: 56677 | R5: 796 | S5: 2146 | T5: 142 | U5: 143 | V5: 125 | W5: 187 | X5: 163 | Y5: 298 | Z5: 299 | AA5: 219 | AB5: 151 | AC5: 152 | AD5: 153 | AE5: 154 | AF5: 756 | AG5: 156 | AH5: 155 | AI5: 182 | AJ5: 212 | AK5: 758 | AL5: 263 | AM5: 265 | AN5: 775 | AO5: 777 | AP5: 2154 | AQ5: 150 | AR5: 149 | AS5: 188 | AT5: 2131 | AU5: 755 | AV5: 252 | AW5: 249 | AX5: 250 | AY5: 117 | AZ5: 267 | BA5: 268 | BB5: 119 | BC5: 120 | BD5: 189 | BE5: 122 | BF5: 266 | BG5: 337 | BH5: 338 | BI5: 251 | BJ5: 115 | BK5: 239 | BL5: 288 | BM5: 240 | BN5: 241 | BO5: 242 | BP5: 191 | BQ5: 194 | BR5: 196 | BS5: 207 | BT5: 236 | BU5: 795 | BV5: 285 | BW5: 995 | BX5: 996 | BY5: 997 | BZ5: 766 | CA5: 926 | CB5: 924 | CC5: 121 | CD5: 103 | CE5: 104 | CF5: 106 | CG5: 105 | CH5: 107 | CI5: 110 | CJ5: 109 | CK5: 144 | CL5: 113 | CM5: 114 | CN5: 193 | CO5: 208 | CP5: 786 | CQ5: 787 | CR5: 788 | CS5: 789 | CT5: 248 | CU5: 2159 | CV5: -1222 | CW5: -1223 | CX5: -1224 | CY5: 1221 | CZ5: 1222 | DA5: 1223 | DB5: 1224 | DC5: 1250 | DD5: 1251 | DE5: 1252 | DF5: 1253 | DG5: 1254 | DH5: 1255 | DI5: 1256 | DJ5: 1257 | DK5: 1258 | DL5: 1259 | DM5: 1260 | DN5: 1261 | DO5: 1226 | DP5: 1219 | DQ5: 1220 | DR5: #### | DS5: 1227 | DT5: 1205 | DU5: 1207 | DV5: 1206 | DW5: 1218 | DX5: 1211 | DY5: 1212 | DZ5: 1213 | EA5: 1214 | EB5: 1229 | EC5: #### | EE5: 289 | EF5: 303 | EG5: #### | EH5: #### | EI5: 1263 | EJ5: #### | EK5: 2194 | EL5: #### | EM5: 216 | EN5: 198 | EO5: 70400 | EP5: 49607 | EQ5: 213 | ER5: 214 | ES5: 260 | ET5: 2152 | EU5: 2128 | EV5: 247 | EW5: 228 | EX5: 2135 | EY5: 261 | EZ5: 237 | FA5: 253 | FB5: 770 | FC5: 235 | FD5: 238 | FE5: 232 | FF5: 2190 | FG5: #### | FH5: 2184 | FI5: 61855 | FJ5: 223 | FK5: 226 | FL5: 201 | FM5: 258 | FN5: 259 | FO5: 920 | FP5: 257 | FQ5: 256 | FR5: 2148 | FS5: 58288 | FT5: 58289 | FU5: 58839 | FV5: 58840 | FW5: 296 | FX5: 297 | FY5: 211 | FZ5: 2175 | GA5: 2178 | GB5: 2181 | GC5: 1262 | GD5: 63425 | GE5: 233 | GF5: 2150 | GG5: 2165 | GH5: 2161 | GI5: 61197 | GJ5: 58851 | GK5: 225 | GL5: 2201 | GM5: 2171 | GN5: 760 | GO5: 234 | GP5: 215 | GQ5: 917 | GS5: 289 | GT5: 58333 | GU5: 58336 | GV5: 213 | GW5: 232 | GX5: 2190 | GY5: 69867 | HA5: 221 | HB5: 222 | HC5: 224 | HD5: 2187 | HE5: 227 | HF5: 49400 | HG5: 199 | HH5: 200 | HJ5: 7000 | HK5: 7001 | HL5: 7002
B6: Día Hora | C6: SAN GABAN III | D6: MANTARO | E6: RESTITUCION | F6: TUMBES MAK 1 | G6: TUMBES MAK 2 | H6: CARHUAQUERO | I6: CAÑON DEL PATO | J6: AGUAYTIA TG1 | K6: AGUAYTIA TG2 | L6: KALLPA TG1 | M6: KALLPA TG2 | N6: KALLPA TG3 | O6: KALLPA TV | P6: LFLORES TG1 | Q6: LFLORES TV | R6: CERRO DEL AGUILA | S6: CERRODELAGUILAG4 | T6: SHOUGESA TV1 | U6: SHOUGESA TV2 | V6: SHOUGESA TV3 | W6: SHOUGESA CUMMINS | X6: MACHUPICCHU | Y6: ARICOTA 1 | Z6: ARICOTA 2 | AA6: INDEPENDENCIA | AB6: CHARCANI I,II,III | AC6: CHARCANI IV | AD6: CHARCANI V | AE6: CHARCANI VI | AF6: CHILINA TG | AG6: MOLLENDO 1, 2, 3 | AH6: CHILINA (SULZ 1,2) | AI6: SAN GABAN II | AJ6: PLATANAL | AK6: RECKA | AL6: RF ETEN TG1 | AM6: RF ETEN TG2 | AN6: CHAGLLA GP1 | AO6: CHAGLLA | AP6: LA VIRGEN | AQ6: CHIMAY | AR6: YANANGO | AS6: HUANCHOR | AT6: MARAÑON | AU6: STA TERESA | AV6: FENIX GT11 | AW6: FENIX GT12 | AX6: FENIX TV10 | AY6: YAUPI | AZ6: OROYA | BA6: PACHACHACA | BB6: MALPASO | BC6: CAHUA | BD6: ARCATA | BE6: GALLITO CIEGO | BF6: CHEVES | BG6: SANTA ROSA 1 | BH6: SANTA ROSA 2 | BI6: HUANZA | BJ6: MALACAS2 TG4 | BK6: MALACAS3 TG 5 | BL6: MALACAS1 TG6 | BM6: RF ILO2 TG1 | BN6: RF ILO2 TG2 | BO6: RF ILO2 TG3 | BP6: YUNCAN | BQ6: CHILCA1 TG1 | BR6: CHILCA1 TG2 | BS6: CHILCA1 TG3 | BT6: CHILCA-TV | BU6: CHILCA2 TG41 | BV6: CHILCA2-TV | BW6: CTNEPI_TG41 | BX6: CTNEPI_TG42 | BY6: CTNEPI_TG43 | BZ6: QUITARACSA | CA6: RF PTO MALDONADO | CB6: RF PUCALLPA | CC6: PARIAC | CD6: HUINCO | CE6: MATUCANA | CF6: MOYOPAMPA | CG6: CALLAHUANCA | CH6: HUAMPANI | CI6: STA ROSA WEST TG7 | CJ6: UTI_5 | CK6: UTI_6 | CL6: VENTANILLA 3 | CM6: VENTANILLA 4 | CN6: VENTANILLA TV | CO6: STAROSA TG8 | CP6: PTO_BRVO TG1 | CQ6: PTO_BRVO TG2 | CR6: PTO_BRVO TG3 | CS6: PTO_BRVO TG4 | CT6: OLLEROS TG1 | CU6: OLLEROS TV | CV6: Total CoGeneracion | CW6: Total Renovables | CX6: Total Generación COES | CY6: Demanda YUPANA | CZ6: Oferta | DA6: Perdidas YUPANA | DB6: Deficit YUPANA | DC6: FLUJO ENLACE CENTRO - SUR | DD6: FLUJO CHILCA CARAPONGO 500 KV | DE6: FLUJO CARAPONGO CARABAYLLO 500 KV | DF6: FLUJO CHIMBOTE TRUJILLO 500 KV | DG6: FLUJO TRUJILLO LA NIÑA 500 KV | DH6: FLUJO COLCABAMBA POROMA 500 KV | DI6: FLUJO CHILCA POROMA 500 KV | DJ6: FLUJO POROMA YARABAMBA 500 KV | DK6: FLUJO POROMA OCOÑA 500 KV | DL6: FLUJO YARABAMBA MOLTALVO 500 KV | DM6: FLUJO HUANCAVELICA - INDEPENDENCIA 220 KV | DN6: FLUJO CHILCA - SAN JUAN 220 KV | DO6: Cmg Santa Rosa YUPANA(US$/MWh) | DP6: Cmg Trujillo YUPANA(US$/MWh) | DQ6: Cmg Socabaya YUPANA(US$/MWh) | DR6: Nivel de Demanda | DS6: Reserva Fría Térmica | DT6: Reserva Eficiente | DU6: Reserva Eficiente Gas | DV6: Reserva Eficiente Carbón | DW6: Nivel Tablachaca | DX6: Demanda Centro | DY6: Demanda Norte | DZ6: Demanda Sur | EA6: Demanda Electroandes | EB6: Demanda Ecuador | EC6: Demanda COES | EE6: CANA BRAVA | EF6: CS YARUCAYA | EG6: SAN JUAN | EH6: MATARANI | EI6: DUNA | EJ6: CARHUAQUERO (CS) | EK6: MANTA I | EL6: ANASHIRONI | EM6: CARHUAQUERO4 | EN6: CAÑA BRAVA | EO6: SUNNY | EP6: TUPURI | EQ6: PARAMONGA | ER6: RONCADOR | ES6: CANCHAYLLO | ET6: RENOVANDESH1 | EU6: POTRERO | EV6: PIZARRAS | EW6: NIMPERIAL | EX6: YARUCAYA | EY6: MOQUEGUA-SOLAR | EZ6: PANAMERICANA-SOLAR | FA6: PQE-EOLICO-MARCONA | FB6: PQE-EOLICO-3-HERMANAS | FC6: TACNA-SOLAR | FD6: YANAPAMPA | FE6: MAPLE | FF6: SAN_JACINTO | FG6: AGROLMOS | FH6: CARHUAC | FI6: HUALLIN | FJ6: PURMACANA | FK6: HUASAHUASI | FL6: STACRUZ_1_2 | FM6: RUNATULLO_II | FN6: RUNATULLO_III | FO6: RUCUY | FP6: PQE-EOLICO-TALARA | FQ6: PQE-EOLICO-CUPISNIQUE | FR6: INTIPAMPA | FS6: PUNTA LOMITAS-BL1 | FT6: PUNTA LOMITAS-BL2 | FU6: PUN LOMITAS_EXP-BL1 | FV6: PUN LOMITAS_EXP-BL2 | FW6: 45877 | FX6: EL CARMEN | FY6: LA JOYA | FZ6: ANGEL_I | GA6: ANGEL_II | GB6: ANGEL_III | GC6: HUAMBOS | GD6: SAN MARTIN SOLAR | GE6: MAJES | GF6: RUBI | GG6: CH_HER1 | GH6: WAYRA-I | GI6: WAYRA EXTENSION | GJ6: CLEMESI | GK6: HUAYCOLORO | GL6: CALLAO | GM6: DONA_CATALINA | GN6: LAGRINGAV | GO6: REPARTICION | GP6: POECHOS2 | GQ6: CHANCAY | GS6: CANA BRAVA | GT6: REFINERIA TALARA TV1 | GU6: REFINERÍA TALARA TV2 | GV6: PARAMONGA | GW6: MAPLE | GX6: SAN_JACINTO | GY6: AGROLMOS | HA6: CARPAPATA | HB6: CENTRALES ELOR | HC6: PIAS1 | HD6: ZANA | HE6: TABLAZO | HF6: TALLANCA | HG6: CURUMUY | HH6: POECHOS1 | HJ6: ReservaFriaTermica | HK6: ReservaFria Rapida Termica | HL6: ReservaFria Termica xMantenimiento
B7: 0.020833333 | F7: 8.8 | G7: 8.5 | J7: 81.1 | T7: 18.1 | U7: 19.2 | V7: 24.4 | W7: 1.1 | AF7: 12.2 | AG7: 24.5 | AH7: 10.3 | AK7: 179.4 | AM7: 7.9 | AX7: 355.9 | BK7: 184.9 | BM7: 164.4 | BN7: 165.5 | BO7: 165.6 | BV7: 110.5 | BW7: 206.5 | BX7: 206.1 | BY7: 206 | CA7: 17.4 | CB7: 44.1 | CI7: 118.1 | CJ7: 52.4 | CK7: 53.7 | CN7: 226.4 | CO7: 191.2 | CP7: 180.6 | CQ7: 180.5 | CR7: 181.3 | CS7: 181 | HJ7: 3587.777 | HK7: 3526.018 | HL7: 542.2
B8: 0.041666667 | F8: 8.8 | G8: 8.5 | J8: 81.1 | T8: 18.1 | U8: 19.2 | V8: 24.4 | W8: 1.1 | AA8: 17.3 | AF8: 12.2 | AG8: 24.5 | AH8: 10.3 | AK8: 179.4 | AM8: 7.9 | AX8: 355.9 | BK8: 184.9 | BM8: 164.4 | BN8: 165.5 | BO8: 165.6 | BV8: 110.5 | BW8: 206.5 | BX8: 206.1 | BY8: 206 | CA8: 17.4 | CB8: 44.1 | CI8: 118.1 | CJ8: 52.4 | CK8: 53.7 | CN8: 477.8 | CO8: 191.2 | CP8: 180.6 | CQ8: 180.5 | CR8: 181.3 | CS8: 181 | HJ8: 3856.438 | HK8: 3794.679 | HL8: 542.2
B9: 0.0625 | F9: 8.8 | G9: 8.5 | J9: 81.1 | T9: 18.1 | U9: 19.2 | V9: 24.4 | W9: 1.1 | AA9: 17.3 | AF9: 12.2 | AG9: 24.5 | AH9: 10.3 | AK9: 179.4 | AM9: 7.9 | AX9: 355.9 | BK9: 184.9 | BM9: 164.4 | BN9: 165.5 | BO9: 165.6 | BV9: 110.5 | BW9: 206.5 | BX9: 206.1 | BY9: 206 | CA9: 17.4 | CB9: 44.1 | CI9: 118.1 | CJ9: 52.4 | CK9: 53.7 | CN9: 477.8 | CO9: 191.2 | CP9: 180.6 | CQ9: 180.5 | CR9: 181.3 | CS9: 181 | HJ9: 3856.438 | HK9: 3794.679 | HL9: 542.2
B10: 0.083333333 | F10: 8.8 | G10: 8.5 | J10: 81.1 | T10: 18.1 | U10: 19.2 | V10: 24.4 | W10: 1.1 | AA10: 17.3 | AF10: 12.2 | AG10: 24.5 | AH10: 10.3 | AK10: 179.4 | AM10: 7.9 | AX10: 355.9 | BK10: 184.9 | BM10: 164.4 | BN10: 165.5 | BO10: 165.6 | BV10: 110.5 | BW10: 206.5 | BX10: 206.1 | BY10: 206 | CA10: 17.4 | CB10: 44.1 | CI10: 118.1 | CJ10: 52.4 | CK10: 53.7 | CN10: 477.8 | CO10: 191.2 | CP10: 180.6 | CQ10: 180.5 | CR10: 181.3 | CS10: 181 | HJ10: 3856.438 | HK10: 3794.679 | HL10: 433.2
B11: 0.10416667 | F11: 8.8 | G11: 8.5 | J11: 81.1 | T11: 18.1 | U11: 19.2 | V11: 24.4 | W11: 1.1 | AA11: 17.3 | AF11: 12.2 | AG11: 24.5 | AH11: 10.3 | AK11: 179.4 | AM11: 7.9 | AX11: 355.9 | BK11: 184.9 | BM11: 164.4 | BN11: 165.5 | BO11: 165.6 | BV11: 110.5 | BW11: 206.5 | BX11: 206.1 | BY11: 206 | CA11: 17.4 | CB11: 44.1 | CI11: 118.1 | CJ11: 52.4 | CK11: 53.7 | CN11: 477.8 | CO11: 191.2 | CP11: 180.6 | CQ11: 180.5 | CR11: 181.3 | CS11: 181 | HJ11: 3856.438 | HK11: 3794.679 | HL11: 433.2
B12: 0.125 | F12: 8.8 | G12: 8.5 | J12: 81.1 | Q12: 211.2 | T12: 18.1 | U12: 19.2 | V12: 24.4 | W12: 1.1 | AA12: 17.3 | AF12: 12.2 | AG12: 24.5 | AH12: 10.3 | AK12: 179.4 | AM12: 7.9 | AX12: 355.9 | BK12: 184.9 | BM12: 164.4 | BN12: 165.5 | BO12: 165.6 | BV12: 110.5 | BW12: 206.5 | BX12: 206.1 | BY12: 206 | CA12: 17.4 | CB12: 44.1 | CI12: 118.1 | CJ12: 52.4 | CK12: 53.7 | CN12: 327.1 | CO12: 191.2 | CP12: 180.6 | CQ12: 180.5 | CR12: 181.3 | CS12: 181 | HJ12: 3916.95 | HK12: 3855.192 | HL12: 542.2
B13: 0.14583333 | F13: 8.8 | G13: 8.5 | J13: 81.1 | Q13: 211.2 | T13: 18.1 | U13: 19.2 | V13: 24.4 | W13: 1.1 | AA13: 17.3 | AF13: 12.2 | AG13: 24.5 | AH13: 10.3 | AK13: 179.4 | AM13: 7.9 | AX13: 355.9 | BK13: 184.9 | BM13: 164.4 | BN13: 165.5 | BO13: 165.6 | BV13: 110.5 | BW13: 206.5 | BX13: 206.1 | BY13: 206 | CA13: 17.4 | CB13: 44.1 | CI13: 118.1 | CJ13: 52.4 | CK13: 53.7 | CN13: 327.1 | CO13: 191.2 | CP13: 180.6 | CQ13: 180.5 | CR13: 181.3 | CS13: 181 | HJ13: 3916.95 | HK13: 3855.192 | HL13: 542.2
B14: 0.16666667 | F14: 8.8 | G14: 8.5 | J14: 81.1 | Q14: 211.2 | T14: 18.1 | U14: 19.2 | V14: 24.4 | W14: 1.1 | AA14: 17.3 | AF14: 12.2 | AG14: 24.5 | AH14: 10.3 | AK14: 179.4 | AM14: 7.9 | AX14: 355.9 | BK14: 184.9 | BM14: 164.4 | BN14: 165.5 | BO14: 165.6 | BV14: 110.5 | BW14: 206.5 | BX14: 206.1 | BY14: 206 | CA14: 17.4 | CB14: 44.1 | CI14: 118.1 | CJ14: 52.4 | CK14: 53.7 | CN14: 327.1 | CO14: 191.2 | CP14: 180.6 | CQ14: 180.5 | CR14: 181.3 | CS14: 181 | HJ14: 3916.95 | HK14: 3855.192 | HL14: 542.2
B15: 0.1875 | F15: 8.8 | G15: 8.5 | J15: 81.1 | Q15: 211.2 | T15: 18.1 | U15: 19.2 | V15: 24.4 | W15: 1.1 | AA15: 17.3 | AF15: 12.2 | AG15: 24.5 | AH15: 10.3 | AK15: 179.4 | AM15: 7.9 | AX15: 355.9 | BK15: 184.9 | BM15: 164.4 | BN15: 165.5 | BO15: 165.6 | BV15: 110.5 | BW15: 206.5 | BX15: 206.1 | BY15: 206 | CA15: 17.4 | CB15: 44.1 | CI15: 118.1 | CJ15: 52.4 | CK15: 53.7 | CN15: 251.4 | CO15: 191.2 | CP15: 180.6 | CQ15: 180.5 | CR15: 181.3 | CS15: 181 | HJ15: 3841.168 | HK15: 3779.409 | HL15: 542.2
B16: 0.20833333 | F16: 8.8 | G16: 8.5 | J16: 81.1 | Q16: 211.2 | T16: 18.1 | U16: 19.2 | V16: 24.4 | W16: 1.1 | AA16: 17.3 | AF16: 12.2 | AG16: 24.5 | AH16: 10.3 | AK16: 179.4 | AM16: 7.9 | AX16: 355.9 | BK16: 184.9 | BM16: 164.4 | BN16: 165.5 | BO16: 165.6 | BV16: 110.5 | BW16: 206.5 | BX16: 206.1 | BY16: 206 | CA16: 17.4 | CB16: 44.1 | CI16: 118.1 | CJ16: 52.4 | CK16: 53.7 | CN16: 251.4 | CO16: 191.2 | CP16: 180.6 | CQ16: 180.5 | CR16: 181.3 | CS16: 181 | HJ16: 3841.168 | HK16: 3779.409 | HL16: 542.2
B17: 0.22916667 | F17: 8.8 | G17: 8.5 | J17: 81.1 | Q17: 211.2 | T17: 18.1 | U17: 19.2 | V17: 24.4 | W17: 1.1 | AA17: 17.3 | AF17: 12.2 | AG17: 24.5 | AH17: 10.3 | AK17: 179.4 | AM17: 7.9 | AX17: 355.9 | BK17: 184.9 | BM17: 164.4 | BN17: 165.5 | BO17: 165.6 | BV17: 110.5 | BW17: 206.5 | BX17: 206.1 | BY17: 206 | CA17: 17.4 | CB17: 44.1 | CI17: 118.1 | CJ17: 52.4 | CK17: 53.7 | CO17: 191.2 | CP17: 180.6 | CQ17: 180.5 | CR17: 181.3 | CS17: 181 | HJ17: 3589.803 | HK17: 3528.044 | HL17: 542.2
B18: 0.25 | F18: 8.8 | G18: 8.5 | J18: 81.1 | Q18: 211.2 | T18: 18.1 | U18: 19.2 | V18: 24.4 | W18: 1.1 | AA18: 17.3 | AF18: 12.2 | AG18: 24.5 | AH18: 10.3 | AK18: 179.4 | AM18: 7.9 | AX18: 355.9 | BK18: 184.9 | BM18: 164.4 | BN18: 165.5 | BO18: 165.6 | BV18: 110.5 | BW18: 206.5 | BX18: 206.1 | BY18: 206 | CA18: 17.4 | CB18: 44.1 | CI18: 118.1 | CJ18: 52.4 | CK18: 53.7 | CO18: 191.2 | CP18: 180.6 | CQ18: 180.5 | CR18: 181.3 | CS18: 181 | HJ18: 3589.803 | HK18: 3528.044 | HL18: 542.2
B19: 0.27083333 | F19: 8.8 | G19: 8.5 | J19: 81.1 | Q19: 211.2 | T19: 18.1 | U19: 19.2 | V19: 24.4 | W19: 1.1 | AA19: 17.3 | AF19: 12.2 | AG19: 24.5 | AH19: 10.3 | AK19: 179.4 | AM19: 7.9 | AX19: 355.9 | BK19: 184.9 | BM19: 164.4 | BN19: 165.5 | BO19: 165.6 | BV19: 110.5 | BW19: 206.5 | BX19: 206.1 | BY19: 206 | CA19: 17.4 | CB19: 44.1 | CI19: 118.1 | CJ19: 52.4 | CK19: 53.7 | CO19: 191.2 | CP19: 180.6 | CQ19: 180.5 | CR19: 181.3 | CS19: 181 | HJ19: 3589.803 | HK19: 3528.044 | HL19: 542.2
B20: 0.29166667 | F20: 8.8 | G20: 8.5 | J20: 81.1 | Q20: 211.2 | T20: 18.1 | U20: 19.2 | V20: 24.4 | W20: 1.1 | AA20: 17.3 | AF20: 12.2 | AG20: 24.5 | AH20: 10.3 | AK20: 179.4 | AM20: 7.9 | AX20: 355.9 | BK20: 184.9 | BM20: 164.4 | BN20: 165.5 | BO20: 165.6 | BV20: 110.5 | BW20: 206.5 | BX20: 206.1 | BY20: 206 | CA20: 17.4 | CB20: 44.1 | CI20: 118.1 | CJ20: 52.4 | CK20: 53.7 | CO20: 191.2 | CP20: 180.6 | CQ20: 180.5 | CR20: 181.3 | CS20: 181 | HJ20: 3589.803 | HK20: 3528.044 | HL20: 542.2
B21: 0.3125 | F21: 8.8 | G21: 8.5 | J21: 81.1 | Q21: 211.2 | T21: 18.1 | U21: 19.2 | V21: 24.4 | W21: 1.1 | AA21: 17.3 | AF21: 12.2 | AG21: 24.5 | AH21: 10.3 | AK21: 179.4 | AM21: 7.9 | AX21: 355.9 | BK21: 184.9 | BM21: 164.4 | BN21: 165.5 | BO21: 165.6 | BV21: 110.5 | BW21: 206.5 | BX21: 206.1 | BY21: 206 | CA21: 17.4 | CB21: 44.1 | CI21: 118.1 | CJ21: 52.4 | CK21: 53.7 | CO21: 191.2 | CP21: 180.6 | CQ21: 180.5 | CR21: 181.3 | CS21: 181 | HJ21: 3589.803 | HK21: 3528.044 | HL21: 542.2
B22: 0.33333333 | F22: 8.8 | G22: 8.5 | J22: 81.1 | Q22: 211.2 | T22: 18.1 | U22: 19.2 | V22: 24.4 | W22: 1.1 | AA22: 17.3 | AF22: 12.2 | AG22: 24.5 | AH22: 10.3 | AK22: 179.4 | AM22: 7.9 | AX22: 355.9 | BK22: 184.9 | BM22: 164.4 | BN22: 165.5 | BO22: 165.6 | BV22: 110.5 | BW22: 206.5 | BX22: 206.1 | BY22: 206 | CA22: 17.4 | CB22: 44.1 | CI22: 118.1 | CJ22: 52.4 | CK22: 53.7 | CO22: 191.2 | CP22: 180.6 | CQ22: 180.5 | CR22: 181.3 | CS22: 181 | HJ22: 3589.803 | HK22: 3528.044 | HL22: 542.2
B23: 0.35416667 | F23: 8.8 | G23: 8.5 | J23: 81.1 | Q23: 211.2 | T23: 18.1 | U23: 19.2 | V23: 24.4 | W23: 1.1 | AA23: 17.3 | AF23: 12.2 | AG23: 24.5 | AH23: 10.3 | AK23: 179.4 | AM23: 7.9 | AX23: 355.9 | BK23: 184.9 | BM23: 164.4 | BN23: 165.5 | BO23: 165.6 | BV23: 110.5 | BW23: 206.5 | BX23: 206.1 | BY23: 206 | CA23: 17.4 | CB23: 44.1 | CI23: 118.1 | CJ23: 52.4 | CK23: 53.7 | CO23: 191.2 | CP23: 180.6 | CQ23: 180.5 | CR23: 181.3 | CS23: 181 | HJ23: 3589.803 | HK23: 3528.044 | HL23: 542.2
