Workbook

Sheet EVENTOS
B3: sábado, 27 de Diciembre del 2025
B5: INFORMACIÓN DE EVENTOS PRINCIPALES EN SUS INSTALACIONES
B6: TIPO DE EVENTO | C6: EMPRESA | D6: UBICACIÓN | E6: TIPO DE EQUIPO | F6: EQUIPO | G6: INICIO | H6: FINAL | I6: DESCRIPCIÓN | J6: MW INDISP. | K6: INTERRUPCIÓN (SI/NO) | L6: TENSIÓN DE FALLA (kV)
B7: EVENTO | C7: ELECTRO ORIENTE | D7: BELAUNDE TERRY - TARAPOTO | E7: LINEA DE TRANSMISION | F7: L-1018 | G7: 27/12/2025 11:06:00 | H7: 27/12/2025 12:01:00 | I7: DECLARACIÓN DE SITUACIÓN EXCEPCIONAL EN LA LÍNEA L-1018 (BELAUNDE TERRY - TARAPOTO) DE 138 kV | K7: NO
B8: EVENTO | C8: ELECTRO ORIENTE | D8: BELAUNDE TERRY - TARAPOTO | E8: LINEA DE TRANSMISION | F8: L-1018 | G8: 27/12/2025 18:24:00 | H8: 27/12/2025 20:40:00 | I8: DECLARACIÓN DE SITUACIÓN EXCEPCIONAL EN LA LÍNEA L-1018 (BELAUNDE TERRY - TARAPOTO) DE 138 kV | K8: NO
B9: FALLA | C9: ISA PERU | D9: CHIMBOTE 1 | E9: TRANSFORMADOR 3D | F9: AT30-211 | G9: 27/12/2025 21:52:00 | H9: 28/12/2025 00:00:00 | I9: DESCONEXION DEL TRANSFORMADOR AT-30 DE LA S.E. CHIMBOTE 1 | K9: NO | L9: 220

Sheet RESTRIC_OPE
B3: sábado, 27 de Diciembre del 2025
B5: RESTRICCIONES OPERATIVAS
B6: FECHA | C6: HORA INICIO | D6: HORA FINAL | E6: EMPRESA | F6: UBICACIÓN | G6: T.Eq. | H6: EQUIPO | I6: DESCRIPCIÓN
B7: 27/12/2025 | C7: 00:00 | D7: 24:00 | E7: CELEPSA | F7: C.H. EL PLATANAL | G7: CH | H7: CENTRAL | I7: De acuerdo con el correo del 13/10/2025. Debido a problemas en el control de la compuerta de bocatoma, informaron que el servicio de RSF queda indisponible.
B8: 27/12/2025 | C8: 00:00 | D8: 24:00 | E8: EGASA | F8: S.E. CONVERTIDOR | G8: BARRA | H8: BARRA138KV | I8: EGASA limitó la capacidad del transformador 138 kV/33 kV a 50 MVA por deterioro del aislamiento.
B9: 27/12/2025 | C9: 00:00 | D9: 24:00 | E9: ELECTROPERU | F9: C.H. MANTARO | G9: CH | H9: CENTRAL | I9: De acuerdo con el correo del día 25.08.2025, la central tiene una limitación de potencia máxima de 650 MW por seguridad de la central.
B10: 27/12/2025 | C10: 00:00 | D10: 24:00 | E10: ENEL GENERACION PIURA S.A. | F10: C.T. MALACAS | G10: CT | H10: CENTRAL | I10: De acuerdo con la comunicación vía correo del día 24.10.2024. ENEL GENERACIÓN PIURA informa una restricción de potencia para alcanzar 105 MW en simultaneo (TG6+TGN4).
B11: 27/12/2025 | C11: 00:00 | D11: 24:00 | E11: ENEL GENERACION PIURA S.A. | F11: C.T. MALACAS | G11: GT | H11: TG4 | I11: De acuerdo a lo informado mediante correo electrónico el día 25.10, con la disponibilidad actual de aproximadamente 13 MMPCD (368.12 Mm³) la unidad TG4 puede con una generación de 80 MW durante 5 horas, y a potencia mínima durante el resto de los periodos
B12: 27/12/2025 | C12: 00:00 | D12: 24:00 | E12: ENGIE ENERGIA PERU S.A.A. | F12: C.H. YUNCÁN | G12: GH | H12: G3 | I12: Según la carta N° ENG/ 198-2024 enviada por su representada, se opera de forma continua el G3 de la CH Yuncán, debido a la ejecución de mantenimientos necesarios para evitar daños en los sellos de seguridad de la válvula esférica del grupo.
B13: 27/12/2025 | C13: 00:00 | D13: 24:00 | E13: ENGIE ENERGIA PERU S.A.A. | F13: C.T. CHILCA 1 | G13: CT | H13: CENTRAL | I13: Restricción de temperatura de la C.T Chilca, ver valor en el modelo de despacho.
B14: 27/12/2025 | C14: 00:00 | D14: 24:00 | E14: ENGIE ENERGIA PERU S.A.A. | F14: C.T. CHILCA 1 | G14: CT | H14: CENTRAL | I14: Con carta ENG/971-2023, indica que no puede cumplir con las IO considerada en el PDO_17122023 dado que vulneran la seguridad de sus activos. Indican que se debe tomar TMO=168h.
B15: 27/12/2025 | C15: 00:00 | D15: 24:00 | E15: ENGIE ENERGIA PERU S.A.A. | F15: C.T. CHILCA 2 | G15: CT | H15: CENTRAL | I15: Con carta ENG/971-2023, indica que no puede cumplir con las IO considerada en el PDO_17122023 dado que vulneran la seguridad de sus activos. Indican que se debe tomar TMO=168h.
B16: 27/12/2025 | C16: 00:00 | D16: 24:00 | E16: FENIX POWER PERÚ | F16: C.T. FENIX | G16: CT | H16: CENTRAL | I16: De acuerdo con lo comunicado en el correo del día 06.05.2025, la CT Fenix cuenta con TMO de 168 hrs en todos sus modos de operación.
B17: 27/12/2025 | C17: 00:00 | D17: 24:00 | E17: KALLPA GENERACION S.A. | F17: C.H. CERRO DEL AGUILA | G17: GH | H17: G1 | I17: De acuerdo a lo informado el día 17/11 por la empresa KALLPA, el G1 tiene un TA = 15min
... B54: 27/12/2025 | C54: 00:00 | D54: 24:00 | E54: TERMOSELVA | F54: C.T. AGUAYTÍA | G54: CT | H54: CENTRAL | I54: Disponibilidad de 12 MMSCF para la CT Aguaytía.

Sheet MANTENIMIENTO EJECUTADOS
B3: sábado, 27 de Diciembre del 2025
B5: Mantenimiento Ejecutado
B6: Empresa | C6: Ubicación | D6: Equipo | E6: Inicio | F6: Final | G6: Descripción | H6: MW Indisp. | I6: Prog. | J6: Dispon | K6: Interrupc. | L6: Tipo | M6: CodEq | N6: TipoEq_Osinerg
B7: AGRO INDUSTRIAL PARAMONGA S.A. | C7: PARAMONGA | D7: TV-01 | E7: 27/12/2025 00:00 | F7: 28/12/2025 00:00 | G7: LIMPIEZA E INSPECCION DE LA CALDERA CBS Y MANTENIMIENTO A SUS PERIFERICOS (CONDUCTORES, VENTILADORES, BOMBAS, MOTORES, ETC) | H7: 14 | I7: P | J7: F/S | K7: N | L7: PREV. | M7: 12664 | N7: G
B8: AGROAURORA S.A.C. | C8: MAPLE ETANOL | D8: CENTRAL | E8: 27/12/2025 00:00 | F8: 28/12/2025 00:00 | G8: CENTRAL TERMOELECTRICA FUERA DE SERVICIO POR REQUERMIENTOS DE FABRICA. | H8: 18 | I8: P | J8: F/S | K8: N | L8: OTROS | M8: 13417 | N8: G
B9: ATLANTICA TRANSMISION SUR S.A. | C9: OCONA | D9: INT-5450 | E9: 27/12/2025 00:00 | F9: 28/12/2025 00:00 | G9: Interruptor INT-5450 cerrado con restriccion operativa, REB-5450 en servicio y suministrando los SS.AA. de la S.E. Oco?a. | H9: 0 | I9: P | J9: E/S | K9: N | L9: OTROS | M9: 13761 | N9: T
B10: ATLANTICA TRANSMISION SUR S.A. | C10: POROMA | D10: REB-5350 | E10: 27/12/2025 00:00 | F10: 28/12/2025 00:00 | G10: Fuera de servicio po falla en el equipo. | H10: 0 | I10: P | J10: F/S | K10: N | L10: OTROS | M10: 13771 | N10: T
B11: ATN S.A. | C11: KIMAN AYLLU | D11: AUT-501 | E11: 27/12/2025 00:00 | F11: 28/12/2025 00:00 | G11: Restriccion Operativa en el circuito de control de cambiador de tap s del AUT-501 | H11: 0 | I11: P | J11: E/S | K11: N | L11: OTROS | M11: 13099 | N11: T
B12: ATRIA ENERGIA S.A.C. | C12: PURMACANA | D12: CENTRAL | E12: 27/12/2025 00:00 | F12: 28/12/2025 00:00 | G12: Mantenimiento correctivo de valvula principal | H12: 0.4 | I12: P | J12: F/S | K12: N | L12: CORR. | M12: 13132 | N12: G
B13: CASA GRANDE S.A.A. | C13: CASA GRANDE | D13: TV1 | E13: 27/12/2025 08:00 | F13: 27/12/2025 19:00 | G13: Ensayos de Potencia Efectiva y Rendimiento (EPEyR) y Ensayos de Potencia Minima (EPMin) en coordinacion con COES | H13: 0 | I13: P | J13: E/S | K13: N | L13: PRUEBA | M13: 26892 | N13: G
B14: CONELSUR LT SAC | C14: CALLAHUANCA (CNS) | D14: S.E. | E14: 27/12/2025 00:00 | F14: 28/12/2025 00:00 | G14: RELE DIFERENCIAL DE BARRAS DE CALLAHUANCA 220KV INOPERATIVO | H14: 0 | I14: P | J14: E/S | K14: N | L14: OTROS | M14: 316 | N14: T
B15: EGASA | C15: CHARCANI II | D15: G3 | E15: 27/12/2025 07:25 | F15: 27/12/2025 13:20 | G15: Mantenimiento Electromecanico Plan 3 | H15: 0.2 | I15: P | J15: F/S | K15: N | L15: PREV. | M15: 115 | N15: G
B16: EGASA | C16: SANTUARIO | D16: ACOPLE 138 | E16: 27/12/2025 00:00 | F16: 28/12/2025 00:00 | G16: En servicio barra 2,uso en grupo N1 Charcani V con interruptor de acoplamiento, por falla | H16: 0 | I16: P | J16: E/S | K16: N | L16: OTROS | M16: 11052 | N16: T
B17: EGESUR | C17: CT INDEPENDENCIA | D17: TR1 (Reserva) | E17: 27/12/2025 00:00 | F17: 28/12/2025 00:00 | G17: Transformador E/S con el Conmutador de Taps sin carga Deshabilitado | H17: 0 | I17: P | J17: E/S | K17: N | L17: OTROS | M17: 19961 | N17: T
B18: EGESUR | C18: INDEPENDENCIA | D18: T-30 | E18: 27/12/2025 00:00 | F18: 28/12/2025 00:00 | G18: Mantenimiento correctivo del transformador de potencia en reserva - DELCROSA | H18: 0 | I18: P | J18: F/S | K18: N | L18: CORR. | M18: 12592 | N18: T
... B85: TRANSMANTARO | C85: YARABAMBA | D85: CL-R-30 | E85: 27/12/2025 00:00 | F85: 28/12/2025 00:00 | G85: CL-R30 CON MANDO SINCRONIZADO ASOCIADO AL INTERRUPTOR IN-5147 INDISPONIBLE. EL 20.11.25 NO PUDO SER AJUSTADO DEBIDO A ANOMALIA EN LA CUCHILLA DE PUESTA A TIERRA ST-5027. | H85: 0 | I85: P | J85: E/S | K85: N | L85: OTROS | M85: 17424 | N85: T

Sheet INGRESO OC
A3: sábado, 27 de Diciembre del 2025
A5: INGRESO A OPERACIÓN COMERCIAL
A6: EMPRESA | B6: TIPO DE EQUIPO | C6: UBICACIÓN | D6: EQUIPO | E6: Fecha y hora de Ingreso a Operación Comercial

Sheet DESPACHO_EJECUTADO
B3: sábado, 27 de Diciembre del 2025
A5: POTENCIA ACTIVA EJECUTADA DE LAS UNIDADES DE GENERACIÓN DEL SEIN (MW) | FP5: CENTRALES NO INTEGRANTES COES
A6: FECHA | B6: HORA | C6: 65333 | D6: 101 | E6: 102 | F6: 42667 | G6: 42668 | H6: 126 | I6: 127 | J6: 138 | K6: 139 | L6: 197 | M6: 203 | N6: 204 | O6: 230 | P6: 209 | Q6: 56677 | R6: 796 | S6: 2146 | T6: 142 | U6: 143 | V6: 125 | W6: 187 | X6: 163 | Y6: 298 | Z6: 299 | AA6: 219 | AB6: 151 | AC6: 152 | AD6: 153 | AE6: 154 | AF6: 756 | AG6: 156 | AH6: 155 | AI6: 182 | AJ6: 212 | AK6: 758 | AL6: 263 | AM6: 265 | AN6: 775 | AO6: 777 | AP6: 2154 | AQ6: 150 | AR6: 149 | AS6: 188 | AT6: 2131 | AU6: 755 | AV6: 252 | AW6: 249 | AX6: 250 | AY6: 117 | AZ6: 119 | BA6: 120 | BB6: 189 | BC6: 122 | BD6: 266 | BE6: 337 | BF6: 338 | BG6: 251 | BH6: 115 | BI6: 239 | BJ6: 288 | BK6: 240 | BL6: 241 | BM6: 242 | BN6: 191 | BO6: 194 | BP6: 196 | BQ6: 207 | BR6: 236 | BS6: 795 | BT6: 285 | BU6: 995 | BV6: 996 | BW6: 997 | BX6: 766 | BY6: 926 | BZ6: 924 | CA6: 121 | CB6: 103 | CC6: 104 | CD6: 106 | CE6: 105 | CF6: 107 | CG6: 110 | CH6: 109 | CI6: 144 | CJ6: 113 | CK6: 114 | CL6: 193 | CM6: 208 | CN6: 786 | CO6: 787 | CP6: 788 | CQ6: 789 | CR6: 248 | CS6: 2159 | CT6: 267 | CU6: 268 | CV6: 2194 | CW6: 303 | CX6: 59715 | CY6: 62255 | CZ6: 1263 | DA6: 61800 | DB6: 69125 | DC6: 216 | DD6: 198 | DE6: 70400 | DF6: 49607 | DG6: 214 | DH6: 260 | DI6: 2152 | DJ6: 2128 | DK6: 247 | DL6: 228 | DM6: 2135 | DN6: 261 | DO6: 237 | DP6: 253 | DQ6: 770 | DR6: 235 | DS6: 238 | DT6: 2184 | DU6: 61855 | DV6: 223 | DW6: 75566 | DX6: 226 | DY6: 201 | DZ6: 258 | EA6: 259 | EB6: 920 | EC6: 257 | ED6: 256 | EE6: 2148 | EF6: 58288 | EG6: 58289 | EH6: 58839 | EI6: 58840 | EJ6: 75260 | EK6: 296 | EL6: 297 | EM6: 211 | EN6: 2175 | EO6: 2178 | EP6: 2181 | EQ6: 1262 | ER6: 63425 | ES6: 233 | ET6: 2150 | EU6: 2165 | EV6: 2161 | EW6: 61197 | EX6: 58851 | EY6: 225 | EZ6: 2201 | FA6: 2171 | FB6: 760 | FC6: 234 | FD6: 215 | FE6: 917 | FF6: 289 | FG6: 58333 | FH6: 58336 | FI6: 213 | FJ6: 232 | FK6: 2190 | FL6: 69867 | FM6: 75066 | FN6: TOTAL COES | FP6: 221 | FQ6: 222 | FR6: 224 | FS6: 2187 | FT6: 227 | FU6: 49400 | FV6: 199 | FW6: 200 | FX6: TOTAL NO COES
C7: SUR | D7: CENTRO | E7: CENTRO | F7: NORTE | G7: NORTE | H7: NORTE | I7: NORTE | J7: CENTRO | K7: CENTRO | L7: CENTRO | M7: CENTRO | N7: CENTRO | O7: CENTRO | P7: CENTRO | Q7: CENTRO | R7: CENTRO | S7: CENTRO | T7: CENTRO | U7: CENTRO | V7: CENTRO | W7: CENTRO | X7: SUR | Y7: SUR | Z7: SUR | AA7: CENTRO | AB7: SUR | AC7: SUR | AD7: SUR | AE7: SUR | AF7: SUR | AG7: SUR | AH7: SUR | AI7: SUR | AJ7: CENTRO | AK7: NORTE | AL7: NORTE | AM7: NORTE | AN7: CENTRO | AO7: CENTRO | AP7: CENTRO | AQ7: CENTRO | AR7: CENTRO | AS7: CENTRO | AT7: CENTRO | AU7: SUR | AV7: CENTRO | AW7: CENTRO | AX7: CENTRO | AY7: CENTRO | AZ7: CENTRO | BA7: CENTRO | BB7: SUR | BC7: NORTE | BD7: CENTRO | BE7: CENTRO | BF7: CENTRO | BG7: CENTRO | BH7: NORTE | BI7: NORTE | BJ7: NORTE | BK7: SUR | BL7: SUR | BM7: SUR | BN7: CENTRO | BO7: CENTRO | BP7: CENTRO | BQ7: CENTRO | BR7: CENTRO | BS7: CENTRO | BT7: CENTRO | BU7: SUR | BV7: SUR | BW7: SUR | BX7: NORTE | BY7: SUR | BZ7: CENTRO | CA7: NORTE | CB7: CENTRO | CC7: CENTRO | CD7: CENTRO | CE7: CENTRO | CF7: CENTRO | CG7: CENTRO | CH7: CENTRO | CI7: CENTRO | CJ7: CENTRO | CK7: CENTRO | CL7: CENTRO | CM7: CENTRO | CN7: SUR | CO7: SUR | CP7: SUR | CQ7: SUR | CR7: CENTRO | CS7: CENTRO | CT7: CENTRO | CU7: CENTRO | CV7: NORTE | CW7: CENTRO | CX7: CENTRO | CY7: SUR | CZ7: NORTE | DA7: NORTE | DB7: CENTRO | DC7: NORTE | DD7: NORTE | DE7: SUR | DF7: SUR | DG7: CENTRO | DH7: CENTRO | DI7: CENTRO | DJ7: NORTE | DK7: NORTE | DL7: CENTRO | DM7: CENTRO | DN7: SUR | DO7: SUR | DP7: CENTRO | DQ7: CENTRO | DR7: SUR | DS7: CENTRO | DT7: CENTRO | DU7: NORTE | DV7: CENTRO | DW7: CENTRO | DX7: CENTRO | DY7: NORTE | DZ7: CENTRO | EA7: CENTRO | EB7: CENTRO | EC7: NORTE | ED7: NORTE | EE7: SUR | EF7: CENTRO | EG7: CENTRO | EH7: CENTRO | EI7: CENTRO | EJ7: SUR | EK7: CENTRO | EL7: CENTRO | EM7: SUR | EN7: SUR | EO7: SUR | EP7: SUR | EQ7: NORTE | ER7: SUR | ES7: SUR | ET7: SUR | EU7: CENTRO | EV7: CENTRO | EW7: CENTRO | EX7: SUR | EY7: CENTRO | EZ7: CENTRO | FA7: CENTRO | FB7: CENTRO | FC7: SUR | FD7: NORTE | FE7: CENTRO | FF7: NORTE | FG7: NORTE | FH7: NORTE | FI7: CENTRO | FJ7: NORTE | FK7: NORTE | FL7: NORTE | FM7: NORTE | FP7: NORTE | FQ7: CENTRO | FR7: NORTE | FS7: NORTE | FT7: NORTE | FU7: NORTE | FV7: NORTE | FW7: NORTE
C8: HIDROELÉCTRICA | D8: HIDROELÉCTRICA | E8: HIDROELÉCTRICA | F8: TERMOELÉCTRICA | G8: TERMOELÉCTRICA | H8: HIDROELÉCTRICA | I8: HIDROELÉCTRICA | J8: TERMOELÉCTRICA | K8: TERMOELÉCTRICA | L8: TERMOELÉCTRICA | M8: TERMOELÉCTRICA | N8: TERMOELÉCTRICA | O8: TERMOELÉCTRICA | P8: TERMOELÉCTRICA | Q8: TERMOELÉCTRICA | R8: HIDROELÉCTRICA | S8: HIDROELÉCTRICA | T8: TERMOELÉCTRICA | U8: TERMOELÉCTRICA | V8: TERMOELÉCTRICA | W8: TERMOELÉCTRICA | X8: HIDROELÉCTRICA | Y8: HIDROELÉCTRICA | Z8: HIDROELÉCTRICA | AA8: TERMOELÉCTRICA | AB8: HIDROELÉCTRICA | AC8: HIDROELÉCTRICA | AD8: HIDROELÉCTRICA | AE8: HIDROELÉCTRICA | AF8: TERMOELÉCTRICA | AG8: TERMOELÉCTRICA | AH8: TERMOELÉCTRICA | AI8: HIDROELÉCTRICA | AJ8: HIDROELÉCTRICA | AK8: TERMOELÉCTRICA | AL8: TERMOELÉCTRICA | AM8: TERMOELÉCTRICA | AN8: HIDROELÉCTRICA | AO8: HIDROELÉCTRICA | AP8: HIDROELÉCTRICA | AQ8: HIDROELÉCTRICA | AR8: HIDROELÉCTRICA | AS8: HIDROELÉCTRICA | AT8: HIDROELÉCTRICA | AU8: HIDROELÉCTRICA | AV8: TERMOELÉCTRICA | AW8: TERMOELÉCTRICA | AX8: TERMOELÉCTRICA | AY8: HIDROELÉCTRICA | AZ8: HIDROELÉCTRICA | BA8: HIDROELÉCTRICA | BB8: HIDROELÉCTRICA | BC8: HIDROELÉCTRICA | BD8: HIDROELÉCTRICA | BE8: HIDROELÉCTRICA | BF8: HIDROELÉCTRICA | BG8: HIDROELÉCTRICA | BH8: TERMOELÉCTRICA | BI8: TERMOELÉCTRICA | BJ8: TERMOELÉCTRICA | BK8: TERMOELÉCTRICA | BL8: TERMOELÉCTRICA | BM8: TERMOELÉCTRICA | BN8: HIDROELÉCTRICA | BO8: TERMOELÉCTRICA | BP8: TERMOELÉCTRICA | BQ8: TERMOELÉCTRICA | BR8: TERMOELÉCTRICA | BS8: TERMOELÉCTRICA | BT8: TERMOELÉCTRICA | BU8: TERMOELÉCTRICA | BV8: TERMOELÉCTRICA | BW8: TERMOELÉCTRICA | BX8: HIDROELÉCTRICA | BY8: TERMOELÉCTRICA | BZ8: TERMOELÉCTRICA | CA8: HIDROELÉCTRICA | CB8: HIDROELÉCTRICA | CC8: HIDROELÉCTRICA | CD8: HIDROELÉCTRICA | CE8: HIDROELÉCTRICA | CF8: HIDROELÉCTRICA | CG8: TERMOELÉCTRICA | CH8: TERMOELÉCTRICA | CI8: TERMOELÉCTRICA | CJ8: TERMOELÉCTRICA | CK8: TERMOELÉCTRICA | CL8: TERMOELÉCTRICA | CM8: TERMOELÉCTRICA | CN8: TERMOELÉCTRICA | CO8: TERMOELÉCTRICA | CP8: TERMOELÉCTRICA | CQ8: TERMOELÉCTRICA | CR8: TERMOELÉCTRICA | CS8: TERMOELÉCTRICA | CT8: HIDROELÉCTRICA | CU8: HIDROELÉCTRICA | CV8: HIDROELÉCTRICA | CW8: SOLAR | CX8: EÓLICA | CY8: SOLAR | CZ8: EÓLICA | DA8: SOLAR | DB8: HIDROELÉCTRICA | DC8: HIDROELÉCTRICA | DD8: HIDROELÉCTRICA | DE8: SOLAR | DF8: HIDROELÉCTRICA | DG8: HIDROELÉCTRICA | DH8: HIDROELÉCTRICA | DI8: HIDROELÉCTRICA | DJ8: HIDROELÉCTRICA | DK8: HIDROELÉCTRICA | DL8: HIDROELÉCTRICA | DM8: HIDROELÉCTRICA | DN8: SOLAR | DO8: SOLAR | DP8: EÓLICA | DQ8: EÓLICA | DR8: SOLAR | DS8: HIDROELÉCTRICA | DT8: HIDROELÉCTRICA | DU8: HIDROELÉCTRICA | DV8: HIDROELÉCTRICA | DW8: SOLAR | DX8: HIDROELÉCTRICA | DY8: HIDROELÉCTRICA | DZ8: HIDROELÉCTRICA | EA8: HIDROELÉCTRICA | EB8: HIDROELÉCTRICA | EC8: EÓLICA | ED8: EÓLICA | EE8: SOLAR | EF8: EÓLICA | EG8: EÓLICA | EH8: EÓLICA | EI8: EÓLICA | EJ8: SOLAR | EK8: HIDROELÉCTRICA | EL8: HIDROELÉCTRICA | EM8: HIDROELÉCTRICA | EN8: HIDROELÉCTRICA | EO8: HIDROELÉCTRICA | EP8: HIDROELÉCTRICA | EQ8: EÓLICA | ER8: SOLAR | ES8: SOLAR | ET8: SOLAR | EU8: HIDROELÉCTRICA | EV8: EÓLICA | EW8: EÓLICA | EX8: SOLAR | EY8: TERMOELÉCTRICA | EZ8: TERMOELÉCTRICA | FA8: TERMOELÉCTRICA | FB8: TERMOELÉCTRICA | FC8: SOLAR | FD8: HIDROELÉCTRICA | FE8: HIDROELÉCTRICA | FF8: TERMOELÉCTRICA | FG8: TERMOELÉCTRICA | FH8: TERMOELÉCTRICA | FI8: TERMOELÉCTRICA | FJ8: TERMOELÉCTRICA | FK8: TERMOELÉCTRICA | FL8: TERMOELÉCTRICA | FM8: TERMOELÉCTRICA | FP8: HIDROELÉCTRICA | FQ8: HIDROELÉCTRICA | FR8: HIDROELÉCTRICA | FS8: HIDROELÉCTRICA | FT8: TERMOELÉCTRICA | FU8: TERMOELÉCTRICA | FV8: HIDROELÉCTRICA | FW8: HIDROELÉCTRICA
C9: HYDRO GLOBAL PERÚ S.A.C. | D9: ELECTROPERU | E9: ELECTROPERU | F9: ELECTROPERU | G9: ELECTROPERU | H9: ORAZUL ENERGY PERÚ | I9: ORAZUL ENERGY PERÚ | J9: TERMOSELVA | K9: TERMOSELVA | L9: KALLPA GENERACION S.A. | M9: KALLPA GENERACION S.A. | N9: KALLPA GENERACION S.A. | O9: KALLPA GENERACION S.A. | P9: KALLPA GENERACION S.A. | Q9: KALLPA GENERACION S.A. | R9: KALLPA GENERACION S.A. | S9: KALLPA GENERACION S.A. | T9: SHOUGESA | U9: SHOUGESA | V9: SHOUGESA | W9: SHOUGESA | X9: EGEMSA | Y9: EGESUR | Z9: EGESUR | AA9: EGESUR | AB9: EGASA | AC9: EGASA | AD9: EGASA | AE9: EGASA | AF9: EGASA | AG9: EGASA | AH9: EGASA | AI9: SAN GABAN | AJ9: CELEPSA | AK9: MINERA CERRO VERDE | AL9: PLANTA DE RESERVA FRIA DE GENERACION DE ETEN S.A. | AM9: PLANTA DE RESERVA FRIA DE GENERACION DE ETEN S.A. | AN9: EMPRESA DE GENERACION HUALLAGA | AO9: EMPRESA DE GENERACION HUALLAGA | AP9: LA VIRGEN | AQ9: CHINANGO S.A.C. | AR9: CHINANGO S.A.C. | AS9: HIDROELECTRICA HUANCHOR S.A.C. | AT9: CELEPSA RENOVABLES S.R.L. | AU9: INLAND ENERGY SAC | AV9: FENIX POWER PERÚ | AW9: FENIX POWER PERÚ | AX9: FENIX POWER PERÚ | AY9: STATKRAFT S.A | AZ9: STATKRAFT S.A | BA9: STATKRAFT S.A | BB9: STATKRAFT S.A | BC9: STATKRAFT S.A | BD9: STATKRAFT S.A | BE9: CENTRALES SANTA ROSA S.A.C. | BF9: CENTRALES SANTA ROSA S.A.C. | BG9: EMPRESA DE GENERACION HUANZA | BH9: ENEL GENERACION PIURA S.A. | BI9: ENEL GENERACION PIURA S.A. | BJ9: ENEL GENERACION PIURA S.A. | BK9: ENGIE ENERGIA PERU S.A.A. | BL9: ENGIE ENERGIA PERU S.A.A. | BM9: ENGIE ENERGIA PERU S.A.A. | BN9: ENGIE ENERGIA PERU S.A.A. | BO9: ENGIE ENERGIA PERU S.A.A. | BP9: ENGIE ENERGIA PERU S.A.A. | BQ9: ENGIE ENERGIA PERU S.A.A. | BR9: ENGIE ENERGIA PERU S.A.A. | BS9: ENGIE ENERGIA PERU S.A.A. | BT9: ENGIE ENERGIA PERU S.A.A. | BU9: ENGIE ENERGIA PERU S.A.A. | BV9: ENGIE ENERGIA PERU S.A.A. | BW9: ENGIE ENERGIA PERU S.A.A. | BX9: ENGIE ENERGIA PERU S.A.A. | BY9: INFRAESTRUCTURAS Y ENERGIAS DEL PERU S.A.C. | BZ9: INFRAESTRUCTURAS Y ENERGIAS DEL PERU S.A.C. | CA9: INVERSIONES SHAQSHA S.A.C. | CB9: ORYGEN PERU S.A.A. | CC9: ORYGEN PERU S.A.A. | CD9: ORYGEN PERU S.A.A. | CE9: ORYGEN PERU S.A.A. | CF9: ORYGEN PERU S.A.A. | CG9: ORYGEN PERU S.A.A. | CH9: ORYGEN PERU S.A.A. | CI9: ORYGEN PERU S.A.A. | CJ9: ORYGEN PERU S.A.A. | CK9: ORYGEN PERU S.A.A. | CL9: ORYGEN PERU S.A.A. | CM9: ORYGEN PERU S.A.A. | CN9: SAMAY I S.A.C | CO9: SAMAY I S.A.C | CP9: SAMAY I S.A.C | CQ9: SAMAY I S.A.C | CR9: TERMOCHILCA S.A.C. | CS9: TERMOCHILCA S.A.C. | CT9: TRANSMISION ANDINA DE GENERACION S.A.C. | CU9: TRANSMISION ANDINA DE GENERACION S.A.C. | CV9: CELARIS ENERGY S.A. | CW9: COLCA SOLAR S.A.C. | CX9: ENERGIA RENOVABLE DEL SUR S.A. | CY9: GR CORTARRAMA SOCIEDAD ANONIMA CERRADA | CZ9: GR TARUCA SOCIEDAD ANONIMA CERRADA | DA9: KONDU SAC | DB9: VARI ENERGIA S.A.C. | DC9: ORAZUL ENERGY PERÚ | DD9: ORAZUL ENERGY PERÚ | DE9: KALLPA GENERACION S.A. | DF9: SAN GABAN | DG9: MAJA ENERGIA S.A.C. | DH9: EMPRESA DE GENERACION ELECTRICA CANCHAYLLO SAC | DI9: EMPRESA DE GENERACION ELECTRICA SANTA ANA S.A.C. | DJ9: EMPRESA ELECTRICA AGUA AZUL | DK9: EMPRESA ELECTRICA RIO DOBLE | DL9: HIDROCAÑETE S.A. | DM9: HUAURA POWER GROUP S.A. | DN9: MOQUEGUA FV S.A.C. | DO9: PANAMERICANA SOLAR SAC. | DP9: PARQUE EOLICO MARCONA S.A.C. | DQ9: PARQUE EOLICO TRES HERMANAS S.A.C. | DR9: TACNA SOLAR SAC. | DS9: ELECTRICA YANAPAMPA SAC | DT9: ANDEAN POWER S.A.C. | DU9: ASOCIACIÓN SANTA LUCIA DE CHACAS | DV9: ATRIA ENERGIA S.A.C. | DW9: COENERGY S.A.C. | DX9: EGEJUNIN | DY9: EGEJUNIN | DZ9: EGEJUNIN | EA9: EGEJUNIN | EB9: EMPRESA DE GENERACION ELECTRICA RIO BAÑOS S.A.C. | EC9: ENERGÍA EÓLICA S.A. | ED9: ENERGÍA EÓLICA S.A. | EE9: ENGIE ENERGIA PERU S.A.A. | EF9: ENGIE ENERGIA PERU S.A.A. | EG9: ENGIE ENERGIA PERU S.A.A. | EH9: ENGIE ENERGIA PERU S.A.A. | EI9: ENGIE ENERGIA PERU S.A.A. | EJ9: ENGIE ENERGIA PERU S.A.A. | EK9: GENERACIÓN ANDINA S.A.C. | EL9: GENERACIÓN ANDINA S.A.C. | EM9: GENERADORA DE ENERGÍA DEL PERÚ | EN9: GENERADORA DE ENERGÍA DEL PERÚ | EO9: GENERADORA DE ENERGÍA DEL PERÚ | EP9: GENERADORA DE ENERGÍA DEL PERÚ | EQ9: GR PAINO SOCIEDAD ANONIMA CERRADA | ER9: JOYA SOLAR S.A.C. | ES9: MAJES ARCUS S.A.C. | ET9: ORYGEN PERU S.A.A. | EU9: ORYGEN PERU S.A.A. | EV9: ORYGEN PERU S.A.A. | EW9: ORYGEN PERU S.A.A. | EX9: ORYGEN PERU S.A.A. | EY9: PETRAMAS | EZ9: PETRAMAS | FA9: PETRAMAS | FB9: PETRAMAS | FC9: REPARTICIÓN ARCUS S.A.C. | FD9: SINERSA | FE9: SINERSA | FF9: BIOENERGIA DEL CHIRA S.A. | FG9: GM OPERACIONES S.A.C. | FH9: GM OPERACIONES S.A.C. | FI9: AGRO INDUSTRIAL PARAMONGA S.A. | FJ9: AGROAURORA S.A.C. | FK9: AGROINDUSTRIAS SAN JACINTO S.A.A. | FL9: AGROLMOS SOCIEDAD ANONIMA - AGROLMOS S.A. | FM9: CASA GRANDE S.A.A. | FP9: UNACEM PERU S.A. | FQ9: ELECTRO ORIENTE | FR9: AGUAS Y ENERGIA PERU | FS9: ELECTRO ZAÑA S.A.C. | FT9: ELECTRONOROESTE S.A. | FU9: SDE PIURA | FV9: SINERSA | FW9: SINERSA
C10: SAN GABAN III | D10: MANTARO | E10: RESTITUCION | F10: TUMBES MAK 1 | G10: TUMBES MAK 2 | H10: CARHUAQUERO | I10: CAÑON DEL PATO | J10: AGUAYTIA TG1 | K10: AGUAYTIA TG2 | L10: KALLPA TG1 | M10: KALLPA TG2 | N10: KALLPA TG3 | O10: KALLPA TV | P10: LFLORES TG1 | Q10: LFLORES TV | R10: CERRO DEL AGUILA | S10: CERRODELAGUILAG4 | T10: SHOUGESA TV1 | U10: SHOUGESA TV2 | V10: SHOUGESA TV3 | W10: SHOUGESA CUMMINS | X10: MACHUPICCHU | Y10: ARICOTA 1 | Z10: ARICOTA 2 | AA10: INDEPENDENCIA | AB10: CHARCANI I,II,III | AC10: CHARCANI IV | AD10: CHARCANI V | AE10: CHARCANI VI | AF10: CHILINA TG | AG10: MOLLENDO 1, 2, 3 | AH10: CHILINA (SULZ 1,2) | AI10: SAN GABAN II | AJ10: PLATANAL | AK10: RECKA | AL10: RF ETEN TG1 | AM10: RF ETEN TG2 | AN10: CHAGLLA GP1 | AO10: CHAGLLA | AP10: LA VIRGEN | AQ10: CHIMAY | AR10: YANANGO | AS10: HUANCHOR | AT10: MARAÑON | AU10: STA TERESA | AV10: FENIX GT11 | AW10: FENIX GT12 | AX10: FENIX TV10 | AY10: YAUPI | AZ10: MALPASO | BA10: CAHUA | BB10: ARCATA | BC10: GALLITO CIEGO | BD10: CHEVES | BE10: SANTA ROSA 1 | BF10: SANTA ROSA 2 | BG10: HUANZA | BH10: MALACAS2 TG4 | BI10: MALACAS3 TG 5 | BJ10: MALACAS1 TG6 | BK10: RF ILO2 TG1 | BL10: RF ILO2 TG2 | BM10: RF ILO2 TG3 | BN10: YUNCAN | BO10: CHILCA1 TG1 | BP10: CHILCA1 TG2 | BQ10: CHILCA1 TG3 | BR10: CHILCA-TV | BS10: CHILCA2 TG41 | BT10: CHILCA2-TV | BU10: CTNEPI_TG41 | BV10: CTNEPI_TG42 | BW10: CTNEPI_TG43 | BX10: QUITARACSA | BY10: RF PTO MALDONADO | BZ10: RF PUCALLPA | CA10: PARIAC | CB10: HUINCO | CC10: MATUCANA | CD10: MOYOPAMPA | CE10: CALLAHUANCA | CF10: HUAMPANI | CG10: STA ROSA WEST TG7 | CH10: UTI_5 | CI10: UTI_6 | CJ10: VENTANILLA 3 | CK10: VENTANILLA 4 | CL10: VENTANILLA TV | CM10: STAROSA TG8 | CN10: PTO_BRVO TG1 | CO10: PTO_BRVO TG2 | CP10: PTO_BRVO TG3 | CQ10: PTO_BRVO TG4 | CR10: OLLEROS TG1 | CS10: OLLEROS TV | CT10: OROYA | CU10: PACHACHACA | CV10: MANTA I | CW10: CS YARUCAYA | CX10: SAN JUAN | CY10: MATARANI | CZ10: DUNA | DA10: CARHUAQUERO (CS) | DB10: ANASHIRONI | DC10: CARHUAQUERO4 | DD10: CAÑA BRAVA | DE10: SUNNY | DF10: TUPURI | DG10: RONCADOR | DH10: CANCHAYLLO | DI10: RENOVANDESH1 | DJ10: POTRERO | DK10: PIZARRAS | DL10: NIMPERIAL | DM10: YARUCAYA | DN10: MOQUEGUA-SOLAR | DO10: PANAMERICANA-SOLAR | DP10: PQE-EOLICO-MARCONA | DQ10: PQE-EOLICO-3-HERMANAS | DR10: TACNA-SOLAR | DS10: YANAPAMPA | DT10: CARHUAC | DU10: HUALLIN | DV10: PURMACANA | DW10: COENERGY | DX10: HUASAHUASI | DY10: STACRUZ_1_2 | DZ10: RUNATULLO_II | EA10: RUNATULLO_III | EB10: RUCUY | EC10: PQE-EOLICO-TALARA | ED10: PQE-EOLICO-CUPISNIQUE | EE10: INTIPAMPA | EF10: PUNTA LOMITAS-BL1 | EG10: PUNTA LOMITAS-BL2 | EH10: PUN LOMITAS_EXP-BL1 | EI10: PUN LOMITAS_EXP-BL2 | EJ10: EXPANSIÓN INTIPAMPA | EK10: 8AGOSTO | EL10: EL CARMEN | EM10: LA JOYA | EN10: ANGEL_I | EO10: ANGEL_II | EP10: ANGEL_III | EQ10: HUAMBOS | ER10: SAN MARTIN SOLAR | ES10: MAJES | ET10: RUBI | EU10: CH_HER1 | EV10: WAYRA-I | EW10: WAYRA EXTENSION | EX10: CLEMESI | EY10: HUAYCOLORO | EZ10: CALLAO | FA10: DONA_CATALINA | FB10: LAGRINGAV | FC10: REPARTICION | FD10: POECHOS2 | FE10: CHANCAY | FF10: CANA BRAVA | FG10: REFINERIA TALARA TV1 | FH10: REFINERÍA TALARA TV2 | FI10: PARAMONGA | FJ10: MAPLE | FK10: SAN_JACINTO | FL10: AGROLMOS | FM10: CASA GRANDE | FN10: MW | FP10: CARPAPATA | FQ10: CENTRALES ELOR | FR10: PIAS1 | FS10: ZANA | FT10: TABLAZO | FU10: TALLANCA | FV10: CURUMUY | FW10: POECHOS1 | FX10: MW
A11: 27/12/2025 | B11: 00:30 | C11: 198.1 | D11: 537.5 | E11: 181.9 | H11: 82.4 | I11: 161.4 | K11: 76.7 | L11: 183.5 | N11: 202.3 | P11: 209.8 | R11: 378.6 | S11: 9.4 | X11: 163 | Y11: 6.7 | Z11: 4.8 | AA11: 22.2 | AB11: 6.9 | AC11: 14.3 | AD11: 88.9 | AI11: 109.7 | AJ11: 0 | AN11: 6.5 | AO11: 157.1 | AP11: 28.2 | AQ11: 60.1 | AR11: 15.5 | AS11: 16 | AT11: 13.9 | AU11: 89.1 | AV11: 177.86025 | AW11: 178.75744 | AX11: 183.63172 | AY11: 102.064 | AZ11: 0 | BA11: 25.292 | BB11: 4.084 | BC11: 32.26 | BD11: 37.315 | BG11: 84.1 | BJ11: 46.3 | BN11: 83.4 | BO11: 148.4 | BP11: 148.3 | BQ11: 156 | BR11: 250.1 | BS11: 73.9 | BT11: 36 | CB11: 71.7 | CC11: 46.8 | CD11: 61.6 | CE11: 63.8 | CF11: 29.7 | CG11: 119.2 | CJ11: 144.2 | CK11: 144.8 | CL11: 170.5 | CM11: 187.9 | CR11: 210.3 | CS11: 101.5 | CT11: 3.1 | CV11: 4.3 | CW11: 0 | CX11: 48.3 | CY11: 0 | CZ11: 0.2 | DA11: 0 | DB11: 4.9 | DC11: 9.9 | DD11: 5.4 | DE11: 0 | DF11: 1.1 | DG11: 1.6 | DH11: 4.1 | DI11: 18.2 | DJ11: 10.6 | DK11: 14.4 | DL11: 2.3 | DM11: 17.2 | DN11: 0 | DO11: 0 | DP11: 13.5 | DQ11: 19.2 | DR11: 0 | DS11: 2 | DT11: 20.2 | DU11: 3 | DW11: 0 | DX11: 4.1 | DY11: 8.2 | DZ11: 10.1 | EA11: 14.9 | EB11: 17.6 | EC11: 18 | ED11: 56 | EE11: 0 | EF11: 18.4 | EG11: 26.2 | EH11: 0.6 | EI11: 0 | EJ11: 0 | EK11: 8.8 | EL11: 2.8 | EM11: 8.5 | EN11: 20.4 | EO11: 20.4 | EP11: 20.1 | EQ11: 0.4 | ER11: 0 | ES11: 0 | ET11: 0 | EU11: 0.6 | EV11: 2.9 | EW11: 0.7 | EX11: 0 | EY11: 4.3 | EZ11: 2.2 | FA11: 1.2 | FB11: 1.2 | FC11: 0 | FD11: 5.7 | FE11: 10 | FF11: 8.4 | FG11: 27.7 | FH11: 34.9 | FK11: 9.1 | FL11: 11.1 | FM11: 19.1 | FN11: 6742.3644 | FP11: 13.86024 | FQ11: 0 | FR11: 11.82869 | FS11: 8 | FT11: 26.81407 | FU11: 18.93389 | FV11: 4.3 | FW11: 15.9 | FX11: 99.63689
A12: 27/12/2025 | B12: 01:00 | C12: 200.1 | D12: 541.5 | E12: 182.2 | H12: 84.1 | I12: 167.2 | K12: 77.7 | L12: 183.5 | N12: 201.6 | P12: 210.5 | R12: 213.3 | S12: 9.2 | X12: 163.4 | Y12: 6.8 | Z12: 4.9 | AA12: 22.2 | AB12: 6.9 | AC12: 14.6 | AD12: 89.9 | AI12: 109.9 | AJ12: 0 | AN12: 6.5 | AO12: 152.5 | AP12: 28.6 | AQ12: 54.3 | AR12: 14.7 | AS12: 16 | AT12: 13.8 | AU12: 91.2 | AV12: 178.64745 | AW12: 179.37847 | AX12: 184.34747 | AY12: 102.849 | AZ12: 0 | BA12: 26.446 | BB12: 4.084 | BC12: 32.14 | BD12: 37.719 | BG12: 84.4 | BJ12: 14 | BN12: 83.6 | BO12: 162 | BP12: 162.1 | BQ12: 163.7 | BR12: 252.1 | BS12: 74 | BT12: 36.1 | CB12: 104.7 | CC12: 45.6 | CD12: 62.1 | CE12: 61.6 | CF12: 29.7 | CG12: 118.9 | CJ12: 143.8 | CK12: 144.5 | CL12: 169.9 | CM12: 187.5 | CR12: 211 | CS12: 101.5 | CT12: 3.2 | CV12: 4.3 | CW12: 0 | CX12: 42.2 | CY12: 0 | CZ12: 0.3 | DA12: 0 | DB12: 5 | DC12: 9.9 | DD12: 5.4 | DE12: 0 | DF12: 1.1 | DG12: 1.6 | DH12: 4.1 | DI12: 16.8 | DJ12: 10.6 | DK12: 14.5 | DL12: 2.3 | DM12: 17.2 | DN12: 0 | DO12: 0 | DP12: 8.3 | DQ12: 10.8 | DR12: 0 | DS12: 2.1 | DT12: 20.2 | DU12: 3 | DW12: 0 | DX12: 4.1 | DY12: 8.2 | DZ12: 10.3 | EA12: 14.7 | EB12: 17.6 | EC12: 19.7 | ED12: 49.5 | EE12: 0 | EF12: 9.3 | EG12: 20.2 | EH12: 0.1 | EI12: 0 | EJ12: 0 | EK12: 8.8 | EL12: 2.8 | EM12: 8.5 | EN12: 20.4 | EO12: 20.4 | EP12: 20.1 | EQ12: 0.6 | ER12: 0 | ES12: 0 | ET12: 0 | EU12: 0.6 | EV12: 0.7 | EW12: 0.7 | EX12: 0 | EY12: 4.3 | EZ12: 2.2 | FA12: 1.2 | FB12: 1.2 | FC12: 0 | FD12: 5.8 | FE12: 10 | FF12: 8.8 | FG12: 27.3 | FH12: 34.4 | FK12: 9 | FL12: 11.1 | FM12: 19.5 | FN12: 6580.5114 | FP12: 12.81188 | FQ12: 0 | FR12: 11.83088 | FS12: 8 | FT12: 26.83652 | FU12: 18.93434 | FV12: 4.5 | FW12: 15.9 | FX12: 98.81362
A13: 27/12/2025 | B13: 01:30 | C13: 201.5 | D13: 494.2 | E13: 162.6 | H13: 85 | I13: 172.9 | K13: 76.3 | L13: 183.7 | N13: 202.4 | P13: 209.6 | R13: 195.1 | S13: 9.3 | X13: 164.8 | Y13: 7.2 | Z13: 5 | AA13: 22.2 | AB13: 6.9 | AC13: 14.6 | AD13: 90 | AI13: 110.5 | AJ13: 0 | AN13: 6.5 | AO13: 149.5 | AP13: 30 | AQ13: 54.5 | AR13: 14.9 | AS13: 16 | AT13: 13.5 | AU13: 89.7 | AV13: 179.41658 | AW13: 180.14569 | AX13: 183.62353 | AY13: 105.245 | AZ13: 0 | BA13: 26.737 | BB13: 4.079 | BC13: 32.47 | BD13: 73.512 | BG13: 45.2 | BJ13: 0 | BN13: 84.3 | BO13: 170.6 | BP13: 168.2 | BQ13: 199.9 | BR13: 266.4 | BS13: 73.6 | BT13: 36 | CB13: 109.6 | CC13: 51.8 | CD13: 62.6 | CE13: 61.8 | CF13: 30.1 | CG13: 118.6 | CJ13: 143.1 | CK13: 144.2 | CL13: 168.7 | CM13: 187.2 | CR13: 210.9 | CS13: 101.5 | CT13: 3.2 | CV13: 4.2 | CW13: 0 | CX13: 36.9 | CY13: 0 | CZ13: 0.7 | DA13: 0 | DB13: 5.1 | DC13: 10 | DD13: 5.4 | DE13: 0 | DF13: 1.1 | DG13: 1.7 | DH13: 4.1 | DI13: 17.1 | DJ13: 10.6 | DK13: 14.3 | DL13: 2.3 | DM13: 17.2 | DN13: 0 | DO13: 0 | DP13: 7 | DQ13: 10.8 | DR13: 0 | DS13: 2.2 | DT13: 14.4 | DU13: 3 | DW13: 0 | DX13: 4.1 | DY13: 8.2 | DZ13: 10.5 | EA13: 14.5 | EB13: 17.6 | EC13: 22.1 | ED13: 57.1 | EE13: 0 | EF13: 6.3 | EG13: 14.4 | EH13: 0 | EI13: 0 | EJ13: 0 | EK13: 9 | EL13: 3 | EM13: 8.5 | EN13: 20.4 | EO13: 20.4 | EP13: 20.1 | EQ13: 1.3 | ER13: 0 | ES13: 0 | ET13: 0 | EU13: 0.6 | EV13: 0.1 | EW13: 0.7 | EX13: 0 | EY13: 4.3 | EZ13: 2.2 | FA13: 1.2 | FB13: 1.2 | FC13: 0 | FD13: 5.7 | FE13: 10 | FF13: 8.4 | FG13: 27.5 | FH13: 34.9 | FK13: 8.6 | FL13: 11.1 | FM13: 20.1 | FN13: 6553.3288 | FP13: 12.86766 | FQ13: 0 | FR13: 11.83088 | FS13: 8 | FT13: 26.81947 | FU13: 18.93443 | FV13: 4.6 | FW13: 15.7 | FX13: 98.75244
A14: 27/12/2025 | B14: 02:00 | C14: 201.2 | D14: 499 | E14: 163.4 | H14: 66.4 | I14: 178.6 | K14: 78.7 | L14: 183 | N14: 204.1 | P14: 210.6 | R14: 208.9 | S14: 9.4 | X14: 155.1 | Y14: 7.4 | Z14: 5.1 | AA14: 22 | AB14: 6.9 | AC14: 14.6 | AD14: 90.5 | AI14: 111 | AJ14: 0 | AN14: 6.5 | AO14: 154.2 | AP14: 29.3 | AQ14: 61.4 | AR14: 14.4 | AS14: 16 | AT14: 13.6 | AU14: 92 | AV14: 180.89391 | AW14: 181.35952 | AX14: 184.41595 | AY14: 107.699 | AZ14: 0 | BA14: 28.021 | BB14: 4.083 | BC14: 32.39 | BD14: 46.831 | BG14: 45.9 | BJ14: 0 | BN14: 84.5 | BO14: 162.6 | BP14: 162.9 | BQ14: 161.9 | BR14: 240.8 | BS14: 73.5 | BT14: 36.2 | CB14: 133.6 | CC14: 48.2 | CD14: 62.7 | CE14: 61.8 | CF14: 30.1 | CG14: 119.2 | CJ14: 144.1 | CK14: 145.2 | CL14: 170 | CM14: 188.5 | CR14: 211.2 | CS14: 101.6 | CT14: 3.1 | CV14: 4.4 | CW14: 0 | CX14: 30.9 | CY14: 0 | CZ14: 0.4 | DA14: 0 | DB14: 5.1 | DC14: 9.9 | DD14: 5.4 | DE14: 0 | DF14: 1.1 | DG14: 1.7 | DH14: 4.3 | DI14: 18.1 | DJ14: 10.6 | DK14: 14 | DL14: 2.3 | DM14: 17.2 | DN14: 0 | DO14: 0 | DP14: 7.3 | DQ14: 10.3 | DR14: 0 | DS14: 2.1 | DT14: 11.4 | DU14: 3 | DW14: 0 | DX14: 4.1 | DY14: 8.2 | DZ14: 10.8 | EA14: 14.7 | EB14: 17.4 | EC14: 22.6 | ED14: 60.8 | EE14: 0 | EF14: 3.5 | EG14: 10.8 | EH14: 0 | EI14: 0 | EJ14: 0 | EK14: 9.3 | EL14: 3.1 | EM14: 8.5 | EN14: 20.4 | EO14: 20.4 | EP14: 20.1 | EQ14: 0.5 | ER14: 0 | ES14: 0 | ET14: 0 | EU14: 0.6 | EV14: 0 | EW14: 0.2 | EX14: 0 | EY14: 4.3 | EZ14: 2.2 | FA14: 1.2 | FB14: 1.2 | FC14: 0 | FD14: 5.6 | FE14: 9.9 | FF14: 8.8 | FG14: 27 | FH14: 34.3 | FK14: 8.6 | FL14: 11.1 | FM14: 19.4 | FN14: 6485.6934 | FP14: 12.99735 | FQ14: 0 | FR14: 11.83006 | FS14: 8 | FT14: 26.86524 | FU14: 18.93772 | FV14: 4.3 | FW14: 16.1 | FX14: 99.03037
A15: 27/12/2025 | B15: 02:30 | C15: 202.5 | D15: 495.6 | E15: 163.6 | H15: 68.2 | I15: 178.3 | K15: 77.2 | L15: 183.9 | N15: 201.1 | P15: 208.7 | R15: 229.2 | S15: 9.4 | X15: 164.2 | Y15: 7.5 | Z15: 5.1 | AA15: 22.1 | AB15: 6.9 | AC15: 14.6 | AD15: 89.8 | AI15: 110.8 | AJ15: 0 | AN15: 6.5 | AO15: 0 | AP15: 28 | AQ15: 57.3 | AR15: 15.7 | AS15: 16 | AT15: 13.6 | AU15: 93 | AV15: 181.55938 | AW15: 182.72725 | AX15: 183.74183 | AY15: 109.243 | AZ15: 0 | BA15: 28.08 | BB15: 4.079 | BC15: 32.96 | BD15: 56.267 | BG15: 46.4 | BJ15: 0 | BN15: 84.7 | BO15: 162.6 | BP15: 162.7 | BQ15: 165.6 | BR15: 254.6 | BS15: 73.6 | BT15: 36.2 | CB15: 123.8 | CC15: 60.2 | CD15: 63 | CE15: 62 | CF15: 30.4 | CG15: 119.1 | CJ15: 143.4 | CK15: 144.2 | CL15: 169.2 | CM15: 187.9 | CR15: 210.9 | CS15: 101.5 | CT15: 3.2 | CV15: 4.4 | CW15: 0 | CX15: 19.1 | CY15: 0 | CZ15: 0.1 | DA15: 0 | DB15: 5.2 | DC15: 9.9 | DD15: 5.3 | DE15: 0 | DF15: 1.1 | DG15: 1.7 | DH15: 4.3 | DI15: 18.9 | DJ15: 10.6 | DK15: 13.5 | DL15: 2.3 | DM15: 17.2 | DN15: 0 | DO15: 0 | DP15: 4.5 | DQ15: 5.8 | DR15: 0 | DS15: 2.3 | DT15: 11 | DU15: 3 | DW15: 0 | DX15: 4.1 | DY15: 8.3 | DZ15: 11.1 | EA15: 14.5 | EB15: 17.8 | EC15: 27.7 | ED15: 51.3 | EE15: 0 | EF15: 3.3 | EG15: 8.3 | EH15: 0 | EI15: 0 | EJ15: 0 | EK15: 9.4 | EL15: 2.9 | EM15: 8.5 | EN15: 20.4 | EO15: 20.4 | EP15: 20.1 | EQ15: 0.3 | ER15: 0 | ES15: 0 | ET15: 0 | EU15: 0.6 | EV15: 0 | EW15: 0 | EX15: 0 | EY15: 4.3 | EZ15: 2.2 | FA15: 1.2 | FB15: 1.2 | FC15: 0 | FD15: 5.6 | FE15: 10 | FF15: 9.1 | FG15: 27.3 | FH15: 34.7 | FK15: 8.6 | FL15: 11.1 | FM15: 19.1 | FN15: 6356.2575 | FP15: 13.45489 | FQ15: 0 | FR15: 11.82944 | FS15: 8 | FT15: 26.93084 | FU15: 18.94043 | FV15: 4.6 | FW15: 16 | FX15: 99.7556
A16: 27/12/2025 | B16: 03:00 | C16: 203.4 | D16: 502.4 | E16: 165.2 | H16: 68.1 | I16: 179.1 | K16: 77.8 | L16: 184.5 | N16: 202.4 | P16: 209 | R16: 251.1 | S16: 9.3 | X16: 161.3 | Y16: 7.6 | Z16: 5.2 | AA16: 22.2 | AB16: 6.9 | AC16: 14.6 | AD16: 91.1 | AI16: 110.8 | AJ16: 0 | AN16: 6.5 | AO16: 0 | AP16: 29.5 | AQ16: 64.9 | AR16: 13.5 | AS16: 16.2 | AT16: 13.6 | AU16: 94.9 | AV16: 181.85097 | AW16: 181.96855 | AX16: 185.69945 | AY16: 108.263 | AZ16: 0 | BA16: 27.981 | BB16: 4.084 | BC16: 32.91 | BD16: 61.327 | BG16: 46.5 | BJ16: 0 | BN16: 84.5 | BO16: 171.9 | BP16: 169.1 | BQ16: 168.8 | BR16: 243.5 | BS16: 73.7 | BT16: 36.2 | CB16: 92.1 | CC16: 71.3 | CD16: 63 | CE16: 62 | CF16: 30.3 | CG16: 119.5 | CJ16: 144.1 | CK16: 144.8 | CL16: 170.4 | CM16: 188.7 | CR16: 211.2 | CS16: 101.5 | CT16: 3.2 | CV16: 4.4 | CW16: 0 | CX16: 12.5 | CY16: 0 | CZ16: 0 | DA16: 0 | DB16: 5.1 | DC16: 9.9 | DD16: 5.3 | DE16: 0 | DF16: 1.1 | DG16: 1.7 | DH16: 4.1 | DI16: 17.3 | DJ16: 10.6 | DK16: 13.6 | DL16: 2.3 | DM16: 17.2 | DN16: 0 | DO16: 0 | DP16: 3 | DQ16: 5.3 | DR16: 0 | DS16: 2.3 | DT16: 11.7 | DU16: 3 | DW16: 0 | DX16: 4.1 | DY16: 8.3 | DZ16: 12.1 | EA16: 14.8 | EB16: 17.8 | EC16: 28.1 | ED16: 55.6 | EE16: 0 | EF16: 1.8 | EG16: 6.3 | EH16: 0 | EI16: 0 | EJ16: 0 | EK16: 9.2 | EL16: 2.8 | EM16: 8.5 | EN16: 20.4 | EO16: 20.4 | EP16: 20.1 | EQ16: 0 | ER16: 0 | ES16: 0 | ET16: 0 | EU16: 0.6 | EV16: 0.4 | EW16: 0 | EX16: 0 | EY16: 4.3 | EZ16: 2.2 | FA16: 1.2 | FB16: 1.2 | FC16: 0 | FD16: 5.6 | FE16: 10 | FF16: 8.6 | FG16: 27.3 | FH16: 34.6 | FK16: 8.1 | FL16: 11 | FM16: 19.5 | FN16: 6386.784 | FP16: 13.82039 | FQ16: 0 | FR16: 11.83081 | FS16: 8 | FT16: 26.94932 | FU16: 18.94035 | FV16: 4.5 | FW16: 16 | FX16: 100.04087
A17: 27/12/2025 | B17: 03:30 | C17: 206.4 | D17: 502.1 | E17: 160.1 | H17: 69.5 | I17: 181.5 | K17: 79.5 | L17: 182.4 | N17: 200.8 | P17: 208.3 | R17: 231.9 | S17: 9.3 | X17: 172 | Y17: 7.7 | Z17: 5.3 | AA17: 22.1 | AB17: 6.9 | AC17: 14.6 | AD17: 90.8 | AI17: 111 | AJ17: 0 | AN17: 6.5 | AO17: 0 | AP17: 29.3 | AQ17: 59 | AR17: 14.4 | AS17: 16.1 | AT17: 13.7 | AU17: 87.5 | AV17: 183.68208 | AW17: 183.7 | AX17: 183.63566 | AY17: 107.894 | AZ17: 0 | BA17: 28.142 | BB17: 4.081 | BC17: 32.88 | BD17: 42.861 | BG17: 47.2 | BJ17: 0 | BN17: 85 | BO17: 158.9 | BP17: 158.7 | BQ17: 156.5 | BR17: 239.6 | BS17: 73.6 | BT17: 36.3 | CB17: 125.5 | CC17: 67.1 | CD17: 63.5 | CE17: 62.4 | CF17: 30.4 | CG17: 119 | CJ17: 143 | CK17: 144 | CL17: 169.3 | CM17: 188 | CR17: 211.8 | CS17: 101.6 | CT17: 3.2 | CV17: 4.5 | CW17: 0 | CX17: 20.2 | CY17: 0 | CZ17: 0 | DA17: 0 | DB17: 5.3 | DC17: 9.9 | DD17: 5.3 | DE17: 0 | DF17: 1.1 | DG17: 1.6 | DH17: 4.1 | DI17: 18.6 | DJ17: 10.6 | DK17: 13.5 | DL17: 2.3 | DM17: 17.2 | DN17: 0 | DO17: 0 | DP17: 3.2 | DQ17: 5 | DR17: 0 | DS17: 2.3 | DT17: 11.7 | DU17: 3 | DW17: 0 | DX17: 4.1 | DY17: 8.3 | DZ17: 12 | EA17: 14.8 | EB17: 17.8 | EC17: 29.2 | ED17: 52.2 | EE17: 0 | EF17: 0.6 | EG17: 9.5 | EH17: 0 | EI17: 0 | EJ17: 0 | EK17: 9.1 | EL17: 2.8 | EM17: 8.5 | EN17: 20.4 | EO17: 20.4 | EP17: 20.1 | EQ17: 0 | ER17: 0 | ES17: 0 | ET17: 0 | EU17: 0.6 | EV17: 0 | EW17: 0 | EX17: 0 | EY17: 4.3 | EZ17: 2.2 | FA17: 1.2 | FB17: 1.2 | FC17: 0 | FD17: 5.7 | FE17: 10 | FF17: 9.3 | FG17: 27 | FH17: 34.3 | FK17: 8.2 | FL17: 11 | FM17: 19.8 | FN17: 6344.1757 | FP17: 14.59503 | FQ17: 0 | FR17: 11.82825 | FS17: 8 | FT17: 26.95864 | FU17: 18.94075 | FV17: 4.5 | FW17: 15.9 | FX17: 100.72267
A18: 27/12/2025 | B18: 04:00 | C18: 199.9 | D18: 490.6 | E18: 162.1 | H18: 66.9 | I18: 179.5 | K18: 77 | L18: 183.2 | N18: 202.4 | P18: 211.5 | R18: 226.9 | S18: 9.3 | X18: 165 | Y18: 6.8 | Z18: 4.9 | AA18: 22.1 | AB18: 7 | AC18: 14.6 | AD18: 89.6 | AI18: 109.7 | AJ18: 0 | AN18: 6.5 | AO18: 0 | AP18: 29.2 | AQ18: 45.5 | AR18: 14.8 | AS18: 16.1 | AT18: 13.7 | AU18: 90.5 | AV18: 179.17222 | AW18: 179.46791 | AX18: 183.90017 | AY18: 106.629 | AZ18: 0 | BA18: 27.299 | BB18: 4.08 | BC18: 32.18 | BD18: 37.96 | BG18: 44.3 | BJ18: 0 | BN18: 83.5 | BO18: 152.9 | BP18: 152.9 | BQ18: 154.3 | BR18: 245.4 | BS18: 73.6 | BT18: 36.2 | CB18: 82 | CC18: 43.2 | CD18: 61.8 | CE18: 61.1 | CF18: 29.7 | CG18: 119.6 | CJ18: 143.9 | CK18: 144.8 | CL18: 170.6 | CM18: 188.6 | CR18: 211.9 | CS18: 101.6 | CT18: 3.2 | CV18: 4.5 | CW18: 0 | CX18: 44 | CY18: 0 | CZ18: 0 | DA18: 0 | DB18: 5 | DC18: 9.9 | DD18: 5.3 | DE18: 0 | DF18: 1.1 | DG18: 1.6 | DH18: 4.1 | DI18: 18.7 | DJ18: 10.6 | DK18: 13.4 | DL18: 2.3 | DM18: 17.2 | DN18: 0 | DO18: 0 | DP18: 4.6 | DQ18: 5.2 | DR18: 0 | DS18: 2.3 | DT18: 11.9 | DU18: 3 | DW18: 0 | DX18: 4.1 | DY18: 8.3 | DZ18: 11.4 | EA18: 16 | EB18: 17.6 | EC18: 28.9 | ED18: 33.6 | EE18: 0 | EF18: 1.7 | EG18: 7.4 | EH18: 0 | EI18: 0 | EJ18: 0 | EK18: 9 | EL18: 2.8 | EM18: 8.5 | EN18: 20.4 | EO18: 20.4 | EP18: 20.1 | EQ18: 0 | ER18: 0 | ES18: 0 | ET18: 0 | EU18: 0.6 | EV18: 0 | EW18: 0 | EX18: 0 | EY18: 4.3 | EZ18: 2.2 | FA18: 1.2 | FB18: 1.2 | FC18: 0 | FD18: 5.7 | FE18: 10 | FF18: 7.8 | FG18: 27.3 | FH18: 34.7 | FK18: 8 | FL18: 11 | FM18: 19 | FN18: 6208.9883 | FP18: 16.76799 | FQ18: 0 | FR18: 11.82612 | FS18: 8 | FT18: 26.97469 | FU18: 18.94114 | FV18: 4.5 | FW18: 15.9 | FX18: 102.90994
A19: 27/12/2025 | B19: 04:30 | C19: 202.8 | D19: 498 | E19: 164.1 | H19: 68 | I19: 188.3 | K19: 77.7 | L19: 183.6 | N19: 201.8 | P19: 209.5 | R19: 206.9 | S19: 9.2 | X19: 168.2 | Y19: 7.3 | Z19: 5.1 | AA19: 22.1 | AB19: 6.9 | AC19: 14.6 | AD19: 90.6 | AI19: 110.8 | AJ19: 0 | AN19: 6.5 | AO19: 0 | AP19: 24.5 | AQ19: 56.2 | AR19: 15.6 | AS19: 16.2 | AT19: 13.7 | AU19: 90.9 | AV19: 181.6362 | AW19: 181.50489 | AX19: 184.56119 | AY19: 108.261 | AZ19: 0 | BA19: 28.027 | BB19: 4.081 | BC19: 32.89 | BD19: 50.356 | BG19: 46.2 | BJ19: 0 | BN19: 84.5 | BO19: 171 | BP19: 168.3 | BQ19: 171.1 | BR19: 256.3 | BS19: 73.9 | BT19: 36.3 | CB19: 145.8 | CC19: 66.8 | CD19: 62.7 | CE19: 58 | CF19: 30.1 | CG19: 65.2 | CJ19: 143.9 | CK19: 145 | CL19: 169.5 | CM19: 188.5 | CR19: 212 | CS19: 101.7 | CT19: 3.2 | CV19: 4.4 | CW19: 0 | CX19: 64.3 | CY19: 0 | CZ19: 0 | DA19: 0 | DB19: 5.1 | DC19: 9.9 | DD19: 5.2 | DE19: 0 | DF19: 1.1 | DG19: 1.6 | DH19: 4 | DI19: 18.8 | DJ19: 10.9 | DK19: 13.6 | DL19: 2.3 | DM19: 17.2 | DN19: 0 | DO19: 0 | DP19: 6.2 | DQ19: 9.8 | DR19: 0 | DS19: 2.3 | DT19: 11.9 | DU19: 3 | DW19: 0 | DX19: 4.1 | DY19: 8.3 | DZ19: 11.6 | EA19: 16.3 | EB19: 17.6 | EC19: 25.6 | ED19: 34.2 | EE19: 0 | EF19: 1.4 | EG19: 17.8 | EH19: 0 | EI19: 0 | EJ19: 0 | EK19: 9 | EL19: 2.8 | EM19: 8.5 | EN19: 20.4 | EO19: 20.4 | EP19: 20.1 | EQ19: 0 | ER19: 0 | ES19: 0 | ET19: 0 | EU19: 0.6 | EV19: 0 | EW19: 1.4 | EX19: 0 | EY19: 4.3 | EZ19: 2.2 | FA19: 1.2 | FB19: 1.2 | FC19: 0 | FD19: 5.8 | FE19: 10 | FF19: 8.9 | FG19: 27.1 | FH19: 34.3 | FK19: 7 | FL19: 11.1 | FM19: 18 | FN19: 6373.2173 | FP19: 17.32822 | FQ19: 0 | FR19: 11.82275 | FS19: 8 | FT19: 27.02326 | FU19: 18.94093 | FV19: 4.5 | FW19: 15.9 | FX19: 103.51516
A20: 27/12/2025 | B20: 05:00 | C20: 203.5 | D20: 499.2 | E20: 164.2 | H20: 67.9 | I20: 187.5 | K20: 78.8 | L20: 183.1 | N20: 202.9 | P20: 210.2 | R20: 276.7 | S20: 9.2 | X20: 167.9 | Y20: 7.6 | Z20: 5.2 | AA20: 22.1 | AB20: 7 | AC20: 14.6 | AD20: 90.6 | AI20: 110.8 | AJ20: 0 | AN20: 6.5 | AO20: 0 | AP20: 20 | AQ20: 58 | AR20: 16.4 | AS20: 16.2 | AT20: 13.7 | AU20: 88.3 | AV20: 181.85122 | AW20: 182.38986 | AX20: 184.3813 | AY20: 109.062 | AZ20: 0 | BA20: 27.969 | BB20: 4.084 | BC20: 33.31 | BD20: 41.928 | BG20: 46.4 | BJ20: 0 | BN20: 84.5 | BO20: 160 | BP20: 159.8 | BQ20: 159.9 | BR20: 243.5 | BS20: 73 | BT20: 36.2 | CB20: 135.6 | CC20: 49.9 | CD20: 62.8 | CE20: 61 | CF20: 30.2 | CG20: 65.2 | CJ20: 144.8 | CK20: 145.7 | CL20: 170.5 | CM20: 188.5 | CR20: 212.5 | CS20: 102 | CT20: 3.2 | CV20: 4.4 | CW20: 0 | CX20: 67.2 | CY20: 0 | CZ20: 0.5 | DA20: 0 | DB20: 5.1 | DC20: 9.9 | DD20: 5 | DE20: 0 | DF20: 1 | DG20: 1.6 | DH20: 4 | DI20: 18.5 | DJ20: 11.2 | DK20: 13.5 | DL20: 2.3 | DM20: 17.2 | DN20: 0.1 | DO20: 0 | DP20: 13 | DQ20: 33.5 | DR20: 0 | DS20: 2.3 | DT20: 11.9 | DU20: 3 | DW20: 0 | DX20: 4.1 | DY20: 8.3 | DZ20: 11.7 | EA20: 16.3 | EB20: 17.6 | EC20: 26.3 | ED20: 38.5 | EE20: 0 | EF20: 3.8 | EG20: 11.8 | EH20: 0 | EI20: 0 | EJ20: 0 | EK20: 9 | EL20: 2.8 | EM20: 8.5 | EN20: 20.4 | EO20: 20.4 | EP20: 20.1 | EQ20: 0.8 | ER20: 0 | ES20: 0 | ET20: 0 | EU20: 0.6 | EV20: 0 | EW20: 0.5 | EX20: 0 | EY20: 4.3 | EZ20: 2.2 | FA20: 1.2 | FB20: 1.2 | FC20: 0 | FD20: 5.7 | FE20: 10 | FF20: 8.1 | FG20: 27.3 | FH20: 34.4 | FK20: 9 | FL20: 11.1 | FM20: 19.7 | FN20: 6409.1754 | FP20: 16.93915 | FQ20: 0 | FR20: 11.82312 | FS20: 8 | FT20: 27.03878 | FU20: 18.94107 | FV20: 4.5 | FW20: 9.9 | FX20: 97.14212
A21: 27/12/2025 | B21: 05:30 | C21: 203.1 | D21: 498.7 | E21: 167.6 | H21: 68.1 | I21: 176.4 | K21: 78.5 | L21: 185.3 | N21: 204.3 | P21: 209.3 | R21: 82.3 | S21: 9.2 | X21: 163.7 | Y21: 7.2 | Z21: 5.2 | AA21: 22 | AB21: 6.9 | AC21: 14.6 | AD21: 91 | AI21: 110.9 | AJ21: 0 | AN21: 6.5 | AO21: 0 | AP21: 20.2 | AQ21: 69.7 | AR21: 17 | AS21: 16.2 | AT21: 13.9 | AU21: 87.4 | AV21: 181.71989 | AW21: 181.64003 | AX21: 185.36264 | AY21: 104.765 | AZ21: 0 | BA21: 27.726 | BB21: 4.088 | BC21: 32.54 | BD21: 83.155 | BG21: 45.9 | BJ21: 0 | BN21: 82.8 | BO21: 170.8 | BP21: 168 | BQ21: 171.6 | BR21: 255 | BS21: 73.8 | BT21: 36.4 | CB21: 155.2 | CC21: 75.2 | CD21: 65.7 | CE21: 62.9 | CF21: 29.9 | CG21: 65.4 | CJ21: 144.5 | CK21: 145.4 | CL21: 171.1 | CM21: 188.8 | CR21: 212.9 | CS21: 101.9 | CT21: 3.2 | CV21: 4.3 | CW21: 0 | CX21: 78.4 | CY21: 0.1 | CZ21: 0 | DA21: 0 | DB21: 5.2 | DC21: 9.9 | DD21: 5.4 | DE21: 2.2 | DF21: 1 | DG21: 1.6 | DH21: 4 | DI21: 19.7 | DJ21: 11.2 | DK21: 13.6 | DL21: 2.3 | DM21: 17.2 | DN21: 0.6 | DO21: 0.7 | DP21: 22.5 | DQ21: 36.2 | DR21: 1 | DS21: 2.4 | DT21: 11.9 | DU21: 2.9 | DW21: 0 | DX21: 4.1 | DY21: 8.3 | DZ21: 11.2 | EA21: 16.9 | EB21: 17.6 | EC21: 27.3 | ED21: 50.8 | EE21: 0.3 | EF21: 3.1 | EG21: 11.9 | EH21: 0 | EI21: 0 | EJ21: 0 | EK21: 9 | EL21: 2.8 | EM21: 8.5 | EN21: 20.4 | EO21: 20.4 | EP21: 20.1 | EQ21: 0.3 | ER21: 2.6 | ES21: 0 | ET21: 0.2 | EU21: 0.6 | EV21: 0 | EW21: 0.6 | EX21: 0.3 | EY21: 4.3 | EZ21: 2.2 | FA21: 1.2 | FB21: 1.2 | FC21: 0 | FD21: 5.7 | FE21: 10 | FF21: 9 | FG21: 26.9 | FH21: 34.1 | FK21: 8.7 | FL21: 11.1 | FM21: 18.8 | FN21: 6387.3966 | FP21: 16.96382 | FQ21: 0 | FR21: 11.03738 | FS21: 8 | FT21: 27.03619 | FU21: 18.9409 | FV21: 4.4 | FW21: 9.8 | FX21: 96.17829
A22: 27/12/2025 | B22: 06:00 | C22: 203.5 | D22: 500.6 | E22: 163.5 | H22: 68.4 | I22: 189 | K22: 79 | L22: 184.6 | N22: 202.7 | P22: 210.8 | R22: 77.8 | S22: 9.4 | X22: 167 | Y22: 7.6 | Z22: 5.2 | AA22: 22.1 | AB22: 7 | AC22: 14.6 | AD22: 90.4 | AI22: 111 | AJ22: 0 | AN22: 6.5 | AO22: 0 | AP22: 29.8 | AQ22: 54.9 | AR22: 18.2 | AS22: 16 | AT22: 14 | AU22: 89.9 | AV22: 181.90811 | AW22: 182.77728 | AX22: 184.58281 | AY22: 108.576 | AZ22: 0 | BA22: 27.985 | BB22: 4.086 | BC22: 32.82 | BD22: 52.624 | BG22: 17.3 | BJ22: 0 | BN22: 84.2 | BO22: 145 | BP22: 145 | BQ22: 145.3 | BR22: 234.2 | BS22: 74.5 | BT22: 36.5 | CB22: 113.2 | CC22: 61.6 | CD22: 65.9 | CE22: 63 | CF22: 30.3 | CG22: 65.8 | CJ22: 145.3 | CK22: 146 | CL22: 171.6 | CM22: 188.4 | CR22: 213.3 | CS22: 102.2 | CT22: 3.2 | CV22: 4.3 | CW22: 0 | CX22: 83.1 | CY22: 19.7 | CZ22: 0 | DA22: 0 | DB22: 7.3 | DC22: 9.8 | DD22: 5.2 | DE22: 17.8 | DF22: 1 | DG22: 1.6 | DH22: 4 | DI22: 20.5 | DJ22: 11.2 | DK22: 13.5 | DL22: 2.2 | DM22: 17.1 | DN22: 1.4 | DO22: 1.6 | DP22: 23.7 | DQ22: 46.6 | DR22: 2.6 | DS22: 2.4 | DT22: 11 | DU22: 2.9 | DW22: 0.043 | DX22: 4.1 | DY22: 8.1 | DZ22: 11.5 | EA22: 17 | EB22: 17.6 | EC22: 25.1 | ED22: 53.3 | EE22: 1.4 | EF22: 2.3 | EG22: 13.6 | EH22: 0 | EI22: 0 | EJ22: 0.86 | EK22: 9.3 | EL22: 2.9 | EM22: 9.1 | EN22: 20.4 | EO22: 20.4 | EP22: 20.1 | EQ22: 0 | ER22: 19.6 | ES22: 0.8 | ET22: 3.6 | EU22: 0.6 | EV22: 1.7 | EW22: 2.9 | EX22: 3 | EY22: 4.3 | EZ22: 2.2 | FA22: 1.2 | FB22: 1.2 | FC22: 0.5 | FD22: 5.8 | FE22: 9.9 | FF22: 8.8 | FG22: 26.8 | FH22: 34.2 | FK22: 9.3 | FL22: 11.1 | FM22: 19 | FN22: 6284.7622 | FP22: 16.98385 | FQ22: 0 | FR22: 10.53769 | FS22: 8 | FT22: 27.0391 | FU22: 18.94045 | FV22: 4.5 | FW22: 9.9 | FX22: 95.90109
... A58: 28/12/2025 | B58: 00:00 | C58: 202.6 | D58: 399.8 | E58: 128.5 | H58: 90.2 | I58: 173.8 | K58: 79.1 | L58: 183.1 | N58: 202.4 | P58: 210.9 | R58: 179.4 | S58: 9.4 | X58: 164.2 | Y58: 7.4 | Z58: 5.1 | AA58: 22.2 | AB58: 6.8 | AC58: 14.6 | AD58: 83.8 | AI58: 110.9 | AJ58: 80.4 | AN58: 6.5 | AO58: 156.1 | AP58: 29.5 | AQ58: 138.8 | AR58: 14.6 | AS58: 15.8 | AT58: 17.1 | AU58: 91.5 | AV58: 180.94506 | AW58: 181.95228 | AX58: 184.52308 | AY58: 108.67 | AZ58: 32.13 | BA58: 28.05 | BB58: 4.05 | BC58: 32.73 | BD58: 54.2 | BG58: 54.7 | BJ58: 20.5 | BN58: 127.9 | BO58: 171.3 | BP58: 169.9 | BQ58: 171.8 | BR58: 252.9 | BS58: 74 | BT58: 36.2 | CB58: 228.9 | CC58: 74.8 | CD58: 64.4 | CE58: 65 | CF58: 29.5 | CG58: 118.9 | CJ58: 143.7 | CK58: 144.6 | CL58: 170.2 | CM58: 187.6 | CR58: 211.9 | CS58: 101.6 | CT58: 3.4 | CV58: 4.2 | CW58: 0 | CX58: 117.2 | CY58: 0 | CZ58: 0 | DA58: 0 | DB58: 8.8 | DC58: 9.9 | DD58: 5.5 | DE58: 0 | DF58: 1.2 | DG58: 1.7 | DH58: 3.8 | DI58: 20.4 | DJ58: 9.2 | DK58: 13.2 | DL58: 2.4 | DM58: 17.1 | DN58: 0 | DO58: 0 | DP58: 29.6 | DQ58: 66.5 | DR58: 0 | DS58: 2 | DT58: 19.9 | DU58: 3 | DW58: 0 | DX58: 4.5 | DY58: 8.5 | DZ58: 11.7 | EA58: 13.9 | EB58: 16.4 | EC58: 18.8 | ED58: 15.3 | EE58: 0 | EF58: 28.7 | EG58: 0 | EH58: 3.3 | EI58: 0.8 | EJ58: 0 | EK58: 9.1 | EL58: 2.8 | EM58: 8.5 | EN58: 20.4 | EO58: 20.4 | EP58: 20.1 | EQ58: 0 | ER58: 0 | ES58: 0 | ET58: 0 | EU58: 0.6 | EV58: 19.8 | EW58: 17.9 | EX58: 0 | EY58: 4.3 | EZ58: 2.2 | FA58: 1.2 | FB58: 1.2 | FC58: 0 | FD58: 5.8 | FE58: 10 | FF58: 8.9 | FG58: 27.1 | FH58: 34.8 | FK58: 8.6 | FL58: 11.2 | FM58: 19.7 | FN58: 6967.5504 | FP58: 13.12036 | FQ58: 0 | FR58: 11.76712 | FS58: 7.8 | FT58: 26.92346 | FU58: 18.94201 | FV58: 4.7 | FW58: 7.8 | FX58: 91.05295
A59: EJEC | C59: 4872.95 | D59: 10871.15 | E59: 3600.2 | F59: 0 | G59: 0 | H59: 1860.95 | I59: 4165 | J59: 0 | K59: 1675.5 | L59: 4374.7 | M59: 0 | N59: 4841.25 | O59: 0 | P59: 4992.5 | Q59: 0 | R59: 3435.55 | S59: 227.2 | T59: 0 | U59: 0 | V59: 0 | W59: 0 | X59: 3966.35 | Y59: 189.6 | Z59: 132.85 | AA59: 521.95 | AB59: 163.1 | AC59: 345.4 | AD59: 2220.25 | AE59: 0 | AF59: 0 | AG59: 0 | AH59: 0 | AI59: 2654.6 | AJ59: 1267.75 | AK59: 0 | AL59: 0 | AM59: 0 | AN59: 156 | AO59: 1166.75 | AP59: 649.5 | AQ59: 2295.95 | AR59: 349.4 | AS59: 382.45 | AT59: 342.3 | AU59: 2158.35 | AV59: 4346.9605 | AW59: 4357.9993 | AX59: 4426.9911 | AY59: 2571.487 | AZ59: 191.3545 | BA59: 643.3985 | BB59: 97.6475 | BC59: 786.34 | BD59: 1242.067 | BE59: 0 | BF59: 0 | BG59: 1415.4 | BH59: 0 | BI59: 0 | BJ59: 786.05 | BK59: 0 | BL59: 0 | BM59: 0 | BN59: 2193.5 | BO59: 3907.15 | BP59: 3892.8 | BQ59: 4023.35 | BR59: 5965.45 | BS59: 1765.2 | BT59: 862.1 | BU59: 0 | BV59: 0 | BW59: 0 | BX59: 0 | BY59: 0 | BZ59: 0 | CA59: 0 | CB59: 3348.2 | CC59: 1607.2 | CD59: 1538.3 | CE59: 1527.05 | CF59: 711.2 | CG59: 2522.4 | CH59: 0 | CI59: 0 | CJ59: 3444.2 | CK59: 3463.8 | CL59: 4075 | CM59: 4459.95 | CN59: 0 | CO59: 0 | CP59: 0 | CQ59: 0 | CR59: 5049.85 | CS59: 2420.55 | CT59: 79.15 | CU59: 0 | CV59: 104.55 | CW59: 8.45 | CX59: 2118.4 | CY59: 760.2 | CZ59: 41.8 | DA59: 3 | DB59: 279.05 | DC59: 237.95 | DD59: 126.7 | DE59: 2163.9 | DF59: 26.9 | DG59: 40.1 | DH59: 99.45 | DI59: 473.55 | DJ59: 249.65 | DK59: 327.7 | DL59: 55.05 | DM59: 410.2 | DN59: 128.15 | DO59: 161.25 | DP59: 510.15 | DQ59: 1387.8 | DR59: 154.35 | DS59: 55.4 | DT59: 355.85 | DU59: 70.75 | DV59: 0 | DW59: 3.044 | DX59: 103.35 | DY59: 191.45 | DZ59: 258.25 | EA59: 357.05 | EB59: 407.8 | EC59: 623.25 | ED59: 1148.35 | EE59: 296 | EF59: 909.35 | EG59: 1455.1 | EH59: 105.6 | EI59: 73 | EJ59: 394.335 | EK59: 220.9 | EL59: 69.35 | EM59: 202.1 | EN59: 489.6 | EO59: 489.6 | EP59: 482.4 | EQ59: 46.05 | ER59: 2451.85 | ES59: 136.7 | ET59: 1264.25 | EU59: 14.4 | EV59: 1150.8 | EW59: 1164.45 | EX59: 975.05 | EY59: 102.45 | EZ59: 52.75 | FA59: 28.8 | FB59: 28.8 | FC59: 123.1 | FD59: 137.15 | FE59: 239.95 | FF59: 211.35 | FG59: 650.8 | FH59: 826 | FI59: 0 | FJ59: 0 | FK59: 199.9 | FL59: 266.35 | FM59: 451 | FN59: 170753.72 | FP59: 317.71965 | FQ59: 58.9615 | FR59: 270.17478 | FS59: 188.3 | FT59: 636.13482 | FU59: 454.52832 | FV59: 100.95 | FW59: 280.95 | FX59: 2307.7191

Sheet REACTIVA
B3: sábado, 27 de Diciembre del 2025
A5: POTENCIA REACTIVA EJECUTADA DE LAS UNIDADES DE GENERACIÓN DEL COES (MVAR) | FP5: CENTRALES NO INTEGRANTES COES
A6: FECHA | B6: HORA | C6: 65333 | D6: 101 | E6: 102 | F6: 42667 | G6: 42668 | H6: 126 | I6: 127 | J6: 138 | K6: 139 | L6: 197 | M6: 203 | N6: 204 | O6: 230 | P6: 209 | Q6: 56677 | R6: 796 | S6: 2146 | T6: 142 | U6: 143 | V6: 125 | W6: 187 | X6: 163 | Y6: 298 | Z6: 299 | AA6: 219 | AB6: 151 | AC6: 152 | AD6: 153 | AE6: 154 | AF6: 756 | AG6: 156 | AH6: 155 | AI6: 182 | AJ6: 212 | AK6: 758 | AL6: 263 | AM6: 265 | AN6: 775 | AO6: 777 | AP6: 2154 | AQ6: 150 | AR6: 149 | AS6: 188 | AT6: 2131 | AU6: 755 | AV6: 252 | AW6: 249 | AX6: 250 | AY6: 117 | AZ6: 119 | BA6: 120 | BB6: 189 | BC6: 122 | BD6: 266 | BE6: 337 | BF6: 338 | BG6: 251 | BH6: 115 | BI6: 239 | BJ6: 288 | BK6: 240 | BL6: 241 | BM6: 242 | BN6: 191 | BO6: 194 | BP6: 196 | BQ6: 207 | BR6: 236 | BS6: 795 | BT6: 285 | BU6: 995 | BV6: 996 | BW6: 997 | BX6: 766 | BY6: 926 | BZ6: 924 | CA6: 121 | CB6: 103 | CC6: 104 | CD6: 106 | CE6: 105 | CF6: 107 | CG6: 110 | CH6: 109 | CI6: 144 | CJ6: 113 | CK6: 114 | CL6: 193 | CM6: 208 | CN6: 786 | CO6: 787 | CP6: 788 | CQ6: 789 | CR6: 248 | CS6: 2159 | CT6: 267 | CU6: 268 | CV6: 2194 | CW6: 303 | CX6: 59715 | CY6: 62255 | CZ6: 1263 | DA6: 61800 | DB6: 69125 | DC6: 216 | DD6: 198 | DE6: 70400 | DF6: 49607 | DG6: 214 | DH6: 260 | DI6: 2152 | DJ6: 2128 | DK6: 247 | DL6: 228 | DM6: 2135 | DN6: 261 | DO6: 237 | DP6: 253 | DQ6: 770 | DR6: 235 | DS6: 238 | DT6: 2184 | DU6: 61855 | DV6: 223 | DW6: 75566 | DX6: 226 | DY6: 201 | DZ6: 258 | EA6: 259 | EB6: 920 | EC6: 257 | ED6: 256 | EE6: 2148 | EF6: 58288 | EG6: 58289 | EH6: 58839 | EI6: 58840 | EJ6: 75260 | EK6: 296 | EL6: 297 | EM6: 211 | EN6: 2175 | EO6: 2178 | EP6: 2181 | EQ6: 1262 | ER6: 63425 | ES6: 233 | ET6: 2150 | EU6: 2165 | EV6: 2161 | EW6: 61197 | EX6: 58851 | EY6: 225 | EZ6: 2201 | FA6: 2171 | FB6: 760 | FC6: 234 | FD6: 215 | FE6: 917 | FF6: 289 | FG6: 58333 | FH6: 58336 | FI6: 213 | FJ6: 232 | FK6: 2190 | FL6: 69867 | FM6: 75066 | FN6: TOTAL COES | FP6: 221 | FQ6: 222 | FR6: 224 | FS6: 2187 | FT6: 227 | FU6: 49400 | FV6: 199 | FW6: 200 | FX6: TOTAL NO COES
C7: SUR | D7: CENTRO | E7: CENTRO | F7: NORTE | G7: NORTE | H7: NORTE | I7: NORTE | J7: CENTRO | K7: CENTRO | L7: CENTRO | M7: CENTRO | N7: CENTRO | O7: CENTRO | P7: CENTRO | Q7: CENTRO | R7: CENTRO | S7: CENTRO | T7: CENTRO | U7: CENTRO | V7: CENTRO | W7: CENTRO | X7: SUR | Y7: SUR | Z7: SUR | AA7: CENTRO | AB7: SUR | AC7: SUR | AD7: SUR | AE7: SUR | AF7: SUR | AG7: SUR | AH7: SUR | AI7: SUR | AJ7: CENTRO | AK7: NORTE | AL7: NORTE | AM7: NORTE | AN7: CENTRO | AO7: CENTRO | AP7: CENTRO | AQ7: CENTRO | AR7: CENTRO | AS7: CENTRO | AT7: CENTRO | AU7: SUR | AV7: CENTRO | AW7: CENTRO | AX7: CENTRO | AY7: CENTRO | AZ7: CENTRO | BA7: CENTRO | BB7: SUR | BC7: NORTE | BD7: CENTRO | BE7: CENTRO | BF7: CENTRO | BG7: CENTRO | BH7: NORTE | BI7: NORTE | BJ7: NORTE | BK7: SUR | BL7: SUR | BM7: SUR | BN7: CENTRO | BO7: CENTRO | BP7: CENTRO | BQ7: CENTRO | BR7: CENTRO | BS7: CENTRO | BT7: CENTRO | BU7: SUR | BV7: SUR | BW7: SUR | BX7: NORTE | BY7: SUR | BZ7: CENTRO | CA7: NORTE | CB7: CENTRO | CC7: CENTRO | CD7: CENTRO | CE7: CENTRO | CF7: CENTRO | CG7: CENTRO | CH7: CENTRO | CI7: CENTRO | CJ7: CENTRO | CK7: CENTRO | CL7: CENTRO | CM7: CENTRO | CN7: SUR | CO7: SUR | CP7: SUR | CQ7: SUR | CR7: CENTRO | CS7: CENTRO | CT7: CENTRO | CU7: CENTRO | CV7: NORTE | CW7: CENTRO | CX7: CENTRO | CY7: SUR | CZ7: NORTE | DA7: NORTE | DB7: CENTRO | DC7: NORTE | DD7: NORTE | DE7: SUR | DF7: SUR | DG7: CENTRO | DH7: CENTRO | DI7: CENTRO | DJ7: NORTE | DK7: NORTE | DL7: CENTRO | DM7: CENTRO | DN7: SUR | DO7: SUR | DP7: CENTRO | DQ7: CENTRO | DR7: SUR | DS7: CENTRO | DT7: CENTRO | DU7: NORTE | DV7: CENTRO | DW7: CENTRO | DX7: CENTRO | DY7: NORTE | DZ7: CENTRO | EA7: CENTRO | EB7: CENTRO | EC7: NORTE | ED7: NORTE | EE7: SUR | EF7: CENTRO | EG7: CENTRO | EH7: CENTRO | EI7: CENTRO | EJ7: SUR | EK7: CENTRO | EL7: CENTRO | EM7: SUR | EN7: SUR | EO7: SUR | EP7: SUR | EQ7: NORTE | ER7: SUR | ES7: SUR | ET7: SUR | EU7: CENTRO | EV7: CENTRO | EW7: CENTRO | EX7: SUR | EY7: CENTRO | EZ7: CENTRO | FA7: CENTRO | FB7: CENTRO | FC7: SUR | FD7: NORTE | FE7: CENTRO | FF7: NORTE | FG7: NORTE | FH7: NORTE | FI7: CENTRO | FJ7: NORTE | FK7: NORTE | FL7: NORTE | FM7: NORTE | FP7: NORTE | FQ7: CENTRO | FR7: NORTE | FS7: NORTE | FT7: NORTE | FU7: NORTE | FV7: NORTE | FW7: NORTE
C8: HIDROELÉCTRICA | D8: HIDROELÉCTRICA | E8: HIDROELÉCTRICA | F8: TERMOELÉCTRICA | G8: TERMOELÉCTRICA | H8: HIDROELÉCTRICA | I8: HIDROELÉCTRICA | J8: TERMOELÉCTRICA | K8: TERMOELÉCTRICA | L8: TERMOELÉCTRICA | M8: TERMOELÉCTRICA | N8: TERMOELÉCTRICA | O8: TERMOELÉCTRICA | P8: TERMOELÉCTRICA | Q8: TERMOELÉCTRICA | R8: HIDROELÉCTRICA | S8: HIDROELÉCTRICA | T8: TERMOELÉCTRICA | U8: TERMOELÉCTRICA | V8: TERMOELÉCTRICA | W8: TERMOELÉCTRICA | X8: HIDROELÉCTRICA | Y8: HIDROELÉCTRICA | Z8: HIDROELÉCTRICA | AA8: TERMOELÉCTRICA | AB8: HIDROELÉCTRICA | AC8: HIDROELÉCTRICA | AD8: HIDROELÉCTRICA | AE8: HIDROELÉCTRICA | AF8: TERMOELÉCTRICA | AG8: TERMOELÉCTRICA | AH8: TERMOELÉCTRICA | AI8: HIDROELÉCTRICA | AJ8: HIDROELÉCTRICA | AK8: TERMOELÉCTRICA | AL8: TERMOELÉCTRICA | AM8: TERMOELÉCTRICA | AN8: HIDROELÉCTRICA | AO8: HIDROELÉCTRICA | AP8: HIDROELÉCTRICA | AQ8: HIDROELÉCTRICA | AR8: HIDROELÉCTRICA | AS8: HIDROELÉCTRICA | AT8: HIDROELÉCTRICA | AU8: HIDROELÉCTRICA | AV8: TERMOELÉCTRICA | AW8: TERMOELÉCTRICA | AX8: TERMOELÉCTRICA | AY8: HIDROELÉCTRICA | AZ8: HIDROELÉCTRICA | BA8: HIDROELÉCTRICA | BB8: HIDROELÉCTRICA | BC8: HIDROELÉCTRICA | BD8: HIDROELÉCTRICA | BE8: HIDROELÉCTRICA | BF8: HIDROELÉCTRICA | BG8: HIDROELÉCTRICA | BH8: TERMOELÉCTRICA | BI8: TERMOELÉCTRICA | BJ8: TERMOELÉCTRICA | BK8: TERMOELÉCTRICA | BL8: TERMOELÉCTRICA | BM8: TERMOELÉCTRICA | BN8: HIDROELÉCTRICA | BO8: TERMOELÉCTRICA | BP8: TERMOELÉCTRICA | BQ8: TERMOELÉCTRICA | BR8: TERMOELÉCTRICA | BS8: TERMOELÉCTRICA | BT8: TERMOELÉCTRICA | BU8: TERMOELÉCTRICA | BV8: TERMOELÉCTRICA | BW8: TERMOELÉCTRICA | BX8: HIDROELÉCTRICA | BY8: TERMOELÉCTRICA | BZ8: TERMOELÉCTRICA | CA8: HIDROELÉCTRICA | CB8: HIDROELÉCTRICA | CC8: HIDROELÉCTRICA | CD8: HIDROELÉCTRICA | CE8: HIDROELÉCTRICA | CF8: HIDROELÉCTRICA | CG8: TERMOELÉCTRICA | CH8: TERMOELÉCTRICA | CI8: TERMOELÉCTRICA | CJ8: TERMOELÉCTRICA | CK8: TERMOELÉCTRICA | CL8: TERMOELÉCTRICA | CM8: TERMOELÉCTRICA | CN8: TERMOELÉCTRICA | CO8: TERMOELÉCTRICA | CP8: TERMOELÉCTRICA | CQ8: TERMOELÉCTRICA | CR8: TERMOELÉCTRICA | CS8: TERMOELÉCTRICA | CT8: HIDROELÉCTRICA | CU8: HIDROELÉCTRICA | CV8: HIDROELÉCTRICA | CW8: SOLAR | CX8: EÓLICA | CY8: SOLAR | CZ8: EÓLICA | DA8: SOLAR | DB8: HIDROELÉCTRICA | DC8: HIDROELÉCTRICA | DD8: HIDROELÉCTRICA | DE8: SOLAR | DF8: HIDROELÉCTRICA | DG8: HIDROELÉCTRICA | DH8: HIDROELÉCTRICA | DI8: HIDROELÉCTRICA | DJ8: HIDROELÉCTRICA | DK8: HIDROELÉCTRICA | DL8: HIDROELÉCTRICA | DM8: HIDROELÉCTRICA | DN8: SOLAR | DO8: SOLAR | DP8: EÓLICA | DQ8: EÓLICA | DR8: SOLAR | DS8: HIDROELÉCTRICA | DT8: HIDROELÉCTRICA | DU8: HIDROELÉCTRICA | DV8: HIDROELÉCTRICA | DW8: SOLAR | DX8: HIDROELÉCTRICA | DY8: HIDROELÉCTRICA | DZ8: HIDROELÉCTRICA | EA8: HIDROELÉCTRICA | EB8: HIDROELÉCTRICA | EC8: EÓLICA | ED8: EÓLICA | EE8: SOLAR | EF8: EÓLICA | EG8: EÓLICA | EH8: EÓLICA | EI8: EÓLICA | EJ8: SOLAR | EK8: HIDROELÉCTRICA | EL8: HIDROELÉCTRICA | EM8: HIDROELÉCTRICA | EN8: HIDROELÉCTRICA | EO8: HIDROELÉCTRICA | EP8: HIDROELÉCTRICA | EQ8: EÓLICA | ER8: SOLAR | ES8: SOLAR | ET8: SOLAR | EU8: HIDROELÉCTRICA | EV8: EÓLICA | EW8: EÓLICA | EX8: SOLAR | EY8: TERMOELÉCTRICA | EZ8: TERMOELÉCTRICA | FA8: TERMOELÉCTRICA | FB8: TERMOELÉCTRICA | FC8: SOLAR | FD8: HIDROELÉCTRICA | FE8: HIDROELÉCTRICA | FF8: TERMOELÉCTRICA | FG8: TERMOELÉCTRICA | FH8: TERMOELÉCTRICA | FI8: TERMOELÉCTRICA | FJ8: TERMOELÉCTRICA | FK8: TERMOELÉCTRICA | FL8: TERMOELÉCTRICA | FM8: TERMOELÉCTRICA | FP8: HIDROELÉCTRICA | FQ8: HIDROELÉCTRICA | FR8: HIDROELÉCTRICA | FS8: HIDROELÉCTRICA | FT8: TERMOELÉCTRICA | FU8: TERMOELÉCTRICA | FV8: HIDROELÉCTRICA | FW8: HIDROELÉCTRICA
C9: HYDRO GLOBAL PERÚ S.A.C. | D9: ELECTROPERU | E9: ELECTROPERU | F9: ELECTROPERU | G9: ELECTROPERU | H9: ORAZUL ENERGY PERÚ | I9: ORAZUL ENERGY PERÚ | J9: TERMOSELVA | K9: TERMOSELVA | L9: KALLPA GENERACION S.A. | M9: KALLPA GENERACION S.A. | N9: KALLPA GENERACION S.A. | O9: KALLPA GENERACION S.A. | P9: KALLPA GENERACION S.A. | Q9: KALLPA GENERACION S.A. | R9: KALLPA GENERACION S.A. | S9: KALLPA GENERACION S.A. | T9: SHOUGESA | U9: SHOUGESA | V9: SHOUGESA | W9: SHOUGESA | X9: EGEMSA | Y9: EGESUR | Z9: EGESUR | AA9: EGESUR | AB9: EGASA | AC9: EGASA | AD9: EGASA | AE9: EGASA | AF9: EGASA | AG9: EGASA | AH9: EGASA | AI9: SAN GABAN | AJ9: CELEPSA | AK9: MINERA CERRO VERDE | AL9: PLANTA DE RESERVA FRIA DE GENERACION DE ETEN S.A. | AM9: PLANTA DE RESERVA FRIA DE GENERACION DE ETEN S.A. | AN9: EMPRESA DE GENERACION HUALLAGA | AO9: EMPRESA DE GENERACION HUALLAGA | AP9: LA VIRGEN | AQ9: CHINANGO S.A.C. | AR9: CHINANGO S.A.C. | AS9: HIDROELECTRICA HUANCHOR S.A.C. | AT9: CELEPSA RENOVABLES S.R.L. | AU9: INLAND ENERGY SAC | AV9: FENIX POWER PERÚ | AW9: FENIX POWER PERÚ | AX9: FENIX POWER PERÚ | AY9: STATKRAFT S.A | AZ9: STATKRAFT S.A | BA9: STATKRAFT S.A | BB9: STATKRAFT S.A | BC9: STATKRAFT S.A | BD9: STATKRAFT S.A | BE9: CENTRALES SANTA ROSA S.A.C. | BF9: CENTRALES SANTA ROSA S.A.C. | BG9: EMPRESA DE GENERACION HUANZA | BH9: ENEL GENERACION PIURA S.A. | BI9: ENEL GENERACION PIURA S.A. | BJ9: ENEL GENERACION PIURA S.A. | BK9: ENGIE ENERGIA PERU S.A.A. | BL9: ENGIE ENERGIA PERU S.A.A. | BM9: ENGIE ENERGIA PERU S.A.A. | BN9: ENGIE ENERGIA PERU S.A.A. | BO9: ENGIE ENERGIA PERU S.A.A. | BP9: ENGIE ENERGIA PERU S.A.A. | BQ9: ENGIE ENERGIA PERU S.A.A. | BR9: ENGIE ENERGIA PERU S.A.A. | BS9: ENGIE ENERGIA PERU S.A.A. | BT9: ENGIE ENERGIA PERU S.A.A. | BU9: ENGIE ENERGIA PERU S.A.A. | BV9: ENGIE ENERGIA PERU S.A.A. | BW9: ENGIE ENERGIA PERU S.A.A. | BX9: ENGIE ENERGIA PERU S.A.A. | BY9: INFRAESTRUCTURAS Y ENERGIAS DEL PERU S.A.C. | BZ9: INFRAESTRUCTURAS Y ENERGIAS DEL PERU S.A.C. | CA9: INVERSIONES SHAQSHA S.A.C. | CB9: ORYGEN PERU S.A.A. | CC9: ORYGEN PERU S.A.A. | CD9: ORYGEN PERU S.A.A. | CE9: ORYGEN PERU S.A.A. | CF9: ORYGEN PERU S.A.A. | CG9: ORYGEN PERU S.A.A. | CH9: ORYGEN PERU S.A.A. | CI9: ORYGEN PERU S.A.A. | CJ9: ORYGEN PERU S.A.A. | CK9: ORYGEN PERU S.A.A. | CL9: ORYGEN PERU S.A.A. | CM9: ORYGEN PERU S.A.A. | CN9: SAMAY I S.A.C | CO9: SAMAY I S.A.C | CP9: SAMAY I S.A.C | CQ9: SAMAY I S.A.C | CR9: TERMOCHILCA S.A.C. | CS9: TERMOCHILCA S.A.C. | CT9: TRANSMISION ANDINA DE GENERACION S.A.C. | CU9: TRANSMISION ANDINA DE GENERACION S.A.C. | CV9: CELARIS ENERGY S.A. | CW9: COLCA SOLAR S.A.C. | CX9: ENERGIA RENOVABLE DEL SUR S.A. | CY9: GR CORTARRAMA SOCIEDAD ANONIMA CERRADA | CZ9: GR TARUCA SOCIEDAD ANONIMA CERRADA | DA9: KONDU SAC | DB9: VARI ENERGIA S.A.C. | DC9: ORAZUL ENERGY PERÚ | DD9: ORAZUL ENERGY PERÚ | DE9: KALLPA GENERACION S.A. | DF9: SAN GABAN | DG9: MAJA ENERGIA S.A.C. | DH9: EMPRESA DE GENERACION ELECTRICA CANCHAYLLO SAC | DI9: EMPRESA DE GENERACION ELECTRICA SANTA ANA S.A.C. | DJ9: EMPRESA ELECTRICA AGUA AZUL | DK9: EMPRESA ELECTRICA RIO DOBLE | DL9: HIDROCAÑETE S.A. | DM9: HUAURA POWER GROUP S.A. | DN9: MOQUEGUA FV S.A.C. | DO9: PANAMERICANA SOLAR SAC. | DP9: PARQUE EOLICO MARCONA S.A.C. | DQ9: PARQUE EOLICO TRES HERMANAS S.A.C. | DR9: TACNA SOLAR SAC. | DS9: ELECTRICA YANAPAMPA SAC | DT9: ANDEAN POWER S.A.C. | DU9: ASOCIACIÓN SANTA LUCIA DE CHACAS | DV9: ATRIA ENERGIA S.A.C. | DW9: COENERGY S.A.C. | DX9: EGEJUNIN | DY9: EGEJUNIN | DZ9: EGEJUNIN | EA9: EGEJUNIN | EB9: EMPRESA DE GENERACION ELECTRICA RIO BAÑOS S.A.C. | EC9: ENERGÍA EÓLICA S.A. | ED9: ENERGÍA EÓLICA S.A. | EE9: ENGIE ENERGIA PERU S.A.A. | EF9: ENGIE ENERGIA PERU S.A.A. | EG9: ENGIE ENERGIA PERU S.A.A. | EH9: ENGIE ENERGIA PERU S.A.A. | EI9: ENGIE ENERGIA PERU S.A.A. | EJ9: ENGIE ENERGIA PERU S.A.A. | EK9: GENERACIÓN ANDINA S.A.C. | EL9: GENERACIÓN ANDINA S.A.C. | EM9: GENERADORA DE ENERGÍA DEL PERÚ | EN9: GENERADORA DE ENERGÍA DEL PERÚ | EO9: GENERADORA DE ENERGÍA DEL PERÚ | EP9: GENERADORA DE ENERGÍA DEL PERÚ | EQ9: GR PAINO SOCIEDAD ANONIMA CERRADA | ER9: JOYA SOLAR S.A.C. | ES9: MAJES ARCUS S.A.C. | ET9: ORYGEN PERU S.A.A. | EU9: ORYGEN PERU S.A.A. | EV9: ORYGEN PERU S.A.A. | EW9: ORYGEN PERU S.A.A. | EX9: ORYGEN PERU S.A.A. | EY9: PETRAMAS | EZ9: PETRAMAS | FA9: PETRAMAS | FB9: PETRAMAS | FC9: REPARTICIÓN ARCUS S.A.C. | FD9: SINERSA | FE9: SINERSA | FF9: BIOENERGIA DEL CHIRA S.A. | FG9: GM OPERACIONES S.A.C. | FH9: GM OPERACIONES S.A.C. | FI9: AGRO INDUSTRIAL PARAMONGA S.A. | FJ9: AGROAURORA S.A.C. | FK9: AGROINDUSTRIAS SAN JACINTO S.A.A. | FL9: AGROLMOS SOCIEDAD ANONIMA - AGROLMOS S.A. | FM9: CASA GRANDE S.A.A. | FP9: UNACEM PERU S.A. | FQ9: ELECTRO ORIENTE | FR9: AGUAS Y ENERGIA PERU | FS9: ELECTRO ZAÑA S.A.C. | FT9: ELECTRONOROESTE S.A. | FU9: SDE PIURA | FV9: SINERSA | FW9: SINERSA
C10: SAN GABAN III | D10: MANTARO | E10: RESTITUCION | F10: TUMBES MAK 1 | G10: TUMBES MAK 2 | H10: CARHUAQUERO | I10: CAÑON DEL PATO | J10: AGUAYTIA TG1 | K10: AGUAYTIA TG2 | L10: KALLPA TG1 | M10: KALLPA TG2 | N10: KALLPA TG3 | O10: KALLPA TV | P10: LFLORES TG1 | Q10: LFLORES TV | R10: CERRO DEL AGUILA | S10: CERRODELAGUILAG4 | T10: SHOUGESA TV1 | U10: SHOUGESA TV2 | V10: SHOUGESA TV3 | W10: SHOUGESA CUMMINS | X10: MACHUPICCHU | Y10: ARICOTA 1 | Z10: ARICOTA 2 | AA10: INDEPENDENCIA | AB10: CHARCANI I,II,III | AC10: CHARCANI IV | AD10: CHARCANI V | AE10: CHARCANI VI | AF10: CHILINA TG | AG10: MOLLENDO 1, 2, 3 | AH10: CHILINA (SULZ 1,2) | AI10: SAN GABAN II | AJ10: PLATANAL | AK10: RECKA | AL10: RF ETEN TG1 | AM10: RF ETEN TG2 | AN10: CHAGLLA GP1 | AO10: CHAGLLA | AP10: LA VIRGEN | AQ10: CHIMAY | AR10: YANANGO | AS10: HUANCHOR | AT10: MARAÑON | AU10: STA TERESA | AV10: FENIX GT11 | AW10: FENIX GT12 | AX10: FENIX TV10 | AY10: YAUPI | AZ10: MALPASO | BA10: CAHUA | BB10: ARCATA | BC10: GALLITO CIEGO | BD10: CHEVES | BE10: SANTA ROSA 1 | BF10: SANTA ROSA 2 | BG10: HUANZA | BH10: MALACAS2 TG4 | BI10: MALACAS3 TG 5 | BJ10: MALACAS1 TG6 | BK10: RF ILO2 TG1 | BL10: RF ILO2 TG2 | BM10: RF ILO2 TG3 | BN10: YUNCAN | BO10: CHILCA1 TG1 | BP10: CHILCA1 TG2 | BQ10: CHILCA1 TG3 | BR10: CHILCA-TV | BS10: CHILCA2 TG41 | BT10: CHILCA2-TV | BU10: CTNEPI_TG41 | BV10: CTNEPI_TG42 | BW10: CTNEPI_TG43 | BX10: QUITARACSA | BY10: RF PTO MALDONADO | BZ10: RF PUCALLPA | CA10: PARIAC | CB10: HUINCO | CC10: MATUCANA | CD10: MOYOPAMPA | CE10: CALLAHUANCA | CF10: HUAMPANI | CG10: STA ROSA WEST TG7 | CH10: UTI_5 | CI10: UTI_6 | CJ10: VENTANILLA 3 | CK10: VENTANILLA 4 | CL10: VENTANILLA TV | CM10: STAROSA TG8 | CN10: PTO_BRVO TG1 | CO10: PTO_BRVO TG2 | CP10: PTO_BRVO TG3 | CQ10: PTO_BRVO TG4 | CR10: OLLEROS TG1 | CS10: OLLEROS TV | CT10: OROYA | CU10: PACHACHACA | CV10: MANTA I | CW10: CS YARUCAYA | CX10: SAN JUAN | CY10: MATARANI | CZ10: DUNA | DA10: CARHUAQUERO (CS) | DB10: ANASHIRONI | DC10: CARHUAQUERO4 | DD10: CAÑA BRAVA | DE10: SUNNY | DF10: TUPURI | DG10: RONCADOR | DH10: CANCHAYLLO | DI10: RENOVANDESH1 | DJ10: POTRERO | DK10: PIZARRAS | DL10: NIMPERIAL | DM10: YARUCAYA | DN10: MOQUEGUA-SOLAR | DO10: PANAMERICANA-SOLAR | DP10: PQE-EOLICO-MARCONA | DQ10: PQE-EOLICO-3-HERMANAS | DR10: TACNA-SOLAR | DS10: YANAPAMPA | DT10: CARHUAC | DU10: HUALLIN | DV10: PURMACANA | DW10: COENERGY | DX10: HUASAHUASI | DY10: STACRUZ_1_2 | DZ10: RUNATULLO_II | EA10: RUNATULLO_III | EB10: RUCUY | EC10: PQE-EOLICO-TALARA | ED10: PQE-EOLICO-CUPISNIQUE | EE10: INTIPAMPA | EF10: PUNTA LOMITAS-BL1 | EG10: PUNTA LOMITAS-BL2 | EH10: PUN LOMITAS_EXP-BL1 | EI10: PUN LOMITAS_EXP-BL2 | EJ10: EXPANSIÓN INTIPAMPA | EK10: 8AGOSTO | EL10: EL CARMEN | EM10: LA JOYA | EN10: ANGEL_I | EO10: ANGEL_II | EP10: ANGEL_III | EQ10: HUAMBOS | ER10: SAN MARTIN SOLAR | ES10: MAJES | ET10: RUBI | EU10: CH_HER1 | EV10: WAYRA-I | EW10: WAYRA EXTENSION | EX10: CLEMESI | EY10: HUAYCOLORO | EZ10: CALLAO | FA10: DONA_CATALINA | FB10: LAGRINGAV | FC10: REPARTICION | FD10: POECHOS2 | FE10: CHANCAY | FF10: CANA BRAVA | FG10: REFINERIA TALARA TV1 | FH10: REFINERÍA TALARA TV2 | FI10: PARAMONGA | FJ10: MAPLE | FK10: SAN_JACINTO | FL10: AGROLMOS | FM10: CASA GRANDE | FN10: MVAR | FP10: CARPAPATA | FQ10: CENTRALES ELOR | FR10: PIAS1 | FS10: ZANA | FT10: TABLAZO | FU10: TALLANCA | FV10: CURUMUY | FW10: POECHOS1 | FX10: MVAR
A11: 27/12/2025 | B11: 00:30 | C11: 39.3 | D11: -45.7 | E11: -5.8 | H11: -15.8 | I11: -2.1 | K11: 0 | L11: -31.5 | N11: -16.9 | P11: 21.6 | R11: 31.4 | S11: 0.1 | X11: -5.1 | Y11: 1 | Z11: 0.9 | AA11: 2.9 | AB11: -3.6 | AC11: 3.1 | AD11: 2 | AI11: 18.3 | AJ11: 0 | AN11: -1.1 | AO11: -3.7 | AP11: 3 | AQ11: 10.4 | AR11: 4.1 | AS11: -0.4 | AT11: 2 | AU11: 1.5 | AV11: -3.65526 | AW11: -22.4188 | AX11: -48.75872 | AY11: -0.989 | AZ11: 0 | BA11: -0.214 | BB11: 0.932 | BC11: -0.13 | BD11: 6.11 | BG11: -1 | BJ11: -2 | BN11: 2.6 | BO11: -40.6 | BP11: -55.9 | BQ11: -22.7 | BR11: 5.9 | BS11: -1.3 | BT11: -1.5 | CB11: 42.2 | CC11: 31.6 | CD11: 2.3 | CE11: 2.5 | CF11: 2.1 | CG11: -23.5 | CJ11: -3.3 | CK11: -5.6 | CL11: -24 | CM11: -45.3 | CR11: -8.2 | CS11: -12 | CT11: -0.5 | CV11: 0.3 | CX11: -8.9 | CY11: 0 | CZ11: -0.6 | DB11: 0 | DC11: 0 | DD11: -0.8 | DE11: 0 | DG11: 0.1 | DH11: 1.2 | DI11: 0.1 | DJ11: 0.1 | DK11: 0.1 | DL11: 0.4 | DN11: 0 | DO11: 0 | DP11: -1.1 | DQ11: -4.1 | DR11: 0 | DS11: -0.1 | DT11: 0.5 | DU11: 0.5 | DW11: 0 | DX11: -1.2 | DY11: 0.5 | DZ11: 0.3 | EA11: 1 | EB11: 0 | ED11: 11.5 | EE11: 0 | EF11: -4.5 | EG11: -5.5 | EH11: -0.4 | EI11: 0 | EJ11: 0 | EK11: 1.3 | EL11: -0.2 | EM11: 1.6 | EN11: 0.2 | EO11: 0.2 | EP11: 0.2 | EQ11: -1.2 | ER11: 0 | ES11: 0 | ET11: 0 | EU11: -0.2 | EV11: -9.8 | EW11: 0 | EX11: 0 | EY11: 1.8 | EZ11: 0.7 | FA11: 0.4 | FB11: 0.5 | FC11: 0 | FD11: 0.2 | FE11: 0 | FF11: 1.8 | FG11: 13 | FH11: 0.4 | FK11: 2.6 | FL11: 3.9 | FM11: 12.14 | FN11: -198.48378 | FP11: 2.69099 | FQ11: 0 | FR11: 2.157 | FS11: 1.1 | FT11: 0.325 | FU11: 1.38911 | FV11: -0.9 | FW11: 1.8 | FX11: 8.5621
A12: 27/12/2025 | B12: 01:00 | C12: 40.8 | D12: -55.3 | E12: -7.8 | H12: -15.8 | I12: -10.5 | K12: 0 | L12: -32.5 | N12: -21.1 | P12: 20.5 | R12: 12.8 | S12: 0.1 | X12: -6.2 | Y12: 1.1 | Z12: 0.8 | AA12: 2.9 | AB12: -3.6 | AC12: 2.9 | AD12: 1.7 | AI12: 18.3 | AJ12: 0 | AN12: -1.1 | AO12: -14.9 | AP12: 2.7 | AQ12: 11.3 | AR12: 3.9 | AS12: -0.9 | AT12: 2 | AU12: 2.1 | AV12: -6.43775 | AW12: -25.04342 | AX12: -46.25053 | AY12: -2.789 | AZ12: 0 | BA12: -1.251 | BB12: 0.964 | BC12: 0 | BD12: 5.786 | BG12: -2.5 | BJ12: -2 | BN12: 0.9 | BO12: -40.3 | BP12: -55.5 | BQ12: -23.3 | BR12: 5 | BS12: -1.7 | BT12: -1.6 | CB12: 43.4 | CC12: 31.8 | CD12: 2.8 | CE12: 4.4 | CF12: 1.9 | CG12: -25.1 | CJ12: -6.8 | CK12: -9.5 | CL12: -29 | CM12: -51.3 | CR12: -11.2 | CS12: -13.7 | CT12: -0.5 | CV12: 0.3 | CX12: -8.9 | CY12: 0 | CZ12: -0.9 | DB12: 0 | DC12: 0 | DD12: -0.8 | DE12: 0 | DG12: 0.1 | DH12: 1.1 | DI12: 0 | DJ12: 0 | DK12: 0.2 | DL12: 0.4 | DN12: 0 | DO12: 0 | DP12: -0.8 | DQ12: -3.9 | DR12: 0 | DS12: 0 | DT12: 0.5 | DU12: 0.5 | DW12: 0 | DX12: -1.2 | DY12: 0.7 | DZ12: 0.4 | EA12: 0.4 | EB12: 0.1 | ED12: 12.9 | EE12: 0 | EF12: -4.3 | EG12: -5.3 | EH12: -0.5 | EI12: 0 | EJ12: 0 | EK12: 1.3 | EL12: -0.2 | EM12: 1.6 | EN12: 0.2 | EO12: 0.2 | EP12: 0.2 | EQ12: -2 | ER12: 0 | ES12: 0 | ET12: 0 | EU12: -0.2 | EV12: -10.5 | EW12: 0 | EX12: 0 | EY12: 1.8 | EZ12: 0.7 | FA12: 0.4 | FB12: 0.5 | FC12: 0 | FD12: 0.2 | FE12: 0 | FF12: 1.9 | FG12: 13.1 | FH12: 0.3 | FK12: 2.7 | FL12: 3.2 | FM12: 11.86 | FN12: -286.3617 | FP12: 2.68284 | FQ12: 0 | FR12: 1.888 | FS12: 1.1 | FT12: 0.30399 | FU12: 1.39688 | FV12: -1 | FW12: 1.7 | FX12: 8.07171
A13: 27/12/2025 | B13: 01:30 | C13: 41.3 | D13: -58 | E13: -8.7 | H13: -14.8 | I13: -8.9 | K13: 0 | L13: -33.1 | N13: -14.1 | P13: 20.1 | R13: 9.2 | S13: 0.2 | X13: -5.6 | Y13: 0.8 | Z13: 0.7 | AA13: 2.8 | AB13: -3.6 | AC13: 2.8 | AD13: 1.1 | AI13: 19.4 | AJ13: 0 | AN13: -1.2 | AO13: -16.1 | AP13: 2.8 | AQ13: 11.1 | AR13: 3.7 | AS13: -1.3 | AT13: 1.8 | AU13: 0.9 | AV13: -7.59164 | AW13: -25.66174 | AX13: -47.04701 | AY13: -1.196 | AZ13: 0 | BA13: 0.732 | BB13: 0.932 | BC13: -0.07 | BD13: 7.323 | BG13: -5.8 | BJ13: 0 | BN13: 1 | BO13: -39.7 | BP13: -55.2 | BQ13: -17 | BR13: 7.5 | BS13: -1.9 | BT13: -1.7 | CB13: 41.9 | CC13: 31.3 | CD13: 2.1 | CE13: 2.4 | CF13: 2 | CG13: -26.9 | CJ13: -9.4 | CK13: -12 | CL13: -32.2 | CM13: -50.8 | CR13: -12.2 | CS13: -14.3 | CT13: -0.5 | CV13: 0.3 | CX13: -8.6 | CY13: 0 | CZ13: -2.5 | DB13: 0 | DC13: -0.1 | DD13: -0.8 | DE13: 0 | DG13: 0 | DH13: 1.2 | DI13: 0.1 | DJ13: 0 | DK13: 0.1 | DL13: 0.4 | DN13: 0 | DO13: 0 | DP13: -0.6 | DQ13: -3.8 | DR13: 0 | DS13: 0 | DT13: -0.4 | DU13: 0.5 | DW13: 0 | DX13: -1.2 | DY13: 0.4 | DZ13: 0.4 | EA13: 0.4 | EB13: -0.1 | ED13: 14.7 | EE13: 0 | EF13: -2.7 | EG13: -3.4 | EH13: 0 | EI13: 0 | EJ13: 0 | EK13: 1.4 | EL13: -0.2 | EM13: 1.9 | EN13: 0.2 | EO13: 0.2 | EP13: 0.2 | EQ13: -4.6 | ER13: 0 | ES13: 0 | ET13: 0 | EU13: -0.2 | EV13: -10.6 | EW13: 0 | EX13: 0 | EY13: 1.8 | EZ13: 0.7 | FA13: 0.4 | FB13: 0.5 | FC13: 0 | FD13: 0.2 | FE13: 0 | FF13: 1.8 | FG13: 12.9 | FH13: 0.1 | FK13: 2 | FL13: 2.5 | FM13: 10.62 | FN13: -294.55939 | FP13: 2.7906 | FQ13: 0 | FR13: 1.8285 | FS13: 1.1 | FT13: 0.33525 | FU13: 1.39216 | FV13: -1 | FW13: 1.7 | FX13: 8.14651
A14: 27/12/2025 | B14: 02:00 | C14: 39.8 | D14: -58.7 | E14: -8.4 | H14: -16.4 | I14: 5.7 | K14: 0 | L14: -33.1 | N14: -15.4 | P14: 20.2 | R14: 13.7 | S14: 0 | X14: -6.8 | Y14: 0.6 | Z14: 0.5 | AA14: 3 | AB14: -3.6 | AC14: 2.7 | AD14: 0.2 | AI14: 19 | AJ14: 0 | AN14: -1.2 | AO14: -13.1 | AP14: 3.1 | AQ14: 10.8 | AR14: 4.2 | AS14: -0.9 | AT14: 1.8 | AU14: 2.6 | AV14: -6.73713 | AW14: -25.72823 | AX14: -47.11241 | AY14: -0.952 | AZ14: 0 | BA14: -0.458 | BB14: 0.94 | BC14: 0.01 | BD14: 3.195 | BG14: -4.7 | BJ14: 0 | BN14: 1.2 | BO14: -41.4 | BP14: -57.2 | BQ14: -25 | BR14: 2.4 | BS14: -2.4 | BT14: -1.9 | CB14: 43.7 | CC14: 32 | CD14: -6.6 | CE14: 2.5 | CF14: -2 | CG14: -26.3 | CJ14: -8.9 | CK14: -11.3 | CL14: -32.1 | CM14: -51.5 | CR14: -13.7 | CS14: -15.2 | CT14: -0.4 | CV14: 0.3 | CX14: -5.5 | CY14: 0 | CZ14: -1.4 | DB14: 0 | DC14: 0.2 | DD14: -0.8 | DE14: 0 | DG14: 0.1 | DH14: 1.2 | DI14: 0.2 | DJ14: -0.7 | DK14: 0.2 | DL14: 0.4 | DN14: 0 | DO14: 0 | DP14: -0.7 | DQ14: -3.1 | DR14: 0 | DS14: 0 | DT14: -0.3 | DU14: 0.5 | DW14: 0 | DX14: -1.2 | DY14: 0.4 | DZ14: 0.4 | EA14: 0.5 | EB14: -0.1 | ED14: 15.6 | EE14: 0 | EF14: -1.2 | EG14: -2.1 | EH14: 0 | EI14: 0 | EJ14: 0 | EK14: 1.4 | EL14: -0.2 | EM14: 2 | EN14: 0.2 | EO14: 0.2 | EP14: 0.2 | EQ14: -1.7 | ER14: 0 | ES14: 0 | ET14: 0 | EU14: -0.2 | EV14: 0 | EW14: 0 | EX14: 0 | EY14: 1.8 | EZ14: 0.7 | FA14: 0.4 | FB14: 0.5 | FC14: 0 | FD14: 0.2 | FE14: -0.1 | FF14: 1.9 | FG14: 12.4 | FH14: 0.4 | FK14: 2 | FL14: 3.5 | FM14: 10.7 | FN14: -286.14277 | FP14: 2.72503 | FQ14: 0 | FR14: 1.725 | FS14: 1.1 | FT14: 0.3377 | FU14: 0.75667 | FV14: -1 | FW14: 1.6 | FX14: 7.2444
A15: 27/12/2025 | B15: 02:30 | C15: 42.1 | D15: -57.8 | E15: -8.6 | H15: -14.1 | I15: -9.9 | K15: 0 | L15: -34.4 | N15: -13.1 | P15: 19.5 | R15: 16 | S15: 0.1 | X15: -4.2 | Y15: 1.3 | Z15: 1 | AA15: 2.9 | AB15: -3.6 | AC15: 3.3 | AD15: 4.9 | AI15: 19.3 | AJ15: 0 | AN15: -1.2 | AO15: 0 | AP15: 2.6 | AQ15: 11 | AR15: 4 | AS15: -1 | AT15: 1.8 | AU15: 1.1 | AV15: -6.37247 | AW15: -25.04667 | AX15: -46.68941 | AY15: -0.493 | AZ15: 0 | BA15: -1.251 | BB15: 0.963 | BC15: -0.03 | BD15: 0.099 | BG15: -5.8 | BJ15: 0 | BN15: 0.2 | BO15: -41.9 | BP15: -55.9 | BQ15: -23.5 | BR15: 3.8 | BS15: -2.2 | BT15: -1.7 | CB15: 42.3 | CC15: 31.9 | CD15: -6.5 | CE15: 2.4 | CF15: -2.2 | CG15: -26.7 | CJ15: -9.7 | CK15: -12.1 | CL15: -33.3 | CM15: -48.5 | CR15: -11 | CS15: -13.5 | CT15: -0.3 | CV15: 0.3 | CX15: -3.6 | CY15: 0 | CZ15: -0.3 | DB15: 0 | DC15: 0 | DD15: -0.7 | DE15: 0 | DG15: 0.1 | DH15: 1.1 | DI15: 0.1 | DJ15: -0.1 | DK15: 0.2 | DL15: 0.4 | DN15: 0 | DO15: 0 | DP15: 0.1 | DQ15: -1.2 | DR15: 0 | DS15: 0.2 | DT15: -0.3 | DU15: 0.5 | DW15: 0 | DX15: -1.2 | DY15: 0.6 | DZ15: 0.4 | EA15: 0.4 | EB15: -0.1 | ED15: 8.4 | EE15: 0 | EF15: -2.5 | EG15: -3.1 | EH15: 0 | EI15: 0 | EJ15: 0 | EK15: 1.4 | EL15: -0.2 | EM15: 1.9 | EN15: 0.2 | EO15: 0.2 | EP15: 0.2 | EQ15: -1 | ER15: 0 | ES15: 0 | ET15: 0 | EU15: -0.2 | EV15: 0 | EW15: 0 | EX15: 0 | EY15: 1.8 | EZ15: 0.7 | FA15: 0.4 | FB15: 0.5 | FC15: 0 | FD15: 0.2 | FE15: 0 | FF15: 2 | FG15: 12.2 | FH15: 0.3 | FK15: 2.3 | FL15: 4.1 | FM15: 11.62 | FN15: -271.70055 | FP15: 2.62687 | FQ15: 0 | FR15: 1.8975 | FS15: 1.1 | FT15: 0.33425 | FU15: 0.29446 | FV15: -1.1 | FW15: 1.8 | FX15: 6.95308
A16: 27/12/2025 | B16: 03:00 | C16: 44.8 | D16: -51.8 | E16: -7.8 | H16: -15.2 | I16: -1.1 | K16: 0 | L16: -32.2 | N16: -17 | P16: 21.6 | R16: 20.3 | S16: 0 | X16: -3.7 | Y16: 1.5 | Z16: 1.2 | AA16: 3 | AB16: -3.6 | AC16: 3.3 | AD16: 5.5 | AI16: 19.8 | AJ16: 0 | AN16: -1.3 | AO16: 0 | AP16: 3 | AQ16: 10.8 | AR16: 4.1 | AS16: -1.2 | AT16: 1.8 | AU16: 1.1 | AV16: -4.41057 | AW16: -23.37276 | AX16: -44.7414 | AY16: -1.506 | AZ16: 0 | BA16: -1.007 | BB16: 0.958 | BC16: -0.01 | BD16: -0.467 | BG16: -4.3 | BJ16: 0 | BN16: 1.6 | BO16: -39 | BP16: -54.1 | BQ16: -22.5 | BR16: 4.5 | BS16: -1.4 | BT16: -1.5 | CB16: 42.5 | CC16: 32.1 | CD16: -6 | CE16: 2.5 | CF16: -2.2 | CG16: -25.4 | CJ16: -8.4 | CK16: -10.9 | CL16: -31.5 | CM16: -51.8 | CR16: -12.1 | CS16: -14.2 | CT16: -0.4 | CV16: 0.3 | CX16: -3.2 | CY16: 0 | CZ16: 0 | DB16: 0 | DC16: 0 | DD16: -0.7 | DE16: 0 | DG16: 0.1 | DH16: 1.2 | DI16: 0.2 | DJ16: -0.3 | DK16: 0.2 | DL16: 0.3 | DN16: 0 | DO16: 0 | DP16: 0.6 | DQ16: -0.9 | DR16: 0 | DS16: 0 | DT16: -0.3 | DU16: 0.5 | DW16: 0 | DX16: -1.3 | DY16: 0.4 | DZ16: 0.5 | EA16: 0.5 | EB16: -0.1 | ED16: 13.7 | EE16: 0 | EF16: -0.8 | EG16: -1.2 | EH16: 0 | EI16: 0 | EJ16: 0 | EK16: 1.4 | EL16: -0.2 | EM16: 2 | EN16: 0.2 | EO16: 0.2 | EP16: 0.2 | EQ16: 0 | ER16: 0 | ES16: 0 | ET16: 0 | EU16: -0.2 | EV16: -7.3 | EW16: 0 | EX16: 0 | EY16: 1.8 | EZ16: 0.7 | FA16: 0.4 | FB16: 0.5 | FC16: 0 | FD16: 0.2 | FE16: 0 | FF16: 1.9 | FG16: 11.9 | FH16: 0.4 | FK16: 2.3 | FL16: 4.1 | FM16: 11.8 | FN16: -228.15673 | FP16: 2.72097 | FQ16: 0 | FR16: 1.6705 | FS16: 1.1 | FT16: 0.32849 | FU16: 0.26609 | FV16: -1.2 | FW16: 1.8 | FX16: 6.68605
A17: 27/12/2025 | B17: 03:30 | C17: 48.5 | D17: -47.9 | E17: -7.9 | H17: -13.4 | I17: -7.3 | K17: 0 | L17: -31.1 | N17: -19.5 | P17: 20.5 | R17: 19 | S17: 0 | X17: -0.7 | Y17: 1.7 | Z17: 1.4 | AA17: 2.9 | AB17: -3.4 | AC17: 3.6 | AD17: 8.3 | AI17: 21.2 | AJ17: 0 | AN17: -1.2 | AO17: 0 | AP17: 3 | AQ17: 11.9 | AR17: 3.8 | AS17: -1.2 | AT17: 1.8 | AU17: 1.1 | AV17: -5.30863 | AW17: -23.67081 | AX17: -45.20545 | AY17: -2.957 | AZ17: 0 | BA17: -1.984 | BB17: 0.994 | BC17: -0.02 | BD17: -0.751 | BG17: -5.4 | BJ17: 0 | BN17: 3.1 | BO17: -39 | BP17: -55.1 | BQ17: -23.8 | BR17: 5 | BS17: -1.5 | BT17: -1.5 | CB17: 42 | CC17: 32.7 | CD17: -5.7 | CE17: 2.4 | CF17: -2.2 | CG17: -26.3 | CJ17: -10 | CK17: -12.3 | CL17: -33.2 | CM17: -56.1 | CR17: -12.4 | CS17: -14.5 | CT17: -0.3 | CV17: 0.3 | CX17: -2.7 | CY17: 0 | CZ17: 0 | DB17: 0 | DC17: 0.1 | DD17: -0.8 | DE17: 0 | DG17: 0.1 | DH17: 1.2 | DI17: 0.3 | DJ17: -0.1 | DK17: 0.2 | DL17: 0.4 | DN17: 0 | DO17: 0 | DP17: 0.8 | DQ17: -0.1 | DR17: 0 | DS17: 0 | DT17: -0.3 | DU17: 0.5 | DW17: 0 | DX17: -1.3 | DY17: 0.5 | DZ17: 0.6 | EA17: 0.6 | EB17: -0.1 | ED17: 14.2 | EE17: 0 | EF17: -0.4 | EG17: -0.9 | EH17: 0 | EI17: 0 | EJ17: 0 | EK17: 1.4 | EL17: -0.2 | EM17: 1.7 | EN17: 0.2 | EO17: 0.2 | EP17: 0.2 | EQ17: 0 | ER17: 0 | ES17: 0 | ET17: 0 | EU17: -0.2 | EV17: 0 | EW17: 0 | EX17: 0 | EY17: 1.8 | EZ17: 0.7 | FA17: 0.4 | FB17: 0.5 | FC17: 0 | FD17: 0 | FE17: 0 | FF17: 2 | FG17: 11.9 | FH17: 0.5 | FK17: 2.4 | FL17: 4 | FM17: 11.31 | FN17: -225.99289 | FP17: 2.71053 | FQ17: 0 | FR17: 1.8455 | FS17: 1.1 | FT17: 0.33242 | FU17: 0.29341 | FV17: -1.2 | FW17: 1.8 | FX17: 6.88186
A18: 27/12/2025 | B18: 04:00 | C18: 43.3 | D18: -63.4 | E18: -9.9 | H18: -15.3 | I18: -11.5 | K18: 0 | L18: -35.1 | N18: -21.2 | P18: 19.2 | R18: 17.1 | S18: 0 | X18: -4 | Y18: 1.7 | Z18: 1.1 | AA18: 2.9 | AB18: -3.5 | AC18: 3.7 | AD18: 7.6 | AI18: 18.7 | AJ18: 0 | AN18: -1.3 | AO18: 0 | AP18: 2.8 | AQ18: 11.4 | AR18: 4.2 | AS18: -0.8 | AT18: 1.9 | AU18: 1.4 | AV18: -7.2833 | AW18: -26.30739 | AX18: -47.4285 | AY18: -1.9 | AZ18: 0 | BA18: -1.587 | BB18: 0.964 | BC18: 0 | BD18: -0.751 | BG18: -5.8 | BJ18: 0 | BN18: 1 | BO18: -43.9 | BP18: -57.8 | BQ18: -25.8 | BR18: 1 | BS18: -2.6 | BT18: -2 | CB18: 42.9 | CC18: 32.5 | CD18: -6.3 | CE18: 2.5 | CF18: -2.2 | CG18: -27 | CJ18: -11 | CK18: -13.4 | CL18: -35.4 | CM18: -55.8 | CR18: -12.4 | CS18: -14.4 | CT18: -0.3 | CV18: 0.3 | CX18: -3.5 | CY18: 0 | CZ18: 0 | DB18: 0 | DC18: 0 | DD18: -0.7 | DE18: 0 | DG18: 0 | DH18: 1.2 | DI18: 0 | DJ18: -0.1 | DK18: 0.2 | DL18: 0.4 | DN18: 0 | DO18: 0 | DP18: 0.3 | DQ18: -0.9 | DR18: 0 | DS18: 0 | DT18: 0 | DU18: 0.5 | DW18: 0 | DX18: -1.3 | DY18: 0.6 | DZ18: 0.4 | EA18: 1.1 | EB18: -0.1 | ED18: 10.5 | EE18: 0 | EF18: -4 | EG18: -4.7 | EH18: 0 | EI18: 0 | EJ18: 0 | EK18: 1.3 | EL18: -0.2 | EM18: 1.8 | EN18: 0.2 | EO18: 0.2 | EP18: 0.2 | EQ18: 0 | ER18: 0 | ES18: 0 | ET18: 0 | EU18: -0.2 | EV18: 0 | EW18: 0 | EX18: 0 | EY18: 1.8 | EZ18: 0.7 | FA18: 0.4 | FB18: 0.5 | FC18: 0 | FD18: 0.2 | FE18: 0 | FF18: 2 | FG18: 11.6 | FH18: 0.3 | FK18: 2.8 | FL18: 4 | FM18: 10.82 | FN18: -310.87319 | FP18: 2.32174 | FQ18: 0 | FR18: 1.9715 | FS18: 1.1 | FT18: 0.33763 | FU18: 0.29822 | FV18: -1.2 | FW18: 1.8 | FX18: 6.62909
A19: 27/12/2025 | B19: 04:30 | C19: 45.8 | D19: -52.1 | E19: -7.9 | H19: -14.8 | I19: -8.3 | K19: 0 | L19: -31.3 | N19: -15.7 | P19: 21.3 | R19: 16.6 | S19: 0.1 | X19: -2.5 | Y19: 2 | Z19: 1.5 | AA19: 2.9 | AB19: -3.5 | AC19: 3.6 | AD19: 8.5 | AI19: 19.6 | AJ19: 0 | AN19: -1.2 | AO19: 0 | AP19: 2.7 | AQ19: 11.3 | AR19: 4 | AS19: -1.1 | AT19: 1.9 | AU19: 1.9 | AV19: -5.42598 | AW19: -24.18287 | AX19: -45.48819 | AY19: -1.429 | AZ19: 0 | BA19: -1.16 | BB19: 0.959 | BC19: -0.01 | BD19: -2.167 | BG19: -5 | BJ19: 0 | BN19: 2.1 | BO19: -37.9 | BP19: -54 | BQ19: -22 | BR19: 7.6 | BS19: -1.4 | BT19: -1.5 | CB19: 33.1 | CC19: 32.3 | CD19: -6.2 | CE19: 2.4 | CF19: -2.2 | CG19: -27.5 | CJ19: -9.6 | CK19: -12 | CL19: -33.1 | CM19: -51.8 | CR19: -11.5 | CS19: -13.9 | CT19: -0.3 | CV19: 0.3 | CX19: -6.6 | CY19: 0 | CZ19: 0 | DB19: 0 | DC19: 0 | DD19: -0.7 | DE19: 0 | DG19: 0.1 | DH19: 1.2 | DI19: 0.1 | DJ19: -0.6 | DK19: 0.2 | DL19: 0.4 | DN19: 0 | DO19: 0 | DP19: 0.3 | DQ19: -1.4 | DR19: 0 | DS19: 0 | DT19: 0 | DU19: 0.5 | DW19: 0 | DX19: -1.3 | DY19: 0.5 | DZ19: 0.5 | EA19: 1.1 | EB19: 0 | ED19: 1.8 | EE19: 0 | EF19: -1.3 | EG19: -2.1 | EH19: 0 | EI19: 0 | EJ19: 0 | EK19: 1.3 | EL19: -0.2 | EM19: 1.8 | EN19: 0.2 | EO19: 0.2 | EP19: 0.2 | EQ19: 0 | ER19: 0 | ES19: 0 | ET19: 0 | EU19: -0.2 | EV19: 0 | EW19: 0 | EX19: 0 | EY19: 1.8 | EZ19: 0.7 | FA19: 0.4 | FB19: 0.5 | FC19: 0 | FD19: 0.2 | FE19: 0 | FF19: 2.2 | FG19: 11.8 | FH19: 0.3 | FK19: 2.7 | FL19: 3.7 | FM19: 11.52 | FN19: -253.88404 | FP19: 2.45381 | FQ19: 0 | FR19: 2.0585 | FS19: 1.1 | FT19: 0.33764 | FU19: 0.31205 | FV19: -1.2 | FW19: 1.9 | FX19: 6.962
A20: 27/12/2025 | B20: 05:00 | C20: 46.5 | D20: -43.9 | E20: -6.7 | H20: -13.8 | I20: 1.2 | K20: 0 | L20: -29.8 | N20: -14.7 | P20: 21.8 | R20: 25.6 | S20: 0 | X20: -2.5 | Y20: 1.8 | Z20: 1.4 | AA20: 2.9 | AB20: -3.6 | AC20: 3.7 | AD20: 8.6 | AI20: 20.1 | AJ20: 0 | AN20: -1.2 | AO20: 0 | AP20: 2.7 | AQ20: 11.1 | AR20: 4.1 | AS20: -0.9 | AT20: 1.9 | AU20: 0.6 | AV20: -4.72909 | AW20: -23.34766 | AX20: -44.8593 | AY20: -0.724 | AZ20: 0 | BA20: -0.214 | BB20: 0.953 | BC20: -0.06 | BD20: -0.876 | BG20: -4.3 | BJ20: 0 | BN20: 3.2 | BO20: -37.8 | BP20: -54.4 | BQ20: -22.8 | BR20: 6.9 | BS20: -1.1 | BT20: -1.4 | CB20: 31.8 | CC20: 32.4 | CD20: -6.8 | CE20: 4.6 | CF20: -2.2 | CG20: -27.1 | CJ20: -8.4 | CK20: -11 | CL20: -31.8 | CM20: -51.4 | CR20: -11.7 | CS20: -14.1 | CT20: -0.3 | CV20: 0.3 | CX20: -7.4 | CY20: 0 | CZ20: -2.1 | DB20: 0 | DC20: 0 | DD20: -0.6 | DE20: -0.2 | DG20: 0.1 | DH20: 1.2 | DI20: 0.2 | DJ20: -0.8 | DK20: 0.2 | DL20: 0.4 | DN20: 0 | DO20: 0 | DP20: -0.2 | DQ20: -2.7 | DR20: 0.4 | DS20: 0.2 | DT20: 0 | DU20: 0.5 | DW20: 0 | DX20: -1.3 | DY20: 0.5 | DZ20: 0.5 | EA20: 1.1 | EB20: -0.1 | ED20: 1.5 | EE20: 0 | EF20: 0.2 | EG20: -1 | EH20: 0 | EI20: 0 | EJ20: 0 | EK20: 1.3 | EL20: -0.2 | EM20: 1.7 | EN20: 0.2 | EO20: 0.2 | EP20: 0.2 | EQ20: -2.6 | ER20: 0 | ES20: 0 | ET20: 0 | EU20: -0.2 | EV20: 0 | EW20: 0 | EX20: 0 | EY20: 1.8 | EZ20: 0.7 | FA20: 0.4 | FB20: 0.5 | FC20: 0 | FD20: 0.2 | FE20: 0 | FF20: 2.1 | FG20: 11.9 | FH20: 0.6 | FK20: 2.1 | FL20: 3.8 | FM20: 11.44 | FN20: -217.61705 | FP20: 2.27464 | FQ20: 0 | FR20: 2.1045 | FS20: 1.1 | FT20: 0.33609 | FU20: 0.32057 | FV20: -1.2 | FW20: 1.8 | FX20: 6.7358
A21: 27/12/2025 | B21: 05:30 | C21: 45.5 | D21: -55.8 | E21: -8.6 | H21: -16.2 | I21: -11.5 | K21: 0 | L21: -30.8 | N21: -18 | P21: 21.5 | R21: 6.8 | S21: 0 | X21: -4.7 | Y21: 1.8 | Z21: 1.3 | AA21: 3 | AB21: -3.5 | AC21: 3.6 | AD21: 7.8 | AI21: 19.8 | AJ21: 0 | AN21: -1.2 | AO21: 0 | AP21: 3.1 | AQ21: 10.5 | AR21: 4 | AS21: -1.3 | AT21: 1.9 | AU21: 1.8 | AV21: -4.93752 | AW21: -23.6482 | AX21: -45.00621 | AY21: -2.146 | AZ21: 0 | BA21: -1.068 | BB21: 0.943 | BC21: 0.01 | BD21: -2.027 | BG21: -4.3 | BJ21: 0 | BN21: 2.1 | BO21: -37.9 | BP21: -54 | BQ21: -22.1 | BR21: 7.5 | BS21: -1.4 | BT21: -1.5 | CB21: 31.7 | CC21: 31.8 | CD21: -6.3 | CE21: 2.5 | CF21: -2.2 | CG21: -26.3 | CJ21: -8.5 | CK21: -10.9 | CL21: -31.4 | CM21: -52.1 | CR21: -11.3 | CS21: -13.8 | CT21: -0.3 | CV21: 0.3 | CX21: -9 | CY21: 0 | CZ21: 0 | DB21: 0 | DC21: 0 | DD21: -0.8 | DE21: 0.1 | DG21: 0.1 | DH21: 1.2 | DI21: 0 | DJ21: -0.8 | DK21: 0.7 | DL21: 0.4 | DN21: 0 | DO21: 0 | DP21: -1 | DQ21: -3.5 | DR21: 0.3 | DS21: 0 | DT21: 0 | DU21: 0.5 | DW21: 0 | DX21: -1.3 | DY21: 0.8 | DZ21: 0.4 | EA21: 0.1 | EB21: 0 | ED21: 1.5 | EE21: 0.3 | EF21: -2.1 | EG21: -2 | EH21: 0 | EI21: 0 | EJ21: 0 | EK21: 1.3 | EL21: -0.2 | EM21: 1.8 | EN21: 0.2 | EO21: 0.2 | EP21: 0.2 | EQ21: -0.8 | ER21: 1 | ES21: 0 | ET21: 2.1 | EU21: -0.2 | EV21: 0 | EW21: 0 | EX21: 0 | EY21: 1.8 | EZ21: 0.7 | FA21: 0.4 | FB21: 0.5 | FC21: 0 | FD21: 0.2 | FE21: 0 | FF21: 2.4 | FG21: 12.1 | FH21: 0.4 | FK21: 2.9 | FL21: 3.8 | FM21: 11.98 | FN21: -276.79993 | FP21: 2.37921 | FQ21: 0 | FR21: 1.943 | FS21: 1 | FT21: 0.33842 | FU21: 0.33039 | FV21: -1.2 | FW21: 1.8 | FX21: 6.59102
A22: 27/12/2025 | B22: 06:00 | C22: 45.1 | D22: -68.1 | E22: -10.7 | H22: -15.7 | I22: -2.2 | K22: 0 | L22: -33.4 | N22: -20.8 | P22: 18.7 | R22: 5 | S22: -0.1 | X22: -4.8 | Y22: 1.5 | Z22: 1.2 | AA22: 2.9 | AB22: -3.5 | AC22: 3.4 | AD22: 6.4 | AI22: 19.6 | AJ22: 0 | AN22: -1.2 | AO22: 0 | AP22: 2.8 | AQ22: 7 | AR22: 0.3 | AS22: -1.3 | AT22: 1.9 | AU22: 2.6 | AV22: -7.79774 | AW22: -26.52167 | AX22: -48.01826 | AY22: -1.838 | AZ22: 0 | BA22: -0.946 | BB22: 0.948 | BC22: 0.04 | BD22: -4.29 | BG22: -5.4 | BJ22: 0 | BN22: 0.4 | BO22: -43 | BP22: -58.3 | BQ22: -26.9 | BR22: 1.5 | BS22: -2.9 | BT22: -2 | CB22: 33.2 | CC22: 31.9 | CD22: -6.6 | CE22: 2.5 | CF22: -2.2 | CG22: -28.6 | CJ22: -11.3 | CK22: -13.8 | CL22: -35.8 | CM22: -56.1 | CR22: -14.6 | CS22: -15.8 | CT22: -0.3 | CV22: 0.3 | CX22: -10.6 | CY22: 0.6 | CZ22: 0 | DB22: 0 | DC22: 0 | DD22: -0.7 | DE22: 0.3 | DG22: 0.1 | DH22: 1.2 | DI22: 0.2 | DJ22: -0.8 | DK22: 0.2 | DL22: 0.4 | DN22: -0.1 | DO22: 0 | DP22: -1.7 | DQ22: -5.6 | DR22: 0.1 | DS22: 0.1 | DT22: -0.1 | DU22: 0.5 | DW22: 0.007 | DX22: -1.3 | DY22: 0.6 | DZ22: 0.5 | EA22: -0.1 | EB22: -0.1 | ED22: 1.5 | EE22: 0.1 | EF22: -3.2 | EG22: -3.3 | EH22: 0 | EI22: 0 | EJ22: 1.08 | EK22: 1.4 | EL22: -0.2 | EM22: 1.8 | EN22: 0.2 | EO22: 0.2 | EP22: 0.2 | EQ22: 0 | ER22: 1 | ES22: 0 | ET22: 2.2 | EU22: -0.2 | EV22: -9.5 | EW22: 0 | EX22: 1.4 | EY22: 1.8 | EZ22: 0.7 | FA22: 0.4 | FB22: 0.5 | FC22: 0 | FD22: 0.2 | FE22: -0.1 | FF22: 2.3 | FG22: 12.3 | FH22: 0.6 | FK22: 2.5 | FL22: 3.9 | FM22: 11.83 | FN22: -370.30667 | FP22: 2.07431 | FQ22: 0 | FR22: 2.151 | FS22: 1.2 | FT22: 0.34017 | FU22: 0.32821 | FV22: -1 | FW22: 1.8 | FX22: 6.89369
... A58: 28/12/2025 | B58: 00:00 | C58: 40.6 | D58: -72.7 | E58: -13.8 | H58: -15.4 | I58: 5.2 | K58: 0 | L58: -38.5 | N58: -6.9 | P58: 15.4 | R58: 12.6 | S58: -0.1 | X58: -4.7 | Y58: 0.8 | Z58: 0.8 | AA58: 2.7 | AB58: -3.4 | AC58: 2.3 | AD58: 2.8 | AI58: 18.9 | AJ58: -3.1 | AN58: -1.4 | AO58: -28.1 | AP58: 2.5 | AQ58: 12.9 | AR58: -1 | AS58: 0.9 | AT58: 2.4 | AU58: 1.5 | AV58: -5.98537 | AW58: -24.4856 | AX58: -46.09572 | AY58: -1.31 | AZ58: 0.45 | BA58: -1.28 | BB58: 1 | BC58: 0.06 | BD58: -5.14 | BG58: -4.7 | BJ58: -6.5 | BN58: 0.9 | BO58: -8.3 | BP58: -23.3 | BQ58: -19.6 | BR58: 4.7 | BS58: -4.4 | BT58: -2.8 | CB58: 28.3 | CC58: 12.9 | CD58: 3.1 | CE58: 2.4 | CF58: 0.1 | CG58: -31.1 | CJ58: 39.6 | CK58: 36.7 | CL58: -34.8 | CM58: -44.5 | CR58: -13.7 | CS58: -15.3 | CT58: -0.5 | CV58: 0.3 | CX58: -12 | CY58: 0 | CZ58: 0 | DB58: 0 | DC58: -0.1 | DD58: -0.8 | DE58: 0 | DG58: 0.1 | DH58: 1.3 | DI58: 0.2 | DJ58: 0.6 | DK58: 0.1 | DL58: 0.3 | DN58: 0 | DO58: 0 | DP58: -3.5 | DQ58: -7.5 | DR58: 0 | DS58: 0 | DT58: -0.2 | DU58: 0.5 | DW58: 0 | DX58: -1.4 | DY58: 0.2 | DZ58: 0.2 | EA58: 0.6 | EB58: -0.1 | ED58: 1.5 | EE58: 0 | EF58: -7.1 | EG58: 0 | EH58: -0.8 | EI58: -0.5 | EJ58: 0 | EK58: 1.4 | EL58: -0.2 | EM58: 1.6 | EN58: 0.2 | EO58: 0.2 | EP58: 0.2 | EQ58: 0 | ER58: 0 | ES58: 0 | ET58: 0 | EU58: -0.2 | EV58: -9.7 | EW58: 0 | EX58: 0 | EY58: 1.8 | EZ58: 0.7 | FA58: 0.4 | FB58: 0.5 | FC58: 0 | FD58: 0.2 | FE58: 0 | FF58: 2.4 | FG58: 7.9 | FH58: 0.6 | FK58: 2.6 | FL58: 4 | FM58: 12.32 | FN58: -231.56669 | FP58: 2.74353 | FQ58: 0 | FR58: 2.0035 | FS58: 1 | FT58: 0.31243 | FU58: 0.30279 | FV58: -0.4 | FW58: 1.6 | FX58: 7.56225
A59: EJEC | C59: 1032.4 | D59: -1126.9 | E59: -151.35 | F59: 0 | G59: 0 | H59: -223.8 | I59: 6.25 | J59: 0 | K59: 12.15 | L59: -750.7 | M59: 0 | N59: -222.5 | O59: 0 | P59: 431.75 | Q59: 0 | R59: 306.55 | S59: 0.85 | T59: 0 | U59: 0 | V59: 0 | W59: 0 | X59: -77.55 | Y59: 24.4 | Z59: 20.45 | AA59: 67.15 | AB59: -82.5 | AC59: 84.1 | AD59: 222.85 | AE59: 0 | AF59: 0 | AG59: 0 | AH59: 0 | AI59: 481.3 | AJ59: -49.5 | AK59: 0 | AL59: 0 | AM59: 0 | AN59: -29.6 | AO59: -102.65 | AP59: 71.5 | AQ59: 260.8 | AR59: 64.2 | AS59: -14.4 | AT59: 46.65 | AU59: 33.45 | AV59: -2.3968 | AW59: -454.10638 | AX59: -1075.4576 | AY59: 10.411 | AZ59: 12.282 | BA59: 10.8435 | BB59: 23.0805 | BC59: 1.64 | BD59: -12.4185 | BE59: 0 | BF59: 0 | BG59: -35.25 | BH59: 0 | BI59: 0 | BJ59: -63.1 | BK59: 0 | BL59: 0 | BM59: 0 | BN59: 64.35 | BO59: 20.9 | BP59: -439.35 | BQ59: -214.7 | BR59: 481.9 | BS59: -76.6 | BT59: -54.6 | BU59: 0 | BV59: 0 | BW59: 0 | BX59: 0 | BY59: 0 | BZ59: 0 | CA59: 0 | CB59: 906.6 | CC59: 656.6 | CD59: 21.7 | CE59: 72.95 | CF59: 67.95 | CG59: -473.65 | CH59: 0 | CI59: 0 | CJ59: 686.9 | CK59: 707.2 | CL59: -491.15 | CM59: -905.6 | CN59: 0 | CO59: 0 | CP59: 0 | CQ59: 0 | CR59: -158.75 | CS59: -261.5 | CT59: -15.65 | CU59: 0 | CV59: 7.2 | CW59: 0 | CX59: -234.85 | CY59: 80.2 | CZ59: -46.95 | DA59: 0 | DB59: 0.5 | DC59: -0.15 | DD59: -19.05 | DE59: 277.6 | DF59: 0 | DG59: 2.2 | DH59: 28.4 | DI59: 3.95 | DJ59: 15.75 | DK59: 4.8 | DL59: 9.45 | DM59: 0 | DN59: -6.45 | DO59: -15.9 | DP59: -38.85 | DQ59: -154.5 | DR59: -26.3 | DS59: 1.4 | DT59: 6.5 | DU59: 12 | DV59: 0 | DW59: 0.083 | DX59: -31.45 | DY59: 12.15 | DZ59: 9.7 | EA59: 1.5 | EB59: 6.45 | EC59: 0 | ED59: 125.85 | EE59: 22.8 | EF59: -90.65 | EG59: -110.85 | EH59: -5.35 | EI59: 0.4 | EJ59: -15.075 | EK59: 32.95 | EL59: -4.8 | EM59: 44.15 | EN59: 4.8 | EO59: 4.8 | EP59: 4.8 | EQ59: -56.6 | ER59: 60.6 | ES59: 17.05 | ET59: -22.9 | EU59: -4.8 | EV59: -91.6 | EW59: 0.5 | EX59: 95.85 | EY59: 42.2 | EZ59: 15.5 | FA59: 9.6 | FB59: 12 | FC59: 11.8 | FD59: 9 | FE59: 3.85 | FF59: 54.25 | FG59: 266.55 | FH59: 6.95 | FI59: 0 | FJ59: 0 | FK59: 71 | FL59: 92.4 | FM59: 295.47 | FN59: 154.25568 | FP59: 63.810055 | FQ59: -6.238 | FR59: 55.20075 | FS59: 25.4 | FT59: 7.43498 | FU59: 9.098195 | FV59: -7.65 | FW59: 58.3 | FX59: 205.35598

Sheet DEMANDA_AREAS
B3: sábado, 27 de Diciembre del 2025
B5: REPORTE DE LA DEMANDA POR ÁREAS Y SUBAREAS OPERATIVAS (MW)
B6: FECHA HORA | C6: DEMANDA | E6: AREA | H6: SUBAREAS
C7: INTERCAMBIOS INTERNACIONALES | D7: SEIN | E7: NORTE | F7: CENTRO | G7: SUR | H7: ELECTROANDES
B8: 00:30 | C8: 0 | D8: 6742.3644 | E8: 1039.8985 | F8: 3914.0074 | G8: 1788.4585 | H8: 265.6107
B9: 01:00 | C9: 0 | D9: 6580.5114 | E9: 957.6802 | F9: 3857.9938 | G9: 1764.8374 | H9: 260.231
B10: 01:30 | C10: 0 | D10: 6553.3288 | E10: 947.1322 | F10: 3832.2548 | G10: 1773.9418 | H10: 265.1431
B11: 02:00 | C11: 0 | D11: 6485.6934 | E11: 938.6591 | F11: 3818.5837 | G11: 1728.4506 | H11: 264.3684
B12: 02:30 | C12: 0 | D12: 6356.2575 | E12: 973.9498 | F12: 3645.2419 | G12: 1737.0658 | H12: 262.465
B13: 03:00 | C13: 0 | D13: 6386.784 | E13: 940.5526 | F13: 3724.486 | G13: 1721.7454 | H13: 261.3249
B14: 03:30 | C14: 0 | D14: 6344.1757 | E14: 954.7176 | F14: 3630.1021 | G14: 1759.356 | H14: 266.3293
B15: 04:00 | C15: 0 | D15: 6208.9883 | E15: 944.4483 | F15: 3517.8403 | G15: 1746.6997 | H15: 260.4014
B16: 04:30 | C16: 0 | D16: 6373.2173 | E16: 920.7327 | F16: 3691.4131 | G16: 1761.0715 | H16: 263.732
B17: 05:00 | C17: 0 | D17: 6409.1754 | E17: 968.8056 | F17: 3672.3784 | G17: 1767.9914 | H17: 259.1533
B18: 05:30 | C18: 0 | D18: 6387.3966 | E18: 962.4239 | F18: 3636.5741 | G18: 1788.3986 | H18: 258.0346
B19: 06:00 | C19: 0 | D19: 6284.7622 | E19: 990.4087 | F19: 3549.8627 | G19: 1744.4908 | H19: 247.1672
... B59: ENERGÍA | C59: 0 | D59: 170753.72 | E59: 26375.417 | F59: 100344.29 | G59: 44034.02 | H59: 6241.4624
B61: LEYENDA:
D63: Potencia recibida del Ecuador
D64: Potencia entregada al Ecuador

Sheet DEMANDA_UL
B3: sábado, 27 de Diciembre del 2025
B5: POTENCIA DE LOS GRANDES USUARIOS LIBRES (MW)
B6: FECHA HORA | C6: GRANDES USUARIOS LIBRES DEL ÁREA NORTE | X6: GRANDES USUARIOS LIBRES DEL ÁREA CENTRO | BP6: GRANDES USUARIOS LIBRES DEL ÁREA SUR
C7: ARCA CONTINENTAL LINDLEY S.A. | D7: AUSTRAL GROUP S.A.A | E7: CEMENTOS PACASMAYO | F7: CONSORCIO MINERO HORIZONTE S.R.L. | G7: CORPORACIÓN PESQUERA INCA S.A.C. | H7: CREDITEX: CIA IND.TEXTIL CREDISA | I7: HIPERMERCADOS TOTTUS S.A | J7: INDUSTRIA TEXTIL PIURA | K7: MINERA BOROO MISQUICHILCA S.A. | L7: MINERA GOLD FIELDS | M7: MINERA MARSA | N7: MINERA MISKY MAYO | O7: MINERA YANACOCHA | P7: OPEN PLAZA | Q7: PESQUERA DIAMANTE | R7: PETROPERU | S7: REAL PLAZA S.R.L. | T7: SIDER PERU | U7: SUPERMERCADOS PERUANOS S.A. | V7: TRUPAL S.A. | W7: UNIÓN DE CERVECERÍAS PERUANAS BACKUS Y JOHNSTON S. | X7: ACEROS AREQUIPA | Y7: ADMINISTRADORA JOCKEY PLAZA SHOPPING CENTER S.A. | Z7: ALICORP | AA7: ARCA CONTINENTAL LINDLEY S.A. | AB7: AUSTRAL GROUP S.A.A | AC7: COMPAÑIA MINERA CONDESTABLE | AD7: CORPORACIÓN PESQUERA INCA S.A.C. | AE7: CREDITEX: CIA IND.TEXTIL CREDISA | AF7: FUNDICION CHILCA S.A. | AG7: HIPERMERCADOS TOTTUS S.A | AH7: INMOBILIARIA KANPU S.A. | AI7: INMUEBLES PANAMERICANA S.A. | AJ7: KIMBERLY-CLARK PERU | AK7: LECHE GLORIA S.A. | AL7: MALL AVENTURA S.A. | AM7: MARCOBRE S.A.C. | AN7: MINERA ANTAMINA | AO7: MINERA ARES | AP7: MINERA BUENAVENTURA | AQ7: MINERA CHINALCO PERÚ S.A. | AR7: MINERA SHOUXIN PERU S.A. | AS7: MINERA VOLCAN | AT7: MINSUR | AU7: MOLYCOP-ADESUR | AV7: NEXA RESOURCES CAJAMARQUILLA S.A. | AW7: NEXA RESOURCES PERÚ S.A.A. | AX7: OPEN PLAZA | AY7: OPP FILM | AZ7: OWENS-ILLINOIS PERÚ S.A. | BA7: PAPELERA NACIONAL S.A. | BB7: PESQUERA DIAMANTE | BC7: QUIMPAC S.A. | BD7: REAL PLAZA S.R.L. | BE7: REFINERIA LA PAMPILLA S.A.A | BF7: SAGA FALABELLA | BG7: SAN MIGUEL INDUSTRIAS PET S.A. | BH7: SHOUGANG HIERRO PERU | BI7: SOFTYS PERU S.A.C. | BJ7: SUPERMERCADOS PERUANOS S.A. | BK7: TEJIDOS SAN JACINTO | BL7: TREN URBANO DE LIMA S.A. | BM7: TRUPAL S.A. | BN7: UNACEM PERU S.A. | BO7: UNIÓN DE CERVECERÍAS PERUANAS BACKUS Y JOHNSTON S. | BP7: ANGLO AMERICAN QUELLAVECO S.A. | BQ7: ARCA CONTINENTAL LINDLEY S.A. | BR7: CAL & CEMENTO SUR S.A. | BS7: COMPAÑIA MINERA ANTAPACCAY S.A. | BT7: COMPAÑÍA MINERA CHUNGAR SAC | BU7: COMPAÑIA MINERA SAN IGNACIO DE MOROCOCHA S.A.A. | BV7: EL BROCAL .S.A. | BW7: EMPRESA ADMINISTRADORA CERRO S.A.C. | BX7: EMPRESA MINERA LOS QUENUALES S.A.C. | BY7: HIPERMERCADOS TOTTUS S.A | BZ7: HUDBAY PERU S.A.C. | CA7: INDUSTRIA CACHIMAYO | CB7: MALL AVENTURA S.A. | CC7: MINERA ARES | CD7: MINERA BUENAVENTURA | CE7: MINERA CERRO VERDE | CF7: MINERA CORONA | CG7: MINERA LAS BAMBAS S.A. | CH7: MINERA VOLCAN | CI7: MINSUR | CJ7: MOLYCOP-ADESUR | CK7: NEXA RESOURCES PERÚ S.A.A. | CL7: OXIDOS DE PASCO S.A.C. | CM7: PESQUERA DIAMANTE | CN7: REAL PLAZA S.R.L. | CO7: SOBREANDES S.A.C. | CP7: SOUTHERN PERU CC | CQ7: SUPERMERCADOS PERUANOS S.A. | CR7: UNACEM PERU S.A. | CS7: UNIÓN DE CERVECERÍAS PERUANAS BACKUS Y JOHNSTON S. | CT7: YURA
B8: 00:30 | E8: 31.2798 | F8: 12.734 | L8: 26.8718 | M8: 13.95507 | N8: 13.76 | O8: 32.422 | R8: 51.122 | T8: 46.0708 | V8: 0.4 | X8: 140.21016 | AC8: 16.39 | AJ8: 5.33786 | AK8: 13.056 | AL8: 1.0595 | AM8: 50.1107 | AN8: 118.75653 | AO8: 25.9165 | AP8: 0.81 | AQ8: 165.57 | AR8: 23.9132 | AS8: 35.62988 | AT8: 32.3 | AV8: 196.6111 | AW8: 35.82764 | AY8: 0.25143 | BA8: 1.4 | BC8: 70.9515 | BI8: 18.42797 | BN8: 28.8 | BO8: 2.04 | BP8: 146.07807 | BR8: 3.75991 | BS8: 129.0676 | BT8: 12.66436 | BV8: 37.2195 | BW8: 3.85819 | CA8: 24.88066 | CB8: 0.4532 | CC8: 0.59 | CD8: 24.2351 | CE8: 415.79112 | CG8: 153.5924 | CH8: 16.51371 | CK8: 16.9349 | CL8: 4.95588 | CO8: 16.59341 | CP8: 289.92 | CR8: 40.093 | CT8: 24.217
B9: 01:00 | E9: 31.3686 | F9: 12.486 | L9: 27.0083 | M9: 14.05135 | N9: 13.79 | O9: 32.63 | R9: 51.036 | T9: 43.2035 | V9: 0.4 | X9: 174.21219 | AC9: 16.13 | AJ9: 5.33431 | AK9: 13.126 | AL9: 0.9095 | AM9: 51.7623 | AN9: 119.00424 | AO9: 25.9224 | AP9: 0.7 | AQ9: 163.34 | AR9: 23.81789 | AS9: 34.44229 | AT9: 34.36 | AV9: 198.5312 | AW9: 34.59975 | AY9: 0.19997 | BA9: 1.3 | BC9: 70.56888 | BI9: 18.13313 | BN9: 29.59 | BO9: 2.08 | BP9: 146.87915 | BR9: 3.7234 | BS9: 126.9559 | BT9: 13.94348 | BV9: 37.1216 | BW9: 3.96348 | CA9: 24.58312 | CB9: 0.4274 | CC9: 0.61 | CD9: 23.99895 | CE9: 399.93084 | CG9: 157.8943 | CH9: 16.36508 | CK9: 17.1483 | CL9: 4.93331 | CO9: 16.04228 | CP9: 291.81 | CR9: 38.346 | CT9: 24.149
B10: 01:30 | E10: 31.3377 | F10: 11.522 | L10: 27.0431 | M10: 14.04383 | N10: 13.86 | O10: 31.874 | R10: 50.866 | T10: 41.1668 | V10: 0.4 | X10: 150.17303 | AC10: 15.91 | AJ10: 5.31128 | AK10: 13.324 | AL10: 0.8646 | AM10: 51.5135 | AN10: 118.06423 | AO10: 26.3953 | AP10: 0.64 | AQ10: 161.84 | AR10: 23.69642 | AS10: 35.53865 | AT10: 35.1 | AV10: 198.1982 | AW10: 34.94661 | AY10: 0.18529 | BA10: 1.4 | BC10: 70.63341 | BI10: 17.54769 | BN10: 28.79 | BO10: 2.13 | BP10: 144.50938 | BR10: 3.81433 | BS10: 127.2843 | BT10: 14.35917 | BV10: 36.9058 | BW10: 4.0073 | CA10: 24.61696 | CB10: 0.4125 | CC10: 0.63 | CD10: 25.33293 | CE10: 410.63863 | CG10: 157.5149 | CH10: 16.78346 | CK10: 17.1377 | CL10: 4.93976 | CO10: 15.66076 | CP10: 290.37 | CR10: 38.335 | CT10: 24.069
B11: 02:00 | E11: 31.57 | F11: 12.079 | L11: 26.7817 | M11: 13.54398 | N11: 13.86 | O11: 30.774 | R11: 50.839 | T11: 38.7419 | V11: 0.4 | X11: 151.00869 | AC11: 15.31 | AJ11: 5.27359 | AK11: 13.204 | AL11: 0.8548 | AM11: 51.3351 | AN11: 119.19799 | AO11: 26.4936 | AP11: 0.44 | AQ11: 162.07 | AR11: 23.67797 | AS11: 36.02678 | AT11: 35.19 | AV11: 197.8851 | AW11: 35.8586 | AY11: 0.19696 | BA11: 1.3 | BC11: 71.00504 | BI11: 17.89475 | BN11: 29.57 | BO11: 2.06 | BP11: 143.52793 | BR11: 3.83235 | BS11: 125.7732 | BT11: 14.48368 | BV11: 36.9659 | BW11: 3.7307 | CA11: 24.80886 | CB11: 0.4037 | CC11: 0.6 | CD11: 25.10848 | CE11: 408.22169 | CG11: 160.5889 | CH11: 17.10247 | CK11: 17.1838 | CL11: 4.80371 | CO11: 16.0295 | CP11: 281.26 | CR11: 38.112 | CT11: 23.977
B12: 02:30 | E12: 31.8504 | F12: 11.27 | L12: 26.6607 | M12: 13.59307 | N12: 13.98 | O12: 30.254 | R12: 50.729 | T12: 48.4462 | V12: 0.4 | X12: 131.80008 | AC12: 14.14 | AJ12: 5.22184 | AK12: 13.414 | AL12: 0.8264 | AM12: 51.2692 | AN12: 119.49766 | AO12: 27.038 | AP12: 0.41 | AQ12: 162.62 | AR12: 23.58146 | AS12: 36.06511 | AT12: 34.23 | AV12: 197.3332 | AW12: 36.44443 | AY12: 0.21228 | BA12: 1.3 | BC12: 70.95008 | BI12: 18.01338 | BN12: 29.6 | BO12: 2.32 | BP12: 143.41707 | BR12: 3.90946 | BS12: 125.7976 | BT12: 14.80673 | BV12: 35.4175 | BW12: 3.87202 | CA12: 24.70172 | CB12: 0.4029 | CC12: 0.6 | CD12: 24.63455 | CE12: 406.55616 | CG12: 160.3498 | CH12: 17.67086 | CK12: 17.0603 | CL12: 4.67396 | CO12: 15.47454 | CP12: 278.63 | CR12: 37.935 | CT12: 23.939
B13: 03:00 | E13: 21.1329 | F13: 12.07 | L13: 26.8109 | M13: 13.52572 | N13: 13.68 | O13: 30.072 | R13: 50.906 | T13: 48.7391 | V13: 0.4 | X13: 111.42844 | AC13: 14.61 | AJ13: 4.81592 | AK13: 13.413 | AL13: 0.8523 | AM13: 48.64 | AN13: 121.10141 | AO13: 27.0215 | AP13: 0.67 | AQ13: 162.87 | AR13: 23.55127 | AS13: 35.4822 | AT13: 34.69 | AV13: 197.5856 | AW13: 35.70866 | AY13: 0.22435 | BA13: 1.3 | BC13: 71.0924 | BI13: 17.98736 | BN13: 29.51 | BO13: 2.31 | BP13: 143.01106 | BR13: 3.84034 | BS13: 124.1703 | BT13: 14.67946 | BV13: 35.1547 | BW13: 3.96593 | CA13: 24.59404 | CB13: 0.3962 | CC13: 0.63 | CD13: 25.1482 | CE13: 406.37721 | CG13: 154.8887 | CH13: 17.49904 | CK13: 17.3501 | CL13: 4.69993 | CO13: 16.11029 | CP13: 286.3 | CR13: 40.763 | CT13: 23.988
B14: 03:30 | E14: 20.573 | F14: 12.06 | L14: 26.9371 | M14: 13.33169 | N14: 13.34 | O14: 29.89 | R14: 51.392 | T14: 41.3679 | V14: 0.4 | X14: 115.57739 | AC14: 14.62 | AJ14: 5.05719 | AK14: 13.048 | AL14: 0.8378 | AM14: 49.1638 | AN14: 121.51696 | AO14: 26.5646 | AP14: 0.48 | AQ14: 162.1 | AR14: 23.7763 | AS14: 35.94914 | AT14: 34.74 | AV14: 183.9014 | AW14: 36.49225 | AY14: 0.28642 | BA14: 1.2 | BC14: 71.1209 | BI14: 17.93318 | BN14: 29.36 | BO14: 2.29 | BP14: 145.20491 | BR14: 3.85736 | BS14: 125.5894 | BT14: 14.57646 | BV14: 37.2407 | BW14: 4.02736 | CA14: 24.60997 | CB14: 0.3865 | CC14: 0.62 | CD14: 24.96091 | CE14: 410.68556 | CG14: 163.3937 | CH14: 17.59228 | CK14: 17.1659 | CL14: 4.69411 | CO14: 16.66932 | CP14: 281.18 | CR14: 40.189 | CT14: 25.554
B15: 04:00 | E15: 19.9463 | F15: 12.395 | L15: 26.6575 | M15: 13.75107 | N15: 13.33 | O15: 30.11 | R15: 51.477 | T15: 45.3748 | V15: 0.4 | X15: 152.13264 | AC15: 13.83 | AJ15: 5.19055 | AK15: 13.227 | AL15: 0.8245 | AM15: 50.9146 | AN15: 121.5712 | AO15: 26.2477 | AP15: 0.18 | AQ15: 161.29 | AR15: 23.84924 | AS15: 35.01114 | AT15: 32.96 | AV15: 175.0853 | AW15: 36.18663 | AY15: 0.32925 | BA15: 1.2 | BC15: 71.07788 | BI15: 17.98312 | BN15: 38.02 | BO15: 2.25 | BP15: 141.49857 | BR15: 3.74125 | BS15: 127.1738 | BT15: 14.86995 | BV15: 37.7072 | BW15: 3.88656 | CA15: 24.66805 | CB15: 0.3725 | CC15: 0.63 | CD15: 25.08633 | CE15: 401.37615 | CG15: 155.7319 | CH15: 17.56158 | CK15: 17.3141 | CL15: 4.73934 | CO15: 16.2081 | CP15: 282.05 | CR15: 38.566 | CT15: 29.413
B16: 04:30 | E16: 19.4842 | F16: 12.252 | L16: 26.9946 | M16: 14.62539 | N16: 12.97 | O16: 29.758 | R16: 51.425 | T16: 40.0723 | V16: 0.4 | X16: 156.55709 | AC16: 14.32 | AJ16: 5.28152 | AK16: 13.387 | AL16: 0.8116 | AM16: 50.5203 | AN16: 121.99447 | AO16: 26.701 | AP16: 1.65 | AQ16: 160.01 | AR16: 23.85134 | AS16: 35.72911 | AT16: 33.61 | AV16: 176.7429 | AW16: 35.22355 | AY16: 0.36055 | BA16: 1.34 | BC16: 70.96061 | BI16: 17.59712 | BN16: 38.63 | BO16: 1.89 | BP16: 140.98003 | BR16: 3.67217 | BS16: 128.6443 | BT16: 14.26868 | BV16: 37.3455 | BW16: 3.90366 | CA16: 24.70186 | CB16: 0.3715 | CC16: 0.59 | CD16: 24.83762 | CE16: 399.61429 | CG16: 155.8163 | CH16: 17.72615 | CK16: 17.1046 | CL16: 4.74371 | CO16: 16.22338 | CP16: 288.8 | CR16: 38.8 | CT16: 30.095
B17: 05:00 | E17: 20.3809 | F17: 11.93 | L17: 27.1957 | M17: 14.78114 | N17: 13.07 | O17: 28.678 | R17: 51.508 | T17: 52.4093 | V17: 0.4 | X17: 152.50953 | AC17: 14.52 | AJ17: 5.03627 | AK17: 13.373 | AL17: 0.797 | AM17: 50.8103 | AN17: 124.60434 | AO17: 26.2827 | AP17: 2.1 | AQ17: 160.02 | AR17: 23.78404 | AS17: 34.73049 | AT17: 33.02 | AV17: 176.7972 | AW17: 35.06467 | AY17: 0.31829 | BA17: 1.4 | BC17: 70.82293 | BI17: 18.25562 | BN17: 39.85 | BO17: 2.27 | BP17: 143.27195 | BR17: 3.67593 | BS17: 131.3815 | BT17: 14.02997 | BV17: 37.583 | BW17: 4.37541 | CA17: 24.23093 | CB17: 0.3715 | CC17: 0.59 | CD17: 24.68326 | CE17: 402.20952 | CG17: 159.0919 | CH17: 17.84003 | CK17: 16.5552 | CL17: 4.66538 | CO17: 15.31166 | CP17: 288.39 | CR17: 38.975 | CT17: 29.919
B18: 05:30 | E18: 19.5476 | F18: 10.713 | L18: 27.6468 | M18: 15.60509 | N18: 12.99 | O18: 30.26 | R18: 51.794 | T18: 38.6776 | V18: 0.4 | X18: 143.154 | AC18: 14.27 | AJ18: 5.08865 | AK18: 13.442 | AL18: 0.8032 | AM18: 49.6706 | AN18: 120.75271 | AO18: 25.8443 | AP18: 1.93 | AQ18: 159.38 | AR18: 23.72193 | AS18: 33.02949 | AT18: 33.5 | AV18: 180.6886 | AW18: 34.94665 | AY18: 0.28986 | BA18: 1.3 | BC18: 70.79603 | BI18: 17.72704 | BN18: 39.88 | BO18: 2.21 | BP18: 144.54804 | BR18: 3.69022 | BS18: 131.2639 | BT18: 13.5401 | BV18: 36.3827 | BW18: 3.85894 | CA18: 24.55401 | CB18: 0.355 | CC18: 0.55 | CD18: 24.23293 | CE18: 403.54914 | CG18: 155.853 | CH18: 17.63811 | CK18: 16.5691 | CL18: 4.66373 | CO18: 13.98756 | CP18: 287.26 | CR18: 37.383 | CT18: 30.109
B19: 06:00 | E19: 20.0955 | F19: 9.764 | L19: 27.8344 | M19: 15.06069 | N19: 12.83 | O19: 29.99 | R19: 51.391 | T19: 43.3412 | V19: 0.4 | X19: 107.4746 | AC19: 14.49 | AJ19: 5.10208 | AK19: 12.966 | AL19: 0.8455 | AM19: 51.2814 | AN19: 124.76801 | AO19: 20.7183 | AP19: 1.54 | AQ19: 156.64 | AR19: 23.84821 | AS19: 32.26522 | AT19: 34.07 | AV19: 184.1922 | AW19: 34.47293 | AY19: 0.32562 | BA19: 1.3 | BC19: 70.83476 | BI19: 18.27411 | BN19: 37.37 | BO19: 2.33 | BP19: 141.42357 | BR19: 3.6599 | BS19: 130.0541 | BT19: 13.54646 | BV19: 36.4294 | BW19: 3.65085 | CA19: 24.49165 | CB19: 0.3486 | CC19: 0.59 | CD19: 23.31323 | CE19: 408.26983 | CG19: 157.6509 | CH19: 17.69557 | CK19: 16.4939 | CL19: 4.65496 | CO19: 13.1334 | CP19: 288.58 | CR19: 36.784 | CT19: 28.647
... B55: 00:00 | E55: 23.7479 | F55: 12.295 | L55: 27.4872 | M55: 13.90095 | N55: 14 | O55: 31.426 | R55: 52.256 | T55: 28.5776 | V55: 0.4 | X55: 106.38309 | AC55: 15.93 | AJ55: 5.27586 | AK55: 13.521 | AL55: 1.2385 | AM55: 51.5506 | AN55: 121.63796 | AO55: 29.2316 | AP55: 0.83 | AQ55: 162.79 | AR55: 23.72643 | AS55: 35.52061 | AT55: 32.07 | AV55: 194.8417 | AW55: 34.61831 | AY55: 0.14566 | BA55: 1.7 | BC55: 69.60204 | BI55: 13.0515 | BN55: 39.22 | BO55: 2.08 | BP55: 147.9279 | BR55: 3.88885 | BS55: 125.8923 | BT55: 14.48609 | BV55: 35.779 | BW55: 3.83695 | CA55: 24.92241 | CB55: 0.4756 | CC55: 0.6 | CD55: 26.14058 | CE55: 418.15791 | CG55: 160.3914 | CH55: 16.76729 | CK55: 19.5886 | CL55: 4.80312 | CO55: 16.26839 | CP55: 294.78 | CR55: 40.308 | CT55: 21.606
B56: MWh | C56: 0 | D56: 0 | E56: 469.6826 | F56: 277.674 | G56: 0 | H56: 0 | I56: 0 | J56: 0 | K56: 0 | L56: 656.73375 | M56: 310.86633 | N56: 317.675 | O56: 744.971 | P56: 0 | Q56: 0 | R56: 1229.103 | S56: 0 | T56: 881.6482 | U56: 0 | V56: 8.55 | W56: 0 | X56: 2546.4032 | Y56: 0 | Z56: 0 | AA56: 0 | AB56: 0 | AC56: 366.97 | AD56: 0 | AE56: 0 | AF56: 0 | AG56: 0 | AH56: 0 | AI56: 0 | AJ56: 118.96792 | AK56: 327.9605 | AL56: 62.9143 | AM56: 1164.8118 | AN56: 2913.9713 | AO56: 629.85405 | AP56: 18.01 | AQ56: 3855.73 | AR56: 572.97232 | AS56: 815.33164 | AT56: 804.73 | AU56: 0 | AV56: 4287.107 | AW56: 835.26523 | AX56: 0 | AY56: 6.244395 | AZ56: 0 | BA56: 36.07 | BB56: 0 | BC56: 1573.1157 | BD56: 0 | BE56: 0 | BF56: 0 | BG56: 0 | BH56: 0 | BI56: 397.48101 | BJ56: 0 | BK56: 0 | BL56: 0 | BM56: 0 | BN56: 787.33 | BO56: 54.96 | BP56: 3473.412 | BQ56: 0 | BR56: 89.105415 | BS56: 3028.9122 | BT56: 310.23318 | BU56: 0 | BV56: 851.0081 | BW56: 93.385435 | BX56: 0 | BY56: 0 | BZ56: 0 | CA56: 506.2856 | CB56: 23.42225 | CC56: 14.6 | CD56: 576.04696 | CE56: 9883.3024 | CF56: 0 | CG56: 3811.0267 | CH56: 412.10945 | CI56: 0 | CJ56: 0 | CK56: 400.8444 | CL56: 114.40954 | CM56: 0 | CN56: 0 | CO56: 361.83459 | CP56: 6730.05 | CQ56: 0 | CR56: 889.6525 | CS56: 0 | CT56: 485.8415
B59: Nota :
B60: Información proporcionada por la empresas
C62: DATOS ESTIMADOS
C64: SIN DATOS

Sheet TIPO_RECURSO
B3: sábado, 27 de Diciembre del 2025
B5: REPORTE POTENCIA GENERADA POR TIPO DE RECURSO
B6: HORA | C6: H. PASADA | D6: H. REGULACION | E6: GAS DE CAMISEA | F6: GAS DE MALACAS | G6: GAS DE AGUAYTIA | H6: DIÉSEL | I6: RESIDUAL | J6: NAFTA+GAS DE REFINERIA | K6: FLEXIGAS+GAS DE REFINERIA | L6: BAGAZO | M6: BIOGÁS | N6: SOLAR | O6: EÓLICA | P6: TOTAL | U6: EMPRESA | V6: CENTRAL | W6: HIDROELECTRICA DE PASADA | X6: HIDROELECTRICA DE REGULACION
B7: 00:30 | C7: 999.44 | D7: 2247.175 | E7: 3049.1494 | F7: 46.3 | G7: 76.7 | K7: =DESPACHO_EJECUTADO!FG11+DESPACHO_EJECUTADO!FH11 -> 62.6 | L7: 47.7 | M7: 8.9 | N7: 0 | O7: 204.4 | P7: =SUM(C7:O7) -> 6742.3644 | U7: ANDEAN POWER S.A.C. | V7: C.H.CARHUAC | W7: 355.85
B8: 01:00 | C8: 1002.679 | D8: 2117.459 | E8: 3087.2734 | F8: 14 | G8: 77.7 | K8: =DESPACHO_EJECUTADO!FG12+DESPACHO_EJECUTADO!FH12 -> 61.7 | L8: 48.4 | M8: 8.9 | N8: 0 | O8: 162.4 | P8: =SUM(C8:O8) -> 6580.5114 | U8: ASOCIACIÓN SANTA LUCIA DE CHACAS | V8: C.H. HUALLIN | W8: 70.75
B9: 01:30 | C9: 981.461 | D9: 2068.682 | E9: 3149.9858 | F9: 0 | G9: 76.3 | K9: =DESPACHO_EJECUTADO!FG13+DESPACHO_EJECUTADO!FH13 -> 62.4 | L9: 48.2 | M9: 8.9 | N9: 0 | O9: 157.4 | P9: =SUM(C9:O9) -> 6553.3288 | U9: CELARIS ENERGY S.A. | V9: C.H. MANTA I | W9: 104.55
B10: 02:00 | C10: 976.703 | D10: 2080.821 | E10: 3084.0694 | F10: 0 | G10: 78.7 | K10: =DESPACHO_EJECUTADO!FG14+DESPACHO_EJECUTADO!FH14 -> 61.3 | L10: 47.9 | M10: 8.9 | N10: 0 | O10: 147.3 | P10: =SUM(C10:O10) -> 6485.6934 | U10: CELEPSA | V10: C.H. EL PLATANAL | X10: 1267.75
B11: 02:30 | C11: 991.302 | D11: 1953.227 | E11: 3095.3285 | F11: 0 | G11: 77.2 | K11: =DESPACHO_EJECUTADO!FG15+DESPACHO_EJECUTADO!FH15 -> 62 | L11: 47.9 | M11: 8.9 | N11: 0 | O11: 120.4 | P11: =SUM(C11:O11) -> 6356.2575 | U11: CELEPSA RENOVABLES S.R.L. | V11: C.H. MARAÑON | W11: 342.3
B12: 03:00 | C12: 988.528 | D12: 1978.437 | E12: 3111.019 | F12: 0 | G12: 77.8 | K12: =DESPACHO_EJECUTADO!FG16+DESPACHO_EJECUTADO!FH16 -> 61.9 | L12: 47.2 | M12: 8.9 | N12: 0 | O12: 113 | P12: =SUM(C12:O12) -> 6386.784 | U12: CHINANGO S.A.C. | V12: C.H. CHIMAY | X12: 2295.95
B13: 03:30 | C13: 989.317 | D13: 1972.041 | E13: 3064.9177 | F13: 0 | G13: 79.5 | K13: =DESPACHO_EJECUTADO!FG17+DESPACHO_EJECUTADO!FH17 -> 61.3 | L13: 48.3 | M13: 8.9 | N13: 0 | O13: 119.9 | P13: =SUM(C13:O13) -> 6344.1757 | V13: C.H. YANANGO | W13: 349.4
B14: 04:00 | C14: 983.508 | D14: 1848.34 | E14: 3058.0403 | F14: 0 | G14: 77 | K14: =DESPACHO_EJECUTADO!FG18+DESPACHO_EJECUTADO!FH18 -> 62 | L14: 45.8 | M14: 8.9 | N14: 0 | O14: 125.4 | P14: =SUM(C14:O14) -> 6208.9883 | U14: EGASA | V14: C.H. CHARCANI III | W14: 163.1
B15: 04:30 | C15: 994.469 | D15: 1957.646 | E15: 3067.4023 | F15: 0 | G15: 77.7 | K15: =DESPACHO_EJECUTADO!FG19+DESPACHO_EJECUTADO!FH19 -> 61.4 | L15: 45 | M15: 8.9 | N15: 0 | O15: 160.7 | P15: =SUM(C15:O15) -> 6373.2173 | V15: C.H. CHARCANI IV | X15: 345.4
B16: 05:00 | C16: 993.115 | D16: 1994.238 | E16: 3028.5224 | F16: 0 | G16: 78.8 | K16: =DESPACHO_EJECUTADO!FG20+DESPACHO_EJECUTADO!FH20 -> 61.7 | L16: 47.9 | M16: 8.9 | N16: 0.1 | O16: 195.9 | P16: =SUM(C16:O16) -> 6409.1754 | V16: C.H. CHARCANI V | X16: 2220.25
B17: 05:30 | C17: 991.979 | D17: 1885.095 | E17: 3075.2226 | F17: 0 | G17: 78.5 | K17: =DESPACHO_EJECUTADO!FG21+DESPACHO_EJECUTADO!FH21 -> 61 | L17: 47.6 | M17: 8.9 | N17: 8 | O17: 231.1 | P17: =SUM(C17:O17) -> 6387.3966 | U17: EGEJUNIN | V17: C.H. HUASAHUASI I | W17: 103.35
B18: 06:00 | C18: 1002.347 | D18: 1777.544 | E18: 2982.5682 | F18: 0 | G18: 79 | K18: =DESPACHO_EJECUTADO!FG22+DESPACHO_EJECUTADO!FH22 -> 61 | L18: 48.2 | M18: 8.9 | N18: 72.903 | O18: 252.3 | P18: =SUM(C18:O18) -> 6284.7622 | V18: C.H. RUNATULLO II | W18: 258.25
B19: 06:30 | C19: 1026.413 | D19: 1669.464 | E19: 2954.8412 | F19: 0 | G19: 81.2 | K19: =DESPACHO_EJECUTADO!FG23+DESPACHO_EJECUTADO!FH23 -> 61.5 | L19: 48.9 | M19: 8.9 | N19: 156.655 | O19: 253.5 | P19: =SUM(C19:O19) -> 6261.3732 | V19: C.H. RUNATULLO III | W19: 357.05
B20: 07:00 | C20: 935.911 | D20: 1484.923 | E20: 2976.2821 | F20: 0 | G20: 77.1 | K20: =DESPACHO_EJECUTADO!FG24+DESPACHO_EJECUTADO!FH24 -> 61.3 | L20: 47 | M20: 8.9 | N20: 452.645 | O20: 268.8 | P20: =SUM(C20:O20) -> 6312.8611 | V20: C.H. SANTA CRUZ I | W20: 191.45
B21: 07:30 | C21: 910.168 | D21: 1409.722 | E21: 2998.1876 | F21: 26.7 | G21: 78 | K21: =DESPACHO_EJECUTADO!FG25+DESPACHO_EJECUTADO!FH25 -> 61.5 | L21: 47.5 | M21: 8.9 | N21: 771.178 | O21: 295.3 | P21: =SUM(C21:O21) -> 6607.1556 | U21: EGEMSA | V21: C.H. MACHUPICCHU | W21: 3966.35
B22: 08:00 | C22: 961.859 | D22: 1544.207 | E22: 3002.5346 | F22: 45.8 | G22: 78.1 | K22: =DESPACHO_EJECUTADO!FG26+DESPACHO_EJECUTADO!FH26 -> 61.1 | L22: 46.1 | M22: 8.9 | N22: 721.973 | O22: 334.8 | P22: =SUM(C22:O22) -> 6805.3736 | U22: EGESUR | V22: C.H. ARICOTA I | X22: 189.6
B23: 08:30 | C23: 956.044 | D23: 1580.917 | E23: 3034.655 | F23: 46.2 | G23: 44.2 | K23: =DESPACHO_EJECUTADO!FG27+DESPACHO_EJECUTADO!FH27 -> 60.7 | L23: 43.3 | M23: 8.9 | N23: 906.395 | O23: 337.9 | P23: =SUM(C23:O23) -> 7019.211 | V23: C.H. ARICOTA II | X23: 132.85
B24: 09:00 | C24: 950.661 | D24: 1644.978 | E24: 3100.0952 | F24: 45.9 | G24: 43.8 | K24: =DESPACHO_EJECUTADO!FG28+DESPACHO_EJECUTADO!FH28 -> 61.1 | L24: 41.7 | M24: 8.9 | N24: 919.771 | O24: 314.8 | P24: =SUM(C24:O24) -> 7131.7052 | U24: ELECTRICA YANAPAMPA SAC | V24: C.H. YANAPAMPA | W24: 55.4
B25: 09:30 | C25: 993.945 | D25: 1809.224 | E25: 3063.6775 | F25: 45.3 | G25: 44.2 | K25: =DESPACHO_EJECUTADO!FG29+DESPACHO_EJECUTADO!FH29 -> 61.2 | L25: 42.9 | M25: 8.9 | N25: 936.95 | O25: 335.1 | P25: =SUM(C25:O25) -> 7341.3965 | U25: ELECTROPERU | V25: C.H. MANTARO | X25: 10871.15
B26: 10:00 | C26: 986.965 | D26: 1775.352 | E26: 3067.5695 | F26: 45.7 | G26: 44.3 | K26: =DESPACHO_EJECUTADO!FG30+DESPACHO_EJECUTADO!FH30 -> 60.4 | L26: 46 | M26: 8.9 | N26: 966.025 | O26: 382.5 | P26: =SUM(C26:O26) -> 7383.7115 | V26: C.H. RESTITUCION | W26: 3600.2
B27: 10:30 | C27: 1008.246 | D27: 1930.274 | E27: 3076.3692 | F27: 45 | G27: 43.5 | K27: =DESPACHO_EJECUTADO!FG31+DESPACHO_EJECUTADO!FH31 -> 61.5 | L27: 47 | M27: 8.9 | N27: 907.554 | O27: 458.6 | P27: =SUM(C27:O27) -> 7586.9432 | U27: EMPRESA DE GENERACION ELECTRICA CANCHAYLLO SAC | V27: C.H. CANCHAYLLO | W27: 99.45
B28: 11:00 | C28: 1011.487 | D28: 1999.764 | E28: 3076.8849 | F28: 44.8 | G28: 44.4 | K28: =DESPACHO_EJECUTADO!FG32+DESPACHO_EJECUTADO!FH32 -> 61.2 | L28: 48.6 | M28: 8.8 | N28: 902.556 | O28: 521.2 | P28: =SUM(C28:O28) -> 7719.6919 | U28: EMPRESA DE GENERACION ELECTRICA RIO BAÑOS S.A.C. | V28: C.H. RUCUY | W28: 407.8
B29: 11:30 | C29: 993.835 | D29: 1957.328 | E29: 3070.7644 | F29: 44.3 | G29: 46.8 | K29: =DESPACHO_EJECUTADO!FG33+DESPACHO_EJECUTADO!FH33 -> 61.1 | L29: 45.9 | M29: 8.8 | N29: 849.657 | O29: 606.7 | P29: =SUM(C29:O29) -> 7685.1844 | U29: EMPRESA DE GENERACION ELECTRICA SANTA ANA S.A.C. | V29: C.H. RENOVANDES H1 | W29: 473.55
B30: 12:00 | C30: 967.354 | D30: 1747.866 | E30: 3024.1473 | F30: 45 | G30: 43.1 | K30: =DESPACHO_EJECUTADO!FG34+DESPACHO_EJECUTADO!FH34 -> 61.1 | L30: 47.2 | M30: 8.8 | N30: 988.662 | O30: 648.1 | P30: =SUM(C30:O30) -> 7581.3293 | U30: EMPRESA DE GENERACION HUALLAGA | V30: C.H. CHAGLLA | X30: 1166.75
B31: 12:30 | C31: 976.81 | D31: 1799.891 | E31: 3055.7568 | F31: 44.8 | G31: 44.2 | K31: =DESPACHO_EJECUTADO!FG35+DESPACHO_EJECUTADO!FH35 -> 60.5 | L31: 48.9 | M31: 8.8 | N31: 989.063 | O31: 666.5 | P31: =SUM(C31:O31) -> 7695.2208 | V31: P.C.H. CHAGLLA | W31: 156
B32: 13:00 | C32: 976.638 | D32: 1740.422 | E32: 3031.2736 | F32: 45.7 | G32: 46.7 | K32: =DESPACHO_EJECUTADO!FG36+DESPACHO_EJECUTADO!FH36 -> 60.5 | L32: 45.6 | M32: 8.8 | N32: 950.56 | O32: 690.2 | P32: =SUM(C32:O32) -> 7596.3936 | U32: EMPRESA DE GENERACION HUANZA | V32: C.H. HUANZA | X32: 1415.4
B33: 13:30 | C33: 934.375 | D33: 1541.923 | E33: 3040.842 | F33: 45.5 | G33: 43.1 | K33: =DESPACHO_EJECUTADO!FG37+DESPACHO_EJECUTADO!FH37 -> 60.3 | L33: 45.4 | M33: 8.8 | N33: 986.158 | O33: 713.3 | P33: =SUM(C33:O33) -> 7419.698 | U33: EMPRESA ELECTRICA AGUA AZUL | V33: C.H. POTRERO | W33: 249.65
B34: 14:00 | C34: 936.727 | D34: 1649.934 | E34: 3080.3131 | F34: 45.6 | G34: 47 | K34: =DESPACHO_EJECUTADO!FG38+DESPACHO_EJECUTADO!FH38 -> 60.9 | L34: 47.8 | M34: 8.7 | N34: 977.654 | O34: 712.2 | P34: =SUM(C34:O34) -> 7566.8281 | U34: EMPRESA ELECTRICA RIO DOBLE | V34: C.H. LAS PIZARRAS | W34: 327.7
B35: 14:30 | C35: 932.876 | D35: 1606.011 | E35: 3072.5334 | F35: 45.6 | G35: 79.5 | K35: =DESPACHO_EJECUTADO!FG39+DESPACHO_EJECUTADO!FH39 -> 60.9 | L35: 48.9 | M35: 8.8 | N35: 911.343 | O35: 718.3 | P35: =SUM(C35:O35) -> 7484.7634 | U35: ENGIE ENERGIA PERU S.A.A. | V35: C.H. YUNCAN | X35: 2193.5
B36: 15:00 | C36: 951.266 | D36: 1683.423 | E36: 3059.6621 | F36: 45.5 | G36: 79 | K36: =DESPACHO_EJECUTADO!FG40+DESPACHO_EJECUTADO!FH40 -> 60.9 | L36: 47.4 | M36: 8.8 | N36: 940.426 | O36: 705.2 | P36: =SUM(C36:O36) -> 7581.5771 | U36: GENERACIÓN ANDINA S.A.C. | V36: C.H. 8 DE AGOSTO | W36: 220.9
B37: 15:30 | C37: 941.879 | D37: 1708.391 | E37: 2966.2072 | F37: 45.5 | G37: 78.3 | K37: =DESPACHO_EJECUTADO!FG41+DESPACHO_EJECUTADO!FH41 -> 61.3 | L37: 46.1 | M37: 8.8 | N37: 773.627 | O37: 744.5 | P37: =SUM(C37:O37) -> 7374.6042 | V37: C.H. EL CARMEN | W37: 69.35
B38: 16:00 | C38: 957.367 | D38: 1759.94 | E38: 3074.4305 | F38: 45.1 | G38: 77.7 | K38: =DESPACHO_EJECUTADO!FG42+DESPACHO_EJECUTADO!FH42 -> 61.5 | L38: 45.8 | M38: 8.8 | N38: 589.215 | O38: 744.8 | P38: =SUM(C38:O38) -> 7364.6525 | U38: GENERADORA DE ENERGÍA DEL PERÚ | V38: C.H. ÁNGEL I | W38: 489.6
B39: 16:30 | C39: 976.47 | D39: 1792.177 | E39: 3015.8923 | F39: 44.9 | G39: 78.6 | K39: =DESPACHO_EJECUTADO!FG43+DESPACHO_EJECUTADO!FH43 -> 61.7 | L39: 47.3 | M39: 8.8 | N39: 598.499 | O39: 767.8 | P39: =SUM(C39:O39) -> 7392.1383 | V39: C.H. ÁNGEL II | W39: 489.6
B40: 17:00 | C40: 954.376 | D40: 1794.257 | E40: 3070.6294 | F40: 45.4 | G40: 78.4 | K40: =DESPACHO_EJECUTADO!FG44+DESPACHO_EJECUTADO!FH44 -> 61.9 | L40: 46.9 | M40: 8.8 | N40: 496.214 | O40: 749.8 | P40: =SUM(C40:O40) -> 7306.6764 | V40: C.H. ÁNGEL III | W40: 482.4
B41: 17:30 | C41: 971.952 | D41: 2011.056 | E41: 3101.6173 | F41: 45.2 | G41: 78.2 | K41: =DESPACHO_EJECUTADO!FG45+DESPACHO_EJECUTADO!FH45 -> 61.8 | L41: 50 | M41: 8.8 | N41: 210.345 | O41: 762.8 | P41: =SUM(C41:O41) -> 7301.7703 | V41: C.H. LA JOYA | W41: 202.1
B42: 18:00 | C42: 972.612 | D42: 2039.089 | E42: 3089.9887 | F42: 46.1 | G42: 78 | K42: =DESPACHO_EJECUTADO!FG46+DESPACHO_EJECUTADO!FH46 -> 61.9 | L42: 49.1 | M42: 8.8 | N42: 61.916 | O42: 746 | P42: =SUM(C42:O42) -> 7153.5057 | U42: HIDROCAÑETE S.A. | V42: C.H. IMPERIAL | W42: 55.05
B43: 18:30 | C43: 1000.64 | D43: 2227.982 | E43: 3102.937 | F43: 46.1 | G43: 79.6 | K43: =DESPACHO_EJECUTADO!FG47+DESPACHO_EJECUTADO!FH47 -> 61.9 | L43: 49.2 | M43: 8.9 | N43: 1.214 | O43: 756 | P43: =SUM(C43:O43) -> 7334.473 | U43: HIDROELECTRICA HUANCHOR S.A.C. | V43: C.H. HUANCHOR | W43: 382.45
B44: 19:00 | C44: 1013.581 | D44: 2477.385 | E44: 3164.0781 | F44: 46.4 | G44: 79.2 | K44: =DESPACHO_EJECUTADO!FG48+DESPACHO_EJECUTADO!FH48 -> 61.9 | L44: 48.7 | M44: 8.9 | N44: 0 | O44: 739.1 | P44: =SUM(C44:O44) -> 7639.2441 | U44: HUAURA POWER GROUP S.A. | V44: C.H. YARUCAYA | W44: 410.2
B45: 19:30 | C45: 1016.909 | D45: 2622.809 | E45: 3166.2897 | F45: 46.4 | G45: 79.9 | K45: =DESPACHO_EJECUTADO!FG49+DESPACHO_EJECUTADO!FH49 -> 61.9 | L45: 48.9 | M45: 8.9 | N45: 0 | O45: 687.8 | P45: =SUM(C45:O45) -> 7739.8077 | U45: HYDRO GLOBAL PERÚ S.A.C. | V45: CH SAN GABAN III | X45: 4872.95
B46: 20:00 | C46: 1013.021 | D46: 2692.2 | E46: 3163.8624 | F46: 46.6 | G46: 77 | K46: =DESPACHO_EJECUTADO!FG50+DESPACHO_EJECUTADO!FH50 -> 61.8 | L46: 48.2 | M46: 8.9 | N46: 0 | O46: 609.3 | P46: =SUM(C46:O46) -> 7720.8834 | U46: INLAND ENERGY SAC | V46: C.H. SANTA TERESA | W46: 2158.35
B47: 20:30 | C47: 1018.744 | D47: 2806.745 | E47: 3118.0846 | F47: 46.7 | G47: 78.3 | K47: =DESPACHO_EJECUTADO!FG51+DESPACHO_EJECUTADO!FH51 -> 62 | L47: 46.3 | M47: 8.9 | N47: 0 | O47: 525.4 | P47: =SUM(C47:O47) -> 7711.1736 | U47: KALLPA GENERACION S.A. | V47: C.H. CERRO DEL AGUILA | X47: 3435.55
B48: 21:00 | C48: 1011.617 | D48: 2814.544 | E48: 3113.0983 | F48: 46.3 | G48: 75.7 | K48: =DESPACHO_EJECUTADO!FG52+DESPACHO_EJECUTADO!FH52 -> 62.4 | L48: 47.9 | M48: 8.9 | N48: 0 | O48: 460.7 | P48: =SUM(C48:O48) -> 7641.1593 | V48: M.C.H. CERRO DEL AGUILA | W48: 227.2
B49: 21:30 | C49: 1020.23 | D49: 2801.4 | E49: 3120.7258 | F49: 46.7 | G49: 77.9 | K49: =DESPACHO_EJECUTADO!FG53+DESPACHO_EJECUTADO!FH53 -> 61.8 | L49: 41.5 | M49: 8.9 | N49: 0 | O49: 402.5 | P49: =SUM(C49:O49) -> 7581.6558 | U49: LA VIRGEN | V49: C.H. LA VIRGEN | X49: 649.5
B50: 22:00 | C50: 995.11 | D50: 2715.41 | E50: 3106.9446 | F50: 46.8 | G50: 78.1 | K50: =DESPACHO_EJECUTADO!FG54+DESPACHO_EJECUTADO!FH54 -> 63 | L50: 48 | M50: 8.9 | N50: 0 | O50: 387.8 | P50: =SUM(C50:O50) -> 7450.0646 | U50: MAJA ENERGIA S.A.C. | V50: C.H. RONCADOR | W50: 40.1
B51: 22:30 | C51: 1011.71 | D51: 2813.06 | E51: 3106.7802 | F51: 46.6 | G51: 78.6 | K51: =DESPACHO_EJECUTADO!FG55+DESPACHO_EJECUTADO!FH55 -> 63.3 | L51: 43.6 | M51: 8.9 | N51: 0 | O51: 371.9 | P51: =SUM(C51:O51) -> 7544.4502 | U51: ORAZUL ENERGY PERÚ | V51: C.H. CAÑA BRAVA | W51: 126.7
B52: 23:00 | C52: 1004.75 | D52: 2616.98 | E52: 3093.4817 | F52: 46.6 | G52: 77.8 | K52: =DESPACHO_EJECUTADO!FG56+DESPACHO_EJECUTADO!FH56 -> 61.9 | L52: 46.7 | M52: 8.9 | N52: 0 | O52: 368.7 | P52: =SUM(C52:O52) -> 7325.8117 | V52: C.H. CAÑON DEL PATO | X52: 4165
B53: 23:30 | C53: 970.6 | D53: 2386.21 | E53: 3092.7454 | F53: 46.5 | G53: 77.5 | K53: =DESPACHO_EJECUTADO!FG57+DESPACHO_EJECUTADO!FH57 -> 61.7 | L53: 48.4 | M53: 8.9 | N53: 0 | O53: 372.2 | P53: =SUM(C53:O53) -> 7064.7554 | V53: C.H. CARHUAQUERO | X53: 1860.95
B54: 00:00 | C54: 967.47 | D54: 2342.76 | E54: 3120.6204 | F54: 20.5 | G54: 79.1 | K54: =DESPACHO_EJECUTADO!FG58+DESPACHO_EJECUTADO!FH58 -> 61.9 | L54: 48.4 | M54: 8.9 | N54: 0 | O54: 317.9 | P54: =SUM(C54:O54) -> 6967.5504 | V54: C.H. CARHUAQUERO IV | W54: 237.95
B55: TOTAL MWh | C55: =SUM(C7:C54)/2 -> 23562.733 | D55: =SUM(D7:D54)/2 -> 48439.361 | E55: =SUM(E7:E54)/2 -> 73714.151 | F55: =SUM(F7:F54)/2 -> 786.05 | G55: =SUM(G7:G54)/2 -> 1675.5 | H55: =SUM(H7:H54)/2 -> 0 | I55: =SUM(I7:I54)/2 -> 0 | J55: =SUM(J7:J54)/2 -> 0 | ... P55: =SUM(P7:P54)/2 -> 170753.72 | U55: ORYGEN PERU S.A.A. | V55: C.H. CALLAHUANCA | X55: 1527.05
B56: % | C56: =C55*100/$P$55 -> 13.79925 | D56: =D55*100/$P$55 -> 28.367968 | E56: =E55*100/$P$55 -> 43.169864 | F56: =F55*100/$P$55 -> 0.46034135 | G56: =G55*100/$P$55 -> 0.98123775 | H56: =H55*100/$P$55 -> 0 | I56: =I55*100/$P$55 -> 0 | J56: =J55*100/$P$55 -> 0 | ... P56: =P55*100/$P$55 -> 100 | V56: C.H. HER 1 | W56: 14.4
V57: C.H. HUAMPANI | W57: 711.2
V58: C.H. HUINCO | X58: 3348.2
V59: C.H. MATUCANA | X59: 1607.2
V60: C.H. MOYOPAMPA | W60: 1538.3
U61: SAN GABAN | V61: C.H. SAN GABAN II | X61: 2654.6
V62: PCH TUPURI | W62: 26.9
U63: SINERSA | V63: C.H. CHANCAY | W63: 239.95
V64: C.H. POECHOS II | W64: 137.15
U65: STATKRAFT S.A | V65: C.H. ARCATA | W65: 97.6475
V66: C.H. CAHUA | W66: 643.3985
V67: C.H. CHEVES | X67: 1242.067
V68: C.H. GALLITO CIEGO | X68: 786.34
V69: C.H. MALPASO | X69: 191.3545
V70: C.H. YAUPI | W70: 2571.487
U71: TRANSMISION ANDINA DE GENERACION S.A.C. | V71: C.H. OROYA | W71: 79.15
U72: VARI ENERGIA S.A.C. | V72: C.H. ANASHIRONI | W72: 279.05
U73: TOTAL MWh | W73: 23562.733 | X73: 48439.361

Sheet GENERACION RER
B3: sábado, 27 de Diciembre del 2025
B5: GENERACIÓN ELÉCTRICA DE LAS CENTRALES RER (MW)
B6: HORA | C6: AGRO INDUSTRIAL PARAMONGA S.A. | D6: AGROAURORA S.A.C. | E6: AGROINDUSTRIAS SAN JACINTO S.A.A. | F6: AGROLMOS SOCIEDAD ANONIMA - AGROLMOS S.A. | G6: ANDEAN POWER S.A.C. | H6: ASOCIACIÓN SANTA LUCIA DE CHACAS | I6: ATRIA ENERGIA S.A.C. | J6: BIOENERGIA DEL CHIRA S.A. | K6: CASA GRANDE S.A.A. | L6: CELARIS ENERGY S.A. | M6: COENERGY S.A.C. | N6: COLCA SOLAR S.A.C. | O6: EGEJUNIN | T6: ELECTRICA YANAPAMPA SAC | U6: EMPRESA DE GENERACION ELECTRICA CANCHAYLLO SAC | V6: EMPRESA DE GENERACION ELECTRICA RIO BAÑOS S.A.C. | W6: EMPRESA DE GENERACION ELECTRICA SANTA ANA S.A.C. | X6: EMPRESA ELECTRICA AGUA AZUL | Y6: EMPRESA ELECTRICA RIO DOBLE | Z6: ENERGÍA EÓLICA S.A. | AB6: ENERGIA RENOVABLE DEL SUR S.A. | AC6: ENGIE ENERGIA PERU S.A.A. | AG6: GENERACIÓN ANDINA S.A.C. | AI6: GENERADORA DE ENERGÍA DEL PERÚ | AM6: GR CORTARRAMA SOCIEDAD ANONIMA CERRADA | AN6: GR PAINO SOCIEDAD ANONIMA CERRADA | AO6: GR TARUCA SOCIEDAD ANONIMA CERRADA | AP6: HIDROCAÑETE S.A. | AQ6: HUAURA POWER GROUP S.A. | AR6: HYDRO PATAPO S.A.C. | AS6: JOYA SOLAR S.A.C. | AU6: KALLPA GENERACION S.A. | AW6: KONDU SAC | AX6: MAJA ENERGIA S.A.C. | AY6: MAJES ARCUS S.A.C. | BA6: MOQUEGUA FV S.A.C. | BB6: ORAZUL ENERGY PERÚ | BD6: ORYGEN PERU S.A.A. | BI6: PANAMERICANA SOLAR SAC. | BJ6: PARQUE EOLICO MARCONA S.A.C. | BK6: PARQUE EOLICO TRES HERMANAS S.A.C. | BL6: PETRAMAS | BP6: REPARTICIÓN ARCUS S.A.C. | BQ6: SAN GABAN | BR6: SINERSA | BT6: TACNA SOLAR SAC. | BU6: VARI ENERGIA S.A.C. | BV6: TOTAL RER
C7: C.T. PARAMONGA | D7: C.T. MAPLE | E7: C.T SAN JACINTO | F7: C.T. AGROLMOS | G7: C.H. CARHUAC | H7: C.H. HUALLIN | I7: C.H. PURMACANA | J7: C.T. CAÑA BRAVA | K7: C.T. CASA GRANDE | L7: C.H. MANTA | M7: CS COENERGY | N7: CS YARUCAYA | O7: C.H. HUASAHUASI I | P7: C.H. HUASAHUASI II | Q7: C.H. RUNATULLO II | R7: C.H. RUNATULLO III | S7: C.H. STA CRUZ I y II | T7: C.H. YANAPAMPA | U7: C.H. CANCHAYLLO | V7: C.H. RUCUY | W7: C.H. RENOVANDES H1 | X7: C.H. POTRERO | Y7: C.H. LAS PIZARRAS | Z7: C.E. CUPISNIQUE | AA7: C.E. TALARA | AB7: CE SAN JUAN | AC7: C.E. P LOM EXPANSION | AD7: C.E. PUNTA LOMITAS | AE7: C.S. INTIPAMPA | AF7: CS EXPANSIÓN INTIPAMPA | AG7: C.H. 8 DE AGOSTO | AH7: C.H. EL CARMEN | AI7: C.H. ANGEL I | AJ7: C.H. ANGEL II | AK7: C.H. ANGEL III | AL7: C.H. LA JOYA | AM7: CS MATARANI | AN7: C.E. HUAMBOS | AO7: C.E. DUNA | AP7: C.H. NUEVAIMPERIAL | AQ7: C.H. YARUCAYA | AR7: MCH PATAPO | AS7: C.S. ILLA 1 | AT7: CS SAN MARTIN SOLAR | AU7: C.S. SUNNY EXPANSION | AV7: CS SUNNY | AW7: CARHUAQUERO (CS) | AX7: C.H. RONCADOR | AY7: C.S. MAJES | AZ7: C.S. SOL DE VERANO | BA7: C.S. MOQUEGUA FV | BB7: C.H. CANA BRAVA | BC7: C.H. CARHUAQUERO4 | BD7: C.E. WAYRA EXTENSION | BE7: C.E. WAYRA I | BF7: C.H. HER 1 | BG7: C.S. CLEMESI | BH7: C.S. RUBI | BI7: C.S. PANAMERICANA-SOLAR | BJ7: C.E. MARCONA | BK7: C.E. 3 HERMANAS | BL7: C.T. HUAYCOLORO | BM7: C.T. LA GRINGA V | BN7: CTB CALLAO | BO7: CTB. DONA CATALINA | BP7: C.S. REPARTICION | BQ7: C.H. TUPURI | BR7: C.H. CHANCAY | BS7: C.H. POECHOS2 | BT7: C.S. TACNA-SOLAR | BU7: C.H. ANASHIRONI | BV7: MW
B8: 0:30 | E8: 9.1 | F8: 11.1 | G8: 20.2 | H8: 3 | J8: 8.4 | K8: 19.1 | L8: 4.3 | O8: 4.1 | Q8: 10.1 | R8: 14.9 | S8: 8.2 | T8: 2 | U8: 4.1 | V8: 17.6 | W8: 18.2 | X8: 10.6 | Y8: 14.4 | Z8: 56 | AA8: 18 | AB8: 48.3 | AC8: 0.6 | AD8: 44.6 | AG8: 8.8 | AH8: 2.8 | AI8: 20.4 | AJ8: 20.4 | AK8: 20.1 | AL8: 8.5 | AN8: 0.4 | AO8: 0.2 | AP8: 2.3 | AQ8: 17.2 | AX8: 1.6 | BB8: 5.4 | BC8: 9.9 | BD8: 0.7 | BE8: 2.9 | BF8: 0.6 | BJ8: 13.5 | BK8: 19.2 | BL8: 4.3 | BM8: 1.2 | BN8: 2.2 | BO8: 1.2 | BQ8: 1.1 | BR8: 10 | BS8: 5.7 | BU8: 4.9 | BV8: 532.4
B9: 1:00 | E9: 9 | F9: 11.1 | G9: 20.2 | H9: 3 | J9: 8.8 | K9: 19.5 | L9: 4.3 | O9: 4.1 | Q9: 10.3 | R9: 14.7 | S9: 8.2 | T9: 2.1 | U9: 4.1 | V9: 17.6 | W9: 16.8 | X9: 10.6 | Y9: 14.5 | Z9: 49.5 | AA9: 19.7 | AB9: 42.2 | AC9: 0.1 | AD9: 29.5 | AG9: 8.8 | AH9: 2.8 | AI9: 20.4 | AJ9: 20.4 | AK9: 20.1 | AL9: 8.5 | AN9: 0.6 | AO9: 0.3 | AP9: 2.3 | AQ9: 17.2 | AX9: 1.6 | BB9: 5.4 | BC9: 9.9 | BD9: 0.7 | BE9: 0.7 | BF9: 0.6 | BJ9: 8.3 | BK9: 10.8 | BL9: 4.3 | BM9: 1.2 | BN9: 2.2 | BO9: 1.2 | BQ9: 1.1 | BR9: 10 | BS9: 5.8 | BU9: 5 | BV9: 490.1
B10: 1:30 | E10: 8.6 | F10: 11.1 | G10: 14.4 | H10: 3 | J10: 8.4 | K10: 20.1 | L10: 4.2 | O10: 4.1 | Q10: 10.5 | R10: 14.5 | S10: 8.2 | T10: 2.2 | U10: 4.1 | V10: 17.6 | W10: 17.1 | X10: 10.6 | Y10: 14.3 | Z10: 57.1 | AA10: 22.1 | AB10: 36.9 | AD10: 20.7 | AG10: 9 | AH10: 3 | AI10: 20.4 | AJ10: 20.4 | AK10: 20.1 | AL10: 8.5 | AN10: 1.3 | AO10: 0.7 | AP10: 2.3 | AQ10: 17.2 | AX10: 1.7 | BB10: 5.4 | BC10: 10 | BD10: 0.7 | BE10: 0.1 | BF10: 0.6 | BJ10: 7 | BK10: 10.8 | BL10: 4.3 | BM10: 1.2 | BN10: 2.2 | BO10: 1.2 | BQ10: 1.1 | BR10: 10 | BS10: 5.7 | BU10: 5.1 | BV10: 479.8
B11: 2:00 | E11: 8.6 | F11: 11.1 | G11: 11.4 | H11: 3 | J11: 8.8 | K11: 19.4 | L11: 4.4 | O11: 4.1 | Q11: 10.8 | R11: 14.7 | S11: 8.2 | T11: 2.1 | U11: 4.3 | V11: 17.4 | W11: 18.1 | X11: 10.6 | Y11: 14 | Z11: 60.8 | AA11: 22.6 | AB11: 30.9 | AD11: 14.3 | AG11: 9.3 | AH11: 3.1 | AI11: 20.4 | AJ11: 20.4 | AK11: 20.1 | AL11: 8.5 | AN11: 0.5 | AO11: 0.4 | AP11: 2.3 | AQ11: 17.2 | AX11: 1.7 | BB11: 5.4 | BC11: 9.9 | BD11: 0.2 | BF11: 0.6 | BJ11: 7.3 | BK11: 10.3 | BL11: 4.3 | BM11: 1.2 | BN11: 2.2 | BO11: 1.2 | BQ11: 1.1 | BR11: 9.9 | BS11: 5.6 | BU11: 5.1 | BV11: 467.8
B12: 2:30 | E12: 8.6 | F12: 11.1 | G12: 11 | H12: 3 | J12: 9.1 | K12: 19.1 | L12: 4.4 | O12: 4.1 | Q12: 11.1 | R12: 14.5 | S12: 8.3 | T12: 2.3 | U12: 4.3 | V12: 17.8 | W12: 18.9 | X12: 10.6 | Y12: 13.5 | Z12: 51.3 | AA12: 27.7 | AB12: 19.1 | AD12: 11.6 | AG12: 9.4 | AH12: 2.9 | AI12: 20.4 | AJ12: 20.4 | AK12: 20.1 | AL12: 8.5 | AN12: 0.3 | AO12: 0.1 | AP12: 2.3 | AQ12: 17.2 | AX12: 1.7 | BB12: 5.3 | BC12: 9.9 | BF12: 0.6 | BJ12: 4.5 | BK12: 5.8 | BL12: 4.3 | BM12: 1.2 | BN12: 2.2 | BO12: 1.2 | BQ12: 1.1 | BR12: 10 | BS12: 5.6 | BU12: 5.2 | BV12: 441.6
B13: 3:00 | E13: 8.1 | F13: 11 | G13: 11.7 | H13: 3 | J13: 8.6 | K13: 19.5 | L13: 4.4 | O13: 4.1 | Q13: 12.1 | R13: 14.8 | S13: 8.3 | T13: 2.3 | U13: 4.1 | V13: 17.8 | W13: 17.3 | X13: 10.6 | Y13: 13.6 | Z13: 55.6 | AA13: 28.1 | AB13: 12.5 | AD13: 8.1 | AG13: 9.2 | AH13: 2.8 | AI13: 20.4 | AJ13: 20.4 | AK13: 20.1 | AL13: 8.5 | AP13: 2.3 | AQ13: 17.2 | AX13: 1.7 | BB13: 5.3 | BC13: 9.9 | BE13: 0.4 | BF13: 0.6 | BJ13: 3 | BK13: 5.3 | BL13: 4.3 | BM13: 1.2 | BN13: 2.2 | BO13: 1.2 | BQ13: 1.1 | BR13: 10 | BS13: 5.6 | BU13: 5.1 | BV13: 433.4
B14: 3:30 | E14: 8.2 | F14: 11 | G14: 11.7 | H14: 3 | J14: 9.3 | K14: 19.8 | L14: 4.5 | O14: 4.1 | Q14: 12 | R14: 14.8 | S14: 8.3 | T14: 2.3 | U14: 4.1 | V14: 17.8 | W14: 18.6 | X14: 10.6 | Y14: 13.5 | Z14: 52.2 | AA14: 29.2 | AB14: 20.2 | AD14: 10.1 | AG14: 9.1 | AH14: 2.8 | AI14: 20.4 | AJ14: 20.4 | AK14: 20.1 | AL14: 8.5 | AP14: 2.3 | AQ14: 17.2 | AX14: 1.6 | BB14: 5.3 | BC14: 9.9 | BF14: 0.6 | BJ14: 3.2 | BK14: 5 | BL14: 4.3 | BM14: 1.2 | BN14: 2.2 | BO14: 1.2 | BQ14: 1.1 | BR14: 10 | BS14: 5.7 | BU14: 5.3 | BV14: 442.7
B15: 4:00 | E15: 8 | F15: 11 | G15: 11.9 | H15: 3 | J15: 7.8 | K15: 19 | L15: 4.5 | O15: 4.1 | Q15: 11.4 | R15: 16 | S15: 8.3 | T15: 2.3 | U15: 4.1 | V15: 17.6 | W15: 18.7 | X15: 10.6 | Y15: 13.4 | Z15: 33.6 | AA15: 28.9 | AB15: 44 | AD15: 9.1 | AG15: 9 | AH15: 2.8 | AI15: 20.4 | AJ15: 20.4 | AK15: 20.1 | AL15: 8.5 | AP15: 2.3 | AQ15: 17.2 | AX15: 1.6 | BB15: 5.3 | BC15: 9.9 | BF15: 0.6 | BJ15: 4.6 | BK15: 5.2 | BL15: 4.3 | BM15: 1.2 | BN15: 2.2 | BO15: 1.2 | BQ15: 1.1 | BR15: 10 | BS15: 5.7 | BU15: 5 | BV15: 445.9
B16: 4:30 | E16: 7 | F16: 11.1 | G16: 11.9 | H16: 3 | J16: 8.9 | K16: 18 | L16: 4.4 | O16: 4.1 | Q16: 11.6 | R16: 16.3 | S16: 8.3 | T16: 2.3 | U16: 4 | V16: 17.6 | W16: 18.8 | X16: 10.9 | Y16: 13.6 | Z16: 34.2 | AA16: 25.6 | AB16: 64.3 | AD16: 19.2 | AG16: 9 | AH16: 2.8 | AI16: 20.4 | AJ16: 20.4 | AK16: 20.1 | AL16: 8.5 | AP16: 2.3 | AQ16: 17.2 | AX16: 1.6 | BB16: 5.2 | BC16: 9.9 | BD16: 1.4 | BF16: 0.6 | BJ16: 6.2 | BK16: 9.8 | BL16: 4.3 | BM16: 1.2 | BN16: 2.2 | BO16: 1.2 | BQ16: 1.1 | BR16: 10 | BS16: 5.8 | BU16: 5.1 | BV16: 481.4
B17: 5:00 | E17: 9 | F17: 11.1 | G17: 11.9 | H17: 3 | J17: 8.1 | K17: 19.7 | L17: 4.4 | O17: 4.1 | Q17: 11.7 | R17: 16.3 | S17: 8.3 | T17: 2.3 | U17: 4 | V17: 17.6 | W17: 18.5 | X17: 11.2 | Y17: 13.5 | Z17: 38.5 | AA17: 26.3 | AB17: 67.2 | AD17: 15.6 | AG17: 9 | AH17: 2.8 | AI17: 20.4 | AJ17: 20.4 | AK17: 20.1 | AL17: 8.5 | AN17: 0.8 | AO17: 0.5 | AP17: 2.3 | AQ17: 17.2 | AX17: 1.6 | BA17: 0.1 | BB17: 5 | BC17: 9.9 | BD17: 0.5 | BF17: 0.6 | BJ17: 13 | BK17: 33.5 | BL17: 4.3 | BM17: 1.2 | BN17: 2.2 | BO17: 1.2 | BQ17: 1 | BR17: 10 | BS17: 5.7 | BU17: 5.1 | BV17: 519.2
B18: 5:30 | E18: 8.7 | F18: 11.1 | G18: 11.9 | H18: 2.9 | J18: 9 | K18: 18.8 | L18: 4.3 | O18: 4.1 | Q18: 11.2 | R18: 16.9 | S18: 8.3 | T18: 2.4 | U18: 4 | V18: 17.6 | W18: 19.7 | X18: 11.2 | Y18: 13.6 | Z18: 50.8 | AA18: 27.3 | AB18: 78.4 | AD18: 15 | AE18: 0.3 | AG18: 9 | AH18: 2.8 | AI18: 20.4 | AJ18: 20.4 | AK18: 20.1 | AL18: 8.5 | AM18: 0.1 | AN18: 0.3 | AP18: 2.3 | AQ18: 17.2 | AT18: 2.6 | AV18: 2.2 | AX18: 1.6 | BA18: 0.6 | BB18: 5.4 | BC18: 9.9 | BD18: 0.6 | BF18: 0.6 | BG18: 0.3 | BH18: 0.2 | BI18: 0.7 | BJ18: 22.5 | BK18: 36.2 | BL18: 4.3 | BM18: 1.2 | BN18: 2.2 | BO18: 1.2 | BQ18: 1 | BR18: 10 | BS18: 5.7 | BT18: 1 | BU18: 5.2 | BV18: 563.8
B19: 6:00 | E19: 9.3 | F19: 11.1 | G19: 11 | H19: 2.9 | J19: 8.8 | K19: 19 | L19: 4.3 | M19: 0.043 | O19: 4.1 | Q19: 11.5 | R19: 17 | S19: 8.1 | T19: 2.4 | U19: 4 | V19: 17.6 | W19: 20.5 | X19: 11.2 | Y19: 13.5 | Z19: 53.3 | AA19: 25.1 | AB19: 83.1 | AD19: 15.9 | AE19: 1.4 | AF19: 0.86 | AG19: 9.3 | AH19: 2.9 | AI19: 20.4 | AJ19: 20.4 | AK19: 20.1 | AL19: 9.1 | AM19: 19.7 | AP19: 2.2 | AQ19: 17.1 | AT19: 19.6 | AV19: 17.8 | AX19: 1.6 | AY19: 0.8 | BA19: 1.4 | BB19: 5.2 | BC19: 9.8 | BD19: 2.9 | BE19: 1.7 | BF19: 0.6 | BG19: 3 | BH19: 3.6 | BI19: 1.6 | BJ19: 23.7 | BK19: 46.6 | BL19: 4.3 | BM19: 1.2 | BN19: 2.2 | BO19: 1.2 | BP19: 0.5 | BQ19: 1 | BR19: 9.9 | BS19: 5.8 | BT19: 2.6 | BU19: 7.3 | BV19: 653.103
B20: 6:30 | E20: 9.1 | F20: 11.1 | G20: 5.3 | H20: 2.9 | J20: 8.5 | K20: 20.2 | L20: 4.5 | M20: 0.085 | O20: 4.8 | Q20: 12.3 | R20: 17.6 | S20: 8 | T20: 2.4 | U20: 4 | V20: 17.6 | W20: 21.2 | X20: 11.1 | Y20: 13.6 | Z20: 47.8 | AA20: 27.4 | AB20: 81.8 | AD20: 10.3 | AE20: 3.4 | AF20: 3.07 | AG20: 9.3 | AH20: 3 | AI20: 20.4 | AJ20: 20.4 | AK20: 20.1 | AL20: 8.4 | AM20: 15.2 | AP20: 2.3 | AQ20: 17.1 | AT20: 55.5 | AV20: 44 | AX20: 1.6 | AY20: 1.8 | BA20: 2.6 | BB20: 5.3 | BC20: 10 | BD20: 7.1 | BE20: 6.5 | BF20: 0.6 | BG20: 9.4 | BH20: 11.1 | BI20: 2.9 | BJ20: 22.4 | BK20: 50.2 | BL20: 4.3 | BM20: 1.2 | BN20: 2.2 | BO20: 1.2 | BP20: 1.5 | BQ20: 1 | BR20: 10 | BS20: 5.7 | BT20: 6.1 | BU20: 7.4 | BV20: 735.855
B21: 7:00 | E21: 9.3 | F21: 11.1 | G21: 5.7 | H21: 2.8 | J21: 8.5 | K21: 18.1 | L21: 4.5 | M21: 0.085 | N21: 0.1 | O21: 4.8 | Q21: 10.6 | R21: 14.8 | S21: 7.9 | T21: 2.4 | U21: 4.2 | V21: 17.7 | W21: 20.1 | X21: 11.1 | Y21: 13.6 | Z21: 40.7 | AA21: 25.8 | AB21: 86.6 | AD21: 8.7 | AE21: 5.4 | AF21: 4.66 | AG21: 9.3 | AH21: 3 | AI21: 20.4 | AJ21: 20.4 | AK21: 20.1 | AL21: 8.3 | AM21: 43.2 | AP21: 2.3 | AQ21: 17.1 | AT21: 165.1 | AV21: 116 | AX21: 1.6 | AY21: 3.8 | BA21: 5 | BB21: 5.3 | BC21: 9.8 | BD21: 13.1 | BE21: 11 | BF21: 0.6 | BG21: 53.5 | BH21: 40.8 | BI21: 7 | BJ21: 22.6 | BK21: 60.3 | BL21: 4.3 | BM21: 1.2 | BN21: 2.2 | BO21: 1.2 | BP21: 2.7 | BQ21: 1.1 | BR21: 10 | BS21: 5.8 | BT21: 5.3 | BU21: 7.9 | BV21: 1040.545
B22: 7:30 | E22: 8 | F22: 11.1 | G22: 5.8 | H22: 2.8 | J22: 8.5 | K22: 19.9 | L22: 4.5 | M22: 0.138 | N22: 0.1 | O22: 4.8 | Q22: 10.7 | R22: 14.8 | S22: 7.9 | T22: 2.4 | U22: 4.1 | V22: 17.7 | W22: 19.9 | X22: 11.1 | Y22: 13.6 | Z22: 39.5 | AA22: 28.6 | AB22: 90.7 | AD22: 7.4 | AE22: 11.5 | AF22: 8.34 | AG22: 9.3 | AH22: 3 | AI22: 20.4 | AJ22: 20.4 | AK22: 20.1 | AL22: 8.3 | AM22: 77.4 | AP22: 2.2 | AQ22: 17.1 | AT22: 220.6 | AV22: 184.2 | AX22: 1.7 | AY22: 6.1 | BA22: 5.5 | BB22: 5.2 | BC22: 9.9 | BD22: 17.9 | BE22: 14 | BF22: 0.6 | BG22: 107.7 | BH22: 128.5 | BI22: 7.2 | BJ22: 25.4 | BK22: 71.8 | BL22: 4.3 | BM22: 1.2 | BN22: 2.2 | BO22: 1.2 | BP22: 6.9 | BQ22: 1.1 | BR22: 10 | BS22: 5.7 | BT22: 7 | BU22: 9.2 | BV22: 1387.178
B23: 8:00 | E23: 7.2 | F23: 11.1 | G23: 5.8 | H23: 2.8 | J23: 8.8 | K23: 19 | L23: 4.5 | M23: 0.183 | N23: 0.1 | O23: 4.8 | Q23: 10.9 | R23: 15 | S23: 7.9 | T23: 2.4 | U23: 4 | V23: 17.7 | W23: 20.2 | X23: 11.1 | Y23: 13.5 | Z23: 43.5 | AA23: 26.4 | AB23: 100 | AD23: 16.9 | AE23: 20.3 | AF23: 15.69 | AG23: 9.3 | AH23: 3.1 | AI23: 20.4 | AJ23: 20.4 | AK23: 20.1 | AL23: 8.5 | AM23: 75.8 | AP23: 2.2 | AQ23: 17.1 | AT23: 231.6 | AV23: 191.9 | AW23: 0.1 | AX23: 1.7 | AY23: 8.5 | BA23: 11.1 | BB23: 5.5 | BC23: 9.9 | BD23: 33.6 | BE23: 21.8 | BF23: 0.6 | BG23: 52.2 | BH23: 74.7 | BI23: 15.2 | BJ23: 23.6 | BK23: 69 | BL23: 4.3 | BM23: 1.2 | BN23: 2.2 | BO23: 1.2 | BP23: 7.9 | BQ23: 1.1 | BR23: 10 | BS23: 5.7 | BT23: 16.7 | BU23: 10.1 | BV23: 1378.073
B24: 8:30 | E24: 7.7 | F24: 11.1 | G24: 5.8 | H24: 2.8 | J24: 8.7 | K24: 15.8 | L24: 4.5 | M24: 0.255 | N24: 0.6 | O24: 4.8 | Q24: 11.1 | R24: 15 | S24: 7.9 | T24: 2.4 | U24: 4 | V24: 17.6 | W24: 20.2 | X24: 11.1 | Y24: 13.5 | Z24: 41 | AA24: 25.3 | AB24: 112 | AD24: 17.4 | AE24: 32.3 | AF24: 26.14 | AG24: 9.3 | AH24: 3.1 | AI24: 20.4 | AJ24: 20.4 | AK24: 20.1 | AL24: 8.5 | AM24: 78.7 | AN24: 0.7 | AO24: 0.4 | AP24: 2.2 | AQ24: 17.1 | AT24: 251.4 | AV24: 202.7 | AW24: 0.2 | AX24: 1.7 | AY24: 10.6 | BA24: 11.3 | BB24: 5.3 | BC24: 9.9 | BD24: 25.3 | BE24: 25.4 | BF24: 0.6 | BG24: 108.7 | BH24: 147.3 | BI24: 14.5 | BJ24: 23.3 | BK24: 67.1 | BL24: 4.3 | BM24: 1.2 | BN24: 2.2 | BO24: 1.2 | BP24: 10.6 | BQ24: 1 | BR24: 10 | BS24: 5.7 | BT24: 11.1 | BU24: 10.1 | BV24: 1562.595
B25: 9:00 | E25: 8.7 | F25: 11.1 | G25: 10 | H25: 2.8 | J25: 8.3 | K25: 13.6 | L25: 4.4 | M25: 0.291 | N25: 0.8 | O25: 4.8 | Q25: 10.5 | R25: 14.9 | S25: 7.9 | T25: 2.4 | U25: 3.9 | V25: 17.2 | W25: 19.6 | X25: 11.1 | Y25: 13.5 | Z25: 31.9 | AA25: 22.1 | AB25: 111.2 | AD25: 21.3 | AE25: 18.4 | AF25: 42.38 | AG25: 9.3 | AH25: 3.1 | AI25: 20.4 | AJ25: 20.4 | AK25: 20.1 | AL25: 8.4 | AM25: 80.6 | AN25: 0.8 | AO25: 1.3 | AP25: 2.2 | AQ25: 17.1 | AT25: 253 | AV25: 211.5 | AW25: 0.2 | AX25: 1.7 | AY25: 12.5 | BA25: 12.1 | BB25: 5.1 | BC25: 9.9 | BD25: 19.6 | BE25: 16.1 | BF25: 0.6 | BG25: 108.8 | BH25: 142.7 | BI25: 14.9 | BJ25: 24.4 | BK25: 66.1 | BL25: 4.3 | BM25: 1.2 | BN25: 2.2 | BO25: 1.2 | BP25: 12.4 | BQ25: 1 | BR25: 10 | BS25: 5.7 | BT25: 9.2 | BU25: 20 | BV25: 1563.171
B26: 9:30 | E26: 8.7 | F26: 11.1 | G26: 18.1 | H26: 2.8 | J26: 8.7 | K26: 14.4 | L26: 4.4 | M26: 0.33 | N26: 0.9 | O26: 4.7 | Q26: 11.1 | R26: 15.1 | S26: 7.9 | T26: 2.4 | U26: 4.1 | V26: 17 | W26: 20.1 | X26: 11.1 | Y26: 13.6 | Z26: 25.2 | AA26: 22.6 | AB26: 106.5 | AD26: 37.8 | AE26: 36.4 | AF26: 27.62 | AG26: 9.3 | AH26: 3.1 | AI26: 20.4 | AJ26: 20.4 | AK26: 20.1 | AL26: 8.2 | AM26: 80.8 | AN26: 2.9 | AO26: 2.6 | AP26: 2.2 | AQ26: 17.1 | AT26: 252.9 | AV26: 220.9 | AW26: 0.3 | AX26: 1.7 | AY26: 14.3 | BA26: 13.5 | BB26: 5.2 | BC26: 9.9 | BD26: 22.8 | BE26: 15.2 | BF26: 0.6 | BG26: 104.8 | BH26: 143.3 | BI26: 16.2 | BJ26: 25.8 | BK26: 73.7 | BL26: 4.3 | BM26: 1.2 | BN26: 2.2 | BO26: 1.2 | BP26: 14.4 | BQ26: 1 | BR26: 10 | BS26: 5.7 | BT26: 10.3 | BU26: 20.2 | BV26: 1611.35
B27: 10:00 | E27: 8.5 | F27: 11 | G27: 18.2 | H27: 2.8 | J27: 9.1 | K27: 17.4 | L27: 4.4 | M27: 0.345 | N27: 1 | O27: 4.7 | Q27: 10.7 | R27: 14.9 | S27: 7.9 | T27: 2.4 | U27: 4.4 | V27: 17 | W27: 19.9 | X27: 11.1 | Y27: 13.7 | Z27: 29.9 | AA27: 24 | AB27: 104.7 | AC27: 0.4 | AD27: 71.4 | AE27: 40.4 | AF27: 49.28 | AG27: 9.3 | AH27: 3.1 | AI27: 20.4 | AJ27: 20.4 | AK27: 20.1 | AL27: 8.5 | AM27: 80.8 | AN27: 3.8 | AO27: 4.4 | AP27: 2.2 | AQ27: 17.1 | AT27: 252.9 | AV27: 211.2 | AW27: 0.3 | AX27: 1.7 | AY27: 15.6 | BA27: 13.1 | BB27: 5.3 | BC27: 9.9 | BD27: 21.4 | BE27: 20 | BF27: 0.6 | BG27: 108 | BH27: 143.6 | BI27: 16.4 | BJ27: 26.1 | BK27: 76.4 | BL27: 4.3 | BM27: 1.2 | BN27: 2.2 | BO27: 1.2 | BP27: 15.6 | BQ27: 1 | BR27: 10 | BS27: 5.7 | BT27: 17.5 | BU27: 20.1 | BV27: 1690.925
B28: 10:30 | E28: 9.3 | F28: 11.1 | G28: 18.2 | H28: 2.8 | J28: 8.9 | K28: 17.7 | L28: 4.5 | M28: 0.354 | N28: 1.1 | O28: 4.6 | Q28: 10.8 | R28: 14.9 | S28: 7.9 | T28: 2.4 | U28: 4.4 | V28: 17.2 | W28: 20 | X28: 11.1 | Y28: 13.8 | Z28: 29.8 | AA28: 25 | AB28: 110.4 | AC28: 3.8 | AD28: 110.5 | AE28: 40.4 | AF28: 50 | AG28: 9.3 | AH28: 3.1 | AI28: 20.4 | AJ28: 20.4 | AK28: 20.1 | AL28: 8.5 | AM28: 80.8 | AN28: 5.7 | AO28: 4.5 | AP28: 2.2 | AQ28: 17.1 | AT28: 176.1 | AV28: 226.1 | AW28: 0.4 | AX28: 1.7 | AY28: 16.8 | BA28: 11.9 | BB28: 5.5 | BC28: 10.1 | BD28: 41.5 | BE28: 20.7 | BF28: 0.6 | BG28: 111.3 | BH28: 144.4 | BI28: 15.9 | BJ28: 25 | BK28: 81.7 | BL28: 4.3 | BM28: 1.2 | BN28: 2.2 | BO28: 1.2 | BP28: 12.3 | BQ28: 1.2 | BR28: 10.1 | BS28: 5.7 | BT28: 19.7 | BU28: 20.1 | BV28: 1710.754
B29: 11:00 | E29: 9.5 | F29: 11.1 | G29: 18.2 | H29: 2.8 | J29: 9.1 | K29: 18.9 | L29: 4.7 | M29: 0.356 | N29: 1.2 | O29: 4.6 | Q29: 11.2 | R29: 15.2 | S29: 7.9 | T29: 2.4 | U29: 4.4 | V29: 17 | W29: 20.4 | X29: 11.1 | Y29: 13.6 | Z29: 35.9 | AA29: 23.4 | AB29: 99.3 | AC29: 8.1 | AD29: 153.9 | AE29: 39 | AF29: 50 | AG29: 9.2 | AH29: 3.1 | AI29: 20.4 | AJ29: 20.4 | AK29: 20.1 | AL29: 8.1 | AM29: 80.8 | AN29: 5.1 | AO29: 6.4 | AP29: 2.3 | AQ29: 17.1 | AT29: 208.3 | AV29: 185.9 | AW29: 0.4 | AX29: 1.7 | AY29: 17.2 | BA29: 13.6 | BB29: 5.5 | BC29: 10 | BD29: 50 | BE29: 43.5 | BF29: 0.6 | BG29: 111.3 | BH29: 144.7 | BI29: 16.6 | BJ29: 22.9 | BK29: 72.7 | BL29: 4.2 | BM29: 1.2 | BN29: 2.2 | BO29: 1.2 | BP29: 13.8 | BQ29: 1.2 | BR29: 10 | BS29: 5.8 | BT29: 19.4 | BU29: 20.4 | BV29: 1770.556
B30: 11:30 | E30: 7.1 | F30: 11.1 | G30: 18.1 | H30: 2.8 | J30: 9.1 | K30: 18.6 | L30: 4.7 | M30: 0.357 | N30: 1.2 | O30: 4.6 | Q30: 11 | R30: 15 | S30: 7.9 | T30: 2.4 | U30: 4.3 | V30: 17 | W30: 19.9 | X30: 11.1 | Y30: 13.8 | Z30: 36.6 | AA30: 26.6 | AB30: 105.8 | AC30: 19.6 | AD30: 187.5 | AE30: 37.9 | AF30: 50 | AG30: 9.1 | AH30: 3 | AI30: 20.4 | AJ30: 20.4 | AK30: 20.1 | AL30: 8.1 | AM30: 80.8 | AN30: 6 | AO30: 9.1 | AP30: 2.3 | AQ30: 17.1 | AT30: 190.6 | AV30: 158 | AW30: 0.4 | AX30: 1.7 | AY30: 18 | BA30: 11.4 | BB30: 5.5 | BC30: 9.9 | BD30: 63.3 | BE30: 52.5 | BF30: 0.6 | BG30: 111.7 | BH30: 145.6 | BI30: 14.7 | BJ30: 24.4 | BK30: 75.3 | BL30: 4.2 | BM30: 1.2 | BN30: 2.2 | BO30: 1.2 | BP30: 10.8 | BQ30: 1.2 | BR30: 10 | BS30: 5.7 | BT30: 18.2 | BU30: 20.1 | BV30: 1798.857
B31: 12:00 | E31: 8.9 | F31: 11.1 | G31: 18.1 | H31: 2.8 | J31: 9.2 | K31: 18 | L31: 4.7 | M31: 0.362 | N31: 1.2 | O31: 4.6 | Q31: 10.1 | R31: 14.6 | S31: 7.9 | T31: 2.4 | U31: 4.3 | V31: 17 | W31: 19.6 | X31: 11.1 | Y31: 13.6 | Z31: 36 | AA31: 28.5 | AB31: 102.7 | AC31: 25.3 | AD31: 196 | AE31: 39.5 | AF31: 50 | AG31: 9.1 | AH31: 2.9 | AI31: 20.4 | AJ31: 20.4 | AK31: 20.1 | AL31: 8.1 | AM31: 80.9 | AN31: 4.8 | AO31: 7.3 | AP31: 2.3 | AQ31: 17.1 | AT31: 253.2 | AV31: 230.8 | AW31: 0.4 | AX31: 1.7 | AY31: 18.2 | BA31: 14.1 | BB31: 5.6 | BC31: 9.8 | BD31: 79.7 | BE31: 66.9 | BF31: 0.6 | BG31: 110.1 | BH31: 141.6 | BI31: 17.9 | BJ31: 23.9 | BK31: 77 | BL31: 4.2 | BM31: 1.2 | BN31: 2.2 | BO31: 1.2 | BP31: 12.5 | BQ31: 1.2 | BR31: 10 | BS31: 5.8 | BT31: 17.9 | BU31: 19.8 | BV31: 1978.462
B32: 12:30 | E32: 9.8 | F32: 11.1 | G32: 18.2 | H32: 2.8 | J32: 9.3 | K32: 18.7 | L32: 4.6 | M32: 0.363 | N32: 1.2 | O32: 4.5 | Q32: 10.9 | R32: 15 | S32: 7.9 | T32: 2.4 | U32: 4.3 | V32: 17.2 | W32: 19.9 | X32: 11 | Y32: 13.6 | Z32: 47.1 | AA32: 29.7 | AB32: 101.9 | AC32: 25.9 | AD32: 201.8 | AE32: 40.1 | AF32: 50 | AG32: 9.1 | AH32: 2.9 | AI32: 20.4 | AJ32: 20.4 | AK32: 20.1 | AL32: 8.2 | AM32: 80.8 | AN32: 3.4 | AO32: 8.9 | AP32: 2.3 | AQ32: 17.1 | AT32: 252.8 | AV32: 217.8 | AW32: 0.4 | AX32: 1.7 | AY32: 18.3 | BA32: 14.7 | BB32: 5.4 | BC32: 9.9 | BD32: 82 | BE32: 64.3 | BF32: 0.6 | BG32: 112.7 | BH32: 148.1 | BI32: 18.6 | BJ32: 24.2 | BK32: 77.3 | BL32: 4.2 | BM32: 1.2 | BN32: 2.2 | BO32: 1.2 | BP32: 14.5 | BQ32: 1.2 | BR32: 10.1 | BS32: 5.7 | BT32: 18.7 | BU32: 19.6 | BV32: 2000.263
B33: 13:00 | E33: 6.9 | F33: 11.1 | G33: 18.2 | H33: 2.9 | J33: 8.8 | K33: 18.8 | L33: 4.5 | M33: 0.36 | N33: 1.2 | O33: 4.5 | Q33: 11.2 | R33: 15.2 | S33: 7.9 | T33: 2.4 | U33: 4.4 | V33: 17 | W33: 20.2 | X33: 10.6 | Y33: 13.7 | Z33: 55.3 | AA33: 29.9 | AB33: 98.9 | AC33: 25.4 | AD33: 192.1 | AE33: 40.4 | AF33: 50 | AG33: 9.1 | AH33: 2.9 | AI33: 20.4 | AJ33: 20.4 | AK33: 20.1 | AL33: 8.2 | AM33: 80.7 | AN33: 4.4 | AO33: 5.4 | AP33: 2.3 | AQ33: 17.1 | AT33: 201.4 | AV33: 233.2 | AW33: 0.4 | AX33: 1.7 | AY33: 14.6 | BA33: 14.6 | BB33: 5.6 | BC33: 9.9 | BD33: 94.1 | BE33: 82.2 | BF33: 0.6 | BG33: 112.6 | BH33: 147.9 | BI33: 18.4 | BJ33: 26.2 | BK33: 76.3 | BL33: 4.2 | BM33: 1.2 | BN33: 2.2 | BO33: 1.2 | BP33: 17.9 | BQ33: 1.2 | BR33: 10 | BS33: 5.7 | BT33: 16.9 | BU33: 19.1 | BV33: 1982.16
B34: 13:30 | E34: 6.7 | F34: 11.1 | G34: 14.3 | H34: 3 | J34: 9.2 | K34: 18.4 | L34: 4.5 | M34: 0.358 | N34: 1.1 | O34: 4.5 | Q34: 10.3 | R34: 14.6 | S34: 7.7 | T34: 2.4 | U34: 4.4 | V34: 16.8 | W34: 19.8 | X34: 10.5 | Y34: 13.6 | Z34: 64 | AA34: 30.3 | AB34: 100.5 | AC34: 22.2 | AD34: 198 | AE34: 40.4 | AF34: 50 | AG34: 9.2 | AH34: 2.9 | AI34: 20.4 | AJ34: 20.4 | AK34: 20.1 | AL34: 8.2 | AM34: 80.8 | AN34: 3.2 | AO34: 2.7 | AP34: 2.3 | AQ34: 17.1 | AT34: 253 | AV34: 225.7 | AW34: 0.4 | AX34: 1.7 | AY34: 16.9 | BA34: 14.5 | BB34: 5.6 | BC34: 9.9 | BD34: 102.8 | BE34: 93.6 | BF34: 0.6 | BG34: 107.7 | BH34: 145.7 | BI34: 17.9 | BJ34: 25.5 | BK34: 70.5 | BL34: 4.2 | BM34: 1.2 | BN34: 2.2 | BO34: 1.2 | BP34: 16.8 | BQ34: 1.2 | BR34: 10 | BS34: 5.8 | BT34: 14.9 | BU34: 18.4 | BV34: 2033.858
B35: 14:00 | E35: 9 | F35: 11 | G35: 12.1 | H35: 3 | J35: 9 | K35: 18.8 | L35: 4.5 | M35: 0.354 | N35: 1.1 | O35: 4.3 | Q35: 10.9 | R35: 15.1 | S35: 7.7 | T35: 2.4 | U35: 4.3 | V35: 16.6 | W35: 20.4 | X35: 10.2 | Y35: 13.6 | Z35: 62.8 | AA35: 30.2 | AB35: 96.4 | AC35: 20 | AD35: 194.1 | AE35: 40 | AF35: 50 | AG35: 9.2 | AH35: 2.9 | AI35: 20.4 | AJ35: 20.4 | AK35: 20.1 | AL35: 8.4 | AM35: 80.7 | AN35: 2.2 | AO35: 3.3 | AP35: 2.3 | AQ35: 17.1 | AT35: 253.1 | AV35: 223.1 | AW35: 0.4 | AX35: 1.7 | AY35: 16.1 | BA35: 14.2 | BB35: 5.5 | BC35: 10 | BD35: 103.2 | BE35: 97.8 | BF35: 0.6 | BG35: 107 | BH35: 139.5 | BI35: 17.8 | BJ35: 26.5 | BK35: 75.7 | BL35: 4.2 | BM35: 1.2 | BN35: 2.1 | BO35: 1.2 | BP35: 15.9 | BQ35: 1.2 | BR35: 10 | BS35: 5.8 | BT35: 18.4 | BU35: 19.2 | BV35: 2026.254
B36: 14:30 | E36: 9.6 | F36: 11.1 | G36: 12.1 | H36: 3 | J36: 9.2 | K36: 19 | L36: 4.4 | M36: 0.343 | N36: 1 | O36: 4.1 | Q36: 11 | R36: 15.2 | S36: 7.7 | T36: 2.4 | U36: 4.2 | V36: 16.6 | W36: 20.5 | X36: 9.2 | Y36: 13.7 | Z36: 60.4 | AA36: 29.9 | AB36: 95.8 | AC36: 18.4 | AD36: 192.6 | AE36: 33.1 | AF36: 50 | AG36: 9.3 | AH36: 2.9 | AI36: 20.4 | AJ36: 20.4 | AK36: 20.1 | AL36: 8.4 | AM36: 80.7 | AN36: 1.9 | AO36: 1.8 | AP36: 2.3 | AQ36: 17.1 | AT36: 253.1 | AV36: 218.6 | AW36: 0.4 | AX36: 1.7 | AY36: 14.7 | BA36: 14.2 | BB36: 5.3 | BC36: 9.9 | BD36: 115.5 | BE36: 102.5 | BF36: 0.6 | BG36: 85.8 | BH36: 107.8 | BI36: 17.6 | BJ36: 26.1 | BK36: 73.4 | BL36: 4.2 | BM36: 1.2 | BN36: 2.2 | BO36: 1.2 | BP36: 14.4 | BQ36: 1.2 | BR36: 10 | BS36: 5.7 | BT36: 19.6 | BU36: 16.5 | BV36: 1963.243
B37: 15:00 | E37: 9 | F37: 11.1 | G37: 12.1 | H37: 3 | J37: 8.7 | K37: 18.6 | L37: 4.2 | M37: 0.316 | N37: 0.9 | O37: 4.1 | Q37: 11.1 | R37: 15.2 | S37: 7.7 | T37: 2.4 | U37: 4.3 | V37: 16.6 | W37: 20 | X37: 10 | Y37: 13.7 | Z37: 66.2 | AA37: 29.6 | AB37: 100 | AC37: 16.6 | AD37: 179.1 | AE37: 18.4 | AF37: 47.01 | AG37: 9.3 | AH37: 2.9 | AI37: 20.4 | AJ37: 20.4 | AK37: 20.1 | AL37: 8.3 | AM37: 80.8 | AO37: 0.1 | AP37: 2.3 | AQ37: 17.1 | AT37: 252.9 | AV37: 215.8 | AW37: 0.4 | AX37: 1.7 | AY37: 13.7 | BA37: 13.7 | BB37: 4.5 | BC37: 10 | BD37: 106.1 | BE37: 110.4 | BF37: 0.6 | BG37: 104.1 | BH37: 143.5 | BI37: 17.2 | BJ37: 24.7 | BK37: 72.4 | BL37: 4.2 | BM37: 1.2 | BN37: 2.2 | BO37: 1.2 | BP37: 12.9 | BQ37: 1.2 | BR37: 10 | BS37: 5.7 | BT37: 18.8 | BU37: 15.4 | BV37: 1976.126
B38: 15:30 | E38: 7.2 | F38: 11.1 | G38: 12.1 | H38: 3 | J38: 9.2 | K38: 18.6 | L38: 4.3 | M38: 0.267 | N38: 0.6 | O38: 4.1 | Q38: 10.8 | R38: 15.1 | S38: 7.7 | T38: 2.4 | U38: 4.3 | V38: 16.8 | W38: 19.9 | X38: 10 | Y38: 13.8 | Z38: 71.4 | AA38: 30.2 | AB38: 104.4 | AC38: 24.7 | AD38: 169.3 | AE38: 17.6 | AF38: 27.16 | AG38: 9.3 | AH38: 2.8 | AI38: 20.4 | AJ38: 20.4 | AK38: 20.1 | AL38: 8.1 | AM38: 32.4 | AN38: 4.1 | AO38: 1 | AP38: 2.4 | AQ38: 17.1 | AT38: 244.2 | AV38: 218.3 | AW38: 0.3 | AX38: 1.7 | AY38: 11.3 | BA38: 13.4 | BB38: 4.7 | BC38: 9.9 | BD38: 131.6 | BE38: 118.2 | BF38: 0.6 | BG38: 69.5 | BH38: 91.2 | BI38: 17.7 | BJ38: 21.1 | BK38: 68.5 | BL38: 4.2 | BM38: 1.2 | BN38: 2.2 | BO38: 1.2 | BP38: 11.6 | BQ38: 1.1 | BR38: 10 | BS38: 5.7 | BT38: 18.1 | BU38: 15.8 | BV38: 1847.427
B39: 16:00 | E39: 7.7 | F39: 11 | G39: 12.1 | H39: 3 | J39: 9 | K39: 18.1 | L39: 4.2 | M39: 0.215 | N39: 0.6 | O39: 4.1 | Q39: 10.8 | R39: 15 | S39: 7.7 | T39: 2.4 | U39: 4.2 | V39: 16.9 | W39: 19.9 | X39: 10 | Y39: 13.7 | Z39: 71.8 | AA39: 29.7 | AB39: 108.2 | AC39: 18.5 | AD39: 166.8 | AE39: 17 | AF39: 30.1 | AG39: 9.3 | AH39: 2.8 | AI39: 20.4 | AJ39: 20.4 | AK39: 20.1 | AL39: 8.1 | AM39: 21 | AN39: 7.5 | AO39: 3 | AP39: 2.3 | AQ39: 17.1 | AT39: 224.7 | AV39: 143.9 | AW39: 0.2 | AX39: 1.6 | AY39: 9.6 | BA39: 12 | BB39: 4.7 | BC39: 9.9 | BD39: 119.1 | BE39: 123.1 | BF39: 0.6 | BG39: 39 | BH39: 56.1 | BI39: 13.5 | BJ39: 26 | BK39: 71.1 | BL39: 4.2 | BM39: 1.2 | BN39: 2.2 | BO39: 1.2 | BP39: 6.7 | BQ39: 1 | BR39: 10 | BS39: 5.6 | BT39: 14.6 | BU39: 14.7 | BV39: 1661.215
B40: 16:30 | E40: 8.8 | F40: 11.1 | G40: 11.9 | H40: 3 | J40: 8.8 | K40: 18.6 | L40: 4.3 | M40: 0.169 | N40: 0.4 | O40: 4.1 | Q40: 11.1 | R40: 14.9 | S40: 7.7 | T40: 2.4 | U40: 4.2 | V40: 16.6 | W40: 20.1 | X40: 10 | Y40: 13.6 | Z40: 75.6 | AA40: 30.3 | AB40: 101.8 | AC40: 19.8 | AD40: 178.3 | AE40: 10.9 | AF40: 26.93 | AG40: 9.3 | AH40: 2.8 | AI40: 20.4 | AJ40: 20.4 | AK40: 20.1 | AL40: 8.1 | AM40: 24.7 | AN40: 6.5 | AO40: 5 | AP40: 2.3 | AQ40: 17.1 | AT40: 205.8 | AV40: 198 | AW40: 0.2 | AX40: 1.6 | AY40: 5.7 | BA40: 7.9 | BB40: 4.5 | BC40: 9.9 | BD40: 128.4 | BE40: 125.5 | BF40: 0.6 | BG40: 39.4 | BH40: 56.4 | BI40: 10.3 | BJ40: 24.5 | BK40: 72.1 | BL40: 4.2 | BM40: 1.2 | BN40: 2.2 | BO40: 1.2 | BP40: 7.2 | BQ40: 0.9 | BR40: 9.9 | BS40: 5.7 | BT40: 4.5 | BU40: 14.5 | BV40: 1694.399
B41: 17:00 | E41: 7.7 | F41: 11.1 | G41: 12 | H41: 3 | J41: 8 | K41: 20.1 | L41: 4.3 | M41: 0.094 | N41: 0.3 | O41: 4.2 | Q41: 10.4 | R41: 14.8 | S41: 7.7 | T41: 2.4 | U41: 4.1 | V41: 16.6 | W41: 19.8 | X41: 10 | Y41: 13.6 | Z41: 76 | AA41: 30.2 | AB41: 93.8 | AC41: 18.6 | AD41: 191 | AE41: 4.1 | AF41: 17.92 | AG41: 9.3 | AH41: 2.8 | AI41: 20.4 | AJ41: 20.4 | AK41: 20.1 | AL41: 8.5 | AM41: 48.9 | AN41: 7.5 | AO41: 4.5 | AP41: 2.3 | AQ41: 17.1 | AT41: 122.6 | AV41: 169.4 | AW41: 0.1 | AX41: 1.6 | AY41: 5.4 | BA41: 7.5 | BB41: 4.7 | BC41: 9.9 | BD41: 107.3 | BE41: 127.1 | BF41: 0.6 | BG41: 49.7 | BH41: 54.9 | BI41: 9.3 | BJ41: 20.8 | BK41: 73 | BL41: 4.2 | BM41: 1.2 | BN41: 2.2 | BO41: 1.2 | BP41: 3.8 | BQ41: 0.9 | BR41: 10 | BS41: 5.7 | BT41: 2.2 | BU41: 13.9 | BV41: 1572.814
B42: 17:30 | E42: 9.6 | F42: 11.1 | G42: 12 | H42: 3 | J42: 9.2 | K42: 20.1 | L42: 4.3 | M42: 0.045 | N42: 0.1 | O42: 4.2 | Q42: 10.2 | R42: 15 | S42: 7.7 | T42: 2.4 | U42: 3.9 | V42: 16.2 | W42: 20.2 | X42: 10 | Y42: 13.8 | Z42: 78.3 | AA42: 30.2 | AB42: 103.6 | AC42: 18 | AD42: 191.5 | AE42: 2.9 | AF42: 6.2 | AG42: 9.4 | AH42: 2.8 | AI42: 20.4 | AJ42: 20.4 | AK42: 20.1 | AL42: 8.3 | AM42: 27.3 | AN42: 8.8 | AO42: 5.1 | AP42: 2.3 | AQ42: 17 | AT42: 81.2 | AV42: 48.2 | AW42: 0.1 | AX42: 1.6 | AY42: 2.4 | BA42: 2.2 | BB42: 4.7 | BC42: 9.9 | BD42: 102.4 | BE42: 125.5 | BF42: 0.6 | BG42: 16 | BH42: 19.4 | BI42: 2.5 | BJ42: 25 | BK42: 74.4 | BL42: 4.2 | BM42: 1.2 | BN42: 2.2 | BO42: 1.2 | BP42: 1.8 | BQ42: 1.1 | BR42: 9.9 | BS42: 5.7 | BU42: 12.9 | BV42: 1301.945
B43: 18:00 | E43: 8.6 | F43: 11.1 | G43: 16 | H43: 3.1 | J43: 8.9 | K43: 20.5 | L43: 4.1 | M43: 0.016 | N43: 0.1 | O43: 4.2 | Q43: 10.1 | R43: 14.3 | S43: 7.7 | T43: 2.3 | U43: 3.8 | V43: 16.4 | W43: 20.2 | X43: 10 | Y43: 13.6 | Z43: 79.6 | AA43: 30.1 | AB43: 110.9 | AC43: 14.4 | AD43: 179.6 | AE43: 0.5 | AF43: 4.5 | AG43: 9.4 | AH43: 2.8 | AI43: 20.4 | AJ43: 20.4 | AK43: 20.1 | AL43: 8.4 | AM43: 6 | AN43: 8.6 | AO43: 4.6 | AP43: 2.4 | AQ43: 17.1 | AT43: 25.5 | AV43: 12.2 | AX43: 1.7 | AY43: 0.5 | BA43: 0.1 | BB43: 4.8 | BC43: 10 | BD43: 93 | BE43: 123.8 | BF43: 0.6 | BG43: 5.8 | BH43: 5.9 | BJ43: 25 | BK43: 76.4 | BL43: 4.2 | BM43: 1.2 | BN43: 2.2 | BO43: 1.2 | BP43: 0.8 | BQ43: 1.2 | BR43: 10 | BS43: 5.7 | BU43: 12.3 | BV43: 1138.916
B44: 18:30 | E44: 8.8 | F44: 11.1 | G44: 20.2 | H44: 3 | J44: 8.8 | K44: 20.5 | L44: 4.1 | M44: 0.004 | O44: 4.1 | Q44: 10.1 | R44: 14.3 | S44: 7.7 | T44: 2.3 | U44: 4.3 | V44: 16.2 | W44: 20.5 | X44: 10 | Y44: 13.8 | Z44: 77.8 | AA44: 29.8 | AB44: 112.3 | AC44: 8 | AD44: 183.7 | AF44: 0.81 | AG44: 9.4 | AH44: 2.8 | AI44: 20.4 | AJ44: 20.4 | AK44: 20.1 | AL44: 8.9 | AP44: 2.3 | AQ44: 17.1 | AV44: 0.4 | AX44: 1.7 | BB44: 4.8 | BC44: 9.9 | BD44: 110.5 | BE44: 123.3 | BF44: 0.6 | BJ44: 27.3 | BK44: 83.3 | BL44: 4.3 | BM44: 1.2 | BN44: 2.2 | BO44: 1.2 | BQ44: 1.2 | BR44: 10 | BS44: 5.7 | BU44: 11.8 | BV44: 1093.014
B45: 19:00 | E45: 8.1 | F45: 11.1 | G45: 20.2 | H45: 3.1 | J45: 9.3 | K45: 20.2 | L45: 4.1 | O45: 4.1 | Q45: 10 | R45: 14.3 | S45: 7.7 | T45: 2.3 | U45: 4.3 | V45: 16.4 | W45: 20.3 | X45: 10 | Y45: 13.6 | Z45: 77.7 | AA45: 29 | AB45: 99.7 | AC45: 7.7 | AD45: 171.8 | AG45: 9.4 | AH45: 2.8 | AI45: 20.4 | AJ45: 20.4 | AK45: 20.1 | AL45: 8.7 | AP45: 2.4 | AQ45: 17.1 | AX45: 1.7 | BB45: 5.4 | BC45: 9.9 | BD45: 121.7 | BE45: 121.6 | BF45: 0.6 | BJ45: 27.7 | BK45: 82.2 | BL45: 4.3 | BM45: 1.2 | BN45: 2.2 | BO45: 1.2 | BQ45: 1.2 | BR45: 10 | BS45: 5.8 | BU45: 10.7 | BV45: 1073.7
B46: 19:30 | E46: 8.9 | F46: 11.1 | G46: 20.2 | H46: 3 | J46: 8.8 | K46: 20.1 | L46: 4.1 | O46: 4.1 | Q46: 9.9 | R46: 14.2 | S46: 7.7 | T46: 2.3 | U46: 4.2 | V46: 16.6 | W46: 20.2 | X46: 10 | Y46: 13.6 | Z46: 68 | AA46: 28.1 | AB46: 93.7 | AC46: 8.6 | AD46: 170 | AG46: 9.4 | AH46: 2.8 | AI46: 20.4 | AJ46: 20.4 | AK46: 20.1 | AL46: 8.4 | AP46: 2.3 | AQ46: 17 | AX46: 1.7 | BB46: 5.4 | BC46: 9.9 | BD46: 95.1 | BE46: 115.1 | BF46: 0.6 | BJ46: 27.5 | BK46: 81.7 | BL46: 4.3 | BM46: 1.2 | BN46: 2.2 | BO46: 1.2 | BQ46: 1.2 | BR46: 10.1 | BS46: 5.7 | BU46: 10.9 | BV46: 1022
B47: 20:00 | E47: 8.4 | F47: 11.1 | G47: 20.2 | H47: 3 | J47: 8.5 | K47: 20.2 | L47: 4.1 | O47: 4.1 | Q47: 9.8 | R47: 14.1 | S47: 7.7 | T47: 2.3 | U47: 4.2 | V47: 16.6 | W47: 20.2 | X47: 10 | Y47: 13.6 | Z47: 61.2 | AA47: 26.3 | AB47: 99.3 | AC47: 3.5 | AD47: 147 | AG47: 9.4 | AH47: 2.8 | AI47: 20.4 | AJ47: 20.4 | AK47: 20.1 | AL47: 8.3 | AP47: 2.3 | AQ47: 16.9 | AX47: 1.7 | BB47: 5.5 | BC47: 10 | BD47: 78.4 | BE47: 87.6 | BF47: 0.6 | BJ47: 26.8 | BK47: 79.2 | BL47: 4.3 | BM47: 1.2 | BN47: 2.2 | BO47: 1.2 | BQ47: 1.2 | BR47: 10 | BS47: 5.7 | BU47: 10.5 | BV47: 942.1
B48: 20:30 | E48: 8.5 | F48: 11.1 | G48: 20.2 | H48: 3.1 | J48: 8.9 | K48: 17.8 | L48: 4.3 | O48: 4.1 | Q48: 10 | R48: 14.1 | S48: 7.8 | T48: 2.3 | U48: 4.2 | V48: 16.2 | W48: 20.5 | X48: 10 | Y48: 13.6 | Z48: 49.4 | AA48: 26.1 | AB48: 98 | AC48: 4.8 | AD48: 139.4 | AG48: 9.3 | AH48: 2.8 | AI48: 20.4 | AJ48: 20.4 | AK48: 20.1 | AL48: 8.3 | AP48: 2.3 | AQ48: 16.9 | AX48: 1.7 | BB48: 5.6 | BC48: 10 | BD48: 53.2 | BE48: 55.2 | BF48: 0.6 | BJ48: 24.1 | BK48: 75.2 | BL48: 4.3 | BM48: 1.2 | BN48: 2.2 | BO48: 1.2 | BQ48: 1.2 | BR48: 10 | BS48: 5.7 | BU48: 10.2 | BV48: 856.5
B49: 21:00 | E49: 8 | F49: 11.1 | G49: 20.2 | H49: 3 | J49: 8.5 | K49: 20.3 | L49: 4.3 | O49: 4.1 | Q49: 9.9 | R49: 13.7 | S49: 7.9 | T49: 2.3 | U49: 4.2 | V49: 16.2 | W49: 20.2 | X49: 10 | Y49: 13.7 | Z49: 29.6 | AA49: 27.4 | AB49: 99.1 | AC49: 3.2 | AD49: 123.6 | AG49: 9.1 | AH49: 2.8 | AI49: 20.4 | AJ49: 20.4 | AK49: 20.1 | AL49: 8.5 | AP49: 2.3 | AQ49: 16.9 | AX49: 1.7 | BB49: 5.4 | BC49: 10 | BD49: 38.4 | BE49: 50 | BF49: 0.6 | BJ49: 24 | BK49: 65.4 | BL49: 4.3 | BM49: 1.2 | BN49: 2.2 | BO49: 1.2 | BQ49: 1.2 | BR49: 10 | BS49: 5.7 | BU49: 10 | BV49: 792.3
B50: 21:30 | E50: 7.8 | F50: 11.1 | G50: 20.2 | H50: 3 | J50: 8.3 | K50: 14.3 | L50: 4.2 | O50: 4.1 | Q50: 10 | R50: 13.9 | S50: 7.9 | T50: 2.3 | U50: 4.2 | V50: 16.2 | W50: 20.4 | X50: 9.6 | Y50: 13.6 | Z50: 13.8 | AA50: 22.9 | AB50: 103 | AC50: 3.1 | AD50: 106.5 | AG50: 9.1 | AH50: 2.8 | AI50: 20.4 | AJ50: 20.4 | AK50: 20.1 | AL50: 8.5 | AP50: 2.3 | AQ50: 16.9 | AX50: 1.7 | BB50: 5.6 | BC50: 9.8 | BD50: 36.4 | BE50: 35.8 | BF50: 0.6 | BJ50: 23.2 | BK50: 57.8 | BL50: 4.3 | BM50: 1.2 | BN50: 2.2 | BO50: 1.2 | BQ50: 1.2 | BR50: 10 | BS50: 5.7 | BU50: 9.3 | BV50: 726.9
B51: 22:00 | E51: 7.6 | F51: 11.2 | G51: 20.2 | H51: 3 | J51: 9 | K51: 20.2 | L51: 4.2 | O51: 4.1 | Q51: 9.9 | R51: 13.8 | S51: 8.2 | T51: 2.1 | U51: 4 | V51: 16.2 | W51: 20.3 | X51: 9.1 | Y51: 13.6 | Z51: 17.4 | AA51: 17.5 | AB51: 102.8 | AC51: 3.7 | AD51: 103.7 | AG51: 9.1 | AH51: 2.8 | AI51: 20.4 | AJ51: 20.4 | AK51: 20.1 | AL51: 8.7 | AP51: 2.3 | AQ51: 16.9 | AX51: 1.7 | BB51: 5.6 | BC51: 9.9 | BD51: 33 | BE51: 26.4 | BF51: 0.6 | BJ51: 21.9 | BK51: 61.4 | BL51: 4.3 | BM51: 1.2 | BN51: 2.2 | BO51: 1.2 | BQ51: 1.2 | BR51: 10 | BS51: 5.7 | BU51: 8.6 | BV51: 717.4
B52: 22:30 | E52: 6.4 | F52: 11.2 | G52: 20.2 | H52: 3 | J52: 9.3 | K52: 16.7 | L52: 4.2 | O52: 4.1 | Q52: 10 | R52: 13.8 | S52: 8.3 | T52: 2 | U52: 4 | V52: 16.2 | W52: 20.6 | X52: 9.1 | Y52: 13.7 | Z52: 14.5 | AA52: 17.3 | AB52: 105.7 | AC52: 3.3 | AD52: 96 | AG52: 9.1 | AH52: 2.8 | AI52: 20.4 | AJ52: 20.4 | AK52: 20.1 | AL52: 8.7 | AP52: 2.3 | AQ52: 17 | AX52: 1.7 | BB52: 5.6 | BC52: 9.9 | BD52: 22 | BE52: 21.1 | BF52: 0.6 | BJ52: 27 | BK52: 65 | BL52: 4.3 | BM52: 1.2 | BN52: 2.2 | BO52: 1.2 | BQ52: 1.2 | BR52: 10 | BS52: 5.7 | BU52: 8.6 | BV52: 697.7
B53: 23:00 | E53: 6 | F53: 11.2 | G53: 20.2 | H53: 3 | J53: 8.9 | K53: 20.6 | L53: 4.2 | O53: 4.1 | Q53: 10.4 | R53: 13.8 | S53: 8.4 | T53: 2 | U53: 4 | V53: 16.2 | W53: 20.3 | X53: 9.1 | Y53: 13.5 | Z53: 15.6 | AA53: 18.5 | AB53: 114 | AC53: 3 | AD53: 89.2 | AG53: 9.1 | AH53: 2.8 | AI53: 20.4 | AJ53: 20.4 | AK53: 20.1 | AL53: 8.5 | AP53: 2.3 | AQ53: 17 | AX53: 1.7 | BB53: 5.5 | BC53: 9.9 | BD53: 15.7 | BE53: 15.1 | BF53: 0.6 | BJ53: 29.1 | BK53: 68.5 | BL53: 4.3 | BM53: 1.2 | BN53: 2.2 | BO53: 1.2 | BQ53: 1.2 | BR53: 10 | BS53: 5.7 | BU53: 8.6 | BV53: 697.3
B54: 23:30 | E54: 7.9 | F54: 11.2 | G54: 20.2 | H54: 3 | J54: 8.8 | K54: 20.5 | L54: 4.2 | O54: 4.5 | Q54: 10.7 | R54: 13.6 | S54: 8.4 | T54: 2.1 | U54: 3.8 | V54: 16.6 | W54: 20 | X54: 9.2 | Y54: 13.1 | Z54: 17.2 | AA54: 18.2 | AB54: 117 | AC54: 3.8 | AD54: 82.3 | AG54: 9.1 | AH54: 2.8 | AI54: 20.4 | AJ54: 20.4 | AK54: 20.1 | AL54: 8.5 | AP54: 2.4 | AQ54: 17 | AX54: 1.7 | BB54: 5.6 | BC54: 9.9 | BD54: 18.1 | BE54: 17.2 | BF54: 0.6 | BJ54: 29.9 | BK54: 68.5 | BL54: 4.3 | BM54: 1.2 | BN54: 2.2 | BO54: 1.2 | BQ54: 1.2 | BR54: 10 | BS54: 5.8 | BU54: 9 | BV54: 703.4
B55: 0:00 | E55: 8.6 | F55: 11.2 | G55: 19.9 | H55: 3 | J55: 8.9 | K55: 19.7 | L55: 4.2 | O55: 4.5 | Q55: 11.7 | R55: 13.9 | S55: 8.5 | T55: 2 | U55: 3.8 | V55: 16.4 | W55: 20.4 | X55: 9.2 | Y55: 13.2 | Z55: 15.3 | AA55: 18.8 | AB55: 117.2 | AC55: 4.1 | AD55: 28.7 | AG55: 9.1 | AH55: 2.8 | AI55: 20.4 | AJ55: 20.4 | AK55: 20.1 | AL55: 8.5 | AP55: 2.4 | AQ55: 17.1 | AX55: 1.7 | BB55: 5.5 | BC55: 9.9 | BD55: 17.9 | BE55: 19.8 | BF55: 0.6 | BJ55: 29.6 | BK55: 66.5 | BL55: 4.3 | BM55: 1.2 | BN55: 2.2 | BO55: 1.2 | BQ55: 1.2 | BR55: 10 | BS55: 5.8 | BU55: 8.8 | BV55: 650.2
B56: EJEC MWh | C56: 0 | D56: 0 | E56: 199.9 | F56: 266.35 | G56: 355.85 | H56: 70.75 | I56: 0 | J56: 211.35 | K56: 451 | L56: 104.55 | M56: 3.044 | N56: 8.45 | O56: 103.35 | P56: 0 | Q56: 258.25 | R56: 357.05 | S56: 191.45 | T56: 55.4 | U56: 99.45 | V56: 407.8 | W56: 473.55 | X56: 249.65 | Y56: 327.7 | Z56: 1148.35 | AA56: 623.25 | AB56: 2118.4 | AC56: 178.6 | AD56: 2364.45 | AE56: 296 | AF56: 394.335 | AG56: 220.9 | AH56: 69.35 | AI56: 489.6 | AJ56: 489.6 | AK56: 482.4 | AL56: 202.1 | AM56: 760.2 | AN56: 46.05 | AO56: 41.8 | AP56: 55.05 | AQ56: 410.2 | AR56: 0 | AS56: 0 | AT56: 2451.85 | AU56: 0 | AV56: 2163.9 | AW56: 3 | AX56: 40.1 | AY56: 136.7 | AZ56: 0 | BA56: 128.15 | BB56: 126.7 | BC56: 237.95 | BD56: 1164.45 | BE56: 1150.8 | BF56: 14.4 | BG56: 975.05 | BH56: 1264.25 | BI56: 161.25 | BJ56: 510.15 | BK56: 1387.8 | BL56: 102.45 | BM56: 28.8 | BN56: 52.75 | BO56: 28.8 | BP56: 123.1 | BQ56: 26.9 | BR56: 239.95 | BS56: 137.15 | BT56: 154.35 | BU56: 279.05 | BV56: 27675.329
L70: TERMOELÉCTRICA | M70: 1341.4 | N70: 4.8469162 | O70: #FFA975
L71: HIDROELÉCTRICA | M71: 6576.2 | N71: 23.761958 | O71: #98D2FF
L72: SOLAR | M72: 9023.629 | N72: 32.605318 | O72: #FFD272
L73: EÓLICA | M73: 10734.1 | N73: 38.785808 | O73: #B9ACFF

Sheet COGENERACIÓN
B3: sábado, 27 de Diciembre del 2025
B5: CENTRALES DE COGENERACIÓN DEL SEIN
B6: HORA | C6: AGRO INDUSTRIAL PARAMONGA S.A. | D6: AGROAURORA S.A.C. | E6: AGROINDUSTRIAS SAN JACINTO S.A.A. | F6: AGROLMOS SOCIEDAD ANONIMA - AGROLMOS S.A. | G6: BIOENERGIA DEL CHIRA S.A. | H6: CASA GRANDE S.A.A. | I6: GM OPERACIONES S.A.C. | J6: TOTAL COGENERACION
C7: C.T. PARAMONGA | D7: C.T. MAPLE | E7: C.T SAN JACINTO | F7: C.T. AGROLMOS | G7: C.T. CAÑA BRAVA | H7: C.T. CASA GRANDE | I7: C.T. REFINERÍA TALARA | J7: MW
B8: 0:30 | E8: 9.1 | F8: 11.1 | G8: 8.4 | H8: 19.1 | I8: 62.6 | J8: 110.3
B9: 1:00 | E9: 9 | F9: 11.1 | G9: 8.8 | H9: 19.5 | I9: 61.7 | J9: 110.1
B10: 1:30 | E10: 8.6 | F10: 11.1 | G10: 8.4 | H10: 20.1 | I10: 62.4 | J10: 110.6
B11: 2:00 | E11: 8.6 | F11: 11.1 | G11: 8.8 | H11: 19.4 | I11: 61.3 | J11: 109.2
B12: 2:30 | E12: 8.6 | F12: 11.1 | G12: 9.1 | H12: 19.1 | I12: 62 | J12: 109.9
B13: 3:00 | E13: 8.1 | F13: 11 | G13: 8.6 | H13: 19.5 | I13: 61.9 | J13: 109.1
B14: 3:30 | E14: 8.2 | F14: 11 | G14: 9.3 | H14: 19.8 | I14: 61.3 | J14: 109.6
B15: 4:00 | E15: 8 | F15: 11 | G15: 7.8 | H15: 19 | I15: 62 | J15: 107.8
B16: 4:30 | E16: 7 | F16: 11.1 | G16: 8.9 | H16: 18 | I16: 61.4 | J16: 106.4
B17: 5:00 | E17: 9 | F17: 11.1 | G17: 8.1 | H17: 19.7 | I17: 61.7 | J17: 109.6
B18: 5:30 | E18: 8.7 | F18: 11.1 | G18: 9 | H18: 18.8 | I18: 61 | J18: 108.6
B19: 6:00 | E19: 9.3 | F19: 11.1 | G19: 8.8 | H19: 19 | I19: 61 | J19: 109.2
... B55: 0:00 | E55: 8.6 | F55: 11.2 | G55: 8.9 | H55: 19.7 | I55: 61.9 | J55: 110.3
B56: EJEC MWh | C56: 0 | D56: 0 | E56: 199.9 | F56: 266.35 | G56: 211.35 | H56: 451 | I56: 1476.8 | J56: 2605.4

Sheet EVO_PRO_ENE
B3: lunes, 1 de Diciembre del 2025 - sábado, 27 de Diciembre del 2025
B5: EVOLUCIÓN DE LA PRODUCCIÓN DE LA ENERGÍA DIARIA DE LOS INTEGRANTES DEL COES (MWh)
B6: EMPRESA | C6: CENTRAL | D6: UNIDAD | E6: TIPO | F6: Diciembre
F7: 1 | G7: 2 | H7: 3 | I7: 4 | J7: 5 | K7: 6 | L7: 7 | M7: 8 | N7: 9 | O7: 10 | P7: 11 | Q7: 12 | R7: 13 | S7: 14 | T7: 15 | U7: 16 | V7: 17 | W7: 18 | X7: 19 | Y7: 20 | Z7: 21 | AA7: 22 | AB7: 23 | AC7: 24 | AD7: 25 | AE7: 26 | AF7: 27 | AG7: TOTAL
B8: AGRO INDUSTRIAL PARAMONGA S.A. | C8: C.T. PARAMONGA | D8: TV-01 | E8: TERMOELÉCTRICA | F8: 225.95 | H8: 244 | I8: 379.55 | J8: 390.2 | K8: 394.55 | L8: 381.75 | M8: 383 | N8: 393.5 | O8: 387.7 | P8: 384.8 | Q8: 392.3 | R8: 370.1 | S8: 424.3 | T8: 422.7 | U8: 419.65 | V8: 409.65 | W8: 410.2 | X8: 418.75 | Y8: 422.7 | Z8: 420.95 | AA8: 404.2 | AB8: 368.1 | AC8: 403.15 | AD8: 407.25 | AE8: 218.75 | AG8: 9477.75
B9: AGROAURORA S.A.C. | C9: C.T. MAPLE ETANOL | D9: TV | E9: TERMOELÉCTRICA | F9: 455.4 | G9: 336.6 | H9: 457.4 | I9: 461.25 | J9: 277.05 | K9: 449.65 | L9: 451.35 | M9: 451.85 | N9: 434.1 | O9: 294.1 | P9: 436.8 | Q9: 429.45 | R9: 141.84 | T9: 336.6 | U9: 479.3 | V9: 485.16 | W9: 478.925 | X9: 443.95 | Y9: 134.25 | AG9: 7435.025
B10: AGROINDUSTRIAS SAN JACINTO S.A.A. | C10: C.T. SAN JACINTO | D10: CENTRAL | E10: TERMOELÉCTRICA | F10: 194.745 | G10: 195.7 | H10: 171.4 | I10: 199.75 | J10: 189.4 | K10: 192.55 | L10: 193.35 | M10: 199.05 | N10: 189 | O10: 194.65 | P10: 161.05 | Q10: 196.95 | R10: 195.75 | S10: 192.72 | T10: 187.8 | U10: 198.6195 | V10: 192.2 | W10: 195.91 | X10: 193.2 | Y10: 203.75 | Z10: 199.95 | AA10: 198.75 | AB10: 201.1 | AC10: 193.6 | AD10: 176.285 | AE10: 191.35 | AF10: 199.9 | AG10: 5198.4795
B11: AGROLMOS SOCIEDAD ANONIMA - AGROLMOS S.A. | C11: C.T. AGROLMOS | D11: CENTRAL | E11: TERMOELÉCTRICA | F11: 217.08 | I11: 34.65 | J11: 262.05 | K11: 262.75 | L11: 269.3 | M11: 268.25 | N11: 261.55 | O11: 269.6 | P11: 245.525 | Q11: 270.3 | R11: 266.25 | S11: 264.65 | T11: 266 | U11: 265.65 | V11: 264.6 | W11: 266.1 | X11: 267.75 | Y11: 268.45 | Z11: 270.1 | AA11: 266.55 | AB11: 270.4 | AC11: 264.45 | AD11: 268.41 | AE11: 264.5 | AF11: 266.35 | AG11: 6361.265
B12: ANDEAN POWER S.A.C. | C12: C.H.CARHUAC | D12: CENTRAL | E12: HIDROELÉCTRICA | F12: 338.85 | G12: 363.95 | H12: 384.7 | I12: 356.85 | J12: 356.25 | K12: 372 | L12: 375.85 | M12: 326 | N12: 309.9 | O12: 365.3 | P12: 308.65 | Q12: 241.6 | R12: 227.65 | S12: 208.45 | T12: 205.35 | U12: 244.05 | V12: 294.365 | W12: 238.66 | X12: 252.3 | Y12: 285.05 | Z12: 263.75 | AA12: 238.45 | AB12: 283.15 | AC12: 339.7 | AD12: 348.85 | AE12: 327.8 | AF12: 355.85 | AG12: 8213.325
B13: ASOCIACIÓN SANTA LUCIA DE CHACAS | C13: C.H. HUALLIN | D13: CENTRAL | E13: HIDROELÉCTRICA | F13: 57.45 | G13: 58.05 | H13: 58.05 | I13: 61.1 | J13: 57.2 | K13: 55.35 | L13: 55.15 | M13: 49.9 | N13: 45.5 | O13: 45.25 | P13: 58.55 | Q13: 58.55 | R13: 56.52 | S13: 48.85 | T13: 44.05 | U13: 60.45 | V13: 40.56 | W13: 48 | X13: 60.25 | Y13: 63.6 | Z13: 63.6 | AA13: 63.6 | AB13: 69 | AC13: 70.35 | AD13: 70.75 | AE13: 69.6 | AF13: 70.75 | AG13: 1560.03
B14: ATRIA ENERGIA S.A.C. | C14: C.H. PURMACANA | D14: CENTRAL | E14: HIDROELÉCTRICA | I14: 8.55 | J14: 2.2 | AG14: 10.75
B15: BIOENERGIA DEL CHIRA S.A. | C15: C.T. CAÑA BRAVA | D15: CENTRAL | E15: TERMOELÉCTRICA | F15: 211.8 | G15: 190.55 | H15: 206.15 | I15: 208.1 | J15: 200.95 | K15: 203.8 | L15: 215.1 | M15: 204.4 | N15: 200.5 | O15: 177.3 | P15: 211.55 | Q15: 208.85 | R15: 204.7 | S15: 204.9 | T15: 212.1 | U15: 214.6 | V15: 203.3 | W15: 205.7 | X15: 212.1 | Y15: 211.15 | Z15: 203.9 | AA15: 211 | AB15: 212.45 | AC15: 215.1 | AD15: 195.15 | AE15: 213.6 | AF15: 211.35 | AG15: 5570.15
B16: CASA GRANDE S.A.A. | C16: C.T. CASA GRANDE | D16: TV3 | E16: TERMOELÉCTRICA | J16: 352.665 | K16: 526.9 | L16: 531.85 | M16: 534.7 | N16: 525.5221 | O16: 472.25 | P16: 535.49 | Q16: 533.88805 | R16: 560.55 | S16: 400.94 | T16: 501.4 | U16: 483.75 | V16: 76.3 | W16: 485 | X16: 514.85 | Y16: 556.7 | Z16: 526.45 | AA16: 440.55 | AB16: 473 | AC16: 408.9 | AD16: 202.6 | AE16: 396.135 | AF16: 451 | AG16: 10491.39
B17: CELARIS ENERGY S.A. | C17: C.H. MANTA I | D17: CENTRAL | E17: HIDROELÉCTRICA | F17: 308.75 | G17: 277.75 | H17: 248.3 | I17: 224.1 | J17: 203.95 | K17: 186.6 | L17: 176.05 | M17: 165.3 | N17: 155.3 | O17: 149.8 | P17: 150 | Q17: 150.8 | R17: 146.95 | S17: 143.15 | T17: 153.55 | U17: 153 | V17: 162.55 | W17: 160.15 | X17: 172.25 | Y17: 154.85 | Z17: 148.7 | AA17: 139.8 | AB17: 128.25 | AC17: 115.7 | AD17: 114.1 | AE17: 107.9 | AF17: 104.55 | AG17: 4502.15
B18: CELEPSA | C18: C.H. EL PLATANAL | D18: CENTRAL | E18: HIDROELÉCTRICA | F18: 1883.15 | G18: 1853.75 | H18: 1826.5 | I18: 1941.5 | J18: 1801.35 | K18: 1837.05 | L18: 1755.75 | M18: 1666.3 | N18: 1723.5 | O18: 1745.6 | P18: 1831.35 | Q18: 1910.3 | R18: 1783.5 | S18: 1809.1 | T18: 1720.55 | U18: 1733.6 | V18: 1686.875 | W18: 1590.09 | X18: 1615.2 | Y18: 1551.15 | Z18: 1548.4 | AA18: 1373.45 | AB18: 1319.8 | AC18: 1226.55 | AD18: 1428.6 | AE18: 1303.9 | AF18: 1267.75 | AG18: 44734.615
B19: CELEPSA RENOVABLES S.R.L. | C19: C.H. MARAÑON | D19: CENTRAL | E19: HIDROELÉCTRICA | F19: 451.2 | G19: 451.2 | H19: 451.2 | I19: 435.25 | J19: 391.1 | K19: 358.25 | L19: 336.4 | M19: 318.3 | N19: 304.65 | O19: 396.45 | P19: 443.9 | Q19: 436.65 | R19: 401.6 | S19: 423.7 | T19: 373.9 | U19: 416.7 | V19: 441.325 | W19: 447.425 | X19: 451.4 | Y19: 451.8 | Z19: 452.7 | AA19: 447.3 | AB19: 419.1 | AC19: 385.6 | AD19: 358.1 | AE19: 341.15 | AF19: 342.3 | AG19: 10928.65
B20: CENTRALES SANTA ROSA S.A.C. | C20: C.H. SANTA ROSA I | D20: CENTRAL | E20: HIDROELÉCTRICA | AG20: 0
B21: CENTRALES SANTA ROSA S.A.C. | C21: C.H. SANTA ROSA II | D21: CENTRAL | E21: HIDROELÉCTRICA | AG21: 0
B22: CHINANGO S.A.C. | C22: C.H. CHIMAY | D22: CENTRAL | E22: HIDROELÉCTRICA | F22: 2426.6 | G22: 2136.95 | H22: 3326.8 | I22: 2700.95 | J22: 2311.2 | K22: 2073.9 | L22: 1904.1 | M22: 2404.45 | N22: 1945.7 | O22: 2326.85 | P22: 2779.5 | Q22: 3568.75 | R22: 3276.6 | S22: 3095.45 | T22: 2484.5 | U22: 2539.65 | V22: 3259.075 | W22: 3022.42 | X22: 3141.25 | Y22: 3376.9 | Z22: 2572.5 | AA22: 2648.5961 | AB22: 2256.15 | AC22: 2237.6 | AD22: 2294.15 | AE22: 2365.7342 | AF22: 2295.95 | AG22: 70772.275
B23: CHINANGO S.A.C. | C23: C.H. YANANGO | D23: CENTRAL | E23: HIDROELÉCTRICA | F23: 478.45 | G23: 438.6 | H23: 444.55 | I23: 423.95 | J23: 399.4 | K23: 375.3 | L23: 375.5 | M23: 374.75 | N23: 374.5 | O23: 713 | P23: 680.9 | Q23: 707.35 | R23: 594.85 | S23: 548.55 | T23: 351.65 | U23: 505.45 | V23: 348.165 | W23: 488.465 | X23: 477.1 | Y23: 492.2 | Z23: 455.05 | AA23: 419.99033 | AB23: 405 | AC23: 380 | AD23: 393.6 | AE23: 357.01713 | AF23: 349.4 | AG23: 12352.737
B24: COENERGY S.A.C. | C24: C.S. COENERGY | D24: CENTRAL | E24: SOLAR | Z24: 2.958 | AA24: 3.03 | AB24: 2.92415 | AC24: 3.049355 | AD24: 2.76709 | AE24: 2.973295 | AF24: 3.044 | AG24: 20.74589
B25: COLCA SOLAR S.A.C. | C25: C.S. YARUCAYA | D25: CENTRAL | E25: SOLAR | F25: 7.85 | G25: 5.3 | H25: 9 | I25: 8.2 | J25: 8.9 | K25: 7.6 | L25: 0.05 | M25: 6.95 | N25: 5.8 | O25: 8.4 | P25: 8.45 | Q25: 8.5 | R25: 9.2 | S25: 8.85 | T25: 8.35 | U25: 8.05 | V25: 8.1 | W25: 8.05 | X25: 8.6 | AC25: 7.8 | AD25: 7.4 | AE25: 8.5 | AF25: 8.45 | AG25: 176.35
B26: EGASA | C26: C.H. CHARCANI III | D26: CENTRAL | E26: HIDROELÉCTRICA | F26: 166.75 | G26: 166.45 | H26: 164 | I26: 165.4 | J26: 163.85 | K26: 165.05 | L26: 164.6 | M26: 164.4 | N26: 164.8 | O26: 164.97 | P26: 164 | Q26: 165.55 | R26: 163.55 | S26: 164.45 | T26: 164.95 | U26: 165.15 | V26: 164.56 | W26: 163.51 | X26: 164.15 | Y26: 164.4 | Z26: 164.5 | AA26: 164.8 | AB26: 166 | AC26: 165.6 | AD26: 165.5 | AE26: 165.7 | AF26: 163.1 | AG26: 4449.74
B27: EGASA | C27: C.H. CHARCANI IV | D27: CENTRAL | E27: HIDROELÉCTRICA | F27: 355.45 | G27: 353.7 | H27: 352.6 | I27: 355.5 | J27: 355 | K27: 351.45 | L27: 352.775 | M27: 353.05 | N27: 352.45 | O27: 353.265 | P27: 324.05 | Q27: 351.8 | R27: 337.95 | S27: 355.95 | T27: 351.45 | U27: 356.05 | V27: 354.57 | W27: 351.615 | X27: 351.05 | Y27: 350.9 | Z27: 352.45 | AA27: 352.35 | AB27: 346.6 | AC27: 348.95 | AD27: 348.25 | AE27: 342.95 | AF27: 345.4 | AG27: 9457.575
B28: EGASA | C28: C.H. CHARCANI V | D28: CENTRAL | E28: HIDROELÉCTRICA | F28: 2279.25 | G28: 2236.2 | H28: 2266.15 | I28: 2253.1 | J28: 2232.75 | K28: 2233.8 | L28: 2226.16 | M28: 2229.05 | N28: 2247.45 | O28: 2223.435 | P28: 2231 | Q28: 2248.95 | R28: 2217.4 | S28: 2245.75 | T28: 2245.1 | U28: 2230.85 | V28: 2246.39 | W28: 2254.25 | X28: 2256.2 | Y28: 2228.5 | Z28: 2231.4 | AA28: 2236.7 | AB28: 2235.2 | AC28: 2239.55 | AD28: 2249.15 | AE28: 2254.15 | AF28: 2220.25 | AG28: 60498.135
B29: EGASA | C29: C.H. CHARCANI VI | D29: CENTRAL | E29: HIDROELÉCTRICA | AG29: 0
B30: EGASA | C30: C.T. CHILINA DIESEL | D30: CENTRAL | E30: TERMOELÉCTRICA | P30: 4.45 | AC30: 0.2 | AG30: 4.65
B31: EGASA | C31: C.T. CHILINA DIESEL | D31: TG | E31: TERMOELÉCTRICA | I31: 4.45 | AG31: 4.45
B32: EGASA | C32: C.T. MOLLENDO DIESEL | D32: CENTRAL | E32: TERMOELÉCTRICA | AG32: 0
B33: EGEJUNIN | C33: C.H. HUASAHUASI I | D33: CENTRAL | E33: HIDROELÉCTRICA | F33: 135.1 | G33: 132.85 | H33: 133.2 | I33: 122.05 | J33: 111.65 | K33: 100.8 | L33: 94.65 | M33: 90.25 | N33: 87.7 | O33: 216.6 | P33: 237.95 | Q33: 238.4 | R33: 224.9 | S33: 196.55 | T33: 165.3 | U33: 159.65 | V33: 164.75 | W33: 172.9 | X33: 166.45 | Y33: 182.35 | Z33: 166.3 | AA33: 149 | AB33: 136.5 | AC33: 118.45 | AD33: 111.35 | AE33: 105.6 | AF33: 103.35 | AG33: 4024.6
B34: EGEJUNIN | C34: C.H. RUNATULLO II | D34: CENTRAL | E34: HIDROELÉCTRICA | F34: 223.25 | G34: 231.3 | H34: 370.9 | I34: 300.3 | J34: 260.8 | K34: 230.3 | L34: 212.2 | M34: 236.05 | N34: 215.05 | O34: 256.55 | P34: 263.1 | Q34: 273 | R34: 294.6 | S34: 277.1 | T34: 246 | U34: 340.3 | V34: 355.18 | W34: 373.18 | X34: 394.85 | Y34: 375.25 | Z34: 342.05 | AA34: 307.45 | AB34: 277.4 | AC34: 258.2 | AD34: 299.85 | AE34: 259.5 | AF34: 258.25 | AG34: 7731.96
B35: EGEJUNIN | C35: C.H. RUNATULLO III | D35: CENTRAL | E35: HIDROELÉCTRICA | F35: 313.95 | G35: 307.9 | H35: 462.6 | I35: 414.25 | J35: 359.3 | K35: 317.7 | L35: 288.7 | M35: 334.1 | N35: 292.85 | O35: 349.55 | P35: 359.3 | Q35: 376.5 | R35: 390.7 | S35: 374.85 | T35: 335.45 | U35: 385.6 | V35: 468.43 | W35: 472.43 | X35: 249.3 | Y35: 485.45 | Z35: 460.75 | AA35: 415.25 | AB35: 379.9 | AC35: 350.2 | AD35: 406.55 | AE35: 354.3 | AF35: 357.05 | AG35: 10062.91
B36: EGEJUNIN | C36: C.H. SANTA CRUZ I | D36: CENTRAL | E36: HIDROELÉCTRICA | F36: 158.95 | G36: 154.2 | H36: 153.3 | I36: 152.75 | J36: 151.85 | K36: 151.8 | L36: 151.5 | M36: 151.7 | N36: 144.6 | O36: 135.4 | P36: 137 | Q36: 142.9 | R36: 154.5 | S36: 156.85 | T36: 156.9 | U36: 158.1 | V36: 154.05 | W36: 153.6 | X36: 159.75 | Y36: 159.2 | Z36: 153.4 | AA36: 160.45 | AB36: 161.15 | AC36: 163.2 | AD36: 169.3 | AE36: 185 | AF36: 191.45 | AG36: 4222.85
B37: EGEMSA | C37: C.H. MACHUPICCHU | D37: CENTRAL | E37: HIDROELÉCTRICA | F37: 3998.8 | G37: 3989.75 | H37: 4012.7 | I37: 4006.55 | J37: 4018.6 | K37: 4012.25 | L37: 3899.85 | M37: 3999.8 | N37: 3992.1 | O37: 3977.55 | P37: 3999.55 | Q37: 3981.3 | R37: 3984.4 | S37: 3306.5 | T37: 3898.8 | U37: 3927.9 | V37: 3953.085 | W37: 3985.2 | X37: 3969.05 | Y37: 4003.15 | Z37: 3922.3 | AA37: 3989 | AB37: 3961.55 | AC37: 3981.75 | AD37: 3983.45 | AE37: 3963.5 | AF37: 3966.35 | AG37: 106684.79
B38: EGESUR | C38: C.H. ARICOTA I | D38: CENTRAL | E38: HIDROELÉCTRICA | F38: 185.65 | G38: 185.95 | H38: 188.05 | I38: 186.85 | J38: 184.9 | K38: 179 | L38: 181.8 | M38: 181.15 | N38: 181.1 | O38: 185.3 | P38: 184.75 | Q38: 186.9 | R38: 186.7 | S38: 175.9 | T38: 172.7 | U38: 174.95 | V38: 173.2 | W38: 184.615 | X38: 186.45 | Y38: 186.95 | Z38: 185.5 | AA38: 185.1 | AB38: 188.75 | AC38: 189.55 | AD38: 187.95 | AE38: 186.15 | AF38: 189.6 | AG38: 4965.465
B39: EGESUR | C39: C.H. ARICOTA II | D39: CENTRAL | E39: HIDROELÉCTRICA | F39: 134.7 | G39: 136.6 | H39: 138.6 | I39: 133.7 | J39: 131.85 | K39: 128.95 | L39: 129.45 | M39: 126.8 | N39: 126.45 | O39: 128.2 | P39: 126.5 | Q39: 124.7 | R39: 126.65 | S39: 37.35 | V39: 43.765 | W39: 115.235 | X39: 128.35 | Y39: 129.2 | Z39: 126.55 | AA39: 128.15 | AB39: 126.75 | AC39: 129.15 | AD39: 129.5 | AE39: 127.85 | AF39: 132.85 | AG39: 3047.85
B40: EGESUR | C40: C.T. INDEPENDENCIA | D40: CENTRAL | E40: TERMOELÉCTRICA | F40: 339.45 | G40: 8.45 | I40: 295.5 | J40: 389.6 | K40: 391 | L40: 401.35 | M40: 284.9 | N40: 388.65 | O40: 401.7 | P40: 207.1 | Q40: 394.7 | R40: 335 | S40: 311.75 | T40: 531.85 | U40: 437.9 | V40: 482.895 | W40: 528.96 | X40: 532.55 | Y40: 531.8 | Z40: 525.5 | AA40: 458.25 | AB40: 535.9 | AC40: 525.7 | AD40: 235.45 | AE40: 509.75 | AF40: 521.95 | AG40: 10507.605
B41: ELECTRICA YANAPAMPA SAC | C41: C.H. YANAPAMPA | D41: CENTRAL | E41: HIDROELÉCTRICA | F41: 60.95 | G41: 55.35 | H41: 54.7 | I41: 52.7 | J41: 53.8 | K41: 57.9 | L41: 51.5 | M41: 52.1 | N41: 49.45 | O41: 55.3 | P41: 58 | Q41: 54.1 | R41: 49.2 | S41: 50.65 | T41: 50.7 | U41: 52.75 | V41: 52.29 | W41: 52.85 | X41: 53.35 | Y41: 51.45 | Z41: 49.2 | AA41: 51 | AB41: 50.1 | AC41: 53.65 | AD41: 56.1 | AE41: 53.4 | AF41: 55.4 | AG41: 1437.94
B42: ELECTROPERU | C42: C.H. MANTARO | D42: CENTRAL | E42: HIDROELÉCTRICA | F42: 14960.9 | G42: 14445.15 | H42: 14848.25 | I42: 13733.15 | J42: 12575.6 | K42: 11380.2 | L42: 11792.8 | M42: 9845.25 | N42: 9829.75 | O42: 10399.8 | P42: 13751.4 | Q42: 12934.3 | R42: 12918.45 | S42: 11534.25 | T42: 13246.7 | U42: 12264.8 | V42: 10694.17 | W42: 11772.59 | X42: 12471.65 | Y42: 12888.365 | Z42: 12516.45 | AA42: 13228.45 | AB42: 11960.46 | AC42: 10605.65 | AD42: 9563.1 | AE42: 12625.4 | AF42: 10871.15 | AG42: 329658.18
B43: ELECTROPERU | C43: C.H. RESTITUCION | D43: CENTRAL | E43: HIDROELÉCTRICA | F43: 5117.95 | G43: 4968.1 | H43: 5088.15 | I43: 4648.6 | J43: 4203.9 | K43: 3756.3 | L43: 3916.1 | M43: 3256.65 | N43: 3213.1 | O43: 3428.8 | P43: 4627 | Q43: 4285.1 | R43: 4338.6 | S43: 3793.95 | T43: 4464.55 | U43: 4052.6 | V43: 3551.35 | W43: 3894.82 | X43: 4115.2 | Y43: 4286.64 | Z43: 4197.75 | AA43: 4429.85 | AB43: 3986.345 | AC43: 3458.5 | AD43: 3116.95 | AE43: 4206.1 | AF43: 3600.2 | AG43: 110003.15
B44: ELECTROPERU | C44: C.T. TUMBES | D44: MAK1 | E44: TERMOELÉCTRICA | N44: 42.65 | AG44: 42.65
B45: ELECTROPERU | C45: C.T. TUMBES | D45: MAK2 | E45: TERMOELÉCTRICA | F45: 21.55 | N45: 42.6 | AG45: 64.15
B46: EMPRESA DE GENERACION ELECTRICA CANCHAYLLO SAC | C46: C.H. CANCHAYLLO | D46: CENTRAL | E46: HIDROELÉCTRICA | F46: 61.05 | G46: 61.55 | H46: 59.9 | I46: 60.75 | J46: 59.75 | K46: 60.75 | L46: 59.5 | M46: 62.5 | N46: 73.05 | O46: 83.7 | P46: 83.9 | Q46: 86.35 | R46: 85.3 | S46: 88.85 | T46: 91.55 | U46: 94.5 | V46: 90.2 | W46: 93.55 | X46: 96.2 | Y46: 95.4 | Z46: 90.65 | AA46: 96.25 | AB46: 97.6 | AC46: 96.75 | AD46: 96.9 | AE46: 99.3 | AF46: 99.45 | AG46: 2225.2
B47: EMPRESA DE GENERACION ELECTRICA RIO BAÑOS S.A.C. | C47: C.H. RUCUY | D47: CENTRAL | E47: HIDROELÉCTRICA | F47: 382.05 | G47: 367.45 | H47: 352.05 | I47: 344.35 | J47: 337.05 | K47: 344 | L47: 335.85 | M47: 329.3 | N47: 330.55 | O47: 361.85 | P47: 340.55 | Q47: 324.6 | R47: 317.55 | S47: 310.9 | T47: 401.75 | U47: 265.35 | V47: 372.55 | W47: 376.37 | X47: 366.55 | Y47: 416.95 | Z47: 338.2 | AA47: 348.65 | AB47: 410.15 | AC47: 384.3 | AD47: 461.95 | AE47: 442.8 | AF47: 407.8 | AG47: 9771.47
B48: EMPRESA DE GENERACION ELECTRICA SANTA ANA S.A.C. | C48: C.H. RENOVANDES H1 | D48: CENTRAL | E48: HIDROELÉCTRICA | F48: 488 | G48: 404.55 | H48: 95.2 | I48: 439.8 | J48: 486.45 | K48: 485.1 | L48: 485.7 | M48: 484.05 | N48: 486.5 | O48: 486.35 | P48: 483.1 | Q48: 483 | R48: 479.85 | S48: 486.8 | T48: 487.4 | U48: 466.1 | V48: 483.88 | W48: 483.35 | X48: 483.85 | Y48: 487.25 | Z48: 487 | AA48: 486.15 | AB48: 485.75 | AC48: 460.6 | AD48: 418.7 | AE48: 451.6 | AF48: 473.55 | AG48: 12429.63
B49: EMPRESA DE GENERACION HUALLAGA | C49: C.H. CHAGLLA | D49: CENTRAL | E49: HIDROELÉCTRICA | F49: 3419.05 | G49: 3119.7 | H49: 4060.7 | I49: 3784.3 | J49: 2428.5 | K49: 2317.6 | L49: 2624.85 | M49: 2311.15 | N49: 3653.55 | O49: 1367.8 | P49: 2001.95 | Q49: 3395.55 | R49: 5462.3 | S49: 8485.2 | T49: 3096.85 | U49: 4367.5 | V49: 3370.45 | W49: 3487.34 | X49: 2525 | Y49: 4182.7 | Z49: 3255.5 | AA49: 6276.9 | AB49: 3214.25 | AC49: 3070.65 | AD49: 1669.9 | AE49: 1206.8 | AF49: 1166.75 | AG49: 89322.79
B50: EMPRESA DE GENERACION HUALLAGA | C50: P.C.H. CHAGLLA | D50: CENTRAL | E50: HIDROELÉCTRICA | F50: 155.45 | G50: 154.75 | H50: 154.25 | I50: 154.35 | J50: 153.95 | K50: 153.85 | L50: 154.9 | M50: 154.55 | N50: 108 | O50: 156 | P50: 156 | Q50: 156 | R50: 156 | S50: 156 | T50: 156 | U50: 156 | V50: 155.735 | W50: 155.71 | X50: 155.85 | Y50: 156 | Z50: 156 | AA50: 156 | AB50: 156.05 | AC50: 155.95 | AD50: 155.9 | AE50: 155.95 | AF50: 156 | AG50: 4151.195
B51: EMPRESA DE GENERACION HUANZA | C51: C.H. HUANZA | D51: CENTRAL | E51: HIDROELÉCTRICA | F51: 1470.95 | G51: 1554.75 | H51: 1658.25 | I51: 1560.5 | J51: 1571.6 | K51: 1610.1 | L51: 1638.15 | M51: 1472.3 | N51: 1367.15 | O51: 1609.05 | P51: 1312.05 | Q51: 1006.65 | R51: 969.4 | S51: 871.4 | T51: 889.4 | U51: 1094.05 | V51: 1253.17 | W51: 1037.335 | X51: 1049.8 | Y51: 1108.45 | Z51: 1025.05 | AA51: 901.65 | AB51: 1117.7 | AC51: 1347.2 | AD51: 1383.35 | AE51: 1370.1 | AF51: 1415.4 | AG51: 34664.955
B52: EMPRESA ELECTRICA AGUA AZUL | C52: C.H. POTRERO | D52: CENTRAL | E52: HIDROELÉCTRICA | F52: 479.9 | G52: 480 | H52: 480 | I52: 479.5 | J52: 345.1 | K52: 398.85 | L52: 322.15 | M52: 258.8 | N52: 207.3 | O52: 146.15 | P52: 129.15 | Q52: 129.05 | R52: 139.05 | S52: 131.55 | T52: 128.85 | U52: 138.1 | V52: 217.65 | W52: 303.25 | X52: 468.95 | Y52: 480 | Z52: 480 | AA52: 480 | AB52: 480 | AC52: 454.65 | AD52: 386 | AE52: 308.65 | AF52: 249.65 | AG52: 8702.3
B53: EMPRESA ELECTRICA RIO DOBLE | C53: C.H. LAS PIZARRAS | D53: CENTRAL | E53: HIDROELÉCTRICA | F53: 457.7 | G53: 457.8 | H53: 458.7 | I53: 458.5 | J53: 458.4 | K53: 457.1 | L53: 446 | M53: 414.35 | N53: 386.75 | O53: 367.45 | P53: 365.6 | Q53: 368.35 | R53: 356.05 | S53: 345.65 | T53: 322.5 | U53: 308.15 | V53: 324.815 | W53: 297.125 | X53: 425.95 | Y53: 458.75 | Z53: 458.15 | AA53: 458.35 | AB53: 458.4 | AC53: 432.95 | AD53: 391.55 | AE53: 354.7 | AF53: 327.7 | AG53: 10817.49
B54: ENEL GENERACION PIURA S.A. | C54: C.T. MALACAS 1 | D54: TG6 | E54: TERMOELÉCTRICA | F54: 955.95 | G54: 1098.1 | H54: 625.3 | I54: 1116.2 | J54: 759.95 | K54: 425.15 | L54: 601.3 | M54: 1017.25 | N54: 963.2 | O54: 978.05 | P54: 886.25 | Q54: 945.85 | R54: 793.1 | S54: 964.2 | T54: 924.55 | U54: 890.75 | V54: 205.05 | W54: 974.79 | X54: 1081.54 | Y54: 1093.8 | Z54: 870.55 | AA54: 869.1 | AB54: 793.25 | AC54: 770.75 | AD54: 426.4 | AE54: 1055.4 | AF54: 786.05 | AG54: 22871.83
B55: ENEL GENERACION PIURA S.A. | C55: C.T. MALACAS 2 | D55: TG4 | E55: TERMOELÉCTRICA | K55: 423 | L55: 164.9 | AG55: 587.9
B56: ENEL GENERACION PIURA S.A. | C56: C.T. RF DE GENERACION TALARA | D56: TG5 | E56: TERMOELÉCTRICA | AG56: 0
B57: ENERGÍA EÓLICA S.A. | C57: C.E. CUPISNIQUE | D57: CENTRAL | E57: EÓLICA | F57: 1194.75 | G57: 665.1 | H57: 1221.15 | I57: 1066.05 | J57: 442.65 | K57: 573.05 | L57: 1228.7 | M57: 948.5 | N57: 757.45 | O57: 795.15 | P57: 1007.15 | Q57: 960.3 | R57: 1077.7 | S57: 1032.2 | T57: 920.5 | U57: 694.3 | V57: 545.02 | W57: 630.3 | X57: 597 | Y57: 1362.1 | Z57: 1260.7 | AA57: 624.9 | AB57: 1052.95 | AC57: 1201.3 | AD57: 964.65 | AE57: 1233.55 | AF57: 1148.35 | AG57: 25205.52
B58: ENERGÍA EÓLICA S.A. | C58: C.E. TALARA | D58: CENTRAL | E58: EÓLICA | F58: 384.4 | G58: 415.2 | H58: 248.35 | I58: 535.05 | J58: 437.5 | K58: 524.4 | L58: 627.15 | M58: 504.1 | N58: 402.9 | O58: 478.85 | P58: 587.1 | Q58: 585.6 | R58: 325 | S58: 459.85 | T58: 294.75 | U58: 209.7 | V58: 245.145 | W58: 274.2 | X58: 261.7 | Y58: 535.85 | Z58: 526.4 | AA58: 491.75 | AB58: 523.25 | AC58: 605.95 | AD58: 566.45 | AE58: 541.15 | AF58: 623.25 | AG58: 12214.995
B59: ENERGIA RENOVABLE DEL SUR S.A. | C59: C.E. SAN JUAN | D59: CENTRAL | E59: EÓLICA | F59: 2344.7 | G59: 1630.05 | H59: 1253.3 | I59: 1333.25 | J59: 625.4 | K59: 784.25 | L59: 2099.45 | M59: 1846.6 | N59: 1315 | O59: 1851.15 | P59: 1628.7 | Q59: 1384.3 | R59: 1714.25 | S59: 2074.9 | T59: 2556.8 | U59: 2181.1 | V59: 2039.055 | W59: 1671.7 | X59: 1135.55 | Y59: 1261.6 | Z59: 2218.3 | AA59: 2032.65 | AB59: 1891.85 | AC59: 1024.9 | AD59: 1159.1 | AE59: 1266.8 | AF59: 2118.4 | AG59: 44443.105
B60: ENGIE ENERGIA PERU S.A.A. | C60: C.E. PUNTA LOMITAS | D60: PL-BL1 | E60: EÓLICA | F60: 1328.1 | G60: 1544.9 | H60: 1386.15 | I60: 1151.4 | J60: 745.65 | K60: 638.05 | L60: 2016.3 | M60: 1676.9 | N60: 1148 | O60: 1375.1 | P60: 1436.55 | Q60: 1199.7 | R60: 1089.5712 | S60: 1337 | T60: 1868.95 | U60: 1518.0742 | V60: 1496.3055 | W60: 969.35 | X60: 797.2 | Y60: 1023.4 | Z60: 1519.55 | AA60: 1643 | AB60: 1549.9 | AC60: 1283.45 | AD60: 1092.4 | AE60: 905.8 | AF60: 909.35 | AG60: 34650.101
B61: ENGIE ENERGIA PERU S.A.A. | C61: C.E. PUNTA LOMITAS | D61: PL-BL2 | E61: EÓLICA | F61: 1610.4 | G61: 1899.95 | H61: 1753.4 | I61: 1491.7 | J61: 906.8 | K61: 714.65 | L61: 2356.8 | M61: 1943.25 | N61: 1407.3 | O61: 1790.4 | P61: 1753.85 | Q61: 1626.15 | R61: 1392.285 | S61: 1616.65 | T61: 2051.55 | U61: 1870.0815 | V61: 2000.878 | W61: 1323.6 | X61: 1197.25 | Y61: 1342.65 | Z61: 1737.7 | AA61: 1834.85 | AB61: 1759.75 | AC61: 1545.8 | AD61: 1551.05 | AE61: 1296.4 | AF61: 1455.1 | AG61: 43230.245
B62: ENGIE ENERGIA PERU S.A.A. | C62: C.E. PUNTA LOMITAS_EXP | D62: PUN LOM_EXP-BL1 | E62: EÓLICA | F62: 219.95 | G62: 242.6 | H62: 217.85 | I62: 180.35 | J62: 92.8 | K62: 79.25 | L62: 309.7 | M62: 247.35 | N62: 154.6 | O62: 188.6 | P62: 207.8 | Q62: 162.8 | R62: 131.02645 | S62: 172.8 | T62: 276.5 | U62: 192.36828 | V62: 191.36711 | W62: 142.18 | X62: 99.75 | Y62: 134 | Z62: 224.05 | AA62: 228.1 | AB62: 182.4 | AC62: 155 | AD62: 148.35 | AE62: 104.4 | AF62: 105.6 | AG62: 4791.5418
B63: ENGIE ENERGIA PERU S.A.A. | C63: C.E. PUNTA LOMITAS_EXP | D63: PUN LOM_EXP-BL2 | E63: EÓLICA | F63: 41.7 | G63: 185.35 | H63: 154.2 | I63: 133.05 | J63: 68.7 | K63: 60.15 | L63: 222.05 | M63: 195.05 | N63: 123.75 | O63: 134.3 | P63: 157.7 | Q63: 116.65 | R63: 91.674615 | S63: 128.15 | T63: 186.15 | U63: 43.120915 | V63: 92.97306 | W63: 82.2 | X63: 59.1 | Y63: 93.45 | Z63: 150.8 | AA63: 165.55 | AB63: 152.8 | AC63: 134.65 | AD63: 92.15 | AE63: 72.2 | AF63: 73 | AG63: 3210.6186
B64: ENGIE ENERGIA PERU S.A.A. | C64: C.H. QUITARACSA | D64: CENTRAL | E64: HIDROELÉCTRICA | G64: 329.7 | J64: 428.5 | M64: 449.9 | P64: 109.25 | X64: 425.45 | Y64: 41.45 | AA64: 196.8 | AB64: 143.75 | AE64: 476.55 | AG64: 2601.35
B65: ENGIE ENERGIA PERU S.A.A. | C65: C.H. YUNCAN | D65: CENTRAL | E65: HIDROELÉCTRICA | F65: 1979.1 | G65: 2050.8 | H65: 2205.25 | I65: 2073.25 | J65: 1796.25 | K65: 1902.55 | L65: 1668.5 | M65: 1920.05 | N65: 2108.4 | O65: 2753.7 | P65: 2975.45 | Q65: 2868.7 | R65: 2832.434 | S65: 1481.95 | T65: 1961.95 | U65: 1624.9129 | V65: 1957.9061 | W65: 1845.705 | X65: 2012.75 | Y65: 2402.65 | Z65: 2061 | AA65: 1785.2 | AB65: 1650.8 | AC65: 1896.25 | AD65: 1849.9 | AE65: 1926.95 | AF65: 2193.5 | AG65: 55785.858
B66: ENGIE ENERGIA PERU S.A.A. | C66: C.S. INTIPAMPA | D66: CENTRAL | E66: SOLAR | F66: 374.25 | G66: 369.55 | H66: 275 | I66: 207.6 | J66: 385.45 | K66: 408.75 | L66: 376.35 | M66: 378.6 | N66: 347.05 | O66: 385.1 | P66: 393.25 | Q66: 402.9 | R66: 387.85 | S66: 388.5 | T66: 394.6 | U66: 402.58446 | V66: 402.37167 | W66: 379.5 | X66: 316.25 | Y66: 379.95 | Z66: 391.8 | AA66: 410.9 | AB66: 411.55 | AC66: 375.35 | AD66: 391.15 | AE66: 203.5 | AF66: 296 | AG66: 9835.7061
B67: ENGIE ENERGIA PERU S.A.A. | C67: C.S. INTIPAMPA EXPANSIÓN | D67: CENTRAL | E67: SOLAR | S67: 25.52 | T67: 171.19815 | U67: 211.065 | V67: 253.81 | W67: 259.23 | X67: 97.235 | Y67: 468.395 | Z67: 374.645 | AA67: 469.5 | AB67: 492.34 | AC67: 475.39 | AD67: 491.135 | AE67: 276.13 | AF67: 394.335 | AG67: 4459.9281
B68: ENGIE ENERGIA PERU S.A.A. | C68: C.T. CHILCA 1 | D68: TG1 | E68: TERMOELÉCTRICA | F68: 1064.9 | G68: 3453.65 | H68: 4123.35 | I68: 4147.95 | J68: 4154.55 | K68: 4137.4 | L68: 3949.4 | M68: 4073.65 | N68: 3924.25 | O68: 3991.85 | P68: 3864.6 | Q68: 3979.15 | R68: 3877.6604 | S68: 3850.65 | T68: 3874.1 | U68: 3896.3077 | V68: 3671.5299 | W68: 3897.345 | X68: 3992.55 | Y68: 3859.35 | Z68: 3891.65 | AA68: 3884.5 | AB68: 3918.35 | AC68: 3854.55 | AD68: 3436.85 | AE68: 3896.45 | AF68: 3907.15 | AG68: 102573.69
B69: ENGIE ENERGIA PERU S.A.A. | C69: C.T. CHILCA 1 | D69: TG2 | E69: TERMOELÉCTRICA | F69: 4051 | G69: 4063.9 | H69: 4064.9 | I69: 4092.5 | J69: 4094.45 | K69: 4076.9 | L69: 3918.4 | M69: 4024.5 | N69: 3902.25 | O69: 3956.45 | P69: 3854.2 | Q69: 3945.5 | R69: 3866.2904 | S69: 3836.1 | T69: 3863.75 | U69: 3882.0039 | V69: 3666.9771 | W69: 3877.72 | X69: 3952.55 | Y69: 3849.5 | Z69: 3866.05 | AA69: 3857.5 | AB69: 3890.35 | AC69: 3842.2 | AD69: 3416.9 | AE69: 3869.7 | AF69: 3892.8 | AG69: 105475.34
B70: ENGIE ENERGIA PERU S.A.A. | C70: C.T. CHILCA 1 | D70: TG3 | E70: TERMOELÉCTRICA | F70: 4792.6 | G70: 4892.75 | H70: 4797.4 | I70: 4909.15 | J70: 4898.1 | K70: 4799.55 | L70: 4167.8 | M70: 4702.3 | N70: 4119.75 | O70: 4267.7 | P70: 3875.55 | Q70: 4366.7 | R70: 3962.2375 | S70: 4000.1 | T70: 3989.65 | U70: 4027.1191 | V70: 3688.0512 | W70: 4097.7 | X70: 4380.25 | Y70: 3947 | Z70: 4136.6 | AA70: 4080.3 | AB70: 4227 | AC70: 3972.85 | AD70: 3654.35 | AE70: 4113.75 | AF70: 4023.35 | AG70: 114889.66
B71: ENGIE ENERGIA PERU S.A.A. | C71: C.T. CHILCA 1 | D71: TV | E71: TERMOELÉCTRICA | F71: 4317.75 | G71: 5978.3 | H71: 6385.15 | I71: 6415 | J71: 6415.85 | K71: 6388.05 | L71: 6048.15 | M71: 6344.4 | N71: 6053.2 | O71: 6114.7 | P71: 5915.9 | Q71: 6161.25 | R71: 5928.8338 | S71: 5951.25 | T71: 5972.25 | U71: 5961.7851 | V71: 5771.8753 | W71: 6028.71 | X71: 6170.2 | Y71: 5927.55 | Z71: 6005.95 | AA71: 6035.2 | AB71: 6087.1 | AC71: 5935.3 | AD71: 5538.5 | AE71: 5991.25 | AF71: 5965.45 | AG71: 161808.9
B72: ENGIE ENERGIA PERU S.A.A. | C72: C.T. CHILCA 2 | D72: TG41 | E72: TERMOELÉCTRICA | J72: 982.5 | K72: 1637.65 | L72: 1077.4 | M72: 958.95 | N72: 1122.15 | O72: 1771.4 | P72: 1770.45 | Q72: 1762.1 | R72: 1763.7918 | S72: 1667.4 | T72: 1777.55 | U72: 1763.5293 | V72: 1755.9824 | W72: 1765.4833 | X72: 1771.7 | Y72: 1768.95 | Z72: 1769.65 | AA72: 1744.95 | AB72: 1749.2 | AC72: 1751.1 | AD72: 1378 | AE72: 1755.35 | AF72: 1765.2 | AG72: 37030.437
B73: ENGIE ENERGIA PERU S.A.A. | C73: C.T. CHILCA 2 | D73: TV42 | E73: TERMOELÉCTRICA | N73: 455.85 | O73: 862.5 | P73: 863.35 | Q73: 862.6 | R73: 864.48117 | S73: 838.3 | T73: 866.45 | U73: 863.11156 | V73: 856.13201 | W73: 862.07667 | X73: 865.35 | Y73: 861.95 | Z73: 862.55 | AA73: 858 | AB73: 857.2 | AC73: 858.8 | AD73: 766.75 | AE73: 860.8 | AF73: 862.1 | AG73: 15848.351
B74: ENGIE ENERGIA PERU S.A.A. | C74: C.T. NEPI | D74: TG41 | E74: TERMOELÉCTRICA | AG74: 0
B75: ENGIE ENERGIA PERU S.A.A. | C75: C.T. NEPI | D75: TG42 | E75: TERMOELÉCTRICA | AG75: 0
B76: ENGIE ENERGIA PERU S.A.A. | C76: C.T. NEPI | D76: TG43 | E76: TERMOELÉCTRICA | AG76: 0
B77: ENGIE ENERGIA PERU S.A.A. | C77: C.T. RF PLANTA ILO | D77: TG1 | E77: TERMOELÉCTRICA | AG77: 0
B78: ENGIE ENERGIA PERU S.A.A. | C78: C.T. RF PLANTA ILO | D78: TG2 | E78: TERMOELÉCTRICA | AG78: 0
B79: ENGIE ENERGIA PERU S.A.A. | C79: C.T. RF PLANTA ILO | D79: TG3 | E79: TERMOELÉCTRICA | AG79: 0
B80: FENIX POWER PERÚ | C80: C.T. FENIX | D80: GT11 | E80: TERMOELÉCTRICA | F80: 4372.65 | G80: 4316.0271 | H80: 4382.25 | I80: 4375.1 | J80: 4387.1 | K80: 4384.6 | L80: 4378.1 | M80: 4223.2 | N80: 4365.75 | O80: 4390.93 | P80: 4367.65 | Q80: 4372.05 | R80: 4376.45 | S80: 4259.4 | T80: 4360.4 | U80: 4376.5 | V80: 4373.4067 | W80: 4376.7167 | X80: 4327.7 | Y80: 4354.7 | Z80: 4344.5 | AA80: 4346.8 | AB80: 4343.35 | AC80: 4351.55 | AD80: 4339.05 | AE80: 4331.9127 | AF80: 4346.9605 | AG80: 117524.8
B81: FENIX POWER PERÚ | C81: C.T. FENIX | D81: GT12 | E81: TERMOELÉCTRICA | F81: 4401.1 | G81: 4329.8008 | H81: 4395.1 | I81: 4386.35 | J81: 4008.45 | K81: 4395.45 | L81: 3551.15 | M81: 4165.15 | N81: 4380.55 | O81: 4378.03 | P81: 4380.2 | Q81: 4386.55 | R81: 4389.8 | S81: 4271.05 | T81: 4372.3 | U81: 4386.5 | V81: 4374.0517 | W81: 4353.8267 | X81: 4338.95 | Y81: 4366.45 | Z81: 4357 | AA81: 4358.95 | AB81: 4357 | AC81: 4364.8 | AD81: 4352.5 | AE81: 4343.8434 | AF81: 4357.9993 | AG81: 116502.9
B82: FENIX POWER PERÚ | C82: C.T. FENIX | D82: TV10 | E82: TERMOELÉCTRICA | F82: 4416.15 | G82: 4409.5639 | H82: 4434.4 | I82: 4439 | J82: 924.3 | L82: 117.65 | M82: 4136.9 | N82: 4420.05 | O82: 4448.59 | P82: 4428.2 | Q82: 4437.95 | R82: 4435.9 | S82: 4362.4 | T82: 4432.6 | U82: 4433.65 | V82: 4431.0067 | W82: 4442.2867 | X82: 4402.5 | Y82: 4420.55 | Z82: 4421.85 | AA82: 4421.95 | AB82: 4419.35 | AC82: 4428.15 | AD82: 4421.35 | AE82: 4426.3136 | AF82: 4426.9911 | AG82: 106939.6
B83: GENERACIÓN ANDINA S.A.C. | C83: C.H. 8 DE AGOSTO | D83: CENTRAL | E83: HIDROELÉCTRICA | F83: 337.35 | G83: 280.95 | H83: 392.55 | I83: 280.7 | J83: 256.15 | K83: 249.6 | L83: 247.4 | M83: 236.45 | N83: 231.05 | O83: 249.6 | P83: 311.95 | Q83: 455.45 | R83: 433.45 | S83: 372.1 | T83: 302.05 | U83: 326.65 | V83: 311.215 | W83: 428.865 | X83: 427.75 | Y83: 353.05 | Z83: 274.8 | AA83: 280.45 | AB83: 280.05 | AC83: 243.55 | AD83: 238.05 | AE83: 222.2 | AF83: 220.9 | AG83: 8244.33
B84: GENERACIÓN ANDINA S.A.C. | C84: C.H. EL CARMEN | D84: CENTRAL | E84: HIDROELÉCTRICA | F84: 84.7 | G84: 75.35 | H84: 81.3 | I84: 76.45 | J84: 70.05 | K84: 66.15 | L84: 61.95 | M84: 58.8 | N84: 57.85 | O84: 77.25 | P84: 134.8 | Q84: 159.8 | R84: 160.55 | S84: 134.55 | T84: 101.4 | U84: 97.4 | V84: 90.935 | W84: 118.66 | X84: 127.2 | Y84: 101.9 | Z84: 87.9 | AA84: 82.6 | AB84: 85.45 | AC84: 78.15 | AD84: 71.9 | AE84: 69.05 | AF84: 69.35 | AG84: 2481.445
B85: GENERADORA DE ENERGÍA DEL PERÚ | C85: C.H. ÁNGEL I | D85: CENTRAL | E85: HIDROELÉCTRICA | F85: 481.6 | G85: 423 | H85: 489.6 | I85: 489.6 | J85: 489.6 | K85: 443.7 | L85: 489.6 | M85: 489.6 | N85: 464.1 | O85: 489.6 | P85: 489.6 | Q85: 489.6 | R85: 489.6 | S85: 489.6 | T85: 489.6 | U85: 489.6 | V85: 483.975 | W85: 483.025 | X85: 489.6 | Y85: 489.6 | Z85: 489.6 | AA85: 489.6 | AB85: 489.6 | AC85: 489.6 | AD85: 489.6 | AE85: 489.6 | AF85: 489.6 | AG85: 13061
B86: GENERADORA DE ENERGÍA DEL PERÚ | C86: C.H. ÁNGEL II | D86: CENTRAL | E86: HIDROELÉCTRICA | F86: 487.7 | G86: 452.4 | H86: 489.6 | I86: 489.6 | J86: 453.9 | K86: 458.3 | L86: 489.6 | M86: 489.6 | N86: 465.85 | O86: 489.6 | P86: 489.6 | Q86: 459.05 | R86: 489.6 | S86: 489.6 | T86: 489.6 | U86: 489.6 | V86: 484.595 | W86: 483.795 | X86: 489.6 | Y86: 489.6 | Z86: 489.6 | AA86: 489.6 | AB86: 489.6 | AC86: 489.6 | AD86: 489.6 | AE86: 489.6 | AF86: 489.6 | AG86: 13047.99
B87: GENERADORA DE ENERGÍA DEL PERÚ | C87: C.H. ÁNGEL III | D87: CENTRAL | E87: HIDROELÉCTRICA | F87: 480.2 | G87: 446.05 | H87: 482.4 | I87: 482.4 | J87: 442.2 | K87: 424.55 | L87: 480 | M87: 482.4 | N87: 440.55 | O87: 482.4 | P87: 482.4 | Q87: 453.5 | R87: 472.25 | S87: 480 | T87: 481.65 | U87: 480 | V87: 477.005 | W87: 477.725 | X87: 482.4 | Y87: 482.4 | Z87: 482.4 | AA87: 482.4 | AB87: 482.4 | AC87: 482.4 | AD87: 472.35 | AE87: 482.4 | AF87: 482.4 | AG87: 12779.23
B88: GENERADORA DE ENERGÍA DEL PERÚ | C88: C.H. LA JOYA | D88: CENTRAL | E88: HIDROELÉCTRICA | F88: 189.85 | G88: 159.55 | H88: 177.3 | I88: 118.7 | J88: 180.35 | K88: 191.4 | L88: 183.5 | M88: 183.8 | N88: 183.1 | O88: 196.75 | P88: 195.35 | Q88: 193 | R88: 195.6 | S88: 200.7 | T88: 202.45 | U88: 199.95 | V88: 199.05 | W88: 194.7 | X88: 200.45 | Y88: 201.25 | Z88: 202.45 | AA88: 204.45 | AB88: 199.3 | AC88: 203.3 | AD88: 203.3 | AE88: 201.4 | AF88: 202.1 | AG88: 5163.1
B89: GM OPERACIONES S.A.C. | C89: CT REFINERIA TALARA | D89: TV1 REF TALARA | E89: TERMOELÉCTRICA | F89: 653.4 | G89: 650.65 | H89: 657.45 | I89: 660.35 | J89: 664.3 | K89: 660.85 | L89: 660 | M89: 654.05 | N89: 657.5 | O89: 663.3 | P89: 659.45 | Q89: 660.7 | R89: 663 | S89: 667.9 | T89: 659.6 | U89: 657.65 | V89: 658.60328 | W89: 666.18327 | X89: 660.55 | Y89: 658.75 | Z89: 659.9 | AA89: 662.15 | AB89: 651.1 | AC89: 644.8 | AD89: 654.55 | AE89: 656.35 | AF89: 650.8 | AG89: 17773.887
B90: GM OPERACIONES S.A.C. | C90: CT REFINERIA TALARA | D90: TV2 REF TALARA | E90: TERMOELÉCTRICA | F90: 821.1 | G90: 826.25 | H90: 821.7 | I90: 832.9 | J90: 832.05 | K90: 828.8 | L90: 829.15 | M90: 825.4 | N90: 826.05 | O90: 831.05 | P90: 827 | Q90: 829.9 | R90: 833.9 | S90: 841 | T90: 830.3 | U90: 825.25 | V90: 821.39172 | W90: 831.22672 | X90: 830.7 | Y90: 825.15 | Z90: 819.7 | AA90: 829.15 | AB90: 532.6 | AC90: 601.5 | AD90: 645.75 | AE90: 787.7 | AF90: 826 | AG90: 21612.668
B91: GR CORTARRAMA SOCIEDAD ANONIMA CERRADA | C91: C.S. MATARANI | D91: C.S. MATARANI | E91: SOLAR | F91: 834 | G91: 767.25 | H91: 610.25 | I91: 598.15 | J91: 775.8 | K91: 838.25 | L91: 759.6 | M91: 739.6 | N91: 764.95 | O91: 846.45 | P91: 766.6 | Q91: 847.9 | R91: 806.7 | S91: 836.85 | T91: 817.4 | U91: 752.25 | V91: 855.05 | W91: 818.8 | X91: 797.35 | Y91: 848.8 | Z91: 857.4 | AA91: 858.45 | AB91: 811.45 | AC91: 781.85 | AD91: 856.8 | AE91: 501.9 | AF91: 760.2 | AG91: 21110.05
B92: GR PAINO SOCIEDAD ANONIMA CERRADA | C92: C.E. HUAMBOS | D92: CENTRAL | E92: EÓLICA | F92: 122.65 | G92: 127.6 | H92: 118.7 | I92: 103.55 | J92: 69.4 | K92: 72.3 | L92: 76.1 | M92: 70.5 | N92: 63.45 | O92: 128.1 | P92: 75 | Q92: 165.6 | R92: 86.95 | S92: 109.6 | T92: 84.95 | U92: 39.965 | V92: 42.815 | W92: 28.3 | X92: 5.5 | Y92: 31.55 | Z92: 55.2 | AA92: 56.6 | AB92: 79.75 | AC92: 123.9 | AD92: 131.65 | AE92: 14.4 | AF92: 46.05 | AG92: 2130.13
B93: GR TARUCA SOCIEDAD ANONIMA CERRADA | C93: C.E. DUNA | D93: CENTRAL | E93: EÓLICA | F93: 76.7 | G93: 71.75 | H93: 60.8 | I93: 56.15 | J93: 36.6 | K93: 31.45 | L93: 49.9 | M93: 35.2 | N93: 39.65 | O93: 111.05 | P93: 71.3 | Q93: 169.2 | R93: 80.75 | S93: 98.95 | T93: 59.15 | U93: 36.75 | V93: 94.21491 | W93: 29.85 | X93: 4.05 | Y93: 11.65 | Z93: 23 | AA93: 54.9 | AB93: 85.75 | AC93: 84.9 | AD93: 87.95 | AE93: 12.8 | AF93: 41.8 | AG93: 1616.2149
B94: HIDROCAÑETE S.A. | C94: C.H. IMPERIAL | D94: CENTRAL | E94: HIDROELÉCTRICA | F94: 78.7 | G94: 75.2 | H94: 75.8 | I94: 75.05 | J94: 76.8 | K94: 74.3 | L94: 76.15 | M94: 75.95 | N94: 72.1 | O94: 69.1 | P94: 71.5 | Q94: 75.7 | R94: 73.55 | S94: 75.55 | T94: 75.2 | U94: 64.95 | V94: 64.25 | W94: 62.05 | X94: 63.9 | Y94: 59.25 | Z94: 59.8 | AA94: 57.55 | AB94: 51.6 | AC94: 49.85 | AD94: 57.25 | AE94: 51.75 | AF94: 55.05 | AG94: 1817.9
... B97: HYDRO GLOBAL PERÚ S.A.C. | C97: CH SAN GABAN III | D97: CENTRAL | E97: HIDROELÉCTRICA | F97: 4233.85 | G97: 4873.85 | H97: 4840.85 | I97: 4876.85 | J97: 4879.4 | K97: 4871.4 | L97: 4874.35 | M97: 4869.6 | N97: 4867.25 | O97: 4860.75 | P97: 4869.15 | Q97: 4867.25 | R97: 4875.1 | S97: 4882.65 | T97: 4867.5 | U97: 4862.15 | V97: 4866.29 | W97: 4870.7 | X97: 4863.3 | Y97: 4878.1 | Z97: 4870.75 | AA97: 4873.9 | AB97: 4868.65 | AC97: 4878.7 | AD97: 4874.6 | AE97: 4858.15 | AF97: 4872.95 | AG97: 130848.04
B98: INFRAESTRUCTURAS Y ENERGIAS DEL PERU S.A.C. | C98: C.T. RF PTO MALDONADO | D98: CENTRAL | E98: TERMOELÉCTRICA | Q98: 7.55 | S98: 121.25 | AD98: 50.85 | AG98: 179.65
B99: INFRAESTRUCTURAS Y ENERGIAS DEL PERU S.A.C. | C99: C.T. RF PUCALLPA | D99: CENTRAL | E99: TERMOELÉCTRICA | T99: 1.45 | V99: 1.5 | AA99: 155.65 | AG99: 158.6
B100: INLAND ENERGY SAC | C100: C.H. SANTA TERESA | D100: CENTRAL | E100: HIDROELÉCTRICA | F100: 2174.955 | G100: 2156.25 | H100: 2176.55 | I100: 2181.6 | J100: 2164 | K100: 2166.75 | L100: 2125.65 | M100: 2188 | N100: 2168.3 | O100: 2180.55 | P100: 2178.7 | Q100: 1889.55 | R100: 2171.75 | S100: 1525.1 | T100: 1366.6 | U100: 1368.3 | V100: 2085.545 | W100: 2161.135 | X100: 2140.1 | Y100: 2168.05 | Z100: 2145.25 | AA100: 2160.05 | AB100: 2148.15 | AC100: 2167.9 | AD100: 2156 | AE100: 2159.5 | AF100: 2158.35 | AG100: 55832.635
B101: INVERSIONES SHAQSHA S.A.C. | C101: C.H. PARIAC | D101: CENTRAL | E101: HIDROELÉCTRICA | F101: 49.9 | G101: 30.1 | H101: 22.05 | I101: 20.15 | J101: 22.65 | K101: 19.8 | L101: 19.2 | M101: 19.2 | N101: 19.2 | O101: 19.1 | P101: 16.8 | Q101: 16.8 | R101: 16 | S101: 5.45 | V101: 7.67 | W101: 11.62 | X101: 8.5 | Y101: 10 | Z101: 9.25 | AA101: 7.5 | AB101: 7.95 | AG101: 358.89
B102: JOYA SOLAR S.A.C. | C102: C.S. SAN MARTIN SOLAR | D102: CENTRAL | E102: SOLAR | F102: 2467.7 | G102: 2327.35 | H102: 1766.55 | I102: 1976.35 | J102: 2556.75 | K102: 2751.85 | L102: 2466.55 | M102: 2536.25 | N102: 2486.8 | O102: 2731.85 | P102: 2552.6 | Q102: 2768.1 | R102: 2682.75 | S102: 2739.5 | T102: 2753.45 | U102: 2699.45 | V102: 2742.45 | W102: 2755.3 | X102: 2558.35 | Y102: 2672.65 | Z102: 2761.45 | AA102: 2658.95 | AB102: 2740.95 | AC102: 2656 | AD102: 2686.2 | AE102: 1851.65 | AF102: 2451.85 | AG102: 68799.65
B103: KALLPA GENERACION S.A. | C103: C.H. CERRO DEL AGUILA | D103: CENTRAL | E103: HIDROELÉCTRICA | F103: 5295.55 | G103: 5774.4 | H103: 6120.55 | I103: 4952.15 | J103: 5770.35 | K103: 3514.25 | L103: 3744.5 | M103: 3601.9 | N103: 2909.2 | O103: 1513.5 | P103: 4179.65 | Q103: 4789.15 | R103: 5093.9 | S103: 5039.8 | T103: 3842.25 | U103: 5922.1 | V103: 3267.92 | W103: 3658.045 | X103: 3230.9 | Y103: 4826.7 | Z103: 4602.3 | AA103: 5806.5 | AB103: 5043.6 | AC103: 2752.15 | AD103: 3115 | AE103: 5162.95 | AF103: 3435.55 | AG103: 116964.82
B104: KALLPA GENERACION S.A. | C104: C.S. SUNNY | D104: CENTRAL | E104: SOLAR | F104: 2198.25 | G104: 2019 | H104: 1409.95 | I104: 1564.5 | J104: 2174.65 | K104: 2295.75 | L104: 2073.8 | M104: 2014.8 | N104: 2103.85 | O104: 2252.4 | P104: 2177.9 | Q104: 2301.6 | R104: 2169.75 | S104: 2247.65 | T104: 2305.65 | U104: 2242.7 | V104: 2277.1 | W104: 2301.565 | X104: 2123.3 | Y104: 2290 | Z104: 2298.95 | AA104: 2291.5 | AB104: 2314 | AC104: 2190.7 | AD104: 2314.85 | AE104: 1315 | AF104: 2163.9 | AG104: 57433.065
B105: KALLPA GENERACION S.A. | C105: C.T. KALLPA | D105: TG1 | E105: TERMOELÉCTRICA | F105: 4146.15 | G105: 4046.6 | H105: 4104.4 | I105: 4145.1 | J105: 4296.02 | K105: 4265.7 | L105: 3211.55 | M105: 2328.65 | N105: 4267.45 | O105: 4299.85 | P105: 2776.45 | Q105: 1572.65 | R105: 2405.5 | S105: 268.95 | T105: 2885.3 | U105: 4371.85 | V105: 4361.22 | W105: 4366.545 | X105: 4312.5 | AB105: 2609.65 | AC105: 3884.05 | AE105: 3939.1 | AF105: 4374.7 | AG105: 81239.935
...

Sheet G_AREAS
B3: sábado, 27 de Diciembre del 2025
B5: HORA | C5: RESUMEN DE GENERACIÓN POR ÁREAS DEL SEIN | D5: RESUMEN DE GENERACIÓN POR ÁREAS DEL SEIN | E5: RESUMEN DE GENERACIÓN POR ÁREAS DEL SEIN | F5: RESUMEN DE GENERACIÓN POR ÁREAS DEL SEIN | G5: RESUMEN DE GENERACIÓN POR ÁREAS DEL SEIN | H5: RESUMEN DE GENERACIÓN POR ÁREAS DEL SEIN | I5: RESUMEN DE GENERACIÓN POR ÁREAS DEL SEIN | J5: RESUMEN DE GENERACIÓN POR ÁREAS DEL SEIN | K5: RESUMEN DE GENERACIÓN POR ÁREAS DEL SEIN | L5: RESUMEN DE GENERACIÓN POR ÁREAS DEL SEIN | M5: RESUMEN DE GENERACIÓN POR ÁREAS DEL SEIN | N5: RESUMEN DE GENERACIÓN POR ÁREAS DEL SEIN | O5: RESUMEN DE GENERACIÓN POR ÁREAS DEL SEIN | P5: RESUMEN DE GENERACIÓN POR ÁREAS DEL SEIN | Q5: RESUMEN DE GENERACIÓN POR ÁREAS DEL SEIN | R5: RESUMEN DE GENERACIÓN POR ÁREAS DEL SEIN | S5: HORA | T5: GENERACIÓN POR TIPO DE GENERACIÓN | U5: GENERACIÓN POR TIPO DE GENERACIÓN | V5: GENERACIÓN POR TIPO DE GENERACIÓN | W5: GENERACIÓN POR TIPO DE GENERACIÓN | X5: GENERACIÓN POR TIPO DE GENERACIÓN | Y5: HORA | Z5: GENERACIÓN POR TIPO DE GENERACIÓN | AA5: GENERACIÓN POR TIPO DE GENERACIÓN | AB5: GENERACIÓN POR TIPO DE GENERACIÓN | AC5: GENERACIÓN POR TIPO DE GENERACIÓN | AD5: GENERACIÓN POR TIPO DE GENERACIÓN
C6: NORTE | D6: NORTE | E6: NORTE | F6: NORTE | G6: CENTRO | H6: CENTRO | I6: CENTRO | J6: CENTRO | K6: SUR | L6: SUR | M6: SUR | N6: SUR | O6: GENERACIÓN INTEGRANTES COES | P6: GENERACIÓN INTEGRANTES COES | Q6: GENERACIÓN INTEGRANTES COES | R6: GENERACIÓN INTEGRANTES COES | T6: INTEGRANTES COES | U6: INTEGRANTES COES | V6: INTEGRANTES COES | W6: INTEGRANTES COES | X6: INTEGRANTES COES | Z6: INTEGRANTES COES RER | AA6: INTEGRANTES COES RER | AB6: INTEGRANTES COES RER | AC6: INTEGRANTES COES RER | AD6: INTEGRANTES COES RER
