Workbook

Sheet EVENTOS
B3: martes, 22 de Julio del 2025
B5: INFORMACIÓN DE EVENTOS PRINCIPALES EN SUS INSTALACIONES
B6: TIPO DE EVENTO | C6: EMPRESA | D6: UBICACIÓN | E6: TIPO DE EQUIPO | F6: EQUIPO | G6: INICIO | H6: FINAL | I6: DESCRIPCIÓN | J6: MW INDISP. | K6: INTERRUPCIÓN (SI/NO) | L6: TENSIÓN DE FALLA (kV)
B7: P.ENERG | C7: ATLANTICA TRANSMISION SUR S.A. | D7: MONTALVO | E7: TRANSFORMADOR 3D | F7: AUT-5672 | G7: 22/07/2025 13:50:00 | H7: 22/07/2025 13:50:00 | I7: PRIMERA ENERGIZACIÓN DEL AUTOTRANSFORMADOR AUT-5672 DE 500/220 KV EN LA S.E. MONTALVO | K7: NO
B8: EVENTO | C8: CONELSUR LT SAC | D8: PORTILLO | E8: SUBESTACION | F8: SS.EE. | G8: 22/07/2025 00:00:00 | H8: 23/07/2025 00:00:00 | I8: DECLARACIÓN DE SITUACIÓN EXCEPCIONAL EN LA S.E. PORTILLO DE 60 kV | K8: NO
B9: FALLA | C9: ISA PERU | D9: AGUAYTÍA - TINGO MARÍA | E9: LINEA DE TRANSMISION | F9: L-2251 | G9: 22/07/2025 10:36:00 | H9: 22/07/2025 11:22:00 | I9: DESCONEXIÓN DE LA LÍNEA L-2251 (TINGO MARÍA - AGUAYTÍA) DE 220 KV | K9: SI | L9: 220

Sheet RESTRIC_OPE
B3: martes, 22 de Julio del 2025
B5: RESTRICCIONES OPERATIVAS
B6: FECHA | C6: HORA INICIO | D6: HORA FINAL | E6: EMPRESA | F6: UBICACIÓN | G6: T.Eq. | H6: EQUIPO | I6: DESCRIPCIÓN
B7: 22/07/2025 | C7: 00:00 | D7: 24:00 | E7: EGASA | F7: C.H. CHARCANI II | G7: GH | H7: G2 | I7: El Grupo N°02 esta operando con una potencia no mayor a 0.07MW en referencia a 0.18MW de su potencia efectiva, con el fin de no generar daños mayores hasta la reparación de su cojinete.
B8: 22/07/2025 | C8: 00:00 | D8: 24:00 | E8: EGASA | F8: S.E. CONVERTIDOR | G8: BARRA | H8: BARRA138KV | I8: EGASA limitó la capacidad del transformador 138 kV/33 kV a 50 MVA por deterioro del aislamiento.
B9: 22/07/2025 | C9: 00:00 | D9: 24:00 | E9: ENEL GENERACION PIURA S.A. | F9: C.T. MALACAS | G9: CT | H9: CENTRAL | I9: De acuerdo con la comunicación vía correo del día 24.10.2024. ENEL GENERACIÓN PIURA informa una restricción de potencia para alcanzar 105 MW en simultaneo (TG6+TGN4).
B10: 22/07/2025 | C10: 00:00 | D10: 24:00 | E10: ENEL GENERACION PIURA S.A. | F10: C.T. MALACAS | G10: GT | H10: TG4 | I10: De acuerdo a lo informado mediante correo electronico el día 04.07, la uniadTG4 puede operar a potencia efectiva durante 3 horas o con 80MW durante 4 horas, y el resto de los periodos a mínima generación.
B11: 22/07/2025 | C11: 00:00 | D11: 24:00 | E11: ENGIE | F11: C.E. PUNTA LOMITAS | G11: CE | H11: CENTRAL | I11: De acuerdo a la carta ENG/737-2024 (Exp:202400007555). Limitación de cables de media tensión a 100 MW de los transformadores PLT1 y PLT2 de la CE Punta Lomitas. Quedan limitados a 200 MW la generación de CE Punta Lomitas y Punta Lomitas Extensión.
B12: 22/07/2025 | C12: 00:00 | D12: 24:00 | E12: ENGIE | F12: C.H. YUNCÁN | G12: GH | H12: G3 | I12: Según la carta N° ENG/ 198-2024 enviada por su representada, se opera de forma continua el G3 de la CH Yuncán, debido a la ejecución de mantenimientos necesarios para evitar daños en los sellos de seguridad de la válvula esférica del grupo.
B13: 22/07/2025 | C13: 00:00 | D13: 24:00 | E13: ENGIE | F13: C.T. CHILCA 1 | G13: CT | H13: CENTRAL | I13: Restricción de temperatura de la C.T Chilca, ver valor en el modelo de despacho.
B14: 22/07/2025 | C14: 00:00 | D14: 24:00 | E14: ENGIE | F14: C.T. CHILCA 1 | G14: CT | H14: CENTRAL | I14: Con carta ENG/971-2023, indica que no puede cumplir con las IO considerada en el PDO_17122023 dado que vulneran la seguridad de sus activos. Indican que se debe tomar TMO=168h.
B15: 22/07/2025 | C15: 00:00 | D15: 24:00 | E15: ENGIE | F15: C.T. CHILCA 2 | G15: CT | H15: CENTRAL | I15: Restricción de temperatura de la C.T Chilca2, ver valor en el modelo de despacho.
B16: 22/07/2025 | C16: 00:00 | D16: 24:00 | E16: ENGIE | F16: C.T. CHILCA 2 | G16: CT | H16: CENTRAL | I16: Con carta ENG/971-2023, indica que no puede cumplir con las IO considerada en el PDO_17122023 dado que vulneran la seguridad de sus activos. Indican que se debe tomar TMO=168h.
B17: 22/07/2025 | C17: 00:00 | D17: 24:00 | E17: FENIX POWER PERÚ | F17: C.T. FENIX | G17: CT | H17: CENTRAL | I17: Restricción de temperatura de la CT FENIX, ver valor en el modelo de despacho
... B42: 22/07/2025 | C42: 00:00 | D42: 24:00 | E42: TERMOSELVA | F42: C.T. AGUAYTÍA | G42: CT | H42: CENTRAL | I42: Disponibilidad de 23.5 MMSCF para la CT Aguaytía.

Sheet MANTENIMIENTO EJECUTADOS
B3: martes, 22 de Julio del 2025
B5: Mantenimiento Ejecutado
B6: Empresa | C6: Ubicación | D6: Equipo | E6: Inicio | F6: Final | G6: Descripción | H6: MW Indisp. | I6: Prog. | J6: Dispon | K6: Interrupc. | L6: Tipo | M6: CodEq | N6: TipoEq_Osinerg
B7: ACEROS AREQUIPA | C7: INDEPENDENCIA | D7: SA-2259 | E7: 22/07/2025 06:00 | F7: 22/07/2025 12:00 | G7: Se requiere la liberacion de la Barra A en la S.E. Indepedencia para Mantenimiento del Seccionador SA-2259 perteneciente a Aceros Arequipa. | H7: 0 | I7: P | J7: F/S | K7: N | L7: PREV. | M7: 10926 | N7: T
B8: ACEROS AREQUIPA | C8: INDEPENDENCIA | D8: SB-2261 | E8: 22/07/2025 12:00 | F8: 22/07/2025 18:00 | G8: Se requiere la liberacion de la Barra B en la S.E. Indepedencia para Mantenimiento del Seccionador SB-2261 perteneciente a Aceros Arequipa. | H8: 0 | I8: P | J8: F/S | K8: N | L8: PREV. | M8: 10925 | N8: T
B9: ACEROS AREQUIPA | C9: INDEPENDENCIA - ACEROS AREQUIPA | D9: L-2217 | E9: 22/07/2025 06:00 | F9: 22/07/2025 18:00 | G9: Mantenimiento Preventivo de la L.T. 220KV L-2217 | H9: 155 | I9: P | J9: F/S | K9: S | L9: PREV. | M9: 748 | N9: T
B10: ATLANTICA TRANSMISION SUR S.A. | C10: MONTALVO | D10: BARRA A_220KV | E10: 22/07/2025 00:00 | F10: 23/07/2025 00:00 | G10: Proyecto Refuerzos: Indisponibilidad de la proteccion diferencial de barras 220 kV por Conexion de la nueva UB-87B hacia la UC existente,Configuracion y Pruebas. | H10: 0 | I10: P | J10: E/S | K10: N | L10: P.ENERG | M10: 13869 | N10: T
B11: ATLANTICA TRANSMISION SUR S.A. | C11: MONTALVO | D11: BARRA A_500KV | E11: 22/07/2025 00:00 | F11: 23/07/2025 00:00 | G11: Proyecto Refuerzos: Indisponibilidad de la proteccion diferencial de barras 500kV por conexion de nueva UB-87B hacia la UC existente, Configuracion y Pruebas. | H11: 0 | I11: P | J11: E/S | K11: N | L11: P.ENERG | M11: 13870 | N11: T
B12: ATLANTICA TRANSMISION SUR S.A. | C12: MONTALVO | D12: BARRA B_220kV | E12: 22/07/2025 00:00 | F12: 23/07/2025 00:00 | G12: Proyecto Refuerzos: Indisponibilidad de la proteccion diferencial de barras 220 kV por Conexion de la nueva UB-87B hacia la UC existente,Configuracion y Pruebas. | H12: 0 | I12: P | J12: E/S | K12: N | L12: P.ENERG | M12: 14765 | N12: T
B13: ATLANTICA TRANSMISION SUR S.A. | C13: MONTALVO | D13: BARRA B_500KV | E13: 22/07/2025 00:00 | F13: 23/07/2025 00:00 | G13: Proyecto Refuerzos: Indisponibilidad de la proteccion diferencial de barras 500kV por conexion de nueva UB-87B hacia la UC existente, Configuracion y Pruebas. | H13: 0 | I13: P | J13: E/S | K13: N | L13: P.ENERG | M13: 13871 | N13: T
B14: ATLANTICA TRANSMISION SUR S.A. | C14: MONTALVO | D14: INT-5652 | E14: 22/07/2025 00:00 | F14: 23/07/2025 00:00 | G14: Proyecto Refuerzos: Indisponible por Implementacion de Conexion de corrientes, disparos, posiciones, enclavamientos hacia los equipos del nuevo Autotransformador. AUT-5671 en servicio solo por Barra A 500kV. | H14: 0 | I14: P | J14: F/S | K14: N | L14: P.ENERG | M14: 13765 | N14: T
B15: ATLANTICA TRANSMISION SUR S.A. | C15: MONTALVO | D15: ACOPLE 220 | E15: 22/07/2025 12:01 | F15: 22/07/2025 17:23 | G15: Proyecto Refuerzos: Reemplazo del HMI existente, Pruebas y Configuracion. No se contara con nivel 1 de operacion. | H15: 0 | I15: P | J15: E/S | K15: N | L15: P.ENERG | M15: 14767 | N15: T
B16: ATLANTICA TRANSMISION SUR S.A. | C16: MONTALVO | D16: CL-2057 | E16: 22/07/2025 12:01 | F16: 22/07/2025 17:23 | G16: Proyecto Refuerzos: Reemplazo del HMI existente, Pruebas y Configuracion. No se contara con nivel 1 de operacion. | H16: 0 | I16: P | J16: E/S | K16: N | L16: P.ENERG | M16: 13812 | N16: T
B17: ATLANTICA TRANSMISION SUR S.A. | C17: MONTALVO | D17: CL-AUT-5671_500 | E17: 22/07/2025 12:01 | F17: 22/07/2025 17:23 | G17: Proyecto Refuerzos: Reemplazo del HMI existente, Pruebas y Configuracion. No se contara con nivel 1 de operacion en INT-5671, INT-5652 y SAT-5671. | H17: 0 | I17: P | J17: E/S | K17: N | L17: P.ENERG | M17: 13809 | N17: T
B18: ATLANTICA TRANSMISION SUR S.A. | C18: MONTALVO | D18: INT-5672 | E18: 22/07/2025 13:50 | F18: 23/07/2025 00:00 | G18: Proyecto Refuerzos: Puesta en servicio del nuevo tercio del diametro INT-5672. Energizacion en vacio por 34 horas de AUT-5672. Prueba con nuevo rele de mando sincronizado PSD | H18: 0 | I18: P | J18: E/S | K18: N | L18: P.ENERG | M18: 24277 | N18: T
... B150: TRANSMANTARO | C150: YARABAMBA | D150: IN-5120 | E150: 22/07/2025 00:00 | F150: 23/07/2025 00:00 | G150: INTERRUPTOR INDISPONIBLE POR FALLA EN LOS MANDOS DE CONTROL DE N1, N2 Y N3. | H150: 0 | I150: P | J150: F/S | K150: N | L150: OTROS | M150: 17437 | N150: T

Sheet INGRESO OC
A3: martes, 22 de Julio del 2025
A5: INGRESO A OPERACIÓN COMERCIAL
A6: EMPRESA | B6: TIPO DE EQUIPO | C6: UBICACIÓN | D6: EQUIPO | E6: Fecha y hora de Ingreso a Operación Comercial
A7: VARI ENERGIA S.A.C. | B7: GENERADOR HIDROELÉCTRICO | C7: ANASHIRONI | D7: ANASHIRONI G1 | E7: 23/07/2025 00:00:00
A8: VARI ENERGIA S.A.C. | B8: CENTRAL HIDROELÉCTRICA | C8: ANASHIRONI | D8: C.H. ANASHIRONI | E8: 23/07/2025 00:00:00

Sheet DESPACHO_EJECUTADO
B3: martes, 22 de Julio del 2025
A5: POTENCIA ACTIVA EJECUTADA DE LAS UNIDADES DE GENERACIÓN DEL SEIN (MW) | FK5: CENTRALES NO INTEGRANTES COES
A6: FECHA | B6: HORA | C6: 65333 | D6: 101 | E6: 102 | F6: 42667 | G6: 42668 | H6: 126 | I6: 127 | J6: 138 | K6: 139 | L6: 197 | M6: 203 | N6: 204 | O6: 230 | P6: 209 | Q6: 56677 | R6: 796 | S6: 2146 | T6: 142 | U6: 143 | V6: 125 | W6: 187 | X6: 163 | Y6: 298 | Z6: 299 | AA6: 219 | AB6: 151 | AC6: 152 | AD6: 153 | AE6: 154 | AF6: 756 | AG6: 156 | AH6: 155 | AI6: 182 | AJ6: 212 | AK6: 758 | AL6: 263 | AM6: 265 | AN6: 775 | AO6: 777 | AP6: 2154 | AQ6: 150 | AR6: 149 | AS6: 188 | AT6: 2131 | AU6: 755 | AV6: 252 | AW6: 249 | AX6: 250 | AY6: 117 | AZ6: 267 | BA6: 268 | BB6: 119 | BC6: 120 | BD6: 189 | BE6: 122 | BF6: 266 | BG6: 337 | BH6: 338 | BI6: 251 | BJ6: 115 | BK6: 239 | BL6: 288 | BM6: 240 | BN6: 241 | BO6: 242 | BP6: 191 | BQ6: 194 | BR6: 196 | BS6: 207 | BT6: 236 | BU6: 795 | BV6: 285 | BW6: 995 | BX6: 996 | BY6: 997 | BZ6: 766 | CA6: 926 | CB6: 924 | CC6: 121 | CD6: 103 | CE6: 104 | CF6: 106 | CG6: 105 | CH6: 107 | CI6: 110 | CJ6: 109 | CK6: 144 | CL6: 113 | CM6: 114 | CN6: 193 | CO6: 208 | CP6: 786 | CQ6: 787 | CR6: 788 | CS6: 789 | CT6: 248 | CU6: 2159 | CV6: 303 | CW6: 59715 | CX6: 62255 | CY6: 1263 | CZ6: 61800 | DA6: 2194 | DB6: 69125 | DC6: 216 | DD6: 198 | DE6: 49607 | DF6: 214 | DG6: 260 | DH6: 2152 | DI6: 2128 | DJ6: 247 | DK6: 228 | DL6: 2135 | DM6: 261 | DN6: 237 | DO6: 253 | DP6: 770 | DQ6: 225 | DR6: 2201 | DS6: 2171 | DT6: 760 | DU6: 235 | DV6: 238 | DW6: 2184 | DX6: 61855 | DY6: 223 | DZ6: 226 | EA6: 201 | EB6: 258 | EC6: 259 | ED6: 920 | EE6: 257 | EF6: 256 | EG6: 2148 | EH6: 58288 | EI6: 58289 | EJ6: 58839 | EK6: 58840 | EL6: 296 | EM6: 297 | EN6: 211 | EO6: 2175 | EP6: 2178 | EQ6: 2181 | ER6: 1262 | ES6: 63425 | ET6: 233 | EU6: 2150 | EV6: 2165 | EW6: 2161 | EX6: 61197 | EY6: 58851 | EZ6: 234 | FA6: 215 | FB6: 917 | FC6: 289 | FD6: 58333 | FE6: 58336 | FF6: 213 | FG6: 232 | FH6: 2190 | FI6: TOTAL COES | FK6: 221 | FL6: 222 | FM6: 224 | FN6: 2187 | FO6: 227 | FP6: 49400 | FQ6: 199 | FR6: 200 | FS6: TOTAL NO COES
C7: SUR | D7: CENTRO | E7: CENTRO | F7: NORTE | G7: NORTE | H7: NORTE | I7: NORTE | J7: CENTRO | K7: CENTRO | L7: CENTRO | M7: CENTRO | N7: CENTRO | O7: CENTRO | P7: CENTRO | Q7: CENTRO | R7: CENTRO | S7: CENTRO | T7: CENTRO | U7: CENTRO | V7: CENTRO | W7: CENTRO | X7: SUR | Y7: SUR | Z7: SUR | AA7: CENTRO | AB7: SUR | AC7: SUR | AD7: SUR | AE7: SUR | AF7: SUR | AG7: SUR | AH7: SUR | AI7: SUR | AJ7: CENTRO | AK7: NORTE | AL7: NORTE | AM7: NORTE | AN7: CENTRO | AO7: CENTRO | AP7: CENTRO | AQ7: CENTRO | AR7: CENTRO | AS7: CENTRO | AT7: CENTRO | AU7: SUR | AV7: CENTRO | AW7: CENTRO | AX7: CENTRO | AY7: CENTRO | AZ7: CENTRO | BA7: CENTRO | BB7: CENTRO | BC7: CENTRO | BD7: SUR | BE7: NORTE | BF7: CENTRO | BG7: CENTRO | BH7: CENTRO | BI7: CENTRO | BJ7: NORTE | BK7: NORTE | BL7: NORTE | BM7: SUR | BN7: SUR | BO7: SUR | BP7: CENTRO | BQ7: CENTRO | BR7: CENTRO | BS7: CENTRO | BT7: CENTRO | BU7: CENTRO | BV7: CENTRO | BW7: SUR | BX7: SUR | BY7: SUR | BZ7: NORTE | CA7: SUR | CB7: CENTRO | CC7: NORTE | CD7: CENTRO | CE7: CENTRO | CF7: CENTRO | CG7: CENTRO | CH7: CENTRO | CI7: CENTRO | CJ7: CENTRO | CK7: CENTRO | CL7: CENTRO | CM7: CENTRO | CN7: CENTRO | CO7: CENTRO | CP7: SUR | CQ7: SUR | CR7: SUR | CS7: SUR | CT7: CENTRO | CU7: CENTRO | CV7: CENTRO | CW7: CENTRO | CX7: SUR | CY7: NORTE | CZ7: NORTE | DA7: NORTE | DB7: CENTRO | DC7: NORTE | DD7: NORTE | DE7: SUR | DF7: CENTRO | DG7: CENTRO | DH7: CENTRO | DI7: NORTE | DJ7: NORTE | DK7: CENTRO | DL7: CENTRO | DM7: SUR | DN7: SUR | DO7: CENTRO | DP7: CENTRO | DQ7: CENTRO | DR7: CENTRO | DS7: CENTRO | DT7: CENTRO | DU7: SUR | DV7: CENTRO | DW7: CENTRO | DX7: NORTE | DY7: CENTRO | DZ7: CENTRO | EA7: NORTE | EB7: CENTRO | EC7: CENTRO | ED7: CENTRO | EE7: NORTE | EF7: NORTE | EG7: SUR | EH7: CENTRO | EI7: CENTRO | EJ7: CENTRO | EK7: CENTRO | EL7: CENTRO | EM7: CENTRO | EN7: SUR | EO7: SUR | EP7: SUR | EQ7: SUR | ER7: NORTE | ES7: SUR | ET7: SUR | EU7: SUR | EV7: CENTRO | EW7: CENTRO | EX7: CENTRO | EY7: SUR | EZ7: SUR | FA7: NORTE | FB7: CENTRO | FC7: NORTE | FD7: NORTE | FE7: NORTE | FF7: CENTRO | FG7: NORTE | FH7: NORTE | FK7: NORTE | FL7: CENTRO | FM7: NORTE | FN7: NORTE | FO7: NORTE | FP7: NORTE | FQ7: NORTE | FR7: NORTE
C8: HIDROELÉCTRICA | D8: HIDROELÉCTRICA | E8: HIDROELÉCTRICA | F8: TERMOELÉCTRICA | G8: TERMOELÉCTRICA | H8: HIDROELÉCTRICA | I8: HIDROELÉCTRICA | J8: TERMOELÉCTRICA | K8: TERMOELÉCTRICA | L8: TERMOELÉCTRICA | M8: TERMOELÉCTRICA | N8: TERMOELÉCTRICA | O8: TERMOELÉCTRICA | P8: TERMOELÉCTRICA | Q8: TERMOELÉCTRICA | R8: HIDROELÉCTRICA | S8: HIDROELÉCTRICA | T8: TERMOELÉCTRICA | U8: TERMOELÉCTRICA | V8: TERMOELÉCTRICA | W8: TERMOELÉCTRICA | X8: HIDROELÉCTRICA | Y8: HIDROELÉCTRICA | Z8: HIDROELÉCTRICA | AA8: TERMOELÉCTRICA | AB8: HIDROELÉCTRICA | AC8: HIDROELÉCTRICA | AD8: HIDROELÉCTRICA | AE8: HIDROELÉCTRICA | AF8: TERMOELÉCTRICA | AG8: TERMOELÉCTRICA | AH8: TERMOELÉCTRICA | AI8: HIDROELÉCTRICA | AJ8: HIDROELÉCTRICA | AK8: TERMOELÉCTRICA | AL8: TERMOELÉCTRICA | AM8: TERMOELÉCTRICA | AN8: HIDROELÉCTRICA | AO8: HIDROELÉCTRICA | AP8: HIDROELÉCTRICA | AQ8: HIDROELÉCTRICA | AR8: HIDROELÉCTRICA | AS8: HIDROELÉCTRICA | AT8: HIDROELÉCTRICA | AU8: HIDROELÉCTRICA | AV8: TERMOELÉCTRICA | AW8: TERMOELÉCTRICA | AX8: TERMOELÉCTRICA | AY8: HIDROELÉCTRICA | AZ8: HIDROELÉCTRICA | BA8: HIDROELÉCTRICA | BB8: HIDROELÉCTRICA | BC8: HIDROELÉCTRICA | BD8: HIDROELÉCTRICA | BE8: HIDROELÉCTRICA | BF8: HIDROELÉCTRICA | BG8: HIDROELÉCTRICA | BH8: HIDROELÉCTRICA | BI8: HIDROELÉCTRICA | BJ8: TERMOELÉCTRICA | BK8: TERMOELÉCTRICA | BL8: TERMOELÉCTRICA | BM8: TERMOELÉCTRICA | BN8: TERMOELÉCTRICA | BO8: TERMOELÉCTRICA | BP8: HIDROELÉCTRICA | BQ8: TERMOELÉCTRICA | BR8: TERMOELÉCTRICA | BS8: TERMOELÉCTRICA | BT8: TERMOELÉCTRICA | BU8: TERMOELÉCTRICA | BV8: TERMOELÉCTRICA | BW8: TERMOELÉCTRICA | BX8: TERMOELÉCTRICA | BY8: TERMOELÉCTRICA | BZ8: HIDROELÉCTRICA | CA8: TERMOELÉCTRICA | CB8: TERMOELÉCTRICA | CC8: HIDROELÉCTRICA | CD8: HIDROELÉCTRICA | CE8: HIDROELÉCTRICA | CF8: HIDROELÉCTRICA | CG8: HIDROELÉCTRICA | CH8: HIDROELÉCTRICA | CI8: TERMOELÉCTRICA | CJ8: TERMOELÉCTRICA | CK8: TERMOELÉCTRICA | CL8: TERMOELÉCTRICA | CM8: TERMOELÉCTRICA | CN8: TERMOELÉCTRICA | CO8: TERMOELÉCTRICA | CP8: TERMOELÉCTRICA | CQ8: TERMOELÉCTRICA | CR8: TERMOELÉCTRICA | CS8: TERMOELÉCTRICA | CT8: TERMOELÉCTRICA | CU8: TERMOELÉCTRICA | CV8: SOLAR | CW8: EÓLICA | CX8: SOLAR | CY8: EÓLICA | CZ8: SOLAR | DA8: HIDROELÉCTRICA | DB8: HIDROELÉCTRICA | DC8: HIDROELÉCTRICA | DD8: HIDROELÉCTRICA | DE8: HIDROELÉCTRICA | DF8: HIDROELÉCTRICA | DG8: HIDROELÉCTRICA | DH8: HIDROELÉCTRICA | DI8: HIDROELÉCTRICA | DJ8: HIDROELÉCTRICA | DK8: HIDROELÉCTRICA | DL8: HIDROELÉCTRICA | DM8: SOLAR | DN8: SOLAR | DO8: EÓLICA | DP8: EÓLICA | DQ8: TERMOELÉCTRICA | DR8: TERMOELÉCTRICA | DS8: TERMOELÉCTRICA | DT8: TERMOELÉCTRICA | DU8: SOLAR | DV8: HIDROELÉCTRICA | DW8: HIDROELÉCTRICA | DX8: HIDROELÉCTRICA | DY8: HIDROELÉCTRICA | DZ8: HIDROELÉCTRICA | EA8: HIDROELÉCTRICA | EB8: HIDROELÉCTRICA | EC8: HIDROELÉCTRICA | ED8: HIDROELÉCTRICA | EE8: EÓLICA | EF8: EÓLICA | EG8: SOLAR | EH8: EÓLICA | EI8: EÓLICA | EJ8: EÓLICA | EK8: EÓLICA | EL8: HIDROELÉCTRICA | EM8: HIDROELÉCTRICA | EN8: HIDROELÉCTRICA | EO8: HIDROELÉCTRICA | EP8: HIDROELÉCTRICA | EQ8: HIDROELÉCTRICA | ER8: EÓLICA | ES8: SOLAR | ET8: SOLAR | EU8: SOLAR | EV8: HIDROELÉCTRICA | EW8: EÓLICA | EX8: EÓLICA | EY8: SOLAR | EZ8: SOLAR | FA8: HIDROELÉCTRICA | FB8: HIDROELÉCTRICA | FC8: TERMOELÉCTRICA | FD8: TERMOELÉCTRICA | FE8: TERMOELÉCTRICA | FF8: TERMOELÉCTRICA | FG8: TERMOELÉCTRICA | FH8: TERMOELÉCTRICA | FK8: HIDROELÉCTRICA | FL8: HIDROELÉCTRICA | FM8: HIDROELÉCTRICA | FN8: HIDROELÉCTRICA | FO8: TERMOELÉCTRICA | FP8: TERMOELÉCTRICA | FQ8: HIDROELÉCTRICA | FR8: HIDROELÉCTRICA
C9: HYDRO GLOBAL PERÚ S.A.C. | D9: ELECTROPERU | E9: ELECTROPERU | F9: ELECTROPERU | G9: ELECTROPERU | H9: ORAZUL ENERGY PERÚ | I9: ORAZUL ENERGY PERÚ | J9: TERMOSELVA | K9: TERMOSELVA | L9: KALLPA GENERACION S.A. | M9: KALLPA GENERACION S.A. | N9: KALLPA GENERACION S.A. | O9: KALLPA GENERACION S.A. | P9: KALLPA GENERACION S.A. | Q9: KALLPA GENERACION S.A. | R9: KALLPA GENERACION S.A. | S9: KALLPA GENERACION S.A. | T9: SHOUGESA | U9: SHOUGESA | V9: SHOUGESA | W9: SHOUGESA | X9: EGEMSA | Y9: EGESUR | Z9: EGESUR | AA9: EGESUR | AB9: EGASA | AC9: EGASA | AD9: EGASA | AE9: EGASA | AF9: EGASA | AG9: EGASA | AH9: EGASA | AI9: SAN GABAN | AJ9: CELEPSA | AK9: MINERA CERRO VERDE | AL9: PLANTA DE RESERVA FRIA DE GENERACION DE ETEN S.A. | AM9: PLANTA DE RESERVA FRIA DE GENERACION DE ETEN S.A. | AN9: EMPRESA DE GENERACION HUALLAGA | AO9: EMPRESA DE GENERACION HUALLAGA | AP9: LA VIRGEN | AQ9: CHINANGO S.A.C. | AR9: CHINANGO S.A.C. | AS9: HIDROELECTRICA HUANCHOR S.A.C. | AT9: CELEPSA RENOVABLES S.R.L. | AU9: INLAND ENERGY SAC | AV9: FENIX POWER PERÚ | AW9: FENIX POWER PERÚ | AX9: FENIX POWER PERÚ | AY9: STATKRAFT S.A | AZ9: STATKRAFT S.A | BA9: STATKRAFT S.A | BB9: STATKRAFT S.A | BC9: STATKRAFT S.A | BD9: STATKRAFT S.A | BE9: STATKRAFT S.A | BF9: STATKRAFT S.A | BG9: CENTRALES SANTA ROSA S.A.C. | BH9: CENTRALES SANTA ROSA S.A.C. | BI9: EMPRESA DE GENERACION HUANZA | BJ9: ENEL GENERACION PIURA S.A. | BK9: ENEL GENERACION PIURA S.A. | BL9: ENEL GENERACION PIURA S.A. | BM9: ENGIE | BN9: ENGIE | BO9: ENGIE | BP9: ENGIE | BQ9: ENGIE | BR9: ENGIE | BS9: ENGIE | BT9: ENGIE | BU9: ENGIE | BV9: ENGIE | BW9: ENGIE | BX9: ENGIE | BY9: ENGIE | BZ9: ENGIE | CA9: INFRAESTRUCTURAS Y ENERGIAS DEL PERU S.A.C. | CB9: INFRAESTRUCTURAS Y ENERGIAS DEL PERU S.A.C. | CC9: INVERSIONES SHAQSHA S.A.C. | CD9: ORYGEN PERU S.A.A. | CE9: ORYGEN PERU S.A.A. | CF9: ORYGEN PERU S.A.A. | CG9: ORYGEN PERU S.A.A. | CH9: ORYGEN PERU S.A.A. | CI9: ORYGEN PERU S.A.A. | CJ9: ORYGEN PERU S.A.A. | CK9: ORYGEN PERU S.A.A. | CL9: ORYGEN PERU S.A.A. | CM9: ORYGEN PERU S.A.A. | CN9: ORYGEN PERU S.A.A. | CO9: ORYGEN PERU S.A.A. | CP9: SAMAY I S.A.C | CQ9: SAMAY I S.A.C | CR9: SAMAY I S.A.C | CS9: SAMAY I S.A.C | CT9: TERMOCHILCA S.A.C. | CU9: TERMOCHILCA S.A.C. | CV9: COLCA SOLAR S.A.C. | CW9: ENERGIA RENOVABLE DEL SUR S.A. | CX9: GR CORTARRAMA SOCIEDAD ANONIMA CERRADA | CY9: GR TARUCA SOCIEDAD ANONIMA CERRADA | CZ9: KONDU SAC | DA9: PERUANA DE INVERSIONES EN ENERGIAS RENOVABLES S.A. | DB9: VARI ENERGIA S.A.C. | DC9: ORAZUL ENERGY PERÚ | DD9: ORAZUL ENERGY PERÚ | DE9: SAN GABAN | DF9: MAJA ENERGIA S.A.C. | DG9: EMPRESA DE GENERACION ELECTRICA CANCHAYLLO SAC | DH9: EMPRESA DE GENERACION ELECTRICA SANTA ANA S.A.C. | DI9: EMPRESA ELECTRICA AGUA AZUL | DJ9: EMPRESA ELECTRICA RIO DOBLE | DK9: HIDROCAÑETE S.A. | DL9: HUAURA POWER GROUP S.A. | DM9: MOQUEGUA FV S.A.C. | DN9: PANAMERICANA SOLAR SAC. | DO9: PARQUE EOLICO MARCONA S.A.C. | DP9: PARQUE EOLICO TRES HERMANAS S.A.C. | DQ9: PETRAMAS | DR9: PETRAMAS | DS9: PETRAMAS | DT9: PETRAMAS | DU9: TACNA SOLAR SAC. | DV9: ELECTRICA YANAPAMPA SAC | DW9: ANDEAN POWER S.A.C. | DX9: ASOCIACIÓN SANTA LUCIA DE CHACAS | DY9: ATRIA ENERGIA S.A.C. | DZ9: EGEJUNIN | EA9: EGEJUNIN | EB9: EGEJUNIN | EC9: EGEJUNIN | ED9: EMPRESA DE GENERACION ELECTRICA RIO BAÑOS S.A.C. | EE9: ENERGÍA EÓLICA S.A. | EF9: ENERGÍA EÓLICA S.A. | EG9: ENGIE | EH9: ENGIE | EI9: ENGIE | EJ9: ENGIE | EK9: ENGIE | EL9: GENERACIÓN ANDINA S.A.C. | EM9: GENERACIÓN ANDINA S.A.C. | EN9: GENERADORA DE ENERGÍA DEL PERÚ | EO9: GENERADORA DE ENERGÍA DEL PERÚ | EP9: GENERADORA DE ENERGÍA DEL PERÚ | EQ9: GENERADORA DE ENERGÍA DEL PERÚ | ER9: GR PAINO SOCIEDAD ANONIMA CERRADA | ES9: JOYA SOLAR S.A.C. | ET9: MAJES ARCUS S.A.C. | EU9: ORYGEN PERU S.A.A. | EV9: ORYGEN PERU S.A.A. | EW9: ORYGEN PERU S.A.A. | EX9: ORYGEN PERU S.A.A. | EY9: ORYGEN PERU S.A.A. | EZ9: REPARTICIÓN ARCUS S.A.C. | FA9: SINERSA | FB9: SINERSA | FC9: BIOENERGIA DEL CHIRA S.A. | FD9: GM OPERACIONES S.A.C. | FE9: GM OPERACIONES S.A.C. | FF9: AGRO INDUSTRIAL PARAMONGA S.A. | FG9: AGROAURORA S.A.C. | FH9: AGROINDUSTRIAS SAN JACINTO S.A.A. | FK9: UNACEM PERU S.A. | FL9: ELECTRO ORIENTE | FM9: AGUAS Y ENERGIA PERU | FN9: ELECTRO ZAÑA S.A.C. | FO9: ELECTRONOROESTE S.A. | FP9: SDE PIURA | FQ9: SINERSA | FR9: SINERSA
C10: SAN GABAN III | D10: MANTARO | E10: RESTITUCION | F10: TUMBES MAK 1 | G10: TUMBES MAK 2 | H10: CARHUAQUERO | I10: CAÑON DEL PATO | J10: AGUAYTIA TG1 | K10: AGUAYTIA TG2 | L10: KALLPA TG1 | M10: KALLPA TG2 | N10: KALLPA TG3 | O10: KALLPA TV | P10: LFLORES TG1 | Q10: LFLORES TV | R10: CERRO DEL AGUILA | S10: CERRODELAGUILAG4 | T10: SHOUGESA TV1 | U10: SHOUGESA TV2 | V10: SHOUGESA TV3 | W10: SHOUGESA CUMMINS | X10: MACHUPICCHU | Y10: ARICOTA 1 | Z10: ARICOTA 2 | AA10: INDEPENDENCIA | AB10: CHARCANI I,II,III | AC10: CHARCANI IV | AD10: CHARCANI V | AE10: CHARCANI VI | AF10: CHILINA TG | AG10: MOLLENDO 1, 2, 3 | AH10: CHILINA (SULZ 1,2) | AI10: SAN GABAN II | AJ10: PLATANAL | AK10: RECKA | AL10: RF ETEN TG1 | AM10: RF ETEN TG2 | AN10: CHAGLLA GP1 | AO10: CHAGLLA | AP10: LA VIRGEN | AQ10: CHIMAY | AR10: YANANGO | AS10: HUANCHOR | AT10: MARAÑON | AU10: STA TERESA | AV10: FENIX GT11 | AW10: FENIX GT12 | AX10: FENIX TV10 | AY10: YAUPI | AZ10: OROYA | BA10: PACHACHACA | BB10: MALPASO | BC10: CAHUA | BD10: ARCATA | BE10: GALLITO CIEGO | BF10: CHEVES | BG10: SANTA ROSA 1 | BH10: SANTA ROSA 2 | BI10: HUANZA | BJ10: MALACAS2 TG4 | BK10: MALACAS3 TG 5 | BL10: MALACAS1 TG6 | BM10: RF ILO2 TG1 | BN10: RF ILO2 TG2 | BO10: RF ILO2 TG3 | BP10: YUNCAN | BQ10: CHILCA1 TG1 | BR10: CHILCA1 TG2 | BS10: CHILCA1 TG3 | BT10: CHILCA-TV | BU10: CHILCA2 TG41 | BV10: CHILCA2-TV | BW10: CTNEPI_TG41 | BX10: CTNEPI_TG42 | BY10: CTNEPI_TG43 | BZ10: QUITARACSA | CA10: RF PTO MALDONADO | CB10: RF PUCALLPA | CC10: PARIAC | CD10: HUINCO | CE10: MATUCANA | CF10: MOYOPAMPA | CG10: CALLAHUANCA | CH10: HUAMPANI | CI10: STA ROSA WEST TG7 | CJ10: UTI_5 | CK10: UTI_6 | CL10: VENTANILLA 3 | CM10: VENTANILLA 4 | CN10: VENTANILLA TV | CO10: STAROSA TG8 | CP10: PTO_BRVO TG1 | CQ10: PTO_BRVO TG2 | CR10: PTO_BRVO TG3 | CS10: PTO_BRVO TG4 | CT10: OLLEROS TG1 | CU10: OLLEROS TV | CV10: CS YARUCAYA | CW10: SAN JUAN | CX10: MATARANI | CY10: DUNA | CZ10: CARHUAQUERO (CS) | DA10: MANTA I | DB10: ANASHIRONI | DC10: CARHUAQUERO4 | DD10: CAÑA BRAVA | DE10: TUPURI | DF10: RONCADOR | DG10: CANCHAYLLO | DH10: RENOVANDESH1 | DI10: POTRERO | DJ10: PIZARRAS | DK10: NIMPERIAL | DL10: YARUCAYA | DM10: MOQUEGUA-SOLAR | DN10: PANAMERICANA-SOLAR | DO10: PQE-EOLICO-MARCONA | DP10: PQE-EOLICO-3-HERMANAS | DQ10: HUAYCOLORO | DR10: CALLAO | DS10: DONA_CATALINA | DT10: LAGRINGAV | DU10: TACNA-SOLAR | DV10: YANAPAMPA | DW10: CARHUAC | DX10: HUALLIN | DY10: PURMACANA | DZ10: HUASAHUASI | EA10: STACRUZ_1_2 | EB10: RUNATULLO_II | EC10: RUNATULLO_III | ED10: RUCUY | EE10: PQE-EOLICO-TALARA | EF10: PQE-EOLICO-CUPISNIQUE | EG10: INTIPAMPA | EH10: PUNTA LOMITAS-BL1 | EI10: PUNTA LOMITAS-BL2 | EJ10: PUN LOMITAS_EXP-BL1 | EK10: PUN LOMITAS_EXP-BL2 | EL10: 8AGOSTO | EM10: EL CARMEN | EN10: LA JOYA | EO10: ANGEL_I | EP10: ANGEL_II | EQ10: ANGEL_III | ER10: HUAMBOS | ES10: SAN MARTIN SOLAR | ET10: MAJES | EU10: RUBI | EV10: CH_HER1 | EW10: WAYRA-I | EX10: WAYRA EXTENSION | EY10: CLEMESI | EZ10: REPARTICION | FA10: POECHOS2 | FB10: CHANCAY | FC10: CANA BRAVA | FD10: REFINERIA TALARA TV1 | FE10: REFINERÍA TALARA TV2 | FF10: PARAMONGA | FG10: MAPLE | FH10: SAN_JACINTO | FI10: MW | FK10: CARPAPATA | FL10: CENTRALES ELOR | FM10: PIAS1 | FN10: ZANA | FO10: TABLAZO | FP10: TALLANCA | FQ10: CURUMUY | FR10: POECHOS1 | FS10: MW
A11: 22/07/2025 | B11: 00:30 | C11: 23.4 | D11: 580.5 | E11: 145.6 | H11: 21.3 | I11: 72.7 | L11: 188.3 | M11: 207.5 | N11: 210.2 | O11: 290.8 | P11: 216 | Q11: 111.9 | R11: 375.7 | S11: 4.3 | X11: 111.5 | Y11: 7.1 | Z11: 4.6 | AB11: 6.8 | AC11: 14.9 | AD11: 82.8 | AI11: 31.4 | AJ11: 44 | AN11: 6.5 | AO11: 0 | AP11: 30.4 | AQ11: 74.1 | AR11: 20.1 | AS11: 18.7 | AT11: 13.6 | AU11: 57.6 | AV11: 180.5 | AW11: 180.5 | AX11: 184.8 | AY11: 81.8 | AZ11: 8 | BA11: 4.9 | BB11: 33.3 | BC11: 35.2 | BD11: 2 | BE11: 17.2 | BF11: 85.2 | BI11: 44.8 | BL11: 0 | BP11: 65.7 | BQ11: 178.5 | BR11: 175.8 | BS11: 209.9 | BT11: 274.3 | CB11: 0 | CC11: 1 | CD11: 168 | CE11: 100.3 | CF11: 64.3 | CG11: 72.8 | CH11: 29.7 | CL11: 146.6 | CM11: 148.9 | CN11: 150.6 | CT11: 218.9 | CU11: 105.1 | CV11: 0 | CW11: 39.1 | CX11: 0 | CY11: 12.8 | CZ11: 0 | DA11: 7.7 | DB11: 5.027 | DC11: 9.9 | DD11: 5.3 | DE11: 0.3 | DF11: 3.2 | DG11: 2 | DH11: 19 | DI11: 6.2 | DJ11: 4.5 | DK11: 3.4 | DL11: 18 | DM11: 0 | DN11: 0 | DO11: 9.9 | DP11: 26.4 | DQ11: 4.5 | DR11: 0.6 | DS11: 2.4 | DT11: 2.6 | DU11: 0 | DV11: 2.4 | DW11: 9.8 | DX11: 1.4 | DZ11: 4.7 | EA11: 3.4 | EB11: 3.1 | EC11: 5.2 | ED11: 15.7 | EE11: 26.2 | EF11: 23.3 | EG11: 0 | EH11: 8.4 | EI11: 26.7 | EJ11: 0.1 | EK11: 0 | EL11: 6.5 | EM11: 2.1 | EN11: 9.1 | EO11: 4 | EP11: 4.6 | EQ11: 4.6 | ER11: 7.8 | ES11: 0 | ET11: 0 | EU11: 0 | EV11: 0.6 | EW11: 0 | EX11: 0 | EY11: 0 | EZ11: 0 | FA11: 10 | FB11: 18.7 | FC11: 9.5 | FD11: 36.9 | FE11: 27.8 | FF11: 13.5 | FG11: 19.1 | FH11: 8.1 | FI11: 6437.027 | FK11: 19.86605 | FL11: 0 | FM11: 6.088 | FN11: 7.2 | FO11: 27.23995 | FP11: 18.86653 | FQ11: 9.7 | FR11: 16 | FS11: 104.96053
A12: 22/07/2025 | B12: 01:00 | C12: 33.2 | D12: 580.3 | E12: 145.5 | H12: 0 | I12: 73 | L12: 188.4 | M12: 205.8 | N12: 208.6 | O12: 288.9 | P12: 215.2 | Q12: 111.9 | R12: 375.3 | S12: 4.4 | X12: 111.1 | Y12: 7.4 | Z12: 5 | AB12: 6.8 | AC12: 14.8 | AD12: 83 | AI12: 34.4 | AJ12: 43.6 | AN12: 6.5 | AO12: 151.6 | AP12: 31 | AQ12: 56.6 | AR12: 19.3 | AS12: 18.6 | AT12: 13.6 | AU12: 59.7 | AV12: 183 | AW12: 183.1 | AX12: 183.1 | AY12: 83.2 | AZ12: 8 | BA12: 4.9 | BB12: 24.7 | BC12: 34.8 | BD12: 2 | BE12: 0 | BF12: 20.6 | BI12: 45 | BL12: 0 | BP12: 66.4 | BQ12: 179 | BR12: 176.4 | BS12: 210.7 | BT12: 274.3 | CB12: 0 | CC12: 1 | CD12: 103.6 | CE12: 88.4 | CF12: 62.9 | CG12: 72.9 | CH12: 30.1 | CL12: 145 | CM12: 147.7 | CN12: 148.7 | CT12: 218.8 | CU12: 105.2 | CV12: 0 | CW12: 44.8 | CX12: 0 | CY12: 13.1 | CZ12: 0 | DA12: 7.6 | DB12: 5.148 | DC12: 0 | DD12: 0 | DE12: 0.3 | DF12: 3.2 | DG12: 2.1 | DH12: 19 | DI12: 6.4 | DJ12: 4.5 | DK12: 3.4 | DL12: 18 | DM12: 0 | DN12: 0 | DO12: 11.6 | DP12: 33.8 | DQ12: 4.5 | DR12: 1.1 | DS12: 2.4 | DT12: 2.6 | DU12: 0 | DV12: 2.4 | DW12: 11.9 | DX12: 1.4 | DZ12: 4.7 | EA12: 3.4 | EB12: 3.2 | EC12: 4.6 | ED12: 15.3 | EE12: 24.3 | EF12: 14.6 | EG12: 0 | EH12: 9.5 | EI12: 26.2 | EJ12: 0.1 | EK12: 0 | EL12: 6.5 | EM12: 2.1 | EN12: 9.1 | EO12: 4 | EP12: 4.6 | EQ12: 4.6 | ER12: 8.5 | ES12: 0 | ET12: 0 | EU12: 0 | EV12: 0.6 | EW12: 1.6 | EX12: 0.4 | EY12: 0 | EZ12: 0 | FA12: 10 | FB12: 18.6 | FC12: 8.9 | FD12: 37 | FE12: 27.9 | FF12: 13 | FG12: 19.1 | FH12: 7.1 | FI12: 6385.748 | FK12: 19.74684 | FL12: 0 | FM12: 6.088 | FN12: 7.2 | FO12: 27.26791 | FP12: 18.86565 | FQ12: 9.9 | FR12: 15.9 | FS12: 104.9684
A13: 22/07/2025 | B13: 01:30 | C13: 25.3 | D13: 576.9 | E13: 145 | H13: 0 | I13: 72.4 | L13: 187.3 | M13: 207.5 | N13: 211.9 | O13: 287.1 | P13: 217.5 | Q13: 111.9 | R13: 368.1 | S13: 4.3 | X13: 111.9 | Y13: 7 | Z13: 5.3 | AB13: 6.8 | AC13: 12.3 | AD13: 49.4 | AI13: 34.7 | AJ13: 33.2 | AN13: 6.5 | AO13: 152 | AP13: 31 | AQ13: 0 | AR13: 20.2 | AS13: 18.5 | AT13: 13.4 | AU13: 58.3 | AV13: 180.9 | AW13: 181.2 | AX13: 183.1 | AY13: 82.8 | AZ13: 7.9 | BA13: 4.9 | BB13: 18.4 | BC13: 25.7 | BD13: 2 | BE13: 0 | BF13: 19.2 | BI13: 44.6 | BL13: 0 | BP13: 65.8 | BQ13: 179 | BR13: 176.3 | BS13: 210.6 | BT13: 274.5 | CB13: 0 | CC13: 1 | CD13: 79.3 | CE13: 81 | CF13: 62.2 | CG13: 72.9 | CH13: 29.7 | CL13: 146.1 | CM13: 148.6 | CN13: 149.7 | CT13: 218 | CU13: 105 | CV13: 0 | CW13: 39.7 | CX13: 0 | CY13: 14 | CZ13: 0 | DA13: 7.6 | DB13: 5.069 | DC13: 0 | DD13: 0 | DE13: 0.3 | DF13: 3.1 | DG13: 2.1 | DH13: 19.2 | DI13: 6.6 | DJ13: 4.5 | DK13: 3.4 | DL13: 18 | DM13: 0 | DN13: 0 | DO13: 11.4 | DP13: 37.3 | DQ13: 4.5 | DR13: 1.2 | DS13: 2.4 | DT13: 2.6 | DU13: 0 | DV13: 2.4 | DW13: 11.9 | DX13: 1.4 | DZ13: 4.7 | EA13: 3.4 | EB13: 3 | EC13: 4.3 | ED13: 15.3 | EE13: 25.7 | EF13: 11.6 | EG13: 0 | EH13: 11.3 | EI13: 26.2 | EJ13: 0.7 | EK13: 0.2 | EL13: 6.3 | EM13: 2.1 | EN13: 9.1 | EO13: 4 | EP13: 4.6 | EQ13: 4.6 | ER13: 8.7 | ES13: 0 | ET13: 0 | EU13: 0 | EV13: 0.6 | EW13: 17.5 | EX13: 8.5 | EY13: 0 | EZ13: 0 | FA13: 10 | FB13: 18.6 | FC13: 9.4 | FD13: 37.1 | FE13: 27.9 | FF13: 13.5 | FG13: 19.1 | FH13: 8.5 | FI13: 6241.269 | FK13: 20.27253 | FL13: 0 | FM13: 6.088 | FN13: 7.2 | FO13: 27.2691 | FP13: 18.86558 | FQ13: 9.9 | FR13: 15.9 | FS13: 105.49521
A14: 22/07/2025 | B14: 02:00 | C14: 26.5 | D14: 575.9 | E14: 144.2 | H14: 0 | I14: 74.8 | L14: 189 | M14: 208.4 | N14: 211.9 | O14: 286.9 | P14: 216.6 | Q14: 112.3 | R14: 369.3 | S14: 4.2 | X14: 112 | Y14: 6.9 | Z14: 5.3 | AB14: 6.8 | AC14: 12 | AD14: 48.9 | AI14: 34.4 | AJ14: 23 | AN14: 6.5 | AO14: 151.2 | AP14: 29.2 | AQ14: 0 | AR14: 20.1 | AS14: 18.3 | AT14: 13.4 | AU14: 57.6 | AV14: 180.5 | AW14: 181.2 | AX14: 182 | AY14: 83.3 | AZ14: 8 | BA14: 4.7 | BB14: 18.4 | BC14: 25.5 | BD14: 2 | BE14: 0 | BF14: 19.3 | BI14: 44.6 | BL14: 0 | BP14: 66.7 | BQ14: 178.4 | BR14: 176.2 | BS14: 210.5 | BT14: 275 | CB14: 0 | CC14: 1 | CD14: 78.2 | CE14: 94.9 | CF14: 43.7 | CG14: 72.9 | CH14: 29.7 | CL14: 146.9 | CM14: 149.2 | CN14: 151 | CT14: 218.8 | CU14: 105.1 | CV14: 0 | CW14: 45.8 | CX14: 0 | CY14: 13.5 | CZ14: 0 | DA14: 7.7 | DB14: 5.029 | DC14: 0 | DD14: 0 | DE14: 0.3 | DF14: 2.8 | DG14: 2.1 | DH14: 19.2 | DI14: 6.6 | DJ14: 7.5 | DK14: 3.4 | DL14: 18 | DM14: 0 | DN14: 0 | DO14: 9.8 | DP14: 28.4 | DQ14: 4.5 | DR14: 1.2 | DS14: 2.4 | DT14: 2.6 | DU14: 0 | DV14: 2.4 | DW14: 11.7 | DX14: 1.3 | DZ14: 4.7 | EA14: 3.4 | EB14: 3 | EC14: 4.4 | ED14: 15.2 | EE14: 26.8 | EF14: 12.9 | EG14: 0 | EH14: 9 | EI14: 22.8 | EJ14: 1.2 | EK14: 0.5 | EL14: 6.2 | EM14: 2.1 | EN14: 9.1 | EO14: 3.8 | EP14: 4.2 | EQ14: 4.2 | ER14: 9.8 | ES14: 0 | ET14: 0 | EU14: 0 | EV14: 0.6 | EW14: 16.8 | EX14: 13.8 | EY14: 0 | EZ14: 0 | FA14: 10 | FB14: 18.4 | FC14: 9.6 | FD14: 37.1 | FE14: 27.9 | FF14: 14 | FG14: 18.9 | FH14: 8.6 | FI14: 6228.529 | FK14: 20.28504 | FL14: 0 | FM14: 6.084 | FN14: 7.2 | FO14: 27.26437 | FP14: 18.86524 | FQ14: 9.8 | FR14: 16 | FS14: 105.49865
A15: 22/07/2025 | B15: 02:30 | C15: 31.1 | D15: 577.8 | E15: 144.6 | H15: 0 | I15: 77.2 | L15: 188.3 | M15: 207 | N15: 210.7 | O15: 288.4 | P15: 217.1 | Q15: 112.1 | R15: 195.5 | S15: 4.3 | X15: 115.1 | Y15: 7.9 | Z15: 5.4 | AB15: 6.8 | AC15: 12 | AD15: 49.9 | AI15: 35.1 | AJ15: 24 | AN15: 6.5 | AO15: 152.2 | AP15: 30.8 | AQ15: 0 | AR15: 21.5 | AS15: 18.5 | AT15: 13.4 | AU15: 59.3 | AV15: 181.8 | AW15: 182.2 | AX15: 182.7 | AY15: 83.7 | AZ15: 8 | BA15: 4.7 | BB15: 19 | BC15: 25.8 | BD15: 2 | BE15: 0 | BF15: 19.6 | BI15: 44.8 | BL15: 0 | BP15: 67 | BQ15: 178.2 | BR15: 175.5 | BS15: 209.7 | BT15: 274.1 | CB15: 0 | CC15: 0.9 | CD15: 82.4 | CE15: 98.5 | CF15: 70.2 | CG15: 73 | CH15: 27.9 | CL15: 146.3 | CM15: 148.7 | CN15: 150.5 | CT15: 218.7 | CU15: 105.1 | CV15: 0 | CW15: 41.9 | CX15: 0 | CY15: 11.4 | CZ15: 0 | DA15: 7.8 | DB15: 5.068 | DC15: 0 | DD15: 0 | DE15: 0.3 | DF15: 2.7 | DG15: 2 | DH15: 19.2 | DI15: 6.8 | DJ15: 7.5 | DK15: 3.4 | DL15: 18 | DM15: 0 | DN15: 0 | DO15: 8.9 | DP15: 25.6 | DQ15: 4.5 | DR15: 1.2 | DS15: 2.4 | DT15: 2.6 | DU15: 0 | DV15: 1.8 | DW15: 11.8 | DX15: 1.3 | DZ15: 4.7 | EA15: 3.4 | EB15: 3.1 | EC15: 4.4 | ED15: 15.4 | EE15: 21.1 | EF15: 10 | EG15: 0 | EH15: 10.1 | EI15: 23.2 | EJ15: 1.3 | EK15: 0 | EL15: 6.2 | EM15: 2.1 | EN15: 9.1 | EO15: 3.8 | EP15: 4.2 | EQ15: 4.2 | ER15: 8.1 | ES15: 0 | ET15: 0 | EU15: 0 | EV15: 0.6 | EW15: 10.3 | EX15: 5 | EY15: 0 | EZ15: 0 | FA15: 9.9 | FB15: 18.5 | FC15: 9.6 | FD15: 37.2 | FE15: 27.8 | FF15: 13.3 | FG15: 19.1 | FH15: 7.1 | FI15: 6072.468 | FK15: 20.54564 | FL15: 0 | FM15: 6.088 | FN15: 7.2 | FO15: 27.22097 | FP15: 18.86496 | FQ15: 9.8 | FR15: 16.1 | FS15: 105.81957
A16: 22/07/2025 | B16: 03:00 | C16: 30.1 | D16: 580.1 | E16: 145.4 | H16: 0 | I16: 74.9 | L16: 188.2 | M16: 206.8 | N16: 209.9 | O16: 289.5 | P16: 216.7 | Q16: 111.7 | R16: 197.8 | S16: 4.3 | X16: 112.7 | Y16: 8.1 | Z16: 4.6 | AB16: 6.9 | AC16: 12 | AD16: 50.2 | AI16: 35.4 | AJ16: 63.1 | AN16: 6.5 | AO16: 151.8 | AP16: 33 | AQ16: 0 | AR16: 22 | AS16: 18.6 | AT16: 13.5 | AU16: 58 | AV16: 182.4 | AW16: 183.1 | AX16: 183.7 | AY16: 83.8 | AZ16: 8 | BA16: 4.7 | BB16: 21 | BC16: 26.9 | BD16: 2 | BE16: 0 | BF16: 20.6 | BI16: 45 | BL16: 0 | BP16: 67.1 | BQ16: 178.1 | BR16: 175.6 | BS16: 209.7 | BT16: 274.4 | CB16: 0 | CC16: 1 | CD16: 91.1 | CE16: 101.9 | CF16: 70.5 | CG16: 73 | CH16: 28.1 | CL16: 146.5 | CM16: 148.4 | CN16: 149.9 | CT16: 218.5 | CU16: 105.1 | CV16: 0 | CW16: 35 | CX16: 0 | CY16: 14.1 | CZ16: 0 | DA16: 7.7 | DB16: 5.12 | DC16: 0 | DD16: 0 | DE16: 0.3 | DF16: 2.9 | DG16: 2 | DH16: 19.3 | DI16: 6.8 | DJ16: 7.5 | DK16: 3.4 | DL16: 18 | DM16: 0 | DN16: 0 | DO16: 9.9 | DP16: 23.7 | DQ16: 4.5 | DR16: 1.2 | DS16: 2.4 | DT16: 2.6 | DU16: 0 | DV16: 1.8 | DW16: 12 | DX16: 1.3 | DZ16: 4.7 | EA16: 3.4 | EB16: 3.2 | EC16: 4.5 | ED16: 16.3 | EE16: 18.5 | EF16: 7 | EG16: 0 | EH16: 16.2 | EI16: 30.7 | EJ16: 2.3 | EK16: 1 | EL16: 6.2 | EM16: 2.1 | EN16: 9.1 | EO16: 3.8 | EP16: 4.2 | EQ16: 4.2 | ER16: 9.8 | ES16: 0 | ET16: 0 | EU16: 0 | EV16: 0.6 | EW16: 4.8 | EX16: 1.8 | EY16: 0 | EZ16: 0 | FA16: 10 | FB16: 18.9 | FC16: 9.5 | FD16: 37.2 | FE16: 27.8 | FF16: 13.1 | FG16: 19.1 | FH16: 8.1 | FI16: 6131.52 | FK16: 20.60876 | FL16: 0 | FM16: 6.084 | FN16: 7.2 | FO16: 27.14751 | FP16: 18.86511 | FQ16: 9.7 | FR16: 16 | FS16: 105.60538
A17: 22/07/2025 | B17: 03:30 | C17: 27.2 | D17: 581.2 | E17: 146 | H17: 0 | I17: 75.6 | L17: 187.9 | M17: 206.5 | N17: 210.1 | O17: 290 | P17: 217.2 | Q17: 111.5 | R17: 198.9 | S17: 4.3 | X17: 110.1 | Y17: 8.3 | Z17: 5.2 | AB17: 6.9 | AC17: 12 | AD17: 50.8 | AI17: 38.1 | AJ17: 34.2 | AN17: 6.5 | AO17: 152.2 | AP17: 32.3 | AQ17: 0 | AR17: 20.6 | AS17: 18.5 | AT17: 13.5 | AU17: 59.3 | AV17: 182.4 | AW17: 183.3 | AX17: 183.7 | AY17: 83.6 | AZ17: 8 | BA17: 4.7 | BB17: 23.2 | BC17: 40 | BD17: 2 | BE17: 0 | BF17: 21 | BI17: 45.1 | BL17: 0 | BP17: 67.1 | BQ17: 177.9 | BR17: 175.4 | BS17: 209.9 | BT17: 274.2 | CB17: 0 | CC17: 1 | CD17: 99.2 | CE17: 101.3 | CF17: 46.2 | CG17: 72.9 | CH17: 28.7 | CL17: 146 | CM17: 148.4 | CN17: 150 | CT17: 218 | CU17: 105.1 | CV17: 0 | CW17: 35.1 | CX17: 0 | CY17: 13.7 | CZ17: 0 | DA17: 7.7 | DB17: 5.097 | DC17: 0 | DD17: 0 | DE17: 0.3 | DF17: 3 | DG17: 2 | DH17: 19.3 | DI17: 7 | DJ17: 7.5 | DK17: 3.4 | DL17: 18 | DM17: 0 | DN17: 0 | DO17: 10 | DP17: 19.5 | DQ17: 4.5 | DR17: 1.2 | DS17: 2.4 | DT17: 2.6 | DU17: 0 | DV17: 1.8 | DW17: 12 | DX17: 1.3 | DZ17: 4.7 | EA17: 3.5 | EB17: 3.3 | EC17: 4.6 | ED17: 15.7 | EE17: 22.9 | EF17: 7.3 | EG17: 0 | EH17: 18.9 | EI17: 40 | EJ17: 2.1 | EK17: 0.9 | EL17: 6.2 | EM17: 2.1 | EN17: 9.2 | EO17: 3.8 | EP17: 4.2 | EQ17: 4.2 | ER17: 10.3 | ES17: 0 | ET17: 0 | EU17: 0 | EV17: 0.6 | EW17: 6.6 | EX17: 3.4 | EY17: 0 | EZ17: 0 | FA17: 10 | FB17: 18.6 | FC17: 9.4 | FD17: 37.1 | FE17: 27.8 | FF17: 13.3 | FG17: 19.1 | FH17: 8.6 | FI17: 6118.997 | FK17: 20.70648 | FL17: 0 | FM17: 6.088 | FN17: 7.2 | FO17: 27.20632 | FP17: 18.86515 | FQ17: 9.7 | FR17: 15.9 | FS17: 105.66595
A18: 22/07/2025 | B18: 04:00 | C18: 30.6 | D18: 580.1 | E18: 145.6 | H18: 0 | I18: 75.1 | L18: 188.6 | M18: 207.8 | N18: 211 | O18: 288.9 | P18: 218.1 | Q18: 111.6 | R18: 199.1 | S18: 4.2 | X18: 114.3 | Y18: 6.6 | Z18: 5.5 | AB18: 6.8 | AC18: 12 | AD18: 49.8 | AI18: 44.8 | AJ18: 32.3 | AN18: 6.5 | AO18: 0 | AP18: 32 | AQ18: 0 | AR18: 21 | AS18: 18.5 | AT18: 13.4 | AU18: 59 | AV18: 182 | AW18: 182.3 | AX18: 184 | AY18: 83.4 | AZ18: 8 | BA18: 4.7 | BB18: 23.2 | BC18: 39.8 | BD18: 2 | BE18: 0 | BF18: 19.8 | BI18: 44.9 | BL18: 0 | BP18: 67.2 | BQ18: 178.4 | BR18: 175.9 | BS18: 209.8 | BT18: 274.1 | CB18: 0 | CC18: 1 | CD18: 99.4 | CE18: 101.7 | CF18: 70.4 | CG18: 70 | CH18: 29.9 | CL18: 146.5 | CM18: 148.7 | CN18: 150.1 | CT18: 218.7 | CU18: 105.1 | CV18: 0 | CW18: 29.6 | CX18: 0 | CY18: 14.3 | CZ18: 0 | DA18: 7.7 | DB18: 5.126 | DC18: 0 | DD18: 0 | DE18: 0.3 | DF18: 2.9 | DG18: 2 | DH18: 19.3 | DI18: 7 | DJ18: 4.5 | DK18: 3.4 | DL18: 18 | DM18: 0 | DN18: 0 | DO18: 6.6 | DP18: 18.4 | DQ18: 4.5 | DR18: 1.2 | DS18: 2.4 | DT18: 2.6 | DU18: 0 | DV18: 1.8 | DW18: 11.9 | DX18: 1.3 | DZ18: 4.7 | EA18: 3.5 | EB18: 3.1 | EC18: 4 | ED18: 15.5 | EE18: 19.9 | EF18: 9.7 | EG18: 0 | EH18: 22.6 | EI18: 44.3 | EJ18: 2 | EK18: 0.2 | EL18: 6.2 | EM18: 2.1 | EN18: 9.2 | EO18: 3.8 | EP18: 4.2 | EQ18: 4.2 | ER18: 10.8 | ES18: 0 | ET18: 0 | EU18: 0 | EV18: 0.6 | EW18: 13.3 | EX18: 6.5 | EY18: 0 | EZ18: 0 | FA18: 10 | FB18: 18.6 | FC18: 9.4 | FD18: 37.1 | FE18: 27.9 | FF18: 14.6 | FG18: 19.1 | FH18: 9 | FI18: 6005.126 | FK18: 20.87239 | FL18: 0 | FM18: 6.088 | FN18: 7.2 | FO18: 27.17993 | FP18: 18.86546 | FQ18: 9.7 | FR18: 16 | FS18: 105.90578
A19: 22/07/2025 | B19: 04:30 | C19: 31.6 | D19: 581.4 | E19: 145.9 | H19: 0 | I19: 77.3 | L19: 188.5 | M19: 208.3 | N19: 211.5 | O19: 287.7 | P19: 215.3 | Q19: 112 | R19: 199.8 | S19: 4.3 | X19: 111.9 | Y19: 6.7 | Z19: 5.6 | AB19: 6.9 | AC19: 12 | AD19: 50.3 | AI19: 55.4 | AJ19: 68.4 | AN19: 6.5 | AO19: 0 | AP19: 32 | AQ19: 0 | AR19: 22.2 | AS19: 18.6 | AT19: 13.5 | AU19: 55.9 | AV19: 182.9 | AW19: 183.2 | AX19: 184.2 | AY19: 84.4 | AZ19: 8 | BA19: 4.7 | BB19: 27.9 | BC19: 31.9 | BD19: 2 | BE19: 0 | BF19: 48.2 | BI19: 45.1 | BL19: 0 | BP19: 67.2 | BQ19: 178.4 | BR19: 175.9 | BS19: 210.6 | BT19: 274.6 | CB19: 0 | CC19: 1 | CD19: 80.2 | CE19: 106.9 | CF19: 70.6 | CG19: 70 | CH19: 28.2 | CL19: 146.5 | CM19: 148.8 | CN19: 150 | CT19: 218.7 | CU19: 105.2 | CV19: 0 | CW19: 30.3 | CX19: 0 | CY19: 14.4 | CZ19: 0 | DA19: 7.7 | DB19: 5.158 | DC19: 0 | DD19: 0 | DE19: 0.3 | DF19: 2.9 | DG19: 1.9 | DH19: 19.4 | DI19: 7.2 | DJ19: 4.5 | DK19: 3.4 | DL19: 18 | DM19: 0 | DN19: 0 | DO19: 7.1 | DP19: 22.4 | DQ19: 4.2 | DR19: 1.2 | DS19: 2 | DT19: 2.3 | DU19: 0 | DV19: 2.4 | DW19: 11.9 | DX19: 1.2 | DZ19: 4.8 | EA19: 3.5 | EB19: 3.2 | EC19: 4.3 | ED19: 15.7 | EE19: 15 | EF19: 6.3 | EG19: 0 | EH19: 25.9 | EI19: 44.4 | EJ19: 4.6 | EK19: 1.9 | EL19: 6.2 | EM19: 2.1 | EN19: 9.2 | EO19: 3.8 | EP19: 4.2 | EQ19: 4.2 | ER19: 11.1 | ES19: 0 | ET19: 0 | EU19: 0 | EV19: 0.6 | EW19: 30.6 | EX19: 23.9 | EY19: 0 | EZ19: 0 | FA19: 10 | FB19: 18.7 | FC19: 9.4 | FD19: 37.1 | FE19: 28.1 | FF19: 14.8 | FG19: 19.1 | FH19: 8.3 | FI19: 6105.658 | FK19: 21.0065 | FL19: 0 | FM19: 6.088 | FN19: 7.2 | FO19: 27.12016 | FP19: 18.86576 | FQ19: 9.5 | FR19: 16 | FS19: 105.78042
A20: 22/07/2025 | B20: 05:00 | C20: 29.4 | D20: 582.9 | E20: 146.6 | H20: 0 | I20: 76.9 | L20: 189.5 | M20: 208.1 | N20: 210.6 | O20: 288.6 | P20: 217.6 | Q20: 112.1 | R20: 199.8 | S20: 4.3 | X20: 113.9 | Y20: 7 | Z20: 5.1 | AB20: 6.9 | AC20: 12 | AD20: 51.3 | AI20: 60.8 | AJ20: 62.2 | AN20: 6.5 | AO20: 0 | AP20: 33.5 | AQ20: 0 | AR20: 23.3 | AS20: 18.6 | AT20: 13.3 | AU20: 56.6 | AV20: 183.8 | AW20: 184.7 | AX20: 184.2 | AY20: 84.4 | AZ20: 8 | BA20: 4.7 | BB20: 25.1 | BC20: 31.2 | BD20: 2 | BE20: 0 | BF20: 39.6 | BI20: 45.3 | BL20: 0 | BP20: 67.4 | BQ20: 178.5 | BR20: 175.9 | BS20: 210.4 | BT20: 274.9 | CB20: 0 | CC20: 1 | CD20: 74.8 | CE20: 105 | CF20: 70.8 | CG20: 70 | CH20: 28.2 | CL20: 146.5 | CM20: 148.8 | CN20: 150.1 | CT20: 219 | CU20: 105.3 | CV20: 0 | CW20: 33.8 | CX20: 0 | CY20: 15.6 | CZ20: 0 | DA20: 7.7 | DB20: 5.228 | DC20: 0 | DD20: 0 | DE20: 0.3 | DF20: 2.8 | DG20: 1.9 | DH20: 19.6 | DI20: 7.4 | DJ20: 4.5 | DK20: 3.4 | DL20: 18 | DM20: 0 | DN20: 0 | DO20: 9.7 | DP20: 23.7 | DQ20: 3.9 | DR20: 1.2 | DS20: 2 | DT20: 2.2 | DU20: 0 | DV20: 2.4 | DW20: 11.9 | DX20: 1.2 | DZ20: 5 | EA20: 3.5 | EB20: 3.3 | EC20: 4.5 | ED20: 15.6 | EE20: 13.1 | EF20: 3.4 | EG20: 0 | EH20: 21.1 | EI20: 44 | EJ20: 1.7 | EK20: 0.9 | EL20: 6.2 | EM20: 2.1 | EN20: 9 | EO20: 3.8 | EP20: 4.2 | EQ20: 4.2 | ER20: 11 | ES20: 0 | ET20: 0 | EU20: 0 | EV20: 0.6 | EW20: 39 | EX20: 26.5 | EY20: 0 | EZ20: 0 | FA20: 10 | FB20: 18.7 | FC20: 9.4 | FD20: 36.9 | FE20: 27.9 | FF20: 14.8 | FG20: 19.1 | FH20: 7.3 | FI20: 6102.228 | FK20: 21.21944 | FL20: 0 | FM20: 6.088 | FN20: 7.2 | FO20: 27.03816 | FP20: 18.86751 | FQ20: 9.7 | FR20: 16.1 | FS20: 106.21311
A21: 22/07/2025 | B21: 05:30 | C21: 34 | D21: 581.4 | E21: 146.1 | H21: 0 | I21: 78.1 | L21: 188.6 | M21: 208.2 | N21: 210.9 | O21: 287.9 | P21: 216.8 | Q21: 111.9 | R21: 319.4 | S21: 4.3 | X21: 113.5 | Y21: 7.6 | Z21: 5 | AB21: 6.8 | AC21: 12 | AD21: 50.9 | AI21: 55.4 | AJ21: 96.1 | AN21: 6.5 | AO21: 0 | AP21: 34 | AQ21: 0 | AR21: 23.3 | AS21: 18.5 | AT21: 13.4 | AU21: 57 | AV21: 183.6 | AW21: 184 | AX21: 184.1 | AY21: 84.8 | AZ21: 8 | BA21: 4.7 | BB21: 13.4 | BC21: 34.8 | BD21: 2 | BE21: 0 | BF21: 56.1 | BI21: 45.1 | BL21: 0 | BP21: 67.3 | BQ21: 178.4 | BR21: 175.9 | BS21: 210.8 | BT21: 275.1 | CB21: 0 | CC21: 1 | CD21: 93.8 | CE21: 105.3 | CF21: 68.4 | CG21: 71 | CH21: 28.2 | CL21: 146.7 | CM21: 148.8 | CN21: 149.9 | CT21: 218.7 | CU21: 105.3 | CV21: 0 | CW21: 34.9 | CX21: 0 | CY21: 14 | CZ21: 0 | DA21: 7.7 | DB21: 5.189 | DC21: 0 | DD21: 0 | DE21: 0.3 | DF21: 2.8 | DG21: 1.9 | DH21: 19.1 | DI21: 7.6 | DJ21: 4.5 | DK21: 3.4 | DL21: 18 | DM21: 0 | DN21: 0 | DO21: 9.5 | DP21: 25.6 | DQ21: 4.5 | DR21: 1.2 | DS21: 2 | DT21: 2.7 | DU21: 0 | DV21: 2.4 | DW21: 11.9 | DX21: 1.2 | DZ21: 5.2 | EA21: 3.5 | EB21: 3.2 | EC21: 4.4 | ED21: 15.6 | EE21: 15.2 | EF21: 2.2 | EG21: 0 | EH21: 14.7 | EI21: 35.8 | EJ21: 0.5 | EK21: 0 | EL21: 6.2 | EM21: 2.1 | EN21: 9 | EO21: 4 | EP21: 4.2 | EQ21: 4.2 | ER21: 10.6 | ES21: 0 | ET21: 0 | EU21: 0 | EV21: 0.6 | EW21: 26.3 | EX21: 20 | EY21: 0 | EZ21: 0 | FA21: 10 | FB21: 18.7 | FC21: 9.4 | FD21: 37.1 | FE21: 27.9 | FF21: 14.6 | FG21: 19.1 | FH21: 8.7 | FI21: 6246.189 | FK21: 21.30825 | FL21: 0 | FM21: 6.088 | FN21: 7.2 | FO21: 27.02572 | FP21: 18.87035 | FQ21: 9.5 | FR21: 16 | FS21: 105.99232
A22: 22/07/2025 | B22: 06:00 | C22: 26 | D22: 580.4 | E22: 145.8 | H22: 0 | I22: 77.7 | L22: 189.1 | M22: 208.3 | N22: 212.6 | O22: 289.6 | P22: 218.4 | Q22: 112 | R22: 376.9 | S22: 4.3 | X22: 112.4 | Y22: 7.1 | Z22: 4.7 | AB22: 7 | AC22: 12 | AD22: 50.4 | AI22: 43.9 | AJ22: 93.5 | AN22: 6.5 | AO22: 0 | AP22: 34 | AQ22: 45 | AR22: 22.3 | AS22: 18.5 | AT22: 13.4 | AU22: 55.6 | AV22: 181.7 | AW22: 181.9 | AX22: 184.3 | AY22: 84.2 | AZ22: 8.2 | BA22: 4.7 | BB22: 29.8 | BC22: 34.2 | BD22: 2 | BE22: 0 | BF22: 62.1 | BI22: 44.9 | BL22: 0 | BP22: 67 | BQ22: 179.1 | BR22: 176.7 | BS22: 210.7 | BT22: 275.3 | CB22: 0 | CC22: 1 | CD22: 70.8 | CE22: 103.8 | CF22: 68.1 | CG22: 71 | CH22: 29.5 | CL22: 147 | CM22: 149.1 | CN22: 150.6 | CT22: 219 | CU22: 105.3 | CV22: 0 | CW22: 41.1 | CX22: 0 | CY22: 17.2 | CZ22: 0 | DA22: 7.9 | DB22: 5.102 | DC22: 0 | DD22: 0 | DE22: 0.3 | DF22: 2.8 | DG22: 1.9 | DH22: 18.9 | DI22: 7.7 | DJ22: 4.5 | DK22: 3.4 | DL22: 18.1 | DM22: 0.1 | DN22: 0 | DO22: 8.8 | DP22: 21.6 | DQ22: 4.5 | DR22: 1.2 | DS22: 2.4 | DT22: 2.6 | DU22: 0 | DV22: 2.3 | DW22: 11.9 | DX22: 1.3 | DZ22: 5.4 | EA22: 3.5 | EB22: 3.1 | EC22: 4 | ED22: 15.6 | EE22: 12.1 | EF22: 3.3 | EG22: 0 | EH22: 11.3 | EI22: 28.7 | EJ22: 0 | EK22: 0.1 | EL22: 6.2 | EM22: 2.1 | EN22: 9 | EO22: 4 | EP22: 4.4 | EQ22: 4.2 | ER22: 12.5 | ES22: 0 | ET22: 0 | EU22: 0 | EV22: 0.6 | EW22: 10.2 | EX22: 6.5 | EY22: 0 | EZ22: 0 | FA22: 10 | FB22: 18.7 | FC22: 9.3 | FD22: 37 | FE22: 28.3 | FF22: 14.5 | FG22: 19.1 | FH22: 8.8 | FI22: 6287.502 | FK22: 21.30008 | FL22: 0 | FM22: 6.088 | FN22: 7.2 | FO22: 26.97764 | FP22: 18.87244 | FQ22: 9.6 | FR22: 16 | FS22: 106.03816
... A58: 23/07/2025 | B58: 00:00 | C58: 28.9 | D58: 648.1 | E58: 215.8 | H58: 0 | I58: 77.6 | L58: 187.6 | M58: 206.8 | N58: 209.5 | O58: 290.6 | P58: 216.4 | Q58: 111.7 | R58: 360.9 | S58: 4.3 | X58: 111 | Y58: 8.1 | Z58: 5.3 | AB58: 7 | AC58: 13.4 | AD58: 77.8 | AI58: 36.3 | AJ58: 51.7 | AN58: 6.4 | AO58: 153.4 | AP58: 28 | AQ58: 53.2 | AR58: 18.6 | AS58: 18.6 | AT58: 13.1 | AU58: 57 | AV58: 183.2 | AW58: 183.5 | AX58: 184.1 | AY58: 82.8 | AZ58: 8 | BA58: 4.9 | BB58: 24.1 | BC58: 32 | BD58: 2 | BE58: 16.3 | BF58: 47.8 | BI58: 39.3 | BL58: 47.6 | BP58: 67.4 | BQ58: 177.6 | BR58: 175.2 | BS58: 209.2 | BT58: 273.9 | CB58: 0 | CC58: 1 | CD58: 79.4 | CE58: 89.4 | CF58: 64.4 | CG58: 74 | CH58: 29.5 | CL58: 146.2 | CM58: 148.4 | CN58: 150.3 | CT58: 137.2 | CU58: 77.8 | CV58: 0 | CW58: 46.9 | CX58: 0 | CY58: 15.2 | CZ58: 0 | DA58: 7.6 | DB58: 5.174 | DC58: 0 | DD58: 0 | DE58: 0.3 | DF58: 3.2 | DG58: 1.8 | DH58: 19 | DI58: 6.8 | DJ58: 7.5 | DK58: 3.4 | DL58: 18 | DM58: 0 | DN58: 0 | DO58: 15.4 | DP58: 34.8 | DQ58: 3 | DR58: 1.9 | DS58: 2.4 | DT58: 2.6 | DU58: 0 | DV58: 2.3 | DW58: 10.5 | DX58: 1.6 | DZ58: 4.4 | EA58: 4.4 | EB58: 3.7 | EC58: 4.9 | ED58: 15.2 | EE58: 9.6 | EF58: 19.4 | EG58: 0 | EH58: 28.8 | EI58: 51.7 | EJ58: 2.1 | EK58: 1.8 | EL58: 5.7 | EM58: 2.1 | EN58: 9 | EO58: 4 | EP58: 4.5 | EQ58: 4.5 | ER58: 10.5 | ES58: 0 | ET58: 0 | EU58: 0 | EV58: 0.6 | EW58: 0 | EX58: 0 | EY58: 0 | EZ58: 0 | FA58: 10 | FB58: 18.5 | FC58: 10.2 | FD58: 36.8 | FE58: 26.8 | FF58: 13.4 | FG58: 19.1 | FH58: 7.1 | FI58: 6511.774 | FK58: 18.91376 | FL58: 0 | FM58: 6.072 | FN58: 7.2 | FO58: 27.13277 | FP58: 18.88019 | FQ58: 9.6 | FR58: 16.1 | FS58: 103.89872
A59: EJEC | C59: 1689.65 | D59: 14879.7 | E59: 4190.25 | F59: 0 | G59: 0 | H59: 687.95 | I59: 1817.9 | J59: 0 | K59: 0 | L59: 4493.7 | M59: 4957.65 | N59: 5030.95 | O59: 6915.6 | P59: 5162.75 | Q59: 2670.45 | R59: 8142.85 | S59: 103 | T59: 0 | U59: 0 | V59: 0 | W59: 0 | X59: 2674.7 | Y59: 177.75 | Z59: 122.4 | AA59: 0 | AB59: 156.85 | AC59: 316.95 | AD59: 1962.2 | AE59: 0 | AF59: 0 | AG59: 0 | AH59: 0 | AI59: 1330.3 | AJ59: 2074.4 | AK59: 0 | AL59: 0 | AM59: 0 | AN59: 151.45 | AO59: 3187.25 | AP59: 742.65 | AQ59: 1214.5 | AR59: 496.3 | AS59: 445.25 | AT59: 318.45 | AU59: 1367.45 | AV59: 4383.7 | AW59: 4393 | AX59: 4419.25 | AY59: 2015.5 | AZ59: 192.6 | BA59: 112.6 | BB59: 633.85 | BC59: 771.8 | BD59: 48 | BE59: 209.25 | BF59: 1271.85 | BG59: 0 | BH59: 0 | BI59: 1133.25 | BJ59: 0 | BK59: 0 | BL59: 819.05 | BM59: 0 | BN59: 0 | BO59: 0 | BP59: 1610.3 | BQ59: 4258.15 | BR59: 4199.8 | BS59: 5018.05 | BT59: 6560.35 | BU59: 0 | BV59: 0 | BW59: 0 | BX59: 0 | BY59: 0 | BZ59: 0 | CA59: 0 | CB59: 16.3 | CC59: 25.5 | CD59: 2465 | CE59: 2323.4 | CF59: 1533.5 | CG59: 1760.7 | CH59: 712.15 | CI59: 0 | CJ59: 0 | CK59: 0 | CL59: 3502 | CM59: 3556.3 | CN59: 3600 | CO59: 0 | CP59: 0 | CQ59: 0 | CR59: 0 | CS59: 0 | CT59: 4901.25 | CU59: 2403 | CV59: 8.1 | CW59: 1576.2 | CX59: 596.95 | CY59: 356 | CZ59: 2.7 | DA59: 184.2 | DB59: 123.1125 | DC59: 178.6 | DD59: 52.15 | DE59: 7.2 | DF59: 67.4 | DG59: 48.15 | DH59: 455.6 | DI59: 178.75 | DJ59: 120 | DK59: 78.35 | DL59: 432.05 | DM59: 126.6 | DN59: 150.95 | DO59: 334.75 | DP59: 964.25 | DQ59: 80.55 | DR59: 34.25 | DS59: 57 | DT59: 62.45 | DU59: 130.85 | DV59: 55.3 | DW59: 298 | DX59: 31.55 | DY59: 0 | DZ59: 113.55 | EA59: 82.5 | EB59: 86.05 | EC59: 120.25 | ED59: 370.6 | EE59: 297.35 | EF59: 542.3 | EG59: 264.75 | EH59: 896.6 | EI59: 1291.2 | EJ59: 127.45 | EK59: 79.3 | EL59: 138.7 | EM59: 47.75 | EN59: 215.95 | EO59: 96.05 | EP59: 107.85 | EQ59: 104.15 | ER59: 288.6 | ES59: 107.8 | ET59: 116.15 | EU59: 1105.65 | EV59: 14.4 | EW59: 684.8 | EX59: 712.2 | EY59: 827 | EZ59: 118.05 | FA59: 240.05 | FB59: 446.6 | FC59: 242.3 | FD59: 888.1 | FE59: 665.6 | FF59: 344.05 | FG59: 450.4 | FH59: 194.05 | FI59: 165550.86 | FK59: 478.68302 | FL59: 41.501 | FM59: 146.068 | FN59: 172.8 | FO59: 642.70142 | FP59: 452.87432 | FQ59: 221.9 | FR59: 384.8 | FS59: 2541.3277

Sheet REACTIVA
B3: martes, 22 de Julio del 2025
A5: POTENCIA REACTIVA EJECUTADA DE LAS UNIDADES DE GENERACIÓN DEL COES (MVAR) | FK5: CENTRALES NO INTEGRANTES COES
A6: FECHA | B6: HORA | C6: 65333 | D6: 101 | E6: 102 | F6: 42667 | G6: 42668 | H6: 126 | I6: 127 | J6: 138 | K6: 139 | L6: 197 | M6: 203 | N6: 204 | O6: 230 | P6: 209 | Q6: 56677 | R6: 796 | S6: 2146 | T6: 142 | U6: 143 | V6: 125 | W6: 187 | X6: 163 | Y6: 298 | Z6: 299 | AA6: 219 | AB6: 151 | AC6: 152 | AD6: 153 | AE6: 154 | AF6: 756 | AG6: 156 | AH6: 155 | AI6: 182 | AJ6: 212 | AK6: 758 | AL6: 263 | AM6: 265 | AN6: 775 | AO6: 777 | AP6: 2154 | AQ6: 150 | AR6: 149 | AS6: 188 | AT6: 2131 | AU6: 755 | AV6: 252 | AW6: 249 | AX6: 250 | AY6: 117 | AZ6: 267 | BA6: 268 | BB6: 119 | BC6: 120 | BD6: 189 | BE6: 122 | BF6: 266 | BG6: 337 | BH6: 338 | BI6: 251 | BJ6: 115 | BK6: 239 | BL6: 288 | BM6: 240 | BN6: 241 | BO6: 242 | BP6: 191 | BQ6: 194 | BR6: 196 | BS6: 207 | BT6: 236 | BU6: 795 | BV6: 285 | BW6: 995 | BX6: 996 | BY6: 997 | BZ6: 766 | CA6: 926 | CB6: 924 | CC6: 121 | CD6: 103 | CE6: 104 | CF6: 106 | CG6: 105 | CH6: 107 | CI6: 110 | CJ6: 109 | CK6: 144 | CL6: 113 | CM6: 114 | CN6: 193 | CO6: 208 | CP6: 786 | CQ6: 787 | CR6: 788 | CS6: 789 | CT6: 248 | CU6: 2159 | CV6: 303 | CW6: 59715 | CX6: 62255 | CY6: 1263 | CZ6: 61800 | DA6: 2194 | DB6: 69125 | DC6: 216 | DD6: 198 | DE6: 49607 | DF6: 214 | DG6: 260 | DH6: 2152 | DI6: 2128 | DJ6: 247 | DK6: 228 | DL6: 2135 | DM6: 261 | DN6: 237 | DO6: 253 | DP6: 770 | DQ6: 225 | DR6: 2201 | DS6: 2171 | DT6: 760 | DU6: 235 | DV6: 238 | DW6: 2184 | DX6: 61855 | DY6: 223 | DZ6: 226 | EA6: 201 | EB6: 258 | EC6: 259 | ED6: 920 | EE6: 257 | EF6: 256 | EG6: 2148 | EH6: 58288 | EI6: 58289 | EJ6: 58839 | EK6: 58840 | EL6: 296 | EM6: 297 | EN6: 211 | EO6: 2175 | EP6: 2178 | EQ6: 2181 | ER6: 1262 | ES6: 63425 | ET6: 233 | EU6: 2150 | EV6: 2165 | EW6: 2161 | EX6: 61197 | EY6: 58851 | EZ6: 234 | FA6: 215 | FB6: 917 | FC6: 289 | FD6: 58333 | FE6: 58336 | FF6: 213 | FG6: 232 | FH6: 2190 | FI6: TOTAL COES | FK6: 221 | FL6: 222 | FM6: 224 | FN6: 2187 | FO6: 227 | FP6: 49400 | FQ6: 199 | FR6: 200 | FS6: TOTAL NO COES
C7: SUR | D7: CENTRO | E7: CENTRO | F7: NORTE | G7: NORTE | H7: NORTE | I7: NORTE | J7: CENTRO | K7: CENTRO | L7: CENTRO | M7: CENTRO | N7: CENTRO | O7: CENTRO | P7: CENTRO | Q7: CENTRO | R7: CENTRO | S7: CENTRO | T7: CENTRO | U7: CENTRO | V7: CENTRO | W7: CENTRO | X7: SUR | Y7: SUR | Z7: SUR | AA7: CENTRO | AB7: SUR | AC7: SUR | AD7: SUR | AE7: SUR | AF7: SUR | AG7: SUR | AH7: SUR | AI7: SUR | AJ7: CENTRO | AK7: NORTE | AL7: NORTE | AM7: NORTE | AN7: CENTRO | AO7: CENTRO | AP7: CENTRO | AQ7: CENTRO | AR7: CENTRO | AS7: CENTRO | AT7: CENTRO | AU7: SUR | AV7: CENTRO | AW7: CENTRO | AX7: CENTRO | AY7: CENTRO | AZ7: CENTRO | BA7: CENTRO | BB7: CENTRO | BC7: CENTRO | BD7: SUR | BE7: NORTE | BF7: CENTRO | BG7: CENTRO | BH7: CENTRO | BI7: CENTRO | BJ7: NORTE | BK7: NORTE | BL7: NORTE | BM7: SUR | BN7: SUR | BO7: SUR | BP7: CENTRO | BQ7: CENTRO | BR7: CENTRO | BS7: CENTRO | BT7: CENTRO | BU7: CENTRO | BV7: CENTRO | BW7: SUR | BX7: SUR | BY7: SUR | BZ7: NORTE | CA7: SUR | CB7: CENTRO | CC7: NORTE | CD7: CENTRO | CE7: CENTRO | CF7: CENTRO | CG7: CENTRO | CH7: CENTRO | CI7: CENTRO | CJ7: CENTRO | CK7: CENTRO | CL7: CENTRO | CM7: CENTRO | CN7: CENTRO | CO7: CENTRO | CP7: SUR | CQ7: SUR | CR7: SUR | CS7: SUR | CT7: CENTRO | CU7: CENTRO | CV7: CENTRO | CW7: CENTRO | CX7: SUR | CY7: NORTE | CZ7: NORTE | DA7: NORTE | DB7: CENTRO | DC7: NORTE | DD7: NORTE | DE7: SUR | DF7: CENTRO | DG7: CENTRO | DH7: CENTRO | DI7: NORTE | DJ7: NORTE | DK7: CENTRO | DL7: CENTRO | DM7: SUR | DN7: SUR | DO7: CENTRO | DP7: CENTRO | DQ7: CENTRO | DR7: CENTRO | DS7: CENTRO | DT7: CENTRO | DU7: SUR | DV7: CENTRO | DW7: CENTRO | DX7: NORTE | DY7: CENTRO | DZ7: CENTRO | EA7: NORTE | EB7: CENTRO | EC7: CENTRO | ED7: CENTRO | EE7: NORTE | EF7: NORTE | EG7: SUR | EH7: CENTRO | EI7: CENTRO | EJ7: CENTRO | EK7: CENTRO | EL7: CENTRO | EM7: CENTRO | EN7: SUR | EO7: SUR | EP7: SUR | EQ7: SUR | ER7: NORTE | ES7: SUR | ET7: SUR | EU7: SUR | EV7: CENTRO | EW7: CENTRO | EX7: CENTRO | EY7: SUR | EZ7: SUR | FA7: NORTE | FB7: CENTRO | FC7: NORTE | FD7: NORTE | FE7: NORTE | FF7: CENTRO | FG7: NORTE | FH7: NORTE | FK7: NORTE | FL7: CENTRO | FM7: NORTE | FN7: NORTE | FO7: NORTE | FP7: NORTE | FQ7: NORTE | FR7: NORTE
C8: HIDROELÉCTRICA | D8: HIDROELÉCTRICA | E8: HIDROELÉCTRICA | F8: TERMOELÉCTRICA | G8: TERMOELÉCTRICA | H8: HIDROELÉCTRICA | I8: HIDROELÉCTRICA | J8: TERMOELÉCTRICA | K8: TERMOELÉCTRICA | L8: TERMOELÉCTRICA | M8: TERMOELÉCTRICA | N8: TERMOELÉCTRICA | O8: TERMOELÉCTRICA | P8: TERMOELÉCTRICA | Q8: TERMOELÉCTRICA | R8: HIDROELÉCTRICA | S8: HIDROELÉCTRICA | T8: TERMOELÉCTRICA | U8: TERMOELÉCTRICA | V8: TERMOELÉCTRICA | W8: TERMOELÉCTRICA | X8: HIDROELÉCTRICA | Y8: HIDROELÉCTRICA | Z8: HIDROELÉCTRICA | AA8: TERMOELÉCTRICA | AB8: HIDROELÉCTRICA | AC8: HIDROELÉCTRICA | AD8: HIDROELÉCTRICA | AE8: HIDROELÉCTRICA | AF8: TERMOELÉCTRICA | AG8: TERMOELÉCTRICA | AH8: TERMOELÉCTRICA | AI8: HIDROELÉCTRICA | AJ8: HIDROELÉCTRICA | AK8: TERMOELÉCTRICA | AL8: TERMOELÉCTRICA | AM8: TERMOELÉCTRICA | AN8: HIDROELÉCTRICA | AO8: HIDROELÉCTRICA | AP8: HIDROELÉCTRICA | AQ8: HIDROELÉCTRICA | AR8: HIDROELÉCTRICA | AS8: HIDROELÉCTRICA | AT8: HIDROELÉCTRICA | AU8: HIDROELÉCTRICA | AV8: TERMOELÉCTRICA | AW8: TERMOELÉCTRICA | AX8: TERMOELÉCTRICA | AY8: HIDROELÉCTRICA | AZ8: HIDROELÉCTRICA | BA8: HIDROELÉCTRICA | BB8: HIDROELÉCTRICA | BC8: HIDROELÉCTRICA | BD8: HIDROELÉCTRICA | BE8: HIDROELÉCTRICA | BF8: HIDROELÉCTRICA | BG8: HIDROELÉCTRICA | BH8: HIDROELÉCTRICA | BI8: HIDROELÉCTRICA | BJ8: TERMOELÉCTRICA | BK8: TERMOELÉCTRICA | BL8: TERMOELÉCTRICA | BM8: TERMOELÉCTRICA | BN8: TERMOELÉCTRICA | BO8: TERMOELÉCTRICA | BP8: HIDROELÉCTRICA | BQ8: TERMOELÉCTRICA | BR8: TERMOELÉCTRICA | BS8: TERMOELÉCTRICA | BT8: TERMOELÉCTRICA | BU8: TERMOELÉCTRICA | BV8: TERMOELÉCTRICA | BW8: TERMOELÉCTRICA | BX8: TERMOELÉCTRICA | BY8: TERMOELÉCTRICA | BZ8: HIDROELÉCTRICA | CA8: TERMOELÉCTRICA | CB8: TERMOELÉCTRICA | CC8: HIDROELÉCTRICA | CD8: HIDROELÉCTRICA | CE8: HIDROELÉCTRICA | CF8: HIDROELÉCTRICA | CG8: HIDROELÉCTRICA | CH8: HIDROELÉCTRICA | CI8: TERMOELÉCTRICA | CJ8: TERMOELÉCTRICA | CK8: TERMOELÉCTRICA | CL8: TERMOELÉCTRICA | CM8: TERMOELÉCTRICA | CN8: TERMOELÉCTRICA | CO8: TERMOELÉCTRICA | CP8: TERMOELÉCTRICA | CQ8: TERMOELÉCTRICA | CR8: TERMOELÉCTRICA | CS8: TERMOELÉCTRICA | CT8: TERMOELÉCTRICA | CU8: TERMOELÉCTRICA | CV8: SOLAR | CW8: EÓLICA | CX8: SOLAR | CY8: EÓLICA | CZ8: SOLAR | DA8: HIDROELÉCTRICA | DB8: HIDROELÉCTRICA | DC8: HIDROELÉCTRICA | DD8: HIDROELÉCTRICA | DE8: HIDROELÉCTRICA | DF8: HIDROELÉCTRICA | DG8: HIDROELÉCTRICA | DH8: HIDROELÉCTRICA | DI8: HIDROELÉCTRICA | DJ8: HIDROELÉCTRICA | DK8: HIDROELÉCTRICA | DL8: HIDROELÉCTRICA | DM8: SOLAR | DN8: SOLAR | DO8: EÓLICA | DP8: EÓLICA | DQ8: TERMOELÉCTRICA | DR8: TERMOELÉCTRICA | DS8: TERMOELÉCTRICA | DT8: TERMOELÉCTRICA | DU8: SOLAR | DV8: HIDROELÉCTRICA | DW8: HIDROELÉCTRICA | DX8: HIDROELÉCTRICA | DY8: HIDROELÉCTRICA | DZ8: HIDROELÉCTRICA | EA8: HIDROELÉCTRICA | EB8: HIDROELÉCTRICA | EC8: HIDROELÉCTRICA | ED8: HIDROELÉCTRICA | EE8: EÓLICA | EF8: EÓLICA | EG8: SOLAR | EH8: EÓLICA | EI8: EÓLICA | EJ8: EÓLICA | EK8: EÓLICA | EL8: HIDROELÉCTRICA | EM8: HIDROELÉCTRICA | EN8: HIDROELÉCTRICA | EO8: HIDROELÉCTRICA | EP8: HIDROELÉCTRICA | EQ8: HIDROELÉCTRICA | ER8: EÓLICA | ES8: SOLAR | ET8: SOLAR | EU8: SOLAR | EV8: HIDROELÉCTRICA | EW8: EÓLICA | EX8: EÓLICA | EY8: SOLAR | EZ8: SOLAR | FA8: HIDROELÉCTRICA | FB8: HIDROELÉCTRICA | FC8: TERMOELÉCTRICA | FD8: TERMOELÉCTRICA | FE8: TERMOELÉCTRICA | FF8: TERMOELÉCTRICA | FG8: TERMOELÉCTRICA | FH8: TERMOELÉCTRICA | FK8: HIDROELÉCTRICA | FL8: HIDROELÉCTRICA | FM8: HIDROELÉCTRICA | FN8: HIDROELÉCTRICA | FO8: TERMOELÉCTRICA | FP8: TERMOELÉCTRICA | FQ8: HIDROELÉCTRICA | FR8: HIDROELÉCTRICA
C9: HYDRO GLOBAL PERÚ S.A.C. | D9: ELECTROPERU | E9: ELECTROPERU | F9: ELECTROPERU | G9: ELECTROPERU | H9: ORAZUL ENERGY PERÚ | I9: ORAZUL ENERGY PERÚ | J9: TERMOSELVA | K9: TERMOSELVA | L9: KALLPA GENERACION S.A. | M9: KALLPA GENERACION S.A. | N9: KALLPA GENERACION S.A. | O9: KALLPA GENERACION S.A. | P9: KALLPA GENERACION S.A. | Q9: KALLPA GENERACION S.A. | R9: KALLPA GENERACION S.A. | S9: KALLPA GENERACION S.A. | T9: SHOUGESA | U9: SHOUGESA | V9: SHOUGESA | W9: SHOUGESA | X9: EGEMSA | Y9: EGESUR | Z9: EGESUR | AA9: EGESUR | AB9: EGASA | AC9: EGASA | AD9: EGASA | AE9: EGASA | AF9: EGASA | AG9: EGASA | AH9: EGASA | AI9: SAN GABAN | AJ9: CELEPSA | AK9: MINERA CERRO VERDE | AL9: PLANTA DE RESERVA FRIA DE GENERACION DE ETEN S.A. | AM9: PLANTA DE RESERVA FRIA DE GENERACION DE ETEN S.A. | AN9: EMPRESA DE GENERACION HUALLAGA | AO9: EMPRESA DE GENERACION HUALLAGA | AP9: LA VIRGEN | AQ9: CHINANGO S.A.C. | AR9: CHINANGO S.A.C. | AS9: HIDROELECTRICA HUANCHOR S.A.C. | AT9: CELEPSA RENOVABLES S.R.L. | AU9: INLAND ENERGY SAC | AV9: FENIX POWER PERÚ | AW9: FENIX POWER PERÚ | AX9: FENIX POWER PERÚ | AY9: STATKRAFT S.A | AZ9: STATKRAFT S.A | BA9: STATKRAFT S.A | BB9: STATKRAFT S.A | BC9: STATKRAFT S.A | BD9: STATKRAFT S.A | BE9: STATKRAFT S.A | BF9: STATKRAFT S.A | BG9: CENTRALES SANTA ROSA S.A.C. | BH9: CENTRALES SANTA ROSA S.A.C. | BI9: EMPRESA DE GENERACION HUANZA | BJ9: ENEL GENERACION PIURA S.A. | BK9: ENEL GENERACION PIURA S.A. | BL9: ENEL GENERACION PIURA S.A. | BM9: ENGIE | BN9: ENGIE | BO9: ENGIE | BP9: ENGIE | BQ9: ENGIE | BR9: ENGIE | BS9: ENGIE | BT9: ENGIE | BU9: ENGIE | BV9: ENGIE | BW9: ENGIE | BX9: ENGIE | BY9: ENGIE | BZ9: ENGIE | CA9: INFRAESTRUCTURAS Y ENERGIAS DEL PERU S.A.C. | CB9: INFRAESTRUCTURAS Y ENERGIAS DEL PERU S.A.C. | CC9: INVERSIONES SHAQSHA S.A.C. | CD9: ORYGEN PERU S.A.A. | CE9: ORYGEN PERU S.A.A. | CF9: ORYGEN PERU S.A.A. | CG9: ORYGEN PERU S.A.A. | CH9: ORYGEN PERU S.A.A. | CI9: ORYGEN PERU S.A.A. | CJ9: ORYGEN PERU S.A.A. | CK9: ORYGEN PERU S.A.A. | CL9: ORYGEN PERU S.A.A. | CM9: ORYGEN PERU S.A.A. | CN9: ORYGEN PERU S.A.A. | CO9: ORYGEN PERU S.A.A. | CP9: SAMAY I S.A.C | CQ9: SAMAY I S.A.C | CR9: SAMAY I S.A.C | CS9: SAMAY I S.A.C | CT9: TERMOCHILCA S.A.C. | CU9: TERMOCHILCA S.A.C. | CV9: COLCA SOLAR S.A.C. | CW9: ENERGIA RENOVABLE DEL SUR S.A. | CX9: GR CORTARRAMA SOCIEDAD ANONIMA CERRADA | CY9: GR TARUCA SOCIEDAD ANONIMA CERRADA | CZ9: KONDU SAC | DA9: PERUANA DE INVERSIONES EN ENERGIAS RENOVABLES S.A. | DB9: VARI ENERGIA S.A.C. | DC9: ORAZUL ENERGY PERÚ | DD9: ORAZUL ENERGY PERÚ | DE9: SAN GABAN | DF9: MAJA ENERGIA S.A.C. | DG9: EMPRESA DE GENERACION ELECTRICA CANCHAYLLO SAC | DH9: EMPRESA DE GENERACION ELECTRICA SANTA ANA S.A.C. | DI9: EMPRESA ELECTRICA AGUA AZUL | DJ9: EMPRESA ELECTRICA RIO DOBLE | DK9: HIDROCAÑETE S.A. | DL9: HUAURA POWER GROUP S.A. | DM9: MOQUEGUA FV S.A.C. | DN9: PANAMERICANA SOLAR SAC. | DO9: PARQUE EOLICO MARCONA S.A.C. | DP9: PARQUE EOLICO TRES HERMANAS S.A.C. | DQ9: PETRAMAS | DR9: PETRAMAS | DS9: PETRAMAS | DT9: PETRAMAS | DU9: TACNA SOLAR SAC. | DV9: ELECTRICA YANAPAMPA SAC | DW9: ANDEAN POWER S.A.C. | DX9: ASOCIACIÓN SANTA LUCIA DE CHACAS | DY9: ATRIA ENERGIA S.A.C. | DZ9: EGEJUNIN | EA9: EGEJUNIN | EB9: EGEJUNIN | EC9: EGEJUNIN | ED9: EMPRESA DE GENERACION ELECTRICA RIO BAÑOS S.A.C. | EE9: ENERGÍA EÓLICA S.A. | EF9: ENERGÍA EÓLICA S.A. | EG9: ENGIE | EH9: ENGIE | EI9: ENGIE | EJ9: ENGIE | EK9: ENGIE | EL9: GENERACIÓN ANDINA S.A.C. | EM9: GENERACIÓN ANDINA S.A.C. | EN9: GENERADORA DE ENERGÍA DEL PERÚ | EO9: GENERADORA DE ENERGÍA DEL PERÚ | EP9: GENERADORA DE ENERGÍA DEL PERÚ | EQ9: GENERADORA DE ENERGÍA DEL PERÚ | ER9: GR PAINO SOCIEDAD ANONIMA CERRADA | ES9: JOYA SOLAR S.A.C. | ET9: MAJES ARCUS S.A.C. | EU9: ORYGEN PERU S.A.A. | EV9: ORYGEN PERU S.A.A. | EW9: ORYGEN PERU S.A.A. | EX9: ORYGEN PERU S.A.A. | EY9: ORYGEN PERU S.A.A. | EZ9: REPARTICIÓN ARCUS S.A.C. | FA9: SINERSA | FB9: SINERSA | FC9: BIOENERGIA DEL CHIRA S.A. | FD9: GM OPERACIONES S.A.C. | FE9: GM OPERACIONES S.A.C. | FF9: AGRO INDUSTRIAL PARAMONGA S.A. | FG9: AGROAURORA S.A.C. | FH9: AGROINDUSTRIAS SAN JACINTO S.A.A. | FK9: UNACEM PERU S.A. | FL9: ELECTRO ORIENTE | FM9: AGUAS Y ENERGIA PERU | FN9: ELECTRO ZAÑA S.A.C. | FO9: ELECTRONOROESTE S.A. | FP9: SDE PIURA | FQ9: SINERSA | FR9: SINERSA
C10: SAN GABAN III | D10: MANTARO | E10: RESTITUCION | F10: TUMBES MAK 1 | G10: TUMBES MAK 2 | H10: CARHUAQUERO | I10: CAÑON DEL PATO | J10: AGUAYTIA TG1 | K10: AGUAYTIA TG2 | L10: KALLPA TG1 | M10: KALLPA TG2 | N10: KALLPA TG3 | O10: KALLPA TV | P10: LFLORES TG1 | Q10: LFLORES TV | R10: CERRO DEL AGUILA | S10: CERRODELAGUILAG4 | T10: SHOUGESA TV1 | U10: SHOUGESA TV2 | V10: SHOUGESA TV3 | W10: SHOUGESA CUMMINS | X10: MACHUPICCHU | Y10: ARICOTA 1 | Z10: ARICOTA 2 | AA10: INDEPENDENCIA | AB10: CHARCANI I,II,III | AC10: CHARCANI IV | AD10: CHARCANI V | AE10: CHARCANI VI | AF10: CHILINA TG | AG10: MOLLENDO 1, 2, 3 | AH10: CHILINA (SULZ 1,2) | AI10: SAN GABAN II | AJ10: PLATANAL | AK10: RECKA | AL10: RF ETEN TG1 | AM10: RF ETEN TG2 | AN10: CHAGLLA GP1 | AO10: CHAGLLA | AP10: LA VIRGEN | AQ10: CHIMAY | AR10: YANANGO | AS10: HUANCHOR | AT10: MARAÑON | AU10: STA TERESA | AV10: FENIX GT11 | AW10: FENIX GT12 | AX10: FENIX TV10 | AY10: YAUPI | AZ10: OROYA | BA10: PACHACHACA | BB10: MALPASO | BC10: CAHUA | BD10: ARCATA | BE10: GALLITO CIEGO | BF10: CHEVES | BG10: SANTA ROSA 1 | BH10: SANTA ROSA 2 | BI10: HUANZA | BJ10: MALACAS2 TG4 | BK10: MALACAS3 TG 5 | BL10: MALACAS1 TG6 | BM10: RF ILO2 TG1 | BN10: RF ILO2 TG2 | BO10: RF ILO2 TG3 | BP10: YUNCAN | BQ10: CHILCA1 TG1 | BR10: CHILCA1 TG2 | BS10: CHILCA1 TG3 | BT10: CHILCA-TV | BU10: CHILCA2 TG41 | BV10: CHILCA2-TV | BW10: CTNEPI_TG41 | BX10: CTNEPI_TG42 | BY10: CTNEPI_TG43 | BZ10: QUITARACSA | CA10: RF PTO MALDONADO | CB10: RF PUCALLPA | CC10: PARIAC | CD10: HUINCO | CE10: MATUCANA | CF10: MOYOPAMPA | CG10: CALLAHUANCA | CH10: HUAMPANI | CI10: STA ROSA WEST TG7 | CJ10: UTI_5 | CK10: UTI_6 | CL10: VENTANILLA 3 | CM10: VENTANILLA 4 | CN10: VENTANILLA TV | CO10: STAROSA TG8 | CP10: PTO_BRVO TG1 | CQ10: PTO_BRVO TG2 | CR10: PTO_BRVO TG3 | CS10: PTO_BRVO TG4 | CT10: OLLEROS TG1 | CU10: OLLEROS TV | CV10: CS YARUCAYA | CW10: SAN JUAN | CX10: MATARANI | CY10: DUNA | CZ10: CARHUAQUERO (CS) | DA10: MANTA I | DB10: ANASHIRONI | DC10: CARHUAQUERO4 | DD10: CAÑA BRAVA | DE10: TUPURI | DF10: RONCADOR | DG10: CANCHAYLLO | DH10: RENOVANDESH1 | DI10: POTRERO | DJ10: PIZARRAS | DK10: NIMPERIAL | DL10: YARUCAYA | DM10: MOQUEGUA-SOLAR | DN10: PANAMERICANA-SOLAR | DO10: PQE-EOLICO-MARCONA | DP10: PQE-EOLICO-3-HERMANAS | DQ10: HUAYCOLORO | DR10: CALLAO | DS10: DONA_CATALINA | DT10: LAGRINGAV | DU10: TACNA-SOLAR | DV10: YANAPAMPA | DW10: CARHUAC | DX10: HUALLIN | DY10: PURMACANA | DZ10: HUASAHUASI | EA10: STACRUZ_1_2 | EB10: RUNATULLO_II | EC10: RUNATULLO_III | ED10: RUCUY | EE10: PQE-EOLICO-TALARA | EF10: PQE-EOLICO-CUPISNIQUE | EG10: INTIPAMPA | EH10: PUNTA LOMITAS-BL1 | EI10: PUNTA LOMITAS-BL2 | EJ10: PUN LOMITAS_EXP-BL1 | EK10: PUN LOMITAS_EXP-BL2 | EL10: 8AGOSTO | EM10: EL CARMEN | EN10: LA JOYA | EO10: ANGEL_I | EP10: ANGEL_II | EQ10: ANGEL_III | ER10: HUAMBOS | ES10: SAN MARTIN SOLAR | ET10: MAJES | EU10: RUBI | EV10: CH_HER1 | EW10: WAYRA-I | EX10: WAYRA EXTENSION | EY10: CLEMESI | EZ10: REPARTICION | FA10: POECHOS2 | FB10: CHANCAY | FC10: CANA BRAVA | FD10: REFINERIA TALARA TV1 | FE10: REFINERÍA TALARA TV2 | FF10: PARAMONGA | FG10: MAPLE | FH10: SAN_JACINTO | FI10: MVAR | FK10: CARPAPATA | FL10: CENTRALES ELOR | FM10: PIAS1 | FN10: ZANA | FO10: TABLAZO | FP10: TALLANCA | FQ10: CURUMUY | FR10: POECHOS1 | FS10: MVAR
A11: 22/07/2025 | B11: 00:30 | C11: -18.2 | D11: 51.7 | E11: 12.3 | H11: -6.4 | I11: 7.2 | L11: -18.1 | M11: -30.5 | N11: -4.4 | O11: 31.9 | P11: 11.3 | Q11: 7.2 | R11: 45.7 | S11: -0.1 | X11: 5.3 | Y11: 1.9 | Z11: 0.7 | AB11: -3.4 | AC11: 2.2 | AD11: 10 | AI11: -3.6 | AJ11: -3.5 | AN11: -1.7 | AO11: 0 | AP11: 1.3 | AQ11: 13.4 | AR11: 9.8 | AS11: -1 | AT11: 1.8 | AU11: 0.2 | AV11: 15.2 | AW11: -10.6 | AX11: -42.9 | AY11: 0.6 | AZ11: -1.1 | BA11: 0 | BB11: -3.7 | BC11: 2.8 | BD11: 0.5 | BE11: 0 | BF11: -7.6 | BI11: -4.4 | BL11: 0 | BP11: 4.1 | BQ11: -15.2 | BR11: -13.7 | BS11: -4.7 | BT11: 7.4 | CB11: 0 | CC11: -0.6 | CD11: 28.7 | CE11: 16.7 | CF11: 0.4 | CG11: 1.8 | CH11: -0.1 | CL11: 5.7 | CM11: 7.8 | CN11: -14.1 | CT11: 2.1 | CU11: -4.7 | CW11: -5 | CX11: 0 | CY11: -8.5 | DA11: 0.5 | DB11: 0.002 | DC11: 0 | DD11: -0.7 | DF11: -0.2 | DG11: 0.7 | DH11: -0.1 | DI11: -0.4 | DJ11: 0.1 | DK11: 0.5 | DM11: 0 | DN11: 0 | DO11: -1.5 | DP11: 2.4 | DQ11: 1.4 | DR11: 0.2 | DS11: 0.8 | DT11: 1.2 | DU11: 0 | DV11: -0.1 | DW11: 0.1 | DX11: 0.3 | DZ11: -1.7 | EA11: 0.1 | EB11: 0.3 | EC11: 0.3 | ED11: 0.3 | EE11: 0.8 | EF11: 4 | EG11: 0 | EH11: -2.3 | EI11: -3.2 | EJ11: -0.2 | EK11: 0 | EL11: 1.2 | EM11: 0.1 | EN11: 1.6 | EO11: 0.1 | EP11: 0.1 | EQ11: 0.1 | ER11: -5.1 | ES11: 0 | ET11: 0 | EU11: 0 | EV11: -0.2 | EW11: 0 | EX11: 0 | EY11: 0 | EZ11: 0 | FA11: 0.2 | FB11: 0.6 | FC11: 2.1 | FD11: 10.8 | FE11: 5.7 | FF11: 4 | FG11: 0.5 | FH11: 2.6 | FI11: 107.902 | FK11: 1.47578 | FL11: 0 | FM11: 1.08 | FN11: 1 | FO11: 0.29936 | FP11: 0 | FQ11: -0.8 | FR11: 0.8 | FS11: 3.85514
A12: 22/07/2025 | B12: 01:00 | C12: -18.1 | D12: 53.3 | E12: 12.1 | H12: 0 | I12: 15.3 | L12: -18 | M12: -30.5 | N12: -6.5 | O12: 31.4 | P12: 11.1 | Q12: 7.8 | R12: 41.9 | S12: 0 | X12: 6.8 | Y12: 2.1 | Z12: 1 | AB12: -3.4 | AC12: 2.1 | AD12: 10 | AI12: -4.1 | AJ12: -4.1 | AN12: -1.7 | AO12: -10.3 | AP12: 1.1 | AQ12: 15.1 | AR12: 8.9 | AS12: -0.6 | AT12: 1.8 | AU12: 0.1 | AV12: 14.6 | AW12: -11.5 | AX12: -43.9 | AY12: -1.1 | AZ12: -1.1 | BA12: -0.2 | BB12: -2.8 | BC12: 2.9 | BD12: 0.5 | BE12: 0 | BF12: -7.8 | BI12: -5.3 | BL12: 0 | BP12: 4 | BQ12: -15.1 | BR12: -13.3 | BS12: -4.6 | BT12: 7.4 | CB12: 0 | CC12: -0.6 | CD12: 26.6 | CE12: 17.9 | CF12: 3.2 | CG12: 1.4 | CH12: 0 | CL12: 3.9 | CM12: 6.4 | CN12: -16.9 | CT12: 0.9 | CU12: -5.3 | CW12: -6.6 | CX12: 0 | CY12: -8.4 | DA12: 0.5 | DB12: 0.008 | DC12: 0 | DD12: 0 | DF12: -0.2 | DG12: 0.7 | DH12: 0 | DI12: -0.3 | DJ12: 0.1 | DK12: 0.5 | DM12: 0 | DN12: 0 | DO12: -1.8 | DP12: 1.8 | DQ12: 1.4 | DR12: 0.4 | DS12: 0.8 | DT12: 1.2 | DU12: 0 | DV12: -0.1 | DW12: 0.2 | DX12: 0.3 | DZ12: -1.8 | EA12: 0.2 | EB12: 0.3 | EC12: 0.3 | ED12: 0.3 | EE12: 0.8 | EF12: 4 | EG12: 0 | EH12: -2.5 | EI12: -3.8 | EJ12: -0.3 | EK12: 0 | EL12: 1.2 | EM12: 0.1 | EN12: 1.6 | EO12: 0.1 | EP12: 0.1 | EQ12: 0.1 | ER12: -5.5 | ES12: 0 | ET12: 0 | EU12: 0 | EV12: -0.2 | EW12: 4.4 | EX12: 0.2 | EY12: 0 | EZ12: 0 | FA12: 0.2 | FB12: 0.6 | FC12: 1.9 | FD12: 10.5 | FE12: 5.4 | FF12: 2.9 | FG12: 0.7 | FH12: 2.5 | FI12: 99.608 | FK12: 1.39913 | FL12: 0 | FM12: 1.07 | FN12: 1 | FO12: 0.31798 | FP12: 0 | FQ12: -0.6 | FR12: 1 | FS12: 4.18711
A13: 22/07/2025 | B13: 01:30 | C13: -18 | D13: 45.5 | E13: 11.3 | H13: 0 | I13: 6.4 | L13: -22.7 | M13: -33.7 | N13: -6.9 | O13: 25.8 | P13: 9.3 | Q13: 5.8 | R13: 40.4 | S13: 0 | X13: 5.6 | Y13: 1.9 | Z13: 1 | AB13: -3.4 | AC13: 2.4 | AD13: 8.7 | AI13: -3.6 | AJ13: -4.8 | AN13: -1.7 | AO13: -10.3 | AP13: 0.9 | AQ13: 0 | AR13: 9.4 | AS13: -0.8 | AT13: 1.8 | AU13: 0.5 | AV13: 11.3 | AW13: -14.5 | AX13: -47 | AY13: 0.5 | AZ13: -1.2 | BA13: -0.2 | BB13: -2.6 | BC13: 3.8 | BD13: 0.5 | BE13: 0 | BF13: -6.7 | BI13: -6.4 | BL13: 0 | BP13: 2 | BQ13: -17.1 | BR13: -15.6 | BS13: -6.8 | BT13: 5.1 | CB13: 0 | CC13: -0.6 | CD13: 28.4 | CE13: 17 | CF13: 1.5 | CG13: 1.9 | CH13: 0.1 | CL13: 0.3 | CM13: 2.6 | CN13: -22.2 | CT13: -0.1 | CU13: -5.9 | CW13: -5.2 | CX13: 0 | CY13: -8.8 | DA13: 0.5 | DB13: 0.006 | DC13: 0 | DD13: 0 | DF13: -0.1 | DG13: 0.6 | DH13: 0 | DI13: -0.1 | DJ13: 0.1 | DK13: 0.5 | DM13: 0 | DN13: 0 | DO13: -1.7 | DP13: 1.5 | DQ13: 1.4 | DR13: 0.4 | DS13: 0.8 | DT13: 1.2 | DU13: 0 | DV13: 0 | DW13: 0.2 | DX13: 0.3 | DZ13: -1.7 | EA13: 0.1 | EB13: 0.3 | EC13: 0.2 | ED13: 0.3 | EE13: 0.8 | EF13: 4 | EG13: 0 | EH13: -3.8 | EI13: -4.3 | EJ13: -0.5 | EK13: -0.5 | EL13: 1.1 | EM13: 0.1 | EN13: 1.7 | EO13: 0.1 | EP13: 0.1 | EQ13: 0.1 | ER13: -5.5 | ES13: 0 | ET13: 0 | EU13: 0 | EV13: -0.2 | EW13: 4.6 | EX13: 0.5 | EY13: 0 | EZ13: 0 | FA13: 0.2 | FB13: 0.4 | FC13: 2.1 | FD13: 10.9 | FE13: 5.8 | FF13: 2.8 | FG13: 1.4 | FH13: 2.4 | FI13: 14.006 | FK13: 1.36134 | FL13: 0 | FM13: 1.42 | FN13: 1 | FO13: 0.31412 | FP13: 0 | FQ13: -1.2 | FR13: 0.7 | FS13: 3.59546
A14: 22/07/2025 | B14: 02:00 | C14: -20 | D14: 45.5 | E14: 11.3 | H14: 0 | I14: 15.7 | L14: -22.9 | M14: -33 | N14: -6.7 | O14: 24.5 | P14: 9.5 | Q14: 5.3 | R14: 41.1 | S14: 0 | X14: 5.2 | Y14: 1.2 | Z14: 0.5 | AB14: -3.4 | AC14: 2.7 | AD14: 8.3 | AI14: -4.4 | AJ14: -5.5 | AN14: -1.8 | AO14: -11.3 | AP14: 0.7 | AQ14: 0 | AR14: 9.5 | AS14: -0.9 | AT14: 1.8 | AU14: 1.4 | AV14: 11 | AW14: -14.3 | AX14: -47.4 | AY14: -0.8 | AZ14: -1 | BA14: 0 | BB14: -2.1 | BC14: 3.9 | BD14: 0.5 | BE14: 0 | BF14: -6.5 | BI14: -6.3 | BL14: 0 | BP14: 1.6 | BQ14: -18.3 | BR14: -16.7 | BS14: -1.6 | BT14: 4.4 | CB14: 0 | CC14: -0.6 | CD14: 27.7 | CE14: 16.5 | CF14: -0.2 | CG14: 1.8 | CH14: 0.1 | CL14: 0.2 | CM14: 2.2 | CN14: -22.5 | CT14: -1.8 | CU14: -6.9 | CW14: -7 | CX14: 0 | CY14: -8.5 | DA14: 0.5 | DB14: 0.016 | DC14: 0 | DD14: 0 | DF14: 0 | DG14: 0.6 | DH14: 0 | DI14: -0.3 | DJ14: 0.1 | DK14: 0.6 | DM14: 0 | DN14: 0 | DO14: -1.7 | DP14: 1.9 | DQ14: 1.4 | DR14: 0.4 | DS14: 0.8 | DT14: 1.2 | DU14: 0 | DV14: 0.1 | DW14: 0.2 | DX14: 0.3 | DZ14: -1.7 | EA14: 0 | EB14: 0.3 | EC14: 0.2 | ED14: 0.3 | EE14: 0.8 | EF14: 4 | EG14: 0 | EH14: -2.5 | EI14: -3.6 | EJ14: -0.3 | EK14: -0.4 | EL14: 1.1 | EM14: 0.1 | EN14: 1.7 | EO14: 0.1 | EP14: 0.1 | EQ14: 0.1 | ER14: -6.2 | ES14: 0 | ET14: 0 | EU14: 0 | EV14: -0.2 | EW14: 0.7 | EX14: 0.5 | EY14: 0 | EZ14: 0 | FA14: 0.2 | FB14: 0.5 | FC14: 2 | FD14: 10.6 | FE14: 5.4 | FF14: 2.6 | FG14: 0.7 | FH14: 2.4 | FI14: 7.316 | FK14: 1.31199 | FL14: 0 | FM14: 1.386 | FN14: 1 | FO14: 0.31853 | FP14: 0 | FQ14: -1 | FR14: 0.8 | FS14: 3.81652
A15: 22/07/2025 | B15: 02:30 | C15: -19.8 | D15: 42.1 | E15: 10.5 | H15: 0 | I15: 19.3 | L15: -23.9 | M15: -33.4 | N15: -6.9 | O15: 23.7 | P15: 8.7 | Q15: 5.4 | R15: 16.7 | S15: 0.1 | X15: 5.6 | Y15: 1.1 | Z15: 0.5 | AB15: -3.4 | AC15: 2.6 | AD15: 7.6 | AI15: -4.1 | AJ15: -5.3 | AN15: -1.8 | AO15: -10.8 | AP15: 0.9 | AQ15: 0 | AR15: 9.5 | AS15: -1.3 | AT15: 1.8 | AU15: 1.3 | AV15: 11.4 | AW15: -13.8 | AX15: -47 | AY15: -0.4 | AZ15: -1 | BA15: 0 | BB15: -0.9 | BC15: 4.6 | BD15: 0.5 | BE15: 0 | BF15: -6.8 | BI15: -6.4 | BL15: 0 | BP15: 2.5 | BQ15: -17.8 | BR15: -16.4 | BS15: -1.3 | BT15: 4 | CB15: 0 | CC15: -0.6 | CD15: 27.5 | CE15: 17 | CF15: 2.1 | CG15: 1.7 | CH15: 0.1 | CL15: -0.1 | CM15: 1.9 | CN15: -23 | CT15: -2.1 | CU15: -7.1 | CW15: -6.6 | CX15: 0 | CY15: -8.3 | DA15: 0.5 | DB15: 0.026 | DC15: 0 | DD15: 0 | DF15: 0 | DG15: 0.7 | DH15: 0 | DI15: 0 | DJ15: 0.1 | DK15: 0.5 | DM15: 0 | DN15: 0 | DO15: -1.7 | DP15: 1.6 | DQ15: 1.4 | DR15: 0.4 | DS15: 0.8 | DT15: 1.2 | DU15: 0 | DV15: 0 | DW15: 0.2 | DX15: 0.3 | DZ15: -1.7 | EA15: 0 | EB15: 0.3 | EC15: 0.2 | ED15: 0.5 | EE15: 0.8 | EF15: 4 | EG15: 0 | EH15: -4.4 | EI15: -5.2 | EJ15: -0.6 | EK15: 0 | EL15: 1.1 | EM15: 0.1 | EN15: 1.7 | EO15: 0.1 | EP15: 0.1 | EQ15: 0.1 | ER15: -5.8 | ES15: 0 | ET15: 0 | EU15: 0 | EV15: -0.2 | EW15: 0.5 | EX15: 0.1 | EY15: 0 | EZ15: 0 | FA15: 0.2 | FB15: 0.6 | FC15: 2 | FD15: 10.8 | FE15: 5.6 | FF15: 1 | FG15: 0.5 | FH15: 2.3 | FI15: -18.874 | FK15: 1.33987 | FL15: 0 | FM15: 1.238 | FN15: 1 | FO15: 0.32043 | FP15: 0 | FQ15: -0.9 | FR15: 0.8 | FS15: 3.7983
A16: 22/07/2025 | B16: 03:00 | C16: -20.2 | D16: 48.2 | E16: 11.5 | H16: 0 | I16: 5.5 | L16: -21.4 | M16: -31.6 | N16: -5.1 | O16: 27.5 | P16: 6.3 | Q16: 3.7 | R16: 18.2 | S16: 0 | X16: 5.5 | Y16: 1.4 | Z16: 0.7 | AB16: -3.4 | AC16: 2.6 | AD16: 7.5 | AI16: -4 | AJ16: -3.4 | AN16: -1.8 | AO16: -10.9 | AP16: 0.8 | AQ16: 0 | AR16: 8.4 | AS16: -1.4 | AT16: 1.8 | AU16: 0.2 | AV16: 4.5 | AW16: -20.9 | AX16: -44.2 | AY16: -1.1 | AZ16: -1 | BA16: 0 | BB16: -1.4 | BC16: 4 | BD16: 0.5 | BE16: 0 | BF16: -6.5 | BI16: -2.6 | BL16: 0 | BP16: 2.1 | BQ16: -20.5 | BR16: -18.8 | BS16: -3.8 | BT16: 1.8 | CB16: 0 | CC16: -0.6 | CD16: 27.7 | CE16: 16.5 | CF16: 2 | CG16: 1.7 | CH16: 0 | CL16: 5.5 | CM16: 7.6 | CN16: -14.9 | CT16: -6.5 | CU16: -9.7 | CW16: -7.4 | CX16: 0 | CY16: -9 | DA16: 0.5 | DB16: 0.014 | DC16: 0 | DD16: 0 | DF16: 0 | DG16: 0.7 | DH16: 0.1 | DI16: 0.4 | DJ16: 0.1 | DK16: 0.6 | DM16: 0 | DN16: 0 | DO16: -1.7 | DP16: 2 | DQ16: 1.4 | DR16: 0.4 | DS16: 0.8 | DT16: 1.2 | DU16: 0 | DV16: 0.1 | DW16: 0.2 | DX16: 0.3 | DZ16: -1.7 | EA16: 0 | EB16: 0.3 | EC16: 0.2 | ED16: 0.9 | EE16: 0.8 | EF16: 4 | EG16: 0 | EH16: -2.1 | EI16: -2.7 | EJ16: -0.2 | EK16: -0.3 | EL16: 1.1 | EM16: 0.1 | EN16: 1.7 | EO16: 0.1 | EP16: 0.1 | EQ16: 0.1 | ER16: -6.3 | ES16: 0 | ET16: 0 | EU16: 0 | EV16: -0.2 | EW16: 0.4 | EX16: 0.2 | EY16: 0 | EZ16: 0 | FA16: 0.2 | FB16: 1 | FC16: 2.1 | FD16: 9.8 | FE16: 4.7 | FF16: 3 | FG16: 0.7 | FH16: 2.4 | FI16: -20.886 | FK16: 1.3218 | FL16: 0 | FM16: 1.522 | FN16: 1 | FO16: 0.3227 | FP16: 0 | FQ16: -1.5 | FR16: 0.8 | FS16: 3.4665
A17: 22/07/2025 | B17: 03:30 | C17: -19.5 | D17: 50.3 | E17: 11.5 | H17: 0 | I17: 13.5 | L17: -19.9 | M17: -32.5 | N17: -6.4 | O17: 28.8 | P17: 5.9 | Q17: 3.7 | R17: 17.3 | S17: 0 | X17: 5.8 | Y17: 0.9 | Z17: 0.5 | AB17: -3.3 | AC17: 2.7 | AD17: 8.2 | AI17: -4.5 | AJ17: -5.4 | AN17: -1.8 | AO17: -11 | AP17: 0.7 | AQ17: 0 | AR17: 8.3 | AS17: -1.3 | AT17: 1.8 | AU17: 0.9 | AV17: 3.5 | AW17: -21.9 | AX17: -45.2 | AY17: -2.1 | AZ17: -0.8 | BA17: 0 | BB17: -1.7 | BC17: 3.1 | BD17: 0.5 | BE17: 0 | BF17: -6.3 | BI17: -0.7 | BL17: 0 | BP17: 2.7 | BQ17: -20.5 | BR17: -18.8 | BS17: -3.9 | BT17: 1.5 | CB17: 0 | CC17: -0.6 | CD17: 26.8 | CE17: 16.9 | CF17: 2.2 | CG17: 1.6 | CH17: 0 | CL17: 9.2 | CM17: 11.5 | CN17: -9.3 | CT17: -10.1 | CU17: -11.8 | CW17: -7.6 | CX17: 0 | CY17: -8.7 | DA17: 0.5 | DB17: 0.013 | DC17: 0 | DD17: 0 | DF17: 0 | DG17: 0.7 | DH17: 0.2 | DI17: 0.7 | DJ17: 0.1 | DK17: 0.6 | DM17: 0 | DN17: 0 | DO17: -1.9 | DP17: 1.9 | DQ17: 1.4 | DR17: 0.4 | DS17: 0.8 | DT17: 1.2 | DU17: 0 | DV17: 0.1 | DW17: 0.1 | DX17: 0.3 | DZ17: -1.8 | EA17: 0.2 | EB17: 0.4 | EC17: 0.2 | ED17: 0.9 | EE17: 0.8 | EF17: 4 | EG17: 0 | EH17: -2.5 | EI17: -3.4 | EJ17: -0.2 | EK17: -0.3 | EL17: 1.1 | EM17: 0.1 | EN17: 1.9 | EO17: 0.1 | EP17: 0.1 | EQ17: 0.1 | ER17: -6.5 | ES17: 0 | ET17: 0 | EU17: 0 | EV17: -0.2 | EW17: 4.9 | EX17: 0.7 | EY17: 0 | EZ17: 0 | FA17: 0.2 | FB17: 1 | FC17: 2 | FD17: 10.4 | FE17: 5.3 | FF17: 4 | FG17: 0.6 | FH17: 2.1 | FI17: -1.987 | FK17: 1.27868 | FL17: 0 | FM17: 1.452 | FN17: 1 | FO17: 0.31125 | FP17: 0 | FQ17: -1.2 | FR17: 0.8 | FS17: 3.64193
A18: 22/07/2025 | B18: 04:00 | C18: -19.2 | D18: 40.1 | E18: 10.4 | H18: 0 | I18: 6.3 | L18: -24.4 | M18: -33.3 | N18: -7 | O18: 23.2 | P18: 4.9 | Q18: 2.7 | R18: 14.9 | S18: 0 | X18: 5.3 | Y18: 1.4 | Z18: 0.8 | AB18: -3.4 | AC18: 2.7 | AD18: 8.1 | AI18: -2.6 | AJ18: -5.8 | AN18: -1.8 | AO18: 0 | AP18: 0.7 | AQ18: 0 | AR18: 8 | AS18: -1.1 | AT18: 1.8 | AU18: 0.6 | AV18: 2.6 | AW18: -22.9 | AX18: -46 | AY18: -0.7 | AZ18: -1 | BA18: 0.2 | BB18: -2.1 | BC18: 3.6 | BD18: 0.5 | BE18: 0 | BF18: -6.7 | BI18: -0.8 | BL18: 0 | BP18: -1.3 | BQ18: -21.5 | BR18: -20 | BS18: -5.2 | BT18: 0.4 | CB18: 0 | CC18: -0.6 | CD18: 27.6 | CE18: 16.2 | CF18: 2.4 | CG18: 1.5 | CH18: -0.1 | CL18: 8.7 | CM18: 10.9 | CN18: -10.1 | CT18: -9.4 | CU18: -11.4 | CW18: -6.8 | CX18: 0 | CY18: -8.9 | DA18: 0.5 | DB18: 0.012 | DC18: 0 | DD18: 0 | DF18: 0 | DG18: 0.7 | DH18: 0 | DI18: 0.8 | DJ18: 0.1 | DK18: 0.5 | DM18: 0 | DN18: 0 | DO18: -1.7 | DP18: 1.6 | DQ18: 1.4 | DR18: 0.4 | DS18: 0.8 | DT18: 1.2 | DU18: 0 | DV18: 0 | DW18: 0.2 | DX18: 0.3 | DZ18: -1.7 | EA18: 0.3 | EB18: 0.3 | EC18: 0.2 | ED18: 0.9 | EE18: 0.8 | EF18: 4 | EG18: 0 | EH18: -5.6 | EI18: -6.5 | EJ18: -0.8 | EK18: -0.6 | EL18: 1.1 | EM18: 0.1 | EN18: 2 | EO18: 0.1 | EP18: 0.1 | EQ18: 0.1 | ER18: -6.7 | ES18: 0 | ET18: 0 | EU18: 0 | EV18: -0.2 | EW18: 4.8 | EX18: 0.9 | EY18: 0 | EZ18: 0 | FA18: 0.2 | FB18: 1 | FC18: 2 | FD18: 10.6 | FE18: 5.5 | FF18: 3.6 | FG18: 0.7 | FH18: 1.4 | FI18: -42.188 | FK18: 1.29373 | FL18: 0 | FM18: 1.466 | FN18: 1.1 | FO18: 0.31226 | FP18: 0 | FQ18: -1.2 | FR18: 0.7 | FS18: 3.67199
A19: 22/07/2025 | B19: 04:30 | C19: -18.3 | D19: 45.6 | E19: 11.3 | H19: 0 | I19: 10 | L19: -21.6 | M19: -31.8 | N19: -5.4 | O19: 26.1 | P19: 7.1 | Q19: 3.9 | R19: 17.5 | S19: 0.1 | X19: 5.3 | Y19: 1.8 | Z19: 1 | AB19: -3.4 | AC19: 2.9 | AD19: 9 | AI19: -1.7 | AJ19: -3.6 | AN19: -1.8 | AO19: 0 | AP19: 0.5 | AQ19: 0 | AR19: 8.5 | AS19: -1.3 | AT19: 1.8 | AU19: 0.9 | AV19: 5.3 | AW19: -20.3 | AX19: -43.4 | AY19: -1.3 | AZ19: -0.9 | BA19: 0 | BB19: -2.9 | BC19: 4.1 | BD19: 0.5 | BE19: 0 | BF19: -7.6 | BI19: 0.1 | BL19: 0 | BP19: 0.2 | BQ19: -20.1 | BR19: -18.4 | BS19: -3.5 | BT19: 2.2 | CB19: 0 | CC19: -0.6 | CD19: 19.6 | CE19: 16.5 | CF19: 1.8 | CG19: 1.7 | CH19: 0 | CL19: 11.6 | CM19: 13.9 | CN19: -5.5 | CT19: -7.2 | CU19: -10.1 | CW19: -6.9 | CX19: 0 | CY19: -8.4 | DA19: 0.5 | DB19: 0.013 | DC19: 0 | DD19: 0 | DF19: 0 | DG19: 0.7 | DH19: 0.1 | DI19: 0.9 | DJ19: 0.1 | DK19: 0.5 | DM19: 0 | DN19: 0 | DO19: -1.4 | DP19: 2.2 | DQ19: 1.2 | DR19: 0.4 | DS19: 0.7 | DT19: 1 | DU19: 0 | DV19: 0 | DW19: 0.2 | DX19: 0.3 | DZ19: -1.7 | EA19: 0.1 | EB19: 0.3 | EC19: 0.2 | ED19: 1 | EE19: 0.8 | EF19: 4 | EG19: 0 | EH19: -4.4 | EI19: -5 | EJ19: -0.6 | EK19: -0.5 | EL19: 1.1 | EM19: 0.1 | EN19: 2 | EO19: 0.1 | EP19: 0.1 | EQ19: 0.1 | ER19: -6.5 | ES19: 0 | ET19: 0 | EU19: 0 | EV19: -0.2 | EW19: 1.4 | EX19: 0.6 | EY19: 0 | EZ19: 0 | FA19: 0.2 | FB19: 1.2 | FC19: 2.1 | FD19: 11.9 | FE19: 6.8 | FF19: 3.8 | FG19: 1.4 | FH19: 2.9 | FI19: 15.513 | FK19: 1.28152 | FL19: 0 | FM19: 1.386 | FN19: 1 | FO19: 0.30883 | FP19: 0 | FQ19: -0.7 | FR19: 0.8 | FS19: 4.07635
A20: 22/07/2025 | B20: 05:00 | C20: -18.9 | D20: 38 | E20: 10.3 | H20: 0 | I20: 14.3 | L20: -22.9 | M20: -35.2 | N20: -9.4 | O20: 26.3 | P20: 7.3 | Q20: 4 | R20: 15.2 | S20: -0.1 | X20: 4.2 | Y20: 1.7 | Z20: 0.9 | AB20: -3.4 | AC20: 2.8 | AD20: 8.9 | AI20: -1.9 | AJ20: -4.3 | AN20: -1.8 | AO20: 0 | AP20: 0.5 | AQ20: 0 | AR20: 8.9 | AS20: -1 | AT20: 1.8 | AU20: 1 | AV20: 7.4 | AW20: -18.8 | AX20: -41.8 | AY20: -2.5 | AZ20: -1.1 | BA20: 0 | BB20: -4.1 | BC20: 3.8 | BD20: 0.5 | BE20: 0 | BF20: -9 | BI20: 0.2 | BL20: 0 | BP20: -0.8 | BQ20: -19.5 | BR20: -17.8 | BS20: -3.2 | BT20: 2.8 | CB20: 0 | CC20: -0.6 | CD20: 19.4 | CE20: 16.8 | CF20: 1.8 | CG20: 1.5 | CH20: 0 | CL20: 13.7 | CM20: 16 | CN20: -2.4 | CT20: -7.1 | CU20: -10.1 | CW20: -6.9 | CX20: 0 | CY20: -8.9 | DA20: 0.5 | DB20: 0.006 | DC20: 0 | DD20: 0 | DF20: 0 | DG20: 0.6 | DH20: 0.1 | DI20: 0.6 | DJ20: 0.1 | DK20: 0.5 | DM20: 0 | DN20: 0 | DO20: -1.8 | DP20: 1.8 | DQ20: 1.2 | DR20: 0.4 | DS20: 0.7 | DT20: 1 | DU20: 0.2 | DV20: 0.1 | DW20: 0.2 | DX20: 0.2 | DZ20: -1.8 | EA20: 0.1 | EB20: 0.4 | EC20: 0.2 | ED20: 1.1 | EE20: 0.8 | EF20: 4 | EG20: 0.4 | EH20: -5.9 | EI20: -7 | EJ20: -0.8 | EK20: -0.7 | EL20: 1.1 | EM20: 0.1 | EN20: 2 | EO20: 0.1 | EP20: 0.1 | EQ20: 0.1 | ER20: -6.3 | ES20: 0 | ET20: 0 | EU20: 0 | EV20: -0.2 | EW20: 1.5 | EX20: 0 | EY20: 0 | EZ20: 0 | FA20: 0.2 | FB20: 1.2 | FC20: 2 | FD20: 11.5 | FE20: 6.4 | FF20: 4.2 | FG20: 1.5 | FH20: 2.9 | FI20: 2.106 | FK20: 1.27261 | FL20: 0 | FM20: 1.514 | FN20: 1 | FO20: 0.3089 | FP20: 0 | FQ20: -0.7 | FR20: 1.2 | FS20: 4.59551
A21: 22/07/2025 | B21: 05:30 | C21: -17.6 | D21: 42.9 | E21: 11.1 | H21: 0 | I21: 18.9 | L21: -20.9 | M21: -31.5 | N21: -5.3 | O21: 27.5 | P21: 8.4 | Q21: 5.2 | R21: 30.7 | S21: 0.1 | X21: 6.2 | Y21: 1.7 | Z21: 1.1 | AB21: -3.3 | AC21: 3.2 | AD21: 9.9 | AI21: -1.5 | AJ21: -0.1 | AN21: -1.7 | AO21: 0 | AP21: 0.3 | AQ21: 0.1 | AR21: 9.5 | AS21: 0.3 | AT21: 1.8 | AU21: 1.2 | AV21: 9.4 | AW21: -16.2 | AX21: -39.3 | AY21: -1.5 | AZ21: -1.1 | BA21: 0 | BB21: -1.7 | BC21: 5.1 | BD21: 0.5 | BE21: 0 | BF21: -7.1 | BI21: 0.8 | BL21: 0 | BP21: 0.1 | BQ21: -18.1 | BR21: -17 | BS21: -1.7 | BT21: 3.7 | CB21: 0 | CC21: -0.6 | CD21: 19.2 | CE21: 16 | CF21: 2.6 | CG21: 1.8 | CH21: 0 | CL21: 17.1 | CM21: 19.4 | CN21: 2.8 | CT21: -4.6 | CU21: -8.5 | CW21: -5.8 | CX21: 0 | CY21: -8 | DA21: 0.5 | DB21: 0.008 | DC21: 0 | DD21: 0 | DF21: 0 | DG21: 0.6 | DH21: 0 | DI21: 0.7 | DJ21: 0.1 | DK21: 0.5 | DM21: 0 | DN21: 0 | DO21: -1.8 | DP21: 1.6 | DQ21: 1.4 | DR21: 0.4 | DS21: 0.7 | DT21: 1.2 | DU21: 0.2 | DV21: 0 | DW21: 0.2 | DX21: 0.2 | DZ21: -2 | EA21: 0.1 | EB21: 0.3 | EC21: 0.2 | ED21: 0.9 | EE21: 0.8 | EF21: 4 | EG21: 0.4 | EH21: -7 | EI21: -8.3 | EJ21: -1 | EK21: 0 | EL21: 1.1 | EM21: 0.1 | EN21: 2.1 | EO21: 0.1 | EP21: 0.1 | EQ21: 0.1 | ER21: -6.1 | ES21: 0 | ET21: 0 | EU21: 0 | EV21: -0.2 | EW21: 1 | EX21: 0.2 | EY21: 0 | EZ21: 0 | FA21: 0.2 | FB21: 1.2 | FC21: 2 | FD21: 12.3 | FE21: 7.1 | FF21: 5 | FG21: 1.5 | FH21: 2.5 | FI21: 90.708 | FK21: 1.26599 | FL21: 0 | FM21: 1.612 | FN21: 1 | FO21: 0.30467 | FP21: 0 | FQ21: -0.2 | FR21: 0.8 | FS21: 4.78266
A22: 22/07/2025 | B22: 06:00 | C22: -17.5 | D22: 47.8 | E22: 11.6 | H22: 0 | I22: 11.4 | L22: -18.5 | M22: -31.7 | N22: -5.5 | O22: 30.2 | P22: 8.9 | Q22: 5.7 | R22: 45 | S22: 0 | X22: 7.1 | Y22: 1.9 | Z22: 0.6 | AB22: -3.3 | AC22: 3.1 | AD22: 10.3 | AI22: -1.7 | AJ22: -0.2 | AN22: -1.6 | AO22: 0 | AP22: 0.5 | AQ22: 8.7 | AR22: 8.6 | AS22: -0.4 | AT22: 1.8 | AU22: 0.7 | AV22: 9.7 | AW22: -15.7 | AX22: -38.7 | AY22: -1.5 | AZ22: -0.9 | BA22: -0.1 | BB22: -4.4 | BC22: 4.1 | BD22: 0.5 | BE22: 0 | BF22: -9.4 | BI22: 1.2 | BL22: 0 | BP22: -0.3 | BQ22: -17.6 | BR22: -15.9 | BS22: -1 | BT22: 5 | CB22: 0 | CC22: -0.6 | CD22: 20.1 | CE22: 16.8 | CF22: 2.8 | CG22: 3.6 | CH22: -0.1 | CL22: 18 | CM22: 20.3 | CN22: 4.1 | CT22: -2.4 | CU22: -7.3 | CW22: -6.8 | CX22: 0 | CY22: -8.7 | DA22: 0.5 | DB22: 0.013 | DC22: 0 | DD22: 0 | DF22: 0 | DG22: 0.6 | DH22: -0.1 | DI22: 1 | DJ22: 0.1 | DK22: 0.6 | DM22: 0 | DN22: 0 | DO22: -1.5 | DP22: 2.5 | DQ22: 1.4 | DR22: 0.4 | DS22: 0.8 | DT22: 1.2 | DU22: 0.2 | DV22: 0 | DW22: 0.1 | DX22: 0.2 | DZ22: -2.1 | EA22: 0.2 | EB22: 0.3 | EC22: 0.2 | ED22: 1 | EE22: 0.8 | EF22: 4 | EG22: 0.3 | EH22: -5.6 | EI22: -6.7 | EJ22: 0 | EK22: -0.8 | EL22: 1.1 | EM22: 0.1 | EN22: 2.1 | EO22: 0.1 | EP22: 0.1 | EQ22: 0.1 | ER22: -6.3 | ES22: 0 | ET22: 0 | EU22: 0 | EV22: -0.2 | EW22: 1.3 | EX22: 0.3 | EY22: 0 | EZ22: 0 | FA22: 0.2 | FB22: 1.2 | FC22: 2.1 | FD22: 13.1 | FE22: 7.9 | FF22: 3.2 | FG22: 2.5 | FH22: 2.4 | FI22: 129.213 | FK22: 1.33059 | FL22: 0 | FM22: 1.532 | FN22: 1 | FO22: 0.31318 | FP22: 0 | FQ22: 0 | FR22: 0.8 | FS22: 4.97577
... A58: 23/07/2025 | B58: 00:00 | C58: -17 | D58: 28.4 | E58: 16.6 | H58: 0 | I58: 15 | L58: -27.6 | M58: -29.9 | N58: -8 | O58: 42.3 | P58: 26.1 | Q58: 14.2 | R58: 38.8 | S58: 0 | X58: 7 | Y58: 1.5 | Z58: 0.6 | AB58: -3.5 | AC58: 4.2 | AD58: 6.6 | AI58: -2.5 | AJ58: -6.6 | AN58: -1.5 | AO58: -21.5 | AP58: 3.1 | AQ58: 18.1 | AR58: 8.1 | AS58: -0.5 | AT58: 1.8 | AU58: 1 | AV58: 10.1 | AW58: -11.9 | AX58: -43.7 | AY58: -2.6 | AZ58: -1.1 | BA58: 0.1 | BB58: -1.4 | BC58: 1.1 | BD58: 0.5 | BE58: 0.1 | BF58: -9 | BI58: -2.7 | BL58: -3.9 | BP58: -3.3 | BQ58: -29.4 | BR58: -30.7 | BS58: 8.2 | BT58: 6.7 | CB58: 0 | CC58: -0.6 | CD58: 36.5 | CE58: 21.3 | CF58: 3.6 | CG58: 6.9 | CH58: 0.9 | CL58: 10.5 | CM58: 12.6 | CN58: -29.6 | CT58: -12.2 | CU58: -10.3 | CW58: -8.4 | CX58: 0 | CY58: -9.8 | DA58: 0.5 | DB58: 0.014 | DC58: 0 | DD58: 0 | DF58: 0 | DG58: 0.5 | DH58: 0.1 | DI58: 0 | DJ58: 0.1 | DK58: 0.5 | DM58: 0 | DN58: 0 | DO58: -2.5 | DP58: 0.3 | DQ58: 1.6 | DR58: 0.6 | DS58: 0.8 | DT58: 1.2 | DU58: 0 | DV58: 0 | DW58: 0.2 | DX58: 0.3 | DZ58: -1.6 | EA58: 0 | EB58: 0.4 | EC58: 0.3 | ED58: 0.5 | EE58: 0.8 | EF58: 4 | EG58: 0 | EH58: -7.2 | EI58: -8.2 | EJ58: -1 | EK58: -0.8 | EL58: 1 | EM58: 0.1 | EN58: 1.7 | EO58: 0.1 | EP58: 0.1 | EQ58: 0.1 | ER58: -6.8 | ES58: 0 | ET58: 0 | EU58: 0 | EV58: -0.2 | EW58: 0 | EX58: 3.7 | EY58: 0 | EZ58: 0 | FA58: 0.2 | FB58: 0.6 | FC58: 2.4 | FD58: 10.9 | FE58: 5.8 | FF58: 3 | FG58: 0 | FH58: 2.9 | FI58: 40.314 | FK58: 1.77155 | FL58: 0 | FM58: 1.232 | FN58: 0.9 | FO58: 0.28081 | FP58: 0.0036 | FQ58: -0.7 | FR58: 0.9 | FS58: 4.38796
A59: EJEC | C59: -273.7 | D59: 954.45 | E59: 342.1 | F59: 0 | G59: 0 | H59: -59.45 | I59: 442.15 | J59: 0 | K59: 0 | L59: -148.25 | M59: -320.35 | N59: 121.05 | O59: 1021.45 | P59: 305.9 | Q59: 173.8 | R59: 761.75 | S59: 0.95 | T59: 0 | U59: 0 | V59: 0 | W59: 0 | X59: 154.65 | Y59: 36.75 | Z59: 10.8 | AA59: 0 | AB59: -82.15 | AC59: 102.05 | AD59: 281.45 | AE59: 0 | AF59: 0 | AG59: 0 | AH59: 0 | AI59: 69.65 | AJ59: 4.5 | AK59: 0 | AL59: 0 | AM59: 0 | AN59: -31 | AO59: -15.35 | AP59: 51.5 | AQ59: 346.9 | AR59: 245.5 | AS59: -12.45 | AT59: 43 | AU59: 17.65 | AV59: 379.5 | AW59: -144.95 | AX59: -982.35 | AY59: 55.3 | AZ59: -29.4 | BA59: 0.1 | BB59: -28.55 | BC59: 48.45 | BD59: 12 | BE59: 1.75 | BF59: -166.4 | BG59: 0 | BH59: 0 | BI59: 46.95 | BJ59: 0 | BK59: 0 | BL59: -6.25 | BM59: 0 | BN59: 0 | BO59: 0 | BP59: 80.1 | BQ59: -153.4 | BR59: -135.25 | BS59: 124.95 | BT59: 527.95 | BU59: 0 | BV59: 0 | BW59: 0 | BX59: 0 | BY59: 0 | BZ59: 0 | CA59: 0 | CB59: 3.25 | CC59: -14.35 | CD59: 1122.55 | CE59: 824 | CF59: 210.15 | CG59: 164.15 | CH59: 85.85 | CI59: 0 | CJ59: 0 | CK59: 0 | CL59: 520.35 | CM59: 574.65 | CN59: -9.75 | CO59: 0 | CP59: 0 | CQ59: 0 | CR59: 0 | CS59: 0 | CT59: 42.9 | CU59: -103.7 | CV59: 0 | CW59: -238.1 | CX59: 59.4 | CY59: -200.7 | CZ59: 0 | DA59: 12 | DB59: 0.326 | DC59: -0.1 | DD59: -3.7 | DE59: 0 | DF59: -0.4 | DG59: 13.35 | DH59: 0.3 | DI59: 14.1 | DJ59: 2.05 | DK59: 12.3 | DL59: 0 | DM59: -6.9 | DN59: -14.3 | DO59: -67.8 | DP59: -36.7 | DQ59: 37 | DR59: 10.3 | DS59: 19.05 | DT59: 28.95 | DU59: -19.6 | DV59: 0.8 | DW59: 5.05 | DX59: 7.25 | DY59: 0 | DZ59: -40.65 | EA59: 3 | EB59: 9.1 | EC59: 7.55 | ED59: 21 | EE59: 19.2 | EF59: 96 | EG59: 17.95 | EH59: -150.65 | EI59: -168.85 | EJ59: -21.35 | EK59: -14.6 | EL59: 25 | EM59: 2.15 | EN59: 45.25 | EO59: 2.4 | EP59: 2.4 | EQ59: 2.4 | ER59: -159.6 | ES59: 4.4 | ET59: 13.15 | EU59: -12.25 | EV59: -4.8 | EW59: 79.4 | EX59: 56.55 | EY59: -31.4 | EZ59: 12.05 | FA59: 9.5 | FB59: 26 | FC59: 54.45 | FD59: 274.2 | FE59: 150.45 | FF59: 71.85 | FG59: 26.6 | FH59: 58.05 | FI59: 7715.676 | FK59: 34.448535 | FL59: -0.997 | FM59: 32.193 | FN59: 23.15 | FO59: 6.82237 | FP59: 0.006 | FQ59: 5.65 | FR59: 33.7 | FS59: 134.9729

Sheet DEMANDA_AREAS
B3: martes, 22 de Julio del 2025
B5: REPORTE DE LA DEMANDA POR ÁREAS Y SUBAREAS OPERATIVAS (MW)
B6: FECHA HORA | C6: DEMANDA | E6: AREA | H6: SUBAREAS
C7: INTERCAMBIOS INTERNACIONALES | D7: SEIN | E7: NORTE | F7: CENTRO | G7: SUR | H7: ELECTROANDES
B8: 00:30 | C8: 0 | D8: 6437.027 | E8: 895.6527 | F8: 3864.9094 | G8: 1676.4649 | H8: 250.4748
B9: 01:00 | C9: 0 | D9: 6385.748 | E9: 909.0232 | F9: 3797.8188 | G9: 1678.906 | H9: 250.0678
B10: 01:30 | C10: 0 | D10: 6241.269 | E10: 854.9917 | F10: 3732.0309 | G10: 1654.2464 | H10: 248.6499
B11: 02:00 | C11: 0 | D11: 6228.529 | E11: 891.2639 | F11: 3699.1082 | G11: 1638.1569 | H11: 245.065
B12: 02:30 | C12: 0 | D12: 6072.468 | E12: 893.1922 | F12: 3545.5012 | G12: 1633.7746 | H12: 243.7664
B13: 03:00 | C13: 0 | D13: 6131.52 | E13: 839.2213 | F13: 3662.2993 | G13: 1629.9994 | H13: 246.7842
B14: 03:30 | C14: 0 | D14: 6118.997 | E14: 874.8098 | F14: 3623.4817 | G14: 1620.7055 | H14: 249.026
B15: 04:00 | C15: 0 | D15: 6005.126 | E15: 854.6764 | F15: 3503.3639 | G15: 1647.0857 | H15: 252.4403
B16: 04:30 | C16: 0 | D16: 6105.658 | E16: 866.1438 | F16: 3564.4193 | G16: 1675.0949 | H16: 251.7101
B17: 05:00 | C17: 0 | D17: 6102.228 | E17: 885.4115 | F17: 3547.4862 | G17: 1669.3303 | H17: 244.2529
B18: 05:30 | C18: 0 | D18: 6246.189 | E18: 937.2461 | F18: 3620.5471 | G18: 1688.3958 | H18: 243.5957
B19: 06:00 | C19: 0 | D19: 6287.502 | E19: 919.9373 | F19: 3682.8403 | G19: 1684.7244 | H19: 235.4267
... B59: ENERGÍA | C59: 0 | D59: 165550.86 | E59: 24960.204 | F59: 99622.948 | G59: 40967.711 | H59: 5841.4109
B61: LEYENDA:
D63: Potencia recibida del Ecuador
D64: Potencia entregada al Ecuador

Sheet DEMANDA_UL
B3: martes, 22 de Julio del 2025
B5: POTENCIA DE LOS GRANDES USUARIOS LIBRES (MW)
B6: FECHA HORA | C6: GRANDES USUARIOS LIBRES DEL ÁREA NORTE | X6: GRANDES USUARIOS LIBRES DEL ÁREA CENTRO | BP6: GRANDES USUARIOS LIBRES DEL ÁREA SUR
C7: ARCA CONTINENTAL LINDLEY S.A. | D7: AUSTRAL GROUP S.A.A | E7: CEMENTOS PACASMAYO | F7: CONSORCIO MINERO HORIZONTE S.R.L. | G7: CORPORACIÓN PESQUERA INCA S.A.C. | H7: CREDITEX: CIA IND.TEXTIL CREDISA | I7: HIPERMERCADOS TOTTUS S.A | J7: INDUSTRIA TEXTIL PIURA | K7: MINERA BOROO MISQUICHILCA S.A. | L7: MINERA GOLD FIELDS | M7: MINERA MARSA | N7: MINERA MISKY MAYO | O7: MINERA YANACOCHA | P7: OPEN PLAZA | Q7: PESQUERA DIAMANTE | R7: PETROPERU | S7: REAL PLAZA S.R.L. | T7: SIDER PERU | U7: SUPERMERCADOS PERUANOS S.A. | V7: TRUPAL S.A. | W7: UNIÓN DE CERVECERÍAS PERUANAS BACKUS Y JOHNSTON S. | X7: ACEROS AREQUIPA | Y7: ADMINISTRADORA JOCKEY PLAZA SHOPPING CENTER S.A. | Z7: ALICORP | AA7: ARCA CONTINENTAL LINDLEY S.A. | AB7: AUSTRAL GROUP S.A.A | AC7: COMPAÑIA MINERA CONDESTABLE | AD7: CORPORACIÓN PESQUERA INCA S.A.C. | AE7: CREDITEX: CIA IND.TEXTIL CREDISA | AF7: FUNDICION CHILCA S.A. | AG7: HIPERMERCADOS TOTTUS S.A | AH7: INMOBILIARIA KANPU S.A. | AI7: INMUEBLES PANAMERICANA S.A. | AJ7: KIMBERLY-CLARK PERU | AK7: LECHE GLORIA S.A. | AL7: MALL AVENTURA S.A. | AM7: MARCOBRE S.A.C. | AN7: MINERA ANTAMINA | AO7: MINERA ARES | AP7: MINERA BUENAVENTURA | AQ7: MINERA CHINALCO PERÚ S.A. | AR7: MINERA SHOUXIN PERU S.A. | AS7: MINERA VOLCAN | AT7: MINSUR | AU7: MOLYCOP-ADESUR | AV7: NEXA RESOURCES CAJAMARQUILLA S.A. | AW7: NEXA RESOURCES PERÚ S.A.A. | AX7: OPEN PLAZA | AY7: OPP FILM | AZ7: OWENS-ILLINOIS PERÚ S.A. | BA7: PAPELERA NACIONAL S.A. | BB7: PESQUERA DIAMANTE | BC7: QUIMPAC S.A. | BD7: REAL PLAZA S.R.L. | BE7: REFINERIA LA PAMPILLA S.A.A | BF7: SAGA FALABELLA | BG7: SAN MIGUEL INDUSTRIAS PET S.A. | BH7: SHOUGANG HIERRO PERU | BI7: SOFTYS PERU S.A.C. | BJ7: SUPERMERCADOS PERUANOS S.A. | BK7: TEJIDOS SAN JACINTO | BL7: TREN URBANO DE LIMA S.A. | BM7: TRUPAL S.A. | BN7: UNACEM PERU S.A. | BO7: UNIÓN DE CERVECERÍAS PERUANAS BACKUS Y JOHNSTON S. | BP7: ANGLO AMERICAN QUELLAVECO S.A. | BQ7: ARCA CONTINENTAL LINDLEY S.A. | BR7: CAL & CEMENTO SUR S.A. | BS7: COMPAÑIA MINERA ANTAPACCAY S.A. | BT7: COMPAÑÍA MINERA CHUNGAR SAC | BU7: COMPAÑIA MINERA SAN IGNACIO DE MOROCOCHA S.A.A. | BV7: EL BROCAL .S.A. | BW7: EMPRESA ADMINISTRADORA CERRO S.A.C. | BX7: EMPRESA MINERA LOS QUENUALES S.A.C. | BY7: HIPERMERCADOS TOTTUS S.A | BZ7: HUDBAY PERU S.A.C. | CA7: INDUSTRIA CACHIMAYO | CB7: MALL AVENTURA S.A. | CC7: MINERA ARES | CD7: MINERA BUENAVENTURA | CE7: MINERA CERRO VERDE | CF7: MINERA CORONA | CG7: MINERA LAS BAMBAS S.A. | CH7: MINERA VOLCAN | CI7: MINSUR | CJ7: MOLYCOP-ADESUR | CK7: NEXA RESOURCES PERÚ S.A.A. | CL7: OXIDOS DE PASCO S.A.C. | CM7: PESQUERA DIAMANTE | CN7: REAL PLAZA S.R.L. | CO7: SOBREANDES S.A.C. | CP7: SOUTHERN PERU CC | CQ7: SUPERMERCADOS PERUANOS S.A. | CR7: UNACEM PERU S.A. | CS7: UNIÓN DE CERVECERÍAS PERUANAS BACKUS Y JOHNSTON S. | CT7: YURA
B8: 00:30 | E8: 24.28833 | F8: 12.223 | L8: 26.0734 | M8: 13.883 | N8: 12.95 | O8: 31.222 | R8: 52.272 | T8: 34.3622 | V8: 3.7 | X8: 144.007 | AC8: 14.9 | AJ8: 5.33786 | AK8: 0 | AM8: 49.53295 | AN8: 86.445 | AO8: 28.43236 | AP8: 0.81 | AQ8: 165.03 | AS8: 40.19236 | AT8: 32.15504 | AV8: 179.44489 | AW8: 35.1006 | BA8: 2.5 | BC8: 65.33817 | BE8: 20.5 | BI8: 19.32181 | BK8: 5.55288 | BM8: 6.987 | BO8: 1.24 | BP8: 142.71591 | BR8: 4.77991 | BS8: 132.67861 | BT8: 14.74458 | BV8: 36.6567 | BW8: 3.85819 | BZ8: 90.4098 | CA8: 24.794 | CC8: 0.59 | CD8: 23.55331 | CE8: 329.57023 | CG8: 157.09406 | CH8: 14.69887 | CK8: 17.69 | CL8: 5.04804 | CO8: 16.66374 | CP8: 294.95 | CR8: 32.181 | CS8: 2.10284 | CT8: 24.155
B9: 01:00 | E9: 25.0267 | F9: 13.175 | L9: 26.1898 | M9: 12.914 | N9: 12.83 | O9: 30.77 | R9: 51.728 | T9: 42.2962 | V9: 3.7 | X9: 139.325 | AC9: 16.17 | AJ9: 5.33431 | AK9: 0 | AM9: 49.81065 | AN9: 87.53291 | AO9: 27.7 | AP9: 0.7 | AQ9: 163.52 | AS9: 40.69145 | AT9: 35.0754 | AV9: 180.08173 | AW9: 35.329 | BA9: 2.5 | BC9: 65.90461 | BE9: 20.5 | BI9: 18.83061 | BK9: 5.59357 | BM9: 7.126 | BO9: 1.33 | BP9: 144.44226 | BR9: 4.6849 | BS9: 133.71242 | BT9: 14.75898 | BV9: 36.032 | BW9: 3.96348 | BZ9: 90.8918 | CA9: 24.857 | CC9: 0.6 | CD9: 24.46113 | CE9: 329.80532 | CG9: 159.09956 | CH9: 14.54751 | CK9: 17.56 | CL9: 5.06878 | CO9: 17.24444 | CP9: 293.91 | CR9: 33.05 | CS9: 2.03853 | CT9: 24.166
B10: 01:30 | E10: 27.18633 | F10: 13.119 | L10: 25.9334 | M10: 13.356 | N10: 12.68 | O10: 30.96 | R10: 51.957 | T10: 42.6622 | V10: 4.8 | X10: 118.417 | AC10: 15.94 | AJ10: 5.31128 | AK10: 0 | AM10: 49.53622 | AN10: 100.34753 | AO10: 28.38874 | AP10: 0.64 | AQ10: 160.37 | AS10: 40.98131 | AT10: 34.99237 | AV10: 183.08552 | AW10: 35.7975 | BA10: 2.4 | BC10: 69.23577 | BE10: 20.5 | BI10: 18.99323 | BK10: 5.52999 | BM10: 6.989 | BO10: 1.32 | BP10: 144.68526 | BR10: 4.84702 | BS10: 133.02231 | BT10: 14.94622 | BV10: 36.0056 | BW10: 4.0073 | BZ10: 91.6039 | CA10: 24.888 | CC10: 0.59 | CD10: 24.92508 | CE10: 326.9019 | CG10: 154.34869 | CH10: 14.55351 | CK10: 17.22 | CL10: 5.06642 | CO10: 17.23019 | CP10: 294.73 | CR10: 32.986 | CS10: 1.73932 | CT10: 24.265
B11: 02:00 | E11: 28.70232 | F11: 13.14 | L11: 26.0934 | M11: 13.867 | N11: 12.62 | O11: 32.116 | R11: 52.329 | T11: 48.3442 | V11: 5.1 | X11: 113.199 | AC11: 15.77 | AJ11: 5.27359 | AK11: 0 | AM11: 50.89999 | AN11: 100.19802 | AO11: 28.87576 | AP11: 0.44 | AQ11: 160.31 | AS11: 39.40568 | AT11: 35.0305 | AV11: 182.42897 | AW11: 36.0988 | BA11: 2.5 | BC11: 69.35009 | BE11: 20.5 | BI11: 19.06216 | BK11: 5.49415 | BM11: 7.123 | BO11: 1.39 | BP11: 142.84945 | BR11: 4.79155 | BS11: 131.73748 | BT11: 14.66025 | BV11: 36.8917 | BW11: 3.7307 | BZ11: 92.2903 | CA11: 24.886 | CC11: 0.57 | CD11: 24.74968 | CE11: 328.24815 | CG11: 161.9033 | CH11: 14.75411 | CK11: 17.11 | CL11: 4.7469 | CO11: 16.99463 | CP11: 285.11 | CR11: 32.799 | CS11: 2.07407 | CT11: 24.429
B12: 02:30 | E12: 29.04275 | F12: 12.992 | L12: 26.1902 | M12: 13.843 | N12: 11.62 | O12: 32.252 | R12: 52.301 | T12: 33.2661 | V12: 6.4 | X12: 139.03 | AC12: 15.62 | AJ12: 5.22184 | AK12: 0 | AM12: 51.41183 | AN12: 106.47953 | AO12: 28.7035 | AP12: 0.41 | AQ12: 162.52 | AS12: 39.8782 | AT12: 36.12513 | AV12: 183.20721 | AW12: 36.1786 | BA12: 2.6 | BC12: 69.37101 | BE12: 20.5 | BI12: 18.66568 | BK12: 5.51099 | BM12: 6.987 | BO12: 1.14 | BP12: 144.78496 | BR12: 4.75277 | BS12: 133.40307 | BT12: 14.61684 | BV12: 36.2367 | BW12: 3.87202 | BZ12: 91.7398 | CA12: 24.897 | CC12: 0.6 | CD12: 25.62026 | CE12: 314.52808 | CG12: 159.25537 | CH12: 14.63114 | CK12: 16.93 | CL12: 4.71046 | CO12: 16.91144 | CP12: 283.6 | CR12: 32.28 | CS12: 2.16897 | CT12: 24.334
B13: 03:00 | E13: 28.82325 | F13: 13.323 | L13: 25.9123 | M13: 13.91 | N13: 8.37 | O13: 31.816 | R13: 52.233 | T13: 45.6653 | V13: 7.8 | X13: 173.953 | AC13: 15.39 | AJ13: 4.81592 | AK13: 0 | AM13: 50.6463 | AN13: 109.06067 | AO13: 28.76431 | AP13: 0.67 | AQ13: 163.05 | AS13: 40.4438 | AT13: 35.64801 | AV13: 183.1723 | AW13: 36.135 | BA13: 2.5 | BC13: 69.498 | BE13: 20.5 | BI13: 18.53615 | BK13: 5.32768 | BM13: 7.126 | BO13: 1.09 | BP13: 143.3912 | BR13: 4.76051 | BS13: 129.92674 | BT13: 13.42149 | BV13: 35.1761 | BW13: 3.96593 | BZ13: 91.9541 | CA13: 24.926 | CC13: 0.57 | CD13: 25.8199 | CE13: 313.4808 | CG13: 162.07706 | CH13: 16.39852 | CK13: 16.9 | CL13: 4.72504 | CO13: 16.89993 | CP13: 291.65 | CR13: 32.394 | CS13: 1.99744 | CT13: 24.296
B14: 03:30 | E14: 32.5708 | F14: 12.993 | L14: 25.6657 | M14: 13.913 | N14: 9.52 | O14: 31.49 | R14: 52.259 | T14: 45.1042 | V14: 8 | X14: 141.979 | AC14: 15.13 | AJ14: 5.05719 | AK14: 0 | AM14: 49.658 | AN14: 105.72126 | AO14: 28.32181 | AP14: 0.48 | AQ14: 159.43 | AS14: 38.87742 | AT14: 35.30115 | AV14: 183.19729 | AW14: 36.1082 | BA14: 2.6 | BC14: 69.45945 | BE14: 20.5 | BI14: 18.40464 | BK14: 5.44738 | BM14: 6.989 | BO14: 1.16 | BP14: 142.81571 | BR14: 4.74627 | BS14: 130.8967 | BT14: 14.61294 | BV14: 34.7458 | BW14: 4.02736 | BZ14: 93.1163 | CA14: 24.938 | CC14: 0.6 | CD14: 26.53962 | CE14: 316.21041 | CG14: 160.50384 | CH14: 16.94509 | CK14: 16.85 | CL14: 4.73615 | CO14: 17.20121 | CP14: 282.25 | CR14: 31.887 | CS14: 1.69476 | CT14: 24.299
B15: 04:00 | E15: 32.51645 | F15: 12.659 | L15: 25.8035 | M15: 14.021 | N15: 11.3 | O15: 31.286 | R15: 52.201 | T15: 48.6721 | V15: 9.2 | X15: 56.651 | AC15: 15.3 | AJ15: 5.19055 | AK15: 0 | AM15: 49.72302 | AN15: 114.44383 | AO15: 27.74955 | AP15: 0.18 | AQ15: 160.71 | AS15: 40.0672 | AT15: 34.03948 | AV15: 183.01867 | AW15: 34.5063 | BA15: 2.6 | BC15: 69.46354 | BE15: 20.5 | BI15: 18.42725 | BK15: 5.53195 | BM15: 7.123 | BO15: 1.24 | BP15: 143.27501 | BR15: 4.72687 | BS15: 134.97455 | BT15: 14.96581 | BV15: 35.4981 | BW15: 3.88656 | BZ15: 93.1111 | CA15: 24.959 | CC15: 0.59 | CD15: 26.67437 | CE15: 325.8224 | CG15: 161.5833 | CH15: 17.04159 | CK15: 16.08 | CL15: 5.18259 | CO15: 16.92358 | CP15: 285.95 | CR15: 32.056 | CS15: 1.62577 | CT15: 24.362
B16: 04:30 | E16: 33.19051 | F16: 11.993 | L16: 26.4458 | M16: 14.305 | N16: 11.58 | O16: 31.388 | R16: 52.218 | T16: 34.3623 | V16: 9.4 | X16: 57.149 | AC16: 14.44 | AJ16: 5.28152 | AK16: 0 | AM16: 49.56405 | AN16: 114.53452 | AO16: 28.17273 | AP16: 1.65 | AQ16: 163.91 | AS16: 39.97028 | AT16: 33.38483 | AV16: 180.866 | AW16: 31.8557 | BA16: 2.5 | BC16: 69.44466 | BE16: 20.5 | BI16: 18.49803 | BK16: 5.40048 | BM16: 6.987 | BO16: 1.39 | BP16: 144.88351 | BR16: 4.68373 | BS16: 135.56694 | BT16: 14.17007 | BV16: 36.7813 | BW16: 3.90366 | BZ16: 92.5647 | CA16: 24.97 | CC16: 0.58 | CD16: 24.72416 | CE16: 329.04843 | CG16: 163.68314 | CH16: 17.74012 | CK16: 16.47 | CL16: 5.12921 | CO16: 17.31273 | CP16: 292.73 | CR16: 32.072 | CS16: 1.48598 | CT16: 24.138
B17: 05:00 | E17: 32.4808 | F17: 12.416 | L17: 26.4716 | M17: 14.723 | N17: 12.44 | O17: 31.508 | R17: 51.637 | T17: 39.1958 | V17: 9.8 | X17: 52.171 | AC17: 14.03 | AJ17: 5.03627 | AK17: 0 | AM17: 48.72074 | AN17: 108.63735 | AO17: 27.98176 | AP17: 2.1 | AQ17: 163.19 | AS17: 40.17361 | AT17: 32.99486 | AV17: 179.53608 | AW17: 30.4264 | BA17: 2.6 | BC17: 69.51189 | BE17: 20.5 | BI17: 18.59012 | BK17: 5.30761 | BM17: 7.126 | BO17: 1.4 | BP17: 148.73972 | BR17: 4.677 | BS17: 134.12794 | BT17: 14.26679 | BV17: 35.1605 | BW17: 4.37541 | BZ17: 92.2108 | CA17: 24.982 | CC17: 0.62 | CD17: 23.71391 | CE17: 329.77863 | CG17: 158.0755 | CH17: 17.86316 | CK17: 16.51 | CL17: 5.06298 | CO17: 16.2907 | CP17: 293.45 | CR17: 32.528 | CS17: 1.91995 | CT17: 24.198
B18: 05:30 | E18: 33.44683 | F18: 11.8 | L18: 26.6473 | M18: 15.156 | N18: 12.89 | O18: 31.188 | R18: 51.477 | T18: 45.0254 | V18: 9.9 | X18: 36.368 | AC18: 14.58 | AJ18: 5.08865 | AK18: 0 | AM18: 49.88268 | AN18: 105.33261 | AO18: 27.26068 | AP18: 1.93 | AQ18: 163.88 | AS18: 37.15278 | AT18: 32.58594 | AV18: 178.76395 | AW18: 29.8284 | BA18: 2.6 | BC18: 69.8266 | BE18: 20.5 | BI18: 18.59709 | BK18: 5.52365 | BM18: 6.989 | BO18: 1.88 | BP18: 147.71326 | BR18: 4.67376 | BS18: 134.66687 | BT18: 14.51403 | BV18: 34.5159 | BW18: 3.85894 | BZ18: 93.0188 | CA18: 24.962 | CC18: 0.59 | CD18: 23.62031 | CE18: 328.81804 | CG18: 157.58074 | CH18: 18.1916 | CK18: 16.53 | CL18: 4.98843 | CO18: 15.616 | CP18: 290.59 | CR18: 32.753 | CS18: 1.55793 | CT18: 24.303
B19: 06:00 | E19: 33.71815 | F19: 10.621 | L19: 26.9902 | M19: 15.202 | N19: 12.87 | O19: 31.992 | R19: 51.616 | T19: 44.4217 | V19: 9.8 | X19: 11.847 | AC19: 15.11 | AJ19: 5.10208 | AK19: 0 | AM19: 50.67557 | AN19: 106.21818 | AO19: 27.55131 | AP19: 1.54 | AQ19: 164.15 | AS19: 35.44464 | AT19: 32.63975 | AV19: 180.65405 | AW19: 28.9595 | BA19: 2.4 | BC19: 69.72521 | BE19: 20.5 | BI19: 18.41631 | BK19: 5.40884 | BM19: 7.123 | BO19: 1.85 | BP19: 147.7446 | BR19: 4.60334 | BS19: 132.52727 | BT19: 13.42636 | BV19: 34.3979 | BW19: 3.65085 | BZ19: 91.8115 | CA19: 24.907 | CC19: 0.64 | CD19: 23.38412 | CE19: 328.62873 | CG19: 153.15472 | CH19: 17.78311 | CK19: 16.74 | CL19: 4.7383 | CO19: 14.92695 | CP19: 284.83 | CR19: 32.416 | CS19: 1.52641 | CT19: 24.226
... B55: 00:00 | E55: 29.73825 | F55: 12.1 | L55: 26.4592 | M55: 13.748 | N55: 12.95 | O55: 32.98 | R55: 51.892 | T55: 42.8641 | V55: 8.1 | X55: 23.831 | AC55: 13.82 | AJ55: 5.27586 | AK55: 0 | AM55: 49.65254 | AN55: 120.9485 | AO55: 28.19067 | AP55: 0.83 | AQ55: 161.33 | AS55: 38.98833 | AT55: 34.95852 | AV55: 179.90709 | AW55: 31.3053 | BA55: 2.6 | BC55: 67.92937 | BE55: 20.8 | BI55: 13.01568 | BK55: 5.27433 | BM55: 7.123 | BO55: 1.67 | BP55: 148.51285 | BR55: 4.53072 | BS55: 132.56231 | BT55: 14.38471 | BV55: 36.2158 | BW55: 3.83695 | BZ55: 93.0287 | CA55: 24.742 | CC55: 0.53 | CD55: 24.12398 | CE55: 327.56102 | CG55: 159.98273 | CH55: 17.92874 | CK55: 19.26 | CL55: 5.3588 | CO55: 17.52173 | CP55: 233 | CR55: 30.854 | CS55: 1.80374 | CT55: 23.507
B56: MWh | C56: 0 | D56: 0 | E56: 720.02642 | F56: 289.73125 | G56: 0 | H56: 0 | I56: 0 | J56: 0 | K56: 0 | L56: 643.38525 | M56: 312.314 | N56: 278.045 | O56: 766.665 | P56: 0 | Q56: 0 | R56: 1243.2125 | S56: 0 | T56: 916.4443 | U56: 0 | V56: 204.8 | W56: 0 | X56: 639.5175 | Y56: 0 | Z56: 0 | AA56: 0 | AB56: 0 | AC56: 356.52 | AD56: 0 | AE56: 0 | AF56: 0 | AG56: 0 | AH56: 0 | AI56: 0 | AJ56: 118.96792 | AK56: 0 | AL56: 0 | AM56: 1142.5391 | AN56: 2748.9997 | AO56: 652.96659 | AP56: 18.01 | AQ56: 3884.275 | AR56: 0 | AS56: 862.56624 | AT56: 789.67115 | AU56: 0 | AV56: 3974.3472 | AW56: 758.99235 | AX56: 0 | AY56: 0 | AZ56: 0 | BA56: 55.7 | BB56: 0 | BC56: 1481.2231 | BD56: 0 | BE56: 493.1 | BF56: 0 | BG56: 0 | BH56: 0 | BI56: 414.39535 | BJ56: 0 | BK56: 128.71926 | BL56: 0 | BM56: 169.35 | BN56: 0 | BO56: 40.685 | BP56: 3483.9948 | BQ56: 0 | BR56: 107.75327 | BS56: 3174.3482 | BT56: 317.09859 | BU56: 0 | BV56: 822.3895 | BW56: 93.42783 | BX56: 0 | BY56: 0 | BZ56: 2184.7773 | CA56: 493.22 | CB56: 0 | CC56: 14.185 | CD56: 576.95276 | CE56: 7760.0522 | CF56: 0 | CG56: 3779.7077 | CH56: 395.79865 | CI56: 0 | CJ56: 0 | CK56: 406.475 | CL56: 115.94569 | CM56: 0 | CN56: 0 | CO56: 383.00402 | CP56: 6074.37 | CQ56: 0 | CR56: 699.2205 | CS56: 46.595825 | CT56: 422.752
B59: Nota :
B60: Información proporcionada por la empresas
C62: DATOS ESTIMADOS
C64: SIN DATOS

Sheet TIPO_RECURSO
B3: martes, 22 de Julio del 2025
B5: REPORTE POTENCIA GENERADA POR TIPO DE RECURSO
B6: HORA | C6: H. PASADA | D6: H. REGULACION | E6: GAS DE CAMISEA | F6: GAS DE MALACAS | G6: GAS DE AGUAYTIA | H6: DIÉSEL | I6: RESIDUAL | J6: NAFTA+GAS DE REFINERIA | K6: FLEXIGAS+GAS DE REFINERIA | L6: BAGAZO | M6: BIOGÁS | N6: SOLAR | O6: EÓLICA | P6: TOTAL | U6: EMPRESA | V6: CENTRAL | W6: HIDROELECTRICA DE PASADA | X6: HIDROELECTRICA DE REGULACION
B7: 00:30 | C7: 802.027 | D7: 1950.2 | E7: 3379.1 | F7: 0 | H7: 0 | K7: =DESPACHO_EJECUTADO!FD11+DESPACHO_EJECUTADO!FE11 -> 64.7 | L7: 50.2 | M7: 10.1 | N7: 0 | O7: 180.7 | P7: =SUM(C7:O7) -> 6437.027 | U7: ANDEAN POWER S.A.C. | V7: C.H.CARHUAC | W7: 298
B8: 01:00 | C8: 789.048 | D8: 1910.8 | E8: 3373.8 | F8: 0 | H8: 0 | K8: =DESPACHO_EJECUTADO!FD12+DESPACHO_EJECUTADO!FE12 -> 64.9 | L8: 48.1 | M8: 10.6 | N8: 0 | O8: 188.5 | P8: =SUM(C8:O8) -> 6385.748 | U8: ASOCIACIÓN SANTA LUCIA DE CHACAS | V8: C.H. HUALLIN | W8: 31.55
B9: 01:30 | C9: 777.269 | D9: 1748.8 | E9: 3376.2 | F9: 0 | H9: 0 | K9: =DESPACHO_EJECUTADO!FD13+DESPACHO_EJECUTADO!FE13 -> 65 | L9: 50.5 | M9: 10.7 | N9: 0 | O9: 212.8 | P9: =SUM(C9:O9) -> 6241.269 | U9: CELEPSA | V9: C.H. EL PLATANAL | X9: 2074.4
B10: 02:00 | C10: 758.329 | D10: 1752.4 | E10: 3379.9 | F10: 0 | H10: 0 | K10: =DESPACHO_EJECUTADO!FD14+DESPACHO_EJECUTADO!FE14 -> 65 | L10: 51.1 | M10: 10.7 | N10: 0 | O10: 211.1 | P10: =SUM(C10:O10) -> 6228.529 | U10: CELEPSA RENOVABLES S.R.L. | V10: C.H. MARAÑON | W10: 318.45
B11: 02:30 | C11: 790.468 | D11: 1603.2 | E11: 3377.1 | F11: 0 | H11: 0 | K11: =DESPACHO_EJECUTADO!FD15+DESPACHO_EJECUTADO!FE15 -> 65 | L11: 49.1 | M11: 10.7 | N11: 0 | O11: 176.9 | P11: =SUM(C11:O11) -> 6072.468 | U11: CHINANGO S.A.C. | V11: C.H. CHIMAY | X11: 1214.5
B12: 03:00 | C12: 792.22 | D12: 1660.8 | E12: 3378.2 | F12: 0 | H12: 0 | K12: =DESPACHO_EJECUTADO!FD16+DESPACHO_EJECUTADO!FE16 -> 65 | L12: 49.8 | M12: 10.7 | N12: 0 | O12: 174.8 | P12: =SUM(C12:O12) -> 6131.52 | V12: C.H. YANANGO | W12: 496.3
B13: 03:30 | C13: 778.997 | D13: 1645.8 | E13: 3377.5 | F13: 0 | H13: 0 | K13: =DESPACHO_EJECUTADO!FD17+DESPACHO_EJECUTADO!FE17 -> 64.9 | L13: 50.4 | M13: 10.7 | N13: 0 | O13: 190.7 | P13: =SUM(C13:O13) -> 6118.997 | U13: EGASA | V13: C.H. CHARCANI III | W13: 156.85
B14: 04:00 | C14: 803.426 | D14: 1494.1 | E14: 3381.6 | F14: 0 | H14: 0 | K14: =DESPACHO_EJECUTADO!FD18+DESPACHO_EJECUTADO!FE18 -> 65 | L14: 52.1 | M14: 10.7 | N14: 0 | O14: 198.2 | P14: =SUM(C14:O14) -> 6005.126 | V14: C.H. CHARCANI IV | X14: 316.95
B15: 04:30 | C15: 792.958 | D15: 1566 | E15: 3382.3 | F15: 0 | H15: 0 | K15: =DESPACHO_EJECUTADO!FD19+DESPACHO_EJECUTADO!FE19 -> 65.2 | L15: 51.6 | M15: 9.7 | N15: 0 | O15: 237.9 | P15: =SUM(C15:O15) -> 6105.658 | V15: C.H. CHARCANI V | X15: 1962.2
B16: 05:00 | C16: 797.328 | D16: 1548.1 | E16: 3388.6 | F16: 0 | H16: 0 | K16: =DESPACHO_EJECUTADO!FD20+DESPACHO_EJECUTADO!FE20 -> 64.8 | L16: 50.6 | M16: 9.3 | N16: 0 | O16: 243.5 | P16: =SUM(C16:O16) -> 6102.228 | U16: EGEJUNIN | V16: C.H. HUASAHUASI I | W16: 113.55
B17: 05:30 | C17: 798.189 | D17: 1725.9 | E17: 3385.6 | F17: 0 | H17: 0 | K17: =DESPACHO_EJECUTADO!FD21+DESPACHO_EJECUTADO!FE21 -> 65 | L17: 51.8 | M17: 10.4 | N17: 0 | O17: 209.3 | P17: =SUM(C17:O17) -> 6246.189 | V17: C.H. RUNATULLO II | W17: 86.05
B18: 06:00 | C18: 794.602 | D18: 1801 | E18: 3390.7 | F18: 0 | H18: 0 | K18: =DESPACHO_EJECUTADO!FD22+DESPACHO_EJECUTADO!FE22 -> 65.3 | L18: 51.7 | M18: 10.7 | N18: 0.1 | O18: 173.4 | P18: =SUM(C18:O18) -> 6287.502 | V18: C.H. RUNATULLO III | W18: 120.25
B19: 06:30 | C19: 806.669 | D19: 1982.7 | E19: 3394.3 | F19: 21.1 | H19: 0 | K19: =DESPACHO_EJECUTADO!FD23+DESPACHO_EJECUTADO!FE23 -> 65.3 | L19: 51.9 | M19: 9.2 | N19: 13.6 | O19: 165.5 | P19: =SUM(C19:O19) -> 6510.269 | V19: C.H. SANTA CRUZ I | W19: 82.5
B20: 07:00 | C20: 800.212 | D20: 1763.3 | E20: 3390.5 | F20: 46.3 | H20: 0 | K20: =DESPACHO_EJECUTADO!FD24+DESPACHO_EJECUTADO!FE24 -> 65.3 | L20: 52.2 | M20: 9.2 | N20: 158.3 | O20: 164.5 | P20: =SUM(C20:O20) -> 6449.812 | U20: EGEMSA | V20: C.H. MACHUPICCHU | W20: 2674.7
B21: 07:30 | C21: 790.494 | D21: 1751.5 | E21: 3386 | F21: 46.5 | H21: 0 | K21: =DESPACHO_EJECUTADO!FD25+DESPACHO_EJECUTADO!FE25 -> 65.2 | L21: 52.2 | M21: 9.2 | N21: 364.3 | O21: 172.7 | P21: =SUM(C21:O21) -> 6638.094 | U21: EGESUR | V21: C.H. ARICOTA I | X21: 177.75
B22: 08:00 | C22: 803.898 | D22: 1798.2 | E22: 3387.3 | F22: 46.5 | H22: 0 | K22: =DESPACHO_EJECUTADO!FD26+DESPACHO_EJECUTADO!FE26 -> 65 | L22: 53.3 | M22: 9.2 | N22: 352.3 | O22: 194.8 | P22: =SUM(C22:O22) -> 6710.498 | V22: C.H. ARICOTA II | X22: 122.4
B23: 08:30 | C23: 799.422 | D23: 2051 | E23: 3386.2 | F23: 46.2 | H23: 0 | K23: =DESPACHO_EJECUTADO!FD27+DESPACHO_EJECUTADO!FE27 -> 65 | L23: 51 | M23: 9.2 | N23: 357.1 | O23: 220.8 | P23: =SUM(C23:O23) -> 6985.922 | U23: ELECTRICA YANAPAMPA SAC | V23: C.H. YANAPAMPA | W23: 55.3
B24: 09:00 | C24: 809.567 | D24: 2068.2 | E24: 3387.1 | F24: 46.4 | H24: 0 | K24: =DESPACHO_EJECUTADO!FD28+DESPACHO_EJECUTADO!FE28 -> 65.6 | L24: 51.4 | M24: 9.2 | N24: 379.5 | O24: 259.6 | P24: =SUM(C24:O24) -> 7076.567 | U24: ELECTROPERU | V24: C.H. MANTARO | X24: 14879.7
B25: 09:30 | C25: 805.259 | D25: 2172.1 | E25: 3373.7 | F25: 45.7 | H25: 0 | K25: =DESPACHO_EJECUTADO!FD29+DESPACHO_EJECUTADO!FE29 -> 64.9 | L25: 51.5 | M25: 9.1 | N25: 380.3 | O25: 237.9 | P25: =SUM(C25:O25) -> 7140.459 | V25: C.H. RESTITUCION | W25: 4190.25
B26: 10:00 | C26: 813.002 | D26: 2241.3 | E26: 3375.9 | F26: 46 | H26: 0 | K26: =DESPACHO_EJECUTADO!FD30+DESPACHO_EJECUTADO!FE30 -> 64.8 | L26: 48.9 | M26: 8.7 | N26: 374.7 | O26: 279.3 | P26: =SUM(C26:O26) -> 7252.602 | U26: EMPRESA DE GENERACION ELECTRICA CANCHAYLLO SAC | V26: C.H. CANCHAYLLO | W26: 48.15
B27: 10:30 | C27: 806.399 | D27: 2270.8 | E27: 3372.3 | F27: 45.7 | H27: 0 | K27: =DESPACHO_EJECUTADO!FD31+DESPACHO_EJECUTADO!FE31 -> 65.2 | L27: 51.6 | M27: 8.7 | N27: 378.3 | O27: 288.8 | P27: =SUM(C27:O27) -> 7287.799 | U27: EMPRESA DE GENERACION ELECTRICA RIO BAÑOS S.A.C. | V27: C.H. RUCUY | W27: 370.6
B28: 11:00 | C28: 795.764 | D28: 2203.7 | E28: 3362 | F28: 44.9 | H28: 10.2 | K28: =DESPACHO_EJECUTADO!FD32+DESPACHO_EJECUTADO!FE32 -> 64.8 | L28: 52.2 | M28: 8.7 | N28: 381.4 | O28: 351.6 | P28: =SUM(C28:O28) -> 7275.264 | U28: EMPRESA DE GENERACION ELECTRICA SANTA ANA S.A.C. | V28: C.H. RENOVANDES H1 | W28: 455.6
B29: 11:30 | C29: 805.038 | D29: 2207.7 | E29: 3352.3 | F29: 46.2 | H29: 22.4 | K29: =DESPACHO_EJECUTADO!FD33+DESPACHO_EJECUTADO!FE33 -> 64.8 | L29: 51.7 | M29: 8.7 | N29: 384.1 | O29: 408.3 | P29: =SUM(C29:O29) -> 7351.238 | U29: EMPRESA DE GENERACION HUALLAGA | V29: C.H. CHAGLLA | X29: 3187.25
B30: 12:00 | C30: 809.484 | D30: 2088.2 | E30: 3343.5 | F30: 46 | H30: 0 | K30: =DESPACHO_EJECUTADO!FD34+DESPACHO_EJECUTADO!FE34 -> 63.8 | L30: 50.6 | M30: 8.7 | N30: 385.6 | O30: 499.5 | P30: =SUM(C30:O30) -> 7295.384 | V30: P.C.H. CHAGLLA | W30: 151.45
B31: 12:30 | C31: 811.901 | D31: 2087 | E31: 3318 | F31: 46.7 | H31: 0 | K31: =DESPACHO_EJECUTADO!FD35+DESPACHO_EJECUTADO!FE35 -> 63.5 | L31: 49.6 | M31: 8.9 | N31: 384.6 | O31: 505.5 | P31: =SUM(C31:O31) -> 7275.701 | U31: EMPRESA DE GENERACION HUANZA | V31: C.H. HUANZA | X31: 1133.25
B32: 13:00 | C32: 809.576 | D32: 2047.7 | E32: 3246 | F32: 46.5 | H32: 0 | K32: =DESPACHO_EJECUTADO!FD36+DESPACHO_EJECUTADO!FE36 -> 64.3 | L32: 51.2 | M32: 9.2 | N32: 385.9 | O32: 512.4 | P32: =SUM(C32:O32) -> 7172.776 | U32: EMPRESA ELECTRICA AGUA AZUL | V32: C.H. POTRERO | W32: 178.75
B33: 13:30 | C33: 806.375 | D33: 2008.5 | E33: 3240.8 | F33: 46.3 | H33: 0 | K33: =DESPACHO_EJECUTADO!FD37+DESPACHO_EJECUTADO!FE37 -> 64.1 | L33: 51 | M33: 9.2 | N33: 387.5 | O33: 501.5 | P33: =SUM(C33:O33) -> 7115.275 | U33: EMPRESA ELECTRICA RIO DOBLE | V33: C.H. LAS PIZARRAS | W33: 120
B34: 14:00 | C34: 817.251 | D34: 2046.1 | E34: 3239.8 | F34: 46.2 | H34: 0 | K34: =DESPACHO_EJECUTADO!FD38+DESPACHO_EJECUTADO!FE38 -> 64.2 | L34: 51.3 | M34: 9.9 | N34: 387 | O34: 532.4 | P34: =SUM(C34:O34) -> 7194.151 | U34: ENGIE | V34: C.H. YUNCAN | X34: 1610.3
B35: 14:30 | C35: 866.466 | D35: 2107.2 | E35: 3236.8 | F35: 46.3 | H35: 0 | K35: =DESPACHO_EJECUTADO!FD39+DESPACHO_EJECUTADO!FE39 -> 65.1 | L35: 50.9 | M35: 10.1 | N35: 383.9 | O35: 534.9 | P35: =SUM(C35:O35) -> 7301.666 | U35: GENERACIÓN ANDINA S.A.C. | V35: C.H. 8 DE AGOSTO | W35: 138.7
B36: 15:00 | C36: 862.311 | D36: 2189.9 | E36: 3241.2 | F36: 46.2 | H36: 0 | K36: =DESPACHO_EJECUTADO!FD40+DESPACHO_EJECUTADO!FE40 -> 65.3 | L36: 50.2 | M36: 9.8 | N36: 375.7 | O36: 496.5 | P36: =SUM(C36:O36) -> 7337.111 | V36: C.H. EL CARMEN | W36: 47.75
B37: 15:30 | C37: 858.097 | D37: 2159.6 | E37: 3230.2 | F37: 46.1 | H37: 0 | K37: =DESPACHO_EJECUTADO!FD41+DESPACHO_EJECUTADO!FE41 -> 65.2 | L37: 48.2 | M37: 9.9 | N37: 361.1 | O37: 523.4 | P37: =SUM(C37:O37) -> 7301.797 | U37: GENERADORA DE ENERGÍA DEL PERÚ | V37: C.H. ÁNGEL I | W37: 96.05
B38: 16:00 | C38: 860.212 | D38: 2038.5 | E38: 3344.6 | F38: 46.5 | H38: 0 | K38: =DESPACHO_EJECUTADO!FD42+DESPACHO_EJECUTADO!FE42 -> 65.1 | L38: 51 | M38: 10 | N38: 305.3 | O38: 588.2 | P38: =SUM(C38:O38) -> 7309.412 | V38: C.H. ÁNGEL II | W38: 107.85
B39: 16:30 | C39: 865.395 | D39: 2104.5 | E39: 3345.7 | F39: 46.6 | H39: 0 | K39: =DESPACHO_EJECUTADO!FD43+DESPACHO_EJECUTADO!FE43 -> 65.4 | L39: 50.6 | M39: 10 | N39: 178.4 | O39: 611.2 | P39: =SUM(C39:O39) -> 7277.795 | V39: C.H. ÁNGEL III | W39: 104.15
B40: 17:00 | C40: 866.43 | D40: 2157.4 | E40: 3355.8 | F40: 46.7 | H40: 0 | K40: =DESPACHO_EJECUTADO!FD44+DESPACHO_EJECUTADO!FE44 -> 64.9 | L40: 50.6 | M40: 10 | N40: 51.3 | O40: 629.6 | P40: =SUM(C40:O40) -> 7232.73 | V40: C.H. LA JOYA | W40: 215.95
B41: 17:30 | C41: 865.954 | D41: 2219 | E41: 3357.4 | F41: 45.9 | H41: 0 | K41: =DESPACHO_EJECUTADO!FD45+DESPACHO_EJECUTADO!FE45 -> 65.4 | L41: 50.7 | M41: 10 | N41: 0.8 | O41: 639.7 | P41: =SUM(C41:O41) -> 7254.854 | U41: HIDROCAÑETE S.A. | V41: C.H. IMPERIAL | W41: 78.35
B42: 18:00 | C42: 868.389 | D42: 2159.7 | E42: 3361.5 | F42: 45.4 | H42: 0 | K42: =DESPACHO_EJECUTADO!FD46+DESPACHO_EJECUTADO!FE46 -> 65.1 | L42: 51.5 | M42: 9.9 | N42: 0 | O42: 619.2 | P42: =SUM(C42:O42) -> 7180.689 | U42: HIDROELECTRICA HUANCHOR S.A.C. | V42: C.H. HUANCHOR | W42: 445.25
B43: 18:30 | C43: 854.834 | D43: 2408 | E43: 3366.3 | F43: 45.7 | H43: 0 | K43: =DESPACHO_EJECUTADO!FD47+DESPACHO_EJECUTADO!FE47 -> 64.7 | L43: 53.7 | M43: 9.9 | N43: 0 | O43: 584.1 | P43: =SUM(C43:O43) -> 7387.234 | U43: HUAURA POWER GROUP S.A. | V43: C.H. YARUCAYA | W43: 432.05
B44: 19:00 | C44: 863.785 | D44: 2480.5 | E44: 3365.8 | F44: 45.9 | H44: 0 | K44: =DESPACHO_EJECUTADO!FD48+DESPACHO_EJECUTADO!FE48 -> 65.5 | L44: 52.7 | M44: 9.9 | N44: 0 | O44: 525.6 | P44: =SUM(C44:O44) -> 7409.685 | U44: HYDRO GLOBAL PERÚ S.A.C. | V44: CH SAN GABAN III | X44: 1689.65
B45: 19:30 | C45: 861.251 | D45: 2531.7 | E45: 3372.8 | F45: 46.2 | H45: 0 | K45: =DESPACHO_EJECUTADO!FD49+DESPACHO_EJECUTADO!FE49 -> 64.8 | L45: 53.9 | M45: 9.9 | N45: 0 | O45: 431.3 | P45: =SUM(C45:O45) -> 7371.851 | U45: INLAND ENERGY SAC | V45: C.H. SANTA TERESA | W45: 1367.45
B46: 20:00 | C46: 867.161 | D46: 2606.2 | E46: 3370.5 | F46: 45.8 | H46: 0 | K46: =DESPACHO_EJECUTADO!FD50+DESPACHO_EJECUTADO!FE50 -> 63.1 | L46: 53.3 | M46: 9.9 | N46: 0 | O46: 368.5 | P46: =SUM(C46:O46) -> 7384.461 | U46: INVERSIONES SHAQSHA S.A.C. | V46: C.H. PARIAC | W46: 25.5
B47: 20:30 | C47: 868.653 | D47: 2619.2 | E47: 3366.9 | F47: 45.7 | H47: 0 | K47: =DESPACHO_EJECUTADO!FD51+DESPACHO_EJECUTADO!FE51 -> 64.9 | L47: 51.2 | M47: 9.9 | N47: 0 | O47: 318.2 | P47: =SUM(C47:O47) -> 7344.653 | U47: KALLPA GENERACION S.A. | V47: C.H. CERRO DEL AGUILA | X47: 8142.85
B48: 21:00 | C48: 863.492 | D48: 2632.5 | E48: 3365.7 | F48: 46.2 | H48: 0 | K48: =DESPACHO_EJECUTADO!FD52+DESPACHO_EJECUTADO!FE52 -> 64 | L48: 53.5 | M48: 9.9 | N48: 0 | O48: 261.1 | P48: =SUM(C48:O48) -> 7296.392 | V48: M.C.H. CERRO DEL AGUILA | W48: 103
B49: 21:30 | C49: 862.812 | D49: 2645.2 | E49: 3370.7 | F49: 46.2 | H49: 0 | K49: =DESPACHO_EJECUTADO!FD53+DESPACHO_EJECUTADO!FE53 -> 63.8 | L49: 53.2 | M49: 9.9 | N49: 0 | O49: 233.1 | P49: =SUM(C49:O49) -> 7284.912 | U49: LA VIRGEN | V49: C.H. LA VIRGEN | X49: 742.65
B50: 22:00 | C50: 858.852 | D50: 2577.5 | E50: 3370.9 | F50: 46.1 | H50: 0 | K50: =DESPACHO_EJECUTADO!FD54+DESPACHO_EJECUTADO!FE54 -> 64 | L50: 53.2 | M50: 9.9 | N50: 0 | O50: 240.6 | P50: =SUM(C50:O50) -> 7221.052 | U50: MAJA ENERGIA S.A.C. | V50: C.H. RONCADOR | W50: 67.4
B51: 22:30 | C51: 860.746 | D51: 2397.9 | E51: 3372 | F51: 46.1 | H51: 0 | K51: =DESPACHO_EJECUTADO!FD55+DESPACHO_EJECUTADO!FE55 -> 64.1 | L51: 51.8 | M51: 9.9 | N51: 0 | O51: 265.3 | P51: =SUM(C51:O51) -> 7067.846 | U51: ORAZUL ENERGY PERÚ | V51: C.H. CAÑA BRAVA | W51: 52.15
B52: 23:00 | C52: 866.715 | D52: 2208.4 | E52: 3371.1 | F52: 46 | H52: 0 | K52: =DESPACHO_EJECUTADO!FD56+DESPACHO_EJECUTADO!FE56 -> 63.9 | L52: 52.4 | M52: 9.9 | N52: 0 | O52: 248.4 | P52: =SUM(C52:O52) -> 6866.815 | V52: C.H. CAÑON DEL PATO | X52: 1817.9
B53: 23:30 | C53: 858.624 | D53: 2089.7 | E53: 3290.5 | F53: 47.7 | H53: 0 | K53: =DESPACHO_EJECUTADO!FD57+DESPACHO_EJECUTADO!FE57 -> 63.9 | L53: 50.6 | M53: 9.9 | N53: 0 | O53: 254 | P53: =SUM(C53:O53) -> 6664.924 | V53: C.H. CARHUAQUERO | X53: 687.95
B54: 00:00 | C54: 855.074 | D54: 1980.4 | E54: 3269.2 | F54: 47.6 | H54: 0 | K54: =DESPACHO_EJECUTADO!FD58+DESPACHO_EJECUTADO!FE58 -> 63.6 | L54: 49.8 | M54: 9.9 | N54: 0 | O54: 236.2 | P54: =SUM(C54:O54) -> 6511.774 | V54: C.H. CARHUAQUERO IV | W54: 178.6
B55: TOTAL MWh | C55: =SUM(C7:C54)/2 -> 19810.213 | D55: =SUM(D7:D54)/2 -> 49754.05 | E55: =SUM(E7:E54)/2 -> 80425.95 | F55: =SUM(F7:F54)/2 -> 819.05 | G55: =SUM(G7:G54)/2 -> 0 | H55: =SUM(H7:H54)/2 -> 16.3 | I55: =SUM(I7:I54)/2 -> 0 | J55: =SUM(J7:J54)/2 -> 0 | ... P55: =SUM(P7:P54)/2 -> 165550.86 | U55: ORYGEN PERU S.A.A. | V55: C.H. CALLAHUANCA | X55: 1760.7
B56: % | C56: =C55*100/$P$55 -> 11.966239 | D56: =D55*100/$P$55 -> 30.053634 | E56: =E55*100/$P$55 -> 48.58081 | F56: =F55*100/$P$55 -> 0.49474221 | G56: =G55*100/$P$55 -> 0 | H56: =H55*100/$P$55 -> 0.0098459167 | I56: =I55*100/$P$55 -> 0 | J56: =J55*100/$P$55 -> 0 | ... O56: =O55*100/$P$55 -> 4.9235624 | P56: 100.00 | V56: C.H. HER 1 | W56: 14.4
V57: C.H. HUAMPANI | W57: 712.15
V58: C.H. HUINCO | X58: 2465
V59: C.H. MATUCANA | X59: 2323.4
V60: C.H. MOYOPAMPA | W60: 1533.5
U61: PERUANA DE INVERSIONES EN ENERGIAS RENOVABLES S.A. | V61: C.H. MANTA I | W61: 184.2
U62: SAN GABAN | V62: C.H. SAN GABAN II | X62: 1330.3
V63: PCH TUPURI | W63: 7.2
U64: SINERSA | V64: C.H. CHANCAY | W64: 446.6
V65: C.H. POECHOS II | W65: 240.05
U66: STATKRAFT S.A | V66: C.H. ARCATA | W66: 48
V67: C.H. CAHUA | W67: 771.8
V68: C.H. CHEVES | X68: 1271.85
V69: C.H. GALLITO CIEGO | X69: 209.25
V70: C.H. MALPASO | X70: 633.85
V71: C.H. OROYA | W71: 192.6
V72: C.H. PACHACHACA | W72: 112.6
V73: C.H. YAUPI | W73: 2015.5
U74: VARI ENERGIA S.A.C. | V74: C.H. ANASHIRONI | W74: 123.1125
U75: TOTAL MWh | W75: 19810.213 | X75: 49754.05

Sheet GENERACION RER
B3: martes, 22 de Julio del 2025
B5: GENERACIÓN ELÉCTRICA DE LAS CENTRALES RER (MW)
B6: HORA | C6: AGRO INDUSTRIAL PARAMONGA S.A. | D6: AGROAURORA S.A.C. | E6: AGROINDUSTRIAS SAN JACINTO S.A.A. | F6: ANDEAN POWER S.A.C. | G6: ASOCIACIÓN SANTA LUCIA DE CHACAS | H6: ATRIA ENERGIA S.A.C. | I6: BIOENERGIA DEL CHIRA S.A. | J6: COLCA SOLAR S.A.C. | K6: EGEJUNIN | P6: ELECTRICA YANAPAMPA SAC | Q6: EMPRESA DE GENERACION ELECTRICA CANCHAYLLO SAC | R6: EMPRESA DE GENERACION ELECTRICA RIO BAÑOS S.A.C. | S6: EMPRESA DE GENERACION ELECTRICA SANTA ANA S.A.C. | T6: EMPRESA ELECTRICA AGUA AZUL | U6: EMPRESA ELECTRICA RIO DOBLE | V6: ENERGÍA EÓLICA S.A. | X6: ENERGIA RENOVABLE DEL SUR S.A. | Y6: ENGIE | AD6: GENERACIÓN ANDINA S.A.C. | AF6: GENERADORA DE ENERGÍA DEL PERÚ | AJ6: GR CORTARRAMA SOCIEDAD ANONIMA CERRADA | AK6: GR PAINO SOCIEDAD ANONIMA CERRADA | AL6: GR TARUCA SOCIEDAD ANONIMA CERRADA | AM6: HIDROCAÑETE S.A. | AN6: HUAURA POWER GROUP S.A. | AO6: HYDRO PATAPO S.A.C. | AP6: JOYA SOLAR S.A.C. | AQ6: KONDU SAC | AR6: MAJA ENERGIA S.A.C. | AS6: MAJES ARCUS S.A.C. | AT6: MOQUEGUA FV S.A.C. | AU6: ORAZUL ENERGY PERÚ | AW6: ORYGEN PERU S.A.A. | BB6: PANAMERICANA SOLAR SAC. | BC6: PARQUE EOLICO MARCONA S.A.C. | BD6: PARQUE EOLICO TRES HERMANAS S.A.C. | BE6: PERUANA DE INVERSIONES EN ENERGIAS RENOVABLES S.A. | BF6: PETRAMAS | BJ6: REPARTICIÓN ARCUS S.A.C. | BK6: SAN GABAN | BL6: SDF ENERGIA SAC | BM6: SINERSA | BO6: TACNA SOLAR SAC. | BP6: VARI ENERGIA S.A.C. | BQ6: TOTAL RER
C7: C.T. PARAMONGA | D7: C.T. MAPLE | E7: C.T SAN JACINTO | F7: C.H. CARHUAC | G7: C.H. HUALLIN | H7: C.H. PURMACANA | I7: C.T. CAÑA BRAVA | K7: C.H. HUASAHUASI I | L7: C.H. HUASAHUASI II | M7: C.H. RUNATULLO II | N7: C.H. RUNATULLO III | O7: C.H. STA CRUZ I y II | P7: C.H. YANAPAMPA | Q7: C.H. CANCHAYLLO | R7: C.H. RUCUY | S7: C.H. RENOVANDES H1 | T7: C.H. POTRERO | U7: C.H. LAS PIZARRAS | AD7: C.H. 8 DE AGOSTO | AE7: C.H. EL CARMEN | AF7: C.H. ANGEL I | AG7: C.H. ANGEL II | AH7: C.H. ANGEL III | AI7: C.H. LA JOYA | AM7: C.H. NUEVAIMPERIAL | AN7: C.H. YARUCAYA | AO7: MCH PATAPO | AR7: C.H. RONCADOR | AU7: C.H. CANA BRAVA | AV7: C.H. CARHUAQUERO4 | BA7: C.H. HER 1 | BE7: C.H. MANTA | BF7: C.T. HUAYCOLORO | BG7: C.T. LA GRINGA V | BH7: CTB CALLAO | BI7: CTB. DONA CATALINA | BK7: C.H. TUPURI | BL7: C.T. OQUENDO | BM7: C.H. CHANCAY | BN7: C.H. POECHOS2 | BP7: C.H. ANASHIRONI | BQ7: MW
B8: 0:30 | C8: 13.5 | D8: 19.1 | E8: 8.1 | F8: 9.8 | G8: 1.4 | I8: 9.5 | K8: 4.7 | M8: 3.1 | N8: 5.2 | O8: 3.4 | P8: 2.4 | Q8: 2 | R8: 15.7 | S8: 19 | T8: 6.2 | U8: 4.5 | V8: 26.2 | W8: 23.3 | X8: 39.1 | Z8: 8.4 | AA8: 26.7 | AB8: 0.1 | AD8: 6.5 | AE8: 2.1 | AF8: 4 | AG8: 4.6 | AH8: 4.6 | AI8: 9.1 | AK8: 7.8 | AL8: 12.8 | AM8: 3.4 | AN8: 18 | AR8: 3.2 | AU8: 5.3 | AV8: 9.9 | BA8: 0.6 | BC8: 9.9 | BD8: 26.4 | BE8: 7.7 | BF8: 4.5 | BG8: 2.6 | BH8: 0.6 | BI8: 2.4 | BK8: 0.3 | BM8: 18.7 | BN8: 10 | BQ8: 426.4
B9: 1:00 | C9: 13 | D9: 19.1 | E9: 7.1 | F9: 11.9 | G9: 1.4 | I9: 8.9 | K9: 4.7 | M9: 3.2 | N9: 4.6 | O9: 3.4 | P9: 2.4 | Q9: 2.1 | R9: 15.3 | S9: 19 | T9: 6.4 | U9: 4.5 | V9: 24.3 | W9: 14.6 | X9: 44.8 | Z9: 9.5 | AA9: 26.2 | AB9: 0.1 | AD9: 6.5 | AE9: 2.1 | AF9: 4 | AG9: 4.6 | AH9: 4.6 | AI9: 9.1 | AK9: 8.5 | AL9: 13.1 | AM9: 3.4 | AN9: 18 | AR9: 3.2 | AW9: 0.4 | AY9: 1.6 | BA9: 0.6 | BC9: 11.6 | BD9: 33.8 | BE9: 7.6 | BF9: 4.5 | BG9: 2.6 | BH9: 1.1 | BI9: 2.4 | BK9: 0.3 | BM9: 18.6 | BN9: 10 | BQ9: 418.7
B10: 1:30 | C10: 13.5 | D10: 19.1 | E10: 8.5 | F10: 11.9 | G10: 1.4 | I10: 9.4 | K10: 4.7 | M10: 3 | N10: 4.3 | O10: 3.4 | P10: 2.4 | Q10: 2.1 | R10: 15.3 | S10: 19.2 | T10: 6.6 | U10: 4.5 | V10: 25.7 | W10: 11.6 | X10: 39.7 | Z10: 11.3 | AA10: 26.2 | AB10: 0.7 | AC10: 0.2 | AD10: 6.3 | AE10: 2.1 | AF10: 4 | AG10: 4.6 | AH10: 4.6 | AI10: 9.1 | AK10: 8.7 | AL10: 14 | AM10: 3.4 | AN10: 18 | AR10: 3.1 | AW10: 8.5 | AY10: 17.5 | BA10: 0.6 | BC10: 11.4 | BD10: 37.3 | BE10: 7.6 | BF10: 4.5 | BG10: 2.6 | BH10: 1.2 | BI10: 2.4 | BK10: 0.3 | BM10: 18.6 | BN10: 10 | BQ10: 445.1
B11: 2:00 | C11: 14 | D11: 18.9 | E11: 8.6 | F11: 11.7 | G11: 1.3 | I11: 9.6 | K11: 4.7 | M11: 3 | N11: 4.4 | O11: 3.4 | P11: 2.4 | Q11: 2.1 | R11: 15.2 | S11: 19.2 | T11: 6.6 | U11: 7.5 | V11: 26.8 | W11: 12.9 | X11: 45.8 | Z11: 9 | AA11: 22.8 | AB11: 1.2 | AC11: 0.5 | AD11: 6.2 | AE11: 2.1 | AF11: 3.8 | AG11: 4.2 | AH11: 4.2 | AI11: 9.1 | AK11: 9.8 | AL11: 13.5 | AM11: 3.4 | AN11: 18 | AR11: 2.8 | AW11: 13.8 | AY11: 16.8 | BA11: 0.6 | BC11: 9.8 | BD11: 28.4 | BE11: 7.7 | BF11: 4.5 | BG11: 2.6 | BH11: 1.2 | BI11: 2.4 | BK11: 0.3 | BM11: 18.4 | BN11: 10 | BQ11: 445.2
B12: 2:30 | C12: 13.3 | D12: 19.1 | E12: 7.1 | F12: 11.8 | G12: 1.3 | I12: 9.6 | K12: 4.7 | M12: 3.1 | N12: 4.4 | O12: 3.4 | P12: 1.8 | Q12: 2 | R12: 15.4 | S12: 19.2 | T12: 6.8 | U12: 7.5 | V12: 21.1 | W12: 10 | X12: 41.9 | Z12: 10.1 | AA12: 23.2 | AB12: 1.3 | AD12: 6.2 | AE12: 2.1 | AF12: 3.8 | AG12: 4.2 | AH12: 4.2 | AI12: 9.1 | AK12: 8.1 | AL12: 11.4 | AM12: 3.4 | AN12: 18 | AR12: 2.7 | AW12: 5 | AY12: 10.3 | BA12: 0.6 | BC12: 8.9 | BD12: 25.6 | BE12: 7.8 | BF12: 4.5 | BG12: 2.6 | BH12: 1.2 | BI12: 2.4 | BK12: 0.3 | BM12: 18.5 | BN12: 9.9 | BQ12: 408.9
B13: 3:00 | C13: 13.1 | D13: 19.1 | E13: 8.1 | F13: 12 | G13: 1.3 | I13: 9.5 | K13: 4.7 | M13: 3.2 | N13: 4.5 | O13: 3.4 | P13: 1.8 | Q13: 2 | R13: 16.3 | S13: 19.3 | T13: 6.8 | U13: 7.5 | V13: 18.5 | W13: 7 | X13: 35 | Z13: 16.2 | AA13: 30.7 | AB13: 2.3 | AC13: 1 | AD13: 6.2 | AE13: 2.1 | AF13: 3.8 | AG13: 4.2 | AH13: 4.2 | AI13: 9.1 | AK13: 9.8 | AL13: 14.1 | AM13: 3.4 | AN13: 18 | AR13: 2.9 | AW13: 1.8 | AY13: 4.8 | BA13: 0.6 | BC13: 9.9 | BD13: 23.7 | BE13: 7.7 | BF13: 4.5 | BG13: 2.6 | BH13: 1.2 | BI13: 2.4 | BK13: 0.3 | BM13: 18.9 | BN13: 10 | BQ13: 409.5
B14: 3:30 | C14: 13.3 | D14: 19.1 | E14: 8.6 | F14: 12 | G14: 1.3 | I14: 9.4 | K14: 4.7 | M14: 3.3 | N14: 4.6 | O14: 3.5 | P14: 1.8 | Q14: 2 | R14: 15.7 | S14: 19.3 | T14: 7 | U14: 7.5 | V14: 22.9 | W14: 7.3 | X14: 35.1 | Z14: 18.9 | AA14: 40 | AB14: 2.1 | AC14: 0.9 | AD14: 6.2 | AE14: 2.1 | AF14: 3.8 | AG14: 4.2 | AH14: 4.2 | AI14: 9.2 | AK14: 10.3 | AL14: 13.7 | AM14: 3.4 | AN14: 18 | AR14: 3 | AW14: 3.4 | AY14: 6.6 | BA14: 0.6 | BC14: 10 | BD14: 19.5 | BE14: 7.7 | BF14: 4.5 | BG14: 2.6 | BH14: 1.2 | BI14: 2.4 | BK14: 0.3 | BM14: 18.6 | BN14: 10 | BQ14: 425.8
B15: 4:00 | C15: 14.6 | D15: 19.1 | E15: 9 | F15: 11.9 | G15: 1.3 | I15: 9.4 | K15: 4.7 | M15: 3.1 | N15: 4 | O15: 3.5 | P15: 1.8 | Q15: 2 | R15: 15.5 | S15: 19.3 | T15: 7 | U15: 4.5 | V15: 19.9 | W15: 9.7 | X15: 29.6 | Z15: 22.6 | AA15: 44.3 | AB15: 2 | AC15: 0.2 | AD15: 6.2 | AE15: 2.1 | AF15: 3.8 | AG15: 4.2 | AH15: 4.2 | AI15: 9.2 | AK15: 10.8 | AL15: 14.3 | AM15: 3.4 | AN15: 18 | AR15: 2.9 | AW15: 6.5 | AY15: 13.3 | BA15: 0.6 | BC15: 6.6 | BD15: 18.4 | BE15: 7.7 | BF15: 4.5 | BG15: 2.6 | BH15: 1.2 | BI15: 2.4 | BK15: 0.3 | BM15: 18.6 | BN15: 10 | BQ15: 430.8
B16: 4:30 | C16: 14.8 | D16: 19.1 | E16: 8.3 | F16: 11.9 | G16: 1.2 | I16: 9.4 | K16: 4.8 | M16: 3.2 | N16: 4.3 | O16: 3.5 | P16: 2.4 | Q16: 1.9 | R16: 15.7 | S16: 19.4 | T16: 7.2 | U16: 4.5 | V16: 15 | W16: 6.3 | X16: 30.3 | Z16: 25.9 | AA16: 44.4 | AB16: 4.6 | AC16: 1.9 | AD16: 6.2 | AE16: 2.1 | AF16: 3.8 | AG16: 4.2 | AH16: 4.2 | AI16: 9.2 | AK16: 11.1 | AL16: 14.4 | AM16: 3.4 | AN16: 18 | AR16: 2.9 | AW16: 23.9 | AY16: 30.6 | BA16: 0.6 | BC16: 7.1 | BD16: 22.4 | BE16: 7.7 | BF16: 4.2 | BG16: 2.3 | BH16: 1.2 | BI16: 2 | BK16: 0.3 | BM16: 18.7 | BN16: 10 | BQ16: 470.5
B17: 5:00 | C17: 14.8 | D17: 19.1 | E17: 7.3 | F17: 11.9 | G17: 1.2 | I17: 9.4 | K17: 5 | M17: 3.3 | N17: 4.5 | O17: 3.5 | P17: 2.4 | Q17: 1.9 | R17: 15.6 | S17: 19.6 | T17: 7.4 | U17: 4.5 | V17: 13.1 | W17: 3.4 | X17: 33.8 | Z17: 21.1 | AA17: 44 | AB17: 1.7 | AC17: 0.9 | AD17: 6.2 | AE17: 2.1 | AF17: 3.8 | AG17: 4.2 | AH17: 4.2 | AI17: 9 | AK17: 11 | AL17: 15.6 | AM17: 3.4 | AN17: 18 | AR17: 2.8 | AW17: 26.5 | AY17: 39 | BA17: 0.6 | BC17: 9.7 | BD17: 23.7 | BE17: 7.7 | BF17: 3.9 | BG17: 2.2 | BH17: 1.2 | BI17: 2 | BK17: 0.3 | BM17: 18.7 | BN17: 10 | BQ17: 475.2
B18: 5:30 | C18: 14.6 | D18: 19.1 | E18: 8.7 | F18: 11.9 | G18: 1.2 | I18: 9.4 | K18: 5.2 | M18: 3.2 | N18: 4.4 | O18: 3.5 | P18: 2.4 | Q18: 1.9 | R18: 15.6 | S18: 19.1 | T18: 7.6 | U18: 4.5 | V18: 15.2 | W18: 2.2 | X18: 34.9 | Z18: 14.7 | AA18: 35.8 | AB18: 0.5 | AD18: 6.2 | AE18: 2.1 | AF18: 4 | AG18: 4.2 | AH18: 4.2 | AI18: 9 | AK18: 10.6 | AL18: 14 | AM18: 3.4 | AN18: 18 | AR18: 2.8 | AW18: 20 | AY18: 26.3 | BA18: 0.6 | BC18: 9.5 | BD18: 25.6 | BE18: 7.7 | BF18: 4.5 | BG18: 2.7 | BH18: 1.2 | BI18: 2 | BK18: 0.3 | BM18: 18.7 | BN18: 10 | BQ18: 443.2
B19: 6:00 | C19: 14.5 | D19: 19.1 | E19: 8.8 | F19: 11.9 | G19: 1.3 | I19: 9.3 | K19: 5.4 | M19: 3.1 | N19: 4 | O19: 3.5 | P19: 2.3 | Q19: 1.9 | R19: 15.6 | S19: 18.9 | T19: 7.7 | U19: 4.5 | V19: 12.1 | W19: 3.3 | X19: 41.1 | Z19: 11.3 | AA19: 28.7 | AC19: 0.1 | AD19: 6.2 | AE19: 2.1 | AF19: 4 | AG19: 4.4 | AH19: 4.2 | AI19: 9 | AK19: 12.5 | AL19: 17.2 | AM19: 3.4 | AN19: 18.1 | AR19: 2.8 | AT19: 0.1 | AW19: 6.5 | AY19: 10.2 | BA19: 0.6 | BC19: 8.8 | BD19: 21.6 | BE19: 7.9 | BF19: 4.5 | BG19: 2.6 | BH19: 1.2 | BI19: 2.4 | BK19: 0.3 | BM19: 18.7 | BN19: 10 | BQ19: 407.7
B20: 6:30 | C20: 14.6 | D20: 19.1 | E20: 8.8 | F20: 11.9 | G20: 1.2 | I20: 9.4 | K20: 5.6 | M20: 3.4 | N20: 4.1 | O20: 3.1 | P20: 2.4 | Q20: 1.8 | R20: 15.7 | S20: 19.2 | T20: 7.7 | U20: 4.5 | V20: 10.4 | W20: 3.9 | X20: 44.8 | Y20: 0.2 | Z20: 12.9 | AA20: 34.4 | AB20: 0.8 | AC20: 0.9 | AD20: 6.2 | AE20: 2.1 | AF20: 4.2 | AG20: 4.4 | AH20: 4.4 | AI20: 9 | AK20: 11.7 | AL20: 16.3 | AM20: 3.3 | AN20: 18 | AP20: 4.1 | AR20: 2.8 | AT20: 2.6 | AV20: 10 | AW20: 0.3 | AX20: 2.1 | AY20: 2.2 | AZ20: 1.8 | BA20: 0.6 | BB20: 2.7 | BC20: 10 | BD20: 16.9 | BE20: 7.9 | BF20: 3 | BG20: 2.6 | BH20: 1.2 | BI20: 2.4 | BK20: 0.3 | BM20: 18.7 | BN20: 10 | BO20: 0.1 | BQ20: 422.7
B21: 7:00 | C21: 14.5 | D21: 19.1 | E21: 8.4 | F21: 11.9 | G21: 1.2 | I21: 10.2 | K21: 5.6 | M21: 3.7 | N21: 4.4 | O21: 2.6 | P21: 2.4 | Q21: 1.8 | R21: 15.6 | S21: 19.2 | T21: 7.7 | U21: 4.5 | V21: 7.8 | W21: 5.9 | X21: 43.1 | Y21: 4 | Z21: 13.1 | AA21: 52.2 | AB21: 0.7 | AC21: 0.4 | AD21: 6.2 | AE21: 2.1 | AF21: 4.2 | AG21: 4.6 | AH21: 4.4 | AI21: 9 | AJ21: 15.6 | AK21: 9.5 | AL21: 14.4 | AM21: 3.3 | AN21: 18 | AP21: 56.4 | AR21: 2.3 | AS21: 1.5 | AT21: 8.9 | AV21: 9.9 | AX21: 33.2 | AZ21: 27 | BA21: 0.6 | BB21: 9.1 | BC21: 5.5 | BD21: 11.9 | BE21: 7.9 | BF21: 3 | BG21: 2.6 | BH21: 1.2 | BI21: 2.4 | BJ21: 1.8 | BK21: 0.3 | BM21: 18.7 | BN21: 10 | BO21: 0.8 | BQ21: 566.3
B22: 7:30 | C22: 14.4 | D22: 19.1 | E22: 8.6 | F22: 11.9 | G22: 1.2 | I22: 10.1 | K22: 5.6 | M22: 3.4 | N22: 3.9 | O22: 2.9 | P22: 2.4 | Q22: 1.9 | R22: 15.6 | S22: 18.7 | T22: 8.1 | U22: 4.5 | V22: 5.3 | W22: 7.7 | X22: 47.6 | Y22: 16.3 | Z22: 15.6 | AA22: 46.7 | AB22: 0.1 | AD22: 6.2 | AE22: 2.1 | AF22: 4.2 | AG22: 4.6 | AH22: 4.4 | AI22: 8.8 | AJ22: 38.8 | AK22: 12.8 | AL22: 15.9 | AM22: 3.2 | AN22: 18 | AP22: 135 | AR22: 2.3 | AS22: 3.8 | AT22: 12.6 | AU22: 2.8 | AV22: 9.9 | AX22: 73.6 | AZ22: 62.9 | BA22: 0.6 | BB22: 15 | BC22: 6 | BD22: 15 | BE22: 7.9 | BF22: 3 | BG22: 2.6 | BH22: 1.2 | BI22: 2.4 | BJ22: 4.2 | BK22: 0.3 | BM22: 18.7 | BN22: 10 | BO22: 2.1 | BQ22: 782.5
B23: 8:00 | C23: 14.4 | D23: 19.1 | E23: 9.2 | F23: 11.9 | G23: 1.2 | I23: 10.6 | J23: 0.1 | K23: 5.6 | M23: 3.7 | N23: 4.5 | O23: 3 | P23: 2.3 | Q23: 2.1 | R23: 15.5 | S23: 19.1 | T23: 8.2 | U23: 4.5 | V23: 3.1 | W23: 10.5 | X23: 50.3 | Y23: 25.1 | Z23: 20.6 | AA23: 46.2 | AB23: 2 | AC23: 0.8 | AD23: 6.2 | AE23: 2.1 | AF23: 4.2 | AG23: 4.8 | AH23: 4.4 | AI23: 8.9 | AJ23: 59.4 | AK23: 12.1 | AL23: 15.5 | AM23: 3.2 | AN23: 18 | AP23: 20.1 | AQ23: 0.1 | AR23: 2.7 | AS23: 6.1 | AT23: 13.1 | AU23: 2.5 | AV23: 9.9 | AX23: 116.9 | AZ23: 84.9 | BA23: 0.6 | BB23: 15.8 | BC23: 10.2 | BD23: 23.5 | BE23: 7.9 | BF23: 3 | BG23: 2.6 | BH23: 1.2 | BI23: 2.4 | BJ23: 6.5 | BK23: 0.3 | BM23: 18.5 | BN23: 10 | BO23: 4.2 | BQ23: 795.4
B24: 8:30 | C24: 14.5 | D24: 19 | E24: 7.4 | F24: 11.9 | G24: 1.2 | I24: 10.1 | J24: 0.6 | K24: 5.6 | M24: 3.6 | N24: 4.3 | O24: 3.1 | P24: 1.9 | Q24: 2.1 | R24: 15.7 | S24: 18.9 | T24: 8.2 | U24: 4.5 | V24: 2.5 | W24: 12.3 | X24: 56.7 | Y24: 30.2 | Z24: 25.2 | AA24: 47.4 | AB24: 1.3 | AC24: 1.8 | AD24: 6.2 | AE24: 2.1 | AF24: 4.2 | AG24: 4.8 | AH24: 4.3 | AI24: 8.9 | AJ24: 63.4 | AK24: 13 | AL24: 17.1 | AM24: 3.2 | AN24: 18 | AQ24: 0.1 | AR24: 2.8 | AS24: 8.3 | AT24: 13.2 | AU24: 2.6 | AV24: 9.9 | AX24: 118.5 | AZ24: 86.3 | BA24: 0.6 | BB24: 15.9 | BC24: 12.7 | BD24: 30.8 | BE24: 7.9 | BF24: 3 | BG24: 2.6 | BH24: 1.2 | BI24: 2.4 | BJ24: 8.8 | BK24: 0.3 | BM24: 18.7 | BN24: 10 | BO24: 11.8 | BQ24: 823.6
B25: 9:00 | C25: 14.5 | D25: 19 | E25: 7.6 | F25: 12 | G25: 1.2 | I25: 10.3 | J25: 0.7 | K25: 5.6 | M25: 3.8 | N25: 4.5 | O25: 3.1 | P25: 2.4 | Q25: 2.1 | R25: 15.7 | S25: 19.1 | T25: 8.2 | U25: 4.5 | V25: 2.8 | W25: 14.2 | X25: 71.3 | Y25: 30.4 | Z25: 38.4 | AA25: 55 | AB25: 5.3 | AC25: 3.5 | AD25: 6.2 | AE25: 2.1 | AF25: 4.2 | AG25: 4.8 | AH25: 3 | AI25: 9.2 | AJ25: 64.9 | AK25: 13.4 | AL25: 15.2 | AM25: 3.2 | AN25: 18 | AQ25: 0.2 | AR25: 3.1 | AS25: 10.7 | AT25: 13.1 | AU25: 2.6 | AV25: 10 | AX25: 125.8 | AZ25: 90.4 | BA25: 0.6 | BB25: 16 | BC25: 11.7 | BD25: 28.8 | BE25: 7.9 | BF25: 3 | BG25: 2.6 | BH25: 1.2 | BI25: 2.4 | BJ25: 10.9 | BK25: 0.3 | BM25: 18.7 | BN25: 10 | BO25: 16.4 | BQ25: 885.8
B26: 9:30 | C26: 14.7 | D26: 18.1 | E26: 7.6 | F26: 12.1 | G26: 1.2 | I26: 11.1 | J26: 0.9 | K26: 5.6 | M26: 3.9 | N26: 4.4 | O26: 3.4 | P26: 2.4 | Q26: 2.1 | R26: 15.6 | S26: 19.1 | T26: 8.2 | U26: 4.5 | V26: 3.5 | W26: 16 | X26: 67.7 | Y26: 30.3 | Z26: 34.3 | AA26: 37.5 | AB26: 5.9 | AC26: 4.1 | AD26: 6.2 | AE26: 2.1 | AF26: 4 | AG26: 4.8 | AH26: 3 | AI26: 9.1 | AJ26: 66 | AK26: 15.1 | AL26: 16.1 | AM26: 3.2 | AN26: 18 | AQ26: 0.3 | AR26: 3 | AS26: 12.6 | AT26: 13.1 | AU26: 2.6 | AV26: 9.9 | AX26: 122.9 | AZ26: 89.3 | BA26: 0.6 | BB26: 15.8 | BC26: 12.5 | BD26: 25.2 | BE26: 7.9 | BF26: 3 | BG26: 2.6 | BH26: 1.1 | BI26: 2.4 | BJ26: 12.6 | BK26: 0.3 | BM26: 18.7 | BN26: 10 | BO26: 16.5 | BQ26: 864.7
B27: 10:00 | C27: 14.5 | D27: 14.5 | E27: 8.3 | F27: 11.9 | G27: 1.2 | I27: 11.6 | J27: 1 | K27: 5.6 | M27: 3.9 | N27: 4.9 | O27: 3.4 | P27: 2.4 | Q27: 2.1 | R27: 15.7 | S27: 19.1 | T27: 8.2 | U27: 4.5 | V27: 4.5 | W27: 13.9 | X27: 69.1 | Y27: 25.3 | Z27: 42.1 | AA27: 52.9 | AB27: 7 | AC27: 4 | AD27: 6 | AE27: 2.1 | AF27: 4 | AG27: 4.8 | AH27: 3 | AI27: 8.9 | AJ27: 65.9 | AK27: 15.1 | AL27: 16 | AM27: 3.1 | AN27: 18 | AQ27: 0.3 | AR27: 2.5 | AS27: 14 | AT27: 12.9 | AU27: 2.6 | AV27: 10 | AX27: 121 | AZ27: 88.4 | BA27: 0.6 | BB27: 15.6 | BC27: 16.3 | BD27: 38.4 | BE27: 7.9 | BF27: 3 | BG27: 2.6 | BH27: 0.7 | BI27: 2.4 | BJ27: 14 | BK27: 0.3 | BM27: 18.7 | BN27: 10 | BO27: 16.3 | BQ27: 897
B28: 10:30 | C28: 14.5 | D28: 16.3 | E28: 9 | F28: 12.1 | G28: 1.2 | I28: 11.8 | J28: 1.1 | K28: 5.5 | M28: 3.7 | N28: 4.7 | O28: 3.4 | P28: 2.4 | Q28: 2.1 | R28: 15.7 | S28: 18.9 | T28: 8.2 | U28: 4.5 | V28: 3.6 | W28: 11.7 | X28: 71.2 | Y28: 27 | Z28: 56 | AA28: 58.5 | AB28: 9.2 | AC28: 5.7 | AD28: 6 | AE28: 2.1 | AF28: 3.9 | AG28: 4.8 | AH28: 4.8 | AI28: 8.9 | AJ28: 66 | AK28: 13.5 | AL28: 16.1 | AM28: 3.1 | AN28: 18 | AQ28: 0.3 | AR28: 2.3 | AS28: 15 | AT28: 13.1 | AU28: 2.6 | AV28: 9.9 | AW28: 1.5 | AX28: 120 | AZ28: 88.3 | BA28: 0.6 | BB28: 16 | BC28: 12 | BD28: 29.8 | BE28: 7.9 | BF28: 3 | BG28: 2.6 | BH28: 0.7 | BI28: 2.4 | BJ28: 15.1 | BK28: 0.3 | BM28: 18.7 | BN28: 10 | BO28: 16.4 | BQ28: 913.7
B29: 11:00 | C29: 14.7 | D29: 18.7 | E29: 7.1 | F29: 12 | G29: 1.2 | I29: 11.7 | J29: 1.1 | K29: 5.2 | M29: 3.7 | N29: 5.7 | O29: 3.4 | P29: 2.4 | Q29: 2.1 | R29: 15.7 | S29: 18.9 | T29: 8.2 | U29: 4.5 | V29: 3.4 | W29: 16.7 | X29: 71.7 | Y29: 29.3 | Z29: 72.1 | AA29: 72.9 | AB29: 11.6 | AC29: 9.4 | AD29: 1.3 | AE29: 0.5 | AF29: 3.9 | AG29: 4.8 | AH29: 4.8 | AI29: 8.9 | AJ29: 65.7 | AK29: 14.3 | AL29: 14.6 | AM29: 3.1 | AN29: 18 | AQ29: 0.4 | AR29: 2.6 | AS29: 15.8 | AT29: 13.2 | AU29: 5.3 | AV29: 9.9 | AW29: 13.3 | AX29: 118.6 | AY29: 1.6 | AZ29: 88.7 | BA29: 0.6 | BB29: 16.1 | BC29: 12 | BD29: 38 | BE29: 8 | BF29: 3 | BG29: 2.6 | BH29: 0.7 | BI29: 2.4 | BJ29: 16.1 | BK29: 0.3 | BM29: 18.7 | BN29: 10.1 | BO29: 16.4 | BQ29: 977.7
B30: 11:30 | C30: 14.6 | D30: 19 | E30: 7.1 | F30: 12 | G30: 1.2 | I30: 11 | J30: 1.2 | K30: 4.8 | M30: 3.9 | N30: 5.8 | O30: 3.5 | P30: 2.4 | Q30: 2.1 | R30: 15.7 | S30: 19 | T30: 8.5 | U30: 4.5 | V30: 4.9 | W30: 22.6 | X30: 90.6 | Y30: 29.5 | Z30: 67.1 | AA30: 81.5 | AB30: 10.6 | AC30: 6.4 | AD30: 0.2 | AF30: 3.9 | AG30: 4.6 | AH30: 4.6 | AI30: 9.1 | AJ30: 65.5 | AK30: 13.3 | AL30: 15.5 | AM30: 3 | AN30: 18 | AQ30: 0.4 | AR30: 2.6 | AS30: 16.2 | AT30: 13.1 | AU30: 5.4 | AV30: 10 | AW30: 22.8 | AX30: 120.1 | AY30: 5.8 | AZ30: 89.4 | BA30: 0.6 | BB30: 15.9 | BC30: 16.9 | BD30: 50.3 | BE30: 8 | BF30: 3 | BG30: 2.6 | BH30: 0.7 | BI30: 2.4 | BJ30: 16.6 | BK30: 0.3 | BM30: 18.7 | BN30: 10 | BO30: 16.2 | BQ30: 1035.2
B31: 12:00 | C31: 14.5 | D31: 19 | E31: 6.8 | F31: 12 | G31: 1.2 | I31: 10.3 | J31: 1.2 | K31: 4.8 | M31: 3.7 | N31: 5.7 | O31: 3.6 | P31: 2.4 | Q31: 2.1 | R31: 15.6 | S31: 18.9 | T31: 8.6 | U31: 4.5 | V31: 12.2 | W31: 33.4 | X31: 99.8 | Y31: 29.6 | Z31: 78.7 | AA31: 83.9 | AB31: 11.9 | AC31: 6.7 | AD31: 5 | AE31: 0.6 | AF31: 3.9 | AG31: 4.6 | AH31: 4.6 | AI31: 9.4 | AJ31: 65.3 | AK31: 16.5 | AL31: 16.5 | AM31: 3 | AN31: 18 | AQ31: 0.4 | AR31: 2.7 | AS31: 16.7 | AT31: 13.1 | AU31: 5.4 | AV31: 9.9 | AW31: 35.5 | AX31: 120.8 | AY31: 16.2 | AZ31: 89.8 | BA31: 0.6 | BB31: 15.7 | BC31: 22.2 | BD31: 66 | BE31: 7.9 | BF31: 3 | BG31: 2.6 | BH31: 0.7 | BI31: 2.4 | BJ31: 16.9 | BK31: 0.3 | BM31: 18.7 | BN31: 10 | BO31: 16.1 | BQ31: 1132.1
B32: 12:30 | C32: 14.2 | D32: 19 | E32: 6.6 | F32: 12 | G32: 1.2 | I32: 9.8 | J32: 1.2 | K32: 4.8 | M32: 3.8 | N32: 5.8 | O32: 3.6 | P32: 2.1 | Q32: 2.1 | R32: 15.5 | S32: 19.1 | T32: 8.6 | U32: 4.5 | V32: 11.4 | W32: 27.2 | X32: 103.7 | Y32: 29.6 | Z32: 76.8 | AA32: 81.6 | AB32: 13.7 | AC32: 8.6 | AD32: 6 | AE32: 2 | AF32: 3.9 | AG32: 4.4 | AH32: 4.3 | AI32: 9.4 | AJ32: 66.3 | AK32: 15.5 | AL32: 16.5 | AM32: 3 | AN32: 18 | AQ32: 0.4 | AR32: 2.1 | AS32: 16.8 | AT32: 13.3 | AU32: 5.4 | AV32: 9.9 | AW32: 43.7 | AX32: 119.5 | AY32: 20 | AZ32: 89 | BA32: 0.6 | BB32: 15.7 | BC32: 22 | BD32: 64.8 | BE32: 7.9 | BF32: 3 | BG32: 2.6 | BH32: 0.9 | BI32: 2.4 | BJ32: 16.8 | BK32: 0.3 | BM32: 18.6 | BN32: 10 | BO32: 16 | BQ32: 1137.5
B33: 13:00 | C33: 14.6 | D33: 19.1 | E33: 6.9 | F33: 12 | G33: 1.2 | I33: 10.6 | J33: 1.2 | K33: 4.8 | M33: 3.7 | N33: 5.7 | O33: 3.5 | P33: 2.4 | Q33: 2.1 | R33: 15.5 | S33: 19 | T33: 8.6 | U33: 4.5 | V33: 14.3 | W33: 39 | X33: 105.2 | Y33: 29.7 | Z33: 73.9 | AA33: 79.8 | AB33: 16.4 | AC33: 9.4 | AD33: 6.2 | AE33: 2.1 | AF33: 3.9 | AG33: 4.4 | AH33: 4.3 | AI33: 9.4 | AJ33: 66.9 | AK33: 16.1 | AL33: 16.2 | AM33: 3 | AN33: 18 | AQ33: 0.4 | AR33: 2 | AS33: 16.4 | AT33: 13.5 | AU33: 5.4 | AV33: 9.9 | AW33: 33 | AX33: 120.2 | AY33: 24.1 | AZ33: 89.2 | BA33: 0.6 | BB33: 16 | BC33: 21.2 | BD33: 63.8 | BE33: 7.8 | BF33: 3 | BG33: 2.6 | BH33: 1.2 | BI33: 2.4 | BJ33: 16.3 | BK33: 0.3 | BM33: 18.7 | BN33: 10 | BO33: 16.1 | BQ33: 1147.7
B34: 13:30 | C34: 14.6 | D34: 19 | E34: 8 | F34: 12.1 | G34: 1.1 | I34: 9.4 | J34: 1.1 | K34: 4.8 | M34: 3.8 | N34: 5.8 | O34: 3.5 | P34: 2.4 | Q34: 2.1 | R34: 15.6 | S34: 19.2 | T34: 8.4 | U34: 4.5 | V34: 15.3 | W34: 40.4 | X34: 102.4 | Y34: 30.2 | Z34: 72.7 | AA34: 82.1 | AB34: 12.2 | AC34: 7 | AD34: 6 | AE34: 2.1 | AF34: 3.9 | AG34: 4.4 | AH34: 4.3 | AI34: 9.2 | AJ34: 67.4 | AK34: 14.8 | AL34: 16.1 | AM34: 3 | AN34: 18 | AQ34: 0.4 | AR34: 2.4 | AS34: 15.7 | AT34: 13.5 | AU34: 5.4 | AV34: 10 | AW34: 34.3 | AX34: 121.9 | AY34: 19.1 | AZ34: 89.5 | BA34: 0.6 | BB34: 16.1 | BC34: 20.9 | BD34: 64.2 | BE34: 7.8 | BF34: 3 | BG34: 2.6 | BH34: 1.2 | BI34: 2.4 | BJ34: 15.6 | BK34: 0.3 | BM34: 18.7 | BN34: 10 | BO34: 16.1 | BQ34: 1138.6
B35: 14:00 | C35: 14.6 | D35: 19 | E35: 8.4 | F35: 12 | G35: 1.2 | I35: 9.3 | J35: 1.1 | K35: 4.7 | M35: 3.8 | N35: 5.8 | O35: 3.5 | P35: 2.4 | Q35: 2.1 | R35: 15.6 | S35: 19.1 | T35: 8.2 | U35: 4.5 | V35: 13.7 | W35: 44.6 | X35: 101.7 | Y35: 30.7 | Z35: 72.2 | AA35: 80.3 | AB35: 13.1 | AC35: 8.5 | AD35: 5.9 | AE35: 2.1 | AF35: 4 | AG35: 4.4 | AH35: 4.3 | AI35: 9.1 | AJ35: 67.5 | AK35: 15.8 | AL35: 17.8 | AM35: 3 | AN35: 18 | AQ35: 0.3 | AR35: 2.4 | AS35: 14.5 | AT35: 13.4 | AU35: 5.4 | AV35: 9.9 | AW35: 43.5 | AX35: 122.8 | AY35: 34.2 | AZ35: 89.8 | BA35: 0.6 | BB35: 16.2 | BC35: 19.7 | BD35: 67.3 | BE35: 7.7 | BF35: 3 | BG35: 2.6 | BH35: 1.9 | BI35: 2.4 | BJ35: 14.6 | BK35: 0.3 | BM35: 18.7 | BN35: 10 | BO35: 16.1 | BQ35: 1169.3
B36: 14:30 | C36: 14.5 | D36: 19 | E36: 8.1 | F36: 12 | G36: 1.2 | I36: 9.3 | J36: 1 | K36: 4.7 | M36: 3.7 | N36: 5.7 | O36: 3.4 | P36: 2.4 | Q36: 2.1 | R36: 15.5 | S36: 19 | T36: 8.2 | U36: 4.5 | V36: 16.1 | W36: 50 | X36: 92.7 | Y36: 30.6 | Z36: 68.2 | AA36: 78.7 | AB36: 11.2 | AC36: 8.1 | AD36: 5.9 | AE36: 2.1 | AF36: 4 | AG36: 4.4 | AH36: 4.4 | AI36: 9 | AJ36: 66.9 | AK36: 14.5 | AL36: 16.6 | AM36: 3.1 | AN36: 18 | AQ36: 0.3 | AR36: 2.4 | AS36: 13.1 | AT36: 13.4 | AU36: 5.4 | AV36: 9.9 | AW36: 51.4 | AX36: 123.6 | AY36: 44.5 | AZ36: 89.5 | BA36: 0.6 | BB36: 16.1 | BC36: 18.8 | BD36: 64.1 | BE36: 7.7 | BF36: 3 | BG36: 2.7 | BH36: 2 | BI36: 2.4 | BJ36: 13.3 | BK36: 0.3 | BM36: 18.7 | BN36: 10 | BO36: 16.1 | BQ36: 1168.1
B37: 15:00 | C37: 14.5 | D37: 18.6 | E37: 7.8 | F37: 8.9 | G37: 1.1 | I37: 9.3 | J37: 0.9 | K37: 4.3 | M37: 3.7 | N37: 5.7 | O37: 3.3 | P37: 2.4 | Q37: 2 | R37: 15.5 | S37: 18.9 | T37: 7.3 | U37: 4.5 | V37: 14.2 | W37: 46.6 | X37: 90.9 | Y37: 30.5 | Z37: 56.3 | AA37: 58.9 | AB37: 9.9 | AC37: 5.4 | AD37: 5.9 | AE37: 2.1 | AF37: 4 | AG37: 4.5 | AH37: 4.4 | AI37: 8.4 | AJ37: 66.2 | AK37: 14.2 | AL37: 15.4 | AM37: 3.1 | AN37: 18 | AQ37: 0.3 | AR37: 2.3 | AS37: 11.4 | AT37: 13.1 | AU37: 3.9 | AV37: 9.9 | AW37: 57.1 | AX37: 122.2 | AY37: 53.5 | AZ37: 88.1 | BA37: 0.6 | BB37: 15.7 | BC37: 17.4 | BD37: 56.7 | BE37: 7.7 | BF37: 3 | BG37: 2.7 | BH37: 1.7 | BI37: 2.4 | BJ37: 11.6 | BK37: 0.3 | BM37: 18.6 | BN37: 10 | BO37: 15.7 | BQ37: 1113.5
B38: 15:30 | C38: 14 | D38: 16.3 | E38: 8.5 | F38: 6.9 | G38: 1.2 | I38: 9.4 | J38: 0.8 | K38: 4 | M38: 3.8 | N38: 5.7 | O38: 3.3 | P38: 2.4 | Q38: 2.1 | R38: 15.5 | S38: 18.8 | T38: 7.3 | U38: 4.5 | V38: 14.5 | W38: 47.6 | X38: 85.2 | Y38: 29.9 | Z38: 62.2 | AA38: 63.5 | AB38: 10.3 | AC38: 7 | AD38: 5.9 | AE38: 2.1 | AF38: 4.1 | AG38: 4.5 | AH38: 4.5 | AI38: 8.3 | AJ38: 63.7 | AK38: 15.2 | AL38: 17.4 | AM38: 3.1 | AN38: 18 | AQ38: 0.3 | AR38: 2.1 | AS38: 9.5 | AT38: 12.6 | AU38: 1.8 | AV38: 9.9 | AW38: 66.7 | AX38: 119.5 | AY38: 58.2 | AZ38: 85.3 | BA38: 0.6 | BB38: 15.1 | BC38: 18.4 | BD38: 57.2 | BE38: 7.6 | BF38: 3 | BG38: 2.7 | BH38: 1.8 | BI38: 2.4 | BJ38: 9.6 | BK38: 0.3 | BM38: 18.6 | BN38: 10 | BO38: 14.8 | BQ38: 1119.5
B39: 16:00 | C39: 14 | D39: 19 | E39: 8.3 | F39: 10.3 | G39: 1.3 | I39: 9.7 | J39: 0.6 | K39: 4 | M39: 3.9 | N39: 5.8 | O39: 3.4 | P39: 2.4 | Q39: 2.1 | R39: 15.4 | S39: 18.6 | T39: 7.3 | U39: 4.5 | V39: 13.6 | W39: 50.9 | X39: 89 | Y39: 23.6 | Z39: 58.9 | AA39: 65.6 | AB39: 10.8 | AC39: 4.9 | AD39: 5.9 | AE39: 2.1 | AF39: 4.1 | AG39: 4.5 | AH39: 4.5 | AI39: 8.3 | AJ39: 53.5 | AK39: 15.4 | AL39: 15.6 | AM39: 3.2 | AN39: 18 | AQ39: 0.2 | AR39: 2.4 | AS39: 7.2 | AT39: 11.3 | AU39: 2 | AV39: 9.9 | AW39: 95.1 | AX39: 96.8 | AY39: 95.3 | AZ39: 79.2 | BA39: 0.6 | BB39: 13.4 | BC39: 16 | BD39: 57.1 | BE39: 7.5 | BF39: 3 | BG39: 2.7 | BH39: 1.9 | BI39: 2.4 | BJ39: 7.4 | BK39: 0.3 | BM39: 18.5 | BN39: 10 | BO39: 12.1 | BQ39: 1135.3
B40: 16:30 | C40: 13.7 | D40: 19 | E40: 8.2 | F40: 12.3 | G40: 1.3 | I40: 9.7 | J40: 0.4 | K40: 4 | M40: 3.8 | N40: 5.8 | O40: 3.3 | P40: 2.4 | Q40: 2.1 | R40: 15.4 | S40: 18.7 | T40: 7.3 | U40: 4.5 | V40: 14.2 | W40: 47.9 | X40: 86.6 | Y40: 13.6 | Z40: 56.8 | AA40: 66.7 | AB40: 9.6 | AC40: 6.5 | AD40: 5.9 | AE40: 2.1 | AF40: 4.1 | AG40: 4.5 | AH40: 4.5 | AI40: 8.6 | AJ40: 29.7 | AK40: 14.6 | AL40: 16.3 | AM40: 3.2 | AN40: 18 | AQ40: 0.2 | AR40: 2.2 | AS40: 4.6 | AT40: 6.1 | AU40: 2 | AV40: 10 | AW40: 104.9 | AX40: 55.9 | AY40: 103.4 | AZ40: 50.8 | BA40: 0.6 | BB40: 7.1 | BC40: 19.1 | BD40: 64.6 | BE40: 7.5 | BF40: 3 | BG40: 2.7 | BH40: 1.9 | BI40: 2.4 | BJ40: 4.9 | BK40: 0.3 | BM40: 18.6 | BN40: 10 | BO40: 5.1 | BQ40: 1033.2
B41: 17:00 | C41: 14.2 | D41: 18.2 | E41: 8.5 | F41: 12.4 | G41: 1.4 | I41: 9.7 | K41: 4 | M41: 3.8 | N41: 5.8 | O41: 3.3 | P41: 2 | Q41: 2 | R41: 15.3 | S41: 18.8 | T41: 7.3 | U41: 4.5 | V41: 15.3 | W41: 38.4 | X41: 93.6 | Y41: 3.9 | Z41: 49.9 | AA41: 61.2 | AB41: 7.9 | AC41: 5.5 | AD41: 5.9 | AE41: 2.1 | AF41: 4.1 | AG41: 4.5 | AH41: 4.5 | AI41: 8.9 | AJ41: 9.3 | AK41: 14.8 | AL41: 15.7 | AM41: 3.2 | AN41: 18 | AQ41: 0.1 | AR41: 2.3 | AS41: 2.2 | AT41: 0.9 | AU41: 2 | AV41: 10 | AW41: 130 | AX41: 15.2 | AY41: 115.5 | AZ41: 16.2 | BA41: 0.6 | BB41: 0.9 | BC41: 18.9 | BD41: 62.9 | BE41: 7.5 | BF41: 3 | BG41: 2.7 | BH41: 1.9 | BI41: 2.4 | BJ41: 2.3 | BK41: 0.3 | BM41: 18.6 | BN41: 9.9 | BO41: 0.3 | BQ41: 924.5
B42: 17:30 | C42: 14.2 | D42: 18.3 | E42: 8.5 | F42: 12.3 | G42: 1.5 | I42: 9.7 | K42: 4.2 | M42: 3.9 | N42: 5.8 | O42: 3.3 | P42: 2.3 | Q42: 2 | R42: 15.1 | S42: 19 | T42: 7.3 | U42: 4.5 | V42: 15.4 | W42: 32.5 | X42: 89.3 | Z42: 42.9 | AA42: 59.3 | AB42: 7.1 | AC42: 3.8 | AD42: 5.9 | AE42: 2.1 | AF42: 4.1 | AG42: 4.5 | AH42: 4.5 | AI42: 8.9 | AK42: 15.4 | AL42: 16 | AM42: 3.2 | AN42: 18 | AR42: 3.3 | AS42: 0.2 | AU42: 2 | AV42: 10 | AW42: 146.5 | AX42: 0.2 | AY42: 129.2 | AZ42: 0.2 | BA42: 0.6 | BC42: 19.2 | BD42: 63.1 | BE42: 7.4 | BF42: 3 | BG42: 2.7 | BH42: 1.9 | BI42: 2.4 | BJ42: 0.2 | BK42: 0.3 | BM42: 18.5 | BN42: 10.1 | BQ42: 885.8
B43: 18:00 | C43: 14.2 | D43: 19.1 | E43: 8.5 | F43: 12.4 | G43: 1.4 | I43: 9.7 | K43: 4.2 | M43: 3.6 | N43: 5.6 | O43: 3.3 | P43: 2.4 | Q43: 2 | R43: 15.1 | S43: 18.7 | T43: 7.2 | U43: 4.5 | V43: 13.6 | W43: 36.7 | X43: 88 | Z43: 42.1 | AA43: 66.3 | AB43: 5.8 | AC43: 4.4 | AD43: 5.9 | AE43: 2.1 | AF43: 4.1 | AG43: 4.5 | AH43: 4.5 | AI43: 8.9 | AK43: 13.6 | AL43: 16.2 | AM43: 3.3 | AN43: 18 | AR43: 3.3 | AU43: 1.5 | AV43: 9.9 | AW43: 124.7 | AY43: 124.6 | BA43: 0.6 | BC43: 21.8 | BD43: 61.4 | BE43: 7.5 | BF43: 3 | BG43: 2.6 | BH43: 1.9 | BI43: 2.4 | BK43: 0.3 | BM43: 18.5 | BN43: 10 | BQ43: 863.9
B44: 18:30 | C44: 15 | D44: 19.1 | E44: 8.9 | F44: 12.3 | G44: 1.4 | I44: 10.7 | K44: 4.2 | M44: 3.7 | N44: 5.3 | O44: 3.3 | P44: 2.4 | Q44: 2.1 | R44: 15.1 | S44: 18.7 | T44: 7.3 | U44: 4.5 | V44: 9.6 | W44: 43.8 | X44: 87.5 | Z44: 41 | AA44: 61.6 | AB44: 6 | AC44: 4.4 | AD44: 5.9 | AE44: 2.1 | AF44: 4.1 | AG44: 4.5 | AH44: 4.5 | AI44: 8.8 | AK44: 11.3 | AL44: 14.3 | AM44: 3.3 | AN44: 18 | AR44: 3.3 | AU44: 1.4 | AV44: 9.9 | AW44: 110.1 | AY44: 114.1 | BA44: 0.6 | BC44: 19.2 | BD44: 61.2 | BE44: 7.5 | BF44: 3 | BG44: 2.6 | BH44: 1.9 | BI44: 2.4 | BK44: 0.3 | BM44: 18.5 | BN44: 10 | BQ44: 830.7
B45: 19:00 | C45: 14.2 | D45: 19 | E45: 8.5 | F45: 12.3 | G45: 1.5 | I45: 11 | K45: 4.2 | M45: 3.8 | N45: 5.4 | O45: 3.3 | P45: 2.4 | Q45: 2.1 | R45: 15.1 | S45: 19 | T45: 7.2 | U45: 4.5 | V45: 9.4 | W45: 40.8 | X45: 87.2 | Z45: 40.4 | AA45: 62.2 | AB45: 6.5 | AC45: 5.4 | AD45: 5.9 | AE45: 2.1 | AF45: 4.1 | AG45: 4.5 | AH45: 4.5 | AI45: 9.2 | AK45: 10.6 | AL45: 14.9 | AM45: 3.3 | AN45: 18 | AR45: 3.3 | AU45: 1.5 | AV45: 9.9 | AW45: 82.1 | AY45: 92 | BA45: 0.6 | BC45: 19.4 | BD45: 54.7 | BE45: 7.5 | BF45: 3 | BG45: 2.6 | BH45: 1.9 | BI45: 2.4 | BK45: 0.3 | BM45: 18.5 | BN45: 10 | BQ45: 772.2
B46: 19:30 | C46: 15 | D46: 19 | E46: 8.4 | F46: 12.2 | G46: 1.5 | I46: 11.5 | K46: 4.2 | M46: 3.8 | N46: 5.3 | O46: 3.3 | P46: 2.4 | Q46: 2 | R46: 15.2 | S46: 18.8 | T46: 7.1 | U46: 4.5 | V46: 9.4 | W46: 31.1 | X46: 77.2 | Z46: 38.3 | AA46: 59.8 | AB46: 4.1 | AC46: 2.1 | AD46: 5.9 | AE46: 2.1 | AF46: 4.1 | AG46: 4.5 | AH46: 4.5 | AI46: 9.1 | AK46: 12.6 | AL46: 13.9 | AM46: 3.4 | AN46: 18 | AR46: 3.3 | AU46: 2.4 | AV46: 9.9 | AW46: 56.6 | AY46: 61.2 | BA46: 0.6 | BC46: 16.1 | BD46: 48.9 | BE46: 7.3 | BF46: 3 | BG46: 2.6 | BH46: 1.9 | BI46: 2.4 | BK46: 0.3 | BM46: 18.5 | BN46: 10.1 | BQ46: 679.4
B47: 20:00 | C47: 15 | D47: 19.1 | E47: 8.7 | F47: 16.2 | G47: 1.5 | I47: 10.5 | K47: 4.2 | M47: 3.9 | N47: 5.4 | O47: 3.3 | P47: 2.4 | Q47: 2 | R47: 15.1 | S47: 19 | T47: 7.1 | U47: 4.5 | V47: 7.6 | W47: 27.9 | X47: 71.3 | Z47: 35.9 | AA47: 58.4 | AB47: 3.9 | AC47: 2.1 | AD47: 5.8 | AE47: 2.1 | AF47: 4.1 | AG47: 4.5 | AH47: 4.5 | AI47: 9.2 | AK47: 12.6 | AL47: 13.6 | AM47: 3.4 | AN47: 18 | AR47: 3.3 | AU47: 2.1 | AV47: 9.9 | AW47: 28.2 | AY47: 43.4 | BA47: 0.6 | BC47: 14.6 | BD47: 49 | BE47: 7.3 | BF47: 3 | BG47: 2.6 | BH47: 1.9 | BI47: 2.4 | BK47: 0.3 | BM47: 18.5 | BN47: 10 | BQ47: 619.9
B48: 20:30 | C48: 14.7 | D48: 18.4 | E48: 7.1 | F48: 16.8 | G48: 1.5 | I48: 11 | K48: 4.2 | M48: 3.8 | N48: 5.4 | O48: 3.3 | P48: 2.4 | Q48: 2 | R48: 15 | S48: 18.9 | T48: 6.9 | U48: 4.5 | V48: 7.3 | W48: 27.1 | X48: 68.1 | Z48: 31.1 | AA48: 51.5 | AB48: 3.3 | AC48: 1.4 | AD48: 5.7 | AE48: 2.1 | AF48: 4 | AG48: 4.5 | AH48: 4.5 | AI48: 9.1 | AK48: 13.1 | AL48: 15.8 | AM48: 3.4 | AN48: 18 | AR48: 3.3 | AU48: 2.2 | AV48: 9.9 | AW48: 21.1 | AY48: 24.1 | BA48: 0.6 | BC48: 12 | BD48: 42.3 | BE48: 7.3 | BF48: 3 | BG48: 2.6 | BH48: 1.9 | BI48: 2.4 | BK48: 0.3 | BM48: 18.5 | BN48: 10 | BQ48: 567.4
B49: 21:00 | C49: 15 | D49: 19.1 | E49: 8.7 | F49: 16.8 | G49: 1.5 | I49: 10.7 | K49: 4.2 | M49: 3.8 | N49: 5.4 | O49: 3.3 | P49: 2.4 | Q49: 1.9 | R49: 15.2 | S49: 18.8 | T49: 6.8 | U49: 4.5 | V49: 7.8 | W49: 15.5 | X49: 56.3 | Z49: 29.9 | AA49: 54.4 | AB49: 3 | AC49: 2.8 | AD49: 5.7 | AE49: 2.1 | AF49: 4 | AG49: 4.5 | AH49: 4.5 | AI49: 8.9 | AK49: 12.6 | AL49: 14.6 | AM49: 3.4 | AN49: 18 | AR49: 3.1 | AU49: 2.2 | AV49: 9.9 | AW49: 5.4 | AY49: 6.7 | BA49: 0.6 | BC49: 12.1 | BD49: 40 | BE49: 7.4 | BF49: 3 | BG49: 2.6 | BH49: 1.9 | BI49: 2.4 | BK49: 0.3 | BM49: 18.5 | BN49: 10 | BQ49: 512.2
B50: 21:30 | C50: 14.9 | D50: 19.1 | E50: 8.7 | F50: 16.8 | G50: 1.5 | I50: 10.5 | K50: 4.3 | M50: 3.8 | N50: 5.3 | O50: 3.8 | P50: 2.4 | Q50: 1.9 | R50: 15.2 | S50: 18.7 | T50: 6.8 | U50: 4.5 | V50: 9.6 | W50: 15.9 | X50: 56.8 | Z50: 28.7 | AA50: 51.2 | AB50: 2.7 | AC50: 1.8 | AD50: 5.7 | AE50: 2.1 | AF50: 4 | AG50: 4.5 | AH50: 4.5 | AI50: 8.9 | AK50: 7.5 | AL50: 11.4 | AM50: 3.4 | AN50: 18 | AR50: 2.9 | AU50: 2.2 | AV50: 9.9 | AW50: 0.3 | AY50: 3.7 | BA50: 0.6 | BC50: 12.2 | BD50: 31.3 | BE50: 7.4 | BF50: 3 | BG50: 2.6 | BH50: 1.9 | BI50: 2.4 | BK50: 0.3 | BM50: 18.5 | BN50: 10 | BQ50: 484.1
B51: 22:00 | C51: 15 | D51: 19.1 | E51: 8.6 | F51: 16.8 | G51: 1.4 | I51: 10.5 | K51: 4.4 | M51: 3.7 | N51: 4.8 | O51: 3.9 | P51: 2.4 | Q51: 1.9 | R51: 15.2 | S51: 18.8 | T51: 6.8 | U51: 4.5 | V51: 10.1 | W51: 21.5 | X51: 59.6 | Z51: 27.2 | AA51: 56.5 | AB51: 2.7 | AC51: 1.8 | AD51: 5.7 | AE51: 2.1 | AF51: 4 | AG51: 4.5 | AH51: 4.5 | AI51: 9 | AK51: 7.6 | AL51: 11.9 | AM51: 3.4 | AN51: 18 | AR51: 3.2 | AU51: 2.2 | AV51: 9.9 | BA51: 0.6 | BC51: 11.5 | BD51: 30.2 | BE51: 7.5 | BF51: 3 | BG51: 2.6 | BH51: 1.9 | BI51: 2.4 | BK51: 0.3 | BM51: 18.5 | BN51: 10 | BQ51: 491.7
B52: 22:30 | C52: 14.5 | D52: 19 | E52: 7.7 | F52: 16.8 | G52: 1.5 | I52: 10.6 | K52: 4.4 | M52: 3.6 | N52: 4.8 | O52: 4 | P52: 2.4 | Q52: 1.9 | R52: 15.1 | S52: 18.7 | T52: 6.8 | U52: 7.5 | V52: 11.9 | W52: 21.1 | X52: 55.8 | Z52: 41.5 | AA52: 62.6 | AB52: 3.4 | AC52: 2.9 | AD52: 5.7 | AE52: 2.1 | AF52: 4 | AG52: 4.5 | AH52: 4.5 | AI52: 9 | AK52: 5.8 | AL52: 11.7 | AM52: 3.4 | AN52: 18 | AR52: 3.3 | AU52: 2.2 | AV52: 9.9 | BA52: 0.6 | BC52: 12.5 | BD52: 36.1 | BE52: 7.5 | BF52: 3 | BG52: 2.6 | BH52: 1.9 | BI52: 2.4 | BK52: 0.3 | BM52: 18.5 | BN52: 10 | BQ52: 518
B53: 23:00 | C53: 14.4 | D53: 19.1 | E53: 8.4 | F53: 16.9 | G53: 1.5 | I53: 10.5 | K53: 4.4 | M53: 3.6 | N53: 4.7 | O53: 4.2 | P53: 2.1 | Q53: 1.8 | R53: 15 | S53: 18.7 | T53: 6.8 | U53: 7.5 | V53: 13.7 | W53: 18 | X53: 61.4 | Z53: 30.7 | AA53: 59.1 | AB53: 2.8 | AC53: 0.9 | AD53: 5.7 | AE53: 2.1 | AF53: 4 | AG53: 4.5 | AH53: 4.5 | AI53: 9 | AK53: 5.3 | AL53: 9.7 | AM53: 3.4 | AN53: 18 | AR53: 3.3 | AU53: 2.2 | AV53: 9.9 | BA53: 0.6 | BC53: 13.4 | BD53: 33.4 | BE53: 7.5 | BF53: 3 | BG53: 2.6 | BH53: 1.9 | BI53: 2.4 | BK53: 0.3 | BM53: 18.5 | BN53: 10 | BQ53: 501.4
B54: 23:30 | C54: 14.3 | D54: 19.1 | E54: 6.9 | F54: 11.8 | G54: 1.6 | I54: 10.3 | K54: 4.4 | M54: 3.4 | N54: 4.7 | O54: 4.3 | P54: 2.1 | Q54: 1.8 | R54: 15.1 | S54: 18.6 | T54: 6.8 | U54: 7.5 | V54: 12.3 | W54: 20.3 | X54: 61 | Z54: 31.7 | AA54: 47.3 | AB54: 3.4 | AC54: 2.7 | AD54: 5.7 | AE54: 2.1 | AF54: 4 | AG54: 4.5 | AH54: 4.5 | AI54: 9 | AK54: 8.5 | AL54: 11.9 | AM54: 3.4 | AN54: 18 | AR54: 3.3 | AU54: 1.8 | AV54: 9.9 | BA54: 0.6 | BC54: 16.5 | BD54: 38.4 | BE54: 7.5 | BF54: 3 | BG54: 2.6 | BH54: 1.9 | BI54: 2.4 | BK54: 0.3 | BM54: 18.5 | BN54: 10 | BQ54: 499.7
B55: 0:00 | C55: 13.4 | D55: 19.1 | E55: 7.1 | F55: 10.5 | G55: 1.6 | I55: 10.2 | K55: 4.4 | M55: 3.7 | N55: 4.9 | O55: 4.4 | P55: 2.3 | Q55: 1.8 | R55: 15.2 | S55: 19 | T55: 6.8 | U55: 7.5 | V55: 9.6 | W55: 19.4 | X55: 46.9 | Z55: 28.8 | AA55: 51.7 | AB55: 2.1 | AC55: 1.8 | AD55: 5.7 | AE55: 2.1 | AF55: 4 | AG55: 4.5 | AH55: 4.5 | AI55: 9 | AK55: 10.5 | AL55: 15.2 | AM55: 3.4 | AN55: 18 | AR55: 3.2 | BA55: 0.6 | BC55: 15.4 | BD55: 34.8 | BE55: 7.6 | BF55: 3 | BG55: 2.6 | BH55: 1.9 | BI55: 2.4 | BK55: 0.3 | BM55: 18.5 | BN55: 10 | BQ55: 469.4
B56: EJEC MWh | C56: 344.05 | D56: 450.4 | E56: 194.05 | F56: 298 | G56: 31.55 | H56: 0 | I56: 242.3 | J56: 8.1 | K56: 113.55 | L56: 0 | M56: 86.05 | N56: 120.25 | O56: 82.5 | P56: 55.3 | Q56: 48.15 | R56: 370.6 | S56: 455.6 | T56: 178.75 | U56: 120 | V56: 297.35 | W56: 542.3 | X56: 1576.2 | Y56: 264.75 | Z56: 896.6 | AA56: 1291.2 | AB56: 127.45 | AC56: 79.3 | AD56: 138.7 | AE56: 47.75 | AF56: 96.05 | AG56: 107.85 | AH56: 104.15 | AI56: 215.95 | AJ56: 596.95 | AK56: 288.6 | AL56: 356 | AM56: 78.35 | AN56: 432.05 | AO56: 0 | AP56: 107.8 | AQ56: 2.7 | AR56: 67.4 | AS56: 116.15 | AT56: 126.6 | AU56: 52.15 | AV56: 178.6 | AW56: 712.2 | AX56: 1105.65 | AY56: 684.8 | AZ56: 827 | BA56: 14.4 | BB56: 150.95 | BC56: 334.75 | BD56: 964.25 | BE56: 184.2 | BF56: 80.55 | BG56: 62.45 | BH56: 34.25 | BI56: 57 | BJ56: 118.05 | BK56: 7.2 | BL56: 0 | BM56: 446.6 | BN56: 240.05 | BO56: 130.85 | BP56: 0 | BQ56: 17543.35
L70: TERMOELÉCTRICA | M70: 1465.05 | N70: 8.3510276 | O70: #FFA975
L71: SOLAR | M71: 3555.55 | N71: 20.267224 | O71: #FFD272
L72: HIDROELÉCTRICA | M72: 4371.75 | N72: 24.919699 | O72: #98D2FF
L73: EÓLICA | M73: 8151 | N73: 46.46205 | O73: #B9ACFF

Sheet COGENERACIÓN
B3: martes, 22 de Julio del 2025
B5: CENTRALES DE COGENERACIÓN DEL SEIN
B6: HORA | C6: AGRO INDUSTRIAL PARAMONGA S.A. | D6: AGROAURORA S.A.C. | E6: AGROINDUSTRIAS SAN JACINTO S.A.A. | F6: BIOENERGIA DEL CHIRA S.A. | G6: GM OPERACIONES S.A.C. | H6: TOTAL COGENERACION
C7: C.T. PARAMONGA | D7: C.T. MAPLE | E7: C.T SAN JACINTO | F7: C.T. CAÑA BRAVA | G7: C.T. REFINERÍA TALARA | H7: MW
B8: 0:30 | C8: 13.5 | D8: 19.1 | E8: 8.1 | F8: 9.5 | G8: 64.7 | H8: 114.9
B9: 1:00 | C9: 13 | D9: 19.1 | E9: 7.1 | F9: 8.9 | G9: 64.9 | H9: 113
B10: 1:30 | C10: 13.5 | D10: 19.1 | E10: 8.5 | F10: 9.4 | G10: 65 | H10: 115.5
B11: 2:00 | C11: 14 | D11: 18.9 | E11: 8.6 | F11: 9.6 | G11: 65 | H11: 116.1
B12: 2:30 | C12: 13.3 | D12: 19.1 | E12: 7.1 | F12: 9.6 | G12: 65 | H12: 114.1
B13: 3:00 | C13: 13.1 | D13: 19.1 | E13: 8.1 | F13: 9.5 | G13: 65 | H13: 114.8
B14: 3:30 | C14: 13.3 | D14: 19.1 | E14: 8.6 | F14: 9.4 | G14: 64.9 | H14: 115.3
B15: 4:00 | C15: 14.6 | D15: 19.1 | E15: 9 | F15: 9.4 | G15: 65 | H15: 117.1
B16: 4:30 | C16: 14.8 | D16: 19.1 | E16: 8.3 | F16: 9.4 | G16: 65.2 | H16: 116.8
B17: 5:00 | C17: 14.8 | D17: 19.1 | E17: 7.3 | F17: 9.4 | G17: 64.8 | H17: 115.4
B18: 5:30 | C18: 14.6 | D18: 19.1 | E18: 8.7 | F18: 9.4 | G18: 65 | H18: 116.8
B19: 6:00 | C19: 14.5 | D19: 19.1 | E19: 8.8 | F19: 9.3 | G19: 65.3 | H19: 117
... B56: EJEC MWh | C56: 344.05 | D56: 450.4 | E56: 194.05 | F56: 242.3 | G56: 1553.7 | H56: 2784.5

Sheet EVO_PRO_ENE
B3: martes, 1 de Julio del 2025 - martes, 22 de Julio del 2025
B5: EVOLUCIÓN DE LA PRODUCCIÓN DE LA ENERGÍA DIARIA DE LOS INTEGRANTES DEL COES (MWh)
B6: EMPRESA | C6: CENTRAL | D6: UNIDAD | E6: TIPO | F6: Julio
F7: 1 | G7: 2 | H7: 3 | I7: 4 | J7: 5 | K7: 6 | L7: 7 | M7: 8 | N7: 9 | O7: 10 | P7: 11 | Q7: 12 | R7: 13 | S7: 14 | T7: 15 | U7: 16 | V7: 17 | W7: 18 | X7: 19 | Y7: 20 | Z7: 21 | AA7: 22 | AB7: TOTAL
B8: AGRO INDUSTRIAL PARAMONGA S.A. | C8: C.T. PARAMONGA | D8: TV-01 | E8: TERMOELÉCTRICA | H8: 66.2 | I8: 335.95 | J8: 305.4 | K8: 314.4 | L8: 355.2 | M8: 274.05 | N8: 344.35 | O8: 213.4 | P8: 296.3 | Q8: 368.45 | R8: 370 | S8: 378.7 | T8: 368.65 | U8: 337.7 | V8: 346.2 | W8: 355.25 | X8: 348.7 | Y8: 341.8 | Z8: 328.35 | AA8: 344.05 | AB8: 6393.1
B9: AGROAURORA S.A.C. | C9: C.T. MAPLE ETANOL | D9: TV | E9: TERMOELÉCTRICA | S9: 57 | T9: 96.65 | U9: 300.8 | V9: 351.6 | W9: 332.9 | X9: 334.05 | Y9: 423.55 | Z9: 442.55 | AA9: 450.4 | AB9: 2789.5
B10: AGROINDUSTRIAS SAN JACINTO S.A.A. | C10: C.T. SAN JACINTO | D10: CENTRAL | E10: TERMOELÉCTRICA | F10: 181.65 | G10: 167.65 | H10: 167.1 | I10: 171.1 | J10: 183.75 | K10: 190.76 | L10: 182.3 | M10: 189.95 | N10: 191.6 | O10: 187.4 | P10: 195.35 | Q10: 194.5 | R10: 195.2 | S10: 194.3 | T10: 184.06 | U10: 195.5 | V10: 194.785 | W10: 188.55 | X10: 198.8 | Y10: 200.05 | Z10: 189.65 | AA10: 194.05 | AB10: 4138.055
B11: ANDEAN POWER S.A.C. | C11: C.H.CARHUAC | D11: CENTRAL | E11: HIDROELÉCTRICA | F11: 316.65 | G11: 284.2 | H11: 324.2 | I11: 330.65 | J11: 301.1 | K11: 343.65 | L11: 325 | M11: 374.9 | N11: 346.2 | O11: 402.25 | P11: 397.2 | Q11: 390.25 | R11: 370.5 | S11: 318.85 | T11: 327.35 | U11: 313.55 | V11: 308 | W11: 301.95 | X11: 323.4 | Y11: 294.25 | Z11: 294.85 | AA11: 298 | AB11: 7286.95
B12: ASOCIACIÓN SANTA LUCIA DE CHACAS | C12: C.H. HUALLIN | D12: CENTRAL | E12: HIDROELÉCTRICA | F12: 33.25 | G12: 32.748 | H12: 31.4 | I12: 30.55 | J12: 30.1 | K12: 15.55 | L12: 29.7 | M12: 30.5 | N12: 32.5 | O12: 32.8 | P12: 33.9 | Q12: 32.8 | R12: 31.65 | S12: 31.65 | T12: 31.95 | U12: 31.4 | V12: 32.35 | W12: 32.05 | X12: 30.35 | Y12: 30.3 | Z12: 31.1 | AA12: 31.55 | AB12: 680.148
B13: ATRIA ENERGIA S.A.C. | C13: C.H. PURMACANA | D13: CENTRAL | E13: HIDROELÉCTRICA | I13: 4.4 | J13: 7.2 | K13: 7.2 | L13: 3.35 | P13: 4.5 | Q13: 6.85 | R13: 7.2 | S13: 3.8 | W13: 3.8 | X13: 7.5 | Y13: 7.35 | Z13: 3.3 | AB13: 66.45
B14: BIOENERGIA DEL CHIRA S.A. | C14: C.T. CAÑA BRAVA | D14: CENTRAL | E14: TERMOELÉCTRICA | F14: 201.95 | G14: 229.7 | H14: 227.6 | I14: 229.65 | J14: 232.45 | K14: 228.9 | L14: 228.9 | M14: 209.9 | N14: 238.5 | O14: 224 | P14: 220.85 | Q14: 233.0473 | R14: 220.6 | S14: 237 | T14: 225 | U14: 175.8 | V14: 230.45 | W14: 225.95 | X14: 223.25 | Y14: 243.1 | Z14: 233.1 | AA14: 242.3 | AB14: 4961.9973
B15: CELEPSA | C15: C.H. EL PLATANAL | D15: CENTRAL | E15: HIDROELÉCTRICA | F15: 2672.3 | G15: 2594.5 | H15: 2573.75 | I15: 2535.35 | J15: 2588 | K15: 2493.65 | L15: 2389.45 | M15: 2356.6 | N15: 2455.4 | O15: 2344.4 | P15: 2280.95 | Q15: 2421.3185 | R15: 2231.7 | S15: 2315.35 | T15: 2272.5 | U15: 2243.05 | V15: 2212.2 | W15: 2211.55 | X15: 2247.25 | Y15: 2104 | Z15: 2097.7 | AA15: 2074.4 | AB15: 51715.369
B16: CELEPSA RENOVABLES S.R.L. | C16: C.H. MARAÑON | D16: CENTRAL | E16: HIDROELÉCTRICA | F16: 474.4 | G16: 475.2 | H16: 473.9 | I16: 467.5 | J16: 444.55 | K16: 427.65 | L16: 416.95 | M16: 408.25 | N16: 398.55 | O16: 389.1 | P16: 381 | Q16: 369.72195 | R16: 362.8 | S16: 358 | T16: 347.75 | U16: 339.55 | V16: 333.9 | W16: 339.7 | X16: 300.3 | Y16: 351.75 | Z16: 334.05 | AA16: 318.45 | AB16: 8513.022
B17: CENTRALES SANTA ROSA S.A.C. | C17: C.H. SANTA ROSA I | D17: CENTRAL | E17: HIDROELÉCTRICA | AB17: 0
B18: CENTRALES SANTA ROSA S.A.C. | C18: C.H. SANTA ROSA II | D18: CENTRAL | E18: HIDROELÉCTRICA | AB18: 0
B19: CHINANGO S.A.C. | C19: C.H. CHIMAY | D19: CENTRAL | E19: HIDROELÉCTRICA | F19: 1885.7 | G19: 2270.7 | H19: 1903.7 | I19: 1723.05 | J19: 1487.75 | K19: 1501.45 | L19: 1894.35 | M19: 1467.9 | N19: 1384.7 | O19: 1322.2 | P19: 1350.05 | Q19: 1365.5 | R19: 1406.65 | S19: 1320.4 | T19: 1210.55 | U19: 1364.35 | V19: 1129.65 | W19: 1463.25 | X19: 1260.45 | Y19: 1317.9 | Z19: 1202.45 | AA19: 1214.5 | AB19: 32447.2
B20: CHINANGO S.A.C. | C20: C.H. YANANGO | D20: CENTRAL | E20: HIDROELÉCTRICA | F20: 690.8 | G20: 692.3 | H20: 684.2 | I20: 664.4 | J20: 650.95 | K20: 630.75 | L20: 611.4 | M20: 596.1 | N20: 589.3 | O20: 568.65 | P20: 589.55 | Q20: 513.65 | R20: 560.15 | S20: 531.45 | T20: 533.35 | U20: 524.15 | V20: 520.35 | W20: 540.55 | X20: 547.1 | Y20: 546.75 | Z20: 510.4 | AA20: 496.3 | AB20: 12792.6
B21: COLCA SOLAR S.A.C. | C21: C.S. YARUCAYA | D21: CENTRAL | E21: SOLAR | F21: 6.55 | G21: 8.25 | H21: 8.25 | I21: 8.35 | J21: 8.4 | K21: 8.6 | L21: 8.4 | M21: 8.4 | N21: 8.4 | O21: 8.35 | P21: 8.3 | Q21: 8.15 | R21: 8.15 | S21: 8.15 | T21: 8.2 | U21: 8.35 | V21: 8.2 | W21: 8.3 | X21: 7.7 | Y21: 8.2 | Z21: 8.15 | AA21: 8.1 | AB21: 179.9
B22: EGASA | C22: C.H. CHARCANI III | D22: CENTRAL | E22: HIDROELÉCTRICA | F22: 164.65 | G22: 164.15 | H22: 164.45 | I22: 164.15 | J22: 163.65 | K22: 164.905 | L22: 163.85 | M22: 164.25 | N22: 164.45 | O22: 166.95 | P22: 167.95 | Q22: 165.0995 | R22: 168.85 | S22: 164.11 | T22: 158.3 | U22: 150.05 | V22: 148.3835 | W22: 158.05 | X22: 164.55 | Y22: 165.45 | Z22: 164.95 | AA22: 156.85 | AB22: 3578.048
B23: EGASA | C23: C.H. CHARCANI IV | D23: CENTRAL | E23: HIDROELÉCTRICA | F23: 291.2 | G23: 289.3 | H23: 290.9 | I23: 286.25 | J23: 287.25 | K23: 289.015 | L23: 286.85 | M23: 278.45 | N23: 283.4 | O23: 280.75 | P23: 284.4 | Q23: 288.86 | R23: 286.7 | S23: 289.155 | T23: 265.7 | U23: 232.1 | V23: 230.6295 | W23: 267.75 | X23: 312.8 | Y23: 308.85 | Z23: 312.55 | AA23: 316.95 | AB23: 6259.8095
B24: EGASA | C24: C.H. CHARCANI V | D24: CENTRAL | E24: HIDROELÉCTRICA | F24: 1784.8 | G24: 1768.85 | H24: 1801 | I24: 1817.7 | J24: 1760.1 | K24: 1774.745 | L24: 1799 | M24: 1794.75 | N24: 1788.7 | O24: 1773.9 | P24: 1788.55 | Q24: 1803.691 | R24: 1794.4 | S24: 1765.69 | T24: 1668.75 | U24: 1435.9 | V24: 1470.9575 | W24: 1665.35 | X24: 1944.25 | Y24: 1943.15 | Z24: 1936.55 | AA24: 1962.2 | AB24: 39042.984
B25: EGASA | C25: C.H. CHARCANI VI | D25: CENTRAL | E25: HIDROELÉCTRICA | AB25: 0
B26: EGASA | C26: C.T. CHILINA DIESEL | D26: CENTRAL | E26: TERMOELÉCTRICA | AB26: 0
B27: EGASA | C27: C.T. CHILINA DIESEL | D27: TG | E27: TERMOELÉCTRICA | M27: 9.4 | AB27: 9.4
B28: EGASA | C28: C.T. MOLLENDO DIESEL | D28: CENTRAL | E28: TERMOELÉCTRICA | N28: 28.45 | AB28: 28.45
B29: EGEJUNIN | C29: C.H. HUASAHUASI I | D29: CENTRAL | E29: HIDROELÉCTRICA | F29: 228.3 | G29: 223.85 | H29: 209.5 | I29: 197.15 | J29: 186.85 | K29: 77.8 | L29: 166.05 | M29: 163.8 | N29: 150.1 | O29: 146.3 | P29: 145.65 | Q29: 142.95 | R29: 140.1 | S29: 127.8 | T29: 125.8 | U29: 122.8 | V29: 125.55 | W29: 130.45 | X29: 131.25 | Y29: 132.2 | Z29: 123.45 | AA29: 113.55 | AB29: 3311.25
B30: EGEJUNIN | C30: C.H. RUNATULLO II | D30: CENTRAL | E30: HIDROELÉCTRICA | F30: 131.55 | G30: 128.35 | H30: 128.1 | I30: 122.9 | J30: 115.05 | K30: 113.3 | L30: 105.95 | M30: 100.65 | N30: 102.85 | O30: 103.7 | P30: 100.05 | Q30: 98.35 | R30: 94.8 | S30: 94.5 | T30: 92.25 | U30: 91.6 | V30: 88.75 | W30: 104.2 | X30: 97.55 | Y30: 95.15 | Z30: 89.7 | AA30: 86.05 | AB30: 2285.35
B31: EGEJUNIN | C31: C.H. RUNATULLO III | D31: CENTRAL | E31: HIDROELÉCTRICA | F31: 185.4 | G31: 190.6 | H31: 180.2 | I31: 176.25 | J31: 163.8 | K31: 161.6 | L31: 153.25 | M31: 151.8 | N31: 143.6 | O31: 148.2 | P31: 141.3 | Q31: 139.3 | R31: 138.2 | S31: 133.45 | T31: 129.6 | U31: 130.4 | V31: 123.25 | W31: 151.45 | X31: 137.9 | Y31: 135 | Z31: 130.45 | AA31: 120.25 | AB31: 3265.25
B32: EGEJUNIN | C32: C.H. SANTA CRUZ I | D32: CENTRAL | E32: HIDROELÉCTRICA | F32: 94.8 | G32: 96.2 | H32: 89.9 | I32: 79.75 | J32: 73.85 | K32: 65.1 | L32: 72.5 | M32: 75.65 | N32: 73.35 | O32: 75.65 | P32: 74.95 | Q32: 69.15 | R32: 69 | S32: 76.55 | T32: 63.1 | U32: 74.15 | V32: 78.75 | W32: 82.4 | X32: 84.15 | Y32: 80.75 | Z32: 74.75 | AA32: 82.5 | AB32: 1706.95
B33: EGEMSA | C33: C.H. MACHUPICCHU | D33: CENTRAL | E33: HIDROELÉCTRICA | F33: 3354.25 | G33: 3343.75 | H33: 3285.5 | I33: 3300.8 | J33: 3296.3 | K33: 3238.9 | L33: 3171.6 | M33: 3051.65 | N33: 3000.4 | O33: 2939 | P33: 2909.4 | Q33: 2914.85 | R33: 2879.6 | S33: 2876.2 | T33: 2831.2 | U33: 2796.8 | V33: 2788.35 | W33: 2777.75 | X33: 2787.3 | Y33: 2751.3 | Z33: 2740.7 | AA33: 2674.7 | AB33: 65710.3
B34: EGESUR | C34: C.H. ARICOTA I | D34: CENTRAL | E34: HIDROELÉCTRICA | F34: 173.8 | G34: 173.85 | H34: 177.45 | I34: 176.8 | J34: 174.3 | K34: 176.8 | L34: 177 | M34: 178.3 | N34: 178.6 | O34: 175.05 | P34: 171.2 | Q34: 172.7 | R34: 171.85 | S34: 171.2 | T34: 172.15 | U34: 176.7 | V34: 177.55 | W34: 176.6 | X34: 128 | Y34: 178.2 | Z34: 179.3 | AA34: 177.75 | AB34: 3815.15
B35: EGESUR | C35: C.H. ARICOTA II | D35: CENTRAL | E35: HIDROELÉCTRICA | F35: 126 | G35: 124.65 | H35: 127.35 | I35: 126.2 | J35: 119.55 | K35: 131.5 | L35: 131.95 | M35: 136.75 | N35: 136.55 | O35: 136.05 | P35: 135.25 | Q35: 138.8 | R35: 134.95 | S35: 128.35 | T35: 128.2 | U35: 135.65 | V35: 137.05 | W35: 138.15 | X35: 115.9 | Y35: 125.3 | Z35: 123.85 | AA35: 122.4 | AB35: 2860.4
B36: EGESUR | C36: C.T. INDEPENDENCIA | D36: CENTRAL | E36: TERMOELÉCTRICA | G36: 20.35 | J36: 175.85 | V36: 200.8 | W36: 140.35 | AB36: 537.35
B37: ELECTRICA YANAPAMPA SAC | C37: C.H. YANAPAMPA | D37: CENTRAL | E37: HIDROELÉCTRICA | F37: 53.1 | G37: 53.6 | H37: 54.9 | I37: 51.15 | J37: 48.9 | K37: 49.5 | L37: 46.7 | M37: 47.45 | N37: 46.25 | O37: 56.2 | P37: 56.55 | Q37: 57.6 | R37: 57.6 | S37: 57.45 | T37: 57.1 | U37: 56.65 | V37: 55.9 | W37: 56.65 | X37: 57.1 | Y37: 56.45 | Z37: 56.4 | AA37: 55.3 | AB37: 1188.5
B38: ELECTROPERU | C38: C.H. MANTARO | D38: CENTRAL | E38: HIDROELÉCTRICA | F38: 15565.4 | G38: 15560.2 | H38: 15569.3 | I38: 14799.655 | J38: 15557.05 | K38: 15072.3 | L38: 15551.25 | M38: 15569.5 | N38: 15583.025 | O38: 15549.3 | P38: 15536.35 | Q38: 15554.4 | R38: 15121.65 | S38: 15521.96 | T38: 15538.3 | U38: 15526.8 | V38: 15353.05 | W38: 14825.2 | X38: 15493.7 | Y38: 15024.5 | Z38: 15431.15 | AA38: 14879.7 | AB38: 338183.74
B39: ELECTROPERU | C39: C.H. RESTITUCION | D39: CENTRAL | E39: HIDROELÉCTRICA | F39: 5165.4 | G39: 5164.05 | H39: 5166.25 | I39: 4977.64 | J39: 5174.2 | K39: 5037.95 | L39: 5170.3 | M39: 5173.75 | N39: 5178.555 | O39: 5172 | P39: 5174.5 | Q39: 5175.4 | R39: 5079.95 | S39: 5179.57 | T39: 5176.05 | U39: 5177.45 | V39: 5132.45 | W39: 5000.15 | X39: 5184.3 | Y39: 5055.85 | Z39: 5148.3 | AA39: 4190.25 | AB39: 112054.32
B40: ELECTROPERU | C40: C.T. TUMBES | D40: MAK1 | E40: TERMOELÉCTRICA | AB40: 0
B41: ELECTROPERU | C41: C.T. TUMBES | D41: MAK2 | E41: TERMOELÉCTRICA | AB41: 0
B42: EMPRESA DE GENERACION ELECTRICA CANCHAYLLO SAC | C42: C.H. CANCHAYLLO | D42: CENTRAL | E42: HIDROELÉCTRICA | F42: 62.4 | G42: 62.4 | H42: 62.4 | I42: 62.2 | J42: 60.2 | K42: 61.55 | L42: 61.95 | M42: 60 | N42: 58.25 | O42: 58.65 | P42: 57.6 | Q42: 57.45 | R42: 54.1 | S42: 54.95 | T42: 54.4 | U42: 54.4 | V42: 50.7 | W42: 47.25 | X42: 48.25 | Y42: 48.05 | Z42: 47.7 | AA42: 48.15 | AB42: 1233
B43: EMPRESA DE GENERACION ELECTRICA RIO BAÑOS S.A.C. | C43: C.H. RUCUY | D43: CENTRAL | E43: HIDROELÉCTRICA | F43: 346.4 | G43: 343.95 | H43: 330.3 | I43: 325.9 | J43: 323.7 | K43: 282.55 | L43: 240.05 | M43: 240 | N43: 240.1 | O43: 239.8 | P43: 239.7 | Q43: 246.2 | R43: 324.55 | S43: 313.9 | T43: 268.35 | U43: 239.9 | V43: 238.95 | W43: 296.85 | X43: 384.85 | Y43: 382.3 | Z43: 376.1 | AA43: 370.6 | AB43: 6595
B44: EMPRESA DE GENERACION ELECTRICA SANTA ANA S.A.C. | C44: C.H. RENOVANDES H1 | D44: CENTRAL | E44: HIDROELÉCTRICA | F44: 279.35 | G44: 389.65 | H44: 432 | I44: 480.1 | J44: 484.9 | K44: 467.45 | L44: 434.45 | M44: 481.15 | N44: 482.7 | O44: 480.5 | P44: 480.5 | Q44: 484.45 | R44: 483.55 | S44: 484.2 | T44: 484.5 | U44: 483.25 | V44: 479.3 | W44: 480.8 | X44: 483.65 | Y44: 478.95 | Z44: 465.8 | AA44: 455.6 | AB44: 10156.8
B45: EMPRESA DE GENERACION HUALLAGA | C45: C.H. CHAGLLA | D45: CENTRAL | E45: HIDROELÉCTRICA | F45: 5030.8 | G45: 3596 | H45: 4892.05 | I45: 3924.95 | J45: 4277.25 | K45: 1374.25 | L45: 2647.85 | M45: 4842.1 | N45: 1639.75 | O45: 2282.8 | P45: 4071.6 | Q45: 3361.9 | R45: 761.90749 | S45: 3443.2 | T45: 1902.6 | U45: 2606.6351 | V45: 4062.2 | W45: 3839 | X45: 1442.65 | Y45: 585.15 | Z45: 3222.5 | AA45: 3187.25 | AB45: 66994.393
B46: EMPRESA DE GENERACION HUALLAGA | C46: P.C.H. CHAGLLA | D46: CENTRAL | E46: HIDROELÉCTRICA | F46: 156 | G46: 116.8 | H46: 35.75 | I46: 155.45 | J46: 153.75 | K46: 153.8 | L46: 154.3 | M46: 154.15 | N46: 154.1 | O46: 154.5 | P46: 154.85 | Q46: 100.35 | R46: 155.05718 | S46: 156.15 | T46: 156.05 | U46: 155.5038 | V46: 155.95 | W46: 156 | X46: 156 | Y46: 156 | Z46: 156 | AA46: 151.45 | AB46: 3197.961
B47: EMPRESA DE GENERACION HUANZA | C47: C.H. HUANZA | D47: CENTRAL | E47: HIDROELÉCTRICA | F47: 1180 | G47: 1228.7 | H47: 1318.5 | I47: 1274.25 | J47: 1274.7 | K47: 1309.7 | L47: 1358.1 | M47: 1441.2 | N47: 1461.5 | O47: 1553.45 | P47: 1573.25 | Q47: 1530.4 | R47: 1515.7 | S47: 1269.2 | T47: 1231.05 | U47: 1193.85 | V47: 1189.6 | W47: 1128.9 | X47: 1198.9 | Y47: 1145.95 | Z47: 1039.85 | AA47: 1133.25 | AB47: 28550
B48: EMPRESA ELECTRICA AGUA AZUL | C48: C.H. POTRERO | D48: CENTRAL | E48: HIDROELÉCTRICA | F48: 367.35 | G48: 353.2 | H48: 327.85 | I48: 314.5 | J48: 295.6 | K48: 274.55 | L48: 253.95 | M48: 244.65 | N48: 240 | O48: 183.3 | P48: 236.35 | Q48: 229.2 | R48: 226.3 | S48: 221.3 | T48: 216.05 | U48: 182.55 | V48: 189.6 | W48: 186.55 | X48: 192.6 | Y48: 184.85 | Z48: 176.1 | AA48: 178.75 | AB48: 5275.15
B49: EMPRESA ELECTRICA RIO DOBLE | C49: C.H. LAS PIZARRAS | D49: CENTRAL | E49: HIDROELÉCTRICA | F49: 235.35 | G49: 228.5 | H49: 219.35 | I49: 204.8 | J49: 183.05 | K49: 188.05 | L49: 173.55 | M49: 177.8 | N49: 171.5 | O49: 167.75 | P49: 163.5 | Q49: 95.75 | R49: 94.15 | S49: 143.65 | T49: 143.5 | U49: 115.6 | V49: 136 | W49: 129.9 | X49: 129 | Y49: 122.85 | Z49: 116.2 | AA49: 120 | AB49: 3459.8
B50: ENEL GENERACION PIURA S.A. | C50: C.T. MALACAS 1 | D50: TG6 | E50: TERMOELÉCTRICA | F50: 1117.05 | G50: 1045.15 | H50: 1106 | I50: 818.85 | J50: 1114.3 | K50: 1111.85 | L50: 686.05 | M50: 802.6 | N50: 758.9 | O50: 814.3 | P50: 838.45 | Q50: 1131.3 | R50: 1125.6 | S50: 1142.85 | T50: 1135.55 | U50: 824.1 | V50: 1135.15 | W50: 1128.35 | X50: 1135.1 | Y50: 1122.2 | Z50: 1120.4 | AA50: 819.05 | AB50: 22033.15
B51: ENEL GENERACION PIURA S.A. | C51: C.T. MALACAS 2 | D51: TG4 | E51: TERMOELÉCTRICA | M51: 2.95 | N51: 273.7 | O51: 140.9 | P51: 241.75 | AB51: 659.3
B52: ENEL GENERACION PIURA S.A. | C52: C.T. RF DE GENERACION TALARA | D52: TG5 | E52: TERMOELÉCTRICA | AB52: 0
B53: ENERGÍA EÓLICA S.A. | C53: C.E. CUPISNIQUE | D53: CENTRAL | E53: EÓLICA | F53: 622.15 | G53: 405.7 | H53: 167 | I53: 262.7 | J53: 646.05 | K53: 532.75 | L53: 309.25 | M53: 378.85 | N53: 588.95 | O53: 387.3 | P53: 827.5 | Q53: 573.25 | R53: 740.95 | S53: 933.2 | T53: 525.3 | U53: 540.2 | V53: 265.7 | W53: 100.35 | X53: 120.2 | Y53: 684 | Z53: 508.75 | AA53: 542.3 | AB53: 10662.4
B54: ENERGÍA EÓLICA S.A. | C54: C.E. TALARA | D54: CENTRAL | E54: EÓLICA | F54: 352.9 | G54: 178.65 | H54: 64.65 | I54: 132.1 | J54: 272.3 | K54: 429.25 | L54: 390.15 | M54: 572.2 | N54: 686.05 | O54: 348.8 | P54: 356 | Q54: 263.1 | R54: 260.9 | S54: 604.6 | T54: 527.55 | U54: 551.4 | V54: 574.7 | W54: 586.8 | X54: 323.4 | Y54: 391.3 | Z54: 296.85 | AA54: 297.35 | AB54: 8461
B55: ENERGIA RENOVABLE DEL SUR S.A. | C55: C.E. SAN JUAN | D55: CENTRAL | E55: EÓLICA | F55: 1374.1 | G55: 624.4 | H55: 219.55 | I55: 80.45 | J55: 437.75 | K55: 1310.25 | L55: 1611.85 | M55: 1015.6 | N55: 1278.4 | O55: 2049.6 | P55: 1360.9 | Q55: 1677 | R55: 1565.4 | S55: 1522.7 | T55: 2738.55 | U55: 2279.55 | V55: 1279.45 | W55: 1767.9 | X55: 1449.85 | Y55: 1265.7 | Z55: 1419.25 | AA55: 1576.2 | AB55: 29904.4
B56: ENGIE | C56: C.E. PUNTA LOMITAS | D56: PL-BL1 | E56: EÓLICA | F56: 738.25 | G56: 347.05 | H56: 35.15 | I56: 54.8 | J56: 367.15 | K56: 1390.2 | L56: 1461.85 | M56: 526.75 | N56: 1461.8 | O56: 1741.9 | P56: 1127.7 | Q56: 986.85 | R56: 815 | S56: 1588.8 | T56: 1902.85 | U56: 1938.4 | V56: 965.84 | W56: 1150.45 | X56: 1066.2 | Y56: 867.9 | Z56: 871.25 | AA56: 896.6 | AB56: 22302.74
B57: ENGIE | C57: C.E. PUNTA LOMITAS | D57: PL-BL2 | E57: EÓLICA | F57: 942.95 | G57: 588.1 | H57: 91 | I57: 96.2 | J57: 526.25 | K57: 1479.6 | L57: 1529.85 | M57: 669.35 | N57: 1570.75 | O57: 1843.75 | P57: 1274.35 | Q57: 1306.4 | R57: 1104.95 | S57: 1817.1 | T57: 1888.3 | U57: 1914.2 | V57: 1239.1 | W57: 1599.15 | X57: 1455.75 | Y57: 1174.1 | Z57: 1236.35 | AA57: 1291.2 | AB57: 26638.75
B58: ENGIE | C58: C.E. PUNTA LOMITAS_EXP | D58: PUN LOM_EXP-BL1 | E58: EÓLICA | F58: 101.9 | G58: 31.7 | H58: 0.95 | I58: 6.5 | J58: 49.6 | K58: 199.5 | L58: 226.45 | M58: 57.5 | N58: 186.5 | O58: 258.15 | P58: 152.45 | Q58: 147.6 | R58: 112.3 | S58: 247.7 | T58: 323.45 | U58: 277.9 | V58: 128.005 | W58: 153.55 | X58: 152.4 | Y58: 119.65 | Z58: 127.3 | AA58: 127.45 | AB58: 3188.505
B59: ENGIE | C59: C.E. PUNTA LOMITAS_EXP | D59: PUN LOM_EXP-BL2 | E59: EÓLICA | F59: 69.15 | G59: 15.15 | H59: 0.05 | I59: 2.9 | J59: 25.4 | K59: 145.6 | L59: 176.4 | M59: 45 | N59: 156.7 | O59: 210.1 | P59: 108.75 | Q59: 73.05 | R59: 65.15 | S59: 197.05 | T59: 264.65 | U59: 236.8 | V59: 78.42 | W59: 88.8 | X59: 98.5 | Y59: 86.4 | Z59: 79.5 | AA59: 79.3 | AB59: 2302.82
B60: ENGIE | C60: C.H. QUITARACSA | D60: CENTRAL | E60: HIDROELÉCTRICA | F60: 354 | I60: 379.9 | K60: 216.55 | N60: 319.6 | Q60: 299.2 | T60: 309.65 | W60: 161.95 | Z60: 301.15 | AB60: 2342
B61: ENGIE | C61: C.H. YUNCAN | D61: CENTRAL | E61: HIDROELÉCTRICA | F61: 1370.3 | G61: 1583.5 | H61: 1360.3 | I61: 1331.7 | J61: 1307.85 | K61: 1085.85 | L61: 1146.1 | M61: 1245.65 | N61: 1164.9 | O61: 889.05 | P61: 1310.3 | Q61: 1074.8 | R61: 1023.45 | S61: 1055.6 | T61: 1017.35 | U61: 955.7 | V61: 1026.41 | W61: 1011.4 | X61: 1135.85 | Y61: 1202.55 | Z61: 1574.7 | AA61: 1610.3 | AB61: 26483.61
B62: ENGIE | C62: C.S. INTIPAMPA | D62: CENTRAL | E62: SOLAR | F62: 216.9 | G62: 244.45 | H62: 244.5 | I62: 249.9 | J62: 246.9 | K62: 252.75 | L62: 251.8 | M62: 252.55 | N62: 254.1 | O62: 255.65 | P62: 256.45 | Q62: 257.05 | R62: 257.7 | S62: 258.95 | T62: 256.85 | U62: 261.55 | V62: 258.95 | W62: 185.5 | X62: 262.65 | Y62: 263.9 | Z62: 257.95 | AA62: 264.75 | AB62: 5511.75
B63: ENGIE | C63: C.T. CHILCA 1 | D63: TG1 | E63: TERMOELÉCTRICA | F63: 4265.65 | G63: 4246.3 | H63: 4254.15 | I63: 4241.4 | J63: 4273.85 | K63: 4183.4 | L63: 4243.2 | M63: 4217.15 | N63: 4237.05 | O63: 4253 | P63: 4237.85 | Q63: 4231.55 | R63: 4248 | S63: 4256.8 | T63: 4260 | U63: 4254.3 | V63: 4245.08 | W63: 4254.25 | X63: 4258.65 | Y63: 4227.9 | Z63: 4254.1 | AA63: 4258.15 | AB63: 93401.78
B64: ENGIE | C64: C.T. CHILCA 1 | D64: TG2 | E64: TERMOELÉCTRICA | F64: 4221.55 | G64: 4202.2 | H64: 4208.7 | I64: 4194 | J64: 4224.25 | K64: 4144.55 | L64: 4195.4 | M64: 4176 | N64: 4188.35 | O64: 4202.75 | P64: 4188.9 | Q64: 4180.55 | R64: 4189.75 | S64: 4205 | T64: 4205.1 | U64: 4199.15 | V64: 4185.82 | W64: 4196.15 | X64: 4200.75 | Y64: 4177.85 | Z64: 4195.7 | AA64: 4199.8 | AB64: 92282.27
B65: ENGIE | C65: C.T. CHILCA 1 | D65: TG3 | E65: TERMOELÉCTRICA | F65: 4800 | G65: 4800 | H65: 4800 | I65: 4800 | J65: 4800 | K65: 4627.6 | L65: 4800 | M65: 4800 | N65: 4800 | O65: 4800 | P65: 4800 | Q65: 4800 | R65: 5000.1 | S65: 5005.05 | T65: 5007.45 | U65: 4999.8 | V65: 4997.125 | W65: 5015.75 | X65: 5012.6 | Y65: 4852.55 | Z65: 5001.4 | AA65: 5018.05 | AB65: 107337.48
B66: ENGIE | C66: C.T. CHILCA 1 | D66: TV | E66: TERMOELÉCTRICA | F66: 6582.75 | G66: 6568.75 | H66: 6578.55 | I66: 6568.4 | J66: 6596 | K66: 6466.75 | L66: 6560.7 | M66: 6558.7 | N66: 6557.45 | O66: 6579.55 | P66: 6572.95 | Q66: 6545.75 | R66: 6556.95 | S66: 6569.25 | T66: 6567.85 | U66: 6565.85 | V66: 6544.615 | W66: 6561.05 | X66: 6565.05 | Y66: 6491.55 | Z66: 6562.05 | AA66: 6560.35 | AB66: 144280.86
B67: ENGIE | C67: C.T. CHILCA 2 | D67: TG41 | E67: TERMOELÉCTRICA | V67: 737.025 | AB67: 737.025
B68: ENGIE | C68: C.T. CHILCA 2 | D68: TV42 | E68: TERMOELÉCTRICA | AB68: 0
B69: ENGIE | C69: C.T. NEPI | D69: TG41 | E69: TERMOELÉCTRICA | AB69: 0
B70: ENGIE | C70: C.T. NEPI | D70: TG42 | E70: TERMOELÉCTRICA | AB70: 0
B71: ENGIE | C71: C.T. NEPI | D71: TG43 | E71: TERMOELÉCTRICA | AB71: 0
B72: ENGIE | C72: C.T. RF PLANTA ILO | D72: TG1 | E72: TERMOELÉCTRICA | AB72: 0
B73: ENGIE | C73: C.T. RF PLANTA ILO | D73: TG2 | E73: TERMOELÉCTRICA | AB73: 0
B74: ENGIE | C74: C.T. RF PLANTA ILO | D74: TG3 | E74: TERMOELÉCTRICA | AB74: 0
B75: FENIX POWER PERÚ | C75: C.T. FENIX | D75: GT11 | E75: TERMOELÉCTRICA | F75: 4086.3 | G75: 4372.2 | H75: 4385.4981 | I75: 4284.1525 | J75: 4350.1 | K75: 4123.85 | L75: 4373.75 | M75: 4382.1 | N75: 4374.75 | O75: 4377.5 | P75: 4361.45 | Q75: 4377.3 | R75: 4368.75 | S75: 4366.9 | T75: 4374.5 | U75: 4367.2 | V75: 4361.75 | W75: 4371.45 | X75: 4377.1504 | Y75: 3838.2175 | Z75: 4297.25 | AA75: 4383.7 | AB75: 94955.818
B76: FENIX POWER PERÚ | C76: C.T. FENIX | D76: GT12 | E76: TERMOELÉCTRICA | F76: 4092.05 | G76: 4383.15 | H76: 4396.2114 | I76: 4196.948 | J76: 544 | K76: 4134.25 | L76: 4380.7 | M76: 4392.15 | N76: 4386.65 | O76: 4386.05 | P76: 4371.5 | Q76: 4386.1 | R76: 4380.1 | S76: 4377 | T76: 4383.85 | U76: 4376 | V76: 4372.05 | W76: 4381.15 | X76: 4384.4421 | Y76: 3847.8753 | Z76: 4306.25 | AA76: 4393 | AB76: 91251.477
B77: FENIX POWER PERÚ | C77: C.T. FENIX | D77: TV10 | E77: TERMOELÉCTRICA | F77: 4264.7 | G77: 4413.8 | H77: 4413.8397 | I77: 4319.5261 | J77: 2413.1 | K77: 4283.65 | L77: 4411.85 | M77: 4416.7 | N77: 4418.85 | O77: 4405.65 | P77: 4410.25 | Q77: 4416.15 | R77: 4411 | S77: 4407.4 | T77: 4410.05 | U77: 4409.95 | V77: 4403.6 | W77: 4412.45 | X77: 4413.9265 | Y77: 4128.7961 | Z77: 4375.2 | AA77: 4419.25 | AB77: 94379.688
B78: GENERACIÓN ANDINA S.A.C. | C78: C.H. 8 DE AGOSTO | D78: CENTRAL | E78: HIDROELÉCTRICA | F78: 245.55 | G78: 252 | H78: 252 | I78: 252 | J78: 245.85 | K78: 223.7 | L78: 206.85 | M78: 196.5 | N78: 187.8 | O78: 177.4 | P78: 168.8 | Q78: 157.3 | R78: 158.25 | S78: 152.2 | T78: 146.25 | U78: 139.95 | V78: 134.8 | W78: 238.85 | X78: 237.85 | Y78: 225.1915 | Z78: 170.25 | AA78: 138.7 | AB78: 4308.0415
B79: GENERACIÓN ANDINA S.A.C. | C79: C.H. EL CARMEN | D79: CENTRAL | E79: HIDROELÉCTRICA | F79: 113.7 | G79: 140.6 | H79: 113.3 | I79: 86.1 | J79: 74.65 | K79: 68.7 | L79: 65.95 | M79: 63.4 | N79: 60.8 | O79: 60 | P79: 58.85 | Q79: 57.65 | R79: 56.7 | S79: 55.2 | T79: 54.55 | U79: 52.8 | V79: 52.8 | W79: 78.9 | X79: 70.5 | Y79: 56.532 | Z79: 47.15 | AA79: 47.75 | AB79: 1536.582
B80: GENERADORA DE ENERGÍA DEL PERÚ | C80: C.H. ÁNGEL I | D80: CENTRAL | E80: HIDROELÉCTRICA | F80: 142.1 | G80: 135.2 | H80: 130.3 | I80: 124.55 | J80: 120.95 | K80: 117.25 | L80: 114.3 | M80: 111.2 | N80: 109.6 | O80: 107.05 | P80: 104.5 | Q80: 104.7 | R80: 102.4 | S80: 99.3 | T80: 97.2 | U80: 96.3 | V80: 117.8 | W80: 122.9 | X80: 119.15 | Y80: 112.05 | Z80: 101.95 | AA80: 96.05 | AB80: 2486.8
B81: GENERADORA DE ENERGÍA DEL PERÚ | C81: C.H. ÁNGEL II | D81: CENTRAL | E81: HIDROELÉCTRICA | F81: 154.7 | G81: 147.75 | H81: 142.95 | I81: 134.15 | J81: 133.25 | K81: 129.6 | L81: 126.7 | M81: 122.45 | N81: 122.1 | O81: 118.55 | P81: 117.7 | Q81: 116.4 | R81: 117.8 | S81: 111.6 | T81: 110.4 | U81: 108.65 | V81: 130.3 | W81: 135.4 | X81: 129.35 | Y81: 124 | Z81: 114.6 | AA81: 107.85 | AB81: 2756.25
B82: GENERADORA DE ENERGÍA DEL PERÚ | C82: C.H. ÁNGEL III | D82: CENTRAL | E82: HIDROELÉCTRICA | F82: 156.7 | G82: 141.8 | H82: 142.55 | I82: 134.5 | J82: 133.45 | K82: 129.7 | L82: 127.7 | M82: 123.4 | N82: 122.85 | O82: 114.6 | P82: 119.75 | Q82: 117.45 | R82: 117.7 | S82: 114 | T82: 109 | U82: 98.65 | V82: 126.5 | W82: 132.55 | X82: 126.5 | Y82: 127.45 | Z82: 114.3 | AA82: 104.15 | AB82: 2735.25
B83: GENERADORA DE ENERGÍA DEL PERÚ | C83: C.H. LA JOYA | D83: CENTRAL | E83: HIDROELÉCTRICA | F83: 202.1 | G83: 201.35 | H83: 180.15 | I83: 189 | J83: 175.2 | K83: 172.65 | L83: 176.2 | M83: 184.15 | N83: 178.45 | O83: 178.35 | P83: 183.85 | Q83: 178.65 | R83: 187.15 | S83: 191.15 | T83: 179.75 | X83: 21.4 | Y83: 177.25 | Z83: 211.65 | AA83: 215.95 | AB83: 3384.4
B84: GM OPERACIONES S.A.C. | C84: CT REFINERIA TALARA | D84: TV1 REF TALARA | E84: TERMOELÉCTRICA | F84: 1026.8 | G84: 1034.95 | H84: 1023.95 | I84: 880.19 | J84: 56.45 | S84: 103.88 | T84: 390 | U84: 832.95 | V84: 805.1343 | W84: 856.6 | X84: 856.8 | Y84: 862.3 | Z84: 885.05 | AA84: 888.1 | AB84: 10503.154
B85: GM OPERACIONES S.A.C. | C85: CT REFINERIA TALARA | D85: TV2 REF TALARA | E85: TERMOELÉCTRICA | F85: 807.7 | G85: 840.5 | H85: 841.85 | I85: 707.585 | U85: 35 | V85: 434.74265 | W85: 618 | X85: 607.55 | Y85: 609 | Z85: 646.6 | AA85: 665.6 | AB85: 6814.1277
B86: GR CORTARRAMA SOCIEDAD ANONIMA CERRADA | C86: C.S. MATARANI | D86: C.S. MATARANI | E86: SOLAR | F86: 492.05 | G86: 559.35 | H86: 561.7 | I86: 555.35 | J86: 566.4 | K86: 571.15 | L86: 452.65 | M86: 457.5 | N86: 578.95 | O86: 586.55 | P86: 574.85 | Q86: 566.3 | R86: 568.55 | S86: 577.25 | T86: 584.65 | U86: 592.4 | V86: 583 | W86: 479.25 | X86: 587.1 | Y86: 587.4 | Z86: 590.7 | AA86: 596.95 | AB86: 12270.05
B87: GR PAINO SOCIEDAD ANONIMA CERRADA | C87: C.E. HUAMBOS | D87: CENTRAL | E87: EÓLICA | F87: 245.8 | G87: 312 | H87: 403.65 | I87: 249.85 | J87: 276 | K87: 334.15 | L87: 343.15 | M87: 277 | N87: 207.8 | O87: 266.4 | P87: 276 | Q87: 52.25 | R87: 13.55 | S87: 311.95 | T87: 134 | U87: 82.25 | V87: 382.05 | W87: 381.75 | X87: 339.9 | Y87: 238.6 | Z87: 276.25 | AA87: 288.6 | AB87: 5692.95
B88: GR TARUCA SOCIEDAD ANONIMA CERRADA | C88: C.E. DUNA | D88: CENTRAL | E88: EÓLICA | F88: 328.75 | G88: 363.55 | H88: 422.95 | I88: 334.35 | J88: 362.6 | K88: 400.4 | L88: 399.55 | M88: 341.95 | N88: 285.4 | O88: 350.15 | P88: 358 | Q88: 85.2 | R88: 13.55 | S88: 334.15 | T88: 85.1 | U88: 73.25 | V88: 400.25 | W88: 424.7 | X88: 379.95 | Y88: 290.8 | Z88: 340.25 | AA88: 356 | AB88: 6730.85
B89: HIDROCAÑETE S.A. | C89: C.H. IMPERIAL | D89: CENTRAL | E89: HIDROELÉCTRICA | F89: 83.65 | G89: 79.1 | H89: 78.4 | I89: 80.05 | J89: 80 | K89: 80.75 | L89: 82 | M89: 82.75 | N89: 79.85 | O89: 79.8 | P89: 78.75 | Q89: 79 | R89: 80.4 | S89: 80.55 | T89: 80.45 | U89: 81 | V89: 79.7 | W89: 78.3 | X89: 78.95 | Y89: 79.2 | Z89: 78.5 | AA89: 78.35 | AB89: 1759.5
B90: HIDROELECTRICA HUANCHOR S.A.C. | C90: C.H. HUANCHOR | D90: CENTRAL | E90: HIDROELÉCTRICA | F90: 440.7 | G90: 437.5 | H90: 433.85 | I90: 431.85 | J90: 429.35 | K90: 429.2 | L90: 425.6 | M90: 424.4 | N90: 421.35 | O90: 401.4 | P90: 416.3 | Q90: 424.1 | R90: 441.5 | S90: 433.9 | T90: 440.85 | U90: 444.15 | V90: 445.35 | W90: 446.1 | X90: 446.16226 | Y90: 446.05 | Z90: 445.7 | AA90: 445.25 | AB90: 9550.6123
B91: HUAURA POWER GROUP S.A. | C91: C.H. YARUCAYA | D91: CENTRAL | E91: HIDROELÉCTRICA | F91: 444 | G91: 444 | H91: 444 | I91: 444 | J91: 444 | K91: 444 | L91: 444 | M91: 444 | N91: 444 | O91: 443.3 | P91: 439.9 | Q91: 331.3 | R91: 441.6 | S91: 441.6 | T91: 441.6 | U91: 437.55 | V91: 435.4 | W91: 438.55 | X91: 441.6 | Y91: 441.6 | Z91: 435.5 | AA91: 432.05 | AB91: 9597.55
B92: HYDRO GLOBAL PERÚ S.A.C. | C92: CH SAN GABAN III | D92: CENTRAL | E92: HIDROELÉCTRICA | F92: 2406.3 | G92: 2325.45 | H92: 2320.95 | I92: 2321.55 | J92: 2370.8 | K92: 1902.5 | L92: 2153.8 | M92: 2086 | N92: 1894.9 | O92: 2056.2 | P92: 2014.7 | Q92: 1894 | R92: 1775.2 | S92: 1827.65 | T92: 1653.15 | U92: 1841.15 | V92: 1798.05 | W92: 1886.55 | X92: 1935.4 | Y92: 1869.85 | Z92: 1724.05 | AA92: 1689.65 | AB92: 43747.85
B93: INFRAESTRUCTURAS Y ENERGIAS DEL PERU S.A.C. | C93: C.T. RF PTO MALDONADO | D93: CENTRAL | E93: TERMOELÉCTRICA | N93: 0.9 | AB93: 0.9
B94: INFRAESTRUCTURAS Y ENERGIAS DEL PERU S.A.C. | C94: C.T. RF PUCALLPA | D94: CENTRAL | E94: TERMOELÉCTRICA | F94: 1.65 | R94: 445.45 | AA94: 16.3 | AB94: 463.4
B95: INLAND ENERGY SAC | C95: C.H. SANTA TERESA | D95: CENTRAL | E95: HIDROELÉCTRICA | F95: 1814.3 | G95: 1789.25 | H95: 1755.55 | I95: 1759.55 | J95: 1758.45 | K95: 1716.15 | L95: 1678.5 | M95: 1608.05 | N95: 1576.35 | O95: 1549.5 | P95: 1520.35 | Q95: 1524.7 | R95: 1498.95 | S95: 1493.4 | T95: 1468.35 | U95: 1442 | V95: 1435.45 | W95: 1428.65 | X95: 1419.8 | Y95: 1414.8 | Z95: 1402.65 | AA95: 1367.45 | AB95: 34422.2
B96: INVERSIONES SHAQSHA S.A.C. | C96: C.H. PARIAC | D96: CENTRAL | E96: HIDROELÉCTRICA | F96: 34.5 | G96: 29.75 | H96: 29.75 | I96: 29.45 | J96: 30.1 | K96: 29.65 | L96: 30.5 | M96: 30.4 | N96: 28.8 | O96: 30.55 | P96: 30.05 | Q96: 28.8 | R96: 29.1 | S96: 28.8 | T96: 28.7 | U96: 27.7 | V96: 26.5 | W96: 24.2 | X96: 23.6 | Y96: 21.45 | Z96: 23.75 | AA96: 25.5 | AB96: 621.6
B97: JOYA SOLAR S.A.C. | C97: C.S. SAN MARTIN SOLAR | D97: CENTRAL | E97: SOLAR | F97: 1597.3 | G97: 1904.35 | H97: 1887.6 | I97: 1886.85 | J97: 1909.55 | K97: 1948.7 | L97: 1959.55 | M97: 1909.75 | N97: 1941.7 | O97: 1965.2 | P97: 1940 | Q97: 1917.25 | R97: 1931.3 | S97: 1974.9 | T97: 1990.05 | U97: 1983.65 | V97: 1959.35 | W97: 1605.9 | X97: 1974.2 | Y97: 1973.25 | Z97: 1979.95 | AA97: 107.8 | AB97: 40248.15
B98: KALLPA GENERACION S.A. | C98: C.H. CERRO DEL AGUILA | D98: CENTRAL | E98: HIDROELÉCTRICA | F98: 10774.75 | G98: 9516.15 | H98: 9537.2 | I98: 9202.7 | J98: 9620.7 | K98: 7140.65 | L98: 9066.05 | M98: 8791.3 | N98: 7296.65 | O98: 6824.55 | P98: 7960.05 | Q98: 8315.7 | R98: 7399.35 | S98: 7734.2 | T98: 6725.85 | U98: 6717.8 | V98: 7466 | W98: 7766.55 | X98: 6655.5 | Y98: 6636.9 | Z98: 7925.05 | AA98: 8142.85 | AB98: 177216.5
B99: KALLPA GENERACION S.A. | C99: C.T. KALLPA | D99: TG1 | E99: TERMOELÉCTRICA | F99: 3800.5 | G99: 4078.25 | H99: 4318.55 | I99: 4329.25 | J99: 4102 | K99: 3439.75 | L99: 4100.4 | M99: 4306.15 | N99: 4336.45 | O99: 4253.9 | P99: 4308.6 | Q99: 4406.65 | R99: 3854.3 | S99: 4054.4 | T99: 3878.7 | U99: 3924.8 | V99: 4204.35 | W99: 4304.25 | X99: 4325.8 | Y99: 3493.65 | Z99: 4368.35 | AA99: 4493.7 | AB99: 90682.75
B100: KALLPA GENERACION S.A. | C100: C.T. KALLPA | D100: TG2 | E100: TERMOELÉCTRICA | F100: 3838.85 | G100: 4136.05 | H100: 4496.35 | I100: 4499.85 | J100: 4211.4 | K100: 3464.05 | L100: 4176 | M100: 4459.4 | N100: 4538.3 | O100: 4406.3 | P100: 4449.95 | Q100: 4619.95 | R100: 3936.3 | S100: 4289.55 | T100: 4033.35 | U100: 4130.85 | V100: 4407.3 | W100: 4493.4 | X100: 4471.9 | Y100: 4134.25 | Z100: 4621.05 | AA100: 4957.65 | AB100: 94772.05
B101: KALLPA GENERACION S.A. | C101: C.T. KALLPA | D101: TG3 | E101: TERMOELÉCTRICA | F101: 3835.2 | G101: 4138.35 | H101: 4501.1 | I101: 4512.4 | J101: 4213.55 | K101: 3465.9 | L101: 4184.6 | M101: 4472.15 | N101: 4548.65 | O101: 4413.9 | P101: 4434.5 | Q101: 4677.8 | R101: 3949.8 | S101: 4335.2 | T101: 4053 | U101: 4142 | V101: 4423.7 | W101: 4488.9 | X101: 4475.5 | Y101: 3588.45 | Z101: 4414.6 | AA101: 5030.95 | AB101: 94300.2
B102: KALLPA GENERACION S.A. | C102: C.T. KALLPA | D102: TV | E102: TERMOELÉCTRICA | F102: 6014.25 | G102: 6303.2 | H102: 6572.85 | I102: 6606.1 | J102: 6284.15 | K102: 5779.4 | L102: 6368 | M102: 6577.9 | N102: 6584.1 | O102: 6544.9 | P102: 6539.45 | Q102: 6650.25 | R102: 6084.5 | S102: 6354.1 | T102: 6195.75 | U102: 6294.6 | V102: 6506.5 | W102: 6518.15 | X102: 6596.65 | Y102: 6017.55 | Z102: 6616.95 | AA102: 6915.6 | AB102: 140924.9
B103: KALLPA GENERACION S.A. | C103: C.T. LAS FLORES | D103: TG1 | E103: TERMOELÉCTRICA | F103: 4820.85 | G103: 4680.8 | H103: 4055.95 | I103: 5138.05 | J103: 5172.7 | K103: 4487.05 | L103: 5143.8 | M103: 5131.75 | N103: 5134.15 | O103: 5162.95 | P103: 5148.1 | Q103: 5132.75 | R103: 5139.6 | S103: 5152.35 | T103: 5169 | U103: 5175 | V103: 5149 | W103: 5165.15 | X103: 5188.35 | Y103: 5039.8 | Z103: 5176.15 | AA103: 5162.75 | AB103: 110726.05
...

Sheet G_AREAS
B3: martes, 22 de Julio del 2025
B5: HORA | C5: RESUMEN DE GENERACIÓN POR ÁREAS DEL SEIN | D5: RESUMEN DE GENERACIÓN POR ÁREAS DEL SEIN | E5: RESUMEN DE GENERACIÓN POR ÁREAS DEL SEIN | F5: RESUMEN DE GENERACIÓN POR ÁREAS DEL SEIN | G5: RESUMEN DE GENERACIÓN POR ÁREAS DEL SEIN | H5: RESUMEN DE GENERACIÓN POR ÁREAS DEL SEIN | I5: RESUMEN DE GENERACIÓN POR ÁREAS DEL SEIN | J5: RESUMEN DE GENERACIÓN POR ÁREAS DEL SEIN | K5: RESUMEN DE GENERACIÓN POR ÁREAS DEL SEIN | L5: RESUMEN DE GENERACIÓN POR ÁREAS DEL SEIN | M5: RESUMEN DE GENERACIÓN POR ÁREAS DEL SEIN | N5: RESUMEN DE GENERACIÓN POR ÁREAS DEL SEIN | O5: RESUMEN DE GENERACIÓN POR ÁREAS DEL SEIN | P5: RESUMEN DE GENERACIÓN POR ÁREAS DEL SEIN | Q5: RESUMEN DE GENERACIÓN POR ÁREAS DEL SEIN | R5: RESUMEN DE GENERACIÓN POR ÁREAS DEL SEIN | S5: HORA | T5: GENERACIÓN POR TIPO DE GENERACIÓN | U5: GENERACIÓN POR TIPO DE GENERACIÓN | V5: GENERACIÓN POR TIPO DE GENERACIÓN | W5: GENERACIÓN POR TIPO DE GENERACIÓN | X5: GENERACIÓN POR TIPO DE GENERACIÓN | Y5: HORA | Z5: GENERACIÓN POR TIPO DE GENERACIÓN | AA5: GENERACIÓN POR TIPO DE GENERACIÓN | AB5: GENERACIÓN POR TIPO DE GENERACIÓN | AC5: GENERACIÓN POR TIPO DE GENERACIÓN | AD5: GENERACIÓN POR TIPO DE GENERACIÓN
C6: NORTE | D6: NORTE | E6: NORTE | F6: NORTE | G6: CENTRO | H6: CENTRO | I6: CENTRO | J6: CENTRO | K6: SUR | L6: SUR | M6: SUR | N6: SUR | O6: GENERACIÓN INTEGRANTES COES | P6: GENERACIÓN INTEGRANTES COES | Q6: GENERACIÓN INTEGRANTES COES | R6: GENERACIÓN INTEGRANTES COES | T6: INTEGRANTES COES | U6: INTEGRANTES COES | V6: INTEGRANTES COES | W6: INTEGRANTES COES | X6: INTEGRANTES COES | Z6: INTEGRANTES COES RER | AA6: INTEGRANTES COES RER | AB6: INTEGRANTES COES RER | AC6: INTEGRANTES COES RER | AD6: INTEGRANTES COES RER
C7: GENERACIÓN HIDROELÉCTRICA NORTE | D7: GENERACIÓN TERMOELÉCTRICA NORTE | E7: GENERACIÓN SOLAR NORTE | F7: GENERACIÓN EÓLICA NORTE | G7: GENERACIÓN HIDROELÉCTRICA CENTRO | H7: GENERACIÓN TERMOELÉCTRICA CENTRO | I7: GENERACIÓN SOLAR CENTRO | J7: GENERACIÓN EÓLICA CENTRO | K7: GENERACIÓN HIDROELÉCTRICA SUR | L7: GENERACIÓN TERMOELÉCTRICA SUR | M7: GENERACIÓN SOLAR SUR | N7: GENERACIÓN EÓLICA SUR | O7: GENERACIÓN COES NORTE | P7: GENERACIÓN COES CENTRO | Q7: GENERACIÓN COES SUR | R7: TOTAL GENERACION | T7: HIDROELÉCTRICA | U7: TERMOELÉCTRICA | V7: SOLAR | W7: EÓLICA | X7: TOTAL GENERACION | Z7: HIDROELÉCTRICA RER | AA7: TERMOELÉCTRICA RER | AB7: SOLAR RER | AC7: EÓLICA RER | AD7: TOTAL RER
B8: 00:30 | C8: 160.6 | D8: 101.4 | E8: 0 | F8: 70.1 | G8: 2226.927 | H8: 3402.7 | I8: 0 | J8: 110.6 | K8: 364.7 | L8: 0 | M8: 0 | N8: 0 | O8: 332.1 | P8: 5740.227 | Q8: 364.7 | R8: 6437.027 | S8: 00:30 | T8: 2752.227 | U8: 3504.1 | V8: 0 | W8: 180.7 | X8: 6437.027 | Y8: 00:30 | Z8: 190.427 | AA8: 60.3 | AB8: 0 | AC8: 180.7 | AD8: 431.427
B9: 01:00 | C9: 107.3 | D9: 100 | E9: 0 | F9: 60.5 | G9: 2212.548 | H9: 3397.4 | I9: 0 | J9: 128 | K9: 380 | L9: 0 | M9: 0 | N9: 0 | O9: 267.8 | P9: 5737.948 | Q9: 380 | R9: 6385.748 | S9: 01:00 | T9: 2699.848 | U9: 3497.4 | V9: 0 | W9: 188.5 | X9: 6385.748 | Y9: 01:00 | Z9: 176.648 | AA9: 58.7 | AB9: 0 | AC9: 188.5 | AD9: 423.848
B10: 01:30 | C10: 106.9 | D10: 102 | E10: 0 | F10: 60 | G10: 2083.569 | H10: 3400.4 | I10: 0 | J10: 152.8 | K10: 335.6 | L10: 0 | M10: 0 | N10: 0 | O10: 268.9 | P10: 5636.769 | Q10: 335.6 | R10: 6241.269 | S10: 01:30 | T10: 2526.069 | U10: 3502.4 | V10: 0 | W10: 212.8 | X10: 6241.269 | Y10: 01:30 | Z10: 176.169 | AA10: 61.2 | AB10: 0 | AC10: 212.8 | AD10: 450.169
B11: 02:00 | C11: 112.3 | D11: 102.1 | E11: 0 | F11: 63 | G11: 2064.429 | H11: 3404.6 | I11: 0 | J11: 148.1 | K11: 334 | L11: 0 | M11: 0 | N11: 0 | O11: 277.4 | P11: 5617.129 | Q11: 334 | R11: 6228.529 | S11: 02:00 | T11: 2510.729 | U11: 3506.7 | V11: 0 | W11: 211.1 | X11: 6228.529 | Y11: 02:00 | Z11: 177.329 | AA11: 61.8 | AB11: 0 | AC11: 211.1 | AD11: 450.229
B12: 02:30 | C12: 114.8 | D12: 100.8 | E12: 0 | F12: 50.6 | G12: 1932.668 | H12: 3401.1 | I12: 0 | J12: 126.3 | K12: 346.2 | L12: 0 | M12: 0 | N12: 0 | O12: 266.2 | P12: 5460.068 | Q12: 346.2 | R12: 6072.468 | S12: 02:30 | T12: 2393.668 | U12: 3501.9 | V12: 0 | W12: 176.9 | X12: 6072.468 | Y12: 02:30 | Z12: 177.268 | AA12: 59.8 | AB12: 0 | AC12: 176.9 | AD12: 413.968
B13: 03:00 | C13: 112.6 | D13: 101.7 | E13: 0 | F13: 49.4 | G13: 1998.82 | H13: 3402 | I13: 0 | J13: 125.4 | K13: 341.6 | L13: 0 | M13: 0 | N13: 0 | O13: 263.7 | P13: 5526.22 | Q13: 341.6 | R13: 6131.52 | S13: 03:00 | T13: 2453.02 | U13: 3503.7 | V13: 0 | W13: 174.8 | X13: 6131.52 | Y13: 03:00 | Z13: 179.32 | AA13: 60.5 | AB13: 0 | AC13: 174.8 | AD13: 414.62
B14: 03:30 | C14: 113.6 | D14: 102 | E14: 0 | F14: 54.2 | G14: 1969.597 | H14: 3401.5 | I14: 0 | J14: 136.5 | K14: 341.6 | L14: 0 | M14: 0 | N14: 0 | O14: 269.8 | P14: 5507.597 | Q14: 341.6 | R14: 6118.997 | S14: 03:30 | T14: 2424.797 | U14: 3503.5 | V14: 0 | W14: 190.7 | X14: 6118.997 | Y14: 03:30 | Z14: 179.097 | AA14: 61.1 | AB14: 0 | AC14: 190.7 | AD14: 430.897
B15: 04:00 | C15: 110.1 | D15: 102.5 | E15: 0 | F15: 54.7 | G15: 1834.326 | H15: 3406.9 | I15: 0 | J15: 143.5 | K15: 353.1 | L15: 0 | M15: 0 | N15: 0 | O15: 267.3 | P15: 5384.726 | Q15: 353.1 | R15: 6005.126 | S15: 04:00 | T15: 2297.526 | U15: 3509.4 | V15: 0 | W15: 198.2 | X15: 6005.126 | Y15: 04:00 | Z15: 174.926 | AA15: 62.8 | AB15: 0 | AC15: 198.2 | AD15: 435.926
B16: 04:30 | C16: 112.4 | D16: 102 | E16: 0 | F16: 46.8 | G16: 1886.558 | H16: 3406.8 | I16: 0 | J16: 191.1 | K16: 360 | L16: 0 | M16: 0 | N16: 0 | O16: 261.2 | P16: 5484.458 | Q16: 360 | R16: 6105.658 | S16: 04:30 | T16: 2358.958 | U16: 3508.8 | V16: 0 | W16: 237.9 | X16: 6105.658 | Y16: 04:30 | Z16: 176.458 | AA16: 61.3 | AB16: 0 | AC16: 237.9 | AD16: 475.658
B17: 05:00 | C17: 112.2 | D17: 100.6 | E17: 0 | F17: 43.1 | G17: 1866.728 | H17: 3412.7 | I17: 0 | J17: 200.4 | K17: 366.5 | L17: 0 | M17: 0 | N17: 0 | O17: 255.9 | P17: 5479.828 | Q17: 366.5 | R17: 6102.228 | S17: 05:00 | T17: 2345.428 | U17: 3513.3 | V17: 0 | W17: 243.5 | X17: 6102.228 | Y17: 05:00 | Z17: 177.028 | AA17: 59.9 | AB17: 0 | AC17: 243.5 | AD17: 480.428
B18: 05:30 | C18: 113.6 | D18: 102.2 | E18: 0 | F18: 42 | G18: 2044.589 | H18: 3410.6 | I18: 0 | J18: 167.3 | K18: 365.9 | L18: 0 | M18: 0 | N18: 0 | O18: 257.8 | P18: 5622.489 | Q18: 365.9 | R18: 6246.189 | S18: 05:30 | T18: 2524.089 | U18: 3512.8 | V18: 0 | W18: 209.3 | X18: 6246.189 | Y18: 05:30 | Z18: 176.889 | AA18: 62.2 | AB18: 0 | AC18: 209.3 | AD18: 448.389
B19: 06:00 | C19: 113.6 | D19: 102.5 | E19: 0 | F19: 45.1 | G19: 2139.002 | H19: 3415.9 | I19: 0 | J19: 128.3 | K19: 343 | L19: 0 | M19: 0.1 | N19: 0 | O19: 261.2 | P19: 5683.202 | Q19: 343.1 | R19: 6287.502 | S19: 06:00 | T19: 2595.602 | U19: 3518.4 | V19: 0.1 | W19: 173.4 | X19: 6287.502 | Y19: 06:00 | Z19: 176.902 | AA19: 62.4 | AB19: 0.1 | AC19: 173.4 | AD19: 412.802
... B56: TOTAL MWh | C56: 3808.4 | D56: 3259.5 | E56: 2.7 | F56: 1484.25 | G56: 55378.412 | H56: 81020.55 | I56: 8.1 | J56: 6666.75 | K56: 10377.45 | L56: 0 | M56: 3544.75 | N56: 0 | O56: 8554.85 | P56: 143073.81 | Q56: 13922.2 | R56: 165550.86 | S56: TOTAL MWh | T56: 69564.262 | U56: 84280.05 | V56: 3555.55 | W56: 8151 | X56: 165550.86 | Y56: TOTAL MWh | Z56: 4494.8625 | AA56: 1465.05 | AB56: 3555.55 | AC56: 8151 | AD56: 17666.463

Sheet HOP
B3: martes, 22 de Julio del 2025
B5: Reporte de Horas de Operación
B6: Empresa | C6: Central | D6: Grupo | E6: Modo de Operación | F6: Inicio | G6: Final | H6: O. Arranque | I6: O. Parada | J6: Tipo Operación | K6: Ensayo de Potencia Efectiva | L6: Ensayo de Potencia Mínima | M6: Sistema | N6: Lim. Transm. | O6: Causa | P6: Observación
B7: AGRO INDUSTRIAL PARAMONGA S.A. | C7: C.T. PARAMONGA | D7: CENTRAL | E7: PARAMONGA - BAGAZO | F7: 22/07/2025 00:00:00 | G7: 23/07/2025 00:00:00 | J7: POR COGENERACION | O7: ...
B8: AGROAURORA S.A.C. | C8: C.T. MAPLE ETANOL | D8: CENTRAL | E8: MAPLE- BAGAZO | F8: 22/07/2025 00:00:00 | G8: 23/07/2025 00:00:00 | J8: POR COGENERACION | O8: ...
B9: AGROINDUSTRIAS SAN JACINTO S.A.A. | C9: C.T. SAN JACINTO | D9: CENTRAL | E9: SAN_JACINTO - BAGAZO | F9: 22/07/2025 00:00:00 | G9: 23/07/2025 00:00:00 | J9: POR COGENERACION | O9: ...
B10: BIOENERGIA DEL CHIRA S.A. | C10: C.T. CAÑA BRAVA | D10: G-1 | E10: CANA BRAVA TV1 - BAGAZO | F10: 22/07/2025 00:00:00 | G10: 22/07/2025 06:57:00 | J10: POR COGENERACION | O10: ...
B11: BIOENERGIA DEL CHIRA S.A. | C11: C.T. CAÑA BRAVA | D11: CENTRAL | E11: CANA BRAVA TV1 & TV2 - BAGAZO | F11: 22/07/2025 06:57:00 | G11: 22/07/2025 13:15:00 | J11: POR COGENERACION | O11: ...
B12: BIOENERGIA DEL CHIRA S.A. | C12: C.T. CAÑA BRAVA | D12: G-1 | E12: CANA BRAVA TV1 - BAGAZO | F12: 22/07/2025 13:15:00 | G12: 22/07/2025 18:18:00 | J12: POR COGENERACION | O12: ...
B13: BIOENERGIA DEL CHIRA S.A. | C13: C.T. CAÑA BRAVA | D13: CENTRAL | E13: CANA BRAVA TV1 & TV2 - BAGAZO | F13: 22/07/2025 18:18:00 | G13: 23/07/2025 00:00:00 | J13: POR COGENERACION | O13: ...
B14: ENEL GENERACION PIURA S.A. | C14: C.T. MALACAS 1 | D14: CENTRAL | E14: MALACAS1 TG6 - GAS | F14: 22/07/2025 00:00:00 | G14: 22/07/2025 00:19:00 | I14: 22/07/2025 00:03:00 | J14: POR POTENCIA O ENERGIA | O14: ...
B15: ENEL GENERACION PIURA S.A. | C15: C.T. MALACAS 1 | D15: CENTRAL | E15: MALACAS1 TG6 - GAS | F15: 22/07/2025 06:23:00 | G15: 23/07/2025 00:00:00 | H15: 22/07/2025 06:10:00 | J15: POR POTENCIA O ENERGIA | O15: ...
B16: ENGIE | C16: C.T. CHILCA 1 | D16: CENTRAL | E16: CHILCA1 CCOMB TG1 & TG2 & TG3 - GAS | F16: 22/07/2025 00:00:00 | G16: 23/07/2025 00:00:00 | J16: POR POTENCIA O ENERGIA | O16: ...
B17: FENIX POWER PERÚ | C17: C.T. FENIX | D17: CENTRAL | E17: FENIX CCOMB GT11 & GT12 - GAS | F17: 22/07/2025 00:00:00 | G17: 23/07/2025 00:00:00 | J17: POR POTENCIA O ENERGIA | O17: ...
B18: GM OPERACIONES S.A.C. | C18: CT REFINERIA TALARA | D18: TV1 REF TALARA | E18: REF_TALARA TV1 - NLH_RFG | F18: 22/07/2025 00:00:00 | G18: 23/07/2025 00:00:00 | J18: POR COGENERACION | O18: ...
B19: GM OPERACIONES S.A.C. | C19: CT REFINERIA TALARA | D19: TV2 REF TALARA | E19: REF_TALARA TV2 - NLH_RFG | F19: 22/07/2025 00:00:00 | G19: 23/07/2025 00:00:00 | J19: POR COGENERACION | O19: ...
B20: INFRAESTRUCTURAS Y ENERGIAS DEL PERU S.A.C. | C20: C.T. RF PUCALLPA | D20: CENTRAL | E20: RF PUCALLPA - D2 | F20: 22/07/2025 10:47:00 | G20: 22/07/2025 11:19:00 | H20: 22/07/2025 10:45:00 | J20: POR SEGURIDAD | M20: AISLADO01 | O20: ...
B21: INFRAESTRUCTURAS Y ENERGIAS DEL PERU S.A.C. | C21: C.T. RF PUCALLPA | D21: CENTRAL | E21: RF PUCALLPA - D2 | F21: 22/07/2025 11:19:00 | G21: 22/07/2025 11:50:00 | I21: 22/07/2025 11:49:00 | J21: A MINIMA CARGA | O21: ...
B22: KALLPA GENERACION S.A. | C22: C.T. KALLPA | D22: CENTRAL | E22: KALLPA CCOMB TG1 & TG2 & TG3 - GAS | F22: 22/07/2025 00:00:00 | G22: 23/07/2025 00:00:00 | J22: POR POTENCIA O ENERGIA | O22: ...
B23: KALLPA GENERACION S.A. | C23: C.T. LAS FLORES | D23: CENTRAL | E23: LAS FLORES CCOMB TG1 - GAS | F23: 22/07/2025 00:00:00 | G23: 22/07/2025 11:03:00 | J23: POR POTENCIA O ENERGIA | O23: ...
B24: KALLPA GENERACION S.A. | C24: C.T. LAS FLORES | D24: CENTRAL | E24: LAS FLORES CCOMB TG1 - GAS | F24: 22/07/2025 11:03:00 | G24: 22/07/2025 13:00:00 | J24: POR PRUEBAS | O24: ...
B25: KALLPA GENERACION S.A. | C25: C.T. LAS FLORES | D25: CENTRAL | E25: LAS FLORES CCOMB TG1 - GAS | F25: 22/07/2025 13:00:00 | G25: 23/07/2025 00:00:00 | J25: POR POTENCIA O ENERGIA | O25: ...
B26: ORYGEN PERU S.A.A. | C26: C.T. VENTANILLA | D26: CENTRAL | E26: VENTANILLA CCOMB TG3 & TG4 - GAS | F26: 22/07/2025 00:00:00 | G26: 23/07/2025 00:00:00 | J26: POR POTENCIA O ENERGIA | O26: ...
B27: PETRAMAS | C27: C.T. HUAYCOLORO | D27: CENTRAL | E27: HUAYCOLORO - BIOGAS | F27: 22/07/2025 00:00:00 | G27: 23/07/2025 00:00:00 | I27: 22/07/2025 06:01:00 | J27: POR POTENCIA O ENERGIA | O27: ...
B28: PETRAMAS | C28: C.T. LA GRINGA | D28: CENTRAL | E28: LA GRINGA V - BIOGAS | F28: 22/07/2025 00:00:00 | G28: 23/07/2025 00:00:00 | J28: POR POTENCIA O ENERGIA | O28: ...
B29: PETRAMAS | C29: C.T.B DOÑA CATALINA | D29: CENTRAL | E29: DONA CATALINA - BIOGAS | F29: 22/07/2025 00:00:00 | G29: 23/07/2025 00:00:00 | J29: POR POTENCIA O ENERGIA | O29: ...
B30: PETRAMAS | C30: C.T.B. CALLAO | D30: CENTRAL | E30: CALLAO - BIOGAS | F30: 22/07/2025 00:00:00 | G30: 23/07/2025 00:00:00 | H30: 22/07/2025 13:31:00 | J30: POR POTENCIA O ENERGIA | O30: ...
B31: TERMOCHILCA S.A.C. | C31: C.T. OLLEROS | D31: CENTRAL | E31: OLLEROS CCOMB TG1 - GAS | F31: 22/07/2025 00:00:00 | G31: 22/07/2025 12:15:00 | J31: POR POTENCIA O ENERGIA | O31: ...
B32: TERMOCHILCA S.A.C. | C32: C.T. OLLEROS | D32: CENTRAL | E32: OLLEROS CCOMB TG1 - GAS | F32: 22/07/2025 12:15:00 | G32: 22/07/2025 15:29:00 | J32: A MINIMA CARGA | O32: ...
B33: TERMOCHILCA S.A.C. | C33: C.T. OLLEROS | D33: CENTRAL | E33: OLLEROS CCOMB TG1 - GAS | F33: 22/07/2025 15:29:00 | G33: 22/07/2025 23:02:00 | J33: POR POTENCIA O ENERGIA | O33: ...
B34: TERMOCHILCA S.A.C. | C34: C.T. OLLEROS | D34: CENTRAL | E34: OLLEROS CCOMB TG1 - GAS | F34: 22/07/2025 23:02:00 | G34: 23/07/2025 00:00:00 | J34: A MINIMA CARGA | O34: ...

Sheet INDISP
B3: martes, 22 de Julio del 2025
B5: Hora Inicio y Fin de Indisponibilidades de las Unidades de Generación SEIN
B6: Empresa | C6: Ubicación | D6: Equipo | E6: Inicio | F6: Final | G6: Descripción | H6: MW Indisp. | I6: Prog. | J6: Dispon | K6: Interrupc. | L6: Tipo | M6: CodEq | N6: TipoEq_Osinerg
B7: EGASA | C7: CHARCANI I | D7: G1 | E7: 22/07/2025 07:28 | F7: 22/07/2025 14:41 | G7: Mantenimiento electromecanico plan 1 | H7: 0.82 | I7: P | J7: F/S | K7: N | L7: PREV. | M7: 111 | N7: G
B8: EGASA | C8: CHARCANI II | D8: CENTRAL | E8: 22/07/2025 13:42 | F8: 22/07/2025 15:03 | G8: Por maniobras de acople G1, Charcani I, por sistema de 5.25 Kv | H8: 0.58 | I8: P | J8: F/S | K8: N | L8: PREV. | M8: 1196 | N8: G
B9: EGASA | C9: CHARCANI VI | D9: G1 | E9: 22/07/2025 00:00 | F9: 23/07/2025 00:00 | G9: Mantenimiento Generador | H9: 0 | I9: P | J9: F/S | K9: N | L9: PREV. | M9: 188 | N9: G
B10: ELECTROPERU | C10: MANTARO | D10: G5 | E10: 22/07/2025 00:05 | F10: 22/07/2025 09:26 | G10: PRUEBAS TRANSFORMADOR DE CORRIENTE LADO REACTOR | H10: 100 | I10: P | J10: F/S | K10: N | L10: PREV. | M10: 5 | N10: G
B11: ELECTROPERU | C11: RESTITUCIÓN | D11: G2 | E11: 22/07/2025 00:13 | F11: 22/07/2025 11:44 | G11: INSTALACIÓN DE AISLADORES 220 KV DE LA FASE R | H11: 100 | I11: P | J11: F/S | K11: N | L11: PREV. | M11: 9 | N11: G
B12: ELECTROPERU | C12: RESTITUCIÓN | D12: G2 | E12: 22/07/2025 00:13 | F12: 22/07/2025 11:44 | G12: MANTENIMIENTO PREVENTIVO Y CONTROLES SISTEMÁTICOS | H12: 100 | I12: P | J12: F/S | K12: N | L12: PREV. | M12: 9 | N12: G
B13: EMPRESA DE GENERACION ELECTRICA CANCHAYLLO SAC | C13: CANCHAYLLO | D13: G02 | E13: 22/07/2025 00:00 | F13: 23/07/2025 00:00 | G13: MANTENIMINETO EQUIPOS AUXILIARES, UNIDAD DE POTENCIA HIDRAULICA, SISTEMA DE REFRIGERACION, TABLEROS DE CONTROL Y PROTRCCIÓN UG2. | H13: 2.507 | I13: P | J13: F/S | K13: N | L13: PREV. | M13: 14794 | N13: G
